{
  "titulo": "Acuerdo por el Que Se Crea el Proyecto Paquetes de Instalación de Tiendas de Abarrotes para Personas",
  "Contenido": "EMITEN SUS REGLAS DE OPERACIÓN PARA EL\nEJERCICIO FISCAL 2020.\nINSTALACIÓN DE TIENDAS DE ABARROTES PARA LA POBLACIÓN VULNERABLE, Y SE EMITEN SUS REGLAS DE\nGUERRERO No. EDICIÓN EXTRAORDINARIA, DE FECHA 24 MAYO DE 2021.\nTEXTO ORIGINAL\nAcuerdo publicado en el Periódico Oficial No. 67 Alcance III, el viernes 28 de agosto de 2020.\nACUERDO POR EL QUE SE CREA EL PROYECTO PAQUETES DE INSTALACION DE TIENDAS DE\nABARROTES PARA PERSONAS VULNERABLES, Y SE EMITEN SUS REGLAS DE OPERACIÓN\nPARA EL EJERCICIO FISCAL 2020.\nPoder Ejecutivo.\nLICENCIADO HÉCTOR ANTONIO ASTUDILLO FLORES, GOBERNADOR CONSTITUCIONAL DEL\nESTADO DE GUERRERO, CON FUNDAMENTO EN LO DISPUESTO POR LOS ARTÍCULOS 4o DE LA\nSALUD; 3 DE LA LEY DE ASISTENCIA SOCIAL; 4 FRACCIÓN XVIII DEL PRESUPUESTO DE\nEGRESOS DE LA FEDERACIÓN PARA EL EJERCICIO FISCAL 2020; 40 DE LA LEY DE\nCOORDINACIÓN FISCAL; 71, 87, 88, 90 NUMERAL 2 Y 91 FRACCIONES I, IX Y XLVI DE LA\nLAS FACULTADES QUE ME CONFIEREN LOS ARTÍCULOS 2, 3, 6, 7, 10, 18 APARTADO A FRACCIÓN\nI, 20 FRACCIÓN III Y 45 DE LA LEY ORGÁNICA DE LA ADMINISTRACIÓN PÚBLICA DEL ESTADO\nDE GUERRERO NÚMERO 08; 15 DE LA LEY SOBRE EL SISTEMA ESTATAL DE ASISTENCIA SOCIAL\nNÚMERO 332; EN RELACIÓN CON EL ARTÍCULO 55 Y ANEXOS 21 Y 21-A DEL DECRETO NÚMERO\n447 DEL PRESUPUESTO DE EGRESOS DEL ESTADO DE GUERRERO PARA EL EJERCICIO FISCAL\n2020 Y LOS LINEAMIENTOS PARA LA ELABORACIÓN DE LAS REGLAS DE OPERACIÓN DE LOS\nPROGRAMAS SOCIALES ESTATALES PARA EL EJERCICIO FISCAL 2017.\nQue el Plan Estatal de Desarrollo 2016-2021 impulsa entre sus prioridades, un Guerrero que garantice el ejercicio efectivo de los derechos sociales de todos los guerrerenses, que vaya más allá del participación social en las políticas públicas.\nLa Constitución Política de los Estado Unidos Mexicanos establece en su artículo 4o que la mujer y el hombre son iguales ante la ley. Esta protegerá la organización y el desarrollo de la familia.\nEMITEN SUS REGLAS DE OPERACIÓN PARA EL\nEJERCICIO FISCAL 2020. asistencialistas y más estructurales para garantizar el desarrollo de quienes menos tienen. Con una en este sector. Uno de los ejes que respaldan esta visión es el eje III.- Guerrero Socialmente\nComprometido. Objetivo 3.7. Fortalecer la asistencia social a grupos vulnerables; Estrategia 3.7.1. Atender integralmente a los grupos vulnerables y fomentar el acceso a los servicios de protección social que les permita mejorar su calidad de vida.\nLa Ley Número 479 del Sistema para el Desarrollo Integral de la Familia del Estado de Guerrero publicada en el Periódico Oficial del Gobierno del Estado número 61 del 02 de agosto de 1983, creó el\nSistema Estatal para el Desarrollo Integral de la Familia, como un organismo público descentralizado, el cual tiene por objeto I.- Promover el bienestar social y prestar al efecto servicios de asistencia social con apoyo en las normas que dicte la Secretaría de Salubridad y Asistencia y el Sistema Nacional para el\nDesarrollo Integral de la Familia, así como el propio Estado; II.- Apoyar el desarrollo de la familia y de la comunidad; III.- Fomentar la educación, para la integración social; IV.- Impulsar el sano crecimiento físico y mental de la niñez; 2 V.- Atender las funciones de auxilio a las instituciones de asistencia privada que le confíe la dependencia competente, con sujeción a lo que disponga la Ley relativa; VI.-Operar establecimientos de asistencia social en beneficio de menores en estado de abandono, de ancianos y de los minusválidos; VII.- Realizar estudios e investigaciones sobre los problemas de la familia, de los menores, de los ancianos y de los minusválidos; VIII.- Prestar servicios de asistencia jurídica y de orientación social de los menores, ancianos y minusválidos sin recursos; IX.- Intervenir en el ejercicio de la tutela de los menores, que corresponda al Estado, en los términos de la Ley respectiva; X.- Auxiliar al\nMinisterio Público en la protección de incapaces y de los procedimientos civiles y familiares que les afecten, de acuerdo con la Ley; XI.- Procurar permanentemente la adecuación de los objetivos y programas del sistema estatal, a los que lleve a cabo el sistema nacional, a través de decretos, acuerdos, convenios o cualquier figura jurídica encaminada a la obtención de bienestar social, y, XII.- Los demás que les encomienden las Leyes.\nLas personas titulares de las secretarías, dependencias y entidades de la administración pública estatal, así como, las servidoras y servidores públicos autorizados para ejercer recursos públicos del presupuesto de inversión de las mismas, serán responsables de los programas y proyectos de inversión que realicen. Que los apoyos otorgados deberán sujetarse a criterios de objetividad, equidad, transparencia, publicidad, selectividad y temporalidad.\nEl Presupuesto de Egresos de la Federación para el Ejercicio Fiscal 2020, contempla en un apartado que las erogaciones para el Ramo General 33 Aportaciones Federales para Entidades\nFederativas y Municipios, serán distribuidos conforme a lo previsto en el Anexo 22 de este Decreto, el cual se precisa en el Fondo de Aportaciones Múltiples erogaciones para asistencia social.\nEl artículo 55 del Decreto Número 447 de Presupuesto de Egresos del Estado de Guerrero, para el Ejercicio Fiscal 2020, establece que con el objeto de asegurar la aplicación eficiente, eficaz, oportuna\nEMITEN SUS REGLAS DE OPERACIÓN PARA EL\nEJERCICIO FISCAL 2020. inversión sujetos a reglas de operación.\nCon sustento en lo anterior, la Secretaría de Planeación y Desarrollo Regional, expidió los\nLineamientos para la Elaboración de las Reglas de Operación de los Programas Sociales Estatales para el\nEjercicio Fiscal 2020, publicados en el Periódico Oficial del Gobierno del Estado número 06, Alcance II.\nLos objetivos del programa y/o proyecto deberán desarrollarse de manera eficaz y oportuna a fin de consolidar la política estatal ya que dentro de los objetivos y estrategias que plantea el ejecutivo estatal, está abatir la marginación y el rezago social que enfrentan los grupos sociales vulnerables para proveerles de igualdad en las oportunidades que les permitan desarrollarse con independencia y plenitud, es por ello que surge este programa con el propósito de mitigar los impactos económicos sociales por las que atraviesan las personas que habiten en zonas rurales, mediante la entrega de proyectos productivos y de servicios.\nEn el Decreto Número 447 del Presupuesto de Egresos del Estado de Guerrero para el Ejercicio\nFiscal 2020 señala que se ejercerán los recursos bajo una política de gasto público, que permita dar cumplimiento a lo que globalmente prevén los ejes rectores del Plan estatal de Desarrollo 2016-2021.\nEn cumplimiento de lo anterior, se ha tenido a bien expedir el siguiente:\nACUERDO POR EL QUE SE CREA EL PROYECTO PAQUETES DE INSTALACIÓN DE TIENDAS DE\nABARROTES PARA PERSONAS VULNERABLES, Y SE EMITEN SUS REGLAS DE OPERACIÓN\nPARA EL EJERCICIO FISCAL 2020.\nArtículo 1. Se crea el Proyecto de Paquetes Instalación de Tiendas de Abarrotes para Personas\nVulnerables, el cual tiene por objeto contribuir a disminuir la desigualdad social entré los guerrerenses, respondiendo de manera cabal a sus expectativas de cambio; articuladora de esfuerzos, incluyente, con rostro humano.\nArtículo 2. Se emiten las Reglas de Operación del Proyecto Paquetes de Instalación de Tiendas de Abarrotes para Personas Vulnerables, en los que se establecen los principios de eficiencia, eficacia, oportunidad, equitativa y transparencia de los recursos públicos y requisitos que se deben de cumplir para poder acceder ha dicho Proyecto.\nPaquetes de Instalación de Tiendas de Abarrotes para Personas Vulnerables, con el objeto de otorgar transparencia y asegurar la aplicación, eficiente, eficaz, oportuno y equitativo de los recursos públicos\nGuerrero.\nEMITEN SUS REGLAS DE OPERACIÓN PARA EL\nEJERCICIO FISCAL 2020.\nArtículo 3. El Sistema para el Desarrollo Integral de la Familia del Estado de Guerrero tendrá a cargo la implementación, ejecución, evaluación y administración del Proyecto Paquetes de Instalación de\nTiendas de Abarrotes para Personas Vulnerables, bajo los criterios de objetividad, equidad, transparencia, publicidad, selectividad y temporalidad, con estricto apego a la normatividad aplicable, por lo tanto será el encargado de la dispersión y asignación de los recursos del Proyecto apegándose plenamente a las siguientes:\nREGLAS DE OPERACIÓN DEL PROYECTO PAQUETES DE INSTALACIÓN DE TIENDAS DE\nABARROTES PARA PERSONAS VULNERABLES PARA EL EJERCICIO FISCAL 2020.\n1. Introducción\n1.1. Antecedentes\nEl Sistema para el Desarrollo Integral para la Familia (SEDIF), a través de la Dirección de\nAsistencia Alimentaría y Desarrollo Comunitario, fomenta y promueve acciones que mitiguen la vulnerabilidad de las personas que son sujeto de asistencia social, y tiene como intención apoyar y coordinar las acciones de desarrollo comunitario en las que participan los tres niveles de gobierno (Federal, Estatal y Municipal) dentro del ámbito de su competencia.\nEn este documento se sustenta la intervención institucional que desde el ejercicio 2013 ha venido atendiendo a población en situaciones de vulnerabilidad, así mismo, se especifica la participación básica de llevar a cabo entre los Sistemas Municipales DIF, con el objetivo de realizar proyectos en coordinación, como el de Instalación de Tiendas de Abarrotes para la Población Vulnerable, teniendo como prioridad la atención a aquellas familias en estado de vulnerabilidad social que habiten en localides de alto y muy alto grado de marginación que tiene el propósito de fomentar el autoempleo y consumo como un elemento clave para que las familias que viven en condiciones de desventaja socioeconómica mejoren sus niveles de vida.\nQue dentro de los objetivos y estrategias que plantea el ejecutivo estatal, está abatir la marginación y el rezago social que enfrentan los grupos sociales vulnerables para proveerles de igualdad en las oportunidades que les permitan desarrollarse con independencia y plenitud; asimismo, plantea elevar la productividad de las personas para que cuenten con mejores opciones de empleo e ingreso, que les permitan reducir sus niveles de pobreza.\nEn consecuencia, la formulación de un programa y/o proyecto de desarrollo social exige conjugar armónicamente todos los elementos que lleven a la materialización de sus objetivos, estrategias, metas y evaluación de resultados. Por ello, se deben considerar en la introducción, los siguientes rubros:\na) Naturaleza del proyecto: Instalación de Tiendas de Abarrotes para Población Vulnerable, es un proyecto social el cual permitirá disminuir el impacto del desempleo temporal, como una de las alternativas para enfrentar dicho fenómeno y brindará a los hogares mitigar los impactos económicos sociales.\nEMITEN SUS REGLAS DE OPERACIÓN PARA EL\nEJERCICIO FISCAL 2020.\nb) Origen y fundamento: Constitución Política de los Estados Unidos Mexicanos, Constitución de Asistencia Social.\nc) Objetivos y metas: Contribuir al gasto de las familias que habitan en los municipios y localidades de alta y muy alta marginación, por lo que se atenderán a 80 familias, para que tengan un negocio propio, así como crear fuentes de empleo y autoempleo que coadyuven en su ingreso familiar, como precedente de sustentabilidad laboral.\nd) Ubicación geográfica: Se atenderán a los 81 municipios que integran el Estado, dando prioridad a los municipios de alta y muy alta marginación.\ne) Actividades a realizar: Gestionar ante las instancias de Gobierno federales y estatales, los recursos financieros, para llevar a cabo la adquisición de los materiales, insumos y productos necesarios en la operatividad del Proyecto; así mismo dar a conocer al Sistema Municipal DIF, las Reglas de Operación del proyecto vigente y proporcionar de forma calendarizada los suministros de los apoyos.\nf) Instancias participantes: La instancia ejecutora es el Sistema para el Desarrollo Integral de la\nFamilia del Estado de Guerrero, a través de la Dirección de Asistencia Alimentaria y Desarrollo Comunitario, quien se coordinará con los Sistemas Municipales DIF para llevar a cabo la ejecución y seguimiento del\nProyecto.\ng) Presupuesto de inversión: Se tiene contemplado una inversión de $2,693,760.00 (Dos millones seiscientos noventa y tres mil setecientos sesenta pesos 00/100 M.N.), recursos presupuestales que provienen del Ramo 33.- Aportaciones Federales para Entidades y Municipios, específicamente del Fondo de Aportaciones Múltiples (Asistencia Social).\nh) Glosario de términos:\nAsistencia Social: Conjunto de acciones tendientes a modificar y mejorar las circunstancias de carácter social que impiden el desarrollo social del individuo, así como la protección física, mental y social de personas en estado de necesidad.\nDIF Guerrero: Sistema para el Desarrollo Integral de la Familia.\nGrupos Vulnerables: Persona o grupo que por sus características de desventaja por edad, sexo, estado civil; nivel educativo, origen étnico, situación o condición física y/o mental; requieren de un esfuerzo\nProyecto: Proyecto de Paquetes de Instalación de Tiendas de Abarrotes para Personas\nVulnerables.\nEMITEN SUS REGLAS DE OPERACIÓN PARA EL\nEJERCICIO FISCAL 2020.\nReglas de Operación: Reglas de Operación del Proyecto de Paquetes de Instalación de Tiendas de Abarrotes para Personas Vulnerables.\nSEDIF: Sistema para el Desarrollo Integral de la Familia.\nSEFINA: Secretaría de Finanzas y Administración.\nSEPLADER: Secretaría de Planeación y Desarrollo Regional.\n1.2. Alineación programática\nEn cumplimiento a lo que globalmente prevén los ejes rectores del Plan Estatal de Desarrollo 20162021, por lo que se alinea en el eje III.- Guerrero Socialmente Comprometido; Objetivos: 3.1. Construir un\nEstado Garante de los Derechos Sociales de las Personas, 3.2. Edificar la ruta hacia una sociedad equitativa e incluyente y Estrategias: 3.1.2. Fortalecer el desarrollo de capacidades de los integrantes de una sociedad con carencias, que permitan contribuir a incrementar su capacidad productiva y su calidad de vida y 3.2.1. Generar programas de desarrollo comunitario por medio de procesos de participación social.\nLíneas de Acción\n• Fomentar el acceso efectivo de las familias a sus derechos sociales, particularmente de aquellas en pobreza extrema, mediante políticas públicas coordinadas y concurrentes.\n• Potenciar la inversión conjunta de la sociedad organizada y de los órdenes de Gobierno, invirtiendo en proyectos de infraestructura social básica, complementaria y productiva.\nLas presentes Reglas de Operación se alinean a lo estipulado en el Programa Sectorial \"Desarrollo y Asistencia Social\" 20162021, cuyo objetivo es atender a personas vulnerables, a través de desarrollar que mejoren su calidad de vida y sus núcleos familiares, logrando fortalecer el tejido social en localidades vulnerables.\n1.3. Diagnóstico localidades a lo largo de todo el país, provoca que la inestabilidad del empleo sea considerada como uno de los principales motivos de preocupación dentro de los hogares mexicanos; que la pérdida del empleo y\nEMITEN SUS REGLAS DE OPERACIÓN PARA EL\nEJERCICIO FISCAL 2020. la pobreza de los hogares, fundamentalmente porque la falta de empleo conduce a una importante disminución del capital económico familiar, mayor presión sobre los recursos naturales, así como el abandono de la educación y el fomento al endeudamiento, estas afectaciones frecuentemente persisten aun cuando sus miembros se reintegran a las actividades productivas y remuneradas.\nQue la oferta laboral puede disminuir en algunas regiones del Estado a lo largo del año debido a emergencias o por efecto de los ciclos productivos, afectando principalmente a la población de escasos recursos que enfrenta periódicamente etapas con una grave disminución en sus ingresos y patrimonio.\nPor ello las políticas de empleo estatal deben considerar además del fomento a la creación de empleos formales e informales, la ejecución de acciones que permitan disminuir el impacto del desempleo temporal; una de las alternativas para enfrentar dicho fenómeno es la implementación de programas y/o proyectos que brinden a los hogares el auto emplearse y/o generar empleo que mitiguen los impactos económicos sociales que viven.\nQue el diseño del Proyecto Paquetes de Instalación de Tiendas de Abarrotes para Personas\nVulnerables implica que los posibles beneficiarios y/o beneficiarias deben participar en proyectos de beneficio familiar o comunitario como corresponsabilidad obligatoria para recibir los apoyos que se les otorgue; dicho requisito no solamente promueve la participación activa de los ciudadanos en el desarrollo de sus hogares y comunidades, sino que además genera beneficios adicionales al resto de la sociedad.\nQue dentro de los objetivos y estrategias que plantea el ejecutivo estatal, está abatir la marginación y el rezago social que enfrentan los grupos sociales vulnerables para proveerles de igualdad en las oportunidades que les permitan desarrollarse con independencia y plenitud; asimismo, plantea elevar la productividad de las personas para que cuenten con mejores opciones de empleo e ingreso, que les permitan reducir sus niveles de pobreza.\nEl trabajo informal en países de economía subdesarrollada como México, está altamente asociada con el autoempleo, la carencia de plazas laborales que brinden una mayor seguridad salarial y mejores condiciones de trabajo orilla a casi el 60% de los buscadores de empleo a resolver por sí mismos su condición de desempleados y generalmente lo logran mediante pequeñas inversiones en el sector comercio y de servicios.\nEn el Estado existen 895, 157 hogares de los cuales 293 086 están conformadas por Jefas de\nFamilias que es el 33% y 602 071, se conforman por Jefes de Familia que en términos porcentuales le corresponde el 67% razón por la cual el Sistema para el Desarrollo Integral de la Familia beneficiará a 80 marginación, considerando la suficiencia presupuestal para el ejercicio vigente y los criterios de focalización y priorización del Proyecto.\nEl Proyecto que se propone, pretende dar utilidad a estos recursos para mejorar la situación en la que se encuentran las familias guerrerenses introduciendo una alternativa más, tanto de ocupación como\nEMITEN SUS REGLAS DE OPERACIÓN PARA EL\nEJERCICIO FISCAL 2020. de alimentación, con este se pretende contribuir en la atención de uno de los problemas identificados en este diagnóstico a través de:\nMisión: Proporcionar a las familias en desventaja económica el Proyecto Paquetes de Instalación de Tiendas de Abarrotes para Personas Vulnerables, como generador de autoempleo y/o empleo e ingresos a través de la prestación de un servicio.\nVisión: Elevar la calidad de vida de la familia mediante el desarrollo de proyectos generadores de autoempleo que coadyuven en el fortalecimiento de la economía familiar.\nA continuación, se detalla el número de beneficiarios del Proyecto durante el periodo 2016-2019, de acuerdo al cuadro que se desglosa a continuación.\nEJERCICIO FISCAL NÚMERO DE BENEFICIARIOS\n2016 50\n2017 42\n2018 42\n2019 40\n2. Dependencia o entidad responsable del proyecto\nLa instancia ejecutora será el Sistema para el Desarrollo Integral de la Familia, a través de la\nDirección de Asistencia y Desarrollo Comunitario quien se coordinará con los Sistemas Municipales DIF para llevar a cabo la ejecución y seguimiento del Proyecto el cual tiene como fundamento legal siguiente:\n• Constitución Política de los Estados Unidos Mexicanos.\n• Ley General de Salud.\n• Ley de Asistencia Social.\n• Ley General para la Inclusión de las Personas con discapacidad.\n• Ley Número 817 para las Personas con Discapacidad del Estado.\n• Ley Número 479 del Sistema para el Desarrollo Integral de la Familia del Estado de\nGuerrero.\n• Ley Número 454 de Presupuesto y Disciplina Fiscal del Estado de Guerrero.\n• Ley Orgánica de la Administración Pública del Estado de Guerrero 08.\n• Ley sobre el Sistema Estatal de Asistencia Social Número 332.\nEMITEN SUS REGLAS DE OPERACIÓN PARA EL\nEJERCICIO FISCAL 2020.\n• Decreto Número 196 por medio del cual la Sexagésima Primera Legislatura al Honorable\n2016-2021.\n• Programa Sectorial Desarrollo y Asistencia Social 2016-2021.\n• Decreto Número 447 del Presupuesto de Egresos del Estado de Guerrero para el Ejercicio\nFiscal 2020.\n• Estrategia Local \"Guerrero Contigo\".\n• Reglamento Interior del Sistema para el Desarrollo Integral de la Familia del Estado de\nGuerrero.\n• Manual de Organización del DIF Guerrero.\n• Y todos aquellos ordenamientos normativos aplicables.\n3. Objetivos y alcances\n3.1. Objetivo general\nContribuir al gasto familiar de la población que vive en condiciones de pobreza y/o que no cuente con empleo a través de la instalación de tiendas de abarrotes para la población vulnerable, para que tengan un negocio propio, así como crear fuentes de empleo y autoempleo que coadyuven en su ingreso familiar a 80 familias, que habiten en municipios o localidades con alto o muy alto grado de marginación.\n3.2. Objetivos específicos\n• Generar una alternativa de autoempleo como precedente de sustentabilidad laboral.\n• Incrementar el ingreso familiar.\n• Brindar un servicio básico.\n3.3. Alcances\nLa operación o ejecución del Proyecto surge para mitigar y garantizar el empleo y/o autoempleo sin empleo a través de la instalación de 80 tiendas de abarrotes, mejorando su economía familiar y comunitaria. o muy alto grado de marginación, considerando la suficiencia presupuestal para el ejercicio vigente y los criterios de focalización y priorización del Proyecto.\n4. Metas físicas\nEMITEN SUS REGLAS DE OPERACIÓN PARA EL\nEJERCICIO FISCAL 2020.\nSe beneficiarán aproximadamente a 80 familias que habiten en municipios y/o localidades de alta y muy alta marginación con vulnerabilidad social; dicho apoyo es entregado directamente al beneficiario en puntos sedes ubicados en su municipio correspondiente.\n5. Programación presupuestal\nEn el Decreto Número 447 del Presupuesto de Egresos del Estado de Guerrero para el Ejercicio\nFiscal 2020, se señala que se ejercerán los recursos bajo una política de gasto público, que permita dar cumplimiento a lo que globalmente prevén los ejes rectores del Plan Estatal de Desarrollo 2016-2021.\nEl Proyecto opera de acuerdo a su presupuesto anual autorizado, recursos presupuestales provenientes del Ramo 33.-Aportaciones Federales para Entidades y Municipios, específicamente del\nFondo de Aportaciones Múltiples (Asistencia Social), para Instalación de Tiendas de Abarrotes para la\nPoblación Vulnerable por un monto de $2,693,760.00 (Dos millones seiscientos noventa y tres mil setecientos sesenta pesos 00/100 M.N.), el cual tiene un costo promedio por beneficiario y/o beneficiarla de $33,672.00 (treinta y tres mil seiscientos setenta y dos pesos 00/100 M.N.).\n6.Requisitos y procedimientos de acceso\n6.1. Difusión opera en coordinación con las diferentes Direcciones que integran el Sistema como son; Programas\nAlimentarios, Proyectos Asistenciales, de Bienestar Social y Desarrollo Comunitario; cuyos requisitos se encuentran en las oficinas del Sistema ubicadas en Av. Rene Juárez Cisneros, Colonia Ciudad de los\nServicios y en Av. Gabriel Leyva s/n esq. Ruffo Figueroa, Col. Burócratas, C.P. 39090, Chilpancingo, Guerrero, con un horario de atención de 8:00 am a 3:00 pm y/o los teléfonos 01(747) 4725595, 01(747)47256 00, 01(747)47 25672 ext. 1151 y 1159. Así mismo al correo electrónico:alimentariadif@prodigy.net.mx, subdireccionalimentaria@prodigy.net.mx.\nEMITEN SUS REGLAS DE OPERACIÓN PARA EL\nEJERCICIO FISCAL 2020.\nSe brinda atención a los 81 municipios del Estado, teniendo una capacidad de atención de niñas, niños y adolescentes, mujeres embarazadas, mujeres en periodo de lactancia, personas con discapacidad, adultos mayores y personas vulnerables por ingresos.\n6.2. Requisitos al acceso\n• Los interesados deberán presentar oficio de solicitud en las instalaciones del DIF Guerrero en escrito libre al Centro de Rehabilitación Integral Guerrero, con domicilio en Boulevard Lic. René Juárez\nCisneros S/N, Col. Ciudad de los Servicios, Chilpancingo, dirigido a la Presidenta o Director General del\nDIF para ser considerado dentro del Proyecto, anexando copia fotostática de la siguiente documentación:\n1.Credencial de elector.\n2.CURP.\n3.Comprante de domicilio.\n• La solicitud es turnada a la Dirección de Asistencia Alimentaria y Desarrollo Comunitario para su atención, quien en un plazo no mayor a 60 días hábiles dará respuesta a la misma.\n• La Dirección de Asistencia Alimentaria y Desarrollo Comunitario aplica estudio socioeconómico al solicitante para determinar si será beneficiario del Proyecto.\n• Se realiza la entrega del apoyo de manera personal o en el municipio beneficiado, solicitándole al beneficiario firme acta de donación que acredite la entrega.\n6.3. Procedimiento de acceso\nLa operación se realiza a través de la demanda ciudadana y/o peticiones que se reciben en las\nSistema Estatal; el Proyecto, surge por la necesidad de atender el problema del desempleo y atendiendo la carencia alimentaria, el cual busca garantizar el derecho a la alimentación atendiendo a los 81 municipios que conforman nuestro Estado, dando prioridad a los municipios de alta o muy alta marginación.\nSerán beneficiados con el Proyecto, las personas que cumplan con las siguientes características:\n1. Familias en estado de vulnerabilidad, mujeres embarazadas, mujeres en periodo de lactancia, tener un empleo formal.\n2. Habitar en el municipio o localidad de alto, muy alto grado de marginación.\nEMITEN SUS REGLAS DE OPERACIÓN PARA EL\nEJERCICIO FISCAL 2020.\nToda persona podrá conocer el estado de su trámite, y su aceptación o no al Proyecto, de acuerdo con las Reglas de Operación vigentes. Las beneficiarias y/o beneficiarios tendrán derecho a ser tratado\n• Recibir la información necesaria de manera clara y oportuna para participar en el programa.\n• Un trato digno y respetuoso oportuno con calidad y equitativo sin discriminación alguna.\n• Reserva y privacidad de su información personal.\nUna vez que las personas solicitantes son incorporadas al proyecto formaran parte del Padrón de beneficiarios, el cual será de carácter público, siendo reservados sus datos personales, de acuerdo con la\nLey Número 207 de Transparencia y Acceso a la Información Pública del Estado de Guerrero; el acceso al\nProyecto podrá ser a solicitud de la persona interesada, asimismo toda persona podrá conocer el estado de su trámite, y su aceptación o no al Proyecto.\n6.4. Requisitos de permanencia, causales de baja o suspensión temporal\nPermanencia: Visita de seguimiento a los beneficiarios, con la finalidad de constatar la situación socioeconómica y seguimiento a las necesidades prioritarias, la población sujeta de atención deberá cumplir con:\n• Dar cumplimiento a las Reglas de Operación del Proyecto.\n• Utilizar los apoyos otorgados de manera adecuada y para los fines a los que se les otorgan y con que fueron autorizados evitando cualquier uso distinto de la misma. Los cuales en ningún caso podrán emplearse para propósitos de proselitismo político, religioso o comercial, ni para ningún otro fin distinto al establecido en las Reglas de Operación del proyecto social.\n• Permitir visita de verificación con la finalidad de validar la información proporcionada en sus expedientes correspondientes.\n• Facilitar los trabajos de supervisión, en cualquier momento después de haber recibido el apoyo.\nPersonas Vulnerables, que incumplan en las disposiciones normativas de estas Reglas de Operación, perderán las prerrogativas que dichas disposiciones establecen.\n6.5. Modos de entrega del beneficio\nLos apoyos serán distribuidos directamente a las beneficiarias y/o beneficiarios en puntos sedes de cada Región del Estado, o en su caso, podrán acudir a recoger el apoyo a las oficinas de la Dirección de Asistencia Alimentaria y Desarrollo Comunitario, dicho apoyo consiste en el otorgamiento de:\nEMITEN SUS REGLAS DE OPERACIÓN PARA EL\nEJERCICIO FISCAL 2020.\n✓ 1 Bulto de Azúcar estándar 50 kilo.\n✓ 1 Bulto de Frijol negro a granel 50 kilos.\n✓ 1 Bulto de Arroz a granel 50 kilos.\n✓ 2 Paquetes de Sal de mesa con 20 piezas, en Bolsa de1 kg.\n✓ 2 Cajas con 12 piezas de Aceite Vegetal Comestible de 945 ml.\n✓ 2 Caja de Detergente en polvo de 500 grs. con 20 piezas.\n✓ 1 Kg. Paquete Canela Estándar.\n✓ 1 Caja con 24 pzas, de Sardina en salsa de Tomate lata de 425 grs.\n✓ 1 Paquete de Cerillos de 50 cajitas\n✓ 1 caja De Jugo de frutas tetra pack de 1/4 con 27 pzas\n✓ 1 caja De Jugo de frutas tetra pack de 1/8 con 27 pzas\n✓ 3 Cajas exhibidoras de café de olla 15gr\n✓ 2 Caja de Jabón en barra de 350 grs. con 25 piezas\n✓ 1 Bulto de Harina estándar de 44 kg.\n✓ 1 Caja de Mayonesa No. 105 con 20 frascos.\n✓ 2 Cajas de Pasta para sopa de sobre de 200 grs. Con 20 paquetes c/u\n✓ 1 Caja de Galletas tipo \"Marías\" máxima de 160 grs. con 20 rollos c/u\n✓ 2 Cajas de formula láctea tetra pack de 1 lt. con 12 litros c/u\n✓ 2 Cajas de Galletas tipo \"Napolitanas\" máxima de 160 grs. con 20 rollos c/u\n✓ 1 Caja Galletas tipo \"mexicanas\" con 20 rollo c/u.\n✓ 2 Cajas de blanqueador de 500 ml. Con 20 pzas. c/u\n✓ 2 Cajas de shampoo en sobre de 900 ml. Con 12 pzas. c/u\n✓ 2 Cajas de chile jalapeño en rajas verdes en lata de 105 grs. c/10 piezas\n✓ 2 Cajas de suavizante de 850 ml. Con 12 pzas.\n✓ 2 Cajas de limpiador fresco pinol de 500 ml. Con 20 pzas. c/u\n✓ 2 Cajas de Jabón neutro de 180 grs. c/72 piezas\n✓ 2 Cajas de frascos de mermelada de fresa de 250 grs.\n✓ 2 Cajas de lechera de 387 grs. con 24 pzas. c/u\n✓ 2 Cajas de servilletas de 125 hojas c/12 paquetes\n✓ 2 Cajas de nescafe de 42grs. c/12 pzas\n✓ 2 Cajas de atún en aceite de 140 grs.\n✓ 2 Paquetes de norsuiza c/50 cubos\n✓ 2 Cajas de espagueti corto de 220 grs. C/20 pzas\n✓ 3 Cajas de crema dental de 75 ml. c/36 pzas\n✓ 2 Paquetes de cepillo dental de 48 pzas. c/u\n✓ 2 Paquetes de toallas femeninas c/alas c/48 piezas\n✓ 2 Paquetes de chocolate de mesa de 360 grs.\n✓ 2 Cajas de galletas napolitanas vainilla 200 grs. con 20 rollos c/u\n✓ 1 Caja de galletas mexicanas de 135 grs. con 20 rollos c/u\n✓ 2 Colchones de papel higiénico en paquetes de 4 rollos c/12\n✓ 1 Bascula de 5 kg. digital\nEMITEN SUS REGLAS DE OPERACIÓN PARA EL\nEJERCICIO FISCAL 2020.\n✓ 3 Anaqueles de 4 entrepaños\n7. Procedimientos de instrumentación\n7.1. Operación\nEl Sistema Estatal DIF tendrá las siguientes responsabilidades:\na) Gestionar ante las instancias de Gobierno federales y estatales, los recursos financieros, para llevar a cabo la adquisición de los materiales, insumos y productos necesarios en la operatividad del\nProyecto.\nb) Dar a conocer al Sistema Municipal DIF, Reglas de Operación del Proyecto Paquetes de\nInstalación de Tiendas de Abarrotes para Personas Vulnerables, vigentes.\nc) Proporcionar al Sistema Municipal DIF, de forma calendarizada los suministros de productos de los proyectos.\nd) Vigilar y verificar que los proyectos sean otorgados directamente a las beneficiarias y/o beneficiarios.\ne) Proporcionará almacenes regionales, para guarda, custodia de los productos que integran los proyectos; que contarán con personal capacitado para su manejo y distribución.\nf) Actualizar y profesionalizar los conocimientos del personal operativo del Sistema Estatal DIF y del Sistema Municipal DIF, a través de capacitaciones a fin de contar con las herramientas básicas para la operatividad de los programas y/o proyectos.\ng) Recepcionar de los Sistemas Municipales DIF la información requerida para comprobación de los programas y/o proyectos con base a las Reglas de Operación vigentes.\nh) Procesará la información a que se refiere el punto anterior y remitirla de acuerdo al calendario de entregas, a fin de comprobar los recursos canalizados al municipio.\ni) Elaborar a inicio de cada ejercicio fiscal, el Proyecto y documentos que contemplarán la aplicación y operatividad de los proyectos con los importes correspondientes.\nSerán obligaciones del Sistema Municipal DIF las siguientes: a. El Sistema Municipal DIF se obliga a cumplir con la implementación del Proyecto productivo que el Proyecto; salvo la pena de incurrir en responsabilidades administrativas. b. Determinará de manera conjunta la población potencial de su municipio tomando en consideración el tipo de beneficiario de todos los proyectos a solicitar, con esta información y en coordinación con el Sistema Estatal DIF, atenderá a la población que se encuentre en situación de vulnerabilidad de localidades de alta y muy alta marginación. c. Integrará y enviará los expedientes, así como los padrones físicos de las beneficiarias y/o beneficiarios de los programas y/o proyectos solicitados a la Subdirección de Desarrollo Comunitario, de\nEMITEN SUS REGLAS DE OPERACIÓN PARA EL\nEJERCICIO FISCAL 2020. aplicables. d. Integrará los padrones de las beneficiarias y/o beneficiarios con sus respectivos expedientes de los programas y/o proyectos objeto de estas Reglas de Operación. Remitiendo al Sistema Estatal DIF el padrón físico, digital y expedientes correspondiente a la comprobación de los mismos. e. Designar personal del Sistema Municipal DIF que realice las funciones de seguimiento y supervisión de los programas y/o proyectos. f. Participar en acciones de apoyo logístico para la distribución de los programas y/o proyectos. g. Es competencia del Sistema Municipal DIF, trasladar los materiales que corresponden a los programas, a las comunidades beneficiadas, en una unidad vehicular. Será responsabilidad del municipio el resguardo y el buen uso de los materiales que se recepcionen, en el entendido que, de existir algún desvío de los mismos, el Sistema Estatal DIF cancelará inmediatamente el suministro del programa y/o proyecto e iniciará un procedimiento ante la contraloría interna del sistema estatal, para determinar las sanciones a que sean acreedores.\nPara garantizar la atención completa del beneficiario, se realizan las acciones siguientes:\n• Determinar el tipo de proyectos a implementar.\n• Adquisición de los materiales y que cumplan con las Especificaciones Técnicas de Calidad.\n• Asegurar el correcto almacenamiento y distribución de los materiales, hasta su entrega al beneficiario.\n• Focalizar los beneficiarios de los proyectos con base a los indicadores socioeconómicos.\n• Coordinar la entrega de apoyos a la población beneficiada con los Sistemas Municipales DIF, a través de convenios de colaboración y conforme a lo establecido en las Reglas de Operación.\n• Promover la participación social a través de los Sistemas Municipales DIF en la formación de comités entre la población beneficiaria, para la recepción, entrega y vigilancia de los apoyos.\n• Promover la formación y operación de grupos de contraloría social para el seguimiento del\nProyecto.\n• Fortalecer la operación de los programas y/o proyectos promoviendo la inclusión general de la sociedad.\nLos datos de la población beneficiada, así como la información generada y administrada se regirán\nAsí mismo el Proyecto, contempla las herramientas necesarias para desempeñar el autoempleo, mejorando su economía familiar y comunitaria mediante el otorgamiento de:\n✓ 1 Bulto de Azúcar estándar 50 kilo.\n✓ 1 Bulto de Frijol negro a granel 50 kilos.\n✓ 1 Bulto de Arroz a granel 50 kilos.\n✓ 2 Paquetes de Sal de mesa con 20 piezas, en Bolsa de 1 kg.\n✓ 2 Cajas con 12 piezas de Aceite Vegetal Comestible de 945 ml.\nEMITEN SUS REGLAS DE OPERACIÓN PARA EL\nEJERCICIO FISCAL 2020.\n✓ 2 Caja de Detergente en polvo de 500 grs. Con 20 piezas.\n✓ 1 Kg. Paquete Canela Estándar.\n✓ 1 Caja con 24 pzas, de Sardina en salsa de Tomate lata de 425 grs.\n✓ 1 Paquete de Cerillos de 50 cajitas.\n✓ 1 Caja de Jugo de frutas tetra pack de 1/4 con 27 pzas.\n✓ 1 Caja de Jugo de frutas tetra pack de 1/8 con 27 pzas.\n✓ 3 Cajas exhibidoras de café de olla 15gr.\n✓ 2 Caja de Jabón en barra de 350 grs. con 25 piezas.\n✓ 1 Bulto de Harina estándar de 44 kg.\n✓ 1 Caja de Mayonesa No.105 con 20 frascos.\n✓ 2 Cajas de Pasta para sopa de sobre de 200 grs. Con 20 paquetes c/u.\n✓ 1 Caja de Galletas tipo \"Marías\" máxima de 160 grs. con 20 rollos c/u.\n✓ 2 Cajas de formula láctea tetra pack de 1 lt. con 12 litros c/u\n✓ 2 Cajas de Galletas tipo \"Napolitanas\" máxima de 160 grs. con 20 rollos c/u.\n✓ 1 Caja Galletas tipo \"mexicanas\" con Cajas de blanqueador de 500 ml. Con 20 pzas. c/u.\n✓ 2 Cajas de shampoo en sobre de 900 ml. Con 12 pzas. c/u.\n✓ 2 Cajas de chile jalapeño en rajas verdes en lata de 105 grs. c/10 piezas.\n✓ 2 Cajas de suavizante de 850 ml. Con 12 pzas.\n✓ 2 Cajas de limpiador fresco pinol de 500 ml. Con 20 pzas. c/u.\n✓ 2 Cajas de Jabón neutro de 180 grs. c/72 piezas.\n✓ 2 Cajas de frascos de mermelada de fresa de 250 grs.\n✓ 2 Cajas de lechera de 387 grs. con 24 pzas. c/u.\n✓ 2 Cajas de servilletas de 125 hojas c/12 paquetes.\n✓ 2 Cajas de nescafe de 42grs. c/12 pzas.\n✓ 2 Cajas de atún en aceite de 140 grs.\n✓ 2 Paquetes de norsuiza c/50 cubos.\n✓ 2 Cajas de espagueti corto de 220 grs. C/20 pzas.\n✓ 3 Cajas de crema dental de 75 ml. c/36 pzas.\n✓ 2 Paquetes de cepillo dental de 48 pzas. c/u.\n✓ 2 Paquetes de toallas femeninas c/alas c/48 piezas.\n✓ 2 Paquetes de chocolate de mesa de 360 grs.\n✓ 2 Cajas de galletas napolitanas vainilla 200 grs. Con 20 rollos c/u.\n✓ 1 Caja de galletas mexicanas de 135 grs. con 20 rollos c/u.\n✓ 2 Colchones de papel higiénico en paquetes de 4 rollos c/12.\n✓ 1 Bascula de 5 kg. Digital.\n✓ 3 Anaqueles de 4 entrepaños.\nComo objetivo a corto plazo, se dará continuidad a la entrega de cada apoyo solicitado, cubriendo cada uno los requisitos solicitados en las presentes Reglas de Operación, mismo que será otorgado en su municipio de residencia o en su caso en el almacén general del Sistema Estatal a la población vulnerable, los tramites y formatos a realizar son gratuitos.\nEMITEN SUS REGLAS DE OPERACIÓN PARA EL\nEJERCICIO FISCAL 2020.\n7.2. Gastos de operación\nEl presupuesto asignado a este Proyecto, es a través del Fondo de Aportaciones Múltiples, no contempla Gastos de Operación.\n8. Transparencia\n8.1. Difusión\nLa Dirección de Asistencia Alimentaria y Desarrollo Comunitario, quien es la responsable de la operación del proyecto difundirá a través de diferentes medios de comunicación; trípticos, periódico, redes sociales en las cuales se dará a conocer la información relacionada con las características del Proyecto de\nInstalación de Tiendas de Abarrotes para la Población Vulnerable.\nAsí mismo se dará amplia difusión al Proyecto a nivel estatal y se promoverán similares acciones por parte de las autoridades locales; la información del Proyecto se dará a conocer en la página de internet https://www.guerrero.gob.mx del Gobierno del Estado, desagregada por municipio, barrio o zona urbanomarginada, proyecto y nombre del beneficiario; las copias de los expedientes de las beneficiarias y/o beneficiarios estarán disponibles oportunamente para su consulta en las oficinas del Sistema ubicadas en Av. Rene Juárez Cisneros, Colonia Ciudad de los Servicios y Av. Gabriel Leyva s/n esq. Ruffo Figueroa, Col. Burócratas, C.P. 39090, Chilpancingo, Guerrero; por otra parte la papelería, documentación oficial, así como la publicidad y promoción del Proyecto, deberán incluir la leyenda descrita en el apartado de \"Blindaje\nElectoral\".\nLa información de montos y beneficiarios deberá ser publicada en los términos de la Ley Número\n207 de Transparencia y Acceso a la Información Pública del Estado de Guerrero.\nUna vez autorizadas estas Reglas de Operación, por las instancias correspondientes, estarán disponibles para su consulta en las oficinas de la Dirección de Asistencia Alimentaria y Desarrollo\nComunitario, quien es la responsable directa de la ejecución, a través de la Subdirección de Desarrollo\nComunitario, ubicada Av. Gabriel Leyva s/n esq. Ruffo Figueroa, Col. Burócratas, C.P. 39090, Chilpancingo, Guerrero, a los teléfonos (01747) 47 2 55 95, (01747) 47 2 56 00, (01747) 47 2 56 72 ext. 1155. Así mismo al correo electrónico: subdescomdif@prodigy.net.mx.\nEstas Reglas de Operación, además de su publicación en el Periódico Oficial del Gobierno del\nEstado, estarán disponibles para su consulta en las oficinas de la Dirección de Asistencia Alimentaria y\nDesarrollo Comunitario, así como en la página electrónica del Sistema para el Desarrollo Integral de la\n8.2. Blindaje electoral\nEMITEN SUS REGLAS DE OPERACIÓN PARA EL\nEJERCICIO FISCAL 2020.\nLa operación y ejecución de los recursos estatales destinados al Proyecto, deberán observar y atender las medidas que emita la Secretaría de Contraloría y Transparencia Gubernamental, para coadyuvar a que éstos, no sean utilizados con fines políticos La operación y ejecución de los recursos estatales destinados al Proyecto, deberán observar y atender las medidas que emita la Secretaría de\nContraloría y Transparencia Gubernamental, para coadyuvar a que éstos, no sean utilizados con fines políticos, por lo que la papelería, documentación oficial, así como la publicidad y promoción del Proyecto deberán incluir la siguiente leyenda:\n\"Este proyecto es público, ajeno a cualquier partido político. Queda prohibido el uso para fines distintos a los establecidos en el proyecto\".\n8.3. Supervisión y control\nLa Dirección de Asistencia Alimentaria y Desarrollo Comunitario deberá reportar mensualmente a la Dirección de Planeación del DIF Guerrero, las acciones ejercidas y los resultados obtenidos, quien a su vez reportará trimestralmente a la Secretaría de Finanzas y Administración, Secretaría de Planeación y\nDesarrollo Regional y la Secretaría de Contraloría y Transparencia Gubernamental, informes sobre el presupuesto ejercido establecidos por el Consejo Nacional de Armonización Contable (CONAC) dichos informes se deberán presentar a más tardar a los quince días hábiles posteriores a la terminación de cada trimestre.\nLos padrones de los beneficiarios serán requisitados por los Sistemas Municipales DIF, remitiendo la integración de los padrones de beneficiarios de los 81 municipios de la entidad misma que serán remitidos a las instancias o dependencias operadoras.\n8.4. Mecanismos de evaluación e indicadores\n8.4.1. Evaluación correspondientes.\n8.4.2. Indicadores\nEMITEN SUS REGLAS DE OPERACIÓN PARA EL\nEJERCICIO FISCAL 2020.\n8.5 Auditoría\nEMITEN SUS REGLAS DE OPERACIÓN PARA EL\nEJERCICIO FISCAL 2020.\nEl ejercicio del recurso y la operatividad del Proyecto, están sujetos a las disposiciones estatales aplicables y podrá ser auditado por la Secretaría de Contraloría y Transparencia Gubernamental, así como por la Auditoria Superior del Estado y Auditoria Superior de la Federación, conforme a la legislación vigente y en el ámbito de sus respectivas competencias.\nEl Sistema DIF Guerrero dará todas las facilidades a dichas instancias para realizar, en el momento en que lo juzguen pertinente, las auditorias que consideren necesarias; así como el seguimiento y la solventación a las observaciones planteadas por los órganos de control.\n8.6. Recursos no devengados\nEl DIF Guerrero deberá reintegrar a la Dirección General de Tesorería de la Secretaría de Finanzas y Administración del Gobierno del Estado los recursos que no se hubiesen destinado a los fines autorizados y aquellos que por cualquier motivo no estuviesen devengados al 31 de diciembre del ejercicio fiscal correspondiente.\n8.7. Contraloría social\nCon la finalidad de incrementar la participación ciudadana, se crearán comités de Contraloría\nSocial, como un órgano ciudadano de control, vigilancia y evaluación de las actividades del Proyecto, conformados por las beneficiarias y beneficiarios, los sectores sociales, y los representantes de la localidad, quienes de manera específica supervisarán la gestión gubernamental, y que los manejos de los recursos públicos se realicen en términos de transparencia, eficacia, legalidad y honradez.\nLos objetivos específicos de este Órgano de Contraloría Social son:\n• Hacer más transparentes las decisiones y la ejecución de los recursos.\n• Incrementar la participación ciudadana.\n• Fomentar la organización social.\n• Inhibir los actos de corrupción y de cooptación social, política y electoral.\n• Incrementar la eficiencia de los recursos públicos.\n• Fortalecer la cultura de la legalidad.\n• Mejorar la rendición de cuentas.\n• Perfeccionar la democracia e incorporar la evaluación ciudadana.\nLas funciones de los comités de Contraloría Social son:\na) Integración: Se conforman con la representación de la comunidad beneficiada por el Proyecto, y fungirán como interlocutores con el DIF Guerrero, en el ejercicio de la contraloría social.\nEMITEN SUS REGLAS DE OPERACIÓN PARA EL\nEJERCICIO FISCAL 2020.\nEl vocal será, el responsable de hacer llegar las quejas o denuncias recibidas al DIF Guerrero, quien dará respuesta en un plazo no mayor de 15 días a partir de la fecha de recepción de la queja o denuncia.\nb) Capacitación y asesoría: Para impulsar la realización de las actividades de contraloría social se brindará capacitación y asesoría, a las servidoras y servidores públicos que intervienen en la operación del programa y/o proyecto, así como a los integrantes de los comités locales, para que estos realicen adecuadamente sus actividades de seguimiento y vigilancia.\nc) Seguimiento: Se deberá integrar un Programa de Trabajo a través del cual se debe incluir la descripción de las actividades, responsables, metas y calendarización de las actividades para su cumplimiento.\nEl Director General o el personal que designe el DIF Guerrero, serán los encargados de conformar los comités de Contraloría Social, asimismo darán acompañamiento durante las actividades de control, seguimiento y vigilancia del Proyecto.\nEl Comité de Contraloría Social debe estar constituido por una Presidencia, una Secretaría y una\nVocalía mínimamente, electos de entre la población beneficiada en donde se va a realizar la entrega del\nProyecto, y tendrá que ser vigilado por un solo comité, el cual deberá controlar, vigilar y dar seguimiento al\nProyecto a través de los formatos que integran el expediente comunitario, integrado por:\n1. Acta de Conformación del Comité de Contraloría Social.\n2. Reunión con beneficiarias y beneficiarios.\n3. Ficha Informativa del Proyecto.\n4. Cédula de Vigilancia del Proyecto.\n5. Actividades de Difusión y Capacitación.\n6. Quejas, Denuncias o Reconocimientos.\n7. Informe Anual.\n8.8. Formas de participación social\nCon apego en lo dispuesto en la Ley Número 684 de Participación Ciudadana del Estado Libre y\nSoberano de Guerrero, se establece que la sociedad podrá participar activamente en la Planeación, Programación, Implementación y Evaluación de los Programas Sociales de Desarrollo Social, por ello las gubernamental, que el manejo de los recursos públicos se realicen en términos de transparencia, eficacia, legalidad y honradez del Proyecto de acuerdo en lo estipulado en estas Reglas de Operación.\nEMITEN SUS REGLAS DE OPERACIÓN PARA EL\nEJERCICIO FISCAL 2020.\n8.9. Procedimiento de queja o inconformidad ciudadana sobre cualquier hecho, acto u omisión que produzca o pueda producir daños al ejercicio de sus derechos establecidos en las presentes Reglas de Operación o contravengan sus disposiciones y de la demás normatividad aplicable. a. El Sistema DIF Guerrero.\nCorreo electrónico: buzon.dif@guerrero.gob.mx\nDomicilio: Centro de Rehabilitación Integral Guerrero.\nBoulevard Lic. René Juárez Cisneros S/N, Col. Ciudad de los Servicios. Chilpancingo, Guerrero.\nC.P. 39095. b. La Secretaría de Contraloría y Transparencia Gubernamental.\nTeléfonos: (474) 47 1 97 41\nCorreo electrónico: contraloria@guerrero.gob.mx\nDomicilio: Palacio de Gobierno Primer Piso Edificio Norte, Blvd. R. Juárez Cisneros 62 Col. Ciudad de los Servicios. Chilpancingo, Guerrero. C.P. 39075.\nLas quejas y denuncias de la ciudadanía derivadas de alguna irregularidad en la operación del\nProyecto, podrán presentarse por escrito, por comparecencia de la beneficiaria y/o beneficiario, por correo electrónico o vía telefónica y deberá proporcionar los siguientes datos:\n• Nombre del servidor público.\n• Área de adscripción.\n• Objeto de la denuncia.\n• Nombre y domicilio del quejoso.\n• Identificación oficial.\n8.10. Mecanismos de exigibilidad mismos pueden ocurrir en al menos los siguientes casos:\nEMITEN SUS REGLAS DE OPERACIÓN PARA EL\nEJERCICIO FISCAL 2020.\n✓ Cuando una persona solicitante cumpla con los requisitos y criterios de inclusión para acceder a determinado derecho.\n✓ Cuando la persona solicitante exija que se cumpla con dicho derecho de manera integral en tiempo y forma.\n✓ Cuando no se pueda satisfacer toda la demanda de incorporación al Proyecto por restricción presupuestal.\nSerá la Secretaría de Contraloría y Transparencia Gubernamental del Gobierno del Estado quién atenderá las denuncias de violación e incumplimiento de derechos en materia de Desarrollo Social.\n8.11. Acta de entrega-recepción\nLa Dirección de Asistencia Alimentaria y Desarrollo Comunitario y resguardará el expediente de las beneficiarias y/o beneficiarios, incluyendo su acta de donación correspondiente, dada la naturaleza del apoyo otorgado, se realiza en apego al control del gasto público.\n9. Criterios de selección y elegibilidad\n9.1. Método de selección de beneficiarios\nSerán beneficiados con el Proyecto, las personas que cumplan con las siguientes características:\n• Familias en estado de vulnerabilidad, mujeres embarazadas, mujeres en periodo de lactancia, adultos mayores y personas vulnerables por ingresos o que presenten alguna discapacidad y no puedan tener un empleo formal.\n• Habitar en el municipio o localidad de alto, muy alto grado de marginación.\n10. Mecánica de operación\n10.1. Instancia ejecutora\nDirección de Asistencia Alimentaria y Desarrollo Comunitario, quien deberá operar con apego a la programación, presupuestación, calendario de ejecución, ejercicio y control del gasto público.\n10.2. Instancia administrativa y/o normativa\nDirección de Asistencia Alimentaria y Desarrollo Comunitario, la Secretaría Contraloría y Transparencia\nGubernamental y la Auditoría Superior del Estado en el ámbito de sus respectivas competencias, quienes darán seguimiento a los objetivos y metas del Proyecto.\nEMITEN SUS REGLAS DE OPERACIÓN PARA EL\nEJERCICIO FISCAL 2020.\n10.3. Delimitación de atribuciones\nProyecto y acciones no se contrapongan, afecten o presenten duplicidades con otros programas o acciones del gobierno estatal; la coordinación institucional y vinculación de acciones busca potenciar el impacto de los recursos, fortalecer la cobertura de las acciones, detonar la complementariedad y reducir gastos administrativos.\n11. Derechos, obligaciones y sanciones de los beneficiarios de programas sociales\n11.1. Derechos\n• Recibir trato digno, respetuoso y equitativo sin discriminación alguna, por el personal de las distintas áreas que participen dentro del Proyecto.\n• Reserva y privacidad de la información personal.\n• Acceder a la información necesaria del Proyecto, sus Reglas de Operación, recursos y cobertura.\n• Solicitar y recibir información sobre el estado que guarda su trámite.\n• Recibir los servicios y prestación del Proyecto conforme a las Reglas de Operación, salvo que le sea suspendido el apoyo por alguna razón justificable.\n11.2. Obligaciones\n• Proporcionar la información socioeconómica bajo protesta de decir verdad que les sea requerida por el DIF Guerrero, en los términos que establezca la normatividad correspondiente.\n• Utilizar los apoyos para los fines con que fueron autorizados evitando cualquier uso distinto de la misma.\n• Facilitar los trabajos de verificación, en cualquier momento después de otorgado el apoyo.\n11.3. Sanciones\nLas beneficiarias y/o los beneficiarios del Proyecto que incumplan en las disposiciones normativas establecidas en los numerales 6.2 y 6.3 para acceder a los beneficios que a través de estos se otorgan, perderán las prerrogativas que dichas disposiciones establecen.\n12. Interpretación\nEMITEN SUS REGLAS DE OPERACIÓN PARA EL\nEJERCICIO FISCAL 2020.\nLa interpretación de las presentes Reglas de Operación para efectos administrativos, estarán a cargo del DIF Guerrero, así como de la Secretaría de Contraloría y Transparencia Gubernamental, en el ámbito de sus respectivas competencias.\nEMITEN SUS REGLAS DE OPERACIÓN PARA EL\nEJERCICIO FISCAL 2020.\nEMITEN SUS REGLAS DE OPERACIÓN PARA EL\nEJERCICIO FISCAL 2020.\nEMITEN SUS REGLAS DE OPERACIÓN PARA EL\nEJERCICIO FISCAL 2020.\nPrimero. El presente Acuerdo entrará en vigor al día siguiente de su publicación en el Periódico\nSegundo. Se abroga el Acuerdo por el que se crea el Proyecto Instalación de Tiendas de\nAbarrotes para la Población Vulnerable y se emiten las Reglas de Operación, para el Ejercicio Fiscal 2019, publicado en el Periódico Oficial del Gobierno del Estado de Guerrero No. 54 Alcance VI, de fecha 05 de julio de 2019.\nDado en la oficina del titular del Poder Ejecutivo, ubicada en el Edificio Centro de Palacio de\nGobierno, Boulevard René Juárez Cisneros No. 62, Colonia Ciudad de los Servicios en la Ciudad de\nChilpancingo de los Bravo, Capital del Estado de Guerrero, a los veintisiete dias del mes de enero del año dos mil veinte.\nEL GOBERNADOR CONSTITUCIONAL DEL ESTADO DE GUERRERO.\nLIC. HÉCTOR ANTONIO ASTUDILLO FLORES\nRúbrica.\nEL SECRETARIO GENERAL DE GOBIERNO.\nLIC. FLORENCIO SALAZAR ADAME.\nRúbrica.\nESTADO DE GUERRERO.\nLIC. JOSÉ FRANCISCO SOLÍS SOLÍS.\nRúbrica.",
  "ordenamiento": "PROGRAMA",
  "jurisdiccion": "GUERRERO",
  "fuente_oficial": "DIARIO OFICIAL DE LA FEDERACION",
  "Fecha de Publicación": "28 de agosto de 2020",
  "ULTIMA REFORMA PUBLICADA": null,
  "status": "VIGENTE",
  "es_escaneado": false,
  "tiene_tablas": true,
  "materia": [
    "general"
  ]
}