{
  "titulo": "Acuerdo por el Que Se Crea el Programa de Alimentación para el Bienestar de Niñas y Niños y Se Emite",
  "Contenido": "PARA EL EJERCICIO FISCAL 2022\nTEXTO ORIGINAL. de Junio de 2022.\nACUERDO POR EL QUE SE CREA EL PROGRAMA DE ALIMENTACIÓN PARA EL BIENESTAR DE\nNIÑAS Y NIÑOS Y SE EMITEN SUS REGLAS DE OPERACIÓN PARA EL EJERCICIO FISCAL 2022.\nPoder Ejecutivo.\nMAESTRA EVELYN CECIA SALGADO PINEDA, GOBERNADORA CONSTITUCIONAL DEL ESTADO\nDE GUERRERO, CON FUNDAMENTO EN LO DISPUESTO POR LOS ARTÍCULOS 71, 87, 88 PÁRRAFO\nPRIMERO, 90 NUMERAL 2 Y 91 FRACCIONES I, VI, IX Y XLVI DE LA CONSTITUCIÓN POLÍTICA DEL\nCONFIEREN LOS ARTÍCULOS 2, 3, 6, 7, 10, 18 APARTADO A FRACCIONES I Y IV, 20 FRACCIÓN III\nY 23 FRACCIÓN III DE LA LEY ORGÁNICA DE LA ADMINISTRACIÓN PÚBLICA DEL ESTADO DE\nGUERRERO NÚMERO 08; 1, 2 FRACCIÓN I, 18 Y 25 DE LA LEY NÚMERO 454 DE PRESUPUESTO Y\nDISCIPLINA FISCAL DEL ESTADO DE GUERRERO; 1, 2, 3, 6, 8, 48, 49 Y 50 DE LA LEY NÚM. 102,\nPARA EL DESARROLLO SOCIAL DEL ESTADO DE GUERRERO; 36 FRACCIÓN II, 49 FRACCIÓN VIII\nY 101 FRACCIÓN I DE LA LEY NÚMERO 812 PARA LA PROTECCIÓN DE LOS DERECHOS DE NIÑAS,\nNIÑOS Y ADOLESCENTES DEL ESTADO DE GUERRERO; EN RELACIÓN CON EL ARTÍCULO 57 Y\nANEXOS 21 (E04) Y 21-A (E04) DEL DECRETO NÚMERO 160 DEL PRESUPUESTO DE EGRESOS\nDEL ESTADO DE GUERRERO PARA EL EJERCICIO FISCAL 2022, Y LOS LINEAMIENTOS PARA LA\nELABORACIÓN DE LAS REGLAS DE OPERACIÓN DE LOS PROGRAMAS SOCIALES ESTATALES\nPARA EL PERIODO 2022 – 2027.\nQue la Agenda 2030 para el Desarrollo Sostenible es un documento que establece en su Objetivo 2 “Poner fin a la pobreza en todas sus formas en todo el mundo”, en su meta 2.1, menciona: de aquí a 2030, poner fin al hambre y asegurar el acceso de todas las personas, en particular los pobres y las personas en situaciones de vulnerabilidad, incluidos los niños menores de 1 año, a una alimentación sana, nutritiva y suficiente durante todo el año, por otro lado el 2.2 señala que: de aquí al 2030 poner fin a todas las formas de malnutrición incluso logrando a más tardar en 2025, las metas convenidas internacionalmente sobre el retraso y crecimiento y la emancipación de los niños menores de 5 años, y abordar las necesidades de nutrición de las adolescentes, las mujeres embarazadas y lactantes y las personas de edad.\nQue en el artículo 4o de la Constitución Política de los Estados Unidos Mexicanos se establece que todas las niñas y niños tienen derechos a la satisfacción de sus necesidades de alimentación, salud, educación para propiciar el respeto a la dignidad de la niñez y el ejercicio pleno de sus derechos.\nPARA EL EJERCICIO FISCAL 2022\nQue, en los Lineamientos para el desarrollo y el ejercicio de la autonomía curricular en las escuelas de educación básica del Sistema Educativo Nacional, emitidos el 07 de junio del 2018, en su capítulo I artículo primero, establece las pautas y procedimientos para que las escuelas de educación básica del Sistema\nEducativo Nacional desarrollen y ejerzan la Autonomía Curricular, en algunos de sus 5 ámbitos.\nQue las Reglas de Operación establecen disposiciones que instituyen la ejecución del Programa de\nAlimentación para el Bienestar de Niñas y Niños, con el objeto de otorgar transparencia y asegurar la aplicación eficiente, eficaz, oportuna y equitativa de los recursos públicos asignados, las cuales deberán publicarse en el Periódico Oficial del Gobierno del Estado de Guerrero.\nQue la Ley Orgánica de la Administración Pública del Estado de Guerrero Número 08, establece que corresponde a la Secretaría de Desarrollo y Bienestar Social, coordinar las acciones que incidan en el abatimiento de los niveles de pobreza que considere la desigualdad existente entre hombres y mujeres, y fomentar un mejor nivel de vida de población, que garanticen una mejoría en los niveles de vida de los grupos de población más desprotegidos.\nQue la Secretaría de Desarrollo y Bienestar Social, tiene la facultad para realizar las gestiones interinstitucionales para que los programas de desarrollo social alcancen los objetivos previstos; así como de ejercer los recursos estatales, con estrategias para incentivar la participación de las y los jóvenes guerrerense y convertirse en agentes de cambio social, mediante el apoyo de iniciativas de participación para el desarrollo comunitario y transformación del entorno, incrementando mecanismos de inclusión y participación social, por ello la Secretaría de Desarrollo y Bienestar Social, tendrá a cargo la implementación, operación, ejecución, evaluación y administración del Programa “Alimentación para el\nBienestar de Niñas y Niños”.\nPor lo anteriormente expuesto, he tenido a bien expedir el siguiente:\nACUERDO POR EL QUE SE CREA EL PROGRAMA DE ALIMENTACIÓN PARA EL BIENESTAR DE\nNIÑAS Y NIÑOS Y SE EMITEN SUS REGLAS DE OPERACIÓN PARA EL EJERCICIO FISCAL 2022.\nArtículo 1. Se crea el Programa de Alimentación para el Bienestar de Niñas y Niños con la finalidad de promover una buena alimentación para que las niñas y niños, tengan un desarrollo y crecimiento adecuado, principalmente, se encuentren inscritos en las escuelas de nivel básico localizadas en comunidades catalogadas como de alta y muy alta marginación.\nArtículo 2. La Secretaría de Desarrollo y Bienestar Social tendrá a su cargo la implementación, operación, ejecución, evaluación y administración del Programa de Alimentación para el Bienestar de Niñas y Niños, bajo los criterios de objetividad, equidad, transparencia, publicidad, selectividad y temporalidad con estricto apego a la normatividad aplicable, por lo tanto, será la encargada de la dispersión y asignación de los recursos del Programa de Alimentación para el Bienestar de Niñas y Niños.\nArtículo 3. Se emiten las Reglas de Operación del Programa de Alimentación para el Bienestar de Niñas y Niños para el Ejercicio Fiscal 2022, en las cuales se establece el procedimiento de ejecución del\nPARA EL EJERCICIO FISCAL 2022\nPrograma, los principios que deben observarse y los requisitos y condiciones para acceder al mismo, en los términos siguientes:\n1. Introducción.\n1.1. Antecedentes.\nLa SBGRO tiene la encomienda de atender y apoyar las necesidades de alimentación entre la población que vive en condiciones de alta, muy alta marginación del estado de Guerrero, propiciando, principalmente, el desarrollo alimenticio de niñas, niños y adolescentes que se encuentra en condiciones de desnutrición infantil, a fin de incrementar la asistencia escolar provocada por la falta de alimentos, así como reducir el gasto familiar. La Organización de las Naciones Unidas destaca que la alimentación en su etapa estudiantil forma parte de los sistemas de protección social de las niñas, niños y sus familias ante contextos de pobreza, conflictos armados, desastres naturales y crisis alimentarias. Las niñas y los niños en edad escolar, necesitan una alimentación nutritiva y suficiente para realizar adecuadamente sus funciones: jugar, correr, estudiar, crecer, etc. La falta de alimentación nutritiva afecta su crecimiento y desarrollo, así como el aprendizaje. En cambio, una buena alimentación permite la formación de buenos hábitos; por ello la alimentación debe ser suficiente, completa, equilibrada, variada y, sobre todo, inocua. (REFORMADO, P.O. 37\nALCANCE I, 09 DE MAYO DE 2023)\nEn México, se considera una alimentación sana a aquella que proporciona la energía y los nutrientes necesarios, y adecuados de acuerdo con la edad y el género, para promover un crecimiento adecuado y un correcto desarrollo físico e intelectual y que, a su vez, contribuya a mantener una buena salud. Como es de saberse, para muchas familias, sobre todo en el Estado de Guerrero, la alimentación suficiente y que, además, esta sea sana, se vuelve todo un desafío que se ha llevado décadas en conseguir. Por tanto, atender la malnutrición de niñas, niños y adolescentes, en todas sus formas, es todo un reto que el estado debe de asumir con plena responsabilidad y buscar los mecanismos necesarios para proveer de alimentos y con ello, propiciar el respeto a la dignidad de la niñez y el ejercicio pleno de sus derechos. (REFORMADO, P.O. 37 ALCANCE I, 09 DE MAYO DE 2023)\nEn la Cumbre Mundial sobre Sistemas Alimentarios, Seguridad Alimentaria y Desafíos Globales de las Naciones Unidas realizada en septiembre del año 2021, las palabras del secretario general:\nAntonio Gutiérrez, fueron muy claras; “el hambre también va a la escuela”. Y esto, nos hace infantil escolar. Son muchas las causas de la deserción escolar, entre las que contamos, niños guerrerenses y reducir con ello, los índices de desnutrición infantil, así como también,\nPARA EL EJERCICIO FISCAL 2022\nComo principal resultado de la implementación del Programa, se logró integrar un padrón de 84 escuelas de nivel básico, las cuales cuentan, en total, con una matrícula vigente de 6,270 alumnos, mismas que fueron beneficiadas con apoyos en especie para el establecimiento de módulos de producción de hortalizas y para la cría y manejo de gallinas de postura bajo un esquema de producción agroecológica, es decir, libre del uso de agroquímicos, mediante estrategias participativas (madres, padres de familia, alumnado y maestras o maestros) para la producción de sus propios alimentos, por ello, y de manera complementaria, se brindaron un total de 336 paquetes que incluían productos de primera necesidad, con los cuales, mediante la estrategia del Programa, las madres y los padres de familia pudieron organizarse para la elaboración de los alimentos que las niñas y los niños requerían. (ADICIONADO, P.O. 37 ALCANCE I, 09 DE MAYO DE 2023)\nPara el presente ejercicio fiscal, la SBGRO busca que, con la implementación de este Programa, se brinden las herramientas necesarias que permitan aplicar un nuevo enfoque a los programas en la alimentación desde la perspectiva de producir sus propios alimentos. Partiendo de la concientización de las y los participantes, los procesos participativos y colectivos, así como el desarrollo de capacidades para la producción de alimentos desde la perspectiva de la seguridad alimentaria. (ADICIONADO, P.O. 37 ALCANCE I, 09 DE MAYO DE 2023)\n2. Alineación Programática al PED y/o PND\nEl Programa estará alineado al Plan Nacional de Desarrollo 2019- 2024, dentro de su apartado número 2 de Política Social, en el punto 6, hace mención sobre la inserción en programas escolares de temas de nutrición, hábitos saludables y salud sexual y reproductiva, así mismo en su apartado 4 del epilogo: Visión de 2024, en su párrafo 5 menciona, que nadie padecerá hambre y la pobreza extrema habrá sido erradicada.\nAsí mismo, el Programa se encuentra alineado al Plan Estatal de Desarrollo del Estado de Guerrero\n2022-2027 en su Eje Programático 1 Bienestar, Desarrollo Humano y Justicia Social: Objetivo 1.2 de\nMejorar la calidad de vida de la población; Estrategia 1.2.2. Sobre el combate al hambre y aumentar el acceso a una alimentación sana, nutritiva y suficiente, con particular atención a la población más pobre y en situación de vulnerabilidad, incluidos niñas y niños; línea de acción 1.2.2.1 Incentivar la\nPor otro lado y en congruencia con el Programa Sectorial de Educación 2020-2024 a nivel federal, se establece dentro de su Objetivo prioritario 1: Garantizar el derecho de la población en México a una educación equitativa, inclusiva, intercultural e integral, que tenga como eje principal el interés superior de las niñas, niños, adolescentes y jóvenes, su Estrategia prioritaria 1.4 Garantizar condiciones de equidad para todos, con énfasis particular en los grupos y poblaciones históricamente discriminados y su Acción puntual 1.4.4 Proveer una alimentación sana, nutritiva y suficiente en las escuelas públicas de educación\nPARA EL EJERCICIO FISCAL 2022\nEl hambre y la inseguridad alimentaria es uno de los principales problemas públicos en Guerrero. significativamente los factores que inciden en las cuatro causas de este problema, identificadas por el Consejo Nacional de Evaluación de la Política Social (CONEVAL):\nDiagrama de las causas de la inseguridad alimentaria\nFuente: ¿Qué funciona y qué no en seguridad alimentaria? Guías Prácticas de Políticas Públicas 2019.\nConsejo Nacional de Evaluación de la Política Social (CONEVAL).\nLa inseguridad alimentaria se clasifica en leve, moderada y severa. En éstas últimas dos categorías es donde se acentúa, más pronunciadamente, la carencia de alimentos y es en las que nos enfocaremos en este Programa.\nEs así como en base a los datos de la medición multidimensional de la pobreza 2018-2020, el 62.6% de la población en Guerrero vivió alguna forma de inseguridad alimentaria; el 29.3% padeció inseguridad alimentaria leve; en tanto que el 21.3% inseguridad alimentaria moderada y que representa 758 mil 020 personas; mientras que el 12.1% inseguridad alimentaria severa que representa 430 mil 613 personas; tan solo con datos del año 2020. Lo anterior significa que, en números absolutos, 2 millones 227 mil 798 personas vivieron alguna situación de inseguridad alimentaria, de los cuales, 1 millón 188 mil 633 personas viven en condiciones de inseguridad alimentaria moderada y severa.\nPARA EL EJERCICIO FISCAL 2022\nEn cuanto a los datos de alimentación en niñas y niños, el Informe de Salud y Nutrición del Fondo de las\nNaciones Unidas para la Infancia (UNICEF) en nuestro país, el 34% de las calorías que consumen diariamente niñas y niños en edad escolar, vienen de productos ultra procesados, y para edad preescolar la proporción sube hasta 39%. Por si fuera poco, 1 de cada 3 niñas y niños menores de 5 años padece desnutrición, y 2 de cada 3 menores de 2 años están mal alimentados. El sobrepeso y la obesidad conllevan al desarrollo de diabetes y enfermedades cardiovasculares y metabólicas. Además, pueden afectar también el ánimo durante la infancia y adolescencia, contribuyendo así a problemas emocionales, depresión y estigmatización.\nLa Encuesta Nacional de Salud y Nutrición (ENSANUT) 2018 arrojó que, en el estado de Guerrero, el 21.9% de las niñas y niños presentaron talla baja, mientras que el 10% presentó un bajo peso. En contraste el\n16.9% presentaron sobrepeso mientras que el 10.7% obesidad.\nLa población que se encuentra en condición de pobreza extrema tiene mayores dificultades para cubrir sus necesidades básicas de alimentación, agravados por los efectos de la pandemia del COVID-19, que repercute en una economía inestable, reduciendo oportunidades de empleo, disminución del poder adquisitivo, y el alza en los costos de alimentación, lo cual no permite contar con una alimentación que sea de cantidad, calidad y diversidad nutritiva, vulnerando los derechos constitucionales, particularmente en las familias de menor ingreso, las cuales destinan una mayor proporción de su gasto total a la compra de alimentos, sin embargo, los malos hábitos alimenticios y el aumento en el consumo de alimentos hipercalóricos, ricos en grasas, sal, azúcar y pobres en vitaminas, minerales y fibras; así como el descenso en la actividad física provoca que no siempre cuenten con una alimentación adecuada, en el caso de que lleguen a cubrir sus necesidades de alimentación.\nPor tanto, en el Programa se atenderá a la población infantil del estado de Guerrero que se encuentran estudiando en alguna de las escuelas de nivel básico (preescolar, primaria y secundaria) y que sufre algún grado de inseguridad alimentaria, dando prioridad a aquellas escuelas que fueron beneficiarias durante el ejercicio fiscal 2022, las cuales pueden consultar en el anexo 3 de las presentes Reglas de Operación.\n2.1.1. Población Potencial.\nSegún datos del Censo Poblacional 2020, existen en el estado de Guerrero 1,104,905 niñas y niños de entre 0 a 15 años, lo cual representa el 31% de la población total de nuestra entidad. (REFORMADO,\nPARA EL EJERCICIO FISCAL 2022\n{\"tabla_1\":{\"columnas\":[\"RANGO DE EDAD\",\"NIÑAS\",\"NIÑOS\",\"TOTALES\"],\"filas\":[{\"columna_1\":\"Menos de 1 año\",\"columna_2\":\"33,436\",\"columna_3\":\"34,013\",\"columna_4\":\"67,449\"},{\"columna_1\":\"1 año\",\"columna_2\":\"31,525\",\"columna_3\":\"32,404\",\"columna_4\":\"63,929\"},{\"columna_1\":\"2 años\",\"columna_2\":\"32,584\",\"columna_3\":\"33,544\",\"columna_4\":\"66,128\"},{\"columna_1\":\"3 años\",\"columna_2\":\"33,928\",\"columna_3\":\"34,077\",\"columna_4\":\"68,005\"},{\"columna_1\":\"4 años\",\"columna_2\":\"34,653\",\"columna_3\":\"35,294\",\"columna_4\":\"69,947\"},{\"columna_1\":\"5 años\",\"columna_2\":\"34,436\",\"columna_3\":\"35,492\",\"columna_4\":\"69,928\"},{\"columna_1\":\"6 años\",\"columna_2\":\"33,457\",\"columna_3\":\"33,443\",\"columna_4\":\"66,900\"},{\"columna_1\":\"7 años\",\"columna_2\":\"35,154\",\"columna_3\":\"35,818\",\"columna_4\":\"70,972\"},{\"columna_1\":\"8 años\",\"columna_2\":\"36,093\",\"columna_3\":\"37,282\",\"columna_4\":\"73,375\"},{\"columna_1\":\"9 años\",\"columna_2\":\"34,707\",\"columna_3\":\"35,128\",\"columna_4\":\"69,835\"},{\"columna_1\":\"10 años\",\"columna_2\":\"35,808\",\"columna_3\":\"37,845\",\"columna_4\":\"73,653\"},{\"columna_1\":\"11 años\",\"columna_2\":\"33,412\",\"columna_3\":\"33,993\",\"columna_4\":\"67,405\"},{\"columna_1\":\"12 años\",\"columna_2\":\"34,615\",\"columna_3\":\"36,069\",\"columna_4\":\"70,684\"},{\"columna_1\":\"13 años\",\"columna_2\":\"33,888\",\"columna_3\":\"33,778\",\"columna_4\":\"67,666\"},{\"columna_1\":\"14 años\",\"columna_2\":\"34,537\",\"columna_3\":\"34,548\",\"columna_4\":\"69,085\"},{\"columna_1\":\"15 años\",\"columna_2\":\"35,031\",\"columna_3\":\"34,913\",\"columna_4\":\"69,944\"},{\"columna_1\":\"(sin dato)\",\"columna_2\":\"547,264\",\"columna_3\":\"557,641\",\"columna_4\":\"1,104,905\"}]}}\nFUENTE: INEGI. Censo de Población y Vivienda 2020.\nPor otra parte, datos de la Dirección General de Planeación, Programación y Estadística Educativa en sus datos preliminares del mes de septiembre del 2022 para el ciclo escolar 2022/2023 de la básico (preescolar, primaria y secundaria) es de un total de 754,227 alumnos de los cuales 373,145 son niñas y 381,082 son niños; distribuidos en 9,930 escuelas sin contar educación inicial.\nPARA EL EJERCICIO FISCAL 2022\nNIVEL ESCOLAR NO. ALUMNOS NIÑAS NIÑOS DOCENTES\nESCUELAS TOTALES\nPREESCOLAR 3,747 159,330 78,931 80,399 9,661\nPRIMARIA 4,312 417,166 205,278 211,888 20,960\nSECUNDARIA 1,871 177,731 88,936 88,795 11,998\nTOTAL\n9,930 754,227 373,145 381,082 42,619\n2.1.2. Población Objetivo.\nLas acciones del Programa de Alimentación para el Bienestar de Niñas y Niños consideran como población objetivo a las niñas y niños inscritos en las escuelas de nivel básico que se encuentran localizadas en los\nMunicipios y localidades de alta y muy alta marginación del estado de Guerrero. A saber, las cifras preliminares de la Dirección General de Planeación, Programación y Estadística Educativa de la Secretaría de Educación Pública, del número total de escuelas de nivel básico, 6,800 escuelas se encuentran localizadas en localidades de alta y muy alta marginación, donde se encuentran inscritos un total de\n431,281 en el presente ciclo escolar en dichas escuelas de los cuales, 213,720 son mujeres y 217,561 son hombres.\nNIVEL ESCOLAR NO. ESCUELAS ALUMNOS TOTALES Mujeres Hombres\nPREESCOLAR 2,558 96,543 47,799 48,744\nPRIMARIA 2,974 243,288 119,906 123,382\nSECUNDARIA 1,268 91,450 46,015 45,435\nTOTAL 6,800 431,281 213,720 217,561\n2.1.3. Población Beneficiaria.\nSe considerarán beneficiarias y beneficiarios, a la población de alumnado con matrícula vigente que estudien en las escuelas de nivel básico que integran el padrón de escuelas beneficiarias del Programa.\nAdemás, se considerarán, población beneficiaria a las escuelas de nuevo ingreso al padrón de escuelas beneficiarias del Programa que la SBGRO integre durante el presente ejercicio fiscal, siempre y cuando\nPARA EL EJERCICIO FISCAL 2022\n2.1.4. Población Indígena.\nEl Programa podrá beneficiar a niñas y niños inscritos en escuelas de nivel básico que pertenezcan a 39 municipios indígenas y afromexicanos de alta y muy alta marginación, dentro del territorio Guerrerense, y que cumplan los requisitos previstos en las presentes Reglas de Operación.\nPREES COLAR PRIM ARIA SECUN DARIA TO TAL total total total total\nN. MUNICIPIO Escuelas alumnos Escuelas alumnos Escuelas alumnos Escuelas alumnos\n1 ACATEPEC 62 2,753 64 6,292 46 2,666 172 11,711\n2 AHUACUOTZINGO 16 585 31 1,838 25 1,362 72 3,785\n3 ALCOZAUCA DE GUERRERO 30 1,531 34 3,643 10 1,073 74 6,247\n4 ATENANGO DEL RÍO 0 1 165 0 1 165\n5 ATLAMAJALCINGO DEL MONTE 12 339 14 861 4 285 30 1,485\n6 ATLIXTAC 38 1,450 40 3,637 26 1,719 104 6,806\n7 AYUTLA DE LOS LIBRES 48 1,569 60 3,751 49 3,790 157 9,110\n9 CHILAPA DE ÁLVAREZ 68 2,815 69 5,390 36 2,055 173 10,260\n10 COCHOAPA EL GRANDE 36 1,513 58 3,964 11 780 105 6,257\n12 COPALILLO 14 637 11 1,729 11 725 36 3,091\n13 COPANATOYAC 42 1,509 43 3,289 12 991 97 5,789\n14 CUAJINICUILAPA 1 35 1 106 0 2 141\n15 CUALÁC 7 224 11 461 4 149 22 834\n16 HUITZUCO DE LOS FIGUEROA 4 232 2 450 2 243 8 925\n17 IGUALAPA 9 466 8 761 5 255 22 1,482\n18 ILIATENCO 24 798 23 1,127 7 823 54 2,748\n19 JOSÉ JOAQUÍN DE HERRERA 23 957 29 2,602 11 1,110 63 4,669\n21 MALINALTEPEC 64 2,102 58 4,730 19 1,992 141 8,824\n22 MARQUELIA 1 12 2 93 0 3 105\n23 MÁRTIR DE CUILAPAN 15 771 11 1,307 14 973 40 3,051\n24 METLATÓNOC 42 1,735 54 3,840 17 1,156 113 6,731\n25 OLINALÁ 31 1,100 31 2,219 15 1,305 77 4,624\n26 OMETEPEC 28 1,808 30 3,549 8 1,237 66 6,594\n27 QUECHULTENANGO 14 287 17 803 8 452 39 1,542\n28 SAN LUIS ACATLÁN 42 1,825 42 4,449 27 2,973 111 9,247\n30 TEPECOACUILCO DE TRUJANO 5 267 7 781 5 376 17 1,424\n31 TIXTLA DE GUERRERO 5 290 4 253 2 333 11 876\n32 TLACOACHISTLAHUACA 24 1,306 27 3,536 19 1,339 70 6,181\n33 TLACOAPA 24 600 24 1,346 5 571 53 2,517\n34 TLALIXTAQUILLA DE MALDONADO 2 128 2 362 1 74 5 564\n35 TLAPA DE COMONFORT 66 3,317 74 7,090 29 5,591 169 15,998\n36 XALPATLÁHUAC 20 778 22 1,834 10 609 52 3,221\n37 XOCHISTLAHUACA 43 1,660 48 3,596 27 1,497 118 6,753\n38 ZAPOTITLÁN TABLAS 16 736 18 1,635 11 550 45 2,921\n39 ZITLALA 20 714 15 1,043 8 1,077 43 2,834\nTOTAL 901 36982 994 83027 487 40275 2382 160284\nLos Municipios del cuadro anterior, son de acuerdo con el catálogo de localidades indígenas, del Instituto\nGeneral de Planeación, Programación y Estadística Educativa de la Secretaría de Educación Pública.\n2.2. Fundamento Legal. jurídico en los ordenamientos siguientes:\na) Constitución Política de los Estados Unidos mexicanos.\nb) Ley General de Desarrollo Social.\nPARA EL EJERCICIO FISCAL 2022\nc) Ley General de Salud.\nd) Ley de Coordinación Fiscal.\nf) Ley Orgánica de la Administración Pública del Estado de Guerrero Número 242. (REFORMADO, P.O. 37\nALCANCE I, 09 DE MAYO DE 2023)\ng) Ley Núm. 102, para el Desarrollo Social del Estado de Guerrero.\nh) Ley Número 207 de Transparencia y Acceso a la Información Pública del Estado de Guerrero.\ni) Ley Número 454 de Presupuesto y Disciplina Fiscal del Estado de Guerrero.\nj) Ley Número 465 de Responsabilidades Administrativas para el Estado de Guerrero.\nk) Ley Número 466 de Protección de Datos Personales en Posesión de Sujetos Obligados del Estado de\nGuerrero.\nl) Ley Número 468 de Fiscalización Superior y Rendición de Cuentas del Estado de Guerrero.\nn) Decreto Número 424 del Presupuesto de Egresos del Estado de Guerrero para el Ejercicio Fiscal 2023.\n(REFORMADO, P.O. 37 ALCANCE I, 09 DE MAYO DE 2023).\no) Reglamento de la Ley para el Desarrollo Social del Estado de Guerrero Núm. 102.\np) Ley Número 812 para la Protección de los Derechos de las Niñas, Niños y Adolescentes del Estado de Guerrero.\nq) Acuerdo que establecen los Compromisos para la Estabilidad y Desarrollo del Estado de Guerrero.\nr) Lineamientos para la Elaboración de las Reglas de Operación de los Programas Sociales Estatales para el Periodo 2022- 2027.\ns) Plan Nacional de Desarrollo 2019-2024. (ADICIONADO, P.O. 37 ALCANCE I, 09 DE MAYO DE 2023).\nt) Decreto Número 181 por medio del cual la Sexagésima Tercera Legislatura al Honorable Congreso del\n(ADICIONADO, P.O. 37 ALCANCE I, 09 DE MAYO DE 2023).\nu) Las demás disposiciones normativas aplicables.\n2.3. Definiciones y Siglas.\nDefiniciones:\nAlimentación: Conjunto de acciones mediante las cuales se proporcionan alimentos al organismo. Es decir, abarca la selección de los alimentos, el cocinado y su ingestión. La salud depende fundamentalmente de la variedad y tipos de alimentos que ingerimos.\nAlumna o alumno: Persona que recibe enseñanzas de un maestro o que sigue estudios en una institución pública o privada.\nAutonomía curricular: Es la facultad que tienen las escuelas para decidir una parte del currículo de acuerdo con los intereses y las necesidades educativas específicas de las y los alumnos, las horas lectivas que cada escuela tenga disponibles y la capacidad organizacional para su implementación, acciones que les permitirá fortalecer los aprendizajes de las y los alumnos.\nPARA EL EJERCICIO FISCAL 2022\nComités de alimentación escolar: Serán los responsables de coordinar las acciones necesarias para la producción y elaboración de los alimentos escolares, además de coordinar el seguimiento del Programa.\nEstará integrado por la sociedad de padres de familia, las autoridades escolares que sean designadas por parte de la escuela beneficiaria y el personal de la Secretaría de Desarrollo y Bienestar Social.\nComité: Comité de Alimentación. (ADICIONADO, P.O. 37 ALCANCE I, 09 DE MAYO DE 2023).\nDesnutrición infantil: Es una enfermedad que aparece como resultado del consumo insuficiente de alimentos en cantidad y calidad suficiente, de la aparición repetitiva de enfermedades infecciosas y de factores sociales que afectan el estado nutricional de la niñez.\nGranja escolar: Al igual que el huerto escolar es el espacio necesario y suficiente de colaboración destinado en las escuelas para la producción de huevo y carne de aves de doble propósito.\nHuerto escolar: Es un espacio de encuentro y colaboración entre alumnas, alumnos, docentes y padres de familia que interactúan en las diferentes actividades para el establecimiento, mantenimiento y producción en el huerto.\nMarginación: tener desventaja económica, profesional, política o de estado social, grupo que debe integrarse a alguno de los sistemas del funcionamiento social.\nPersona beneficiaria: Persona que recibe un apoyo económico o en especie, previamente seleccionado después de cumplir con ciertos requisitos.\nPrograma: Programa de Alimentación para el Bienestar de Niñas y Niños, dirigido a todas aquellas personas estudiantes inscritas en instituciones públicas de educación nivel básico que se encuentran localizadas en los Municipios y localidades de alta y muy alta marginación del estado de Guerrero.\nReglas de operación: Reglas de Operación del Programa de Alimentación para el Bienestar de Niñas y\nNiños para el Ejercicio Fiscal 2022.\nSeguridad alimentaria: Consiste en garantizar que la totalidad de las personas que integran una comunidad puedan tener acceso de forma permanente a una alimentación sin riesgos, equilibrada y suficiente para cubrir sus necesidades nutricionales.\nVulnerabilidad social: Término utilizado para describir la inhabilitación de los derechos de las personas, organizaciones o sociedades en situaciones extremas, responde a dimensiones del ser humano en las cuales el abuso conlleva a la exclusión social.\nPARA EL EJERCICIO FISCAL 2022\nSiglas:\nIED: Inversión Estatal Directa.\nCONAPO: Consejo Nacional de Población- regula el crecimiento poblacional, movimientos demográficos, SBGRO: Secretaría de Bienestar del Estado de Guerrero. (REFORMADO, P.O. 37 ALCANCE I, 09 DE MAYO DE\n2023)\nSEFINA: Secretaría de Finanzas y Administración del Gobierno de Estado.\nSEPLADER: Secretaría de Planeación y Desarrollo Regional del Gobierno del Estado.\nSIBIS: Sistema de Información para el Bienestar Social. (ADICIONADO, P.O. 37 ALCANCE I, 09 DE MAYO DE\n2023).\n3. Objetivos y Alcances.\n3.1. Objetivo General.\nProveer una alimentación sana, nutritiva y suficiente a las niñas y niños que cursan la educación básica de las zonas con mayor vulnerabilidad del estado de Guerrero mediante la implementación de apoyos en especie necesarios para mejorar las condiciones que les permitan continuar sin interrupción sus estudios e incrementar su rendimiento escolar. (REFORMADO, P.O. 37 ALCANCE I, 09 DE MAYO DE 2023)\n3.2. Objetivos Específicos. (REFORMADO, P.O. 37 ALCANCE I, 09 DE MAYO DE 2023)\na) Incrementar, mediante apoyos en especie, la capacidad productiva de huertos y granjas establecidos.\nb) Dotar a las escuelas beneficiarias de kits de bienes de consumo, los cuales se integrarán con productos de primera necesidad, según la cantidad de alumnado, para complementar la dieta alimentaria que se escolares.\nc) Entregar, a los comités de alimentación, apoyos en especie destinados al equipamiento de áreas de cocina y comedores escolares en las escuelas dándole prioridad a las más necesitadas.\nd) Incorporar nuevas escuelas, de acuerdo a lo establecido en las presentes Reglas de Operación, al ejercicio fiscal vigente.\nPARA EL EJERCICIO FISCAL 2022\n3.3. Cobertura.\nEl Programa tendrá cobertura estatal, dando prioridad a la población estudiantil de las escuelas de nivel básico que integran el padrón de escuelas beneficiarias del Programa y en el que, además, se considerará la integración de nuevas escuelas a dicho padrón, siempre y cuando cumplan con los requisitos y criterios establecidos en las presentes Reglas de Operación y que por ningún motivo sean sujetas o estén siendo beneficiadas con apoyos de las mismas características de este Programa por parte de otra dependencia o programa del Gobierno Federal o Estatal. (REFORMADO, P.O. 37 ALCANCE I, 09 DE MAYO DE 2023)\n3.4. Alcances.\nEl Programa al tener como objetivo el proveer de una alimentación sana y suficiente a las niñas y niños del estado de Guerrero que viven en situación de vulnerabilidad buscamos que mediante la entrega de apoyos en especie, podamos lograr los alcances esperados, entre, lo que destacamos, la importancia de garantizar el derecho a la alimentación así como disminuir los índices de deserción escolar ocasionados por la falta de alimentos, además de contribuir a disminuir el gasto familiar que implica la adquisición de alimentos en los hogares. (REFORMADO, P.O. 37 ALCANCE I, 09 DE MAYO DE 2023)\nPor ello, se vuelve necesario, las acciones que contempla el Programa para el equipamiento de cocinas y comedores escolares, así como la ampliación de los módulos de producción para incrementar su productividad y, además, la dotación de kits de consumo con los productos de primera necesidad, todo esto acorde a las necesidades y matrícula vigente de las escuelas. Todo ello, serán aportaciones en especie que la SBGRO otorgará a las escuelas que integran el Padrón de Escuelas Beneficiarias y las que se sumen durante el presente ejercicio fiscal según los criterios y requisitos establecidos.\n4. Metas Físicas.\nEl Programa para el ejercicio fiscal 2023 se establecen las siguientes metas, mismas que se resumen en la tabla siguiente: (REFORMADO, P.O. 37 ALCANCE I, 09 DE MAYO DE 2023)\nNO. CONCEPTO CANTIDAD DESCRIPCIÓN\n1 PADRÓN DE ESCUELAS BENEFICIARIAS 105 ESCUELAS\n2 ALUMNADO BENEFICIADOS 7,500 ALUMNOS\n3 IMPULSAR LA PRODUCCIÓN AGROECOLÓGICA DE 105 ESCUELAS\nCULTIVOS PARA LA DOTACIÓN DE ALIMENTOS\nESCUELAS BENEFICIARIAS DEL PROGRAMA DE\nALIMENTACIÓN PARA EL EJERCICIO FISCAL 2023\n4 PUESTA EN MARCHA DE COMEDORES ESCOLARES\n90 COMEDORES\nPARA EL EJERCICIO FISCAL 2022\n{\"tabla_2\":{\"columnas\":[\"5\",\"PUESTA EN MARCHA DE COCINAS ESCOLARES\",\"90\",\"COCINAS\"],\"filas\":[{\"columna_1\":\"6\",\"columna_2\":\"MANTENIMIENTO DE MÓDULOS DE PRODUCCIÓN\",\"columna_3\":\"(sin dato)\",\"columna_4\":\"(sin dato)\"},{\"columna_1\":\"(sin dato)\",\"columna_2\":\"ESCOLAR\",\"columna_3\":\"84\",\"columna_4\":\"ESCUELAS\"},{\"columna_1\":\"7\",\"columna_2\":\"AMPLIACIÓN DE MÓDULOS DE PRODUCCIÓN ESCOLAR\",\"columna_3\":\"(sin dato)\",\"columna_4\":\"(sin dato)\"},{\"columna_1\":\"(sin dato)\",\"columna_2\":\"(sin dato)\",\"columna_3\":\"50\",\"columna_4\":\"ESCUELAS\"},{\"columna_1\":\"8\",\"columna_2\":\"INCORPORACIÓN DE NUEVAS ESCUELAS AL PADRÓN\",\"columna_3\":\"(sin dato)\",\"columna_4\":\"(sin dato)\"},{\"columna_1\":\"(sin dato)\",\"columna_2\":\"DE ESCUELAS BENEFICIARIAS DEL PROGRAMA DE\",\"columna_3\":\"(sin dato)\",\"columna_4\":\"(sin dato)\"},{\"columna_1\":\"(sin dato)\",\"columna_2\":\"ALIMENTACIÓN PARA EL EJERCICIO FISCAL 2023,\",\"columna_3\":\"(sin dato)\",\"columna_4\":\"(sin dato)\"},{\"columna_1\":\"(sin dato)\",\"columna_2\":\"(sin dato)\",\"columna_3\":\"21\",\"columna_4\":\"ESCUELAS\"},{\"columna_1\":\"(sin dato)\",\"columna_2\":\"CLASIFICADAS POR EL NÚMERO DE ALUMNAS Y\",\"columna_3\":\"(sin dato)\",\"columna_4\":\"(sin dato)\"},{\"columna_1\":\"(sin dato)\",\"columna_2\":\"ALUMNOS VIGENTES AL CICLO ESCOLAR.\",\"columna_3\":\"(sin dato)\",\"columna_4\":\"(sin dato)\"},{\"columna_1\":\"9\",\"columna_2\":\"DOTACIÓN DE KITS DE BIENES DE CONSUMO DE\",\"columna_3\":\"(sin dato)\",\"columna_4\":\"KITS\"},{\"columna_1\":\"(sin dato)\",\"columna_2\":\"PRIMERA NECESIDAD PARA LA ALIMENTACIÓN DE\",\"columna_3\":\"(sin dato)\",\"columna_4\":\"ESCOLARES\"},{\"columna_1\":\"(sin dato)\",\"columna_2\":\"(sin dato)\",\"columna_3\":\"1,000\",\"columna_4\":\"(sin dato)\"},{\"columna_1\":\"(sin dato)\",\"columna_2\":\"NIÑAS Y NIÑOS POR ESCUELA BENEFICIARIA\",\"columna_3\":\"(sin dato)\",\"columna_4\":\"(sin dato)\"}]}}\nPARA EL EJERCICIO FISCAL 2022\nLos apoyos en especie contemplados en este Programa, serán otorgados de acuerdo a lo establecido en las presentes Reglas de Operación y de conformidad a la disponibilidad presupuestal y financiera.\na) Criterios de Elegibilidad.\nPrograma, deberá contener lo siguiente:\n● Ser una de las 84 escuelas de educación básica enlistadas en dicho Padrón.\n● Contar con acta de integración de Comité de Alimentación vigente o con sus respectivas modificaciones; integrado por un mínimo de 7 y un máximo de 15 madres o padres de familia.\n● En caso de ser una escuela con matrícula vigente de más de 60 alumnas o alumnos, y requerir la ampliación del huerto y la granja escolar, deberán contar con el espacio suficiente según sean las necesidades de cada escuela.\nPARA EL EJERCICIO FISCAL 2022\n● Contar con el espacio suficiente para el equipamiento de los comedores y áreas de cocina. Este espacio puede estar dentro o fuera de la institución escolar, a consideración del Comité de Alimentación, con la de cocina, así como para la elaboración de los alimentos que se realizarán para las y los alumnos de la escuela.\n● Aquellas que además de ser seleccionadas por el Programa, cumplan en tiempo y forma con la entrega de los requisitos.\n● Para la integración de los expedientes por el tipo de apoyo que se le vaya a otorgar, deberán contar con una Cédula técnica expedido por personal de la SBGRO en donde constate las necesidades que requiere cada escuela conforme el historial de trabajo realizado en ellas.\nPara la incorporación de nuevas escuelas al padrón de beneficiarias y beneficiarios durante el presente ejercicio fiscal, deberán cumplir lo siguiente:\n● Escuelas de educación básica ubicadas en las zonas con mayor vulnerabilidad que dentro de su matrícula vigente no rebase la cantidad de 120 alumnas y alumnos inscritos en el ciclo escolar corriente.\n● Escuelas que cuenten con las condiciones edafológicas, fuentes de abastecimiento de agua, así como con el espacio de terreno necesario para el establecimiento del huerto y la granja escolar, así como de acondicionamiento de la cocina y el comedor escolar.\n● Aquellas que además de ser seleccionadas por el Programa, cumplan en tiempo y forma con la entrega de los requisitos.\nb) Requisitos de Elegibilidad:\nPara la actualización de expedientes de las escuelas que integran el padrón de escuelas beneficiarias del\nPrograma, deberán presentar:\n● Acta de integración del Comité de Alimentación o sus respectivas modificaciones.\n● Copia de la identificación oficial de cada uno de las personas que integran el Comité de Alimentación.\n● Comprobante de domicilio vigente de la escuela.\n● Formato de solicitud dirigida a la titular de la SBGRO en donde manifieste su interés en darle continuidad al Programa, así como solicitando los respectivos apoyos que se requieran para su implementación oportuna. En caso de que tanto la cocina como el comedor no se encuentren dentro del área escolar, el\nComité de Alimentación y la directora o el director de la escuela por así decidirlo conveniente, deberán expedir un oficio dirigido a la titular de la SBGRO en donde se justifique esta razón. Dicha solicitud deberá ir acompañada de la firma y sello de visto bueno de la autoridad de la localidad. Además, de que en caso\nPARA EL EJERCICIO FISCAL 2022 de que el espacio donde se ubique, sea de algún particular, deberá integrar un contrato de comodato en\n5 años.\n● La solicitud deberá ir acompañada de la cédula técnica, misma que deberá de expedirse durante el primer trimestre del presente año por parte del personal que para tal caso, designe la SBGRO. En la cédula técnica deberá especificarse los requerimientos que tiene cada escuela ya sea de mantenimiento y ampliación de huertos, así como de equipamiento de áreas de comedor y cocinas.\n● En caso de ser una escuela que cuenta con una matrícula de alumnas y alumnos vigentes mayor a 65 deberá integrar y especificar en la cédula técnica correspondiente en donde señale que cuentan con el espacio necesario que permite la ampliación de los espacios destinados para el huerto y la granja escolar.\n● Listado de alumnas y alumnos vigentes.\nPara la incorporación de nuevas escuelas al padrón de beneficiarias y beneficiarios durante el presente ejercicio fiscal, deberán presentar:\n● Acta de asamblea de la sociedad de madres y padres de familia en donde se nombren una persona representante del Comité, así como de la tesorería o secretaría y vocalía. Además, deberá especificar que dicho Comité estará nombrado exclusivamente para la ejecución y operación del Programa en la escuela interesada.\n● Copia de la identificación oficial de cada uno de las personas que integran el Comité.\n● Comprobante de domicilio donde se ubica la escuela.\n● Solicitud dirigida a la titular de la SBGRO firmada por la persona representante del Comité y la autoridad escolar vigente en donde manifieste estar interesadas en participar en el Programa.\n● Ficha donde se indica que la escuela cuenta con los requerimientos técnicos necesarios para la factibilidad del proyecto.\n● Croquis a mano alzada de la ubicación de la escuela, así como del espacio designado para la instalación del huerto y la granja.\n● Al menos 4 fotografías a color impresas del lugar o los lugares donde se pretende implementar la instalación de los módulos de producción.\n● Listado de alumnas y alumnos vigentes.\n● Carta compromiso en la que padres de familia y autoridades escolares aceptan las disposiciones que en materia de estos apoyos resulten necesarios para lograr los objetivos establecidos por el Programa.\nPARA EL EJERCICIO FISCAL 2022\n● En caso de no contar con el espacio dentro del área escolar, deberán notificar mediante oficio dirigida a la titular de la SBGRO, así como integrar su respectivo contrato de comodato del área a utilizarse.\n● En caso de ser escuelas que requieran los apoyos de equipo, mobiliario y enseres domésticos para el acondicionamiento de cocinas y comedores escolares, deberán integrar la solicitud correspondiente para tal caso, una para cada concepto de apoyo.\n7. Tipo, Monto y Periodicidad de los Apoyos. (REFORMADO, P.O. 37 ALCANCE I, 09 DE MAYO DE 2023)\nPara la ejecución del Programa durante el presente ejercicio fiscal y para una mejor comprensión de los tipos de apoyo y siguiendo con el esquema de continuidad planteado, es menester mencionar que, en base al Padrón de Escuelas Beneficiarias del año en curso se elaboró una clasificación de escuelas por el número de alumnas y alumnos registrados como vigente, quedando dicha clasificación como sigue:\nTABLA DE CLASIFICACIÓN DE ESCUELAS POR NÚMERO DE ALUMNAS Y ALUMNOS\n{\"tabla_4\":{\"columnas\":[\"CATEGORÍA\",\"NÚMERO DE ALUMNADO\"],\"filas\":[{\"columna_1\":\"CAT1\",\"columna_2\":\"20-40\"},{\"columna_1\":\"CAT2\",\"columna_2\":\"41-65\"},{\"columna_1\":\"CAT3\",\"columna_2\":\"66-100\"},{\"columna_1\":\"CAT4\",\"columna_2\":\"101-150\"},{\"columna_1\":\"CAT5\",\"columna_2\":\"101-151\"}]}}\nDe acuerdo a la clasificación anterior el Programa tiene tres vertientes de apoyo.\nCOMPONENTE A: EQUIPAMIENTO DE CANTIDAD DE\nCOMEDORES ESCOLARES. APOYOS MONTO DE LOS APOYOS\nPor única vez, hasta\n$25,000.00 (Veinticinco mil\nEQUIPAMIENTO DE COCINAS ESCOLARES 90 pesos 00/100 M.N.) por\nEscuela\nPor única vez, hasta\n$20,000.0 (Veinte mil pesos\nEQUIPAMIENTO DE COMEDORES ESCOLARES 90\n00/100 M.N.) por Escuela\nPARA EL EJERCICIO FISCAL 2022\n{\"tabla_5\":{\"columnas\":[\"COMPONENTE B: MODULOS DE PRODUCCIÓN\",\"CANTIDAD DE\",\"MONTO DE LOS APOYOS\"],\"filas\":[{\"columna_1\":\"ESCOLAR\",\"columna_2\":\"APOYOS\",\"columna_3\":\"(sin dato)\"},{\"columna_1\":\"(sin dato)\",\"columna_2\":\"(sin dato)\",\"columna_3\":\"Por única vez, hasta\"},{\"columna_1\":\"(sin dato)\",\"columna_2\":\"(sin dato)\",\"columna_3\":\"$25,000.00 (Veinticinco\"},{\"columna_1\":\"AMPLIACIÓN DE MÓDULOS DE PRODUCCIÓN\",\"columna_2\":\"(sin dato)\",\"columna_3\":\"(sin dato)\"},{\"columna_1\":\"(sin dato)\",\"columna_2\":\"50\",\"columna_3\":\"mil pesos 00/100 M.N.)\"},{\"columna_1\":\"(Huertos y granjas establecidos)\",\"columna_2\":\"(sin dato)\",\"columna_3\":\"(sin dato)\"},{\"columna_1\":\"(sin dato)\",\"columna_2\":\"(sin dato)\",\"columna_3\":\"por Escuela\"},{\"columna_1\":\"MANTENIMIENTO DE MÓDULOS DE PRODUCCIÓN\",\"columna_2\":\"(sin dato)\",\"columna_3\":\"Por única vez, hasta\"},{\"columna_1\":\"ESTABLECIDOS (semillas, medicamentos,\",\"columna_2\":\"(sin dato)\",\"columna_3\":\"$8,000.00 (Ocho mil\"},{\"columna_1\":\"herramientas, nutrientes, alimentos, etc)\",\"columna_2\":\"84\",\"columna_3\":\"pesos 00/100 M.N.) por\"},{\"columna_1\":\"(sin dato)\",\"columna_2\":\"(sin dato)\",\"columna_3\":\"Escuela\"},{\"columna_1\":\"INCORPORACIÓN DE NUEVOS MÓDULOS\",\"columna_2\":\"(sin dato)\",\"columna_3\":\"Por única vez, hasta\"},{\"columna_1\":\"CATEGORÍA 1\",\"columna_2\":\"(sin dato)\",\"columna_3\":\"$35,000.00 (Treinta y\"},{\"columna_1\":\"(sin dato)\",\"columna_2\":\"(sin dato)\",\"columna_3\":\"cinco mil pesos 00/100\"},{\"columna_1\":\"(sin dato)\",\"columna_2\":\"(sin dato)\",\"columna_3\":\"M.N.) por Escuela para\"},{\"columna_1\":\"(sin dato)\",\"columna_2\":\"2\",\"columna_3\":\"los dos módulos (huerto\"},{\"columna_1\":\"(sin dato)\",\"columna_2\":\"(sin dato)\",\"columna_3\":\"y granja) según\"},{\"columna_1\":\"(sin dato)\",\"columna_2\":\"(sin dato)\",\"columna_3\":\"especificaciones\"},{\"columna_1\":\"(sin dato)\",\"columna_2\":\"(sin dato)\",\"columna_3\":\"técnicas\"},{\"columna_1\":\"(sin dato)\",\"columna_2\":\"(sin dato)\",\"columna_3\":\"Por única vez, hasta\"},{\"columna_1\":\"(sin dato)\",\"columna_2\":\"(sin dato)\",\"columna_3\":\"$45,000.00 (Cuarenta y\"},{\"columna_1\":\"(sin dato)\",\"columna_2\":\"(sin dato)\",\"columna_3\":\"cinco mil pesos 00/100\"},{\"columna_1\":\"(sin dato)\",\"columna_2\":\"(sin dato)\",\"columna_3\":\"M.N.) por Escuela para\"},{\"columna_1\":\"INCORPORACIÓN DE NUEVOS MÓDULOS\",\"columna_2\":\"(sin dato)\",\"columna_3\":\"(sin dato)\"},{\"columna_1\":\"(sin dato)\",\"columna_2\":\"6\",\"columna_3\":\"los dos módulos (huerto\"},{\"columna_1\":\"CATEGORÍA 2\",\"columna_2\":\"(sin dato)\",\"columna_3\":\"(sin dato)\"},{\"columna_1\":\"(sin dato)\",\"columna_2\":\"(sin dato)\",\"columna_3\":\"y granja) según\"},{\"columna_1\":\"(sin dato)\",\"columna_2\":\"(sin dato)\",\"columna_3\":\"especificaciones\"},{\"columna_1\":\"(sin dato)\",\"columna_2\":\"(sin dato)\",\"columna_3\":\"técnicas\"},{\"columna_1\":\"(sin dato)\",\"columna_2\":\"(sin dato)\",\"columna_3\":\"Por única vez, hasta\"},{\"columna_1\":\"(sin dato)\",\"columna_2\":\"(sin dato)\",\"columna_3\":\"$55,800.00 (Cincuenta y\"},{\"columna_1\":\"(sin dato)\",\"columna_2\":\"(sin dato)\",\"columna_3\":\"cinco mil ochocientos\"},{\"columna_1\":\"(sin dato)\",\"columna_2\":\"(sin dato)\",\"columna_3\":\"pesos 00/100 M.N.) por\"},{\"columna_1\":\"INCORPORACIÓN DE NUEVOS MÓDULOS\",\"columna_2\":\"(sin dato)\",\"columna_3\":\"Escuela para los dos\"},{\"columna_1\":\"(sin dato)\",\"columna_2\":\"6\",\"columna_3\":\"(sin dato)\"},{\"columna_1\":\"CATEGORÍA 3\",\"columna_2\":\"(sin dato)\",\"columna_3\":\"módulos (huerto y\"},{\"columna_1\":\"(sin dato)\",\"columna_2\":\"(sin dato)\",\"columna_3\":\"granja) según\"},{\"columna_1\":\"(sin dato)\",\"columna_2\":\"(sin dato)\",\"columna_3\":\"especificaciones\"},{\"columna_1\":\"(sin dato)\",\"columna_2\":\"(sin dato)\",\"columna_3\":\"técnicas\"}]}}\nPARA EL EJERCICIO FISCAL 2022\nPor única vez, hasta\n$70,000.00 (Setenta mil pesos 00/100 M.N.) por\nEscuela para los dos\nINCORPORACIÓN DE NUEVOS MÓDULOS\n4 módulos (huerto y\nCATEGORÍA 4 granja) según especificaciones técnicas\nCOMPONENTE C: KITS DE BIENES DE CONSUMO PRIMERA NECESIDAD M\nCATEGORÍA NO. ESCUELAS MONTO DE APOYO CANTIDAD PERIODICIDAD\nHasta $3,500.00 (Tres mil quinientos pesos 00/100 M.N.)\n10 MENSUAL por Escuela\nCAT1 16\nHasta $5,000.00 (Cinco mil pesos 10 MENSUAL\nCAT2 28 00/100 M.N.) por Escuela\nHasta $7,500.00 (Siete mil quinientos pesos 00/100 M.N.)\n10 MENSUAL por Escuela\nCAT3 29\nHasta $9,800.00 (Nueve mil ochocientos pesos 00/100 M.N.)\n10 MENSUAL por Escuela\nCAT4 16\nHasta por $12,000.00 (Doce mil 10 MENSUAL\nCAT5 16 pesos 00/100 M.N.) por Escuela\na) Equipamiento de Comedores Escolares: Consiste en brindar apoyos en especie relacionados con el equipamiento, ampliación, así como herramientas e insumos para el buen funcionamiento de las cocinas ejercicio fiscal 2023.\nPARA EL EJERCICIO FISCAL 2022\nNO. CONCEPTO DE APOYO CARACTERISTICAS\n1 EQUIPAMIENTO DE COCINAS Se refiere a la dotación de equipos para el adquisición de paquetes que pueden incluir, algunos de los siguientes:\nPAQUETE 1 PAQUETE 2\nEstufa de gas Parrilla de 2 y 3 hornillas\nTanque de gas Tanque de gas\nKit de instalación Kit de instalación\nComal Comal\nPAQUETE 3\nConstrucción de Estufa\nEcológica\nComales\nDentro de cada paquete podrá incluirse Licuadoras, freidoras, extractor de jugos o electrodomésticos según las necesidades de la escuela sin rebasar los montos máximos establecidos.\nAdemás de lo anterior, también deberá incluirse, según las necesidades de cada escuela, la dotación de utensilios y enseres necesarios para la elaboración y posterior dotación de las comidas de los niños en los comedores escolares. Se otorgará un paquete en el que se incluyan: Ollas, vaporeras, sartenes de distintos tamaños, recipientes de plásticos, vasos, platos, cubiertos, cuchillos, jarras, tazas, vitroleros, etc.\n2 EQUIPAMIENTO DE COMEDORES Se refiere a la entrega en especie de paquetes de sillas, mesas, bancos, charolas y demás artículos necesarios para el equipamiento de los comedores escolares. otorgará un paquete de insumos como láminas, armex, bultos de cemento, polines, montenes, etc., o alimentación con la finalidad de que ellos acondicionen dichos espacios. El paquete se limitará al monto establecido.\nPARA EL EJERCICIO FISCAL 2022\nb) Módulos de Producción Escolar: Consiste en brindar apoyos en especie relacionados con el equipamiento de nuevos módulos de producción, así como la ampliación, el equipamiento y la entrega de enlistadas en el Padrón de Escuelas Beneficiarias para el ejercicio 2023 así como las que se logren incorporar, conforme la tabla siguiente:\nNO. CONCEPTO DE APOYO CARACTERISTICAS\n1 AMPLIACIÓN DE MÓDULOS DE\nAplica para las escuelas que según el numeral 7 en\nPRODUCCIÓN ESTABLECIDOS la Tabla de clasificación de escuelas por número de alumnas y alumnos, caen en el supuesto de las categorías CAT3, CAT4 y CAT5 con más de 65 alumnas y alumnos y que se encuentran en el\nPadrón de Escuelas Beneficiarias, por lo que el espacios de producción conforme a los montos establecidos. Este apoyo se refiere a la entrega en especie de insumos, principalmente para ampliar requieran. Dentro de los materiales e insumos que se pueden apoyar se encuentran, principalmente:\nGRANJAS ESCOLARES:\n* Láminas\nPARA EL EJERCICIO FISCAL 2022\n* Malla gallinera\n* Perchas de descanso de madera\n* Polines de madera\n* Comederos\n* Bebederos\n* Tabiques\n* Block\n* Cemento\n* Armex\n* Clavos\n* Arena\n* Grava\n* Gallinas de Postura\n* Charolas de germinación\n* Entre otros materiales, necesarios para la producción.\nHUERTOS ESCOLARES\n* Tinaco\n* Equipo de Riego\n* Cinta de riego\n* Malla sombra\n* Paquete de fertilizantes\n* Paquete de Bioplaguicidas\n* Composta y mejoradores de suelo\n* Charolas y sustrato\n* Malla de cercado\n* Equipo de trabajo\n* Puertas\n* Almacenes para la producción de biocombustibles\n* Entre otros materiales, necesarios para la producción.\nPARA EL EJERCICIO FISCAL 2022\n{\"tabla_6\":{\"columnas\":[\"2\",\"INSUMOS DE MANTENIMIENTO DE\",\"Se refiere al paquete de insumos complementario\"],\"filas\":[{\"columna_1\":\"(sin dato)\",\"columna_2\":\"MÓDULOS DE PRODUCCIÓN\",\"columna_3\":\"de los módulos establecidos que se hacen\"},{\"columna_1\":\"(sin dato)\",\"columna_2\":\"ESTABLECIDOS\",\"columna_3\":\"necesario para el mantenimiento y cuidado de los\"},{\"columna_1\":\"(sin dato)\",\"columna_2\":\"(sin dato)\",\"columna_3\":\"módulos de producción (huerto y granja) y se\"},{\"columna_1\":\"(sin dato)\",\"columna_2\":\"(sin dato)\",\"columna_3\":\"refiere a herramientas como palas, picos, bieldos,\"},{\"columna_1\":\"(sin dato)\",\"columna_2\":\"(sin dato)\",\"columna_3\":\"deshierbadores, martillos, guantes, carretillas,\"},{\"columna_1\":\"(sin dato)\",\"columna_2\":\"(sin dato)\",\"columna_3\":\"machetes, cavahoyos y barretas, además de\"},{\"columna_1\":\"(sin dato)\",\"columna_2\":\"(sin dato)\",\"columna_3\":\"algunos elementos complementarios para el\"},{\"columna_1\":\"(sin dato)\",\"columna_2\":\"(sin dato)\",\"columna_3\":\"funcionamiento actual de los módulos como\"},{\"columna_1\":\"(sin dato)\",\"columna_2\":\"(sin dato)\",\"columna_3\":\"puedes ser alimentos, paquetes sanitarios,\"},{\"columna_1\":\"(sin dato)\",\"columna_2\":\"(sin dato)\",\"columna_3\":\"insumos para la producción de biopesticias o\"},{\"columna_1\":\"(sin dato)\",\"columna_2\":\"(sin dato)\",\"columna_3\":\"bioplaguicidas, insumos para la elaboración de\"},{\"columna_1\":\"(sin dato)\",\"columna_2\":\"(sin dato)\",\"columna_3\":\"fertilizantes orgánicos, etc.\"},{\"columna_1\":\"(sin dato)\",\"columna_2\":\"(sin dato)\",\"columna_3\":\"Lo anterior siempre y cuando el Comité de\"},{\"columna_1\":\"(sin dato)\",\"columna_2\":\"(sin dato)\",\"columna_3\":\"Alimentación establezca un criterio en base a sus\"},{\"columna_1\":\"(sin dato)\",\"columna_2\":\"(sin dato)\",\"columna_3\":\"necesidades más importantes y según sus\"},{\"columna_1\":\"(sin dato)\",\"columna_2\":\"(sin dato)\",\"columna_3\":\"condiciones de producción.\"},{\"columna_1\":\"3\",\"columna_2\":\"PAQUETE DE INCORPORACIÓN DE\",\"columna_3\":\"(sin dato)\"},{\"columna_1\":\"(sin dato)\",\"columna_2\":\"NUEVOS MÓDULOS DE PRODUCCIÓN\",\"columna_3\":\"GRANJAS ESCOLARES Los paquetes para el\"},{\"columna_1\":\"(sin dato)\",\"columna_2\":\"(Instalación de huertos y granjas)\",\"columna_3\":\"establecimiento de nuevas granjas escolares\"},{\"columna_1\":\"(sin dato)\",\"columna_2\":\"(sin dato)\",\"columna_3\":\"incluyen:\"},{\"columna_1\":\"(sin dato)\",\"columna_2\":\"(sin dato)\",\"columna_3\":\"* Láminas\"},{\"columna_1\":\"(sin dato)\",\"columna_2\":\"(sin dato)\",\"columna_3\":\"* Malla gallinera\"},{\"columna_1\":\"(sin dato)\",\"columna_2\":\"(sin dato)\",\"columna_3\":\"* Diseño y estructura de madera\"},{\"columna_1\":\"(sin dato)\",\"columna_2\":\"(sin dato)\",\"columna_3\":\"* Perchas de descanso de madera\"},{\"columna_1\":\"(sin dato)\",\"columna_2\":\"(sin dato)\",\"columna_3\":\"* Polines de madera\"},{\"columna_1\":\"(sin dato)\",\"columna_2\":\"(sin dato)\",\"columna_3\":\"* Comederos\"},{\"columna_1\":\"(sin dato)\",\"columna_2\":\"(sin dato)\",\"columna_3\":\"* Bebederos\"},{\"columna_1\":\"(sin dato)\",\"columna_2\":\"(sin dato)\",\"columna_3\":\"* Nidales\"},{\"columna_1\":\"(sin dato)\",\"columna_2\":\"(sin dato)\",\"columna_3\":\"* Herramientas y equipo de trabajo\"},{\"columna_1\":\"(sin dato)\",\"columna_2\":\"(sin dato)\",\"columna_3\":\"* Alimentos\"},{\"columna_1\":\"(sin dato)\",\"columna_2\":\"(sin dato)\",\"columna_3\":\"* Paquete Sanitario\"},{\"columna_1\":\"(sin dato)\",\"columna_2\":\"(sin dato)\",\"columna_3\":\"* Tabiques\"},{\"columna_1\":\"(sin dato)\",\"columna_2\":\"(sin dato)\",\"columna_3\":\"* Block\"},{\"columna_1\":\"(sin dato)\",\"columna_2\":\"(sin dato)\",\"columna_3\":\"* Cemento\"},{\"columna_1\":\"(sin dato)\",\"columna_2\":\"(sin dato)\",\"columna_3\":\"* Armex\"},{\"columna_1\":\"(sin dato)\",\"columna_2\":\"(sin dato)\",\"columna_3\":\"* Clavos\"},{\"columna_1\":\"(sin dato)\",\"columna_2\":\"(sin dato)\",\"columna_3\":\"* Arena\"},{\"columna_1\":\"(sin dato)\",\"columna_2\":\"(sin dato)\",\"columna_3\":\"* Grava\"},{\"columna_1\":\"(sin dato)\",\"columna_2\":\"(sin dato)\",\"columna_3\":\"Para las escuelas de nuevo ingreso al padrón de\"},{\"columna_1\":\"(sin dato)\",\"columna_2\":\"(sin dato)\",\"columna_3\":\"beneficiarios es necesario considerar las\"},{\"columna_1\":\"(sin dato)\",\"columna_2\":\"(sin dato)\",\"columna_3\":\"siguientes especificaciones técnicas:\"},{\"columna_1\":\"(sin dato)\",\"columna_2\":\"(sin dato)\",\"columna_3\":\"CONCEPTO NO. MEDIDAS * NÚMERO DE\"},{\"columna_1\":\"(sin dato)\",\"columna_2\":\"(sin dato)\",\"columna_3\":\"ALUMNOS (M2) GALLINAS **\"}]}}\nPARA EL EJERCICIO FISCAL 2022\nCAT1 20-40 40 20\nCAT2 41-65 50 25\nCAT3 66-100 65 30\nCAT4 101-120 80 40\n* Las medidas se refieren al espacio en metros cuadros necesarios para el establecimiento de la granja\n** El número de gallinas se refiere a la cantidad de aves a entregarse\n*** Los comités de Alimentación deberán garantizar el abastecimiento oportuno del agua, así como garantizar el cuidado y manejo según las especificaciones técnicas\nHUERTOS ESCOLARES\n* Tinaco e instalación\n* Equipo de Riego\n* Cinta de riego\n* Malla sombra\n* Paquete de fertilizantes\n* Paquete de Bioplaguicidas\n* Composta y mejoradores de suelo\n* Herramientas de trabajo\n* Charolas y sustrato\n* Semillas\n* Plántulas\n* Cama de composteo\n* Malla de cercado\n* Equipo de trabajo\n* Puertas beneficiarios es necesario considerar las siguientes especificaciones técnicas:\nNO. MEDIDAS* NÚMERO\nCONCEPTO ALUMNOS (M2) CAMAS **\nCAT1 20-40 135 8\nCAT2 41-65 200 12\nCAT3 66-100 250 16\nCAT4 101-120 300 18\nPARA EL EJERCICIO FISCAL 2022\n* Las medidas se refieren al espacio en metros cuadros\n** El número de camas, es la cantidad de camas biointensivas a establecer.\n*** Los comités de Alimentación deberán garantizar el abastecimiento oportuno del agua, así como garantizar el cuidado y manejo según las especificaciones técnicas\nc) Kit de Bienes de Consumo de Primera Necesidad: Como ya se había mencionado, son apoyos en especie con productos de primera necesidad que complementen la dieta alimenticia juntamente con los alimentos producidos en los módulos de producción para beneficios de las escuelas que integran el Padrón de Escuelas Beneficiarias para el ejercicio fiscal 2023 bajo la siguiente categorización.\nEn base a la clasificación de escuelas por el número de alumnas y alumnos, se considerará el tamaño y cantidad de los productos que conformen este kit, el cual, contendrá, como mínimo, los productos siguientes:\n{\"tabla_7\":{\"columnas\":[\"CATEGORÍA\",\"NÚMERO ALUMNOS\",\"PRODUCTOS\",\"CARACTERISTICAS\"],\"filas\":[{\"columna_1\":\"CAT1\",\"columna_2\":\"20-40\",\"columna_3\":\"*\\nArroz\",\"columna_4\":\"Las cantidades, así como los costos\"},{\"columna_1\":\"(sin dato)\",\"columna_2\":\"(sin dato)\",\"columna_3\":\"*\\nFrijol\",\"columna_4\":\"de cada despensa variará conforme la\"},{\"columna_1\":\"CAT2\",\"columna_2\":\"41-65\",\"columna_3\":\"(sin dato)\",\"columna_4\":\"categorización establecida.\"},{\"columna_1\":\"(sin dato)\",\"columna_2\":\"(sin dato)\",\"columna_3\":\"*\\nLentejas\",\"columna_4\":\"(sin dato)\"},{\"columna_1\":\"(sin dato)\",\"columna_2\":\"(sin dato)\",\"columna_3\":\"*\\nAceite\",\"columna_4\":\"(sin dato)\"},{\"columna_1\":\"CAT3\",\"columna_2\":\"66-100\",\"columna_3\":\"(sin dato)\",\"columna_4\":\"(sin dato)\"},{\"columna_1\":\"(sin dato)\",\"columna_2\":\"(sin dato)\",\"columna_3\":\"*\\nAzúcar\",\"columna_4\":\"(sin dato)\"},{\"columna_1\":\"CAT4\",\"columna_2\":\"101-150\",\"columna_3\":\"*\\nHarina de Maíz o Maíz en\",\"columna_4\":\"(sin dato)\"},{\"columna_1\":\"(sin dato)\",\"columna_2\":\"(sin dato)\",\"columna_3\":\"grano\",\"columna_4\":\"(sin dato)\"},{\"columna_1\":\"(sin dato)\",\"columna_2\":\"(sin dato)\",\"columna_3\":\"*\\nPasta para sopa\",\"columna_4\":\"(sin dato)\"},{\"columna_1\":\"(sin dato)\",\"columna_2\":\"(sin dato)\",\"columna_3\":\"*\\nLeche en polvo\",\"columna_4\":\"(sin dato)\"},{\"columna_1\":\"(sin dato)\",\"columna_2\":\"(sin dato)\",\"columna_3\":\"*\\nSazonadores\",\"columna_4\":\"(sin dato)\"},{\"columna_1\":\"(sin dato)\",\"columna_2\":\"(sin dato)\",\"columna_3\":\"*\\nSal\",\"columna_4\":\"(sin dato)\"},{\"columna_1\":\"(sin dato)\",\"columna_2\":\"(sin dato)\",\"columna_3\":\"Además, dependiendo las necesidades\",\"columna_4\":\"(sin dato)\"},{\"columna_1\":\"(sin dato)\",\"columna_2\":\"(sin dato)\",\"columna_3\":\"de los Comités de Alimentación, se\",\"columna_4\":\"(sin dato)\"},{\"columna_1\":\"(sin dato)\",\"columna_2\":\"(sin dato)\",\"columna_3\":\"podrán integrar más productos,\",\"columna_4\":\"(sin dato)\"},{\"columna_1\":\"(sin dato)\",\"columna_2\":\"(sin dato)\",\"columna_3\":\"siempre y cuando, estos sean\",\"columna_4\":\"(sin dato)\"},{\"columna_1\":\"CAT5\",\"columna_2\":\"101-151\",\"columna_3\":\"productos de primera necesidad.\",\"columna_4\":\"(sin dato)\"}]}} durante el ejercicio fiscal 2023, siendo de carácter gratuito y sin costo alguno para las y los beneficiarios. ejecución y funcionamiento del Programa, y en consecuencia de la asesoría para la puesta en marcha del mismo.\nPARA EL EJERCICIO FISCAL 2022\n7.2. Recursos no Devengados.\nEl presupuesto autorizado al Programa que no se haya aplicado a los fines autorizados, y los recursos que por cualquier motivo no se hayan devengado al 31 de diciembre de cada ejercicio fiscal, será reintegrado inmediatamente a la instancia normativa del ejercicio y control del gasto público, es decir a la SEFINA.\n7.3. Resguardo de la Documentación.\nLa Dirección General de Desarrollo Comunitario y Desarrollo Productivo de Grupos Vulnerables de la SBGRO será el área encargada de resguardar la documentación original generada por la operación, ejecución y seguimiento del Programa, así como también tendrá bajo su resguardo la documentación comprobatoria de los recursos ejercidos además de dar seguimiento puntual de la operación hasta el cierre del ejercicio. (REFORMADO, P.O. 37 ALCANCE I, 09 DE MAYO DE 2023)\n7.4. Supervisión y Control.\nLa SBGRO, en operación del Programa y para la mejora de éste, integrará informes a través de la\nDirección General de Desarrollo Comunitario y Desarrollo Productivo de Grupos Vulnerables a través de las instancias correspondientes hasta la validación normativa por parte de la SEPLADER, así como a la SEFINA y a la Secretaría de Contraloría, mediante las cédulas o informes de registro de los indicadores, reportes de avances físico-financieros 15 días posteriores a la terminación de cada trimestre y registrar en el sistema establecido para su control, además llevará a cabo el seguimiento y supervisión de los recursos asignados al Programa. (REFORMADO, P.O. 37 ALCANCE I, 09\nDE MAYO DE 2023)\nLa SBGRO, será responsable de la supervisión directa de las obras, proyectos o acciones, así como de verificar que en su ejecución se cumpla con la normatividad aplicable. de escuelas beneficiarias del Programa, se requiere:\na) Haber utilizado de manera correcta los apoyos que le fueron otorgados.\nb) Haber concluido los trabajos necesarios para el establecimiento del huerto y la granja escolar.\nc) Manifestar mediante oficio, la solicitud de continuar en el Programa, el cual deberá ser acompañado de la Cédula Técnica.\nd) Contar con acta de integración de Comité vigente con una antigüedad no mayor a 6 meses. En todo caso, presentar las correspondientes modificaciones realizadas.\nPARA EL EJERCICIO FISCAL 2022\ne) Notificar mediante oficio cualquier situación que contraponga o contravenga el buen funcionamiento del\nPrograma en la escuela.\nf) Deberá constatar el número de alumnas y alumnos vigentes mediante el listado expedido por alguna autoridad escolar competente, el cual, deberá acompañarse de la firma y sello de la institución.\ng) Garantizar el abastecimiento oportuno de agua a los módulos de producción.\nh) Garantizar bajo protesta de decir verdad que el Comité de Alimentación se compromete a brindar de manera gratuita los trabajos que deriven del cuidado y manejo de los módulos de producción, así como de la elaboración de los alimentos para los que está destinado el Programa.\ni) Garantizar bajo cualquier esquema que se cuentan con los espacios suficientes, ya sea, para la ampliación de los módulos, el acondicionamiento de la cocina o el establecimiento del área de comedores, así como el resguardo de los utensilios y enseres domésticos que para tal caso fuesen otorgados.\nPara acceder a los apoyos que corresponden a las escuelas que se van a integrar al padrón de escuelas beneficiarias del Programa, se requiere:\na) La sociedad de madres, padres de familia deberá nombrar un comité, encargado exclusivamente para el seguimiento y ejecución de las acciones de este Programa.\nb) Las obligaciones y responsabilidades del comité serán exclusivamente para la organización en la preparación de alimentos destinados a las y los estudiantes, así como la del cuidado y manejo de los módulos de producción de hortalizas y aves.\nPara que el Comité de Alimentación se dé como válido, deberán integrar:\n● Acta de asamblea de la sociedad de madres, padres de familia en donde se nombren un representante del comité, así como secretario y vocal o sus equivalentes. Además, deberá especificar que dicho comité estará nombrado exclusivamente para la ejecución y operación del Programa en la escuela interesada. cabo el trabajo.\n● Anexar una copia de la identificación oficial de cada uno de las personas que lo integren.\n● Anexar un comprobante de domicilio donde se ubica la escuela.\nc) Las escuelas deberán ubicarse exclusivamente en municipios y localidades de alta y muy alta marginación.\nd) Las escuelas de reciente integración no deberán rebasar las 100 alumnas y alumnos vigentes.\nPARA EL EJERCICIO FISCAL 2022\ne) Hacer el compromiso de llevar a cabo la elaboración de los alimentos que estarán dirigidos hacia las niñas y niños de las escuelas que sean seleccionadas.\nf) El comité de alimentación estará obligado a apoyar durante la instalación y equipamiento de los módulos de producción de alimentos por lo que tendrán la responsabilidad de recibir la capacitación, así como su posterior acompañamiento técnico que para tal caso la SBGRO brinde mediante un equipo de técnicos con experiencia en el manejo de los módulos.\ng) Las capacitaciones a las que haya lugar por parte del equipo de técnicos encargados del acompañamiento y la asistencia técnica son de carácter obligatorio para los integrantes del comité.\nh) El comité deberá estar integrado por padres de familia que tengan experiencia en la producción de alimentos tanto para el manejo de los huertos y granjas, así como también para la elaboración de las comidas.\ni) Escuelas que cuenten con las condiciones edafológicas, fuentes de abastecimiento de agua, así como con el espacio de terreno necesario para el establecimiento del huerto y la granja escolar, así como del acondicionamiento de la cocina y el comedor escolar.\n8.1. Casos Especiales.\nCuando por casos de emergencias, contingencias o desastres naturales que puedan afectar la integridad física de las beneficiarias y beneficiarios o personal de la Dirección de Desarrollo Comunitario y\nDesarrollo Productivo de Grupos Vulnerables y esto provoque que sea imposible acceder a los lugares de origen de las y los beneficiarios, se buscará el apoyo de las autoridades municipales o enlaces que previamente sean nombrados por la Dirección General de Desarrollo Comunitario y Desarrollo Productivo de Grupos Vulnerables, con los que se podrán establecer los mecanismos para una adecuada coordinación o en su caso reprogramación de las acciones a seguir. (REFORMADO, P.O. 37 ALCANCE I, 09 DE MAYO DE 2023)\n8.2. Casos de Emergencia o Desastre.\nEn caso de suscitarse algún desastre natural y de no permitir este cumplir con las metas y tiempos establecidos, los comités tendrán la facultad de tomar determinaciones en casos emergentes, pudiendo decidir la entrega anticipada de los apoyos, sobre todo los relacionados a las acciones de dotación de presentada.\n8.3. Suspensión o Cancelación del Programa Social.\nSon causales de suspensión o cancelación de los beneficios, los siguientes:\na) Cuando los componentes del apoyo sean destinados a fines ajenos a los objetivos del Programa.\nb) Que se presenten conflictos dentro de la escuela y no existan las condiciones óptimas para la ejecución del Programa.\nPARA EL EJERCICIO FISCAL 2022\nc) Cuando el Comité de Alimentación envié su solicitud por escrito donde solicita la baja del Programa debido a la poca o nula participación.\nd) Cuando el Comité de Alimentación no muestre interés en la elaboración de las comidas.\ne) Cuando el Comité de Alimentación no cumpla con destinar un espacio para la elaboración de los alimentos.\nf) Dejar de entregar los reportes de seguimiento.\ng) No acudir, de manera consecutiva, al menos a 3 capacitaciones que se otorguen por parte del equipo técnico. (ADICIONADO, P.O. 37 ALCANCE I, 09 DE MAYO DE 2023)\nContando con la evidencia suficiente, la SBGRO mediante la Dirección General de Desarrollo\nComunitario y Desarrollo Productivo de Grupos Vulnerables podrá designar y trasladar el apoyo a otra escuela en la que si cuenten con las condiciones establecidas en el presente ordenamiento.\n(ADICIONADO, P.O. 37 ALCANCE I, 09 DE MAYO DE 2023)\n8.4. Integración del Padrón de Personas Beneficiarias.\nUna vez que las escuelas solicitantes sean aceptadas por el Programa, formarán parte de un padrón de escuelas beneficiarias en el que constatarán la matrícula, clave, así como nombre y ubicación de cada una de ellas, mismas que podrá ser consultado en la página oficial de la SBGRO, y será de carácter público siendo reservados los datos personales de acuerdo con la Ley Número 207 de\nTransparencia y Acceso a la Información Pública del Estado de Guerrero, mismo que estará ordenado por sexo, grupo, edad, discapacidad, municipio y región. (REFORMADO, P.O. 37 ALCANCE I, 09 DE MAYO DE 2023)\nEn todo momento, las personas que sean beneficiarias podrán ejercer los derechos de alta, acceso, rectificación, cancelación y oposición de datos personales. (ADICIONADO, P.O. 37 ALCANCE I, 09 DE MAYO\nDE 2023)\nLos datos personales recabados serán utilizados con la finalidad siguiente: validar que se cumplan los requisitos de elegibilidad para ser persona beneficiaria de este Programa; que serán integrados de acuerdo a las facultades propias, compatibles análogos para la realización de compulsas para la integración del padrón único de personas beneficiarias. (ADICIONADO, P.O. 37 ALCANCE I, 09 DE MAYO\nDE 2023)\nPor lo tanto, se garantiza la protección de los datos personales que sean recabados y en\n9. Mecánica Operativa del Programa Social.\n9.1. Instancia ejecutora y/o Responsable.\nPARA EL EJERCICIO FISCAL 2022\nLas instancias ejecutoras son: la SBGRO a través de la Dirección General de Desarrollo Comunitario y Desarrollo Productivo de Grupos Vulnerables, quién será la responsable de la operación y ejecución\n9.2. Proceso de incorporación al Programa Social.\nQue cuenten con la actualización de expedientes de las escuelas que integran el padrón de escuelas beneficiarias del Programa. (REFORMADO, P.O. 37 ALCANCE I, 09 DE MAYO DE 2023)\nPara el caso de las escuelas enlistadas en el padrón de escuelas beneficiarias es necesario manifestar mediante oficio expedido a la titular de la SBGRO el deseo de participación conforme a los apoyos establecidos en el presente ordenamiento, además de cumplir con los requisitos establecidos para tal caso.\nDicho oficio deberá ser entregado a partir del día siguiente a la publicación del presente ordenamiento y hasta el 28 de abril del presente año el cual deberá estar acompañado, principalmente, de la cédula técnica donde constate los requerimientos necesarios para cada escuela, expedido por el equipo técnico en campo, donde constate de manera legible, los requerimientos y apoyos a los que puede tener acceso.\nIncorporación de nuevas escuelas al padrón de beneficiarias y beneficiarios durante el presente ejercicio fiscal.\na) Para el caso de las escuelas de nueva incorporación, dicho trámite se realizará mediante solicitud expresa a la titular de la SBGRO en donde manifieste el deseo de incorporación al Programa, el cual deberá ser entregado con toda la documentación acorde al apartado 5 relacionado a los requisitos de incorporación al padrón de escuelas beneficiarias del presente ordenamiento.\nb) El periodo para recibir solicitudes será a partir del día siguiente a la publicación en el Periódico\nOficial del Gobierno del Estado de Guerrero de las Reglas de Operación del Programa y hasta el 28 de abril del presente año.\nc) Una vez recepcionada la solicitud, será analizada por el área de apoyo técnico para a su vez, notificar a los técnicos en campo la supervisión de la escuela solicitante, por lo que éste deberá acudir de manera física y revisar que cuentan con las condiciones mínimas necesarias, por lo que emitirá una ficha técnica donde constate el resultado de su supervisión, así como dejar la evidencia fotográfica correspondiente.\nd) Integrado el expediente con la correspondiente verificación en campo, la Dirección General de\nDesarrollo Comunitario y Desarrollo Productivo de Grupos Vulnerables, emitirá un dictamen de aprobación o rechazo según sea el caso y hará llegar mediante oficio a la escuela, la decisión tomada al respecto.\ne) Se considerarán las y los beneficiarios seleccionados conforme la fecha de la solicitud, por lo padrón de escuelas beneficiarias.\nPARA EL EJERCICIO FISCAL 2022\nLas escuelas solicitantes serán seleccionadas en función de la elegibilidad, requisitos y los criterios de selección estipulados en las presentes Reglas de Operación, en los lugares y fechas establecidas en el presente ordenamiento.\nPor tanto, para la incorporación al Programa se definirán las acciones siguientes:\na) Promoción y difusión del Programa: Se realizará una estrategia de comunicación integral a través de la página oficial de la SBGRO o podrán pedir información las personas interesadas sobre el apoyo que otorga el Programa en las oficinas de la SBGRO.\nb) Recepción de solicitudes y documentación.\nc) Visitas de validación de la escuela solicitante y se verificará que cuente con un espacio adecuado para el establecimiento de huerto y/o granjas escolares de Autoconsumo.\nd) Se elaborará un manual de operación de los módulos de producción, así como un manual de buenas prácticas alimenticias, mismo que será repartido para información de los Comités de\nAlimentación y autoridades escolares.\ne) Dar seguimiento a la implementación o avances del Programa, a través de los informes, visitas y reuniones de trabajo a las y los beneficiarios del Programa.\nf) Integración de Comités de Contraloría Social: La Dirección General de Desarrollo Comunitario y\nDesarrollo Productivo de Grupos Vulnerables o el personal que designe la SBGRO del estado, serán los encargados de conformar dichos comités de contraloría social, así mismo darán acompañamiento durante las actividades de control, seguimiento y vigilancia de los proyectos. El\nComité de Contraloría Social deberá controlar, vigilar y dar seguimiento a las acciones a través de los formatos y escritos simples que integran el expediente de contraloría social, conforme a lo establecido en las presentes Reglas de Operación.\ng) En caso de que las escuelas no hayan sido seleccionadas ya sea por no cumplir con los requisitos y criterios de elegibilidad o en todo caso por insuficiencia presupuestal, se le notificará mediante escrito a los 30 días hábiles después de haber ingresado su solicitud.\n10. Evaluación.\nLa SBGRO, podrá realizar las evaluaciones que crea pertinente de carácter externo del Programa sujeto a las presentes Reglas de Operación, para lo cual tendrá la facultad de designar a la instancia que realizará\nLas evaluaciones externas que se realicen al Programa serán coordinadas por la Secretaría de Contraloría.\nPARA EL EJERCICIO FISCAL 2022\n10.1. Indicadores (Construcción de la Matriz de Indicadores para Resultados.- Anexo 1).\nEn congruencia con la metodología de presupuesto basado en resultados, usando la metodología de Marco\nLógico, se han determinado indicadores a partir de los cuales se cuantificarán y evaluarán los avances asociados a los objetivos en la ejecución del Programa, de acuerdo con la siguiente Ficha Técnica de\nIndicadores de Desempeño:\nPARA EL EJERCICIO FISCAL 2022\nPARA EL EJERCICIO FISCAL 2022\nPARA EL EJERCICIO FISCAL 2022\n10.2. Seguimiento. sociales Facebook de la SBGRO, así como también los resultados, al finalizar el periodo de recepción, podrán consultarse de manera digital a través de los diferentes medios electrónicos con los que cuenta la\nSBGRO. (REFORMADO, P.O. 37 ALCANCE I, 09 DE MAYO DE 2023)\nEs de mencionarse que el comité de alimentación será quienes podrán recibir de manera directa los componentes en especie contemplados en el Programa, es decir, aunque el beneficio es para garantizar la alimentación de las niñas y niños serán los familiares que integren el comité de alimentación mismos que firmarán de recibido al momento de la entrega de los módulos de producción, así como de los productos de la canasta básica de manera mensual. Así mismo, garantizarán que los beneficios derivados de los alimentos lleguen a cada alumna o alumno.\nLa supervisión de entrega de apoyos podrá realizarse de manera bimestral con el fin de garantizar mediante bitácoras fotográficas que los recursos se entregan de manera directa y eficaz, también podrán participar dependencias que deseen corroborar esta información de manera directa.\n10.3. Auditoría.\nLa SBGRO y la Dirección General de Desarrollo Comunitario y Desarrollo Productivo de Grupos\nVulnerables serán los responsables de la supervisión directa de las acciones, así como de verificar que en su ejecución se cumpla con la normatividad aplicable. (REFORMADO, P.O. 37 ALCANCE I, 09 DE MAYO DE\n2023)\nLos recursos asignados para la operación del Programa no pierden su carácter estatal, por lo que la\nSEFINA, la Contraloría, el órgano de fiscalización de las entidades paraestatales y la Auditoría Superior del\nEstado, en el ámbito de sus respectivas competencias, realizarán actividades de fiscalización y auditoría.\nEs importante destacar que para los años subsecuentes el Programa deberá ir evolucionando con una visión de mediano y largo plazo, sufriendo algunas modificaciones en apego a un plan de mejora que resulte de las evaluaciones de los resultados que se le hagan durante el presente ejercicio, con la intención de que el Programa se mantenga y se garantice la asignación de presupuesto, así como el incremento presupuestal para los siguientes ejercicios fiscales.\na) Parón de Escuelas Beneficiadas Enlistadas:\n● Una vez realizado el seguimiento pertinente, así como determinado y constatado las necesidades requeridas para cada una de las escuelas, la Dirección General de Desarrollo Comunitario y Desarrollo\nPARA EL EJERCICIO FISCAL 2022 apoyos que le fueron asignados, considerando un periodo no mayor a 30 días naturales la entrega de los insumos o paquetes de insumos a los que fueron acreedores.\n● La entrega se hará directamente al comité de alimentación en el domicilio de la escuela señalado, firmando para ello, una hoja de entrega recepción y hoja de resguardo, según sea el caso con sus respectivas evidencias fotográficas.\n● Una vez recepcionado el material, equipo, mobiliario o utensilios asignados, es responsabilidad del\nComité de Alimentación el uso adecuado del mismo, por lo que, con apoyo, del equipo técnico, deberá darse un plazo no mayor a 30 días naturales la instalación y acondicionamiento de cada concepto según sea el caso.\nb) Nuevas Escuelas Integradas al Padrón:\n● Las escuelas que sean seleccionadas y que cumplen con criterios y requisitos de elegibilidad, serán notificadas mediante oficio a los apoyos que le fueron asignados, considerando un periodo no mayor a 30 días naturales la entrega de los insumos o paquetes de insumos a los que fueron acreedoras o acreedores.\n● La entrega se hará directamente al Comité de Alimentación en el domicilio de la escuela señalado, firmando para ello, una hoja de entrega recepción y hoja de resguardo, según sea el caso con sus respectivas evidencias fotográficas.\n● Una vez recepcionado el material, equipo, mobiliario o utensilios asignados, es responsabilidad del\nComité de Alimentación el uso adecuado del mismo, por lo que, con apoyo, del equipo técnico, deberá darse un plazo no mayor a 30 días naturales la instalación y acondicionamiento de cada concepto según sea el caso.\nc) Kits de Bienes de 3 Consumo Básico:\nEl apoyo de productos será de entrega mensual durante 10 meses del ciclo escolar y la entrega será de manera directa a las personas representantes de los comités de alimentación previo acuerdo de entrega financiero de conformidad con el apartado 5 de las presentes Reglas de Operación.\n12. Derechos y Obligaciones de las Personas Beneficiarias.\na) Derechos de las personas beneficiadas.\nDe las escuelas beneficiarias a través de sus comités de alimentación o de sus autoridades escolares, tendrán los derechos siguientes:\n1. Recibir la información necesaria del Programa de manera clara y oportuna.\n2. Trato digno, respetuoso, oportuno, con calidad, equidad y sin discriminación alguna.\nPARA EL EJERCICIO FISCAL 2022\n3. Atención y entrega de apoyos sin costo alguno.\n4. La reserva y privacidad de su información personal.\n5. Recibir su apoyo a través de terceras personas cumpliendo con los requisitos establecidos.\n6. Solicitar y acceder a la información que guarda su trámite y sobre cualquier otra que considere necesaria para transparentar y operar de mejor manera el Programa.\n7. Presentar quejas o inconformidades en las oficinas de la Dirección General de Desarrollo\nComunitario y Desarrollo Productivo de Grupos Vulnerables o en las oficinas de la SBGRO, referente a faltas o irregularidades que cometan las servidoras o los servidores públicos que acuden a entregar los apoyos del Programa o en las que incurran las demás escuelas beneficiarias\n(REFORMADO, P.O. 37 ALCANCE I, 09 DE MAYO DE 2023).\n8. Recibir acompañamiento y asistencia técnica por parte de la SBGRO para el manejo agroecológico de los huertos y granjas escolares. (REFORMADO, P.O. 37 ALCANCE I, 09 DE MAYO DE\n2023).\nb) Obligaciones de las Personas Beneficiadas.\nLas escuelas beneficiarias a través de sus comités de alimentación o de las autoridades escolares, tendrán las obligaciones siguientes\n1. Proporcionar bajo protesta de decir verdad, la información que se les requiera de acuerdo a lo establecido en las presentes Reglas de Operación.\n2. Acudir a las reuniones que se deriven de la solicitud, ejecución y seguimiento de los beneficios que se contemplan en el Programa y que previamente convoque la Dirección General de Desarrollo\nComunitario y Desarrollo Productivo de Grupos Vulnerables. (REFORMADO, P.O. 37 ALCANCE I, 09 DE\nMAYO DE 2023).\n3. Enviar de manera oportuna los informes necesarios y suficientes, establecidos en las presentes\nReglas de Operación.\n4. Elaborar un rol de trabajo que garantice la elaboración de las comidas de las niñas y niños.\n5. Establecer un calendario de trabajo que garantice el cuidado y manejo de los huertos y las granjas.\n12.1. Causales de suspensión o Baja de las Personas Beneficiarias.\nSe consideran causales de baja, en los casos siguientes:\na) No cumplir con la instalación de los huertos y granjas en tiempo y forma.\nb) Cuando no se dé el uso establecido en las presentes Reglas de Operación referente a las aportaciones a la canasta básica.\nc) Cuando se compruebe que existió falsedad en la información o documentación presentada.\nd) Cuando la institución escolar renuncie expresamente por escrito a los beneficios del Programa.\ne) Cuando contravengan con lo establecido en las presentes Reglas de Operación.\nf) Cuando mediante una supervisión de seguimiento se encuentren inoperantes los apoyos otorgados por el Programa.\nPARA EL EJERCICIO FISCAL 2022\n12.2. Proceso de Baja.\nEl trámite de baja de los apoyos del Programa se puede dar por las siguientes causas: por acuerdo mutuo, por renuncia o consentimiento, por falta de coordinación, por falta de interés.\na) Se solicitará por escrito mediante carta renuncia dirigida a la persona titular de la SBGRO.\n(REFORMADO, P.O. 37 ALCANCE I, 09 DE MAYO DE 2023).\nb) En los casos que proceda, la persona titular de la dependencia informará por escrito a la Dirección\nGeneral de Desarrollo Comunitario y Desarrollo Productivo de Grupos Vulnerables la baja definitiva del Programa. (REFORMADO, P.O. 37 ALCANCE I, 09 DE MAYO DE 2023).\nc) La persona solicitante deberá ser el representante, tesorero, vocal o el comité de alimentación en su conjunto, también puede ser a solicitud expresa del representante de la comisión de alimentación y las autoridades escolares.\nd) La notificación o informe que dé la o el titular de la dependencia deberá estar acompañada de las evidencias documentales o de cualquier índole que acrediten el motivo de la baja.\n13. Instancias Participantes.\na) SBGRO: Secretaría de Bienestar del Estado de Guerrero. (REFORMADO, P.O. 37 ALCANCE I, 09 DE\nMAYO DE 2023).\nb) SEPLADER: Secretaría de Planeación y Desarrollo Regional.\nc) SEFINA: Secretaría de Finanzas y Administración del Gobierno del Estado de Guerrero.\nd) Secretaría de Contraloría: Secretaría de Contraloría y Transparencia Gubernamental.\n(REFORMADO, P.O. 37 ALCANCE I, 09 DE MAYO DE 2023).\ne) Dirección Administrativa de la SBGRO (REFORMADO, P.O. 37 ALCANCE I, 09 DE MAYO DE 2023).\nf) Dirección General de Desarrollo Comunitario y Desarrollo\ng) Productivo de Grupos Vulnerables de la SBGRO. (REFORMADO, P.O. 37 ALCANCE I, 09 DE MAYO DE\n2023).\n13.1. Instancia Normativa.\nLa instancia administrativa y/o normativa será la SBGRO, SEPLADER, SEFINA, Secretaría de Contraloría.\n14. Transparencia.\n14.1. Promoción y Difusión del Programa Social.\nPública del Estado de Guerrero, la SDyBS, promoverá el Programa a través de los diferentes medios informativos frecuentes utilizados entre la comunidad estudiantil, siendo los siguientes:\nPARA EL EJERCICIO FISCAL 2022\nb) Facebook de la Secretaría de Bienestar del Estado de Guerrero. (REFORMADO, P.O. 37 ALCANCE\nDesarrollo Productivo de Grupos Vulnerables y que se pueden acceder directamente en las oficinas de la SBGRO que se ubican al interior del Recinto de las oficinas del Poder Ejecutivo del Estado, Edificios\nNorte y Tierra Caliente Planta Baja, en el Boulevard René Juárez Cisneros, número 62, Colonia Ciudad de los Servicios en Chilpancingo, Guerrero. (REFORMADO, P.O. 37 ALCANCE I, 09 DE MAYO DE 2023).\n14.2. Contraloría Social.\nComo señalamos y con la finalidad de incrementar la participación ciudadana en cada una de las escuelas, la Dirección General de Desarrollo Comunitario y Desarrollo Productivo de Grupos Vulnerables podrá instalar de manera alterna un Comité de Contraloría Social, mismo que fungirá como un órgano ciudadano de control, vigilancia y evaluación de las actividades del Programa, conformado por algunos padres de las niñas o niños beneficiarios acompañado del sello de alguna autoridad escolar o comunitaria competente, quienes de manera específica supervisarán la gestión gubernamental y que el manejo de los recursos públicos se realicen en términos de eficiencia, eficacia, oportunidad, equidad, transparencia, legalidad y honradez. (REFORMADO, P.O. 37 ALCANCE I, 09 DE MAYO DE 2023).\nLos objetivos específicos de este órgano de contraloría social son:\na) Hacer más transparentes las decisiones y la ejecución de los recursos;\nb) Incrementar la participación ciudadana;\nc) Fomentar la organización social;\nd) Inhibir los actos de corrupción y de cooptación social, política y electoral;\ne) Incrementar la eficiencia de los recursos públicos;\nf) Fortalecer la cultura de la legalidad; y,\ng) Mejorar la rendición de cuentas.\nEl Comité de Contraloría Social, deberá vigilar y dar seguimiento a las acciones a través de los formatos que componen el expediente del comité, el cual quedará integrado por:\na) Acta de conformación del Comité.\nb) Reunión con beneficiarias y beneficiarios.\nc) Ficha informativa del Programa.\nd) Cédula de vigilancia del Programa.\ne) Queja, denuncia, reclamo o reconocimiento.\nEl Comité debe estar constituido mínimamente por una presidencia, una secretaría y una vocalía, electos entrega del Programa, dicho Comité deberá revisar los avances y resultados del Programa, así como la detección de cualquier presunta irregularidad.\nPARA EL EJERCICIO FISCAL 2022\nLa vocalía será el responsable de hacer llegar las quejas o denuncias recibidas a la SBGRO, quien dará respuesta en un plazo no mayor de 15 días hábiles a partir de la fecha de recepción de la misma.\n14.3. Protección de Datos Personales.\nLa información solicitada a las escuelas para la integración del Padrón de Personas Beneficiarias quedará resguardada en la Dirección General de Desarrollo Comunitario y Desarrollo Productivo de Grupos\nVulnerables, solo podrá ser publicada previo consentimiento de las madres, padres de familia en los medios digitales, esto con el fin de checar sus resultados de la solicitud enviada por parte de la escuela y saber si fueron beneficiados, no se deberá hacer uso de esta información para fines ajenos al Programa.\n(REFORMADO, P.O. 37 ALCANCE I, 09 DE MAYO DE 2023).\nEn todo momento la persona beneficiaria podrá ejercer los derechos de alta, acceso, rectificación, cancelación y oposición de datos personales recabados. (ADICIONADO, P.O. 37 ALCANCE I, 09 DE MAYO\nDE 2023).\nLos datos personales recabados serán utilizados con la finalidad siguiente: validar que se cumplan los requisitos de elegibilidad para ser persona beneficiaria de este Programa; que serán integrados de acuerdo a las facultades propias, compatibles análogos para la realización de compulsas para la integración del padrón único de personas beneficiarias. (ADICIONADO, P.O. 37 ALCANCE I, 09 DE MAYO\nDE 2023).\nPor lo tanto, se garantiza la protección de los datos personales que sean recabados y en cumplimiento con las disposiciones en materia de transparencia y acceso a la información pública.\n(ADICIONADO, P.O. 37 ALCANCE I, 09 DE MAYO DE 2023).\n14.4. Quejas y Denuncias.\nLas y los beneficiarios pueden presentar sus quejas o denuncias a través de los comités de contraloría social o directamente en las oficinas de la SBGRO sobre cualquier hecho, acto u omisión que produzca o pueda producir daños al ejercicio de sus derechos establecidos en las presentes Reglas de Operación o contravengan sus disposiciones y demás normatividad aplicable. (REFORMADO, P.O. 37 ALCANCE I, 09 DE ubicado en Edificio Norte Planta Baja, interior, Boulevard René Juárez Cisneros No. 62, Colonia Ciudad\nEn la queja o inconformidad se deberán integrar:\na) Copia de la credencial de elector del denunciante.\nb) Objeto de la denuncia.\nPARA EL EJERCICIO FISCAL 2022\nc) Nombre completo de la persona que denuncia.\nd) Municipio donde se ubica el problema objeto de la denuncia.\ne) Correo electrónico de la persona beneficiaria o persona quejosa.\nf) Teléfono celular, casa y/o de la escuela.\nLa Contraloría, es el órgano competente para conocer las denuncias de violación e incumplimiento de derechos en materia de desarrollo social.\n14.5. Acciones de Blindaje.\nLa SDyBS, para la operación y ejecución de los recursos del Programa, deberá observar y atender las medidas que emita la Contraloría, el Instituto de Transparencia y Acceso a la Información Pública del\nEstado de Guerrero (ITAIGro), el Instituto Electoral y de Participación Ciudadana del Estado de Guerrero\n(IEPC) y las demás autoridades competentes con la finalidad de impedir que los apoyos sean utilizados con fines político electorales.\nLa papelería, documentación oficial, así como la publicidad y promoción del Programa deberán incluir la siguiente leyenda “Este Programa es público ajeno a cualquier partido político. Queda prohibido el uso para fines distintos a los establecidos en el Programa”.\nEn cuanto a la publicidad en medios electrónicos, impresos, complementarios o de cualquier otra índole vinculada con los programas de comunicación social, se deberá incluir la leyenda “Este Programa es público y queda prohibido su uso con fines partidistas o de promoción personal”.\n14.6. Acta de Entrega - Donación (Anexo 2). (REFORMADO, P.O. 37 ALCANCE I, 09 DE MAYO DE 2023).\nCuando se entregan los beneficios se deberá firmar un acta de entrega-recepción de los insumos y material suministrado firmado por la SBGRO, la persona representante del Comité de\nAlimentación de las escuelas beneficiarias, de ser posible, estar acompañado del sello y/o de alguna autoridad escolar o comunitaria competente, por lo que el acta de donación se sustituye por el acta de entrega - recepción.\nDe conformidad con el acta de entrega-recepción, la beneficiaria o el beneficiario se compromete a vigilar su adecuada operación y darle seguimiento al apoyo recibido. El acta forma parte del expediente y constituye la prueba documental que certifica la existencia del apoyo otorgado, dicho documento estará bajo el resguardo y responsabilidad de la SBGRO.\n15. Perspectiva de Género. la escuela de su localidad, de ninguna manera se priorizará beneficiar a alguna parte del alumnado por el hecho de distinguir entre mujeres y hombres.\nPARA EL EJERCICIO FISCAL 2022\n16. Enfoque de Derechos.\nConforme al artículo 3 segundo párrafo de la Convención sobre los derechos del niño establece que “Los\nEstados Partes” se comprometen a asegurar a la niña y niño la protección y el cuidado que sean necesarios para su bienestar, teniendo en cuenta los derechos y deberes de sus padres, tutores u otras personas responsables de él ante la ley y, con ese fin, tomará todas las medidas legislativas y administrativas adecuadas.\nCon el objetivo de generar las condiciones necesarias para el acceso equitativo en términos de disponibilidad, accesibilidad y calidad en las acciones que realiza el Programa, se implementarán mecanismos que hagan efectivo el acceso a la información gubernamental, se asegurará que el acceso a los apoyos y servicios se dé únicamente con base en lo establecido en estas Reglas de Operación, sin discriminación alguna.\nBajo el mismo enfoque la Ley General de los Derechos de Niñas, Niños y Adolescentes señala que para garantizar la protección de los derechos de niñas, niños, adolescentes y jóvenes, las autoridades realizarán las acciones y tomarán medidas con un enfoque integral, transversal y con perspectiva de derechos humanos en el diseño y la instrumentación de políticas y programas de gobierno.\nTodas las personas servidoras públicas involucradas en la operación del Programa deben promover, respetar, proteger y garantizar el ejercicio efectivo de los derechos humanos de las y los beneficiarios del\nPrograma, con base en los principios de universalidad, interdependencia, indivisibilidad y progresividad, brindando en todo momento un trato digno y de respeto a la población objetivo, con apego a los criterios de igualdad y no discriminación.\nEn la aplicación del Programa, se harán valer los derechos de las niñas y niños a una alimentación sana, suficiente y nutritiva tomando en consideración los factores de desigualdad que pudieran poner en riesgo de vulnerabilidad a personas que pertenecen a grupos históricamente discriminados, como lo son niñas y niños, jóvenes, personas con discapacidad, personas en situación de calle, en situación de desplazamiento interno, mujeres, personas migrantes, afrodescendientes, y a aquellas pertenecientes a pueblos y comunidades indígenas, entre otros, tomando en consideración sus circunstancias y necesidades, a fin de contribuir a generar conocimiento y acciones que potencien su desarrollo integral e inclusión plena.\n17. Acciones Contra el SARS-COV 2.\nDerivado de la Pandemia por COVID-19 y atendiendo las recomendaciones de la Secretaría de Salud\nFederal, dependiendo del color del semáforo, se contemplará seguir los protocolos de cuidados para evitar contagios, por tanto se procurará entregar el apoyo a un mínimo de personas para evitar aglomeraciones, cada mes para beneficio de las niñas y niños. las personas que resulten beneficiadas, a fin de evitar contagios innecesarios y que afecten el flujo de\nPARA EL EJERCICIO FISCAL 2022 recursos para la ejecución del Programa. El personal que brindará las capacitaciones también deberá respetar los protocolos sanitarios establecidos.\n18. Anexos que reflejen la entrega del apoyo (Económico. Especie o Servicios). (REFORMADO, P.O. 37\nAnexo 1.- MIR.\nAnexo 2.- Acta de Donación o entrega-recepción.\nAnexo 3.- Padrón de escuelas Beneficiarias del Programa de\nAlimentación para el Bienestar de Niñas y Niños.\nPARA EL EJERCICIO FISCAL 2022\nAnexo 1.- MIR\nPARA EL EJERCICIO FISCAL 2022\nPARA EL EJERCICIO FISCAL 2022\nAnexo 2.- Acta de Donación o entrega-recepción.\nPARA EL EJERCICIO FISCAL 2022\nAnexo 3.- Padrón de escuelas Beneficiarias del Programa de Alimentación para el Bienestar de\nNiñas y Niños\n{\"tabla_8\":{\"columnas\":[\"NO.\",\"MUNICIPIO\",\"LOCALIDAD\",\"NOMBRE DE LA ESCUELA\",\"CLAVE\"],\"filas\":[{\"columna_1\":\"1\",\"columna_2\":\"(sin dato)\",\"columna_3\":\"APALANI\",\"columna_4\":\"TELESECUNDARIA OCTAVIO PAZ\",\"columna_5\":\"12DTV0716V\"},{\"columna_1\":\"2\",\"columna_2\":\"(sin dato)\",\"columna_3\":\"HUAMUCHITOS\",\"columna_4\":\"TELESECUNDARIA NICOLAS BRAVO\",\"columna_5\":\"12DTV0614Y\"},{\"columna_1\":\"(sin dato)\",\"columna_2\":\"(sin dato)\",\"columna_3\":\"BELLAVISTA PAPAGAYO\",\"columna_4\":\"TELESENCUDARIA PABLO MENA\",\"columna_5\":\"12DTV0630P\"},{\"columna_1\":\"3\",\"columna_2\":\"ACAPULCO DE JUAREZ\",\"columna_3\":\"(sin dato)\",\"columna_4\":\"MEDINA\",\"columna_5\":\"(sin dato)\"},{\"columna_1\":\"4\",\"columna_2\":\"(sin dato)\",\"columna_3\":\"CERRO PIEDRA\",\"columna_4\":\"SECUNDARIA FRANCISCO MARQUEZ\",\"columna_5\":\"12DTV0163L\"},{\"columna_1\":\"5\",\"columna_2\":\"(sin dato)\",\"columna_3\":\"SAN ANTONIO\",\"columna_4\":\"PRIMARIA VICENTE GUERRERO\",\"columna_5\":\"12DPR04305\"},{\"columna_1\":\"(sin dato)\",\"columna_2\":\"AJUCHITLAN DEL\",\"columna_3\":\"CHANGATA\",\"columna_4\":\"JARDIN DE NIÑOS DR. ABEL OLEA\",\"columna_5\":\"12DJN0253O\"},{\"columna_1\":\"6\",\"columna_2\":\"PROGRESO\",\"columna_3\":\"(sin dato)\",\"columna_4\":\"BORJA\",\"columna_5\":\"(sin dato)\"},{\"columna_1\":\"7\",\"columna_2\":\"ATOYAC DE ALVAREZ\",\"columna_3\":\"EL PARAISO\",\"columna_4\":\"PRIMARIA GUILLERMO PRIETO\",\"columna_5\":\"12DPR5929F\"},{\"columna_1\":\"(sin dato)\",\"columna_2\":\"AYUTLA DE LOS LIBRES\",\"columna_3\":\"COL. PIEDRA DEL\",\"columna_4\":\"JARDIN DE NIÑOS MARIA MONTESSORI\",\"columna_5\":\"12DJN6076P\"},{\"columna_1\":\"8\",\"columna_2\":\"(sin dato)\",\"columna_3\":\"ZOPILOTE\",\"columna_4\":\"(sin dato)\",\"columna_5\":\"(sin dato)\"},{\"columna_1\":\"(sin dato)\",\"columna_2\":\"(sin dato)\",\"columna_3\":\"BARRIO DE SAN\",\"columna_4\":\"JARDIN DE NIÑOS INDIGENA LUIS\",\"columna_5\":\"12DCC0921Z\"},{\"columna_1\":\"9\",\"columna_2\":\"(sin dato)\",\"columna_3\":\"FRANCISCO\",\"columna_4\":\"DONALDO COLOSIO MURRIETA\",\"columna_5\":\"(sin dato)\"},{\"columna_1\":\"(sin dato)\",\"columna_2\":\"ZITLALA\",\"columna_3\":\"(sin dato)\",\"columna_4\":\"(sin dato)\",\"columna_5\":\"(sin dato)\"},{\"columna_1\":\"(sin dato)\",\"columna_2\":\"(sin dato)\",\"columna_3\":\"BARRIO DE SAN\",\"columna_4\":\"PRIMARIA BILINGÜE NICOLAS BRAVO\",\"columna_5\":\"12DPB0972L\"},{\"columna_1\":\"10\",\"columna_2\":\"(sin dato)\",\"columna_3\":\"FRANCISCO\",\"columna_4\":\"(sin dato)\",\"columna_5\":\"(sin dato)\"},{\"columna_1\":\"(sin dato)\",\"columna_2\":\"(sin dato)\",\"columna_3\":\"LAS TUNAS\",\"columna_4\":\"JARDIN DE NIÑOS JUAN JACOBO\",\"columna_5\":\"12DJN0533Y\"},{\"columna_1\":\"11\",\"columna_2\":\"(sin dato)\",\"columna_3\":\"(sin dato)\",\"columna_4\":\"ROUSSEAU\",\"columna_5\":\"(sin dato)\"},{\"columna_1\":\"12\",\"columna_2\":\"(sin dato)\",\"columna_3\":\"LLANO REAL\",\"columna_4\":\"PRIMARIA JOAQUIN BARANDA\",\"columna_5\":\"12DPR5345C\"},{\"columna_1\":\"(sin dato)\",\"columna_2\":\"BENITO JUAREZ\",\"columna_3\":\"(sin dato)\",\"columna_4\":\"(sin dato)\",\"columna_5\":\"(sin dato)\"},{\"columna_1\":\"(sin dato)\",\"columna_2\":\"(sin dato)\",\"columna_3\":\"LLANO REAL\",\"columna_4\":\"JARDIN DE NIÑOS PRAXEDIS\",\"columna_5\":\"12DJN2983P\"},{\"columna_1\":\"13\",\"columna_2\":\"(sin dato)\",\"columna_3\":\"(sin dato)\",\"columna_4\":\"GUERRERO\",\"columna_5\":\"(sin dato)\"},{\"columna_1\":\"14\",\"columna_2\":\"CHILPANCINGO DE LOS\",\"columna_3\":\"CHAUTIPAN\",\"columna_4\":\"PRIMARIA IGNACIO ZARAGOZA\",\"columna_5\":\"12DPR0476M\"},{\"columna_1\":\"(sin dato)\",\"columna_2\":\"BRAVO\",\"columna_3\":\"(sin dato)\",\"columna_4\":\"(sin dato)\",\"columna_5\":\"(sin dato)\"},{\"columna_1\":\"15\",\"columna_2\":\"(sin dato)\",\"columna_3\":\"JALEACA\",\"columna_4\":\"PRIMARIA BALTAZAR CASTORENA\",\"columna_5\":\"12DPR0515Z\"},{\"columna_1\":\"(sin dato)\",\"columna_2\":\"COCHOAPA EL GRANDE\",\"columna_3\":\"CAHUAÑAÑA\",\"columna_4\":\"PRIMARIA BILINGÜE VICENTE\",\"columna_5\":\"12DPB0923C\"},{\"columna_1\":\"16\",\"columna_2\":\"(sin dato)\",\"columna_3\":\"(sin dato)\",\"columna_4\":\"GUERRERO\",\"columna_5\":\"(sin dato)\"},{\"columna_1\":\"(sin dato)\",\"columna_2\":\"COCULA\",\"columna_3\":\"PUENTE RIO SAN JUAN\",\"columna_4\":\"JARDIN DE NIÑOS CARLOS LORENZINI\",\"columna_5\":\"12DJN0602D\"},{\"columna_1\":\"17\",\"columna_2\":\"(sin dato)\",\"columna_3\":\"(sin dato)\",\"columna_4\":\"(sin dato)\",\"columna_5\":\"(sin dato)\"},{\"columna_1\":\"(sin dato)\",\"columna_2\":\"(sin dato)\",\"columna_3\":\"SAN SALVADOR DE LAS\",\"columna_4\":\"PRIMARIA LIC. ISRAEL NOGUEDA\",\"columna_5\":\"12DPR1140I\"},{\"columna_1\":\"18\",\"columna_2\":\"(sin dato)\",\"columna_3\":\"POZAS\",\"columna_4\":\"OTERO\",\"columna_5\":\"(sin dato)\"},{\"columna_1\":\"(sin dato)\",\"columna_2\":\"COYUCA DE BENITEZ\",\"columna_3\":\"(sin dato)\",\"columna_4\":\"(sin dato)\",\"columna_5\":\"(sin dato)\"},{\"columna_1\":\"(sin dato)\",\"columna_2\":\"(sin dato)\",\"columna_3\":\"SAN SALVADOR DE LAS\",\"columna_4\":\"SECUNDARIA HEROES DE LA\",\"columna_5\":\"12DTV0197B\"},{\"columna_1\":\"19\",\"columna_2\":\"(sin dato)\",\"columna_3\":\"POZAS\",\"columna_4\":\"REVOLUCION\",\"columna_5\":\"(sin dato)\"}]}}\nPARA EL EJERCICIO FISCAL 2022\n{\"tabla_9\":{\"columnas\":[\"(sin encabezado)\",\"(sin encabezado)\",\"VALLE DEL RÍO\",\"PRIMARIA JUAN FRANCISCO ESCUTIA\",\"12DPR5954E\"],\"filas\":[{\"columna_1\":\"20\",\"columna_2\":\"(sin dato)\",\"columna_3\":\"(sin dato)\",\"columna_4\":\"(sin dato)\",\"columna_5\":\"(sin dato)\"},{\"columna_1\":\"21\",\"columna_2\":\"(sin dato)\",\"columna_3\":\"VALLE DEL RÍO\",\"columna_4\":\"PRIMARIA JUAN R ESCUDERO\",\"columna_5\":\"12DPR1815C\"},{\"columna_1\":\"(sin dato)\",\"columna_2\":\"(sin dato)\",\"columna_3\":\"BARRANCA DE SAN\",\"columna_4\":\"“PRIM. COMUNITARIA RURAL LÁZARO\",\"columna_5\":\"12KPR0439T\"},{\"columna_1\":\"22\",\"columna_2\":\"(sin dato)\",\"columna_3\":\"JOSE\",\"columna_4\":\"CARDENAS”\",\"columna_5\":\"(sin dato)\"},{\"columna_1\":\"23\",\"columna_2\":\"(sin dato)\",\"columna_3\":\"PLACERES DEL ORO\",\"columna_4\":\"JARDIN DE NIÑOS MANUEL M PONCE\",\"columna_5\":\"12DJNCO25U\"},{\"columna_1\":\"(sin dato)\",\"columna_2\":\"COYUCA DE CATALÁN\",\"columna_3\":\"(sin dato)\",\"columna_4\":\"(sin dato)\",\"columna_5\":\"(sin dato)\"},{\"columna_1\":\"(sin dato)\",\"columna_2\":\"(sin dato)\",\"columna_3\":\"PLACERES DEL ORO\",\"columna_4\":\"PRIMARIA FEDERAL VICENTE\",\"columna_5\":\"12DPR1863M\"},{\"columna_1\":\"24\",\"columna_2\":\"(sin dato)\",\"columna_3\":\"(sin dato)\",\"columna_4\":\"GUERRERO\",\"columna_5\":\"(sin dato)\"},{\"columna_1\":\"25\",\"columna_2\":\"(sin dato)\",\"columna_3\":\"EL CARRIZAL\",\"columna_4\":\"PRIMARIA PLAN DE GUADALUPE\",\"columna_5\":\"12DPR5713G\"},{\"columna_1\":\"26\",\"columna_2\":\"(sin dato)\",\"columna_3\":\"PATAMBO\",\"columna_4\":\"PRIMARIA VENUSTIANO CARRANZA\",\"columna_5\":\"12EPR0404T\"},{\"columna_1\":\"(sin dato)\",\"columna_2\":\"(sin dato)\",\"columna_3\":\"CUAJINICUILAPA\",\"columna_4\":\"PRIMARIA IGNACIO MANUEL\",\"columna_5\":\"12EPR0411C\"},{\"columna_1\":\"27\",\"columna_2\":\"(sin dato)\",\"columna_3\":\"(sin dato)\",\"columna_4\":\"ALTAMIRANO\",\"columna_5\":\"(sin dato)\"},{\"columna_1\":\"(sin dato)\",\"columna_2\":\"(sin dato)\",\"columna_3\":\"MALDONADO\",\"columna_4\":\"SECUNDARIA TECNICA N°167 \\\"MOISES\",\"columna_5\":\"12DST0167U\"},{\"columna_1\":\"28\",\"columna_2\":\"(sin dato)\",\"columna_3\":\"(sin dato)\",\"columna_4\":\"SAENZ\\\"\",\"columna_5\":\"(sin dato)\"},{\"columna_1\":\"(sin dato)\",\"columna_2\":\"CUAJINICUILAPA\",\"columna_3\":\"(sin dato)\",\"columna_4\":\"(sin dato)\",\"columna_5\":\"(sin dato)\"},{\"columna_1\":\"29\",\"columna_2\":\"(sin dato)\",\"columna_3\":\"CUAJINICUILAPA\",\"columna_4\":\"PRIMARIA VICENTE GUERRERO\",\"columna_5\":\"12DPR5578S\"},{\"columna_1\":\"(sin dato)\",\"columna_2\":\"(sin dato)\",\"columna_3\":\"SAN NICOLAS\",\"columna_4\":\"PRIMARIA EMPERADOR CUAUHTEMOC\",\"columna_5\":\"12DPR0438K\"},{\"columna_1\":\"30\",\"columna_2\":\"(sin dato)\",\"columna_3\":\"(sin dato)\",\"columna_4\":\"(sin dato)\",\"columna_5\":\"(sin dato)\"},{\"columna_1\":\"31\",\"columna_2\":\"(sin dato)\",\"columna_3\":\"EL SALTO\",\"columna_4\":\"PRIMARIA GUADALUPE VICTORIA\",\"columna_5\":\"12EPR0417X\"},{\"columna_1\":\"32\",\"columna_2\":\"(sin dato)\",\"columna_3\":\"EL LLANO\",\"columna_4\":\"TELESECUNDARIA RUBEN MORA\",\"columna_5\":\"(sin dato)\"},{\"columna_1\":\"(sin dato)\",\"columna_2\":\"CUAUTEPEC\",\"columna_3\":\"(sin dato)\",\"columna_4\":\"(sin dato)\",\"columna_5\":\"(sin dato)\"},{\"columna_1\":\"33\",\"columna_2\":\"(sin dato)\",\"columna_3\":\"EL PABELLON\",\"columna_4\":\"PRIMARIA CUAUHTEMOC\",\"columna_5\":\"12DPR1755E\"},{\"columna_1\":\"34\",\"columna_2\":\"(sin dato)\",\"columna_3\":\"CHILACACHAPA\",\"columna_4\":\"PRIMARIA PLAN DE AYUTLA\",\"columna_5\":\"12DPR2610Q\"},{\"columna_1\":\"(sin dato)\",\"columna_2\":\"CUETZALA DEL\",\"columna_3\":\"(sin dato)\",\"columna_4\":\"(sin dato)\",\"columna_5\":\"(sin dato)\"},{\"columna_1\":\"(sin dato)\",\"columna_2\":\"(sin dato)\",\"columna_3\":\"TLAQUILPA\",\"columna_4\":\"JARDIN DE NIÑOS ILUSIÓN CAMPESINA\",\"columna_5\":\"12EJN0448Z\"},{\"columna_1\":\"(sin dato)\",\"columna_2\":\"PROGRESO\",\"columna_3\":\"(sin dato)\",\"columna_4\":\"(sin dato)\",\"columna_5\":\"(sin dato)\"},{\"columna_1\":\"35\",\"columna_2\":\"(sin dato)\",\"columna_3\":\"(sin dato)\",\"columna_4\":\"(sin dato)\",\"columna_5\":\"(sin dato)\"},{\"columna_1\":\"36\",\"columna_2\":\"(sin dato)\",\"columna_3\":\"COL. SANTA MARÍA\",\"columna_4\":\"PRIMARIA LUIS DONALDO COLOSIO\",\"columna_5\":\"12EPR00116\"},{\"columna_1\":\"(sin dato)\",\"columna_2\":\"EDUARDO NERI\",\"columna_3\":\"(sin dato)\",\"columna_4\":\"(sin dato)\",\"columna_5\":\"(sin dato)\"},{\"columna_1\":\"37\",\"columna_2\":\"(sin dato)\",\"columna_3\":\"EL MIRAVAL\",\"columna_4\":\"PRIMARIA BENITO JUAREZ\",\"columna_5\":\"12EPR0177I\"},{\"columna_1\":\"(sin dato)\",\"columna_2\":\"(sin dato)\",\"columna_3\":\"SAN FRANCISCO\",\"columna_4\":\"SECUNDARIA TECNICA LA GRAN\",\"columna_5\":\"12DST0276A\"},{\"columna_1\":\"38\",\"columna_2\":\"(sin dato)\",\"columna_3\":\"OZOMATLÁN\",\"columna_4\":\"TENOCHTITLAN\",\"columna_5\":\"(sin dato)\"},{\"columna_1\":\"(sin dato)\",\"columna_2\":\"(sin dato)\",\"columna_3\":\"TULIMAN\",\"columna_4\":\"JARDÍN DE NIÑOS MAURICIO\",\"columna_5\":\"12DCC0115X\"},{\"columna_1\":\"39\",\"columna_2\":\"HUITZUCO DE LOS\",\"columna_3\":\"(sin dato)\",\"columna_4\":\"SWADESH INDÍGENA\",\"columna_5\":\"(sin dato)\"},{\"columna_1\":\"(sin dato)\",\"columna_2\":\"FIGUEROA\",\"columna_3\":\"(sin dato)\",\"columna_4\":\"(sin dato)\",\"columna_5\":\"(sin dato)\"},{\"columna_1\":\"(sin dato)\",\"columna_2\":\"(sin dato)\",\"columna_3\":\"TULIMAN\",\"columna_4\":\"JARDÍN DE NIÑOS RAFAEL JIMENEZ\",\"columna_5\":\"12DCC1227H\"},{\"columna_1\":\"40\",\"columna_2\":\"(sin dato)\",\"columna_3\":\"(sin dato)\",\"columna_4\":\"PARRA INDÍGENA\",\"columna_5\":\"(sin dato)\"},{\"columna_1\":\"41\",\"columna_2\":\"(sin dato)\",\"columna_3\":\"TULIMAN\",\"columna_4\":\"JARDIN DE NIÑOS JUAN N. ALVAREZ\",\"columna_5\":\"12EJN0079X\"},{\"columna_1\":\"42\",\"columna_2\":\"(sin dato)\",\"columna_3\":\"AYAHUALTEMPA\",\"columna_4\":\"PRIMARIA BILINGÜE KALMECA\",\"columna_5\":\"12DPV1049Z\"}]}}\nPARA EL EJERCICIO FISCAL 2022\n{\"tabla_10\":{\"columnas\":[\"(sin encabezado)\",\"(sin encabezado)\",\"AYAHUALTEMPA\",\"PRIM. RURAL FED. ROMAN VAZQUEZ\",\"12DPR2029U\"],\"filas\":[{\"columna_1\":\"43\",\"columna_2\":\"JOSÉ JOAQUÍN\",\"columna_3\":\"(sin dato)\",\"columna_4\":\"ABARCA\",\"columna_5\":\"(sin dato)\"},{\"columna_1\":\"(sin dato)\",\"columna_2\":\"HERRERA\",\"columna_3\":\"(sin dato)\",\"columna_4\":\"(sin dato)\",\"columna_5\":\"(sin dato)\"},{\"columna_1\":\"44\",\"columna_2\":\"(sin dato)\",\"columna_3\":\"TLACOAPA\",\"columna_4\":\"PRIMARIA INDIGENA CUAUHTEMOC\",\"columna_5\":\"12DPB00501\"},{\"columna_1\":\"(sin dato)\",\"columna_2\":\"(sin dato)\",\"columna_3\":\"COL. 1o DE MAYO\",\"columna_4\":\"PRIMARIA URB. EST. GENERAL LAZARO\",\"columna_5\":\"12EPR0583V\"},{\"columna_1\":\"45\",\"columna_2\":\"(sin dato)\",\"columna_3\":\"(sin dato)\",\"columna_4\":\"CARDENAS\",\"columna_5\":\"(sin dato)\"},{\"columna_1\":\"(sin dato)\",\"columna_2\":\"LA UNIÓN DE ISIDORO\",\"columna_3\":\"(sin dato)\",\"columna_4\":\"(sin dato)\",\"columna_5\":\"(sin dato)\"},{\"columna_1\":\"(sin dato)\",\"columna_2\":\"MONTES DE OCA\",\"columna_3\":\"COL. 28 DE MARZO\",\"columna_4\":\"PRIMARIA FEDERAL 28 DE MARZO\",\"columna_5\":\"12DPR5873U\"},{\"columna_1\":\"46\",\"columna_2\":\"(sin dato)\",\"columna_3\":\"(sin dato)\",\"columna_4\":\"(sin dato)\",\"columna_5\":\"(sin dato)\"},{\"columna_1\":\"47\",\"columna_2\":\"(sin dato)\",\"columna_3\":\"TIERRA COLORADA\",\"columna_4\":\"PRIMARIA JUAN N. ÁLVAREZ\",\"columna_5\":\"12DPR0556Y\"},{\"columna_1\":\"(sin dato)\",\"columna_2\":\"LEONARDO BRAVO\",\"columna_3\":\"TIERRA COLORADA\",\"columna_4\":\"JARDIN DE NIÑOS VICENTE GUERRERO\",\"columna_5\":\"12DJN5773E\"},{\"columna_1\":\"48\",\"columna_2\":\"(sin dato)\",\"columna_3\":\"(sin dato)\",\"columna_4\":\"SALDAÑA\",\"columna_5\":\"(sin dato)\"},{\"columna_1\":\"(sin dato)\",\"columna_2\":\"(sin dato)\",\"columna_3\":\"SAN PEDRO ATZOMPA\",\"columna_4\":\"PRIMARIA BILINGÜE JUAN PABLO\",\"columna_5\":\"12DPB0543U\"},{\"columna_1\":\"49\",\"columna_2\":\"(sin dato)\",\"columna_3\":\"(sin dato)\",\"columna_4\":\"GALEANA\",\"columna_5\":\"(sin dato)\"},{\"columna_1\":\"(sin dato)\",\"columna_2\":\"METLATONOC\",\"columna_3\":\"(sin dato)\",\"columna_4\":\"(sin dato)\",\"columna_5\":\"(sin dato)\"},{\"columna_1\":\"(sin dato)\",\"columna_2\":\"(sin dato)\",\"columna_3\":\"SAN PABLO ATZOMPA\",\"columna_4\":\"PRIMARIA BILINGÜE HERMENEGILDO\",\"columna_5\":\"12DPB0122L\"},{\"columna_1\":\"50\",\"columna_2\":\"(sin dato)\",\"columna_3\":\"(sin dato)\",\"columna_4\":\"GAELANA\",\"columna_5\":\"(sin dato)\"},{\"columna_1\":\"(sin dato)\",\"columna_2\":\"MOCHITLAN\",\"columna_3\":\"SAN MIGUEL\",\"columna_4\":\"TELESECUNDARIA RAFAEL RAMIREZ\",\"columna_5\":\"12DTV0600V\"},{\"columna_1\":\"51\",\"columna_2\":\"(sin dato)\",\"columna_3\":\"(sin dato)\",\"columna_4\":\"CASTAÑEDA\",\"columna_5\":\"(sin dato)\"},{\"columna_1\":\"(sin dato)\",\"columna_2\":\"PETATLAN\",\"columna_3\":\"PETATLAN\",\"columna_4\":\"PRIMARIA RUR. FED. BELISARIO\",\"columna_5\":\"12DPR0403V\"},{\"columna_1\":\"52\",\"columna_2\":\"(sin dato)\",\"columna_3\":\"(sin dato)\",\"columna_4\":\"DOMINGUEZ\",\"columna_5\":\"(sin dato)\"},{\"columna_1\":\"53\",\"columna_2\":\"(sin dato)\",\"columna_3\":\"PETATLAN\",\"columna_4\":\"PRIMARIA. URB. NETZAHUALCOYOTL\",\"columna_5\":\"12DPR5499F\"},{\"columna_1\":\"54\",\"columna_2\":\"(sin dato)\",\"columna_3\":\"BELLA VISTA\",\"columna_4\":\"PRIMARIA LIC. BENITO JUAREZ\",\"columna_5\":\"12EPR0666D\"},{\"columna_1\":\"(sin dato)\",\"columna_2\":\"(sin dato)\",\"columna_3\":\"BELLA VISTA\",\"columna_4\":\"JARDIN DE NIÑOS ESCUDO NACIONAL\",\"columna_5\":\"12EJN0343F\"},{\"columna_1\":\"55\",\"columna_2\":\"(sin dato)\",\"columna_3\":\"(sin dato)\",\"columna_4\":\"(sin dato)\",\"columna_5\":\"(sin dato)\"},{\"columna_1\":\"(sin dato)\",\"columna_2\":\"SAN MARCOS\",\"columna_3\":\"(sin dato)\",\"columna_4\":\"(sin dato)\",\"columna_5\":\"(sin dato)\"},{\"columna_1\":\"(sin dato)\",\"columna_2\":\"(sin dato)\",\"columna_3\":\"EL TAMARINDO\",\"columna_4\":\"JARDIN DE NIÑOS ZUMPANGO DEL RIO\",\"columna_5\":\"12DJN2957R\"},{\"columna_1\":\"56\",\"columna_2\":\"(sin dato)\",\"columna_3\":\"(sin dato)\",\"columna_4\":\"(sin dato)\",\"columna_5\":\"(sin dato)\"},{\"columna_1\":\"(sin dato)\",\"columna_2\":\"(sin dato)\",\"columna_3\":\"PANDOLOMA\",\"columna_4\":\"TELESECUNDARIA LEONARDO BRAVO\",\"columna_5\":\"12DTV0186W\"},{\"columna_1\":\"57\",\"columna_2\":\"(sin dato)\",\"columna_3\":\"(sin dato)\",\"columna_4\":\"(sin dato)\",\"columna_5\":\"(sin dato)\"},{\"columna_1\":\"(sin dato)\",\"columna_2\":\"SAN MIGUEL\",\"columna_3\":\"(sin dato)\",\"columna_4\":\"(sin dato)\",\"columna_5\":\"(sin dato)\"},{\"columna_1\":\"58\",\"columna_2\":\"(sin dato)\",\"columna_3\":\"PANDOLOMA\",\"columna_4\":\"JARDIN DE NIÑOS AMELIA ROBLES\",\"columna_5\":\"12DJN5953P\"},{\"columna_1\":\"(sin dato)\",\"columna_2\":\"TOTOLAPAN\",\"columna_3\":\"(sin dato)\",\"columna_4\":\"(sin dato)\",\"columna_5\":\"(sin dato)\"},{\"columna_1\":\"59\",\"columna_2\":\"(sin dato)\",\"columna_3\":\"PANDOLOMA\",\"columna_4\":\"PRIMARIA JUSTO SIERRA\",\"columna_5\":\"12DPR0994Y\"},{\"columna_1\":\"(sin dato)\",\"columna_2\":\"(sin dato)\",\"columna_3\":\"ARROYO FRIO\",\"columna_4\":\"PRIMARIA. JOSE MA MORELOS Y PAVON\",\"columna_5\":\"12EPR0684T\"},{\"columna_1\":\"60\",\"columna_2\":\"(sin dato)\",\"columna_3\":\"(sin dato)\",\"columna_4\":\"(sin dato)\",\"columna_5\":\"(sin dato)\"},{\"columna_1\":\"(sin dato)\",\"columna_2\":\"TECPAN DE GALEANA\",\"columna_3\":\"(sin dato)\",\"columna_4\":\"(sin dato)\",\"columna_5\":\"(sin dato)\"},{\"columna_1\":\"(sin dato)\",\"columna_2\":\"(sin dato)\",\"columna_3\":\"EL MORENO\",\"columna_4\":\"SECUNDARIA JUAN RUIZ DE ALARCON\",\"columna_5\":\"12DTV0412B\"},{\"columna_1\":\"61\",\"columna_2\":\"(sin dato)\",\"columna_3\":\"(sin dato)\",\"columna_4\":\"(sin dato)\",\"columna_5\":\"(sin dato)\"},{\"columna_1\":\"(sin dato)\",\"columna_2\":\"(sin dato)\",\"columna_3\":\"ZOQUIAPA\",\"columna_4\":\"JARDIN DE NIÑOS LEOBARDO VALLE\",\"columna_5\":\"12EJN0139V\"},{\"columna_1\":\"62\",\"columna_2\":\"(sin dato)\",\"columna_3\":\"(sin dato)\",\"columna_4\":\"NAVA\",\"columna_5\":\"(sin dato)\"},{\"columna_1\":\"(sin dato)\",\"columna_2\":\"TIXTLA DE GUERRERO\",\"columna_3\":\"(sin dato)\",\"columna_4\":\"(sin dato)\",\"columna_5\":\"(sin dato)\"},{\"columna_1\":\"(sin dato)\",\"columna_2\":\"(sin dato)\",\"columna_3\":\"ALMOLONGA\",\"columna_4\":\"SECUNDARIA DONACIANO\",\"columna_5\":\"11DES0049N\"},{\"columna_1\":\"63\",\"columna_2\":\"(sin dato)\",\"columna_3\":\"(sin dato)\",\"columna_4\":\"GUITIERREZ GARDUÑO\",\"columna_5\":\"(sin dato)\"}]}}\nPARA EL EJERCICIO FISCAL 2022\n{\"tabla_11\":{\"columnas\":[\"(sin encabezado)\",\"(sin encabezado)\",\"COL. BARRIO DEL\",\"PRIMARIA FEDERAL AGUSTIN MELGAR\",\"12DPR5897D\"],\"filas\":[{\"columna_1\":\"64\",\"columna_2\":\"(sin dato)\",\"columna_3\":\"TANCON\",\"columna_4\":\"(sin dato)\",\"columna_5\":\"(sin dato)\"},{\"columna_1\":\"(sin dato)\",\"columna_2\":\"(sin dato)\",\"columna_3\":\"LAS MINAS\",\"columna_4\":\"TELESECUNDARIA JOSEFA ORTIZ DE\",\"columna_5\":\"12DTV0954W\"},{\"columna_1\":\"65\",\"columna_2\":\"TLACOACHISTLAHUACA\",\"columna_3\":\"(sin dato)\",\"columna_4\":\"DOMINGUEZ\",\"columna_5\":\"(sin dato)\"},{\"columna_1\":\"(sin dato)\",\"columna_2\":\"(sin dato)\",\"columna_3\":\"RANCHO\",\"columna_4\":\"PRIMARIA BILINGÜE JUAN DEL CARMEN\",\"columna_5\":\"12DPR0282Z\"},{\"columna_1\":\"66\",\"columna_2\":\"(sin dato)\",\"columna_3\":\"CUANANCHINICHA\",\"columna_4\":\"(sin dato)\",\"columna_5\":\"(sin dato)\"},{\"columna_1\":\"(sin dato)\",\"columna_2\":\"(sin dato)\",\"columna_3\":\"LA MONTAÑA\",\"columna_4\":\"PRIMARIA FEDERAL RURAL EMILIANO\",\"columna_5\":\"12DPR0293F\"},{\"columna_1\":\"67\",\"columna_2\":\"(sin dato)\",\"columna_3\":\"(sin dato)\",\"columna_4\":\"ZAPATA\",\"columna_5\":\"(sin dato)\"},{\"columna_1\":\"68\",\"columna_2\":\"(sin dato)\",\"columna_3\":\"LA MONTAÑA\",\"columna_4\":\"JARDIN DE NIÑOS PETATITOS\",\"columna_5\":\"12DJN2890Z\"},{\"columna_1\":\"(sin dato)\",\"columna_2\":\"TLALCHAPA\",\"columna_3\":\"(sin dato)\",\"columna_4\":\"(sin dato)\",\"columna_5\":\"(sin dato)\"},{\"columna_1\":\"69\",\"columna_2\":\"(sin dato)\",\"columna_3\":\"COL. CUAUHTEMOC\",\"columna_4\":\"PRIMARIA POTRERO DEL LLANO\",\"columna_5\":\"12DPR4078Q\"},{\"columna_1\":\"70\",\"columna_2\":\"(sin dato)\",\"columna_3\":\"COL. CUAUHTEMOC\",\"columna_4\":\"PRIMARIA JUSTO SIERRA\",\"columna_5\":\"12DPR1437S\"},{\"columna_1\":\"71\",\"columna_2\":\"(sin dato)\",\"columna_3\":\"TLAPA DE COMONFORT\",\"columna_4\":\"PRIMARIA CARMEN SERDAN\",\"columna_5\":\"12DPV0531P\"},{\"columna_1\":\"(sin dato)\",\"columna_2\":\"(sin dato)\",\"columna_3\":\"TLAPA DE COMONFORT\",\"columna_4\":\"PRIMARIA ARNULFO CERON SORIANO\",\"columna_5\":\"12DPB0557X\"},{\"columna_1\":\"72\",\"columna_2\":\"(sin dato)\",\"columna_3\":\"(sin dato)\",\"columna_4\":\"(sin dato)\",\"columna_5\":\"(sin dato)\"},{\"columna_1\":\"(sin dato)\",\"columna_2\":\"TLAPA DE COMONFORT\",\"columna_3\":\"(sin dato)\",\"columna_4\":\"(sin dato)\",\"columna_5\":\"(sin dato)\"},{\"columna_1\":\"(sin dato)\",\"columna_2\":\"(sin dato)\",\"columna_3\":\"TLAPA DE COMONFORT\",\"columna_4\":\"PRIMARIA BILINGÜE RICARDO FLORES\",\"columna_5\":\"12DPB1177V\"},{\"columna_1\":\"73\",\"columna_2\":\"(sin dato)\",\"columna_3\":\"(COL LAS PALMAS)\",\"columna_4\":\"MAGON\",\"columna_5\":\"(sin dato)\"},{\"columna_1\":\"74\",\"columna_2\":\"(sin dato)\",\"columna_3\":\"SAN JUAN MINA\",\"columna_4\":\"PRIMARIA NIÑOS HEROES\",\"columna_5\":\"12DPR1392M\"},{\"columna_1\":\"75\",\"columna_2\":\"(sin dato)\",\"columna_3\":\"EL TINOCO\",\"columna_4\":\"PRIMARIA VICENTE GUERRERO\",\"columna_5\":\"12EPR0572P\"},{\"columna_1\":\"(sin dato)\",\"columna_2\":\"(sin dato)\",\"columna_3\":\"SAN ANTONIO LAS\",\"columna_4\":\"PRIMARIA RAYMUNDO ALARCON\",\"columna_5\":\"12EPR0566E\"},{\"columna_1\":\"76\",\"columna_2\":\"TLAPEHUALA\",\"columna_3\":\"HUERTAS\",\"columna_4\":\"(sin dato)\",\"columna_5\":\"(sin dato)\"},{\"columna_1\":\"77\",\"columna_2\":\"(sin dato)\",\"columna_3\":\"SAN JUAN MINA\",\"columna_4\":\"JARDIN DE NIÑOS JUANA DE ARCO\",\"columna_5\":\"12DJN0767M\"},{\"columna_1\":\"78\",\"columna_2\":\"(sin dato)\",\"columna_3\":\"NUEVO GUERRERO\",\"columna_4\":\"PRIMARIA BENITO JUARÉZ\",\"columna_5\":\"12DPR2019N\"},{\"columna_1\":\"(sin dato)\",\"columna_2\":\"ZIHUATANEJO DE\",\"columna_3\":\"COL. UN NUEVO\",\"columna_4\":\"(sin dato)\",\"columna_5\":\"(sin dato)\"},{\"columna_1\":\"(sin dato)\",\"columna_2\":\"AZUETA\",\"columna_3\":\"HORIZONTE PARA\",\"columna_4\":\"(sin dato)\",\"columna_5\":\"(sin dato)\"},{\"columna_1\":\"79\",\"columna_2\":\"(sin dato)\",\"columna_3\":\"(sin dato)\",\"columna_4\":\"TELESECUNDARIA JUAN ESCUTIA\",\"columna_5\":\"12DTV0471R\"},{\"columna_1\":\"(sin dato)\",\"columna_2\":\"(sin dato)\",\"columna_3\":\"GUERRERO (BARRIO\",\"columna_4\":\"(sin dato)\",\"columna_5\":\"(sin dato)\"},{\"columna_1\":\"(sin dato)\",\"columna_2\":\"(sin dato)\",\"columna_3\":\"NUEVO)\",\"columna_4\":\"(sin dato)\",\"columna_5\":\"(sin dato)\"},{\"columna_1\":\"(sin dato)\",\"columna_2\":\"(sin dato)\",\"columna_3\":\"VALLECITOS DE\",\"columna_4\":\"PRIMARIA URBANA FEDERAL EMILIANO\",\"columna_5\":\"12DPR4657Y\"},{\"columna_1\":\"(sin dato)\",\"columna_2\":\"ZIRANDARO DE LOS\",\"columna_3\":\"ZARAGOZA\",\"columna_4\":\"ZAPATA\",\"columna_5\":\"(sin dato)\"},{\"columna_1\":\"80\",\"columna_2\":\"(sin dato)\",\"columna_3\":\"(sin dato)\",\"columna_4\":\"(sin dato)\",\"columna_5\":\"(sin dato)\"},{\"columna_1\":\"(sin dato)\",\"columna_2\":\"CHAVEZ\",\"columna_3\":\"(sin dato)\",\"columna_4\":\"(sin dato)\",\"columna_5\":\"(sin dato)\"},{\"columna_1\":\"(sin dato)\",\"columna_2\":\"(sin dato)\",\"columna_3\":\"VALLECITOS DE\",\"columna_4\":\"SECUNDARIA TEC. IGNACIO ZARAGOZA\",\"columna_5\":\"12DT0119K\"},{\"columna_1\":\"81\",\"columna_2\":\"(sin dato)\",\"columna_3\":\"ZARAGOZA\",\"columna_4\":\"(sin dato)\",\"columna_5\":\"(sin dato)\"},{\"columna_1\":\"82\",\"columna_2\":\"(sin dato)\",\"columna_3\":\"LA CALERA\",\"columna_4\":\"PRIMARIA LAZARO CARDENAS\",\"columna_5\":\"12DPR0371T\"},{\"columna_1\":\"83\",\"columna_2\":\"(sin dato)\",\"columna_3\":\"LA CALERA\",\"columna_4\":\"TELESECUNDARIA CALMECAC\",\"columna_5\":\"12DTV0085Y\"},{\"columna_1\":\"84\",\"columna_2\":\"ZIRANDARO DE LOS\",\"columna_3\":\"PANDACUAREO\",\"columna_4\":\"PRIMARIA CUAUHTEMOC\",\"columna_5\":\"12DPR0376O\"},{\"columna_1\":\"(sin dato)\",\"columna_2\":\"CHAVEZ\",\"columna_3\":\"(sin dato)\",\"columna_4\":\"(sin dato)\",\"columna_5\":\"(sin dato)\"}]}}\nPARA EL EJERCICIO FISCAL 2022\nPrimero. El presente Acuerdo entrará en vigor al día siguiente de su publicación en el Periódico Oficial del\nSegundo. A partir de la entrada en vigor del presente Acuerdo, las Reglas de Operación del Programa de\nAlimentación para el Bienestar de Niñas y Niños, subsecuentes o sus modificaciones serán emitidas por la persona titular de la Secretaría de Desarrollo y Bienestar Social del Estado de Guerrero.\nDado en el “Recinto de las oficinas del Poder Ejecutivo del Estado” el inmueble ubicado en el número 62, Edificio Centro Planta Baja, en Boulevard René Juárez Cisneros, Código Postal 39000, Colonia Ciudad de los Servicios, en la Ciudad de Chilpancingo de los Bravo, Capital del Estado de Guerrero, a los diez días del mes de junio de dos mil veintidós.\nLA GOBERNADORA CONSTITUCIONAL DEL ESTADO DE GUERRERO.\nMTRA. EVELYN CECIA SALGADO PINEDA.\nRúbrica.\nEL SECRETARIO GENERAL DE GOBIERNO.\nMTRO. LUDWIG MARCIAL REYNOSO NUÑEZ.\nRúbrica.\nLA SECRETARIA DE DESARROLLO Y BIENESTAR SOCIAL.\nLIC. MA. DEL CARMEN CABRERA LAGUNAS.\nRúbrica.\nN. DE E. A CONTINUACIÓN, SE TRANSCRIBEN LOS ARTÍCULOS TRANSITORIOS DE LOS ACUERDO\nDE MODIFICACIÓN A LAS PRESENTES REGLAS DE OPERACIÓN.\nOPERACIÓN PARA EL EJERCICIO FISCAL 2022; PARA QUE SE AMPLÍE SU VIGENCIA POR EL\nPERIODO QUE SE ENCUENTRE EN APLICACIÓN DICHO PROGRAMA.\nPrimero. El presente Acuerdo de Modificación, entrará en vigor al siguiente día de su\nSegundo. Se derogan todas las disposiciones que se opongan al presente Acuerdo de",
  "ordenamiento": "PROGRAMA",
  "jurisdiccion": "GUERRERO",
  "fuente_oficial": "DIARIO OFICIAL DE LA FEDERACION",
  "Fecha de Publicación": "09 DE MAYO DE 2023",
  "ULTIMA REFORMA PUBLICADA": null,
  "status": "VIGENTE",
  "es_escaneado": false,
  "tiene_tablas": true,
  "materia": [
    "derechos de la niñez",
    "desarrollo social",
    "alimentación"
  ]
}