{
  "titulo": "Acuerdo por el Que Se Crea el Programa Atención Integral para los Pueblos Indígenas y Afromexicano,",
  "Contenido": "REGLAS DE OPERACIÓN PARA EL EJERCICIO FISCAL\nTEXTO ORIGINAL.\nDecreto publicado en el Periódico Oficial del Gobierno del Estado Edición Extraordinaria II, Miércoles 03 de Agosto de 2022.\nACUERDO POR EL QUE SE CREA EL PROGRAMA ATENCIÓN INTEGRAL PARA LOS\nPUEBLOS INDÍGENAS Y AFROMEXICANO, Y SE EMITEN SUS REGLAS DE OPERACIÓN PARA EL\nEJERCICIO FISCAL 2022.\nGuerrero.- Poder Ejecutivo.\nMAESTRA EVELYN CECIA SALGADO PINEDA, GOBERNADORA CONSTITUCIONAL DEL ESTADO\nDE GUERRERO, CON FUNDAMENTO EN LO DISPUESTO POR LOS ARTÍCULOS 71, 87, 88 PÁRRAFO\nPRIMERO, 90 NUMERAL 2 Y 91 FRACCIONES I, VI, IX Y XLVI DE LA CONSTITUCIÓN POLÍTICA DEL\nCONFIEREN LOS ARTÍCULOS 2, 3, 6, 7, 10, 18 APARTADO A FRACCIONES I Y XIV, 20 FRACCIÓN I\nY 32 DE LA LEY ORGÁNICA DE LA ADMINISTRACIÓN PÚBLICA DEL ESTADO DE GUERRERO 08;\n1, 2 FRACCIÓN I, 18 Y 25 DE LA LEY NÚMERO 454 DE PRESUPUESTO Y DISCIPLINA FISCAL DEL\nESTADO DE GUERRERO; 7 DE LA LEY NÚMERO 701 DE RECONOCIMIENTO, DERECHOS Y\nCULTURA DE LOS PUEBLOS Y COMUNIDADES INDÍGENAS DEL ESTADO DE GUERRERO; EN\nRELACIÓN CON EL ARTÍCULO 57 Y ANEXOS 21 (E14) Y 21-A (E14) DEL DECRETO NÚMERO 160\nDEL PRESUPUESTO DE EGRESOS DEL ESTADO DE GUERRERO PARA EL EJERCICIO FISCAL\n2022 Y LOS LINEAMIENTOS PARA LA ELABORACIÓN DE LAS REGLAS DE OPERACIÓN DE LOS\nPROGRAMAS SOCIALES ESTATALES PARA EL PERIODO 2022-2027.\nQue el Plan Nacional de Desarrollo 2019-2024 en el apartado de Política y Gobierno incluye\nRecuperar el Estado de Derecho y Libertad e Igualdad, reconoce y respeta las atribuciones y facultades que el marco legal del país otorga a las comunidades indígenas. derechos de los pueblos indígenas y afromexicanos. originarios y afromexicanos, el cual tiene como objetivo y metas, otorgar apoyos en casos de emergencia a la población indígena y afromexicana, además de brindar protección a las y los jornaleros agrícolas migrantes que se encuentran en tránsito hacia los campos de trabajo. La población indígena y afromexicana representa el sector social del país y del estado de Guerrero con mayores rezagos, principalmente en lo que se refiere a ingresos económicos, lo cual influye de manera relevante para que el 40% de la población indígena y afromexicana del estado se ubique en el rango de pobreza extrema.\nREGLAS DE OPERACIÓN PARA EL EJERCICIO FISCAL\nQue estas difíciles condiciones de vida, sitúan a un vasto número de personas indígenas y afromexicanas en una situación de riesgo, principalmente cuando al interior de las familias se presentan episodios de emergencia, ya sea por casos de enfermedad, muerte, desastres naturales o fenómenos meteorológicos. Con el Programa Atención Integral para los Pueblos Indígenas y Afromexicano, el gobierno del estado, a través de la Secretaría de Asuntos Indígenas y Afromexicanos, brinda diferentes apoyos a las personas y familias que no cuentan con recursos para enfrentar eventualidades o imprevistos, que pueden conducirlas a endeudamientos o pérdida de su exiguo patrimonio. Así también el Programa atiende algunas emergencias comunitarias, específicamente las relacionadas con el apoyo a viviendas precarias, dotación de utensilios y mobiliario a las casas de la mujer indígena y atención al medio ambiente; de igual manera, se brinda apoyo al comedor comunitario de la unidad de servicios integrales de la ciudad de Tlapa de Comonfort, que atiende a jornaleros agrícolas, migrantes indígenas, que se encuentran en tránsito a los campos de trabajo.\nQue mediante la Ley Orgánica de la Administración Pública del Estado de Guerrero Número 433, publicada en el Periódico Oficial del Gobierno del Estado el 12 de octubre de 1999, se crea la Secretaría de Asuntos Indígenas, con el propósito de proteger y preservar los derechos y cultura de las comunidades indígenas, así como para dar seguimiento a la aplicación y operación de los programas y acciones de las dependencias federales, estatales y municipales, dirigidos a promover el desarrollo integral de las y los indígenas, correspondiéndole el despacho entre otros asuntos, el de promover el respeto de los derechos, lengua y cultura de las comunidades indígenas.\nQue con la reforma del 28 de agosto de 2018 de la citada Ley Orgánica, en su artículo 32 establece que la Secretaría de Asuntos Indígenas y Afromexicanos, es la encargada de establecer y conducir las acciones encaminadas a preservar los derechos y cultura de los pueblos y comunidades indígenas y afromexicanas, promoviendo su desarrollo y fomentando el respeto a los derechos humanos, particularmente los de las mujeres, así como de dar seguimiento a la aplicación y operación de los programas y acciones de las dependencias federales, estatales y municipales, dirigidos a promover su desarrollo integral.\nQue conforme al Decreto Número 160 del Presupuesto de Egresos del Estado de Guerrero para el Ejercicio Fiscal 2022, señala que se ejercerán los recursos bajo una política de gasto público, con la finalidad de dar cumplimiento a los programas.\nQue las y los titulares de las Secretarías, Dependencias y Entidades de la Administración Pública\nEstatal, así como, las y los servidores públicos autorizados para ejercer recursos públicos del presupuesto de inversión de las mismas, serán responsables de los programas y proyectos de inversión que realicen, y que además deberán administrar los recursos públicos que estén bajo su responsabilidad, sujetándose a los principios de disciplina, legalidad, objetividad, profesionalismo, honradez, lealtad, imparcialidad, integridad, rendición de cuentas, transparencia, eficacia y eficiencia que rigen el servicio público, tal como lo menciona el artículo 7 de la Ley Número 465 de Responsabilidades Administrativas para el Estado de\nGuerrero.\nREGLAS DE OPERACIÓN PARA EL EJERCICIO FISCAL\nQue el artículo 57 del Decreto Número 160 antes citado, establece que con el objeto de asegurar la aplicación eficiente, eficaz, oportuna equitativa y transparente de los recursos públicos, la Secretaría de\nFinanzas y Administración y la Secretaría de Planeación y Desarrollo Regional, emitirán las disposiciones a que deberán sujetarse los programas de inversión sujetos a Reglas de Operación.\nQue, con sustento en lo anterior, la Secretaría de Planeación y Desarrollo Regional, expidió los\nLineamientos para la Elaboración de las Reglas de Operación de los Programas Sociales Estatales para el ejercicio fiscal 2022, publicados en el periódico oficial número 06, alcance II del Gobierno del Estado.\nQue el gobierno del estado de Guerrero, a través de la Secretaría de Asuntos Indígenas y\nAfromexicanos, ejecutará para este ejercicio fiscal 2022, el Programa Atención Integral para los Pueblos\nIndígenas y Afromexicano, con el objetivo de impulsar procesos y acciones que impacten en la creatividad y revitalización del patrimonio cultural y las identidades de los pueblos y comunidades indígenas y afromexicanas, para propiciar el reconocimiento de la diversidad y un diálogo intercultural entre la sociedad\nGuerrerense.\nQue la citada Secretaría, tendrá a cargo la implementación, operación, ejecución, evaluación y administración del Programa Atención Integral para los Pueblos Indígenas y Afromexicano, cuyo objetivo y metas son, las de otorgar apoyos en casos de emergencia a la población indígena y afromexicana, además de brindar protección a las y los jornaleros agrícolas migrantes que se encuentran en tránsito hacia los campos de trabajo.\nPor lo anteriormente expuesto y con fundamento en las disposiciones legales antes citadas, he tenido a bien expedir el siguiente:\nACUERDO POR EL QUE SE CREA EL PROGRAMA ATENCIÓN INTEGRAL PARA LOS PUEBLOS\nINDÍGENAS Y AFROMEXICANO, Y SE EMITEN SUS LAS REGLAS DE OPERACIÓN PARA EL\nEJERCICIO FISCAL 2022.\nArtículo 1. Se crea el Programa Atención Integral para los Pueblos Indígenas y Afromexicano con el objeto de proporcionar servicios y apoyos emergentes a la población indígena y afromexicana, y contribuir a la protección de los jornaleros agrícolas migrantes en tránsito a los campos de trabajo, a través de una atención expedita y humana, en coordinación con dependencias federales y estatales.\nArtículo 2. La Secretaría de Asuntos Indígenas y Afromexicanos, tendrá a cargo la implementación, ejecución, evaluación y administración del Programa Atención Integral para los Pueblos\nIndígenas y Afromexicano, bajo los criterios de objetividad, equidad, transparencia, publicidad, selectividad y temporalidad, con estricto apego a la normatividad aplicable, por lo tanto, será la encargada de la dispersión y asignación de los recursos del Programa, apegándose plenamente a las Reglas de Operación.\nArtículo 3. Se emiten las Reglas de Operación del Programa Atención Integral para los Pueblos\nIndígenas y Afromexicano para el Ejercicio Fiscal 2022, en las que se establece el procedimiento de\nREGLAS DE OPERACIÓN PARA EL EJERCICIO FISCAL ejecución del Programa, los principios, requisitos y condiciones que deben observarse para acceder al mismo, en los términos siguientes:\nINDÍGENAS Y AFROMEXICANO, PARA EL EJERCICIO FISCAL 2022\n1. Introducción.\n1.1. Antecedentes.\nEn el año 2006, la Secretaría de Asuntos Indígenas (actualmente denominada Secretaría para el\nDesarrollo de las Comunidades y Pueblos Indígenas y Afromexicanos) instrumentó el Programa\nAtención Integral para los Pueblos Indígenas y afromexicanos, que contemplaba la ejecución de un conjunto de acciones que permitían la atención inmediata a los Pueblos Indígenas, brindando servicios de emergencia social con oportunidad, calidad y calidez humana, que incidieran en el mejoramiento de sus condiciones sociales y calidad de vida. (REFORMADO, P.O. 33 ALCANCE II, 25 DE ABRIL DE 2023)\nDentro de los apoyos brindados originalmente por el Programa, se contemplaban entre otros: apoyo con ataúdes, apoyo para traslado de enfermos, apoyo para traslado de fallecidos, apoyo para pasajes a gestores de comunidades, apoyo para consultas médicas de especialidad, medicamentos y estudios clínicos, entre otros.\nAsimismo en sus inicios del Programa se ha brindado una especial atención a los jornaleros agrícolas, migrantes indígenas que salen de sus comunidades para trabajar en los campos de trabajo, principalmente en los estados del norte del País, a través de apoyos en especie para el Comedor\nComunitario de la Unidad de Servicios Integrales de la ciudad de Tlapa de Comonfort, encargada de brindar alojamiento y alimentación a las y los jornaleros que se encuentran en tránsito de sus comunidades a los campos de trabajo.\nA través de los años, este Programa ha sido adaptado de acuerdo a la demanda de la población indígena y, a partir del año 2013, contempló en su cobertura a la población afromexicana. de Desarrollo 2019– 2024, es atacar las causas profundas de la emigración, mediante la creación de empleos dignos, el desarrollo regional, la edificación de un estado de bienestar y el impulso a los procesos de construcción de la paz. Con el propósito de esta política, es que ningún ciudadano mexicano se vea obligado a abandonar su lugar de residencia por pobreza, marginación, falta de perspectivas de realización personal o inseguridad.\nSin embargo, en lo que ese esfuerzo da frutos, el gobierno estatal, sigue atendiendo a esta población migrante, que año con año va en la búsqueda de un mejor futuro a los campos agrícolas del país.\nREGLAS DE OPERACIÓN PARA EL EJERCICIO FISCAL\n2. Alineación Programática al PED y / o PND. específicas para alcanzarlos, el Programa Apoyos Prioritarios para los Pueblos Indígenas y\nAfromexicano es atender a los pueblos originarios y afromexicanos; promover el Desarrollo Integral respetando la cultura y el ejercicio de los derechos individuales y colectivos de los pueblos indígenas y afromexicanos; asegurar el ejercicio de los derechos de los pueblos originarios y afromexicanos en materia de alimentación salud, e infraestructura básica; impulsar políticas para el aprovechamiento sustentable de los recursos naturales, la conservación del medio ambiente y biodiversidad, al hacer correcto uso de sus conocimientos tradicionales; impulsar acciones que garanticen los derechos humanos y las condiciones de seguridad de los jornaleros agrícolas, migrantes indígenas y afromexicanos que se trasladan al interior del estado y otras regiones del País. (REFORMADO, P.O. 33 ALCANCE II, 25 DE ABRIL DE 2023)\nEl Programa se encuentra alineado al PED 2022-2027, en el Eje Temático 1. Bienestar, Desarrollo\nHumano y Justicia Social: Para garantizar los derechos de todas y todos desde una perspectiva integral, con el bienestar y la justicia social como ejes articuladores de una política pública, humana y sensible;\nObjetivo 1.3. Disminuir las desigualdades a través de la atención a grupos vulnerables; Estrategia 1.3.2.\nAtención prioritaria a grupos vulnerables; Línea de acción1.3.2.6. Impulsar acciones que garanticen el pleno goce de los derechos inalienables de los pueblos y comunidades indígenas y afromexicana del estado y con el Eje transversal B. Igualdad de Género e Inclusión Social; Objetivo: B.1. Implementar Programas y\nAcciones que Contribuyan a la Creación de los Derechos Individuales y Colectivas de los Pueblos\nIndígenas y Afromexicano, así como el Desarrollo Social, Económico y Cultural, basado en el Dialogo y\nParticipación conjunta entre las Instituciones y Comunidades, en un Marco de Respeto a sus Derechos\nContenidos en los Convenios e Instrumentos Legales de los Ámbitos Estatal, Nacional e Internacional;\nEstrategia: B.1.1. Generar Oportunidades para los Pueblos Originarios y Afromexicano, que permitan su\nDesarrollo Económico, Político, Social, Respetando las Manifestaciones de su Cultura y el Ejercicio de sus\nDerechos, a través de la Línea de Acción: B.1.1.1. Fomentar la Participación de los Pueblos Originarios y\nAfromexicano en la Planeación y la Gestión de su Propio Desarrollo, Asegurando el Respeto a sus\nDerechos y sus Formas de Vida y Contar con Mejor Acceso a la Seguridad Social. (REFORMADO, P.O. 33\nALCANCE II, 25 DE ABRIL DE 2023)\n2.1. Diagnóstico.\nNà savi (mixteco), Me’phaa (tlapaneco) y Nn´anncue Ñomdaa (amuzgo), y el pueblo Afromexicana, son el sustento del carácter multiétnico, plurilingüe y pluricultural de Guerrero. (REFORMADO, P.O. 33 ALCANCE\nNo obstante, la importancia histórica, cultural, social y demográfica de estos cinco pueblos, desigualdad, lo cual se refleja en los altos índices de pobreza y pobreza extrema que enfrentan, con los consecuentes rezagos en los ámbitos social y económico, así como en la salud, educación y medio ambiente.\nREGLAS DE OPERACIÓN PARA EL EJERCICIO FISCAL pobreza, ha sido históricamente construido por factores políticos, económicos, sociales y ambientales, que han articulado experiencias de privación material, jurídica y simbólica, y de reproducción de relaciones de desventaja; esta situación convierte particularmente vulnerables a las personas indígenas y afromexicanas al resto de las expresiones de marginación o precariedad, lo cual resulta en la profundización de la experiencia de desigualdad o exclusión social, sobre todo cuando, además de su condición étnica, se es pobre, mujer o adulto mayor, así sus estándares de vida son por lo general más bajos que los de otras personas de las mismas regiones y municipios.\nEn este sentido, el análisis de la situación de pobreza de los municipios considerados indígenas y afromexicanos, revela que, efectivamente, existe una relación directa y positiva entre la pobreza y el volumen de dicha población, aunque cabe señalar que es más amplia la pobreza en los municipios indígenas.\nPor lo tanto, mientras en los municipios con escasa presencia indígena, cuatro de cada diez habitantes se encuentran en pobreza, en los municipios indígenas esta situación alcanza a casi toda la población, es decir nueve de cada diez personas son pobres de la misma manera, en municipios donde la población indígena es mayor, más de la mitad experimenta extrema pobreza.\nEl estado de Guerrero posee un carácter multicultural, expresado por los diferentes grupos étnicos que se asientan en su territorio, principalmente por los pueblos indígenas Nahua, Na savi (mixteco), Me’pha (tlapaneco) y Nn´anncue Ñomdaa (amuzgo), y el pueblo afromexicano; estos pueblos y sus comunidades constituyen el cimiento de la identidad y la raíz histórica del estado, contribuyendo con sus saberes ancestrales, cosmovisiones, organización social y expresiones lingüísticas y artísticas a la riqueza cultural de Guerrero.\nDe acuerdo con información sociodemográfica del año 2020, en Guerrero se registraron las\nGUERRERO 2020\nTotal de población de Guerrero: 3´540,685\nMujeres: 1´840,073\nHombres: 1´700,612\nTotal Población hablante de lengua indígena: 515,487\nTotal Población que se autoreconoce indígena: 1’198,362\nTotal Población que se autoreconoce afromexicana: 303,923\nREGLAS DE OPERACIÓN PARA EL EJERCICIO FISCAL\n2.1.1. Población Potencial.\nEn Guerrero la población total es de 3´540,685 habitantes de los cuales 548,098 hablantes de la lengua indígena que representa el 15.48 % y 303,790 habitantes que se auto reconocen afromexicanos que equivale al 8.58 %, el cual da como resultado un total de 852,243 habitantes que constituyen nuestra población potencial que representa el 24.07% de la población total del estado de Guerrero.\n2.1.2. Población objetivo.\nAtender a la población indígena y afromexicana que habita en los 85 municipios del estado y cumpla con los requisitos previos para ser beneficiados en el numeral 6 Criterios y Requisitos de\nElegibilidad de las presentes Reglas de Operación.\n2.1.3. Población Beneficiaria.\nPersonas y grupo de personas indígenas y afromexicanas que se encuentran en situación de emergencia por motivos de salud y decesos; personas y autoridades comunitarias que se trasladan de sus localidades a la ciudad de Chilpancingo para realizar trámites o gestiones ante instituciones públicas de jornaleros agrícolas migrantes. El número de personas que serán apoyadas estarán determinadas de acuerdo a las situaciones de emergencia que se presenten y de acuerdo a la disponibilidad financiera del presente Programa. (REFORMADO, P.O. 33 ALCANCE II, 25 DE ABRIL DE 2023)\n2.1.4. Población Indígena.\nRegión Acapulco Región Montaña Región Costa Chica\nAcapulco de Juárez Acatepec Ayutla de los Libres\nRegión Centro Alcozauca de Guerrero Igualapa\nAhuacuotzingo Alpoyeca San Luis Acatlán\nChilapa de Álvarez Atlamajalcingo del Monte Tlacoachistlahuaca\nChilpancingo de los Bravo Atlixtac Xochistlahuaca\nEduardo Neri Cochoapa el Grande Municipios Afromexicanos\nJosé Joaquín de Herrera Copanatoyac Azoyú\nMártir de Cuilapan Cualác Copala\nTixtla de Guerrero Huamuxtitlan Cuajinicuilapa\nZitlala Iliatenco Cuautepec\nCopalillo Metlatónoc Juchitán\nHuitzuco de los Figueroa Olinala Marquelia\nIguala de la Independencia Tlacoapa Ometepec\nXalpatlahuac\nXochihuehuetlan\nZapotitlan Tablas\nREGLAS DE OPERACIÓN PARA EL EJERCICIO FISCAL\n2.2. Fundamento Legal.\nEl Programa tiene como fundamento legal los instrumentos jurídicos siguientes:\na). Constitución Política de los Estados Unidos Mexicanos.\nc). Ley General para la Igualdad entre Mujeres y Hombres.\nd). Ley Número 701 de Reconocimiento, Derechos y Cultura de los Pueblos y Comunidades\nIndígenas del Estado de Guerrero.\ne) Ley General de Acceso de las Mujeres a una Vida Libre de Violencia.\nf) Ley Orgánica de la Administración Pública del Estado de Guerrero Número 242. (REFORMADO,\nP.O. 33 ALCANCE II, 25 DE ABRIL DE 2023)\ng) Ley Número 207 de Transparencia y Acceso a la Información Pública del Estado de Guerrero.\nh) Ley Número 465 de Responsabilidades Administrativas para el Estado de Guerrero.\ni) Ley Número 466 de Protección de Datos Personales en Posesión de Sujetos Obligados del\nEstado de Guerrero.\nj) Ley Número 494 para la Igualdad entre Mujeres y Hombres del Estado de Guerrero.\nk) Ley Número 553 de Acceso de las Mujeres a una Vida Libre de Violencia del Estado Libre y\nSoberano de Guerrero.\nm) Declaración Universal de las Naciones Unidas sobre los Derechos de los Pueblos Indígenas.\nn) Convenio 169 sobre Pueblos Indígenas y Tribales, de la Organización Internacional del Trabajo. ñ) Plan Nacional de Desarrollo 2019-2024.\no) Decreto Número 424 del Presupuesto de Egresos del Estado de Guerrero para el Ejercicio\nREGLAS DE OPERACIÓN PARA EL EJERCICIO FISCAL\np) Decreto Número 181 por medio del cual la Sexagésima Tercera Legislatura al Honorable\nq) Lineamientos para la Elaboración de las Reglas de Operación de los Programas Sociales\nEstatales para el periodo 2022-2027.\nr) Ley Número 454 de Presupuesto y Disciplina Fiscal del Estado de Guerrero.\ns) Todos aquellos ordenamientos normativos aplicables.\n2.3. Definiciones y Siglas.\nDefiniciones:\nAuto adscripción afromexicana: Autor reconocimiento como persona descendiente de población africana que llegó al territorio de México durante la conquista y colonización española, con base en su propia cultura, tradiciones e historia.\nAuto adscripción indígena: Autor reconocimiento como persona indígena con base en su propia cultura, tradiciones e historia, ya sea hablante o no de alguna lengua indígena.\nPersona Beneficiaria: Persona que recibe los bienes y/o servicios, por haber cumplido con los requisitos establecidos en las presentes Reglas de Operación.\nPrograma: Programa Apoyos Prioritarios para los Pueblos Indígenas y Afromexicano.\n(REFORMADO, P.O. 33 ALCANCE II, 25 DE ABRIL DE 2023)\nReglas de Operación: Reglas de Operación del Programa Apoyos Prioritarios para los\nSiglas:\nSEDEPIA: Secretaría para el Desarrollo de las Comunidades y Pueblos Indígenas y\n3. Objetivos y Alcances.\n3.1. Objetivo General.\nProporcionar servicios y apoyos emergentes a la población indígena y afromexicana, y contribuir a la protección de los jornaleros agrícolas migrantes en tránsito a los campos de trabajo, a través de una atención expedita y humana, en coordinación con dependencias federales y estatales.\nREGLAS DE OPERACIÓN PARA EL EJERCICIO FISCAL\n3.2. Objetivo Específico.\na) Otorgar apoyos inmediatos en contingencias de salud, traslados de enfermos y fallecidos, pasajes, alimentación y hospedaje temporal.\nb) Proporcionar acompañamiento en la gestión, canalización y resolución institucional a las demandas de los ciudadanos indígenas y afromexicanos.\nc) Contribuir a mejorar las condiciones de traslado de los jornaleros agrícolas migrantes indígenas.\n3.3. Cobertura.\nEl Programa tendrá una cobertura estatal, abarcando la población Indígena y Afromexicana de los municipios y será implementado por la SEDEPIA, a través de la Delegación Administrativa. (REFORMADO,\nP.O. 33 ALCANCE II, 25 DE ABRIL DE 2023)\n3.4. Alcances.\nA través de este Programa se otorgan servicios y apoyos a la población indígena y afromexicana que enfrenta situaciones de emergencia, dando cumplimiento al artículo 6, fracción VIII, de la Constitución acceder a condiciones de bienestar y hacer posible su inclusión social. Los servicios y apoyos específicos se relacionan con: decesos (traslado de fallecidos y dotación de ataúdes); atención a la salud (compra de medicamentos, estudios de laboratorio y pago de gastos médicos); pago de pasajes y alimentación; alojamiento en el albergue temporal de la ciudad de Chilpancingo a personas, autoridades y gestores comunitarios que acuden a esta ciudad a realizar trámites oficiales.\nEste Programa apoya también a las y los jornaleros agrícolas migrantes, en lo relacionado con su traslado de sus comunidades a los campos de trabajo, para lo cual se apoya con diferentes insumos al comedor comunitario de la Unidad de Servicios Integrales de Tlapa de Comonfort, que atiende con hospedaje y alimentación a las y los jornaleros agrícolas en tránsito a los campos de trabajo, con lo que se busca también contribuir al cumplimiento de su derecho a recibir un trato digno.\nA. Apoyo a la Población Indígena y Afromexicana:\na) 10 donaciones de ataúdes.\nb) 10 traslados de enfermos y fallecidos.\nREGLAS DE OPERACIÓN PARA EL EJERCICIO FISCAL\nc) 5 apoyos para gastos de hospitalización, medicamentos, estudios de laboratorio y radiografías.\nd) 1100 personas que acuden a la capital a realizar trámites administrativos apoyados con pago de pasajes.\ne) 1100 personas que acuden a la capital a realizar trámites administrativos apoyados con pago de alimentación.\nf) 1,000 personas indígenas y afromexicanas beneficiadas con los servicios del Albergue\nTemporal en la ciudad de Chilpancingo, a través de la adquisición de materiales para su mantenimiento, limpieza, colchones, ropa de cama tales como cobertores almohadas.\nB. Atención a jornaleros agrícolas migrantes indígenas y afromexicanos:\na) 5 paquetes de insumos y alimentos para el Comedor Comunitario de la Unidad de Servicios Integrales de la ciudad de Tlapa, que atiende a 7,500 jornaleros agrícolas migrantes indígenas.\nb) 1000 personas jornaleras agrícolas migrantes indígenas y afromexicanas apoyadas con pago de pasajes.\n5. Programación Presupuestal.\nLos recursos aprobados en el Decreto Número 424 del Presupuesto de Egresos del Estado para el ejercicio Fiscal 2023 para este Programa corresponden a Inversión Estatal Directa, que asciende a\n$1´861,500.00 (Un millón ochocientos sesenta y un mil quinientos pesos 00/100 m.n.). (REFORMADO,\nREGLAS DE OPERACIÓN PARA EL EJERCICIO FISCAL\nCalendario de Ministración\n5.1. Gastos de Operación.\nEn cumplimiento al artículo 47 de la Ley de Coordinación Fiscal, podrá aplicarse hasta un 3% del presupuesto total del Programa, a gastos de operación y realización de diversas acciones, asociadas con la planeación, operación, supervisión, seguimiento, contraloría social y evaluación o asesoría externa del\nPrograma, por un monto de $55,845.00 (Cincuenta y cinco mil ochocientos cuarenta y cinco pesos\nREGLAS DE OPERACIÓN PARA EL EJERCICIO FISCAL\nUNIDAD DE COSTO\nCAPITULO CONCEPTO PARTIDA CANTIDAD TOTAL\nMEDIDA UNITARIO\n21111\nPaquete 2,500.00 5,000.00\n(Papelería)\n2100 2120\n2000 Paquete 2 2,500.00 5,000.00\n(Consumibles)\n2610\n2600 Litro 600 24.00 14,400.00\n(Combustible) copias pieza 945 1.00 945.00\n3720\n7 500.00\nViaje 3,500.00\n3000 3700 (Peajes)\n3750\nDía 27\n1,000.00 27,000.00\n(Viáticos)\nTOTAL: 55,845.00\n6. Criterios y Requisitos de Elegibilidad.\nLa forma de acceder a los servicios y apoyos que ofrece el Programa, responde a solicitud de las personas que demandan el beneficio, y los criterios serán trasparentes, equitativos y no discrecionales.\nLos requisitos, la forma de acceso y criterios de selección establecidos por el Programa son públicos, y estarán a la vista de las personas solicitantes en las oficinas centrales y delegaciones regionales de la\nSEDEPIA, cuya ubicación y horarios se anotan en el numeral 9.2 de estas Reglas de Operación, y conforme a lo siguiente: (REFORMADO, P.O. 33 ALCANCE II, 25 DE ABRIL DE 2023)\nA. Donación de ataúdes y traslados de personas fallecidas.\nEl familiar o gestor de la persona fallecida, deberá presentar solicitud escrita en formato libre de manera indistinta en su propia lengua o en castellano, dirigida a la persona titular de la SEDEPIA, la cual deberá ir debidamente firmada. Dicha solicitud deberá ir acompañada de los documentos siguientes:\na) Acta o Certificado de defunción (ministerial o médico).\nb) Identificación oficial de quien realiza el trámite.\nc) Acta de nacimiento del fallecido.\nd) CURP de la persona fallecida.\nDe acuerdo a la disposición presupuestal, el tiempo de respuesta de la solicitud será inmediata.\nUna vez realizado el trámite correspondiente, la funeraria contratada por la SEDEPIA se encargará de\nREGLAS DE OPERACIÓN PARA EL EJERCICIO FISCAL entregar el ataúd y, si fuera el caso, preparará el cuerpo de la persona fallecida y realizará el traslado del sitio donde sucedió el deceso, al lugar indicado por los familiares.\nB. Apoyo para gastos de hospitalización, estudios de laboratorio y radiológicos, y compra de medicamentos.\nEl familiar o gestor de la persona enferma presentará solicitud escrita en formato libre, de manera indistinta en su propia lengua o en castellano, dirigida a la persona titular de la SEDEPIA, especificando el apoyo solicitado y acompañada de los documentos siguientes:\na) Identificación oficial de la persona enferma y de quien realiza el trámite.\nb) Para el caso de apoyo para gastos de hospitalización, deberá presentarse copia desglosada por conceptos, del importe a pagar en el hospital.\nc) Para estudios de laboratorio y radiológicos, se deberá presentar copia de la solicitud de dichos estudios, expedida por el médico tratante.\nd) Para el caso de compra de medicamentos, copia de la receta con membrete del médico tratante, que incluya su número de cédula profesional y con fecha menor a 60 días de haber sido expedida.\ne) El tiempo de respuesta de la solicitud será inmediato. Una vez entregada la documentación señalada y de acuerdo a la disponibilidad financiera del Programa, la SEDEPIA cubrirá el monto del gasto médico, ya sea directamente al prestador del servicio o a la persona beneficiaria, en cuyo caso deberá presentar la factura original.\nC. Apoyo para pasajes, alimentación y hospedaje en el Albergue Temporal.\nLas autoridades, gestores comunitarios y personas indígenas o afromexicanos que realizan trámites en la ciudad de Chilpancingo, así como las personas que asisten a consulta médica, visita o cuidado de enfermos en los hospitales de Chilpancingo, y necesitan alguno de estos apoyos deberán proceder como se indica:\na) Entregar solicitud de apoyo en formato libre dirigida a la persona titular de la SEDEPIA y/o solicitarlo de manera verbal.\nb) Entregar copia de identificación oficial.\nc) Firma o huella del recibo respectivo (en caso de apoyo económico).\nd) En caso de solicitar hospedaje en el albergue temporal, deberá apegarse al reglamento establecido por la SEDEPIA.\nREGLAS DE OPERACIÓN PARA EL EJERCICIO FISCAL\ne) El tiempo de respuesta de la solicitud será inmediato y, en el caso de apoyo económico, estará supeditado a la disponibilidad financiera del Programa.\nD. Atención a Jornaleros agrícolas migrantes indígenas y afromexicanos.\nSe ofrecen dos tipos de apoyo; uno se entrega directamente a las personas interesadas, y el otro a la Unidad de Servicios Integrales, ubicada en la ciudad de Tlapa de Comonfort, así como a los centros de reunión y traslado de Chilapa de Álvarez y Ometepec. Los procedimientos para cada uno de los apoyos son los siguientes:\na) Apoyo de pasajes:\n● Personal de la SEDEPIA acude en los meses de agosto a diciembre a la Unidad de Servicios\nIntegrales de Tlapa de Comonfort, así como a los centros de reunión y traslado de Chilapa de Álvarez y\nOmetepec, para hacer entrega individual de apoyo económico de pasajes, cuyo monto estará en función de la distancia de las comunidades de residencia de las y los jornaleros a dichos centros de reunión.\n● La beneficiaria o beneficiario deberá entregar copia de identificación oficial.\nb) Apoyo de alimentos e insumos para Comedores Comunitarios de la Unidad de Servicios\nIntegrales de la ciudad de Tlapa de Comonfort.\n● Solicitud escrita por parte del Consejo de Jornaleros Agrícolas de la Montaña, instancia responsable del Comedor Comunitario de Tlapa de Comonfort, dirigida a la persona titular de la SEDEPIA, especificando los insumos requeridos.\n● La SEDEPIA entregará los alimentos e insumos, durante los meses de agosto y noviembre, en un plazo máximo de 15 días hábiles, a partir de la fecha de la solicitud.\nLos criterios para otorgar los apoyos del Programa tendrán como base la situación de emergencia específica de las personas solicitantes, así como de la disponibilidad presupuestal con que cuente dicho\nPrograma.\nEl Programa dará prioridad a las personas con mayor vulnerabilidad, como son niñas y niños, mujeres y personas adultas mayores. documentación que se enuncian al inicio de este apartado; dadas las situaciones de emergencia que atiende este Programa, las peticiones o entrega de solicitudes no se someten a un horario definido.\nEn cuanto a la Unidad de Servicios Integrales de Tlapa de Comonfort, que atienden a jornaleros agrícolas migrantes, deberán entregar la solicitud de apoyo en los meses de julio y septiembre, de acuerdo a lo establecido en el apartado 9.2.3, en un horario de 9:00 a 15:00 horas.\nREGLAS DE OPERACIÓN PARA EL EJERCICIO FISCAL\nLa entrega de solicitudes se hará en la Delegación Administrativa, ubicada en las oficinas centrales de la SEDEPIA o en sus Delegaciones Regionales, cuyas direcciones y números telefónicos se anotan en el apartado 9.2.3 de las presentes Reglas de Operación.\nLas personas en situación de emergencia, relacionada con la donación de ataúdes, traslado de fallecidos y enfermos, gastos médicos, apoyo de pasajes y alimentación, y alojamiento en el Albergue\nTemporal, recibirán de manera inmediata la respuesta a su solicitud y accederán con prontitud al apoyo solicitado, de acuerdo a la disponibilidad presupuestal del Programa y a la capacidad del Albergue\nTemporal.\nEn el caso del comedor comunitario de las y los jornaleros agrícolas migrantes, el apoyo se entregará en un término de quince días hábiles, a partir de la fecha en que sea entregada la solicitud y a la disponibilidad de recursos.\nUna vez que las personas solicitantes cumplan con la entrega completa de documentos y demás requisitos, recibirán el comprobante respectivo que ampara su solicitud.\nTodas las personas beneficiarias del Programa estarán incluidas en un Padrón Único de Personas\nBeneficiarias, el cual será de carácter público, teniendo la garantía de privacidad de sus datos personales y de la información adicional generada, de acuerdo a lo estipulado por la Ley Número 207 de Transparencia y Acceso a la Información Pública del Estado de Guerrero; en ningún caso esta información podrá emplearse para propósitos de proselitismo político, religioso o comercial, ni para otro fin distinto al establecido en las Reglas de Operación.\nLas servidoras y los servidores públicos que intervengan en los procesos y operación de este\nPrograma, no podrán solicitar contraprestación alguna o proceder de manera diferente a lo establecido en estas Reglas de Operación.\nUna vez que las personas solicitantes hayan cubierto los requisitos establecidos para acceder a los servicios y apoyos del Programa, se entregará el comprobante respectivo y recibirán el beneficio de manera gratuita, rápida y expedita, de acuerdo a la urgencia y complejidad del problema planteado.\n7. Tipo, Monto y Periodicidad del Apoyo.\nTipo Hasta un Periodicidad monto de:\nAtaúdes $4,800.00 Situación de emergencia y\nDisponibilidad Financiera\nTraslados $15,000.00\nHospitalarios $8,000.00\nPasajes y Alimentación $400.00\nAlbergue Temporal $150.00\nREGLAS DE OPERACIÓN PARA EL EJERCICIO FISCAL\nREGLAS DE OPERACIÓN PARA EL EJERCICIO FISCAL\nf) Además del anterior apoyo, se proporciona $0.00 alojamiento en el Albergue Temporal.\n(ADICIONADO, P.O. 33 ALCANCE II, 25 DE ABRIL DE\n2023)\nTIPO DE APOYO CONCEPTO HASTA UN MONTO DE:\na) Se otorgarán insumos para la preparación de alimentos al Comedor Comunitario de la Unidad\n5 paquetes de insumos hasta por un de Servicios Integrales de la ciudad de Tlapa de monto de\nComonfort. $60,000.00 cada uno.\nAtención a jornaleros agrícolas migrantes\nb) Apoyo para pasajes a jornaleros y indígenas y afromexicanos $400.00 por persona. jornaleras agrícolas migrantes\nc) Apoyo económico a 2 personas que participan Hasta por $6,000.00 en la preparación de alimentos y limpieza de la mensuales a cada persona, Unidad de Servicios Integrales de la ciudad de\nTlapa de Comonfort. (ADICIONADO, P.O. 33 durante los meses de agosto a\nALCANCE II, 25 DE ABRIL DE 2023) diciembre de 2023.\n7.2. Recursos no Devengados.\nEl presupuesto no ejercido para los fines autorizados al 31 de diciembre de 2023, será reintegrado a la Dirección General de Tesorería, de la Secretaría de Finanzas y Administración. (REFORMADO, P.O. 33\nALCANCE II, 25 DE ABRIL DE 2023)\n7.3. Resguardo de la Documentación.\nLa SEDEPIA a través de la Delegación Administrativa se hará cargo de la recepción y resguardo de la documentación comprobatoria para la solventación de los recursos ejercidos del Programa que desarrollan estas Reglas de Operación, así como también el informe del cierre del ejercicio fiscal.\n7.4. Supervisión y Control.\nLa supervisión, control y evaluación del Programa, será interna y estará a cargo de la Delegación\nAdministrativa, para lo cual se utilizará la Metodología del Marco Lógico y los resultados de la evaluación\nContralaría y Transparencia Gubernamental, mismos que se deberán presentar a más tardar a los 15 días hábiles posteriores a la terminación de cada trimestre, así como los informes sobre el presupuesto ejercido y en base a los indicadores de resultados previstos en este precepto.\nREGLAS DE OPERACIÓN PARA EL EJERCICIO FISCAL comprobación respectiva.\nLas delegaciones regionales y la Dirección General de Defensa y Asesoría Jurídica de la SAIA, llevarán a cabo el seguimiento al trabajo desarrollado por las instancias ejecutoras, con relación a las metas comprometidas, a fin de verificar la aplicación correcta de los recursos otorgados y el cumplimiento de objetivos y metas establecidas.\nEste seguimiento se realizará mediante la revisión de los informes presentados por las instancias ejecutoras, y a través de la evaluación y acompañamiento de las acciones desarrolladas en campo.\n8. Criterios de Selección.\nEl Programa está sujeto al presupuesto autorizado en el Decreto Número 424 del Presupuesto de\nEgresos del Estado de Guerrero para el Ejercicio Fiscal 2023, y las personas beneficiarias del Programa deben cumplir con los siguientes criterios de elegibilidad: (REFORMADO, P.O. 33 ALCANCE II, 25 DE ABRIL DE\n2023)\na) Ser originarios/as de comunidades y municipios indígenas y afromexicanos, o auto adscribirse como tales, independientemente de su sexo, edad, filiación política y religiosa.\nb) Ser autoridades comunitarias, gestores comunitarios y personas indígenas o afromexicanos, que realicen gestiones en la ciudad de Chilpancingo. (REFORMADO, P.O. 33 ALCANCE II, 25 DE ABRIL DE 2023)\nc) Ser jornaleras o jornaleros agrícolas migrantes en tránsito de sus comunidades a los campos de trabajo del interior o exterior del estado, o que estén ya establecidos en dichos campos.\nd) Solicitud por escrito dirigida al titular de la SEDEPIA, en caso de emergencia, la solicitud puede ser verbal. (REFORMADO, P.O. 33 ALCANCE II, 25 DE ABRIL DE 2023)\ne) Las solicitudes se entregarán en las oficinas centrales de la SEDEPIA, ubicadas en la ciudad de Chilpancingo, o en las Delegaciones Regionales de Tlapa de Comonfort, Chilapa de Álvarez y Ometepec\nGuerrero, en función del lugar donde ocurra el percance o contingencia. (REFORMADO, P.O. 33 ALCANCE II, 25\nf) Copia de identificación oficial de la persona que solicita el apoyo (credencial del INE, pasaporte, licencia de conducir, CURP, acta de nacimiento o constancia de identidad avalada por la\ng) Receta médica y factura originales que ampare los gastos de medicamentos, consulta médica o estudios radiológicos o de laboratorio.\nREGLAS DE OPERACIÓN PARA EL EJERCICIO FISCAL\nh) Copia del acta de defunción y original para cotejo, expedida por autoridad ministerial o delegaciones regionales, el apoyo podrá ser solicitado por un familiar o autoridad municipal o comunitaria, previa presentación de identificación oficial de la o el gestor y de la beneficiaria o beneficiario.\n8.1. Casos Especiales.\nPara casos especiales, se relacionan con hospedaje en el Albergue Temporal que opera en la ciudad de Chilpancingo, y apoyo de pasajes y alimentación a autoridades comunitarias, gestores comunitarios y personas indígenas o afromexicanas, que realicen gestiones en la ciudad de\nChilpancingo de los Bravo. (REFORMADO, P.O. 33 ALCANCE II, 25 DE ABRIL DE 2023).\n8.2. Casos de Emergencia o Desastre.\nPara el caso de emergencia o desastres naturales, la SEDEPIA podrá dar atención de manera inmediata de acuerdo a la disponibilidad financiera y la evaluación de los daños a la población afectada y facilitará los mecanismos para cumplir con los requisitos establecidos en las presentes Reglas de\nOperación. (REFORMADO, P.O. 33 ALCANCE II, 25 DE ABRIL DE 2023).\n8.3. Suspensión o Cancelación de Programa Social.\nSe cancelará el apoyo solicitado, cuando se incurra en los casos siguientes:\na) Presentar información o documentación alterada o falsa.\nb) No aplicar los recursos que se reciban conforme a los conceptos autorizados.\nc) No existan condiciones sociales y económicas para llevar a cabo las actividades.\n8.4. Integración del Padrón de Personas Beneficiadas.\nLas personas y agrupaciones beneficiarias del Programa, formarán parte de un Padrón de\nPersonas Beneficiarias, el cual será de carácter público, siendo reservados sus datos personales, de\nGuerrero y, en ningún caso, podrán emplearse para propósitos de proselitismo político, religioso o comercial, ni para ningún otro fin distinto al establecido en estas Reglas de Operación. solicitar pago alguno por el servicio que prestan, ni procederán de manera diferente a lo establecido en las presentes Reglas de Operación.\nREGLAS DE OPERACIÓN PARA EL EJERCICIO FISCAL\n9. Mecánica Operativa del Programa Social.\nPara la ejecución del Programa, la SEDEPIA, a través de la Delegación Administrativa, elaborará las Reglas de Operación y la programación presupuestal. (REFORMADO, P.O. 33 ALCANCE II, 25 DE ABRIL DE\n2023).\nLa implementación del Programa estará a cargo de la Delegación Administrativa, la cual será responsable de brindar los servicios a la población indígena y afromexicana, así como vigilar el correcto seguimiento y cumplimiento a los servicios prestados.\nLa vigencia de los servicios se realizará a partir de la entrada en vigor de las presentes Reglas de\nOperación.\nLas personas e instancias interesadas deberán entregar, en las unidades administrativas receptoras, la solicitud de apoyo mediante escrito libre en original, en el que se indique, el nombre de la(s) persona(s) solicitante(s), el tipo de apoyo que requiere y sus datos personales para localización, acompañada por los requisitos establecidos.\nEl personal de las unidades administrativas receptoras deberá orientar a las personas solicitantes, en la elaboración y presentación de las solicitudes y la documentación establecida en el Programa.\nLas unidades administrativas receptoras, al recibir cada solicitud, deberán verificar que el expediente cumpla con los requisitos señalados en estas Reglas de Operación, y deberán entregar el acuse de recibo a quien solicita el servicio, señalando los documentos o datos faltantes para que sean entregados en un plazo no mayor de cinco días hábiles.\nLos datos de las personas beneficiarias del Programa, así como la información que éste genere y administre estará regida por lo que establece la Ley Número 207 de Transparencia y Acceso a la\nInformación Pública del Estado de Guerrero.\nPrograma, así como los trámites a realizar serán totalmente gratuitos.\n9.1. Instancia Ejecutora y/o Responsable.\nLa ejecución del Programa, está bajo la responsabilidad de la SEDEPIA, a través de la Delegación\nAdministrativa; que además será la unidad responsable de la gestión, ministración y comprobación de\n9.2. Proceso de Incorporación al Programa Social. (REFORMADO, P.O. 33 ALCANCE II, 25 DE ABRIL\nDE 2023).\nREGLAS DE OPERACIÓN PARA EL EJERCICIO FISCAL acceder a ellos, siempre y cuando cumplan con los requisitos que para tal efecto se han establecido, y gozarán de las siguientes garantías:\na) Ser persona indígena o afromexicana en situación de emergencia.\nb) Ser jornalero agrícola migrante indígena o afromexicano.\nc) Ser persona indígena o afromexicana.\nd) Habitar en municipios identificados como indígenas y/o afromexicanos.\ne) Auto reconocerse persona indígena o afromexicana.\nf) Gozarán de las siguientes garantías:\n● Recibir el servicio o apoyo, sin que esto implique pago alguno a funcionarios, gestores u organizaciones de cualquier filiación.\n● Mantener en privacidad sus datos personales.\n● Si hubiera quejas o denuncias de las personas solicitantes de un servicio o apoyo o que son beneficiarias del Programa, la SEDEPIA deberá informar a la Secretaría de Contraloría y Transparencia\nGubernamental del Gobierno del Estado.\nLas solicitudes de servicios y apoyos de este Programa, deberán presentarse en las oficinas centrales de la SEDEPIA, o ante sus Delegaciones Regionales, ubicadas en las siguientes direcciones:\n● Chilpancingo: Av. De la Juventud, No. 05, Col. El Centenario, C.P. 39090, Tel. 747 494 9029.\n● Chilapa de Álvarez: Calle 8 Norte, No. 801, Barrio del Dulce Nombre, C.P. 41100, Tel. 756 475 0253.\n● Ometepec: Calle Juan Ruiz de Alarcón, núm. 32, Barrio de la Guadalupe, C.P. 41700, Tel. 741 412\n0055.\n● Tlapa de Comonfort: Calle Aquiles Serdán, No. 01, Col. Tepeyac, C.P. 41300, Tel. 757 476 0377.\nProceso de incorporación para:\n9.2.1. Apoyo en situaciones de emergencia.\nDonación de ataúdes y traslado de personas fallecidas.\nREGLAS DE OPERACIÓN PARA EL EJERCICIO FISCAL\nEl familiar o gestor de la persona fallecida, deberá presentar solicitud escrita en formato libre de manera indistinta en su propia lengua o en castellano, dirigida al titular de la SAIA, la cual deberá ir debidamente firmada. Dicha solicitud debe ir acompañada de los documentos siguientes:\na) Certificado de defunción (ministerial o médico)\nb) Identificación de quien realiza el trámite.\nc) Acta de nacimiento del fallecido.\nd) CURP de la persona fallecida.\nDe acuerdo a la disposición presupuestal, el tiempo de respuesta de la solicitud será inmediata.\nUna vez realizado el trámite correspondiente, la funeraria contratada por la SAIA se encargará de entregar el ataúd y, si fuera el caso, preparará el cuerpo de la persona fallecida y realizará el traslado del sitio donde sucedió el deceso, al lugar indicado por los familiares.\nEl solicitante deberá firmar de conformidad el acta de donación por el servicio prestado.\nTraslado de personas enfermas.\nEl familiar o gestor de la persona enferma presentará solicitud escrita de manera indistinta en castellano o en su propia lengua, especificando que la persona a trasladar se auto adscribe como indígena o afromexicano, y donde se mencionará el sitio de partida y destino, dirigida a la persona titular de la SAIA y acompañada de los siguientes documentos:\nIdentificación oficial de la persona enferma y/o de quien realiza el trámite.\nEl tiempo de respuesta de la solicitud será inmediato. Una vez realizado el trámite correspondiente, de acuerdo a la disponibilidad financiera del Programa.\nEn los casos en que las condiciones del enfermo requieran un servicio de traslado especializado, el solicitante deberá presentar en hoja membretada y firmada por el médico tratante, el diagnóstico y las características del vehículo idóneo para realizar el traslado.\nAl término del traslado, la persona solicitante deberá firmar de conformidad el servicio o apoyo recibido.\nApoyo para gastos de hospitalización, estudios de laboratorio y radiológicos, y compra de medicamentos.\nREGLAS DE OPERACIÓN PARA EL EJERCICIO FISCAL\nEl familiar o gestor de la persona enferma presentará solicitud escrita en formato libre, de manera indistinta en su propia lengua o en castellano, dirigida al titular de la SAIA, especificando el apoyo solicitado y acompañada de los documentos siguientes:\na) Identificación oficial de la persona enferma o de quien realiza el trámite.\nb) Para el caso de apoyo para gastos de hospitalización, deberá presentarse copia desglosada por conceptos, del importe a pagar en el hospital.\nc) Para estudios de laboratorio y radiológicos, se deberá presentar copia de la solicitud de dichos estudios, expedida por el médico tratante.\nd) Para el caso de compra de medicamentos, copia de la receta con membrete del médico tratante, que incluya su número de cédula profesional y con fecha menor a 60 días de haber sido expedida.\ne) El tiempo de respuesta de la solicitud será inmediato. Una vez entregada la documentación señalada y de acuerdo a la disponibilidad financiera del Programa, la SAIA cubrirá el monto del gasto médico, ya sea directamente al prestador del servicio o a la persona beneficiaria, en cuyo caso deberá presentar la factura original.\nApoyo para pasajes, alimentación y hospedaje en el Albergue Temporal.\nLas autoridades y gestores comunitarios que realizan trámites en la ciudad de Chilpancingo, así como las personas que asisten a consulta médica, visita o cuidado de enfermos en los hospitales de\nChilpancingo, y necesitan alguno de estos apoyos deberán proceder como se indica:\na) Entregar solicitud de apoyo en formato libre dirigida al titular de la SAIA y/o solicitarlo de manera verbal.\nb) Entregar copia de identificación oficial.\nc) Firma o huella del recibo respectivo (en caso de apoyo económico).\nd) En caso de solicitar hospedaje en el albergue temporal, deberá apegarse al reglamento establecido por la SAIA.\ne) El tiempo de respuesta de la solicitud será inmediato y, en el caso de apoyo económico, estará supeditado a la disponibilidad financiera del Programa.\n9.2.2. Atención a Jornaleros agrícolas migrantes indígenas y afromexicanos.\nSe ofrecen dos tipos de apoyo; uno se entrega directamente a las personas interesadas, y el otro a la Unidad de Servicios Integrales, ubicada en la ciudad de Tlapa de Comonfort, así como a los centros\nREGLAS DE OPERACIÓN PARA EL EJERCICIO FISCAL de reunión y traslado de Chilapa y Ometepec. Los procedimientos para cada uno de los apoyos son los siguientes:\nApoyo de pasajes y alimentación:\nPersonal de la SAIA acude en los meses de agosto y octubre a la Unidad de Servicios Integrales de Tlapa que atiende a las y los jornaleros agrícolas migrantes, así como a los centros de reunión y traslado de Chilapa y Ometepec, para hacer entrega individual de apoyo económico de pasajes y alimentación, cuyo monto estará en función de la distancia de las comunidades de residencia de las y los jornaleros a dichos centros de reunión.\nLa beneficiaria o beneficiario deberá entregar copia de identificación oficial.\nApoyo de alimentos e insumos para Comedores Comunitarios de la Unidad de Servicios\nIntegrales de la ciudad de Tlapa:\nSolicitud escrita por parte del Consejo de Jornaleros Agrícolas de la Montaña, instancia responsable del Comedor Comunitario de Tlapa, dirigida a la persona titular de la SAIA, especificando los insumos requeridos.\nLa SAIA entregará los alimentos e insumos, durante los meses de agosto y noviembre, en un plazo máximo de 15 días hábiles, a partir de la fecha de la solicitud.\n9.2.3. Direcciones y Teléfonos de contacto:\nLas solicitudes de servicios y apoyos de este Programa, deberán presentarse en las oficinas centrales de la SAIA, o ante sus delegaciones regionales, ubicadas en las direcciones siguientes:\na) Chilpancingo: Calle Guillermo Soberón Acevedo, núm. 8, Col. Salubridad. Tel. 01(747)\n137 0620.\nb) Chilapa de Álvarez: Calle 3 Norte, núm. 108, Col. Centro. Tel. (756) 475 0253.\nc) Ometepec: Calle Juan Ruiz de Alarcón, núm. 32, Barrio de la Guadalupe. Tel. (741) 412 0055.\nd) Tlapa de Comonfort: Calle Morelos, núm. 124, Col Centro. Tel. (757) 476 0377.\n10. Evaluación.\nLa SEDEPIA tendrá la obligación de revisar, de manera interna, la correcta operación y aplicación de las presentes Reglas de Operación y, en caso necesario, podrá solicitar una evaluación externa por parte de una instancia con experiencia en el tema. Asimismo, efectuará periódicamente acciones de supervisión y evaluación para garantizar el adecuado desarrollo del Programa, a efecto de corregir\nREGLAS DE OPERACIÓN PARA EL EJERCICIO FISCAL\nDesarrollo Regional y la Secretaría de Finanzas y Administración a fin de cubrir rubros prioritarios, con recursos de este mismo Programa o de otros que no hayan sido ejercidos en su momento, o bien que\n10.1. Indicadores (Construcción de la Matriz de Indicadores para Resultados. - Anexo 1).\nREGLAS DE OPERACIÓN PARA EL EJERCICIO FISCAL\nREGLAS DE OPERACIÓN PARA EL EJERCICIO FISCAL\nREGLAS DE OPERACIÓN PARA EL EJERCICIO FISCAL\n10.2. Seguimiento.\nLa supervisión, control y evaluación del Programa, será interna y estará a cargo de la Delegación\nAdministrativa de la SEDEPIA, a fin de verificar la aplicación correcta de los recursos otorgados y el cumplimiento de objetivos y metas establecidas en las presentes Reglas de Operación. Dicho seguimiento se hará con eficacia, eficiencia y efectividad. (REFORMADO, P.O. 33 ALCANCE II, 25 DE ABRIL DE 2023)\n10.3. Auditoría.\nLa SEDEPIA será la responsable de la supervisión directa de las acciones, así como de verificar que en su ejecución se cumpla con la normatividad aplicable. Los recursos asignados para la operación del Programa no pierden su carácter estatal, por lo que la Secretaría de Finanzas y Administración, la\nSecretaría de Contraloría y Transparencia Gubernamental y la Auditoría Superior del Estado, en el ámbito de sus respectivas competencias, realizarán actividades de fiscalización y auditoría. (REFORMADO, P.O. 33\nALCANCE II, 25 DE ABRIL DE 2023)\nAsimismo, otorgará todas las facilidades a las instancias fiscalizadoras para realizar en el momento que juzguen pertinente, las auditorías necesarias; asimismo, efectuará el seguimiento y la solventación de las observaciones planteadas por los órganos de control. La inobservancia de esta disposición, independientemente de las sanciones a que haya lugar, limitará la ministración de los recursos estatales en el siguiente ejercicio presupuestal.\n11. Mecanismos de Entrega del Apoyo.\nUna vez que ya fueron validados, verificados y revisados los requisitos, de acuerdo al numeral 9.2 de las presentes Reglas de Operación y el beneficio, será entregado en las instalaciones de la SEDEPIA.\n(REFORMADO, P.O. 33 ALCANCE II, 25 DE ABRIL DE 2023)\nPersonas indígenas y afromexicanas bajo las circunstancias siguientes:\na) Emergencias relacionadas con situaciones de muerte.\nb) Que se trasladan de sus comunidades a la ciudad de Chilpancingo para realizar gestiones, agrícolas migrantes concentrados en la Unidad de Servicios Integrales de Tlapa de Comonfort, o en los centros de reunión de Chilapa de Álvarez y Ometepec.\n12. Derechos y Obligaciones de las Personas Beneficiadas.\nDerechos:\na) Recibir un trato digno, respetuoso, oportuno, equitativo y de calidad.\nREGLAS DE OPERACIÓN PARA EL EJERCICIO FISCAL\nb) Acceder a los apoyos que otorga el Programa de acuerdo con lo establecido en estas Reglas de Operación y según disponibilidad presupuestal.\nc) Recibir orientación de la SEDEPIA para la presentación de solicitudes de apoyo e integración de expedientes sin costo alguno. (REFORMADO, P.O. 33 ALCANCE II, 25 DE ABRIL DE 2023).\nd) Recibir información respecto a los lineamientos de los albergues.\nObligaciones:\na) Conducirse con verdad y aportar la información personal que la SEDEPIA requiera de acuerdo a los requisitos establecidos en el numeral 6 de estos Lineamientos. (REFORMADO, P.O. 33 ALCANCE\nII, 25 DE ABRIL DE 2023).\nb) Cumplir con el Reglamento del Albergue Temporal. (REFORMADO, P.O. 33 ALCANCE II, 25 DE\nABRIL DE 2023).\na) Utilizar los apoyos y/o servicios para los fines que fueron solicitados.\nb) Respetar a las servidoras y servidores públicos que le ofrecen atención y/o orientación.\n12.1. Causales de Suspensión o Baja de las Personas Beneficiadas.\na) Dado que los apoyos y servicios que se otorgan a través de este Programa, responden a situaciones de emergencia, sólo las personas que incumplan con la documentación, requisitos e información establecida en estas Reglas de Operación, no podrán acceder a los servicios y apoyos del\nPrograma.\nb) No entregar la documentación e información requerida, de acuerdo a las Reglas de\nOperación.\nc) No emplear el bien o apoyo recibido para los fines por los que fue otorgado.\nd) Se cancelarán los servicio o apoyos asignados a las personas beneficiarias que presenten documentación o información falsa.\ne) Las personas beneficiarias de los servicios del Albergue Temporal, que presenten mala conducta o contravengan estas Reglas de Operación que para tal efecto se les entregará en el sitio, serán desalojadas del inmueble.\n12.2. Proceso de Baja.\nREGLAS DE OPERACIÓN PARA EL EJERCICIO FISCAL\nPara cumplir con las metas trazadas en las presentes Reglas de Operación, es importante que las solicitados, esto para contribuir a las necesidades de tan vulnerable sociedad, entre ellas los beneficios de ataúdes, traslado, apoyos en gastos de hospitalización, medicamentos, estudios especializados en laboratorio y radiografías, pasajes, alimentación, servicios y equipamiento para comedor comunitario, podrán ser supervisados de forma aleatoria con la finalidad de garantizar que los recursos son ejercidos correctamente. En caso contrario se realizará el proceso de baja y para el caso de albergues temporales al no cumplir con los lineamientos el servidor público responsable del albergue le informa que debido al incumplimiento no podrá continuar recibiendo el servicio, el cual quedará en un acta de hechos.\nEn caso contrario se realizará el proceso de baja y para el caso del Albergue Temporal al no cumplir con los lineamientos, el servidor público responsable del albergue informará al usuario que debido al incumplimiento no podrá continuar recibiendo el servicio, el cual quedará en un acta de hechos.\n(ADICIONADO, P.O. 33 ALCANCE II, 25 DE ABRIL DE 2023).\n13. Instancias Participantes.\nLa SEDEPIA será la instancia ejecutora del Programa, a través de la Delegación Administrativa, de acuerdo a los lineamientos establecidos en estas Reglas de Operación para el ejercicio fiscal 2023, la cual operará y comprobará los recursos del Programa, la Secretaría de Finanzas y Administración la cual realizará las ministraciones correspondientes de acuerdo al cronograma financiero y la Secretaría de\nContraloría y Transparencia Gubernamental para realizar las recomendaciones y sanciones pertinentes.\n(REFORMADO, P.O. 33 ALCANCE II, 25 DE ABRIL DE 2023).\n13.1. Instancia Normativa.\nLa instancia administrativa y/o normativa quien será responsable de la operación es la\nSEDEPIA, así como lo señala en el reglamento interno de la institución. Esto con el objeto de armonizar el correcto desempeño y aplicación de los recursos asignados por el estado para los fines del Programa.\n(REFORMADO, P.O. 33 ALCANCE II, 25 DE ABRIL DE 2023).\n14. Transparencia.\n14.1. Promoción y Difusión del Programa Social.\nOperación del Decreto Número 424 del Presupuesto de Egresos del Estado de Guerrero para el Ejercicio\nFiscal 2023, estas Reglas de Operación, además de ser publicadas en el Periódico Oficial del Gobierno del\nEstado, estarán disponibles para la población en general en las Oficinas Centrales de la SEDEPIA cuya ubicación es en Avenida de la Juventud, No. 05, Col. El Centenario, C.P. 39090, Chilpancingo de los\nBravo, México y Delegaciones Regionales, así como en las páginas electrónicas:\nREGLAS DE OPERACIÓN PARA EL EJERCICIO FISCAL\nAsimismo, a través de las Delegaciones Regionales ubicadas en las ciudades de Tlapa de\nComonfort, Chilapa de Álvarez y Ometepec, se difundirá la información relativa al Programa, incluyendo a las autoridades municipales y comunitarias de los municipios indígenas y afromexicanos. La papelería, documentación oficial y difusión del Programa, deberá incluir la leyenda de Blindaje Electoral descrita en el apartado 14.5 de las presentes Reglas de Operación.\n14.2. Contraloría Social.\nLa SEDEPIA, como instancia ejecutora, promoverá la contraloría social, la cual comprende un conjunto de acciones de control, vigilancia y evaluación que realizan las beneficiarias y beneficiarios, ya sea de manera organizada o independiente, bajo un esquema de derechos y compromisos ciudadanos con el propósito de contribuir a que la gestión gubernamental se realice en términos de transparencia, eficacia y honradez. Entre dichas acciones destacan las siguientes: (REFORMADO, P.O. 33 ALCANCE II, 25 DE ABRIL DE\n2023).\na) Informar a la ciudadanía acerca de los apoyos otorgados y su costo.\nb) Capacitar a las y los beneficiarios para que se constituyan en instancias de vigilancia y evaluación social.\nc) Establecer espacios de comunicación (reuniones vecinales, asambleas comunitarias, entre otros).\nd) Promover la integración de organizaciones de la sociedad civil para realizar acciones de contraloría social.\ne) Instrumentar mecanismos de recepción y atención de quejas y denuncias. El Órgano Interno de Control verificará en lo correspondiente la realización de dichas acciones.\n14.3. Protección de Datos Personales.\nLas solicitudes de servicios y apoyos de este Programa, deberán presentarse en las oficinas centrales de la SAIA.\nEn todo momento la persona beneficiaria podrá ejercer los derechos de alta, acceso, rectificación, cancelación y oposición de datos personales robados. (REFORMADO, P.O. 33 ALCANCE II, 25 DE\nLos datos recabados personales serán utilizados con la finalidad siguiente: validar que se cumplan los requisitos de elegibilidad para ser persona beneficiaria de este programa; que serán integrados de acuerdo a las facultades propias, compactibles análogos para la realización de compulsas para la\nREGLAS DE OPERACIÓN PARA EL EJERCICIO FISCAL\nPor lo tanto, se garantiza la protección de los datos personales que sean recabados y en\n14.4. Quejas y Denuncia.\nLas quejas, denuncias, peticiones y sugerencias relativas a este Programa, se realizarán de manera escrita, por comparecencia de la persona interesada, por correo electrónico o vía telefónica, y para aquellas que sean escritas se depositarán en los buzones instalados en las oficinas centrales de la\nSEDEPIA, ubicada en Avenida de la Juventud, No. 05, Col. el Centenario, C.P. 39090, Chilpancingo de los Bravo, así como en las Delegaciones Regionales, situadas en las ciudades de Tlapa de Comonfort, Chilapa de Álvarez y Ometepec Guerrero. (REFORMADO, P.O. 33 ALCANCE II, 25 DE ABRIL DE 2023).\nLa persona denunciante deberá proporcionar los siguientes datos: Nombre de la servidora o servidor público, departamento de adscripción, objeto de la denuncia, nombre y domicilio de la persona quejosa e identificación oficial.\nLas quejas, denuncias, peticiones y sugerencias relativas a este Programa, se atenderán a través de la Unidad de Transparencia y Acceso a la Información Pública, la cual dará seguimiento y respuesta en un término máximo de 20 días hábiles.\nEn caso de que la SEDEPIA no resuelva la queja de las personas solicitantes o beneficiarias, éstas podrán presentarla ante la Contraloría Social de la Secretaría de Contraloría y Transparencia\nGubernamental del Estado de Guerrero. (REFORMADO, P.O. 33 ALCANCE II, 25 DE ABRIL DE 2023).\n14.5. Acciones de Blindaje.\nEn la operación y ejecución de los recursos estatales de este Programa, se deberá observar y atender las medidas que emita la Fiscalía Especializada para la Atención de Delitos Electorales (FEPADE) políticos en el desarrollo de procesos electorales federales, estatales y municipales, por lo que la papelería y documentación oficial, así como la publicidad y promoción del Programa deberá de incluir la leyenda siguiente: “Este Programa es público, ajeno a cualquier partido político. Queda prohibido el uso para fines distintos a los establecidos en el Programa”.\n14.6. Acta de Donación (Anexo 2).\nPara el presente Programa, no aplica el formato de acta de donación. Se anexan formatos de\nREGLAS DE OPERACIÓN PARA EL EJERCICIO FISCAL\n15. Perspectiva de Género.\nLa operación del Programa y su implementación se establece con perspectiva de género, respeto y garantía al ejercicio de los derechos de las Mujeres Indígenas y Afromexicanas, busca mostrar que las diferencias entre mujeres y hombres se dan no sólo por su determinación biológica, sino también por las diferencias culturales asignadas a los seres humanos por lo que la SEDEPIA pondrá especial atención a mujeres para fortalecer sus capacidades y ampliar sus oportunidades y así potenciar la agencia económica en favor de mayores oportunidades para su bienestar y desarrollo. (REFORMADO, P.O. 33 ALCANCE\nII, 25 DE ABRIL DE 2023).\n16. Enfoque de Derechos.\nLas personas que fungen como servidoras o servidores públicos y participen en la operación del\nPrograma deberán promover, respetar, proteger y garantizar el ejercicio efectivo de los derechos humanos de las personas beneficiarias, de conformidad con los principios de universalidad, interdependencia, indivisibilidad y progresividad. En particular, se fomentará la eficacia y respeto irrestricto a los derechos colectivos de los pueblos indígenas y afromexicanos, reconocidos en la Constitución Política de los Estados\nUnidos Mexicanos e instrumentos internacionales. Con el objetivo de generar las condiciones necesarias para el acceso igualitario, en términos de disponibilidad, accesibilidad y calidad en las acciones que realiza este Programa, se implementarán mecanismos que hagan efectivo el acceso a la información gubernamental y se asegurará que el acceso a los apoyos y servicios se dé únicamente con base en lo establecido en estas Reglas de Operación, sin discriminación o distinción alguna.\n17. Acciones contra el SARS-COV 2.\nEn septiembre de 2019, la Organización Mundial de la Salud (OMS) planteó la urgencia de\n“prepararse para lo peor: una pandemia causada por un patógeno respiratorio letal y que se propague rápidamente” y sostuvo, además, que “los sistemas y capacidades existentes en materia de preparación y respuesta ante brotes epidemiológicos son insuficientes para hacer frente a la enorme repercusión y rápida propagación de una pandemia altamente mortífera, así como a la conmoción que supondría para los sistemas sanitarios, sociales y económicos” (OMS, 2019,). Pocos meses después, esta alerta se hizo realidad: tras un nuevo brote epidémico provocado por el virus SARS-CoV-2.9, que se había iniciado en\nChina y se había expandido ya a 15 países, el 30 de enero de 2020 la OMS declaró una emergencia que disponen de sistemas de salud precarios (OMS, 2020a). Debido a su rápida propagación por todo el mundo, el 11 de marzo la OMS declaró que el COVID-19 constituía una pandemia3, por lo que exhortó a:\ni) “prepararse y estar a punto”; ii) “detectar, proteger y tratar”; iii) “reducir la transmisión”; y iv) “innovar y aprender”. En la medida en que el virus se ha propagado a escala mundial, América se ha transformado en el epicentro de la nueva pandemia. En particular, en la actualidad algunos países latinoamericanos se sitúan entre las 20 naciones que, a nivel global, registran el mayor número de contagiados y fallecidos por el COVID-19 (Brasil, Perú, Colombia, México, Argentina y Chile); además de figurar en la lista de los 20 países con mayor número de casos por millón de habitantes (Panamá, Chile, Perú, Brasil y Colombia).\nREGLAS DE OPERACIÓN PARA EL EJERCICIO FISCAL\nEn este contexto, la Organización Panamericana de la Salud (OPS) estima que, para el 1 de octubre, ya se habrán registrado más de 438 000 muertes por COVID-19 en América Latina y el Caribe\n(DW, 2020). Junto con estas cifras alarmantes, la crisis socio sanitaria está exacerbando las ya de por sí amplias desigualdades sociales y económicas que caracterizan al subcontinente y, de no adoptarse medidas oportunas y adecuadas, también recrudecerá la inestabilidad política y social que ya asolaba a varios países de la región antes de la pandemia. Sin embargo, el mayor impacto lo sufrirán aquellos sectores de la sociedad que, históricamente, han quedado excluidos del poder político y económico, en particular, los pueblos indígenas, incluidos las mujeres, los jóvenes, las niñas y niños y las personas mayores indígenas.\n18. Anexos que Reflejan la Entrega del Apoyo (Económico, Especie o Servicio)\nAnexo 1. MIR.\nREGLAS DE OPERACIÓN PARA EL EJERCICIO FISCAL\nAnexo 2.\nREGLAS DE OPERACIÓN PARA EL EJERCICIO FISCAL\nREGLAS DE OPERACIÓN PARA EL EJERCICIO FISCAL\nPrimero. El presente Acuerdo entrará en vigor al día siguiente de su publicación en el Periódico\nSegundo. Se abrogan todas las disposiciones que contravengan a las presentes Reglas de\nOperación, siendo de nueva creación el presente Programa.\nTercero. A partir de la entrada en vigor del presente Acuerdo, las Reglas de Operación del\nPrograma Atención Integral para los Pueblos Indígenas y Afromexicano, subsecuente o sus modificaciones serán emitidos por la persona titular de la Secretaría de Asuntos Indígenas y Afromexicanos, responsable directa de la operación y ejecución de las mismas.\nDado en el “Recinto de las Oficinas del Poder Ejecutivo del Estado”, el inmueble ubicado en el número 62, Edificio Norte Planta Baja, en Boulevard René Juárez Cisneros, Código Postal 39074, Colonia\nCiudad de los Servicios, en la Ciudad de Chilpancingo de los Bravo, capital del estado de Guerrero, a los trece días del mes de junio del año dos mil veintidós.\nLA GOBERNADORA CONSTITUCIONAL DEL ESTADO DE GUERRERO.\nMTRA. EVELYN CECIA SALGADO PINEDA.\nRúbrica.\nEL SECRETARIO GENERAL DE GOBIERNO.\nMTRO. LUDWIG MARCIAL REYNOSO NUÑEZ.\nRúbrica.\nLA SECRETARIA DE ASUNTOS INDÍGENAS Y AFROMEXICANOS.\nLIC. REYNA MEJÍA MORALES.\nRúbrica.\nN. DE E. A CONTINUACIÓN, SE TRANSCRIBEN LOS ARTÍCULOS TRANSITORIOS DE LOS ACUERDO\nDE MODIFICACIÓN A LAS PRESENTES REGLAS DE OPERACIÓN.\nINTEGRAL PARA LOS PUEBLOS INDÍGENAS Y AFROMEXICANO, Y SE EMITEN SUS REGLAS DE\nOPERACIÓN PARA EL EJERCICIO FISCAL 2022\nPrimero. El presente Acuerdo entrará en vigor al día siguiente de su publicación en el Periódico\nSegundo. Se derogan todas las disposiciones que se opongan al presente Acuerdo de",
  "ordenamiento": "PROGRAMA",
  "jurisdiccion": "GUERRERO",
  "fuente_oficial": "DIARIO OFICIAL DE LA FEDERACION",
  "Fecha de Publicación": "25 DE ABRIL DE 2023",
  "ULTIMA REFORMA PUBLICADA": "28 de agosto de 2018",
  "status": "VIGENTE",
  "es_escaneado": false,
  "tiene_tablas": true,
  "materia": [
    "indígena"
  ]
}