{
  "titulo": "Acuerdo por el Que Se Crea el Programa Guerrero Nos Necesita con Uniformes (secundaria), y Se Expide",
  "Contenido": "OPERACIÓN\nI. INTRODUCCIÓN................................................................................................................................ 7\n1.1 Antecedentes................................................................................................................................... 7\n1.2 Alineación del Programa.................................................................................................................. 7\n1.3 Diagnostico...................................................................................................................................... 8\n2. MISIÓN Y VISIÓN.............................................................................................................................. 9\n2.1 Misión.............................................................................................................................................. 9\n2.2 Visión............................................................................................................................................... 9\n3. DEPENDENCIA O ENTIDAD RESPONSABLE DEL PROGRAMA.................................................... 9\n4. FUNDAMENTO LEGAL..................................................................................................................... 9\n5. OBJETIVOS Y ALCANCES............................................................................................................... 10\n5.1. Objetivo General............................................................................................................................. 10\n5.2. Objetivo Específico......................................................................................................................... 10\n5.3 Alcances.......................................................................................................................................... 10\n6. METAS FÍSICAS................................................................................................................................ 10\n7. PROGRAMACIÓN PRESUPUESTAL................................................................................................ 10\n8. REQUISITOS Y PROCEDIMIENTOS DE ACCESO.......................................................................... 11\n8.1 Difusión............................................................................................................................................ 11\n8.2 Requisitos de Acceso....................................................................................................................... 11\n8.3 Procedimientos de Acceso............................................................................................................... 12\n8.4 Requisitos de Permanencia, Causales de Baja o Suspensión Temporal.......................................... 12\n8.5 Modos de Entrega del Beneficio....................................................................................................... 12\n9. PROCEDIMIENTOS DE INSTRUMENTACIÓN................................................................................. 13\nOPERACIÓN\n9.1 Operación........................................................................................................................................ 13\n9.1.1. Espacio........................................................................................................................................ 13\n9.1.2. Determinación y precisión de actividades.................................................................................... 13\n9.1.3. Tiempo y calendario de actividades............................................................................................. 14\n9.1.4 Patrimonio del Programa............................................................................................................... 14\n9.1.5 Información del Programa............................................................................................................. 14\n9.1.5 Exposición del Programa.............................................................................................................. 15\n9.2 Gastos de Operación....................................................................................................................... 15\n10. TRANSPARENCIA........................................................................................................................... 15\n10.1 Difusión.......................................................................................................................................... 15\n10.2 Blindaje Electoral........................................................................................................................... 16\n10.3 Supervisión y Control..................................................................................................................... 16\n10. 4 Mecanismos de evaluación e indicadores..................................................................................... 16\n10.4.1 Evaluación.................................................................................................................................. 16\n10.4.2. Indicadores................................................................................................................................ 17\n10.5 Auditoria......................................................................................................................................... 17\n10.6 Recursos no devengados............................................................................................................... 17\n10.7 Contraloría Social.......................................................................................................................... 18\n10.8 Procedimiento de Queja o Inconformidad Ciudadana.................................................................... 18\n10.9 Mecanismos de exigibilidad........................................................................................................... 19\n10.10 Acta de Entrega-Recepción......................................................................................................... 19\n11 CRITERIOS DE SELECCIÓN Y ELEGIBILIDAD............................................................................... 20\nOPERACIÓN\n11.1 Método de selección de beneficiarios............................................................................................. 20\n12. MECÁNICA DE OPERACIÓN.......................................................................................................... 20\n12.1 Instancia Ejecutora......................................................................................................................... 20\n12.2 Instancia Administrativa y Normativas............................................................................................ 21\n12.3 Delimitación de atribuciones.......................................................................................................... 21\n13. DERECHOS, OBLIGACIONES Y SANCIONES DE LOS BENEFICIARIOS DE PROGRAMAS\nSOCIALES............................................................................................................................................. 22\n13.1 Derechos....................................................................................................................................... 22\n13.2 Obligaciones.................................................................................................................................. 22\n13.3 Sanciones...................................................................................................................................... 22\n14. INTERPRETACIÓN......................................................................................................................... 23\n15. GLOSARIO DE TÉRMINOS............................................................................................................. 23\nOPERACIÓN\nCREA EL PROGRAMA UNIFORMES (SECUNDARIAS) TRANSFORMANDO LA EDUCACIÓN DE LAS\nNO. 68 ALCANCE IV, DE FECHA 26 DE AGOSTO DEL 2022.\nTEXTO ORIGINAL.\nAcuerdo y Reglas de Operación publicados en el Periódico Oficial del Gobierno del Estado No. 26\nAlcance I, el Viernes 31 de Marzo de 2017.\nACUERDO POR EL QUE SE CREA EL PROGRAMA GUERRERO NOS NECESITA CON UNIFORMES\n(SECUNDARIA), Y SE EXPIDEN SUS REGLAS DE OPERACIÓN.\nGuerrero.- Poder Ejecutivo.\nLICENCIADO HÉCTOR ANTONIO ASTUDILLO FLORES, GOBERNADOR CONSTITUCIONAL\nDEL ESTADO DE GUERRERO, CON FUNDAMENTO EN LOS ARTÍCULOS 90 NUMERAL 2 Y 91\nGUERRERO; 2, 3, 6, 10, 11, 18 APARTADO A FRACCIONES I Y VII Y 26 DE LA LEY ORGÁNICA DE\nLA ADMINISTRACIÓN PÚBLICA DEL ESTADO DE GUERRERO NÚMERO 08; Y EL DECRETO\nNÚMERO 426 DEL PRESUPUESTO DE EGRESOS DEL ESTADO DE GUERRERO PARA EL\nEJERCICIO FISCAL 2017, ASÍ COMO LAS ESTRATEGIAS Y OBJETIVOS ESTABLECIDOS EN EL\nPLAN ESTATAL DE DESARROLLO DE GUERRERO 2016 -2021; Y\nQue en el Plan Estatal de Desarrollo 2016 - 2021, Eje 3.- Guerrero Socialmente Comprometido, objetivo 3.1. Denominado \"Construir un Estado garante pleno de los derechos sociales de las personas\" en sus Estrategia 3.2.2. Articular Políticas Públicas que atienden de manera específica cada Etapa del\nCiclo de Vida de la Población, por lo que se emprenden programas especiales de asistencia social a grupos vulnerables con el fin de brindar condiciones mínimas necesarias para el desarrollo humano. Una de sus líneas de acción tiene como propósito asegurar que las niñas, los niños y jóvenes de las familias contengan económicos.\nQue uno de los compromisos del Ejecutivo Estatal con la ciudadanía guerrerense, al asumir y tomar protesta como Gobernador Constitucional del Estado es, lograr un Guerrero de tranquilidad, de paz, de justicia, de crecimiento y de empleo, contribuyendo con ello a construir historias de éxitos individuales y colectivos que permitan consolidar el crecimiento económico y estabilidad social.\nQue el Ejecutivo Estatal, está comprometido con ser el principal promotor de acciones y establecer rutas encaminadas a lograr un estado moderno, inteligente y visionario.\nOPERACIÓN permanencia y equidad educativa en el Estado de Guerrero, por lo que ha decidido dar continuidad al mismo, para coadyuvar así en la disminución de la deserción escolar mediante el otorgamiento de una mochila escolar, al inicio de cada ciclo escolar para todos los niños y niñas inscritos en escuelas públicas de nivel de educación Secundaria con reconocimiento oficial de la Secretaría de Educación Guerrero.\nQue en el Decreto número 426 del Presupuesto de Egresos del Estado de Guerrero para el\nEjercicio Fiscal 2017, se señala que se ejercitarán los recursos bajo una política de gasto público, que permita dar cumplimiento a lo que globalmente prevén los ejes rectores del Plan Estatal de Desarrollo 2016\n- 2021. Las políticas encaminadas al desarrollo social, se orientaron a los sectores desprotegidos del\nEstado y a programas sociales.\nQue por lo antes expuesto he decidido crear el Programa Guerrero Nos Necesita Con\nUniformes (Secundaria) y emitir sus Reglas de Operación, con el objeto de otorgar transparencia y asegurar la aplicación eficiente, eficaz, oportuna y equitativa de los recursos públicos asignados al mismo.\nEn cumplimiento de lo anterior he tenido a bien expedir el siguiente:\nACUERDO POR EL QUE SE CREA EL PROGRAMA GUERRERO NOS NECESITA CON UNIFORMES\n(SECUNDARIA), Y SE EXPIDEN SUS REGLAS DE OPERACIÓN.\nArtículo 1. Se crea el Programa Guerrero Nos Necesita Con Uniformes (Secundaria), y se expiden sus Reglas de Operación, el Programa tiene por objeto favorecer la permanencia y equidad educativa en el Estado otorgando una mochila escolar, al inicio de cada ciclo escolar para todos los niños y niñas inscritos en escuelas públicas de nivel de educación Secundaria con reconocimiento oficial de la SEG.\nArtículo 2. Se emiten las Reglas de Operación del Programa Guerrero Nos Necesita Con\nUniformes (Secundaria), en las que se establecen los principios de eficiencia, eficacia, oportunidad, equitativa y transparencia de los recursos públicos y requisitos que se deben de cumplir para poder acceder ha dicho Programa.\nEn las Reglas de Operación del Programa Guerrero Nos Necesita Con Uniformes (Secundaria), se establecerán los criterios y requisitos que se deben de cumplir para poder acceder a dicho Programa.\nArtículo 3. La Secretaría de Educación Guerrero, tendrá a cargo la implementación, operación, ejecución, evaluación y administración del Programa Guerrero Nos Necesita Con Uniformes (Secundaria), bajo los criterios de objetividad, equidad, transparencia, publicidad, selectividad y temporalidad, con estricto apego a la normatividad aplicable, por lo tanto será la encargada de la asignación de los recursos del\nPrograma apegándose plenamente a las reglas de operación.\n1. Introducción\nOPERACIÓN\n1.1 Antecedentes\n1.2 Alineación del Programa\n1.3 Diagnostico\n2. Misión y Visión\n2.1 Misión\n2.2 Visión\n3. Dependencia o Entidad Responsable del Programa\n4. Fundamento Legal\n5. Objetivos y Alcances\n5.1 Objetivos Generales\n5.2 Objetivos Específicos\n5.3 Alcances\n6. Metas físicas\n7. Programación Presupuestal\n8. Requisitos y Procedimientos de Acceso\n8.1 Difusión\n8.2 Requisitos de Acceso\n8.3 Procedimientos de Acceso\n8.4 Requisitos de Permanencia, Causales de Baja o Suspensión Temporal\n8.5 Modos de entrega del beneficio.\n9. Procedimientos de instrumentación\n9.1 Operación\n9.2 Gastos de Operación\n10. Transparencia\n10.1 Difusión\n10.2 Blindaje Electoral\n10.3 Supervisión y control\n10.4 Mecanismos de Evaluación e Indicadores\n10.4.1 Evaluación\n10.4.2. Indicadores\n10.5 Auditoria\n10.6 Recursos No devengados\n10.7 Contraloría Social\n10.8 Procedimiento de Queja o Inconformidad Ciudadana\n10.9 Mecanismos de Exigibilidad\n10.10 Acta de Entrega- Recepción\nOPERACIÓN\n11. Criterios de Selección y elegibilidad\n11.1 Método de selección de beneficiarios.\n12. Mecánica de Operación\n12.1 Instancia Ejecutora\n12.2 Instancia Administrativa y/o Normativas\n12.3 Delimitación de Atribuciones\n13. Derechos, obligaciones y sanciones de los beneficiarios de programas sociales.\n13.1 Derechos\n13.2 Obligaciones\n13.3 Sanciones\n14. Interpretación\n15. Glosario de términos\nI. INTRODUCCIÓN\n1.1 Antecedentes\nEn el Estado de Guerrero, durante el presente ciclo escolar 2015 - 2016, asisten a la escuela secundaria 459,401 alumnos de las modalidades de educación Secundaria general, indígena y CONAFE.\nConsecuencia de la pobreza en la que vive gran parte de la población en el Estado de Guerrero, la entidad es considerada la tercera con mayor índice de pobreza a nivel nacional, sólo superada por\nOaxaca y Chiapas.\nEs por esto que el Programa Guerrero Nos Necesita Con Uniformes (Secundaria), se genera suministrando uniformes escolares a las alumnas y alumnos de educación básica del nivel Secundaria de escuelas públicas con reconocimiento oficial de la Secretaría de Educación Guerrero (SEG), ubicadas en los 81 Municipios del Estado como una estrategia compensatoria que favorezca la permanencia y equidad educativa, identificándoles como alumnas y alumnos de educación Secundaria, reforzando su seguridad, evitando la discriminación, y fortaleciendo su disciplina y orgullo de pertenencia a su escuela.\nFUENTE: Instituto Nacional para la Educación de los Adultos. Estudio Estadístico Educativo en el\n1.2 Alineación del Programa\nEl Programa denominado Guerrero Nos Necesita Con Uniformes (Secundaria) se encuentra enmarcado en Objetivo 3.1. Construir un Estado garante pleno de los derechos sociales de las personas, del Eje 3.- Guerrero Socialmente comprometido del Plan Estatal de Desarrollo 2016 - 2021.\nOPERACIÓN\nEstrategia 3.2.2. Articular políticas públicas que atiendan de manera específica cada etapa del ciclo de vida de la población.\nLíneas de acción:\n• Promover el desarrollo integral de las niñas y los niños, sobre todo en materia de alimentación, salud y educación, mediante la implementación de acciones entre los órdenes de Gobierno y la sociedad civil.\n• Fomentar el desarrollo personal y profesional de los jóvenes del Estado de Guerrero para que participen activamente en el desarrollo del mismo y alcancen sus expectativas profesionales, laborales, culturales y sociales.\n• Vigilar y promover el respeto de los derechos sociales de las personas adultas mayores, para garantizar su calidad de vida en materia de salud, alimentación, empleo, vivienda y bienestar emocional.\nEste Programa se alinea al Programa Sectorial Educativo, por lo que además, con su aplicación y ejecución favorece la permanencia y equidad educativa en el Estado otorgando una mochila escolar, al inicio de cada ciclo escolar para todos los niños y niñas inscritos en escuelas públicas de nivel de educación\nSecundaria con reconocimiento oficial de la Secretaría de Educación Guerrero.\n1.3 Diagnostico\nDatos recientes del Instituto Nacional de Educación de los Adultos (INEA) señalan que 33 millones de personas en México están en rezago educativo: seis no saben leer y escribir; 10 no han terminado sus estudios de educación secundaria y 17 dejaron inconclusa la secundaria, cerca de 30 por ciento de la población nacional tiene deficiencias educativas. Si estos mismos datos se aplican en el estado de\nGuerrero, tenemos que el problema casi se duplica, pues en nuestra entidad, de acuerdo con la información del Consejo Nacional de Evaluación de las Políticas de Desarrollo Social (CONEVAL), el 57.98 por ciento de los mayores de 15 años se encuentran en una situación similar; 20 por ciento no sabe leer y escribir; 38 por ciento no ha finalizado su primaria o terminado la secundaria. Considerando que en Censo de Población de 2010 somos 3.4 millones de guerrerenses, entonces tenemos que 680 mil no están alfabetizados y 1.3 millones no concluyeron su primaria o la secundaria.\nEl rezago educativo guerrerense no es, por supuesto, igual en las siete regiones y en los 81 municipios que forman parte de nuestra entidad. El municipio con el mayor rezago es Cochoapa el Grande, en La Montaña, con 96.68 por ciento y el de menor atraso es Chilpancingo, en la zona Centro, que tiene\n37.74. Iguala, en la región Norte, con 41.33 es el segundo mejor municipio en avance educativo. Acapulco ocupa el tercero con un porcentaje de 42.34.\nEn la Costa Grande, el mejor posicionado de los ocho municipios que la forman, es Zihuatanejo con 45.84 por ciento y el de mayor atraso es Coahuayutla, por cierto el de mayor extensión territorial, que tiene 88.83 por ciento.\nEn la Tierra Caliente, Pungarabato es el más avanzado tiene un rezago de 52 y Zirándaro el más atrasado, de los nueve de la región, con 83.38. De los 15 municipios que pertenecen a la Costa Chica,\nOPERACIÓN\nMarquelia y Ometepec son los mejores con un 59 por ciento de rezago y Xochistlahuaca, el de mayor atraso con 86.71 por ciento de su población sin educación básica concluida.\nEl derecho a la educación supone para todos los mexicanos que esta sea pública, laica y de calidad, la cual no debe circunscribirse a grupos de edad, al ciclo señalado como obligatorio o al sistema escolarizado. Además debe garantizarse la permanencia, por lo menos, a la conclusión del nivel básico que es seis años de primaria y tres de secundaria.\nEs importante puntualizar que el aprendizaje obtenido sea relevante y pertinente para que los mexicanos logren un mejor desarrollo humano como lo establece el artículo tercero de nuestra Carta\nMagna, su ley reglamentaria y los convenios internacionales signados por nuestro país sobre los derechos humanos, económicos, sociales y culturales.\nFUENTE: Instituto Nacional para la Educación de los Adultos. Estudio Estadístico Educativo en el\nEstado de Guerrero, 2013-2014. Publicado en el portal de: http://www.snie.sep.gob.mx\n2. MISIÓN Y VISIÓN\n2.1 Misión\nFavorecer la permanencia educativa y contribuir a la disminución de los niveles de deserción escolar en el Estado, ya que proporcionará identidad escolar y equidad, logrando un mejor compañerismo.\n2.2 Visión\nQue las personas beneficiadas con el Programa obtengan un incentivo que les permita concluir sus estudios de nivel de educación Secundaria, para que puedan seguir desarrollándose de manera individual en un marco de derechos humanos.\n3. DEPENDENCIA O ENTIDAD RESPONSABLE DEL PROGRAMA\nLa instancia ejecutora y responsable de este Programa será la Secretaría de Educación Guerrero, misma que realizará las actividades relacionadas con la gestión, operación, administración, comprobación y ejecución de los recursos.\n4. FUNDAMENTO LEGAL\na) Constitución Política de los Estados Unidos Mexicanos;\nb) Ley General de los Derechos de Niñas, Niños y Adolescentes;\nd) Ley Sobre el Sistema Estatal de Asistencia Social número 332;\ne) Ley número 812 para la Protección de los Derechos de Niñas, Niños y Adolescentes del Estado de Guerrero;\nOPERACIÓN\nh) Ley número 695 de Responsabilidades de los Servidores Públicos del Estado y de los\nMunicipios de Guerrero;\ni) Ley Orgánica de la Administración Pública del Estado de Guerrero No. 08;\nj) Reglamento Interior del Organismo Público Descentralizado Sistema para el Desarrollo Integral de la Familia del Estado de Guerrero;\nk) Decreto número 196 por medio del cual la Sexagésima Primera\nEstatal de Desarrollo de Guerrero 2016-2021;\nl) Decreto número 426 del Presupuesto de Egresos del Estado de Guerrero para el Ejercicio Fiscal\n2017;\nm) Declaración Universal de los Derechos Humanos;\nn) Declaración de los Derechos del Niño;\no) Convención de los Derechos del Niño; y\np) Todos aquellos ordenamientos normativos que sean aplicables.\n5. OBJETIVOS Y ALCANCES\n5.1. Objetivo General.\nFavorecer la permanencia y equidad educativa en el Estado evitando la discriminación, fortaleciendo su disciplina y orgullo de pertenencia a su escuela, en el nivel secundaria. Apoyar a la economía familiar de los padres o tutores.\n5.2. Objetivo Específico.\nOtorgar una mochila escolar, al inicio de cada ciclo escolar para todos los niños y niñas inscritos en escuelas públicas de nivel de educación Secundaria con reconocimiento oficial de la Secretaría de\nEducación Guerrero.\n5.3 Alcances\nEn el Programa Guerrero Nos Necesita Con Uniformes (Secundaria), se busca beneficiar para el ciclo escolar 2017 - 2018 a 200,000 niñas y niños de manera directa y de acuerdo a la disponibilidad presupuestal con que cuenta el Programa, favoreciendo su permanencia y equidad educativa, dando prioridad a los municipio de mayor grado de marginación.\nPara el logro de los objetivos, esto se alcanza en el corto y mediano plazo, atendiendo la disposición presupuestal.\n6. METAS FÍSICAS\n200,000 beneficiarios directos.\nOPERACIÓN\n7. PROGRAMACIÓN PRESUPUESTAL\nPara la aplicación y ejecución del Programa, el origen del financiamiento es a través Inversión\nEstatal Directa, como se estipula en el Decreto número 426 del Presupuesto de Egresos para el Ejercicio\nFiscal 2017:\nRESUMEN GENERAL DEL PRESUPUESTO\nACCIONES INVERSION\nDispersión al Programa Guerrero Nos Necesita con Uniformes (Secundaria) $29.100.000 00\nGastos de Operación 900,000.00\nTOTAL DEL PRESUPUESTO: $30,000.000.00\nComo se ha señalado el origen del financiamiento para el Programa Guerrero Nos Necesita Con\nUniformes (Secundaria), es por la modalidad de administración directa, en tanto no se convenga con instancias estatales o federales, instituciones educativas u organizaciones no gubernamentales (ONG) no se estará en la disponibilidad de ampliar metas.\nLos recursos asignados a éste Programa son mediante Inversión Estatal Directa y se asignarán en función de la disponibilidad presupuestal.\nLa instancia ejecutora del Programa Guerrero Nos Necesita Con Uniformes (Secundaria), deberá presentar a la Secretaría de Finanzas y Administración (SEFINA) y a la Secretaría de Planeación y\nDesarrollo Regional un reporte final del Ejercicio Fiscal 2017 al cierre de este. Además dicha información deberá ser registrada en el Sistema Integral de Evaluación y Seguimiento (SIES).\n8. REQUISITOS Y PROCEDIMIENTOS DE ACCESO\n8.1 Difusión. medios de comunicación estatales, el uso de los espacios en radio y televisión así como en la página web:\n8.2 Requisitos de Acceso a. Convocatoria. Publicación de convocatoria en los diferentes medios de comunicación, (Secundaria), en todas las escuelas públicas de los 81 Municipios del Estado de Guerrero.\nOPERACIÓN b. Registro. Este se llevará a cabo a través de las instituciones educativas de nivel Secundaria, al Secretaría de Educación Guerrero. c. Integración de la base de datos. Una vez obtenidos los expedientes de los beneficiarios en las diferentes instituciones educativas, se capturan y digitalizan en el Sistema de Información (SIC) la\nSecretaría de Educación Guerrero, lo que permitirá actualizar la Base de Datos de Beneficiarios. Dicha información será incorporada en el sistema de datos personales el cual se denomina: Sistema Informático\nÚnico de la Secretaría de Educación Guerrero, cuya finalidad es contar con un padrón de beneficiarios homogéneo y confiable. d. Beneficiarios. Serán todos los niños y niñas que se encuentren legalmente inscritos en instituciones educativas públicas de nivel Secundaria del Estado de Guerrero con reconocimiento oficial de la Secretaría de Educación Guerrero. e. Entrega. Se llevará a cabo en la primera semana, al inicio de cada ciclo escolar, a través del\nPrograma Guerrero Nos Necesita Con Uniformes (Secundaria).\n8.3 Procedimientos de Acceso\nCon el fin de obtener un registro para el control de la información, las posibles beneficiarias y beneficiarios presentarán (a través de sus padres o tutores), original y copia de los documentos siguientes:\na) Acta de nacimiento;\nb) Clave Única de Registro de Población (CURP);\nc) Identificación oficial con fotografía de la madre o tutor (IFE, cédula profesional o pasaporte);\nd) Constancia de inscripción vigente que avale que la alumna o alumno se encuentre legalmente inscrito en la institución pública de educación Secundaria del Estado de Guerrero.\nLos documentos deberán ser entregados (a través de sus padres o tutores) en la escuela a la que pertenezcan las y los solicitantes, el trámite se realizará invariablemente de manera personal, en lugar y tiempo que lo requiera el Programa, por lo que no se le dará trámite a los paquetes de solicitudes enviadas por representantes o líderes partidistas.\n8.4 Requisitos de Permanencia, Causales de Baja o Suspensión Temporal\n• El único registro de permanencia en el Programa \"Guerrero Nos Necesita con Uniformes\n(Secundaria)\" es comprobar estar legalmente inscrito en una Institución Educativa Pública con reconocimiento oficial de la Secretaría de Educación Guerrero.\n• La suspensión o baja temporal del Programa se dará cuando haya el alumno o alumna haya sido dado de baja en la Institución Educativa, ya sea de manera temporal o definitiva según sea el caso.\n• La baja definitiva del Programa se dará por fallecimiento del beneficiario.\n8.5 Modos de Entrega del Beneficio\nOPERACIÓN\nLa entrega del apoyo será anual y se llevará a cabo en la primera semana, al inicio de cada ciclo escolar, a través del Programa Guerrero Nos Necesita Con Uniformes (Secundaria). estas Reglas de Operación, estarán condicionados a la disponibilidad presupuestal del Programa, así como al dictamen técnico que efectúe La Secretaría de Educación Guerrero, para obtener el beneficio directo.\n9. PROCEDIMIENTOS DE INSTRUMENTACIÓN\n9.1 Operación\nLa operación del Programa se desarrollará a través de Reglas de Operación que permitan delimitar las facultades y competencia de ejecución de las instancias que participan, así como para coadyuvar en la correcta realización de las labores encomendadas al personal y propiciar la eficiencia y uniformidad en este apoyo social.\nPersonal la Secretaría de Educación Guerrero:\na) Tipo y número\nCARGO ÁREA CANTIDAD CATEGORÍA\nCoordinación General. 1 Coordinador General.\nCoordinador de Seguimiento y Evaluación Social. 1 Coordinador\nCoordinación Operativa. 1 Coordinador Operativo\nCoordinadores Regionales 7 Coordinador Regional\nDepartamento de Seguimiento y Control. 1 Jefe de Departamento\nDepartamento de Evaluación y Estadísticas. 1 Jefe de Departamento\nc) (SIC) Reclutamiento. Ninguno (solo apoyo de personal, con apoyos económicos por prestación de servicios).\nd) Adiestramiento.\nEs responsabilidad (SIC) la Secretaría de Educación Guerrero, dar a conocer al personal adscrito\nCon Uniformes (Secundaria).\n9.1.1. Espacio.\nEl espacio en que se desarrollará el Programa Guerrero Nos Necesita con Uniformes (Secundaria) es la Secretaría de Educación Guerrero, como un Organismo Público Descentralizado del Estado de\nOPERACIÓN\nGuerrero en las oficinas, que este mismo ocupa ubicadas en: Av. de la Juventud S/N. Col. Burócratas\nChilpancingo, Guerrero, Guerrero (SIC) y en giras de trabajo realizadas por el Ejecutivo del Estado.\n9.1.2. Determinación y precisión de actividades.\nLa Secretaría de Educación Guerrero, llevará a cabo actividades que permitan cristalizar los objetivos del Programa, entre las cuales se precisan las siguientes:\na) Difundir las actividades de Contraloría Social en programas sociales que se implementarán a través de los Comités de Padres de Familia con el apoyo de la Secretaría de Contraloría y Transparencia\nGubernamental;\nb) Capturar las solicitudes para integrar la demanda ciudadana;\nc) Supervisar por parte (SIC) la Secretaría de Educación Guerrero, la entrega de los uniformes, en los almacenes de la Secretaría de Educación Guerrero.\nd) Realizar el seguimiento y evaluación del Programa Guerrero Nos Necesita Con Uniformes\n(Secundaria); y\ne) Realizar las comisiones oficiales e institucionales.\n9.1.3. Tiempo y calendario de actividades.\nMESES\nACTIVIDADES\nENE FEB MAR ABR MAY JUN JUL AGO SEP OCT NOV DIC\nDifusión de Contraloría\nSocial).\nRecepción de solicitudes\nCaptura de solicitudes.\nRevisión e integración de expedientes.\nAutorización del apoyo.\nCaptura de padrón de beneficiarias\nSupervisiones en almacenes\nComisiones oficiales.\nEntrega\nSeguimiento y evaluación.\n9.1.4 Patrimonio del Programa.\nEn el Decreto número 426 del Presupuesto de Egresos del Estado de Guerrero para el Ejercicio\nFiscal 2017, se le asignó al Programa Guerrero Nos Necesita Con Uniformes (Secundaria), un monto de\nOPERACIÓN\n$30,000,000.00 (Treinta Millones de Pesos 00/100 M.N.), en Inversión Estatal Directa, mismos que serán coordinados a través de la Secretaría de Educación Guerrero.\n9.1.5 Información del Programa.\nLa Secretaría de Educación Guerrero, promoverá el Programa a través de los medios informativos tales como periódicos, carteles, trípticos, radio, televisión y páginas electrónicas oficiales del Gobierno del\nEstado.\n9.1.5 Exposición del Programa.\nLas Reglas de Operación del Programa Guerrero Nos Necesita Con Uniformes (Secundaria), se publican en el Periódico Oficial del Gobierno del Estado y están disponibles en la página oficial del Gobierno del Estado https://www.guerrero.gob.mx/\nPara cualquier información referente al Programa, se cuenta con un módulo de información en el lugar que ocupan las oficinas centrales (SIC) la Secretaría de Educación Guerrero ubicadas en: Av. de la\nJuventud S/N. Col. Burócratas Chilpancingo, Guerrero, Guerrero y con la línea telefónica 01 800 727 17\n17.\n9.2 Gastos de Operación\nLos gastos de operación serán de hasta el tres por ciento del presupuesto total asignado a este\nPrograma; dichos recursos económicos serán destinados a las diversas acciones asociadas con la planeación, operación, supervisión, seguimiento, contraloría social y evaluación o asesoría externa del\nPrograma, tal como lo señala el artículo 47 de la Ley de Coordinación Fiscal.\n10. TRANSPARENCIA\nPara garantizar la imparcialidad y transparencia en la entrega de apoyos a las y los beneficiarios seleccionados, el seguimiento detallado y auditado en la operación del Programa se llevará a cabo por programa que asigne la Secretaría de Educación Guerrero.\nPública del Estado de Guerrero, La Secretaría de Educación Guerrero, publicará periódicamente la\nPrograma Guerrero Nos Necesita Con Uniformes (Secundaria), se sustenta en la corresponsabilidad del Gobierno con sus dependencias. El Gobierno Estatal instrumentará el Programa presupuestal.\nOPERACIÓN\nLos datos personales que se recaben con motivo de la operación del presente Programa, serán protegidos y serán incorporados y tratados en el sistema de datos personales el cual se denomina: Sistema\nInformático Único de la Secretaría de Educación Guerrero, cuya finalidad es contar con un padrón de de los recursos que se otorgan a través del Programa, favoreciendo con ello conductas a favor de una cultura de integridad, legalidad, honestidad y rendición de cuentas.\n10.1 Difusión\nLa Secretaría de Educación Guerrero, a través del Programa Guerrero Nos Necesita Con\nUniformes (Secundaria), emitirá y publicará la convocatoria para el otorgamiento del apoyo a las y los solicitantes que demuestren estar inscritos en escuela Secundaria pública, en ella obligatoriamente se darán a conocer cuando menos el objetivo del Programa, los requisitos que deberán cumplir los aspirantes, la dirección de los módulos de información, número telefónico para pedir informes, la fecha de recepción de solicitudes y la fecha y forma de entrega de resultados, por conducto de los principales medios de difusión.\nLa información referente al Programa se podrá consultar de manera permanente en el portal oficial del Gobierno del Estado, así como el padrón de beneficiarios actualizado.\n10.2 Blindaje Electoral\nComo estrategia de blindaje electoral; la papelería, documentación oficial, así como la publicidad y promoción del Programa deberán incluir alguna de las siguientes leyendas:\n\"Este Programa es de carácter público, no es patrocinado ni promovido por partido político alguno y sus recursos provienen de los impuestos que pagan todos los contribuyentes\".\n\"Está prohibido el uso de este Programa con fines políticos, electorales, de lucro y otros distintos a los establecidos. Quién haga uso indebido de los recursos de este Programa deberá ser denunciado y sancionado de acuerdo con la ley aplicable y ante la autoridad competente\".\nEn cuanto a la publicidad en medios electrónicos, impresos, complementarios o de cualquier otra índole, vinculados con los programas de comunicación social, se deberá incluir la siguiente leyenda:\n\"Este Programa es público y queda prohibido su uso con fines partidistas o de promoción personal\".\n10.3 Supervisión y Control\nLa Secretaría de Educación Guerrero; en operación al Programa Guerrero Nos Necesita Con\nUniformes (Secundaria) y para la mejora de éste, integrará informes a través de la Coordinación de\nPrograma.\nEl control y la vigilancia del Programa Guerrero Nos Necesita Con Uniformes (Secundaria), se\nOPERACIÓN\nGeneral del programa que asigne la Secretaría de Educación Guerrero; quien será la encargada de validar los criterios de elegibilidad de los beneficiarios y dar seguimiento a las denuncias recibidas.\n10.4 Mecanismos de evaluación e indicadores\n10.4.1. Evaluación\nLa evaluación del Programa Guerrero Nos Necesita con Uniformes (Secundaria), se hará a través de la Coordinación de Seguimiento y Evaluación Social dependiente de la Coordinación General del\nPrograma que asigne la Secretaría de Educación Guerrero, quien evaluará cuantitativamente los resultados de acuerdo al número de beneficiarios y al porcentaje de cobertura, para conocer el cumplimiento de las metas propuestas; en tal sentido y una vez concluida la evaluación del Programa, se atenderá y dará seguimiento a los aspectos susceptibles de mejora.\nLa evaluación puede ser:\n1. Simultánea y al final del Programa. La evaluación que aplicará la Secretaría de Educación\nGuerrero, se llevará a cabo al final del programa, salvo indicaciones de su titular podrá ser simultánea.\n2. Cuantitativa y cualitativa. La Secretaría de Educación Guerrero, fungirá como la instancia administrativa y normativa del Programa Guerrero Nos Necesita Con Uniformes (Secundaria), en caso de requerirlo podrá contar con el apoyo de los organismos que considere importantes para el exitoso desarrollo de sus actividades.\n3. Interna y externa. El Programa Guerrero Nos Necesita Con Uniformes (Secundaria), estará sujeto a procesos periódicos de seguimiento y evaluación que permitan ajustar su ejecución y garantizar que los mecanismos de funcionamiento y administración faciliten tanto la obtención de información como la evaluación de los beneficios económicos y sociales.\nLa Secretaría de Educación Guerrero, podrá realizar una evaluación de resultados de carácter externo del Programa sujeto a las reglas de operación, para lo cual tendrá la facultad de designar a la instancia que realizará dicho análisis.\nContraloría y Transparencia Gubernamental.\n10.4.2. Indicadores número de beneficiarios que recibieron el apoyo. Dichos indicadores se encuentran en construcción.\nLa Secretaría de Educación Guerrero, será responsable de compilar e integrar un reporte estatal\nUniformes (Secundaria) que indiquen el número de beneficiarias y beneficiarios atendidos al finalizar el\nEjercicio Fiscal.\nOPERACIÓN\n10.5 Auditoria\nEn caso de ser necesario, el recurso asignado a éste Programa, será verificado por la Secretaría de Contraloría y Transparencia Gubernamental, como resultado de las acciones de auditoría que se lleven a cabo, la instancia auditora mantendrá un seguimiento interno que le permita emitir informes de las revisiones efectuadas.\n10.6 Recursos no devengados\nLos recursos que al cierre del ejercicio no se hayan ejercido, deberán ser reintegrados a más tardar el 31 de diciembre del presente ejercicio, (SIC) la Secretaría de Educación Guerrero, quien a su vez depositará a la Secretaría de Finanzas y Administración del Gobierno del Estado de Guerrero.\n10.7 Contraloría Social\nSe propiciará la participación de las y los beneficiarios del Programa a través de la integración y operación de los Comités de Contraloría Social, existirá un Comité por cada escuela beneficiada, para el seguimiento, supervisión y vigilancia en el cumplimiento de entrega de apoyos a las y los beneficiados de su escuela.\nLos Comités de Padres de Familias de cada escuela fungirán como Comités de Contraloría Social debido a que las y los beneficiarios directos son menores de edad.\nLos medios que se utilizarán para la propagación y divulgación de los beneficios del Programa, como acción de contraloría social serán los siguientes:\n• Auditivos.- Radio;\n• Impresos y escritos.- Diarios, trípticos;\n• Audiovisuales.- Televisión;\n• Multimedia.- Internet y televisión digital;\n• Telecomunicación.- Teléfonos fijos y celulares; y\n• Grupales.- Reuniones informativas.\nLos integrantes del Comité, tendrán que levantar un informe que contendrá como mínimo los siguientes datos:\n• Nombre del Programa;\n• Nombre de la Escuela;\n• Cantidad de apoyos otorgados;\n• Número de alumnos que recibieron el apoyo;\n• Número de alumnos que no recibieron el apoyo;\n• Fecha de entrega de apoyos; y\n• Observaciones.\nOPERACIÓN\n(SIC) la Secretaria de Educación Guerrero, ubicada en: Av. de la Juventud S/N. Col. Burócratas\nChilpancingo, Guerrero.\n10.8 Procedimiento de Queja o Inconformidad Ciudadana\nLos solicitantes así como los beneficiarios (a través de sus padres o tutores) pueden acudir en cualquier momento a las oficinas centrales (SIC) la Secretaría de Educación Guerrero, ubicada en: Av. de la Juventud S/N. Col. Burócratas Chilpancingo, Guerrero Así (SIC) como en la líneas telefónica 01 800 727\n17 17 y el correo electrónico segcontacto@seg.gob.mx para expresar sus comentarios sobre la implementación y funcionamiento del Programa, así como las quejas y denuncias sobre cualquier hecho, acto u omisión que produzca o pueda producir daños al ejercicio de sus derechos establecidos en las presentes Reglas de Operación.\nLas quejas y denuncias de la ciudadanía en general por la presunción de actos de corrupción o desvío de recursos por parte de servidores públicos la Secretaría de Educación Guerrero, se captarán en la Secretaría de Contraloría y Transparencia Gubernamental ubicada en Boulevard René Juárez Cisneros\nNo. 62 Cd. de los Servicios, C.P. 39074 Palacio de Gobierno número telefónico 01 800 727 17 17. Los medios por los cuales podrán presentarse quejas y denuncias ciudadanas son las siguientes:\na) Por escrito;\nb) Por comparecencia del interesado;\nc) Por correo electrónico; y\nd) Vía telefónica.\nEl denúnciate o quejoso deberá proporcionar los datos siguientes:\na) Nombre del servidor(es) Público(s);\nb) Dependencia de adscripción;\nc) Objeto de la denuncia;\nd) Nombre y domicilio del quejoso; y\ne) Identificación oficial.\n10.9 Mecanismos de exigibilidad mismos pueden ocurrir en al menos los siguientes casos:\n•Cuando una persona solicitante cumpla con los requisitos y criterios de inclusión para acceder a determinado derecho.\n• Cuando la persona solicitante exija que se cumpla con dicho derecho de manera integral en tiempo y forma.\nOPERACIÓN\n• Cuando no se pueda satisfacer toda la demanda de incorporación al programa por restricción presupuestal. atenderá las denuncias de violación e incumplimiento de derechos en materia de Desarrollo Social.\n10.10 Acta de Entrega-Recepción\nLa instancia ejecutora conformará y resguardará el expediente de las conciliaciones de inventarios, dada la naturaleza del apoyo otorgado, en apego al control del gasto público.\n11. CRITERIOS DE SELECCIÓN Y ELEGIBILIDAD\nPara tener acceso a los apoyos del Programa Guerrero Nos Necesita Con Uniformes (Secundaria), las niñas y niños solicitantes deberán estar inscritos en una escuela pública de nivel básico en educación\nSecundaria de la entidad, comprobándolo a través de la constancia de inscripción vigente.\nEl Programa se plantea bajo el principio de la universalidad, por lo que todo estudiante que cumpla con los criterios de selección establecidos en las presentes Reglas de Operación, podrá ser beneficiaria o beneficiario del Programa siempre y cuando pertenezcan a una escuela con reconocimiento oficial de la\nSecretaría de Educación Guerrero.\n11.1 Método de selección de beneficiarios.\nCuando la o el solicitante ha culminado exitosamente su proceso de registro en el Programa y se cuenta con el expediente físico completo, éste se captura y digitaliza en el Sistema de Información (SIC) la\nSecretaría de Educación Guerrero, que permite conformar la Base de Datos de Solicitantes y se procede de la manera siguiente:\na) Validación. Se hace una validación al expediente de la alumna o alumno en lo que respecta a los datos proporcionados a fin de determinar si cumple con los criterios generales y las disposiciones específicas establecidas en las presentes Reglas de Operación, de ser así pasa a la siguiente etapa de lo contrario se desecha esa solicitud;\nb) Confrontación. Con la finalidad de verificar que la escuela Secundaria a la que pertenecen las y los solicitantes cuente con reconocimiento oficial de la Secretaría de Educación Guerrero (SEG) se\nEducación Guerrero.\nSi la escuela solicitante no tiene reconocimiento oficial, automáticamente quedan sus alumnos y alumnas fuera del proceso de selección, por incumplir con lo establecido en las presentes Reglas de\nOperación.\nOPERACIÓN\nLos seleccionados para recibir el apoyo, quedan sujetos a la disponibilidad presupuestal del\nPrograma.\n12. MECÁNICA DE OPERACIÓN\n12.1 Instancia Ejecutora\nLa instancia ejecutora del Programa Guerrero Nos Necesita con Uniformes (Primaria), es la\nSecretaría de Educación Guerrero, sin embargo esta dependencia podrá mediante convenio asignar a otra\nDependencia del Gobierno Estatal en materia de Asistencia Social, para ejecutar el Programa con estricto apego a las presentes Reglas de Operación.\n12.2 Instancia Administrativa y Normativas\nLa Secretaría de Educación Guerrero, fungirá como la instancia administrativa y/o normativa del\nPrograma Guerrero Nos Necesita con Uniformes (Secundaria) en caso de requerirlo podrá contar con el apoyo de los organismos que considere importantes para el exitoso desarrollo de sus actividades.\n12.3 Delimitación de atribuciones\nCARGO AREA FUNCIONES\n1. Gestionar los recursos económicos para la ejecución del Programa.\n2. Autorizar las tareas operativas para del Programa.\nCoordinación General 3. Coordinar las estrategias para la correcta ejecución del Programa.\n1. Planificar el Programa de Verificación del otorgamiento de\nUniformes Escolares a Beneficiarios del Programa.\n2. Planificar el Programa de Evaluación de Resultados.\n3. Autorizar en coordinación con la Coordinación Operativa y la\nCoordinación de Seguimiento y Evaluación Social\nCoordinación General, el apoyo a beneficiarios del Programa.\n4. Solicitar a la Dirección Operativa la terminación del apoyo a beneficiarios por criterios de validación o por denuncias comprobadas.\n1. Organizar, dirigir y controlar la operación de los programas sociales a cargo de la Coordinación General, así como los tiempos y modos de áreas administrativas correspondientes.\n2. Propiciar el cumplimiento de las metas, acciones y objetivos de los programas y proyectos ejecutados por la Coordinación General.\nCoordinación Operativa\n3. Fomentar el aumento de la productividad, eficacia y eficiencia de los\nCoordinación General.\nOPERACIÓN\n1. Diseñar las acciones de contraloría social que han de ejecutarse a la par con el Programa, bajo la autorización del Coordinador General.\n2. Elaborar los lineamientos de los Comités de Contraloría Social.\n3. Diseñar y aplicar las acciones y mecanismos que aseguren una cobertura estatal de inscripción de candidatos a los beneficios de los programas sociales ejecutados por la Coordinación General.\nCoordinadores Regionales 4. Efectuar las actividades de trabajo de campo en coordinación con las demás áreas administrativas de la Coordinación General y las necesidades de la misma;\n5. Definir estrategias de logística que permitan el correcto desarrollo de las actividades que realice la Coordinación General en los 81 municipios de la entidad.\n1. Elaborarlas reglas de operación del Programa.\n2. Elaborar los Contratos de Coordinación que se requieran para la\nDepartamento de Seguimiento ejecución del Programa y Control 3. Atender las denuncias ciudadanas que le sean turnadas.\n1. Validar el padrón de beneficiarios para reportar a los que no cumplen con los criterios de selección y elegibilidad de las Reglas de\nOperación del Programa.\nDepartamento de Evaluación y 2. Elaborar los avances físicos financieros del Programa.\nEstadísticas 3. Subir información relevante al portal de la dependencia.\n4. Responder solicitudes de información del Sistema Info-Gro.\n13. DERECHOS, OBLIGACIONES Y SANCIONES DE LOS BENEFICIARIOS DE LOS\nPROGRAMAS SOCIALES\n13.1 Derechos\nLas alumnas y alumnos beneficiarios recibirán (a través de sus padres o tutores) por parte de la dependencia:\na) La información necesaria, de manera clara y oportuna, para participar en el Programa;\nb) La relación de escuelas y matricula beneficiada que se publicará en la página oficial del\nc) La mochila escolar integra, en buenas condiciones de acuerdo al grado escolar y sexo, en forma gratuita y en su centro escolar, una vez que haya cumplido con los requisitos establecidos en estas Reglas de Operación;\nd) Un trato digno, respetuoso, oportuno y equitativo;\ne) Atención sin costo alguno; y\nf) La reserva y privacidad de su información personal.\n13.2 Obligaciones\nLas alumnas y alumnos beneficiarios deberán (a través de sus padres o tutores):\nOPERACIÓN\na) Acudir puntualmente a los lugares en la fecha y hora señalada a recibir su mochila escolar;\nb) Informar al Secretaría de Educación Guerrero aquellos casos en los que no reciba su apoyo oportuno y total;\nc) Dar uso adecuado a la mochila escolar que reciban, para lo cual, los directores de las escuelas promoverán el cumplimiento de esta obligación; y\nd) Participar en las acciones de contraloría social para la vigilancia del cumplimiento y en el otorgamiento del Programa, por ser menores de edad serán representados por sus padres o tutores.\n13.3 Sanciones\nSe suspenderán definitivamente los apoyos correspondientes al Programa Guerrero Nos Necesita con Uniformes (Secundaria), a los beneficiarios que:\na) No cumplan con alguna de las obligaciones estipuladas en las Reglas de Operación;\nb) Presentar documentación falsa, y\nc) En el caso de que la dependencia o algún órgano de fiscalización detecte alguna anomalía;\n14. INTERPRETACIÓN\nLa interpretación de las presentes Reglas de Operación, para efectos administrativos, estarán a cargo (SIC) la Secretaría de Educación Guerrero.\n15. GLOSARIO DE TÉRMINOS.\nApoyo. Será en especie o vale, para una mochila escolar, integrado de acuerdo al nivel educativo, sexo, grado escolar y talla con características convenientes de criterios socioculturales y ambientales.\nBeneficiaria/o. Alumna o alumno legalmente inscrito en escuela pública de nivel Secundaria con reconocimiento oficial de la Secretaría Educación Guerrero.\nPrograma. Programa Guerrero Nos Necesita Con Uniformes (Secundaria).\nReglas de Operación. Conjunto de disposiciones que precisan la forma de operar un programa.\nSEG. Secretaría de Educación Guerrero.\nSolicitante. Persona, que de manera formal y siguiendo el procedimiento establecido en las reglas de operación, solicita ser beneficiaria del Programa Guerrero Nos Necesita Con Uniformes (Secundaria).\nPrimero. El presente Acuerdo entrará en vigor al día siguiente de su publicación en el Periódico\nOPERACIÓN\nSegundo. A partir de la entrada en vigor de las presentes Reglas de Operación del Programa\nGuerrero Nos Necesita Con Uniformes (Secundaria), la Secretaría de Educación Guerrero, será\nTercero. En un plazo de sesenta días, se emitirán los Lineamientos de los Comités de Contraloría\nSocial, que existirá un comité por cada escuela de educación Secundaria de la entidad integrado por los\nComités de Padres de Familia.\nDado en la Oficina del titular del Poder Ejecutivo, ubicada en el Edificio Centro de Palacio de\nGobierno, Boulevard René Juárez Cisneros No. 62 Ciudad de los Servicios en la Ciudad de Chilpancingo de los Bravo, Capital del Estado de Guerrero, a los treinta y un días del mes de enero de dos mil diecisiete.\nGOBERNADOR CONSTITUCIONAL DEL ESTADO DE GUERRERO.\nLIC. HÉCTOR ANTONIO ASTUDILLO FLORES.\nRúbrica.\nSECRETARIO GENERAL DE GOBIERNO.\nLIC. FLORENCIO SALAZAR ADAME.\nRúbrica.\nSECRETARIO DE EDUCACIÓN GUERRERO.\nLIC. JOSÉ LUIS GONZÁLEZ DE LA VEGA OTERO.\nRúbrica.",
  "ordenamiento": "PROGRAMA",
  "jurisdiccion": "GUERRERO",
  "fuente_oficial": "DIARIO OFICIAL DE LA FEDERACION",
  "Fecha de Publicación": "31 de Marzo de 2017",
  "ULTIMA REFORMA PUBLICADA": null,
  "status": "VIGENTE",
  "es_escaneado": false,
  "tiene_tablas": true,
  "materia": [
    "general"
  ]
}