{
  "titulo": "Acuerdo por el Que Se Crea el Programa Pensión para el Bienestar de Guerrero y Se Emiten Sus Reglas",
  "Contenido": "TEXTO ORIGINAL.\nACUERDO POR EL QUE SE CREA EL PROGRAMA PENSIÓN PARA EL BIENESTAR DE GUERRERO\nY SE EMITEN SUS REGLAS DE OPERACIÓN.\nGuerrero.- Poder Ejecutivo.\nMAESTRA EVELYN CECIA SALGADO PINEDA, GOBERNADORA CONSTITUCIONAL DEL\nESTADO DE GUERRERO, CON FUNDAMENTO EN LO DISPUESTO POR LOS ARTÍCULOS 71, 87, 88\nEJERCICIO DE LAS FACULTADES QUE ME CONFIEREN LOS ARTÍCULOS 1, 2, 4, 8, 9, 16, 22\nAPARTADO A FRACCIÓN I, 23 FRACCIÓN III Y 46 DE LA LEY ORGÁNICA DE LA ADMINISTRACIÓN\nPÚBLICA DEL ESTADO DE GUERRERO NÚMERO 242; 1, 2 FRACCIÓN I, 18 Y 25 DE LA LEY NÚMERO\n454 DE PRESUPUESTO Y DISCIPLINA FISCAL DEL ESTADO DE GUERRERO; 2, 3 FRACCIONES I Y\nIII, 15, 37, 38, 50 FRACCIÓN XII, 51, 53 FRACCIONES I, V, VII, VIII Y IX, 59, 60, 71 Y 73 FRACCIÓN VI\nDE LA LEY NÚMERO 375 DE LOS DERECHOS DE LAS PERSONAS ADULTAS MAYORES DEL\nESTADO DE GUERRERO; EN RELACIÓN CON EL ARTÍCULO 47 Y ANEXO 23-A (P25) DEL DECRETO\nNÚMERO 680 RELATIVO AL PRESUPUESTO DE EGRESOS DEL ESTADO DE GUERRERO PARA EL\nEJERCICIO FISCAL 2024, Y LOS LINEAMIENTOS PARA LA ELABORACIÓN DE LAS REGLAS DE\nOPERACIÓN DE LOS PROGRAMAS SOCIALES ESTATALES PARA EL PERIODO 2022-2027.\nQue el Plan Estatal de Desarrollo 2022-2027, Eje 1. Bienestar, Desarrollo Humano y Justicia\nSocial, Objetivo 1.3. Disminuir las desigualdades a través de la atención a grupos vulnerables; a la\nEstrategia 1.3.2. Atención prioritaria a grupos vulnerables con la Línea de acción 1.3.2.5. Mejorar el nivel de bienestar y envejecimiento digno de los Adultos Mayores de 63 a 64 años 11 meses a través de apoyos y acciones orientadas a satisfacer sus necesidades básicas.\nQue en la Agenda 2030 para el Desarrollo Sostenible se alinea en el Objetivo 1. “Fin a la pobreza” en su meta 1.1. “Erradicar para todas las personas y en todo el mundo la pobreza extrema. Se considera que sufren pobreza extrema las personas que viven con menos de 1,25 dólares al día” con el indicador\n1.1.1. Proporción de la población que vive por debajo del umbral internacional de la pobreza, desglosada por sexo, edad, situación laboral y ubicación geográfica (urbana o rural).\nQue es responsabilidad de la administración pública estatal, que la planeación y aplicación de las políticas públicas se adecúen a los principios, objetivos y programas, así como a los compromisos internacionales adquiridos por el gobierno mexicano, con respecto a los derechos de las Personas Adultas\nMayores.\nQue uno de los compromisos de la titular del ejecutivo estatal con la ciudadanía guerrerense, al asumir y tomar protesta como Gobernadora Constitucional del Estado es, lograr un Guerrero de tranquilidad, de paz y de justicia, que permitan consolidar el crecimiento económico y estabilidad social de las Personas Adultas Mayores de nuestro estado.\nQue el artículo 47 del Decreto Número 680 relativo al Presupuesto de Egresos del Estado de\nGuerrero para el Ejercicio Fiscal 2024, establece que, con el objeto de asegurar la aplicación eficiente, eficaz, oportuna, equitativa y transparente de los recursos públicos, la Secretaría de Finanzas y\nAdministración y la Secretaría de Planeación y Desarrollo Regional, emitirán las disposiciones a que deberán sujetarse los programas de inversión sujetos a reglas de operación.\nQue la Secretaría de Planeación y Desarrollo Regional, los lineamientos para la Elaboración de las Reglas de Operación de los Programas Sociales del Estado para el periodo 2022-2027, publicados en el Periódico Oficial del Estado No. 14 de fecha 18 de febrero de 2022, los cuales tienen la finalidad de ofrecer a las secretarías, dependencias y entidades paraestatales del gobierno del estado, un instrumento técnico que guie la elaboración de los apartados centrales de las Reglas de Operación, así como los elementos para integrar su contenido.\nQue la Ley Número 375 de los Derechos de las Personas Adultas Mayores del Estado de Guerrero, en el artículo 37, se fundamenta la creación del Instituto Guerrerense para la Atención Integral de las\nPersonas Adultas Mayores IGATIPAM, como Organismo Público Descentralizado de la Administración\nPública Estatal, con personalidad jurídica y patrimonio propio y autonomía técnica de gestión para el cumplimiento de sus atribuciones, objetivos y fines, con domicilio en la ciudad de Chilpancingo de los Bravo, Guerrero, en su artículo 38 del mismo ordenamiento jurídico, refiere que el IGATIPAM es rector responsable de la formulación, desarrollo, ejecución, evaluación y vigilancia de la política pública estatal de las personas adultas mayores, que forma parte prioritaria de la política para el Desarrollo Social, cuyo objeto es coordinar, promover, apoyar, vigilar y evaluar las acciones públicas, estrategias y programas que se deriven de ella, y será el enlace con los Organismos Nacionales y Municipales afines en la materia.\nDe acuerdo al Decreto Número 680 relativo al Presupuesto de Egresos para el Ejercicio Fiscal\n2024, el Programa Pensión para el Bienestar de Guerrero, operará en dos componentes, en forma de pensión y su vertiente envejecimiento digno con un apoyo único.\nQue el Programa Pensión para el Bienestar de Guerrero, está orientado a otorgar un apoyo económico a manera de pensión, para atender a las personas adultas mayores en situación de vulnerabilidad que surge por la reducción del ingreso al final de la vida productiva, y con la dependencia como resultado de las enfermedades crónicas, la discapacidad y reducción de la funcionalidad, por lo que crecimiento, de ahí que se establecen para su ejecución reglas de operación, mismas que especifican los criterios para acceder a los beneficios de este programa, acordes a lo establecido en la Ley Número 375 de los Derechos de las Personas Adultas Mayores del Estado de Guerrero.\nQue en cumplimiento a lo dispuesto por el artículo 50 fracción XII de la Ley Número 375 de los\nDerechos de las Personas Adultas Mayores del Estado de Guerrero, el Consejo Directivo del Instituto\nGuerrerense para la Atención Integral de las Personas Adultas Mayores, como máximo órgano de gobierno, aprobó las Reglas de Operación del Programa Pensión para el Bienestar de Guerrero.\nPor lo anteriormente expuesto y con fundamento en las disposiciones legales antes citadas, he tenido a bien expedir el siguiente:\nACUERDO POR EL QUE SE CREA EL PROGRAMA PENSIÓN PARA EL BIENESTAR DE GUERRERO\nY SE EMITEN SUS REGLAS DE OPERACIÓN.\nArtículo 1. Se crea el Programa Pensión para el Bienestar de Guerrero, el cual tiene como objetivo mejorar la calidad de vida de las personas adultas mayores que radiquen dentro del territorio guerrerense, mediante el otorgamiento de un apoyo económico.\nArtículo 2. El Instituto Guerrerense para la Atención Integral de las Personas Adultas Mayores tendrá a cargo la implementación, ejecución, evaluación y administración del Programa Pensión para el\nBienestar de Guerrero, bajo los criterios de objetividad, equidad, transparencia, publicidad, selectividad y temporalidad, con estricto apego a la normatividad aplicable, por lo tanto, será el encargado de la asignación de los recursos del Programa apegándose plenamente a las Reglas de Operación.\nArtículo 3. Se emiten las Reglas de Operación del Programa Pensión para el Bienestar de\nGuerrero, en las cuales se establece el procedimiento de ejecución del Programa, los principios y requisitos que se deben observar para acceder al mismo en los términos siguientes:\nREGLAS DE OPERACIÓN DEL PROGRAMA PENSIÓN PARA EL BIENESTAR DE\nGUERRERO.\n1. Introducción.\n1.1. Antecedentes.\nEn 1982 se realizó la Primera Asamblea Mundial sobre el Envejecimiento, convocada y organizada por la Organización de las Naciones Unidas (ONU), resultado de esta Asamblea fue la elaboración del Plan de Viena, mismo que concentra las recomendaciones que emanaron de los países reunidos y constituyó marca el futuro del mundo.\nEn México, 20 años después entró en vigor la Ley Federal de los Derechos de las Personas\nAdultas Mayores, entre sus alcances está el dar impulso a las acciones desde el estado y la sociedad, para promover el desarrollo integral de esta población. En el marco de esta Ley es que se establece el Programa\nPensión para el Bienestar de Guerrero, consistente en otorgar un apoyo económico a las personas adultas mayores en situación de vulnerabilidad, desempleadas, que no cuenten con seguridad social y radiquen en territorio guerrerense adicionalmente, y para coadyuvar a una mejor calidad de vida se implementan las vertientes de Envejecimiento Digno y pago de marcha, incluidos en el Programa Sectorial Desarrollo y\nAsistencia Social Capítulo IV, Programas y Proyectos a Desarrollar 2016-2021 y responsables de su ejecución, con la visión de mejorar el bienestar productivo, económico, emocional y mejora por ende de la calidad de vida de las personas adultas mayores del estado de Guerrero.\nLa Ley Número 375 de los Derechos de las Personas Adultas Mayores del Estado de Guerrero, fundamenta la creación del Instituto Guerrerense para la Atención Integral de las Personas Adultas Mayores e instituye el Programa Pensión Guerrero; respectivamente, como ente responsable de la formulación, desarrollo y ejecución de la política pública estatal de las personas adultas mayores.\nEl Programa Pensión Guerrero, inicia en el año 2003 con un presupuesto de 20 millones de pesos en las 5 ciudades más grandes del estado: Acapulco de Juárez, Chilpancingo de los Bravo, Iguala de la\nIndependencia, Taxco de Alarcón y Zihuatanejo de Azueta; en 2005 se extendió a 77 municipios y de 2006 a 2011 se incluyeron todos los municipios con un monto de 245 Millones de Pesos atendiendo a 50,020 beneficiarias y beneficiarios en todo el estado de Guerrero. A partir del 2012 el presupuesto ha venido reduciéndose considerablemente hasta el año 2022 con 24 Millones de Pesos. Hasta que en el año 2023 se inicia con un incremento en el presupuesto de 4 Millones más para quedar en 28 Millones de Pesos, En el año 2024 el presupuesto incrementa 2 Millones Ochocientos Mil Pesos, dando un total de 30 Millones\n800 Mil Pesos y para el año 2025 el presupuesto no sufre modificación alguna y se autorizan 30 Millones\n800 Mil Pesos, mismos que serán ejercidos en apoyos que serán otorgados en el Programa Pensión para el Bienestar de Guerrero. (REFORMADO, P.O. 23 ALCANCE XII, 21 DE MARZO DE 2025)\nLos apoyos históricamente fueron otorgados a partir de los 65 años de edad, posteriormente, a partir de los 63 años y hasta los 64 años con 11 meses de edad, hasta el ejercicio próximo pasado, en razón de que la estrategia del gobierno federal que a través de la Secretaría del Bienestar apoya de manera universal a mujeres y hombres mayores de 65 años en todo el país.\n2. Alineación Programática al PED y/o PND.\nEl Programa Pensión para el Bienestar de Guerrero, se alinea al Plan Nacional de Desarrollo 20192024 en el Eje II Política Social, apartado Programas: 1. El Programa para el Bienestar de las Personas\nAdultas Mayores que otorga un apoyo universal a mujeres y hombres de más de 65 años en todo el país.\nEn el Plan Estatal de Desarrollo 2022-2027, el Programa está, alineado al Eje 1 Bienestar, Desarrollo Humano y Justicia Social, Objetivo 1.3 Disminuir las desigualdades a través de la atención a grupos vulnerables; Estrategia 1.3.2 Atención prioritaria a grupos vulnerables con la Línea de acción 1.3.2.5\nMejorar el nivel de bienestar y envejecimiento digno de los Adultos Mayores de 63 a 64 años 11 meses a través de apoyos y acciones orientadas a satisfacer sus necesidades básicas. la Agenda 2030 para el Desarrollo Sostenible se alinea en el Objetivo 1 “Fin a la pobreza” en su meta 1.1 “Erradicar para todas las personas y en todo el mundo la pobreza extrema. Se considera que sufren pobreza extrema las personas que viven con menos de 1,25 dólares al día” con el indicador 1.1.1\nProporción de la población que vive por debajo del umbral internacional de la pobreza, desglosada por sexo, edad, situación laboral y ubicación geográfica (urbana o rural).\n2.1. Diagnóstico. biológico, psicológico y social. Cada persona sigue un proceso de envejecimiento particular que depende de las características innatas, empíricas y conocimientos adquiridos y de las circunstancias enfrentadas durante la vida. El método más utilizado para identificar a las personas adultas mayores es a través de grupos quinquenales de edad, para dicho propósito se han empleado las edades de 60, 65, 70 años y más, entre otras.\nExiste una tendencia nacional que nos muestra que desde hace 10 años se han reducido los índices de natalidad. En México, la esperanza de vida aumentó considerablemente; en 1930 las personas vivían en promedio 34 años; 40 años después en 1970 este indicador se ubicó en 61; en 2000 fue de 74 y en 2022 es de poco más de 75 años. Esto significa que año con año las personas mayores de 60 años estarán en constante aumento, y de ellas destaca un mayor porcentaje de mujeres. De acuerdo con proyecciones del CONAPO (02 de noviembre de 2023), para el año 2030, la esperanza de vida al nacimiento alcanzará los 76.7 años en promedio, para las mujeres será de 79.6 años y para los hombres de 73.8 años. Ello implica la necesidad de contar con los mecanismos que permitan una vida digna a las personas adultas mayores: salud, movilidad e ingresos, entre otros.\nDe manera particular en el estado de Guerrero sigue la misma tendencia con relación al aumento de esperanza de vida, pero con algunas particularidades: una mayor tasa de natalidad respecto al nivel nacional (el crecimiento de la natalidad apenas se ha detenido hace cinco años), y un mayor porcentaje de mujeres respecto a hombres entre los 50 a 60 años. Esto revela que en los siguientes años más personas se irán incorporando al rango de edad susceptible de recibir algún tipo de pensión.\nEl aumento de este grupo poblacional es un tema de mucha importancia para el Instituto\nGuerrerense para la Atención Integral de las Personas Adultas Mayores, principalmente por la vulnerabilidad que surge por la carencia de servicios para la atención integral de sus necesidades básicas, porque viven en condiciones precarias con una alta incidencia de enfermedades crónicas y dicha vulnerabilidad se agrava debido a que el sistema de pensiones deja fuera a un número importante de las personas adultas mayores quienes no cuentan con acceso a los beneficios que otorgan las instituciones de seguridad social. funcional de familiares o terceros, lo cual es un factor que les resta autonomía y podría generar una situación en la que las personas adultas mayores sean consideradas una carga para la familia, su autoestima disminuye provocando un acelerado deterioro en su salud. necesidades primarias de alimentación y vivienda; por lo que la solidaridad y protección entre los integrantes es esencial para alcanzar el bienestar físico y emocional de todos los que conforman el hogar.\nEn 2010 se identificaron 6.4 millones de hogares con al menos una persona mayor de los cuales\n4.5 millones albergaban a las personas adultas mayores sin pensión, ni jubilación. Los restantes 1.9 jubilación.\nEn este diagnóstico se considera el umbral de 60 a 64 años grupo quinquenal que en los últimos\n10 años se ha incrementado en un 30% en nuestro estado (Tabulados del INEGI Censo 2010 y 2020 población total por entidad federativa y grupo quinquenal de edad según sexo).\n2.1.1. Población Potencial.\nEn Guerrero, se presenta un incremento acelerado de la población adulta mayor que se encuentra en situación de vulnerabilidad y no cuenta con un ingreso económico a manera de pensión. Actualmente dentro del rango de 60 a 64 años existen 126,765 adultos mayores que no tienen beneficios con el gobierno\nFederal, ni con el gobierno estatal, especialmente aquellas que se encuentran fuera de los esquemas institucionales de seguridad social, con poca o nula solvencia económica y la falta de garantías sociales y laborales.\n2.1.2. Población Objetivo.\nEn nuestro estado de Guerrero existen 47,198 personas adultas mayores dentro del rango de 63 a 64 años con 11 meses de edad, que representa el 37.23% de la población potencial.\n2.1.3. Población Beneficiaria.\nEl Programa con una cobertura estatal, beneficiará a 2,000 personas adultas mayores de 63 a 64 años con 11 meses de edad que representa el 5% de la población objetivo, se atenderá a las personas que se encuentran en situación de vulnerabilidad, radiquen dentro del territorio guerrerense y que cumplan los requisitos previstos en el numeral 9.2 de las presentes Reglas de Operación.\n2.1.4. Población Indígena.\nEl Programa podrá beneficiar prioritariamente a 212 personas adultas mayores provenientes de cualquiera de los 25 municipios con población indígena y/o de los 10 municipios con presencia de población afromexicana que se encuentran en situación de vulnerabilidad, siempre y cuando radiquen dentro del territorio guerrerense y cumplan los requisitos previstos en el numeral 9.2, de las presentes Reglas de\nOperación.\n2.2. Fundamento Legal.\na) Constitución Política de los Estados Unidos Mexicanos.\nb) Ley General de Desarrollo Social.\nc) Ley de los Derechos de las Personas Adultas Mayores.\nd) Ley General para la Igualdad entre Mujeres y Hombres.\ne) Ley General de Acceso de las Mujeres a una Vida Libre de Violencia.\ng) Ley Orgánica de la Administración Pública del Estado de Guerrero Número 242.\nh) Ley Número 026 para el Bienestar del Estado de Guerrero; (REFORMADO, P.O. 23 ALCANCE XII,\n21 DE MARZO DE 2025)\ni) Ley Número 207 de Transparencia y Acceso a la Información Pública del Estado de Guerrero.\nj) Ley Número 375 de los Derechos de las Personas Adultas Mayores del Estado de Guerrero.\nk) Ley Número 454 de Presupuesto y Disciplina Fiscal del Estado de Guerrero.\nl) Ley Número 465 de Responsabilidades Administrativas para el Estado de Guerrero.\nm) Ley Número 466 de Protección de Datos Personales en Posesión de Sujetos Obligados del\nEstado de Guerrero.\nn) Ley Número 468 de Fiscalización Superior y Rendición de Cuentas del Estado de Guerrero. ñ) Ley Número 494 para la Igualdad entre Mujeres y Hombres del Estado de Guerrero.\no) Ley Número 553 de Acceso de las Mujeres a una Vida Libre de Violencia del Estado Libre y\nSoberano de Guerrero.\nq) Decreto Número 203 del Presupuesto de Egresos del Estado de Guerrero para el Ejercicio\nFiscal 2025.\ns) Reglamento Interior del Organismo Público Descentralizado, Instituto Guerrerense para la\nAtención Integral de las Personas Adultas Mayores.\nu) Decreto Número 181 por el que se aprueba el Plan Estatal de Desarrollo 2022-2027.\nv) Acuerdo que establecen los Compromisos para la Estabilidad y Desarrollo del Estado de\nGuerrero.\nw) Decreto por el que se formula la declaratoria de las Zonas de Atención Prioritaria para el año\nx) Lineamientos para la Elaboración de las Reglas de Operación de los Programas Sociales\nEstatales para el Periodo 2022-2027\ny) Todas aquellas disposiciones normativas aplicables.\n2.3. Definiciones y Siglas.\nDefiniciones:\nBeneficiaria o Beneficiario: Persona Adulta Mayor que cumple con los requisitos de la normatividad correspondiente y que está dentro del padrón de beneficiarios del Programa Pensión para el\nBienestar de Guerrero.\nComité Técnico de Validación: Órgano que establece las normas que regulan la actuación, vigilancia, control, funcionamiento y que resuelve los casos no previstos en las Reglas de Operación del\nPrograma.\nComprobante de Domicilio: Documento con máximo tres meses de antigüedad, ya sea recibo de servicio de energía eléctrica, servicio de agua potable, recibo predial, recibo de telefonía fija.\nMatriz de Indicadores Para Resultados (MIR): Herramienta de planeación que en forma resumida, sencilla y armónica establece con claridad los objetivos e indicadores que miden dichos objetivos del Programa.\nPadrón de Personas Beneficiarias: Relación oficial de personas beneficiarias que incluye a las personas atendidas por el Programa y su vertiente envejecimiento digno, cuyo perfil socioeconómico cumple con la normatividad correspondiente.\nPago de Marcha: Apoyo económico que se entrega por única ocasión, a la persona designada para el fin, que la persona beneficiaria haya designado al momento de hacer su trámite de ingreso al\nPrograma, cuando ésta haya fallecido.\nPersonas Adultas Mayores: Personas de 60 años y más que radican en territorio guerrerense.\nPoblación Indígena: Aquellas que formen un pueblo originario o una unidad social, económica y cultural, asentadas en territorio guerrerense, y que reconocen autoridades propias de acuerdo con sus usos y costumbres.\nPrograma: Programa Pensión para el Bienestar de Guerrero.\nReglas de Operación: Conjunto de disposiciones que precisan la forma de operar un programa, con el propósito de transparentar y normar la distribución y entrega de los apoyos.\nSupervivencia: Presentación de la persona beneficiaria en los lugares y fechas que requiera el\nInstituto, para verificar que continúa con vida.\nSiglas:\nCONAC: Consejo Nacional de Armonización Contable.\nCURP: Clave Única de Registro de Población.\nIEPC: Instituto Electoral y de Participación Ciudadana del Estado de Guerrero.\nIGATIPAM: Instituto Guerrerense para la Atención Integral de las Personas Adultas Mayores.\nINAPAM: Instituto Nacional de las Personas Adultas Mayores. INEGI: Instituto Nacional de\nEstadística y Geografía.\nINE: Instituto Nacional Electoral.\nITAIGro: Instituto de Transparencia, Acceso a la Información y Protección de Datos Personales del Estado de Guerrero.\nSEFINA: Secretaría de Finanzas y Administración. SEPLADER: Secretaría de Planeación y\nDesarrollo Regional. SCyTG: Secretaría de Contraloría y Transparencia Gubernamental.\n3. Objetivos y Alcances.\n3.1. Objetivo General.\nEl Programa, tiene como objetivo contribuir a que las personas adultas mayores que radican en el estado de Guerrero reciban un apoyo económico a manera de pensión de forma bimestral, que les permita elevar su calidad de vida y les brinde seguridad social.\n3.2. Objetivos Específicos.\n1. Otorgar apoyos económicos a las personas adultas mayores de 63 a 64 años con 11 meses de edad considerando los 85 municipios que conforman las 8 regiones de nuestro estado de Guerrero.\n2. Concientizar la corresponsabilidad entre los integrantes de la familia, conservando las relaciones personales y el trato directo con ella, aún en los casos de estar separados. Se podrán realizar visitas domiciliarias a fin de verificar las condiciones del entorno de la persona adulta mayor; lo anterior en coordinación con instituciones especializadas en la defensa de los derechos de las personas mayores.\n3. Mejorar la situación de la persona adulta mayor que se encuentre en riesgo o desamparo mediante el otorgamiento de un apoyo económico que coadyuve para su alimentación, salud, educación y mejoramiento de la vivienda.\n3.3. Cobertura.\nEl Programa opera a nivel estatal en los 85 municipios que lo integran en sus dos componentes, beneficiando a las personas adultas mayores de 63 a 64 años con 11 meses de edad, posibles personas beneficiarias de nuevo ingreso o que se reactiven por haber causado baja por algún motivo establecido en el numeral 12.2., del presente ordenamiento y de los beneficios adicionales previstos en las presentes\nReglas de Operación, mismos que estarán sujetos a la disponibilidad presupuestal del Programa, en la intención de ofrecer una atención integral.\n3.4. Alcances.\nSe beneficiará a 2,000 personas adultas mayores de 63 a 64 años con 11 meses de edad con el apoyo de pensión económica, considerando los 85 municipios que conforman a nuestro estado de\nGuerrero; con apoyos económicos del componente Envejecimiento Digno se beneficiará a 1,100 personas adultas mayores de 60 años o más, con un apoyo a su economía mismo que puede ser de manera continua; atendiendo a su derecho a la seguridad social. La forma más común de identificar la seguridad social es mediante las prestaciones y la asistencia médica, sin embargo, esas son solo algunas de las formas en las que se presenta en la vida cotidiana. En los hechos, la seguridad social también se encuentra en los actos solidarios e inclusivos de las personas hacia los demás, pues esos actos llevan en sí mismos la búsqueda del bienestar social.\n4. Metas Físicas.\nBeneficiarios Meta\nApoyos (Adulto anual Tipo\nMayor) (Apoyos)\nApoyo\nPensión para el Bienestar de Guerrero 2,000 12,000 económico\nEnvejecimiento Digno, consiste en otorgar subsidios:\nApoyo como apoyo a su economía. 1,100 6,600 económico\n5. Programación Presupuestal.\nEl origen de los recursos del Programa proviene de Inversión Estatal Directa (IED), contenidos en el Decreto Número 203 del Presupuesto de Egresos del Estado de Guerrero para el Ejercicio Fiscal 2025, No. 105 con fecha 31 de diciembre del 2024, el cual contempla un monto autorizado de $30'800,000.00\n(Treinta Millones Ochocientos Mil Pesos 00/100 M.N.). Dichos recursos estarán sujetos a la disponibilidad de los ingresos recaudados por la SEFINA por lo que la calendarización y metas pueden variar.\nCronograma Financiero.\nCronograma Financiero.\nFuente Acciones Total Ene Feb Mar Abr May\nInversión\nIED 30,800,000 0 5,253,000 0 5,253,0000 0 a ejercer\nTotal 30,800,000 0 5,253,000 0 5,253,000 0\n(REFORMADO, P.O. 23 ALCANCE XII, 21 DE MARZO DE 2025)\nJun Jul Ago Sep Oct Nov Dic\n5,253,000 0 5,253,000 0 5,253,000 0 4,535,000\n5,253,000 0 5,253,000 0 5,253,000 0 4,535,000\n(REFORMADO, P.O. 23 ALCANCE XII, 21 DE MARZO DE 2025)\n5.1. Gastos de Operación.\nAcorde al artículo 47 fracción I de la Ley de la Coordinación Fiscal, se aplicará hasta un 3% para gastos de operación que serán liberados por la SEFINA, mismos que serán destinados a las diversas acciones asociadas con la planeación, operación, supervisión, verificación, seguimiento, evaluación, dichas erogaciones serán congruentes con las partidas presupuestales dispuestas en el Clasificador por Objeto del Gasto para la Administración Pública Estatal en vigor, principalmente para materiales, suministros y servicios, estudios e investigación, contratación de personas instructoras, y promotoras entre otros servicios y acciones que coadyuven a la operación y cumplimiento de las metas del Programa. Observando en todo momento los criterios de racionalidad y austeridad presupuestal; propiciando la eficiencia, eficacia y transparencia en el ejercicio de los recursos.\nPara desarrollar las actividades operativas, para las personas beneficiarias en los municipios del estado, el IGATIPAM podrá contratar personas promotoras, bajo la figura de prestadora de servicios independientes, inscritos en el SAT, la Dirección de Asistencia Social será quien asignará las tareas específicas y realizará reportes periódicos, en los cuales adjuntará el expediente para su pago correspondiente.\nLas personas promotoras para su contratación, deberán cumplir con los requisitos siguientes:\na) Solicitud de empleo elaborada.\nb) Original y copia para cotejo de identificación oficial (INE, Pasaporte, INAPAM).\nc) Copia de la Clave Única de Registro de Población (CURP).\nd) Original y copia para cotejo del Acta de Nacimiento.\ne) Original y copia para cotejo del comprobante de domicilio de fecha reciente.\nf) Curriculum vitae.\ng) Fotografía tamaño infantil.\nh) Datos de cuenta bancaria para transferencia electrónica y/o depósito.\ni) Constancia de Situación Fiscal expedida por el SAT.\n6. Criterios y Requisitos de Elegibilidad.\na). Se consideran elegibles para apoyo económico (Pensión) las personas adultas mayores de 63 a 64 años 11 meses, que cubran los requisitos establecidos en el numeral 9.2 y de acuerdo con la disponibilidad presupuestal con la que cuente el programa.\nb). Se consideran elegibles para Envejecimiento Digno las personas adultas mayores de 60 años o más, que cubran los requisitos establecidos en el numeral 9.2 y de acuerdo con la disponibilidad presupuestal con la que cuente el Programa.\n7. Tipo, Monto y Periodicidad del Apoyo.\nTipo Monto Periodicidad\nEconómico (Pensión). 2,000.00 Bimestral\nEconómico (Envejecimiento Digno). 1,000.00 Bimestral\n7.1. Características de los Apoyos.\nEl apoyo económico (Pensión). Se entregará mediante transferencia electrónica de forma bimestral a las personas adultas mayores de 63 a 64 años con 11 meses de edad, a las personas acuerdo a los requisitos del numeral 9.2.\nEl componente de Envejecimiento Digno el apoyo económico, podrá ser en forma electrónica (en tarjeta bancaria) o en efectivo, con esta vertiente se mejorará la atención a las necesidades básicas de las personas adultas mayores.\nPara cubrir el pago de marcha, el apoyo económico se dispondrá en la tarjeta bancaria asignada a la persona beneficiaria fallecida.\nAlgunos serán proporcionados en una sola ocasión, otros permanentes y dependerán de los nuevos lineamientos y disponibilidad presupuestal del Programa.\n7.2. Recursos no Devengados.\nEl IGATIPAM, podrá reintegrar los recursos que al cierre del ejercicio no se hayan ejercido a más tardar el 31 de diciembre del presente ejercicio fiscal a la SEFINA para su correspondiente comprobación y registro contable.\n7.3. Resguardo de la documentación.\nEl resguardo de la documentación comprobatoria de los recursos ejercidos del Programa estará a cargo del Instituto Guerrerense para la Atención Integral de las Personas Adultas Mayores (IGATIPAM) y se informará al Comité de Validación del Programa las cifras ejecutadas y las no devengadas (si lo hubiera) al cierre del ejercicio.\n7.4. Supervisión y Control.\nCon el propósito de mejorar la operación, supervisión y control del Programa, el IGATIPAM, remitirá de forma trimestral a la SEPLADER, SEFINA, y a la SCyTG, los informes de los recursos ejercidos de acuerdo al Consejo Nacional de Armonización Contable (CONAC) a más tardar a los 15 días de haber concluido el trimestre, de esta forma se llevará a cabo el seguimiento al ejercicio de recursos financieros, acciones ejecutadas, resultados, indicadores, metas alcanzadas y se verificará la congruencia de la información presentada en la Cuenta Pública.\n8. Criterios de Selección.\na) Se dará prioridad a la persona solicitante de acuerdo al grado de marginación del municipio en el que radique, tomando como referencia el Decreto por el que se formula la declaratoria de las Zonas de\nAtención Prioritaria para el año 2025. (REFORMADO, P.O. 23 ALCANCE XII, 21 DE MARZO DE 2025)\nb) Se dará prioridad a la persona solicitante cuando se demuestre que pertenece a un grupo de atención prioritaria y/o vive en situación de vulnerabilidad, riesgo o desamparo que le impide alcanzar mejores niveles de vida.\n8.1. Casos Especiales.\nPara resolver casos especiales no previstos, nuevos ingresos sugeridos por la presidenta o el presidente del Comité de Validación del Programa y/o sus personas integrantes, se plantearán en sesión ordinaria y/o extraordinaria según sea el caso, las cuales serán convocadas por el IGATIPAM en donde se expondrán las situaciones especiales para su respectiva solución, en casos de veda electoral se podrán adelantar la entrega de apoyos económicos o en especie a las personas beneficiarias del Programa.\n8.2. Casos de Emergencia o Desastre.\nCon el fin de evitar la interrupción de la operación del Programa, en caso de que exista una\nDeclaratoria de Emergencia o de Desastre, el IGATIPAM, podrá convocar a una reunión ordinaria y/o extraordinaria al Comité de Validación del Programa y/o sus personas integrantes para adelantar los desastre; así como, ayuda humanitaria para mitigar sus necesidades prioritarias por la emergencia social o desastre natural.\n8.3. Suspensión o Cancelación del Programa Social.\nEl IGATIPAM podrá suspender la operación del Programa, cuando no existan las condiciones sociales-económicas entre las partes, cuando una o algunas de las personas beneficiarias no acaten las disposiciones de estos lineamientos y otras señaladas por las personas ejecutoras que afecte la norma estatal o por problemas de gobernabilidad o en caso de que algún órgano de fiscalización detecte alguna irregularidad; como el caso de homonimia, duplicidad del beneficio, entre otros.\n8.4. Integración del Padrón de Personas Beneficiarias.\nLas personas beneficiarias incorporadas al programa formarán parte de un Padrón Único de\nPersonas Beneficiarias, el cual será de carácter público y estará conformado sin distinción alguna de raza, color, sexo, grupo de edad, discapacidad, estado civil, municipio, región, idioma, religión, opinión política, origen nacional o social, indígenas, afromexicanos, posición económica, nacimiento o cualquier otra condición social o de cualquier otra índole. Será de carácter público, siendo reservados sus datos personales de acuerdo con la Ley Número 207 de Transparencia y Acceso a la Información Pública del\nEstado de Guerrero, los cuales en ningún caso podrán emplearse para propósitos de proselitismo político, religioso o comercial, ni para ningún otro fin distinto al establecido en las presentes Reglas de Operación.\n9. Mecánica Operativa del Programa Social.\n9.1. Instancia Ejecutora y/o Responsable.\nEl IGATIPAM, será la instancia responsable de la planeación, coordinación, operación y ejecución ejercidos.\nLa SEFINA, liberará los recursos con oportunidad al IGATIPAM, incluido el 3% de gasto operativo de acuerdo al cronograma financiero autorizado y al calendario de entrega de apoyos.\nLa SEPLADER, SEFINA y la SCyTG, serán las instancias encargadas de dar seguimiento a los informes presentados.\n9.2. Proceso de Incorporación al Programa Social.\nEl acceso al Programa o al componente de Envejecimiento Digno, será a petición de la parte interesada, presentándose a realizar el trámite de solicitud de ingreso al Programa de manera personal, en las oficinas ubicadas en Calle Madero, número 22, Colonia Centro, Chilpancingo de los Bravo, Guerrero, C.P. 39000, con un horario de atención de 9:00 a 15:00 horas en días hábiles y/o presentándose con el enlace municipal designado por el IGATIPAM, en su municipio de origen; el instituto, informará incorporación al Programa, por vía telefónica a los números proporcionados por la persona peticionaria en su solicitud de ingreso.\nLa persona solicitante, podrá recibir información de los nombres y domicilios de los enlaces municipales, así como de los requisitos para el ingreso al Programa en el número telefónico (747) 47 1 42\n33.\nAtendiendo a la suficiencia presupuestal, dependiente de la recaudación del estado, el número de nuevas personas beneficiarias a ingresar al padrón de personas beneficiarias del Programa, dependerá del número de bajas resultantes de las personas beneficiarias que cumplan los 65 años de edad o por fallecimiento y/o en las causales de los supuestos del numeral el 12.1., en dichos supuestos, se podrá realizar la sustitución de titulares.\nEl Comité Técnico de Validación, verificará y aprobará la integración del padrón de personas beneficiarias de acuerdo a los requisitos de ingreso establecidos en el numeral 9.2, de las presentes Reglas de Operación y a la disponibilidad presupuestal del Programa.\nUna vez validado el registro de la persona beneficiaria, se iniciará el proceso de entrega del apoyo económico mediante tarjeta bancaria en el lugar que previamente el IGATIPAM dio a conocer. La entrega del apoyo económico se realizará de manera directa y sin personas intermediarias.\nEn el caso supuesto de que la documentación entregada tuviese errores o faltase algún documento, la persona solicitante podrá realizar la corrección y/o actualización de datos presentados y/o presentar la faltante en cualquier momento del ejercicio fiscal o cuando el IGATIPAM lo solicite.\n● Requisitos para ingreso al apoyo económico (Pensión).\na) Tener de 63 a 64 años con 11 meses de edad.\nb) Copia de identificación oficial (INE, INAPAM, Pasaporte al 200%).\nc) Copia de Clave Única de Registro de Población (CURP).\nd) Copia del acta de nacimiento con CURP.\ne) Copia del comprobante de domicilio.\nf) Dos fotografías reciente tamaño infantil.\ng) Ser residente en el estado de Guerrero. municipal.\ni) No estar inscrito en los programas de Pensión para el Bienestar de las Personas Adultas de los programas similares del gobierno estatal y municipal, no estar pensionada o pensionado por el gobierno de otros países.\nj) No contar con ningún esquema institucional de seguridad social.\nk) Solicitud en formato libre dirigida a la persona titular del IGATIPAM.\nl) Requisitar el cuestionario socioeconómico que será aplicado por personal del Instituto\nGuerrerense para la Atención Integral de las Personas Adultas Mayores o enlace municipal designado por el Instituto.\nm) Que la persona adulta mayor designe a una persona como su representante por si sucediera un caso en que la persona beneficiaria tuviera una enfermedad grave que lo imposibilite acudir a recibir el apoyo, dicha persona, podrá asistir en nombre de la persona titular, debiendo presentar carta poder debidamente requisitada, copia de su credencial de elector y un número telefónico de contacto.\nSe podrán realizar visitas domiciliarias para verificar la situación de la persona beneficiaria el estado de salud y las condiciones de vida en que se encuentre.\nLa persona adulta mayor aprobada será incorporada de acuerdo a la disponibilidad presupuestal y en función de las bajas en el padrón de personas beneficiarias que se presenten.\nEl IGATIPAM, a fin de no duplicar los apoyos del Programa a una misma persona beneficiaria, hará cruce de padrones en forma bimestral con las diferentes instituciones que otorguen apoyos económicos similares.\n● Requisitos para Reactivación.\nEn casos de incidencias en la continuidad del apoyo económico, para la reactivación al Programa, la persona adulta mayor presentará los requisitos siguientes:\na) Que la persona beneficiaria titular se apersone a realizar su trámite de reactivación a la\nDirección de Asistencia Social del IGATIPAM, o bien, con la persona enlace del Programa designada por el IGATIPAM en el municipio donde radique.\nb) La solicitud será autorizada de acuerdo a los espacios, generados en el cruce correspondiente le notificará vía telefónica para realizar los trámites correspondientes.\nc) Copia de identificación oficial (INE, INAPAM, Pasaporte al 200%).\nd) 1 fotografía tamaño infantil.\ne) Número telefónico de contacto.\n● Requisitos para Envejecimiento Digno (Pensión).\na) Tener 60 o más años de edad.\nb) Copia de identificación oficial (INE, INAPAM, Pasaporte) al 200%.\nc) Solicitud en formato libre dirigida a la persona titular del IGATIPAM, solicitando el tipo de apoyo.\nd) Dos fotografías tamaño infantil reciente (para el componente recreación y economía, para el componente educación, fotografía de cuerpo completo para el componente salud).\ne) Copia del comprobante de domicilio.\nf) Copia de la Clave Única de Registro de Población (CURP).\ng) Acta de nacimiento, original y copia.\nh) Ser persona residente en el estado de Guerrero.\ni) Designar a una persona como su representante, en el supuesto de que la persona beneficiaria tenga una enfermedad grave que lo imposibilite acudir a recibir el apoyo, esta persona con carta poder y certificado médico pueda asistir en su nombre con copia de su credencial de elector y un número telefónico de contacto.\n● Requisitos para Pago de Marcha. del Programa, su representante o persona designada, deberá presentar, original y copia para cotejo lo siguiente:\na) Certificado o acta de defunción en original y copia simple, expedido por autoridad civil o médica correspondiente, donde acredite la defunción de la persona beneficiaria titular.\nb) Credencial de elector (INE) de la persona beneficiaria titular del Programa.\nc) Copia simple de la credencial de elector (INE) de la persona representante de la persona titular o persona designada para el cobro.\nEl Comité Técnico de Validación del Programa, verificará y aprobará la integración del Padrón\nÚnico de Personas Beneficiarias de acuerdo a los requisitos de ingreso establecidos en el numeral 9.2 y a la disponibilidad presupuestal con la que cuente el Programa.\nIGATIPAM, ubicadas en Calle Madero Número 22, Colonia Centro, Chilpancingo de los Bravo, Guerrero.\nC.P. 39000, con un horario de atención de 9:00 a 15:00 horas en días hábiles en Chilpancingo de los Bravo, Guerrero.\n10. Evaluación.\nEl IGATIPAM, como instancia ejecutora del Programa, podrá solicitar la evaluación de carácter interno y/o externo con base en los Objetivos Estratégicos, Metas, Indicadores de desempeño relacionados con la eficiencia, eficacia, economía, la calidad de la administración pública y el impacto social del gasto, para garantizar que los mecanismos de funcionamiento y administración del Programa son acordes a la normatividad vigente, y que existe una correcta aplicación de los recursos, o en su defecto ajustar o reorientar su ejecución para el mejoramiento de la operatividad del Programa conforme al anexo 25 Sistema de Evaluación al desempeño establecido en el Decreto Número 203 del Presupuesto de Egresos del Estado de Guerrero, para el Ejercicio Fiscal 2025. (REFORMADO, P.O. 23 ALCANCE XII, 21 DE MARZO DE 2025)\nLas evaluaciones internas y/o externas que se realicen al Programa serán coordinadas por la\nSCyTG.\n10.1. Indicadores (Construcción de la Matriz de Indicadores para Resultados. - Anexo 1).\nEn congruencia con la metodología de presupuesto basado en resultados (PBR) empleada a nivel nacional, y adoptada por el gobierno del estado de Guerrero y para el seguimiento y evaluación del\nPrograma se utilizarán los indicadores que se especifican en la Matriz de Indicadores de Resultados (MIR) para el ejercicio fiscal 2025 publicada en la página de internet integral-de-las-personas-adultas-mayores-igatipam/, que son los siguientes:\nIndicador apoyo (Pensión):\na). Porcentaje de apoyos entregados a manera de pensión para el bienestar a la población adulta mayor de 63 a 64 años con 11 meses en el estado de Guerrero.\nIndicador apoyo Envejecimiento Digno:\nb). Porcentaje de apoyos entregados para Envejecimiento Digno a la población adulta mayor de\nFicha Técnica\nIndicadores del Desempeño\nPlan Estatal de Desarrollo 2022-2027\nRAMO: 28 FECHA: 22 de enero 2025\nFONDO: Inversión Estatal Directa\nNOMBRE DEL PROGRAMA: Envejecimiento digno\nEJE TEMATICO: 1 Bienestar, Desarrollo Humano y Justicia Social.\nOBJETIVO: 1.3 Disminuir las desigualdades a través de la atención a grupos vulnerables.\nESTRATEGIA: 1.3.2 Atención prioritaria a grupos vulnerables.\nLÍNEA DE ACCIÓN: 1.3.2.5 Mejorar el nivel de bienestar y envejecimiento digno de los Adultos Mayores de 63 a 64 años 11 meses a través de apoyos y acciones orientadas a satisfacer sus necesidades básicas.\nDatos de identificación del indicador\nClave Nombre Fuente\n1.3.2.5\nPorcentaje de apoyos entregados para envejecimiento digno a la población adulta mayor de Dirección Asistencia\n60 años en adelante en el Estado de Guerrero. Social\nDefinición Nivel en la MIR Dimensión\nMide el porcentaje de apoyos económicos entregados respecto a los apoyos económicos programados a las personas adultas mayores de 60 años en adelante Componente 1 Eficiencia en el estado de Guerrero\nMétodo de cálculo Unidad de Medida.\n(Apoyos económicos entregados/Total de apoyos económicos programados)*100 Porcentaje\nFrecuencia de medición Desagregación geográfica Serie de información disponible\nTrimestral Estatal 2024\nLínea base\nSentido del indicador\nAño Periodo Valor\nConstante 2024 Enero-Diciembre 100%\nParámetros de semaforización Metas\nVerde Amarillo Rojo Año Periodo Valor\n76% a 100% 51% a 75% 0% a 50% 2025 Enero-Diciembre 100%\nVariables que conforman el indicador\nNombre Unidad de medida Fuente de información\nInformes trimestral es, Apoyos económicos entregados Apoyo Padrones y avance del\nPrograma Operativo Anual de lIan foDrmireecsc ión detr imAessisttreanlecsia, Total de apoyos económicos programados Apoyo SPoacdiarol nes y avance del hPtrtopgsr:/a/tmraan sOpapreernactiivao.g uAenrurearl\nObservaciones ode.g loab D.mirxe/cscuijóento d_eo balsigisatdeon/cinia\nCon este indicador se pretende cumplir con las metas establecidas para entrar dentro del parámetro de sema sSf too itcr u iiz tao al- c g ió u n e r c r u e a r n e d n o s e m -p en a o ra s - e n color amarillo. https://transparencia.guerrer\nResponsable del indicador o.gob.mx/sujeto_obligado/in\nNombre del Servidor Público Dependencia stituto-guerrÁerreean se-paraInstituto Guerrerense para la\nDirección de Asistencia\nLic. Julián Díaz López. Atención Integral de las Personas\nSocial.\nAdultas Mayores\nNombre del puesto, encargo o comisión Teléfono Correo electrónico\nDirector de Asistencia Social 74 74 71 42 33 y 74 74 72 58 64 igatipam@yahoo.com.mx\nElaboró Revisó A\nLic. Julián Díaz López. Lic. Cutberto Quiñones Flores. Mtra. Rosita Espinozat Ortega\nDirector de Finanzas y Administración Directora General doel IGATIPAM.\nDirector de Asistencia Social del del IGATIPAM. r\nIGATIPAM.\nFicha Técnica\nIndicadores del Desempeño\nPlan Estatal de Desarrollo 2022-2027\nRAMO: 28 FECHA: 22 de enero 2025\nFONDO: Inversión Estatal Directa\nNOMBRE DEL PROGRAMA: Envejecimiento digno\nEJE TEMATICO: 1 Bienestar, Desarrollo Humano y Justicia Social.\nOBJETIVO: 1.3 Disminuir las desigualdades a través de la atención a grupos vulnerables.\nESTRATEGIA: 1.3.2 Atención prioritaria a grupos vulnerables.\nLÍNEA DE ACCIÓN: 1.3.2.5 Mejorar el nivel de bienestar y envejecimiento digno de los Adultos Mayores de 63 a 64 años 11 meses a través de apoyos y acciones orientadas a satisfacer sus necesidades básicas.\nDatos de identificación del indicador\nClave Nombre Fuente\nPorcentaje de apoyos entregados para envejecimiento digno a la poblaciòn adulta Dirección Asistencia\n1.3.2.5 mayor de 60 años en adelante en el Estado de Guerrero. Social\nDefinición Nivel en la MIR Dimensión\nMide el porcentaje de apoyos económicos entregados respecto a los apoyos económicos programados a las personas adultas mayores de Componente 2 Eficiencia\n60 años en adelante en el estado de Guerrero..\nMétodo de cálculo Unidad de Medida.\n(Apoyos económicos entregados / Total de apoyos económicos programados) * 100 Porcentaje\nFrecuencia de medición Desagregación geográfica Serie de información disponible\nAnual Estatal 2024\nLínea base\nSentido del indicador\nAño Periodo Valor\nAscendente 2024 Enero-Diciembre 100%\nParámetros de semaforización Metas\nVerde Amarillo Rojo Año Periodo Valor\n76% a 100% 51% a 75% 0% a 50% 2025 Enero-Diciembre 100%\nVariables que conforman el indicador\nNombre Unidad de medida Fuente de información\nInformes trimestral es, Apoyos económicos entregados Apoyo Padrones y avance del\nPrograma Operativo Anual dInef olram Deisre cción dtrei mAessisttreanlecsia, Total de apoyos económicos programados Apoyo SPoacdiarol nes y avance del hPtrtopgsr:/a/tmraan sOpapreernactiivao.g uAenrurearl\nObservaciones ode.g loab D.mirex/cscuijóento d_eo balsigisatdeon/cinia\nCon este indicador se pretende cumplir con las metas establecidas para entrar dentro del parásSmtoitecutitraool- gduee srreemreanfosreiz-apcaiórancuando menos en color amarillo. https://transparencia.guerre\nResponsable del indicador ro.gob.mx/sujeto_obligado/i\nNombre del Servidor Público Dependencia nstituto-guerÁrreerae nse-paraInstituto Guerrerense para la\nDirección de Asistencia\nLic. Julián Díaz López. Atención Integral de las Personas\nSocial.\nAdultas Mayores\nNombre del puesto, encargo o comisión Teléfono Correo electrónico\nElaboró Revisó A\nLic. Julián Díaz López. Lic. Cutberto Quiñones Flores. Mtra. Rosita Espinuoza Ortega\nIGATIPAM. Administración del IGATIPArM.\n(REFORMADO, P.O. 23 ALCANCE XII, 21 DE MARZO DE 202IG5)A TIPAM. i\n10.2. Seguimiento.\nPara la mejora permanente del Programa, así como para la integración de informes, la Dirección de Asistencia Social del IGATIPAM, llevará a cabo el seguimiento de los recursos asignados al Programa, de la Secretaría de Bienestar del Estado de Guerrero; y con la SEPLADER, dichas instancias participarán en el seguimiento integral a las acciones del Programa y de igual forma verificarán que este cumpla con la normatividad aplicable.\n10.3. Auditoría.\nEl IGATIPAM, será responsable de la supervisión directa de las acciones, así como de verificar que en su ejecución se cumpla con la normatividad aplicable en tiempo y forma.\nLos recursos asignados para la operación del Programa no pierden su carácter estatal, por lo que la SEFINA, la SCyTG, el órgano de fiscalización de las entidades paraestatales y la Auditoría Superior del estado de Guerrero, en el ámbito de sus respectivas competencias, realizarán actividades de fiscalización y auditoría.\nEl IGATIPAM, dará todas las facilidades a las instancias fiscalizadoras para realizar en el momento que juzguen pertinente, las auditorías necesarias; asimismo, efectuará el seguimiento y la solventación de las observaciones por irregularidades planteadas por los órganos de control en tiempo y forma.\nLa inobservancia de esta disposición, independientemente de las sanciones a que hubiere lugar, limitará la ministración de los recursos estatales en el siguiente ejercicio presupuestal.\n11. Mecanismo de Entrega del Apoyo.\nLas personas beneficiarias, cuyos datos fueron verificados, validados y revisados por el personal asignado de la Dirección de Asistencia Social, que cumplan con los criterios y requisitos de elegibilidad, establecidos en las presentes Reglas de Operación, recibirán el apoyo económico proporcionado por el\nPrograma. El IGATIPAM, como organismo ejecutor, será el encargado de solicitar bimestralmente, el apoyo de acuerdo al numeral 9.2 el pago del apoyo económico, mediante dispersión electrónica o en efectivo cuando así se considere pertinente a las personas beneficiarias de (Pensión) así mismo para\nEnvejecimiento Digno.\nEn caso de fallecimiento de la persona beneficiaria, la persona designada por la persona beneficiaria titular, podrá recibir un apoyo a través del pago de marcha posterior al último bimestre de vida de la persona, para contribuir a los gastos funerarios, presentando, original y copia (para cotejo) del\nCertificado de Defunción expedido por la autoridad municipal y/o acta levantada por el personal médico que certificó la defunción, con original y copia (para cotejo) de la credencial de identificación oficial de la persona beneficiaria y de la persona que recibe el apoyo. cruces de información, para el pago de marcha se considerará como pagado en el bimestre de su fallecimiento y/o cuando es detectado en el cruce.\nPara la operación y ejecución del Programa, la Dirección de Asistencia Social en coordinación con la Dirección de Finanzas y Administración del IGATIPAM, cuantificarán las necesidades de los recursos materiales y humanos que habrán de intervenir en el proceso de entrega bimestral de apoyos a las personas beneficiarias, que incluye la contratación de servicios bancarios, programación de la distribución en especie o electrónica de recursos por municipio, de acuerdo con al numeral 9.2., que se establezca para cada uno de los rubros del Programa.\nLa cuantificación que de estas actividades resulten, se notificará a la SEFINA, quien suministrará y/o dispersará el recurso para abastecer los requerimientos al IGATIPAM y éste será responsable de su ejercicio y comprobación respectiva.\nEl IGATIPAM se coordinará con los ayuntamientos para la ejecución del Programa en su municipio.\nConsiderando las condiciones de cada municipio, para la entrega de apoyos económicos del\nPrograma, se podrán utilizar las modalidades siguientes:\n● Tarjeta Electrónica a través de instituciones bancarias. (A los municipios que cuenten con la misma).\n● Efectivo. (A aquellos municipios que por su lejanía no cuentan con instituciones bancarias).\nLa Dirección de Asistencia Social del IGATIPAM, coordinará mediante la designación de responsables, la instalación de módulos regionales y/o municipales, o personal autorizado por el\nIGATIPAM, quienes llevarán el control de ingreso al módulo y recepcionarán la documentación para la identificación de sus respectivas tarjetas, sobres y/o recibos; verificarán la personalidad de la persona beneficiaria mediante cotejo de documentos de identidad; y realizará la entrega de apoyos de manera de Operación.\nPago de Marcha.\nEn caso de fallecimiento de la persona beneficiaria, la persona que lo represente podrá recibir un apoyo a través del pago de marcha posterior al último bimestre de vida de la persona beneficiaria, para contribuir a los gastos funerarios, presentando, original y copia (para cotejo) del Certificado de Defunción expedido por la autoridad municipal y/o acta levantada por el personal médico que certificó la defunción, con original y copia (para cotejo) de la credencial de identificación oficial de la persona beneficiaria y de la persona que recibe el apoyo. cruces de información, para el pago de marcha se considerará como pagado en el bimestre de su fallecimiento y/o cuando es detectado en el cruce.\nSupervivencia. cualquiera de las oficinas del IGATIPAM, o en los lugares que éste señale para tal fin, dicha verificación de supervivencia podrá realizarse una vez al año, en caso de imposibilidad para cumplir con esta obligación y si las condiciones lo permiten, se podrá verificar la supervivencia en el domicilio de la persona beneficiaria, solo si ésta se localiza dentro del estado de Guerrero.\nLa entrega de apoyos a las personas beneficiarias a través de terceras personas mediante carta poder, será validada sólo en el caso de que la persona beneficiaria se encuentre enferma, situación que se comprobará con la carta poder debidamente integrada con los requisitos establecidos en el inciso 12 del numeral 9.2.1, en su caso la entrega del apoyo se podrá realizar de manera domiciliaria.\nSe considera que la carta poder se encuentra debidamente requisitada, cuando además de los nombres de quienes la suscriben, esté debidamente firmada o con huella digital de la persona beneficiaria otorgando a una tercera persona el derecho para recibir su apoyo en su nombre y deberá estar certificada por una autoridad municipal.\n12. Derechos y Obligaciones de las Personas Beneficiadas.\na). Derechos.\n1. Recibir la información necesaria del Programa de manera clara y oportuna.\n2. Trato digno, respetuoso, oportuno, con calidad, equidad y sin discriminación alguna.\n3. Atención y entrega de apoyos sin costo alguno.\n4. La reserva y privacidad de su información personal.\n5. Recibir su apoyo a través de terceras personas (representante) cumpliendo con los requisitos y procedimientos establecidos.\n6. En caso de fallecimiento de la persona beneficiaria, la persona representante recibirá el apoyo a través del Pago de Marcha.\n7. Solicitar y acceder a la información que guarda su trámite y sobre cualquier otra que considere necesaria para transparentar y operar de mejor manera el Programa.\n8. Presentar quejas o inconformidades ante el Comité de Contraloría Social, en las oficinas del\nIGATIPAM, referente a faltas o irregularidades que cometan las personas servidoras públicas que acuden familiares y autoridades municipales en la utilización del mismo.\nLa persona representante de la persona beneficiaria del numeral 5 de este apartado, tendrá las obligaciones siguientes:\n1. Informar la defunción y proporcionar la documentación que acredite la defunción de la persona beneficiaria para actualizar la base de datos.\n2. Informar al IGATIPAM los cambios de domicilio cuando la persona beneficiaria se encuentre imposibilitada para hacerlo.\n3. Facilitar el acceso al personal del IGATIPAM para verificar las condiciones de vida de las personas beneficiarias.\nb) Obligaciones\n1. Proporcionar bajo protesta de decir verdad, la información que se les requiera de acuerdo a lo establecido en las presentes Reglas de Operación.\n2. Actualizar su expediente cuando el IGATIPAM lo solicite.\n3. Nombrar a una persona representante para que, en caso de fallecimiento, imposibilidad física o enfermedad, pueda recibir el apoyo que corresponda.\n4. Acudir a los lugares en la fecha y hora señalada a recibir su apoyo.\n5. Informar al IGATIPAM los cambios de domicilio.\n6. Acudir a las reuniones que previamente convoque el IGATIPAM.\n7. Acudir a su verificación de supervivencia a las oficinas del IGATIPAM o en las cabeceras municipales que les correspondan cuando así se haya programado.\nLa persona representante de la persona beneficiaria tendrá las obligaciones siguientes:\n1. Informar al IGATIPAM, la defunción de la persona beneficiaria para actualizar la base de datos.\n2. Informar al IGATIPAM, los cambios de domicilio cuando la persona beneficiaria se encuentre imposibilitado para hacerlo.\n12.1. Causales de Suspensión o Baja de las Personas Beneficiadas.\na). En caso de que el IGATIPAM, o algún órgano de fiscalización detecte alguna irregularidad, como el caso de homonimia, duplicidad del beneficio, entre otros.\nb). Por no presentarse a recibir su apoyo en dos bimestres consecutivos.\nc). Por no acudir a su verificación de supervivencia.\nd). Por proporcionar información personal falsa.\ne). Por no actualizar su expediente cuando el IGATIPAM lo solicitó.\nf). Cuando la persona beneficiaria o a través de su representante soliciten la baja voluntaria del\nPrograma.\ng). Por cambio de residencia fuera del estado de Guerrero.\nh). Por cumplir 65 años de edad excepto la vertiente de Envejecimiento Digno.\ni). Por detectarse alteraciones en su información presentada.\nj). Por encontrarse inscritos en los programas de Pensión para el Bienestar de las Personas\nAdultas Mayores y para el Bienestar de las Personas con Discapacidad del Gobierno Federal, ni en ningún padrón de los programas similares del gobierno estatal y municipal, no estar pensionada o pensionado por el gobierno de otros países.\nSe podrán realizar visitas domiciliarias para revisar la veracidad de la información proporcionada en el cuestionario, a fin de que exista congruencia con las condiciones y requisitos establecidos ya sea para permanencia, nuevo ingreso o reactivación al Programa.\n12.2. Proceso de Baja.\nCon la finalidad de que los recursos etiquetados para el Programa sean ejercidos en su totalidad el IGATIPAM, realizará cruces de padrones con las instituciones que brinden seguridad social, con la para detectar personas beneficiarias que ya tengan una pensión o jubilación, que estén beneficiadas por algún programa similar o personas beneficiarias que hayan fallecido, también con base en la información recopilada en la entrega de tarjetas, supervivencia, avisos de fallecimientos por los familiares y por los así, cumplir con las metas propuestas al inicio del ejercicio fiscal 2025. (REFORMADO, P.O. 23 ALCANCE XII, 21\n13. Instancias Participantes.\nLas instancias participantes serán, la SEFINA, la SCyTG, el Consejo Directivo, el Comité Técnico de Validación del Programa; y el IGATIPAM, quién será el responsable de la operación del Programa de\nNúmero 203 del Presupuesto de Egresos del Estado de Guerrero, para el Ejercicio Fiscal 2025, Anexo\n23-A publicado en el Periódico Oficial del Gobierno del Estado de Guerrero, Edición No.105 con fecha 31 de diciembre del 2024, el cual contempla un monto autorizado de $30'800,000.00 (Treinta Millones\nOchocientos Mil Pesos 00/100 M.N.). Con las atribuciones siguientes: (REFORMADO, P.O. 23 ALCANCE XII, 21\nDE MARZO DE 2025)\na). Coordinar y conducir la operación del Programa de acuerdo a los lineamientos establecidos en las presentes Reglas de Operación.\nb). Administrar a través de la Dirección de Finanzas y Administración del IGATIPAM, los recursos financieros autorizados.\nc). Diseñar los instrumentos técnicos necesarios para evaluar el impacto social del Programa.\nd). La organización del personal técnico y operativo que resulte indispensable para garantizar el funcionamiento del Programa.\ne). Contratar personas promotoras para realizar las actividades de operación del Programa.\n13.1. Instancia Normativa.\nLas instancias normativas serán, la SEPLADER la SEFINA, la SCyTG, el Consejo Directivo y el\nComité Técnico de Validación del Programa.\n14. Transparencia.\n14.1. Promoción y Difusión del Programa Social.\nCon base a lo establecido en la Ley Número 207 de Transparencia y Acceso a la Información\nPública del Estado de Guerrero, el IGATIPAM, además de su publicación en el Periódico Oficial del para-la-atencion-integral-de-las-personas-adultas-mayores-igatipam/, la información relativa al Programa, Operación, el padrón de personas beneficiarias, los datos personales que se recaben serán protegidos conforme a la normatividad aplicable e incorporados y tratados en el Sistema de Datos Personales, pero otorgados, además de ser tratados como datos estadísticos, cuya finalidad será contar con un padrón de permita rediseñar las políticas públicas encaminadas a este sector vulnerable.\n14.2. Contraloría Social. beneficiada por el Programa y con apego en lo dispuesto en la Ley Núm. 102, para el Desarrollo Social de Guerrero, se establece que la sociedad podrá participar activamente en la planeación, implementación, administración, programación, desarrollo y evaluación de los programas y acciones de desarrollo social; por ello, el Instituto Guerrerense para la Atención Integral de las Personas Adultas Mayores por medio del\nComité Técnico de Validación del Programa y de acuerdo al artículo 56 de la Ley Número 375 de los\nDerechos de las Personas Adultas Mayores del Estado de Guerrero, incluye a personas ciudadanas representantes del sector social de las personas adultas mayores para que conjuntamente contribuyan a lograr resultados de impacto en la ciudadanía adulta mayor, dicho Comité verificará y aprobará la integración del Padrón de Personas Beneficiarias de acuerdo a los requisitos de ingreso establecidos en las Reglas de Operación en el numeral 9.2 y a la disponibilidad presupuestal con la que cuente el\nPrograma, realizando las acciones siguientes:\nLa SCyTG, se encargan de promover la contraloría social en los programas de desarrollo social.\nLos objetivos específicos de este órgano de Contraloría Social, son:\na). Dar seguimiento, supervisión, vigilancia y evaluación del cumplimiento de criterios de elegibilidad y derechos de las personas beneficiarias.\nb). Vigilar el desempeño, honestidad y calidad de las servidoras y servidores públicos.\nc). Hacer más transparentes las decisiones y la ejecución de los recursos.\nd). Inhibir los actos de corrupción y de cooptación social, política y electoral.\ne). Incrementar la eficiencia de los recursos públicos.\nf). Participar en las reuniones calendarizadas del Comité Técnico de Validación del Programa.\ng). Mejorar la rendición de cuentas.\nDebe estar constituido mínimamente por una presidencia, una secretaria y una vocalía electos de entre la población beneficiada.\nDicho Comité deberá revisar en conjunto con la población, los avances y resultados del programa, así como la detección de cualquier irregularidad. inconformidades recibidas al IGATIPAM, quien dará respuesta en un plazo no mayor de 15 días a partir de la fecha de recepción de la queja o inconformidad. asesoría a las personas servidoras públicas que intervienen en la operación del Programa, así como a las personas integrantes de los comités locales, para que éstos realicen adecuadamente sus actividades de seguimiento y vigilancia.\nSe deberá integrar un Programa de Trabajo de acuerdo al Programa, que debe incluir la descripción de las actividades, responsables de éstas, metas y calendarización de las actividades para su cumplimiento.\n14.3. Protección de Datos Personales.\nLos datos personales recabados serán utilizados para validar que se cumplan con los requisitos de elegibilidad para ser beneficiaria o beneficiario de este Programa, asimismo serán integrados en los sistemas de datos personales del IGATIPAM y podrán ser transmitidos a otros entes públicos de los tres niveles de gobierno en el ejercicio de las facultades propias, compatibles o análogas, para la realización de compulsas y la integración del padrón de personas beneficiarias. Por lo tanto, se garantiza la protección de datos personales cuyos datos se recogen, se mantienen y se procesan mismos que se regirán por en\n(SIC) Aviso de Privacidad fundado en los artículos 16, 17, 35, 36, 37, 38, 39, 40, 64 y 92 de la Ley Número\n466 de Protección de Datos Personales en Posesión de Sujetos Obligados del Estado de Guerrero y en la Ley Número 207 de Transparencia y Acceso a la Información Pública del Estado de Guerrero.\nPara el ejercicio de los derechos de acceso, rectificación, cancelación y oposición de los datos personales recabados, deberán realizarse por escrito y por comparecencia del interesado, mismo que deberá presentarse en las oficinas del IGATIPAM ubicado en Calle Madero, Número 22, Colonia Centro, Chilpancingo de los Bravo, Guerrero. C.P. 39000 o llamar a los teléfonos: (747) 47 1 42 33; de igual forma lo podrán realizar a través de la dirección electrónica: integral-de-las-personas-adultas-mayores-igatipam/\n14.4. Quejas y Denuncias. irregularidad de cualquier hecho, actos de corrupción u omisión, desvío de recursos que produzca o pueda contravengan sus disposiciones y demás normatividad aplicable en la operación del Programa.\nLos medios por los cuáles podrán presentarse quejas y denuncias ciudadanas son:\na). Por escrito.\nb). Por comparecencia de la persona interesada.\nc). Por correo electrónico.\nd). Vía telefónica.\nEn las oficinas del IGATIPAM ubicado en Calle Madero, Número 22, Colonia Centro, Chilpancingo de los Bravo, Guerrero. C.P. 39000, o bien vía correo electrónico: igatipam2027@gmail.com o llamar al teléfono: (747) 47 1 42 33.\nLa persona denunciante o quejosa deberá proporcionar la narración de los hechos que constituyan la queja, acompañando los documentos o evidencias que comprueben los actos incurridos acompañado de la siguiente información:\na). Nombre de la servidora o servidor (es) público (s).\nb). Secretaría o dependencia de adscripción.\nc). Objeto de la denuncia\nd). Nombre y domicilio de la persona quejosa.\ne). Copia de Identificación oficial.\nf). Correo electrónico.\ng). Domicilio para oír y recibir notificaciones.\nh). Número telefónico.\n14.5. Acciones de Blindaje.\nEl IGATIPAM, para la operación y ejecución de los recursos estatales que opera el Programa deberá observar y atender las medidas que emitan la SCyTG, el Instituto de Transparencia, Acceso a la\nInformación y Protección de Datos Personales del Estado de Guerrero (ITAIGro), el IEPC y las demás autoridades competentes, con la finalidad de prevenir que el uso y manejo de los recursos públicos y programas sociales se vean relacionados con fines partidistas y/o político-electorales; todo ello con la firme intención de garantizar los principios de imparcialidad y equidad durante los comicios; por lo que la papelería y documentación oficial del Programa deberá incluir la siguiente leyenda:\n\"Este programa es público y ajeno a cualquier partido político. Queda prohibido el uso para fines distintos a los establecidos en el programa”\n14.6. Acta de Donación. (Anexo 2)\nEl IGATIPAM, presentará debidamente requisitada el Acta de entrega – recepción de apoyos que formará parte de la transparencia de la ejecución de los recursos del Programa.\n15. Perspectiva de Género.\nDe conformidad con la Ley Número 494 para la Igualdad entre Mujeres y Hombres del Estado de\nGuerrero, para regular y garantizar la igualdad entre mujeres y hombres se incorpora la perspectiva de género en las Reglas de Operación del Programa con el propósito de contribuir al acceso de las mujeres a los beneficios de este Programa en igualdad de condiciones; privilegiando, en su caso, la inclusión de medidas especiales, para solucionar las condiciones inmediatas en la vida de las mujeres, y medidas estratégicas que tiendan a la valorización de la posición que tienen en la comunidad, modificando los patrones culturales y eliminando los estereotipos que ocasionan discriminación y violencia, así como medidas que aceleren el logro de la igualdad sustantiva para el ejercicio pleno de todos los derechos de las mujeres y su participación igualitaria, atendiendo a los preceptos establecidos en la Convención sobre la eliminación de todas las formas de discriminación contra la mujer.\n16. Enfoque de Derechos.\nEl Programa atiende y cumple con los derechos universales y con base en los principios de universalidad, interdependencia, indivisibilidad y progresividad, brindando en todo momento un trato digno y de respeto, se reconocen a todos los seres humanos sin exclusión alguna, es una obligación del estado velar por su respeto, garantizar la igualdad y la no discriminación, todo ser humano nace libre y en igualdad en cuanto a dignidad y a derecho se refiere, las personas servidoras públicas involucradas en la operación del Programa deben en todo momento promover, respetar, proteger y garantizar el ejercicio efectivo de los derechos humanos de las personas beneficiarias.\nEn la aplicación del Programa, se harán valer los derechos de las personas beneficiarias, personas que pertenecen a grupos históricamente discriminados, como lo son las personas adultas mayores, afromexicanas, y aquellas que son comunidades integrantes de un pueblo indígena, que formen una unidad social, económica y cultural, asentadas en el territorio guerrerense y que reconocen autoridades propias de acuerdo a sus usos y costumbres, entre otros, tomando en consideración sus circunstancias y necesidades, a fin de contribuir a generar conocimiento y acciones que potencien su desarrollo e inclusión plena.\n17. Acciones Contra el SARS-COV 2.\nCOVID-19, el IGATIPAM, aplica las medidas sanitarias en la entrega de apoyos, priorizando las medidas sanitarias tanto del personal operativo como de las personas beneficiarias, en cuanto a trámites, dispersiones y demás servicios del Programa.\n18. Anexos que reflejen la entrega del apoyo (Económico. Especie o Servicios).\nAnexo 1.- MIR.\nAnexo 2.- Acta de Donación.\nFormato 4. MIR Fecha: 22 de enero del 2025\nEje: 1 Bienestar, Desarrollo Humano y Justicia Social.\nObjetivo: 1.3 Disminuir las desigualdades a través de la atención a grupos vulnerables.\nEstrategia: 1.3.2 Atención prioritaria a grupos vulnerables.\nLínea de Acción: 1.3.2.5 Mejorar el nivel de bienestar y envejecimiento digno de los Adultos Mayores de 63 a 64 años 11 meses a través de apoyos y acciones orientadas a satisfacer sus necesidades básicas.\nMatriz de indicadores para Resultados\nResumen Narrativo Indicadores de desempeño Medios de Verificación Supuesto\nTabulados del censo de población y vivienda 2020. https://www.inegi.org.mx/programas/ccpv/2020/#Tabulados\nContribuir a reducir las carencias\nPadrón de beneficiarios de los programas sociales otorgados en el estado de Guerrero: sociales de las personas adultas La Población Adulta Mayor de\nPersonas Adultas Mayores beneficiadas https://transparencia.guerrero.gob.mx/transparencia/xv-lamayores en situación de vulnerabilidad Guerrero accede a los programas\nFin con los programas sociales en el Estado de informacion-de-los-programas-de-subsidios-estimulos-y-apoyos-enen el estado de Guerrero, mediante sociales otorgados para este sector\nGuerrero. el-que-se-deberá-informar-respecto-de-los-programas-depolíticas públicas que mejoren su de la población. transferencia-de-servicios-de-infraestructura-social-y-de-subsidio-2/ bienestar. https://pub.bienestar.gob.mx/v2/pub/programasIntegrales/13/232\nEstadísticas de la población adulta mayor por región y municipio.\n:/\n/\n/\n/\n.g\n/\n/\n.g\n.m\n/\n-\n2 0-Pension-GuerreroLos adultos mayores cuentan con\nPorcentaje de la población adulta mayor\n2023-para-MIR.pdf apoyos económicos y actividades y Padrones de Beneficiarios del programa publicados en la página Las personas adultas mayores del Estado de Guerrero beneficiadas con\nPropósito (resultados) orientadas al esparcimiento, de internet institucional acceden a los beneficios que se algún tipo de apoyo y/o acción de los satisfaciendo sus necesidades básicas https://transparencia.guerrero.gob.mx/transparencia/xv-la- entregan y proporcionan con los programas con bienestar. para elevar su calidad de vida. informacion-de-los-programas-de-subsidios-estimulos-y-apoyos-en- programas. el-que-se-deberá-informar-respecto-de-los-programas-detransferencia-de-servicios-de-infraestructura-social-y-de-subsidio-\n2/\nPorcentaje de apoyos entregados a Informes trimestrales, padrones y avance del Programa Operativo\nAnual de la Dirección de Asistencia Social\n1. Pensión para el Bienestar de manera de pensión para el bienestar a la https://transparencia.guerrero.gob.mx/transparencia/iv-las-metasLas Personas Adultas Mayores\nGuerrero. población adulta mayor de 63 a 64 años acuden a recibir su apoyo con 11 meses en el Estado de Guerrero. y-objetivos-de-las-áreas-de-conformidad-con-sus-programas- económico. operativos-34/\nInformes trimestrales, listas de asistencia y avance del Programa Las Personas Adultas Mayores\nComponentes (Servicios\nOperativo Anual de la Dirección de Asistencia Social, Dirección de solicitan y acuden en las actividades y y Productos)\nGestión Interinstitucional y Unidad de Asuntos Jurídicos. gestiones institucionales.\nPorcentaje de apoyos entregados para https://transparencia.guerrero.gob.mx/transparencia/iv-las-metasenvejecimiento digno a la población adulta\n2. Envejecimiento digno y-objetivos-de-las-áreas-de-conformidad-con-sus-programasmayor de 60 años en adelante en el Estado operativos-34/ de Guerrero.\nInformes trimestrales y avance del Programa Operativo Anual de la\nDirección de Asistencia Social, publicados trimestralmente en el portal\n. a Total de apoyos entregados de pensión tt p\n:/\n/\n:\n64 años 11 meses. para el bienestar de guerrero. y-objetivos-de-las-areas-de-conformidad-con-sus-programas- 64 años 11 meses que accedieron operativos-34/ al programa, acuden a recibir su apoyo económico.\nAnexo 2.- Acta de Donación.\nPrimero. El presente Acuerdo entrará en vigor al día siguiente de su publicación en el\nSegundo. Se abroga el Acuerdo por el que se emiten las Reglas de Operación del\nPrograma “Pensión Guerrero” para el Ejercicio Fiscal 2023, publicado en el Periódico Oficial del\nGobierno del estado de Guerrero Edición No. 31 Alcance V, de fecha 18 de abril de 2023.\nTercero. A partir de la entrada en vigor del presente Acuerdo, las Reglas de Operación del Programa Pensión para el Bienestar de Guerrero, subsecuentes o sus modificaciones, serán emitidas por la persona titular del Instituto Guerrerense para la Atención Integral de las\nPersonas Adultas Mayores del Estado de Guerrero, responsable directa de la operación y ejecución de las mismas.\nDado en el “Recinto de las oficinas del Poder Ejecutivo del estado”, el inmueble ubicado en el Edificio Centro, Boulevard René Juárez Cisneros, número 62 de la Ciudad de los Servicios en Chilpancingo de los Bravo, capital del estado de Guerrero, a los veintidós días del mes de marzo del año dos mil veinticuatro.\nMTRA. EVELYN CECIA SALGADO PINEDA.\nRúbrica.\nDRA. ANACLETA LÓPEZ VEGA.\nRúbrica.\nDIRECTORA GENERAL DEL IGATIPAM\nMTRA. ROSITA ESPINOZA ORTEGA.\nRúbrica.\nN. DE E. A CONTINUACIÓN, SE TRANSCRIBEN LOS ARTÍCULOS TRANSITORIOS DE LOS ACUERDO\nDE MODIFICACIÓN A LAS PRESENTES REGLAS DE OPERACIÓN.\nPrimero. El presente Acuerdo de Modificación entrará en vigor al día siguiente de su publicación\nSegundo. Se derogan todas las disposiciones que se opongan al Presente Acuerdo de\nModificación.\nDado en el Inmueble ubicado en Calle Francisco I. Madero, número 22, colonia Centro, código postal\n39000 en Chilpancingo de los Bravo, capital del estado de Guerrero, a los dieciocho días del mes de febrero del año dos mil veinticinco.\nLA DIRECTORA GENERAL DEL IGATIPAM.\nMTRA. ROSITA ESPINOZA ORTEGA.\nRúbrica.",
  "ordenamiento": "PROGRAMA",
  "jurisdiccion": "GUERRERO",
  "fuente_oficial": "DIARIO OFICIAL DE LA FEDERACION",
  "Fecha de Publicación": "21 DE MARZO DE 2025",
  "ULTIMA REFORMA PUBLICADA": null,
  "status": "VIGENTE",
  "es_escaneado": false,
  "tiene_tablas": true,
  "materia": [
    "desarrollo social"
  ]
}