{
  "titulo": "Acuerdo por el Que Se Crea el Programa de Salud Mental Dirigido A Niñas, Niños y Adolescentes, y Se",
  "Contenido": "OPERACIÓN\nTEXTO ORIGINAL. de mayo 2024.\nACUERDO POR EL QUE SE CREA EL PROGRAMA DE SALUD MENTAL DIRIGIDO A NIÑAS, NIÑOS\nY ADOLESCENTES, Y SE EMITEN SUS REGLAS DE OPERACIÓN.\nPoder Ejecutivo.\nMAESTRA EVELYN CECIA SALGADO PINEDA, GOBERNADORA CONSTITUCIONAL DEL\nESTADO DE GUERRERO, CON FUNDAMENTO EN LO DISPUESTO POR LOS ARTÍCULOS 71, 87, 88,\nLOS ARTÍCULOS 2, 4, 8, 9, 14, 16, 22 APARTADO A FRACCIONES I Y IX, 23 FRACCIÓN III Y 31 DE\nLA LEY ORGÁNICA DE LA ADMINISTRACIÓN PÚBLICA DEL ESTADO DE GUERRERO NÚMERO 242;\n1, 2 FRACCIÓN I, 18 Y 25 DE LA LEY NÚMERO 454 DE PRESUPUESTO Y DISCIPLINA FISCAL DEL\nESTADO DE GUERRERO; 3 Y 7 DEL ACUERDO POR EL QUE SE CREA EL CONSEJO DE SALUD\nMENTAL Y CONTRA LAS ADICCIONES DEL ESTADO DE GUERRERO; EN RELACIÓN CON LOS\nARTÍCULOS FRACCIONES II Y III DE LA LEY NÚMERO 1212 DE SALUD DEL ESTADO DE\nGUERRERO; 47 Y ANEXOS 23 Y 23-A (E09) DEL DECRETO NÚMERO 680 RELATIVO AL\nPRESUPUESTO DE EGRESOS DEL ESTADO DE GUERRERO PARA EL EJERCICIO FISCAL 2024, Y\nLOS LINEAMIENTOS PARA LA ELABORACIÓN DE LAS REGLAS DE OPERACIÓN DE LOS\nPROGRAMAS SOCIALES ESTATALES PARA EL PERIODO 2022-2027.\nQue el artículo 4o de la Constitución Política de los Estados Unidos Mexicanos, establece que toda persona tiene derecho a la protección de la salud. La ley definirá las bases y modalidades para el acceso a los servicios de salud y establecerá la concurrencia de la Federación y las entidades federativas en materia de salubridad general, conforme a lo que dispone la facción XVI del artículo 73 de esta Constitución. La Ley definirá un sistema de salud para el bienestar, con el fin de garantizar la extensión progresiva, cuantitativa con seguridad social. superior de la niñez, garantizando de manera plena sus derechos. Las niñas y los niños tienen derecho a la satisfacción de sus necesidades de alimentación, salud, educación y sano esparcimiento para su desarrollo integral. Este principio deberá guiar el diseño, ejecución, seguimiento y evaluación de las políticas públicas dirigidas a la niñez, el estado otorgará facilidades a las personas particulares para que coadyuven al cumplimiento de los derechos de la niñez.\nOPERACIÓN la meta de atención es el “reducir en un tercio la mortalidad prematura por enfermedades no transmisibles, mediante su prevención y tratamiento, y promover la salud mental y el bienestar”, nos viene a refrendar la importancia de atender con urgencia los problemas de salud, que se presentan en el estado.\nQue el 16 de marzo del 2018, se instaló el Consejo Estatal de la Agenda 2030 para el Desarrollo\nSostenible del Estado de Guerrero, el cual tiene a su cargo la coordinación institucional intergubernamental para el diseño, implementación, seguimiento y evaluación de políticas públicas y programas para el cumplimiento de la Agenda 2030, para dar seguimiento a los 17 Objetivos para el Desarrollo Sostenible\n(ODS) de la agenda 2030, se han identificado y vinculado en la estructura programática del Anteproyecto de Presupuesto de Egresos del Ejercicio Fiscal 2024 con los Programas presupuestarios. En la implementación de la metodología para la identificación de la vinculación de los Programas presupuestarios con las metas de los ODS se realiza un análisis, donde se identifican posibles vinculaciones, a través de la coincidencia del objetivo con alguna meta de los ODS, o si el diseño de los beneficios es acorde al propósito de la meta, o si atiende necesidades de fortalecimiento de los ejecutores que actúan a favor de la meta.\nQue la Estrategia prioritaria 5.3, del Programa Sectorial derivado del Plan Nacional de Desarrollo, es la de garantizar el acceso a los servicios de salud mental y apoyo psicológico bajo un enfoque integral y diferenciado para atender los trastornos mentales y problemas relacionados con adicciones especialmente a grupos históricamente discriminados o en condición de vulnerabilidad.\nQue se focaliza en una de las estrategias 3.4.2 Tasa de mortalidad por suicidio en la que actualmente en coordinación con nivel federal y estatal están implementando el programa nacional de prevención de la conducta suicida en niños, niñas y adolescentes.\nQue la línea 3.5 Fortalecer la prevención el tratamiento del abuso de sustancias adictivas, incluido el uso indebido de estupefacientes y el consumo nocivo de alcohol.\nQue uno de los compromisos de la titular del Poder Ejecutivo con la ciudadanía guerrerense, al asumir y tomar protesta como Gobernadora Constitucional del estado, es lograr un Guerrero de tranquilidad, de paz, de justicia, de crecimiento y de empleo, contribuyendo con ello a construir historias de éxitos individuales y colectivos que permitan consolidar el crecimiento económico y estabilidad social. acciones y establecer rutas encaminadas a lograr un estado moderno, inteligente y visionario, estableciendo como propósito último de los servicios de salud mental la recuperación y el bienestar, el despliegue óptimo de sus potencialidades individuales para la convivencia, el trabajo y la recreación.\nQue en el Decreto Número 680 relativo al Presupuesto de Egresos del Estado de Guerrero, para el Ejercicio Fiscal 2024, se señala que se ejercitarán los recursos bajo una política de gasto públicos, que permita dar cumplimiento a lo que globalmente prevén las dimensiones, ejes, temáticos, objetivos, estrategias y líneas de acción del Plan Estatal de Desarrollo 2022-2027, orientados a los sectores, municipios y comunidades más desprotegidos del estado.\nOPERACIÓN\nQue la Secretaría de Planeación y Desarrollo Regional, expidió los lineamientos para la elaboración de las Reglas de Operación de los Programas Sociales Estatales para el periodo 2022-2027, cuales tienen la finalidad de ofrecer a las secretarías, dependencias y entidades paraestatales del gobierno del estado, un instrumento técnico que guie la elaboración de los apartados centrales de las Reglas de\nOperación, así como los elementos para integrar su contenido.\nQue en la Ley Número 1212 de Salud del Estado de Guerrero, contempla que la Secretaría de\nSalud, entre sus atribuciones, le corresponde, prestar atención médica, preventivo-curativa y promoción de la salud para la población, preferentemente en beneficio de los grupos vulnerables; prestar servicios de atención y promoción de salud mental; propiciar el desarrollo de la familia y de la comunidad, así ́como la integración social y el crecimiento físico y mental de la niñez.\nQue la creación del Programa de Salud Mental dirigido a Niñas, Niños y Adolescentes, y emitir sus\nReglas de Operación, es con el objeto de otorgar transparencia y asegurar la aplicación eficiente, eficaz, oportuna y equitativa de los recursos públicos asignados al mismo.\nPor lo anteriormente expuesto y con fundamento en las disposiciones legales antes citadas, he tenido a bien expedir el siguiente:\nACUERDO POR EL QUE SE CREA EL PROGRAMA DE SALUD MENTAL DIRIGIDO A NIÑAS, NIÑOS\nY ADOLESCENTES, Y SE EMITEN SUS REGLAS DE OPERACIÓN.\nArtículo 1. Se crea el Programa Salud Mental dirigido a Niñas, Niños y Adolescentes, el cual tiene por objeto brindar a las niñas, niños y adolescentes acciones de atención integrales de promoción e intervención en salud mental, la prevención y el tratamiento del abuso de sustancias adictivas, incluido el uso indebido de estupefacientes y el consumo nocivo de alcohol y lograr disminuir la tasa de mortalidad por suicidio, garantizando así una vida sana a través de estilos de vida saludables.\nArtículo 2. La Secretaría de Salud del estado de Guerrero, tendrá a cargo la implementación, operación, ejecución, evaluación y administración del Programa Salud Mental dirigido a Niñas, Niños y\nAdolescentes, bajo los criterios de objetividad, equidad, transparencia, publicidad, selectividad y temporalidad, con estricto apego a la normatividad aplicable, por tanto, será la encargada de la asignación de los recursos del Programa apegándose plenamente a las Reglas de Operación.\nArtículo 3. Se emiten las Reglas de Operación del Programa Salud Mental dirigido a Niñas, Niños y Adolescentes, en las cuales se establece el procedimiento de ejecución, los principios, requisitos que se deben observar para acceder al mismo en los términos siguientes:\nREGLAS DE OPERACIÓN DEL PROGRAMA DE SALUD MENTAL DIRIGIDO A NIÑAS, NIÑOS Y\nADOLESCENTES.\n1. Introducción.\nOPERACIÓN\n1.1. Antecedentes.\nDe acuerdo a la OMS, la salud mental se define como un estado de bienestar en el cual el individuo es consciente de sus propias capacidades, puede afrontar las tensiones normales de la vida, trabajar de forma productiva y fructífera y es capaz de realizar una contribución a su comunidad. En este sentido positivo, la salud mental concierne no solo a la estabilidad individual y del funcionamiento eficaz de la comunidad, sino también a la capacidad colectiva e individual de pensar, manifestar sentimientos, interactuar con los demás, ganar el sustento y disfrutar de la vida. El cuál se iniciará durante el 2o trimestre del año en curso, tiene como finalidad disminuir la tasa de mortalidad por suicidio a través de acciones integrales en coordinación, garantizando así una vida sana a través de estilos de vida saludables.\n2. Alineación Programática al PED y/o PND.\nEl Programa se encuentra alineado al Plan Estatal de Desarrollo del Estado de Guerrero 20222027, así como como al Plan Nacional de Desarrollo 2019-2024 y a los ODS establecidos por la ONU que constituyen un llamamiento a la acción universal a la acción deponer fin a la pobreza, proteger el planeta y mejorar las vidas y las perspectivas de las personas en todo el mundo. En 2017, todos los Estados\nMiembros de las Naciones Unidas aprobaron 17 Objetivos como parte de la Agenda 2030 para el Desarrollo\nSostenible, el cual establece un plan para alcanzar los Objetivos en 15 años.\nEn el objetivo 3. Garantizar una vida sana y promover el bienestar para todos en todas las edades.\nSe establece como tema 3.5. Fortalecer la prevención y el tratamiento del abuso de sustancias adictivas, incluido el uso indebido de estupefacientes y el consumo nocivo de alcohol.\nGuerrero, la cual establece que el proceso de planeación democrática inicia con un diagnóstico consensuado que permita identificar el contexto global y nacional, así como también, las principales áreas de oportunidad en cada una de las trece dimensiones estratégicas. Siendo las dimensiones número 2\n(pobreza y grupos vulnerables) y 7 (salud) en esta dimensión se establece que la Secretaría de Salud y\nServicios Estatales de Salud del estado de Guerrero tiene la misión de: “Hacer efectivo el derecho a la protección de la salud, mediante el acceso digno, corresponsable, oportuno, eficiente y eficaz que permita otorgar servicios de salud con calidad, equidad de género y transparencia en el uso de los recursos asignados por los diferentes niveles de gobierno en beneficio de todos los guerrerenses”.\nAmbas dimensiones forman parte del Eje Temático. 1. Bienestar, Desarrollo Humano y Justicia\nSocial del Plan Estatal de Desarrollo del Estado de Guerrero 2022-2027. En este sentido, garantizar una vida sana a través de estilos de vida saludables y promover la salud mental en niñas, niños y adolescentes, es esencial para el desarrollo sostenible de nuestro estado y municipios, las que están dirigidas a la población objetivo de este programa social.\nDesarrollo el cual define los principios, ejes y estrategias, así como las prioridades nacionales que busca\nOPERACIÓN\nEl Programa Sectorial de Salud 2020-2024, es un programa derivado del PND que establece entonces los objetivos, estrategias y acciones, a los que deberán apegarse las diferentes instituciones de la Administración Pública Federal para materializar el derecho a la protección de la salud.\nLa Secretaría de Salud es la responsable de coordinar la publicación, ejecución y seguimiento del\nPrograma Sectorial de Salud 2020-2024. El quinto objetivo tiene como propósito la atención de los problemas predominantes de salud pública, como es la obesidad y las enfermedades no transmisibles, la salud sexual y reproductiva, la salud mental y adicciones cuya conjunción afectan tanto la salud individual y poblacional.\nLos problemas del estado de Guerrero como la pobreza, la desigualdad, la marginación y la violencia, han tenido impacto directo en el desarrollo y salud mental de niñas, niños y adolescentes, impidiendo un adecuado crecimiento en etapas posteriores. La falta de información y la accesibilidad de los servicios han relegado a las niñas, niños y adolescentes como un sector con niveles bajos de participación activa y social.\nEn México, de acuerdo con el INEGI, en 2019 existían más de 3’300,000 de niñas y niños entre 5 y 17 años de edad que se encuentran en condiciones de trabajo infantil, esto representa una tasa de 11.5%.\nLa Organización Internacional del Trabajo, considera al trabajo infantil como toda actividad económica llevada a cabo por personas menores de 15 años de edad, que priva a las niñas y niños de su infancia, su potencial, su dignidad, y que es perjudicial para su desarrollo físico y mental.\nCon relación al Plan Estatal de Desarrollo 2022-2027, el Programa, está alineado a los ejes, objetivos, estrategias y líneas de acción siguientes:\nObjetivo 1.3. Disminuir las desigualdades a través de la atención a grupos vulnerables\nEstrategia Línea de Acción\n1.3.1. Garantizar el pleno goce de los derechos 1.3.1.1. Impulsar proyectos de atención a las fundamentales de las niñas, niños y niñas, niños y adolescentes para prevenir adolescentes. riesgos psicosociales, mediante la coordinación de acciones integrales.\nObjetivo 1.11. Mejorar la calidad de vida de cada guerrerense, mediante la aplicación de políticas públicas intersectoriales, a través de la transformación del Sistema de Salud del Estado.\nEstrategia Línea de Acción\n1.11.1. Fortalecer la vinculación interinstitucional del Sector Salud. 1.11.1.2. Dar seguimiento a la operación y estatales que cuentan con participación sectorial.\nOPERACIÓN\nObjetivo 1.12. Mejorar la prestación de servicios de salud con calidad, integrales, eficaces, eficientes, inclusivos y transparentes, contribuyendo con esto a incrementar la esperanza de vida.\nEstrategia Línea de Acción\n1.12.1. Adoptar el modelo SABI, la identificación de programas prioritarios y la evaluación periódica de resultados.\n1.12.1.1. Fortalecer los programas de salud, incluyendo aquellos identificados como prioritarios, definiendo los indicadores que les apliquen.\n1.12.1.2. Diseñar y aplicar de un sistema único de evaluación, que funcione de manera constante y periódica.\n1.12.1.3. Usar de los resultados de las evaluaciones de indicadores para la toma de decisiones y mejora de los servicios de salud.\n2.1. Diagnóstico.\nLa cobertura de salud a nivel nacional es apenas del 73% de la población total en Guerrero del cual el 70.9% es afiliada a una institución de salud en el estado de Guerrero, esta se encuentra afiliada de la siguiente manera; el 19.2 % al IMSS, el 11.2% al ISSSTE, el 0.5% al ISSSTE estatal, el 1.4% a PEMEX, Defensa Nacional y Marina, el 0.5% a Hospitales Privados, el 66.3% a INSABI, el 1.4% a IMSS-BIENESTAR y el 0.3% a alguna otra. Lo que significa que el 67.7% de la población afiliada demanda la atención en las unidades de salud que se encuentran distribuidas en las 8 regiones del estado de Guerrero.\nDurante la pandemia por COVID-19 el Observatorio de Salud Mental y Consumo de Sustancias\nPsicoactivas reportó en su informe del (2021) algunos aspectos de salud mental en México, con respecto a la situación emocional originadas por la pandemia de COVID-19 y las medidas de confinamiento, los participantes refirieron sobre sus sentimientos de la última semana a la fecha de la encuesta que, el 31.6% presentó un estado emocional óptimo, el 39.4% se sintió estresado, el 35.3% preocupado, el 20.8% angustiado, el 17.2% desesperado en algún momento, el 15.3 % deprimido, y el 13.0% decaído. Mientras que con respecto a considerar que requerían asesoría o apoyo psicológico, el 18.5% consideró que sí y el\n20.1% ya había consultado a algún profesional de la salud (médico o psicológico).\nEn el año 2020, 33,262 personas acudieron a algún servicio de urgencias por trastornos mentales y del comportamiento debido al uso de sustancias. Con base en datos generados por la DGIS del 20102019 se han registrado 28,122 fallecimientos por trastornos mentales y del comportamiento debido al uso de sustancias, en este periodo se presentaron 827 muertes por trastornos mentales y del comportamiento atribuido al consumo de múltiples sustancias.\nLa carga de enfermedad mide la pérdida de la salud atribuible a diversas enfermedades y lesiones, así como la muerte prematura y discapacidad derivada de estas condiciones. De acuerdo al ECME, en el\n2019 se perdieron 1,710.62 Años de Vida Saludable por cada 100,000 habitantes debido a trastornos mentales y del comportamiento, siendo los padecimientos más significativos el trastorno depresivo mayor\nOPERACIÓN\n(561.98), la esquizofrenia (190.48), la distimia (90.28), el trastorno bipolar (207.43), y los trastornos por ansiedad (347), donde en este último las mujeres se ven más afectadas en comparación con los hombres.\nRef. Instituto de Métricas y Evaluación de la Salud.\nA diferencia de otros indicadores la carga de enfermedad refleja el impacto a la salud, donde los trastornos mentales y del comportamiento revisten una importante carga de enfermedad, incluso en algunos casos mayor que los trastornos por uso de sustancias, siendo la depresión y la ansiedad los que mayor impacto tienen en la población, lo cual desmitifica en gran medida la idea de que el consumo de sustancias es el mayor problema de salud pública respecto a los temas de salud mental, tal vez a la par o por encima, condiciones como la depresión y la ansiedad son altamente incapacitantes y deben ser atendidas con el mismo nivel de calidad. Se menciona también que el impacto es uniforme en todas las\nEn Guerrero no es diferente a la problemática que se enfrenta a nivel nacional, durante el año\n2020 del 100% de hospitalizaciones por consumo de sustancias psicoactivas y otros trastornos mentales y del comportamiento, se presentó con mayor frecuencia en los municipios de Ayutla de los Libres con 30%, Coyuca de Catalán con 25% e Iguala de la Independencia con 15%, de acuerdo al CIE10 la principal causa es por el uso de alcohol con un 85% cuando otras causas solo representan el 5% cada una. La media de edad de estancia hospitalaria es de 33.80 y la media de días de estancia hospitalaria 3.85 días.\n2.1.1. Población Potencial.\nOPERACIÓN\nNiñas y niños de 6 años en adelante y adolescentes de 12 a 19 años que requieran atenciones integrales de promoción e intervención en salud mental, la prevención y el tratamiento del abuso de sustancias adictivas, incluido el uso indebido de estupefacientes y el consumo nocivo de alcohol.\n2.1.2. Población Objetivo.\nPara la aplicación de este Programa se pretende trabajar con la población de niñas y niños matriculados escolarizados, ya que representa un mercado cautivo con el que se cubre la viabilidad, factibilidad y pertinencia de dicho Programa. La población en Guerrero de población escolarizada de 6 a\n14 años de edad es del 94% de la población de 629,575 que pertenece a este grupo, con un aproximado de 122,957 niñas y niños escolarizados del grupo de 15 a 17 años de edad. Según la tasa de escolaridad de 6 a 11 años de edad corresponde al 96.4%, de 12 a 14 años de edad el 76.7% y de 15 a 17 años de edad el 57.5%.\nDe acuerdo a las estadísticas publicadas por la Dirección General de Planeación, Programación y\nEstadística Educativa la población escolarizada de nivel primaria en Guerrero corresponde a 430,709 de nivel primaria, 184,425 de nivel secundaria, y 137,398 de nivel medio superior, lo cual representa aproximadamente 752,532 niñas y niños con las que se estará trabajando.\n2.1.3. Población Beneficiaria.\nEscuelas de nivel básico y niveles medio superiores tantos públicos como privadas en cuya matrícula se encuentran inscritos niñas y niños de 6 años en adelante y adolescentes de 12 a 19 años.\nTales entidades educativas pueden ser primarias, secundarias y nivel bachillerato de las regiones del estado de Guerrero.\n2.1.4. Población Indígena.\nSegún el INEGI, Censo de Población y Vivienda 2010-2020, en Guerrero hay 515,487 personas mayores de 3 años de edad que hablan alguna lengua indígena.\nSegún la Comisión Nacional para el Desarrollo de los Pueblos Indígenas, los grupos con mayor presencia en el estado de Guerrero son, los grupos amuzgos, mixtecos, nahuas y tlapanecos. De cada 100 personas que hablan alguna lengua indígena, 12 no hablan español. En Guerrero el 8.6% de la población total se auto reconoce como población afromexicana.\nEste Programa incluye también a la población indígena, la cual cuenta con el derecho al goce de la salud, por lo que no serán la excepción, ya que se incluirán a niñas y niños de 6 años en adelante y adolescentes de 12 a 19 años de cualquier etnia o pueblo indígena de nuestro estado, teniendo derecho a la prevención, tratamiento y promoción de la salud mental, con la preservación y respeto de sus tradiciones y costumbres.\n2.2. Fundamento Legal.\nOPERACIÓN\nLa Secretaría de Salud es la responsable en la planeación y ejecución del Programa, el cual tiene como fundamento legal lo siguiente:\na) Constitución Política de los Estados Unidos Mexicanos;\nb) Ley General de los Derechos de las Niñas, Niños y Adolescentes;\nc) La Declaración Universal de Derechos Humanos;\nd) Ley General de Salud;\nf) Ley Orgánica de la Administración Pública del Estado de Guerrero Número 242;\ng) Ley Número 454 de Presupuesto y Disciplina Fiscal del Estado Guerrero;\nh) Ley Número 1212 de Salud del Estado de Guerrero;\ni) Ley Número 812 para la Protección de las Niñas, Niños y Adolescentes del Estado de Guerrero;\nk) Ley Número 701 de Reconocimiento, Derechos y Cultura de los Pueblos y Comunidades\nIndígenas y Afromexicanas del Estado de Guerrero;\nl) Decreto Número 181 por medio del cual la Sexagésima Tercera Legislatura al Honorable\n2022-2027;\nm) Decreto por el que se reforman, adicionan y derogan diversas disposiciones de la Ley General\nn) Acuerdo por el que se crea el Consejo de Salud Mental y Contra las Adicciones del Estado de\nGuerrero;\no) Decreto por el que se reforman, adicionan y derogan diversas disposiciones del Reglamento\nInterior de la Secretaría de Salud y de los Servicios Estatales de Salud del Estado de Guerrero;\np) Declaración de los Derechos del Retrasado Mental;\nq) Declaración de Caracas;\nOPERACIÓN\nr) Principios para la Protección de los Enfermos Mentales y el Mejoramiento de la Atención de la\nSalud Mental, adoptados por la Asamblea General de la ONU en su resolución 46/119, de 17 de diciembre de 1991;\ns) Agenda 2030 para el Desarrollo Sostenible, Asamblea General de la ONU; t) Manual de\nRecursos de la OMS sobre Salud Mental, Derechos Humanos y Legislación;\nu) Norma Oficial Mexicana NOM-028-SSA2-2009. Para la Marco normativo prevención, tratamiento y control de las adicciones;\nv) Norma Oficial Mexicana NOM-004-SSA3-2012. del expediente clínico;\nw) Norma Oficial Mexicana NOM-016-SSA3-2012. Que establece las características mínimas de infraestructura y equipamiento de hospitales y consultorios de atención médica especializada;\nx) Norma Oficial Mexicana NOM-025-SSA2-2014. Para la prestación de servicios de salud en unidades de atención integral hospitalaria médico-psiquiátrica;\ny) Lineamientos para la Elaboración de las Reglas de Operación de los Programas Sociales\nEstatales 2022-2027, y z) Todos Aquellos ordenamientos normativos que sean aplicables.\n2.3. Definiciones y Siglas.\nDefiniciones:\nApoyo: Apoyo a través de acciones de promoción de la salud mental y prevención de los trastornos mentales.\nBeneficiarias y Beneficiarios: Las niñas, niños y adolescentes que se inscriban al Programa.\nPrograma: El Programa de Salud Mental Dirigido a Niñas, Niños y Adolescentes.\nReglas de Operación: Conjunto de disposiciones que precisan la forma de operar un programa, con el propósito de transparentar y normar la distribución y entrega de los apoyos.\nPersona Solicitante: Niñas, niños y adolescentes que requieran el servicio.\nSiglas:\nBASM: Brigadas de Apoyo en Salud Mental.\nCESAMA: Coordinación Estatal de Salud Mental y Adicciones. (REFORMADO, P.O. 23 ALCANCE\nDIF: Desarrollo Integral de las Familias.\nOPERACIÓN\nDGIS: Dirección General de Información en Salud.\nECME: Estudio de Carga Mundial de Enfermedad (ECME).\nGI mhGAP: Guía de intervención para los trastornos mentales, neurológicos y por consumo de sustancias en el nivel de atención de salud no especializada.\nGI mhGAP V 2.0: Guía de intervención para los trastornos mentales, neurológicos y por consumo de sustancias en el nivel de atención de salud no especializada Versión 2.\nICATEGRO: Instituto de Capacitación para el Trabajo del Estado de Guerrero.\nIMSS BIENESTAR: Servicios de Salud del Instituto Mexicano del Seguro Social para el\nBienestar (REFORMADO, P.O. 23 ALCANCE XI, 21 DE MARZO DE 2025).\nINSABI: Instituto de Salud para el Bienestar.\nISSSTE: Instituto de Seguridad y Servicios Sociales de los Trabajadores del Estado.\nINEGI: Instituto Nacional de Estadísticas y Geografía.\nLGBTQI+: Lésbico, Gay, Bisexual, Trans, Queer e Intersexual (REFORMADO, P.O. 23 ALCANCE XI,\n21 DE MARZO DE 2025).\nODS: Objetivos de desarrollo sostenibles.\nOMS: Organización Mundial de la Salud.\nONU: Organización de las Naciones Unidas.\nPEMEX: Petróleos Mexicanos.\nSCyTG: Secretaría de Contraloría y Transparencia Gubernamental.\nSEFINA: Secretaría de Finanzas y Administración.\nSEG: Secretaría de Educación Guerrero.\nSMA: Salud Mental y Adicciones.\nUNEME-CAPA: Unidades de Especialidades Médicas-Centro de Atención Primaria Contra las\nAdicciones.\nOPERACIÓN\nCOSAMA: Consejo de Salud Mental y contra las Adicciones del Estado de Guerrero\nSSA: SECRETARIA DE SALUD Y SERVICIOS ESTATALES DE SALUD (REFORMADO, P.O. 23\nUNEME-CECOSAMA: Unidades de Especialidades Médicas-Centro Comunitario de Salud\nMental y Adicciones (REFORMADO, P.O. 23 ALCANCE XI, 21 DE MARZO DE 2025).\nRENASME: Reporte Nacional de Adicciones y Salud Mental (REFORMADO, P.O. 23 ALCANCE XI,\n21 DE MARZO DE 2025).\n3. Objetivos y Alcances.\n3.1. Objetivo General.\nBrindar a las niñas, niños y adolescentes acciones integrales de promoción de salud mental para promover estilos de vida saludables y acciones de prevención, dirigidas a los principales trastornos de salud mental acordes al curso de vida, con un enfoque de equidad, inclusión y derechos humanos.\nRealizar identificación oportuna en niñas, niños y adolescentes a través de servicios integrales de prevención, promoción e intervención para la salud, a lo largo de la línea de la vida.\nA través de las siguientes acciones:\na) Promoción de la salud mental.\nb) Capacitación a madres/padres en habilidades de crianza.\nc) Capacitación a profesoras y profesores en la detección de trastornos del desarrollo y del\nComportamiento.\nd) Intervenciones terapéuticas basadas en el aprendizaje socioemocional, regulación emocional, habilidades interpersonales, atención plena y manejo de estrés.\ne) Entrenamiento en el manejo de estrés.\nf) Concientización sobre el uso indebido de alcohol y drogas.\ng) Capacitación en la GI mhGAP V 2.0 para la identificación de trastornos de salud mental a personas trabajadoras de salud del primer nivel de atención.\nh) Ferias de la salud.\nOPERACIÓN\nj) Educación y sensibilización universal sobre el suicidio (REFORMADO, P.O. 23 ALCANCE XI, 21\nk) Pláticas sobre el autocuidado y salud mental (REFORMADO, P.O. 23 ALCANCE XI, 21 DE MARZO\nDE 2025).\nl) Talleres de “Habilidades para la vida” (REFORMADO, P.O. 23 ALCANCE XI, 21 DE MARZO DE 2025).\nm) Contención emocional a personas en proceso de duelo (REFORMADO, P.O. 23 ALCANCE XI, 21\nDE MARZO DE 2025).\nn) Talleres de “Habilidades para la vida”. o) Contención emocional a personas en proceso de duelo.\np) Atención especializada a grupos vulnerables (población indígena, migrantes, personas de la comunidad LGBTTTI).\nCada una de las acciones a realizar en el marco del Programa contará con un estricto apego a los derechos humanos y enfoque de perspectiva de género, cuya finalidad es contar con entornos respetuosos e incluyentes. La población objetivo para desarrollar las acciones descritas serán niñas y niños de 6 a 11 años y adolescentes de 12 a 19 años, cabe destacar que si otro tipo de población distinta a la señalada requiere el servicio se le proporcionará sin distinción alguna.\n3.2. Objetivo Específico.\na) Contribuir a la reorientación de servicios de salud mental, fomentando la promoción de estilos de vida saludables y prevención del consumo de sustancias psicoactivas.\nb) Aumentar la resiliencia emocional y reducir la vulnerabilidad a los problemas de salud mental a través del desarrollo de habilidades personales que conducen a una mayor capacidad para hacer frente a las transiciones y el estrés de la vida.\nc) Construir entornos saludables y fomentar redes sociales inclusivas y de apoyo.\nSe realizará sinergia con instancias, instituciones y organizaciones civiles que permitan coadyuvar para cumplir con el objetivo del Programa, de tal manera que la SEG, los ayuntamientos municipales, la diferentes programas de la SEG y comunidades del estado de Guerrero, se sumarán a las actividades a desarrollar, teniendo como resultado final la suma de esfuerzos y la población objetivo beneficiada así como la reducción del estigma y la discriminación en población con problemas relacionados a la salud mental.\n3.3. Cobertura.\nLa CESAMA, tiene a su cargo 11 UNEME-COSAMA, distribuida en las 8 regiones de la entidad,\nOPERACIÓN\n1. Altamirano.\n2. Iguala de la Independencia.\n3. Taxco de Alarcón.\n4. Chilpancingo de los Bravo.\n5. Tlapa de Comonfort.\n6. Zihuatanejo de Azueta.\n7. Coyuca de Benítez.\n8. San Marcos.\n9. Ometepec.\n10. Acapulco (Colonia Progreso).\n11. Acapulco (Ciudad Renacimiento).\nDentro de la estructura también hay profesionales de la salud ubicados en cada una de las jurisdicciones sanitarias del estado, distribuidas de la siguiente manera:\n•Jurisdicción Sanitaria 01 Tierra Caliente\n•Jurisdicción Sanitaria 02 Norte\n•Jurisdicción Sanitaria 03 Centro\n•Jurisdicción Sanitaria 04 Montaña\n•Jurisdicción Sanitaria 05 Costa Grande\n•Jurisdicción Sanitaria 06 Costa Chica\n•Jurisdicción Sanitaria 07 Acapulco psicología, licenciadas y licenciados en trabajo social, médicas y médicos generales, así como promotoras y promotores de salud.\n3.4. Alcances. que se definan objetivos, el mensaje clave que se desea transmitir, la selección de destinatarios, la elección de canales de comunicación, el diseño de materiales de comunicación a la población a la que van dirigidos.\nPara poder realizar cada una de las acciones de intervención se requiere material impreso (folletos), artículos de papelería, gastos de imprenta, compra de material de promoción, gastos de camino/viáticos,\nOPERACIÓN combustible, servicio general a vehículos oficiales, compra de insumos de seguridad e higiene, compra de mobiliario de oficina y equipo informático.\n4. Metas Físicas.\nEl Programa contempla realizar 90 actividades de promoción de la salud mental, 90\n{\"tabla_1\":{\"columnas\":[\"Acción\",\"Indicador\",\"Descripción del\\nIndicador\",\"Meta\",\"Recurso\"],\"filas\":[{\"columna_1\":\"Brindar a las\\nniñas, niños y\\nadolescentes\\nacciones\\nintegrales de\\npromoción de\\nsalud mental para\\npromover estilos\\nde vida\\nsaludables.\",\"columna_2\":\"Porcentaje de acciones\\nintegrales brindadas a\\nniños, niñas y\\nadolescentes con\\ntrastorno mentales\",\"columna_3\":\"Beneficiar a niñas,\\nniños y adolescentes a\\ntravés de acciones\\nintegrales de\\npromoción de salud\\nmental y promover\\nestilos de vida\\nsaludable, acordes al\\ncurso de vida, con un\\nenfoque de equidad,\\ninclusión y derechos\\nhumanos.\",\"columna_4\":\"100%\",\"columna_5\":\"$2,000,000\"}]}}\n5.1. Gastos de Operación. este Programa, dicho recurso será destinado para realizar diversas acciones y estrategias\nOPERACIÓN asociadas con efecto de logística, planeación, supervisión y seguimiento (REFORMADO, P.O. 23\n6. Criterios y Requisitos de Elegibilidad.\na) Convocatoria: Se realizará la difusión de convocatoria a través de la Secretaría\nEducación, especificando los requisitos y características del Programa que deben cumplir las niñas, niños y adolescentes. (REFORMADO, P.O. 23 ALCANCE XI, 21 DE MARZO DE 2025)\nb) Registro: El registro se realizará a través del CASAMA, en coordinación con la SEG, identificando geográficamente la ubicación de la población. (REFORMADO, P.O. 23 ALCANCE XI, 21 DE MARZO\nDE 2025)\nc) Beneficiarias y Beneficiarios: niñas, niños y adolescentes que se encuentren oficialmente inscritos en las instituciones de educación. (REFORMADO, P.O. 23 ALCANCE XI, 21 DE MARZO DE 2025)\nd) El Programa: Podrán ser beneficiados las niñas, niños y adolescentes que cumplan con los criterios de selección establecidos en las presentes Reglas de Operación. (REFORMADO, P.O. 23\nALCANCE XI, 21 DE MARZO DE 2025)\ne) El Programa: Las niñas, niños y adolescentes que cumplan con los criterios de selección establecidos en las presentes Reglas de Operación, podrán ser beneficiados.\n7. Tipo, Monto y Periodicidad del Apoyo.\nLa cantidad de apoyos, así como el monto de apoyo, y su periodicidad, quedarán sujetos a la autorización que emita el CESAMA.\nEstos conceptos de apoyo, son indicativos, no limitativos y podrán considerarse otros apoyos, previa autorización del CESAMA.\n7.1. Característica de los Apoyos.\nMATERIAL UNIDADES\nGuía Preventiva para padres y maestros 1000\nLona para actividades lúdicas 40\nMorrales con logos de NNA 1,000\nDominó de las emociones 100\nLotería de las emociones 100\nCilindros para agua con logos NNA 1,000\nPelotas anti Estrés con logos NNA 1,000\nBalón de futbol con logos NNA 500\nOPERACIÓN\nPlayeras con logos NNA 500\nGorras niños con logos NNA 2,000\nTermos con logos NNA 100\nLapiceros 5000\nAcrílico separador para escucha. 20\nTríptico de Depresión. 5000\nTríptico de Ansiedad. 5000\nTríptico de Mitos del suicidio. 5000\nTríptico de Autocuidado 5000\nTríptico de Autismo 5000\nTríptico de Mindfulnees 5000\nTríptico de Estrés 5000\nTríptico de Recomendaciones a los Padres. 5000\nTríptico de Depresión. 5000\n(REFORMADO, P.O. 23 ALCANCE XI, 21 DE MARZO DE 2025)\n7.2. Recursos no Devengados.\nEl recurso que no se haya aplicado para los fines autorizados y todos que por cualquier motivo no se hayan devengado al 31 de diciembre del presente año, serán reintegrados a la instancia normativa del ejercicio y control del gasto público, es decir a la SEFINA.\n7.3. Resguardo de la Documentación.\nUna vez terminadas de realizar las actividades y/o acciones descritas en el Programa, todos los materiales comprobatorios de los recursos ejercidos serán resguardados en la Coordinación Estatal de\nSalud Mental y Contra las Adicciones, ubicada en Calle Venustiano Carranza Número 18, Colonia 20 de\nNoviembre, Chilpancingo de los Bravo, Guerrero.\n7.4. Supervisión y Control.\nLas actividades a realizar en el marco del Programa, serán evaluadas y supervisadas a través de indicadores y metas contenidas en el apartado 4 (metas físicas) del presente Programa. Mismas que serán\nMental y Adicciones, para el reporte de acciones (indicadores) y evaluación de metas. (REFORMADO, Esta evaluación estará a cargo de la Secretaria de Salud, a través del CESAMA. (REFORMADO,\nOPERACIÓN\n8. Criterios de Selección.\nEl COSAMA, en coordinación con la Secretaría de Educación Guerrero, definirán las focalizada en los municipios que se tiene presencia con las UNEMES- CECOSAMA así como con las Jurisdicciones Sanitarias. (REFORMADO, P.O. 23 ALCANCE XI, 21 DE MARZO DE 2025)\na) Criterios de Inclusión.\n1. Niñas y niños de 6 años en adelante y adolescentes de 12 a 19 años en situación de vulnerabilidad.\n2. Tener factores de riesgo en las áreas de vida: personal, familiar, escolar, etc.\n3. Que presenten algún padecimiento actual de SMA.\n4. Tener familiar con problemas de salud mental y adicciones.\n5. Que cuenten con tutora o tutor o familiar responsable.\n6. Domicilio permanente.\nb) Metodología de Identificación.\nSe realizará un censo o base de datos con información general de niñas, niños y adolescentes, que contenga los siguientes rubros: nombre con apellidos, CURP, fecha de nacimiento, nombre de la madre o padre de familia o de la persona tutora, domicilio, teléfonos de referencia, escolaridad, padecimientos actuales.\nc) Permanencia.\n● Acatar las disposiciones de los lineamientos del presente Programa.\n● Asistir a las diferentes actividades preventivas (sesiones informativas y de sensibilización, talleres, pláticas, etc.)\n● En caso de cambio de domicilio, avisar a la entidad supervisora (CESAMA).\n● Acudir a sesiones de intervención psicológica en SMA, evitando faltar a más de 3 sesiones consecutivas.\n● En caso de abandono de tratamiento injustificado, se procederá a la baja del Programa.\nd) Formas y tramites de incorporación.\nOPERACIÓN de los servicios estatales de salud se realizará la difusión de dicho Programa.\nLos requisitos de incorporación será el cumplimiento de los criterios de inclusión, mismos que serán valorados en entrevistas por personal del módulo de Atención a Niñas, Niños y Adolescentes.\nRespecto a los trámites de incorporación, todas y todos los beneficiarios deberán acudir al módulo de Atención con la documentación siguiente:\n1. Acta de nacimiento.\n2. CURP.\n3. Identificación oficial de la madre o padre de familia o de la persona tutora.\n4. Comprobante de domicilio.\n8.1. Casos Especiales.\nEl mecanismo de operación en caso de inasistencia a las actividades preventivas llevados a cabo en los centros educativos, será con forme a la lista de asistencia del grupo y fecha correspondientes de acuerdo al calendario escolar vigente. En caso de cancelación del calendario programado por cuestiones ajenas a las instituciones, se realizará una nueva programación en cuanto existan las posibilidades de llevarse a cabo, sin afectar las demás actividades programadas en las dependencias en coordinación. (REFORMADO, P.O. 23 ALCANCE XI, 21 DE MARZO DE 2025)\n8.2. Casos de Emergencia o Desastre.\nEn caso de declaratoria de emergencia o de desastre, se brindará apoyo socioemocional en materia de salud mental, a través de las Brigadas de Apoyo en Salud Mental (BASM). La cobertura de la atención será focalizada en los primeros auxilios psicológicos, contención emocional, estrategias o establecimiento destinado al resguardo y protección de la población.\n8.3. Suspensión o Cancelación del Programa Social.\nSe podrá suspender la operación del Programa en los supuestos siguientes:\n● Falta de apoyo económico, material e insumos para la realización de actividades.\n● Más de 2 faltas consecutivas injustificadas a las diferentes actividades preventivas (sesiones informativas y de sensibilización, talleres, pláticas, etc.); Falta de aviso a la entidad supervisora en caso de\nOPERACIÓN cambio de domicilio; faltar a más de 3 sesiones de intervención psicológica consecutivas; abandono de tratamiento injustificado.\n8.4. Integración del Padrón de Personas Beneficiarias.\nUna vez establecida la coordinación entre la Secretaria de Salud y la Secretaria de\nEducación Guerrero, se beneficiarán la población estudiantil inscrita en la institución educativa, así como la planta docente y padres de familia pertenecientes al mismo plantel educativo donde se realizarán las actividades. (REFORMADO, P.O. 23 ALCANCE XI, 21 DE MARZO DE 2025)\nSe tomará como referencia la base de datos basada en la metodológica (identificación) contenida en el apartado 8. Criterios de selección del presente Programa.\n9. Mecánica Operativa del Programa Social.\n9.1. Instancia Ejecutora y/o Responsable.\nLa instancia responsable de la operación del presente Programa, así como la ejecución del gasto será el Consejo Estatal de Salud Mental y contra las Adicciones (CESAMA).\n9.2. Proceso de Incorporación al Programa Social. determinarán los centros educativos donde se llevará a cabo el programa en mención, de acuerdo\n10. Evaluación.\nLas evaluaciones del Programa se realizarán de manera cualitativa y cuantitativa, de tal manera que se medirán los alcances descritos en las metas, así como el impacto alcanzado en la\n10.1. Indicadores (Construcción de la Matriz de Indicadores para Resultados. -Anexo 1).\nOPERACIÓN\nOPERACIÓN\nOPERACIÓN\nOPERACIÓN\n10.2. Seguimiento.\nTodo gasto realizado para el cumplimiento y operación del Programa, será comprobado como lo establecen las Reglas de Operación, el seguimiento a las acciones realizadas será constante y se revisarán listas de asistencia, evidencia fotográfica y monitoreo a la población beneficiada.\n10.3. Auditoría.\nLa auditoría es una función de fiscalización de los recursos autorizados para este Programa con lo cual podrán constatar su correcta aplicación y promover la eficacia y transparencia en sus operaciones y verificar el cumplimiento de los objetivos y metas programados.\nLos recursos asignados para la operación del Programa no pierden su carácter estatal, por lo que la SEFINA, la SCyTG y la Auditoría Superior del estado de Guerrero, en el ámbito de sus respectivas competencias, realizarán actividades de fiscalización y auditoría.\nLa Secretaria de Salud dará todas las facilidades a las instancias fiscalizadoras para realizar en el momento que juzguen pertinente, las auditorías necesarias; asimismo, efectuará el seguimiento y la solventación de las observaciones por irregularidades planteadas por los órganos de control en tiempo y forma.\n11. Mecanismos de Entrega del Apoyo.\nLas actividades de prevención y promoción de la salud mental son acciones universales dirigidas a niñas, niños y adolescentes, las cuales se realizan solo con la asistencia de las personas\n12. Derechos y Obligaciones de las Personas Beneficiadas.\na) Derechos:\nI. Recibir atención psicológica adecuada;\nII. Recibir trato digno y respetuoso;\nIII. Recibir información suficiente, clara y veraz;\nb) Obligaciones:\nOPERACIÓN\nI. Informar al personal de salud en forma completa y veraz, acerca de los síntomas y\nIII. Informar al personal de salud en forma completa y veraz, acerca de los síntomas y posibles causas de su padecimiento;\nIV. Cumplir con la normatividad vigente, y\nV. En caso de no poder asistir a sus citas, avisar a la unidad y/o reagendar cita.\n12.1. Causales de Suspensión o Baja de las Personas Beneficiadas.\nToda vez que la persona beneficiaria incumpla algunos puntos de las obligaciones y con el protocolo de ingreso al Programa tendrá que ser suspendida del mismo.\n12.2. Proceso de Baja.\nSe realizarán sinergias con otras instancias/instituciones para impactar la mayor población objetivo posible, de tal manera que se abordarán instituciones educativas, así como población urbana y rural.\n13. Instancias Participantes.\na) Secretaría de Salud.\nb) IMSS-BIENESTAR. (REFORMADO, P.O. 23 ALCANCE XI, 21 DE MARZO DE 2025)\nc) COSAMA. (REFORMADO, P.O. 23 ALCANCE XI, 21 DE MARZO DE 2025)\nd) Personal responsable estatal del Programa de Salud Mental y Contra las Adicciones.\n13.1. Instancia Normativa.\nI. La SEPLADER, con la validación y aprobación de las Reglas de Operación.\nII. La SEFINA, con la ministración de recursos presupuestales para la operación del Programa.\nIII. La SCyTG, es un ente que puede realizar la fiscalización del Programa.\nIV. La Secretaría de Salud, es la instancia ejecutora del Programa, a través del CESAMA.\nOPERACIÓN\n14. Transparencia.\nPara garantizar el acceso y transparencia de todas las niñas, niños y adolescentes que cumplieron con los registros en tiempo y forma, el seguimiento detallado y auditado en la operación del Programa se llevará a cabo por medio de la Contraloría Interna de la Secretaría de Salud.\nCon base a lo establecido en la Ley Número 207 de Transparencia y Acceso a la Información\nPública del Estado de Guerrero, la Secretaría de Salud publicará periódicamente la información relacionada a la operación del Programa.\nLos datos recabados de las personas beneficiarias serán protegidos en confidencialidad, de acuerdo a lo establecido en Instituto Nacional de Transparencia, Acceso a la Información y Protección de\nDatos Personales.\n14.1. Promoción y Difusión del Programa Social.\nLa difusión del Programa se realizará a través de la página oficial de la Secretaría de Salud, así como de la página oficial del CESAMA. De igual manera se dará difusión en las 11 UNEME-CECOSAMA y las 7 Jurisdicciones Sanitarias. (REFORMADO, P.O. 23 ALCANCE XI, 21 DE MARZO DE 2025)\n14.2. Contraloría Social.\nLa SCyTG será la autoridad competente para realizar el control, vigilancia y evaluación del\nPrograma.\n14.3. Protección de Datos Personales.\nLas 11 UNEME-CECOSAMA, se encuentran inscritas al Instituto Nacional de Transparencia, Acceso a la Información y Protección de Datos Personales, lo que garantiza la confidencialidad de datos recabados a las personas. (REFORMADO, P.O. 23 ALCANCE XI, 21 DE MARZO DE 2025)\n14.4. Quejas y Denuncias.\nDentro de las UNEME-CECOSAMA se encuentran instalados buzones en físico para que las personas depositen sus papeletas con las opciones de: queja, sugerencia o felicitaciones, mismos que cada mes se apertura frente a un aval ciudadano para su puntual seguimiento hasta la resolución.\n14.5. Acciones de Blindaje.\nEste Programa se utilizará sin fines políticos, electorales, de lucro y otro distinto a lo establecido por las leyes federales y estatales aplicables a las disposiciones emitidas por las autoridades electorales.\n14.6. Acta de Donación.\nOPERACIÓN\nEl Programa no contempla, la figura de donación en el otorgamiento de apoyos, en consecuencia, Programas Sociales Estatales para el periodo 2022-2027, publicados en el Periódico Oficial del Gobierno\n15. Perspectiva de Género.\nTodas las acciones tanto de promoción como de intervenciones realizadas por personal de Salud\nMental y Adicciones, incluyen perspectiva de género y el estricto apego a los derechos humanos, teniendo programas de intervención focalizados para mujeres en diferentes condiciones. (REFORMADO, P.O. 23\nALCANCE XI, 21 DEMARZO DE 2025)\n16. Enfoque de Derechos.\nEn la aplicación del Programa, se harán valer los derechos de las personas beneficiarias tomando en consideración los factores de desigualdad de cada persona, así como su condición en diferentes áreas de la vida.\n17. Acciones contra el SARS-COV 2.\nLas medidas sanitarias que se llevarán a cabo son las descritas por las autoridades sanitarias, como es la aplicación de gel antibacterial, el lavado constante de manos, el uso correcto del cubre boca.\n18. Anexos que Reflejen la Entrega de Apoyo (Económico, Especie o Servicios).\nAnexo 1. MIR\nOPERACIÓN\nSALUD\nFormato 4. MIR\nEje: 1. Bienestar, Desarrollo Humano y Justicia Social\n1.11 Mejorar la calidad de vida de cada guerrerense, medienta la aplicación de políticas públicas intersectoriales, a través de la\nObjetivo: transformación del Sistema de Salud del Estado.\nEstrategia: 1.11.1 Fortalecer la vinculación interinstitucional del Sector Salud\nLínea de Acción: 1.11.1.3 Implementar los mecanismos necesarios para la operación del convenio de htercambio de servicios en el sector.\nMatriz de indicadores para Resultados\nResumen Narrativo Indicadores de desempeño Medios de Verificación Supuestos\nContr buir al derecho a la protección de la salud mediante el acceso digno, corresponsable, oportuno, eficiente y con altos estándares de calidad que aseguren la equidad en la prestación de los servicios en el Estado de Guerrero.\nLa población del Estado de Guerrero cuenta con Servicios de salud de calidad\nPropósito en salud mental, oncológica y de\n(resultados) unidades apIlativas para atender las actividades forenses. https://www.guerrero.gob. Los niños, niñas y\nComponentes\nPrograma de Salud Mental dirijido a niñas, Porcentaje de población NNA atendida mx adolescentes que acuden a\n(Servicios y niños y adolescentes. en trastornos mentales /dependencia/sector- acciones preventivas e\nProductos) central/secretaria-de-salud/ intervenciones psicológicas\nLos niños, niñas y\nPorcentaje de acciones integrales https://www.guerrero.gob.\nActividades Impulsar proyectos de atención a las NNA mx adolescentes que acuden a la brindadas a niños, niñas y adolecentes\n(Procesos) para prevenir riesgos psicosociales /depende ncia/sector- aplicación de factores con trastornos mentales central/secretaria-de-salud/ protectores psicosociales.\nEl personal docente que https://www.guerrero.gob.\nPorcentaje de capacitaciones otorgadas mx relacionados a la salud mental de Niños, temas de salud mental para a docentes en temas de salud mental /dependencia/sectorniñas y adolescentes. niños, niñas y adolescentes. central/secretaria-de-salud/\nPrimero. El presente Acuerdo entrará en vigor al día siguiente de su publicación en el Periódico\nOPERACIÓN\nSegundo. Se abroga el Acuerdo por el que se crea el Programa Salud Mental dirigido a Niñas, Niños y Adolescentes y se emiten sus Reglas de Operación, publicado en el Periódico Oficial del Gobierno del Estado de Guerrero, No. 50 Alcance I de fecha 23 de junio del 2023.\nTercero. A partir de la entrada en vigor del presente Acuerdo, las Reglas de Operación del\nPrograma de Salud Mental dirigido a Niñas, Niños y Adolescentes, subsecuentes o sus modificaciones serán emitidas por la persona titular de la Secretaría de Salud del estado de Guerrero, responsable directa de la operación y ejecución de estas.\nDado en el “Recinto de las oficinas del Poder Ejecutivo del Estado” el inmueble ubicado en el número 62, en Boulevard René Juárez Cisneros, Código Postal 39074, colonia Ciudad de los Servicios en\nChilpancingo de los Bravo, capital del estado de Guerrero, a los doce días del mes de abril del año dos mil veinticuatro.\nLA GOBERNADORA CONSTITUCIONAL DEL ESTADO DE GUERRERO.\nMTRA. EVELYN CECIA SALGADO PINEDA.\nRúbrica.\nLA SUBSECRETARIA DE GOBIERNO, ASUNTOS JURÍDICOS Y DERECHOS HUMANOS\nENCARGADA DE DESPACHO DE LA SECRETARIA GENERAL DE GOBIERNO.\nDRA. ANACLETA LÓPEZ VEGA.\nRúbrica.\nLA SECRETARIA DE SALUD.\nDRA. AIDÉ IBÁREZ CASTRO.\nRúbrica.\nN. DE E. A CONTINUACIÓN, SE TRANSCRIBEN LOS ARTÍCULOS TRANSITORIOS DE LOS ACUERDO\nDE MODIFICACIÓN A LAS PRESENTES REGLAS DE OPERACIÓN.\nMENTAL DIRIGIDO A NIÑAS, NIÑOS Y ADOLESCENTES, Y SE EMITEN SUS REGLAS DE\nOPERACIÓN.\nPrimero. El presente Acuerdo entrará en vigor al día siguiente de su publicación en el Periódico\nSegundo. Se derogan todas las disposiciones que se opongan al presente Acuerdo de\nModificación.",
  "ordenamiento": "PROGRAMA",
  "jurisdiccion": "GUERRERO",
  "fuente_oficial": "DIARIO OFICIAL DE LA FEDERACION",
  "Fecha de Publicación": "21 DE MARZO DE 2025",
  "ULTIMA REFORMA PUBLICADA": null,
  "status": "VIGENTE",
  "es_escaneado": false,
  "tiene_tablas": true,
  "materia": [
    "derechos de la niñez",
    "salud"
  ]
}