{
  "titulo": "Acuerdo por el Que Se Crea el Programa de Autoempleo Productivo para el Bienestar de Comunidades Jor",
  "Contenido": "REGLAS DE OPERACIÓN\nTEXTO ORIGINAL.\nEL BIENESTAR DE COMUNIDADES JORNALERAS, Y SE EMITEN SUS REGLAS DE OPERACIÓN.\nGuerrero. - Poder Ejecutivo.\nMAESTRA EVELYN CECIA SALGADO PINEDA, GOBERNADORA CONSTITUCIONAL DEL ESTADO\nDE GUERRERO, CON FUNDAMENTO EN LO DISPUESTO POR LOS ARTÍCULOS 71, 87, 88, 90\nLOS ARTÍCULOS 2, 4, 8, 9, 14, 22 APARTADO A FRACCIONES I Y XVII, 23 FRACCIÓN III Y 39 DE LA\nLEY ORGÁNICA DE LA ADMINISTRACIÓN PÚBLICA DEL ESTADO DE GUERRERO NÚMERO 242;\n47 FRACCIÓN I DE LA LEY DE COORDINACIÓN FISCAL; 1, 2 FRACCIÓN I, 18 Y 25 DE LA LEY\nNÚMERO 454 DE PRESUPUESTO Y DISCIPLINA FISCAL DEL ESTADO DE GUERRERO; 3 DE LA LEY\nNÚMERO 838 DE ATENCIÓN A LOS MIGRANTES DEL ESTADO DE GUERRERO; EN RELACIÓN CON\nEL ARTÍCULO 47 Y ANEXO 23 DEL DECRETO NÚMERO 424 DEL PRESUPUESTO DE EGRESOS DEL\nESTADO DE GUERRERO PARA EL EJERCICIO FISCAL 2023, Y LOS LINEAMIENTOS PARA LA\nELABORACIÓN DE LAS REGLAS DE OPERACIÓN DE LOS PROGRAMAS SOCIALES ESTATALES\nPARA EL PERIODO 2022-2027.\nQue el Plan Estatal de Desarrollo 2022-2027, en su objetivo B.10., mandata “Atender integralmente a los migrantes nacionales, poniendo énfasis en los jornaleros agrícolas guerrerenses que emigran de sus localidades de origen a otros municipios del estado y al interior de la República, para mejorar sus condiciones de vida y de trabajo, a través de alternativas productivas que detonen el desarrollo regional y generen un contexto propicio al arraigo; transversalizando y operando un Programa Estratégico Integral de\nApoyo en el Ciclo Migratorio de Migrantes Nacionales, en especial de jornaleros agrícolas y para el desarrollo de las regiones con alta marginación y/o expulsoras de jornaleros agrícolas de la entidad”.\nQue, en el citado Plan Estatal de Desarrollo se plantea la estrategia B.10.2. de fortalecimiento de derechos sociales, empleo productivo y arraigo, a través de la línea de acción B.10.2.2. “Definir, operar y evaluar para el bienestar con equipamiento, promoción social, fomento organizativo y capacitación microempresarial, induciendo a otros programas sociales a focalizar acciones en comunidades expulsoras de jornaleros agrícolas migrantes”.\nQue la política estatal con el lema “Transformando Guerrero”, tiene la firme convicción de combatir de manera frontal tanto los rezagos históricos que ha padecido el estado de Guerrero, bajo los principios de la Cuarta Transformación. Estos propósitos sólo se pueden lograr, escuchando las voces de los jornaleros\nREGLAS DE OPERACIÓN agrícolas marginados y más necesitados del medio rural; promoviendo y fortaleciendo el desarrollo de capacidades de las y los habitantes del campo que han sobrevivido con grandes carencias.\nQue es de suma importancia, implementar programas que fortalezcan atender integralmente a los migrantes nacionales, poniendo énfasis en las y los jornaleros agrícolas guerrerenses que emigran de sus localidades de origen a otros municipios del estado y al interior de la República, para mejorar sus condiciones de vida y de trabajo, a través de alternativas productivas que detonen el desarrollo regional y generen un contexto propicio al arraigo; transversalizando y operando un Programa Estratégico Integral de\nApoyo en el Ciclo Migratorio de Migrantes Nacionales, en especial de jornaleras y jornaleros agrícolas y para el desarrollo de las regiones con alta marginación y/o expulsoras de jornaleras y jornaleros agrícolas de la entidad. instituye que el estado atenderá de manera programática y planificada los derechos económicos, sociales, culturales y ambientales para hacer realidad el progreso y el bienestar de sus habitantes.\nQue la Ley Número 838 de Atención a los Migrantes del Estado de Guerrero, establece que el gobierno del estado reconocerá, promoverá y garantizará a los migrantes y sus familias, el ejercicio pleno de sus derechos conforme a lo establecido por la Constitución Política de los Estados Unidos Mexicanos, la materia de los cuales el Estado Mexicano sea parte y demás disposiciones jurídicas aplicables.\nQue derivado del Decreto Número 424 del Presupuesto de Egresos del Estado de Guerrero para el Ejercicio\nFiscal 2023, publicado en el Periódico Oficial del Gobierno del Estado No. 103, de fecha 27 de diciembre de 2022, señala que las secretarías, dependencias y entidades de la administración pública estatal, podrán ejercer los montos para programas y proyectos de inversión aprobados en este presupuesto, en los términos de las disposiciones emitidas por la Secretaría de Finanzas y Administración del estado y la\nSecretaría de Planeación y Desarrollo Regional, en función de la disponibilidad presupuestal y financiera del estado.\nQue el citado Decreto Número 424 en su artículo 47, establece que, con el objeto de asegurar la aplicación eficiente, eficaz, oportuna, equitativa y transparente de los recursos públicos, la Secretaría de Finanzas y\nAdministración y la Secretaría de Planeación y Desarrollo Regional, emitirán las disposiciones a que deberán sujetarse los programas de inversión sujetos a reglas de operación.\nQue la Secretaría de Planeación y Desarrollo Regional, expidió los Lineamientos para la Elaboración de las Reglas de Operación de los Programas Sociales Estatales, para el periodo 2022-2027, publicadas en de operación, así como los elementos para integrar su contenido.\nQue, por consiguiente, las personas titulares de las secretarías y/o entidades paraestatales de la administración pública, así como las servidoras y servidores públicos autorizados para ejercer recursos públicos del presupuesto e inversión de los mismos, serán responsables de los programas y/o proyectos\nREGLAS DE OPERACIÓN de inversión que aplican, en que los apoyos otorgados deberán sujetarse a los criterios de objetividad, equidad, transparencia, publicidad, selectividad y temporalidad.\nQue conforme al artículo 39 de la Ley Orgánica de la Administración Pública del Estado de Guerrero\nNúmero 242, la Secretaría de los Migrantes y Asuntos Internacionales, es el órgano encargado de regular, conducir y evaluar las políticas públicas de la movilidad humana migratoria y de la paradiplomacia de la entidad, garantizando la promoción, respeto, protección de los derechos humanos de las personas guerrerenses que migran de sus localidades de origen a otros municipios del estado, al interior de la\nRepública, que se encuentran radicados en el extranjero.\nQue el Programa a cargo de la Secretaría de los Migrantes y Asuntos Internacionales tiene como objetivo general, apoyar a las y los jornaleros agrícolas migrantes de Guerrero así como a miembros de sus familias en propensión de emigrar, con el equipo, herramientas y accesorios necesario para que emprendan un proyecto productivo de autoempleo, con el apoyo de promoción social y fomento organizativo, dirigidos al fomento y mejoramiento de las actividades agropecuarias, microindustriales y agroindustriales, de servicios y artesanales, para la reactivación de cadenas productivas y circuitos microrregionales de produccióncomercialización-consumo.\nPor lo anteriormente expuesto y con fundamento en las disposiciones legales antes citadas, he tenido a bien expedir el siguiente:\nACUERDO POR EL QUE SE CREA EL PROGRAMA DE AUTOEMPLEO PRODUCTIVO PARA EL\nBIENESTAR DE COMUNIDADES JORNALERAS, Y SE EMITEN SUS REGLAS DE OPERACIÓN.\nArtículo 1. Se crea el Programa de Autoempleo Productivo para el Bienestar de Comunidades Jornaleras, el cual tiene como objetivo, impulsar la puesta en marcha y operación de proyectos productivos, de equipamiento e infraestructura complementaria, dirigidas al fomento y mejoramiento de las actividades agropecuarias, microindustriales y agroindustriales, de servicios y artesanales en las regiones de la entidad, para la reactivación de cadenas productivas y circuitos microrregiones de producción-comercializaciónconsumo.\nArtículo 2. La Secretaría de los Migrantes y Asuntos Internacionales, tendrá a cargo la implementación, operación, ejecución, evaluación y administración del Programa de Autoempleo Productivo para el\nBienestar de Comunidades Jornaleras, bajo los criterios de objetividad, equidad, transparencia, publicidad, selectividad y temporalidad, con estricto apego a la normatividad aplicable, encargada de la dispersión y asignación de los recursos del Programa, sujetándose plenamente a las Reglas de Operación.\nArtículo 3. Se emiten las Reglas de Operación del Programa de Autoempleo Productivo para el Bienestar de Comunidades Jornaleras, en las cuales se establece el procedimiento de ejecución del Programa, los principios, requisitos y condiciones que deben observarse para acceder al mismo, en los términos siguientes:\nDE COMUNIDADES JORNALERAS.\nREGLAS DE OPERACIÓN\n1. Introducción.\n1.1. Antecedentes.\nAnte la necesidad de atender a las y los migrantes nacionales, específicamente a la población jornalera\nInternacionales, órgano encargado de regular, conducir y evaluar la política estatal en materia de migración en el estado, al cual corresponde atender integralmente a las comunidades de guerrerenses que emigran de sus lugares de origen a otros municipios del estado, así como al interior de la república, tiene por objeto fomentar una atención integral para la población de trabajadoras y trabajadores agrícolas migrantes de la entidad, contribuyendo a disminuir sus déficits sociales, mediante una estrategia basada en la planeación para la coordinación e implementación de acciones intersecretariales, que en el ámbito de sus competencias se involucran en el aseguramiento de la salud, educación, seguridad social, vivienda, desarrollo social, desarrollo rural, protección del medio ambiente y protección integral de la familia en beneficio de la población jornalera agrícola migrante de Guerrero, orientada a disminuir el flujo de jornaleras y jornaleros agrícolas migrantes que se desplazan al interior de la propia entidad y hacia diversas entidades federativas del territorio nacional, a través de una metodología de promoción social que comprenda el diagnóstico, la planeación, ejecución de acciones de inversión, evaluación, así como acciones de coordinación institucional y de concertación social.\nAnualmente emigran de Guerrero alrededor de 60 mil jornaleras y jornaleros agrícolas a laborar en los campos del noroeste mexicano. Aunque se afirma que la estacionalidad se ha diluido, podemos observar dos hechos relevantes:\n• La mayoría sigue saliendo de la entidad a partir de septiembre y noviembre; más del 50% emigra a\nSinaloa. Lo cual permite aún sentar las bases de un proceso ordenado de atención.\n• Guerrero siempre ha estado inscrito en la gran ruta migratoria del pacífico, que provee mano de obra desde las regiones Centro, Montaña y Costa Chica, a los agroindustriales del noroeste mexicano.\n2. Alineación Programática al PED y/o PND.\nEl Programa, se encuentra alineado, en el Plan Estatal de Desarrollo 2022-2027, al Eje Transversal B, “Igualdad de Género e Inclusión Social”; el objetivo B.10. “Atender integralmente a las y los migrantes nacionales, poniendo especial énfasis en las y los jornaleros agrícolas guerrerenses que emigran de sus localidades de origen a otros municipios del estado y al interior de la República, para mejorar sus condiciones de vida y de trabajo, a través de alternativas productivas que detonen el desarrollo regional y generen un contexto propicio al arraigo; transversalizando y operando un Programa Estratégico Integral de\nApoyo en el Ciclo Migratorio de Migrantes Nacionales, en especial de jornaleras y jornaleros agrícolas y para el desarrollo de las regiones con alta marginación y/o expulsoras de jornaleras y jornaleros agrícolas de la entidad”, así como la Estrategia B.10.2.- Fortalecimiento de Derechos Sociales, Empleo productivo y arraigo y la Línea de acción B.10.2.2. “Definir, operar y evaluar programas de autoempleo jornalero productivo y fomento a la organización de microempresas jornaleras para el bienestar, con proyectos productivos de equipamiento, promoción social, fomento organizativo, capacitación microempresarial,\nREGLAS DE OPERACIÓN dirigida al mejoramiento de las actividades agropecuarias, microindustriales, agroindustriales de servicios y artesanales, y transferencia de conocimiento ancestral para la reactivación de cadenas productivas y circuitos microrregionales de producción-comercialización-consumo, y focalizar programas sociales y acciones en comunidades expulsoras de jornaleras y jornaleros agrícolas migrantes.\nAsimismo, se encuentra inmerso en el Programa Especial Migrantes, 2022-2027, a través del Objetivo\nB.10, que establece el imperativo de “Atender integralmente a los migrantes nacionales, poniendo énfasis en las y los jornaleros agrícolas guerrerenses que emigran de sus localidades de origen a otros municipios del estado y al interior de la República, para mejorar sus condiciones de vida y de trabajo, a través de alternativas productivas que detonen el desarrollo regional y generen un contexto propicio al arraigo; transversalizando y operando un Programa Estratégico Integral de Apoyo en el Ciclo Migratorio de\nMigrantes Nacionales, en especial de jornaleras y jornaleros agrícolas y para el desarrollo de las regiones con alta marginación y/o expulsoras de jornaleras y jornaleros agrícolas de la entidad”\n2.1. Diagnóstico.\nAnualmente emigran de Guerrero alrededor de 60 mil jornaleras y jornaleros agrícolas a laborar en los campos del noroeste mexicano, propiciando de manera gradual el desarraigo, principalmente de las regiones Centro, Montaña y Costa Chica.\nLa migración es un fenómeno que se ha incrementado durante los últimos años. Guerrero ocupa ahora el primer lugar en migración interestatal, desplazando a Oaxaca. Diversos autores estiman en alrededor de 3 millones, a la cantidad de jornaleras y jornaleros agrícolas migrantes existentes en México, con un probable subregistro.\nLas regiones que presentan altos índices de marginación y profundos niveles de pobreza, son las de mayor expulsión de mano de obra, debido principalmente a las siguientes causas: desempleo y falta de oportunidades productivas, inadecuado manejo de los recursos naturales, baja productividad, bajos niveles tecnológicos, acceso limitado a mercados, insuficiente desarrollo organizativo, falta de una cultura o capacitación empresarial, infraestructura insuficiente, dispersión demográfica, escaso apoyo técnico y de capacitación, altos costos de producción, desarticulación institucional e inexistencia de una planeación integral del desarrollo que, aunado con altos grados de inseguridad, descalifican las potencialidades de desarrollo de dichas regiones, haciéndolas poco atractivas a la inversión y, por ende, generadoras de escasas oportunidades de empleo e ingreso. y organización social de los propios migrantes, más allá de la organización para subsistir; así como al desencuentro entre los ciclos fiscales de las instituciones gubernamentales y los ciclos agrícolas, educativos o electorales en que transcurre la vida cotidiana de las y los migrantes, lo cual los coloca al margen del ejercicio de diversos derechos.\nEn la entidad no se ha contado con políticas públicas, programas o leyes que promuevan la atención social o productiva a la población jornalera agrícola migrante. Por otra parte, el respaldo a las y los jornaleros\nREGLAS DE OPERACIÓN de origen en la entidad, ha sido discontinuo en el tiempo, siendo nulo en la actualidad.\n2.1.1. Población Potencial.\nAnualmente emigran de Guerrero alrededor de 60 mil jornaleras y jornaleros agrícolas a laborar en los campos del noroeste mexicano, propiciando de manera gradual el desarraigo. Las condiciones de vida y de trabajo en que se desenvuelven, son violatorias de sus garantías y derechos económicos, sociales y culturales consagrados en la Constitución Política de los Estados Unidos Mexicanos. Las regiones de donde más emigran las y los jornaleros agrícolas son: Centro, Montaña, Costa Chica y Región Norte, en un flujo migratorio que comprende alrededor de mil localidades de 70 municipios de la entidad.\n2.1.2. Población Objetivo.\nLas condiciones de vida y de trabajo en que se desenvuelven las y los jornaleros agrícolas migrantes, son violatorias de sus garantías y derechos económicos, sociales y culturales consagrados en la Constitución\nPolítica de los Estados Unidos Mexicanos.\nLa población objetivo del Programa la constituyen las jornaleras y jornaleros agrícolas migrantes residentes en comunidades jornaleras estratégicas seleccionadas con base en la mayor proporción de población jornalera migrante por región y/o municipio, que decidan optar por desarrollar una actividad productiva de autoempleo en su propia localidad, con el propósito de generar bienes de consumo para el mercado local y regional.\nPara la priorización y programación de los proyectos disponibles en el Programa que serán elegibles en cada localidad participante según su contexto local, se realizará un taller de planeación comunitaria, en el que se informarán los lineamientos básicos del Programa, los tipos de proyectos, así como los requisitos para acceder a los apoyos. Los proyectos serán definidos a partir de las vocaciones productivas existentes en cada comunidad jornalera, con base en la experiencia de las y los jornaleros, que incorporen los saberes de la agricultura campesina u orgánica, así como a partir del conocimiento ancestral relacionado con los procesos productivos locales.\nUna vez realizado dicho taller, las personas interesadas podrán presentar sus solicitudes y documentos\nAsuntos internacionales, quienes remitirán a esta instancia las solicitudes de los proyectos, misma que, en presupuestal, valorará y dictaminará la autorización de los proyectos solicitados que serán sujetos de apoyo.\n2.1.3. Población Beneficiaria.\nLa población beneficiaria del Programa son las jornaleras y jornaleros agrícolas migrantes, que cumplen con los requisitos de acceso del Programa, que soliciten el apoyo, obtengan la autorización de su proyecto\nREGLAS DE OPERACIÓN localidad.\n2.1.4. Población Indígena.\nEntre el conjunto de población jornalera agrícola migrante, existen jornaleras y jornaleros mestizos, indígenas y afromexicanos. El Programa orientará sus acciones de atención a la población jornalera agrícola migrante en sus comunidades de origen, con mayor índice de migración interna o nacional, sin ningún distingo o discriminación alguna, en los municipios con población indígena de las lenguas Naua\n(Náhuatl), Ñuu Savi (Mixteco), Me´Phaa (Tlapaneco) y N´amcue Ñ’omdaá (Amuzgo), con alto o muy alto grado de marginación, sujetándose a los criterios de selección del Programa, así como a los requisitos establecidos en el presente ordenamiento.\n2.2. Fundamento Legal.\na) Constitución Política de los Estados Unidos Mexicanos;\nb) Plan Nacional de Desarrollo 2019-2024;\nd) Ley Orgánica de la Administración Pública del Estado de Guerrero Número 242;\ne) Ley Número 838 de Atención a los Migrantes del Estado de Guerrero;\ng) Ley de Número 427 de Coordinación Hacendaria del Estado de Guerrero;\nh) Ley Número 701 de Reconocimiento, Derechos y Cultura de los Pueblos y Comunidades Indígenas y\nAfromexicanas del Estado de Guerrero; de Guerrero;\nk) Lineamientos para la Elaboración de las Reglas de Operación de los Programas Sociales Estatales para el periodo 2022-2027,\nREGLAS DE OPERACIÓN\nm) Decreto Número 424 de Presupuesto de Egresos del Estado de Guerrero para el Ejercicio Fiscal 2023,\nn) Todos aquellos ordenamientos normativos aplicables.\n2.3. Definiciones y Siglas.\nDefiniciones:\nAgroindustrias: Se refiere a las empresas agroindustriales de carácter nacional e internacional que invierten en la producción agrícola en el norte, occidente, noroeste, centro norte, y noreste mexicano.\nCampos Agrícolas: Los campos agrícolas son las parcelas pertenecientes a las empresas agroindustriales mexicanas o transnacionales, donde las y los jornaleros agrícolas desempeñan sus labores de preparación del suelo, siembra, fertilización, riego y cosecha en combinación con múltiples elementos tecnológicos, así como con maquinaria y equipo.\nCondiciones de Vida y de Trabajo: Se refiere a las condiciones sociales de salud, educación, alimentación, vivienda, empleo, ingresos, pobreza, marginación y violación a sus derechos humanos y laborales de las y los Jornaleros Agrícolas, en las cuales la población jornalera transcurre su vida cotidiana.\nConsejo Estatal de Jornaleros Agrícolas: Se refiere al Consejo Estatal de los Jornaleros Agrícolas\nMigrantes de Guerrero. A.C.\nEstado de Atracción: Entidades federativas de la república mexicana cuyo dinamismo económico y regional se constituyen en regiones a donde acuden jornaleras y jornaleros agrícolas migrantes de Guerrero y el resto del país, para contratarse en la prestación de servicios en labores agropecuarias.\nEmpresas Transnacionales: Se refiere a las empresas de capital e inversión global que invierten en el norte de México para desarrollar cultivos hortícolas competitivos con la agroindustria del sur, sureste y medio oeste de Estados Unidos y Canadá.\nJornalera o Jornalero Agrícola Migrante: Personas que se desplazan de su lugar de origen a otros lugares a trabajar en actividades agrícolas a cambio de un salario.\nPoblación Beneficiaria: Se refiere a las jornaleras y jornaleros agrícolas migrantes de Guerrero, que se sitios donde se embarcan en transporte para trasladarse a las entidades o regiones (región Tierra Caliente de Guerrero) de atracción o destino laboral; durante el periodo de su estadía en los campos agrícolas de las entidades de atracción migratoria, para emplearse temporalmente como jornaleras y jornaleros agrícolas, así como durante su traslado de una entidad federativa a otra, o en su retorno a sus regiones, municipios y comunidades jornaleras de origen en el estado de Guerrero.\nREGLAS DE OPERACIÓN\nPoblación Indígena: Se refiere a la población jornalera agrícola migrante originaria de comunidades de origen indígena, con mayor índice de migración interna o nacional, sin ningún distingo o discriminación alguna, pertenecientes a los municipios con población indígena de las lenguas Naua (náhuatl), Ñuu Savi\n(Mixteco), Me´Phaa (Tlapaneco) y N´amcue Ñ’omdaá (Amuzgo).\nPoblación Jornalera Agrícola Migrante: Se refiere a todas las y los guerrerenses, jornaleros agrícolas migrantes que se desplazan de su lugar de origen a otros lugares a trabajar en actividades agrícolas a cambio de un salario, comprendiendo a localidades, municipios y regiones de la entidad guerrerense, así como indistintamente si su origen es mestizo, indígena o afromexicano, así como de grupos de edad de los 12 a los 80 años.\nPrograma: Programa de Autoempleo Productivo para el Bienestar de Comunidades Jornaleras.\nPresupuesto de Egresos: Se refiere al Decreto 424 del Presupuesto de Egresos del Estado de Guerrero, para el Ejercicio Fiscal 2023.\nRegión de Atracción: Regiones con dinamismo económico agropecuario a donde acuden jornaleras y jornaleros agrícolas migrantes de otras regiones, para contratarse en la prestación de servicios en labores agropecuarias (Tierra Caliente).\nReglas de Operación: Reglas de Operación del Programa de Autoempleo Productivo para el Bienestar de\nComunidades Jornaleras para el Ejercicio Fiscal 2023.\nSecretaría de Contraloría: Secretaría de Contraloría y Transparencia Gubernamental.\nTránsito Migratorio: Se refiere al flujo migratorio que transcurre desde que las jornaleras y jornaleros agrícolas migrantes y sus familias, se organizan en sus comunidades para salir a trabajar, pasando por pernoctar desde una noche a una semana en alguno de los centros de reclutamiento laboral (Unidades de\nServicios Integrales en Chilapa de Álvarez y Tlapa de Comonfort) de Chilapa, Tlapa u Ometepec (Campo de Aviación), donde se embarcan en autobuses que los llevarán hasta el campamento, campo agrícola y entidad de destino, pasando por diversas rutas en el territorio nacional.\nUnidad de Servicios Integrales: Por centros de reclutamiento laboral llamamos a las Unidades de\nServicios Integrales (o también denominadas USIs), que son ciertos complejos diseñados y construidos en los años noventa por un programa federal, (localizados en Chilapa y Tlapa), para brindar dormitorio, comedor, servicios de baños, regaderas y servicios de salud para las y los jornaleros agrícolas. Estas Usis, agrícolas del noroeste, occidente, centro-norte, noreste, centro y el bajío mexicano, ya que cuentan con laboral.\nSiglas:\nCONAPO: Consejo Nacional de Población.\nREGLAS DE OPERACIÓN\nCOVID: 19. Enfermedad por el Nuevo Coronavirus-2019.\nCURP: Clave Única de Registro de Población.\nINE: Instituto Nacional Electoral.\nINEGI: Instituto Nacional de Estadística, Geografía e Informática.\nPED: Plan Estatal de Desarrollo 2022-2027.\nPND: Plan Nacional de Desarrollo 2019-2024.\nRFC: Registro Federal de Causantes.\nSEDESOL-PAJA: Se refiere a la extinta Secretaría de Desarrollo Social y su organismo desconcentrado\nPrograma de Apoyo a Jornaleros Agrícolas.\nSEFINA: Secretaría de Finanzas y Administración.\nSEFODECO: Secretaría de Fomento y Desarrollo Económico.\nSEPLADER: Secretaría de Planeación y Desarrollo Regional.\nSARS COV-2: Síndrome Respiratorio Agudo Grave, por Covid.\nSEMAI: Secretaría de los Migrantes y Asuntos Internacionales.\n3. Objetivos y Alcances.\n3.1. Objetivo General.\nApoyar a las y los jornaleros agrícolas migrantes de Guerrero así como a miembros de sus familias en propensión de emigrar, con el equipo, herramientas y accesorios necesario para que emprendan un proyecto productivo de autoempleo, con el apoyo de promoción social y fomento organizativo, dirigidos al fomento y mejoramiento de las actividades agropecuarias, microindustriales y agroindustriales, de servicios y artesanales, para la reactivación de cadenas productivas y circuitos microrregionales de produccióncomercialización-consumo.\n3.2. Objetivo Específico.\nLos objetivos específicos del Programa son:\n• Generar oportunidades de empleo e ingreso en comunidades jornaleras e impulsar la producción local de bienes de consumo a bajo costo en comunidades jornaleras.\nREGLAS DE OPERACIÓN\n• Disminuir el flujo de migración de comunidades jornaleras y evitar la migración de familiares de jornaleros propensos a emigrar.\n• Realizar acciones de promoción social y fomento organizativo de las y los jornaleros agrícolas en comunidades jornaleras.\n3.3. Cobertura.\nEl Programa tendrá cobertura en comunidades jornaleras estratégicas, definidas a partir de la mayor proporción de población jornalera, en los municipios y regiones de más alta marginación, niveles de pobreza y migración jornalera.\n3.4. Alcances.\nLos alcances del Programa son los siguientes:\n• Con el propósito de generar oportunidades de empleo e ingreso, impulsar la producción local de bienes a bajo costo, disminuir el flujo de migración, evitar la migración de familiares de jornaleros y fomentar la organización de las y los jornaleros agrícolas, el Programa apoyará proyectos productivos agropecuarios, microindustriales y agroindustriales, del sector servicios, artesanal, infraestructura productiva complementaria y de promoción social, mediante el otorgamiento en especie de equipos, herramientas, materiales y accesorios, así como servicios de capacitación que las y los beneficiarios requieran para desarrollarlos, en comunidades jornaleras estratégicas.\n• El Programa otorgará únicamente apoyo en especie; no otorgará apoyo en efectivo o monetario alguno.\n• La asignación de recursos estará en función de las características y viabilidad del proyecto, así como del compromiso de la persona interesada en operarlo sustentablemente.\n• El Programa otorgará paritariamente los apoyos: 50% para jornaleros agrícolas y 50% para jornaleras agrícolas.\n• El monto promedio por proyecto será de $20,000.00 (Veinte mil pesos 00/100 m.n.), siendo el monto máximo de $25,000.00 (Veinticinco mil pesos 00/100 m.n.), sin que sea obligatorio otorgar ninguno de esos montos a algún proyecto en específico. En la inteligencia que, podrá haber proyectos con montos menores a $20,000.00 (Veinte mil pesos 00/100 m.n.).\n• En los casos en que, por requerimiento del proyecto, las y los beneficiarios necesiten equipo con valor monetario mayor al monto máximo por proyecto individual, podrán asociarse y conjuntar sus apoyos individuales para la ejecución de un proyecto común de mayor costo, hasta un máximo de 5 proyectos individuales. Para el efecto, la SEMAI proveerá una cédula de identificación de proyecto grupal.\n• Se otorgará una cantidad máxima de proyectos por cada una de las comunidades jornaleras estratégicas, misma que será determinada por la SEMAI.\nREGLAS DE OPERACIÓN\n4. Metas Físicas.\nEl Programa apoyará aproximadamente 117 proyectos productivos específicamente en comunidades jornaleras estratégicas, a igual número de jornaleras y jornaleros agrícolas migrantes.\n5. Programación Presupuestal.\nEl Programa tiene asignado, a través de una adecuación presupuestal compensada, un presupuesto financiero de $ 3, 000,000.00 (Tres millones, de pesos 00/100 m.n.) para el ejercicio fiscal 2023, teniendo como fuente de financiamiento Inversión Estatal Directa, recurso que será destinado para realizar las acciones referidas en estas Reglas de Operación en beneficio de la población jornalera agrícola migrante de Guerrero, de conformidad con el cronograma financiero siguiente:\nCALENDARIO DE MINISTRACIÓN DE RECURSOS\n--------- ----------- ----------- ----------- L\nDEPENDENCIA: SECRETARIA DE LOS MIGRANTES Y ASUNTOS INTERNACIONALES.\nPROGRAMA INVERSIÓN ESTATAL DIRECTA\nENERO FEBRERO MARZO ABRIL MAYO JUNIO JULIO AGOSTO SEPTIEMBRE OCTUBRE NOVIEMBRE DICIEMBRE TOTAL\nPrograma de\nAutoempleo\nProductivo para el\nBienestar de\nComunidades\nJornaleras. 1,000,000.00 1,000,000.00 1,000,000.00 1,000,000.00\n5.1. Gastos de Operación.\nEl Programa contará con gastos de operación, a los cuales se destinará el 3% de los recursos del\nPrograma; para llevar a cabo acciones de planeación, operación, supervisión, seguimiento y evaluación; la\nSEMAI podrá realizar visitas a algunas comunidades para verificar la buena marcha de los proyectos otorgados, así como la adquisición de equipo y artículos de papelería, mobiliario y equipo de cómputo, que apoyen las funciones de administración y operación del Programa.\n6. Criterios y Requisitos de Elegibilidad.\nPara acceder a los apoyos del Programa, serán necesarios los requisitos siguientes:\na) Solicitud de apoyo al Programa para gestionar el proyecto de su interés, en formato libre, dirigido a la persona titular de la SEMAI. Podrá haber casos especiales de proyectos grupales, como se especifica en el apartado de “Alcances”.\nb) Acreditar su condición de jornalero o jornalera agrícola migrante de Guerrero. (Recibo de pago, a la persona interesada, solo en caso de fuerza mayor se admitirá constancia de referencia laboral expedida por la autoridad local).\nc) Copia del acta de nacimiento.\nREGLAS DE OPERACIÓN\nd) Copia de la Credencial de Elector.\ne) Copia de la Clave Única de Registro de Población (Solo si no la incluye la identificación INE).\nf) Copia de comprobante de domicilio (Recibo de agua o CFE). En su defecto, constancia de radicación de la autoridad local.\ng) Formato de Identificación de proyecto. (Formato proporcionado por la SEMAI).\nPara el acceso de las trabajadoras y trabajadores agrícolas propensos a emigrar, se deberá acreditar:\n• Que su comunidad de origen es jornalera (30% o más de trabajadoras o trabajadores agrícolas cuyos ingresos dependen del trabajo migratorio, corroborándolo mediante fuente estadística de INEGI, CONAPO, SEDESOL-PAJA, Encuesta-Municipal o conteo de la SEMAI.\n• Que su familia es jornalera, de alguna comunidad jornalera, de conformidad con el parágrafo anterior.\n• Acreditar ser niña, niño o adolescente migrante, mediante alguno de los siguientes documentos: boletas de programa escolar de atención a migrantes, credencial escolar, registro de arribo a campo agrícola o fotografía en campo agrícola.\n7. Tipo, Monto y Periodicidad del Apoyo.\nEl apoyo del Programa será en especie y por única vez. El apoyo del Programa consistirá en el otorgamiento de los equipos, herramientas, accesorios y bienes muebles diversos, indispensables para la puesta en marcha de los proyectos productivos que cada jornalera o jornalero haya elegido para producir algún bien económico de calidad y bajo precio, competitivo en el mercado local, que permita sostener su autoempleo y propender a la generación de empleos sustentables adicionales.\nLos apoyos estarán dirigidos a fomentar la reactivación productiva orientada al autoconsumo y a la comercialización de excedentes en el mercado microrregional.\nLa convocatoria, recepción de solicitudes y entrega de apoyos se llevará a cabo mediante un módulo en las instalaciones de la SEMAI, en coordinación con los ayuntamientos municipales.\nLa tabla siguiente especifica los tipos, montos y periodicidad de los apoyos:\nTIPO, MONTO Y PERIODICIDAD DEL APOYO.\nTIPO MONTO PERIODICIDAD\nESPECIE\nVERTIENTE I\nAgropecuario HASTA $25,000.00 UNICA VEZ\nMicroindustrial y agroindustrial HASTA $25,000.00 UNICA VEZ\nSector servicios HASTA $25,000.00 UNICA VEZ\nSector Artesanal HASTA $25,000.00 UNICA VEZ\nREGLAS DE OPERACIÓN\nVERTIENTE II\nProyectos de infraestructura complementaria HASTA$25,000.00 UNICA VEZ\nVERTIENTE III\nProyectos de planeación y promoción social HASTA$15,000.00 UNICA VEZ\n7.1. Características de los Apoyos.\nEl Programa apoya las tres vertientes de proyectos que se describen a continuación.\nEn caso de ser solicitado algún otro tipo de proyecto, se analizará su viabilidad de conformidad con los objetivos del Programa y las especificaciones de las presentes Reglas de Operación.\na) Vertiente I. Proyectos Productivos.\n• Del Sector Agropecuario.\nEn esta vertiente se apoyarán, cultivos en parcela o de traspatio, como: producción de plantas medicinales, cultivos nutracéuticos, producción de hortalizas, reforestación con especies nativas o de fácil adaptación, productivas y de rápido crecimiento, huertos frutales y granos básicos; así como cría y engorda de bovino, caprinos, aves, porcinos, ovinos, producción apícola, acuícola; equipamiento mediante desintegradores de forraje, desgranadoras, silos y motocultores, así como herramienta menor para actividades agropecuarias y proyectos semejantes; apoyos dirigidos a fomentar la reactivación productiva orientada al autoconsumo\nCon el propósito de evitar el impacto ambiental del libre pastoreo en la erosión y pérdida de suelos, para la autorización de proyectos de cría y engorda de ganado bovino, se deberá acreditar por la persona interesada, lo siguiente: contar con la propiedad del inmueble donde se realizará la cría y engorda, que cuente con la superficie suficiente de agostadero y el agua suficiente para el mantenimiento de las cabezas de ganado (una hectárea por cabeza); la o el beneficiario que reciba apoyo con cabezas de ganado, procurará obtener su registro ganadero correspondiente, a efecto de contar con acceso a otros programas agropecuarios.\nDe la misma forma, para la autorización de proyectos de cría de caprinos, será necesario acreditar la capacidad para su manejo semiestabulado, contar con la propiedad del inmueble y la superficie de agostadero y agua suficiente para las instalaciones de manejo y superficie para fase de pastoreo, así mismo, procurará obtener su registro ganadero correspondiente, a efecto de contar con acceso a otros programas agropecuarios. conservación de suelos y agua.\nPara la implementación de los proyectos del sector agropecuario, se destinará un monto máximo de inversión de $25,000.00 (Veinticinco mil pesos 00/100 m.n.), para cada proyecto individual.\nREGLAS DE OPERACIÓN\n• Del Sector Microindustrial y Agroindustrial.\nEn esta vertiente, se fondearán, proyectos de equipamiento para establecer talleres de herrería, bloqueras, carpintería, costura, bordados, panaderías, rosticerías y molinos de nixtamal o proyectos semejantes.\n$25, 000.00 (Veinticinco mil pesos 00/100 m.n.), para cada proyecto individual.\n• Del Sector Servicios.\nEn esta vertiente, se financiarán proyectos para la prestación de servicios como: cocina económica, carnicería, albañilería, plomería, vulcanizadora, electricista, salón de belleza o peluquería, centros de cómputo y tiendas de abarrotes o proyectos semejantes.\nEn esta modalidad se destinará un monto máximo de inversión de $25,000.00, (Veinticinco mil pesos\n00/100 m.n.) para cada proyecto individual.\n• Del Sector Artesanal.\nEn esta vertiente, se apoyarán proyectos para la producción y comercialización de artesanías, como:\nProducción de ropa típica (telar de cintura), bordados, elaboración de petates y sombreros, elaboración de hamacas, así como artesanía local de diversos materiales y proyectos semejantes.\nEn esta modalidad se podrá destinar un monto máximo de inversión de $25,000.00 (Veinticinco mil pesos\n00/100 m.n.) para cada proyecto individual.\nb) Vertiente II. Proyectos de Infraestructura Complementaria.\nEn esta vertiente se apoyarán proyectos de infraestructura complementaria para el sector agropecuario, como: pequeños bordos de abrevadero, muros de piedra acomodada, geocostales, ramas o morillos disponibles sin deforestar, para conservación de suelos, pequeñas ollas de agua debidamente impermeabilizadas, bebederos, sistemas de riego por goteo, cisternas de almacenamiento de agua y pequeñas represas de material industrializado, con la finalidad de contribuir y fomentar las actividades del sector agropecuario.\nDe los proyectos en referencia, se desprenden acciones de capacitación y asistencia técnica para dicho propósito, esto es con la finalidad de que los proyectos tengan mayor éxito. El Programa, buscará las los jornaleros agrícolas migrantes de Guerrero. monto máximo de $25,000.00 (Veinticinco mil pesos 00/100 m.n.) por proyecto individual.\nREGLAS DE OPERACIÓN\nSe podrán considerar otras opciones de infraestructura, siempre que sean estrictamente necesarias en máximo de un proyecto individual.\nc) Vertiente III. Proyectos de Planeación y Promoción Social.\nEn esta vertiente se erogarán recursos para operar una metodología de planeación, comprendida por: actividades de diagnóstico, actividades de planeación comunitaria y de promoción social. Para esta vertiente se podrá erogar un máximo de 3 por ciento de la inversión total programada.\nPara la justificación y control del ejercicio de este tipo de proyectos se formulará un perfil por proyecto, mismo del cual deberá contarse con informe de ejecución y evaluatorio de resultados alcanzados.\nEn esta vertiente se apoyarán proyectos relacionados con la definición de la programación y formación de cuadros para el diagnóstico, la planeación comunitaria y la promoción social. Entre otros, se apoyarán talleres de capacitación sobre metodología básica, instrumentos y estrategias de diagnóstico situacional, planeación comunitaria y acciones de promoción social, a los que se podrá destinar un monto de inversión desde $5,000.00 (Cinco mil pesos 00/100 m.n.) hasta $ 15,000.00. (Quince mil pesos 00/100 m.n.)\nDichos talleres serán impartidos por las y los promotores comunitarios del Programa a regidores, directores, personal de los ayuntamientos municipales, becarios y prestadores de servicio social que laboren en actividades vinculadas con las y los jornaleros agrícolas migrantes, con el propósito de propiciar la multiplicación de operadores entrenados para la atención integral a las y los jornaleros agrícolas.\n7.2. Recursos no Devengados.\nEl presupuesto autorizado al Programa que no se haya aplicado a los fines autorizados, y los recursos que por cualquier motivo no se hayan devengado al 31 de diciembre del presente ejercicio fiscal, será reintegrado inmediatamente a la SEFINA.\n7.3. Resguardo de la Documentación.\nEl resguardo de la documentación comprobatoria de los recursos ejercidos del Programa. Así como la\nDelegación Administrativa de la SEMAI.\n7.4. Supervisión y Control.\nPara la puesta en marcha del Programa, se llevarán a cabo las siguientes actividades, con el correspondiente control y supervisión de las mismas:\na) Diseño y Publicación de la Convocatoria.\nLa Subsecretaría de Migrantes Nacionales coordinará el diseño y publicación de la convocatoria.\nREGLAS DE OPERACIÓN\nLa convocatoria establecerá, el objetivo del Programa, la población objetivo que se convoca a participar, las modalidades y montos de apoyo, así como los requisitos de elegibilidad, así como el sitio en que se publicarán los resultados de las y los beneficiarios seleccionados para la recepción del apoyo.\nb) Recepción de Solicitudes.\nPara la recepción de solicitudes, se establecerá periodo, lugar y horario en el cual, personal de la SEMAI o, si así se determina, personal municipal adecuadamente capacitado, recibirá las solicitudes, organizándolas de conformidad con los términos de la convocatoria.\nc) Análisis y Programación de Solicitudes.\nPara el análisis y la programación de solicitudes, se integrarán las propuestas recibidas desde las comunidades y municipios participantes, ordenándolas mediante un concentrado de prelación que establecerá la convocatoria, de conformidad con los criterios de selección establecidos en estas Reglas de\nOperación en el apartado 8.\nd) Entrega de Apoyos.\nPara la entrega de apoyos se publicará previamente el listado de las y los beneficiarios y proyectos seleccionados, así como los sitios y fechas en que serán convocados para recibir el apoyo, con la especificación de que, de no presentarse en el lapso máximo de una semana, dicho apoyo será reasignado.\nConcluida le entrega de apoyo se realizará una verificación de cumplimiento de los indicadores contenidos en la ficha técnica de indicadores, del apartado 10.1. Indicadores, de las presentes Reglas de Operación.\ne) Integración de la Comprobación.\nUna vez concluido el proceso de entrega de apoyos, se integrará la comprobación y expedientes de cada beneficiario y proyecto, para ser entregados a la SEFINA.\nColateralmente con la documentación comprobatoria, se integrarán informes trimestrales y un informe anual de la ejecución del Programa.\nLa SEMAI será la máxima instancia de decisión en el marco del Programa, misma que resolverá sobre los casos no previstos en las presentes Reglas de Operación. actividades inherentes al Programa, misma que instruirá lo conducente para la operación, procesamiento de información, informes o evaluaciones, a las áreas administrativas adscritas a la misma.\nEn cumplimiento a la Ley número 494 para la Igualdad entre Mujeres y Hombres y la Ley número 553 de\nAcceso de las Mujeres a una Vida Libre de Violencia, ambas del estado de Guerrero, el programa considerará en su operación, objetivos e indicadores de desempeño, la perspectiva de género. Asimismo,\nREGLAS DE OPERACIÓN identificará y registrará la población objetivo y la atendida, diferenciada por sexo, grupo de edad, discapacidad, región del estado, municipio o localidad, población indígena o afromexicana.\nLa SEMAI es garante de que el Programa no se contrapone, afecta, o presenta duplicidad con otros programas y acciones del gobierno estatal y federal en cuanto a su diseño, beneficios, apoyos otorgados y población objetivo, en virtud de que no existen otros programas orientados al apoyo de proyectos productivos para población jornalera agrícola migrante y los existentes, corresponde a esta instancia su ejecución.\nLa SEMAI enviará para su publicación en el Periódico Oficial del Gobierno del Estado, las Reglas de\nOperación o, en su caso, las modificaciones a las mismas, a más tardar a los cinco días hábiles posteriores a que obtengan la autorización y el dictamen; asimismo, se colocarán dichas Reglas de Operación a disposición de la población en sus oficinas estatales, en su página de internet y a través de los gobiernos municipales en los espacios que ellos dispongan.\nA partir de la publicación de las presentes Reglas de Operación, la SEMAI iniciará el ejercicio de los recursos presupuestarios aprobados de acuerdo con la programación de los calendarios de ministración de los mismos.\n8. Criterios de Selección.\nA partir del objetivo general y de los objetivos específicos, se realizará un proceso de jerarquización y priorización de proyectos, de conformidad con la información recogida en sesiones de análisis, coordinación y concertación en comunidades jornaleras y con la organización social de las y los jornaleros agrícolas.\nUna vez realizado dicho ejercicio de priorización, las personas interesadas podrán presentar sus solicitudes y planteamientos ante la SEMAI, la cual, en apego a los criterios de estas Reglas de Operación y la disponibilidad presupuestal, valorará y dictaminará la autorización de los proyectos solicitados que serán sujetos de apoyo, de conformidad con los siguientes criterios de selección:\n• Ser persona jornalera agrícola migrante, o pertenecer a una familia jornalera agrícola migrante;\n• Ser persona originaria o residente de un municipio y/o comunidad de alta migración jornalera, de altos y muy altos niveles de pobreza y marginación social;\n• Tener identificada una idea de proyecto viable para desarrollar una actividad productiva de autoempleo en su propia localidad, con el propósito de generar bienes de consumo para el mercado local y regional;\n• Que los proyectos incorporen los saberes de la agricultura campesina u orgánica, así como a partir del conocimiento ancestral relacionado con los procesos productivos locales;\n• Que los proyectos se encuentren alineados a las recomendaciones de bajo impacto ambiental que se especifican en las presentes reglas de operación, y\nREGLAS DE OPERACIÓN\n• Que los proyectos generen empleo o tengan como efecto multiplicador propiciar el arraigo de otros participantes de su cadena productiva microrregional.\n8.1. Casos Especiales.\nEn caso de ocurrir alguna situación extraordinaria que impida la operación normal del Programa, la SEMAI resolverá todo caso especial, imprevisto o no esperado, con fundamento en los lineamientos y ordenamientos que rigen las políticas de inversión y gasto del gobierno del estado de Guerrero.\nEn casos extraordinarios que un hijo, hija o miembro de la familia jornalera agrícola migrante en primer grado requiera apoyo, así como en casos de fuerza mayor en que, por razones humanitarias se requiera apoyar algún proyecto especial, o que se requiera una cobertura especial de los requisitos, corresponderá a la persona titular de la SEMAI resolver dichas situaciones casuísticamente, con fundamento en la naturaleza del suceso.\nEl mismo criterio prevalecerá ante emergencias grupales de diverso tipo que enfrentan las y los jornaleros agrícolas migrantes guerrerenses o sucesos socio-organizativos de impacto en el orden público que afecten grupalmente a la población jornalera.\nEn casos excepcionales de que existan solicitudes de menores de 18 años y mayores de 16, deberán presentar una constancia de identidad, con fotografía, así como el consentimiento por escrito de sus padres de familia.\n8.2. Casos de Emergencia o Desastre.\nCon el fin de evitar la interrupción de la operación del Programa en caso de que exista una Declaratoria de\nEmergencia o de Desastre, la SEMAI, solicitará a la SEFINA, reservar los recursos del Programa, en virtud de atender una situación humanitaria de muy alto desempleo entre la población jornalera, equivalente a las necesidades prioritarias provocadas por una emergencia social o desastre natural, así como con fundamento en el artículo 16 de la Ley Número 838 de Atención a los Migrantes del Estado de Guerrero, que a la letra dice: “Los programas y recursos destinados a la atención de migrantes será considerada de interés público, no podrán sufrir disminuciones ni transferirse para otros conceptos en el ejercicio”.\n8.3. Suspensión o Cancelación del Programa Social.\nLa SEMAI, podrá suspender y/o cancelar la operación del Programa, cuando no existan las condiciones para su ejecución en alguna(s) de las comunidades jornaleras estratégicas seleccionadas para su operación, o bien, cuando una de las personas beneficiarias no acate las disposiciones de las presentes\nReglas de Operación, cuando lo determine la persona titular del ejecutivo estatal o por problemas de gobernabilidad.\n8.4. Integración del Padrón de Personas Beneficiarias.\nREGLAS DE OPERACIÓN\nEl Programa contará con un proceso permanente de elaboración del padrón de beneficiarias y beneficiarios.\nPara su elaboración una vez que las personas solicitantes son incorporadas al Programa, se integran al registro de beneficiarias y beneficiarios y formarán parte de un Padrón Único de Personas Beneficiarias, el cual será de carácter público, siendo reservados sus datos personales, de acuerdo con la normatividad vigente; los cuales en ningún caso podrán emplearse para propósitos de proselitismo político, religioso o comercial, ni para ningún otro fin distinto al establecido en las Reglas de Operación de este Programa.\n9. Mecánica Operativa del Programa Social.\n9.1. Instancia Ejecutora y/o Responsable.\nLa SEMAI será la responsable de la ejecución del Programa y es la ejecutora del gasto.\nLa Subsecretaría de Migrantes Nacionales, las unidades administrativas o servidoras y servidores públicos que ésta designe, estarán involucrados en la operación del Programa.\n9.2. Proceso de Incorporación al Programa Social.\nPara poder ser beneficiada o beneficiado, las y los interesados deberán participar en la convocatoria que emitirá el Programa, así como:\n• Ser jornalera o jornalero agrícola migrante, ciudadano guerrerense por nacimiento o radicación en el estado de Guerrero, de acuerdo a las disposiciones legales correspondientes.\n• Cumplir con los criterios de elegibilidad establecidos en el apartado 6.\nLa prestación del servicio estará sujeta a la disponibilidad presupuestal del Programa y se le deberá informar a la persona solicitante si recibirá o no el servicio, de conformidad con los tiempos establecidos en estas Reglas de Operación.\nLas jornaleras y jornaleros agrícolas migrantes accederán al Programa social a solicitud expresa, una vez que sean publicadas las presentes Reglas de Operación.\nLos criterios son transparentes, equitativos y no discrecionales. Los requisitos, forma de acceso y criterios\nReglas de Operación.\nSe accederá al servicio del Programa, presentando la solicitud y documentación correspondiente, en el domicilio de Torre Azul. Piso B. Prolongación Prosperidad 10. Col. Universal. CP. 39089. Chilpancingo de los Bravo, Gro., a los teléfonos: 7474712980, o al correo electrónico: migrantesguerrerenses@hotmail.com, en días y horas hábiles.\nLas personas solicitantes podrán conocer el estado de su trámite en el domicilio señalado, o por cualquiera de los medios de comunicación con antelación.\nREGLAS DE OPERACIÓN\n10. Evaluación. eficacia, ya que se podrá medir el grado de cumplimiento de los objetivos y metas programadas. Asimismo, del mismo.\n10.1. Indicadores (Construcción de la Matriz de Indicadores para Resultados. - Anexo 1).\nPara monitorear el desempeño e impacto adecuado del Programa, se implementará el seguimiento del indicador “porcentaje de jornaleros y jornaleras agrícolas migrantes atendidos”, el cual se contrastará continuamente con el conjunto de solicitudes de “jornaleros y jornaleras agrícolas migrantes con solicitud de proyecto”, para obtener el porcentaje de avance en el cumplimiento de los objetivos y metas del mismo, mediante la fórmula siguiente:\nPorcentaje de jornaleros y jornaleras agrícolas migrantes atendidos / jornaleros y jornaleras agrícolas migrantes con solicitud de proyecto * 100 = % de avance.\nEl monitoreo del Programa se realizará de acuerdo con los indicadores de la ficha siguiente:\nFicha Técnica\nIndicadores del Desempeño\nPlan Estatal de Desarrollo 2022-2027\nRAMO: E17 FECHA: 31/01/2023\nFONDO: INVERSIÓN ESTATAL DIRECTA\nPROGRAMA: PROGRAMA DE AUTOEMPLEO PRODUCTIVO PARA EL BIENESTAR DE COMUNIDADES JORNALERAS.\nEJE TEMATICO: B.- Igualdad de género e inclusión social.\nOBJETIVO: B.1O Atender integralmente a los migrantes, poniendo énfasis en los jornaleros agrícolas guerrerenses que emigran de sus localidades de origen a otros municipios del estado y al interior de la república, para mejorar sus condiciones de vida y de trabajo, a través de alternativas productivas que detonen el desarrollo regional y generen un contexto propicio al arraigo; transversalizando y operando un Programa Estratégico Integral de Apoyo en el Ciclo Migratorio de Migrantes Nacionales en especial de Jornaleros\nAgrícolas y para el desarrollo de las regiones con alta marginación y/o expulsoras de jornaleros agrícolas de la entidad.\nESTRATEGIA: B.1O.2. Fortalecimiento de derechos sociales, empleo productivo y arraigo.\nLÍNEA DE ACCIÓN: B.10.2.2. \"Definir, operar y evaluar programas de autoempleo jornalero productivo y fomento a la organización de microempresas jornaleras para el bienestar con equipamiento. promoción social, fomento organizativo y capacitación microempresarial, induciendo a otros programas sociales a focalizar acciones en comunidades expulsoras de jornaleros agrícolas migrantes\".\nDatos de identificación del indicador\nClave Nombre Fuente\nB.10.2.1 Porcentaje de jornaleros y jornaleras agrícolas apoyados SEMAI\nDefinición Nivel en la MIR Dimensión\nPermite conocer la proporción de jornaleras y jornaleros apoyados, respecto del\n6 Eficacia total de jornaleras y jornaleros con solicitud de apoyo.\nMétodo de cálculo Unidad de Medida.\nCantidad de jornaleras y jornaleros apoyados/cantidad de jornaleras y jornaleros que solicitaron apoyo * Jornalera o jornalero agrícola\n100 = %) apoyado\nTrimestral Estatal Ninguna\nLínea base\nSentido del indicador\nAño Periodo Valor\nAscendente 2023 Enero-Diciembre 0%\nREGLAS DE OPERACIÓN\nParámetros de semaforización Metas\nVerde Amarillo Rojo Año Periodo Valor\n76%-100% 51%-75% 0%-50% 2023 Enero-Diciembre 100%\nVariables que conforman el indicador\nNombre Unidad de medida Fuente de información\nJornalero o Jornalera agrícola Jornalero o Jornalera apoyado SEMAI\nObservaciones\nResponsable del indicador\nNombre del Servidor Público Dependencia Área\nSecretaría de los Migrantes y Subsecretaría de los Migrantes\nLic. Eleazar Marín Quebrado\nAsuntos Internacionales Nacionales\nNombre del puesto, encargo o comisión Teléfono Correo electrónico\nSubsecretaría de Migrantes Nacionales 47 8 30 29/47 1 29 80 migrantes@guerrero.gob.mx\nElaboró Revisó Autorizó\nLic. Eleazar Marín Quebrado Lic. Silvia Rivera Carbajal\nDir. Gral. De Planeación y Políticas Secretaría de los Migrantes y Asuntos\nSubsecretaría de Migrantes Nacionales\nPúblicas Migratorias Internacionales\nDirección General de Evaluación\nRecinto del Poder Ejecutivo. Edificio Tierra Caliente, planta baja, correo electrónico: dge.seplader@guerrero gob.mx\n10.2. Seguimiento.\nEn el seguimiento de la operación del Programa, se llevará un registro con las características de todas las personas beneficiarias incorporadas al Programa, a efecto de monitorear que el proceso de operación se ajuste a los criterios de supervisión y control del Programa, de tal forma que sea útil como base para la toma de decisiones respecto al desempeño de los indicadores de gestión, desempeño y gasto.\n10.3. Auditoría.\nEl ejercicio de los recursos del Programa comprende la correcta aplicación, así como promover la eficacia y transparencia en las operaciones y verificar el cumplimiento de los objetivos y metas programadas.\nEl Programa podrá ser auditado por las siguientes instancias, conforme a la legislación vigente y en el ámbito de sus respectivas competencias: la Secretaría de Contraloría y la Auditoría Superior del Estado de\nGuerrero. que se plasmen en el informe de auditoría correspondiente.\n11. Mecanismo de Entrega del Apoyo.\nLas personas beneficiarias, cuyos datos fueron verificados, validados y revisados por el personal asignado por la Subsecretaría de Migrantes Nacionales, que cumplan con los criterios y requisitos de elegibilidad, establecidos en las presentes Reglas de Operación, recibirán el apoyo en especie o servicios especificados por el Programa.\nREGLAS DE OPERACIÓN seleccionados, el seguimiento detallado en la operación del Programa se llevará a cabo por medio de la\nSubsecretaría de Migrantes Nacionales de la SEMAI, para garantizar la más alta eficacia en la operación del mismo.\n12. Derechos y Obligaciones de las Personas Beneficiadas.\na) Derechos:\nLa población beneficiaria de este Programa tiene derecho a recibir un trato digno, respetuoso y equitativo, sin distinción de sexo, partido político o religión; tendrá derecho a solicitar y recibir información sobre el estado que guardan las gestiones que hubiere realizado en los términos que señala la Ley Federal de\nTransparencia y Acceso a la Información Pública Gubernamental, y a recibir los apoyos conforme a las disposiciones normativas del Programa.\nb) Obligaciones:\nPor otra parte, las y los beneficiarios tienen la obligación de manifestar sin faltar a la verdad, si les fueran requeridos, sus datos personales relativos a nombre, edad, sexo, domicilio, situación socioeconómica, Registro Federal de Contribuyentes (RFC), Clave Única de Registro de Población (CURP), grado máximo de estudios y número de dependientes económicos; asimismo tienen la obligación de utilizar los apoyos exclusivamente para los fines con que fueron autorizados y de informar a la SEMAI, si le fuera requerido, sobre la aplicación de los mismos.\nEn los casos en que las y los usuarios o beneficiarios del Programa incumplan las disposiciones de las presentes Reglas de Operación, no tendrán el derecho de recibir los apoyos del Programa.\nSi hicieran mal uso de los apoyos recibidos, se procederá conforme a derecho con base en la normatividad aplicable.\n12.1. Causales de Suspensión o Baja de las Personas Beneficiadas.\nLa SEMAI, cancelará los apoyos, cuando las y los solicitantes incumplan en la entrega de documentos solicitados de forma oportuna y/o falta de información relacionada al caso relativo. Se podrá suspender la radicación de los apoyos y beneficios e inclusive solicitar su reintegro, sin prejuicio de lo establecido en las disposiciones aplicables.\n12.2. Proceso de Baja.\nLa persona beneficiaria que sea sorprendida dando un mal uso de los recursos públicos, será excluida del los recursos obtenidos del erario público. El Programa sustituirá a dicha beneficiaria o beneficiario, por otra persona.\nREGLAS DE OPERACIÓN\n13. Instancias Participantes.\nLas instancias participantes del Programa son: SEMAI, Subsecretaría de Migrantes Nacionales y las instancias internas que designen. de Guerrero, así como organizaciones de la sociedad civil, siempre con el propósito común de apoyar al jornalero o jornalera agrícola que se encuentre desarrollando un proyecto productivo.\n13.1. Instancia Normativa.\nCorresponde a la SEMAI ejercer la función de instancia normativa, para la interpretación de las presentes\nReglas de Operación, así como para la regulación y definición de los aspectos que conforman el Programa.\n14. Transparencia.\n14.1. Promoción y Difusión del Programa Social.\nLa SEMAI será la encargada de realizar la promoción y divulgación del Programa en las comunidades jornaleras de mayor expulsión de los municipios con más alto índice de migración jornalera, en coordinación con los ayuntamientos municipales.\nToda la información necesaria para acceder a los apoyos del Programa, se encontrará en las presentes\nReglas de Operación, mismas que serán publicadas en el Periódico Oficial del Gobierno del Estado de\nGuerrero y sólo podrán brindarse los apoyos de acuerdo a las condiciones aquí establecidas.\nLos expedientes de cada apoyo otorgado estarán resguardados en la Subsecretaría de Migrantes\nNacionales de la SEMAI, sujetos a las disposiciones relativas a la información pública o reservada establecidas por la Ley de Transparencia.\nLos resultados e indicadores de gestión cuantitativos y cualitativos obtenidos por el Programa serán difundidos a través de medios de difusión digital y la página oficial del gobierno del estado\n14.2. Contraloría Social.\nLos procedimientos de contraloría social buscan incorporar a la ciudadanía en el control, vigilancia y evaluación de los programas sociales. La instancia ejecutora promoverá la contraloría social con base en la normatividad establecida para tal efecto, fomentando acciones que transparenten la operación del\nPrograma. de las acciones a realizar por la SEMAI, de la promoción, difusión y realización de las acciones necesarias\nREGLAS DE OPERACIÓN de comités de contraloría social para dar seguimiento, supervisión, vigilancia y evaluación del cumplimiento de criterios de elegibilidad y derechos de las personas beneficiarias, obligaciones del Programa y el desempeño, honestidad y calidad de las servidoras y servidores públicos.\n14.3. Protección de Datos Personales.\nCon base en lo establecido en la Ley Número 207 de Transparencia y Acceso a la Información Pública del\nEstado de Guerrero, la SEMAI publicará periódicamente la lista de apoyos otorgados, con las reservas sobre datos personales establecidas por Ley, en la página oficial del Gobierno del estado www.guerrero.gob.mx/dependencias/secretaria-de-los-migrantes, así como información adicional relativa al Programa.\nAsimismo, con base en la Ley Número 207 de Transparencia y Acceso a la información Pública del Estado de Guerrero, la información de los montos y las personas beneficiarias del Programa será publicado en el\nSistema Nacional de Transparencia, acceso a la información Pública y Protección de Datos Personales.\nEn todo momento la persona beneficiaria podrá ejercer los derechos de alta, acceso, rectificación, cancelación y oposición de datos personales recabados.\nLos datos recabados personales serán utilizados con la finalidad siguiente: validar que se cumplan los requisitos de elegibilidad para ser persona beneficiaria de este Programa; que serán integrados los requisitos de acuerdo a las facultades propias, compatibles, análogos para la realización de compulsas para la integración del Padrón Único de Personas Beneficiarias.\nPor lo tanto, se garantiza la protección de los datos personales que sean recabados y en cumplimiento con las disposiciones en materia de transparencia y acceso a la información pública aplicable.\n14.4. Quejas y Denuncias.\nLas personas beneficiarias del Programa podrán presentar sus quejas y denuncias relativas a una mala actuación por personal de la SEMAI en relación con este Programa, a través de un oficio dirigido a la persona titular de la SEMAI, directamente en el área de recepción de documentos, ubicada dentro de las oficinas, donde especifique: Nombre de la persona servidora (as) pública (s), objeto de la denuncia, nombre y domicilio de la persona quejosa e identificación oficial. bien a los teléfonos 747 47 1 29 80 y 747 47 8 30 29, así como a través del correo electrónico:\nTambién se puede hacer uso del buzón de quejas y denuncias instalado por la Secretaría de la Contraloría, en el pasillo interior de la SEMAI.\n14.5. Acciones de Blindaje.\nREGLAS DE OPERACIÓN\nEn la operación y ejecución de los recursos del Programa, se deberán observar y atender las medidas de carácter permanente, contenidas en las leyes federales y/o locales aplicables, las disposiciones emitidas por las autoridades electorales, tanto de carácter federal como local, así como aquellas específicas que sean emitidas de forma previa para los procesos electorales federales, estatales y municipales, con la finalidad de prevenir que el uso y manejo de los recursos públicos y programas sociales se vean relacionados con fines partidistas y/o político- electorales; todo ello con la firme intención de garantizar los principios de imparcialidad y equidad durante los comicios.\nLa documentación oficial y la publicidad e información del Programa deberá incluir la siguiente leyenda:\n“Este Programa es de carácter público, no es patrocinado ni promovido por partido político alguno y sus recursos provienen de los impuestos que pagan todas las personas contribuyentes. Queda prohibido el uso de este Programa con fines políticos, electorales, de lucro y otros distintos a los establecidos. Quien haga uso indebido de los recursos de este Programa deberá ser denunciada o denunciado y sancionada o sancionado de acuerdo con la ley aplicable y ante la autoridad competente”.\n14.6. Acta de Donación. (Anexo 2)\nLa SEMAI integrará y presentará, debidamente requisitados, un recibo de recepción del apoyo, que formará parte de las acciones de transparencia en la ejecución de los recursos.\n15. Perspectiva de Género.\nTal como se consigna en el apartado 7.4. Supervisión y control, en cumplimiento a la Ley número 494 para la Igualdad entre Mujeres y Hombres y la Ley Número 553 de Acceso de las Mujeres a una Vida Libre de\nViolencia, ambas del estado de Guerrero, el Programa considerará en su operación, objetivos e indicadores de desempeño, la perspectiva de género.\nEl Programa incorporará la perspectiva de género con el propósito de contribuir al acceso de las mujeres a los beneficios de este Programa en igualdad de condiciones; así como medidas que aceleren el logro de igualitaria en la inclusión productiva, en la toma de decisiones y en los procesos de implementación del\nPrograma.\n16. Enfoque de Derechos. disponibilidad, accesibilidad y calidad en las acciones que realiza este Programa, se implementarán mecanismos que hagan efectivo el acceso a la información gubernamental, se asegurará que el acceso a los apoyos y servicios se dé únicamente con base en lo establecido en estas Reglas de Operación, sin discriminación alguna.\nREGLAS DE OPERACIÓN\nTodas las personas servidoras públicas involucradas en la operación del Programa deben promover, respetar, proteger y garantizar el ejercicio efectivo de los derechos humanos de las y los beneficiarios del\nPrograma, con base en los principios de universalidad, interdependencia, indivisibilidad y progresividad, brindando en todo momento un trato digno y de respeto a la población objetivo, con apego a los criterios de igualdad y no discriminación.\nEn la aplicación del Programa, se harán valer los derechos de las familias jornaleras agrícolas migrantes, tomando en consideración los factores de desigualdad que pudieran poner en riesgo de vulnerabilidad a personas que pertenecen a grupos históricamente discriminados, como lo son niñas y niños, jóvenes, personas con discapacidad, personas en situación de calle, en situación de desplazamiento interno, mujeres, personas migrantes, afrodescendientes, y aquellas pertenecientes a pueblos y comunidades indígenas, entre otros, tomando en consideración sus circunstancias y necesidades, a fin de contribuir a generar conocimiento y acciones que potencien su atención integral e inclusión plena, en concordancia también con los objetivos de la Agenda 2030.\n17. Acciones Contra el SARS-COV 2.\nEn atención a la pandemia por COVID-19, la SEMAI, ha implementado medidas sanitarias para la recepción de las solicitudes de manera presencial y vía telefónica y correo electrónico.\nLas medidas sanitarias tanto del personal operativo como de las y los solicitantes son, el uso de cubrebocas, el acceso a las instalaciones de la institución a través de filtro sanitario, con aplicación de gel antibacterial.\nAsimismo, la atención por vía telefónica y el envío de documentos vía correo electrónico, propicia la posibilidad de disminuir al máximo la posibilidad de contagios de SARS-COV2.\n18. Anexos que reflejen la entrega del apoyo (Económico. Especie o Servicios).\nAnexo 1. Matriz de indicadores para Resultados.\nAnexo 2. Acta de Donación.\nREGLAS DE OPERACIÓN\nAnexo 1\nFamilias Jornaleras.\n{\"tabla_1\":{\"columnas\":[\"(sin encabezado)\",\"Resumen\\nNarrativo\",\"Indicadores\",\"Medios de\\nverificación\",\"Supuestos\"],\"filas\":[{\"columna_1\":\"Fin\",\"columna_2\":\"Generar Oportunidades\\nde empleo e ingreso en\\ncomunidades jornaleras,\\nmediante el impulso a la\\nproducción local de\\nbienes de consumo a\\nbajo costo,\\ndisminuyendo el flujo de\\nmigración y evitando la\\nmigración de familiares\\nde jornaleras y jornaleros\\npropensos a emigrar.\",\"columna_3\":\"Autoempleos\\njornaleros\\ngenerados.\",\"columna_4\":\"Informe\\nanual\\nSEMAI.\",\"columna_5\":\"Han sido\\ngenerados\\nautoempleos,\\npropiciando\\nel arraigo\\nsocial de las\\ny los jornaleros.\"},{\"columna_1\":\"Propósito\",\"columna_2\":\"Apoyar a las y los\\nJornaleros agrícolas\\nMigrantes de Guerrero\\nasí como a miembros de\\nsus familias en\\npropensión de\\nemigrar, con el equipo,\\nherramientas y\\naccesorios\\nnecesario para que\\nemprendan un\\nproyecto\\nproductivo de\\nautoempleo o una\\nmicroempresa\\nsocial productiva.\",\"columna_3\":\"Jornaleras y\\nJornaleros\\nagrícolas\\napoyados.\",\"columna_4\":\"Informe\\nanual\\nSEMAI.\",\"columna_5\":\"Las y los\\njornaleros\\nagrícolas han\\nsido\\napoyados.\"}]}}\nREGLAS DE OPERACIÓN\n{\"tabla_2\":{\"columnas\":[\"Componentes\",\"Proyectos\\nproductivos:\\n● Del Sector\\nAgropecuario.\\n● Del sector\\nMicroindustrial y\\nAgroindustrial.\\n● Del sector Servicios.\\n● Del Sector Artesanal\\n● Proyectos de\\nInfraestructura\\nComplementaria.\\n● Proyectos de\\nPlaneación y promoción\\nSocial.\",\"Componentes\\nejecutados.\",\"Informe\\nanual\\nSEMAI.\",\"Los\\ncomponentes del\\nPrograma han\\nsido respaldados\\ny se encuentran\\nen ejecución.\"],\"filas\":[{\"columna_1\":\"Actividades\",\"columna_2\":\"Proyectos productivos,\\nde equipamiento,\\npromoción social y\\nfomento organizativo,\\ndirigidas al fomento y\\nmejoramiento de las\\nactividades\\nagropecuarias,\\nmicroindustriales y\\nagroindustriales, de\\nservicios y artesanales,\\npara la reactivación de\\ncadenas productivas y\\ncircuitos\\nmicrorregionales de\\nproducción-\\ncomercialización-\\nconsumo.\",\"columna_3\":\"Proyectos\\nproductivos\\nrealizados.\",\"columna_4\":\"Informe\\nanual\\nSEMAI.\",\"columna_5\":\"Los productivos\\nhan sido\\napoyados y se\\nencuentran en\\nejecución.\"}]}}\nREGLAS DE OPERACIÓN\nAnexo 2\nActa de Donación.\nBienestar de Comunidades Jornaleras, dependiente de la Secretaría de los Migrantes y Asuntos\nInternacionales, el importe correspondiente al proyecto de_____________________, que se ejecutará en la localidad de: _____________________, municipio de ___________________, del estado de Guerrero.\nAcreditación de Jornalero Agrícola: Talón de pago. () Constancia de empresa o patrón. ()\nChilpancingo, Gro; a _______de __________del 2023.\nNOMBRE:\nDOMICILIO:\nOCUPACION:\nClave Única de Registro de Población (CURP): _________________________________________\nEste programa es de carácter público, no es patrocinado ni promovido por partido político alguno y sus recursos provienen de los impuestos que pagan todos los contribuyentes. Está prohibido el uso de este programa con fines políticos, electorales, de lucro y otros distintos a los establecidos. Quien haga uso aplicable y ante la autoridad competente”.\nREGLAS DE OPERACIÓN\nPrimero. El presente Acuerdo entrará en vigor al día siguiente de su publicación en el Periódico Oficial del\nSegundo. A partir de la entrada en vigor del presente Acuerdo, las Reglas de Operación del Programa de\nAutoempleo Productivo para el Bienestar de Comunidades Jornaleras, subsecuentes o sus modificaciones serán emitidas por la persona titular de la Secretaría de los Migrantes y Asuntos Internacionales del Estado de Guerrero, responsable directa de la operación y ejecución de estas.\nDado en el “Recinto de las Oficinas del Poder Ejecutivo del Estado”, inmueble ubicado en el número 62, Edificio Norte, Planta Baja, en el Boulevard René Juárez Cisneros, código postal 39974, colonia Ciudad de los Servicios, en la Ciudad de Chilpancingo de los Bravo, Capital del estado de Guerrero, a los diecisiete días del mes de marzo del año dos mil veintitrés.\nGOBERNADORA CONSTITUCIONAL DEL ESTADO DE GUERRERO.\nMTRA. EVELYN CECIA SALGADO PINEDA.\nRúbrica.\nSECRETARIO GENERAL DE GOBIERNO.\nMTRO. LUDWIG MARCIAL REYNOSO NÚÑEZ.\nRúbrica.\nSECRETARIA DE LOS MIGRANTES Y ASUNTOS INTERNACIONALES.\nLIC. SILVIA RIVERA CARBAJAL.\nRúbrica.",
  "ordenamiento": "PROGRAMA",
  "jurisdiccion": "GUERRERO",
  "fuente_oficial": "DIARIO OFICIAL DE LA FEDERACION",
  "Fecha de Publicación": "18 \nde Abril de 2023",
  "ULTIMA REFORMA PUBLICADA": null,
  "status": "VIGENTE",
  "es_escaneado": false,
  "tiene_tablas": true,
  "materia": [
    "laboral",
    "desarrollo social",
    "económico"
  ]
}