{
  "titulo": "Acuerdo por el Que Se Crea el Programa Uniformes (primaria Secundaria) Transformando la Educación D",
  "Contenido": "NIÑOS DE GUERRERO CON UNIFORMES, Y SE\nEMITEN SUS REGLAS DE OPERACIÓN\nGUERRERO CON UNIFORMES, Y SE EMITEN SUS REGLAS DE OPERACIÓN, PUBLICADO EN EL PERIÓDICO OFICIAL DEL\nGOBIERNO DEL ESTADO No. 74 ALCANCE I, EL VIERNES 13 DE SEPTIEMBRE DE 2024.\nTEXTO ORIGINAL.\nAcuerdo publicado en el Periódico Oficial del Gobierno del Estado número 19 el día martes 07 de marzo de 2023.\nACUERDO POR EL QUE SE CREA EL PROGRAMA UNIFORMES (PRIMARIA- SECUNDARIA)\nTRANSFORMANDO LA EDUCACIÓN DE LAS NIÑAS Y NIÑOS DE GUERRERO CON UNIFORMES, Y\nSE EMITEN SUS REGLAS DE OPERACIÓN.\nPoder Ejecutivo.\nMAESTRA EVELYN CECIA SALGADO PINEDA, GOBERNADORA CONSTITUCIONAL DEL ESTADO\nDE GUERRERO, CON FUNDAMENTO EN LO DISPUESTO POR LOS ARTÍCULOS 71, 87, 88, 90\nLOS ARTÍCULOS 1, 2, 4, 8, 9, 14, 16, 22 APARTADO A FRACCIONES I Y VII, 23 FRACCIÓN III Y 29\nDE LA LEY ORGÁNICA DE LA ADMINISTRACIÓN PÚBLICA DEL ESTADO DE GUERRERO NÚMERO\n242; 1, 2 FRACCIÓN I, 18 Y 25 DE LA LEY NÚMERO 454 DE PRESUPUESTO Y DISCIPLINA FISCAL\nDEL ESTADO DE GUERRERO; EN RELACIÓN CON EL ARTÍCULO 109 PÁRRAFO SEGUNDO\nGUERRERO; 47 Y ANEXOS 23 (E07) Y 23-A DEL DECRETO NÚMERO 424 DEL PRESUPUESTO DE\nEGRESOS DEL ESTADO DE GUERRERO PARA EL EJERCICIO FISCAL 2023 Y LOS LINEAMIENTOS\nPARA LA ELABORACIÓN DE LAS REGLAS DE OPERACIÓN DE LOS PROGRAMAS SOCIALES\nESTATALES 2022-2027.\nQue el artículo 3o Constitucional en su reforma actual, establece que el sistema educativo “tenderá a desarrollar armónicamente todas las facultades del ser humano y fomentará en él, a la vez, el amor a la\nPatria, el respeto a todos los derechos, las libertades, la cultura de paz y la conciencia de la solidaridad internacional, en la independencia y en la justicia; promoverá la honestidad, los valores y la mejora continua del proceso de enseñanza aprendizaje”. Por lo que la educación se basará en el respeto intrínseco de la dignidad de las personas, con un enfoque de igualdad sustantiva.\nQue la Nueva Escuela Mexicana (NEM) como Reforma Educativa impulsada en el primer año de gobierno adolescentes y jóvenes “promover el aprendizaje de excelencia, inclusivo, pluricultural, colaborativo y equitativo a lo largo del trayecto de su formación”.\nNIÑOS DE GUERRERO CON UNIFORMES, Y SE\nEMITEN SUS REGLAS DE OPERACIÓN el eje central del modelo educativo, además de ser incluyente, democrático, nacional, equitativo, integral, inclusivo, intercultural, plurilingüe que responde a las necesidades actuales y globales de nuestro entorno.\nQue el objetivo 4, Educación de Calidad para el Desarrollo Sostenible de México en su Agenda 2030:\n“Garantizar una educación inclusiva y equitativa de calidad y promover oportunidades de aprendizaje permanente para todos”, nos viene a refrendar la importancia de atender con urgencia los déficits educativos o áreas de oportunidad que se presentan en el estado.\nEl 16 de marzo de 2018, se instaló el Consejo Estatal de la Agenda 2030 para el Desarrollo Sostenible del\nEstado de Guerrero, el cual tiene a su cargo la coordinación institucional e intergubernamental para el diseño, implementación, seguimiento y evaluación de políticas públicas y programas para el cumplimiento de la Agenda 2030 para el Desarrollo Sostenible. Para dar seguimiento a los 17 Objetivos para el Desarrollo\nSostenible (ODS) de la Agenda 2030, se han identificado y vinculado en la estructura programática del\nAnteproyecto de Presupuesto de Egresos del Ejercicio Fiscal 2023 con los Programas presupuestarios\n(Pp). En la implementación de la metodología para la identificación de la vinculación de los Pp con las metas de los ODS se realiza un análisis, donde se identifican posibles vinculaciones a través de la coincidencia del objetivo con alguna meta de los ODS, o si el diseño de los beneficios es acorde al propósito de la meta, o si atiende necesidades de fortalecimiento de los ejecutores que actúan a favor de la meta.\nQue en atención a la meta 4.5 de la agenda 2030, la cual refiere, “eliminar las disparidades de género en la educación y asegurar el acceso igualitario a todos los niveles de la enseñanza y la formación profesional para las personas vulnerables, incluidas las personas con discapacidad, los pueblos indígenas y los niños en situaciones de vulnerabilidad”12, en esta nueva era de la Cuarta Transformación, se tiene el compromiso social y moral de que las condiciones desiguales y no favorables presentadas en las diferentes regiones de la entidad puedan ser transformadas positivamente para alcanzar el enfoque deseado, haciendo justicia social y laboral a los pueblos originarios del estado de Guerrero.\nQue en el Plan Estatal de Desarrollo 2022-2027 Dimensión VI Eje temático 1. Bienestar, Desarrollo Humano y Justicia Social, Objetivo 1.4 establece Garantizar una educación para todos como derecho fundamental de las y los guerrerenses, con equidad, inclusión y excelencia, para promover oportunidades de aprendizaje pertinentes en todas las edades, niveles y modalidades del Sistema Educativo.\nQue la estrategia 1.4.1 del citado Plan Estatal de Desarrollo, permitirá contribuir a que las niñas, niños, adolescentes, jóvenes y adultos accedan a los servicios públicos de educación en todos los niveles y modalidades mediante la ampliación de la cobertura escolarizada y no escolarizada.\nQue la línea de acción1.4.1.6 del mencionado Plan, contempla mejorar la atención educativa en los municipios y localidades actualmente atendidos, permitirá asegurar que las niñas y los niños de las familias económicos.\nNIÑOS DE GUERRERO CON UNIFORMES, Y SE\nEMITEN SUS REGLAS DE OPERACIÓN\nUno de los compromisos de la titular del ejecutivo estatal con la ciudadanía guerrerense, al asumir y tomar protesta como Gobernadora Constitucional del Estado es, lograr un Guerrero de tranquilidad, de paz, de justicia, de crecimiento y de empleo, contribuyendo con ello a construir historias de éxitos individuales y colectivos que permitan consolidar el crecimiento económico y estabilidad social.\nComo titular del Poder Ejecutivo, estoy comprometida con ser la principal promotora de acciones y establecer rutas encaminadas a lograr un estado moderno, inteligente y visionario. que las autoridades educativas estatal y municipal prestarán servicios educativos con equidad y excelencia, que para tal efecto establecerá, de acuerdo con la suficiencia presupuestal, programas de entrega gratuita de uniformes para los educandos de educación básica.\nActualmente he reconocido las bondades del Programa Uniformes (Primaria- Secundaria)\nTrasformando la Educación de las Niñas y Niños de Guerrero con Uniformes, para fortalecer la asistencia social a grupos vulnerables sobre todo a los encaminados a favorecer la permanencia y equidad educativa en el estado de Guerrero, por lo que he decidido dar continuidad al mismo, para coadyuvar así en la disminución de la deserción escolar mediante el otorgamiento de un uniforme escolar, al inicio de cada ciclo escolar para las niñas y niños inscritos en escuelas públicas el siguiente:\nACUERDO POR EL QUE SE CREA EL PROGRAMA UNIFORMES (PRIMARIA- SECUNDARIA)\nTRANSFORMANDO LA EDUCACIÓN DE LAS NIÑAS Y NIÑOS DE GUERRERO CON UNIFORMES, Y\nSE EMITEN SUS REGLAS DE OPERACIÓN.\nArtículo 1. Se crea el Programa Uniformes (Primaria-Secundaria) Transformando la Educación de las\nNiñas y Niños de Guerrero con Uniformes, el cual tiene por objeto favorecer la permanencia y equidad educativa en el estado otorgando uniformes escolares, al inicio de cada ciclo escolar para niñas y niños inscritos en escuelas públicas de nivel de educación primaria y secundaria con reconocimiento oficial de la\nSecretaría de Educación Guerrero (SEG).\nArtículo 2. La Secretaría de Educación Guerrero, tendrá a cargo la implementación, operación, ejecución, evaluación y administración del Programa, bajo los criterios de objetividad, equidad, transparencia, publicidad, selectividad y temporalidad, con estricto apego a la normatividad aplicable, por tanto, será la\nOperación.\nArtículo 3. Se emiten las Reglas de Operación del Programa Uniformes (Primaria-Secundaria)\nTransformando la Educación de las Niñas y Niños de Guerrero con Uniformes, en las cuales se establece el procedimiento de ejecución del Programa, los principios, requisitos que se deben observar para acceder al mismo en los términos siguientes:\nREGLAS DE OPERACIÓN DEL PROGRAMA UNIFORMES (PRIMARIA- SECUNDARIA)\nTRANSFORMANDO LA EDUCACIÓN DE LAS NIÑAS Y NIÑOS DE GUERRERO CON UNIFORMES.\nNIÑOS DE GUERRERO CON UNIFORMES, Y SE\nEMITEN SUS REGLAS DE OPERACIÓN\n1. Introducción.\n1.1. Antecedentes.\nEn el estado de Guerrero, durante el presente ciclo escolar 2022-2023, asisten a la escuela primaria\n211,663 (103,856 niñas y 107,423 niños) y secundaria 88,367 (43,931 niñas y 44,436 niños) de las modalidades de educación general (federal transferido y federal transferido estatal), indígena, del Consejo\nNacional de Fomento Educativo (CONAFE) y particulares.\nConsecuencia de la pobreza en la que vive gran parte de la población en el estado de Guerrero, la entidad es considerada la tercera con mayor índice de pobreza a nivel nacional, sólo superada por los estados de\nOaxaca y Chiapas.\nEs por ello que el Programa Uniformes (Primaria-Secundaria) Transformando la Educación de las Niñas y\nNiños de Guerrero con Uniformes, se genera suministrando uniformes escolares a las niñas y niños de educación primaria y secundaria de escuelas públicas con reconocimiento oficial de la Secretaría de\nEducación Guerrero (SEG), ubicadas en los municipios del estado como una estrategia compensatoria que favorezca la permanencia y equidad educativa, identificándoles como niñas, niños y reforzando su seguridad, evitando la discriminación, y fortaleciendo su disciplina y orgullo de pertenencia a su escuela.\n2. Alineación Programática al PED y/o PND.\nEl Programa denominado Uniformes (Primaria-Secundaria) Transformando la educación de las niñas y niños de guerrero con uniformes se encuentra enmarcado en el Plan Estatal de Desarrollo 2022-2027\nDimensión VI; Eje temático 1. Bienestar, Desarrollo Humano y Justicia Social, Objetivo 1.3 disminuir las desigualdades a través de la atención a grupos vulnerables.\nEstá alineado a la Estrategia 1.3.1 garantizar el pleno goce de los derechos fundamentales de las niñas, niños y adolescentes.\nEn la Línea de acción 1.3.1.3 disminuir la deserción escolar de las niñas, niños y adolescentes de nivel que fortalezcan la economía familiar.\nEste Programa se alinea al Programa Sectorial Educativo 2022- 2027, por lo que, además, con su aplicación y ejecución favorece la permanencia y equidad educativa en el estado, otorgando uniformes educación primaria y secundaria con reconocimiento oficial de la SEG.\n2.1. Diagnóstico.\nDatos recientes del Instituto Nacional de Educación de los Adultos (INEA) señalan que 33 millones de personas en México están en rezago educativo: seis no saben leer y escribir; 10 no han terminado sus\nNIÑOS DE GUERRERO CON UNIFORMES, Y SE\nEMITEN SUS REGLAS DE OPERACIÓN estudios de educación secundaria y 17 dejaron inconclusa la secundaria, cerca de 30 por ciento de la población nacional tiene deficiencias educativas.\nSi estos mismos datos se aplican en el estado de Guerrero, tenemos que el problema casi se duplica, pues en nuestra entidad, de acuerdo con la información del Consejo Nacional de Evaluación de las Políticas de\nDesarrollo Social (CONEVAL), el 57.98 por ciento de personas mayores de 15 años se encuentran en una situación similar; 20 por ciento no sabe leer y escribir; 38 por ciento no ha finalizado su primaria o terminado la secundaria. Considerando que en Censo de Población de 2010 somos 3.4 millones de guerrerenses, entonces tenemos que 680 mil no están alfabetizados y 1.3 millones no concluyeron su primaria o la secundaria.\nEl rezago educativo es un problema de alta dimensión y de acumulación histórica, cuya tarea está encomendada a las instancias de atención educativa de jóvenes y adultos de la entidad. Según la publicación de resultados del portal del INEA, en el 2021 alfabetizaron 2,935 personas, 3,466 concluyeron sus estudios de nivel primaria y 5,692 concluyeron sus estudios de secundaria, para una suma de 12,093 guerrerenses mayores de 15 años que dejaron de pertenecer al rezago educativo, cuantificado en un universo de más de 1’065,000. El analfabetismo en Guerrero es de 304,774 personas de 15 y más; 284,593 no cuentan con estudios con la educación primaria concluida y 476 mil 186 sin estudios de educación secundaria concluida. En suma, 1’065,553 guerrerenses mayores de 15 años forman parte del rezago educativo de nivel básico, que representan el 42.5 % en la entidad.30 Guerrero, es el tercer estado de la república con el mayor rezago educativo en educación básica con el 42.6 %, segundo lugar nacional en analfabetismo con el 12.5 %, sexto lugar en población mayor de 15 años sin educación primaria; y quinto lugar en población sin educación secundaria.\nLos datos estadísticos de la deserción escolar en Guerrero muestran un comportamiento histórico ascendente en educación primaria. En el ciclo escolar 2015-2016 era de 1.2 %, hasta posicionarse en el año 2019 en el 2.1 %. Sin duda, un problema de impacto en el Sistema Educativo Estatal, considerando que la media nacional es del 0.4 %. En educación secundaria, en el ciclo escolar 2015-2016 era del 4.7 %, con tendencia ascendente hasta el 6.3 % en el año 2019. La educación media superior, en el ciclo escolar\n2015-2016, era del 8.6 %, su tendencia fue de incremento hasta ubicarse en el 14.4 % en 2019. Sólo en educación superior hay una mínima diferencia respecto al ciclo escolar 2016-2017 en el que la deserción escolar fue del 6.1 %, registrando en 2019 el 6.2 %. El factor deserción escolar de la educación básica y\nSistema Educativo del estado.\nEl rezago educativo guerrerense no es, por supuesto, igual en las ocho regiones y en todos los municipios que forman parte de nuestra entidad. El municipio con el mayor rezago es Cochoapa el Grande, en La\nMontaña, con 96.68% y el de menor atraso es Chilpancingo, en la zona Centro, que tiene 37.74%, Iguala de la Independencia, en la región Norte, con 41.33%, es el segundo mejor municipio en avance educativo.\nAcapulco de Juárez ocupa el tercero con un porcentaje de 42.34%.\nNIÑOS DE GUERRERO CON UNIFORMES, Y SE\nEMITEN SUS REGLAS DE OPERACIÓN\nEn la Costa Grande, el mejor posicionado de los ocho municipios que la forman, es Zihuatanejo de Azueta con 45.84%, y el de mayor atraso es Coahuayutla de José María Izazaga, por cierto, el de mayor extensión territorial, que tiene 88.83%.\nEn la Región Tierra Caliente, Pungarabato, es el más avanzado tiene un rezago de 52%, y Zirándaro de los Chávez el más atrasado, de los nueve de la región, con 83.38% de los municipios que pertenecen a la\nCosta Chica, Marquelia y Ometepec con un 59% de rezago y Xochistlahuaca, el de mayor atraso con\n86.71% de su población sin educación básica concluida.\nEl derecho a la educación supone para las y los mexicanos que esta sea pública, laica y de calidad, la cual no debe circunscribirse a grupos de edad, al ciclo señalado como obligatorio o al sistema escolarizado.\nAdemás, debe garantizarse la permanencia, por lo menos, a la conclusión del nivel básico que es seis años de primaria y tres de secundaria.\nEs importante puntualizar que el aprendizaje obtenido sea relevante y pertinente para que las y los mexicanos logren un mejor desarrollo humano como lo establece el artículo 3o de nuestra Carta Magna, su ley reglamentaria y los convenios internacionales signados por nuestro país sobre los derechos humanos, económicos, sociales y culturales.\n2.1.1. Población Potencial.\nNiñas y niños inscritos en escuelas públicas de nivel primaria y secundaria modalidad general, particulares e indígena, con reconocimiento oficial de la SEG.\n2.1.2. Población Objetivo.\nLa población objetivo del Programa, 211, 663 niñas y niños de primarias y 88, 367 niñas y niños de secundarias legalmente inscritos en escuelas públicas de nivel primaria y secundaria modalidad general, e indígena, con reconocimiento oficial de la SEG, de todos los municipios y localidades del estado, para evitar la deserción escolar.\n2.1.3. Población Beneficiaria. y que cumplan con los criterios y requisitos previstos en las presentes Reglas de Operación, las cuales obtendrán el apoyo de un uniforme escolar para dar continuidad sus estudios. Con la implementación del\nPrograma se espera beneficiar a 211, 663 niñas y niños de primaria y 88, 367 niñas y niños de secundaria con un total de 300, 030 niñas y niños.\n2.1.4. Población Indígena.\nNIÑOS DE GUERRERO CON UNIFORMES, Y SE\nEMITEN SUS REGLAS DE OPERACIÓN los criterios y requisitos previstos en las presentes Reglas de Operación.\n2.2. Fundamento Legal.\na) Constitución Política de los Estados Unidos Mexicanos;\nb) Ley General de los Derechos de Niñas, Niños y Adolescentes;\nd) Ley Sobre el Sistema Estatal de Asistencia Social Número 332;\ne) Ley Número 812 para la Protección de los Derechos de Niñas, Niños y Adolescentes del Estado de\nGuerrero;\ng) Ley Número 207 de Transparencia y Acceso a la Información Pública del Estado de Guerrero;\nh) Ley Orgánica de la Administración Pública del Estado de Guerrero Número 242;\ni) Decreto Número 181 por medio del cual la Sexagésima Tercera Legislatura al Honorable Congreso del\nj) Decreto Número 424 del Presupuesto de Egresos del Estado de Guerrero para el Ejercicio Fiscal 2023;\nk) Declaración Universal de los Derechos Humanos;\nl) Declaración de los Derechos del Niño;\nm) Convención de los Derechos del Niño;\nn) Ley Número 760 de Responsabilidades Política, Penal y Civil de los Servidores Públicos del Estado de\nGuerrero;\no) Ley Número 454 de Presupuesto y Disciplina Fiscal del Estado de Guerrero;\np) Ley Número 464 de Educación del Estado de Guerrero;\nq) Lineamientos para la Elaboración de las Reglas de Operación de los Programas Sociales Estatales\n2022-2027, y\nNIÑOS DE GUERRERO CON UNIFORMES, Y SE\nEMITEN SUS REGLAS DE OPERACIÓN\nr) Todos aquellos ordenamientos normativos que sean aplicables.\n2.3. Definiciones y Siglas.\nDefiniciones:\nApoyo: Será en especie o vale, para un uniforme escolar, integrado de acuerdo al nivel educativo de educación primaria y secundaria, grado escolar, talla y sexo, con características convenientes y criterios.\nSocioculturales y ambientales.\nBeneficiarias y Beneficiarios: Las Niñas y niños legalmente inscritos en escuela pública y de nivel primaria y secundaria con reconocimiento oficial de la Secretaría Educación Guerrero.\nPrograma: El Programa Uniformes (Primaria-Secundaria) Transformando la Educación de las Niñas y\nNiños de Guerrero con Uniformes.\nReglas de Operación: Conjunto de disposiciones que precisan la forma de operar un programa, con el propósito de transparentar y normar la distribución y entrega de los apoyos.\nSecretaría de Contraloría: La Secretaría de Contraloría y Transparencia Gubernamental.\nSolicitante: Madres o padres, tutoras o tutores de las Niñas y niños.\nSiglas:\nCONEVAL: Consejo Nacional de Evaluación de las Políticas de Desarrollo Social.\nIED: Inversión Estatal Directa.\nINEA: Instituto Nacional para la Educación de los Adultos.\nPED: Plan Estatal de Desarrollo.\nSEG: Secretaría de Educación Guerrero.\nREUNE: Registro Estatal de Uniformes Escolares.\nSEFINA: Secretaría de Finanzas y Administración.\nSEPLADER: Secretaría de Planeación y Desarrollo Regional.\n3. Objetivos y Alcances.\nNIÑOS DE GUERRERO CON UNIFORMES, Y SE\nEMITEN SUS REGLAS DE OPERACIÓN\n3.1. Objetivo General. de Guerrero.\n3.2. Objetivos Específicos.\na) Otorgar un uniforme escolar, al inicio de cada ciclo escolar para las niñas y niños inscritos en escuelas públicas y de nivel de educación primaria y secundaria con reconocimiento oficial de la SEG.\nb) Motivar a las niñas y niños inscritos en escuelas públicas y particulares, para que logren continuar y concluir su educación primaria y secundaria.\n3.3. Cobertura.\nEl Programa busca beneficiar en cada ciclo escolar a 211, 663 niñas y niños de escuelas de nivel primaria y 88, 367 niñas y niños de escuelas de nivel secundaria con reconocimiento oficial registradas por la SEG, de manera directa y de acuerdo a la disponibilidad presupuestal con que cuenta el Programa favoreciendo su permanencia y equidad educativa, dando prioridad a los municipios y localidades de mayor grado de marginación.\n3.4. Alcances.\nPara el logro de los objetivos, esto se alcanza en el corto y mediano plazo, atendiendo la disponibilidad presupuestal.\n4. Metas Físicas.\nEl Programa contempla atender a 300,030 niñas y niños beneficiarios directos, contemplando también casos emergentes o especiales de acuerdo a la disponibilidad presupuestaria y financiera.\n5. Programación Presupuestal.\nPara la aplicación y ejecución del Programa, el origen del financiamiento es a través de Inversión Estatal\nDirecta (IED), le fue asignado un monto de $84’048,000.00 (Ochenta y cuatro millones cuarenta y ocho mil pesos 00/100 m.n.), mismos que serán coordinados a través de la SEG.\nNIÑOS DE GUERRERO CON UNIFORMES, Y SE\nEMITEN SUS REGLAS DE OPERACIÓN\nUNIFORMES (PRIMARIAS) TRANSFORMANDO LA EDUCACIÓN DE LAS\nNIÑAS Y NIÑOS DE GUERRERO CON UNIFORMES\nPROGRAMACIÓN PRESUPUESTAL\nConceptos de gasto IED\nDispersión al Programa $53,096,674.80\nGastos de Operación 3% $1,642,165.20\nTOTAL $54,738,840.00\nUNIFORMES (SECUNDARIAS) TRANSFORMANDO LA EDUCACIÓN DE LAS\nNIÑAS Y NIÑOS DE GUERRERO CON UNIFORMES\nPROGRAMACIÓN PRESUPUESTAL\nConceptos de gasto IED\nDispersión al Programa $28,429,885.20\nGastos de Operación 3% $ 879,274.80\nTOTAL $29,309.160.00\nComo se ha señalado el origen del financiamiento para el Programa, es por la modalidad de administración directa, en tanto no se convenga con instancias estatales o federales, instituciones educativas u organizaciones no gubernamentales (ONG) no se estará en la disponibilidad de ampliar metas.\nLos recursos asignados a éste Programa son mediante IED y se asignarán en función de la disponibilidad presupuestal.\nLa instancia ejecutora del Programa, deberá presentar a la SEFINA y a la SEPLADER un reporte final al cierre de cada ejercicio fiscal. De igual manera, dicha información deberá ser registrada en el Sistema\nIntegral de Evaluación y Seguimiento (SIES).\n5.1. Gastos de Operación.\nLos gastos de operación serán de hasta el tres por ciento del presupuesto total asignado a este Programa; dichos recursos económicos serán destinados a las diversas acciones asociadas con la planeación, operación, supervisión, seguimiento, contraloría social y evaluación o asesoría externa del Programa, tal como lo señala el artículo 47 de la Ley de Coordinación Fiscal.\n6. Criterios y Requisitos de Elegibilidad.\n6.1. Requisitos de Acceso.\nNIÑOS DE GUERRERO CON UNIFORMES, Y SE\nEMITEN SUS REGLAS DE OPERACIÓN\na) Convocatoria. Publicación de convocatoria en medios de comunicación, especificando los requisitos y características del Programa, que deben cubrir las niñas y niños de las escuelas públicas de primaria y secundaria con reconocimiento oficial de la Secretaría de Educación Guerrero (SEG), ubicadas en los municipios del estado de Guerrero.\nb) Registro. Este se llevará cabo a través de las instituciones educativas de nivel primaria y secundaria del estado de Guerrero, las cuales en términos de la convocatoria harán llegar los expedientes del total de niñas y niños oficialmente inscritos a la SEG, que soliciten acceder a la plataforma (REUNE).\nc) Beneficiarias y Beneficiarios. Las niñas y niños que se encuentren oficialmente inscritos en instituciones educativas públicas de nivel primaria y secundaria del estado de Guerrero, con reconocimiento oficial de la SEG.\nd) Para tener acceso a los apoyos del Programa: Las niñas y niños solicitantes deberán estar inscritos en una escuela pública de nivel básico en educación primaria y secundaria de la entidad, comprobándolo a través de la constancia de inscripción vigente.\ne) El Programa: Se plantea bajo el principio de la universalidad, por lo que las niñas y niños que cumplan con los criterios de selección establecidos en las presentes Reglas de Operación, podrán ser beneficiarias o beneficiarios siempre y cuando pertenezcan a una escuela con reconocimiento oficial de la SEG.\n7. Tipo, Monto y Periodicidad del Apoyo.\n7.1. Características de los Apoyos.\nEntrega de un uniforme escolar para cada niña y niño de las escuelas de nivel primaria y secundaria oficialmente registrada o registrado por la SEG, ubicadas en todos los municipios. La entrega se llevará a cabo en la primera semana, al inicio de cada ciclo escolar, a través del Programa.\n7.2. Recursos no Devengados.\nEl presupuesto autorizado al Programa que no se haya aplicado a los fines autorizados, y los recursos que por cualquier motivo no se hayan devengado al 31 de diciembre de cada ejercicio fiscal, serán reintegrados inmediatamente a la instancia normativa del ejercicio y control del gasto público, es decir a la SEFINA.\n7.3. Resguardo de la Documentación.\nLos expedientes de las beneficiarias y beneficiarios en las diferentes instituciones educativas, serán resguardados, se capturarán y digitalizarán en el Sistema de Información de la SEG, lo que permitirá actualizar la base de datos de las beneficiarias y beneficiarios. Dicha información será incorporada en el sistema de datos personales el cual se denominarán Sistema Informático Único de la SEG, cuya finalidad es contar con un padrón de beneficiarias y beneficiarios homogéneo y confiable.\nNIÑOS DE GUERRERO CON UNIFORMES, Y SE\nEMITEN SUS REGLAS DE OPERACIÓN\n7.4. Supervisión y Control.\nLa SEG, en operación al Programa, para la mejora de éste, integrará informes a través de la Coordinación\nPrograma.\nEl control y la vigilancia del Programa, para niñas y niños de escuelas de nivel de educación primaria y secundaria con reconocimiento oficial de la SEG, se hará a través de la\nCoordinación de Seguimiento y Evaluación Social dependiente de la Coordinación General del Programa que asigne la SEG, quien será la encargada de validar los criterios de elegibilidad de las beneficiarias y beneficiarios y dar seguimiento a las denuncias recibidas.\n8. Criterios de Selección.\nCuando las niñas y niños solicitantes han culminado exitosamente su proceso de registro en la Plataforma\nREUNE y se cuenta con el expediente físico completo, éste se captura y digitaliza en el Sistema Informático\nÚnico de la SEG, que permite conformar la Base de Datos de Solicitantes y se procede de la manera siguiente:\na) Validación. Se hace una validación al expediente de la niña o niño en lo que respecta a los datos proporcionados a fin de determinar si cumple con los criterios generales y las disposiciones específicas establecidas en las presentes Reglas de Operación, de ser así pasa a la siguiente etapa, de lo contrario se desecha esa solicitud;\nb) Confrontación. Con la finalidad de verificar que la escuela primaria y secundaria a la que pertenecen las niñas y niños solicitantes cuente con reconocimiento oficial de la SEG se confrontará su Clave de Centro de Trabajo con el Catálogo de Centros de Trabajo de la SEG, además:\n●Si la escuela solicitante no tiene reconocimiento oficial, automáticamente quedan sus niñas y niños fuera del proceso de selección, por incumplir con lo establecido en las presentes Reglas de Operación.\n●Las seleccionadas y seleccionados para recibir el apoyo, quedan sujetos a la disponibilidad presupuestal del Programa.\nc) Con el fin de obtener un registro para el control de la información, las posibles beneficiarias y beneficiarios presentarán (a través de sus madres, padres o tutoras, tutores), deberán de presentar original y copia de los documentos siguientes:\n● Acta de Nacimiento;\n● Clave Única de Registro de Población (CURP);\n● Identificación oficial con fotografía de la madre, padre o tutora, tutor (INE, cédula profesional o pasaporte);\nNIÑOS DE GUERRERO CON UNIFORMES, Y SE\nEMITEN SUS REGLAS DE OPERACIÓN\nd) Constancia de inscripción vigente que avale que la alumna o alumno se encuentre legalmente inscrito en la institución pública de educación primaria y secundaria del estado de Guerrero, expedida por la directora o director de la escuela.\nLos documentos deberán ser entregados (a través de sus madres, padres o tutoras, tutores) en la escuela a la que pertenezcan las niñas y niños solicitantes, el trámite se realizará invariablemente de manera personal, en lugar y tiempo que lo requiera el Programa, por lo que no se les dará trámite a los paquetes de solicitudes enviadas por representantes o líderes partidistas.\nLas niñas y niños solicitantes que hayan cumplido en tiempo y forma con los requisitos establecidos en estas Reglas de Operación, estarán condicionados a la disponibilidad presupuestal del Programa, así como al dictamen técnico que efectúe la SEG, para obtener el beneficio directo.\n8.1. Casos Especiales\nEl único registro de permanencia en el Programa es comprobar estar legalmente inscrito en una institución educativa pública de nivel primaria, con reconocimiento oficial de la SEG.\nLa suspensión o baja temporal del Programa, se dará cuando la niña o niño, haya sido dado de baja en la institución educativa, ya sea de manera temporal o definitiva según sea el caso.\nLa baja definitiva del Programa se dará por fallecimiento de la beneficiaria o beneficiario.\n8.2. Casos de Emergencias o Desastre.\nCon el fin de evitar la interrupción de la operación del Programa, en caso de que exista una Declaratoria de Emergencia o de Desastre, la SEG, podrá entregar a la población beneficiaria del Programa que se encuentre inmersa en la zona de desastre, se podrá postergar la entrega de uniformes a las beneficiarias y beneficiarios, hasta en tanto concluye la presencia del fenómeno natural.\n8.3. Suspensión o Cancelación del Programa Social.\nLa SEG podrá suspender o cancelar la operación del Programa, cuando no exista las condiciones socioeconómicas entre las partes, cuando uno de las beneficiarias y beneficiarios no acate las estatal, federal, cuando lo determine la persona titular del ejecutivo estatal y por problemas de gobernabilidad.\n8.4. Integración del Padrón de Personas Beneficiarias.\nUna vez que las personas solicitantes son incorporadas al Programa, formarán parte de un Padrón Único de Personas Beneficiarias, el cual será de carácter público, siendo reservados sus datos personales, de acuerdo con la normatividad vigente; los cuales en ningún caso podrán emplearse para propósitos de\nNIÑOS DE GUERRERO CON UNIFORMES, Y SE\nEMITEN SUS REGLAS DE OPERACIÓN proselitismo, religioso o comercial, ni para ningún otro fin distinto al establecido en las Reglas de Operación del Programa.\n9. Mecánica Operativa del Programa Social.\nLa operación del Programa se desarrollará a través de Reglas de Operación que permitan delimitar las facultades y competencia de ejecución de las instancias que participan, así como para coadyuvar en la correcta realización de las labores encomendadas al personal y propiciar la eficiencia y uniformidad en este apoyo social.\n9.1. Instancia Ejecutora y /o Responsable.\nLa instancia ejecutora y responsable de este Programa será la SEG, misma que realizará las actividades relacionadas con la gestión, operación, administración, comprobación y ejecución de los recursos.\nPersonal de la Secretaría de Educación Guerrero:\na) Tipo y Número.\nCANTIDA\nCARGO CATEGORÍA\nSecretario de Educación Guerrero 1 Coordinador General.\nCoordinador de\nSubsecretario de Administración y\n1 Seguimiento y Evaluación\nFinanzas\nSocial.\nDirección de Recursos Materiales 1 Coordinador de Logística\nDepartamento de Almacenes e Inventarios 1 Coordinador Estatal\nAlmacenes Regionales 8 Operativos Regionales\nCoordinador de Supervisores 8 Supervisores de Zona\nContraloría Social 1 Contralor Interno\nb) Reclutamiento Temporal (Personal con apoyos económicos por prestación de servicios). de la localidad de El Ocotito, municipio de Chilpancingo y para el apoyo de la distribución de maquila en el estado, el tiempo de contratación no será mayor al indicado en el calendario de actividades.\nNIÑOS DE GUERRERO CON UNIFORMES, Y SE\nEMITEN SUS REGLAS DE OPERACIÓN\nPERSONAL PARA EL CONTROL Y MANEJO DE\nUNIFORMES\nCANTIDA\nCARGO CATEGORÍA\nEncargado del Responsable de\nAlmacén en El 1 Almacén\nOcotito\nJefe de Almacén 1 Jefe de área\nAuxiliar de almacén 30 Personal de apoyo\nPersonal de aseo 2 Personal de aseo\nc) Adiestramiento. Es responsabilidad de la SEG, dar a conocer al personal adscrito a la misma el contenido y responsabilidad de las Reglas de Operación del Programa.\nd) Espacio físico. El espacio en que se desarrollará el Programa, será en las oficinas de la SEG ubicada en: Calle Capitán Julio Calva Capetillo No. 4, Colonia Ampliación Universal de la Ciudad de Chilpancingo, Guerrero y en giras de trabajo realizadas por la titular del Poder Ejecutivo del estado.\n9.2. Proceso de Incorporación al Programa Social.\nMediante convocatoria pública en al menos, en dos periódicos de mayor circulación en el estado de\nGuerrero, la SEG, emitirá los criterios que deben ser transparentes, equitativos y no discrecionales.\nSerán señalados los requisitos, forma de acceso y criterios de selección y mencionar los lugares, horarios de atención, y periodos de registro de las y los solicitantes.\nEn la convocatoria, serán señaladas las unidades administrativas responsables.\nCalendarización de actividades.\nACTIVIDADES\nDifusión de Contraloría\nSocial.\nRecepción de solicitudes.\nCaptura de solicitudes.\nRevisión e integración de expedientes.\nAutorización del apoyo.\nNIÑOS DE GUERRERO CON UNIFORMES, Y SE\nEMITEN SUS REGLAS DE OPERACIÓN\nCaptura de padrón de beneficiarias y beneficiarios.\nSupervisiones en almacenes.\nComisiones oficiales.\nEntrega\nSeguimiento y evaluación.\n10. Evaluación.\nLa evaluación del Programa, se hará a través de la Coordinación de Seguimiento y Evaluación Social dependiente de la Coordinación General del programa que asigne la SEG, se hará mediante la cuantificación de los resultados de acuerdo al número de beneficiarias y beneficiarios y al porcentaje de cobertura, para conocer el cumplimiento de las metas propuestas; en tal sentido y una vez concluida la evaluación, se atenderá y dará seguimiento a los Aspectos Susceptibles de Mejora (ASM).\nEn el marco de la operación del Programa, la evaluación puede ser:\na) Simultánea y al final del Programa. La evaluación que aplicará la SEG, se llevará a cabo al final del\nPrograma; no obstante, salvo indicaciones de su titular, podrá ser simultánea.\nb) Cuantitativa y cualitativa. La SEG, fungirá como la instancia administrativa y normativa del Programa, en caso de requerirlo podrá contar con el apoyo de los organismos que considere importantes para el exitoso desarrollo de sus actividades.\nc) Interna y externa. El Programa, estará sujeto a procesos periódicos de seguimiento y evaluación que tanto la obtención de información como la evaluación de los beneficios económicos y sociales.\nd) La Secretaría de Educación Guerrero. Podrá realizar una evaluación de resultados de carácter externo del Programa sujeto a las Reglas de Operación, para lo cual tendrá la facultad de designar a la instancia que realizará dicho análisis.\ne) Las evaluaciones externas. Las que se realicen al Programa serán coordinadas por la Secretaría de\nContraloría y la Contraloría Interna de la SEG.\n10.1. Indicadores (Construcción de la Matriz de Indicadores para Resultados. - Anexo 1) (Formato de la\nFID)\nNIÑOS DE GUERRERO CON UNIFORMES, Y SE\nEMITEN SUS REGLAS DE OPERACIÓN\nRAMO:INVERSIÓN ESTATAL DIRECTA\nFONDO: INVERSIÓN ESTATAL DIRECTA\nNIÑOS DEL ESTADO DE GUERRERO CON UNIFORMES\nEJE: 1 BIENESTAR, DESARROLLO HUMANO Y JUSTICIA SOCIAL\nOBJETIVO: 1.3 DISMINUIR LAS DESIGUALDADES A TRAVÉS DE LA ATENCIÓN A GRUPOS VULNERABLES.\nESTRATEGIA: 1.3.1 GARANTIZAR EL PLENO GOCE DE LOS DERECHOS FUNDAMENTALES DE LAS NIÑAS, NIÑOS Y\nADOLESCENTES.\nLÍNEA DE ACCIÓN: 1.3.1.3 DISMINUIR LA DESERCIÓN ESCOLAR DE LAS NIÑAS, NIÑOS Y ADOLESCENTES DE NIVEL BÁSICO QUE\nHABITAN EN LAS LOCALIDADES DE ALTA Y MUY ALTA MARGINACIÓN MEDIANTE EL IMPULSO DE PROGRAMAS QUE\nFORTALEZCAN LA ECONOMÍA FAMILIAR.\nDatos de identificación del indicador\nClave Nombre Fuente\n1.3.1.3\nDefinición NIVEL DE LA MIR Dimensión\nFIN EFICACIA\nMétodo de cálculo Unidad de medida\nPORCENTAJE\nFrecuencia de medición Desagregación geográfica Serie de información disponible\nESTATAL\nLínea base\nSentido del indicador\nAño Periodo Valor\nASCENDENTE 2023 2022-2023 0% (0)\nParámetros de semaforización Metas\nVerde Amarillo Rojo Año Periodo Valor\n2023\nVariables que conforman el indicador\nNombre Unidad de medida Fuente de información\nNombre Unidad de medida Fuente de información\nSECRETARÍA DE EDUCACIÓN\nGUERRERO.\nObservaciones\nResponsable del indicador\nNombre del Servidor Público Dependencia Área\nDR. MARCIAL RODRÍGUEZ SALDAÑA GUERRERO GUERRERO\nNombre del puesto, encargo o comisión Teléfono Correo electrónico\nSECRETARIO DE EDUCACIÓN GUERRERO 7474718300\nElaboró Revisó Autorizó\nNIÑOS DE GUERRERO CON UNIFORMES, Y SE\nEMITEN SUS REGLAS DE OPERACIÓN\nLIC. TEÓFILO PÉREZ PACHECO M.C. ALEJANDRO MORENO LIRA DR. MARCIAL RODRÍGUEZ SALDAÑA\nSUBSECRETARIO DE\nPalacio de Gobierno, Edificio Tierra Caliente, planta baja, correo electrónico: dge.seplader@guerrero.gob.mx\n10.2. Seguimiento.\nEl seguimiento a la operación del Programa, permitirá atender los principios de economía, eficacia, eficiencia, efectividad, imparcialidad, honestidad y apego a la normatividad, considerando que es un requisito previo indispensable para la aplicación de los instrumentos de evaluación o auditoría que implementará la unidad responsable y el órgano interno de control del gobierno del estado.\nPermitirá a su vez, la generación sistemática de información confiable sobre la asignación y el ejercicio de los recursos públicos destinados al programa, haciendo posible su valoración en diferentes ámbitos, según las necesidades de los tomadores de decisiones. (gestión, desempeño o gasto).\n10.3. Auditoría.\nEn caso de ser necesario, el recurso asignado al Programa, será verificado por la Secretaría de Contraloría y la Contraloría Interna de la SEG, como resultado de las acciones de auditoría que se lleven a cabo, la instancia auditora mantendrá un seguimiento interno que le permita emitir informes de las revisiones efectuadas.\n11. Mecanismo de Entrega del Apoyo.\nLa SEG, llevará a cabo actividades que permitan cristalizar los objetivos del Programa, entre las cuales se precisan las siguientes:\na) Difundir las actividades de Contraloría Social del Programa que se implementará a través de los Comités de Padres de Familia con el apoyo de la Secretaría de Contraloría y la Contraloría Interna de la SEG;\nb) Captura las solicitudes para integrar la demanda ciudadana;\nc) Supervisar por parte de la SEG, la entrega de los uniformes, en los almacenes de la misma SEG y las escuelas primarias y secundarias oficialmente registradas y ubicadas en todos los municipios del estado, con apoyo de la Subsecretaría de Administración y Finanzas, la Subsecretaría de Educación Básica y la\nContraloría Interna.\nd) Realizar el seguimiento y evaluación del Programa.\ne) Realizar las comisiones oficiales e institucionales.\nNIÑOS DE GUERRERO CON UNIFORMES, Y SE\nEMITEN SUS REGLAS DE OPERACIÓN\n12. Derechos y Obligaciones de las Personas Beneficiarias.\nLas beneficiarias y beneficiarios del Programa, tendrán derechos a recibir un uniforme escolar y la obligación de mantenerlo en buenas condiciones de uso en el ciclo escolar para el que le fue asignado; a través de los comités de contraloría social ubicadas en cada una de las escuelas, vigilarán que las alumnas y los alumnos, hagan buen uso del beneficio otorgado.\n12.1. Causales de Suspensión o Baja de la Persona Beneficiaria.\nLa suspensión o baja temporal del Programa, se dará cuando la niña y niño haya sido dado de baja en la institución educativa en la que, estando inscrito, solicitó el apoyo, ya sea de manera temporal o definitiva según sea el caso.\nLa baja definitiva de la beneficiaria o beneficiario del Programa se dará por fallecimiento.\nLos directivos de las escuelas de nivel primaria y secundaria receptoras del beneficio para sus niñas y niños legalmente inscritos y los comités de contraloría social, serán los enlaces para determinar esta acción.\n12.2. Proceso de Baja.\nLa dirección de las escuelas de nivel primaria y secundaria, los comités de contraloría social, incluso las madres o padres, podrán solicitar la baja temporal o definitiva del beneficio del Programa, como se establece en el punto 12.1, notificando a la coordinación general dicha acción.\nLa coordinación general del Programa, habiendo recepcionado el reporte de baja, procederá a la asignación del beneficio a otra alumna u otro alumno, ya sea de la propia escuela o cualquier otra escuela ubicada en los municipios y localidades del estado.\nSanciones: beneficiarios que:\na) No cumplan con alguna de las obligaciones estipuladas en las Reglas de Operación;\nb) Presentar documentación falsa, y\nc) En el caso de que la dependencia o algún órgano de fiscalización detecte alguna anomalía.\n13. Instancias participantes.\na) La SEPLADER, con la validación y aprobación de las Reglas de Operación.\nNIÑOS DE GUERRERO CON UNIFORMES, Y SE\nEMITEN SUS REGLAS DE OPERACIÓN\nb) La SEFINA, con la ministración de recursos presupuestales para la operación del Programa.\nc) La Secretaría de Contraloría y la Contraloría Interna de la SEG, son entes que pueden realizar la fiscalización del Programa.\nd) La SEG, es la instancia ejecutora del Programa, a través de la Coordinación General.\n13.1. Instancia Normativa.\nLa SEG, será la instancia normativa y de operación del Programa, esto último a través de la Coordinación\nGeneral y el apoyo de la Subsecretaría de Educación Básica y la Subsecretaría de Administración y\nFinanzas, las delegaciones regionales y los directivos de escuelas de nivel primaria y secundarias ubicadas en todos los municipios del estado de Guerrero.\nDe igual manera, el órgano interno de control del gobierno del estado y las instancias de la SEFINA.\nIntervendrán en la vigilancia de la operación del Programa y los recursos asignados, los comités de contraloría social ubicados en cada una de las escuelas.\nFunciones del Comité Técnico del Programa.\nEl Comité Técnico es un órgano de control interno para el seguimiento, control y evaluación del Programa, sus integrantes no podrán recibir remuneración alguna por su participación.\nEl Comité Técnico estará integrado por la SEG quien lo presidirá, la Secretaría de la Contraloría, la SEFINA, las subsecretarías de Administración y Finanzas y Educación Básica, el órgano interno de control de la\nSEG y la Coordinación General del Programa quien fungirá como Secretaría Técnica.\nSesionará de forma trimestral para presentar resultados, informes, toma de decisiones, evaluar la operatividad del Programa, determinar las fechas de las sesiones, firmar las actas correspondientes y, demás asuntos relativos al mismo.\nPara resolver asuntos importantes no previstos y casos urgentes o especiales, se celebrarán sesiones extraordinarias, las cuales serán convocadas por el Secretaría Técnica del Comité Técnico.\nPrograma.\n14. Transparencia. seleccionados, el seguimiento detallado y auditado en la operación del Programa, se llevará a cabo por\nNIÑOS DE GUERRERO CON UNIFORMES, Y SE\nEMITEN SUS REGLAS DE OPERACIÓN\nGeneral del Programa que asigne la SEG.\nEstado de Guerrero, la SEG, publicará periódicamente la información relativa al Programa en la página oficial del gobierno del estado https://www.guerrero.gob.mx/ y de la SEG http://www.seg.gob.mx/.\nEl Programa, se sustenta en la corresponsabilidad del gobierno con sus dependencias.\nEl gobierno estatal instrumentará el Programa con base en lo establecido en estas Reglas de Operación considerando siempre su disponibilidad presupuestal.\nLos datos personales que se recaben con motivo de la operación del presente Programa, serán protegidos e incorporados y tratados en el sistema de datos personales el cual se denomina: Sistema Informático\nÚnico de la SEG, cuya finalidad es contar con un padrón de beneficiarias y beneficiarios homogéneo dando transparencia y seguimiento puntual al estatus de las niñas y niños beneficiarios y de los recursos que se otorgan a través del Programa, favoreciendo con ello conductas a favor de una cultura de integridad, legalidad, honestidad y rendición de cuentas.\n14.1. Promoción y Difusión del Programa Social.\nLa SEG, a través del Programa, emitirá y publicará la convocatoria para el otorgamiento del apoyo a las niñas y niños solicitantes que demuestren estar inscritos en escuelas públicas de nivel de educación primaria con reconocimiento oficial de la SEG, en ella obligatoriamente se darán a conocer cuando menos el objetivo del Programa, los requisitos que deberán cumplir quienes aspiren al beneficio, la dirección de los módulos de información, número telefónico para pedir informes, la fecha de recepción de solicitudes y la fecha y forma de entrega de resultados, por conducto de los principales medios de difusión.\nLa información referente al Programa se podrá consultar de manera permanente en el portal oficial del gobierno del estado, así como el padrón de beneficiarias y beneficiarios actualizado.\nLa SEG, promoverá el Programa a través de los medios informativos tales como periódicos, carteles, Para cualquier información referente al Programa, se cuenta con un módulo de información ubicado en:\nCalle Capitán Julio Calva Capetillo #4, Colonia Ampliación Universal de la Ciudad de Chilpancingo, Guerrero y con la línea telefónica 01 800 727 17 17, y en las siete delegaciones regionales de la SEG en el estado.\nNIÑOS DE GUERRERO CON UNIFORMES, Y SE\nEMITEN SUS REGLAS DE OPERACIÓN\n14.2. Contraloría social. operación de los comités de contraloría social, existirá un Comité por cada escuela beneficiada, para el seguimiento, supervisión y vigilancia en el cumplimiento de entrega de uniformes.\nLos comités de padres de familias de cada escuela fungirán como comités de contraloría social debido a que las beneficiarias y beneficiarios directos no cuentan con la mayoría de edad.\nLos medios que se utilizarán para la promoción y divulgación de los beneficios del Programa, como acción de contraloría social serán los siguientes:\n● Auditivos. - Radio;\n● Impresos y escritos. - Diarios, trípticos;\n● Audiovisuales. - Televisión;\n● Multimedia. - Internet y televisión digital;\n● Telecomunicación. - Teléfonos fijos y celulares, y Grupales. - Reuniones informativas.\nLas personas que integren el Comité de Contraloría Social, tendrán que levantar un informe que contendrá como mínimo los datos siguientes:\n● Nombre del programa;\n● Nombre de la escuela;\n● Cantidad de apoyos otorgados;\n● Número de niñas y niños que recibieron el apoyo;\n● Número de niñas y niños que no recibieron el apoyo;\n●Fecha de entrega de apoyos, y\n● Observaciones.\nSEG, Calle Capitán Julio Calva Capetillo #4, Colonia Ampliación Universal de la Ciudad de Chilpancingo, Guerrero y las siete delegaciones regionales de la SEG en todo el estado.\nFormas de participación social:\nFORMAS DE PARTICIPACIÓN SOCIAL\nEtapa en la que Forma de\nParticipantes Modalidad participa participación\nNIÑOS DE GUERRERO CON UNIFORMES, Y SE\nEMITEN SUS REGLAS DE OPERACIÓN\nEstar presente en las\nComité de Etapa de entrega Vigilante en las actividades y dar fe de\nContraloría de uniformes. acciones de desarrollo la entrega de\nSocial. social del Programa uniformes.\n14.3. Protección de Datos personales.\nLos datos personales que se recaben con motivo de la operación del presente Programa, serán protegidos e incorporados y tratados en el sistema de datos personales el cual se denomina: Sistema Informático\nÚnico de la SEG, cuya finalidad es contar con un padrón de beneficiarias y beneficiarios homogéneo dando transparencia y seguimiento puntual al estatus de las niñas y niños beneficiarios y de los recursos que se otorgan a través del Programa, favoreciendo con ello conductas para una cultura de integridad, legalidad, honestidad y rendición de cuentas.\n14.4. Quejas y Denuncias.\nLas niñas y niños solicitantes o a través de sus madres, padres o tutoras, tutores podrán acudir en cualquier momento en la oficina de recursos materiales ubicada en Calle Obsidiana manzana 1 lote 1 fraccionamiento las Margaritas de la Ciudad de Chilpancingo, Guerrero, así como en la línea telefónica 7471388554 y el correo electrónico teofilo.perez@seg.gob.mx para expresar sus comentarios sobre la implementación y funcionamiento del Programa, de igual manera las quejas y denuncias sobre cualquier hecho, acto u omisión que produzca o pueda producir daños al ejercicio de sus derechos establecidos en las presentes\nReglas de Operación.\nLas quejas y denuncias de la ciudadanía en general por la presunción de actos de corrupción o desvío de recursos por parte de las servidoras o servidores públicos la SEG, se captarán en la Secretaría de\nContraloría, ubicada en Boulevard René Juárez Cisneros No. 62 Cd. de los Servicios, C.P. 39074 Palacio de Gobierno número telefónico 01 800 727 17 17 y en el órgano interno de control de la SEG.\nLos medios por los cuales podrán presentarse quejas y denuncias ciudadanas son las siguientes:\na) Por escrito;\nb) Por comparecencia de la persona interesada;\nc) Por correo electrónico, y\nd) por vía telefónica.\nLa persona denúnciate o quejosa deberá proporcionar los datos siguientes:\na) Nombre de la servidora o servidor;\nb) Dependencia de adscripción;\nc) Objeto de la denuncia;\nd) Nombre y domicilio de la persona quejosa, y\nNIÑOS DE GUERRERO CON UNIFORMES, Y SE\nEMITEN SUS REGLAS DE OPERACIÓN\ne) Identificación oficial.\n14.5. Acciones de Blindaje.\nComo estrategia de blindaje electoral; la papelería, documentación oficial, así como la publicidad y promoción del Programa deberán incluir alguna de las leyendas siguientes:\n“Este Programa es de carácter público, no es patrocinado ni promovido por partido político alguno y sus recursos provienen de los impuestos que pagan todos los contribuyentes”.\n“Está prohibido el uso de este Programa con fines políticos, electorales, de lucro y otros distintos a los establecidos. Quién haga uso indebido de los recursos de este Programa deberá ser denunciado y sancionado de acuerdo con la ley aplicable y ante la autoridad competente”.\nEn cuanto a la publicidad en medios electrónicos, impresos, complementarios o de cualquier otra índole, vinculados con los programas de comunicación social, se deberá incluir la siguiente leyenda: “Este\nPrograma es público y queda prohibido su uso con fines partidistas o de promoción personal”.\n14.6. Acta o vale de donación. Anexo 2.\n15. Perspectiva de género.\nSerá incorporada la perspectiva para contribuir al acceso de las niñas y niños a los beneficios de este\nPrograma en igualdad de condiciones; privilegiando, en su caso, la inclusión de medidas especiales de carácter temporal (acciones afirmativas), para solucionar las condiciones inmediatas en la vida de las niñas y los niños, y medidas estratégicas que tiendan a la valorización de la posición que las niñas tienen en la comunidad, modifique los patrones culturales y destierre los estereotipos que ocasionan discriminación y violencia, así como medidas que aceleren el logro de la igualdad sustantiva para el ejercicio pleno de todos los derechos de las alumnas y su participación igualitaria en la inclusión productiva, en la toma de decisiones, en los procesos de implementación del programa y en general, en el logro de los objetivos planteados en la Agenda 2030 para el desarrollo sostenible.\n16. Enfoque de derecho. pueden ocurrir en al menos en los casos siguientes:\na) Cuando una persona solicitante cumpla con los requisitos y criterios de inclusión para acceder a determinado derecho.\nb) Cuando la persona solicitante exija que se cumpla con dicho derecho de manera integral en tiempo y forma.\nNIÑOS DE GUERRERO CON UNIFORMES, Y SE\nEMITEN SUS REGLAS DE OPERACIÓN\nc) Cuando no se pueda satisfacer toda la demanda de incorporación al Programa por restricción presupuestal.\nSerá la Secretaría de Contraloría y el órgano interno de control de la SEG, quienes atenderán las denuncias de violación e incumplimiento de atención del Programa.\nTodas las personas servidoras públicas involucradas en la operación del Programa deben promover, respetar, proteger y garantizar el ejercicio efectivo de los derechos humanos de las y los beneficiarios, con base en los principios de universalidad, interdependencia, indivisibilidad y progresividad, brindando en todo momento un trato digno y de respeto a la población objetivo, con apego a los criterios de igualdad y no discriminación.\n17. Acciones contra SARS-COVID 19.\nEn atención a la pandemia por COVID-19, la SEG, implementará los protocolos y las medidas sanitarias que establezcan las autoridades de salud, antes durante y después de la entrega de los beneficios a que refiera el Programa para la no propagación de contagios, y así darle continuidad de la entrega de los mismos, priorizando las medidas sanitarias tanto del personal operativo como de las beneficiarias y los beneficiarios.\n18. Anexos que reflejen la entrega de apoyos (Económico, Especie o Servicios).\nAnexo 1. MIR\nNIÑOS DE GUERRERO CON UNIFORMES, Y SE\nEMITEN SUS REGLAS DE OPERACIÓN\nAnexo 1. MIR.\nFormato 4. MIR\nEje: 1 BIENESTAR, DESARROLLO HUMANO Y JUSTICIA SOCIAL\nAlineación al Plan\nObjetivo: 1.3 DISMINUIR LAS DESIGUALDADES A TRAVÉS DE LA ATENCIÓN A GRUPOS VULNERABLES. 2022-202 7.\nEstrategia: 1.3.1 GARANTIZAR EL PLENO GOCE DE LOS DERECHOS FUNDAMENTALES DE LAS NIÑAS, NIÑOS Y ADOLESCENTES.\nLínea de Acción: MARGINACIÓN MEDIANTE EL IMPULSO DE PROGRAMAS QUE FORTALEZCAN LA ECONOMÍA FAMILIAR.\nMatriz de indicadores para Resultados\nResumen Narrativo Indicadores de desempeño Medios de Verificación Supuestos\nCONTRIBUIR PARA DISMINUIR LA DESERCIÓN SECRETARÍA DE EDUCACIÓN\nPORCENTAJE DE CENTROS LAS COORDINACIONES DE LAS DIFERENTES\nESCOLAR DE LAS NIÑAS Y LOS NIÑOS DE GUERRERO.\nEDUCATIVOS A NIVEL BÁSICO REGIONES DE LA S.E.G DIFUNDEN LA\nFin NIVEL BÁSICO MEDIANTE LA ENTREGA DE https://w w w.guerrero.gob.mx/depende\nEN LA ENTREGA DE UNIFORMES CONVOCATORIA PARA EL REGISTRO DE LA\nUNIFORMES ESCOLARES EN LAS DIFERENTES ncia/sector-central/secretaria-deESCOLARES. PLATAFORMA REUNE.\nREGIONES DEL ESTADO DE GUERRERO. educacion-guerrero/\nCOORDINAR EL SUMINISTRO DE LOS\nRECURSOS MATERIALES GARANTIZANDO EL SECRETARÍA DE EDUCACIÓN\nLOS DIRECTIVOS DE CADA PLANTEL EDUCATIVO\nADECUADO SUMINISTRO DE UNIFORMES COBERTURA DE ENTREGA DE GUERRERO.\nPropósito A NIVEL BÁSICO PRIMARIA Y SECUNDARIA DAN A\nESCOLARES A LOS PLANTELES EDUCATIVOS UNIFORMES ESCOLARES EN EL https://w w w.guerrero.gob.mx/depende\n(resultados) CONOCER LA CONVOCATORIA A LOS PADRES DE\nEN EL NIVEL BÁSICO DE PRIMARIA Y NIVEL BÁSICO. ncia/sector-central/secretaria-deFAMILIA.\nSECUNDARIA, EN LAS DIFERENTES REGIONES educacion-guerrero/\nDEL ESTADO DE GUERRERO.\n1.-ENTREGA DE UNIFORMES ESCOLARES PORCENTAJE DE NIÑAS Y LOS PADRES DE FAMILIA O TUTORES REALIZAN\nNIVEL PRIMARIA, TRANSFORMANDO LA NIÑOS EN LA ENTREGA DE DIRECCIÓN DE RECURSOS EL REGISTRO DE LAS NIÑAS Y LOS NIÑOS, EN LA\nEDUCACIÓN DE LAS NIÑAS Y LOS NIÑOS DEL UNIFORMES ESCOLARES EN EL MATERIALES DE LA SEG. (matricula) PLATAFORMA RENUE DE NIVEL BÁSICO\nComponentes ESTADO DE GUERRERO. NIVEL BÁSICO DE PRIMARIA. PRIMARIA.\n(Servicios y 2.-ENTREGA DE UNIFORMES ESCOLARES, PORCENTAJE DE NIÑAS Y\nLOS PADRES DE FAMILIA O TUTORES REALIZAN\nProductos) NIVEL BÁSICO SECUNDARIA, NIÑOS EN LA ENTREGA DE\nDIRECCIÓN DE RECURSOS EL REGISTRO DE LAS ALUMNAS Y LOS\nTRANSFORMANDO LA EDUCACIÓN DE LAS UNIFORMES ESCOLARES EN EL\nMATERIALES DE LA SEG. (matricula) ALUMNOS, EN LA PLATAFORMA REUNE DE NIVEL\nNIÑAS Y LOS NIÑOS DEL ESTADO DE NIVEL BÁSICO DE SECUNDARIA.\nBÁSICO SECUNDARIA.\nGUERRERO..\nUNIDAD DE ORGANIZACIÓN,\n1. 1.-APERTURA DE LA PLATAFORMA RENUEE\nPORCENTAJE DE ADQUISICIÓN INNOVACIÓN Y CALIDAD Y LA LOS PROVEDORES ENTREGAN LOS UNIFORMES\nY LA ADQUISICIÓN DE UNIFORMES\nDE UNIFORMES ESCOLARES DIRECCIÓN DE TECNOLOGÍAS DE LA ECOLARES NIVEL BÁSICO DE PRIMARIA EN\nESCOLARES PARA LAS NIÑAS Y LOS NIÑOS\nNIVEL BÁSICO PRIMARIA INFORMACIÓN DE LA SEG.. TIEMPO Y FORMA.\nDE NIVEL BÁSICO EN PRIMARIA. http://reune.seg.gob.mx/\n1.2. CALENDARIZACIÓN Y ENTREGA DE\nUNIFORMES ESCOLARES PARA LAS NIÑAS Y\nPORCENTAJE DE UNIFORMES\nEL LUGAR DONDE SE REALIZA LA ENTREGA DE\nLOS NIÑOS BENEFICIADOS DE NIVEL BÁSICO\nESCOLARES ENTREGADOS EN\nDIRECCIÓN DE RECURSOS LOS UNIFORMES ESCOLARES A NIVEL BÁSICO\nDE PRIMARIA REGISTRADOS EN LA\nNIVEL BÁSICO PRIMARIA.\nMATERIALES DE LA SEG. PRIMARIA PERMITA EL FÁCIL ACCESO Y EXISTA\nPLATAFORMA DE REGISTRO DE UNIFORMES LA SEGURIDAD\nActividades ESCOLARES.\n(Procesos) UNIDAD DE ORGANIZACIÓN,\n2.1. APERTURA DE LA PLATAFORMA RENUEE\nPORCENTAJE DE ADQUISICIÓN INNOVACIÓN Y CALIDAD Y LA LOS PROVEDORES ENTREGAN LOS UNIFORMES\nY LA ADQUISICIÓN DE UNIFORMES\nDE UNIFORMES ESCOLARES DIRECCIÓN DE TECNOLOGÍAS DE LA ECOLARES NIVEL BÁSICO DE SECUNDARIA EN\nESCOLARES PARA LAS ALUMNAS Y LOS\nNIVEL BÁSICO SECUNDARIA INFORMACIÓN DE LA SEG.. TIEMPO Y FORMA.\nALUMNOS DE NIVEL BÁSICO EN SECUNDARIA. http://reune.seg.gob.mx/\n2.2 CALENDARIZACIÓN Y ENTREGA DE\nUNIFORMES ESCOLARES, PARA LAS EL LUGAR DONDE SE REALIZA LA ENTREGA DE\nPORCENTAJE DE UNIFORMES\nALUMNAS Y ALUMNOS, BENEFICIADOS DE DIRECCIÓN DE RECURSOS LOS UNIFORMES ESCOLARES A NIVEL BÁSICO\nESCOLARES ENTREGADOS EN\nNIVEL BÁSICO EN SECUNDARIA MATERIALES DE LA SEG. SECUNDARIA SEA DE FÁCIL ACCESO Y EXISTE LA\nNIVEL BÁSICO SECUNDARIA\nREGISTRADOS EN LA PLATAFORMA DE SEGURIDAD\nREGISTRO DE UNIFORMES ESCOLARES.\nNIÑOS DE GUERRERO CON UNIFORMES, Y SE\nEMITEN SUS REGLAS DE OPERACIÓN\nAnexo 2. Acta de donación\nPROGRAMA UNIFORMES (PRIMARIA-SECUNDARIA) TRANSFORMANDO\nUNIFORMES\nActa de Entrega - Recepción de uniformes escolares\nEn la ciudad de............................. comparecen por una parte la Sra. o el\nSr.\n............... en su calidad de tutora o tutor de la alumna(o) “…................... ”, a quien se le identificará para efecto de esta acta como “LA MADRE O PADRE” o “LA TUTORA O\nTUTOR” y, por otra parte, la Secretaría de Educación Guerrero como “LA SEG”, que a continuación se identifican, con el objeto de suscribir esta acta de entrega recepción de un uniforme escolar de nivel primaria, contenido en las cláusulas siguientes:\nPRIMERA. ANTECEDENTES. La Secretaría de Educación Guerrero, establece el compromiso de entregar para el ciclo escolar 2022-2023, en forma gratuita un uniforme de nivel primaria o secundaria a niñas y niños inscritos en escuelas públicas de nivel de educación primaria con reconocimiento oficial de la Secretaría de Educación Guerrero SEG.\nSEGUNDA. ENTREGA - RECEPCIÓN. Con el antecedente expuesto “LA SEG” entrega un uniforme escolar y que será utilizado obligatoriamente durante su asistencia a las clases durante el ciclo escolar vigente.\nLa prenda de vestir entregada a las niñas y niños consiste en:\nTERCERA. ACEPTACIÓN. “LA MADRE O PADRE” o “LA TUTORA O TUTOR”, declara, a la fecha de suscripción de esta acta, haber recibido la prenda de vestir antes identificada a su entera satisfacción, razón por la que acepta el contenido de este instrumento en todas sus partes, sin formular observación alguna. Además, declara que ha recibido, el uniforme escolar, correspondiente al ciclo escolar 2022-2023.\nDe esta forma, se atiende el objetivo establecido en las Reglas de Operación del\nPrograma.\nNIÑOS DE GUERRERO CON UNIFORMES, Y SE\nEMITEN SUS REGLAS DE OPERACIÓN\nPara constancia y plena eficacia de este instrumento legal, los comparecientes lo firman en dos ejemplares de igual tenor, en la ciudad de Chilpancingo de los Bravo, Guerrero, a los días, del mes del año dos mil veintitrés.\n“LA MADRE O PADRE” o “LA TUTORA “LA SEG”\nO TUTOR”\nPrimero. El presente Acuerdo entrará en vigor al día siguiente de su publicación en el Periódico Oficial del\nGobierno del estado de Guerrero.\nSegundo. Se abrogan el Acuerdo por el que se crea el Programa Uniformes (Primarias) Transformando la\nEducación de las Niñas y Niños de Guerrero y se emiten sus Reglas de Operación para el Ejercicio Fiscal\n2022 y el Acuerdo por el que se crea el Programa Uniformes (Secundarias) Transformando la Educación de las Alumnas y los Alumnos de Guerrero y se emiten sus Reglas de Operación para el Ejercicio Fiscal\n2022, ambos publicados en el Periódico Oficial del Gobierno del estado de Guerrero No. 68 Alcance IV, de fecha 26 de agosto del año 2022.\nTercero. En un plazo del día siguiente de su publicación, se emitirán los Lineamientos de los Comités de\nContraloría Social, comités que existirá en cada escuela de educación primaria y secundaria de la entidad integrado por los comités de padres de familia.\nCuarto. A partir de la entrada en vigor del presente Acuerdo, las Reglas de Operación del Programa, subsecuentes o sus modificaciones, serán emitidas por la persona titular de la Secretaría de Educación\nGuerrero, responsable directa de la operación y ejecución de las mismas.\nEdificio Centro, Boulevard René Juárez Cisneros No. 62 de la Ciudad de los Servicios en Chilpancingo de los Bravo, capital del estado de Guerrero, a los veintitrés días del mes de febrero del año dos mil veintitrés.\nGOBERNADORA CONSTITUCIONAL DEL ESTADO DE GUERRERO.\nMTRA. EVELYN CECIA SALGADO PINEDA.\nRúbrica.\nEL SECRETARIO GENERAL DE GOBIERNO.\nMTRO. LUDWIG MARCIAL REYNOSO NÚÑEZ.\nRúbrica.\nNIÑOS DE GUERRERO CON UNIFORMES, Y SE\nEMITEN SUS REGLAS DE OPERACIÓN\nEL SECRETARIO DE EDUCACIÓN GUERRERO.\nDR. MARCIAL RODRÍGUEZ SALDAÑA.\nRúbrica.",
  "ordenamiento": "PROGRAMA",
  "jurisdiccion": "GUERRERO",
  "fuente_oficial": "DIARIO OFICIAL DE LA FEDERACION",
  "Fecha de Publicación": "13 DE SEPTIEMBRE DE 2024",
  "ULTIMA REFORMA PUBLICADA": null,
  "status": "VIGENTE",
  "es_escaneado": false,
  "tiene_tablas": true,
  "materia": [
    "educación"
  ]
}