{
  "titulo": "Acuerdo para la Implementación del Programa Estatal de Ética, Transparencia y Combate A la Corrupció",
  "Contenido": "TEXTO ORIGINAL.\nACUERDO PARA LA IMPLEMENTACIÓN DEL PROGRAMA ESTATAL DE ÉTICA, TRANSPARENCIA\nGuerrero.- Poder Ejecutivo.\nHÉCTOR ANTONIO ASTUDILLO FLORES, GOBERNADOR CONSTITUCIONAL DEL\nCONFIEREN LOS ARTÍCULOS 90 NUMERAL 2 Y 91 FRACCIONES I Y XLVI DE LA CONSTITUCIÓN\nDISPUESTO POR LOS ARTÍCULOS 2°, 3°, 4° ÚLTIMO PÁRRAFO, 6°, 7° Y 9° DE LA LEY ORGÁNICA\nDE LA ADMINISTRACIÓN PÚBLICA DEL ESTADO DE GUERRERO NÚMERO 08; Y\nQue la ética en el servicio público y el combate a la corrupción deben ser prioridades de la acción de los gobiernos estatal y municipales de Guerrero. La ética en el servicio público orienta la política hacia la integridad, la honestidad y el sentido de responsabilidad social. El combate a la corrupción es un requisito para mejorar la eficacia de los programas públicos, destinar mayores recursos a quienes menos tienen, ofrecer igualdad de oportunidades para todos y recuperar la confianza en las instituciones públicas.\nQue de acuerdo con la Encuesta Nacional de Calidad e Impacto Gubernamental, realizada en el\n2013, por el Instituto Nacional de Estadística y Geografía (INEGI), Guerrero ocupa el primer lugar a nivel nacional en corrupción respecto al manejo de recursos, servicios públicos y trámites. A su vez, el 90.1% de los guerrerenses opinó que la corrupción en la entidad es muy frecuente. Como consecuencia, de acuerdo al mismo estudio, Guerrero enfrenta una crisis de credibilidad institucional debido a que solamente 34.3% de la población confía en las instituciones del estado y es considerado por la población como el 5° problema más importante, según el Informe 2013 de la Organización Latinobarómetro.\nQue Transparencia Mexicana, a través del Índice Nacional de Corrupción y Buen Gobierno 2010, muestra que los índices de corrupción en la entidad son altos, ubicando a Guerrero en la posición 30 de los 32 estados de la República, posición que ha mantenido como lo demuestran los resultados de las encuestas anteriores (2001, 2003, 2005 y 2007). demuestra la medición Métrica de Transparencia de 2015, elaborada por el Centro de Investigación y información. Por otro lado, en materia presupuestaria, la calidad de la información de las finanzas públicas es deficiente. Guerrero ocupa el vigésimo octavo lugar nacional en el Índice de Información\nPresupuestal Estatal 2015 elaborado por el Instituto Mexicano para la Competitividad (IMCO), con un margen solamente de 60% de cumplimiento en transparencia presupuestaria.\nQue en el ámbito municipal, el rezago también es significativo. El Índice de Información\nPresupuestal Municipal 2015 elaborado por el IMCO, posicionó a Chilpancingo, Zihuatanejo y Coyuca de\nBenítez entre los últimos lugares de los 443 municipios analizados. Los municipios guerrerenses obtuvieron notas menores al 15% en transparencia presupuestaria.\nQue durante mi campaña definí que uno de los principales ejes de acción de gobierno, sería el combate a la corrupción para garantizar el Estado de Derecho. El compromiso fue, en alcance al Sistema\nNacional Anticorrupción, implementar el Sistema Estatal Anticorrupción, para transparentar el gasto público.\nQue el 27 de octubre de 2015, en el marco de la toma de protesta como Gobernador\nConstitucional del Estado de Guerrero, me comprometí a fortalecer el Estado de Derecho que promueva una cultura de la legalidad, implementar un nuevo Código de Ética, erradicar la impunidad y transformar la Administración Pública Estatal.\nQue el combate a la corrupción no sólo es una urgencia, sino también un instrumento que permitiría solventar otros problemas como la pobreza, el rezago social, la criminalidad y la impunidad, que permean en la entidad. Es un mecanismo que reconstruye el tejido social bajo una visión democrática, horizontal y participativa.\nQue el combate a la corrupción debe ser integral, abarcando las dimensiones: institucional, administrativa, legal, social y cultural del problema. Asimismo, debe enfocarse hacia el ámbito preventivo: sistemas de control interno e integridad que eviten un uso indebido de los recursos públicos, mecanismos e instrumentos de transparencia que permitan a la sociedad vigilar el uso correcto del dinero de la ciudadanía y disuadir malas prácticas, un código de ética que establezca los límites entre la actuación legal y responsable de los servidores públicos y aquellas acciones que puedan constituir conductas inapropiadas o violatorias del marco legal. No obstante, cuando los mecanismos preventivos de la corrupción sean insuficientes, el Estado debe actuar con todo vigor y rigor para sancionar los actos de corrupción.\nQue a su vez, el combate a la corrupción requiere de la corresponsabilidad de todos y enfrentarla con eficacia requiere el concurso de los poderes públicos, los órganos autónomos, los gobiernos municipales, así como los organismos empresariales y la sociedad civil. se reforman, adicionan y derogan diversas disposiciones de la Constitución Política de los Estados\nUnidos Mexicanos, en materia de combate a la corrupción, con el que se crea el Sistema Nacional federativas, lo que permitirá articular esfuerzos institucionales que significarán un elemento fundamental para fortalecer la confianza de los ciudadanos en las instituciones. A su vez, todas las entidades del país deberán adecuar sus legislaciones locales. De igual forma se promulgaron la Ley General de promuevan la transparencia y prevengan la corrupción.\nQue el presidente de la República, Enrique Peña Nieto, expresó que las reformas son un paso histórico a favor de una nueva cultura de la legalidad. Consideró que la corrupción es un problema estructural, por ello se requiere igualmente, una solución integral. El mandatario federal reconoció que se necesita una respuesta institucional amplia y sistémica, permanente y decisiva, y justamente la reforma constitucional ofrece una respuesta de esta magnitud al crear el Sistema Nacional Anticorrupción.\nQue en los próximos meses, Guerrero deberá asumir con responsabilidad los retos legislativos y normativos para responder a los cambios constitucionales y legales promovidos desde la Federación. Ello representa una oportunidad para liderar desde la entidad un esfuerzo colectivo, integral y responsable para retomar en el servicio público la transparencia y el combate a la corrupción como ejes centrales del funcionamiento de los gobiernos de la entidad.\nQue con el objeto de lograr una mayor eficacia y eficiencia en las acciones de la Administración\nPública del Estado, se plantea la instauración del Programa Estatal de Ética, Transparencia y Combate a la Corrupción, como instrumento propio del Ejecutivo Estatal.\nPor lo anteriormente expuesto y fundado, he tenido a bien emitir el siguiente:\nACUERDO PARA LA IMPLEMENTACIÓN DEL PROGRAMA ESTATAL DE ÉTICA, TRANSPARENCIA\nY COMBATE A LA CORRUPCIÓN\nARTÍCULO PRIMERO.- Se instaura el Programa Estatal de Ética, Transparencia y Combate a la\nCorrupción, en respuesta a los cambios venideros de las reformas constitucionales en materia de transparencia y anticorrupción, para establecer convenios de coordinación con la Secretaría de la\nFunción Pública y otras dependencias del Gobierno Federal; incorporar trámites y servicios a la Ventanilla\nÚnica Nacional, así como correlacionar al sector privado y a los organismos internacionales para que coadyuven a desarrollar mejores prácticas en la materia; de igual forma, reforzar los trabajos del Sistema\nNacional de Fiscalización, en coordinación con la Auditoría Superior de la Federación.\nEstatal para combatir la corrupción en el marco de las atribuciones y obligaciones que le competen, así aquí se establece.\nParaestatal de Guerrero se comprometen a colocar, el combate a la corrupción, como una prioridad de su operación, organización y procedimientos. El Programa Estatal de Ética, Transparencia y Combate a la ejecutables dentro de las esferas de competencia de cada una de las dependencias y entidades.\nARTÍCULO TERCERO.- Varias de las medidas del Programa Estatal de Ética, Transparencia y poderes Ejecutivo, Legislativo y Judicial, Órganos Autónomos, Ayuntamientos, Sociedad Civil y de los\nPartidos Políticos. El Gobierno del Estado, con base en sus atribuciones legales y en una actitud de diálogo permanente con todos los actores de la entidad, propiciará y definirá las iniciativas de reforma constitucional o legal para fomentar los cambios necesarios, sin menoscabo para que otros actores puedan presentar sus propias propuestas.\nARTÍCULO CUARTO.- El Programa Estatal de Ética, Transparencia y Combate a la Corrupción se compone de cinco ejes principales:\nI. Instaurar el Sistema Estatal Anticorrupción;\nII. Instrumentar las reformas necesarias en materia de transparencia;\nIII. Reordenar la administración de las finanzas públicas en estricto apego a la Ley General de\nContabilidad Gubernamental;\nIV. Fortalecer el control interno y los programas de integridad y;\nV. Transparentar las adquisiciones y la obra pública.\nARTÍCULO QUINTO.- Con la instauración del Sistema Estatal Anticorrupción se busca homologar la legislación estatal con la del Sistema Nacional Anticorrupción en materia de rendición de cuentas, responsabilidad de los servidores públicos, administración de recursos materiales, transparencia, acceso a la información pública y protección de datos personales, así como otras leyes complementarias, dando seguimiento en todo momento a su implementación.\nARTÍCULO SEXTO.- Para instrumentar las reformas necesarias en materia de transparencia se llevará a cabo la implementación de una agenda que incluya el mandato de la reforma constitucional en el ámbito federal promulgada el 7 de febrero de 2014, así como lo dispuesto por la Ley General de corrupción. La implementación de dicha agenda contempla las siguientes acciones:\nI. Modificar la normatividad del Estado para incorporar los nuevos elementos y principios de la reforma en materia de transparencia;\nII. Instrumentar políticas de Gobierno Abierto;\nIV. Garantizar la presentación oportuna y fidedigna de las declaraciones patrimonial y de intereses, como lo establecen, el artículo 108 párrafo quinto de la Constitución Política de los Estados\nUnidos Mexicanos y los artículos 112 a 118 y 128 de la Ley Número 695 de Responsabilidades de\nServidores Públicos del Estado y de los Municipios de Guerrero; y para quienes sean sujetos obligados, una copia de su declaración fiscal ante el Sistema de Administración Tributaria;\nV. En el caso de los servidores públicos, a partir de Director General de la Administración\nPública Centralizada y su equivalente jerárquico en el sector Paraestatal, estarán obligados a hacer públicas dichas declaraciones a más tardar el 30 de junio de cada año. Para definir las modalidades y formatos de las versiones públicas, el Poder Ejecutivo llevará a cabo una evaluación en la cual tomará en cuenta el derecho de la ciudadanía a estar informada, así como el derecho de los servidores públicos a preservar la integridad, seguridad y el resguardo de datos personales, utilizando la normativa vigente y realizando las adecuaciones legales y reglamentarias;\nVI. Transparentar y depurar las reglas de operación y los padrones de beneficiarios, así como los recursos que fundamenten la política social del Estado.\nARTÍCULO SÉPTIMO.- El reordenamiento de las finanzas públicas consistirá en instrumentar sistemas y mecanismos de vigilancia, control interno, transparencia en la gestión y el uso de los recursos financieros y materiales, que coadyuven a mantener el orden y definir responsabilidades en el ejercicio de las finanzas públicas estatales de Guerrero por medio de las siguientes acciones:\nI. Reingeniería de los mecanismos de control presupuestario y pagos de la tesorería para asegurar que la Secretaría de Finanzas y Administración pueda mantener el balance entre los ingresos y los gastos, así como el control de las operaciones financieras y los pagos de toda la administración pública estatal;\nII. Bancarizar las operaciones de ingreso y gasto de la Secretaría de Finanzas y Administración para conocer el origen y el destino final de cada peso gastado, quedando registro de cada una de las operaciones, con lo que se inhibe el mal uso de los recursos públicos y se facilita la tarea a las áreas de auditoría y fiscalización;\nIII. Sistematizar las operaciones presupuestarias para todos los compromisos de gasto público, con el fin de evitar que las dependencias y áreas ejecutoras de gasto comprometan recursos públicos que no estén contemplados en el Decreto de Presupuesto Anual, generando con ello presiones de gasto sin fondeo o desvío de otras partidas para atenderlos;\nIV. Modernizar y transparentar el Registro Público de la Propiedad y apoyar la modernización de los catastros municipales, para evitar las prácticas de corrupción en las operaciones que se realicen en estas dependencias y;\nV. Estructurar los mecanismos de transparencia fiscal y presupuestaria que le permita al recursos públicos, así como los resultados que se espera obtener y el valor público que generan.\nARTÍCULO OCTAVO.- Con la aprobación de los recientes cambios constitucionales que dan origen al Sistema Nacional de Anticorrupción, como la instancia de coordinación entre las autoridades de todos los órdenes de gobierno competente en la prevención, detección y sanción de responsabilidades administrativas y de hechos de corrupción, así como en la fiscalización y control de los recursos públicos, entidades, que coadyuvan a la rendición de cuentas como vigilantes de los procesos de control y fiscalización en los diferentes órdenes de gobierno y, a través del mismo se impulsa entre otros aspectos la implementación del Marco Integrado de Control Interno emitido por la Secretaria de la Función Pública y la Auditoría Superior de la Federación en los ámbitos Federal, Estatal y Municipal en el marco del citado\nSistema Nacional de Fiscalización.\nEl Control Interno tiene por objetivo proporcionar una seguridad razonable en el logro de objetivos y metas de las instituciones dentro de las siguientes categorías:\nI. Operación: Eficacia, eficiencia y economía de las operaciones, programas y proyectos;\nII. Información: Confiabilidad, veracidad y oportunidad de la información financiera, presupuestaria y de operación;\nIII. Cumplimiento: Apego al marco legal, reglamentario, normativo y administrativo aplicable a las instituciones, y\nIV. Salvaguarda: Protección de los recursos públicos y prevención de actos de corrupción.\nEl Marco Integrado de Control Interno para su implementación, actualización y mejora se divide en tres niveles de responsabilidad de conformidad con el ámbito de su competencia y nivel jerárquico:\nI. Estratégico: Se conforma por el Titular de la Institución y los servidores públicos del segundo nivel jerárquico, quienes tienen como propósito lograr la misión, visión, objetivos y metas institucionales.\nII. Directivo: Se integra por los servidores públicos del tercer y cuarto nivel jerárquico y son responsables de que la operación de los procesos, programas y proyectos se realice correctamente.\nIII. Operativo: Incluye a los servidores públicos del quinto nivel y demás servidores públicos de nivel descendente. Los responsables de este nivel tienen como propósito que las acciones y tareas requeridas en las áreas de su competencia se ejecuten con eficacia. jerárquicos señalados, el Titular de la Institución determinará el nivel jerárquico que conformará cada nivel de Control Interno, atendiendo a la naturaleza de las responsabilidades y/o funciones de cada uno de ellos.\nARTÍCULO NOVENO.- Toda vez que una parte importante del presupuesto público se destina a evaluar si dichas contrataciones se están realizando de manera eficiente y apegada a la legalidad, a través de:\nI. Consolidar el uso de COMPRANET para atenuar cualquier acción de corrupción en las asignaciones y en el pago de sobrecostos en los bienes y servicios y en la obra pública;\nII. Crear un sistema de información pública de las adquisiciones del Ejecutivo, que permita mayor transparencia y ponga a disposición del ciudadano la información sobre los precios de compra, el catálogo de proveedores y las condiciones de contratación;\nIII. Instrumentar mecanismos de centralización de compras públicas y consolidadas, que permitan generar economías en las contrataciones, al reducir los precios que pagan los gobiernos por los bienes y servicios. Adicionalmente, permite que exista un mayor control en las adquisiciones y en el gasto público por parte del área centralizadora del Gobierno del Estado;\nIV. Transparentar las listas de los servidores públicos que participen en contrataciones públicas con el fin de que exista una mayor supervisión de los órganos de control y de la sociedad sobre la evolución patrimonial de estas personas;\nV. Publicar la lista de proveedores que han incurrido en irregularidades de manera que se pueda identificar todos aquellos que se encuentren impedidos a participar en futuras licitaciones;\nVI. Establecer reglas de contacto en materia de contrataciones públicas de tal forma que tanto los servidores públicos como los proveedores, se apeguen a una normatividad en cuanto a su interacción y se comporten de manera ética en la interrelación que exista entre ellos; y\nVII. Instituir la figura de testigo social para compras y contratos de obra pública superiores que por su naturaleza o monto lo ameriten.\nARTÍCULO DÉCIMO.- Para garantizar la operatividad y ejecución del Programa Estatal de Ética, Transparencia y Combate a la Corrupción se crearán dos comités:\nI. Un Comité Rector; y\nII. Un Comité Consultivo.\nARTÍCULO ONCE.- El Comité Rector estará integrado por:\nI. El Gobernador del Estado;\nII. El Secretario General de Gobierno;\nIII. El Secretario de Contraloría y Transparencia Gubernamental;\nIV. El Secretario de Finanzas y Administración; y\nV. El Secretario de Desarrollo Urbano, Obras Públicas y Ordenamiento Territorial.\nEl Comité tendrá las siguientes atribuciones:\nI. Vigilar que el Programa Estatal de Ética, Transparencia y Combate a la Corrupción se ejecute conforme a los lineamientos establecidos en el presente Acuerdo;\nII. Evaluar los avances en la ejecución del Programa Estatal de Ética, Transparencia y Combate resolver los rezagos observados;\nIII. Velar porque las reformas constitucionales y legales, así como las medidas administrativas y y dignificar la vida pública en el estado; y\nIV. Propiciar un diálogo entre las fuerzas políticas del Estado, así como otros actores de la vida pública, para avanzar en las negociaciones que permitan cumplir con el Programa.\nLas atribuciones anteriormente descritas son enunciativas más no limitativas, siendo el Comité\nRector el órgano encargado de la toma de decisiones de todo lo que competa al Programa Estatal de\nÉtica, Transparencia y Combate a la Corrupción.\nEl número de sesiones y la estructura detallada del Comité Rector será descrita en instrumentos específicos posteriores. Asimismo, se crearán las instancias correspondientes para la consecución de los objetivos del Programa Estatal de Ética, Transparencia y Combate a la Corrupción que de cada acuerdo surja.\nPara dar seguimiento a las decisiones del Comité Rector, cada titular designará un enlace, pudiendo ser el responsable del área administrativa o en su caso el contralor interno de cada una de las dependencias que componen la Administración Pública Centralizada y Paraestatal de la entidad.\nEste grupo de seguimiento acatará las decisiones que tome el Comité Rector, llevando a cabo labores de coordinación e informes, en las cuales podrán proponer nuevas líneas de acción y recomendaciones para cumplir con el objetivo del Programa.\nARTÍCULO DOCE.- Se conformará el Comité Consultivo, que operará de manera paralela al\nComité Rector, y estará integrado por:\nI. Representantes de la sociedad civil organizada;\nII. Organismos empresariales;\nIII. Contralorías ciudadanas; y\nIV. Medios de comunicación.\nEl Comité Rector, en consulta con organismos de la sociedad civil, emitirá una convocatoria para integrar el Consejo Consultivo. Los integrantes lo serán de forma honorífica y no recibirán gratificación alguna por su labor.\nARTICULO TRECE.- Las funciones del Comité Consultivo son:\nI. Supervisar la implementación del Programa Estatal de Ética, Transparencia y Combate a la\nCorrupción;\nII. Rendir un informe trimestral de los avances y rezagos en la ejecución del Programa Estatal de\nÉtica, Transparencia y Combate a la Corrupción; y\nIII. Proponer medidas adicionales e innovadoras para fortalecerlo.\nARTÍCULO CATORCE.- Para el desarrollo de los compromisos del Programa Estatal de Ética, Transparencia y Combate a la Corrupción asumidos por las dependencias de la Administración Pública\nCentralizada y Paraestatal se suscribirán los convenios específicos respectivos.\nARTÍCULO QUINCE.- Con el objeto de dar pleno cumplimiento al Programa Estatal de Ética, Transparencia y Combate a la Corrupción, las dependencias del Ejecutivo Estatal podrán proponer adiciones o modificaciones al Comité Rector. Asimismo, se podrán allegar de expertos para consultar sobre temas especializados.\nARTICULO DIECISEIS.- El titular del Poder Ejecutivo, exhortará a los poderes Legislativo y\nJudicial, Órganos Autónomos y Ayuntamientos, para que, en apego a sus respectivos regímenes internos y competencias legales, puedan implementar programas de Ética, Transparencia y Combate a la\nCorrupción.\nArtículo Primero. El presente Acuerdo surtirá efectos a partir de su publicación en el Periódico\nOficial y tendrá duración indefinida.\nArtículo Segundo.- Publíquese el presente Acuerdo en el Periódico Oficial del Gobierno del\nEstado.\nChilpancingo de los Bravo, Estado de Guerrero, a los 4 días del mes de abril del año 2016.\nEL C. GOBERNADOR CONSTITUCIONAL DEL ESTADO.\nLIC. HÉCTOR ANTONIO ASTUDILLO FLORES.\nRúbrica.\nEL C. SECRETARIO GENERAL DE GOBIERNO.\nLIC. FLORENCIO SALAZAR ADAME.\nRúbrica.\nEL C. SECRETARIO DE CONTRALORÍA Y TRANSPARENCIA\nGUBERNAMENTAL.\nLIC. MARIO RAMOS DEL CARMEN.\nRúbrica.\nEL C. SECRETARIO DE FINANZAS Y ADMINISTRACIÓN.\nLIC. HÉCTOR APREZA PATRÓN.\nRúbrica.\nEL C. SECRETARIO DE DESARROLLO URBANO, OBRAS\nPÚBLICAS Y ORDENAMIENTO TERRITORIAL.\nMTRO. RAFAEL NAVARRETE QUEZADA.\nRúbrica.\nTESTIGOS DE HONOR\nEL C. SECRETARIO DE LA FUNCIÓN PÚBLICA.\nMTRO. VIRGILIO ANDRADE MARTÍNEZ.\nRúbrica.\nEL C. AUDITOR SUPERIOR DE LA FEDERACIÓN.\nC.P.C. JUAN MANUEL PORTAL MARTÍNEZ.\nRúbrica.\nLA C. COMISIONADA PRESIDENTA DEL INSTITUTO NACIONAL DE TRANSPARENCIA,\nACCESO A LA INFORMACIÓN Y PROTECCIÓN DE DATOS PERSONALES.\nDRA. XIMENA PUENTE DE LA MORA.\nRúbrica.",
  "ordenamiento": "PROGRAMA",
  "jurisdiccion": "GUERRERO",
  "fuente_oficial": "DIARIO OFICIAL DE LA FEDERACION",
  "Fecha de Publicación": "05 de Abril de 2016",
  "ULTIMA REFORMA PUBLICADA": null,
  "status": "VIGENTE",
  "es_escaneado": false,
  "tiene_tablas": false,
  "materia": [
    "transparencia",
    "ética"
  ]
}