{
  "titulo": "Acuerdo por el Que Se Crea el Programa Fortalecimiento de las Culturas E Identidades Indígenas y Afr",
  "Contenido": "EMITEN SUS REGLAS DE OPERACIÓN PARA EL\nEJERCICIO FISCAL 2020\nY AFROMEXICANO, Y SE EMITEN SUS REGLAS DE OPERACIÓN PARA EL EJERCICIO FISCAL 2022, PUBLICADO EN\nEL PERIÓDICO OFICIAL DEL GOBIERNO DEL ESTADO EDICIÓN EXTRAORDINARIA, EL MIÉRCOLES 03 DE AGOSTO\nDE 2022\nTEXTO ORIGINAL.\nAcuerdo publicado en el Periódico Oficial del Gobierno del Estado No.45 Alcance I, el Viernes 12 de Junio de 2020.\nACUERDO POR EL QUE SE CREA EL PROGRAMA FORTALECIMIENTO DE LAS CULTURAS E\nIDENTIDADES INDÍGENAS Y AFROMEXICANA Y EMITEN SUS REGLAS DE OPERACIÓN PARA EL\nEJERCICIO FISCAL 2020.\nGuerrero.- Poder Ejecutivo.\nLICENCIADO HÉCTOR ANTONIO ASTUDILLO FLORES, GOBERNADOR CONSTITUCIONAL\nDEL ESTADO DE GUERRERO, CON FUNDAMENTO EN LO DISPUESTO POR LOS ARTÍCULOS 71,\n87, 88, 90 NUMERAL 2 Y 91 FRACCIONES I, VI, IX Y XLVI DE LA CONSTITUCIÓN POLÍTICA DEL\nCONFIEREN LOS ARTÍCULOS 2, 3, 6, 7, 10, 11, 18 APARTADO A FRACCIONES I Y XIV, 20 FRACCIÓN\nIII Y 32 DE LA LEY ORGÁNICA DE LA ADMINISTRACIÓN PÚBLICA DEL ESTADO DE GUERRERO\nNÚMERO 08; 1, 2 FRACCIÓN I, 18 Y 25 DE LA LEY NÚMERO 454 DE PRESUPUESTO Y DISCIPLINA\nFISCAL DEL ESTADO DE GUERRERO; EN RELACIÓN CON EL ARTÍCULO 55 Y ANEXOS 21 Y 21-A\nDEL DECRETO NÚMERO 447 DEL PRESUPUESTO DE EGRESOS DEL ESTADO DE GUERRERO\nPARA EL EJERCICIO FISCAL 2020 Y LOS LINEAMIENTOS PARA LA ELABORACIÓN DE LAS\nREGLAS DE OPERACIÓN DE LOS PROGRAMAS SOCIALES ESTATALES PARA EL EJERCICIO\nFISCAL 2017.\nQue el Plan Estatal de Desarrollo 2016-2021, impulsa entre sus prioridades, reconocer, valorar, promover y difundir las culturas indígenas vivas en todas sus expresiones y como parte esencial de la identidad y la cultura, así como fortalecer la difusión entre los jóvenes, de las lenguas originarias en las comunidades indígenas, con el fin de preservar nuestra identidad cultural. De la misma manera que en su eje 6 transversal 4, se establece atender a los pueblos originarios y afromexicano, para promover su desarrollo integral respetando la cultura y el ejercicio de sus derechos individuales y colectivos; y que indica la estrategia 6.4.1., generar oportunidades para los pueblos originarios y afromexicano que permita su desarrollo económico, político y social, respetando las manifestaciones de su cultura y el ejercicio de sus derechos.\nEn cumplimento a línea de acción del PED 2016-2021 que instruye revalorizar las culturas de los pueblos del Estado de Guerrero, se incorporó nuevamente en el ejercicio fiscal 2020, el programa:\nEMITEN SUS REGLAS DE OPERACIÓN PARA EL\nEJERCICIO FISCAL 2020\nFortalecimiento de las Culturas e Identidades Indígenas y Afromexicana, con el objetivo de impulsar de los pueblos indígenas y afromexicano, para propiciar el reconocimiento de la diversidad y un diálogo intercultural entre la sociedad guerrerense.\nEl artículo 55 del Decreto Número 447 del Presupuesto de Egresos del Estado de Guerrero, para el Ejercicio Fiscal 2020, establece que con el objeto de asegurar la aplicación eficiente, eficaz, oportuna equitativa y transparente de los recursos públicos la Secretaría de Finanzas y Administración y la Secretaría de Planeación y Desarrollo Regional, emitirán las disposiciones a que deberán sujetarse los programas de inversión sujetos a Reglas de Operación.\nCon sustento en lo anterior, la Secretaría de Planeación y Desarrollo Regional, expidió los\nLineamientos para la Elaboración de las Reglas de Operación de los Programas Sociales Estatales para el ejercicio fiscal 2017, publicados en el periódico oficial número 06, alcance II del Gobierno del Estado.\nEn el Decreto Número 447 del Presupuesto de Egresos del Estado de Guerrero para el Ejercicio\nFiscal 2020 se señala que se ejercerán los recursos bajo una política de gasto público, que permita dar cumplimiento a lo que globalmente prevén los ejes rectores del Plan Estatal de Desarrollo 2016-2021.\nPor lo anteriormente expuesto y con fundamento en las disposiciones legales antes citadas, he tenido a bien expedir el siguiente:\nACUERDO POR EL QUE SE CREA EL PROGRAMA FORTALECIMIENTO DE LAS CULTURAS E\nIDENTIDADES INDÍGENAS Y AFROMEXICANA Y EMITEN SUS REGLAS DE OPERACIÓN PARA EL\nEJERCICIO FISCAL 2020.\nArtículo 1. Se crea el Programa Fortalecimiento de las Culturas e Identidades Indígenas y\nAfromexicana con inversión estatal directa, el cual tienen por objeto impulsar procesos y acciones que impacten en la creatividad y revitalización del patrimonio cultural y las identidades de los pueblos indígenas y afromexicanos, para propiciar el reconocimiento de la diversidad y un diálogo intercultural entre la sociedad guerrerense.\nArtículo 2. Se emiten las Reglas de Operación del Programa Fortalecimiento de las Culturas e\nIdentidades Indígenas y Afromexicana para el Ejercicio Fiscal 2020 en las que se establecen los principios de eficiencia, eficacia, oportunidad, equitativa y transparencia de los recursos públicos y requisitos que se deben de cumplir para poder acceder a dicho Programa. y Afromexicana, se establecerán las disposiciones que instituyen la ejecución del Programa, con el objeto de otorgar transparencia y asegurar la aplicación eficiente, eficaz, oportuna y equitativa de los recursos de Guerrero.\nEMITEN SUS REGLAS DE OPERACIÓN PARA EL\nEJERCICIO FISCAL 2020\nArtículo 3. La Secretaría de Asuntos Indígenas y Afromexicanos, tendrá a cargo la implementación, ejecución, evaluación y administración del Programa Fortalecimiento de las Culturas e\nIdentidades Indígenas y Afromexicana, bajo los criterios de objetividad, equidad, transparencia, publicidad, selectividad y temporalidad, con estricto apego a la normatividad aplicable, por lo tanto, será la encargada de la dispersión y asignación de los recursos del Programa, apegándose plenamente a las Reglas de\nOperación siguientes:\nREGLAS DE OPERACIÓN DEL PROGRAMA FORTALECIMIENTO DE LAS CULTURAS E\nIDENTIDADES INDÍGENAS Y AFROMEXICANA PARA EL EJERCICIO FISCAL 2020.\n1. Introducción\nLa identidad es el conjunto de rasgos que caracteriza a un individuo o a una colectividad frente a los demás. En el primer caso, el individual, resalta el hecho de que cada individuo es único y diferente debido a las particularidades comunes que distinguen a los seres humanos del resto del reino animal. En el segundo caso, el colectivo, una persona se representa como tal cuando se reconoce a sí misma y a otras personas como miembros de una comunidad. Las identidades colectivas se componen de varios elementos: la construcción de una representación de quiénes somos y qué define a una cultura, e involucra entorno, historia, lengua, tradiciones, costumbres y educación. De todas las identidades, una muy importante relacionada con los derechos de los pueblos y personas pertenecientes a ellos es la identidad cultural.\nEl derecho a la identidad de los pueblos indígenas está establecido en instrumentos internacionales, que México ha ratificado, de manera explícita en el Convenio 169 de la OIT, que expresa que “Los gobiernos deberán asumir la responsabilidad de desarrollar, con la participación de los pueblos interesados, una acción coordinada y sistemática con miras a proteger los derechos de esos pueblos y a garantizar el respeto de su integridad. Esta acción deberá incluir, entre otras medidas, la promoción de “la plena efectividad de los derechos sociales, económicos y culturales de esos pueblos, respetando su identidad social y cultural, sus costumbres y tradiciones, y sus instituciones” 1\nEl espíritu del Convenio 169 de la OIT se fundamenta en el necesario reconocimiento de las aspiraciones de todos los pueblos indígenas, a recrear y fortalecer sus identidades, lenguas y cosmovisiones en el marco de los Estados en los que viven. de 1982, la cultura debe ser considerada como “el conjunto de los rasgos distintivos espirituales y además de las artes y las letras, los modos de vida, las maneras de vivir juntos, los sistemas de valores, 1 Convenio 169 de la OIT sobre Pueblos Indígenas y Tribales en Países Independientes, Art. 2. Junio.1989.\nEMITEN SUS REGLAS DE OPERACIÓN PARA EL\nEJERCICIO FISCAL 2020 las tradiciones y las creencias”.2 Todas las culturas tienen un valor y una dignidad que deben ser respetados y protegidos.\nPara la UNESCO, “la cultura, es obra de todos los seres humanos y patrimonio común de la humanidad, y la educación, en el sentido más amplio de la palabra, proporcionan a los hombres y a las mujeres medios cada vez más eficaces de adaptación, que no sólo les permiten afirmar que nacen iguales en dignidad y derechos, sino también reconocer que deben respetar el derecho de todos los grupos humanos a la identidad cultural y al desarrollo de su propia vida cultural en el marco nacional e internacional, en la inteligencia de que corresponde a cada grupo el decidir con toda libertad si desea mantener y, llegado el caso, adaptar o enriquecer los valores que considere esenciales para su identidad”.3\nPor otra parte, la Declaración de Naciones Unidas sobre los Derechos de los Pueblos Indígenas, dispone, que “los pueblos y los individuos indígenas son libres e iguales a todos los demás pueblos y personas y tienen derecho a no ser objeto de ningún tipo de discriminación en el ejercicio de sus derechos, en particular la fundada en su origen o identidad indígenas[…] a practicar y revitalizar sus tradiciones y costumbres culturales [y] a mantener, proteger y desarrollar las manifestaciones pasadas, presentes y futuras de sus culturas, como lugares arqueológicos e históricos, objetos, diseños, ceremonias, tecnologías, artes visuales e interpretativas y literaturas; a promover, desarrollar y mantener sus estructuras institucionales y sus propias costumbres, espiritualidad, tradiciones, procedimientos, prácticas y, cuando existan, costumbres o sistemas jurídicos, de conformidad con las normas internacionales de derechos humanos”.4\nMéxico tiene una composición pluricultural sustentada originalmente en sus pueblos indígenas quienes conforman un importante grupo social de mexicanos que dada su cultura, historia y lengua identificamos como pueblos originarios del país. Todos ellos con una riqueza histórica y cultural propia que dan sentido de pertenencia e identidad a la Nación y a todos los mexicanos.\nEn virtud de la reforma de 2011 que modificó el artículo 1o. de la Constitución Política de los\nEstados Unidos Mexicanos, se fortaleció el derecho a la identidad de los pueblos y personas indígenas.\nPor ese motivo, el artículo 2o., que contiene los derechos reconocidos y garantizados a los pueblos indígenas que habitan en nuestro país, entre ellos el de la libre determinación y, en consecuencia, la autonomía para preservar y enriquecer sus lenguas, conocimientos y todos los elementos que constituyan su cultura e identidad, adquiere una nueva dimensión para mejorar sus condiciones de vida, acceso a la justicia y dignidad.\nEn Guerrero, con el Programa de Fortalecimiento de las Culturas e Identidades Indígenas y Afromexicana, se impulsan políticas públicas que contribuyan a la transmisión de la cosmovisión, fortalezcan la identidad, fomenten la organización, se promuevan sus saberes y preserve la memoria de las comunidades indígenas\n2 Definición conforme a las conclusiones de la Conferencia Mundial sobre las Políticas Culturales (MONDIACUlT, México,\n1982), de la Comisión Mundial de Cultura y Desarrollo (Nuestra Diversidad Creativa, 1995) y de la Conferencia\nIntergubernamental sobre Políticas Culturales para el Desarrollo (Estocolmo, 1998).\n3 A rtículo 5°. de la Declaración de la UNESCO sobre la Raza y los Prejuicios Raciales. 1978\n4 Declaración de la Organización de las Naciones Unidas sobre los Derechos de los Pueblos Indígenas, 2007.\nEMITEN SUS REGLAS DE OPERACIÓN PARA EL\nEJERCICIO FISCAL 2020 los pueblos indígenas y afromexicano, a través del cumplimiento de sus derechos, relacionados con la preservación y revitalización de sus culturas y el fortalecimiento de sus identidades, como fundamento en la construcción de una sociedad democrática y respetuosa de la diversidad y la pluriculturalidad que de Guerrero en su artículo 8, en el que se destaca que nuestro estado sustenta su identidad multiétnica, plurilingüística y pluricultural en sus pueblos originarios indígenas particularmente los nahuas, mixtecos, tlapanecos y amuzgos, así como en sus comunidades afromexicanas.\nLa ejecución del Programa hace posible también dar cumplimiento al artículo 11, fracción V, en el que se reconoce como derecho el preservar y enriquecer sus lenguas, conocimientos y todos los elementos que constituyen su cultura e identidad. Bajo estas premisas, el programa contempla el impulso de diversas expresiones artísticas y culturales, principalmente las relacionadas con la música y danzas tradicionales, así como el fortalecimiento de los saberes de los terapeutas tradicionales y la promoción cultural, a través de la publicación de trípticos, carteles y libros.\nDe esta manera, la Secretaría de Asuntos Indígenas y Afromexicanos (SAIA), como instancia responsable de implementar el Programa, conjuntamente con los grupos y promotores culturales interesados en los beneficios de las acciones, propicia espacios y mecanismos de difusión y participación para impulsar y fortalecer las culturas, las identidades y el tejido social de los pueblos indígenas y afromexicano.\nEs importante señalar que, si bien dentro de las acciones del Programa se propiciará el fortalecimiento cultural e identitario de los cinco pueblos, se hará un especial énfasis en promover la revitalización cultural indígena y la reafirmación de la identidad afromexicana. Lo anterior en razón de que el pueblo afromexicano, a diferencia de los cuatro pueblos indígenas, recién en los últimos treinta años transita en un proceso de reconocimiento, reivindicación y auto adscripción, cuyos resultados positivos se han reflejado en su inclusión dentro de la Constitución local y en la Encuesta Intercensal 2015 del INEGI, que por primera vez considera en sus registros a la población afromexicana.\nEl Programa tiene una cobertura estatal, dando prioridad a los municipios con mayor población indígena y afromexicana y será ejecutado por la Secretaría de Asuntos Indígenas y Afromexicanos, a través de la\nDirección General de Promoción Cultural y Apoyo Social. El presupuesto de inversión estatal directa es de\n$4,800,000.00 (cuatro millones ochocientos mil pesos 00/100 M.N).\n1.1. Antecedentes múltiples manifestaciones culturales en simples piezas de artesanía, danza o música, sin ninguna gracias a los mecanismos de lucha y preservación de los pueblos indígenas y afromexicano.\nEMITEN SUS REGLAS DE OPERACIÓN PARA EL\nEJERCICIO FISCAL 2020\nAnte este panorama, la Secretaría de Asuntos Indígenas y Afromexicanos ha procurado aproximarse respetuosamente a las culturas indígenas y afromexicana, a partir del conocimiento de aquello que subyace a esta diversidad de expresiones para evitar, así, corromper, banalizar o folclorizar los atributos culturales que son los componentes esenciales de las identidades de estos pueblos.\nEste Programa fue implementado por primera vez en el año 2006, presentando una interrupción por cuestiones presupuestarias en los años 2017 y 2018; en el ejercicio fiscal 2019 se retoman las acciones de impulso y difusión de las culturas indígenas y, como se viene haciendo desde el año 2013, se agrega la atención al pueblo afromexicano. En este sentido, se prestará una especial atención a los elementos culturales intangibles, como la música, la danza, las lenguas y los saberes y conocimientos tradicionales, que por un lado revitalizarán las culturas indígenas, y por el otro contribuirán en el fortalecimiento y reafirmación de la cultura afromexicana.\n1.2. Alineación programática\nEn cumplimiento a los objetivos de las políticas públicas del Gobierno del Estado y a las acciones específicas para alcanzarlos, el Programa Fortalecimiento de las Culturas e Identidades Indígenas y\nAfromexicana se encuentra alineado al Plan Estatal de Desarrollo 2016-2021, específicamente al Eje 6, Transversal 4: Atender a los pueblos originarios y Afromexicano; Objetivo: Promover el Desarrollo Integral respetando la cultura y el ejercicio de los derechos individuales y colectivos de los pueblos indígenas y afromexicano; Estrategia 6.4.1. “Generar oportunidades para los pueblos originarios y afromexicano que permita su desarrollo económico, político y social, respetando las manifestaciones de su cultura y el ejercicio de sus derechos”; Línea de acción 11 “Revalorizar las culturas de los pueblos del Estado de\nGuerrero”.\n1.3. Diagnóstico\nUn rasgo fundamental de la población indígena es su diversidad y pluralidad. Los indígenas mexicanos no son un cuerpo homogéneo. Por eso, si bien, en México existen 68 Pueblos Indígenas que se corresponde con las 68 lenguas que se hablan a lo largo de todo el país, lo cierto es que entre ellos y a su interior se vive una pluralidad lingüística, cultural e incluso religiosa.\nGuerrero es un Estado rico en expresiones de cultura popular. Sus comunidades indígenas, sus poblaciones afromestizas y sus aldeas campesinas son depositarias de un valioso patrimonio cultural”5. El en su territorio, principalmente por los pueblos indígenas Nahua, Na savi (mixteco), Me’pha (tlapaneco) y\nNn´anncue Ñomdaa (amuzgo), y el pueblo afromexicano. Además, estos pueblos y sus comunidades son base fundamental de la identidad y la raíz histórica del estado, contribuyendo con sus saberes ancestrales, cosmovisiones, organización social y expresiones lingüísticas y artísticas a la riqueza cultural de Guerrero.\nCabe señalar que estos cinco pueblos comparten algunos rasgos culturales, sin embargo, cada uno de\n5 Plan Estatal de Desarrollo 2016-2021. P. 81\nEMITEN SUS REGLAS DE OPERACIÓN PARA EL\nEJERCICIO FISCAL 2020 ellos guarda su propia cultura e identidad que los define, diferencia y, paralelamente, los hace reconocerse como tales.\nLa trascendencia de los pueblos indígenas y afromexicano, no sólo se fundamenta en sus aportes culturales e históricos, sino también por su importancia numérica, tal como lo muestra la Encuesta\nIntercensal 20156\nNo obstante, la significación de estos pueblos y sus comunidades, históricamente han padecido discriminación, marginación, pobreza y limitación en el ejercicio de sus derechos humanos, lo cual ha afectado su desarrollo individual y colectivo.\nAsimismo, los pueblos indígenas y afromexicano de Guerrero, a través de sus representantes, demandaron en el Foro de Consulta Ciudadana para la elaboración del Plan Estatal de Desarrollo 201620217, una mirada más sistémica sobre sus culturas, que no se las reduzca únicamente a los aspectos materiales y a las expresiones exotizantes, ya que no sólo son un cúmulo de cosas a ser observadas, o bienes y patrimonios materiales. En sus culturas se producen procesos de comunicación e interacción entre las personas, lo cual hace posible la construcción de los diversos sentidos de su vida social; en las manifestaciones folclóricas apenas se expresan formas de intercambio que quedan en el nivel más manifiesto, externo y secundario de la cultura.\nHoy las instituciones públicas de cultura deben trabajar en procesos de revitalización cultural, construyen. En la revitalización cultural la comunidad y los actores sociales comunitarios se construyen en sujetos sociales, políticos e históricos, lo que permite eliminar la visión de los rescatadores, a quienes sólo les interesa encontrar “piezas” para ser fosilizadas en los museos. Mientras que las personas que revitalizan la cultura lo hacen desde las dimensiones profundas de la memoria colectiva, incrementando la\n6 Encuesta Intercensal 2015 INEGI.\n7 Libro de ponencias del Foro Especial Pueblos Originarios: Eje 6 Estrategias Transversales, pp. 113-146\nEMITEN SUS REGLAS DE OPERACIÓN PARA EL\nEJERCICIO FISCAL 2020 experiencia social de la existencia comunitaria, que le permita afirmar los propios recursos culturales que han sido capaces de construir como pueblos.\nEn congruencia con lo anterior, la Secretaría de Asuntos Indígenas y Afromexicanos implementa el presente Programa con el objeto de atender las demandas indígenas y afromexicanas en materia cultural, e iniciar un proceso que revitalice las culturas e identidades de estos pueblos.\n2. Secretaría, dependencia o entidad responsable del Programa\nLa ejecución del Programa Fortalecimiento de las Culturas e Identidades Indígenas y\nAfromexicana, está bajo la responsabilidad de la Secretaría de Asuntos Indígenas y Afromexicanos (SAIA), a través de la Dirección General de Promoción Cultural y Apoyo Social; la ministración de recursos será comprobada por la Delegación Administrativa.\nEl Programa tiene como fundamento legal los instrumentos jurídicos siguientes:\na) Constitución Política de los Estados Unidos Mexicanos (Artículo 2°).\nc) Ley Número 701 de Reconocimiento, Derechos y Cultura de los Pueblos y Comunidades\nIndígenas del Estado de Guerrero.\nd) Ley Orgánica de la Administración Pública del Estado de Guerrero Número 08, artículo 32\n(Reforma publicada el 28 de agosto de 2018).\ne) Convenio 169 sobre Pueblos Indígenas y Tribales, de la Organización Internacional del Trabajo.\nf) Declaración Universal de las Naciones Unidas sobre los Derechos de los Pueblos Indígenas.\ng) Plan Estatal de Desarrollo 2016-2021.\nh) Programa Especial de Pueblos Indígenas y Afromexicanos 2016-2021.\ni) Decreto Número 447 del Presupuesto de Egresos del Estado de Guerrero para el Ejercicio Fiscal\n2020.\nj) Reglamento interior de la Secretaria de Asuntos Indígenas.\n3. Objetivos y Alcances\n3.1. Objetivo General\nEMITEN SUS REGLAS DE OPERACIÓN PARA EL\nEJERCICIO FISCAL 2020 y las identidades de los pueblos indígenas y afromexicano, para propiciar el reconocimiento de la diversidad y un diálogo intercultural entre la sociedad guerrerense.\n3.2. Objetivos específicos\na) Impulsar y difundir las diferentes expresiones artísticas y culturales de los pueblos indígenas y afromexicano.\nb) Contribuir al fortalecimiento de la identidad afromexicana, a través de estrategias y acciones que propicien la autoadscripción y la revaloración cultural.\n3.3. Alcances\na) La trascendencia del Programa\nb) El tipo de programa social:\nLa forma más común de identificar la seguridad social es mediante las prestaciones y la asistencia médica, sin embargo, esas son solo algunas de las formas en las que se presenta en la vida cotidiana.\nEn los hechos, la seguridad social también se encuentra en los actos solidarios e inclusivos de las personas hacia los demás, pues esos actos llevan en sí mismos la búsqueda del bienestar social.\nPor ello la Secretaría de Asuntos Indígenas y Afromexicanos, busca apoyar a las personas más vulnerables entre ellas a la población indígena, a través del Programa Fortalecimiento de las Culturas e\nIdentidades Indígenas y Afromexicanas, favoreciendo su inclusión e integración a la sociedad; garantizando con ello su derecho a la seguridad social.\nDe igual forma, con el presente Programa, se busca dar cumplimiento a lo dispuesto en el artículo preservación y enriquecimiento de las lenguas indígenas, conocimientos y todos los elementos que constituyen sus culturas, incluyendo a la población afromexicana.\nAsimismo, la Ley Número 701 de Reconocimiento, Derechos y Cultura de los Pueblos y\nComunidades Indígenas del Estado de Guerrero, en su artículo 26, fracción IV, mandata que el Estado y las instituciones deberán preservar y enriquecer las lenguas indígenas, así como sus conocimientos y todos los elementos que constituyan sus culturas e identidades. Asimismo, bajo los mismos términos este estado, en las que ya se incorpora al pueblo afromexicano al goce de éste y otros derechos. recogidas en los Foros de Consulta Ciudadana, efectuados para elaborar el Plan Estatal de Desarrollo\nEMITEN SUS REGLAS DE OPERACIÓN PARA EL\nEJERCICIO FISCAL 2020\n2016-2021, se plantea la necesidad de implementar un programa que cumpla con las políticas públicas dictadas por el titular del Ejecutivo, destacando las acciones encaminadas a impulsar y promover el uso de las cuatro lenguas indígenas e impulsar las culturas e identidades indígenas y afromexicana.\nc) La Población objetivo:\nPoblación indígena y afromexicana que habita en el territorio estatal, dando prioridad a aquellos municipios que cuentan con una mayor presencia de esta población objetivo.\nd) Población beneficiaria:\nPersonas y grupo de personas indígenas y afromexicanas que realicen actividades vinculadas con las diferentes expresiones artísticas y culturales, específicamente las relacionadas con la música, la danza y las lenguas indígenas.\n4. Metas físicas\nLos servicios y acciones estarán sujetos a la disponibilidad presupuestal del Programa, y son los siguientes:\na) Edición y publicación de libros, folletos y discos compactos para la difusión de expresiones culturales y artísticas:\n● 4 libros publicados para la difusión de expresiones artísticas y culturales.\n● 3 folletos para la difusión de las culturas indígenas y afromexicana, y de información sobre los programas y acciones de la SAIA.\n● 3 discos compactos publicados de música tradicional indígena y afromexicana.\nb) Eventos para el impulso de las culturas e identidades:\n● 6 encuentros y festivales para el impulso cultural e identitario, en los municipios de Iliatenco, Malinaltepec, Ometepec, Xochistlahuaca, Tlacoachistlahuaca y Chilpancingo.\n● 2 talleres para el fortalecimiento de la medicina indígena tradicional, en los municipios de Tlapa de Comonfort y Xochistlahuaca.\nc) Promoción y difusión de la música y danzas indígenas y afromexicanas:\n● 4 talleres de capacitación para reparación de instrumentos musicales, en los municipios de Tlapa de Comonfort, Chilapa de Álvarez, Ometepec y Xochistlahuaca.\n● 150 instrumentos donados a agrupaciones musicales tradicionales.\n● 37 grupos de danza con apoyo de vestuario.\n5. Programación presupuestal\nEMITEN SUS REGLAS DE OPERACIÓN PARA EL\nEJERCICIO FISCAL 2020\n6. Requisitos y procedimientos de acceso\n6.1. Difusión\nFortalecimiento de las Culturas e Identidades Indígenas y Afromexicana, en la cuarta semana del mes de mayo de 2020, a través del Portal Oficial del Gobierno del Estado de Guerrero y de la red social Facebook de la SAIA; en la Convocatoria se establecerá los trámites y requisitos que las y los interesados deberán cumplir.\nLa Convocatoria e información general del Programa, se podrá consultar también en las oficinas centrales de la SAIA, y en sus delegaciones regionales, en un horario de 9:30 a 14:00 horas.\nOperación del Decreto Número 447 del Presupuesto de Egresos del Estado de Guerrero para el Ejercicio\nFiscal 2020; las Reglas de Operación de este Programa, además de ser publicadas en el Periódico Oficial como en la red social Facebook Secretaría de Asuntos Indígenas y Afromexicanos.\nEMITEN SUS REGLAS DE OPERACIÓN PARA EL\nEJERCICIO FISCAL 2020\nOficinas Regionales:\n● Chilpancingo: Calle Guillermo Soberón Acevedo, núm. 8, Col. Salubridad;\n● Ometepec: Calle Juan Ruiz de Alarcón, núm. 32, Barrio de la Guadalupe;\n● Chilapa de Álvarez: Calle 3 Norte, núm. 108 Col. Centro;\n● Tlapa de Comonfort: Calle Morelos, núm. 124, Col Centro.\n6.2. Requisitos de acceso\n6.2.1. Requisitos generales de acceso\n● Ser originarios y originarias de comunidades y municipios indígenas y afromexicanos, o auto adscribirse como tales, independientemente de su sexo, edad y filiación política o religiosa.\n● Solicitud por escrito dirigida a la persona titular de la Secretaría de Asuntos Indígenas y Afromexicanos, que puede ser presentada por grupos informales o legalmente constituidos por al menos tres mayores de edad, cuyos integrantes vivan y sean reconocidos por la comunidad donde se desarrollará su actividad cultural, especificando el tipo de apoyo que se demanda.\n● Constancia expedida por la autoridad comunitaria, en la que se establezca que el escritor, compositor, interprete, grupo musical o de danza cumple con una función cultural, de beneficio para su comunidad y sin fines de lucro. En el caso de grupos de música o de danza, dicha constancia deberá especificar también el periodo de tiempo que llevan constituidos, así como especificar en caso de contar con él, el nombre del grupo.\n● Cumplir con las bases generales que especifique la convocatoria.\n6.2.2. Requisitos específicos\nPara acceder a los servicios y apoyos del Programa, se deberá cumplir con los requisitos y procedimientos que se citan a continuación, según el tipo de apoyo o servicio solicitado:\n6.2.2.1. Edición y publicación de libros, folletos y discos compactos para la difusión de expresiones culturales y artísticas\na) Edición y publicación de libros y folletos\n● Las personas indígenas y afromexicanas que aspiren a la publicación de algún texto de su autoría (investigación, ensayo, poesía o narrativa), además de los requisitos de la convocatoria, deberán entregar solicitud por escrito, dirigida a la persona titular de la SAIA, así como el texto en versión impresa y electrónica, en la Dirección General de Promoción Cultural y Apoyo Social.\n● Los textos que se presenten para su posible publicación, deberán ser inéditos y relacionarse con temas que aborden las culturas indígenas y afromexicana, enfocados a la protección, fortalecimiento y difusión de los valores culturales, cualquiera que sea su línea literaria: investigación, ensayo, poesía o\nEMITEN SUS REGLAS DE OPERACIÓN PARA EL\nEJERCICIO FISCAL 2020 narrativa; en el caso indígena, los textos podrán estar escritos en español o en lengua náhuatl, mixteca, tlapaneca o amuzga.\n● Una comisión dictaminadora integrada por directivos de la SAIA, promotores culturales de reconocido prestigio en el Estado de Guerrero y defensores del fortalecimiento de los derechos y la cultura indígena y afromexicana, será la responsable de analizar y seleccionar los textos a publicar.\n● Una vez dictaminada positivamente la impresión y publicación del texto, el autor o autora realizará una carta compromiso con la SAIA, para recibir como retribución el 5% del tiraje total del libro, bajo el compromiso de distribuirlo en bibliotecas, escuelas y comunidades interesadas, sin fines de lucro.\n● En caso de que la comisión dictaminadora juzgue que ningún trabajo presentado reúne los requisitos de calidad y pertinencia necesarios, podrá publicar otra obra no dictaminada o aplicar el recurso en otra acción relacionada con el Programa.\nb) Grabación y publicación de discos compactos.\nEn lo que respecta a la grabación y publicación de tres discos compactos, su programación responde a demandas expresadas a la SAIA en los años 2018 y 2019, por compositores, intérpretes y agrupaciones musicales indígenas y afromexicanos de diversos municipios, que mantienen viva la música tradicional de las diferentes regiones del Estado de Guerrero. Los interesados deberán cubrir los requisitos siguientes:\n● Además de cumplir con las bases de la convocatoria, enviarán solicitud por escrito libre, firmada por el representante del grupo o la persona interesada, dirigida a la persona titular de la SAIA, especificando el nombre del grupo (cuando así sea el caso), municipio y comunidad de origen, tipo de música tradicional que interpretan especificando en su caso si es composición propia, así como los nombres de las y los integrantes del grupo.\n● Identificación oficial de las y los integrantes del grupo, o de la persona interesada (copia).\n● Demo simple en CD o en USB de lo que se solicita grabar.\n● Una comisión dictaminadora integrada por directivos de la SAIA, promotores culturales de reconocido prestigio en el Estado de Guerrero y defensores del fortalecimiento de los derechos y la cultura indígena y afromexicana, será la responsable de analizar y seleccionar las solicitudes acreedoras al apoyo.\nLo cual se comunicará por escrito a los interesados.\n6.2.2.2. Eventos para el impulso de las culturas e identidades\na) Encuentros y Festivales afromexicano, corresponde a diversas actividades que la SAIA realizará en fechas conmemorativas, como\nDía Internacional de los Pueblos Indígenas, Día de la Mujer Indígena, Día Internacional de la Lengua\nIndígena, entre otros. Las sedes contempladas son los municipios de, Iliatenco, Malinaltepec, Ometepec, Xochistlahuaca, Tlacoachistlahuaca y Chilpancingo.\nEMITEN SUS REGLAS DE OPERACIÓN PARA EL\nEJERCICIO FISCAL 2020\nb) Talleres de Medicina tradicional para médicos tradicionales y parteras.\nEn cuanto a los talleres de medicina tradicional, su programación responde a una demanda expresa hecha en 2019 por médicos y parteras tradicionales amuzgos y nahuas, por lo que las sedes de estos talleres serán los municipios de Tlapa de Comonfort y Xochistlahuaca.\nLas y los participantes deberán cubrir los requisitos siguientes:\n● Solicitud por escrito libre, firmada por el representante del grupo de médicos. En el caso de parteras tradicionales, anexar copia simple de la autorización vigente, que obtuvieron de la autoridad de salud competente, que las habilita a ejercer como tales.\n● Identificación oficial (copia).\n6.2.2.3. Promoción y difusión de la música y danzas indígenas y afromexicanas a) Talleres de capacitación para reparación de instrumentos musicales:\n● Solicitud por escrito libre, firmada por el representante del grupo, dirigida a la persona titular de la SAIA, especificando las comunidades, municipio y número de músicos que requieren la capacitación, así como el tipo de instrumentos en el que desean capacitarse.\n● Identificación oficial de las y los participantes (copia).\n● La persona titular de la SAIA dará respuesta por escrito a la solicitud, en un término de treinta días hábiles, posteriores a la recepción de la misma.\n● En caso de que la respuesta sea afirmativa, se procederá a establecer, de común acuerdo, la sede y fecha del taller.\n● El grupo beneficiario deberá contribuir con el mobiliario y el local, para la realización del taller.\n● No podrán beneficiarse, quienes hayan recibido esta capacitación en los dos años inmediatos anteriores\nb) Donación de instrumentos musicales y vestuario para grupos de danza:\n● Solicitud por escrito libre, firmada por el representante del grupo, dirigida a la persona titular de la SAIA, en la que se asiente el tipo de apoyo requerido. La petición podrá presentarse en las oficinas centrales, ubicadas en la ciudad de Chilpancingo, o en las delegaciones regionales situadas en las ciudades de Tlapa, Chilapa y Ometepec.\n● Identificación oficial de las y los integrantes de las agrupaciones musicales y grupos de danza.\n● Las agrupaciones musicales y los grupos de danza deberán demostrar, mediante constancia expedida por la autoridad comunitaria, que el grupo cumple con una función de beneficio para su comunidad y que su integración tiene al menos tres años.\n● La SAIA analizará las solicitudes y determinará, de acuerdo al presupuesto del Programa, a las agrupaciones musicales que no hayan recibido ningún apoyo de otra institución, y que reúnan los requisitos de elegibilidad para recibir el apoyo, el cual será en especie.\n● La SAIA notificará a los grupos beneficiarios, por escrito, la aprobación de su solicitud, en un término de sesenta días hábiles, posteriores a la recepción de la misma.\nEMITEN SUS REGLAS DE OPERACIÓN PARA EL\nEJERCICIO FISCAL 2020\n● Las personas responsables de los grupos beneficiarios y sus autoridades comunitarias deberán firmar una Carta Compromiso, en la que se asiente la obligación de brindar un buen cuidado a los bienes recibidos, participar en las festividades y ceremonias comunitarias, así como reintegrar los bienes a las autoridades locales, en caso de desintegración del grupo, para ser reasignados a otra agrupación.\n● No podrán beneficiarse, los grupos de música o danza que hayan recibido un apoyo similar por cualquier nivel de Gobierno en los dos años inmediatos anteriores.\nLas personas y agrupaciones interesadas en los apoyos arriba señalados, deberán dirigir su solicitud por escrito libre a la persona titular de la SAIA, y entregarla en las oficinas centrales de la\nSecretaría de Asuntos Indígenas y Afromexicanos, así como en sus delegaciones regionales, en un horario de 9:00 a 15:00 horas:\n● Chilpancingo: Calle Guillermo Soberón Acevedo, núm. 8, Col. Salubridad. Tel. 01(747) 1 38 62\n81 Y 01 (747) 1 39 67 54.\n● Chilapa de Álvarez: Calle 3 Norte, núm. 108, Col. Centro. Tel. 01 (756) 475 0253\n● Ometepec: Calle Juan Ruiz de Alarcón, núm. 32, Barrio de la Guadalupe. Tel. 01 (741) 412\n0055.\n● Tlapa de Comonfort: Calle Morelos, núm. 124, Col Centro. Tel. 01 (757) 476 0377.\n6.3. Procedimientos de acceso\nLa forma de acceder a los servicios y apoyos que ofrece el Programa, es a través del cumplimiento de las bases de la convocatoria que publicará la SAIA y de los requisitos que se especifican en los numerales 6.2 y 6.3 de las presentes Reglas de Operación, y los criterios de evaluación y seguimiento a las solicitudes de apoyo, serán trasparentes, equitativos y no discrecionales.\nLos requisitos, la forma de acceso y criterios de selección establecidos por el Programa son públicos, y estarán disponibles para las personas solicitantes en las oficinas centrales y delegaciones de la SAIA, cuya ubicación y horarios se mencionaron con anterioridad.\nUna vez que las personas y/o agrupaciones hayan cubierto los requisitos establecidos para acceder a los apoyos del Programa, se entregará el comprobante respectivo y, en caso de ser aprobada su solicitud, recibirán el beneficio de manera gratuita, de acuerdo a la disponibilidad presupuestal del\nPrograma.\nLas personas y agrupaciones beneficiarias del Programa, formarán parte de un Padrón Único de\nBeneficiarias y Beneficiarios, el cual será de carácter público, siendo reservados sus datos personales, de\nGuerrero y, en ningún caso, podrán emplearse para propósitos de proselitismo político, religioso o comercial, ni para ningún otro fin distinto al establecido en estas Reglas de Operación.\nEMITEN SUS REGLAS DE OPERACIÓN PARA EL\nEJERCICIO FISCAL 2020 solicitar pago alguno por el servicio que prestan, ni procederán de manera diferente a lo establecido en las presentes reglas de Operación.\n6.4. Requisitos de permanencia y causales de baja o suspensión temporal La SAIA, a través de la Dirección General de Promoción Cultural y Apoyo Social, vigilará que se cumplan las presentes Reglas de Operación, así como del seguimiento y revisión de las solicitudes de apoyo que brinda el Programa.\nSe suspenderá el apoyo, cuando las personas o las agrupaciones incurra en las siguientes faltas:\n● Presentar información o documentación alterada o falsa.\n● No se cumpla con los requisitos de manera íntegra.\n● Utilizar con fines de lucro los instrumentos musicales y vestuario entregados por la SAIA.\n6.5. Modos de entrega del beneficio\n● Los instrumentos musicales y vestuario para grupos de danza, se entregarán solamente en especie.\n● La entrega de instrumentos y vestuario se realizará en las comunidades beneficiarias, en las delegaciones regionales u oficinas centrales de la SAIA.\n● En base a la disponibilidad presupuestal, a quienes participen en los talleres de capacitación, mediante solicitud previa a la persona titular de la SAIA, se les proporcionará alimentación y pago de pasajes de su comunidad al lugar sede.\n● En el caso de la edición y publicación de libros, los autores firmarán una carta compromiso con la SAIA, para recibir como retribución el 5% del tiraje total, bajo el compromiso de distribuir el material en bibliotecas, escuelas o comunidades interesadas, sin fines de lucro.\n● Las y los terapeutas tradicionales recibirán capacitación, materiales y utensilios para la preparación de medicamentos herbolarios, los cuales se distribuirán de manera equitativa.\n7. Procedimientos de instrumentación\n7.1. Operación\n● Para la ejecución del Programa Fortalecimiento de las Culturas e identidades Indígenas y\nAfromexicana, la SAIA elaborará las Reglas de Operación y la programación presupuestal.\n● La implementación del Programa estará a cargo de la Dirección General de Promoción Cultural y Apoyo Social, la cual será la responsable de recibir y dar seguimiento a las solicitudes de apoyo, y conformar el Padrón Único de Personas Beneficiarias del Programa.\n● Los datos de las personas y agrupaciones beneficiarias de este Programa, así como la información que se genere estará regida por lo que establece la Ley Número 207 de Transparencia y\nAcceso a la Información Pública del Estado de Guerrero.\n● Los apoyos entregados a las personas y agrupaciones beneficiarias, serán totalmente gratuitos.\nEMITEN SUS REGLAS DE OPERACIÓN PARA EL\nEJERCICIO FISCAL 2020\n7.2. Gastos de operación\nEn cumplimiento al artículo 47 de la Ley de Coordinación Fiscal, podrá aplicarse hasta un 3% del presupuesto total del programa, a gastos de operación y realización de diversas acciones, asociadas con la planeación, operación, supervisión, seguimiento, contraloría social y evaluación o asesoría externa del\nPrograma, por un monto de $144,000.00, de acuerdo a la tabla siguiente:\n8. Transparencia\n8.1. Difusión\nConforme a las disposiciones establecidas en el apartado de Programas Sujetos a Reglas de\nOperación del Decreto Número 447 del presupuesto de egresos del Estado de Guerrero para el Ejercicio\nFiscal 2020, estas Reglas de Operación, además de ser publicadas en el Periódico Oficial del Gobierno del\nEstado, estarán disponibles para la población en general en las oficinas centrales y delegaciones regionales de la SAIA, cuya ubicación se anota en el apartado 6 de las presente Reglas de Operación, así como en las páginas electrónicas: www.guerrero.gob.mx y www.asuntosindígenas.guerrero.gob.mx o en la página de la red social Facebook: Secretaria de Asuntos indígenas y Afromexicanos.\nAsimismo, a través de las delegaciones regionales Montaña, Costa Chica y Centro de la SAIA, se difundirá la información relativa al Programa, incluyendo a las autoridades municipales y comunitarias de los municipios indígenas y afromexicanos.\nLa papelería, documentación oficial y difusión del Programa, deberá incluir la leyenda descrita en el numeral 8.2. de las presente Reglas de Operación.\n8.2. Blindaje electoral\nCulturas e Identidades Indígenas y Afromexicana, deberán observar y atender las medidas que emita la con fines políticos, por lo que la papelería y documentación oficial, así como la publicidad y promoción del\nPrograma deberá de incluir la leyenda siguiente: “Este Programa es público, ajeno a cualquier partido político. Queda prohibido el uso para fines distintos a los establecidos en el Programa”.\nEMITEN SUS REGLAS DE OPERACIÓN PARA EL\nEJERCICIO FISCAL 2020\n8.3. Supervisión y control\nLa supervisión, control y evaluación del Programa Fortalecimiento de las Culturas e identidades\nIndígenas y Afromexicana, será interna y estará a cargo de la Dirección General de Promoción Cultural y\nApoyo Social, para lo cual se utilizará la Metodología del Marco Lógico y los resultados de la evaluación serán compartidos cada trimestre con la Secretaría de Planeación y Desarrollo Regional y la Secretaría de\nContraloría y Transparencia Gubernamental, mismos que se deberán presentar a más tardar 15 días hábiles posteriores a la terminación de cada trimestre, así como los informes sobre el presupuesto ejercido y en base a los indicadores de resultados previstos en este precepto.\nTodos los gastos generados en cada una de las actividades y acciones estarán soportados con la comprobación respectiva.\nLas delegaciones regionales y la Dirección General de Promoción Cultural y Apoyo Social de la\nSAIA, llevarán a cabo el seguimiento relacionado con las metas comprometidas a fin de verificar la aplicación correcta de los recursos otorgados y el cumplimiento de objetivos y metas establecidas.\nEste seguimiento se realizará a través de la evaluación y acompañamiento de las acciones desarrolladas en campo.\n8.4. Mecanismos de evaluación e indicadores\n8.4.1. Evaluación\nLa SAIA tendrá la obligación de revisar, de manera interna, la correcta operación y aplicación de las presentes Reglas de Operación y, en caso necesario, podrá solicitar una evaluación externa por parte de una instancia con experiencia en el tema.\nAsimismo, efectuará periódicamente acciones de supervisión y evaluación para garantizar el adecuado desarrollo del Programa, con el objeto de corregir desfases o efectuar reasignaciones financieras\nAdministración, a fin de cubrir rubros prioritarios con recursos de este mismo Programa o de otros que no hayan sido ejercidos en su momento, o bien que provengan de ahorros presupuestales.\n8.4. 2. Indicadores\nEMITEN SUS REGLAS DE OPERACIÓN PARA EL\nEJERCICIO FISCAL 2020\n8.5. Auditoría\nEste Programa podrá ser auditado, a través de las instancias correspondientes en el ámbito de recursos del erario público. Como resultado de las acciones de auditoría que se llevan a cabo, el órgano estatal de control mantendrá seguimiento interno que permita emitir los informes de las revisiones practicadas, dando principal importancia a la atención en tiempo y forma de las irregularidades detectadas hasta ser solventadas.\n8.6. Recursos no devengados a la Dirección General de Tesorería, de la Secretaría de Finanzas y Administración del Estado de Guerrero.\n8.7. Contraloría social\nLa SAIA, como instancia ejecutora, promoverá la contraloría social, la cual comprende un conjunto de acciones de control, vigilancia y evaluación que realizan las y los beneficiarios, ya sea de manera organizada o independiente, bajo un esquema de derechos y compromisos ciudadanos, con el propósito de contribuir a que la gestión gubernamental se realice en términos de transparencia, eficacia y honradez.\nEntre dichas acciones destacan las siguientes:\na) Informar a la ciudadanía acerca de los apoyos otorgados y su costo.\nEMITEN SUS REGLAS DE OPERACIÓN PARA EL\nEJERCICIO FISCAL 2020\nb) Capacitar a las y los beneficiarios para que se constituyan en instancias de vigilancia y evaluación social.\nc) Establecer espacios de comunicación (reuniones vecinales, asambleas comunitarias, entre otros).\nd) Promover la integración de organizaciones de la sociedad civil para realizar acciones de contraloría social.\ne) Instrumentar mecanismos de recepción y atención de quejas y denuncias. El Órgano Estatal de\nControl verificará en lo correspondiente la realización de dichas acciones.\n8.8. Formas de participación social\nCon apego en lo dispuesto en la Ley Número 684 de Participación Ciudadana del Estado Libre y\nSoberano de Guerrero, se establece que la sociedad podrá participar activamente en la Planeación, Programación, Implementación y Evaluación de los Programas de esta Secretaría, ya sea de manera individual o de manera colectiva, tales como consejos, comités vecinales, comités de seguimiento de administración, de supervisión, de control, entre otros, por lo que en cumplimiento de estas disposiciones, la forma de participación para el Programa será a través de un Consejo, cuyos miembros participarán en la etapa de la implementación y podrán supervisar la gestión gubernamental, y que el manejo de los recursos públicos se realicen en términos de transparencia, eficacia, legalidad y honradez del Programa de acuerdo en lo estipulado en estas Reglas de Operación.\n8.9. Procedimiento de queja o inconformidad ciudadana\nLas quejas, denuncias, peticiones y sugerencias relativas a este programa, se realizarán de manera escrita, por comparecencia del interesado, por correo electrónico o vía telefónica, y para aquellas que sean escritas se depositarán en los buzones instalados en las oficinas centrales de la SAIA, ubicadas en la ciudad de Chilpancingo, así como en las delegaciones regionales, situadas en las ciudades de Tlapa de Comonfort, Chilapa de Álvarez y Ometepec.\nLa persona denunciante deberá proporcionar los datos siguientes:\n● Nombre de la servidora o servidor público\n● Departamento de adscripción\n● Objeto de la denuncia\n● Nombre y domicilio de la persona quejosa\nEMITEN SUS REGLAS DE OPERACIÓN PARA EL\nEJERCICIO FISCAL 2020\n● Identificación oficial de la persona quejosa.\nEl seguimiento a las quejas, denuncias, peticiones y sugerencias relativas a este Programa, se en un término máximo de 20 días hábiles.\nEn caso de que la SAIA no resuelva la queja de las personas solicitantes o beneficiarias, éstas podrán presentarla ante la Contraloría Social de la Secretaría de Contraloría y Transparencia\nGubernamental del Estado de Guerrero.\n8.10. Mecanismos de exigibilidad\nLos requisitos para acceder a los apoyos del Programa, estarán disponibles para todas las personas interesadas en las oficinas centrales de la SAIA, ubicadas en la ciudad de Chilpancingo, así como en las delegaciones regionales, situadas en las ciudades de Tlapa de Comonfort, Chilapa de Álvarez y\nOmetepec, cuyas direcciones aparecen en el apartado 6 las presentes Reglas de Operación.\nUna vez que las personas y agrupaciones hayan cubierto los requisitos establecidos por el\nPrograma y resulten beneficiarios, recibirán el apoyo solicitado, de acuerdo a la disponibilidad presupuestal de la SAIA.\nLos casos en los que se podrán exigir los derechos por incumplimiento o por violación de los mismos pueden ocurrir en al menos los casos siguientes:\na) Cuando una persona o grupo solicitante cumpla con los requisitos y criterios de inclusión para acceder a los apoyos del Programa y exija a la SAIA ser beneficiaria del mismo.\nb) Cuando la persona o grupo beneficiario del Programa exija a la SAIA que se cumpla con su derecho, de manera integral en tiempo y forma, como lo establece el Programa.\nc) Cuando no se pueda satisfacer toda la demanda de incorporación al Programa por restricción presupuestal, y la persona o grupos exijan que las incorporaciones sean claras, transparentes, equitativas, sin favoritismos, ni discriminación. desarrollo social.\n8.11. Acta de entrega-recepción\nSe conformará un padrón de personas beneficiarias y resguardarán sus expedientes, incluyendo su acta de donación correspondiente, dada la naturaleza del apoyo otorgado, se realiza en apego al control del gasto público.\nEMITEN SUS REGLAS DE OPERACIÓN PARA EL\nEJERCICIO FISCAL 2020\n9. Criterios de selección y elegibilidad y elegibilidad, establecidos en el apartado 6 de las presentes Reglas de Operación.\n9.1. Métodos de selección de personas beneficiarias\nPara el otorgamiento de los apoyos del Programa, la comisión dictaminadora de la SAIA dará prioridad a las personas y agrupaciones que provengan de municipios indígenas y afromexicanos con mayores niveles de pobreza, que radiquen en sus localidades de origen y que enfoquen sus acciones al beneficio comunitario, así como a la protección y difusión de los valores culturales e identitarios de sus pueblos y comunidades.\n10. Mecánica de operación\n10.1. Instancia ejecutora\nLa Secretaría de Asuntos Indígenas y Afromexicanos será la instancia ejecutora del Programa\nFortalecimiento de las Culturas e Identidades Indígenas y Afromexicana, a través de la Dirección General de Promoción Cultural y Apoyo Social y de sus delegaciones regionales, de acuerdo a los lineamientos establecidos en estas Reglas de Operación para el ejercicio fiscal 2020.\n10.2. Instancia administrativa y/o normativa\nLa Secretaría de Planeación y Desarrollo Regional y la Secretaria de Contraloría y Transparencia\nGubernamental serán las instancias normativas y facultadas para autorizar y verificar la aplicación de estas\nReglas de Operación.\n10.3. Delimitación de atribuciones\nRespetando las presentes Reglas de Operación, las instancias ejecutoras y administradoras del presente Programa, se limitarán a realizar sus funciones establecidas, así como lo señalado en el reglamento interno de la institución. Esto con el objeto de armonizar el correcto desempeño y aplicación de los recursos asignados por el Estado para los fines del Programa.\n11. Derechos, obligaciones y sanciones de los beneficiaros de programas sociales\n11.1. Derechos\na) Recibir un trato digno, respetuoso, oportuno, equitativo y de calidad.\nb) Acceder a los apoyos que otorga el Programa, de acuerdo con lo establecido en estos lineamientos y con la disponibilidad presupuestal.\nEMITEN SUS REGLAS DE OPERACIÓN PARA EL\nEJERCICIO FISCAL 2020\nc) Recibir orientación de la SAIA para la presentación de solicitudes de apoyo e integración de expedientes sin costo alguno.\nd) Tener la garantía de privacidad de sus datos personales.\n11.2. Obligaciones\na) Conducirse con la verdad en toda la información solicitada.\nb) Emplear el bien o apoyo recibido para los fines por los que fue otorgado.\nc) Entregar la documentación e información requeridas, de acuerdo a las Reglas de Operación.\nd) Firmar una Carta-Compromiso con la SAIA, en los casos de instrumentos musicales y vestuario de danza.\ne) Comprometerse a conservar los instrumentos musicales en condiciones favorables.\nf) Informar a la SAIA, a través de sus oficinas centrales o delegaciones regionales, cuando se presente algún suceso que evite la correcta aplicación de los apoyos otorgados a las agrupaciones musicales y de danza.\n11.3. Sanciones\nLas agrupaciones musicales y de danza que utilicen los apoyos recibidos con un fin distinto a lo previsto en estas Reglas de Operación, deberán devolver el bien a las autoridades comunitarias, quienes lo entregarán a personas u otra agrupación que cumpla con lo previsto.\n12. Interpretación\nLas presentes Reglas de Operaciónse interpretarán de forma unilateral y clara, de acuerdo a su contenido; lo anterior en el sentido que son específicas y entendibles en su contenido y alcance. Cualquier aclaración de las mismas, será responsabilidad de la instancia ejecutora y administrativa, disipar las dudas de la población indígena y afromexicana, con respecto a la adecuada presentación de sus solicitudes, documentación y requisitos, así como la correcta aplicación de los recursos económicos asignados para el fin propuesto.\nPara la interpretación de las presentes Reglas de Operación, se entenderá por:\nPrograma: El Programa Fortalecimiento de las Culturas e Identidades Indígenas y Afromexicana.\nReglas de Operación: Las Reglas de Operación del Programa Fortalecimiento de las Culturas e\nIdentidades Indígenas y Afromexicana.\nEMITEN SUS REGLAS DE OPERACIÓN PARA EL\nEJERCICIO FISCAL 2020\nSAIA: La Secretaría de Asuntos Indígenas y Afromexicanos.\nEMITEN SUS REGLAS DE OPERACIÓN PARA EL\nEJERCICIO FISCAL 2020\nANEXO\nANEXO 1. FORMATO DE ACTA DE DONACION DE INSTRUMENTOS MUSICALES\nEMITEN SUS REGLAS DE OPERACIÓN PARA EL\nEJERCICIO FISCAL 2020\nPrimero. El presente Acuerdo entrará en vigor al día siguiente de su publicación en el Periódico Oficial del\nSegundo. Se abroga el Acuerdo por el que se emiten las reglas de Operación del Programa\nFortalecimiento de las Culturas e Identidades Indígenas y Afromexicana, de la Secretaría de Asuntos\nIndígenas y Afromexicana para el Ejercicio Fiscal 2020, publicado en el Periódico oficial del Gobierno del\nEstado No. 48, de fecha 14 de junio de 2019.\nTercero. A partir de la entrada en vigor del presente Acuerdo, las Reglas de Operación del\nPrograma Fortalecimiento de las Culturas e Identidades Indígenas y Afromexicana, subsecuentes y sus modificaciones serán emitidas por la persona titular de la Secretaría de Asuntos Indígenas y\nAfromexicanos, responsable directa de la operación y ejecución de las mismas.\nDado en la Oficina del titular del Poder Ejecutivo, ubicada en el Edificio Centro de Palacio de\nGobierno, Boulevard René Juárez Cisneros No. 62, Colonia Ciudad de los Servicios en la Ciudad de\nChilpancingo de los Bravo, Capital del Estado de Guerrero, a los cuatro días del mes de mayo del año dos mil veinte.\nEL GOBERNADOR CONSTITUCIONAL DEL ESTADO DE GUERRERO.\nLIC. HÉCTOR ANTONIO ASTUDILLO FLORES.\nRúbrica.\nEL SECRETARIO GENERAL DE GOBIERNO\nLIC. FLORENCIO SALAZAR ADAME.\nRúbrica.\nEL SECRETARIO DE ASUNTOS INDÍGENAS Y AFROMEXICANOS.\nMTRO. JAVIER ROJAS BENITO.\nRúbrica.",
  "ordenamiento": "PROGRAMA",
  "jurisdiccion": "GUERRERO",
  "fuente_oficial": "DIARIO OFICIAL DE LA FEDERACION",
  "Fecha de Publicación": "03 DE AGOSTO \nDE 2022",
  "ULTIMA REFORMA PUBLICADA": null,
  "status": "VIGENTE",
  "es_escaneado": false,
  "tiene_tablas": false,
  "materia": [
    "cultura",
    "indígena"
  ]
}