{
  "titulo": "Acuerdo por el Que Se Crea el Proyecto Paquetes de Insumos y Enseres Agrícolas para la Producción Pr",
  "Contenido": "REGLAS DE OPERACIÓN, PARA EL EJERCICIO FISCAL\nGUERRERO No. 67 ALCANCE II, DE FECHA 28 DE AGOSTO DE 2020.\nTEXTO ORIGINAL\nAcuerdo publicado en el Periódico Oficial del Gobierno del Estado No. 54 Alcance VII, el Viernes\n05 de julio de 2019.\nACUERDO POR EL QUE SE CREA EL PROYECTO PAQUETES DE INSUMOS Y ENSERES\nAGRÍCOLAS PARA LA PRODUCCIÓN PRIMARIA Y SE EMITEN LAS REGLAS DE OPERACIÓN, PARA\nEL EJERCICIO FISCAL 2019.\nLIC. JOSÉ FRANCISCO SOLÍS SOLÍS, DIRECTOR GENERAL DEL SISTEMA PARA EL DESARROLLO\nINTEGRAL DE LA FAMILIA DEL ESTADO DE GUERRERO, EL CUAL ES UN ORGANISMO PÚBLICO\nDESCENTRALIZADO, CON PERSONALIDAD JURÍDICA Y PATRIMONIO PROPIO CREADO MEDIANTE\nLEY 107 PUBLICADA EN EL PERIÓDICO OFICIAL NÚMERO 10 DEL GOBIERNO DEL ESTADO CON\nFECHA 9 DE MARZO DE 1977 Y REGULADO POR LA LEY 479 PUBLICADA EN EL PERIÓDICO OFICIAL\nNÚMERO 61 DEL 02 DE AGOSTO DE 1983, CON FUNDAMENTO EN LA LEY 690 DE ENTIDADES\nPARAESTATALES PARA EL ESTADO DE GUERRERO; EL ARTÍCULO 27 FRACCIÓN X DEL\nREGLAMENTO INTERIOR DEL ORGANISMO PÚBLICO DESCENTRALIZADO, ASÍ COMO LA LEY\nSOBRE EL SISTEMA ESTATAL DE ASISTENCIA SOCIAL NÚMERO 332, ARTICULO 4, FRACCIONES I\nA LA XV; ARTICULO II BIS, FRACCIÓN I AL IV Y ARTÍCULO 11 TER, ÚLTIMA REFORMA PUBLICADA\nEN EL PERIÓDICO OFICIAL DEL GOBIERNO DEL ESTADO NÚMERO 15 DE FECHA 20 DE FEBRERO\nDEL 2015, Y LOS LINEAMIENTOS PARA LA ELABORACIÓN DE LAS REGLAS DE OPERACIÓN DE LOS\nPROGRAMAS SOCIALES ESTATALES PARA EL EJERCICIO FISCAL 2017, Y\nCONSIDERANDO\nQue en el Dictamen y Decreto Número 182 del Presupuesto de Egresos del Estado de Guerrero para el\nEjercicio Fiscal 2019, se señala que se ejercerán los recursos bajo una política de gasto público, que permita dar cumplimiento a lo que globalmente prevén los ejes rectores del Plan Estatal de Desarrollo 20162021, alineándose en el eje III.- Guerrero Socialmente Comprometido. Objetivo 3.1 garantizar el ejercicio efectivo de los derechos sociales para la población. Objetivo 3.2. Transitar hacia una sociedad equitativa e incluyente y Objetivo 3.9. Proveer un entorno adecuado para el desarrollo de una vida digna; dentro de la política de Desarrollo Social, el Sistema para el Desarrollo Integral de la Familia del Estado de Guerrero, opera Proyectos productivos, cuyo objetivo es Fortalecer la economía de las personas que habiten en zonas rurales.\nEl Sistema para el Desarrollo Integral de la Familia tendrá a cargo la implementación, ejecución, evaluación y administración del Proyecto Paquetes de Insumos y Enseres Agrícolas para la Producción Primaria, bajo los criterios de objetividad, equidad, transparencia, publicidad, selectividad y temporalidad, con estricto\nREGLAS DE OPERACIÓN, PARA EL EJERCICIO FISCAL apego a la normatividad aplicable, por lo tanto será el encargado de la dispersión y asignación de los\nPor lo antes expuesto y con fundamento en las disposiciones legales antes citadas, he tenido a bien expedir el siguiente:\nACUERDO POR EL QUE SE CREA EL PROYECTO PAQUETES DE INSUMOS Y ENSERES\nAGRÍCOLAS PARA LA PRODUCCIÓN PRIMARIA Y SE EMITEN LAS REGLAS DE OPERACIÓN PARA\nEL EJERCICIO FISCAL 2019.\nÚnico: Se emiten las Reglas de Operación del Proyecto Paquetes de Insumos y Enseres Agrícolas para la Producción Primaria, para el Ejercicio Fiscal 2019.\nCONTENIDO\n1. INTRODUCCIÓN\n1.1 Antecedentes\n1.2 Alineación programática\n1.3 Diagnóstico\n2. DEPENDENCIA O ENTIDAD RESPONSABLE DEL PROGRAMA\n3. OBJETIVOS Y ALCANCES\n3.1 General\n3.2 Específicos\n3.2 Alcances\n4. METAS FÍSICAS\n5. PROGRAMACIÓN PRESUPUESTAL\n6 REQUISITOS Y PROCEDIMIENTO DE ACCESO\n6.1 Difusión\n6.2 Requisitos de Acceso\n6.3 Procedimientos de Acceso\n6.4 Requisitos de Permanencia, Causales de Baja o Suspensión Temporal\n6.5 Modos de Entrega del Beneficio\nREGLAS DE OPERACIÓN, PARA EL EJERCICIO FISCAL\n7 PROCEDIMIENTOS DE INSTRUMENTACIÓN\n7.1 Operación\n7.2 Gastos de Operación\n8. TRANSPARENCIA\n8.1 Difusión\n8.2 Blindaje Electoral\n8.3 Supervisión y Control\n8.4 Mecanismos de Evaluación e Indicadores\n8.4.1 Evaluación\n8.4.2 Indicadores\n8.5 Auditoria\n8.6 Recursos no Devengados\n8.7 Contraloría Social\n8.8 Formas de Participación Social\n8.9 Procedimiento de Queja o Inconformidad Ciudadana\n8.10 Mecanismos de Exigibilidad\n8.11 Acta de Entrega-Recepción\n9. CRITERIOS DE SELECCIÓN Y ELEGIBILIDAD\n9.1 Método de Selección de Beneficiarios\n10. MECÁNICA DE OPERACIÓN\n10.1 Instancia Ejecutora\n10.2 Instancia administrativa y/o normativas\n10.3 Delimitación de atribuciones\n11. DERECHOS, OBLIGACIONES Y SANCIONES DE LOS BENEFICIARIOS DE PROGRAMAS\nSOCIALES\n11.1 Derechos\n11.2 Obligaciones\n11.3 Sanciones\nREGLAS DE OPERACIÓN, PARA EL EJERCICIO FISCAL\n12. INTERPRETACIÓN TRANSITORIOS ANEXOS\n1. INTRODUCCIÓN\n1.1. ANTECEDENTES\nEl DIF Guerrero, a través de la Dirección de Asistencia Alimentaría y Desarrollo Comunitario, fomenta y promueve acciones que mitiguen la vulnerabilidad de las personas que son sujeto de asistencia social, y tiene como Intención apoyar y coordinar las acciones de desarrollo comunitario en las que participan los tres niveles de gobierno Federal, Estatal y Municipal, dentro del ámbito de su competencia, en coordinación con los Sistemas DIF Municipales.\nEn este documento se sustenta la intervención institucional que desde el ejercicio 2012 ha venido atendiendo a población en situaciones de vulnerabilidad, así mismo, se especifica la participación básica de llevar a cabo entre los sistemas DIF municipales, la realización proyectos productivos los cuales tienen como prioridad la atención de aquellas familias en estado de vulnerabilidad social que habiten en localides de alto y muy alto grado de marginación y tienen el propósito de fomentar el autoempleo y consumo como un elemento clave para que las familias que viven en condiciones de desventaja socioeconómica mejoren sus niveles de vida, para lo cual se les otorgaran Paquetes de Insumos y Enseres Agrícolas para la\nProducción Primaria, mismo que tendrá una cuota de recuperación determinada por un estudio socioeconómico.\nEn consecuencia, la formulación de un programa y / o proyecto de desarrollo social exige conjugar armónicamente todos los elementos que lleven a la materialización de sus objetivos, estrategias, metas y evaluación de resultados. Por ello, se deben considerar en la introducción, los siguientes rubros:\nNaturaleza del Proyecto: Es un proyecto social el cual permitirá disminuir el impacto del desempleo temporal, como una de las alternativas para enfrentar dicho fenómeno brindando a los hogares mitigar los impactos económicos sociales, buscando cumplir con los objetivos y estrategias que plantea el Ejecutivo\nEstatal. plenitud; asimismo, plantea elevar la productividad de las personas para que cuenten con mejores opciones de empleo e ingreso, que les permitan reducir sus niveles de pobreza.\nOrigen y Fundamento: Constitución Política de los Estados Unidos Mexicanos Constitución Política del\nSocial.\nREGLAS DE OPERACIÓN, PARA EL EJERCICIO FISCAL\nObjetivos y Metas: Contribuir al gasto de las familias que habitan en los municipios y localidades de alta y muy alta marginación, por lo que se atenderán a 131 familias, para que tengan un negocio propio, así como crear fuentes de empleo y autoempleo que coadyuven en su ingreso familiar, como precedente de sustentabilidad laboral.\nUbicación Geográfica: Se atenderán a los 81 municipios que integran el Estado, dando prioridad a los municipios de alta y muy alta marginación.\nActividades a Realizar: Gestionar ante las instancias de Gobierno Federales y Estatales, los recursos financieros, para llevar a cabo la adquisición de los materiales, insumos y productos necesarios en la operatividad del proyecto; así mismo dar a conocer al Sistema Municipal DIF, las Reglas de Operación del proyecto vigentes y proporcionar de forma calendarizada los suministros de los apoyos.\nInstancias Participantes: La instancia ejecutora es el Sistema para el Desarrollo Integral de la Familia, a través de la Dirección de Asistencia Alimentaria y Desarrollo Comunitario, quien se coordinará con los\nSistemas Municipales DIF para llevar a cabo la ejecución y seguimiento del proyecto.\nPresupuesto de Inversión: Se tiene contemplado $ 1,683,600.00 (Un millón seiscientos ochenta y seis mil seiscientos pesos 00/100 M.N.); recursos presupuestales que provienen del Ramo 33.- Aportaciones\nFederales para Entidades y Municipios, específicamente del Fondo de Aportaciones Múltiples (Asistencia\nSocial).\nGlosario de Términos:\nSEDIF: Sistema para el Desarrollo Integral de la Familia.\nSEFINA: Secretaría de Administración y Finanzas.\nSEPLADER: Secretaría de Planeación y Desarrollo Regional.\nSecretaría de Contraloría: Secretaría de Contraloría y Transparencia Gubernamental.\nAsistencia Social: Conjunto de Acciones Tendientes a Modificar y Mejorar las Circunstancias de Carácter\nSocial que Impiden el Desarrollo Social del Individuo, así como la Protección Física, Mental y Social de\nPersonas en Estado de Necesidad.\nGrupos Vulnerables: Persona o grupo que por sus características de desventaja por edad, sexo, estado civil; nivel educativo, origen étnico, situación o condición física y/o mental; requieren de un esfuerzo\n1.2. ALINEACIÓN PROGRAMÁTICA\nEn cumplimiento a lo que globalmente prevén los ejes rectores del Plan Estatal de Desarrollo 20162021este proyecto se alinea en el Eje III.- Guerrero Socialmente Comprometido; Objetivos: 3.1. Construir un Estado Garante de los Derechos Sociales de las Personas; 3.2. Edificar la ruta hacia una sociedad\nREGLAS DE OPERACIÓN, PARA EL EJERCICIO FISCAL equitativa e incluyente; Estrategias: 3.1.2. Fortalecer el desarrollo de capacidades de los integrantes de una sociedad con carencias, que permitan contribuir a incrementar su capacidad productiva y su calidad de vida y 3.2.1. Generar programas de desarrollo comunitario por medio de procesos de participación social.\nLíneas de Acción\n• Fomentar el acceso efectivo de las familias a sus derechos sociales, particularmente de aquellas en pobreza extrema, mediante políticas públicas coordinadas y concurrentes.\n• Potenciar la inversión conjunta de la sociedad organizada y de los órdenes de Gobierno, invirtiendo en proyectos de infraestructura social básica, complementaria y productiva.\nAsí mismo las presentes Reglas se alinean a lo estipulado en el Programa Sectorial \"Desarrollo y Asistencia\nSocial\" 2016-2021, cuyo objetivo es atender a personas vulnerables, a través de desarrollar capacidades y habilidades de las familias con carencias alimentarias al proporcionar los apoyos necesarios que mejoren su calidad de vida y sus núcleos familiares, logrando fortalecer el tejido social en localidades vulnerables.\n1.3. DIAGNOSTICO\nEl alto nivel de informalidad de la economía nacional y la marginación de numerosos municipios y localidades a lo largo de todo el país, provoca que la inestabilidad del empleo sea considerada como uno de los principales motivos de preocupación dentro de los hogares mexicanos; que la pérdida del empleo y la consecuente disminución de los ingresos aún de manera temporal tienen graves consecuencias sobre la pobreza de los hogares, fundamentalmente porque la falta de empleo conduce a una importante disminución del capital económico familiar, mayor presión sobre los recursos naturales, así como el abandono de la educación y el fomento al endeudamiento, estas afectaciones frecuentemente persisten aun cuando sus miembros se reintegran a las actividades productivas y remuneradas.\nQue la oferta laboral puede disminuir en algunas regiones del Estado a lo largo del año debido a emergencias o por efecto de los ciclos productivos, afectando principalmente a la población de escasos recursos que enfrenta periódicamente etapas con una grave disminución en sus ingresos y patrimonio. formales e informales (se refiere a la actividad laboral de los trabajos independientes), la ejecución de acciones que permitan disminuir el impacto del desempleo temporal; una de las alternativas para enfrentar brinden a los hogares el auto emplearse y/o generar empleo. los posibles beneficiarios y / o beneficiarias deben participar en proyectos de beneficio familiar o\nREGLAS DE OPERACIÓN, PARA EL EJERCICIO FISCAL comunitario como corresponsabilidad obligatoria para recibir los apoyos que se les otorguen, este requisito comunidades, sino que además genera beneficios adicionales.\nEl trabajo informal en países de economía subdesarrollada como México, está altamente asociada con el autoempleo, La carencia de plazas laborales que brinden una mayor seguridad salarial y mejores condiciones de trabajo orilla a casi el 60% de los buscadores de empleo a resolver por sí mismos su condición de desempleados y generalmente lo logran mediante pequeñas inversiones en el sector comercio y de servicios.\nEn el Estado existen 895, 157 hogares de los cuales 293 086 están conformadas por Jefas de Familias que es el 33% y 602 071, se conforman por Jefes de Familia que en términos porcentuales le corresponde el\n67% razón por la cual el Sistema para el Desarrollo Integral de la Familia beneficiará a 113 familias que conforma nuestra población objetivo y la constituyen las familias en estado de vulnerabilidad que habiten en Municipios o Localidades con alto o muy alto grado de marginación, considerando la suficiencia presupuestal para el ejercicio vigente y los criterios de focalización y priorización del Proyecto. Con respecto a la evolución del valor de la canasta alimentaria publicada por el CONEVAL, a nivel nacional se observa que entre septiembre de 2015 y septiembre de 2016, el valor de la canasta alimentaria ha crecido, aproximadamente, 4.6 por ciento en zonas rurales y 3.8 por ciento en zonas urbanas.\nQue dentro de los objetivos y estrategias que plantea el Ejecutivo Estatal, está abatir la marginación y el rezago social que enfrentan los grupos sociales vulnerables para proveerles de igualdad en las oportunidades que les permitan desarrollarse con independencia y plenitud; asimismo, plantea elevar la productividad de las personas para que cuenten con mejores opciones de empleo e ingreso, que les permitan reducir sus niveles de pobreza, por ello se busca atender el problema identificado en el diagnostico a través de:\nMisión: Proporcionar a las familias en desventaja económica el Proyecto Paquetes de Insumos y Enseres\nAgrícolas para la Producción Primaria, como generador de autoempleo y / o empleo e ingresos a través de la prestación de un servicio.\nVisión: Elevar la calidad de vida de la familia mediante el desarrollo de proyectos generadores de autoempleo que coadyuven en el fortalecimiento de la economía familiar.\n2. DEPENDENCIA O ENTIDAD RESPONSABLE DEL PROGRAMA\nLa instancia ejecutora será el sistema para el Desarrollo Integral de la Familia, a través de la Dirección de\nAsistencia Alimentaria y Desarrollo Comunitario, quien se coordinará con los Sistemas Municipales DIF para llevar a cabo la ejecución y seguimiento del proyecto, el cual tiene como fundamento legal a la:\nREGLAS DE OPERACIÓN, PARA EL EJERCICIO FISCAL periódico oficial del Gobierno del Estado número 71, alcance I de fecha 04 de septiembre de 2018).\n• Ley General de Salud, (última reforma publicada en el Diario Oficial de la Federación de fecha 12 julio de 2018).\n• Ley de Asistencia Social, (última reforma publicada en el Diario Oficial de la Federación de fecha\n24 de abril 2018).\n• Ley General para la Inclusión de las Personas con discapacidad, (última reforma publicada en el\nDiario Oficial de la Federación de fecha 12 de julio 2018).\n• Ley No. 817 para las Personas con Discapacidad del Estado, (última reforma publicada en el\nPeriódico Oficial número 103, de fecha 26 de diciembre de 2014).\n• Ley 479 del Sistema para el Desarrollo Integral de la Familia, publicada en el periódico Oficial el martes 02 de agosto de 1983. el Periódico Oficial número 74, alcance I, de fecha 13 de septiembre de 2016).\n• Ley 454 de Presupuesto y Disciplina Fiscal del Estado de Guerrero, (última reforma publicada en el\nPeriódico Oficial número 91, alcance II, de fecha 11 de noviembre de 2016).\n• Ley Orgánica de la Administración Publica 08 (última reforma publicada en el Periódico Oficial del\nEstado número 69 de fecha 28 de agosto de 2018).\n• Ley 207 de Transparencia y Acceso a la Información Pública del Estado.\n• Ley sobre el Sistema Estatal de Asistencia Social 332 (Última reforma publicada el 20 de febrero del 2015).\n• Plan Estatal de Desarrollo 2016 - 2021.\n• Programa Sectorial Desarrollo y Asistencia Social 2016-2021.\n• Decreto Número 182 del Presupuesto de Egresos del Estado de Guerrero para el ejercicio fiscal\n2019.\n• Estrategia Local \"Guerrero Contigo\"\n• Reglamento Interno del Sistema para el Desarrollo Integral de la Familia del Estado de Guerrero.\n• Manual de Organización del DIF Guerrero.\n• Y todos aquellos Ordenamientos Normativos Aplicables.\n3. OBJETIVOS Y ALCANCES\n3.1. GENERAL marginación, para que tengan un negocio propio, a través del otorgamiento de 113 Paquetes de Insumos y Enseres Agrícolas para la Producción Primaria, generando fuentes de empleo y autoempleo que coadyuven en su ingreso familiar.\nREGLAS DE OPERACIÓN, PARA EL EJERCICIO FISCAL\n3.2. ESPECÍFICOS\n• Generar una alternativa de autoempleo como precedente de sustentabilidad laboral.\n• Incrementar el ingreso familiar.\n• Brindar un servicio básico.\n3.3 ALCANCES\nLa operación o ejecución del proyecto surge para mitigar y garantizar el empleo y/o autoempleo atendiendo al derecho al trabajo y a la alimentación de la población que viven en situación de pobreza y/o sin empleo a través de la dotación de 113 Paquetes de Insumos y Enseres Agrícolas para la Producción Primaria, mejorando su economía familiar y comunitaria.\nLa población objetivo la constituyen las familias que habiten en Municipios o Localidades con alto o muy alto grado de marginación, considerando la suficiencia presupuestal para el ejercicio vigente y los criterios de focalización y priorización del Proyecto.\n4. METAS FÍSICAS\nSe beneficiaran aproximadamente a 113 familias, dicho apoyo será entregado directamente a las familias beneficiarias o ben puntos sedes ubicados en su Municipio correspondiente.\n5. PROGRAMACIÓN PRESUPUESTAL\nDictamen y Decreto Número 182 del Presupuesto de Egresos del Estado de Guerrero para el Ejercicio\nFiscal 2019, se señala que se ejercerán los recursos bajo una política de gasto público, que permita dar cumplimiento a lo que globalmente prevén los ejes rectores del Plan Estatal de Desarrollo 2016-2021.\nProyecto que es subsidiado a través de recursos presupuestales que provienen del Ramo 33.- Aportaciones\nFederales para Entidades y Municipios, específicamente del Fondo de Aportaciones Múltiples (Asistencia\nSocial), el cual tiene asignado $ 1, 683,600.00 (Un millón seiscientos ochenta y seis mil seiscientos pesos\n00/100 M.N.), mismo que tiene un costo promedio por beneficiario y / o beneficiaria de $ 14,899.11 (Catorce mil ochocientos noventa y nueve pesos 11/100 M.N.).\nCRONOGRAMA FINANCIERO\nPRES. AUT. ENERO FEBRERO MARZO ABRIL MAYO\nREGLAS DE OPERACIÓN, PARA EL EJERCICIO FISCAL\n1,683,600 0.00 0.00 0.00 1,683,600 0.00\nJUNIO JULIO AGOSTO SEP. OCT. NOV DIC.\n0.00 0.00 0.00 0.00 0.00 0.00 0.00\nNOTA: PUEDE EXISTIR VARIACION EN RELACION A LO APROBADO POR EL DOF. Y/O POR LAS NECESIDADES PROPIAS DEL SEDIF\n6. REQUISITOS Y PROCEDIMIENTOS DE ACCESO\n6.1. DIFUSIÓN\nEl sistema para el Desarrollo Integral de la Familia a través de los diferentes medios de comunicación y de las redes sociales da conocer cada uno de los diferentes programas de asistencia social que ejecuta y opera en coordinación con las diferentes Direcciones que integran el Sistema como son; Programas\nAlimentarios, Proyectos Asistenciales, de Bienestar Social y Desarrollo Comunitario; cuyos requisitos se encuentran en las oficinas del Sistema ubicadas en Boulevard Rene Juárez Cisneros, Colonia Ciudad de los Servicios y Av. Gabriel Leyva s/n esq. Ruffo Figueroa, Col. Burócratas, C.P. 39090, Chilpancingo, Guerrero, con un horario de atención de 8:00 am a 3:00 pm y/o los teléfonos 01(747) 4725595, 01(747)47256 00, 01(747)47 25672 ext 1151 Y 1159. Así mismo al correo electrónico: alimentariadif@prodigy.net.mx, y http://www.dif.guerrero.gob.mx\nLas reglas de operación de cada uno de los programas son difundidas por personal capacitado de cada una de las Direcciones que conforman el Sistema para el Desarrollo Integral de la Familia y en la página web https://www.guerrero.gob.mx del Portal del Gobierno del Estado. Por otra parte, los programas tienen cobertura Estatal.\n6.2. REQUISITOS DE ACCESO\n• Los interesados deberán presentar oficio de solicitud en formato libre en las instalaciones del DIF\nGuerrero con domicilio en el Centro de Rehabilitación Integral Guerrero, Boulevard Lic. René Juárez\nCisneros S/N, Col. Ciudad de los Servicios, Chilpancingo, dirigido a la Presidenta o Director General del DIF para ser considerado dentro del Proyecto, anexando copia fotostática de la siguiente documentación:\n1. Credencial de elector.\n2. CURP.\nREGLAS DE OPERACIÓN, PARA EL EJERCICIO FISCAL\n• La solicitud es turnada a la Dirección de Asistencia Alimentaria y Desarrollo Comunitario para su atención, quien en un plazo no mayor a 60 días hábiles dará respuesta a la misma.\n• La Dirección de Asistencia Alimentaria y Desarrollo Comunitario aplica estudio socioeconómico al solicitante para determinar si será beneficiario del programa.\n• Se realiza la entrega del apoyo de manera personal o en el municipio beneficiado, solicitándole al beneficiario firme acta de donación que acredite la entrega.\n6.3. PROCEDIMIENTO DE ACCESO\nLa operación del Proyecto Paquetes de Insumos y Enseres Agrícolas para la Producción Primaria surge por la necesidad de atender el problema del desempleo y atendiendo la carencia alimentaria, el cual busca garantizar el derecho a la alimentación de la población vulnerable atendiendo a los 81 municipios que conforman nuestro Estado, dando prioridad a los municipios de alta o muy alta marginación, mismo que surge por la demanda ciudadana y / o peticiones que se reciben en las instalaciones del Sistema para el\nDesarrollo Integral de la Familia o directamente a la Presidenta del Sistema Estatal.\nSerán beneficiados con el apoyo del proyecto, los solicitantes que cumplan con las siguientes características y con la disponibilidad presupuestal del programa:\n1. personas adultos mayores y personas vulnerables por ingresos.\n2. Habitar en Municipios o Localidades de alto o muy alto grado de marginación.\nToda persona podrá conocer el estado de su trámite, y su aceptación o no al proyecto, de acuerdo con las reglas de operación vigentes. Las beneficiarias y / o beneficiarios tendrán derecho a ser tratado con\n• Recibir la información necesaria de manera clara y oportuna para participar en el programa.\n• Un trato digno y respetuoso oportuno con calidad y equitativo sin discriminación alguna.\n• Reserva y privacidad de su información personal.\nUna vez aceptados los beneficiarios y/o beneficiarias pasaran a formar parte del Padrón único de beneficiarios, el cual será de carácter público, siendo reservados sus datos personales, de acuerdo con la tramites y llenados de formatos son gratuitos.\n6.4. REQUISITOS DE PERMANENCIA, CAUSALES DE BAJA O SUSPENSIÓN TEMPORAL.\nREGLAS DE OPERACIÓN, PARA EL EJERCICIO FISCAL\nVisita de seguimiento a los beneficiarios, con la finalidad de constatar la situación socioeconómica y seguimiento a las necesidades prioritarias, la población sujeta de atención deberá cumplir con:\n• Dar cumplimiento a las Reglas de Operación del Proyecto.\n• Utilizar los apoyos otorgados de manera adecuada y para los fines que fueron autorizados, evitando cualquier uso distinto de los mismos. Los cuales en ningún caso podrán emplearse para propósitos de proselitismo político, religioso o comercial, ni para ningún otro fin distinto al establecido en las\nReglas de operación del proyecto social.\n• Permitir visita de verificación con la finalidad de validar la información proporcionada en sus expedientes correspondientes.\n• Facilitar los trabajos de supervisión, en cualquier momento después de haber recibido el apoyo\nLos beneficiarios y/o beneficiarias del proyecto de Paquetes de Insumos y Enseres Agrícolas para la\nProducción Primaria, que incumplan en la Disposiciones Normativas de estas Reglas de Operación, perderán las prerrogativas que dichas disposiciones establecen.\n6.5. MODOS DE ENTREGA DEL BENEFICIO\nLos apoyos serán distribuidos directamente a los beneficiarios y/o beneficiarias, en puntos sedes en cada\nRegión del Estado, o en su caso, podrán acudir a recoger el apoyo a las oficinas de la Dirección de\nAsistencia Alimentaria y Desarrollo Comunitario. El proyecto Paquetes de Insumos y Enseres Agrícolas para la Producción Primaria contempla las herramientas necesarias para desempeñar un autoempleo y mejorar la economía familiar y comunitaria.\n7. PROCEDIMIENTOS DE INSTRUMENTACIÓN\n7.1. OPERACIÓN\nEl Sistema Estatal DIF tendrá las siguientes responsabilidades:\na) Gestionar ante las instancias de Gobierno Federales y Estatales, los recursos financieros, para llevar a cabo la adquisición de los materiales, insumos y productos necesarios en la operatividad de los programas y proyectos.\nb) Dar a conocer al Sistema Municipal DIF, las Reglas de Operación del proyecto paquetes de insumos y enseres agrícolas para la producción primaria, vigentes.\nc) Proporcionar al Sistema Municipal DIF, de forma calendarizada los suministros de productos de los\nProgramas.\nd) Vigilar y verificar que los proyectos sean otorgados directamente a los beneficiarios.\ne) Proporcionará almacenes regionales, para guarda, custodia de los productos que integran los proyectos; que contaran con personal capacitado para su manejo y distribución.\nREGLAS DE OPERACIÓN, PARA EL EJERCICIO FISCAL\nf) Actualizar y profesionalizar los conocimientos del personal operativo del Sistema Estatal DIF y del\nSistema Municipal DIF, a través de capacitaciones a fin de contar con las herramientas básicas para la operatividad de los programas.\ng) Recepcionar de los Sistema Municipal DIF la información requerida para comprobación de los programas con base a las Reglas de Operación vigentes.\nh) Procesará la información a que se refiere el punto anterior y remitirla de acuerdo al calendario de entregas, a fin de comprobar los recursos canalizados al municipio.\ni) Elaborar a inicio de cada ejercicio fiscal, el Proyecto de los Programas y documentos que contemplarán la aplicación y operatividad de los proyectos con los importes correspondientes.\nj) Proporcionar cursos de capacitación al personal de Sistema Municipal DIF, relativos a la operatividad de los programas y/o proyectos; así como asesoramiento en la elaboración de propuestas de proyectos.\nSerán obligaciones del Sistema Municipal DIF las siguientes: a. El Sistema Municipal DIF se obliga a cumplir con la implementación de los Proyectos productivos que se tienen establecidos en los Lineamientos de la subdirección de desarrollo comunitario y en las reglas de operación que regula el proyecto; salvo la pena de incurrir en responsabilidades administrativas. b. Determinará de manera conjunta la población potencial de su municipio tomando en consideración el tipo de beneficiario de todos los programas y/o proyectos a solicitar, con esta información y en coordinación con el Sistema Estatal DIF, atenderá a la población que se encuentre en situación de vulnerabilidad de localidades de alta y muy alta marginación. c. Integrará y enviara los expedientes así como los padrones físicos de los beneficiarios de los\nProgramas solicitados a la Subdirección de Desarrollo Comunitario, de igual forma informará a los beneficiarios que los datos personales recabados serán protegidos en términos de los principios de protección de datos personales contenidos en la ley de la materia y demás normativas aplicables. d. Integrará los padrones de los beneficiarios con sus respectivos expedientes de los programas objeto de estas Reglas. Remitiendo al Sistema Estatal DIF el padrón físico, digital y expedientes correspondiente a la comprobación de los programas. e. Designar personal del Sistema Municipal DIF que realice las funciones de seguimiento y supervisión de los Programas. f. Participar en acciones de apoyo logístico para la distribución de los programas. g. Es competencia del Sistema Municipal DIF, trasladar los materiales que corresponden a los programas, a las comunidades beneficiadas, en una unidad vehicular. Será responsabilidad del municipio el resguardo y el buen uso de los materiales que se recepcionen, en el entendido que, de existir algún desvío de los mismos, el Sistema Estatal DIF cancelará inmediatamente el suministro del programa e iniciará un procedimiento ante la contraloría interna del sistema estatal, para determinar las sanciones a que sean acreedores.\nPara garantizar la atención completa del beneficiario, se realizan las acciones:\nREGLAS DE OPERACIÓN, PARA EL EJERCICIO FISCAL\n• Adquisición de los materiales y que cumplan con las Especificaciones Técnicas de Calidad.\n• Asegurar el correcto almacenamiento y distribución de los materiales, hasta su entrega al beneficiario.\n• Focalizar los beneficiarios y/o beneficiarias de los Programas y/o proyectos con base a los indicadores socioeconómicos.\n• Coordinar la entrega de apoyos a la población beneficiada con los Sistemas Municipales DIF, a través de convenios de colaboración y conforme a lo establecido en las Reglas de Operación.\n• Promover la participación social a través de los Sistema Municipal DIF en la formación de comités entre la población beneficiaria, para la recepción, entrega y vigilancia de los apoyos.\n• Promover la formación y operación de grupos de contraloría social para el seguimiento del programa.\n• Fortalecer la operación de los programas y/o proyectos, promoviendo la inclusión general de la sociedad.\nLos datos de los beneficiarios, asi como la información generada y administrada se regirán por la Ley\nNúmero 207 de Transparencia y Acceso a la Información Pública del Estado de Guerrero.\nLos apoyos de Paquetes de Insumos y Enseres Agrícolas para la Producción Primaria, contempla las herramientas necesarias para desempeñar un autoempleo y mejorar la economía familiar y comunitaria mediante otorgamiento de:\n✓ 1 pico con cabo\n✓ 1 pala cuadrada\n✓ 1 machete recto\n✓ 1 machete de garabato grande\n✓ 1 bomba aspersora de 20 litros\n✓ 1 azadón angosto con cabo\n✓ 1 barreta de 1.5 mts.\n✓ 1 rastrillo metálico\n✓ 1 pala cóncava\n✓ 1 bieldo metálico\n✓ 1 carretilla\n✓ 1 martillo grande\n✓ 1 motobomba, de 6 hp. De gasolina, Para agua, con adaptadores con salida para 2\" con accesorios, pichancha, abrazaderas y 10 metros de manguera de succión\n✓ 1 lt. de insecticida agrícola\n✓ 1 lt. de fungicida agrícola\n✓ 1 lt. de herbicida agrícola\n✓ 1 rollo de manguera negra de 100 mts.\n✓ 1 cabahoyos de 48\"\nREGLAS DE OPERACIÓN, PARA EL EJERCICIO FISCAL\n✓ 1 hacha grande con cabo\n✓ 1 motosierra de 14\"\nComo objetivo a corto plazo, se dará continuidad a la entrega de cada apoyo solicitado, cubriendo cada uno los requisitos solicitados en las presentes reglas de operación, mismo que será otorgado en su municipio de residencia o en su caso en el almacén general del Sistema Estatal a la población vulnerable.\n7.2. GASTOS DE OPERACIÓN\nEl presupuesto asignado a este programa, es a través del Fondo de Aportaciones Múltiples, no contempla\nGastos de Operación.\n8. TRANSPARENCIA\n8.1. DIFUSIÓN\nLa Dirección de Asistencia Alimentaria y Desarrollo Comunitario, quien difundirá a través de diferentes medios de comunicación; trípticos, periódico, redes sociales en las cuales se dará a conocer la información relacionada con las características del proyecto Paquetes de Insumos y Enseres Agrícolas para la\nProducción Primaria.\nAsí mismo se dará amplia difusión al proyecto a nivel Estatal y se promoverán similares acciones por parte de las autoridades locales; la información del proyecto se dará a conocer en la página de internet https://www.guerrero.gob.mx del Gobierno del Estado, desagregada por municipio, barrio o zona urbanomarginada, proyecto y nombre del beneficiario y/o beneficiaria; las copias de los expedientes de los beneficiarios y / o beneficiarias estarán disponibles oportunamente para su consulta en las oficinas del\nSistema ubicadas en Boulevard Rene Juárez Cisneros, Colonia Ciudad de los Servicios y en Av. Gabriel\nLeyva s/n esq. Ruffo Figueroa, Col. Burócratas, C.P. 39090, Chilpancingo, Guerrero; por otra parte, la papelería, documentación oficial, así como la publicidad y promoción de los Programas, deberán incluir la leyenda descrita en el apartado de \"Blindaje Electoral\".\nLa información de montos y beneficiarios deberá ser publicada en los términos de la Ley No. 207 de\nUna vez autorizadas estas Reglas de Operación, por las instancias correspondientes, estarán disponibles para su consulta en las Oficinas de la Dirección de Asistencia Alimentaria y Desarrollo Comunitario, y El responsable directo de la ejecución será la Dirección de Asistencia Alimentaria y Desarrollo Comunitario, a través de la Subdirección de Desarrollo Comunitario, ubicada Av. Gabriel Leyva s/n esq. Ruffo Figueroa, Col. Burócratas, C.P. 39090, Chilpancingo, Guerrero., a los teléfonos (01747) 47 2 55 95, (01747) 47 2 56\n00, (01747) 47 2 56 72 ext. 1155. Así mismo al correo electrónico: subdescomdif@prodigy.net.mx Para información sobre el programa.\nREGLAS DE OPERACIÓN, PARA EL EJERCICIO FISCAL y beneficiarios y/o beneficiarias, será publicada en los términos de la Ley No. 207 de Transparencia y\nAcceso a la Información Pública del Estado de Guerrero.\nEstas Reglas de Operación, además de su publicación en el Periódico Oficial del Gobierno del Estado, estarán disponibles para su consulta en las Oficinas de la Dirección de Asistencia Alimentaria y Desarrollo\nComunitario, así como en la página electrónica del Sistema para el Desarrollo Integral de la Familia http://www.dif.guerrero.gob.mx\n8.2. BLINDAJE ELECTORAL\nLa operación y ejecución de los recursos estatales destinados al Proyecto, deberán observar y atender las medidas que emita la Secretaría de Contraloría y Transparencia Gubernamental, para coadyuvar a que éstos, no sean utilizados con fines políticos, por lo que, la papelería, documentación oficial, así como la publicidad y promoción del Proyecto deberán incluir la siguiente leyenda:\n\"Este Programa es público, ajeno a cualquier partido político. Queda prohibido el uso para fines distintos a los establecidos en el proyecto\"\n8.3. SUPERVISIÓN Y CONTROL\nEl Dirección de Asistencia Alimentaria y Desarrollo Comunitario deberá reportar mensualmente a la\nDirección de Planeación del DIF Guerrero, las acciones ejercidas y los resultados obtenidos, quien a su vez reportará trimestralmente a la Secretaria de Finanzas y Administración, Secretaria de Planeación y\nDesarrollo Regional y la Secretaria de Contraloría y Transparencia Gubernamental, informes sobre el presupuesto ejercido establecidos por el Consejo Nacional de Armonización Contable (CONAC) dichos trimestre.\nLos padrones de los beneficiarios serán requisitados por los Sistemas Municipales DIF, remitiendo para su los Padrones de Beneficiarios de los 81 municipios de la Entidad mismo que serán remitidos a las instancias o dependencias operadoras.\n8.4. MECANISMOS DE EVALUACIÓN E INDICADORES\n8.4.1 EVALUACIÓN\nREGLAS DE OPERACIÓN, PARA EL EJERCICIO FISCAL correspondientes.\n8.4.2 INDICADORES\nMatriz de Indicadores de Resultados\nDetalle de la Matriz 2019\nRamo:\n5 - Sector Paraestatal\nUnidad Responsable:\nP-46 -O.P.D. Sistema para el Desarrollo Integral de la Familia\nClave y Modalidad del Pp:\nS- Sujetos a Reglas de Operación\nE- Prestación de Servicios Públicos\nDenominación del Pp: S01\nE01\nClasificacion Funcional:\nFinalidad: 2. Desarrollo Social\nFunción: 2.3. SALUD\n2.4. RECREACIÓN, CULTURA Y OTRAS MANIFESTACIONES SOCIALES\n2.6. PROTECCIÓN SOCIAL\nSubfunción: 2.3.2 Prestación de Servicios de 2.6.5 Alimentación y Nutrición\nSalud a la Persona 2.6.6 Apoyo Social para la Vivienda\n2.4.2 Cultura 2.6.7 Indígenas\n2.6.1 Enfermedad e Incapacidad 2.6.8 Otros Grupos Vulnerables\n2.6.3 Edad Avanzada 2.6.9 Otros de Seguridad Social y\n2.6.4 Familia e Hijos Desempleo Asistencia Social\nResumen narrativo Orden Supuestos\nContribuir a mejorar el nivel de vida de los Se fortalecen la cobertura grupos vulnerables mediante acciones de Padrón de beneficiarios poblacional de los programas\nAsistencia Social sociales\nUnidad Frecuencia Línea\nTipo de Meta Medios de\nIndicador Método de Cálculo de de Base\nIndicador 2018 Verificación\nMedida Medición 2017\nPorcentaje de (Población población atendida/Total de Padrón de\nPersonas Anual Estratégico 70% 90% vulnerable población beneficiarios atendida vulnerable)*100\nPropósito\nResumen narrativo Orden Supuestos\nREGLAS DE OPERACIÓN, PARA EL EJERCICIO FISCAL\nFortalecer las acciones de desarrollo Ampliación de cobertura poblacional Las obras y/o acciones de vida\nUnidad Frecuencia Línea\nTipo de Meta Medios de\nIndicador Método de Cálculo de de Base\nIndicador 2018 Verificación\nMedida Medición 2017\n(Programas\nPorcentaje de implementados en\nOficios de\nProgramas 2017 / Programas Programas Anual Estratégico 70% 90% autorización implementados implementados en\n2018)* 100\nComponente\nResumen narrativo Orden Supuestos\nFortalecer el nivel nutricional de la Contribuir a mejorar la dieta de población con mayor índice de las niñas y niños de nivel marginación, poniendo énfasis en los primaria y prescolar, así como\nAsistencia Social grupos de alto riesgo, a fin de mejorar la implementar Proyectos calidad en la dieta y apoyar el gasto Productivos, de Economía y familiar. Traspatio\nUnidad Frecuencia Línea\nTipo de Meta Medios de\nIndicador Método de Cálculo de de Base\nIndicador 2018 Verificación\nMedida Medición 2017\n(Número de despensasProporción de dotaciones distribuidas despensasen el periodo de dotaciones acuerdo a los criterios Avance Físicoentregadas que Porcentaje Trimestral Estratégico 0% 100% de calidad nutricia de Financiero cumplen con los los Lineamientos de la criterios de calidad\nEIASA / Número total nutricia de apoyos entregados en el periodo) * 100\nPorcentaje de\n(Total de apoyos apoyos de otorgados / total de Avance FísicoDesarrollo Porcentaje Semestral Estratégico 0% 100% apoyos programados) Financiero\nComunitario\n* 100 otorgados\nResumen narrativo Orden Supuestos\nElevar la calidad de vida de las familias y comunidades marginadas, a través de su Beneficiar a los grupos asistencia social y apoyo jurídico, que les físico y mental permita alcanzar su desarrollo integral\nUnidad Frecuencia Línea\nTipo de Meta Medios de\nIndicador Método de Cálculo de de Base\nIndicador 2018 Verificación\nMedida Medición 2017\nREGLAS DE OPERACIÓN, PARA EL EJERCICIO FISCAL\n(Total de apoyos\nPorcentaje de otorgados / total de Avance Físicoapoyos Sociales Porcentaje Semestral Estratégico 0% 100% apoyos programados) Financiero otorgados\n* 100\nResumen narrativo Orden Supuestos\nAtender y apoyar a las personas con Los servicios otorgados discapacidad, mediante servicios contribuyen a la rehabilitación\nDescendente asistenciales y de rehabilitación, para de las personas con lograr su incorporación al entorno social discapacidad\nUnidad Frecuencia Línea\nTipo de Meta Medios de\nIndicador Método de Cálculo de de Base\nIndicador 2018 Verificación\nMedida Medición 2017\n(Total de servicios\nPorcentaje de otorgados / total de Avance FísicoServicios Porcentaje Semestral Estratégico 0% 100% servicios Financiero otorgados programados) * 100\nResumen narrativo Orden Supuestos\nSe recibe en tiempo las\nAdministración interna y servicios\nAscendente comprobaciones por parte de generales del DIF los ejecutores del Gasto.\nUnidad Frecuencia Línea\nTipo de Meta Medios de\nIndicador Método de Cálculo de de Base\nIndicador 2018 Verificación\nMedida Medición 2017\n(Numero de\nPorcentaje de comprobaciones comprobaciones entregadas en Avance FísicoPorcentaje Semestral Estratégico 0% 100% entregadas a tiempo/Total de Financiero tiempo. comprobaciones realizadas)*100\nActividades\nResumen narrativo Orden Supuestos\nDeterminar el nivel de atención\nBeneficiar a los grupos alimentaria a población en condiciones emergencia afectada por Desastres físico y mental\nNaturales.\nUnidad Frecuencia Línea\nTipo de Meta Medios de\nIndicador Método de Cálculo de de Base\nIndicador 2018 Verificación\nMedida Medición 2017\nREGLAS DE OPERACIÓN, PARA EL EJERCICIO FISCAL\nAtención Alimentaria en Mpios. En\nEmergencia = Mpios. con Declaracion de\nAcceso Alimentario Avance Físicoemergencia atendidos Personas Anual Estratégico 100 100% en Riesgo Financiero\n/ Total de Mpios. con\nDeclaratoria de emergencia en la\nEntidad.\nResumen narrativo Orden Supuestos\nDeterminar el porcentaje de desnutrición Los menores beneficiados, en los menores beneficiados con insumos Descendente disponen de una alimentación alimentarios. con calidad nutricia\nUnidad Frecuencia Línea\nTipo de Meta Medios de\nIndicador Método de Cálculo de de Base\nIndicador 2018 Verificación\nMedida Medición 2017\n(Menores beneficiados que tienen algún grado de\nDesnutrición Avance FísicoDesnutrición / Total de Menores Anual Estratégico 22% 20%\nInfantil Financiero\nMenores beneficiados con insumos alimentarios) * 100\nResumen narrativo Orden Supuestos\nDeterminar el porcentaje de obesidad en\nDisminuyen los índices de los menores beneficiados con insumos Descendente obesidad infantil alimentarios.\nUnidad Frecuencia Línea\nTipo de Meta Medios de\nIndicador Método de Cálculo de de Base\nIndicador 2018 Verificación\nMedida Medición 2017\nPorcentaje de\nObesidad en Menores\n= Menores\nBeneficiados que\nAvance FísicoObesidad Infantil tienen algún grado de Menores Anual Estratégico 15% 11%\nFinanciero\nObesidad / Total de\nMenores Beneficiados con insumos\nAlimenticios\nResumen narrativo Orden Supuestos\nDeterminar el porcentaje de atención de alimentarios.\nREGLAS DE OPERACIÓN, PARA EL EJERCICIO FISCAL\nUnidad Frecuencia Línea\nTipo de Meta Medios de\nIndicador Método de Cálculo de de Base\nIndicador 2018 Verificación\nMedida Medición 2017\nPorcentaje de\nObesidad en Menores\n= Menores\nAcceso Alimentario Beneficiados que\nAvance Físicoen Menores no tienen algún grado de Menores Anual Estratégico 100% 100%\nFinanciero\nEscolarizados Obesidad / Total de\nMenores Beneficiados con insumos\nAlimenticios\nResumen narrativo Orden Supuestos\nPermite determinar el nivel de atención a municipios con alto índice de carencia La población vulnerable, alimentaria, a fin de propiciar el Descendente dispone de una alimentación mejoramiento alimentario de los grupos con calidad nutricia con mayor vulnerabilidad en la entidad.\nUnidad Frecuencia Línea\nTipo de Meta Medios de\nIndicador Método de Cálculo de de Base\nIndicador 2018 Verificación\nMedida Medición 2017\nMpios con Alto Indice de Carencia\nAlimentaria No\nAcceso a la Avance FísicoAtendidos = Mpios. Municipio Anual Estratégico 0 100%\nAlimentación Financiero con A.I.C.A. no atendidos / Total de\nMpios. en la Entidad.\nResumen narrativo Orden Supuestos\nLa población beneficiada recibe\nConocer la cantidad de personas apoyos para fortalecer la\nAscendente beneficiadas con los Proyectos economía, alimentación y de\nProductivos de Economía y Traspatio sus familias\nUnidad Frecuencia Línea\nTipo de Meta Medios de\nIndicador Método de Cálculo de de Base\nIndicador 2018 Verificación\nMedida Medición 2017\nÍndice de avance (beneficiarios en la entrega de atendidos / Avance FísicoPersonas Anual Estratégico 80% 100%\nProyectos Beneficiarios Financiero\nProductivos programados) * 100\nResumen narrativo Orden Supuestos\nREGLAS DE OPERACIÓN, PARA EL EJERCICIO FISCAL\nPoblación que requiere algún tipo de\nLa población vulnerable tiene acceso a los servicios de salud medico\nUnidad Frecuencia Línea\nTipo de Meta Medios de\nIndicador Método de Cálculo de de Base\nIndicador 2018 Verificación\nMedida Medición 2017\nPoblación sin acceso\nPoblación sin a los servicios de acceso a los Avance Físicosalud = Población Personas Anual Estratégico 80% 100% servicios de salud Financiero atendida / Población\n(PSASS) programada\nResumen narrativo Orden Supuestos\nConocer los apoyos entregados en la\nSe entregan todos los apoyos a temporada invernal (Suéteres y Ascendente la población vulnerable\nCobertores)\nUnidad Frecuencia Línea\nTipo de Meta Medios de\nIndicador Método de Cálculo de de Base\nIndicador 2018 Verificación\nMedida Medición 2017\nEntrega de Apoyos =\nApoyos\nTotal de Apoyos Padrón de entregados en la Apoyos Anual Estratégico 0% 100%\nAtendidos / Total de Beneficiarios temporada invernal\nApoyos Programados\nResumen narrativo Orden Supuestos\nLos apoyos entregados, Personas Beneficiadas con Apoyos Ascendente contribuyen a subsanar las\nEconómicos y en Especie necesidades de la sociedad.\nUnidad Frecuencia Línea\nTipo de Meta Medios de\nIndicador Método de Cálculo de de Base\nIndicador 2018 Verificación\nMedida Medición 2017\n(Total de apoyos\nPorcentaje de otorgados / total de Avance Físicoapoyos Sociales Porcentaje Semestral Estratégico 0% 100% apoyos programados) Financiero otorgados\n* 100\n8.5. AUDITORIA\nEl ejercicio del recurso y la operatividad del Proyecto, están sujetos a las disposiciones estatales aplicables y podrá ser auditado por la Secretaría de Contraloría y Transparencia Gubernamental, así por la Auditoría\nSuperior del Estado y Auditoria Superior de la Federación, conforme a la legislación vigente y en el ámbito de sus respectivas competencias.\nREGLAS DE OPERACIÓN, PARA EL EJERCICIO FISCAL\nEl Sistema DIF Guerrero dará todas las facilidades a dichas instancias para realizar, en el momento en que lo juzguen pertinente, las auditorías que consideren necesarias; así como el seguimiento y la solventación a las observaciones planteadas por los órganos de control.\n8.6. RECURSOS NO DEVENGADOS\nEl DIF Guerrero deberá reintegrar a la Dirección General de Tesorería de la Secretaría de Finanzas y\nAdministración del Gobierno del Estado los recursos que no se hubiesen destinado a los fines autorizados y aquellos que por cualquier motivo no estuviesen devengados al 31 de diciembre del Ejercicio fiscal correspondiente.\n8.7. CONTRALORÍA SOCIAL\nCon la finalidad de incrementar la participación ciudadana, se crearán Comités de Contraloría Social, como un órgano ciudadano de control, vigilancia y evaluación de las actividades del Proyecto, conformados por los beneficiarios y beneficiarias, los sectores sociales, y los representantes de la localidad, quienes de manera específica supervisarán la gestión gubernamental, y que los manejos de los recursos públicos se realicen en términos de transparencia, eficacia, legalidad y honradez.\nLos objetivos específicos de este Órgano de Contraloría Social son:\n• Hacer más transparentes las decisiones y la ejecución de los recursos.\n• Incrementar la participación ciudadana.\n• Fomentar la organización social.\n• Inhibir los actos de corrupción y de cooptación social, política y electoral.\n• Incrementar la eficiencia de los recursos públicos.\n• Fortalecer la cultura de la legalidad.\n• Mejorar la rendición de cuentas.\n• Perfeccionar la democracia e incorporar la evaluación ciudadana.\nLas funciones de los Comités de Contraloría Social son:\na) Integración: Se conforman con la representación de la comunidad beneficiada por el Programa, y fungirán como interlocutores con el DIF Guerrero, en el ejercicio de la contraloría social.\nEl vocal será, el responsable de hacer llegar las quejas o denuncias recibidas al DIF Guerrero, quien dará respuesta en un plazo no mayor de 15 días a partir de la fecha de recepción de la queja o denuncia.\nb) Capacitación y asesoría: Para impulsar la realización de las actividades de Contraloría Social se brindará capacitación y asesoría, a los servidores y servidoras públicas que intervienen en la operación del\nREGLAS DE OPERACIÓN, PARA EL EJERCICIO FISCAL\nPrograma y / o Proyecto, así como a los integrantes de los Comités Locales, para que estos realicen adecuadamente sus actividades de seguimiento y vigilancia.\nc) Seguimiento: Se deberá integrar un Programa de Trabajo a través del cual se debe incluir la descripción de las actividades, responsables, metas y calendarización de las actividades para su cumplimiento.\nEl Director General o el personal que designe el DIF Guerrero, serán los encargados de conformar los\nComités de Contraloría Social, asimismo darán acompañamiento durante las actividades de control, seguimiento y vigilancia del proyecto.\nEl Comité de Contraloría Social debe estar constituido por un Presidente, un Secretario y un Vocal mínimamente, electos de entre la población beneficiada en donde se va a realizar la entrega del proyecto, y tendrá que ser vigilado por un solo Comité, el cual deberá controlar, vigilar y dar seguimiento al proyecto a través de los formatos que integran el expediente comunitario, integrado por:\n1. Acta de Conformación del Comité de Contraloría Social.\n2. Reunión con beneficiarios y beneficiaras.\n3. Ficha Informativa del Programa.\n4. Cédula de Vigilancia del Programa.\n5. Actividades de Difusión y Capacitación.\n6. Quejas, Denuncias o Reconocimientos.\n7. Informe Anual.\n8.8. FORMAS DE PARTICIPACIÓN SOCIAL\nGuerrero, se establece que la sociedad podrá participar activamente en la Planeación, Programación, Implementación y Evaluación de los Programas Sociales de Desarrollo Social, por ello los beneficiarios y beneficiarias participaran en la etapa de la implementación y podrán supervisar la gestión gubernamental, que el manejo de los recursos públicos se realicen en términos de transparencia, eficacia, legalidad y honradez del Programa de acuerdo en lo estipulado en estas Reglas de Operación. participa Participación\nBeneficiarios/ Implementación Comités de Contraloría Seguimiento\nBeneficiarias\n8.9. PROCEDIMIENTO DE QUEJA O INCONFORMIDAD CIUDADANA\nLos beneficiarios y/o beneficiarias pueden presentar quejas y denuncias ante las instancias correspondientes sobre cualquier hecho, acto u omisión que produzca o pueda producir daños al ejercicio\nREGLAS DE OPERACIÓN, PARA EL EJERCICIO FISCAL normatividad aplicable. a. En el Sistema DIF Guerrero\nCorreo electrónico: buzon.dif@guerrero.gob.mx\nDomicilio: Centro de Rehabilitación Integral Guerrero.\nBoulevard Lic. René Juárez Cisneros S/N, Col. Ciudad de los Servicios. Chilpancingo, Guerrero. C.P.\n39095. b. En la Secretaría de Contraloría y Transparencia Gubernamental\nTeléfonos: (474) 47 1 97 41\nCorreo electrónico: contraloria@guerrero.gob.mx\nDomicilio: Palacio de Gobierno Primer Piso Edificio Norte, Blvd. R. Juárez Cisneros 62 Col. Ciudad de los Servicios. Chilpancingo, Guerrero. C.P. 39075.\nLas quejas y denuncias de la ciudadanía derivadas de alguna irregularidad en la operación del Programa, podrán presentarse por escrito, por comparecencia del beneficiario (a), por correo electrónico o vía telefónica y deberá proporcionar los siguientes datos:\n• Nombre del servidor público.\n• Área de adscripción.\n• Objeto de la denuncia.\n• Nombre y domicilio del quejoso.\n• Identificación oficial.\n8.10. MECANISMOS DE EXIGIBILIDAD\nLos casos en los que se podrán exigir los derechos por incumplimiento o por violación de los mismos pueden ocurrir en al menos los siguientes casos:\n✓ Cuando una persona solicitante cumpla con los requisitos y criterios de inclusión para acceder a determinado derecho.\n✓ Cuando la persona solicitante exija que se cumpla con dicho derecho de manera integral en tiempo y forma.\n✓ Cuando no se pueda satisfacer toda la demanda de incorporación al programa por restricción presupuestal. las denuncias de violación e incumplimiento de derechos en materia de Desarrollo Social.\nREGLAS DE OPERACIÓN, PARA EL EJERCICIO FISCAL\n8.11. ACTA DE ENTREGA RECEPCIÓN\nLa instancia ejecutora conformará y resguardará el expediente de los beneficiarios y/o beneficiarias, incluyendo su acta de donación correspondiente, dada la naturaleza del apoyo otorgado, se realiza en apego al control del gasto público.\n9. CRITERIOS DE SELECCIÓN Y ELEGIBILIDAD\n9.1. MÉTODO DE SELECCIÓN DE BENEFICIARIOS (AS)\nSerán beneficiados con el Programa, los solicitantes que cumplan con las siguientes características:\n• Familias en estado de vulnerabilidad, que presenten alguna discapacidad y no puedan tener un empleo formal.\n• Habitar en los 2 Municipios o Localidades de muy alto grado de marginación.\n• Habitar preferentemente en Municipios o Localidades de alto o muy alto grado de marginación.\n10. MECÁNICA DE OPERACIÓN\n10.1. INSTANCIA EJECUTORA\nLa Instancia Ejecutora será el sistema para el Desarrollo Integral de la Familia a través de la Dirección de\nAsistencia Alimentaria y Desarrollo Comunitario, quien deberá operar con apego a la programación, presupuestación, calendario de ejecución, ejercicio y control del gasto público.\n10.2. INSTANCIA ADMINISTRATIVA Y/O NORMATIVAS\nLa Instancia Administrativa y Normativa será la Dirección General del Sistema DIF Guerrero y la Dirección\nGubernamental y la Auditoría Superior del Estado en el ámbito de sus respectivas competencias, quienes darán seguimiento a los objetivos y metas del Programa.\n10.3. DELIMITACIÓN DE ATRIBUCIONES programas y acciones no se contrapongan, afecten o presenten duplicidades con otros programas o acciones del gobierno estatal; la coordinación institucional y vinculación de acciones busca potenciar el impacto de los recursos, fortalecer la cobertura de las acciones, detonar la complementariedad y reducir gastos administrativos.\nREGLAS DE OPERACIÓN, PARA EL EJERCICIO FISCAL\n11. DERECHOS, OBLIGACIONES Y SANCIONES DE LOS BENEFICIARIOS DE PROGRAMAS\nSOCIALES.\n11.1. DERECHOS\n• Recibir trato digno, respetuoso y equitativo sin discriminación alguna, por el personal de las distintas áreas que participen dentro del proyecto.\n• Reserva y privacidad de la información personal.\n• Acceder a la información necesaria del programa, sus Reglas de Operación, recursos y cobertura.\n• Solicitar y recibir información sobre el estado que guarda su trámite.\n• Recibir los servicios y prestación del proyecto conforme a las Reglas de Operación, salvo que le sea suspendido el apoyo por alguna razón justificable.\n11.2. OBLIGACIONES\n• Proporcionar la información socioeconómica bajo protesta de decir verdad que les sea requerida por el DIF Guerrero, en los términos que establezca la normatividad correspondiente.\n• Utilizar los apoyos para los fines con que fueron autorizados evitando cualquier uso distinto de la misma.\n• Facilitar los trabajos de verificación, en cualquier momento después de otorgado el apoyo.\n11.3. SANCIONES acceder a los beneficios que a través de estos se otorgan, perderán las prerrogativas, establecidas en los numerales 6.2 y 6.3 que dichas disposiciones establezcan.\n12. INTERPRETACIÓN\nLa interpretación de las presentes Reglas de Operación para efectos administrativos, estarán a cargo del\nDIF Guerrero, así como de la Secretaría de Contraloría y Transparencia Gubernamental, en el ámbito de sus respectivas competencias.\nREGLAS DE OPERACIÓN, PARA EL EJERCICIO FISCAL\nTRANSITORIOS\nPrimero: El presente acuerdo entrará en vigor al día siguiente de su publicación en el Periódico Oficial del\nSegundo: Las Reglas de Operación del Proyecto Paquetes de Insumos y Enseres Agrícolas para la\nProducción Primaria, para el Ejercicio Fiscal 2019, se publican en su totalidad para mejor entendimiento.\nTercero: Quedan abrogadas las Reglas de Operación del Proyecto Paquetes de Insumos y Enseres\nAgrícolas para la Producción Primaria, Publicadas en el periódico Oficial número 28, alcance VIII del\nGobierno del Estado de Guerrero, de fecha 06 de abril de 2018.\nDado en la Oficina del Titular del Sistema para el Desarrollo Integral de la Familia, ubicada en las\nInstalaciones del Centro de Rehabilitación Guerrero, Boulevard René Juárez Cisneros S/N, Ciudad de los\nServicios, No. 62, Col. Recursos Hidráulicos, en la Ciudad de Chilpancingo de los Bravo, Capital del Estado de Guerrero, a los 25 días del mes de enero de dos mil diecinueve.\nESTADO DE GUERRERO.\nLic. José Francisco Solís Solís.\nRúbrica.\nANEXOS\nCada uno de los formatos deberá llevar la leyenda de Blindaje Electoral: \"Este Programa es público, ajeno a cualquier partido político. Queda prohibido el uso para fines distintos a los establecidos en el programa\" Nota: los formatos adjuntos podrán sufrir cambios de acuerdo a los lineamientos federales de los programas establecidos por él Fondo de Aportaciones Múltiples (Asistencia Social).\nREGLAS DE OPERACIÓN, PARA EL EJERCICIO FISCAL\nREGLAS DE OPERACIÓN, PARA EL EJERCICIO FISCAL\nREGLAS DE OPERACIÓN, PARA EL EJERCICIO FISCAL",
  "ordenamiento": "PROGRAMA",
  "jurisdiccion": "GUERRERO",
  "fuente_oficial": "DIARIO OFICIAL DE LA FEDERACION",
  "Fecha de Publicación": "28 DE AGOSTO DE 2020",
  "ULTIMA REFORMA PUBLICADA": null,
  "status": "VIGENTE",
  "es_escaneado": false,
  "tiene_tablas": true,
  "materia": [
    "general"
  ]
}