{
  "titulo": "Acuerdo Mediante el Cual Se Emiten las Reglas de Operación del Programa 4. Defensa y Asesoría Jurídi",
  "Contenido": "AFROMEXICANO DE LA SECRETARÍA DE ASUNTOS\nINDÍGENAS Y COMUNIDADES AFROMEXICANAS,\nPARA EL EJERCICIO 2016\nÍndice\n1. Introducción....................................................................................................................................... 5\n2. Objetivo.............................................................................................................................................. 6\n2.1 General............................................................................................................................................ 6\n2.2 Específicos...................................................................................................................................... 6\n2.3. Población Objetivo.......................................................................................................................... 6\n3. Misión................................................................................................................................................ 7\n4. Visión................................................................................................................................................. 7\n5. Reglas de operatividad...................................................................................................................... 7\n5. 1 Lineamientos generales.................................................................................................................. 7\n5.1.1. Fundamento legal........................................................................................................................ 8\n5.1.2. Participantes................................................................................................................................ 8\n5.1.3. Patrimonio del programa.............................................................................................................. 9\n5.1.4 Tipos de apoyo............................................................................................................................. 9\n6. Información del Programa.................................................................................................................. 10\n6.1. Exposición del programa................................................................................................................. 10\n6.2. Cobertura........................................................................................................................................ 10\n6.3. Modos de entrega del beneficio...................................................................................................... 11\n6.4. Gastos de operación....................................................................................................................... 11\n7. Transparencia.................................................................................................................................... 11\n7. 1 Difusión........................................................................................................................................... 11\nAFROMEXICANO DE LA SECRETARÍA DE ASUNTOS\nINDÍGENAS Y COMUNIDADES AFROMEXICANAS,\nPARA EL EJERCICIO 2016\n7.2. Seguimiento de Avances Físicos y financieros................................................................................ 12\n7.3. Evaluación...................................................................................................................................... 12\n7.4. Auditoría......................................................................................................................................... 12\n7.5. Recursos no devengados................................................................................................................ 12\n7.6. Blindaje electoral............................................................................................................................. 13\n7.7. Contraloría social............................................................................................................................ 13\n7.8. Quejas y denuncias......................................................................................................................... 13\n8. Criterios de selección y elegibilidad................................................................................................... 14\n8.1. Método de selección de beneficiarios............................................................................................. 14\n9. Mecánica de operación...................................................................................................................... 14\n9.1. Instancia ejecutora.......................................................................................................................... 14\n9.2. Instancia administrativa y normativa............................................................................................... 14\n9.3. Delimitación de atribuciones........................................................................................................... 14\n10. Derechos, obligaciones y sanciones de los beneficiarios de programas sociales............................. 14\n10.1. Derechos...................................................................................................................................... 14\n10.2. Obligaciones................................................................................................................................. 14\n10.3. Sanciones..................................................................................................................................... 15\n11. Interpretación................................................................................................................................... 15\nAFROMEXICANO DE LA SECRETARÍA DE ASUNTOS\nINDÍGENAS Y COMUNIDADES AFROMEXICANAS,\nPARA EL EJERCICIO 2016\nAFROMEXICANO, DE LA SECRETARÍA DE ASUNTOS ÍNDIGENAS Y COMUNIDADES AFROMEXICANAS, PARA\nEL EJERCICIO FISCAL 2017, PUBLICADO EN EL PERIODICO OFICIAL DEL GOBIERNO DEL ESTADO DE\nGUERRERO No. 48, DE FECHA 16 DE JUNIO DE 2017.\nTEXTO ORIGINAL.\nAcuerdo publicados en el Periódico Oficial del Gobierno del Estado No. 61 Alcance I, el Viernes\n29 de Julio de 2016.\nACUERDO MEDIANTE EL CUAL SE EMITEN LAS REGLAS DE OPERACIÓN DEL PROGRAMA 4.\nDEFENSA Y ASESORÍA JURÍDICA A PUEBLOS INDÍGENAS Y AFROMEXICANO DE LA SECRETARÍA\nDE ASUNTOS INDÍGENAS Y COMUNIDADES AFROMEXICANAS, PARA EL EJERCICIO 2016.\nLIC. GILBERTO SOLANO ARREAGA, Secretario de Asuntos Indígenas y Comunidades\nAfromexicanas, con fundamento en los Artículos 11, 14 y 16 de la Ley Orgánica de la Administración Pública del Estado de Guerrero número 8, y el artículo 32 de la Ley en referencia por el que se crea la Secretaría de Asuntos Indígenas y Comunidades Afromexicanas, publicado en el Periódico Oficial del Gobierno del\nEstado de Guerrero, número 85, de fecha 23 de Octubre de 2015, y\nCONSIDERANDO\nQue en el Decreto número 170 del Presupuesto de Egresos del Estado de Guerrero, para el\nEjercicio Fiscal 2016, se señala que se ejercitarán los recursos bajo una política de gasto público que permita dar cumplimiento a los seis ejes rectores del Plan Estatal de Desarrollo 2016 - 2021. Las políticas encaminadas a desarrollo social, se orientaron a los sectores desprotegidos del estado y a programas sociales.\nQue dentro de las políticas de Desarrollo Social la Secretaría de Asuntos Indígenas y\nComunidades Afromexicanas, implementará el programa: 4. Defensa y Asesoría Jurídica a Pueblos\nIndígenas y Afromexicano, a fin de contribuir a la mejora de la calidad de vida de cada uno de las y los beneficiarios del programa.\nPor lo anterior expuesto y con fundamento en las disposiciones legales antes citadas, he tenido a bien expedir el siguiente:\nEJERCICIO FISCAL 2016.\nÚnico: se emiten las Reglas de Operación del Programa 4. Defensa y Asesoría Jurídica a\nPueblos Indígenas y Afromexicano, que implementará la Secretaría de Asuntos Indígenas y\nComunidades Afromexicanas, para el Ejercicio Fiscal 2016.\nAFROMEXICANO DE LA SECRETARÍA DE ASUNTOS\nINDÍGENAS Y COMUNIDADES AFROMEXICANAS,\nPARA EL EJERCICIO 2016\nTRANSITORIOS\nPrimero.- El presente acuerdo entrará en vigor al día siguiente de su publicación en el Periódico\nOficial del Gobierno del Estado de Guerrero.\nSegundo.- Quedan abrogadas las Reglas de Operación del Programa 4. Defensa y Asesoría\nJurídica a Pueblos Indígenas y Afromexicano, publicadas en el Periódico Oficial del Estado de Guerrero, numero 70 de fecha 29 de agosto del 2008.\nTercero.- Las Reglas de Operación del Programa de la Secretaría de Asuntos Indígenas y\nComunidades Afromexicanas: 4. Defensa y Asesoría Jurídica a Pueblos Indígenas y Afromexicano, para el Ejercicio Fiscal 2016, se publican en su totalidad para mejor entendimiento.\nDado en la ciudad de Chilpancingo de los Bravo, Guerrero, a los dieciocho días del mes de marzo de dos mil dieciséis.\nEL SECRETARIO DE ASUNTOS INDÍGENAS Y COMUNIDADES AFROMEXICANAS\nLIC. GILBERTO SOLANO ARREAGA.\nRúbrica.\nÍndice\n1. Introducción.\n2. Objetivos.\n2.1. General\n2.2. Especifico\n2.3. Población objetivo\n3. Misión.\n4. Visión.\n5. Reglas de operatividad.\n5.1 Lineamientos generales\n5.1.1. Fundamento legal\n5.1.2 Participantes\n5.1.3. Patrimonio del programa\n5.1.4. Tipos de apoyo\n6. Información del Programa.\n6.1. Exposición del Programa\nAFROMEXICANO DE LA SECRETARÍA DE ASUNTOS\nINDÍGENAS Y COMUNIDADES AFROMEXICANAS,\nPARA EL EJERCICIO 2016\n6.2. Cobertura\n6.3. Modos de entrega del beneficio\n6.4. Gastos de operación\n7. Transparencia.\n7.1. Difusión\n7.2. Seguimiento de avances físicos y financieros\n7.3. Evaluación\n7.4. Auditoria\n7.5. Recursos no devengados\n7.6. Blindaje electoral\n7.7. Contraloría social\n7.8. Quejas y denuncias\n8. Criterios de selección y elegibilidad.\n8.1. Método de selección de beneficiarios\n9. Mecánica de operación.\n9.1. Instancia ejecutora\n9.2. Instancia administrativa y normativa\n9.3. Delimitación de atribuciones\n10. Derechos, obligaciones y sanciones de los beneficiarios de programas sociales.\n10.1. Derechos\n10.2. Obligaciones\n10.3. Sanciones\n11. Interpretación.\n1. Introducción\nEl reconocimiento pleno de los derechos e inclusión social de los pueblos indígenas y afromexicano, continúan siendo una asignatura pendiente para el Estado mexicano, ya que el cumplimiento de la norma constitucional obliga a impulsar y consolidar dicho reconocimiento, lo que implica también hacer efectivos sus derechos culturales y sus derechos sociales a la alimentación, la salud, la educación, la vivienda, el trabajo, el acceso pleno a la jurisdicción del Estado y al desarrollo pleno de sus capacidades.\nEn el caso particular del estado de Guerrero, los pueblos originarios han exigido el reconocimiento de sus derechos colectivos que posibiliten su permanencia y reproducción social, económica y cultural. En respuesta a estas demandas, en los últimos años se han registrado avances importantes en materia de de Reconocimiento, Derechos y Cultura de los Pueblos y Comunidades Indígenas del Estado de Guerrero\nAFROMEXICANO DE LA SECRETARÍA DE ASUNTOS\nINDÍGENAS Y COMUNIDADES AFROMEXICANAS,\nPARA EL EJERCICIO 2016 al 12, en los que se consideran los derechos de los pueblos indígenas, y se incluye el reconocimiento constitucional del pueblo afromexicano, bajo los mismos términos y beneficios que los indígenas.\nNo obstante estos adelantos, aún existen limitaciones jurídicas que generan lagunas legales, propiciando, así, la persistencia de discriminación y exclusión; en consecuencia, los pueblos indígenas y afromexicano continúan enfrentando serias dificultades para acceder a la jurisdicción del Estado. En este sentido, la Secretaría de Asuntos Indígenas y Comunidades Afromexicanas (SAICA) implementa el programa Defensa y Asesoría Jurídica a Pueblos Indígenas y Afromexicano, el cual busca contribuir al cumplimiento de los derechos de estos pueblos, a través de la prestación de diversos servicios jurídicos y la promoción de sus derechos individuales y colectivos.\nEntre los servicios que se ofrecen destacan los siguientes: defensa y asesoría jurídica, traducciones en las cuatro lenguas indígenas en procesos legales y administrativos; regularización de actas del Registro Civil ante las autoridades jurisdiccionales y administrativas; trámites administrativos ante la\nDirección General del Régimen Penitenciario y del Archivo Criminalístico, así como diferentes apoyos a los internos indígenas y afromexicanos de los CERESOS del estado, consistentes en pago de fianzas, multas y reparación de daño, además periódicamente se realiza un censo de la población indígena y afromexicana que se encuentra recluida en estos Centros, con el objeto de procurarles un auxilio ágil y que coadyuve en su reinserción social. Cabe señalar que derivado de las condiciones de vulnerabilidad de la población indígena y afromexicana, los apoyos entregados, a través de pago de fianzas, multas y reparación de daño, serán a fondo perdido.\n2.Objetivo\n2.1 General\nContribuir al cumplimiento de los derechos de los pueblos indígenas y afromexicano, a través de la prestación de servicios jurídicos y trámites administrativos que permitan su pleno acceso a la jurisdicción del Estado y a la procuración y administración de justicia incluyente, con perspectiva intercultural y de género.\n2.2 Específicos\nBrindar asesoría, gestoría y defensa jurídica a la población indígena y afromexicana que se encuentra bajo procedimientos legales.\n✓ Proporcionar servicios de traducción en las cuatro lenguas indígenas en los procesos legales y ante otras instancias gubernamentales, a través de enlaces interculturales competentes, con pleno conocimientos de sus culturas, lenguas y variantes dialectales.\n✓ Realizar trámites administrativos ante la Coordinación Técnica del Sistema Estatal del Registro\nCivil, para asegurar el ejercicio de derechos de la población indígena y afromexicana.\nAFROMEXICANO DE LA SECRETARÍA DE ASUNTOS\nINDÍGENAS Y COMUNIDADES AFROMEXICANAS,\nPARA EL EJERCICIO 2016\n2.3. Población Objetivo\nLos beneficiarios del presente programa serán mujeres y hombres de todas las edades, que formen parte o se auto adscriban como integrantes de un pueblo indígena o del afromexicano, y que requieran o demanden un servicio relacionado con defensa y asesoría jurídica, o la realización de un trámite ante la Coordinación Técnica del Sistema Estatal del Registro Civil.\n3. Misión\nContribuir al cumplimiento de los derechos conquistados por los pueblos indígenas y afromexicano, a través de coadyuvar para que accedan a la jurisdicción del Estado, y a un desarrollo integral y con identidad.\n4. Visión\nSer el programa del Gobierno del Estado que acompañe a los pueblos indígenas y afromexicano en sus procesos de autonomía y libre determinación, desarrollando acciones conjuntas que fortalezcan sus sistemas normativos y los empoderen como pueblos y sujetos de derecho.\n5. Reglas de operatividad\n5. 1 Lineamientos generales\nEl programa tendrá cobertura estatal y a través de él la SAICA atenderá a personas, organizaciones sociales y comunidades indígenas y afromexicanas que soliciten servicios de defensa y asesoría jurídica en los campos penal, agrario, civil, familiar y laboral, principalmente; asimismo, prestará servicios de traducción en las lenguas náhuatl, mixteca, tlapaneca y amuzga, a las instituciones que así lo soliciten. Se realizarán también trámites ante la Coordinación Técnica del Sistema Estatal del Registro\nCivil y otras instancias administrativas.\nLas etapas y procedimientos que deberán seguir, son las siguientes:\nServicios de defensa y asesoría jurídica\n✓ Entregar solicitud por escrito, dirigida al titular de la Secretaría de Asuntos Indígenas y\nComunidades Afromexicanas, describiendo el servicio solicitado y el problema legal que enfrenta el solicitante. La petición podrá presentarse en las oficinas centrales, ubicadas en la ciudad de Chilpancingo, o en las Delegaciones Regionales situadas en las ciudades de Tlapa, Chilapa y Ometepec.\n✓ Ser familiar, representante legal o gestor del involucrado en los asuntos de carácter legal.\n✓ Copia de identificación oficial del interesado y del familiar, representante legal o gestor, (Credencial para Votar, Cartilla del Servicio Militar o Constancia de Identidad, avalada por la autoridad comunitaria.\n✓ Presentar la información y documentación correspondiente a la Dirección General de Defensa y\nAsesoría Jurídica, la cual definirá los documentos e información a entregar, de acuerdo al tipo de servicio solicitado.\nAFROMEXICANO DE LA SECRETARÍA DE ASUNTOS\nINDÍGENAS Y COMUNIDADES AFROMEXICANAS,\nPARA EL EJERCICIO 2016\n✓ El área responsable estudiará el caso específico gestionado, y de manera inmediata o en un plazo no mayor a cinco días hábiles, dependiendo de la gravedad o urgencia del proceso, dará respuesta a la solicitud.\n✓ La Secretaría de Asuntos Indígenas y Comunidades Afromexicanas dará el seguimiento puntual a los procesos legales e informará puntualmente al beneficiario (s) la situación que guarda el asunto, desde el inicio de éste hasta su culminación.\nServicios de traducción en las cuatro lenguas indígenas\n✓ La institución solicitante deberá enviar a la Secretaría de Asuntos Indígenas y Comunidades\nAfromexicanas solicitud por escrito, dirigida a su titular, en la que se describa el asunto o proceso legal que amerita el servicio de traducción, especificando la lengua indígena, fecha, lugar y hora en la que habrá de presentarse el traductor. Dicha solicitud deberá ser entregada con un mínimo de cinco días hábiles antes de la fecha del servicio.\n✓ La Secretaría de Asuntos Indígenas y Comunidades Afromexicanas dará respuesta inmediata a la petición, y se encargará de comisionar a un enlace intercultural (traductor e intérprete) debidamente calificado para desarrollar las funciones solicitadas.\nTrámites ante la Coordinación Técnica del Sistema Estatal del Registro Civil.\n✓ Solicitud por escrito, dirigida al titular de la SAICA, en la que se asiente el nombre del interesado\n(a) y el trámite requerido. La petición podrá presentarse en las oficinas centrales, ubicadas en la ciudad de\nChilpancingo, o en las Delegaciones Regionales situadas en las ciudades de Tlapa, Chilapa y Ometepec\n✓ Entregar la información personal y documentos necesarios a la Dirección General de Defensa y\nAsesoría, la cual indicará los requisitos específicos de acuerdo al trámite solicitado, e iniciará las gestiones respectivas.\n✓ La SAICA, a través de la Dirección General de Defensa y Asesoría Jurídica, realizará la revisión, elaboración de oficios y demás trámites de seguimiento y conclusión a que haya lugar, de acuerdo al tipo de gestión solicitada.\n✓ La duración del trámite y entrega de documentos solicitados estará en función de sus características, estimando un tiempo mínimo de siete días hábiles hasta un máximo de treinta.\n✓ Proporcionar un número telefónico, donde se localice a la persona que solicita el trámite.\n5.1.1. Fundamento legal\n✓ Constitución Política de los Estados Unidos Mexicanos (artículo 2). artículo 11, fracción VI).\n✓ Ley Orgánica de la Administración Pública del Estado de Guerrero Número 08 (artículo 32).\n✓ Plan Estatal de Desarrollo 2016-2021 (Eje VI, Estrategia 6.4.1.)\n✓ Ley número 701 de Reconocimiento, Derechos y Cultura Indígena de los Pueblos y Comunidades\nIndígenas de Guerrero.\n✓ Decreto Número 170 del Presupuesto de Egresos del Estado de Guerrero para el Ejercicio Fiscal\n2016.\n✓ Convenio 169 sobre Pueblos Indígenas y Tribales, de la Organización Internacional del Trabajo.\nAFROMEXICANO DE LA SECRETARÍA DE ASUNTOS\nINDÍGENAS Y COMUNIDADES AFROMEXICANAS,\nPARA EL EJERCICIO 2016\n✓ Declaración Universal de las Naciones Unidas sobre los Derechos de los Pueblos Indígenas.\n5.1.2. Participantes\nLa Secretaría de Asuntos Indígenas y Comunidades Afromexicanas; instituciones federales, estatales y municipales, principalmente las relacionadas con la procuración, acceso y administración de justicia; autoridades comunitarias; personas, grupos y organizaciones sociales indígenas y afromexicanas.\n5.1.3. Patrimonio del programa\nEl programa Defensa y Asesoría Jurídica a Pueblos Indígenas y Afromexicano tiene asignado un presupuesto financiero de $2'271,250.00 (dos millones doscientos setenta y un mil doscientos cincuenta pesos 00/100 M.N.), para ser ejercido en el presente ejercicio fiscal 2016, teniendo como fuente de financiamiento la Inversión Estatal Directa. Este recurso deberá ser destinado a la realización de las acciones en beneficio de la población indígena y afromexicana.\n5.1.4 Tipos de apoyo\nLos servicios y acciones estarán sujetos a la disponibilidad presupuestal del programa, y son los siguientes:\na) Prestación de servicios de defensa y asesoría jurídica, a través de las siguientes acciones:\n- Traducciones en las lenguas náhuatl, na'savi (mixteca), me'phaa (tlapaneca) y ñomndaa\n(amuzga), ante los órganos de procuración y administración de justicia, e instituciones de los tres niveles de gobierno.\n- Asesoría y seguimiento a los conflictos de carácter agrario, tanto individuales como colectivos, para comuneros, ejidatarios, avecindados y posesionarios, ante las instancias federales, estatales, municipales y judiciales, propiciando alternativas de conciliación.\n- Visitas de diagnóstico a los Centros de Reinserción Social (CERESOS) del Estado, para identificar el número y situación jurídica de los internos indígenas y afromexicanos.\n- Asesoría y seguimiento a los juicios de los internos indígenas y afromexicanos, recluidos en los\nCERESOS del estado.\n- Pago de fianzas por delitos no graves, en favor de la población indígena y afromexicana que se encuentra interna en los CERESOS del estado..\n- Pago de reparación de daño y multas, derivado de las sentencias emitidas por los tribunales de alzada.\n- Trámite de libertad anticipada del fuero común y federal, en favor de los internos indígenas y afromexicanos.\n- Gestión de traslados y anuencias, a favor de los internos indígenas y afromexicanos de los\nCERESOS estatales y nacionales.\n- Realización de eventos sociales, culturales y deportivos, para los internos indígenas y afromexicanos, recluidos en los CERESOS del estado.\n- Dotación de materia prima para la elaboración de artesanías y manualidades, en beneficio de los internos indígenas y afromexicanos, recluidos en los CERESOS del estado.\nAFROMEXICANO DE LA SECRETARÍA DE ASUNTOS\nINDÍGENAS Y COMUNIDADES AFROMEXICANAS,\nPARA EL EJERCICIO 2016\nb) Realización de trámites ante la Coordinación Técnica del Sistema Estatal del Registro Civil, que incluye los siguientes beneficios:\n- Registro de nacimientos y de nacimientos extemporáneos\n- Expedición de actas de nacimiento, defunción y matrimonio.\n- Aclaraciones y rectificaciones administrativas.\n- Anotaciones marginales.\n- Constancias de inexistencia de registro de nacimiento, defunción y matrimonio.\n- Emisión de la Cedula Única de Registro de Población (CURP).\nc) Taller de capacitación para el personal de la SAICA, sobre cultura y derechos indígenas y afromexicanos, con la finalidad de brindar una mejor atención a la población objetivo.\n6. Información del Programa\nLa difusión del programa denominado Defensa y Asesoría Jurídica a Pueblos Indígenas y\nAfromexicano, se realizará mediante trípticos, y en las páginas electrónicas www.guerrero.gob.mx y www.asuntosindigenas.guerrero.gob.mx\n6.1. Exposición del programa.\nSe brindan servicios de defensa y asesoría jurídica a personas, grupos, organizaciones sociales y comunidades indígenas y afromexicanas, en las diferentes ramas del derecho, principalmente penal, civil, familiar, agrario, laboral y mercantil; se proporcionan servicios de traducción en las lenguas náhuatl, na'savi\n(mixteca), me'phaa (tlapaneca) y ñomndaa (amuzga), ante instituciones de procuración y administración de justicia, y del órdenes administrativo de los tres niveles de gobierno; se ofrece defensa y seguimiento de procesos legales en favor de los internos (as) indígenas y afromexicanos que purgan alguna condena en los CERESOS del estado, así como pago de fianzas por delitos no graves, pago de daño, traslado a los\nCERESOS más cercanos a su lugar de residencia, realización de convivios familiares y dotación de materia prima para elaboración de artesanías y manualidades; asimismo, se realiza todo trámite ante la\nCoordinación Técnica del Sistema Estatal del Registro Civil.\n6.2. Cobertura\nLas acciones de este programa beneficiarán a la población indígena y afromexicana que se ubica en los 81 municipios del estado, con prioridad a la que habita en 48 municipios con preponderancia o presencia indígena y afromexicana.\nMUNICIPIOS PRIORITARIOS\nMONTAÑA COSTA CHICA CENTRO\n1. Acatepec 1. Ayutla de los Libres 1. Ahuacuotzingo\n2. Alcozauca de Guerrero 2. Igualapa 2. Eduardo Neri\n3. Alpoyeca 3. San Luis Acatlán 3. Chilapa de Álvarez\n4. Atlamajalcingo del Monte 4. Tlacoachistlahuaca 4. Chilpancingo de los Bravo\n5. Atlixtac 5. Xochistlahuaca 5. José Joaquín de Herrera\n6. Cochoapa el Grande Municipios Afromexicanos 6. Mártir de Cuilapan\nAFROMEXICANO DE LA SECRETARÍA DE ASUNTOS\nINDÍGENAS Y COMUNIDADES AFROMEXICANAS,\nPARA EL EJERCICIO 2016\n7. Copanatoyac 6. Azoyú 7. Tixtla de Guerrero\n8. Cualác 7. Copala 8. Zitlala\n9. Huamuxtitlan 8. Cuajinicuilapa NORTE\n10. Iliatenco 9. Cuautepec 1. Copalillo\n11. Malinaltepec 10. Florencio Villarreal 2. Huitzuco de los Figueroa\n12. Metlatónoc 11. Juchitán 3. Iguala de la Independencia\n13. Olinalá 12. Marquelia 4. Taxco de Alarcón\n14. Tlacoapa 13. Ometepec 5. Tepecoacuilco de Trujano\n15. Tlapa de Comonfort 14. San Marcos ACAPULCO\n16. Tlalixtaquilla 15. Tecoanapa 1. Acapulco de Juárez\n17. Xalpatláhuac\n18. Xochihuehietlan\n19. Zapotitlán Tablas\n6.3. Modos de entrega del beneficio\nUna vez que los solicitantes -personas, grupos, organizaciones sociales y comunidades- hayan cubierto los requisitos establecidos para recibir los servicios y apoyos descritos, recibirán los beneficios del programa de manera gratuita, rápida y expedita, de acuerdo a la urgencia y complejidad del problema por resolver.\n6.4. Gastos de operación\nEn cumplimiento al artículo 47 de la Ley de Coordinación Fiscal, podrá aplicarse hasta un 3% del presupuesto total del programa, a gastos de operación y realización de diversas acciones, asociadas con la planeación, operación, supervisión, seguimiento, contraloría social y evaluación o asesoría externa del programa.\n✓ Materiales, útiles y equipos menores de oficina. Hasta por un monto de $10,000.00/paquete.\nSe utilizarán para la compilación, sistematización, análisis y elaboración de demandas y trámites administrativos.\n✓ Materiales y útiles de impresión y reproducción. Hasta un monto de $10,000.00/paquete. Se utilizarán para la compilación, sistematización, análisis y elaboración de demandas y trámites administrativos.\n✓ Viáticos. Se ejercerán de acuerdo a la tarifa establecida por la Secretaría de Finanzas y\nAdministración. Se utilizarán para las actividades de promoción, ejecución, capacitación, difusión del programa, y trámites administrativos.\n✓ Combustibles, lubricantes y aditivos. Se ejercerán de acuerdo a la tarifa establecida para el desarrollo de las actividades del programa, en visitas institucionales y de campo que realice el personal directivo y técnico de la SAICA.\n✓ Peajes: hasta un monto de $520.00/viaje\n✓ Servicios de apoyo administrativo, fotocopiado e impresión:\n- Lona: hasta por un monto de $1,200.00/pieza.\nAFROMEXICANO DE LA SECRETARÍA DE ASUNTOS\nINDÍGENAS Y COMUNIDADES AFROMEXICANAS,\nPARA EL EJERCICIO 2016\n- Fotocopias: hasta por un monto de $1.00/pieza.\n✓ Paquetería: hasta por un monto de $200.00/envío.\n7. Transparencia\n7. 1 Difusión\nConforme a las disposiciones establecidas en el apartado de programas sujetos a Reglas de\nOperación del Decreto Número 170 del Presupuesto de Egresos del Estado de Guerrero para el Ejercicio\nFiscal 2016; estas Reglas de Operación, además de ser publicadas en el Periódico Oficial del Gobierno del\nEstado, estarán disponible para la población en general en las oficinas centrales y delegaciones regionales de la Secretaría de Asuntos Indígenas y Comunidades Afromexicanas, así como en la página electrónica del Gobierno del Estado: www.guerrero.gob.mx y www.asuntosindigenas.guerrero.gob.mx\n7.2. Seguimiento de Avances Físicos y financieros\nCon el propósito de mejorar la operación del programa Defensa y Asesoría Jurídica a Pueblos\nIndígenas y Afromexicano, la SAICA llevará a cabo el seguimiento del ejercicio de recursos financieros, acciones ejecutadas, resultados, indicadores y metas alcanzadas; asimismo, realizará el seguimiento en campo de las acciones, conforme a lo que se determine.\nLa SAICA deberá reportar trimestralmente a la Secretaría de Planeación y Desarrollo Regional\n(SEPLADER) y a la Secretaría de Finanzas y Administración (SEFINA), durante los primeros diez días hábiles del mes inmediato, posterior al trimestre que se reporta, los avances físicos y financieros de las acciones autorizadas.\nEn el caso que la Secretaría de Planeación y Desarrollo Regional (SEPLADER) detecte información faltante, informará a la instancia ejecutora detalladamente y por escrito, la cual deberá presentar la información faltante en el plazo que se señala.\nPor otra parte, la Secretaría de Asuntos Indígenas y Comunidades Afromexicanas integrará el cierre de ejercicio y lo remitirá a la Secretaría de Finanzas y Administración (SEFINA), con un tanto original, misma que servirá para verificar la congruencia de la información con respecto a la cuenta pública.\n7.3. Evaluación\nLa SAICA tendrá la obligación de revisar, de manera interna, la correcta operación y aplicación de las presentes reglas de operación y, en caso necesario, podrá solicitar una evaluación externa por parte de una instancia con experiencia en el tema. adecuado desarrollo del Programa, a efecto de corregir desfases o efectuar reasignaciones financieras con\nAdministración, a fin de cubrir rubros prioritarios, con recursos de este mismo programa o de otros que no hayan sido ejercidos en su momento, o bien que provengan de ahorros presupuestales.\nAFROMEXICANO DE LA SECRETARÍA DE ASUNTOS\nINDÍGENAS Y COMUNIDADES AFROMEXICANAS,\nPARA EL EJERCICIO 2016\n7.4. Auditoría\nEste programa podrá ser auditado, a través de las instancias correspondientes en el ámbito de sus respectivas competencias del gobierno del estado, encargadas de vigilar la correcta aplicación de los recursos del erario público.\n7.5. Recursos no devengados\nEl presupuesto no ejercido al 31 de diciembre de 2016, será reintegrado a la Secretaría de\nFinanzas y Administración del Estado de Guerrero (SEFINA).\n7.6. Blindaje electoral\nComo estrategia de blindaje electoral, la papelería, documentación oficial, así como la publicidad y promoción del Programa deberán incluir la siguiente leyenda:\n\"Este Programa es de carácter público, no es patrocinado ni promovido por partido político alguno y sus recursos provienen de los impuestos que pagan todos los contribuyentes. Está prohibido el uso de este programa con fines políticos, electorales, de lucro y otros distintos a los establecidos. Quien haga uso indebido de los recursos de este programa deberá ser denunciado y sancionado de acuerdo con la ley aplicable y ante la autoridad competente\".\nEn cuanto a la publicidad en medios electrónicos, impresos, complementarios o de cualquier otra índole, vinculados con los Programas de comunicación social, se deberá incluir la siguiente leyenda:\n\"Este Programa es público y queda prohibido su uso con fines partidistas o de promoción personal\".\n7.7. Contraloría social\nLa SAICA, como instancia ejecutora, promoverá la contraloría social, la cual comprende un conjunto de acciones de control, vigilancia y evaluación que realizan los beneficiarios, ya sea de manera organizada o independiente, bajo un esquema de derechos y compromisos ciudadanos con el propósito de contribuir a que la gestión gubernamental se realice en términos de transparencia, eficacia y honradez.\nEntre dichas acciones destacan las siguientes:\na) Informar a la ciudadanía acerca de los apoyos otorgados y su costo.\nb) Capacitar a los beneficiarios para que se constituyan en instancias de vigilancia y evaluación social.\nc) Establecer espacios de comunicación (reuniones vecinales, asambleas comunitarias, entre otros).\nd) Promover la integración de organizaciones de la sociedad civil para realizar acciones de contraloría social.\ne) Instrumentar mecanismos de recepción y atención de quejas y denuncias. El Órgano Estatal de\nControl verificará en lo correspondiente la realización de dichas acciones.\nAFROMEXICANO DE LA SECRETARÍA DE ASUNTOS\nINDÍGENAS Y COMUNIDADES AFROMEXICANAS,\nPARA EL EJERCICIO 2016\n7.8. Quejas y denuncias\nLas quejas, denuncias, peticiones y sugerencias relativas a este programa, se realizarán de manera escrita, por comparecencia del interesado, por correo electrónico o vía telefónica, y para aquellas que sean escritas se depositarán en los buzones instalados en las oficinas centrales de la SAICA, ubicadas en la ciudad de Chilpancingo, así como en las delegaciones regionales, situadas en las ciudades de Tlapa de Comonfort, Chilapa de Álvarez y Ometepec. El denunciante o quejoso deberá proporcionar los siguientes datos:\n- Nombre y domicilio\n- Identificación oficial\n- Nombre del servidor público denunciado\n- Objeto de la denuncia\n8. Criterios de selección y elegibilidad\n8.1. Método de selección de beneficiarios\nLos beneficiarios (as) del programa deberán cumplir con los siguientes criterios de selección y elegibilidad:\n✓ Ser originario de comunidades y municipios indígenas y afromexicanos, o auto adscribirse como tales, independientemente de su sexo, edad y filiación política o religiosa.\n✓ Solicitud por escrito, dirigida al titular de la SAICA, especificando el trámite o servicio que se demanda.\n9. Mecánica de operación\n9.1. Instancia ejecutora\nLa Secretaría de Asuntos Indígenas y Comunidades Afromexicanas será la instancia ejecutora del programa Defensa y Asesoría Jurídica a Pueblos Indígenas y Afromexicano, a través de la Dirección\nGeneral de Defensa y Asesoría Jurídica, de acuerdo a los lineamientos establecidos en estas reglas de operación para el ejercicio fiscal 2016.\n9.2. Instancia administrativa y normativa reglas de operación, y resolver los casos no previstos en las mismas.\n9.3. Delimitación de atribuciones reglas de operación, una vez que la Secretaría de Finanzas y Administración libere los recursos destinados para este programa, dando cumplimiento a los lineamientos de la Secretaría de Planeación y Desarrollo\nRegional y de la Secretaría de Contraloría y Transparencia Gubernamental.\nAFROMEXICANO DE LA SECRETARÍA DE ASUNTOS\nINDÍGENAS Y COMUNIDADES AFROMEXICANAS,\nPARA EL EJERCICIO 2016\n10. Derechos, obligaciones y sanciones de los beneficiarios de programas sociales\n10.1. Derechos\n✓ Recibir los beneficios que otorga este programa.\n✓ Recibir un trato digno, respetuoso y oportuno, sin discriminación alguna.\n✓ Recibir información, de manera clara y sencilla, sobre el estado que guarda el proceso o el trámite del servicio que se brinda, ✓ Reserva y privacidad de los datos personales.\n10.2. Obligaciones\n✓ Conducirse con la verdad en toda la información que se les requiera, de acuerdo al servicio, trámite o proceso que se siga.\n✓ Entregar la información y documentación solicitada, de acuerdo al servicio, trámite o proceso que se siga.\n✓ Presentarse ante la dirección ejecutora del Programa, cuando así se solicite, para actualizar datos o brindar información relacionada con el seguimiento y conclusión del procedimiento legal.\n10.3 Sanciones\nSe cancelarán los apoyos de asesoría, representación legal y trámites administrativos, a aquellos beneficiarios que presenten documentación o información falsa, incumplan con los requisitos o abandonen los procesos legales.\n11. Interpretación\nEl programa estará a cargo de la Secretaría de Asuntos Indígenas y Comunidades Afromexicanas, y sus acciones se desarrollarán bajo las reglas de operación respectivas, que entrarán en vigor el día\nAFROMEXICANO DE LA SECRETARÍA DE ASUNTOS\nINDÍGENAS Y COMUNIDADES AFROMEXICANAS,\nPARA EL EJERCICIO 2016\nLIC. FELIPE SÁNCHEZ RAMÍREZ, DIRECTOR GENERAL DE LA DEFENSA Y ASESORÍA\nGOBIERNO DEL ESTADO DE GUERRERO; DE CONFORMIDAD CON LO ESTABLECIDO EN EL\nNUMERAL 32, FRACCIÓN XVIII, DE LA LEY ORGÁNICA DE LA ADMINISTRACIÓN PÚBLICA DEL\nESTADO DE GUERRERO NÚMERO 08, ASÍ COMO EL NUMERAL 16 FRACCIONES V, XXI Y XXII DEL\nREGLAMENTO INTERNO VIGENTE DE ESTA DEPENDENCIA.\nHAGO CONSTAR Y CERTIFICO\nQUE LAS PRESENTES COPIAS FOTOSTÁTICAS, COMPUESTAS DE 20 FOJAS ÚTILES SON\nSECRETARÍA, MISMAS QUE SE EXPIDEN PARA LOS USOS LEGALES A QUE HAYA LUGAR, EN LA\nATENTAMENTE.\nLIC. FELIPE SÁNCHEZ RAMÍREZ.\nDIRECTOR GENERAL DE LA DEFENSA Y ASESORÍA JURÍDICA.\nRúbrica.",
  "ordenamiento": "REGLA",
  "jurisdiccion": "GUERRERO",
  "fuente_oficial": "DIARIO OFICIAL DE LA FEDERACION",
  "Fecha de Publicación": "16 DE JUNIO DE 2017",
  "ULTIMA REFORMA PUBLICADA": "16 DE JUNIO DE 2017",
  "status": "VIGENTE",
  "es_escaneado": false,
  "tiene_tablas": true,
  "materia": [
    "general"
  ]
}