{
  "titulo": "Acuerdo Mediante el Cual Se Emiten las Reglas de Operación del Programa 1. Servicios Emergentes para",
  "Contenido": "INDÍGENA Y FROMEXICANA (SIC) DE LA\nCOMUNIDADES AFROMEXICANAS, PARA EL\nEJERCICIO 2016\nÍndice\n1. Introducción....................................................................................................................................... 6\n2. Objetivos............................................................................................................................................ 6\n2.1. General........................................................................................................................................... 6\n2.2. Específicos..................................................................................................................................... 7\n2.3. Población objetivo........................................................................................................................... 7\n3. Misión................................................................................................................................................ 7\n4. Visión................................................................................................................................................. 7\n5. Reglas de operatividad...................................................................................................................... 7\n5.1. Lineamientos generales.................................................................................................................. 7\n5.1.1. Fundamento legal........................................................................................................................ 9\n5.1.2. Participantes................................................................................................................................ 9\n5.1.3. Patrimonio del programa.............................................................................................................. 9\n5.1.4. Tipos de apoyo............................................................................................................................ 9\n6. Información del programa.................................................................................................................. 10\n6.1. Exposición del programa................................................................................................................. 10\n6.2. Cobertura........................................................................................................................................ 10\n6.3. Modos de entrega del beneficio...................................................................................................... 11\n6.4. Gastos de operación....................................................................................................................... 11\n7. Transparencia.................................................................................................................................... 12\n7.1. Difusión........................................................................................................................................... 12\nINDÍGENA Y FROMEXICANA (SIC) DE LA\nCOMUNIDADES AFROMEXICANAS, PARA EL\nEJERCICIO 2016\n7.2. Seguimiento de avances físicos y financieros................................................................................ 12\n7.3. Evaluación...................................................................................................................................... 13\n7.4. Auditoria.......................................................................................................................................... 13\n7.5. Recursos no devengados............................................................................................................... 13\n7.6. Blindaje electoral............................................................................................................................. 13\n7.7. Contraloría social............................................................................................................................ 13\n7.8. Quejas y denuncias......................................................................................................................... 13\n8. Criterios de selección y elegibilidad................................................................................................... 14\n8.1. Método de selección de beneficiarios............................................................................................. 14\n9. Mecánica de operación...................................................................................................................... 14\n9.1. Instancia ejecutora.......................................................................................................................... 14\n9.2. Instancia administrativa y normativa……………………………………………………………………….15\n9.3. Delimitación de atribuciones........................................................................................................... 15\n10. Derechos, obligaciones y sanciones de los beneficiarios de programas sociales............................. 15\n10.1. Derechos...................................................................................................................................... 15\n10.2. Obligaciones................................................................................................................................. 15\n10.3. Sanciones..................................................................................................................................... 15\n11. Interpretación................................................................................................................................... 15\nINDÍGENA Y FROMEXICANA (SIC) DE LA\nCOMUNIDADES AFROMEXICANAS, PARA EL\nEJERCICIO 2016\nDE OPERACIÓN DEL PROGRAMA DE LA SECRETARÍA DE ASUNTOS INDÍGENAS Y COMUNIDADES AFROMEXICANAS,\nPUBLICADO EN EL PERIODICO OFICIAL DEL GOBIERNO DEL ESTADO DE GUERRERO No. 34, DE FECHA 28 DE ABRIL DE\n2017\nTEXTO ORIGINAL.\nAcuerdo publicados en el Periódico Oficial del Gobierno del Estado No. 61 Alcance I, el Viernes\n29 de Julio de 2016.\nACUERDO MEDIANTE EL CUAL SE EMITEN LAS REGLAS DE OPERACIÓN DEL PROGRAMA 1.\nSERVICIOS EMERGENTES PARA POBLACIÓN INDIGENA Y FROMEXICANA DE LA SECRETARÍA\nDE ASUNTOS INDÍGENAS Y COMUNIDADES AFROMEXICANAS, PARA EL EJERCICIO 2016.\nLIC. GILBERTO SOLANO ARREAGA, Secretario de Asuntos Indígenas y Comunidades\nAfromexicanas, con fundamento en los Artículos 11, 14 y 16 de la Ley Orgánica de la Administración Pública del Estado de Guerrero número 8, y el artículo 32 de la Ley en referencia por el que se crea la Secretaría de Asuntos Indígenas y Comunidades Afromexicanas, publicado en el Periódico Oficial del Gobierno del\nEstado de Guerrero, número 85, de fecha 23 de Octubre de 2015, y\nCONSIDERANDO\nQue en el Decreto número 170 del Presupuesto de Egresos del Estado de Guerrero, para el\nEjercicio Fiscal 2016, se señala que se ejercitarán los recursos bajo una política de gasto público que permita dar cumplimiento a los seis ejes rectores del Plan Estatal de Desarrollo 2016 - 2021. Las políticas encaminadas a desarrollo social, se orientaron a los sectores desprotegidos del estado y a programas sociales.\nQue dentro de las políticas de Desarrollo Social la Secretaría de Asuntos Indígenas y\nComunidades Afromexicanas, implementará cincos programas: 1. Servicios Emergentes para Población\nIndígena y Afromexicana; 2. Becas a Estudiantes Indígenas y Afromexicanos; 3. Impulso a la\nProducción, Organización y Autogestión Comunitaria; 4. Defensa y Asesoría Jurídica a Pueblos\nIndígenas y Afromexicano; 5. Fortalecimiento de las Culturas e Identidades Indígenas y\nAfromexicana, a fin de contribuir a la mejora de la calidad de vida de cada uno de las y los beneficiarios de los programas.\nPor lo anterior expuesto y con fundamento en las disposiciones legales antes citadas, he tenido a bien expedir el siguiente:\nEJERCICIO FISCAL 2016.\nÚnico: se emiten las Reglas de Operación del Programa 1. Servicios Emergentes para\nPoblación Indígena y Afromexicana, que implementará la Secretaría de Asuntos Indígenas y\nComunidades Afromexicanas, para el Ejercicio Fiscal 2016.\nINDÍGENA Y FROMEXICANA (SIC) DE LA\nCOMUNIDADES AFROMEXICANAS, PARA EL\nEJERCICIO 2016\nTRANSITORIOS\nPrimero.- El presente acuerdo entrará en vigor al día siguiente de su publicación en el Periódico\nOficial del Gobierno del Estado de Guerrero.\nSegundo.- Quedan abrogadas las Reglas de Operación de los Programas 1. Servicios\nEmergentes para Población Indígena y Afromexicana; 2. Becas a Estudiantes Indígenas y\nAfromexicanos; 3. Impulso a la Producción, Organización y Autogestión Comunitaria; 4. Defensa y\nAsesoría Jurídica a Pueblos Indígenas y Afromexicano; 5. Fortalecimiento de las Culturas e\nIdentidades Indígenas y Afromexicana, publicadas en el Periódico Oficial del Estado de Guerrero, numero 70 de fecha 29 de agosto del 2008.\nTercero.- Las Reglas de Operación de los Programas de la Secretaría de Asuntos Indígenas y\nComunidades Afromexicanas: 1. Servicios Emergentes para Población Indígena y Afromexicana; 2.\nBecas a Estudiantes Indígenas y Afromexicanos; 3. Impulso a la Producción, Organización y\nAutogestión Comunitaria; 4. Defensa y Asesoría Jurídica a Pueblos Indígenas y Afromexicano; 5.\nFortalecimiento de las Culturas e Identidades Indígenas y Afromexicana, para el Ejercicio Fiscal 2016, se publican en su totalidad para mejor entendimiento.\nDado en la ciudad de Chilpancingo de los Bravo, Guerrero, a los 16 días del mes de marzo de dos mil diez y seis.\nEL SECRETARIO DE ASUNTOS INDÍGENAS Y COMUNIDADES AFROMEXICANAS.\nLIC. GILBERTO SOLANO ARREAGA.\nRúbrica.\nÍndice\n1. Introducción.\n2. Objetivos.\n2.1. General\n2.2. Especifico\n2.3. Población objetivo\n3. Misión.\n4. Visión.\n5. Reglas de operatividad.\n5.1 Lineamientos generales\nINDÍGENA Y FROMEXICANA (SIC) DE LA\nCOMUNIDADES AFROMEXICANAS, PARA EL\nEJERCICIO 2016\n5.1.1. Fundamento legal\n5.1.2 Participantes\n5.1.3. Patrimonio del programa\n5.1.4. Tipos de apoyo\n6. Información del Programa.\n6.1. Exposición del Programa\n6.2. Cobertura\n6.3. Modos de entrega del beneficio\n6.4. Gastos de operación\n7. Transparencia.\n7.1. Difusión\n7.2. Seguimiento de avances físicos y financieros\n7.3. Evaluación\n7.4. Auditoria\n7.5. Recursos no devengados\n7.6. Blindaje electoral\n7.7. Contraloría social\n7.8. Quejas y denuncias\n8. Criterios de selección y elegibilidad.\n8.1. Método de selección de beneficiarios\n9. Mecánica de operación.\n9.1. Instancia ejecutora\n9.2. Instancia administrativa y normativa\n9.3. Delimitación de atribuciones\n10. Derechos, obligaciones y sanciones de los beneficiarios de programas sociales.\n10.1. Derechos\n10.2. Obligaciones\n10.3. Sanciones\n11. Interpretación.\nINDÍGENA Y FROMEXICANA (SIC) DE LA\nCOMUNIDADES AFROMEXICANAS, PARA EL\nEJERCICIO 2016\n1. Introducción\nDe acuerdo a la Constitución Política de nuestro estado, los pueblos nahua, mixteco, tlapaneco, amuzgo y afromexicano son el sustento del carácter multiétnico, plurilingüe y pluricultural de Guerrero. No obstante su importancia histórica, cultural y social de estos cinco pueblos, continúan enfrentando serios problemas estructurales que los sitúan en condiciones de desventaja y desigualdad, lo cual se refleja en los altos índices de pobreza extrema que se presentan en estos sectores de la población. Estas difíciles condiciones de vida sitúan a la población indígena y afromexicana en un constante riesgo, principalmente cuando al interior de las familias se presentan episodios de emergencia, ya sea por casos de enfermedad, muerte o de otra índole.\nOtro problema generado por la apremiante situación económica se relaciona con los episodios de migración de hombres, mujeres y niños indígenas hacia los estados de la República que captan mano de obra barata, principalmente Sinaloa, Colima, Zacatecas y Baja California. Aunque este fenómeno migratorio permite a las familias indígenas obtener un mejor ingreso económico, deben soportar numerosas condiciones adversas que inician desde el traslado de sus comunidades a las ciudades de Tlapa, Chilapa y Ometepec, y se tornan más delicadas conforme son contratados y embarcados en autobuses a los distintos campos agrícolas de destino. Ya en los campos de trabajo deben enfrentar todavía la explotación, los bajos salarios, las pésimas condiciones de alojamiento y vivienda, las enfermedades y los riesgos y accidentes de trabajo.\nA través de estas reglas de operación que norman los beneficios del programa Servicios\nEmergentes para Población Indígena y Afromexicana, la Secretaría de Asuntos Indígenas y Comunidades\nAfromexicanas ofrece diferentes servicios a esta población en situaciones emergentes y, específicamente, a los jornaleros agrícolas migrantes en tránsito a los campos de trabajo del interior y exterior del estado.\nNo sólo se busca dar respuesta a las apremiantes necesidades de los migrantes indígenas y afromexicanos, sino establecer una coordinación intersectorial que garantice una mejor atención y solución a la problemática que enfrentan los jornaleros agrícolas migrantes y, en general, la población indígena y afromexicana, alineándose así el programa al Plan Estatal de Desarrollo 2016-2021, específicamente al\nEje VI, Estrategia 6.4.1, la cual establece la atención de los pueblos indígenas y afromexicano, a fin de generar oportunidades que permitan su desarrollo económico, político y social. trámites en la ciudad de Chilpancingo, brindándoles ayuda económica para gastos de transporte y alimentación, así como hospedaje en el albergue temporal.\n2. Objetivos\n2.1. General\nProporcionar servicios y apoyos emergentes a la población indígena y afromexicana, y contribuir a la protección de los jornaleros agrícolas, a través de una atención expedita y humana, y la coordinación con dependencias federales y estatales.\nINDÍGENA Y FROMEXICANA (SIC) DE LA\nCOMUNIDADES AFROMEXICANAS, PARA EL\nEJERCICIO 2016\n2.2. Específicos\n✓ Otorgar apoyos inmediatos en casos de desastre y contingencias de salud, traslados de enfermos y fallecidos, pasajes, alimentación y hospedaje temporal.\n✓ Proporcionar acompañamiento en la gestión, canalización y resolución institucional a las demandas de los ciudadanos indígenas.\n✓ Contribuir a mejorar las condiciones de tránsito de los jornaleros migrantes indígenas.\n2.3. Población objetivo\nLos beneficiarios del presente programa serán niñas(os), jóvenes, mujeres, hombres, jornaleros agrícolas migrantes y personas con capacidades diferentes que formen parte de un pueblo indígena o afromexicano, o se autoadscriban como tales.\n3. Misión\nBrindar atención en situaciones emergentes a la población indígena y afromexicana, y contribuir al bienestar de los jornaleros agrícolas migrantes en tránsito de sus comunidades a los campos de trabajo.\n4. Visión\nSer un programa que propicie la coordinación institucional con los pueblos y comunidades indígenas y afromexicanas, para la solución de problemas de gestión y atención de demandas, así como para establecer estrategias de arraigo con los jornaleros migrantes.\n5. Reglas de operatividad.\n5.1. Lineamientos generales\nEl programa tendrá cobertura estatal y nacional, e incluso internacional en caso de los jornaleros agrícolas migrantes, y atenderá a personas indígenas y afromexicanas que soliciten apoyo en situaciones de emergencia, así como ayuda para pasajes, alimentación y hospedaje, cuando acuden a la ciudad de\nChilpancingo a realizar trámites o gestiones comunitarias. Las etapas y procedimientos que deberán seguir, son las siguientes:\nDonación de ataúdes y traslado de fallecidos\n✓ El familiar o gestor del fallecido deberá presentar a la Delegación Administrativa de la Secretaría de\nAsuntos Indígenas y Comunidades Afromexicanas solicitud escrita, dirigida al titular y, acompañada de los siguientes documentos:\n- Certificado y Acta de Defunción\n- Identificación oficial del fallecido y de la persona que realiza el trámite\n- Acta de nacimiento del fallecido\n- CURP del fallecido\n-Constancia de radicación y de pobreza, emitida por autoridad local o municipal.\nINDÍGENA Y FROMEXICANA (SIC) DE LA\nCOMUNIDADES AFROMEXICANAS, PARA EL\nEJERCICIO 2016\n✓ Una vez realizado los trámites correspondientes, la funeraria contratada por la SAICA se encargará de entregar el ataúd y realizar el traslado del fallecido del sitio donde acaeció el fallecimiento al lugar indicado por los familiares.\nApoyo para gastos de hospitalización, estudios de laboratorio y radiológicos, compra de medicamentos y aparatos ortopédicos:\n✓ El familiar o gestor del enfermo deberá presentar solicitud por escrito, dirigida al titular de la\nSecretaría de Asuntos Indígenas y Comunidades Afromexicanas, acompañada de los siguientes documentos:\n-Identificación oficial del enfermo y de la persona que realiza el trámite.\n-Nota médica, especificando el diagnóstico.\n-Certificado médico, especificando las necesidades clínicas del enfermo, como son: estudios clínicos o radiológicos, aparato ortopédico o medicamentos y, en su caso, el importe por gastos de hospitalización.\n✓ Una vez entregada la documentación señalada, la Secretaría de Asuntos Indígenas y Comunidades\nAfromexicanas cubrirá el costo del gasto médico, ya sea directamente al prestador del servicio o al beneficiario, en cuyo caso deberá presentar la factura original. En el caso de los aparatos ortopédicos, la SAICA realizará gestiones de concurrencia interinstitucional para obtener y entregar el apoyo solicitado.\nApoyo para pasajes y alimentación, y hospedaje en el Albergue Temporal\n✓ Las autoridades y gestores comunitarios que realizan algún trámite en beneficio de sus localidades, en la ciudad de Chilpancingo, y necesiten alguno de estos apoyos deberán proceder como se indica:\n-Solicitud verbal ante la Delegación Administrativa\n-Presentar copia de identificación oficial\n-Firmar el recibo respectivo (en caso de apoyo económico)\n-La entrega de beneficios es inmediata\nAtención a Jornaleros agrícolas migrantes indígenas y afromexicanos\n✓ Se ofrecen dos tipos de apoyo a los jornaleros agrícolas; uno se les entrega directamente, y el otro al Consejo de Jornaleros Agrícolas de la Montaña que operan la Unidad de Servicios Integrales, ubicada en la ciudad de Tlapa. Los procedimientos para cada uno son los siguientes:\nApoyo de pasajes y alimentación:\n-Personal de la Secretaría de Asuntos Indígenas y Comunidades Afromexicanas acude en los meses de agosto y octubre a la Unidad de Servicios Integrales que atiende a los jornaleros agrícolas migrantes, en la ciudades de Tlapa, así como a los centros de reunión y traslado de las ciudades de Chilapa y\nOmetepec, para hacer entrega individual de apoyo económico de pasajes y alimentación, cuyo monto reunión.\n-El beneficiario únicamente deberá entregar copia de identificación oficial.\nINDÍGENA Y FROMEXICANA (SIC) DE LA\nCOMUNIDADES AFROMEXICANAS, PARA EL\nEJERCICIO 2016 de la ciudad de Tlapa:\n✓ Solicitud escrita por parte del Consejo de Jornaleros Agrícolas de la Montaña, dirigida al titular de la Secretaria de Asuntos Indígenas y Comunidades Afromexicanas, especificando los alimentos e insumos requeridos.\n✓ La Secretaría de Asuntos Indígenas y Comunidades Afromexicanas entregará en especie los alimentos e insumos, en un plazo máximo de 15 días hábiles, en los meses de agosto y noviembre.\n5.1.1. Fundamento legal\n✓ Constitución Política de los Estados Unidos Mexicanos (artículo 2). artículos 8 al 14).\n✓ Ley Orgánica de la Administración Pública del Estado de Guerrero Número 08 (artículo 32).\n✓ Ley número 701 de Reconocimiento, Derechos y Cultura Indígena de los Pueblos y Comunidades\nIndígenas de Guerrero.\n✓ Decreto Número 170 del Presupuesto de Egresos del Estado de Guerrero para el Ejercicio Fiscal\n2016.\n✓ Plan Estatal de Desarrollo 2016-2021 (Eje VI, Estrategia 6.4.1.)\n✓ Convenio 169 sobre Pueblos Indígenas y Tribales, de la Organización Internacional del Trabajo.\n✓ Declaración Universal de las Naciones Unidas sobre los Derechos de los Pueblos Indígenas.\n5.1.2. Participantes\nLa Secretaría de Asuntos Indígenas y Comunidades Afromexicanas, instituciones federales, estatales y municipales, autoridades comunitarias, personas, grupos y organizaciones sociales indígenas y afromexicanas.\n5.1.3. Patrimonio del programa.\nEl programa Servicios Emergentes para Población Indígena y Afromexicana tiene asignado un presupuesto financiero de $5'500,000.00 (cinco millones quinientos mil pesos 00/100MN), para ser ejercido en el presente ejercicio fiscal 2016, teniendo como fuente de financiamiento la Inversión Estatal Directa.\nEste recurso deberá ser destinado a la realización de las acciones en beneficio de la población indígena y afromexicana.\n5.1.4. Tipos de apoyo\n✓ Apoyo inmediato en casos de contingencia y emergencia, relacionado con atención médica, compra de medicamentos, pago de estudios de laboratorio y radiológicos, traslado de enfermos y fallecidos, y donación de ataúdes.\n✓ Pago de pasajes y alimentación, así como hospedaje en el Albergue Temporal, a personas que realizan trámites o gestiones comunitarias en la ciudad de Chilpancingo.\n✓ Insumos para el Comedor Comunitario de la Unidad de Servicios Integrales, que brinda atención a los jornaleros agrícolas migrantes en la ciudad de Tlapa de Comonfort.\nINDÍGENA Y FROMEXICANA (SIC) DE LA\nCOMUNIDADES AFROMEXICANAS, PARA EL\nEJERCICIO 2016\n✓ Pago de pasajes, alimentación y gastos médicos a jornaleros agrícolas migrantes indígenas y afromexicanos que se encuentran en tránsito de sus comunidades a los campos de trabajo.\n6. Información del programa.\nLa difusión del programa denominado Servicios Emergentes para Población Indígena y\nAfromexicana, se realizará mediante trípticos, y en las páginas electrónicas www.guerrero.gob.mx y www.asuntosindigenas.guerrero.gob.mx\n6.1. Exposición del programa.\nSe brindan diferentes tipos de apoyos a la población indígena y afromexicana, principalmente en situaciones de emergencia, relacionadas con atención de la salud y fallecimientos, así como apoyo a gestores y autoridades comunitarias, y atención a jornaleros agrícolas migrantes.\n6.2. Cobertura\nLas acciones de este programa beneficiarán a la población indígena y afromexicana que se ubica en los 81 municipios del estado, con prioridad a la que habita en 48 municipios con preponderancia o presencia indígena y afromexicana.\nMUNICIPIOS PRIORITARIOS\nMONTANA COSTA CHICA CENTRO\n1. Acatepec 1. Ayutla de los Libres 1. Ahuacuotzingo\n2. Alcozauca de Guerrero 2. Igualapa 2. Eduardo Neri\n3. Alpoyeca 3. San Luis Acatlán 3. Chilapa de Álvarez\n4. Atlamajalcingo del Monte 4. Tlacoachistlahuaca 4. Chilpancingo de los Bravo\n5. Atlixtac 5. Xochistlahuaca 5. José Joaquín de Herrera\n6. Cochoapa el Grande Municipios Afromexicanos 6. Mártir de Cuilapan\n7. Copanatoyac 6. Azoyú 7. Tixtla de Guerrero\n8. Cualác 7. Copala 8. Zitlala\n9. Huamuxtitlan 8. Cuajinicuilapa NORTE\n10. Iliatenco 9. Cuautepec 1. Copalillo\n11. Malinaltepec 10. Florencio Villarreal 2. Huitzuco de los Figueroa\n12. Metlatónoc 11. Juchitán 3. Iguala de la Independencia\n13. Olinalá 12. Marquelia 4. Taxco de Alarcón\n14. Tlacoapa 13. Ometepec 5. Tepecoacuilco de Trujano\n15. Tlapa de Comonfort 14. San Marcos ACAPULCO\nINDÍGENA Y FROMEXICANA (SIC) DE LA\nCOMUNIDADES AFROMEXICANAS, PARA EL\nEJERCICIO 2016\n16. Tlalixtaquilla 15. Tecoanapa 1. Acapulco de Juárez\n17. Xalpatláhuac\n18. Xochihuehietlan\n19. Zapotitlán Tablas\n6.3. Modos de entrega del beneficio\nUna vez que el beneficiario haya cubierto los requisitos establecidos por el programa, se entregará de manera personal el apoyo requerido, de acuerdo a lo siguiente:\n✓ Los apoyos consistentes en donación de ataúdes y aparatos ortopédicos, así como traslado de enfermos y fallecidos, no se otorgarán en efectivo, sino en especie.\n✓ En los casos de gastos de hospitalización, medicamentos y estudios de laboratorio y radiografías, se cubrirá el importe directamente a la institución de salud responsable de la atención del beneficiario.\n✓ En los apoyos de pasaje y alimentación para autoridades y gestores comunitarios que se trasladan de sus comunidades a la ciudad de Chilpancingo, se entregarán en efectivo, previa comprobación del trámite o asunto que tramitan y copia de identificación oficial.\n✓ Los apoyos de pasaje y alimentación para jornaleros agrícolas migrantes, se entregarán de manera individual y en efectivo en los centros de contratación y traslados, ubicados en las ciudades de\nTlapa, Ometepec y Chilapa.\n✓ El apoyo de alimentos, bebidas y gas para el Comedor Comunitario de la Unidad de Servicios\nIntegrales que atiende a los jornaleros agrícolas migrantes en la ciudad de Tlapa, se realizará en especie directamente al Consejo de Jornaleros Agrícolas de la Montaña.\n6.4. Gastos de operación\nEn cumplimiento al artículo 47 de la Ley de Coordinación Fiscal, podrá aplicarse hasta un 3% del presupuesto total del programa, a gastos de operación y realización de diversas acciones, asociadas con la planeación, operación, supervisión, seguimiento, contraloría social y evaluación o asesoría externa del programa.\n✓ Papelería: hasta un monto de $5,000.00/paquete.\n✓ Consumibles: hasta un monto de $5,000.00/paquete\n✓ Viáticos: se ejercerán de acuerdo a la tarifa establecida por la Secretaría de Finanzas y\nAdministración.\n✓ Combustible y peajes: se ejercerán de acuerdo a la tarifa establecida para el desarrollo de las actividades del programa, en visitas institucionales y de campo que realice el personal directivo y técnico de la SAICA.\n✓ Impresión de recibos: hasta un monto de $5,000.00/millar.\n✓ Fotocopias: hasta un monto de $1.00/pieza.\n✓ Lonas: hasta por un monto de $1,500.00/pieza.\n✓ Tríptico informativos: hasta por un monto de $4,500.00/ millar.\nINDÍGENA Y FROMEXICANA (SIC) DE LA\nCOMUNIDADES AFROMEXICANAS, PARA EL\nEJERCICIO 2016\n7. Transparencia\n7.1. Difusión\nConforme a las disposiciones establecidas en el apartado de programas sujetos a Reglas de\nOperación del Decreto Número 170 del Presupuesto de Egresos del Estado de Guerrero para el Ejercicio\nFiscal 2016; estas Reglas de Operación, además de ser publicadas en el Periódico Oficial del Gobierno del\nEstado, estarán disponible para la población en general en las oficinas centrales y delegaciones regionales de la Secretaría de Asuntos Indígenas y Comunidades Afromexicanas, así como en la página electrónica del Gobierno del Estado: www.guerrero.gob.mx y www.asuntosindigenas.guerrero.gob.mx\n7.2. Seguimiento de avances físicos y financieros\nCon el propósito de mejorar la operación del programa, la Secretaría de Asuntos Indígenas y\nComunidades Afromexicanas llevará a cabo el seguimiento del ejercicio de recursos financieros, acciones ejecutadas, resultados, indicadores y metas alcanzadas; asimismo, realizará el seguimiento en campo de las acciones, conforme a lo que se determine.\nLa Secretaría de Asuntos Indígenas y Comunidades Afromexicanas deberá reportar trimestralmente a la Secretaría de Planeación y Desarrollo Regional (SEPLADER) y a la Secretaría de\nFinanzas y Administración (SEFINA), durante los primeros diez días hábiles del mes inmediato, posterior al trimestre que se reporta, los avances físico financieros de las acciones autorizadas.\nEn el caso de que la Secretaría de Planeación y Desarrollo Regional (SEPLADER) detecte información faltante, informará a la instancia ejecutora detalladamente y por escrito, la cual deberá presentar la información faltante en el plazo que se señala.\nPor otra parte, la Secretaría de Asuntos Indígenas y Comunidades Afromexicanas integrará el cierre de ejercicio y lo remitirá a la Secretaría de Finanzas y Administración (SEFINA), con un tanto original, misma que servirá para verificar la congruencia de la información con respecto a la cuenta pública.\n7.3. Evaluación\nLa Secretaría de Asuntos Indígenas y Comunidades Afromexicanas tendrá la obligación de revisar, de manera interna, la correcta operación y aplicación de las presentes reglas de operación y, en caso necesario, podrá solicitar una evaluación externa por parte de una instancia con experiencia en el tema. acciones de supervisión y evaluación para garantizar el adecuado desarrollo del Programa, a efecto de y Desarrollo Regional y de la Secretaría de Finanzas y Administración, a fin de cubrir rubros prioritarios, con recursos de este mismo programa o de otros que no hayan sido ejercidos en su momento, o bien que provengan de ahorros presupuestales.\nINDÍGENA Y FROMEXICANA (SIC) DE LA\nCOMUNIDADES AFROMEXICANAS, PARA EL\nEJERCICIO 2016\n7.4. Auditoria\nEste programa podrá ser auditado, a través de las instancias correspondientes en el ámbito de sus respectivas competencias del gobierno del estado, encargadas de vigilar la correcta aplicación de los recursos del erario público.\n7.5. Recursos no devengados\nEl presupuesto no ejercido al 31 de diciembre de 2016, será reintegrado a la Secretaría de\nFinanzas y Administración del Estado de Guerrero (SEFINA).\n7.6. Blindaje electoral\nComo estrategia de blindaje electoral, la papelería, documentación oficial, así como la publicidad y promoción del programa deberán incluir la siguiente leyenda:\n\"Este Programa es de carácter público, no es patrocinado ni promovido por partido político alguno y sus recursos provienen de los impuestos que pagan todos los contribuyentes. Está prohibido el uso de este programa con fines políticos, electorales, de lucro y otros distintos a los establecidos. Quien haga uso indebido de los recursos de este programa deberá ser denunciado y sancionado de acuerdo con la ley aplicable y ante la autoridad competente\".\nEn cuanto a la publicidad en medios electrónicos, impresos, complementarios o de cualquier otra índole, vinculados con los Programas de comunicación social, deberá incluirse la siguiente leyenda: \"Este\nPrograma es público y queda prohibido su uso con fines partidistas o de promoción personal\".\n7.7. Contraloría social\nLa Secretaría de Asuntos Indígenas y Comunidades Afromexicanas, como instancia ejecutora, promoverá la contraloría social, con base en la normatividad establecida para tal efecto, fomentando acciones que transparenten la operación del programa, tales como:\na) Informar a la ciudadanía acerca de los apoyos otorgados y su costo.\nb) Capacitar a los beneficiarios para que se constituyan en instancias de vigilancia y evaluación social.\nc) Establecer espacios de comunicación (reuniones vecinales, asambleas comunitarias, entre otros).\nd) Promover la integración de organizaciones de la sociedad civil para realizar acciones de contraloría social.\ne) Instrumentar mecanismos de recepción y atención de quejas y denuncias. El Órgano Estatal de\nControl verificará en lo correspondiente la realización de dichas acciones.\n7.8. Quejas y denuncias\nLas quejas, denuncias, peticiones y sugerencias relativas a este programa, se realizarán de manera escrita, por comparecencia del interesado, por correo electrónico o vía telefónica, y para aquellas\nINDÍGENA Y FROMEXICANA (SIC) DE LA\nCOMUNIDADES AFROMEXICANAS, PARA EL\nEJERCICIO 2016\nAsuntos Indígenas y Comunidades Afromexicanas, ubicadas en la ciudad de Chilpancingo, así como en las delegaciones regionales, situadas en las ciudades de Tlapa de Comonfort, Chilapa de Álvarez y\nOmetepec. El denunciante o quejoso deberá proporcionar los siguientes datos:\n-Nombre y domicilio -Identificación oficial\n-Nombre del servidor público denunciado\n-Objeto de la denuncia\n8. Criterios de selección y elegibilidad\n8.1. Método de selección de beneficiarios\n✓ Los beneficiarios del programa deberán cumplir con los siguientes criterios de elegibilidad:\n✓ Ser originarios de comunidades y municipios indígenas y afromexicanos, o autoadscribirse como tales, independientemente de su sexo, edad, filiación política y/o religiosa.\n✓ Ser autoridades comunitarias o gestores comunitarios, debidamente acreditados, que realicen gestiones en la ciudad de Chilpancingo, en beneficio de sus comunidades.\n✓ Ser jornaleros agrícolas migrantes en tránsito de sus comunidades a los campos de trabajo del interior o exterior del estado o del país, o que estén ya establecidos en dichos campos.\n✓ Solicitud por escrito dirigida al titular de la SAICA; en caso de emergencia la solicitud podrá ser verbal.\n✓ Las solicitudes se entregarán en las oficinas centrales de la SAICA, ubicadas en la ciudad de Chilpancingo, o en las delegaciones regionales de Tlapa de Comonfort, Chilapa de\nÁlvarez y Ometepec, en función del lugar donde ocurra el percance o contingencia.\n✓ Copia de identificación oficial del interesado(a) (credencial del INE, CURP, acta de nacimiento o constancia de identidad, avalada por la autoridad comunitaria).\n✓ Receta médica y factura originales que amparen los gastos por medicamentos, consulta o realización de estudios radiológicos o de laboratorio.\n✓ Acta de defunción original, en caso de solicitar ataúd.\n✓ Cuando el beneficiario directo se vea imposibilitado para acudir a las oficinas centrales o delegaciones regionales, podrá solicitar el apoyo un familiar o autoridad municipal o comunitaria, previa presentación de identificación oficial del gestor y del beneficiario.\n9. Mecánica de operación\n9.1. Instancia ejecutora programa Servicios Emergentes para Población Indígena y Afromexicana, a través de la Delegación\nAdministrativa, de acuerdo a los lineamientos establecidos en estas reglas de operación para el ejercicio fiscal 2016.\nINDÍGENA Y FROMEXICANA (SIC) DE LA\nCOMUNIDADES AFROMEXICANAS, PARA EL\nEJERCICIO 2016\n9.2. Instancia administrativa y normativa\nLa Secretaría de Planeación y Desarrollo Regional y la Secretaría de Contraloría y Transparencia\nGubernamental serán las instancias normativas y facultadas para autorizar y verificar la aplicación de las reglas de operación, y resolver los casos no previstos en las mismas.\n9.3. Delimitación de atribuciones\nLa Secretaría de Asuntos Indígenas y Comunidades Afromexicanas ejecutará las acciones del presente programa, conforme al marco jurídico y normativo de la administración pública estatal y a las reglas de operación, una vez que la Secretaría de Finanzas y Administración libere los recursos destinados para este programa, dando cumplimiento a los lineamientos de la Secretaría de Planeación y Desarrollo\nRegional y de la Secretaría de Contraloría y Transparencia Gubernamental.\n10. Derechos, obligaciones y sanciones de los beneficiarios de programas sociales\n10.1. Derechos\n✓ Recibir los beneficios que otorga este programa, aún a través de un familiar o representante, cuando el caso emergente así lo amerite.\n✓ Recibir un trato digno, respetuoso y oportuno, sin discriminación alguna.\n\"Reserva y privacidad de los datos personales.\n10.2. Obligaciones\n✓ Conducirse con la verdad en toda la información solicitada.\n✓ Emplear el apoyo recibido para los fines por los que fue otorgado.\n✓ Entregar la documentación e información requeridas, de acuerdo a las Reglas de Operación.\n10.3. Sanciones información falsa.\n11. Interpretación\nEl programa estará a cargo de la Secretaría de Asuntos Indígenas y Comunidades Afromexicanas, y sus acciones se desarrollarán bajo las reglas de operación respectivas, que entrarán en vigor el día\nINDÍGENA Y FROMEXICANA (SIC) DE LA\nCOMUNIDADES AFROMEXICANAS, PARA EL\nEJERCICIO 2016\nLIC. FELIPE SÁNCHEZ RAMÍREZ, DIRECTOR GENERAL DE LA DEFENSA Y ASESORÍA\nJURÍDICA DE LA SECRETARÍA DE ASUNTOS INDÍGENAS Y COMUNIDADES AFROMEXICANAS DEL\nGOBIERNO DEL ESTADO DE GUERRERO; DE CONFORMIDAD CON LO ESTABLECIDO EN EL\nNUMERAL 32, FRACCIÓN XVIII, DE LA LEY ORGÁNICA DE LA ADMINISTRACIÓN PÚBLICA DEL\nESTADO DE GUERRERO NÚMERO 08, ASÍ COMO EL NUMERAL 16 FRACCIONES V, XXI Y XXII DEL\nREGLAMENTO INTERNO VIGENTE DE ESTA DEPENDENCIA.\nHAGO CONSTAR Y CERTIFICO\nQUE LAS PRESENTES COPIAS FOTOSTÁTICAS, COMPUESTAS DE 19 FOJAS ÚTILES SON\nSECRETARÍA, MISMAS QUE SE EXPIDEN PARA LOS USOS LEGALES A QUE HAYA LUGAR, EN LA\nATENTAMENTE.\nLIC. FELIPE SÁNCHEZ RAMÍREZ.\nDIRECTOR GENERAL DE LA DEFENSA Y ASESORÍA JURÍDICA.\nRúbrica.",
  "ordenamiento": "REGLA",
  "jurisdiccion": "GUERRERO",
  "fuente_oficial": "DIARIO OFICIAL DE LA FEDERACION",
  "Fecha de Publicación": "28 DE ABRIL DE \n2017",
  "ULTIMA REFORMA PUBLICADA": "28 DE ABRIL DE 2017",
  "status": "VIGENTE",
  "es_escaneado": false,
  "tiene_tablas": true,
  "materia": [
    "general"
  ]
}