{
  "titulo": "Acuerdo Mediante el Cual Se Emiten las Reglas de Operación del Programa 5. Fortalecimiento de las Cu",
  "Contenido": "IDENTIDADES INDÍGENAS Y AFROMEXICANAS DE LA\nCOMUNIDADES AFROMEXICANAS, PARA EL\nEJERCICIO 2016\nÍndice\n1. Introducción....................................................................................................................................... 6\n2. Objetivos............................................................................................................................................ 6\n2.1. Objetivo General............................................................................................................................. 6\n2.2. Objetivos Específicos...................................................................................................................... 7\n2.3. Población objetivo........................................................................................................................... 7\n3. Misión................................................................................................................................................ 7\n4. Visión................................................................................................................................................. 7\n5. Reglas de operatividad...................................................................................................................... 7\n5.1. Lineamientos generales.................................................................................................................. 7\n5.1.1. Fundamento legal........................................................................................................................ 9\n5.1.2. Participantes................................................................................................................................ 9\n5.1.3. Patrimonio del programa.............................................................................................................. 9\n5.1.4. Tipos de apoyo............................................................................................................................ 9\n6. Información del Programa.................................................................................................................. 10\n6.1. Exposición del programa................................................................................................................. 10\n6.2. Cobertura........................................................................................................................................ 10\n6.3. Modos de entrega del beneficio...................................................................................................... 11\n6.4. Gastos de operación....................................................................................................................... 11\n7. Transparencia.................................................................................................................................... 11\n7.1. Difusión........................................................................................................................................... 11\nIDENTIDADES INDÍGENAS Y AFROMEXICANAS DE LA\nCOMUNIDADES AFROMEXICANAS, PARA EL\nEJERCICIO 2016\n7.2. Seguimiento de avances físicos y financieros................................................................................. 12\n7.3. Evaluación...................................................................................................................................... 12\n7.4. Auditoría......................................................................................................................................... 13\n7.5. Recursos no devengados................................................................................................................ 13\n7.6. Blindaje electoral............................................................................................................................. 13\n7.7. Contraloría social............................................................................................................................ 13\n7.8. Quejas y denuncias......................................................................................................................... 13\n8. Criterios de selección y elegibilidad................................................................................................... 14\n8.1. Método de selección de beneficiarios............................................................................................. 14\n9. Mecánica de operación...................................................................................................................... 14\n9.1. Instancia ejecutora.......................................................................................................................... 14\n9.2. Instancia administrativa y normativa............................................................................................... 14\n9.3. Delimitación de atribuciones........................................................................................................... 14\n10. Derechos, obligaciones y sanciones de los beneficiarios de programas sociales............................. 15\n10.1. Derechos...................................................................................................................................... 15\n10.2. Obligaciones................................................................................................................................. 15\n10.3. Sanciones..................................................................................................................................... 15\n11. Interpretación................................................................................................................................... 15\nIDENTIDADES INDÍGENAS Y AFROMEXICANAS DE LA\nCOMUNIDADES AFROMEXICANAS, PARA EL\nEJERCICIO 2016\nABROGADO POR CONCLUIDA SU VIGENCIA TÁCITAMENTE EL 31 DE DICIEMBRE 2016.\nTEXTO ORIGINAL.\nAcuerdo publicados en el Periódico Oficial del Gobierno del Estado No. 61 Alcance I, el Viernes\n29 de Julio de 2016.\nACUERDO MEDIANTE EL CUAL SE EMITEN LAS REGLAS DE OPERACIÓN DEL PROGRAMA 5.\nFORTALECIMIENTO DE LAS CULTURAS E IDENTIDADES INDÍGENAS Y AFROMEXICANAS DE LA\nSECRETARÍA DE ASUNTOS INDÍGENAS Y COMUNIDADES AFROMEXICANAS, PARA EL\nEJERCICIO 2016.\nLIC. GILBERTO SOLANO ARREAGA, Secretario de Asuntos Indígenas y Comunidades\nAfromexicanas, con fundamento en los Artículos 11, 14 y 16 de la Ley Orgánica de la Administración Pública del Estado de Guerrero número 8, y el artículo 32 de la Ley en referencia por el que se crea la Secretaría de Asuntos Indígenas y Comunidades Afromexicanas, publicado en el Periódico Oficial del Gobierno del\nEstado de Guerrero, número 85, de fecha 23 de Octubre de 2015, y\nCONSIDERANDO\nQue en el Decreto número 170 del Presupuesto de Egresos del Estado de Guerrero, para el\nEjercicio Fiscal 2016, se señala que se ejercitarán los recursos bajo una política de gasto público que permita dar cumplimiento a los seis ejes rectores del Plan Estatal de Desarrollo 2016 - 2021. Las políticas encaminadas a desarrollo social, se orientaron a los sectores desprotegidos del estado y a programas sociales.\nQue dentro de las políticas de Desarrollo Social la Secretaría de Asuntos Indígenas y\nComunidades Afromexicanas, implementará el Programa: 5. Fortalecimiento de las Culturas e\nIdentidades Indígenas y Afromexicana, a fin de contribuir a la mejora de la calidad de vida de cada uno de las y los beneficiarios, mismo que se enmarca en el Eje VI. Estrategias Transversales, específicamente en la Estrategia 4. Atender a los Pueblos Originarios y Afromexicano, y en el Eje III, Objetivo 3.1. Garantizar el ejercicio efectivo de los derechos sociales para toda la población.\nPor lo anterior expuesto y con fundamento en las disposiciones legales antes citadas, he tenido a bien expedir el siguiente:\nEJERCICIO FISCAL 2016.\nIDENTIDADES INDÍGENAS Y AFROMEXICANAS DE LA\nCOMUNIDADES AFROMEXICANAS, PARA EL\nEJERCICIO 2016\nÚnico: se emiten las Reglas de Operación del Programa 5. Fortalecimiento de las Culturas e\nIdentidades Indígenas y Afromexicana, que implementará la Secretaría de Asuntos Indígenas y\nComunidades Afromexicanas, para el Ejercicio Fiscal 2016.\nTRANSITORIOS\nPrimero.- El presente acuerdo entrará en vigor al día siguiente de su publicación en el Periódico\nOficial del Gobierno del Estado de Guerrero.\nSegundo.- Las Reglas de Operación de los Programas de la Secretaría de Asuntos Indígenas y\nComunidades Afromexicanas: 5. Fortalecimiento de las Culturas e Identidades Indígenas y Afromexicana, para el Ejercicio Fiscal 2016, se publican en su totalidad.\nDado en la ciudad de Chilpancingo de los Bravo, Guerrero, a los dieciocho días del mes de marzo de dos mil dieciséis.\nEL SECRETARIO DE ASUNTOS INDÍGENAS Y COMUNIDADES AFROMEXICANAS.\nLIC. GILBERTO SOLANO ARREAGA.\nRúbrica.\nÍndice\n1. Introducción.\n2. Objetivos.\n2.1. General\n2.2. Especifico\n2.3. Población objetivo\n3. Misión.\n4. Visión.\n5. Reglas de operatividad.\n5.1 Lineamientos generales\n5.1.1. Fundamento legal\n5.1.2 Participantes\n5.1.3. Patrimonio del programa\n5.1.4. Tipos de apoyo\n6. Información del Programa.\nIDENTIDADES INDÍGENAS Y AFROMEXICANAS DE LA\nCOMUNIDADES AFROMEXICANAS, PARA EL\nEJERCICIO 2016\n6.1. Exposición del Programa\n6.2. Cobertura\n6.3. Modos de entrega del beneficio\n6.4. Gastos de operación\n7. Transparencia.\n7.1. Difusión\n7.2. Seguimiento de avances físicos y financieros\n7.3. Evaluación\n7.4. Auditoria\n7.5. Recursos no devengados\n7.6. Blindaje electoral\n7.7. Contraloría social\n7.8. Quejas y denuncias\n8. Criterios de selección y elegibilidad.\n8.1. Método de selección de beneficiarios\n9. Mecánica de operación.\n9.1. Instancia ejecutora\n9.2. Instancia administrativa y normativa\n9.3. Delimitación de atribuciones\n10. Derechos, obligaciones y sanciones de los beneficiarios de programas sociales.\n10.1. Derechos\n10.2. Obligaciones\n10.3. Sanciones\n11. Interpretación.\nIDENTIDADES INDÍGENAS Y AFROMEXICANAS DE LA\nCOMUNIDADES AFROMEXICANAS, PARA EL\nEJERCICIO 2016\n1. Introducción\nEl reconocimiento de las culturas y las identidades de los pueblos indígenas y afromexicano es fundamental para la construcción de una sociedad democrática y respetuosa de la diversidad, basada en el respeto y el ejercicio de los derechos políticos, culturales y económicos de todas y todos los guerrerenses.\nEsta importante diversidad social determina el carácter pluricultural y multilingüe del estado de\nGuerrero, sustentado principalmente en los pueblos indígenas Nahua, Na savi (mixteco), Me'pha\n(tlapaneco) y Nn'anncue Ñomdaa (amuzgo), así como el pueblo afromexicano. No obstante que estos cinco pueblos comparten algunos rasgos culturales, cada uno de ellos guarda su propia cultura e identidad que los define, diferencia y, paralelamente, los hace reconocerse como tales.\nEste patrimonio cultural tangible e intangible que durante siglos ha sido atesorado en el territorio guerrerense, constituye un factor activo y dinámico en el desarrollo y progreso de los pueblos originarios, por lo que no podemos aspirar a un desarrollo sin una política basada en el reconocimiento, respeto y fomento de las culturas indígenas y afromexicana.\nCon estas reglas de operación del Programa Fortalecimiento de las Culturas e Identidades\nIndígenas y Afromexicanas, la Secretaría de Asuntos Indígenas y Comunidades Afromexicanas (SAICA), norma los mecanismos, servicios y apoyos orientados a propiciar el impulso y fortalecimiento de la cultura, la identidad y el tejido social de las comunidades y pueblos indígenas y afromexicano, con lo cual se alinea dicho programa al Plan Estatal de Desarrollo 2016-2021, específicamente al Eje VI, Estrategia 6.4.1, la cual establece la atención de los pueblos indígenas y afromexicano, a fin de generar oportunidades que permitan su desarrollo económico, político y social; asimismo la SAICA asume su papel de promotora y difusora de las culturas indígenas y afro-mexicana. identitario de los cinco pueblos, se hará un especial énfasis en promover la revitalización cultural indígena y la reafirmación de la identidad afromexicana. Lo anterior en razón de que el pueblo afromexicano, a diferencia de los cuatro pueblos indígenas, recién en los últimos treinta años transita en un proceso de reconocimiento, reivindicación y auto adscripción, cuyos resultados positivos se han reflejado en su inclusión dentro de la Constitución local y en la Encuesta Intercensal 2015 del INEGI, que por primera vez considera en sus registros a la población afromexicana.\n2. Objetivos\n2.1. Objetivo General\nIDENTIDADES INDÍGENAS Y AFROMEXICANAS DE LA\nCOMUNIDADES AFROMEXICANAS, PARA EL\nEJERCICIO 2016\nImpulsar procesos y acciones que impacten en la creatividad, revaloración y fortalecimiento del patrimonio cultural y las identidades de los pueblos indígenas y afromexicano, para propiciar el reconocimiento de la diversidad y un diálogo intercultural entre la sociedad guerrerense.\n2.2. Objetivos Específicos\n✓ Acompañar a las Academias de las Lenguas Indígenas en la gestión y creación del Instituto de las\nLenguas Indígenas del Estado de Guerrero.\n✓ Impulsar y difundir las diferentes expresiones artísticas y culturales de los pueblos indígenas y afromexicano, a través de documentales, publicaciones y festivales regionales y estatales que muestren los valores intangibles de estos pueblos.\n✓ Contribuir al fortalecimiento de la identidad afromexicana, a través de estrategias y acciones que propicien la auto adscripción y la revaloración cultural.\n2.3. Población objetivo\nLos beneficiarios del presente programa son jóvenes, adultos y personas de la tercera edad, pertenecientes a los pueblos nahua, Me'phaa (tlapaneco), na savi (mixteco), nancue ñomnda (amuzgo) y afromexicano que habiten en el estado de Guerrero, con prioridad a los que habiten en los 48 municipios con preponderancia o presencia indígena y afromexicana, y estén organizados en grupos de danza, bandas de música de viento u otras agrupaciones artísticas; promotores culturales, terapeutas tradicionales y otros creadores y reproductores culturales, que no hayan sido beneficiados por la SAICA con ningún tipo de bien o apoyo cultural en los últimos tres años. Las personas que resulten beneficiarias de este programa no podrán tener acceso a los bienes de otros programas que implementa la SAICA.\n3. Misión\nPromover y coordinar la política pública del Gobierno del Estado en favor de la diversidad cultural de los pueblos indígenas y afromexicano, a través del impulso y difusión de sus expresiones artísticas y culturales y la reafirmación de sus identidades, considerando estos valores y atributos como parte esencial de su desarrollo económico y social.\n4. Visión\nSer un programa que acompañe los procesos de producción, promoción y autogestión de los grupos culturales indígenas y afromexicanos, y coadyuve en la revitalización de sus culturas e identidades, considerando a la cultura no sólo como un bien de consumo, sino como un acervo integrador y creativo, y un emergente personal y social.\n5. Reglas de operatividad\n5.1. Lineamientos generales y afromexicanos que realizan actividades en las diferentes expresiones culturales y artísticas. Las etapas y procedimientos que deberán seguir, son los siguientes:\nIDENTIDADES INDÍGENAS Y AFROMEXICANAS DE LA\nCOMUNIDADES AFROMEXICANAS, PARA EL\nEJERCICIO 2016\nEdición y publicación de libros\n✓ Los creadores y creadoras indígenas y afromexicanos (as) que aspiren a recibir apoyo para la publicación de algún texto de su autoría, deberán entregar solicitud por escrito, dirigida al titular de la\nSAICA, y entregar el trabajo en versión impresa y electrónica, en la Dirección General de Promoción y\nDifusión Cultural, instancia que será la responsable de seleccionar el trabajo a publicar.\n✓ Una vez dictaminada positivamente la impresión y publicación del texto, el autor (a) realizará una carta compromiso con la SAICA, para recibir como retribución el 5% del tiraje total del libro, bajo el compromiso de distribuirlo en bibliotecas, escuelas y comunidades interesadas, sin fines de lucro.\n✓ La publicación del libro tendrá un tiempo de cuatro meses, a partir de la fecha en que fue aceptado.\n✓ En caso de que la SAICA juzgue que ningún trabajo presentado reúne los requisitos de calidad y pertinencia necesarios, podrá publicar otra obra no dictaminada o aplicar el recurso en otra acción relacionada con la cultura.\nTalleres de capacitación para la reparación de instrumentos musicales\n✓ Solicitud escrita, dirigida al titular de la SAICA, especificando las comunidades y el municipio, así como el número de músicos que requieren la capacitación y el nombre y firma del representante.\n✓ El titular o el Director General de Difusión y Promoción Cultural darán respuesta por escrito a la solicitud.\n✓ En caso de que la respuesta sea afirmativa, se procederá a establecer, de común acuerdo, la sede y fecha del taller.\n✓ Para la realización del taller, la SAICA cubrirá los honorarios del instructor y brindará los materiales e insumos necesarios, así como la alimentación y un apoyo económico para el traslado de los participantes durante los días que dure la capacitación.\n✓ El grupo beneficiario deberá contribuir con el local en donde se desarrollará el taller, y con el mobiliario.\nDonación de Instrumentos musicales y vestuario para grupos de danzas tradicionales\n✓ Solicitud por escrito, dirigida al titular de la SAICA, en la que se asiente el tipo de apoyo requerido.\nLa petición podrá presentarse en las oficinas centrales, ubicadas en la ciudad de Chilpancingo, o en las\nDelegaciones Regionales situadas en las ciudades de Tlapa, Chilapa y Ometepec\n✓ Las bandas de música de viento y los grupos de danza deberán demostrar, mediante constancia expedida por la autoridad comunitaria, que el grupo cumple con una función de beneficio para su comunidad.\n✓ La SAICA analizará las solicitudes y determinará, de acuerdo al techo presupuestal del programa, los requisitos de elegibilidad para recibir el apoyo, el cual será en especie.\n✓ La SAICA notificará a los grupos beneficiarios, por escrito, vía telefónica o correo electrónico, la aprobación de su solicitud, en un término de sesenta días hábiles, posteriores a la recepción de la misma.\n✓ Los responsables de los grupos beneficiarios y sus autoridades comunitarias deberán firmar una\nCarta Compromiso, donde se destaque la obligación de brindar un buen cuidado a los bienes recibidos,\nIDENTIDADES INDÍGENAS Y AFROMEXICANAS DE LA\nCOMUNIDADES AFROMEXICANAS, PARA EL\nEJERCICIO 2016 participar en las festividades y ceremonias comunitarias, así como reintegrar los bienes a las autoridades locales, en caso de desintegración del grupo, para ser reasignados a otra agrupación.\n5.1.1. Fundamento legal\n✓ Constitución Política de los Estados Unidos Mexicanos (artículo 2). artículo 11, fracción V).\n✓ Ley Orgánica de la Administración Pública del Estado de Guerrero Número 08 (artículo 32).\n✓ Ley número 701 de Reconocimiento, Derechos y Cultura Indígena de los Pueblos y Comunidades\nIndígenas de Guerrero.\n✓ Decreto Número 170 del Presupuesto de Egresos del Estado de Guerrero para el Ejercicio Fiscal\n2016.\n✓ Convenio 169 sobre Pueblos Indígenas y Tribales, de la Organización Internacional del Trabajo.\n✓ Declaración Universal de las Naciones Unidas sobre los Derechos de los Pueblos Indígenas.\n5.1.2. Participantes\nLa Secretaría de Asuntos Indígenas y Comunidades Afromexicanas; instituciones federales, estatales y municipales, principalmente las relacionadas con la promoción y difusión de las culturas indígenas y afromexicana; así como personas y grupos indígenas y afromexicanos que realizan actividades relacionadas con sus expresiones artísticas y culturales.\n5.1.3. Patrimonio del programa\nEl programa Fortalecimiento de las Culturas e Identidades Indígenas y Afromexicana tiene asignado un presupuesto financiero de $2'271,250.00 (dos millones doscientos setenta y un mil doscientos cincuenta pesos 00/100 M.N.), para ser ejercido en el presente ejercicio fiscal 2016, teniendo como fuente de financiamiento la Inversión Estatal Directa. Este recurso deberá ser destinado a la realización de las acciones en beneficio de la población indígena y afromexicana.\n5.1.4. Tipos de apoyo\n✓ Publicación de 1 libro y 4 folletos para la difusión de expresiones artísticas y culturales.\n✓ Realización de 4 talleres para la reparación de instrumentos musicales.\n✓ Dotación de 66 instrumentos musicales para bandas de música de viento.\n✓ Dotación de insumos para la confección de vestuario para 20 grupos de danza tradicionales.\n✓ Realización de 2 talleres de capacitación para los recursos humanos comunitarios de atención a la salud (médicos tradicionales y parteras).\nAsimismo, el programa contempla la realización de diversas actividades y actos orientados al impulso, promoción, difusión y fortalecimiento de las culturas indígenas y afromexicana, tales como:\nIDENTIDADES INDÍGENAS Y AFROMEXICANAS DE LA\nCOMUNIDADES AFROMEXICANAS, PARA EL\nEJERCICIO 2016\n✓ Acompañamiento y gestión para la creación del Instituto de Lenguas Indígenas del Estado de\nGuerrero.\n✓ Realización de 2 documentales sobre los pueblos indígenas y afromexicano en las cuatro lenguas originarias.\n✓ Realización de 3 festivales para la promoción y difusión de las culturas indígenas y afromexicana, y para el fortalecimiento de sus identidades.\n✓ Realización de 3 eventos conmemorativos relacionados con los pueblos Indígenas y afromexicano.\n6. Información del Programa\nLa difusión del programa denominado Fortalecimiento de las Culturas e Identidades Indígenas y\nAfromexicana, se realizará mediante trípticos, y en las siguientes páginas electrónicas: www.guerrero.gob.mx y www.asuntosindigenas.guerrero.gob.mx\n6.1. Exposición del programa\nSe brindan bienes y apoyos a personas y grupos indígenas y afromexicanos que realizan acciones para la preservación y difusión de sus expresiones artísticas y culturales, tales como: lenguas indígenas, música, danza, medicina tradicional, historia comunitaria y creación literaria. Asimismo, mediante diferentes actividades y actos se promueven las culturas indígenas y afromexicana, y se fortalecen y revitalizan sus identidades culturales.\n6.2. Cobertura\nLas acciones de este programa beneficiarán a la población indígena y afromexicana que se ubica en los 81 municipios del estado, con prioridad a la que habita en 48 municipios con preponderancia o presencia indígena y afromexicana.\nMUNICIPIOS PRIORITARIOS\nMONTAÑA COSTA CHICA CENTRO\n1. Acatepec 1. Ayutla de los Libres 1. Ahuacuotzingo\n2. Alcozauca de Guerrero 2. Igualapa 2. Eduardo Neri\n3. Alpoyeca 3. San Luis Acatlán 3. Chilapa de Álvarez\n4. Atlamajalcingo del Monte 4. Tlacoachistlahuaca 4. Chilpancingo de los Bravo\n5. Atlixtac 5. Xochistlahuaca 5. José Joaquín de Herrera\n6. Cochoapa el Grande Municipios Afromexicanos 6. Mártir de Cuilapan\n7. Copanatoyac 6. Azoyú 7. Tixtla de Guerrero\n8. Cualác 7. Copala 8. Zitlala\n9. Huamuxtitlan 8. Cuajinicuilapa NORTE\n10. Iliatenco 9. Cuautepec 1. Copalillo\n11. Malinaltepec 10. Florencio Villarreal 2. Huitzuco de los Figueroa\nIDENTIDADES INDÍGENAS Y AFROMEXICANAS DE LA\nCOMUNIDADES AFROMEXICANAS, PARA EL\nEJERCICIO 2016\n12. Metlatónoc 11. Juchitán 3. Iguala de la Independencia\n13. Olinalá 12. Marquelia 4. Taxco de Alarcón\n14. Tlacoapa 13. Ometepec 5. Tepecoacuilco de Trujano\n15. Tlapa de Comonfort 14. San Marcos ACAPULCO\n16. Tlalixtaquilla 15. Tecoanapa 1. Acapulco de Juárez\n17. Xalpatláhuac\n18. Xochihuehietlan\n19. Zapotitlán Tablas\n6.3. Modos de entrega del beneficio\n✓ Los instrumentos musicales y vestuario para grupos de danza, se entregarán solamente en especie y no en efectivo.\n✓ La entrega de instrumentos y vestuario se realizará en las comunidades, delegaciones regionales u oficinas centrales de la SAICA.\n✓ En los talleres de capacitación se proporcionará, según el caso, alimentación, hospedaje y pago en efectivo de pasajes.\n✓ En el caso de la impresión y publicación de textos, los autores firmarán un convenio con la\nSAICA, y recibirán como retribución el 5% del tiraje total, bajo el compromiso de distribuir el material en bibliotecas, escuelas y comunidades interesadas, sin fines de lucro.\n✓ Los (as) terapeutas tradicionales recibirán capacitación, materiales y utensilios para la preparación de medicamentos herbolarios, los cuales se distribuirán equitativamente, con la finalidad de establecer en sus hogares pequeñas farmacias comunitarias, sin fines de lucro.\n6.4. Gastos de operación\nEn cumplimiento al artículo 47 de la Ley de Coordinación Fiscal, podrá aplicarse hasta un 3% del presupuesto total del programa, a gastos de operación y realización de diversas acciones, asociadas con la planeación, operación, supervisión, seguimiento, contraloría social y evaluación o asesoría externa del programa.\n✓ Materiales, útiles y equipos menores de oficina: hasta un monto de $5,000.00/ paquete.\n✓ Materiales y útiles de impresión y reproducción: hasta un monto de $5,000.00/paquete.\n✓ Servicios de apoyo administrativo, fotocopiado e impresión:\n- Lona: hasta por un monto de $1,200.00/pieza.\n- Fotocopias: hasta por un monto de $1.00/pieza.\n✓ Viáticos: de acuerdo a la tarifa establecida por la Secretaría de Finanzas y Administración. Se ejercerán para las actividades de promoción, ejecución, capacitación y difusión del programa.\n✓ Combustibles, lubricantes y aditivos: hasta un monto de $14.00/litro\n✓ Peaje: hasta por un monto de $520/viaje.\n7. Transparencia\n7.1. Difusión\nIDENTIDADES INDÍGENAS Y AFROMEXICANAS DE LA\nCOMUNIDADES AFROMEXICANAS, PARA EL\nEJERCICIO 2016\nOperación del Decreto Número 170 del Presupuesto de Egresos del Estado de Guerrero para el Ejercicio\nFiscal 2016; estas Reglas de Operación, además de ser publicadas en el Periódico Oficial del Gobierno del\nEstado, estarán disponible para la población en general en las oficinas centrales y delegaciones regionales de la SAICA, así como en la página electrónica del Gobierno del Estado: www.guerrero.gob.mx y www.asuntosindigenas.guerrero.gob.mx\n7.2. Seguimiento de avances físicos y financieros\nEl resultado final de este programa debe cumplir con sus objetivos, dando respuesta a las demandas de los pueblos indígenas y afromexicano, relacionadas con el fortalecimiento de sus culturas e identidades, así como con su efectiva participación en los programas y acciones institucionales.\nLa ejecución del programa Fortalecimiento de las Culturas e Identidades Indígenas y\nAfromexicana, que implementa la SAICA, estará a cargo de la Dirección General de Promoción y Difusión\nCultural, y el financiamiento del programa será ministrado y comprobado por la Delegación Administrativa, mismo que reportará a la Secretaría de Finanzas y Administración, Secretaría de Contraloría y\nTransparencia Gubernamental y a la Secretaría de Planeación y Desarrollo Regional los informes sobre el presupuesto ejercido y en base a los indicadores de resultados, a más tardar a los quince días hábiles posteriores a la terminación de cada trimestre.\nTodos los gastos generados en cada una de las actividades y acciones estarán soportados con la comprobación respectiva.\n7.3. Evaluación\nCon el propósito de mejorar la operación del programa, la Secretaría de Asuntos Indígenas y\nComunidades Afromexicanas llevará a cabo el seguimiento del ejercicio de recursos financieros, acciones ejecutadas, resultados, indicadores y metas alcanzadas; asimismo, realizará el seguimiento en campo de las acciones, conforme a lo que se determine.\nLa Secretaría de Asuntos Indígenas y Comunidades Afromexicanas deberá reportar trimestralmente a la Secretaría de Planeación y Desarrollo Regional (SEPLADER) y a la Secretaría de\nFinanzas y Administración (SEFINA), durante los primeros diez días hábiles del mes inmediato, posterior al trimestre que se reporta, los avances físico financieros de las acciones autorizadas.\nPor otra parte, la Secretaría de Asuntos Indígenas y Comunidades Afromexicanas integrará el cierre de ejercicio y lo remitirá a la Secretaría de Finanzas y Administración (SEFINA), con un tanto original, misma que servirá para verificar la congruencia de la información con respecto a la cuenta pública.\nLa SAICA tendrá la obligación de revisar, de manera interna, la correcta operación y aplicación de las presentes reglas de operación y, en caso necesario, podrá solicitar una evaluación externa por parte de una instancia con experiencia en el tema.\nIDENTIDADES INDÍGENAS Y AFROMEXICANAS DE LA\nCOMUNIDADES AFROMEXICANAS, PARA EL\nEJERCICIO 2016 adecuado desarrollo del Programa, a efecto de corregir desfases o efectuar reasignaciones financieras con la autorización de la Secretaría de Desarrollo Regional o de la Secretaría de Finanzas y Administración, a fin de cubrir rubros prioritarios, con recursos de este mismo programa o de otros que no hayan sido ejercidos en su momento, o bien que provengan de ahorros presupuestales.\n7.4. Auditoría\nEste programa podrá ser auditado, a través de las instancias del gobierno del estado encargadas de vigilar la correcta aplicación de los recursos del erario público.\n7.5. Recursos no devengados\nEl presupuesto no ejercido al 31 de diciembre de 2016, será reintegrado a la Secretaría de\nFinanzas y Administración del Estado de Guerrero (SEFINA).\n7.6. Blindaje electoral\nComo estrategia de blindaje electoral, la papelería, documentación oficial, así como la publicidad y promoción del programa deberán incluir la siguiente leyenda:\n\"Este Programa es de carácter público, no es patrocinado ni promovido por partido político alguno y sus recursos provienen de los impuestos que pagan todos los contribuyentes. Está prohibido el uso de este programa con fines políticos, electorales, de lucro y otros distintos a los establecidos. Quien haga uso indebido de los recursos de este programa deberá ser denunciado y sancionado de acuerdo con la ley aplicable y ante la autoridad competente\".\nEn cuanto a la publicidad en medios electrónicos, impresos, complementarios o de cualquier otra índole, vinculados con los Programas de comunicación social, deberá incluirse la siguiente leyenda: \"Este\nPrograma es público y queda prohibido su uso con fines partidistas o de promoción personal\".\n7.7. Contraloría social\nLa SAICA, como instancia ejecutora, promoverá la contraloría social, con base en la normatividad establecida para tal efecto, fomentando acciones que transparenten la operación del programa, tales como:\na) Informar a la ciudadanía acerca de los apoyos otorgados y su monto.\nb) Capacitar a los beneficiarios para que se constituyan en instancias de vigilancia y evaluación social.\nc) Establecer espacios de comunicación (reuniones vecinales, asambleas comunitarias, entre otros).\nd) Promover la integración de organizaciones de la sociedad civil para realizar acciones de contraloría social.\ne) Instrumentar mecanismos de recepción y atención de quejas y denuncias. El Órgano Estatal de\nControl verificará en lo correspondiente la realización de dichas acciones.\nIDENTIDADES INDÍGENAS Y AFROMEXICANAS DE LA\nCOMUNIDADES AFROMEXICANAS, PARA EL\nEJERCICIO 2016\n7.8. Quejas y denuncias\nLas quejas, denuncias, peticiones y sugerencias relativas a este programa, se realizarán de manera escrita, por comparecencia del interesado, por correo electrónico o vía telefónica; para aquellas que sean escritas deberán depositarse en los buzones instalados en las oficinas centrales de la SAICA, ubicadas en la ciudad de Chilpancingo, así como en las delegaciones regionales, situadas en las ciudades de Tlapa de Comonfort, Chilapa de Álvarez y Ometepec. La o el denunciante deberá proporcionar los siguientes datos:\n- Nombre y domicilio\n- Identificación oficial\n- Nombre del servidor público denunciado\n- Objeto de la denuncia\n8. Criterios de selección y elegibilidad\n8.1. Método de selección de beneficiarios\nLos beneficiarios del programa deberán cumplir con los siguientes criterios de elegibilidad:\n✓ Ser originarios de comunidades y municipios indígenas y afromexicanos, o autoadscribirse como tales, independientemente de su sexo, edad, filiación política y/o religiosa.\n✓ En el caso de solicitar instrumentos musicales y vestuario, deberá demostrarse, mediante constancia expedida por la autoridad local, que el grupo cumple con una función de beneficio para su comunidad.\n✓ No haber sido beneficiados con instrumentos musicales, vestuario de danzas u otro tipo de bien cultural en los últimos 3 años, ya sea por la SAICA o por otra institución federal, estatal o municipal.\n9. Mecánica de operación\n9.1. Instancia ejecutora\nLa Secretaría de Asuntos Indígenas y Comunidades Afromexicanas será la instancia ejecutora del programa Fortalecimiento de las Culturas e Identidades Indígenas y Afromexicana, a través de la Dirección\nGeneral de Promoción y Difusión Cultural de acuerdo a los lineamientos establecidos en estas reglas de operación para el ejercicio fiscal 2016.\n9.2. Instancia administrativa y normativa recursos.\n9.3. Delimitación de atribuciones reglas de operación, una vez que la Secretaría de Finanzas y Administración libere los recursos destinados\nIDENTIDADES INDÍGENAS Y AFROMEXICANAS DE LA\nCOMUNIDADES AFROMEXICANAS, PARA EL\nEJERCICIO 2016 para este programa, dando cumplimiento a los lineamientos de la Secretaría de Planeación y Desarrollo\nRegional y de la Secretaría de Contraloría y Transparencia Gubernamental.\n10. Derechos, obligaciones y sanciones de los beneficiarios de programas sociales.\n10.1. Derechos\n✓ La población indígena y afromexicana tendrá derecho a los beneficios que otorga este programa, siempre y cuando cumplan con los requisitos que para tal efecto se han establecido.\n✓ Solicitar información a la SAICA sobre el estado que guarda el proceso de autorización de su solicitud.\n✓ Recibir asesoría o información necesaria respecto a la aplicación de los recursos autorizados.\n✓ Recibir los apoyos que hayan sido autorizados.\n10.2. Obligaciones\n✓ Conducirse con la verdad en toda la información solicitada. ü Emplear el bien o apoyo recibido para los fines por los que fue otorgado.\n✓ Entregar la documentación e información requeridas, de acuerdo a las reglas de operación.\n✓ Firmar la Carta-Compromiso con la SAICA, en los casos de instrumentos musicales y vestuario de danza.\n✓ Comprometerse a conservar los instrumentos musicales en condiciones favorables, mínimamente dos años\n✓ Informar a la SAICA, a través de sus oficinas centrales o delegaciones regionales, cuando se presente algún suceso que evite la correcta aplicación de los recursos asignados al proyecto.\n10.3. Sanciones previsto en las reglas de operación de este programa.\n11. Interpretación\nEl programa estará a cargo de la Secretaría de Asuntos Indígenas y Comunidades Afromexicanas, y sus acciones se desarrollarán bajo las reglas de operación respectivas, las cuales entrarán en vigor el\nIDENTIDADES INDÍGENAS Y AFROMEXICANAS DE LA\nCOMUNIDADES AFROMEXICANAS, PARA EL\nEJERCICIO 2016\nLIC. FELIPE SÁNCHEZ RAMÍREZ, DIRECTOR GENERAL DE LA DEFENSA Y ASESORÍA\nJURÍDICA DE LA SECRETARÍA DE ASUNTOS INDÍGENAS Y COMUNIDADES AFROMEXICANAS DEL\nGOBIERNO DEL ESTADO DE GUERRERO; DE CONFORMIDAD CON LO ESTABLECIDO EN EL\nNUMERAL 32, FRACCIÓN XVIII, DE LA LEY ORGÁNICA DE LA ADMINISTRACIÓN PÚBLICA DEL\nESTADO DE GUERRERO NÚMERO 08, ASÍ COMO EL NUMERAL 16 FRACCIONES V, XXI Y XXII DEL\nREGLAMENTO INTERNO VIGENTE DE ESTA DEPENDENCIA.\nHAGO CONSTAR Y CERTIFICO\nQUE LAS PRESENTES COPIAS FOTOSTÁTICAS,COMPUESTAS DE 19 FOJAS ÚTILES SON\nSECRETARÍA, MISMAS QUE SE EXPIDEN PARA LOS USOS LEGALES A QUE HAYA LUGAR, EN LA\nATENTAMENTE.\nLIC. FELIPE SÁNCHEZ RAMÍREZ.\nDIRECTOR GENERAL DE LA DEFENSA Y ASESORÍA JURÍDICA.\nRúbrica.",
  "ordenamiento": "REGLA",
  "jurisdiccion": "GUERRERO",
  "fuente_oficial": "DIARIO OFICIAL DE LA FEDERACION",
  "Fecha de Publicación": "29 de Julio de 2016",
  "ULTIMA REFORMA PUBLICADA": "23 de Octubre de 2015",
  "status": "VIGENTE",
  "es_escaneado": false,
  "tiene_tablas": true,
  "materia": [
    "general"
  ]
}