{
  "titulo": "Acuerdo por el Que Se Emiten las Reglas de Operación del Programa Asistencia Alimentaria A Sujetos V",
  "Contenido": "DOTACIÓN A PARA EL EJERCICIO FISCAL 2014\n1. Introducción.............................................................................................................................. 6\n1.1 Glosario.................................................................................................................................. 6\n2 Objetivo..................................................................................................................................... 7\n2.1 General................................................................................................................................... 7\n2.2 Especifico............................................................................................................................... 7\n2.3 Población Objetivo.................................................................................................................. 8\n3 Misión....................................................................................................................................... 8\n4 Visión....................................................................................................................................... 8\n5 Reglas de Operatividad.............................................................................................................. 8\n5.1 Lineamientos Generales......................................................................................................... 8\n5.1.1 Fundamento Legal............................................................................................................... 10\n5.1.2 Participantes........................................................................................................................ 11\n5.1.3 Patrimonio del Programa...................................................................................................... 11\n5.1.4 Tipos de Apoyo.................................................................................................................... 11\n6 Información del Programa.......................................................................................................... 12\n6.1 Exposición del Programa........................................................................................................ 12\n6.2 Cobertura................................................................................................................................ 12\n6.3 Método de Entrega del Beneficio............................................................................................ 12\n6.4 Gastos de Operación.............................................................................................................. 13\n7 Transparencia............................................................................................................................ 13\n7.1 Difusión................................................................................................................................... 13\n7.2 Seguimiento de Avances Físicos-Financieros......................................................................... 13\nDOTACIÓN A PARA EL EJERCICIO FISCAL 2014\n7.3 Evaluación.............................................................................................................................. 13\n7.4 Auditoría................................................................................................................................. 18\n7.5 Recursos No Devengados...................................................................................................... 18\n7.6 Blindaje Electoral.................................................................................................................... 19\n7.7 Contraloría Social................................................................................................................... 19\n7.8 Quejas y Denuncias................................................................................................................ 21\n8 Criterios de Selección y Elegibilidad.......................................................................................... 21\n8.1 Método de Selección de los Beneficiarios y beneficiarias....................................................... 21\n8.2 Método de Selección de los Insumos Alimentarios................................................................. 22\n9 Mecánica de Operación............................................................................................................. 23\n9.1 Instancia Ejecutora................................................................................................................. 23\n9.2 Instancia Administrativa y Normativa...................................................................................... 24\n9.3 Delimitación de Atribuciones................................................................................................... 24\n10 Derechos, Obligaciones y Sanciones de los Beneficiarios y las beneficiarias.......................... 24\n10.1 Derechos.............................................................................................................................. 24\n10.2 Obligaciones......................................................................................................................... 24\n10.3 Sanciones............................................................................................................................. 24\n11 Interpretación........................................................................................................................... 24\nDOTACIÓN A PARA EL EJERCICIO FISCAL 2014\nTEXTO ORIGINAL.\nALIMENTARIA A SUJETOS VULNERABLES DOTACIÓN A PARA EL EJERCICIO FISCAL 2014.\nQBP. SARA SALINAS BRAVO Directora General del Sistema para el Desarrollo Integral de la\nFamilia del Estado de Guerrero, con fundamento en el artículo 27 fracción X del Reglamento Interior del\nOrganismo Público Descentralizado Sistema para el Desarrollo Integral de la Familia del Estado de\nGuerrero, así como la Ley que crea al Sistema para el Desarrollo Integral de la Familia del Estado de\nGuerrero número 107 publicada en el Periódico Oficial del Gobierno del Estado el 9 de marzo de 1977 y regido actualmente por la Ley Sobre el Sistema Estatal de Asistencia Social número 332, publicada en el\nPeriódico Oficial del Gobierno del Estado número 56 de fecha 15 de julio de 1986, y\nCONSIDERANDO\nQue en el Dictamen y Decreto del Presupuesto de Egresos del Estado de Guerrero para el\nEjercicio Fiscal 2014, se señala que se ejercerán los recursos bajo una política de gasto público, que permita dar cumplimiento a lo que globalmente prevén los cinco ejes rectores del Plan Estatal de\nDesarrollo 2011- 2015. Dentro de la política de Desarrollo Social, el Sistema para el Desarrollo Integral de la Familia del Estado de Guerrero, opera el Programa Asistencia Alimentaria A Sujetos Vulnerables\nDotación A, a través de la cual, se Contribuye a la seguridad alimentaria de los sujetos que habitan en los\n81 municipios del Estado de Guerrero, en condiciones de riesgo y vulnerabilidad, mediante la entrega de apoyos alimentarios diseñados con base en los Criterios de Calidad Nutricia, y acompañados de acciones de orientación alimentaria, aseguramiento de calidad y producción de alimentos.\nPor lo expuesto y con fundamento en las disposiciones legales antes citadas, he tenido a bien expedir el siguiente:\nALIMENTARIA A SUJETOS VULNERABLES DOTACIÓN A PARA EL EJERCICIO FISCAL 2014.\nÚnico: Se emiten las Reglas de Operación del Programa Asistencia Alimentaria A Sujetos\nVulnerables Dotación A para el Ejercicio Fiscal 2014.\nPrimero: El presente acuerdo entrará en vigor al día siguiente de su publicación en el Periódico\nDado en la Ciudad de Chilpancingo de los Bravo, Guerrero, a los veinticuatro días del mes de febrero del dos mil catorce.\nDOTACIÓN A PARA EL EJERCICIO FISCAL 2014\nESTADO DE GUERRERO.\nQBP. SARA SALINAS BRAVO.\nRúbrica.\n1. Introducción\n1.1 Glosario\n2 Objetivo\n2.1 General\n2.2 Especifico\n2.3 Población Objetivo\n3 Misión\n4 Visión\n5 Reglas de Operatividad\n5.1 Lineamientos Generales\n5.1.1 Fundamento Legal\n5.1.2 Participantes\n5.1.3 Patrimonio del Programa\n5.1.4 Tipos de Apoyo\n6 Información del Programa\n6.1 Exposición del Programa\n6.2 Cobertura\n6.3 Método de Entrega del Beneficio\n6.4 Gastos de Operación\n7 Transparencia\n7.1 Difusión\n7.2 Seguimiento de Avances Físicos-Financieros\n7.3 Evaluación\n7.4 Auditoría\n7.5 Recursos No Devengados\n7.6 Blindaje Electoral\nDOTACIÓN A PARA EL EJERCICIO FISCAL 2014\n7.7 Contraloría Social\n7.8 Quejas y Denuncias\n8 Criterios de Selección y Elegibilidad\n8.1 Método de Selección de los Beneficiarios y beneficiarias\n8.2 Método de Selección de los Insumos Alimentarios\n9 Mecánica de Operación\n9.1 Instancia Ejecutora\n9.2 Instancia Administrativa y Normativa\n9.3 Delimitación de Atribuciones\n10 Derechos, Obligaciones y Sanciones de los Beneficiarios y las beneficiarias\n10.1 Derechos\n10.2 Obligaciones\n10.3 Sanciones\n11 Interpretación\nDOTACIÓN A PARA EL EJERCICIO FISCAL 2014\n1. INTRODUCCIÓN cumplimiento de la Ley General de Salud y la Ley General de Asistencia Social.\nEl art. 4 de la Constitución Política de los Estados Unidos Mexicanos, establece que toda persona tiene derecho a la alimentación nutritiva, suficiente y de calidad. Asimismo, que Varón y Mujer son iguales ante la ley.\nEn 1929 la institución del sector social\" Gota de Leche\", fue creada con el fin de beneficiar con leche y desayunos escolares a niños desamparados de la capital del país. A fines de los años 70's operaron los programas Raciones alimentarias (PRA) y Asistencia Social Alimentaria a Familias en Desamparo\n(PASAF) de manera centralizada desde el Sistema Nacional DIF.\nEn 1961 se creó el Instituto Nacional de Protección a la Infancia (INPI), cuya función principal fue la entrega de desayunos escolares. En 1968 se creó el Instituto Mexicano de Asistencia a la Niñez (IMAN) contribuyendo a resolver problemas originados por el abandono y la explotación de menores.\nFusionándose de esta manera el INPI con el IMAN permitió la constitución del Sistema Nacional para el\nDesarrollo Integral de la Familia (DIF), decretándose en el año de 1977., cuyo propósito fue de reunir en un solo organismo la responsabilidad de coordinar los programas gubernamentales de asistencia social y en general las medidas a favor del bienestar de las familias mexicanas.\nLa Ley sobre el Sistema Estatal de Asistencia Social Número 332, Última reforma publicada en el periódico oficial del Estado de Guerrero, el 15 de julio de 1986. En su artículo 15: Confiere al Sistema para el Desarrollo Integral de la Familia del Estado de Guerrero, la promoción y la prestación de servicios de asistencia social.\nPor ello la Asistencia Social es una acción obligatoria en nuestro Estado y un derecho de todos los\nGuerrerenses, por esto se definen las metas como un mejoramiento constante, mediante la aplicación de programas alimentarios que generen un mayor impacto que responda a las necesidades actuales, considerando la misión que nos confiere tanto la Ley como las Políticas Públicas Estatales.\n1.1 GLOSARIO\nSe entenderá en las siguientes Reglas de Operación por:\nAGE.- Auditoría General del Estado.\nCOPLADEG.- Comité de Planeación para el Desarrollo del Estado de Guerrero\nDIF Guerrero.- Sistema Estatal para el Desarrollo Integral de la Familia.\nPRA.-Programas de Raciones alimentarias\nPASAF.- Programa de Asistencia Social Alimentaria a Familias en Desamparo\nDOTACIÓN A PARA EL EJERCICIO FISCAL 2014\nASISTENCIA SOCIAL.- La asistencia social es una actividad que se ocupa de diferentes situaciones, entre las que se destacan: promover el cambio social hacia un estado de superación, la resolución de conflictos que surjan en la interacción humana, el fortalecimiento y la liberación de los pueblos conforme al objetivo de alcanzar el bien común.\nLas relaciones que mantienen las personas entre sí y en sus ambientes son múltiples y complejas y entonces, allí, donde se susciten los conflictos, o en su defecto, la carencia, estará la asistencia social para salvaguardar los derechos de los afectados por los mencionados problemas.\nAsistencia Alimentaria a Sujetos Vulnerables.- Programa dirigido a grupos de riesgo, sujetos de asistencia social alimentaria, preferentemente Adultos Mayores, Discapacitados, mujeres en periodo de lactancia, mujeres embarazadas, madres solteras y personas vulnerables por ingresos.\n2. OBJETIVO\n2.1. GENERAL.\nContribuir a la seguridad alimentaria de los sujetos que habitan en los 81 municipios del Estado de\nGuerrero, en condiciones de riesgo y vulnerabilidad, mediante la entrega de apoyos alimentarios diseñados con base en los Criterios de Calidad Nutricia, y acompañados de acciones de orientación alimentaria, aseguramiento de calidad y producción de alimentos.\n2.2. ESPECIFICO.\n• Contribuir a mejorar el estado nutricional de mujeres en periodo de lactancia, mujeres embarazadas, personas con discapacidad, adultos mayores y personas que se han visto afectados por la crisis económica con la disminución de sus ingresos reales, mediante la entrega de un paquete de insumos alimentarios que le permitan cubrir sus necesidades de alimentación complementada con la orientación que refuerce los hábitos alimentarios adecuados al interior del núcleo familiar.\n• Ello a través de la dotación de un apoyo mensual en especie denominado despensa con lo cual el beneficiario y su familia pueden consumir los nutrientes necesarios para hacer frente a las necesidades de alimentación básica y que de otra forma no serían capaces de obtener.\n• Contribuir al gasto familiar y complemento de la canasta básica de las personas vulnerables.\n• Difundir material educativo de orientación alimentaria, que le permita al beneficiario o beneficiaria adquirir los conocimientos para una adecuada nutrición.\n• Promover la integración de Clubes de la Tercera Edad, cuyos integrantes reciban apoyo alimentario como complemento de la canasta básica y contribuir en su gasto familiar.\nAsimismo fomentar actividades que les permita sentirse útiles.\n• Promover cambios en las prácticas alimentarias de la población vulnerable especialmente de las personas con discapacidad, mejorando su salud y calidad de vida.\n• Prevenir la desnutrición de los beneficiarios y beneficiarias.\n• Promover la seguridad alimentaria mediante la producción de alimentos para autoconsumo.\nDOTACIÓN A PARA EL EJERCICIO FISCAL 2014\n2.3. POBLACIÓN OBJETIVO.\nGrupos de riesgo, sujetos de asistencia social alimentaria, preferentemente mujeres embarazadas, mujeres en período de lactancia, madres solteras, personas con discapacidad, adultos mayores y personas vulnerables por ingresos.\n3. MISIÓN\nPromover la integración y el desarrollo humano individual, familiar y comunitario, a través de políticas de\nAsistencia Social y estrategias que permitan proporcionar de manera oportuna, sostenida y garantizada los alimentos nutricionalmente adecuados en cantidad, calidad, variedad y aceptación cultural para la población sujeta de asistencia social que les permita llevar una vida sana y socialmente útil. Asimismo la profesionalización y calidad de los servicios desde una perspectiva de seguridad alimentaria.\n4. VISIÓN\nConsolidar un DIF Guerrero que regule y garantice a los sujetos de asistencia, el fortalecimiento de la seguridad alimentaria mediante la entrega de despensas que promueven los tres órdenes de Gobierno, a fin de mejorar su estado nutricional y promover una alimentación correcta.\n5. REGLAS DE OPERATIVIDAD\n5.1. LINEAMIENTOS GENERALES\n• El DIF Municipal remite a la Dirección General del DIF Guerrero, la solicitud de ingreso al\nPrograma Asistencia Alimentaria a Sujetos Vulnerables Dotación A, mencionando el nombre de los beneficiarios y beneficiarias.\n• Tipo de vulnerabilidad y cantidad solicitada por beneficiario o beneficiaria.\n• El beneficiario o la beneficiaria podrá remitir su solicitud directamente al DIF Guerrero, con libre formato. Adjuntar:\n• Copia de identificación oficial (IFE, pasaporte o licencia de conducir).\n• Encuesta de Inseguridad Alimentaria debidamente llenada y avalada su aplicación por el\nSistema Municipal DIF y/o el DIF Guerrero; la cual permitirá determinar el grado de atención y prioridad.\n• CURP del beneficiario o beneficiaria (Esto es importante para la captura de padrones de beneficiarios o beneficiarias, sin él no podrá ingresar al programa).\n• Constancia de vulnerabilidad (ejemplo: credencial de discapacidad, constancia emitida por salud de la evolución del embarazo, etc.)\n• En el caso de vulnerabilidad por ingresos presentar comprobante de ingresos económicos.\n• Proporcionar todos los datos necesarios para integrarse en el padrón de beneficiarios en formato físico y magnético.\n• Estar de acuerdo en pagar la cuota de recuperación de $3.0 por despensa.\n• El programa dará preferencia a personas ubicadas en comunidades de Alto y Muy alto grado de marginación.\nDOTACIÓN A PARA EL EJERCICIO FISCAL 2014\n• Se turna a la Dirección de Asistencia Alimentaria y Desarrollo Comunitario, y este a su vez, a la Subdirección de Asistencia Alimentaria; quien al momento de focalizar a los beneficiarios y beneficiarias, dará prioridad a los habitantes de comunidades de mayor índice de marginación y vulnerabilidad. En el caso de que en una familia existiere más de dos sujetos vulnerables factibles de apoyo, se deberá considerar una despensa por cada unidad familiar.\n• En base a lo anterior y a los lineamientos de la Estrategia Integral de Asistencia Social\nAlimentaria, la atención es dirigida preferentemente a mujeres embarazadas, mujeres en período de lactancia, personas con discapacidad, adultos mayores y personas vulnerables por ingresos (El ingreso familiar no debe exceder el tope de una vez el salario mínimo general de la región, de acuerdo al área geográfica B, que en Guerrero para este 2014 es de $63.77 como un salario por día, por lo que para ser beneficiario (a) de la despensa deben ganar mensualmente como máximo $1,913.10), los cuales pueden presentar estar catalogados como migrantes, desplazados o situación vulnerable.\n• Todo beneficiario o beneficiaria deberá contar con un expediente que se encontrará en el\nSistema Municipal DIF, en los casos donde la entrega de despensa sea a través del mismo.\nPara el caso de los beneficiarios o las beneficiarias como son Asociaciones de\nDiscapacitados, Adultos Mayores, entre otros; cuya entrega de las despensas es directamente a través del DIF Guerrero, los expedientes estarán bajo resguardo de la\nDirección de Asistencia Alimentaria y Desarrollo Comunitario. Cada expediente incluirá: a. Cédula de Inseguridad Alimentaria (Anexo 11), constancia de vulnerabilidad, copia de credencial de elector y CURP.\n• Los expedientes deberán estar presentados en orden de acuerdo al Padrón de beneficiarios y beneficiarias y por cada beneficiario o beneficiaria, que contenga su documentación, por localidad, los cuales deberán resguardarse.\n• Pagar la cuota de recuperación por cada despensa de $3.00 (tres pesos 00/ 100 M.N.), la cual podrá ser aumentada máximo a $5.00 por los Sistemas Municipales DIF siempre y cuando justifiquen por escrito la razón del incremento.\n• Si no cumplen con los requisitos anteriores se rechaza la solicitud mediante oficio dirigido al solicitante o la solicitante. El tiempo de respuesta será considerada no mayor a un mes.\n• En caso de cumplir con los requisitos se procede a calendarizar la entrega de insumos, se notifica al beneficiario o las beneficiarias y/o a los Sistemas Municipales DIF la fecha de entrega.\n• Se supervisa la operatividad del programa. (Ver anexo 3 y formatos sdif-DAAYDC-SAAALIMENTARIOS-AEN4, SDIF-DAAYDC-SAA-VULNE_A-R2).\n• Se integran los padrones de beneficiario de acuerdo al formato sdif-daaydc-saa-vulne_a-R5 Y sdIF-DAAYDC-SAA-VULNE_A-R6., remitiendo el mismo al Sistema Nacional DIF.\n• Se realizan capacitaciones de orientación alimentaria, higiene personal y de los alimentos, así como del Plato del Buen Comer, con la finalidad de reforzar la inocuidad de los alimentos entregados a los beneficiarios. sdif-daaydc-SAA-ALIMENTARIOS-AEN1\n• Se integran los informes físicos y financieros por municipio, remitiendo estos resultados al\n• Fin del procedimiento\nDOTACIÓN A PARA EL EJERCICIO FISCAL 2014\n5.1.1. FUNDAMENTO LEGAL\n2012.\n4. Ley General de Salud. Última reforma publicada DOF 25-01 -2013. Acuerdo por el que se determinan los aditivos. Artículo 115. La Secretaría de Salud tendrá a su cargo: VI.\nRecomendar las dietas. Artículo 210., Artículo 212, Artículo 213.\n5. Ley de Asistencia Social. Última reforma publicada 08-06-2012.\n6. Ley General de Educación. Última reforma publicada DOF 09-04-2012. Artículo 33 XVII.\nImpulsara esquemas eficientes.\n7. Ley para la Protección de los Derechos de Niñas, Niños y Adolescentes. Última reforma publicada DOF 19-08-2010.\n8. Ley Federal de Presupuesto y Responsabilidad Hacendaria. Última reforma publicada DOF\n09-04-2012.\n9. Ley de Coordinación Fiscal. Última reforma publicada DOF 12-12-2011.\n10.Norma Oficial Mexicana NOM-169-SSA1-1998, Para la Asistencia Social Alimentaria a\nGrupos de Riesgo. Publicada DOF 19-11 -1999\n11.Norma Oficial Mexicana NOM-043-SSA2-2005, Servicios Básicos de Salud. Promoción y\nAdecuación para la Salud en Materia Alimentaria. Criterios para Brindar Orientación.\nPublicada DOF 23-01-2006.\n12.PROY-NOM-043-SSA2-2011, Proyecto de modificación a la Norma Oficial Mexicana NOM043-SSA2-2005, Servicios básicos de salud. Promoción y educación para la salud en materia alimentaria. Criterios para brindar orientación; para quedar como proyecto de Norma Oficial\nMexicana. Publicada DOF 28-05-2012.\n13. Norma Oficial Mexicana NOM-251-SSA1 -2009, Prácticas de higiene para el proceso de alimentos, bebidas o suplementos alimenticios. Publicada DOF 01-03-2010.\n14. NOM-051-SCFI/SSA1 -2010 «Especificaciones Generales de Etiquetado para Alimentos y\nBebidas no Alcohólicas Preenvasados-Información comercial y sanitaria. Publicada DOF 0504-2010.\n15. Norma Oficial Mexicana NOM-155-SCFI-2012, Leche-Denominaciones, especificaciones fisicoquímicas, información comercial y métodos de prueba. Publicada DOF 03-05-2012.\n16. Secretaría de Salud. Acuerdo Nacional para la Salud Alimentaria: Estrategia contra el\nSobrepeso y la Obesidad; Secretaría de Salud; México, enero 2010. [En línea]. [Accesado el 2\n17. Acuerdo mediante el cual se establecen los Lineamientos Generales para el expendio o\n18. Ley sobre el Sistema Estatal de Asistencia Social Número 332, Artículo 3.\n19. Convenio de colaboración para la operatividad de los programas de la EIASA.\n20. Lineamientos de la Estrategia Integral de Asistencia Social Alimentaria, DIF Nacional.\n21. (Ver Anexo 14)\nDOTACIÓN A PARA EL EJERCICIO FISCAL 2014\n22. Plan Nacional de Desarrollo 2013 -2018. Artículo cuarto.\n23. Sistema Nacional para la Cruzada Contra el Hambre. Artículo primero. Artículo segundo.\nArtículo sexto.\n24. Lineamientos para dictaminar y dar seguimiento a los programas derivados del Plan Nacional de Desarrollo 2013-2018. Programas sectoriales, institucionales, especiales y regionales\n25. Ley General de Desarrollo Social. Artículo 30.\n5.1.2. PARTICIPANTES\nEl Sistema para el Desarrollo Integral de la Familia, así como otras instancias públicas y de la sociedad civil que deseen y muestren interés en contribuir al logro de los objetivos del Programa, en apego a lo dispuesto en las presentes reglas operativas y demás normatividad aplicable, además de las localidades que se encuentran con un alto grado de marginación.\n5.1.3. PATRIMONIO DEL PROGRAMA\nEl presente programa opera de acuerdo a su presupuesto autorizado, cuyos recursos provienen del\nFondo de Aportaciones Múltiples (FAM), para el presente ejercicio fiscal 2014.\n5.1.4. TIPOS DE APOYO\nDespensa integrada por insumos no perecederos, el cual está calculado para una ración por beneficiario durante 20 días Contenido\n1 kg. de Frijol 1 kg. de Avena\n1 kg. de Harina de Maíz 500 grs. de Soya Texturizada\n1 Atún de 140 g 1 lata de sardina de 425 gr la cual cumple con la recomendación de alimentos (ver anexo 5).\n1 kg. de Arroz\n500 grs de Lenteja\nSujetos Vulnerables Dotación A\nIncluir 4 o más alimentos básicos Incluir cuando menos 2 de los tres grupos de alimentos referidos en la\nNOM-043-SSA2-2012 (Verduras y Frutas; Cereales; y Leguminosas y\nAlimentos de Origen Animal), (ver anexo 4).\nDOTACIÓN A PARA EL EJERCICIO FISCAL 2014\nIncluir al menos 2 cereales que Incluir al menos 2 variedades de En caso de incluir un complemento, sean fuente de fibra dietética leguminosas. éste no deberá contener azúcares ni edulcorantes entre sus primeros tres ingredientes.\nIncluir al menos 1 alimento que sea fuente de calcio\nAdemás, para la conformación de los apoyos alimentarios se recomienda:\nDiseñar menús cíclicos dependiendo del período que cubre la entrega y entregarlos a la población beneficiaria.\nDeterminar las cantidades de insumos que serán integrados en la dotación, a partir de las raciones de los menús diseñados en la etapa de planeación del programa.\n6. INFORMACIÓN DEL PROGRAMA\n6.1. EXPOSICIÓN DEL PROGRAMA\nEstas Reglas de Operación, además de su publicación en el Periódico Oficial del Gobierno del Estado, estarán disponibles para su consulta en las Oficinas de la Dirección de Asistencia Alimentaria y\nDesarrollo Comunitario, así como en la página electrónica del Sistema para el Desarrollo Integral de la\nFamilia http://www.dif.guerrero.gob.mx, información pública de oficio, fracción III Marco normativo especifico.\n6.2. COBERTURA\nTendrá cobertura Estatal, dando prioridad a todas aquellas localidades que se encuentran con un muy alto y alto grado de marginación. El Programa apoyará a toda persona del Estado de Guerrero sin distinción de sexo, religión, raza y/o partido político que necesite del apoyo y que no cuenten con un esquema de seguridad social. (Preferentemente a mujeres embarazadas, madres solteras, viudas, etc.)\n6.3. MÉTODO DE ENTREGA DEL BENEFICIO\nREQUISITOS PARA INGRESAR AL PROGRAMA\nPertenecer preferentemente al grupo vulnerable mujeres embarazadas, mujeres en periodo de lactancia, madres solteras del Estado de Guerrero, personas con discapacidad, adultos mayores y personas vulnerables por ingresos (El ingreso familiar no debe exceder el tope de una vez el salario mínimo general de la región, de acuerdo al área geográfica B, que en Guerrero para este 2014 es de $63.77 como un salario por día, por lo que para ser beneficiario de la despensa deben ganar mensualmente como máximo $1,913.10)\nDOTACIÓN A PARA EL EJERCICIO FISCAL 2014\n• Dirigir una solicitud a la Dirección General del DIF Guerrero, con libre formato y Adjuntar:\n• Copia de identificación oficial (IFE, pasaporte o licencia de conducir).\n• Encuesta de Inseguridad Alimentaria debidamente llenada y avalada su aplicación por el\nSistema Municipal DIF y/o el Sistema Estatal DIF Guerrero; la cual permitirá determinar el grado de atención y prioridad.\n• CURP del beneficiario o beneficiaria (Esto es importante para la captura de padrones de beneficiarios y beneficiarias, sin él no podrá ingresar al programa).\n• Constancia de vulnerabilidad (ejemplo: credencial de discapacidad, constancia emitida por salud de la evolución del embarazo, etc.).\n• En el caso de vulnerabilidad por ingresos presentar comprobante de ingresos económicos.\n• Proporcionar todos los datos necesarios para integrarse en el padrón de beneficiarios y beneficiarias en formato físico y magnético.\n• Estar de acuerdo en pagar la cuota de recuperación de $3.0 por despensa.\n• El programa dará preferencia a personas ubicadas en comunidades de Alto y Muy alto grado de marginación.\n6.4. GASTOS DE OPERACIÓN\nNo aplica para el desarrollo del presente Programa debido a que el presupuesto se destina para la adquisición de los apoyos, el gasto de operación es erogado por otra fuente de financiamiento.\n7. TRANSPARENCIA\n7.1. DIFUSIÓN\nUna vez autorizados estas Reglas de Operación, por las instancias correspondientes, estarán disponibles para su consulta en las Oficinas de la Dirección de Servicios Médicos Asistenciales, así como en los medios electrónicos oficiales http://www.dif.guerrero.gob.mx información pública de oficio, fracción III\nMarco Normativo específico.\n7.2. SEGUIMIENTO DE AVANCES FÍSICO FINANCIEROS\nGuerrero, las acciones ejercidas y los resultados obtenidos, quien a su vez reportara al COPLADEG,\n7.3. EVALUACIÓN correspondientes.\nDOTACIÓN A PARA EL EJERCICIO FISCAL 2014\nINDICADOR FORMULA OBJETIVO\nFRECUENCIA\nDE MEDICION\nInversión del IAF Anual Conocer la cantidad\nIF=\nFAM de porcentual de la inversión\nIAFFF x 100 en Asistencia Social en el\nAsistencia Social\nDIF Estatal del Fondo de en el DIF Estatal IF= Inversión del FAM de Asistencia Social en\nAportaciones Múltiples el DIF Estatal (Unidad de medida: pesos)\nIAF = Importe autorizado del FAM- Asistencia\nSocial al Estado.\nIAFFF= Importe autorizado del FAMAsistencia Social más otras fuentes de financiamiento al DIF Estatal\nAFRIOS+ACALIENTES Anual\nMejoramiento de Conocer la cantidad\nMAA= la Asistencia NTOTAL x 100 porcentual de\nSocial mejoramiento de la\nMAA= Mejoramiento de la Asistencia Social Asistencia Social.\nAFRIOS = Número de apoyos alimentarios fríos distribuidos en el periodo correspondiente a menús y despensas, diseñadas de acuerdo a los criterios de calidad nutricia de los lineamientos de la estrategia integral de asistencia social alimentaria.\nACALIENTES = Número de apoyos correspondiente a menús diseñados de acuerdo a los criterios de calidad nutricia de los lineamientos de la estrategia integral de asistencia social alimentaria.\nNTOTAL= Número total de apoyos entregados en el periodo.\nDOTACIÓN A PARA EL EJERCICIO FISCAL 2014\nAM Conocer la cantidad\nPAM= porcentual de asesorías\nNAP x 100 realizadas\nPorcentaje de PAM= Porcentaje de asesorías Anual a municipios. asesorías realizadas a municipios (Unidad de realizadas a medida: asesorías) municipios AM = Número de asesorías realizadas a municipios.\nNAP= Número de asesorías programadas.\nREFAM Conocer la cantidad\nEG31 = porcentual del ejercicio\nEjercicio del Gasto RAFAM x 100 Anual de gasto asistencia\nAsistencia Social al 31 social al 31 de\nEG31= Ejercicio del gasto asistencia social (Unidad de medida: pesos) diciembre. de diciembre\nREFAM = Recursos ejercidos FAM\nAsistencia social al 31 de diciembre.\nRAFAM= Recursos autorizados FAM\nAsistencia Social.\nREFAMFE Conocer la cantidad\nEGFE= porcentual del ejercicio\nEjercicio del Gasto RAFAMFE x 100 Anual de gasto asistencia\nAsistencia Social a la social a la fecha de fecha de revisión\nEGFE= Ejercicio del gasto asistencia revisión. social a la fecha de revisión (Unidad de medida: pesos)\nREFAMFE = Recursos ejercidos FAM\nAsistencia social a la fecha\nRAFAMFE= Recursos autorizados FAM\nAsistencia Social a la fecha\nRNE31\nConocer el subejercicio\nPRNE31 al 31 de diciembre.\n= RAFAMAA x 100\nDOTACIÓN A PARA EL EJERCICIO FISCAL 2014\nRecurso no ejercido PRNE31= Porcentaje de Recursos no Anual\nSocial al 31 de 31 Diciembre (Unidad de medida: diciembre pesos)\n(subejercicio)\nRNE31 = Recursos no ejercidos del\nFAM Asistencia Social al 31 de\nDiciembre\nRAFAMAA= Recursos autorizados FAM\nAsistencia Social.\nRNEFE Conocer el subejercicio\nPRNEFE= a la fecha de revisión.\nRAFAMFE x 100\nAnual\nRecurso no ejercido del PRNEFE= Porcentaje de Recursos no ejercidos\nFAM Asistencia Social a la del FAM Asistencia Social a la fecha de revisión fecha de (Unidad de medida: pesos) revisión (subejercicio)\nRNEFE = Recursos no ejercidos del FAM\nAsistencia Social a la fecha de revisión.\nRAFAMFE= Recursos autorizados FAM\nAsistencia Social.\nDAICA Conocer la cantidad\nICA= porcentual de las\nTDME x 100 despensas\nDistribución de ICA= Distribución de Despensas en Anual distribuidas en municipios\nMunicipios con Alimentaria. (Unidad de medida: despensas) alimentaria.\nAlto Índice de DAICA = Despensas distribuidas en\nCarencia\nDOTACIÓN A PARA EL EJERCICIO FISCAL 2014 alimentaria.\nTDME = Total de despensas distribuidas en todos los municipios del Estado\nMANA Conocer la cantidad\nMNA= porcentual de municipios\nTMA x 100 con alto\nMunicipios con MNA = Municipios con alto índice de carencia índice de carencia alto índice de alimentaria no atendidos por el FAM Asistencia alimentaria no atendidos.\nSocial.\n(Unidad de medida: Municipios) Anual carencia alimentaria no atendidos por el MANA= Municipios con Alto Indice de\nSocial.\nTMA = Total de Municipios atendidos en el\nEstado\n{\"tabla_1\":{\"columnas\":[\"Población atendida con\",\"PA\",\"Anual\",\"Indicar el porcentaje de\"],\"filas\":[{\"columna_1\":\"(sin dato)\",\"columna_2\":\"PARFAM=\",\"columna_3\":\"(sin dato)\",\"columna_4\":\"(sin dato)\"},{\"columna_1\":\"recursos del FAM de\",\"columna_2\":\"(sin dato)\",\"columna_3\":\"(sin dato)\",\"columna_4\":\"población atendida con\"},{\"columna_1\":\"(sin dato)\",\"columna_2\":\"PSAx100\",\"columna_3\":\"(sin dato)\",\"columna_4\":\"(sin dato)\"},{\"columna_1\":\"Asistencia Social\",\"columna_2\":\"(sin dato)\",\"columna_3\":\"(sin dato)\",\"columna_4\":\"recursos del FAM\"},{\"columna_1\":\"(sin dato)\",\"columna_2\":\"(sin dato)\",\"columna_3\":\"(sin dato)\",\"columna_4\":\"Asistencia Social.\"},{\"columna_1\":\"(sin dato)\",\"columna_2\":\"PARFAM = Población atendida con recursos\",\"columna_3\":\"(sin dato)\",\"columna_4\":\"(sin dato)\"},{\"columna_1\":\"(sin dato)\",\"columna_2\":\"del FAM de Asistencia Social (Unidad de\",\"columna_3\":\"(sin dato)\",\"columna_4\":\"(sin dato)\"},{\"columna_1\":\"(sin dato)\",\"columna_2\":\"medida: Población)\",\"columna_3\":\"(sin dato)\",\"columna_4\":\"(sin dato)\"},{\"columna_1\":\"(sin dato)\",\"columna_2\":\"PA = Población atendida\",\"columna_3\":\"(sin dato)\",\"columna_4\":\"(sin dato)\"},{\"columna_1\":\"(sin dato)\",\"columna_2\":\"PSA = Población susceptible de atender en el\",\"columna_3\":\"(sin dato)\",\"columna_4\":\"(sin dato)\"},{\"columna_1\":\"(sin dato)\",\"columna_2\":\"Estado.\",\"columna_3\":\"(sin dato)\",\"columna_4\":\"(sin dato)\"}]}}\nDOTACIÓN A PARA EL EJERCICIO FISCAL 2014\n{\"tabla_2\":{\"columnas\":[\"Cumplimiento del\",\"TE\",\"Anual\",\"Conocer el porcentaje de\"],\"filas\":[{\"columna_1\":\"(sin dato)\",\"columna_2\":\"PADQ\",\"columna_3\":\"(sin dato)\",\"columna_4\":\"(sin dato)\"},{\"columna_1\":\"programa\",\"columna_2\":\"(sin dato)\",\"columna_3\":\"(sin dato)\",\"columna_4\":\"cumplimiento del programa\"},{\"columna_1\":\"(sin dato)\",\"columna_2\":\"= PAAAx 100\",\"columna_3\":\"(sin dato)\",\"columna_4\":\"(sin dato)\"},{\"columna_1\":\"anual de\",\"columna_2\":\"(sin dato)\",\"columna_3\":\"(sin dato)\",\"columna_4\":\"anual de adquisiciones\"},{\"columna_1\":\"(sin dato)\",\"columna_2\":\"(sin dato)\",\"columna_3\":\"(sin dato)\",\"columna_4\":\"alimentarias.\"},{\"columna_1\":\"adquisiciones\",\"columna_2\":\"PADQ = Cumplimiento del programa anual de\",\"columna_3\":\"(sin dato)\",\"columna_4\":\"(sin dato)\"},{\"columna_1\":\"alimentarias.\",\"columna_2\":\"adquisiciones alimentarias (Unidad de medida:\",\"columna_3\":\"(sin dato)\",\"columna_4\":\"(sin dato)\"},{\"columna_1\":\"(sin dato)\",\"columna_2\":\"Pesos)\",\"columna_3\":\"(sin dato)\",\"columna_4\":\"(sin dato)\"},{\"columna_1\":\"(sin dato)\",\"columna_2\":\"TE = Total ejercido en programas alimentarios\",\"columna_3\":\"(sin dato)\",\"columna_4\":\"(sin dato)\"},{\"columna_1\":\"(sin dato)\",\"columna_2\":\"(desayunos escolares y asistencia alimentaria)\",\"columna_3\":\"(sin dato)\",\"columna_4\":\"(sin dato)\"},{\"columna_1\":\"(sin dato)\",\"columna_2\":\"31 diciembre\",\"columna_3\":\"(sin dato)\",\"columna_4\":\"(sin dato)\"},{\"columna_1\":\"(sin dato)\",\"columna_2\":\"PAAA = Programa anual de adquisiciones\",\"columna_3\":\"(sin dato)\",\"columna_4\":\"(sin dato)\"},{\"columna_1\":\"(sin dato)\",\"columna_2\":\"alimentarias.\",\"columna_3\":\"(sin dato)\",\"columna_4\":\"(sin dato)\"},{\"columna_1\":\"Sujetos\",\"columna_2\":\"SVCAA\",\"columna_3\":\"Anual\",\"columna_4\":\"Conocer la cantidad\"},{\"columna_1\":\"(sin dato)\",\"columna_2\":\"SVDE\",\"columna_3\":\"(sin dato)\",\"columna_4\":\"(sin dato)\"},{\"columna_1\":\"vulnerables\",\"columna_2\":\"(sin dato)\",\"columna_3\":\"(sin dato)\",\"columna_4\":\"porcentual de sujetos\"},{\"columna_1\":\"(sin dato)\",\"columna_2\":\"A= SVSCAAx100\",\"columna_3\":\"(sin dato)\",\"columna_4\":\"(sin dato)\"},{\"columna_1\":\"susceptibles de\",\"columna_2\":\"(sin dato)\",\"columna_3\":\"(sin dato)\",\"columna_4\":\"vulnerables susceptibles\"},{\"columna_1\":\"(sin dato)\",\"columna_2\":\"(sin dato)\",\"columna_3\":\"(sin dato)\",\"columna_4\":\"de atender.\"},{\"columna_1\":\"atender con\",\"columna_2\":\"SVDEA = Sujetos vulnerables susceptibles\",\"columna_3\":\"(sin dato)\",\"columna_4\":\"(sin dato)\"},{\"columna_1\":\"asistencia\",\"columna_2\":\"de atender con asistencia alimentaria (Unidad\",\"columna_3\":\"(sin dato)\",\"columna_4\":\"(sin dato)\"},{\"columna_1\":\"alimentaria\",\"columna_2\":\"de medida: Población)\",\"columna_3\":\"(sin dato)\",\"columna_4\":\"(sin dato)\"},{\"columna_1\":\"(sin dato)\",\"columna_2\":\"SVCAA = Sujetos vulnerables atendidos con\",\"columna_3\":\"(sin dato)\",\"columna_4\":\"(sin dato)\"},{\"columna_1\":\"(sin dato)\",\"columna_2\":\"asistencia alimentaria.\",\"columna_3\":\"(sin dato)\",\"columna_4\":\"(sin dato)\"},{\"columna_1\":\"(sin dato)\",\"columna_2\":\"SVSCAA = Sujetos vulnerables susceptibles\",\"columna_3\":\"(sin dato)\",\"columna_4\":\"(sin dato)\"},{\"columna_1\":\"(sin dato)\",\"columna_2\":\"de atender con asistencia alimentaria.\",\"columna_3\":\"(sin dato)\",\"columna_4\":\"(sin dato)\"}]}}\n7.4. AUDITORIA aplicables y podrá ser auditado por la Contraloría General del Estado, así como por la Auditoría General del Estado, conforme a la legislación vigente y en el ámbito de sus respectivas competencias.\n7.5. RECURSOS NO DEVENGADOS\nDOTACIÓN A PARA EL EJERCICIO FISCAL 2014 aquellos que por cualquier motivo no estuviesen devengados al 31 de diciembre del Ejercicio fiscal correspondiente\n7.6. BLINDAJE ELECTORAL\nLa operación y ejecución de los recursos estatales destinados al Programa, deberán observar y atender las medidas que emita la Contraloría General del Estado, para coadyuvar a que estos, no sean utilizado con fines políticos en el desarrollo de procesos electorales federales, estatales y municipales.\nComo estrategia de blindaje electoral, la papelería, documentación oficial, así como la publicidad y promoción del Programa deberán incluir la siguiente leyenda:\n\"Este Programa es de carácter público, no es patrocinado ni promovido por partido político alguno y sus recursos provienen de los impuestos que pagan todos los contribuyentes. Está prohibido el uso de este programa con fines políticos, electorales, de lucro y otros distintos a los establecidos. Quien haga uso indebido de los recursos de este programa deberá ser denunciado y sancionado de acuerdo con la ley aplicable y ante la autoridad competente\".\nEn cuanto a la publicidad en medios electrónicos, impresos, complementarios o de cualquier otra índole, vinculados con los Programas de comunicación social, se deberá incluir la siguiente leyenda:\n\"Este Programa es público y queda prohibido su uso con fines partidistas o de promoción personal\".\n7.7. CONTRALORÍA SOCIAL\nCon la finalidad de incrementar la participación ciudadana, se crearán Comités de Contraloría Social, como un órgano ciudadano de control, vigilancia y evaluación de las actividades del Programa Asistencia\nAlimentaria a Sujetos Vulnerables Dotación A; conformados por los beneficiarios y las beneficiarias, los sectores sociales y los representantes de la localidad, quienes de manera especificas supervisarán la gestión gubernamental, y que el manejo de los recursos públicos se realicen en términos de transparencia, eficacia, legalidad y honradez.\nLos objetivos específicos de este Órgano de Contraloría Social son:\n• Hacer más transparentes las decisiones y la ejecución de los recursos.\n• Incrementar la participación ciudadana.\n• Fomenta la organización social.\n• Inhibir los actos de corrupción y de cooptación social, política y electoral.\n• Incrementar la eficiencia de los recursos públicos.\n• Fortalecer la cultura de la legalidad.\n• Mejorar la rendición de cuentas.\n• Perfeccionar la democracia, e incorporar la evaluación ciudadana.\nDOTACIÓN A PARA EL EJERCICIO FISCAL 2014\nA) Integración el Programa Asistencia Alimentaria a Sujetos Vulnerables Dotación A, y fungirán como interlocutores con el DIF Guerrero, en el ejercicio de la Contraloría Social.\nEl Comité de Contraloría Social revisa en conjunto con la población, los avances y resultados del programa, así como la detección de cualquier irregularidad.\nEl vocal del Comité de Contraloría Social será, el responsable de hacer llegar las quejas o denuncias recibidas al DIF Guerrero, quien dará respuesta en un plazo no mayor de 15 días a partir de la fecha de recepción de la queja o denuncia.\nB) Capacitación y Asesoría\nPara impulsar la realización de las actividades de Contraloría Social se brindará capacitación y asesoría, a los servidores y servidoras públicas que intervienen en la operación del Programa Asistencia\nAlimentaria a Sujetos Vulnerables Dotación A; así como a los integrantes de los Comités Locales, para que estos realicen adecuadamente sus actividades de seguimiento y vigilancia.\nC) Seguimiento\nSe deberá integrar un Programa de Trabajo de acuerdo al Programa Asistencia Alimentaria a Sujetos\nVulnerables Dotación A; debe incluir la descripción de las actividades, responsables, metas y calendarización de las actividades para su cumplimiento.\nLa Directora General o el personal que designe el DIF Guerrero, serán las encargadas de conformar los\nComités de Contraloría Social, así mismo darán acompañamiento durante las actividades de control, seguimiento y vigilancia de los proyectos.\nEl Comité de Contraloría Social debe estar constituido por un Presidente, un Secretario y un Vocal mínimamente, electos de entre la población beneficiada en donde se va a realizar la entrega del\nPrograma Asistencia Alimentaria a Sujetos Vulnerables Dotación A; y tendrá que ser vigilado por un solo\nComité.\nEl Comité de Contraloría Social deberá controlar, vigilar y dar seguimiento al proyecto a través de los formatos que integran el expediente comunitario, integrado por:\n1.- Acta de Conformación del Comité de Contraloría Social.\n2.- Reunión con beneficiarios y beneficiaras.\n3.- Ficha Informativa del Programa.\n4.- Cedula de Vigilancia del Programa.\n5.- Actividades de Difusión y Capacitación.\n6.- Quejas, Denuncias o Reconocimientos.\nDOTACIÓN A PARA EL EJERCICIO FISCAL 2014\n7.- Informe Anual.\n7.8. QUEJAS Y DENUNCIAS\nEn caso de desvió de recursos por parte de servidores públicos, estatales y municipales, las quejas podrán ser por escrito, por comparecencia del interesado y la interesada, por correo electrónico y vía telefónica; a la Dirección de Asistencia Alimentaria y Desarrollo Comunitario del Sistema Estatal DIF\nGuerrero, ubicado en Av. Gabriel Leyva esq. Ruffo Figueroa, Col. Burócratas, C.P. 39070, Chilpancingo, Guerrero.\nTel (01-747) 47-2-13-75 y al correo electrónico alimentariadif@prodigy.net.mx; proporcionando los siguientes datos: Nombre del servidor público, dependencia de adscripción, objeto de la denuncia, nombre y domicilio del quejoso e identificación oficial. a. En el Sistema DIF Guerrero\nTeléfonos: (747) 47-1-84-90 o 47-1-84-92 Correo electrónico: buzon.dif@guerrero.gob.mx\nDomicilio: Centro de Rehabilitación Integral Guerrero. Boulevard Lic. René Juárez Cisneros S/N, Col.\nCiudad de los Servicios. Chilpancingo, Guerrero. C.P. 39095. b. En la Contraloría General del Estado.\nTeléfonos: (474) 47 1 97 40 o 47 1 97 41 Correo electrónico: contraloria@guerrero.gob.mx\nDomicilio: Palacio de Gobierno Primer Piso Edificio Norte, Blvd. R. Juárez Cisneros 62 Col. de los\nServicios C.P. 39075.\nLas quejas y denuncias de la ciudadanía derivadas de alguna irregularidad en la operación del Programa, podrán presentarse por escrito, por comparecencia del interesado, por correo electrónico o vía telefónica y deberá proporcionar los siguientes datos: nombre del servidor público, área de adscripción, objeto de la denuncia, nombre y domicilio del quejoso e identificación oficial.\n8. CRITERIOS DE SELECCIÓN Y ELEGIBILIDAD\n8.1. MÉTODO DE SELECCIÓN DE LOS BENEFICIARIOS Y LAS BENEFICIARIAS\n• El primer paso para la selección de beneficiarios y beneficiarias es la denominada focalización geográfica, la cual debe entenderse como la asignación de un orden de prelación de las rezago social. Las herramientas de apoyo serán el Índice de Marginación (CONAPO) y del Índice de Rezago Social (CONEVAL).\n• El segundo paso será determinar el Índice de Focalización por Municipio, que se compone de los siguientes indicadores: población con carencia por acceso a la alimentación; población con carencia por rezago educativo; vulnerables por ingresos; línea de bienestar; rezago del ingreso;\nDOTACIÓN A PARA EL EJERCICIO FISCAL 2014 población con carencia por acceso a los servicios de salud; población con carencia por acceso a la seguridad social; y pobreza.\n• En tercera instancia, la identificación de los beneficiarios y las beneficiarias, se realiza a través de la Encuesta para Focalizar Hogares con Inseguridad Alimentaria (ENHINA), (ver anexo 11), instrumento que se compone por tres cuestionarios: socioeconómico, calidad de la dieta, y de inseguridad alimentaria, los cuales clasifican a las familias que la responden en distintos grados de nivel socioeconómico: alto, medio, bajo y muy bajo; en la variedad y diversidad de su dieta; y entre un nivel de inseguridad alimentaria severa, moderada, leve o seguros alimentarios. Así mismo, ofrece una calificación global de inseguridad/seguridad alimentaria, la cual va en la misma escala de inseguridad alimentaria descrita anteriormente, pero considerando cada uno de los tres cuestionarios, por lo que es un concepto mucho más completo, del cual se puede arribar a mejores conclusiones.\n8.2.- MÉTODO DE SELECCIÓN PARA LOS INSUMOS ALIMENTARIOS\nEl presente numeral se fundamenta en los Lineamientos de la estrategia Integral de Asistencia Social\nAlimentaria 2014, emitida por el Sistema Nacional para el Desarrollo Integral de la Familia y Secretaria de\nSalud; la cual aplica para los Sistemas Estatales DIF, la cual mandata elaborar las Reglas de Operación por programa, con el propósito de transparentar y normar la distribución y entrega de los apoyos alimentarios, de acuerdo con lo establecido en el artículo 77 de la ley Federal de presupuesto y\nResponsabilidad Hacendaria (última reforma DOF 09-04-2012).\nLos insumos alimentarios que serán entregados a los beneficiarios o beneficiarias deberán ser elegidos:\n• Con base en los Criterios de Calidad Nutricia Específicos para cada programa alimentario.\n• Dar preferencia a los productos regionales, siempre que existan opciones y que éstos cumplan con las Especificaciones Técnicas de Calidad (ETC) establecidas.\nLas ETC, describen a detalle todas las características que debe presentar el insumo alimentario. Son una herramienta fundamental para garantizar la calidad nutricia y la inocuidad de los insumos adquiridos.\nDeben ser claras y fundamentarse con base en las Normas Oficiales Mexicanas vigentes, de acuerdo a cada insumo alimentario. En caso que no exista normatividad nacional respecto a un insumo en específico, se fundamentan con normas internacionales aplicables (Ver Anexo 12).\nEn cuanto al etiquetado, todo alimento que se distribuya, deberá cumplir con la norma de etiquetado\nNOM-051-SCFI/SSA1-2010 \"Especificaciones Generales de Etiquetado para Alimentos y Bebidas no\nAlcohólicas Preenvasados-Información comercial y sanitaria, así como, la Leyenda del Presupuesto de\nEgresos de la Federación \"Este programa es público, ajeno a cualquier partido político. Queda prohibido el uso para fines distintos a los establecidos en el programa\". manipulación inapropiada, pudiendo ocasionar afectaciones a la salud.\nDOTACIÓN A PARA EL EJERCICIO FISCAL 2014\nEn el caso de la leche, se deberá aplicar la NOM-155-SCFI-2012 \"Leche-Denominaciones, Especificaciones Fisicoquímicas, Información Comercial y Métodos de Prueba.\nUna vez elegidos los insumos alimentarios, para adquirirlos, se lleva a cabo la Licitación Pública\nNacional, con el objetivo de contratar un proveedor (productor directo o comercializador), considerando el cumplimiento de las especificaciones establecidas, su capacidad de producción, almacenamiento y distribución, las prácticas de higiene y otros controles que aseguren la inocuidad de los insumos alimentarios; así como, el precio y su financiamiento, sin perder de vista el objetivo de los programas alimentarios. Así mismo, se establecen los términos y condiciones a los que deben ajustarse los licitantes que decidan participar en el proceso. Se deben considerar al menos los siguientes puntos:\nCriterios de evaluación (se utilizarán para establecer los criterios de selección de las ofertas y los requisitos que deberá poseer el licitante para ejecutar el contrato). Presentación de propuestas (técnica y económica por parte de los licitantes). Plan de rutas de entrega y cronograma de cumplimiento.\nEspecificaciones Técnicas de Calidad (ETC) de los insumos alimentarios. (Ver anexo 10) Condiciones de transporte y embalaje de los insumos por parte del proveedor.\nSolicitud de documentos de control de cumplimiento de ETC (análisis de laboratorio y certificados de calidad). Deben especificarse las características del documento, frecuencia con que deben realizarse y entregarse al SEDIF.\nCertificados de fumigación para transporte y almacenes indicando frecuencia, plagas que controla y sustancias químicas utilizadas, así como la licencia donde se acredite a la empresa encargada del control de plagas, expedida por la Secretaría de Salud.\nVisitas de inspección sanitaria a almacenes de proveedores, indicando las condiciones bajo las cuales se llevarán a cabo.\nSanciones o penalizaciones por incumplimiento en ETC, en la entrega de documentación de control y en las entregas de insumos a los beneficiarios y las beneficiarias.\nAnexos (en ellos pueden explicarse de manera detallada: características de las ofertas, guías de documentación a presentar, Especificaciones Técnicas de Calidad de los insumos, reglas a las que se sujetarán al presentar ofertas, entre otras).\n9. MECÁNICA DE OPERACIÓN\n9.1. INSTANCIA EJECUTORA de Asistencia Alimentaria y Desarrollo Comunitario, quien tendrá la responsabilidad de verificar que la\nDOTACIÓN A PARA EL EJERCICIO FISCAL 2014 instancia normativa, tales como apego a la planeación estratégica, programación, presupuestación, calendario de ejecución, ejercicio y control del gasto público.\n9.2. INSTANCIA ADMINISTRATIVA Y NORMATIVA\nDirección de Asistencia Alimentaria y Desarrollo Comunitario, quienes tendrán la responsabilidad de definir los métodos y procedimientos para normar y regular la ejecución del programa, tales como mecanismos de control y seguimiento durante su ejecución, para asegurar el cumplimiento de los objetivos y metas trazadas.\n9.3. DELIMITACIÓN DE ATRIBUCIONES\nEl DIF Guerrero establecerá los mecanismos de coordinación necesaria para garantizar que sus programas y acciones no se contrapongan, afecten o presenten duplicidades con otros programas o acciones del gobierno estatal; la coordinación institucional y vinculación de acciones busca potenciar el impacto de los recursos, fortalecer la cobertura de las acciones, detonar la complementariedad y reducir gastos administrativos.\n10. DERECHOS, OBLIGACIONES Y SANCIONES DE LOS BENEFICIARIOS Y LAS BENEFICIARIAS\nDE LOS PROGRAMAS SOCIALES\n10.1. DERECHOS\na) Recibir trato digno, respetuoso y equitativo sin discriminación alguna, por el personal de las distintas áreas que participen dentro del programa.\nb) Tener la reserva y privacidad de la información personal\nc) Acceder a las información necesaria del programa, sus Reglas de Operación, recursos y cobertura\nd) Solicitar y recibir información sobre el estado que guarda su trámite.\ne) Recibir los servicios y prestación del programa conforme a las Reglas de Operación, salvo que le sea suspendido su apoyo por alguna razón justificable.\nf) Recibir del Sistema Estatal una respuesta en los 30 días hábiles, después de haber entregado sus documentos y haber sido aceptado dentro del programa.\n10.2. OBLIGACIONES\na) Proporcionar la información socioeconómica bajo protesta de decir verdad que les sea requerida por el DIF Guerrero, en los términos que establezca la normatividad correspondiente.\nb) Utilizar los apoyos para los fines con que fueron autorizados evitando cualquier uso distinto de la misma.\nc) Permitir la visita con la finalidad de validar la información proporcionada en sus expedientes correspondientes\nDOTACIÓN A PARA EL EJERCICIO FISCAL 2014\nd) Facilitar los trabajos de verificación, en cualquier momento después de otorgado el apoyo.\n10.3. SANCIONES\nNormativas para acceder a los beneficios que a través de estos se otorgan, perderán las prerrogativas que dichas disposiciones establezcan.\n11. INTERPRETACIÓN\nLa interpretación de las presentes Reglas de Operación para efectos administrativos, estarán a cargo del\nDIF Guerrero, así como de la Contraloría General del Estado, en el ámbito de sus respectivas competencias.\nDIRECTOR DE ASISTENCIA ALIMENTARIA Y\nDESARROLLO COMUNITARIO.\nM.C. URIEL ADAME PÉREZ.\nRúbrica.\nDIRECTORA GENERAL DEL DIF GUERRERO.\nQBP. SARA SALINAS BRAVO.\nRúbrica.\nDIRECTOR GENERAL DE PROGRAMAS DE\nINVERSIÓN DEL COPLADEG.\nLIC. SALVIO HERRERA LOZANO.\nRúbrica.",
  "ordenamiento": "REGLA",
  "jurisdiccion": "GUERRERO",
  "fuente_oficial": "DIARIO OFICIAL DE LA FEDERACION",
  "Fecha de Publicación": "15 de julio de 1986",
  "ULTIMA REFORMA PUBLICADA": null,
  "status": "VIGENTE",
  "es_escaneado": false,
  "tiene_tablas": true,
  "materia": [
    "desarrollo social",
    "alimentación"
  ]
}