{
  "titulo": "Acuerdo por el Que Se Emiten las Reglas de Operación del Programa de Apoyos A la Producción Agropecu",
  "Contenido": "SACACOSECHA Y BORDOS\nTEXTO ORIGINAL\nA LA PRODUCCIÓN AGROPECUARIA, CAMINOS SACACOSECHA Y BORDOS.\nJuan José Castro Justo, Secretario de Agricultura, Ganadería, Pesca y Desarrollo Rural, con fundamento en los artículos 1°, 2°, 3°, 4°, 6°, 7° de la Ley de Desarrollo Rural Sustentable del Estado de\nGuerrero, publicada en el Periódico Oficial de fecha 21 de octubre del 2011, así como su homóloga Federal, en los diversos 1°, 2°, 5°, 6°, 7°, 8°, 9° y 32 publicada en el Diario Oficial de la Federación el 7 de diciembre de 2001, además tomando en consideración lo estipulado en el Presupuesto de Egresos del Estado de\nGuerrero para el ejercicio fiscal 2018, publicado en el decreto número 654, en el Periódico Oficial, el 12 de diciembre del año 2017, y\nQue el Estado de Guerrero cuenta con una superficie potencial susceptible de ser aprovechada con actividades del sector primario, del orden de 6.3 millones de hectáreas; de éstas, para uso forestal son aproximadamente 2 millones de hectáreas; para otros usos le corresponden 0.7 millones de hectáreas; mientras que a la actividad pecuaria se destinan 2.9 millones de hectáreas; y a la agricultura casi 0.8 millones de hectáreas. Es importante mencionar que la superficie agrícola se clasifica, por su condición, de temporal y de riego, a la primera pertenecen casi 0.7 millones de hectáreas y a la segunda casi 0.09 millones de hectáreas. El 91.3% de esta superficie es de propiedad ejidal y el 8.4% es propiedad privada.\nEl sector primario de la economía aporta el 10.84 % en la conformación del producto interno bruto estatal y absorbe el 2 6 % de la población ocupada. Tanto el campo como la industria no son competitivos en el mercado nacional e internacional, solo el turismo sobresale en este contexto.\nQue en esta entidad suriana, la agricultura, representa una de las ramas económicas de mayor relevancia, aun cuando su aportación sea limitada en los indicadores del comercio estatal, nacional e internacional; sin embargo, socialmente, es por excelencia la que mayor aporte hace para la sobrevivencia de un gran número de familias.\nQue el Programa de Apoyos a la Producción Agropecuaria, Caminos Sacacosecha y Bordos, tiene como objetivo general, cumplir con lo establecido en la Ley de Desarrollo Rural Sustentable del Estado de\nGuerrero, asi como la homóloga Federal. Por lo expuesto y con fundamento en las disposiciones legales antes citadas, he tenido a bien expedir el siguiente:\nÚNICO.- Se expiden las Reglas de Operación del Programa Apoyos a la Producción Agropecuaria, Caminos Sacacosecha y Bordos, las cuales se anexan al presente.\nSACACOSECHA Y BORDOS\nTRANSITORIOS\nPRIMERO.- Las presentes reglas de operación, entrarán en vigor al dia siguiente de su publicación en los medios electrónicos oficiales.\nEL SECRETARIO DE AGRICULTURA, GANADERÍA,\nPESCA Y DESARROLLO RURAL LIC. JUAN JOSÉ CASTRO JUSTO.\nRúbrica.\nREGLAS DE OPERACIÓN\nPrograma Apoyos a la Producción Agropecuaria, Caminos Sacacosecha y Bordos 2018\nEnero de 2018\n1.- INTRODUCCIÓN\n1.1 Antecedentes\n1.2 Alineación Programática\n1.3 Diagnóstico\n2. MISIÓN Y VISIÓN\n2.2 Misión\n2.2 Visión\n3 DEPENDENCIA O ENTIDAD RESPONSABLE DEL PROGRAMA\n4 FUNDAMENTO LEGAL\n5 OBJETIVOS Y ALCANCES\n5.1 Objetivo General\n5.2 Objetivos Específicos\n5.3 Alcances\n6 METAS FÍSICAS\n7 PROGRAMACIÓN PRESUPUESTAL\n8 REQUISITOS Y PROCEDIMIENTOS DE ACCESO\n8.1 Difusión\n8.2 Requisitos de Acceso\nSACACOSECHA Y BORDOS\n8.3 Procedimientos de Acceso\n8.4 Requisitos de Permanencia, Causales de baja o Suspensión Temporal\n8.5 Modos de entrega del beneficio\n9 PROCEDIMIENTOS DE INSTRUMENTACIÓN\n9.1 Operación\n9.2 Gastos de operación\n10. TRANSPARENCIA\n10.1 Difusión\n10.2 Blindaje electoral\n10.3 Supervisión y Control\n10.4 Mecanismos de Evaluación e Indicadores\n10.4.1 Evaluación\n10.4.2 Indicadores\n10.5 Auditoría\n10.6 Recursos no devengados\n10.7 Contraloría social\n10.8 Procedimiento de Queja o Inconformidad Ciudadana\n10.9 Mecanismo de Exigibilidad\n10.10 Acta de Entrega-Recepción\n11. CRITERIOS DE SELECCIÓN Y ELEGIBILIDAD\n11.1 Método de selección de beneficiarios\n12 MECÁNICA DE OPERACIÓN\n12.1 Instancia ejecutora\n12.2 Instancia administrativa y/o normativa\n12.3 Delimitación de atribuciones\n13. DERECHOS, OBLIGACIONES Y SANCIONES DE LOS BENEFICIARIOS\n13.1 Derechos\n13.2 Obligaciones\n13.3 Sanciones\n14 INTERPRETACIÓN\nAnexos\nSACACOSECHA Y BORDOS\nI. INTRODUCCIÓN\n1.1. ANTECEDENTES productores agropecuarios y pesqueros acerca de obtener subsidios para la adquisición de equipos, herramientas, servicios, especies animales y obras agropecuarias, que en programas federales no son susceptibles de apoyos, pero que los productores en realidad utilizan en las labores diarias en sus unidades de producción rural.\nLa creación del programa, se fundamenta en el Plan Estatal de Desarrollo Rural 2016-2021, específicamente en el eje II Guerrero Próspero, el cual mandata promover la diversificación de la economía y aprovechar las potencialidades que existen en nuestro estado. Para que Guerrero tenga un cambio cualitativo en su economía, se contempla impulsar cinco proyectos estratégicos entre los que se encuentra la Producción Agroindustrial, estableciendo como objetivo construir un sector agropecuario y pesquero productivo que garantice la seguridad alimentaria del Estado.\nActualmente en la Ley Orgánica de la Administración Pública del Estado de Guerrero número 08, publicada el día 23 de octubre de 2015, en su artículo 31 contempla a la Secretaria de Agricultura, Ganadería, Pesca y Desarrollo Rural, como el órgano encargado de Promover y Fomentar el Desarrollo\nAgrícola, Forestal, Ganadero, Pesquero, así como el manejo de los recursos naturales en el Estado, procurando la participación de las mujeres, en igualdad de condiciones.\n1.2 ALINEACIÓN PROGRAMÁTICA\nEl programa está alineado al Plan Estatal de Desarrollo del Estado de Guerrero 2016-2021 y al\nPrograma Sectorial de Desarrollo Rural y Pesca 2016-2021, en el eje programático Guerrero Próspero, al objetivo 2.2 Impulsar la productividad del sector agropecuario y pesquero, para garantizar la seguridad alimentaria, a la estrategia 2.2.1 Fortalecer los sectores agropecuario y pesquero y crear condiciones para aumentar la competitividad y la autosuficiencia para garantizar la seguridad alimentaria en la entidad y a las líneas de acción Apoyar en coordinación con los productores, a mercados nacientes como el de la floricultura y plantas ornamentales. La diversificación de productos guerrerenses es necesaria para detonar el desarrollo del sector agrícola y Promover la producción de ganado bovino, porcino y caprino en el Estado y su presencia en los mercados nacional y extranjero.\n1.3 DIAGNÓSTICO\na) Problema social: los productores agropecuarios y pesqueros, obtienen bajos ingresos por las actividades agropecuarias y pesqueras que realizan en sus unidades de producción.\nb) Causas y Efectos observados del Problema Social: Las causas por las que los productores obtienen escasos ingresos es derivado de las escasas cosechas agrícolas, escasa producción pecuaria y escasa pesca en sus unidades de producción rural. Los efectos que se observan en la población por los\nSACACOSECHA Y BORDOS escasos ingresos, se refleja en un bajo poder adquisitivo, alimentación deficiente, bajo nivel educativo, alta incidencia de enfermedades y en general una mala calidad de vida.\nc) Resolución del problema identificado: Con el apoyo a los productores agropecuarios y pesqueros, en la adquisición de equipos, materiales, especies animales, insumos, maquinaria agrícola, apertura de caminos, e infraestructura, para el fomento y acceso a financiamiento y cultura agropecuaria, plataformas de información, contratación de servicios de asistencia técnica y capacitación, que coadyuven a realizar de manera más eficiente las labores agropecuarias y pesqueras, y que agreguen valor a la producción, contribuyendo a obtener mayor volumen en sus cosechas y obteniendo mejores ingresos por las ventas de los excedentes de sus cosechas.\nd) Línea Base: En el año 2016, se programó subsidiar a 7,000 productores agropecuarios y pesqueros.\ne) Población Potencial: La población total de la entidad es de 3,388,768, de los cuales, el 42% vive en el sector rural, mismos que por su productividad, rentabilidad y competitividad, los productores rurales, se ubican en tres segmentos, Productores de Menores Ingresos, en este segmento se encuentra el 78.7% de los productores y está conformado por productores de menores ingresos, temporaleros y su producción es para autoconsumo, el segundo segmento es el de Productores en transición, a este sector, corresponde el 20.9% de los productores, y está conformado por productores que se encuentran en proceso de alcanzar mayor productividad y competitividad y el tercer segmento, corresponde a los productores empresariales en los que se encuentran el 0.4% de los productores, estos productores están integrados al mercado nacional e internacional, son altamente eficientes y rentables.\nSACACOSECHA Y BORDOS\nLa población objetivo para el presente programa, son los productores de Menores ingresos, temporales y que su producción es para autoconsumo.\na. NATURALEZA DEL PROGRAMA SOCIAL\nEl programa de Apoyos a la Producción Agropecuaria, Caminos Sacacosecha y Bordos, es un programa social, que otorga subsidios para fomentar las actividades agropecuarias, pesqueras, acuícolas y de servicios en el medio rural de la entidad, a través de la adquisición de equipos, herramientas, servicios, especies animales y obras agropecuarias, coadyuvando a capitalizar las unidades de producción rural y mejorando el nivel de vida de los habitantes de las zonas rurales.\nb. EL ORIGEN Y FUNDAMENTO\nEl Programa se origina derivado de la urgente necesidad de atender las demandas de los productores rurales acerca de obtener subsidios para la adquisición de equipos, herramientas, servicios, especies animales y obras agropecuarias, que en programas federales no son susceptibles de apoyos, pero que los productores en realidad utilizan en las labores diarias en sus unidades de producción rural.\nLa creación del programa, se fundamenta en el Plan Estatal de Desarrollo Rural 2016-2021, específicamente en el eje II Guerrero Próspero, el cual mandata promover la diversificación de la economía y aprovechar las potencialidades que existen en nuestro estado. Para que Guerrero tenga un cambio cualitativo en su economía, se contempla impulsar cinco proyectos estratégicos entre los que se encuentra la Producción Agroindustrial, estableciendo como objetivo construir un sector agropecuario y pesquero productivo que garantice la seguridad alimentaria del Estado.\nActualmente en la Ley Orgánica de la Administración Pública del Estado de Guerrero número 08, publicada el día 23 de octubre de 2015, en su artículo 31 contempla a la Secretaria de Agricultura, Ganadería, Pesca y Desarrollo Rural, como el órgano encargado de Promover y Fomentar el Desarrollo\nAgrícola, Forestal, Ganadero, Pesquero, así como el manejo de los recursos naturales en el Estado, procurando la participación de las mujeres, en igualdad de condiciones.\nc. OBJETIVOS Y METAS\nEl programa tiene como objetivo fomentar en la población rural, la producción de alimentos a través del apoyo para la adquisición de maquinaria, insumos, especies animales, construcción de obras y mejora en las condiciones de infraestructura de caminos para el traslado de cosechas.\nLa meta es apoyar a 2,000 productores con diversos apoyos para el mejor desarrollo de sus actividades agropecuarias, acuícolas y de servicios.\nSACACOSECHA Y BORDOS\nd. UBICACIÓN GEOGRÁFICA DE LOS PROYECTOS A DESARROLLAR\nEl programa se implementará en el Estado de Guerrero, abarcando las ocho regiones económicas:\n• Tierra Caliente\n• Norte\n• Centro\n• Montaña\n• Costa Grande\n• Costa Chica\n• Acapulco\n• Sierra e. Actividades a Realizar\nOtorgar subsidio para la adquisición de equipos, materiales, especies animales, insumos, maquinaria agrícola, apertura de caminos, e infraestructura, para el fomento y acceso a financiamiento y cultura agropecuaria, plataformas de información, contratación de servicios de asistencia técnica y capacitación, que coadyuven a realizar de manera más eficiente las labores agropecuarias y pesqueras, y que agreguen valor a la producción.\nLa Secretaría de Agricultura, Ganadería, Pesca y Desarrollo Rural, elaborará un catálogo de conceptos a apoyar por el programa, mismo que se encontrará disponible en la página electrónica www.campoguerrero.gob.mx, que serán cubiertos con la aportación del Gobierno del Estado.\nAsimismo, la Secretaría de Agricultura, Ganadería, Pesca y Desarrollo Rural, de conformidad con la Ley de Administración de Recursos Materiales del Estado y las bases que para tal efecto emita la apoyos que comprende el Programa, en caso de ser necesario.\nLa Secretaría de Agricultura, Ganadería, Pesca y Desarrollo Rural, vigilará que los beneficiarios cumplan con los requisitos para acceder al programa y entregará los apoyos a los beneficiarios. f. Instancias participantes\nLa ejecución del programa estará a cargo de la Secretaria de Agricultura, Ganadería, Pesca y\nSACACOSECHA Y BORDOS g. Presupuesto de Inversión\nEn el decreto número 654 del Presupuesto de Egresos del Estado de Guerrero, para el programa de Apoyos a la Producción Agropecuaria, Caminos Sacacosecha y bordos establece la inversión de\n$25,756,800.00 (Veinticinco millones setecientos cincuenta y seis mil ochocientos pesos 00/M.N), presupuestos que derivado de las modificaciones presupuestales entre los programas que opera la\nSecretaría de Agricultura, Ganadería, Pesca y Desarrollo Rural, ascendió a la inversión de $32,756,800.00\n(Treinta y dos millones setecientos cincuenta y seis mil ochocientos pesos 00/100 M.N. h. Glosario de Términos:\nSAGADEGRO: Secretaría de Agricultura, Ganadería, Pesca y Desarrollo Rural.\nSEPLADER: Secretaría de Planeación y Desarrollo Regional.\nCURP: Clave única de Registro de Población.\nUPP: Unidad de Producción Pecuaria.\nRNPA: Registro Nacional de Pesca y Acuacultura.\nRFC: Registro Federal de Contribuyentes.\n2. MISIÓN Y VISIÓN\n2.1. MISIÓN\nImpulsar la producción de alimentos, mediante el otorgamiento de subsidios a productores rurales, para la adquisición de maquinaria, insumos, especies animales, construcción de obras y mejora en las condiciones de infraestructura de caminos para el traslado de cosechas, contribuyendo a elevar la productividad, la calidad, la inocuidad y la competitividad de los sectores agropecuarios, pesqueros y acuícolas, privilegiando la autosuficiencia agroalimentaria, así como el incremento al valor agregado y la comercialización de sus productos, a fin de mejorar la economía y las condiciones de vida de las familias del medio rural.\n2.2 VISIÓN\nSer el programa generador del desarrollo económico y sociocultural de la población rural de Guerrero, que transforme la pobreza alimentaria y económica, en soluciones y oportunidades a través de políticas públicas rentables, integrales y sustentables, mediante el impulso a la producción, la transformación y la comercialización de los productos agropecuarios, pesqueros y acuícolas, obteniendo así productos con potencial competitivo en los mercados regionales, nacional e internacional, que repercutan directamente en el bienestar social de los guerrerenses.\n3. DEPENDENCIA O ENTIDAD RESPONSABLE\n3.1 La Secretaría de Agricultura, Ganadería, Pesca y Desarrollo Rural, será la responsable directa de la ejecución del programa.\nSACACOSECHA Y BORDOS\n3.2 En la operación del programa participará la Subsecretaría de Desarrollo Rural Sustentable, la\nSubsecretaría de Agricultura e Infraestructura Rural, la subsecretaría de Ganadería y Pesca, y la\nDelegación Administrativa de la SAGADEGRO.\n3.3 El programa solo lo ejercerá la SAGADEGRO.\n3.4. La Subsecretaría de Desarrollo Rural Sustentable, será la encargada de registrar las solicitudes presentadas por los productores, presentarlas ante el Secretario de la SAGADEGRO, para su autorización correspondiente, posteriormente turnará a las Subsecretarías de Agricultura e Infraestructura\nRural, y de Ganadería y Pesca, para que revisen e integren las solicitudes en coordinación con los productores, estas subsecretarías, elaborarán las notificaciones de autorización para los productores, mismos que presentarán el acta de entrega recepción y la factura del bien adquirido, en las subsecretarías de Agricultura e Infraestructura Rural y de Ganadería y Pesca, para que realicen el trámite de pago ante la\nDelegación Administrativa, esta delegación, realizará el pago de los apoyos adquiridos al productor o al proveedor, según sea requerido por el productor.\n3.5 La SAGADEGRO será la dependencia involucrada en la operación del programa, así como las\nSubsecretarías de Desarrollo Rural Sustentable, la Subsecretaría de Agricultura e Infraestructura Rural, la\nSubsecretaría de Ganadería y Pesca y la Delegación Administrativa de la SAGADEGRO.\n3.6 La SAGADEGRO, es la entidad que será la responsable en la planeación y ejecución del programa.\n4. Fundamento Legal\nLas presentes reglas de operación, tienen su fundamento en las siguientes leyes:\nLey Orgánica de la Administración Pública del Estado de Guerrero, número 08, en el Artículo 31 establece que La Secretaría de Agricultura, Ganadería, Pesca y Desarrollo Rural, es el órgano encargado de promover y fomentar el desarrollo agrícola, forestal, ganadero, pesquero, así como del manejo de los recursos naturales en el Estado, procurando la participación de las mujeres, en igualdad de condiciones en estas actividades de diseño y planeación y cumplimiento correspondiéndole el despacho de los asuntos siguientes:\nI.- Elaborar los planes, programas y acciones, de corto, mediano y largo plazo, del sector agropecuario, forestal y pesquero, que respondan a un criterio de manejo sustentable de los recursos naturales, con la participación de las dependencias federales y estatales correspondientes, ayuntamientos, organizaciones de productores individuales y campesinos, en el seno de la Secretaría de Planeación y\nDesarrollo Regional y coordinar su implementación;\nII.- Formular y ejecutar los planes, programas y acciones para el desarrollo integral de las personas que viven y trabajan en zonas rurales del Estado, principalmente aquellos dirigidos a mejorar las condiciones de las mujeres;\nSACACOSECHA Y BORDOS\nIII.- Fomentar, formular, supervisar y coordinar la operación de los programas de desarrollo agrícola, ganadero, pesquero con criterios de manejo sustentable de los recursos naturales.\nIV.- Apoyar la organización para la producción, coordinando con las dependencias federales afines y productores, las acciones para el financiamiento, seguros, insumos, asistencia técnica y administrativa, investigación, capacitación y transferencia de tecnología, en beneficio de mujeres, campesinos, ejidatarios, comuneros, pequeños propietarios y organizaciones de productores legalmente constituidos;\nDecretos Presidenciales y Secretariales.\n1 Constitución Política de los Estados Unidos Mexicanos, publicada en el Diario Oficial de la\nFederación de fecha 5 de febrero de 1917; artículos 1, 27 fracción XX, 26 inciso a), párrafo 3° y artículo 25 párrafo 2°.\nEstado de Guerrero, Número 18, 19 y 20 del 3, 10 y 17 de noviembre de 1917 y número 1 del 5 de enero de 1918, artículos 1 58, 59 y 74 en su fracción XXXVII.\nLeyes:\n2 Ley de Desarrollo Rural Sustentable, publicada en el Diario Oficial de la Federación de fecha 7 de diciembre del 2001, artículos 1,2,3,4,5,6,7,8,9,12,13,17,21 y 178;\n3 Ley Número 814 de Desarrollo Rural Sustentable del Estado de Guerrero, publicada en el\nPeriódico Oficial del Gobierno del Estado de Guerrero, de fecha 21 de octubre de 2011, artículos 1,2,3,4,6 y 7;\nPeriódico Oficial del Gobierno del Estado de Guerrero, de fecha 26 de diciembre de 2008, artículos 1,2,3,4,5 y 6;\n5 Ley de Administración de Recursos Materiales del Estado de Guerrero, publicada en el Periódico\n7 El Plan Estatal de Desarrollo 2016-2021 específicamente en el eje II Guerrero Próspero, establece diversificar la economía y aprovechar las potencialidades que existen en nuestro Estado, para que Guerrero tenga un cambio cualitativo en su economía, teniendo como objetivo construir un sector agropecuario y pesquero productivo que garantice la seguridad alimentaria del Estado.\nSACACOSECHA Y BORDOS\n8 Decreto 654 del Presupuesto de Egresos del Estado de Guerrero, publicado en el Periódico productivas en el medio rural.\n5. OBJETIVOS Y ALCANCES\n5.1 Objetivo General\nCoadyuvar en la capitalización de las unidades de producción rural y mejorar el nivel de vida de los habitantes de las zonas rurales a través del apoyo en la adquisición de maquinaria, insumos, especies animales, construcción de obras y mejora en las condiciones de infraestructura de caminos para el traslado de cosechas.\n5.2 Objetivo Específico\nSubsidiar la adquisición de maquinaria, insumos, especies animales, construcción de obras y mejora en las condiciones de infraestructura de caminos para el traslado de cosechas, para fomentar la producción de alimentos en las zonas rurales de la entidad.\n5.3 Alcances\ng) Con la implementación del programa se busca que los productores agropecuarios y pesqueros, sean capaces de obtener mayor volumen en sus cosechas y los excedentes sean comercializados para obtener ingresos que mejoren su nivel de vida.\nh) El programa otorgará apoyos o subsidios a los productores agropecuarios y pesqueros de la entidad.\ni) La población objetivo del programa son los productores agropecuarios, pesqueros y acuícolas de escasos ingresos.\n6. METAS FÍSICAS\nLa meta del programa, es apoyar a 2,000 productores con diversos apoyos para el mejor desarrollo de sus actividades agropecuarias, pesqueras y acuícolas y de servicios.\n7. PROGRAMACIÓN PRESUPUESTAL\n7.1 El monto total del presupuesto autorizado para el ejercicio fiscal es de $25,756,800.00\n(Veinticinco millones setecientos cincuenta y seis mil ochocientos pesos 00/100 M.N.), y derivado de\nSACACOSECHA Y BORDOS modificaciones presupuestales, la inversión que se ejercerá, asciende a $32,756,800 (Treinta y dos millones setecientos cincuenta y seis mil ochocientos pesos 00/100 M.N.)}\n7.2 El calendario de gasto es el siguiente:\n8. REQUISITOS Y PROCEDIMIENTOS DE ACCESO\nPara la obtención de los apoyos, los productores agropecuarios, pesqueros y acuicolas, deberán observar y cumplir con los requisitos:\n8.1. DIFUSIÓN\nLa Secretaría de Agricultura, Ganadería, Pesca y Desarrollo Rural, dará amplia difusión de los programas que ejecuta y opera en coordinación con las diferentes secretarías que la conforman, a través de diferentes medios de comunicación impresos y electrónicos para que la población conozca los beneficios y requisitos de los programas.\nLa información de los programas se darán a conocer en la página de internet campoguerrero.gob.mx, de la Secretaría de Agricultura, Ganadería, Pesca y Desarrollo Rural.\nLos horarios de atención a los productores, será de lunes a viernes de 09:00 a 16:00 horas en las instalaciones de la SAGADEGRO, sita en Carretera Nacional México - Acapulco Km 274.5, Colonia\nBurócratas, teléfono 01 747 1 92 10.\nEl programa también será difundido en reuniones por personal de la SAGADEGRO, quienes se apoyaran interesados deben reunir.\nLa cobertura del programa será estatal, ateniéndose los productores agropecuarios, pesqueros y acuícolas de la entidad.\nSACACOSECHA Y BORDOS\n8.2 Requisitos de Acceso\nLos productores interesados en obtener beneficios del programa, deberán presentar en la ventanilla de la Secretaría de Agricultura, Ganadería, Pesca y Desarrollo Rural, la siguiente documentación:\nApoyos de manera individual:\nPara la obtención del apoyo los interesados deberán presentar o Solicitud de apoyo en el formato establecido (Anexo a), proporcionado en la Secretaría de\nAgricultura, Ganadería, Pesca y Desarrollo Rural y disponibles en la página www.campoguerrero.gob.mx, ó Anexo I del programa de Concurrencia. o Comprobante de domicilio con vigencia no mayor a tres meses o Copia de identificación oficial vigente (credencial de elector, pasaporte, cartilla de servicio militar nacional o cédula profesional). o Copia de la CURP o Documento que acredite la actividad productiva o En el caso de apoyos a solicitudes provenientes del Programa de Concurrencia, deberán presentar para el caso de proyectos pecuarios la constancia UPP y para proyectos pesqueros y/o acuícolas el RNPA y para proyectos de apicultura clave de rastreabilidad de miel.\nApoyos a productores organizados en grupos o Presentar solicitud de apoyo en el formato establecido, (Anexo a), firmada por el representante del grupo, ó Anexo I del programa de Concurrencia. o Comprobante de domicilio con vigencia no mayor a tres meses o Copia de las identificaciones oficiales vigentes (credencial de elector, pasaporte, cartilla de servicio militar nacional o cédula profesional). o Copia de la CURP o Acta constitutiva de grupo de trabajo o Relación de integrantes del grupo o Documento que acredite la actividad productiva o En el caso de apoyos a solicitudes provenientes del Programa de Concurrencia, deberán presentar para el caso de proyectos pecuarios la constancia UPP y para proyectos pesqueros y/o acuícolas el RNPA y para proyectos de apicultura clave de rastreabilidad de miel.\nPara la obtención de garantías líquidas, deberán presentar los siguientes requisitos: o Autorización de la línea de crédito. o Contrato del fideicomiso crédito. o Acta constitutiva del sujeto de crédito (en caso de personas morales) o RFC o CURP o Comprobante de domicilio\nSACACOSECHA Y BORDOS\n8.3. Procedimiento de Acceso\n8.3.1 Los productores agropecuarios y pesqueros, deberán presentar la solicitud de apoyo, conforme al anexo a) y/o el formato Anexo 1.\n8.3.2 Los criterios para ser beneficiarios, son: presentar su solicitud de apoyo, acompañada de la documentación personal, posteriormente, la SAGADEGRO, analizara y viabilidad de apoyo de la solicitud, con base en el disposición presupuestal del programa.\n8.3.3 Podrán ser beneficiarios del programa todos los productores agropecuarios y pesqueros de la entidad.\n8.3.4 La documentación será recepcionada en las instalaciones que ocupa la SAGADEGRO, de lunes a viernes en horario de 09:00 a 16:00 horas.\n8.3.5 Se dará prioridad de atención a las solicitudes de apoyo, dirigidas a cultivos de mayor relevancia para la entidad.\n8.3.6 Las solicitudes de apoyo autorizadas, podrán ser consultadas en la página electrónica www.campoguerrero.gob.mx,\n8.3.7 La SAGADEGRO, entregará un comprobante al productor de haber completado su registro en el programa.\n8.3.8 Los productores que sean autorizados con apoyos del programa, serán incorporados al\nPadrón Único de Beneficiarios de la SAGADEGRO, siendo reservados sus datos personales y en ningún caso podrán emplearse para propósitos de proselitismo político, religioso o comercial, ni para ningún otro distinto al establecido en las presentes reglas de operación.\n8.3.9 En ningún caso las y los servidores públicos podrán solicitar o proceder de manera diferente a lo establecido en las reglas de operación. programa.\nLos productores conocerán el estado de su trámite, en la página electrónica\nLas solicitudes dictaminadas como positivas de apoyo, se incorporaran al programa, y formarán parte de un Padrón Único de Beneficiarios, será de carácter público, siendo reservados los datos personales, de acuerdo con la normatividad vigente; los cuales en ningún caso podrán emplearse para propósitos de proselitismo político, religioso o comercial, ni para ningún otro fin distinto al establecido en las Reglas de Operación del programa social.\nSACACOSECHA Y BORDOS las presentes Reglas de Operación.\n8.4 Requisitos de Permanencia, Causales de Baja o Suspensión Temporal\n8.4.1 El beneficiario está obligado a:\n• Dar buen uso, conservación y/o mantenimiento de los bienes recibidos\n• Otorgar las facilidades y proporcionar la información necesaria a las instancias de coordinación, supervisión y control de los niveles de gobierno facultados para realizar visitas de inspección y monitoreo de los apoyos otorgados.\n• Seguir las recomendaciones técnico-productivas emitidas por las instancias de gobierno.\n• Mantener los apoyos por un plazo mínimo de tres años con el fin de que estén disponibles para las supervisiones físicas y documentales de las instancias de control y fiscalización\n• Sanciones\n• Los beneficiarios del programa que incumplan con las obligaciones, y/o presenten documentos falsos, la instancia normativa, definirá la sanción a la que se hará acreedor.\n8.5 Modos de entrega del beneficio\nPara los productores que hayan cumplido en tiempo y forma con el trámite de la entrega de la documentación en los formatos establecidos, se les comunicará los lugares para la entrega de los apoyos, debiendo ser preferentemente en actos públicos organizados por el Gobierno del Estado.\n9. PROCEDIMIENTOS DE INSTRUMENTACIÓN\n9.1 Operación\n9.1.1 Para acceder a los beneficios del programa, los productores presentarán en la\nSAGADEGRO, la solicitud en el formato establecido, misma que será registrada, analizada y dependiendo de la suficiencia presupuestal, se le notificará al productor que haya sido beneficiado, para que continúe con la adquisición, comprobación y se le tramite el pago del beneficio.\n9.1.2 En las subsecretarías de Agricultura e Infraestructura Rural, Ganadería Pesca y de\nDesarrollo Rural Sustentable y la Delegación Administrativa de la SAGADEGRO, serán las responsables de coordinar esfuerzos para la operación del programa.\n9.1.3. Los datos personales de las personas beneficiarias del programa, y la información adicional\nInformación Pública del Estado de Guerrero.\nSACACOSECHA Y BORDOS\n9.1.4. Los formatos y los trámites a realizar para la obtención del beneficio del programa, son gratuitos.\n9.2. Gastos de Operación.\nPara cubrir los gastos ocasionados por la operación, seguimiento, supervisión y verificación de las acciones del programa, se dispondrá hasta el 3% de la inversión total del programa. Estos recursos corresponden al capítulo 4000 de la apertura programática.\nEn la erogación de los gastos de operación se deberán observar los criterios de racionalidad, austeridad presupuestal, propiciando la eficiencia, eficacia y transparencia.\n10. TRANSPARENCIA\n10.1 Difusión\nLa SAGADEGRO, dará amplia difusión al programa Apoyos a la Producción Agropecuaria, Caminos Sacacosecha y Bordos, a nivel estatal a través de la página electrónica campoguerrero.gob.mx, folletos y en reuniones que se organicen por región y/o municipio, así como con organizaciones de productores, y para mayor información acudir a las instalaciones que ocupa la SAGADEGRO, sita en\nCarretera Nacional México-Acapulco km 274.5 Colonia Burócratas, Chilpancingo de los Bravo, de lunes a viernes en horario de 09:00 a 16:00 horas, o llamar al teléfono 017474719210.\nLa papelería, publicidad y promoción del programa incluirá la leyenda descrita en el apartado\n\"Blindaje Electoral\".\nLa información de montos y beneficiarios se publicará en los términos de la ley No. 207 de\nTransparencia y Acceso a la Información Pública del Estado de Guerrero.\n10.2 Blindaje electoral\nPara blindar al programa del clientelismo y que no sea utilizado para usos partidistas, en la documentación siempre deberán incluir la leyenda siguiente:\n\"Este programa es de carácter público, no es patrocinado ni promovido por partido político alguno y sus recursos provienen de los impuestos que pagan todos los contribuyentes. Está prohibido el uso de este programa con fines políticos, electorales, de lucro y otros distintos a los establecidos. Quien haga uso indebido de los recursos de este programa en el Estado de Guerrero, será sancionado de acuerdo con la ley aplicable y ante la autoridad competente.\nEn cuanto a la publicidad en medios electrónicos impresos, complementarios o de cualquier otra índole, vinculados con los programas de comunicación social, se deberá incluir la siguiente leyenda: \"Este programa es público y queda prohibido su uso con fines partidistas o de promoción personal\".\nSACACOSECHA Y BORDOS\n10.3. Supervisión y Control\na) Como procedimiento interno de supervisión y control del programa, se utilizarán informes mensuales, trimestrales, semestrales y anuales.\nb) Las Subsecretarías de Agricultura e Infraestructura Rural, Ganadería y Pesca y de Desarrollo\nRural Sustentable y la Delegación Administrativa de la SAGADEGRO, serán las responsables de coordinar esfuerzos para la operación del programa.\nc) Se enviarán trimestralmente a la Secretaría de Finanzas, a la Secretaría de Planeación y a la\nSecretaría de Contraloría, informes sobre el Presupuesto ejercido establecidos por el Consejo Nacional de\nArmonización Contable (CONAC) y con base en los indicadores de resultados previstos en las Reglas de\nOperación.\nd) Se adicionaran a los informes, la evaluación de los indicadores determinados en el programa.\ne) La SAGADEGRO, remitirá a la SEPLADER, el calendario de entrega de los apoyos.\nf) La SAGADEGRO integrará un Padrón Único de Beneficiarios del programa.\n10.4 Mecanismo de Evaluación e Indicadores.\n10.4.1 Evaluación.\nCon el propósito de conocer los resultados de los programas y proyectos sociales, se solicitará nacional, que cuenten con reconocimiento y experiencia en la materia; y en los términos de las disposiciones establecidas por las instancias normativas correspondientes.\n10.4.2 Indicadores\nSACACOSECHA Y BORDOS\n10.5 Auditoria\nLos recursos ejercidos en el programa, podrán ser fiscalizados por el Órgano Estatal de Control y demás instancias que el ámbito de sus respectivas atribuciones resulten competentes.\nComo resultado de las acciones de auditoría que se lleven a cabo, el Órgano Estatal de Control mantendrá un seguimiento interno que permita emitir los informes de las revisiones practicadas, dando principal importancia a la atención en tiempo y forma, de las irregularidades detectadas, hasta su total solventación.\n10.6 Recursos no devengados\nEl presupuesto autorizado que no se aplique a los fines autorizados, y los recursos que por cualquier motivo no estén devengados al 31 de diciembre, serán reintegrados a la Tesorería de la\n10.7 Contraloría social\nSe establecerán acciones de control, vigilancia y evaluación, bajo un esquema de derechos y compromisos ciudadanos, con el propósito de contribuir a que la gestión gubernamental se realice en términos de transparencia, eficacia y honradez.\nEstas actividades estarán a cargo de los miembros de la comunidad, incluidos los integrantes del comité o instancia asociativa de los beneficiarios del programa. efecto, fomentando acciones que transparenten la operación del programa en cuestión.\nSACACOSECHA Y BORDOS\nLas acciones a fomentar serán las siguientes:\na) Informar a la ciudadanía acerca de los apoyos otorgados y su costo a nivel de obra, acción, nombre de los beneficiarios, derechos y obligaciones de los mismos.\nb) Capacitar a los beneficiarios para que se constituyan en instancias de vigilancia y evaluación social.\nc) Establecer espacios de comunicación (reuniones vecinales, atención directa a beneficiarios, etc).\nd) Promover la integración de organizaciones de la sociedad civil en acciones de contraloría social.\ne) Instrumentar mecanismos de recepción y atención de quejas y denuncias. El Órgano Estatal de\nControl verificará, en lo correspondiente, la realización de dichas acciones.\n10.8 Procedimiento de Queja o Inconformidad Ciudadana\nLas quejas y denuncias de la ciudadanía en general por la presunción de actos de corrupción o desvío de recursos por parte de servidores públicos, se captarán por la Contraloría y la Auditoría General del Estado, a través de denuncias por escrito, vía internet, vía telefónica y por comparecencia del interesado. El sitio es www.contraloria.guerrero.gob.mx, y al teléfono 01 800 000 7422.\nEl denunciante o quejoso deberá proporcionar los siguientes datos:\na) Nombre del Servidor (s) Público (s)\nb) Dependencia de adscripción\nc) Objeto de la denuncia\nd) Nombre y domicilio del quejoso\ne) Identificación Oficial\n10.9 Mecanismos de Exigibilidad\nLos productores podrán verificar el estatus de su solicitud en la página electrónica campoguerrero.gob.mx.\n10.10. Acta de Entrega Recepción\nPara cada una de las obras terminadas o acciones entregadas, se elaborará un acta de entregarecepción, en la que participará un representante de la Secretaría de Agricultura, Ganadería, Pesca y\nDesarrollo Rural y un representante de la comunidad beneficiada y/o un beneficiario.\nMunicipales. De conformidad con el acta de entrega-recepción, la comunidad o el orden de gobierno que recibe las obras o acciones, deberá hacer explícito en el acta el compromiso de vigilar su adecuada operación y darle el mantenimiento correspondiente.\nEl acta de entrega. Recepción forma parte del expediente de la obra o acción y constituye la prueba documental que certifica la existencia de la obra o acción.\nSACACOSECHA Y BORDOS\nEs responsabilidad de la Secretaría de Agricultura, Ganadería, Pesca y Desarrollo Rural, resguardar las actas de entrega recepción, así como el expediente de la obra o acción.\n11. Criterios de selección y elegibilidad\n11.1 Método de selección y elegibilidad\nSerán susceptibles de apoyos todos los productores y/o productoras, de bajos ingresos del medio rural que se dediquen o quieran dedicarse a realizar actividades agrícolas, pecuarias, pesqueras y forestales.\nPara ser beneficiarios, deberán cumplir con presentar la documentación requerida en el numeral\n8.2 de las presentes reglas de operación, según sea el caso de solicitar apoyo de manera individual o por grupo u organización.\n12. Mecánica de Operación\nLa Secretaría de Agricultura Ganadería, Pesca y Desarrollo, designará un responsable del\nPrograma y un auxiliar administrativo quienes llevarán un puntual seguimiento a las solicitudes recibidas para ser apoyadas por el programa y presentarán las solicitudes recibidas ante la Secretaría de Agricultura, Ganadería, Pesca y Desarrollo Rural, para que a través de su titular emita la autorización correspondiente, la cual se notificará de manera escrita a los beneficiarios del programa, especificándole el concepto y monto de apoyo a recibir, así como los plazos de tiempo para hacer efectivo el apoyo, esta notificación se realizará a más tardar en 5 días hábiles de haber presentado la solicitud de apoyo.\nLa Secretaria de Agricultura, Ganadería, Pesca y Desarrollo Rural, entregará el bien, el subsidio o el apoyo que corresponda y el beneficiario firmará el acta de entrega recepción.\nEl responsable del programa integrará los expedientes de los beneficiarios, incluyendo el acta de entrega recepción y la factura correspondiente, para las revisiones a que haya lugar por parte de la\nSecretaria de Contraloría y Transparencia Gubernamental.\n12.1. Instancia ejecutora\nLa Secretaria de Agricultura, Ganadería, Pesca y Desarrollo Rural, será la dependencia que ejercerá los recursos del programa, también, tendrá la responsabilidad de verificar que la formulación de los expedientes técnicos de los proyectos, reúnan los requisitos exigidos por la instancia normativa, tales como apego a la planeación estratégica, programación, presupuestación, calendario de ejecución, ejercicio y control del gasto público.\nSACACOSECHA Y BORDOS\n12.2 Instancia administrativa y/o normativas\nLa Auditoria y la Contraloria, vigilarán que la ejecución del programa sea con apego a la normatividad para asegurar el cumplimiento de los objetivos y metas trazados.\n12.3. Delimitación de atribuciones\nLa Ley Orgánica de la Administración Pública del Estado de Guerrero, número 08, en el Artículo\n31 establece que La Secretaría de Agricultura, Ganadería, Pesca y Desarrollo Rural, es el órgano encargado de promover y fomentar el desarrollo agrícola, forestal, ganadero, pesquero, así como del manejo de los recursos naturales en el Estado, procurando la participación de las mujeres, en igualdad de condiciones en estas actividades de diseño y planeación y cumplimiento correspondiéndole el despacho de los asuntos siguientes:\nI.- Elaborar los planes, programas y acciones, de corto, mediano y largo plazo, del sector agropecuario, forestal y pesquero, que respondan a un criterio de manejo sustentable de los recursos naturales, con la participación de las dependencias federales y estatales correspondientes, ayuntamientos, organizaciones de productores individuales y campesinos, en el seno de la Secretaria de Planeación y\nDesarrollo Regional del Estado de Guerrero, y coordinar su implementación;\nII.- Formular y ejecutar los planes, programas y acciones para el desarrollo integral de las personas que viven y trabajan en zonas rurales del Estado, principalmente aquellos dirigidos a mejorar las condiciones de las mujeres;\nIII.- Fomentar, formular, supervisar y coordinar la operación de los programas de desarrollo agrícola, ganadero, pesquero con criterios de manejo sustentable de los recursos naturales.\nIV.- Apoyar la organización para la producción, coordinando con las dependencias federales afines y productores, las acciones para el financiamiento, seguros, insumos, asistencia técnica y administrativa, investigación, capacitación y transferencia de tecnología, en beneficio de mujeres, campesinos, ejidatarios, comuneros, pequeños propietarios y organizaciones de productores legalmente constituidos;\n13. Derechos, obligaciones y sanciones de los beneficiarios de programas sociales\n13.1 Derechos principios rectores de desarrollo social, así como a recibir un trato digno y respetuoso en los términos establecidos en la constitución política de los Estados Unidos Mexicanos.\nSACACOSECHA Y BORDOS\n13.2 Obligaciones\n• Dar buen uso, conservación y/o mantenimiento de los bienes recibidos\n• Otorgar las facilidades y proporcionar la información necesaria a las instancias de coordinación, de los apoyos otorgados.\n• Seguir las recomendaciones técnico-productivas emitidas por las instancias de gobierno.\n• Mantener los apoyos por un plazo mínimo de tres años con el fin de que estén disponibles para las supervisiones físicas y documentales de las instancias de control y fiscalización.\n13.3 Sanciones\n• Los beneficiarios del programa que incumplan con las obligaciones, y/o presenten documentos falsos, la instancia normativa, definirá la sanción a la que se hará acreedor.\n14. Interpretación\nLa interpretación de las reglas de operación, para efectos administrativos, estará a cargo de la programa, así como de la Secretaría de Contraloría y Transparencia Gubernamental.",
  "ordenamiento": "REGLA",
  "jurisdiccion": "GUERRERO",
  "fuente_oficial": "DIARIO OFICIAL DE LA FEDERACION",
  "Fecha de Publicación": "23 de octubre de 2015",
  "ULTIMA REFORMA PUBLICADA": null,
  "status": "VIGENTE",
  "es_escaneado": false,
  "tiene_tablas": false,
  "materia": [
    "general"
  ]
}