{
  "titulo": "Acuerdo Mediante el Cual Se Emiten las Reglas de Operación del Programa 2. Becas A Estudiantes Indíg",
  "Contenido": "LA SECRETARÍA DE ASUNTOS INDÍGENAS Y\nCOMUNIDADES AFROMEXICANAS, PARA EL\nEJERCICIO 2016\nÍndice\n1. Introducción....................................................................................................................................... 6\n2. Objetivos............................................................................................................................................ 6\n2.1. General........................................................................................................................................... 6\n2.2. Objetivos Específicos...................................................................................................................... 6\n2.3. Población objetivo........................................................................................................................... 6\n3. Misión………………………………………………………………………………..…………………………..7\n4. Visión…………………………………………………………………………….………………………………7\n5. Reglas de operatividad...................................................................................................................... 7\n5.1. Lineamientos generales.................................................................................................................. 7\n5.1.1. Fundamento legal........................................................................................................................ 8\n5.1.2. Participantes................................................................................................................................ 8\n5.1.3. Patrimonio del programa.............................................................................................................. 9\n5.1.4. Tipos de apoyo............................................................................................................................ 9\n6. Información del Programa.................................................................................................................. 9\n6.1. Exposición del programa................................................................................................................. 9\n6.2. Cobertura........................................................................................................................................ 9\n6.3. Modos de entrega del beneficio...................................................................................................... 10\n6.4. Gastos de operación....................................................................................................................... 10\n7. Transparencia.................................................................................................................................... 11\n7.1. Difusión........................................................................................................................................... 11\nLA SECRETARÍA DE ASUNTOS INDÍGENAS Y\nCOMUNIDADES AFROMEXICANAS, PARA EL\nEJERCICIO 2016\n7.2. Seguimiento de avances físicos y financieros................................................................................ 11\n7.3. Evaluación...................................................................................................................................... 11\n7.4. Auditoría......................................................................................................................................... 12\n7.5. Recursos no devengados................................................................................................................ 12\n7.6. Blindaje electoral............................................................................................................................. 12\n7.7. Contraloría social............................................................................................................................ 12\n7.8. Quejas y denuncias......................................................................................................................... 13\n8. Criterios de selección y elegibilidad................................................................................................... 13\n8.1. Método de selección de beneficiarios............................................................................................. 13\n9. Mecánica de operación...................................................................................................................... 13\n9.1. Instancia ejecutora.......................................................................................................................... 13\n9.2. Instancia administrativa y normativa............................................................................................... 13\n9.3. Delimitación de atribuciones........................................................................................................... 14\n10. Derechos, obligaciones y sanciones de los beneficiarios de programas sociales............................. 14\n10.1. Derechos...................................................................................................................................... 14\n10.2. Obligaciones................................................................................................................................. 14\n10.3. Sanciones..................................................................................................................................... 14\n11. Interpretación................................................................................................................................... 14\n12. Anexos............................................................................................................................................. 15\nLA SECRETARÍA DE ASUNTOS INDÍGENAS Y\nCOMUNIDADES AFROMEXICANAS, PARA EL\nEJERCICIO 2016\nCOMUNIDADES AFROMEXICANAS, PARA EL EJERCICIO FISCAL 2017, PUBLICADO EN EL PERIODICO OFICIAL\nDEL GOBIERNO DEL ESTADO DE GUERRERO No. 34, DE FECHA 28 DE ABRIL DE 2017\nTEXTO ORIGINAL.\nAcuerdo publicados en el Periódico Oficial del Gobierno del Estado No. 61 Alcance I, el Viernes\n29 de Julio de 2016.\nACUERDO MEDIANTE EL CUAL SE EMITEN LAS REGLAS DE OPERACIÓN DEL PROGRAMA 2.\nBECAS A ESTUDIANTES INDÍGENAS Y AFROMEXICANOS DE LA SECRETARÍA DE ASUNTOS\nINDÍGENAS Y COMUNIDADES AFROMEXICANAS, PARA EL EJERCICIO 2016.\nLIC. GILBERTO SOLANO ARREAGA, Secretario de Asuntos Indígenas y Comunidades\nAfromexicanas, con fundamento en los Artículos 11, 14 y 16 de la Ley Orgánica de la Administración Pública del Estado de Guerrero número 8, y el artículo 32 de la Ley en referencia por el que se crea la Secretaría de Asuntos Indígenas y Comunidades Afromexicanas, publicado en el Periódico Oficial del Gobierno del\nEstado de Guerrero, número 85, de fecha 23 de Octubre de 2015, y\nCONSIDERANDO\nQue en el Decreto número 170 del Presupuesto de Egresos del Estado de Guerrero, para el\nEjercicio Fiscal 2016, se señala que se ejercitarán los recursos bajo una política de gasto público que permita dar cumplimiento a los seis ejes rectores del Plan Estatal de Desarrollo 2016 - 2021. Las políticas encaminadas a desarrollo social, se orientaron a los sectores desprotegidos del estado y a programas sociales.\nQue dentro de las políticas de Desarrollo Social la Secretaría de Asuntos Indígenas y\nComunidades Afromexicanas, implementará el Programa 2. Becas a Estudiantes Indígenas y\nAfromexicanos, a fin de contribuir a la mejora de la calidad de vida de cada uno de las y los beneficiarios, mismo que se enmarca en el Eje VI. Estrategias Transversales, específicamente en la Estrategia 4. Atender a los Pueblos Originarios y Afromexicanos, y en el Eje III, Objetivo 3.1. Garantizar el ejercicio efectivo de los derechos sociales para toda la población.\nPor lo anterior expuesto y con fundamento en las disposiciones legales antes citadas, he tenido a bien expedir el siguiente:\nEJERCICIO FISCAL 2016.\nÚnico: se emiten las Reglas de Operación del Programa 2. Becas a Estudiantes Indígenas y\nAfromexicanos, que implementará la Secretaría de Asuntos Indígenas y Comunidades Afromexicanas, para el Ejercicio Fiscal 2016.\nLA SECRETARÍA DE ASUNTOS INDÍGENAS Y\nCOMUNIDADES AFROMEXICANAS, PARA EL\nEJERCICIO 2016\nTRANSITORIOS\nPrimero.- El presente acuerdo entrará en vigor al día siguiente de su publicación en el Periódico\nOficial del Gobierno del Estado de Guerrero.\nSegundo.- Las Reglas de Operación del Programa de la Secretaría de Asuntos Indígenas y\nComunidades Afromexicanas: 2. Becas a Estudiantes Indígenas y Afromexicanos, para el Ejercicio\nFiscal 2016, se publican en su totalidad\nDado en la ciudad de Chilpancingo de los Bravo, Guerrero, a los dieciocho días del mes de marzo de dos mil dieciséis.\nEL SECRETARIO DE ASUNTOS INDÍGENAS Y COMUNIDADES AFROMEXICANAS.\nLIC. GILBERTO SOLANO ARREAGA.\nRúbrica.\nÍndice\n1. Introducción.\n2. Objetivos.\n2.1. General\n2.2. Específicos\n2.3. Población objetivo\n3. Misión.\n4. Visión.\n5. Reglas de operatividad.\n5.1 Lineamientos generales\n5.1.1. Fundamento legal\n5.1.2. Participantes\n5.1.3. Patrimonio del programa\n5.1.4. Tipos de apoyo\n6. Información del Programa.\n6.1. Exposición del Programa\n6.2. Cobertura\n6.3. Modos de entrega del beneficio\n6.4. Gastos de operación\nLA SECRETARÍA DE ASUNTOS INDÍGENAS Y\nCOMUNIDADES AFROMEXICANAS, PARA EL\nEJERCICIO 2016\n7. Transparencia.\n7.1. Difusión\n7.2. Seguimiento de avances físicos y financieros\n7.3. Evaluación\n7.4. Auditoría\n7.5. Recursos no devengados\n7.6. Blindaje electoral\n7.7. Contraloría social\n7.8. Quejas y denuncias\n8. Criterios de selección y elegibilidad.\n8.1. Método de selección de beneficiarios\n9. Mecánica de operación.\n9.1. Instancia ejecutora\n9.2. Instancia administrativa y normativa\n9.3. Delimitación de atribuciones\n10. Derechos, obligaciones y sanciones de los beneficiarios de programas sociales.\n10.1. Derechos\n10.2. Obligaciones\n10.3. Sanciones\n11. Interpretación.\n12. Anexos.\nLA SECRETARÍA DE ASUNTOS INDÍGENAS Y\nCOMUNIDADES AFROMEXICANAS, PARA EL\nEJERCICIO 2016\n1. Introducción\nLas desventajas que enfrentan la población indígena y afromexicana, originadas por la marginación, la exclusión y la pobreza, influyen de manera relevante en los altos índices de deserción escolar en todos los niveles educativos, siendo el nivel superior donde se observa un menor acceso de jóvenes indígenas y afromexicanos, así como un mayor abandono de estudios. No obstante que en el nivel superior cada vez son más los jóvenes indígenas y afromexicanos (as) que ingresan a cursar alguna carrera, las limitaciones económicas son la causa principal que impiden su permanencia y conclusión académica.\nAnte esta situación, el programa Becas a Estudiantes Indígenas y Afromexicanos tiene como propósito apoyar a estudiantes indígenas y afromexicanos (as) que cursan el nivel superior de educación, a través de una ayuda económica que permita mantener sus estudios y garantizar la permanencia y culminación de su carrera. De esta manera, la Secretaría de Asuntos Indígenas y Comunidades\nAfromexicanas (SAICA), alinea este programa al Plan Estatal de Desarrollo 2016-2021, específicamente al eje VI, Estrategia 6.4.1, la cual establece la atención de los pueblos indígenas y afromexicano, a fin de generar oportunidades que permitan su desarrollo económico, político y social, respetando las manifestaciones de su cultura y el ejercicio de sus derechos.\nLa finalidad de estas reglas de operación es la de normar, detallar y difundir el conjunto de disposiciones que garanticen los niveles esperados de eficacia, eficiencia, equidad y transparencia del programa arriba citado.\n2. Objetivos\n2.1. General\nPropiciar que las y los estudiantes indígenas y afromexicanos inscritos en escuelas públicas del estado u otra entidad, concluyan la educación superior y eleven su rendimiento escolar, a través del estímulo económico, para incrementar su eficiencia terminal y nivel educativo.\n2.2. Objetivos Específicos\n✓ Otorgar becas a estudiantes indígenas y afromexicanos de escasos recursos, inscritos en instituciones educativas públicas de nivel superior del estado de Guerrero u otras entidades.\n✓ Impulsar el principio de corresponsabilidad con los becarios (as), para que realicen actividades en favor de sus comunidades o de la población indígena y afromexicana, de acuerdo a sus perfiles académicos.\n2.3. Población objetivo\nLas y los beneficiarios del presente programa son estudiantes indígenas y afromexicanos, de ambos sexos, que cursan el nivel superior en universidades y escuelas públicas del estado de Guerrero o de otra entidad de la República mexicana, con prioridad a los originarios de Guerrero, siempre y cuando cumplan con el presente precepto.\nLA SECRETARÍA DE ASUNTOS INDÍGENAS Y\nCOMUNIDADES AFROMEXICANAS, PARA EL\nEJERCICIO 2016\n3. Misión\nDotar de un estímulo económico a estudiantes indígenas y afromexicanos(as), que contribuya a incrementar su rendimiento académico y coadyuve a disminuir la deserción.\n4. Visión\nSer el programa que contribuya a elevar el nivel académico y disminuir la deserción escolar de las y los estudiantes indígenas y afromexicanos (as) del nivel superior de educación.\n5. Reglas de operatividad\n5.1. Lineamientos generales\nLas y los solicitantes de beca deberán cumplir con las etapas y procedimientos siguientes:\nI. La SAICA emitirá la Convocatoria del programa Becas a Estudiantes Indígenas y Afromexicanos, en la cuarta semana del mes de marzo, a través del Portal Oficial del Gobierno del Estado de Guerrero y de la red social Facebook de la SAICA. En la convocatoria se estipularán las fechas de recepción de documentos, los requisitos y la documentación a entregar:\n- Kardex de calificaciones original con promedio mínimo de 8.0, debidamente sellada y firmada por la autoridad escolar competente.\n- Constancia de estudios original con promedio de calificaciones, que acredite estar inscrito y ser alumno regular, sellada y firmada por la autoridad escolar competente.\n- Copia de identificación oficial (credencial del INE).\n- Copia del acta de nacimiento.\n- Copia de la Clave Única de Registro de Población (CURP).\n- Copia de comprobante de domicilio.\nII. Las y los aspirantes deberán presentar la documentación requerida en las fechas señaladas en la convocatoria -contando con un lapso de diez días hábiles para efectuar el trámite-, y realizarán la entrega de manera personal en las oficinas centrales de la SAICA, ubicadas en la ciudad de Chilpancingo, así como en las Delegaciones Regionales situadas en Chilapa de Álvarez, Tlapa de Comonfort y Ometepec.\nIII. El personal de la SAICA realizará la revisión y recepción de documentos y, cuando sea necesario, indicará al aspirante las inconsistencias en los requisitos o los documentos faltantes, en cuyos casos deberán subsanarse dentro de las fechas de recepción, o bien informará que el solicitante cumple\n(sin) con todo lo establecido.\nIV. Una vez que el aspirante cumpla con los requisitos y con la entrega completa de documentos, recibirá inmediatamente los formatos de \"Solicitud de Beca\" y \"Estudio Socioeconómico\", los cuales serán llenados y entregados por el aspirante, quien recibirá el comprobante foliado que ampara su inscripción.\nV. Las y los aspirantes conocerán los resultados del concurso, en un término de diez días hábiles, a partir de la fecha en que finalice la recepción de documentos, a través de la publicación de la lista de becarios (as) por las vías electrónicas oficiales ya citadas, así como en las Oficinas Centrales y\nDelegaciones Regionales de la SAICA.\nVI. Las y los becarios recibirán la primera parte de la beca, mediante cheque bancario con un monto de $4,000.00 (cuatro mil pesos 00/100 M.N.), en la cuarta semana del mes de abril, para lo cual deberán presentarse con el original de su identificación oficial en el lugar donde efectuaron los trámites, en la fecha y horario que con antelación se comunicará.\nLA SECRETARÍA DE ASUNTOS INDÍGENAS Y\nCOMUNIDADES AFROMEXICANAS, PARA EL\nEJERCICIO 2016\nVII. Para tener derecho a la parte complementaria de la beca, las y los becarios deberán presentar en la tercera semana de agosto, los siguientes documentos en original, debidamente sellados y firmados por la autoridad escolar competente:\n- Kardex de calificaciones con promedio mínimo de 8.0, correspondiente al ciclo escolar febrerojulio 2016 o su equivalente.\n- Constancia de estudios con promedio de calificaciones, que acredite estar inscrito y ser alumno regular.\nVIII. Una vez cubiertos los requisitos satisfactoriamente, los becarios deberán acudir en la segunda semana de septiembre a la sede de la SAICA donde realizaron sus trámites, con el objeto de recibir el segundo pago de la beca, a través de cheque bancario con un monto de $4,000.00 (cuatro mil pesos 00/100\nM.N.).\nIX. No tendrán derecho a cobrar la segunda parte de la beca, aquellos becarios (as) que para el mes de agosto hayan concluido el plan de estudios de sus respectivas carreras; en estos casos la SAICA entregará esta parte proporcional de las becas a igual número de aspirantes que tengan los mejores promedios y que no hayan logrado acceder a una beca en la primera etapa del Programa.\nX. Los seleccionados para recibir esta parte proporcional de la beca, serán informados por la\nSAICA y deberán entregar en las Oficinas Centrales o en las Delegaciones Regionales, la actualización del kardex de calificaciones y de la constancia de estudios, para corroborar que continúan siendo alumnos regulares y mantienen un promedio de calificaciones mínimo de 8.0. El pago de la beca, con un monto de\n$4,000.00 (cuatro mil pesos 00/100 M.N.), tendrá las mismas características y se realizará en fechas similares a los del resto de becarios (as).\n5.1.1. Fundamento legal\n√ Constitución Política de los Estados Unidos Mexicanos (artículo 2). artículo 12).\n√ Ley Orgánica de la Administración Pública del Estado de Guerrero Número 08 (artículo 32).\n√ Ley número 701 de Reconocimiento, Derechos y Cultura Indígena de los Pueblos y\nComunidades Indígenas de Guerrero.\n√ Decreto Número 170 del Presupuesto de Egresos del Estado de Guerrero para el Ejercicio Fiscal\n2016.\n√ Convenio 169 sobre Pueblos Indígenas y Tribales, de la Organización Internacional del Trabajo.\n5.1.2. Participantes\nLa Secretaría de Asuntos Indígenas y Comunidades Afromexicanas, autoridades comunales y ejidales, los H. Ayuntamientos de los 48 municipios prioritarios, instituciones educativas y estudiantes indígenas y afromexicanos (as) que cursan el nivel superior en universidades y escuelas públicas del estado de Guerrero, o de otras entidades del país.\nLA SECRETARÍA DE ASUNTOS INDÍGENAS Y\nCOMUNIDADES AFROMEXICANAS, PARA EL\nEJERCICIO 2016\n5.1.3. Patrimonio del programa\nEl programa Becas a Estudiantes Indígenas y Afromexicanos, tiene asignado para el ejercicio fiscal 2016 un presupuesto de $4'000,000.00 (cuatro millones de pesos 00/100 M.N.), teniendo como fuente de financiamiento Inversión Estatal Directa.\n5.1.4. Tipos de apoyo\nApoyo económico mensual de $800.00 (ochocientos pesos 00/ 100 M.N.) por beneficiario, durante los 10 meses del ciclo escolar. Los apoyos se otorgarán en base a la disponibilidad presupuestal del\nPrograma, en los plazos y techos señalados en este prepcepto (sic).\n6. Información del Programa\nLa difusión del programa denominado Becas a Estudiantes Indígenas y Afromexicanos, se realizará mediante tríptico, y en las páginas electrónicas www.guerrero.gob.mx y www.asuntosindigenas. guerrero.gob.mx\n6.1. Exposición del programa\nEl programa ofrece una beca de $800.00 (ochocientos pesos 00/100 M. N.) mensuales, cubriendo los 10 meses del ciclo escolar vigente, a estudiantes indígenas y afromexicanos (as) que cursan el nivel superior en universidades o escuelas públicas de la entidad o de otro estado del país.\nLa beca se entregará en dos únicos pagos, en los meses de abril y septiembre de 2016, excepto a los beneficiarios que para el segundo pago hayan concluido el plan de estudios de sus respectivas carreras. Por lo tanto, la beca no cubre otras etapas académicas o trámites administrativos, como son servicio social, elaboración de tesis y trámites de titulación, entre otros\n6.2. Cobertura\nSe atenderá a los y las estudiantes indígenas y afromexicanos (as) de las siete regiones y 81 municipios de la entidad, que cursan el nivel superior en escuelas y universidades públicas, otorgando prioridad a los (as) originarios de los 48 municipios con preponderancia o presencia indígena y afromexicana, señalando que aquellos que reciben beca por parte de otras dependencias serán excluidos.\nMUNICIPIOS PRIORITARIOS\nMONTAÑA COSTA CHICA CENTRO\n1. Acatepec 1. Ayutla de los Libres 1. Ahuacuotzingo\n2. Alcozauca de Guerrero 2. Igualapa 2. Eduardo Neri\n3. Alpoyeca 3. San Luis Acatlán 3. Chilapa de Álvarez\n4. Atlamajalcingo del 4. Tlacoachistlahuaca 4. Chilpancingo de los\nMonte Bravo\n5. Atlixtac 5. Xochistlahuaca 5. José Joaquín de\nHerrera\nLA SECRETARÍA DE ASUNTOS INDÍGENAS Y\nCOMUNIDADES AFROMEXICANAS, PARA EL\nEJERCICIO 2016\n6. Cochoapa el Grande Municipios 6. Mártir de Cuilapan\nAfromexicanos\n7. Copanatoyac 6. Azoyú 7. Tixtla de Guerrero\n8. Cualác 7. Copala 8. Zitlala\n9. Huamuxtitlan 8. Cuajinicuilapa NORTE\n10. Iliatenco 9. Cuautepec 1. Copalillo\n11. Malinaltepec 10. Florencio Villarreal 2. Huitzuco de los\nFigueroa\n12. Metlatónoc 11. Juchitán 3. Iguala de la\nIndependencia\n13. Olinalá 12. Marquelia 4. Taxco de Alarcón\n14. Tlacoapa 13. Ometepec 5. Tepecoacuilco de\nTrujano\n15. Tlapa de Comonfort 14. San Marcos ACAPULCO\n16. Tlalixtaquilla 15. Tecoanapa 1. Acapulco de Juárez\n17. Xalpatláhuac\n18. Xochihuehietlan\n19. Zapotitlán Tablas\n6.3. Modos de entrega del beneficio\nUna vez que los becarios (as) hayan cubierto los requisitos establecidos por el programa, y sean seleccionados para recibir la beca, la SAICA publicará la lista de los 485 Beneficiarios en el Portal Oficial del Gobierno del Estado (www.guerrero.gob.mx y www.asuntosindigenas.guerrero.gob.mx), y estará disponible también a la vista en las oficinas centrales de la SAICA y en sus delegaciones regionales de\nTlapa, Chilapa y Ometepec.\nLa SAICA informará a los beneficiarios (as) las fechas y horarios en los que habrá de realizar el primer pago de la beca, consistente en $4,000.00 (cuatro mil pesos 00/100 M.N.), a través de un cheque bancario (no en efectivo), para lo cual los becarios (as) deberán presentarse en las oficinas centrales o en las delegaciones regionales, donde recibirá el pago correspondiente.\nPara el pago de la segunda parte de la beca, con un monto de $4,000.00 (cuatro mil pesos 00/100\nM.N.), se seguirá similar mecanismo que el anterior, sólo que los becarios (as) deberán presentar en el kardex de calificaciones, con un promedio mínimo de 8.0, obtenido en el último semestre cursado.\nLos becarios (as) que hayan obtenido en el último semestre cursado un promedio por debajo de\n8.0, perderán automáticamente el beneficio de cobrar la segunda parte de la beca.\nLA SECRETARÍA DE ASUNTOS INDÍGENAS Y\nCOMUNIDADES AFROMEXICANAS, PARA EL\nEJERCICIO 2016\n6.4. Gastos de operación.\nDe acuerdo al artículo 47 de la Ley de Coordinación Fiscal, podrá aplicarse hasta un 3% del presupuesto total del programa, el cual se destinará a gastos de operación y realización de diversas acciones, asociados con la planeación, operación, supervisión, seguimiento, contraloría social y evaluación o asesoría externa del programa.\n✓ Materiales, útiles y equipos menores de oficina: hasta un monto de $2,000.00/ paquete.\n✓ Materiales y útiles de impresión y reproducción: hasta un monto de $3,000.00/paquete.\n✓ Viáticos: de acuerdo a la tarifa establecida por la Secretaría de Finanzas y Administración.\n✓ Combustibles, lubricantes y aditivos: hasta un monto de $14.00/litro.\n✓ Servicios de apoyo administrativo, fotocopiado e impresión: hasta por un monto de\n$10,000.00/paquete\n✓ Materiales y útiles de impresión y reproducción (fotocopias): hasta un monto de un peso/pieza\n✓ Materiales y útiles de impresión y reproducción (Lonas): hasta por un monto de $1, 500.00/pieza\n✓ Peaje: hasta por un monto de $520.00/por viaje.\n7. Transparencia\n7.1. Difusión\nConforme a las disposiciones establecidas en el apartado de programas sujetos a Reglas de\nOperación del Decreto Número 170 del Presupuesto de Egresos del Estado de Guerrero para el Ejercicio\nFiscal 2016; estas Reglas de Operación, además de ser publicadas en el Periódico Oficial del Gobierno del\nEstado, estarán disponible para la población en general en las oficinas centrales y delegaciones regionales de la Secretaría de Asuntos Indígenas y Comunidades Afromexicanas, así como en la página electrónica del Gobierno del Estado: www.guerrero.gob.mx y www.asuntosindigenas. guerrero.gob.mx\n7.2. Seguimiento de avances físicos y financieros\nLa ejecución del programa Becas a Estudiantes Indígenas y Afromexicanos, que implementa la\nSecretaría de Asuntos Indígenas y Comunidades Afromexicanas, estará a cargo de la Dirección General de Planeación y Desarrollo, y el financiamiento será ministrado y comprobado por la Delegación\nAdministrativa, que a su vez reportará trimestralmente a la Secretaría de Planeación y Desarrollo Regional\n(SEPLADER) y a la Secretaría de Contralaría y Transparencia Gubernamental los informes sobre el presupuesto ejercido y en base a los indicadores de resultados previstos en este precepto, dichos informes se deberán presentar a más tardar a los quince días hábiles posteriores a la terminación de cada trimestre. comprobación respectiva.\n7.3. Evaluación\nLa Secretaría de Asuntos Indígenas y Comunidades Afromexicanas tendrá la obligación de revisar, de manera interna, la correcta operación y aplicación de las presentes reglas de operación y, en caso necesario, podrá solicitar una evaluación externa por parte de una instancia con experiencia en el tema.\nLA SECRETARÍA DE ASUNTOS INDÍGENAS Y\nCOMUNIDADES AFROMEXICANAS, PARA EL\nEJERCICIO 2016 acciones de supervisión y evaluación para garantizar el adecuado desarrollo del Programa, a efecto de corregir desfases o efectuar reasignaciones financieras con la autorización de la Secretaría de Planeación y Desarrollo Regional y de la Secretaría de Finanzas y Administración (SEFINA), a fin de cubrir rubros prioritarios, con recursos de este mismo programa o de otros que no hayan sido ejercidos en su momento, o bien que provengan de ahorros presupuestales.\n7.4. Auditoría\nEste programa podrá ser auditado, a través de las instancias correspondientes en el ámbito de sus respectivas competencias del Gobierno del Estado encargadas de vigilar la correcta aplicación de los recursos del erario público.\n7.5. Recursos no devengados\nEl presupuesto no ejercido para los fines autorizados al 31 de diciembre de 2016, será reintegrado a la Dirección General de Tesorería, de la Secretaría de Finanzas y Administración del Gobierno del Estado.\n7.6. Blindaje electoral\nComo estrategia de blindaje electoral, la papelería, documentación oficial, así como la publicidad y promoción del programa deberán incluir la siguiente leyenda:\n\" Este Programa es de carácter público, no es patrocinado ni promovido por partido político alguno y sus recursos provienen de los impuestos que pagan todos los contribuyentes. Está prohibido el uso de este programa con fines políticos, electorales, de lucro y otros distintos a los establecidos. Quien haga uso indebido de los recursos de este programa deberá ser denunciado y sancionado de acuerdo con la ley aplicable y ante la autoridad competente\".\nEn cuanto a la publicidad en medios electrónicos, impresos, complementarios o de cualquier otra índole, vinculados con los Programas de comunicación social, deberá incluirse la siguiente leyenda: \"Este\nPrograma es público y queda prohibido su uso con fines partidistas o de promoción personal\".\n7.7. Contraloría social\nLa SAICA, como instancia ejecutora, promoverá la contraloría social, con base en la normatividad establecida para tal efecto, fomentando acciones que transparenten la operación del programa, tales como:\na) Informar a la ciudadanía acerca de los apoyos otorgados y su costo.\nb) Capacitar a los beneficiarios para que se constituyan en instancias de vigilancia y evaluación social.\nc) Establecer espacios de comunicación (reuniones vecinales y estudiantiles, asambleas comunitarias, entre otros).\nd) Promover la integración de organizaciones de la sociedad civil para realizar acciones de contraloría social.\ne) Instrumentar mecanismos de recepción y atención de quejas y denuncias. El Órgano Estatal de\nControl verificará en lo correspondiente la realización de dichas acciones.\nLA SECRETARÍA DE ASUNTOS INDÍGENAS Y\nCOMUNIDADES AFROMEXICANAS, PARA EL\nEJERCICIO 2016\n7.8. Quejas y denuncias\nLas quejas, denuncias, peticiones y sugerencias relativas a este programa, se realizarán de manera escrita, por comparecencia del interesado, por correo electrónico o vía telefónica, y para aquellas que sean escritas se depositarán en los buzones instalados en las oficinas centrales de la SAICA, ubicadas en la ciudad de Chilpancingo, así como en las delegaciones regionales, situadas en las ciudades de Tlapa de Comonfort, Chilapa de Álvarez y Ometepec. El denunciante o quejoso deberá proporcionar los siguientes datos:\n-Nombre y domicilio\n-Identificación oficial\n-Nombre del servidor público denunciado\n-Objeto de la denuncia\n8. Criterios de selección y elegibilidad\nLas y los estudiantes que aspiren a recibir una beca deberán cumplir los requisitos de selección y elegibilidad, previamente establecidos en las presentes reglas de operación.\n8.1. Método de selección de beneficiarios\nLos (as) aspirantes a beca deberán cumplir con los criterios de elegibilidad que se describen a continuación:\n✓ Ser originarios (as) de comunidades y municipios indígenas y afromexicanos, o auto adscribirse como tales, independientemente de su sexo, edad, filiación política, religiosa o de otro tipo de organización social o estudiantil.\n✓ Ser estudiantes indígenas y afromexicanos (as), que estén inscritos en universidades o escuelas públicas de nivel superior del estado de Guerrero o de otra entidad del país.\n✓ Ser alumno (a) regular, con un promedio de calificación mínimo de 8.0.\n✓ No ser beneficiario (a) de otro programa de becas, sea de origen municipal, estatal o federal.\n9. Mecánica de operación\n9.1. Instancia ejecutora programa Becas a Estudiantes Indígenas y Afromexicanos, a través de la Dirección de Planeación y\nDesarrollo, de acuerdo a los lineamientos establecidos en estas reglas de operación para el ejercicio fiscal\n2016.\n9.2. Instancia administrativa y normativa reglas de operación.\nLA SECRETARÍA DE ASUNTOS INDÍGENAS Y\nCOMUNIDADES AFROMEXICANAS, PARA EL\nEJERCICIO 2016\n9.3. Delimitación de atribuciones presente programa, conforme al marco jurídico y normativo de la Administración Pública Estatal y a las reglas de operación. Y una vez que la SEFINA libere los recursos destinados para este programa, dando, así, cumplimiento a los lineamientos La Secretaría de Planeación y Desarrollo Regional y la Secretaria de\nContraloría y Transparencia Gubernamental.\n10. Derechos, obligaciones y sanciones de los beneficiarios de programas sociales\n10.1. Derechos\n✓ Las y los becarios indígenas y afromexicanos (as) tendrán derecho a los beneficios que otorga este programa, siempre y cuando cumplan con los requisitos que para tal efecto se han establecido.\n✓ Podrán solicitar información a la SAICA sobre el estado que guarda el proceso de aprobación de su beca.\n✓ Recibirán la beca que haya sido aprobada, sin que esto implique pago alguno a gestores u organizaciones de cualquier filiación.\n✓ Tendrán la garantía de privacidad de sus datos personales.\n10.2. Obligaciones\n✓ Deberán informar a la Secretaría de Asuntos indígenas y Comunidades Afromexicanas, a través de las delegaciones regionales u oficinas centrales, los casos que impidan la correcta aplicación o el mal uso de los recursos asignados al programa.\n✓ Mantendrán o incrementarán su promedio escolar, y observaran buena conducta.\n10.3. Sanciones\nSe cancelará la beca a las y los estudiantes que incurran en las siguientes conductas:\n• Abandonar el ciclo escolar.\n• Disminuir el promedio mínimo de 8.0.\n• Falsificar o alterar documentos oficiales e información.\n11. Interpretación\nEl programa estará a cargo de la Secretaría de Asuntos Indígenas y Comunidades Afromexicanas,\nLA SECRETARÍA DE ASUNTOS INDÍGENAS Y\nCOMUNIDADES AFROMEXICANAS, PARA EL\nEJERCICIO 2016\nLA SECRETARÍA DE ASUNTOS INDÍGENAS Y\nCOMUNIDADES AFROMEXICANAS, PARA EL\nEJERCICIO 2016\nLA SECRETARÍA DE ASUNTOS INDÍGENAS Y\nCOMUNIDADES AFROMEXICANAS, PARA EL\nEJERCICIO 2016\nLIC. FELIPE SÁNCHEZ RAMÍREZ, DIRECTOR GENERAL DE LA DEFENSA Y ASESORÍA\nGOBIERNO DEL ESTADO DE GUERRERO; DE CONFORMIDAD CON LO ESTABLECIDO EN EL\nNUMERAL 32, FRACCIÓN XVIII, DE LA LEY ORGÁNICA DE LA ADMINISTRACIÓN PÚBLICA DEL\nESTADO DE GUERRERO NÚMERO 08, ASÍ COMO EL NUMERAL 16 FRACCIONES V, XXI Y XXII DEL\nREGLAMENTO INTERNO VIGENTE DE ESTA DEPENDENCIA.\nHAGO CONSTAR Y CERTIFICO\nQUE LAS PRESENTES COPIAS FOTOSTÁTICAS,COMPUESTAS (SIC) DE 19 FOJAS ÚTILES SON\nSECRETARÍA, MISMAS QUE SE EXPIDEN PARA LOS USOS LEGALES A QUE HAYA LUGAR, EN LA\nATENTAMENTE.\nLIC. FELIPE SÁNCHEZ RAMÍREZ.\nDIRECTOR GENERAL DE LA DEFENSA Y ASESORÍA JURÍDICA.\nRúbrica.",
  "ordenamiento": "REGLA",
  "jurisdiccion": "GUERRERO",
  "fuente_oficial": "DIARIO OFICIAL DE LA FEDERACION",
  "Fecha de Publicación": "28 DE ABRIL DE 2017",
  "ULTIMA REFORMA PUBLICADA": "28 DE ABRIL DE 2017",
  "status": "VIGENTE",
  "es_escaneado": false,
  "tiene_tablas": true,
  "materia": [
    "educación"
  ]
}