{
  "titulo": "Acuerdo por el Que Se Emiten las Reglas de Operación del Programa de Empleo Temporal para el Ejercic 1",
  "Contenido": "1. Introducción.............................................................................................................................. 5\n2. Objetivo..................................................................................................................................... 6\n2.1. Objetivo general..................................................................................................................... 6\n2.2. Objetivos Específicos............................................................................................................. 6\n2.3. Población Objetivo................................................................................................................. 6\n3. Misión....................................................................................................................................... 6\n4. Visión........................................................................................................................................ 7\n5. Reglas de Operatividad............................................................................................................. 7\n5.1. Lineamientos Generales........................................................................................................ 7\n5.1.1. Fundamento Legal.............................................................................................................. 8\n5.1.2. Participantes....................................................................................................................... 8\n5.1.3. Patrimonio del programa......................................................................................... 8\n5.1.4. Tipos de apoyo................................................................................................................... 9\n5.1.4.1 Apoyo económico al beneficiario....................................................................................... 9\n5.1.4.2 Apoyo económico para Adquisición o Arrendamiento de Herramientas/\nMateriales o Equipo...................................................................................................................... 9\n6. Información del programa......................................................................................................... 10\n6.1. Exposición del programa........................................................................................................ 10\n6.2. Cobertura............................................................................................................................... 10\n6.3. Modos de entrega del beneficio............................................................................................. 10\n6.4 Gastos de Operación.............................................................................................................. 10\n7. Transparencia........................................................................................................................... 10\n7.1 Difusión................................................................................................................................... 10\n7.2 Seguimiento de avances físicos y financieros......................................................................... 11\n7.3 Evaluación.............................................................................................................................. 11\n7.4 Auditoria.................................................................................................................................. 12\n7.5 Recursos no devengados....................................................................................................... 12\n7.6 Blindaje electoral..................................................................................................................... 12\n7.7 Contraloría social.................................................................................................................... 13\n7.8 Quejas y denuncias................................................................................................................. 14\n8. Criterios de selección y elegibilidad.......................................................................................... 14\n9. Mecánica de operación............................................................................................................. 15\n9.1 Instancia Ejecutora................................................................................................................. 15\n9.2 Instancia Administrativa c normativa....................................................................................... 15\n9.3 Delimitación de atribuciones................................................................................................... 15\n10. Derechos, obligaciones y sanciones de los beneficiarios de programas sociales.................... 16\n10.1 Derechos.............................................................................................................................. 16\n10.2 Obligaciones......................................................................................................................... 16\n10.3 Sanciones............................................................................................................................. 16\n11. Anexos.................................................................................................................................... 17\n11.1 Anexo 1. Glosario de Términos............................................................................................. 17\n11.2 Anexo 2. Lista de Raya......................................................................................................... 17\n11.3 Anexo 3. Acta Constitutiva.................................................................................................... 19\nEJERCICIO FISCAL 2014, PUBLICADO EN EL PERIÓDICO OFICIAL No. 57, EL 18 DE JULIO DE\n2014).\nTEXTO ORIGINAL.\nAcuerdo publicado en el Periódico Oficial del Gobierno del Estado de Guerrero No 42 Alcance I, el Viernes 24 de Mayo de 2013.\nACUERDO POR EL QUE SE EMITEN LAS REGLAS DE OPERACIÓN DEL PROGRAMA DE EMPLEO\nTEMPORAL PARA EL EJERCICIO FISCAL 2013.\nBeatriz Mojica Morga, Secretaría de Desarrollo Social, con fundamento en los artículos 117 de la\nOrgánica de la Administración Pública del Estado de Guerrero Número 433; lo., 2o., 3o., y 6o de la Ley\nNúmero 102 para el Desarrollo Social del Estado de Guerrero; lo., 2o fracción I, 18, 25, de la Ley Número\n454 de Presupuesto y Disciplina Fiscal del Estado de Guerrero; así como las estrategias y objetivos establecidos eh el Plan Estatal de Desarrollo de Guerrero 2011-2015; y\nCONSIDERANDO\nQue en el Dictamen y Decreto número 148 del Presupuesto de Egresos del Estado de Guerrero para el Ejercicio Fiscal 2013 y el Acuerdo emitido por el Titular del Ejecutivo del Estado, el primero de abril del año 2011, se establecen los Lineamientos Generales de legalidad, honestidad, eficiencia, eficacia, economía, racionalidad, austeridad, transparencia, control, rendición de cuentas, equidad de género e impacto social en grupos vulnerables y en la sociedad en general del gasto de la Administración\nPública Estatal, para fortalecer el desarrollo, estableciendo como una estrategia el Programa de Empleo\nTemporal;\nQue bajo dicho contexto la Secretaría de Desarrollo Social del Estado de Guerrero, a través de la Subsecretaría de Política Social, será responsable de emitir las Reglas de Operación respecto al programa, para que inicie su operación en el ejercicio fiscal siguiente o en su caso, las modificaciones a aquéllas que continúen vigentes.\nEstatales, con el objeto de otorgar transparencia y asegurar la aplicación eficiente, eficaz, oportuna y equitativa de los recursos públicos asignados al mismo.\nEn cumplimiento de lo anterior se ha tenido a bien expedir el siguiente:\nÚNICO.- Se emiten las Reglas de Operación del Programa de Empleo Temporal paira el\nEjercicio Fiscal 2013.\nTRANSITORIOS\nPRIMERO. - El presente Acuerdo entrará en vigor el día siguiente de su publicación en el\nPeriódico Oficial del Gobierno del Estado de Guerrero.\nSEGUNDO.- Quedan abrogadas las Reglas de Operación del Programa de Empleo Temporal, publicadas en el Periódico Oficial del Estado de Guerrero, número 16 de fecha 24 de febrero de 2012.\nDado en la Ciudad de Chilpancingo de los Bravo, Guerrero, a los 16 días del mes de enero de\n2013.\nSECRETARIA DE DESARROLLO SOCIAL.\nMTRA. BEATRIZ MOJICA MORGA.\nRúbrica.\nSUBSECRETARIO DE POLÍTICA SOCIAL.\nMTRO. SALOMÓN BELTRÁN BARRERA.\nRúbrica\nDIRECTOR DE LA UNIDAD DE ASUNTOS JURÍDICOS.\nLIC. FIDELMAR FLORES MÉNDEZ.\nRúbrica.\nContenido\n1. Introducción\n2. Objetivo\n2.1 Objetivo general\n2.2 Objetivos Específicos\n2.3 Población Objetivo\n3. Misión\n4. Visión\n5. Reglas de Operatividad 5.1 Lineamientos Generales\n5.1.1. Fundamento Legal\n5.1.2. Participantes\n5.1.3. Patrimonio del programa\n5.1.4. Tipos de apoyo\n5.1.4.1. Apoyo económico al beneficiario\n5.1.4.2. Apoyo económico para adquisición o arrendamiento de herramientas, materiales o equipo\n6. Información del programa\n6.1 Exposición del Programa\n6.2 Cobertura\n6.3 Modos de entrega del beneficio\n6.4 Gastos de Operación\n7. Transparencia\n7.1 Difusión\n7.2 Seguimiento de avances físicos y financieros\n7.3 Evaluación\n7.4 Auditoria\n7.5 Recursos no devengados\n7.6 Blindaje electoral\n7.7 Contraloría social\n7.8 Quejas y denuncias\n8. Criterios de selección y elegibilidad\n9. Mecánica de operación\n9.1 Instancia Ejecutora\n9.2 Instancia Administrativa- o normativa\n9.3 Delimitación de atribuciones\n10. Derechos, obligaciones y sanciones de los beneficiarios de programas sociales\n10.1 Derechos\n10.2 Obligaciones\n10.3 Sanciones\n11. Anexos\n11.1 Anexo 1. Glosario de Términos\n11.2 Anexo 2. Lista de Raya\n11.3 Anexo 3. Acta Constitutiva\n1. Introducción\nLa población nacional económicamente activa (PEA) suma alrededor de 45.7 millones de personas; de ellas, cerca de 2.2 millones están en búsqueda de empleo. Obtener y conservar un empleo constituye uno de los mayores retos que enfrentan las familias, principalmente aquellas en condiciones de vulnerabilidad social. La ausencia de una fuente de ingresos impide a sus integrantes fortalecer sus vínculos familiares y cristalizar un proyecto de vida.\nAdicionalmente, a lo largo del año la oferta laboral disminuye en algunas regiones del país a causa de alguna emergencia o por efectos de los ciclos productivos, afectando particularmente a la población de escasos recursos que ve disminuidos sus ingresos y patrimonio de manera significativa.\nAmbas situaciones, justifican operar instrumentos de política social y económica que se orienten con alta presencia de población indígena. En este contexto, el Programa de Empleo Temporal, enmarca sus acciones en el documento rector del Plan Estatal de Desarrollo 2011-2015, en el Eje: 2 Desarrollo\nSocial con Equidad, Objetivo: Desarrollo Humano, Pobreza y Marginación; Estrategias: 2.2.2.1 Ampliar la en pobreza y en el 2.2.2.5. Facilitar el acceso a servicios financieros, incluyendo de manera especial los programas de apoyo para actividades generadoras de ingreso.\nDe igual forma, se establece en el Eje: 3 Desarrollo Económico Sustentable, Objetivo: Impulsar el desarrollo de microempresas y el autoempleo, Estrategia: 3.2.17.2. Facilitar el acceso al crédito y otros servicios financieros, a través de los programas existentes, y ampliar estos mecanismos hacia la atención a grupos de menores ingresos.\nDentro de estos objetivos y estrategias que plantea el Ejecutivo Estatal, está abatir la marginación y el rezago social que enfrentan los grupos sociales vulnerables para proveerles de igualdad en las oportunidades que les permitan desarrollarse con independencia y plenitud, asimismo, plantea elevar la productividad de las personas para que cuenten con mejores opciones de empleo e ingreso que les permita reducir sus niveles de pobreza.\nEn razón de lo anterior, el Programa de Empleo Temporal (PET), estará orientado a apoyar transitoriamente el ingreso de estas familias, en el marco de la ejecución de proyectos y acciones de beneficio familiar o comunitario. Respecto al origen de los recursos que integra y aplica el programa que proviene de Inversión Estatal Directa (IED).\n2. Objetivo\n2.1 Objetivo general\n• Disminuir la problemática de la población que demanda trabajo, mediante la entrega de apoyos temporales a su ingreso por su participación en proyectos y/o acciones de beneficio familiar o comunitario de fácil realización.\n2.2 Objetivos Específicos\n• Proporcionar a hombres y mujeres de 16 años de edad o más, apoyos temporales en su ingreso para afrontar los efectos de escasez de demanda laboral.\nEjecutar proyectos y/o acciones que contribuyan al mejoramiento de las condiciones familiares o comunitarias y que con su ejecución se obtengan fuentes de ingreso temporal.\n2.3. Población Objetivo\nMujeres y hombres de 16 años o más de edad, que enfrentan una disminución temporal en su ingreso por escasez de demanda de mano de obra.\n3. Misión oportunidades de empleo temporal, mediante acciones y proyectos de carácter familiar o comunitario de fácil realización que apoyen su ingreso y economía familiar.\n4. Visión\nQue las personas beneficiadas con el programa vean satisfechas sus necesidades mínimas básicas de bienestar social para que puedan seguir desarrollándose de manera individual, familiar o comunitaria en un marco de derechos y libertades sociales.\n5. Reglas de Operatividad\n5.1 Lineamientos Generales\nLa solicitud podrá ser presentada de manera individual o en grupo por parte de los solicitantes para proyectos y/o acciones de beneficio familiar o comunitario, dirigida al Titulas de la Sedesol, presentando la original y copia para acuse de recibo en las oficinas de la SEDESOL Guerrero, así como copia de la credencial de elector de la persona que entregue la solicitud, proporcionando un número telefónico para hacerle llegar la notificación sobre el apoyo solicitado.\nLa SEDESOL del Estado dará respuesta a la solicitud dentro de los.30 días hábiles siguientes al ingreso de la misma; en caso de no obtener respuesta en el plazo establecido, se entenderá que dicha solicitud no fue aceptada.\nCuando la solicitud no incluya toda la información requerida o faltara algún documento, la\nDependencia informará al solicitante en un plazo no mayor a 15 días hábiles. El solicitante tendrá un plazo hasta de 5 días hábiles, a partir de la fecha de haber recibido la notificación para solventar la omisión.\nPara los casos en que llegase a faltar algún tipo de información, se le indicará verbalmente en el momento de la solicitud. Quedando pendiente su ingreso al programa hasta que el solicitante complemente la información.\nLas personas podrán solicitar información sobre el apoyo que otorga el PET: En las oficinas de la\nSEDESOL, ubicadas en Edificio Norte Planta Baja, Palacio de Gobierno, Sita en Boulevard René Juárez\nCisneros No. 62, Chilpancingo, Gro. C. P. 039074.\nCon los datos que aporten los solicitantes, se integrará el Listado de Beneficiarios del PET en cumplimiento a las disposiciones legales vigentes.\nEn el Anexo 1, se presenta un glosario con los conceptos y siglas utilizadas frecuentemente en las presentes Reglas.\n5.1.1. Fundamento Legal\nEl Estado de Guerrero es parte integrante de la Federación Mexicana y tiene como marco legal la los Derechos Humanos y sus Garantías, establece que.. \"...Todas las autoridades, en el ámbito de sus competencias, tienen la obligación de promover, respetar, proteger y garantizar los derechos humanos de conformidad con los principios de' universalidad, interdependencia, indivisibilidad y progresividad\". De\nDécimo Cuarto de la Administración Pública, Capítulo Único, Artículo 117, párrafo tercero, que al alcance dice...\"El Plan Estatal de Desarrollo, con sujeción a las Leyes, definirá las áreas prioritarias en las cuales podrá establecerse y operar Entidades de la Administración Pública Paraestatal, así como los programas que les serán confiados, con sujeción a las prioridades sociales y productivas y a las disponibilidades presupuéstales\". Y que para el despacho de los asuntos que le competen, el Gobernador del Estado se auxiliará con las dependencias y entidades que señalen la Constitución Política local, la Ley Orgánica de la Administración Pública y las demás disposiciones jurídicas vigentes en la entidad.\nEn este sentido la normatividad aplicable es la siguiente:\n1) Constitución Política de los Estados Unidos Mexicanos;\n3) Ley Orgánica de la Administración Pública del Estado de Guerrero Número 433;\n4) Ley Número 102 para el Desarrollo Social del Estado de Guerrero;\n5) Ley Número 374 de Transparencia y Acceso a la Información Pública del Estado de Guerrero;\n6) Ley Número 674 de Responsabilidades de los Servidores Públicos del Estado de Guerrero;\n7) Código de Conducta de la Secretaría de Desarrollo Social;\n8) Reglamento de la Ley para el Desarrollo Social del Estado de Guerrero Número 102;\n9) Plan Estatal de Desarrollo del Estado de Guerrero 2011-2015;\n10) Decreto Número 148 de Presupuesto de Egresos del Estado de Guerrero para el Ejercicio\nFiscal 2013.\n11) Y todos aquellos ordenamientos normativos que sean aplicables.\n5.1.2. Participantes\nSe podrá concertar la participación de las Secretarías del Sector Central; los H. Ayuntamientos y\nOrganizaciones de la Sociedad Civil, que intervienen como receptores y gestores de los proyectos y/o\nSocial, para su revisión y validación correspondiente.\n5.1.3. Patrimonio del programa\nRespecto al origen de los recursos que integra y aplica el programa, estos provienen de la\nInversión Estatal Directa (IED), y están contenidos en el Decreto Número 148 del Presupuesto de para su correcta aplicación.\n5.1.4. Tipos de apoyo\nLa entrega de los apoyos se realizarán de dos formas: apoyos de forma económica a los beneficiarios equivalentes a jornales de trabajo de acuerdo a la zona que se trate y apoyos económicos para adquisición o arrendamiento de herramientas, materiales o equipo de trabajo para el desarrollo del proyecto y/o acción a realizar.\nLos apoyos que el Programa entrega a los beneficiarios no dan lugar a relación laboral o contractual alguna con la Dependencia responsable del programa.\n5.1.4.1. Apoyo económico a los beneficiarios\nSe otorgará un apoyo económico a los participantes por haber cumplido con su corresponsabilidad, consistente en jornales equivalentes al 99% de un salario mínimo general diario vigente en la zona económica en que se desarrolle el proyecto y/o acción, conforme a lo establecido por la Comisión Nacional de los Salarios Mínimos, que se encuentran vigentes a partir del 1 de enero de\n2013. Dicho apoyo se entregará en forma monetaria en un máximo anual de 90 jornales por beneficiario\n(ANEXO 2).\n5.1.4.1. Apoyo para Adquisición o Arrendamiento de Herramientas/ Materiales o Equipo\nSe podrá destinar un apoyo económico para la adquisición de materiales o herramientas, o para el arrendamiento de maquinaria o equipo necesarios para realizar el proyecto y/o acción autorizada en un porcentaje no mayor al 30% del total del proyecto y/o acción a ejecutar.\nLos apoyos que otorga el programa serán orientados a los siguientes rubros de atención:\nMejoramiento de infraestructura local:\n• Desarrollo de proyectos y/o acciones en infraestructura para la dotación de agua, saneamiento, ampliación de drenaje y alcantarillado.\n• Mantenimiento, limpieza y desazolve de cunetas y canales de riego.\n• Mejoramiento, rehabilitación y limpieza de espacios públicos\n• Mejoramiento, rehabilitación, ampliación y construcción de infraestructura básica en vivienda.\n• Saneamiento, construcción, rehabilitación y mantenimiento de infraestructura de salud\nConservación y rehabilitación, caminos, puentes, carreteras y brechas.\n• Conservación, rehabilitación y apertura de brechas, caminos rurales \"y alimentadores.\n• Construcción, conservación, rehabilitación y apertura de puentes principalmente en zonas rurales.\nConservación ambiental:\n• Protección, conservación, restauración y aprovechamiento sustentable de los recursos naturales.\nApoyo a la educación:\n• Rehabilitación, mantenimiento y limpieza a la infraestructura educativa.\nApoyo a la producción:\n• Acciones de rehabilitación, conservación y mantenimiento a la infraestructura productiva agrícola, pesquera, artesanal y forestal.\n6. Información del programa\n6.1 exposición del Programa\nEl Programa de Empleo Temporal (PET), atenderá por igual a hombres y mujeres que se encuentren temporalmente desempleados y deseen apoyar con memo de obra acciones de carácter familiar o comunitario de fácil realización, para lo cual se les apoyara con jornales de trabajo hasta por un periodo de 3 meses, los solicitantes para ser beneficiarios del programa deberán sujetarse a los criterios y requisitos que establecen las presentes reglas de operación.\n6.2 Cobertura\nEl programa podrá operar a nivel estatal en los 81 municipios que lo integran, beneficiando principalmente a población que vive en zonas urbano marginadas y municipios con Bajo índice de\nDesarrollo Humano (BIDH).\n6.3 Modos de entrega del beneficio beneficiarios, en los plazos y lugares en donde se desarrollen los proyectos y/o acciones acordados con el Comité de Desarrollo Local.\n6.4 Gastos de Operación\nDel total de recursos autorizados al programa, podrán aplicarse hasta un 3% del presupuesto asignado al Programa para gastos de operación, destinados a las diversas acciones asociadas con la planeación, operación, supervisión, seguimiento, contraloría social y evaluación o asesoría externa del\nPrograma.\n7. Transparencia\n7.1Difusión\nEstas Reglas de Operación, además de su publicación en el Periódico Oficial del Gobierno del\nEstado de Guerrero, estarán disponibles en la página de Internet de la SEDESOL del estado realizar las acciones conducentes para dar a conocer los requisitos de participación, la corresponsabilidad de los beneficiarios y los apoyos a otorgar.\nLa SEDESOL del Estado, en coordinación con los municipios, serán los encargados de realizar la promoción y difusión del Programa, darán a conocer las acciones a realizar y las comunidades beneficiadas.\nAsí mismo, con base en lo establecido en la Ley Número 374 de Transparencia y Acceso a la\nInformación Pública del Estado de Guerrero, la SEDESOL Estatal publicará periódicamente en la página electrónica http: //www. sedesol.guerrero.gob.mx la información relativa al Programa.\n7.2 Seguimiento de avances físicos y financieros\nCon el propósito de mejorar la operación del programa, la SEDESOL del Estado llevará a cabo el seguimiento al ejercicio de recursos fiscales, acciones ejecutadas, resultados, indicadores y metas alcanzadas.\nAsimismo, realizarán el seguimiento en campo de las obras, proyectos y acciones conforme a lo que cada una determine.\nLa Sedesol deberá reportar trimestralmente al COPLADEG, durante los primeros 5 días hábiles del mes inmediato posterior al trimestre que se reporta, los avances físico-financieros de los proyectos y/o acciones autorizados. en un tanto original. La Dependencia verificará la congruencia de la información con la Cuenta Pública.\n7.3 Evaluación\nEvaluación Interna ejecución y garantizar que los mecanismos de funcionamiento y administración, faciliten tanto la aplicación..\nEvaluación Externa sujeto a reglas de operación, para lo cual, la SEDESOL, tendrá la facultad de designar en su caso a la instancia que realizará dicho análisis.\nGeneral del Estado.\nIndicadores\nPara el seguimiento y evaluación del Programa se utilizarán los indicadores que corresponden al nivel de propósito detallados a continuación:\n• Número de proyectos y/o acciones ejecutadas\n• Número de beneficiarios que recibieron apoyo\n• Número de jornales realizados\nLa SEDESOL del Estado será responsable de compilar e integrar un reporte estatal de resultados tomando como base los proyectos y/o acciones desarrollados por el Programa Estatal de\nEmpleo Temporal, al finalizar el ejercicio fiscal.\n7.4 Auditoria\nLos ejecutores serán responsables de la supervisión directa de los proyectos o acciones, así como de verificar que en su ejecución se cumpla con la normatividad aplicable.\nLos recursos asignados para la operación del Programa no pierden su carácter estatal, por lo que, la Secretarla de Finanzas, la Contralor la General del Estado y la Auditoria General del Estado, en el ámbito de sus respectivas competencias, realizarán actividades de fiscalización y auditoría.\nLa Instancia Ejecutora dará todas las facilidades a las instancias fiscal i zadoras paira realizar, en el momento en que lo juzguen pertinente, las auditorias que consideren necesarias; asimismo, efectuará el seguimiento y la solventación de las observaciones planteadas por los órganos de control. La inobservancia de esta disposición, independientemente de las sanciones a que hubiere lugar, limitará la ministración de los recursos estatales en el siguiente ejercicio presupuestal.\n7.5 Recursos no devengados\nLos recursos que al cierre del ejercicio se conserven o que no se hayan devengado al 31 de\nDiciembre del presente ejercicio, deberán ser reintegrados a la Secretaría de Finanzas del Estado.\nDentro del mismo plazo, deberán remitir copia del reintegro a la SEFINA para su registro correspondiente.\n7.6 Blindaje electoral deberá observar y atender las medidas que emitan la Contraloría General del Estado, el Instituto de\nElectoral del Estado de Guerrero (IEEGRO) y las demás autoridades competentes, con la finalidad de impedir que los apoyos sean utilizados con fines políticos electorales.\nEn cuanto a la publicidad en medios electrónicos, impresos, complementarios o de cualquier otra índole vinculados.con los programas de comunicación social, se deberá incluir la leyenda:\n\"Este Programa es de carácter público, no es patrocinado ni promovido por partido político alguno y sus recursos provienen de los impuestos que pagan todos los contribuyentes, Está prohibido el uso de este programa con fines políticos, electorales, de lucro y otros distintos a los establecidos. Quien haga uso indebido de los recursos de este programa deberá ser denunciado y sancionado de acuerdo con la Ley aplicable y ante la autoridad competente\".\n7.7 Contraloría social\nCon la finalidad de incrementar la participación ciudadana, para cada uno de los proyectos y/o acciones se crearán Comités de Comunitarios los cuales fungirán como Contraloría Social, como un órgano ciudadano de control, vigilancia y evaluación de las actividades del Programa, conformado por los beneficiarios y alguna autoridad local, quienes de manera específica supervisarán la gestión gubernamental, y que el manejo de los recursos públicos se realicen en términos de transparencia, eficacia, legalidad y honradez.\n7.7.1 Integración de los comités comunitarios\nLos Comités de Contraloría Social se conforman con la representación de la comunidad beneficiada por el Programa, y fungirán como interlocutores con la Secretaría de Desarrollo Social, en el ejercicio de la contraloría social.\nEl Comité de Contraloría Social debe estar constituido por un Presidente, un Secretario y un\nVocal mínimamente, electos de entre la población beneficiada en donde se va a realizar la entrega del programa, y tendrá que ser vigilado por un solo comité. programa, así como la detección de cualquier irregularidad. denuncias recibidas a la Secretaría de Desarrollo Social, quien dará respuesta en un plazo no mayor de\n15 días a partir de la fecha de recepción de la queja o denuncia.\n7.7.2 Capacitación y Asesoría asesoría, a los servidores públicos que intervienen en la operación del Programa, así Gomo a los integrantes de los Comités Locales, para que éstos realicen adecuadamente sus actividades de seguimiento y vigilancia.\n7.7.3 Seguimiento\nEl Subsecretario (a) de la Política Social o el personal que designe la Secretaría de Desarrollo\nSocial, serán los encargados de conformar los Comités de Contraloría Social, así mismo darán acompañamiento durante las actividades de control, seguimiento y vigilancia de los proyectos y/o acciones que se están realizando.\n7.8 Quejas y denuncias\nLos beneficiarios pueden presentar sus quejas c denuncias directamente en las Oficinas de la\nSecretaría de Desarrollo Social sobre cualquier hecho, acto u omisión que produzca o pueda producir daños al ejercicio de sus derechos establecidos en las presentes Reglas o contravengan sus disposiciones y de la demás normatividad aplicable.\nLas quejas y denuncias de la ciudadanía derivadas de alguna irregularidad en la operación del programa podrán realizarse por escrito y ser entregadas de manera directa en el domicilio ubicado en\nEdificio Norte Planta Baja, Palacio de Gobierno, Sita en Boulevard René Juárez Cis-neros No. 62, Chilpancingo, Gro. C. P. 0390746 por vía telefónica a los Teléfonos: 01 (747) 47 1 98 63; 47 1 98 48 y 47\n1 98 49.\n8. Criterios de selección y elegibilidad\nEl programa está diseñado para proporcionar apoyo temporal a personas desempleadas y que no cuenten con ningún apoyo de este tipo, estableciendo como prioridad su condición de pobreza en que se encuentre. requisitos.\n8.1 Criterios de elegibilidad:\na) Que los proyectos y/o acciones se ejecuten preferentemente en zonas marginadas y de bajo índice de Desarrollo Humano;\nb) Que los proyectos y/o acciones sean de fácil realización y que generen un mayor beneficio familiar o comunitario y de impacto ambiental; y\nc) Proyectos y/o acciones en que la mayoría de los integrantes manifiesten ser jefes o jefas de hogar, la cual será validada por su representante de grupo.\nSumado a estos criterios, los posibles beneficiarios deberán presentar los siguientes requisitos:\na) Presentar solicitud dirigida al Titular de la Secretaría de Desarrollo Social, mediante escrito libre que contenga: Nombre completo del interesado o persona que acuda en representación de los interesados en el proyecto; Fecha y Lugar; Presentar justificación del proyecto el cual incluirá el nombre y la descripción breve del proyecto ya sea de beneficio familiar o comunitario que se planea realizar, indicando el lugar para su ejecución, número de beneficiarios y tiempo estimado para su realización; firma o huella digital del interesado o representante del grupo. Deberá anexar a la petición, la lista de solicitantes que integran el proyecto en cuestión; las solicitudes se recibirán en el Edificio Norte Planta\nBaja, Palacio de Gobierno, Sita en Boulevard René Juárez Cisneros No. 62, Chilpancingo, Gro. C. P. 03\n9074;\nb) Los solicitantes deberán contar con 16 años cumplidos o más al inicio de los proyectos;\nc) Entregar copia fotostática de cada uno de los solicitantes del Acta de nacimiento; CURP;\nCredencial de elector; Constancia de Identidad (expedida por la autoridad municipal), presentar en original cualquiera de los documentos antes señalados para su cotejo;\nd) Solo se apoyará a un miembro por familia;\ne) No ser servidor público;\nf) No recibir apoyos de otros programas para el mismo fin; y\ng) Estar de acuerdo en cumplir con su corresponsabilidad dentro de un proyecto.\nPara los proyectos y/o acciones\nLa Secretaría de Desarrollo Social a través de la Subsecretaría de Política Social, emitirá su opinión normativa, y en su caso, la autorización de acuerdo a la viabilidad técnica, económica y social considerando la disponibilidad presupuestal para su ejecución.\n9. Mecánica de operación\n9.1 Instancia Ejecutora concertar la participación activa y responsable de los H. Ayuntamientos y Organizaciones de la Sociedad\nCivil conforme a los lineamientos contenidos en las presentes reglas de operación del programa.\n9.2 Instancia Administrativa c normativa la aplicación de las Reglas de Operación y de resolver los casos no previstos en las mismas.\n9.3 Delimitación de atribuciones\nPresupuesto de Egresos del Estado, tendrá las siguientes atribuciones:\n• Coordinar y conducir la operación del programa, de acuerdo a los lineamientos establecidos en las presentes reglas;\n• Administrar a través de la Dirección General de Administración y Finanzas de la SEDESOL los recursos financieros autorizados;\n• Diseñar los instrumentos técnicos necesarios para evaluar el impacto social del programa; y\n• La organización del personal técnico y operativo que resulte indispensable para garantizar el funcionamiento del programa.\n10. Derechos, obligaciones y sanciones de los beneficiarios de programas sociales\n10.1 Derechos\nLos beneficiarios tendrán derecho a recibir:\na) La información necesaria de manera clara y oportuna para participar en el Programa;\nb) Un trato digno, respetuoso, oportuno, con calidad y equitativo, sin discriminación alguna;\nc) Atención y apoyos sin costo alguno;\nd) La reserva y privacidad de su información personal; y\ne) Recibir en caso de que sea elegible su proyecto y/o acción el apoyo económico establecido en estas reglas de operación.\n10.2 Obligaciones\nLos beneficiarios del Programa tendrán las siguientes obligaciones:\na) Proporcionar, bajo protesta de decir verdad, la información que se les requiera de acuerdo a lo establecido en las presentes reglas de operación;\nb) Cumplir con su corresponsabilidad en el proyecto autorizado y el Comité de Desarrollo\nComunitario (ANEXO 3) respectivo para el propósito del proyecto y/o acción; y\nc) Nombrar a un representante, para que, en caso de fallecimiento, imposibilidad física o enfermedad, alguno de sus integrantes pueda recibir los jornales que le correspondan. Así como cumplir con cada uno de los requisitos que se le soliciten.\n10.3 Sanciones\nSe suspenderán definitivamente los apoyos a los beneficiarios que:\na) No cumplan con alguna de las obligaciones estipuladas en las reglas de operación; y\nb) En el caso de que la Dependencia o algún Órgano de Fiscalización detecte desviaciones o incumplimiento en el ejercicio de los recursos a las presentes Reglas de Operación, por parte de los beneficiarios, por lo cual la SEDESOL suspenderá los apoyos, y solicitará el reintegro total, de acuerdo a la normatividad aplicable.\n11. Anexos\n11.1 Anexo 1. Glosario de Términos\nBeneficiario: Mujer u hombre, de 16 años o más de edad, que recibe los apoyos del programa por haber cumplido con su responsabilidad así como con los Requisitos y Criterios de Elegibilidad establecidos en estas. Reglas.\nCorresponsabilidad: Se refiere a la ejecución por parte de los beneficiarios de las actividades que les corresponde de acuerdo a los proyectos o acciones que les fueron aprobados.\nCURP: Clave única de Registro de Población.\nPrograma: Programa de Empleo Temporal.\nReglas: las Reglas de Operación del Programa Estatal de Empleo Temporal.\nRubros de Atención: Son ámbitos de acción determinados por cada dependencia de acuerdo a sus atribuciones y competencias.\nSolicitante: Persona que pide participar en el Programa de manera forma.\n11.2 Anexo 2. Lista de Raya\n11.3 Anexo 3. Acta Constitutiva\nEN EL POBLADO DE____________________________________________________ MUNICIPIO DE\n_______________________________________. GUERRERO, SIENDO LAS ______ HORAS DEL DIA\n___________DEL MES DE ____________________________DEL 2013, EN EL LUGAR QUE OCUPA\nSE REUNIERON LOS HABITANTES DEL MUNICIPIO DE____________________ DE LA LOCALIDAD\nDE. _________________________Y EL REPRESENTANTE DE LA SECRETARIA DE DESARROLLO\nSOCIAL DEL GOBIERNO DEL ESTADO C._________________________________________. QUIEN\nFUNGIRÁ COMO MODERADOR, ASI COMO LOS CIUDADANOS QUE SE RELACIONAN AL FINAL DE\nLA PRESENTE ACTA, CON EL PROPÓSITO DE CONSTITUIR UN COMITÉ PARA COOPERAR A LA\nREALIZACIÓN DE OBRAS Y ACCIONES DE DESARROLLO EN BENEFICIO________(FAMILIAR Y/0\nCOMUNITARIO) ' PARA LLEVAR A CABO:\n____________________________________________________________________________________\n____________________________________________________________________________________\n___________________________________________________________________________________\nSE PODRÁN REALIZAR A TRAVES DEL PROGRAMA, LOS CRITERIOS QUE SERVIRÁN DE BASE\nPARA LA AUTORIZACIÓN DE LOS RECURSOS Y EJECUCIÓN DE LAS OBRAS, ASI COMO LOS\nASPIREN A RECIBIR LOS APOYOS, QUIENES DEBERÁN COOPERAR CON SU ESFUERZO Y\nCOLABORAR ORGANIZADAMENTE EN SU REALIZACION, ADMINISTRACIÓN Y OPERACIÓN\nENTERADOS LOS PRESENTES DE LO EXPRESADO POR EL C. REPRESENTANTE, DECIDEN\nEJECUTIVO, CUYA INTEGRACION Y FUNCIONAMIENTO SE SUJETA A LOS ESTATUTOS\nCONTENIDOS EN LAS SIGUIENTES:\nCLÁUSULAS\nPRIMERA.-EL COMITÉ SE DENOMINABA: COMITÉ LOCAL DE DESARROLLO COMUNITARIO DE\n___________________________________________________________________________________\nSEGUNDA.-EL COMITÉ TENDRÁ POR OBJETO CONTRIBUIR A LA REALIZACIÓN DE LAS\nACCIONES QUE SE HACEN REFERENCIA EN LA PRESENTE ACTA, EN LAS FORMAS QUE A\nCONTINUACIÓN SE EXPRESAN:\n♦ APORTAR EN MANO DE OBRA LA CANTIDAD SUFICIENTE PARA QUE LOS PROYECTOS Y/O\nACCIONES SE REALICE EN EL MENOR TIEMPO POSIBLE.\n♦ PROPORCIONAR LOS BANCOS DE MATERIALES QUE SE REQUIERAN.\n♦ GESTIONAR LA DISPONIBILIDAD DE LA SUPERFICIE QUE SE REQUIERA PARA LAS OBRAS.\n♦ COLABORAR CON LAS AUTOR' JADES FEDERALES, ESTATALES Y MUNICIPALES EN LA\nRESOLUCIÓN DE LOS PROBLEMAS QUE SE PRESENTEN DURANTE LA EJECUCIÓN DE LOS\nTRABAJOS.\nTERCERA -EL COMITÉ ESTARÁ INTEGRADO POR LA ASAMBLEA GENERAL Y UN ÓRGANO\nEJECUTIVO.\nEL ÓRGANO EJECUTIVO DEL COMITÉ CONTARÁ CON UN PRESIDENTE, UN SECRETARIO, UN\nTESORERO Y DOS VOCALES.\nCUARTA.-LOS MIEMBROS DEL ÓRGANO EJECUTIVO, SERÁN ELEGIDOS POR EL PLENO DE LA\nASAMBLEA GENERAL.\nQUINTA.-LAS DECISIONES DEL COMITÉ LOCAL SE TOMARÁN POR VOTACIÓN DE LA MAYORÍA\nDE LOS INTEGRANTES DE LA ASAMBLEA GENERAL.\nSEXTA.-EL PRESIDENTE DEL COMITÉ, TENDRÁ LA REPRESENTACIÓN DE LA ASAMBLEA\nGENERA! ANTE TODA CLASE DE AUTORIDADES, ORGANISMOS, PERSONAS FÍSICAS O\nMORALES, SIEMPRE QUE SEA NECESARIO PARA EL CUMPLIMIENTO DE LOS COMPROMISOS\nDEL COMITÉ.\nSÉPTIMA -EL SECRETARIO TENDRÁ A SU CARGO EL ARCHIVO DE LA DOCUMENTACIÓN\nCORRESPONDIENTE, ASI COMO CONTESTAR Y RECIBIR TODA CLASE DE CORRESPONDENCIA.\nOCTAVA.- EL TESORERO CONTROLARA LOS FONDOS Y MATERIALES, Y LOS DISTRIBUIRÁ PARA\nCUBRIR LAS NECESIDADES DE LAS OBRAS O ACCIONES SEGÚN SU AVANCE FÍSICO.\nNOVENA.- 2 VOCALES: UNO SE ENCARGARA DE LLEVAR A CABO TAREAS DE ORGANIZACION\nCOMO CONTRALORÍA SOCIAL, INSTRUMENTANDO LOS ELEMENTOS BÁSICOS DE CONTROL Y\nVIGILANCIA RELATIVOS AL EJERCICIO DE LOS RECURSOS PARA EL AVANCE DE LAS ACCIONES\nY ATENDERÁ Y RESOLVERÁ Y/O CANALIZARA LAS QUEJAS QUE SE DERIVEN DE LA EJECUCIÓN.\nDECIMA-LA ASAMBLEA GENERAL ES LA MAXIMA AUTORIDAD DEL COMITÉ PARA CONVOCAR A\nASAMBLEAS CUANDO SE REQUIERA O A JUICIO DEL ÓRGANO EJECUTIVO CUANDO EXISTAN\nPUNTOS IMPORTANTES QUE TRATAR, SIENDO NECESARIO QUE ASISTAN LOS INTEGRANTES\nDE ESTE ULTIMO Y LA MAYORIA DE LOS MIEMBROS DE LA ASAMBLEA.\nLAS DECISIONES DE LA ASAMBLEA SE TOMARAN POR MAYORIA DE VOTOS\nDE LOS ASISTENTES.\nDÉCIMA PRIMERA.-ES OBLIGACIÓN DEL COMITÉ, DAR CUENTA MENSUAL A LA ASAMBLEA\nACCIONES A REALIZAR.\nPROCEDIÓ A DESIGNAR A LOS MIEMBROS DEL ÓRGANO EJECUTIVO, CONFORME A LAS\nPROPUESTAS SE LLEVO A CABO LA VOTACIÓN, RESULTANDO ELECTAS LAS SIGUIENTES\nPERSONAS.\nCONSTITUTIVA SIENDO LAS.____ HORAS, FIRMANDO DE CONFORMIDAD LAS PERSONAS QUE\nEN ELLA INTERVINIERON:",
  "ordenamiento": "REGLA",
  "jurisdiccion": "GUERRERO",
  "fuente_oficial": "DIARIO OFICIAL DE LA FEDERACION",
  "Fecha de Publicación": "18 DE JULIO DE \n2014",
  "ULTIMA REFORMA PUBLICADA": "18 DE JULIO DE 2014",
  "status": "VIGENTE",
  "es_escaneado": false,
  "tiene_tablas": false,
  "materia": [
    "laboral"
  ]
}