{
  "titulo": "Acuerdo por el Que Se Crea el Programa Gubernamental de Garantía para la Reactivación de las PYMES O",
  "Contenido": "CONTINGENCIA COVID-19 Y SE EMITEN SUS REGLAS\nDE OPERACIÓN PARA EL EJERCICIO FISCAL 2020\nGUERRERO NO. 39 ALCANCE I, DE FECHA 14 DE MAYO DE 2021.\nTEXTO ORIGINAL.\nAcuerdo publicado en el Periódico Oficial del Gobierno del Estado No.74, el Martes 22 de\nSeptiembre de 2020.\nACUERDO POR EL QUE SE CREA EL PROGRAMA GUBERNAMENTAL DE GARANTÍA PARA LA\nREACTIVACIÓN DE LAS PYMES OCASIONADO POR LA CONTINGENCIA COVID-19 Y SE EMITEN\nSUS REGLAS DE OPERACIÓN PARA EL EJERCICIO FISCAL 2020.\nGuerrero.- Poder Ejecutivo.\nLICENCIADO HÉCTOR ANTONIO ASTUDILLO FLORES, GOBERNADOR CONSTITUCIONAL DEL\nESTADO DE GUERRERO, CON FUNDAMENTO EN LO DISPUESTO POR LOS ARTÍCULOS 71, 87, 88,\nLOS ARTÍCULOS 2, 3, 6, 7, 10, 11, 18 APARTADO A FRACCIONES I Y X, 20 FRACCIÓN III Y 29\nFRACCIONES I, XII, XIV, XV Y XIX DE LA LEY ORGÁNICA DE LA ADMINISTRACIÓN PÚBLICA DEL\nESTADO DE GUERRERO NÚMERO 08; 1, 2 FRACCIÓN I, 18 Y 25 DE LA LEY NÚMERO 454 DE\nPRESUPUESTO Y DISCIPLINA FISCAL DEL ESTADO DE GUERRERO; 33, 34 Y 35 FRACCIONES I Y\nII DE LA LEY DE FOMENTO ECONÓMICO, INVERSIÓN Y DESARROLLO DEL ESTADO DE\nGUERRERO NÚMERO 487; 55 DEL DECRETO NÚMERO 447 DEL PRESUPUESTO DE EGRESOS DEL\nESTADO DE GUERRERO PARA EL EJERCICIO FISCAL 2020 Y LOS LINEAMIENTOS PARA LA\nELABORACIÓN DE LAS REGLAS DE OPERACIÓN DE LOS PROGRAMAS SOCIALES ESTATALES\nPARA EL EJERCICIO FISCAL 2017.\nQue el Plan Estatal de Desarrollo 2016-2021 en el Eje II Guerrero Prospero en los objetivos 2.1 y\n2.7, menciona fomentar y generar empleo de calidad, así como gestionar con eficacia Proyectos\nEstratégicos mediante las líneas de acción donde se menciona apoyar a las PyMES, para impulsar su crecimiento y su generación de fuentes de empleo en las diferentes regiones de la entidad, así también impulsar esquemas de financiamiento para la comercialización. que se ha venido expandiendo a todo el mundo cobrando miles de vidas humanas, afectando la salud y anteriormente. Es sin duda un suceso sin precedentes, y en el que no se tiene memoria en los últimos\nCONTINGENCIA COVID-19 Y SE EMITEN SUS REGLAS\nDE OPERACIÓN PARA EL EJERCICIO FISCAL 2020 cincuenta años en el país ni en el mundo entero, impactando a los sectores de la economía más importantes como los son el comercio, la construcción, la minería y los servicios turísticos.\nPor tal motivo es importante promover un programa estatal, que nos permita la reactivación económica de las empresas guerrerenses, las cuales podrán contener esta pandemia global en la que estamos viviendo.\nCon el Programa Gubernamental de Garantía para la Reactivación de las PyMES Ocasionado por\nContingencia COVID-19, a través de la Secretaría de Fomento y Desarrollo Económico (SEFODECO), se busca garantizar la reactivación económica de las empresas guerrerenses, sin duda será un aliciente para las unidades económicas al poderles otorgar algún apoyo o crédito en los que logren mantenerse por esta contingencia ambiental en la que estamos viviendo no solo nuestro Estado sino el mundo entero.\nEl Programa Gubernamental de Garantía para la Reactivación de las PyMES Ocasionado por\nContingencia COVID-19, tiene como objetivo y metas otorgar apoyos y créditos a las Micro, Pequeñas y\nMedianas Empresas del Estado de Guerrero; mismo que estará a cargo de la Secretaría de Fomento y\nDesarrollo Económico para su operación, ejecución, evaluación y administración.\nPor lo antes expuesto, he tenido a bien expedir el siguiente:\nACUERDO POR EL QUE SE CREA EL PROGRAMA GUBERNAMENTAL DE GARANTÍA PARA LA\nREACTIVACIÓN DE LAS PYMES OCASIONADO POR LA CONTINGENCIA COVID-19 Y SE EMITEN\nSUS REGLAS DE OPERACIÓN PARA EL EJERCICIO FISCAL 2020.\nArtículo 1. Se crea el Programa Gubernamental de Garantía para la Reactivación de las PyMES\nOcasionado por la Contingencia COVID-19, el cual tiene por objeto otorgar apoyos y créditos a las Micro, Pequeñas y Medianas Empresas del Estado de Guerrero.\nArtículo 2. Se emiten las Reglas de Operación del Programa Gubernamental de Garantía para la\nReactivación de las PyMES Ocasionado por la Contingencia COVID-19 para el Ejercicio Fiscal 2020, en las que se establecen los principios de eficiencia, eficacia, oportunidad, equitativa y transparencia de los recursos públicos y requisitos que se deben de cumplir para poder acceder a dicho Programa.\nArtículo 2. La Secretaría de Fomento y Desarrollo Económico, tendrá a su cargo la implementación, operación, ejecución, evaluación y administración del Programa Gubernamental de\nGarantía para la Reactivación de las PyMES Ocasionado por la Contingencia COVID-19, bajo los criterios de objetividad, equidad, transparencia, publicidad, selectividad y temporalidad, con estricto apego a la normatividad aplicable, por lo tanto, será la encargada de la dispersión y asignación de los recursos del\nPrograma, apegándose plenamente a las siguientes:\nREACTIVACIÓN DE LAS PYMES OCASIONADO POR CONTINGENCIA COVID19 PARA EL EJERCICIO FISCAL 2020.\nCONTINGENCIA COVID-19 Y SE EMITEN SUS REGLAS\nDE OPERACIÓN PARA EL EJERCICIO FISCAL 2020\n1. Introducción\n1.1. Antecedentes que se ha venido expandiendo a todo el mundo cobrando miles de vidas humanas, afectando la salud y economía de todas las personas del mundo y que por su agresividad y falta de medicamentos no se ha podido combatir de manera frontal que permita salir a las calles libremente como lo hacíamos anteriormente. Es sin duda un suceso sin precedentes, y en el que no se tiene memoria en los últimos cincuenta años en el país ni en el mundo entero, impactando a los sectores de la economía más importantes como los son el comercio, la construcción, la minería y los servicios turísticos.\nPara atender la problemática anterior, es importante promover un programa que nos garantice la reactivación económica y poder contrarrestar las perdidas por falta de apertura de las empresas guerrerenses, mediante el otorgamiento de apoyos y créditos a las empresas que permitan mantener su planta laboral y así poder estar en condiciones de aislamiento temporal.\n1.2. Alineación programática\nEn cumplimiento a lo que globalmente prevén los ejes rectores del Plan Estatal de Desarrollo 20162021, se alinea en el Eje VII.2. Guerrero Próspero con perspectiva de género e intercultural.\nObjetivo:\nEl programa se vincula a los siguientes objetivos del Plan Estatal de Desarrollo 2016-2021:\n2.1. Fomentar y generar empleo de calidad.\n2.7. Gestionar con eficacia Proyectos Estratégicos.\nEstrategia:\nEl programa se vincula a las siguientes estrategias del Plan Estatal de Desarrollo 2016-2021:\n2.1.1. Asegurar la promoción y la generación de empleo de calidad y con igualdad de género como estrategia central para atender las necesidades más urgentes de los guerrerenses: seguridad alimentaria, educación y salud. El compromiso es contribuir de manera significativa al desarrollo humano en la entidad.\n2.7.1.4. Desarrollar la red hidráulica y la producción agroindustrial.\n2.7.5. Desarrollar la actividad agroindustrial para mejorar la productividad al impulsar el desarrollo de los sectores agrícola, pesquero y acuícola; fortalecer el desarrollo empresarial de proyectos agroindustriales; propiciar el desarrollo gradual económico, social, productivo y sustentable; aprovechar las potencialidades y las vocaciones productivas agropecuarias del Estado; generar mayor productividad y competitividad que se refleje en mayores ingresos y en la mejora de la economía de las familias.\nCONTINGENCIA COVID-19 Y SE EMITEN SUS REGLAS\nDE OPERACIÓN PARA EL EJERCICIO FISCAL 2020\nLíneas de Acción:\nEl programa se vincula a las siguientes líneas de acción del Plan Estatal de Desarrollo 2016-2021:\n• Apoyar a las PyMES, para impulsar su crecimiento y su generación de fuentes de empleo en las diferentes regiones de la entidad.\n• Impulsar esquemas de financiamiento para la comercialización.\nEl Programa se vincula con el siguiente objetivo del Programa Sectorial: Industria, Minería\nComercio, Abasto y Apoyo a MIPYMES:\nObjetivo 6\nFortalecer el desarrollo empresarial de las MIPYMES, a los emprendedores y los organismos del sector social de la economía.\nEstrategia\nEl Programa se vincula con las siguientes estrategias del Programa Sectorial: Industria, Minería\nComercio, Abasto y Apoyo a MIPYMES:\n6.2. Garantizar el mejoramiento de las MIPYMES mediante acciones integrales de apoyo incluyente, facilitando el acceso al crédito, a la capacitación y recursos para proyectos productivos que estimulen su permanencia y la generación de empleo o autoempleo. El compromiso es contribuir a mejorar el bienestar de la población guerrerense sin distinción alguna; se trata de brindar apoyo a hombres y mujeres, jóvenes, adultos, adultos mayores y discapacitados.\n6.3. El desarrollo de las MIPYMES tendrá impacto directo en: acceso a créditos bancarios y de otras instituciones financieras, mejor posicionamiento en el mercado, seguridad jurídica, Generación de empleos, Contribución al desarrollo económico local, estatal y nacional, Oportunidad de exportación, Mayor aceptación y confianza del cliente.\n6.4. Apoyar a los productores con recursos económicos para cumplir con los requisitos indispensables para poder entrar a un mercado formal (registro de marca, trámite de código de barras, tabla nutricional y empaque corporativo), y de esta forma, percibir mejores ingresos, estar amparados ante la ley y seguir en condiciones de competitividad en relación a otros productos. guerrerenses, vía la asistencia con el pago de viáticos de los empresarios para la participación en las ferias de comercio y exportación nacionales e internacionales más importantes, así como un traductor.\nLíneas de acción:\nEl Programa se vincula con las siguientes líneas de acción del Programa Sectorial: Industria, Minería Comercio, Abasto y Apoyo a MIPYMES:\nCONTINGENCIA COVID-19 Y SE EMITEN SUS REGLAS\nDE OPERACIÓN PARA EL EJERCICIO FISCAL 2020\n• Establecer una partida presupuestal especifica que atienda contingencias de empresas riesgo su operación.\n• Proponer el mejoramiento del entorno regulatorio en beneficio de las MIPYMES.\n• Atraer programas de cooperación internacional que impulsen el desarrollo de proyectos empresariales, institucionales y gubernamentales.\n• Impulsar el emprendimiento y apoyar el autoempleo vía el otorgamiento de proyectos productivos que desarrollen las capacidades y habilidades del guerrerense, se forma directa y oportuna.\n1.3. Diagnóstico\na) El problema social que se atiende y su magnitud\nDerivado de la pandemia mundial del coronavirus COVID-19, dejando por su paso miles de muertes humanas y una afectación económica de grandes magnitudes para el mundo entero, el 30 de marzo del presente año, el Consejo de Salubridad General declaró una emergencia sanitaria por causa de fuerza mayor, como consecuencia de la evolución de casos confirmados y muertes por la enfermedad en el país, se optó por el cierre de las empresas afectando a los trabajadores, lo cual dio lugar a la ejecución de acciones adicionales para su prevención y control.\nb) Las causas y efectos observados del problema social\nLas cusas de la pandemia del COVID-19 en nuestro Estado, ha sido de igual manera como en otras entidades del país y del mundo entero, una afectación directa a la economía de nuestra población, falta de generación y preservación de empleos, ocasionando el cierre de miles de empresas en la entidad, como consecuencia la falta de generación y preservación de empleos.\nc) La manera en que el programa social busca contribuir a la resolución del problema identificado y la conservación y generación de empleos. Es importante impulsar un esquema financiero que permita a las unidades económicas de nuestra entidad, el acceso a créditos y apoyos económicos para garantizar la economía local.\nd) Línea de base\nEs un suceso sin precedentes, y en el que no se tiene memoria en los últimos cincuenta años en el país ni en el mundo entero, impactando a los sectores de la economía más importantes como los son el comercio, la construcción, la minería y los servicios turísticos, por lo que no se contempla una línea base.\ne) Población objetivo\nCONTINGENCIA COVID-19 Y SE EMITEN SUS REGLAS\nDE OPERACIÓN PARA EL EJERCICIO FISCAL 2020\nPyMES Ocasionado por Contingencia COVID-19, son las unidades económicas con domicilio en el Estado de Guerrero.\nMisión\nImpulsar y reactivar a las unidades económicas afectadas por la pandemia del coronavirus\n(COVID-19), a través de la instrumentación de esquemas de financiamiento y apoyos económicos.\nVisión\nApoyar el financiamiento de las unidades económicas del Estado de Guerrero, para la reactivación económica.\nPara la interpretación de las presentes Reglas de Operación, se entenderá por:\nPrograma: El Programa Gubernamental de Garantía para la Reactivación de las PyMES\nOcasionado por la Contingencia COVID-19.\nReglas de Operación: Las Reglas de Operación del Programa Gubernamental de Garantía para la Reactivación de las PyMES Ocasionado por la Contingencia COVID-19 para el Ejercicio Fiscal\n2020.\nSEFODECO: La Secretaría de Fomento y Desarrollo Económico.\nFundamento legal\n● Constitución Política de los Estados Unidos Mexicanos.\n● Ley Orgánica de la Administración Pública del Estado de Guerrero Número 08.\n● Ley Número 454 de Presupuesto y Disciplina Fiscal del Estado de Guerrero.\n● Ley de Fomento Económico, Inversión y Desarrollo del Estado de Guerrero Número 487.\n● Decreto Número 196 por medio del cual la Sexagésima Primera Legislatura al Honorable\n2016-2021.\nCONTINGENCIA COVID-19 Y SE EMITEN SUS REGLAS\nDE OPERACIÓN PARA EL EJERCICIO FISCAL 2020\n● Decreto Número 447 del Presupuesto de Egresos del Estado de Guerrero para el Ejercicio Fiscal\n2020.\n● Acuerdo por el que se establecen acciones extraordinarias para atender la emergencia sanitaria generada por el virus SARS- CoV2.\n● Acuerdo extraordinario por el que se aprueban medidas económicas y fiscales a las empresas\n2. Secretaría, dependencia o entidad responsable del programa\nLa Secretaría de Fomento y Desarrollo Económico (SEFODECO), a través de la Dirección General de Fomento Empresarial y el Organismo Público Descentralizado, Fondo de Apoyo a la Micro, Pequeña y\nMediana Empresa (FAMPEGRO).\n3. Objetivos y alcances\n3.1. Objetivo general\nOtorgar créditos blandos y apoyos económicos a las Micro, Pequeñas y Medianas Empresas del\nEstado de Guerrero, con el propósito de mitigar las afectaciones económicas derivadas de la pandemia del\nCOVID-19.\n3.2. Objetivos específicos\n● Crear un fondo de garantías con Nacional Financiera SNC., para el otorgamiento de créditos a las MIPYMES, a través de la banca comercial.\n● Creación de fondos de garantía con dependencias y organismos de los tres niveles de gobierno, e instituciones privadas nacionales e internaciones, para potencializar el financiamiento a las MIPYMES.\n● Otorgar créditos blandos a MIPYMES a través de la Secretaría de Fomento y Desarrollo\nEconómico y el Organismo Público Descentralizado, Fondo de Apoyo a la Micro, Pequeña y Mediana\nEmpresa (FAMPEGRO).\n● Otorgar apoyos económicos a través de la Secretaría de Fomento y Desarrollo Económico, a unidades económicas que no tienen acceso a esquemas de financiamiento de la banca comercial.\n3.3. Alcances\nOcasionado por Contingencia COVID-19, se busca garantizar la reactivación de las unidades económicas\nCONTINGENCIA COVID-19 Y SE EMITEN SUS REGLAS\nDE OPERACIÓN PARA EL EJERCICIO FISCAL 2020 de la entidad, mediante el otorgamiento de créditos blandos y apoyos económicos que logren contrarrestar la afectación por la pandemia del COVID-19.\nLos créditos blandos y los apoyos económicos deberán entregarse de manera oportuna y expedita, con los requisitos mínimos necesarios y en el menor tiempo posible, considerando las características de las unidades económicas y con estricto apego a las medidas sanitarias emitidas por las autoridades de salud federales y estatales.\n4. Metas físicas\nEl Programa Gubernamental de Garantía para la Reactivación de las PyMES Ocasionado por\nContingencia COVID-19, pretende beneficiar a las unidades económicas con domicilio en el Estado de\nGuerrero que lo soliciten, de acuerdo a la suficiencia presupuestaria del Programa a través de cuatro componentes:\nComponentes Meta\nPrograma de Reactivación Económica NAFIN + Estado de unidades económicas\nGuerrero.\nCreación de Fondos de Garantías con dependencias de los tres niveles de gobierno e instituciones privadas nacionales e unidades económicas internaciones. unidades económicas\nCréditos Blandos. unidades económicas\nApoyos Económicos.\nEn cada uno de estos rubros se integrarán listados de personas beneficiarias y participantes del\nPrograma en mención.\n5. Programación presupuestal\nEl recurso para la operación del Programa Gubernamental de Garantía para la Reactivación de las PyMES Ocasionado por Contingencia COVID-19, será de $54,800,000.00 (Cincuenta y cuatro millones ochocientos mil pesos 00/100 M.N.), cuyo monto podrá ser sujeto de ampliaciones subsecuentes; los recursos provienen del fondo de financiamiento de Inversión Estatal Directa (IED) y destinado a la planteados en estas Reglas de Operaciones. En la ejecución de los recursos deberá cumplirse con el principio de anualidad del Presupuesto de Egresos del Estado de Guerrero para el Ejercicio Fiscal 2020. potencializar los recursos destinados al presente Programa.\nCONTINGENCIA COVID-19 Y SE EMITEN SUS REGLAS\nDE OPERACIÓN PARA EL EJERCICIO FISCAL 2020\nEl presupuesto en mención se ejercerá mediante las siguientes categorías:\nNo. Categorías\nPrograma de Reactivación Económica NAFIN + Estado de Guerrero\nFondos de garantías\nCréditos blandos\nApoyos Económicos\n6. Requisitos y procedimientos de acceso\n6.1. Difusión\nA través de medios electrónicos como lo es el Portal Oficial del Gobierno del Estado, se anunciarán los esquemas de apoyos descritos en estas Reglas de Operaciones, esto de acuerdo a las medidas emitidas por el gobierno federal y estatal de prevenir contagios al tener contacto directo, por lo que tendrán que enviar documentación por medio de las vías digitales y en casos excepcionales, será de manera física, la meta es apoyar al mayor número de unidades económicas que así se requieran en los 81 municipios del\nEstado de Guerrero.\nEstas Reglas de Operación, además de su publicación en el Periódico Oficial del Gobierno del\nEstado de Guerrero, estarán disponibles para su consulta en las oficinas de la Secretaría de Fomento y\nDesarrollo Económico, así como en la dirección electrónica oficial de la dependencia: http://www.sefodeco.guerrero.gob.mx.\nA través de los diferentes medios de comunicación, se dará a conocer el Programa Gubernamental de Garantía para la Reactivación de las PyMES Ocasionado por Contingencia COVID-19.\nAsí mismo, para mayor información deberán contactarse con el titular de la Dirección General de\nJuárez Cisneros No. 62, Edificio Acapulco, 1er Piso, Col. Ciudad de los Servicios, C.P. 39074, Chilpancingo, Guerrero, en un horario de atención de 9:00 a 15:00 horas, o al teléfono 747 47 1 97 00 ext. fomentoempresarial.sefodeco@gmail.com.\nLa difusión del Programa tiene una cobertura, en los 81 municipios del Estado de Guerrero, abarcando las siete regiones de la entidad:\n1. Tierra Caliente;\nCONTINGENCIA COVID-19 Y SE EMITEN SUS REGLAS\nDE OPERACIÓN PARA EL EJERCICIO FISCAL 2020\n2. Norte;\n3. Centro;\n4. Montaña;\n5. Costa Grande;\n6. Costa Chica; y\n7. Acapulco.\nPara implementar dichas acciones, el Programa podrá realizar los ajustes necesarios en su planeación y operación, sin alterar lo establecido en las presentes Reglas de Operación y de las metas establecidas, en función de la capacidad operativa y disponibilidad presupuestal.\n6.2. Requisitos de acceso\nLas unidades económicas con domicilio en el Estado de Guerrero, que realicen alguna actividad económica y que cumplan con los requisitos, podrá acceder a una de las categorías del Programa\nGubernamental de Garantía para la Reactivación de las PyMES Ocasionado por Contingencia COVID-19, cuyos requisitos son los siguientes:\nPrograma de Reactivación Económica NAFIN + Estado de Guerrero:\nLa Secretaría de Fomento y Desarrollo Económico, expedirá a los interesados la Cédula de acceso al Programa misma que remitirá a Nacional Financiera con la siguiente documentación:\n▪ Formato de solicitud de cédula.\n▪ Constancia de Situación Fiscal.\n▪ Copia de Acta Constitutiva.\n▪ Identificación oficial con fotografía del contribuyente ó del representante legal, en caso de persona moral.\n▪ Comprobante de domicilio. solicitante, que emitirá la resolución correspondiente de autorización o negativa a la solicitud de crédito.\nFondos de garantías:\nLa Secretaría de Fomento y Desarrollo Económico, gestionará en su caso, fondos de garantía con dependencias y organismos de los tres niveles de gobierno, e instituciones privadas nacionales e internaciones, para potencializar el financiamiento a las MIPYMES, y de acuerdo a las disposiciones normativas aplicables.\nCréditos blandos:\n▪ Escrito libre de solicitud dirigida a la persona titular de la SEFODECO.\nCONTINGENCIA COVID-19 Y SE EMITEN SUS REGLAS\nDE OPERACIÓN PARA EL EJERCICIO FISCAL 2020\n▪ Copia de identificación oficial con fotografía de la persona solicitante.\n▪ Clave Única de Registro de Población (CURP).\n▪ Copia de comprobante de domicilio particular de la persona solicitante.\n▪ En su caso, comprobante de Clave Bancaria Estandarizada (CLABE interbancaria).\nAval solidario:\n▪ Copia de identificación oficial con fotografía.\n▪ Clave Única de Registro de Población (CURP).\n▪ Copia de comprobante de domicilio particular.\nAdicionalmente, en el caso del Organismo Público Descentralizado, Fondo de Apoyo a la Micro, Pequeña y Mediana Empresa (FAMPEGRO), los requisitos que establezca su normatividad.\nApoyos económicos:\n▪ Escrito libre de solicitud dirigida a la persona titular de la SEFODECO.\n▪ Copia de identificación oficial con fotografía.\n▪ Clave Única de Registro de Población (CURP).\n▪ Comprobante de domicilio.\n▪ En su caso, comprobante de Clave Bancaria Estandarizada (CLABE interbancaria).\nPor la contingencia sanitaria y atendiendo el distanciamiento social, las solicitudes podrán presentarse en las oficinas de la Secretaría de Fomento y Desarrollo Económico con domicilio en Palacio de Gobierno del Estado, Boulevard Lic. René Juárez Cisneros No. 62, Edificio Acapulco, 1er Piso, Col.\nCiudad de los Servicios, C.P. 39074, Chilpancingo, Guerrero, en un horario de atención de 9:00 a 15:00 horas, o a los correos electrónicos mipymes.sefodeco@guerrero.gob.mx, fomentoempresarial.sefodeco@gmail.com.\n6.3. Procedimiento de acceso\nLa Secretaría de Fomento y Desarrollo Económico y el Organismo Público Descentralizado, Fondo de Apoyo a la Micro, Pequeña y Mediana Empresa (FAMPEGRO), tomando en cuenta la revisión de la documentación que integre el expediente del solicitante, autorizarán o rechazarán las solicitudes que le sean presentadas y considerando que:\n▪ Cumplan con los requisitos previstos en las presentes Reglas de Operación y que sean congruentes con los objetivos del Programa; e\n▪ Incidan en la reactivación económica de las MIPYMES. su solicitud:\nPrograma de Reactivación Económica NAFIN + Estado de Guerrero\nCONTINGENCIA COVID-19 Y SE EMITEN SUS REGLAS\nDE OPERACIÓN PARA EL EJERCICIO FISCAL 2020 participar en el Programa de Reactivación Económica NAFIN + Estado de Guerrero y pertenezcan al perfil empresarial de los sectores Industria, Comercio y Servicios.\nSi el análisis de la información que se recibió es positivo, se procede a notificar vía correo electrónico, para avisar que su cedula ha sido validada y ha sido enviada a NAFIN para continuar con la siguiente etapa; por el contrario, si es negativo se notificará las observaciones detectadas con sus respectivas opciones para su solventación.\nLa emisión de Cédula será negada si la empresa solicitante manifiesta en su Constancia de\nSituación Fiscal que su domicilio se localiza en otra entidad que no sea el Estado de Guerrero, las\nMIPYMES con sucursales o aperturas de establecimientos en el Estado de Guerrero domiciliadas en otra entidad no podrán participar en el Programa.\nLas cédulas validadas serán enviadas a Nacional Financiera para continuar con el proceso de solicitud y autorización de crédito ante la Institución Financiera elegida por el solicitante.\nTodos los datos son obligatorios y sin ellos no podrán acceder al Programa o completar el trámite para ser posible beneficiaria o beneficiario. Con relación a la transferencia de información confidencial, los terceros receptores de los datos personales pueden ser: terceros, para fines públicos y específicos, sin que pueda utilizarse para otros distintos, y con quienes en todo momento exista firmado un convenio con cláusula de confidencialidad en los más amplios términos; autoridades jurisdiccionales, con la finalidad de dar atención a los requerimientos judiciales que puedan surgir; y autoridades estatales y municipales que soliciten los datos y que los vayan a usar para el ejercicio de sus atribuciones o para fines públicos específicos, sin que pueda usarse para otros distintos. Así, la Secretaría de Fomento y Desarrollo\nEconómico del Estado de Guerrero no realizará ningún tipo de transferencia a un tercero receptor de sus datos personales, salvo en los casos señalados en el párrafo anterior; su trámite puede ser incluido dentro de los informes estadísticos que se elaboren para el seguimiento de avances institucionales del Gobierno del Estado de Guerrero; no obstante, dichos informes serán meramente de carácter estadístico y no incluirán información que permitan identificarle en lo individual.\nFondos de garantías gobierno, e instituciones privadas nacionales e internaciones, para potencializar el financiamiento a las\nMIPYMES, y de acuerdo a las disposiciones normativas aplicables.\nCréditos blandos\nOcasionado por Contingencia COVID-19, el solicitante deberá presentar un escrito libre de solicitud dirigido\nCONTINGENCIA COVID-19 Y SE EMITEN SUS REGLAS\nDE OPERACIÓN PARA EL EJERCICIO FISCAL 2020 a la persona titular de la Secretaría de Fomento y Desarrollo Económico, anexando la documentación descrita anteriormente.\nLa Dirección General de Fomento Empresarial, dictaminará si proceden las solicitudes de créditos blandos, mismas que serán autorizadas por el Comité de Reactivación Económica, y serán otorgados mediante transferencia bancaria o cheque nominativo.\nEl Comité de Reactivación Económica estará integrado de la siguiente manera:\na) La persona titular de la Secretaría de Fomento y Desarrollo Económico, que fungirá como presidente;\nb) La persona titular de la Dirección General de Fomento Empresarial, quien fungirá como secretario;\nc) La persona titular de la Unidad de Asuntos Jurídicos que, adicionalmente, realiza las funciones de Vocal y Coordinador institucional del Comité de Control y Desempeño Institucional (COCODI);\nd) La persona titular de la Delegación Administrativa, y\ne) La persona titular de la Unidad de Planeación y Presupuesto.\nLa documentación comprobatoria de los créditos blandos otorgados, serán el comprobante de depósito bancario o la póliza de cheque, y los documentos establecidos como requisitos en el apartado 6.2 de las presentes Reglas de Operación.\nLos créditos blandos otorgados por el Organismo Público Descentralizado, Fondo de Apoyo a la\nMicro, Pequeña y Mediana Empresa (FAMPEGRO), serán autorizados de acuerdo a la normatividad del propio organismo.\nLa Secretaría de Fomento y Desarrollo Económico y el Organismo Público Descentralizado, Fondo de Apoyo a la Micro, Pequeña y Mediana Empresa (FAMPEGRO), serán los encargados de efectuar la recuperación correspondiente de los créditos blandos otorgados.\nLos recursos recuperados de los créditos blandos otorgados, podrán ser utilizados para el otorgamiento de este tipo de créditos o apoyos económicos. concertación al Organismo Público Descentralizado, Fondo de Apoyo a la Micro, Pequeña y Mediana\nEmpresa (FAMPEGRO), para el otorgamiento de créditos blandos a unidades económicas de la población objetivo y una vez efectuada la recuperación del recurso de los créditos otorgados, lo reintegrará a la compruebe el ejercicio del recurso transferido.\nCONTINGENCIA COVID-19 Y SE EMITEN SUS REGLAS\nDE OPERACIÓN PARA EL EJERCICIO FISCAL 2020\nOcasionado por Contingencia COVID-19, estará sujeto a la suficiencia presupuestal del Fondo de\nFinanciamiento de Inversión Estatal Directa.\nApoyos Económicos\nEn esta categoría del Programa Gubernamental de Garantía para la Reactivación de las PyMES\nOcasionado por Contingencia COVID-19, el solicitante deberá presentar un escrito dirigido a la persona titular de la SEFODECO, anexando la documentación descrita anteriormente.\nLa Dirección General de Fomento Empresarial, dictaminará si proceden las solicitudes de apoyo económico, mismas que serán autorizadas por el Comité de Reactivación Económica, y serán otorgados mediante transferencia bancaria o cheque nominativo.\nLa documentación comprobatoria de los apoyos económicos otorgados, serán el comprobante de depósito bancario o la póliza de cheque, y los documentos establecidos como requisitos en el apartado 6.2 de las presentes Reglas de Operación.\nEl acceso al Programa Gubernamental de Garantía para la Reactivación de las PyMES\nOcasionado por Contingencia COVID-19, estará sujeto a la suficiencia presupuestal del Fondo de\nFinanciamiento de Inversión Estatal Directa.\n6.4. Requisitos de permanencia, causales de baja o suspensión temporal\nLa Secretaría de Fomento y Desarrollo Económico, de acuerdo al listado generado por las acciones realizadas, procederá a dar de baja o suspender temporalmente el apoyo del Programa aquellas personas beneficiarias que:\na) Proporcionen información falsa o alteren algún documento que se establezca como requisito para el trámite de lo solicitado, independientemente de las acciones legales a que se pudiera hacer acreedor; y\nb) Hagan uso indebido de los recursos o beneficios otorgados. de Fomento Empresarial al teléfono 747 47 1 97 00 ext. 9924 o al correo electrónico:\nRené Juárez Cisneros No. 62, Edificio Acapulco, 1er Piso, Col. Ciudad de los Servicios, C.P. 39074, Chilpancingo, Guerrero.\n6.5. Modos de entrega del beneficio\nCONTINGENCIA COVID-19 Y SE EMITEN SUS REGLAS\nDE OPERACIÓN PARA EL EJERCICIO FISCAL 2020\nPyMES Ocasionado por Contingencia COVID-19, se entregarán a través de transferencias bancarias o cheque nominativo.\nPara lo anterior la Secretaría de Fomento y Desarrollo Económico, a través de la Dirección General de Fomento Empresarial y el Fondo de Apoyo a la Micro, Pequeña y Mediana Empresa, entregarán el beneficio de acuerdo a los que lograron acreditar su solicitud, de las que se mencionan a continuación:\n● Programa de Reactivación Económica NAFIN + Estado de Guerrero: el beneficio consiste en el otorgamiento de créditos a las empresas con domicilio en el Estado de Guerrero, mediante el Fondo de Garantías del Gobierno del Estado y Nacional Financiera a través la banca comercial que aprobarán en su caso los créditos correspondientes.\n● Fondos de garantías: En esta modalidad del Programa las unidades económicas recibirán créditos de acuerdo a las características de los fondos de garantías que en su caso suscriba la Secretaría de Fomento y Desarrollo Económico con dependencias y organismos de los tres niveles de gobierno, e instituciones privadas nacionales e internaciones, para potencializar el financiamiento a las MIPYMES.\n● Créditos Blandos: en esta categoría la Secretaría de Fomento y Desarrollo Económico y el\nFondo de Apoyo a la Micro, Pequeña y Mediana Empresa (FAMPEGRO), otorgarán créditos blandos a las unidades económicas con domicilio en el Estado de Guerrero, mediante transferencia bancaria o cheque nominativo.\n● Apoyos Económicos: en esta categoría la Secretaría de Fomento y Desarrollo Económico, otorgará apoyos económicos a las unidades económicas con domicilio en el Estado de Guerrero, mediante transferencia bancaria o cheque nominativo.\nEl otorgamiento de créditos y apoyos económicos de las solicitudes que hayan cumplido en tiempo y forma con los requisitos establecidos en las presentes reglas de operación, estarán condicionados a la disponibilidad presupuestal del Programa Gubernamental de Garantía para la Reactivación de las PyMES\nOcasionado por Contingencia COVID-19.\n7. Procedimientos de instrumentación\n7.1. Operación\nContingencia COVID-19 operará de manera estratégica a nivel estatal en los 81 municipios que lo integran, beneficiando a la población objetivo en alguna de las categorías señaladas.\nSe dará seguimiento y atención a todas las solicitudes del Programa, atendiendo de manera individual cada caso para su respuesta y observaciones pertinentes, dando cumplimiento requisitos descritos.\nCONTINGENCIA COVID-19 Y SE EMITEN SUS REGLAS\nDE OPERACIÓN PARA EL EJERCICIO FISCAL 2020\nGubernamental de Garantía para la Reactivación de las PyMES Ocasionado por Contingencia COVID-19 y la información adicional generada y administrada, se regirá por lo establecido en la Ley Número 207 de\nTransparencia y Acceso a la Información Pública del Estado de Guerrero.\nLa unidad administrativa responsable de la implementación del Programa durante el ejercicio fiscal vigente y por sus facultades correspondientes es la Dirección General de Fomento Empresarial de la\nSecretaría de Fomento y Desarrollo Económico y el Fondo de Apoyo a la Micro, Pequeña y Mediana\nEmpresa (FAMPEGRO).\nLos formatos y trámites son gratuitos para las y los participantes de este Programa.\n7.2. Gastos de operación\nEl presupuesto asignado al Programa Gubernamental de Garantía para la Reactivación de las\nPyMES Ocasionado por Contingencia COVID-19, contempla gastos de operación y podrá aplicarse hasta un 3% de dicho presupuesto, destinados a las diversas acciones asociadas con la planeación, operación, supervisión, contraloría social, evaluación del programa, difusión, publicidad y capacitación.\n8. Transparencia\n8.1. Difusión\nEstas Reglas de Operación, además de su publicación en el Periódico Oficial del Gobierno del\nEstado de Guerrero, estarán disponibles para su consulta en las oficinas de la Secretaría de Fomento y\nDesarrollo Económico, así como en la dirección electrónica oficial de la dependencia: http://www.sefodeco.guerrero.gob.mx.\nA través de los diferentes medios de comunicación, se dará a conocer el Programa Gubernamental de Garantía para la Reactivación de las PyMES ocasionado por Contingencia COVID-19. Así mismo, para mayor información del Programa con el área responsable de llevarlo a cabo es la Dirección General de\nFomento Empresarial, al teléfono 74747197 00 ext. 9924 o a los correos electrónicos:\nCiudad de los Servicios, C.P. 39074, Chilpancingo, Guerrero.\nLa papelería, documentación oficial, así como la publicidad y promoción del Programa\nGubernamental de Garantía para la Reactivación de las PyMES Ocasionado por Contingencia COVID-19, deberán incluir la leyenda descrita en el apartado de “Blindaje Electoral”.\nCONTINGENCIA COVID-19 Y SE EMITEN SUS REGLAS\nDE OPERACIÓN PARA EL EJERCICIO FISCAL 2020\n8.2. Blindaje electoral\nGarantía para la Reactivación de las PyMES Ocasionado por Contingencia COVID-19, deberán observar y atender las medidas que emita la Secretaría de Contraloría y Transparencia Gubernamental, para coadyuvar a que éstos, no sean utilizados con fines políticos en el desarrollo de procesos electorales federales, estatales y municipales.\nComo estrategia de blindaje electoral, la papelería, documentación oficial, así como la publicidad y promoción del Programa deberán incluir la siguiente leyenda:\n“Este Programa es de carácter público, no es patrocinado ni promovido por partido político alguno y sus recursos provienen de los impuestos que pagan todos los contribuyentes. Está prohibido el uso de este programa con fines políticos, electorales, de lucro y otros distintos a los establecidos. Quien haga uso indebido de los recursos de este programa deberá ser denunciado y sancionado de acuerdo con la ley aplicable y ante la autoridad competente”.\nEn cuanto a la publicidad en medios electrónicos, impresos, complementarios o de cualquier otra índole, vinculados con los programas de comunicación social, se deberá incluir la siguiente leyenda:\n“Este Programa es público y queda prohibido su uso con fines partidistas o de promoción personal”.\n8.3. Supervisión y control\nEl área responsable del Programa, realizará el trámite de apoyos y créditos económicos, verificando el cumplimiento de los objetivos planteados reportando de manera mensual a la Unidad de\nPlaneación y Presupuesto de la Secretaría de Fomento y Desarrollo Económico, las acciones ejercidas y los resultados obtenidos, quien a su vez reportará a la Secretaría Planeación y Desarrollo Regional, el avance de cada acción que se realice en el Programa, determinando el avance y las metas planteadas en el Programa Operativo Anual del año fiscal en curso.\nEnviar trimestralmente a la Secretaría de Finanzas y Administración, a la Secretaría de Planeación presupuesto ejercido establecidos por el Consejo Nacional de Armonización Contable (CONAC) y con base en los indicadores de resultados previstos en las Reglas de Operación. Dichos informes se deberán presentar a más tardar a los quince días hábiles posteriores a la terminación de cada trimestre. Así mismo remitir el calendario de la dispersión de los recursos de manera mensual en conjunto con los indicadores.\n8.4. Mecanismos de evaluación e indicadores\n8.4.1. Evaluación\nCONTINGENCIA COVID-19 Y SE EMITEN SUS REGLAS\nDE OPERACIÓN PARA EL EJERCICIO FISCAL 2020\nLa evaluación interna del Programa, la hará la Secretaría de Fomento y Desarrollo Económico, cobertura en la entidad, para conocer el cumplimiento del Programa y sus metas.\nEl instrumento de medición de evaluación del Programa se realizará mediante los indicadores, los cuales serán reportados a la Unidad de Planeación y Presupuesto para la integración de los informes correspondientes.\nLa persona titular de la SEFODECO con el área de Planeación y las áreas involucradas en la operación del Programa, se reunirán de manera mensual, a efecto de evaluar los resultados e indicadores del mismo, identificando aciertos, fortalezas, posibles problemas y soluciones, informando de manera oportuna, para la aprobación de propuestas y alternativas de solución a la problemática expuesta para mejoría del Programa en su ejecución y los resultados conforme a las metas y objetivos planteados.\n8.4.2. Indicadores\nSe realizará la Matriz de Indicadores siguiendo la Metodología del Marco Lógico. Se desarrollará en el proceso de ejecución del Programa y se remitirá a la Secretaría de Planeación y Desarrollo Regional.\nPara el seguimiento y evaluación del Programa Gubernamental de Garantía para la Reactivación de las\nPyMES Ocasionado por Contingencia COVID-19, se utilizarán los indicadores que corresponden al nivel de propósito, detallado a continuación:\nNombre del Unidad de Frecuencia de\nFormula\nIndicador Medida medición\nCrédito NAFIN +\nCrédito otorgado Crédito Anual\nEstado de Guerrero\nCréditos de Fondos\nCrédito otorgado Crédito Anual de Garantía\nCréditos Blandos Créditos otorgado Crédito Anual\nApoyo económico\nLa Dirección General de Fomento Empresarial, será responsable de compilar e integrar un reporte de resultados tomando como base las acciones desarrolladas por el Programa, que indique el número de personas beneficiarias atendidas al finalizar el ejercicio fiscal.\n8.5. Auditoría\nEl ejercicio del recurso y la operatividad del Programa, están sujetos a las disposiciones estatales aplicables y podrá ser auditado por la Secretaría de Contraloría y Transparencia Gubernamental, así como\nCONTINGENCIA COVID-19 Y SE EMITEN SUS REGLAS\nDE OPERACIÓN PARA EL EJERCICIO FISCAL 2020 por la Auditoría Superior del Estado, conforme a la legislación vigente y en el ámbito de sus respectivas competencias.\nLa Secretaría de Fomento y Desarrollo Económico, dará todas las facilidades a dichas instancias para realizar en el momento en que lo juzguen pertinente, las auditorías que consideren necesarias; así como el seguimiento y la solventación a las observaciones planteadas por los órganos de control.\n8.6. Recursos no devengados\nLa Secretaría de Fomento y Desarrollo Económico deberá reintegrar a la Secretaría de Finanzas y Administración del Gobierno del Estado, los recursos no devengados al 31 de diciembre del ejercicio fiscal correspondiente.\n8.7. Contraloría social\nLa Secretaría de Fomento y Desarrollo Económico, será responsable de la supervisión directa del\nPrograma Gubernamental de Garantía para la Reactivación de las PyMES Ocasionado por Contingencia\nCOVID-19, así como de verificar que, en su ejecución, se cumpla con la normatividad aplicable.\nEs importante mencionar que, si las condiciones del semáforo epidemiológico del Sistema de\nAlerta Sanitaria lo permiten, se podrán integrar las actividades de Contraloría Social, en la medida de lo humanamente posible y por los medios disponibles.\nAsimismo, para cualquier queja, comentario o sugerencia, las personas interesadas podrán acudir a la Secretaría de Fomento y Desarrollo Económico o a la Secretaría de la Contraloría y Transparencia\nGubernamental.\nLos objetivos específicos de este Órgano de Contraloría Social son:\n• Hacer más transparentes las decisiones y la ejecución de los recursos.\n• Verificar la correcta entrega de créditos y apoyos.\n• Fomentar la organización social.\n• Inhibir los actos de corrupción y de cooptación social, política y electoral.\n• Incrementar la eficiencia de los recursos públicos.\n• Fortalecer la cultura de la legalidad.\n• Mejorar la rendición de cuentas.\n• Perfeccionar la democracia e incorporar la evaluación ciudadana.\n8.8. Formas de participación social\nDe acuerdo a lo establecido por la Ley Número 684 de Participación Ciudadana del Estado Libre implementación y evaluación de los programas y acciones de desarrollo social; para lo cual la población\nCONTINGENCIA COVID-19 Y SE EMITEN SUS REGLAS\nDE OPERACIÓN PARA EL EJERCICIO FISCAL 2020\nOcasionado por Contingencia COVID-19, mediante grupos organizados entre ellos, apoyarán en su implementación, decidiendo entre la población objetivo la mejor implementación de aplicación de los recursos utilizados para los programas, organizando mediante reuniones de trabajos y/o comisiones establecidas por ellos.\nEtapa en la que Forma de\nParticipante Modalidad participa Participación\nPlaneación, Integración de los Información y\nMIPYMES programación listados decisión\na) Integración\nLos comités de contraloría social, se conforman con la representación de la comunidad beneficiada por el Programa, y fungirán como interlocutores con la Secretaría de Fomento y Desarrollo Económico, en el ejercicio de la contraloría social.\nEl vocal del Comité de Contraloría Social será, el responsable de hacer llegar las quejas o denuncias recibidas a la Secretaría de Fomento y Desarrollo Económico, quien dará respuesta en un plazo no mayor de 15 días a partir de la fecha de recepción de la queja o denuncia.\nb) Capacitación y asesoría\nPara impulsar la realización de las actividades de contraloría social se brindará capacitación y asesoría, a las servidoras y servidores públicos que intervienen en la operación del Programa aquí descrito en estas Reglas de Operación para que estos realicen adecuadamente sus actividades de seguimiento y vigilancia.\nc) Seguimiento\nSe deberá integrar un Programa de Trabajo a través del cual se debe incluir la descripción de las actividades, responsables, metas y calendarización de las actividades para su cumplimiento.\nEl Director General Fomento Empresarial, será el encargado de conformar los comités de contraloría social, asimismo darán acompañamiento durante las actividades de control, seguimiento y\nOcasionado por Contingencia COVID-19.\nEl Comité de Contraloría Social debe estar constituido por una presidencia, una secretaría y una vocalía mínimamente, electos de entre la población objetivo beneficiada, en donde se aplicó el Programa.\nEl Comité de Contraloría Social deberá controlar, vigilar y dar seguimiento al Programa a través de los formatos que integran el expediente:\nCONTINGENCIA COVID-19 Y SE EMITEN SUS REGLAS\nDE OPERACIÓN PARA EL EJERCICIO FISCAL 2020\n1. Acta de Conformación del Comité de Contraloría Social.\n2. Reunión con beneficiarias y beneficiarios.\n3. Ficha Informativa del Programa.\n4. Quejas, Denuncias o Reconocimientos.\n5. Informe Anual.\n8.9. Procedimiento de queja o inconformidad ciudadana\nLas personas beneficiarias pueden presentar quejas y denuncias ante las instancias correspondientes sobre cualquier hecho, acto u omisión que produzca o pueda producir daños al ejercicio de sus derechos establecidos en las presentes Reglas de Operación o contravengan sus disposiciones y de la demás normatividad aplicable. a. En la Secretaría de Fomento y Desarrollo Económico\nTeléfonos: (747) 47 1 98 28 o 01 747 47 1 97 00 EXT. 9924\nCorreo electrónico: mipymes.sefodeco@guerrero.gob.mx\nDomicilio: Palacio de Gobierno del Estado de Guerrero, Edificio Acapulco, Primer Piso. Boulevard\nRené Juárez Cisneros No. 62, Col. Ciudad de los Servicios. Chilpancingo, Guerrero. C.P. 39074. b. En la Secretaría de Contraloría y Transparencia Gubernamental\nCorreo electrónico: contraloria@guerrero.gob.mx\nDomicilio: Palacio de Gobierno Primer Piso Edificio Norte, Primer Piso.\nBoulevard René Juárez Cisneros No. 62, Col. Ciudad de los\nServicios. Chilpancingo, Guerrero. C.P. 39074.\nLas quejas y denuncias de la ciudadanía derivadas de alguna irregularidad en la operación del\nPrograma Gubernamental de Garantía para la Reactivación de las PyMES Ocasionado por Contingencia\nCOVID-19, podrán presentarse por escrito, por comparecencia de la persona beneficiaria, por correo electrónico o vía telefónica y deberá proporcionar los siguientes datos:\n• Nombre de la servidora o servidor público.\n• Área de adscripción.\n• Objeto de la denuncia.\n• Nombre y domicilio de la persona quejosa.\n• Identificación oficial.\n8.10. Mecanismos de exigibilidad\nA través de la página de la Secretaría de Fomento y Desarrollo Económico, del Programa.\nCONTINGENCIA COVID-19 Y SE EMITEN SUS REGLAS\nDE OPERACIÓN PARA EL EJERCICIO FISCAL 2020 violación de los mismos pueden ocurrir en al menos los siguientes casos:\n• Cuando una persona solicitante cumpla con los requisitos y criterios de inclusión para acceder a determinado derecho y exija a la autoridad administrativa ser derechohabiente del mismo. Cuando la persona derechohabiente de un programa social exija a la autoridad que se cumpla con dicho derecho de manera integral en tiempo y forma, como lo establece el Programa.\n• Cuando no se pueda satisfacer toda la demanda de incorporación a un programa por restricción presupuestal, y estas exijan que las incorporaciones sean claras, transparentes, equitativas, sin favoritismos, ni discriminación.\nSerá la Secretaría de Contraloría y Transparencia Gubernamental del Gobierno del Estado de\nGuerrero, quién atenderá las denuncias de violación e incumplimiento de derechos en materia de desarrollo social.\n8.11. Acta de entrega-recepción (Anexo C)\nLa instancia ejecutora conformará y resguardará los expedientes que se generen de los\nProgramas de Fomento y Desarrollo Económico, dada la naturaleza del beneficio otorgado, en apego al control del gasto público.\n9. Criterios de selección y elegibilidad\n9.1. Método de selección de personas beneficiarias\nSerán beneficiados con el Programa, los solicitantes que presenten los requisitos descritos en la presente Reglas de Operación, así como los que se verifique que requieren algún apoyo económico.\n10. Mecánica de operación\n10.1. Instancia ejecutora\nDirección General de Fomento Empresarial y el Fondo de Apoyo a la Micro, Pequeña y Mediana Empresa\n(FAMPEGRO).\n10.2. Instancia administrativa y/o normativa\nCon el objeto de asegurar la aplicación eficiente, eficaz, oportuna, equitativa y transparente de los recursos públicos, la Secretaría de Finanzas y Administración y la Secretaría de Planeación y Desarrollo\nRegional, emitirán las disposiciones a que deberán sujetarse los programas de inversión sujetos a reglas de operación.\nCONTINGENCIA COVID-19 Y SE EMITEN SUS REGLAS\nDE OPERACIÓN PARA EL EJERCICIO FISCAL 2020\nLa Secretaría de Fomento y Desarrollo Económico, será la instancia ejecutora del Programa\nGubernamental de Garantía para la Reactivación de las PyMES Ocasionado por Contingencia COVID19, así mismo turnará a las instancias correspondientes las presentes Reglas de Operación con el objeto de ser aprobadas, corregidas o modificadas según sea el caso.\nLa Secretaría de Planeación y Desarrollo Regional, será la encargada de validar y aprobar las\nReglas de Operación de la Secretaría de Fomento y Desarrollo Económico, las correcciones o modificaciones según sea el caso, acorde las disposiciones que establezcan la Secretaría de Finanzas y\nAdministración y la Secretaría de Planeación y Desarrollo Regional.\nLa Secretaría de Finanzas y Administración, será la encargada de otorgar las ministraciones presupuestales acorde al presupuesto aprobado y la normatividad aplicable vigente.\nUna vez aprobadas las Reglas de Operación del Programa Gubernamental de Garantía para la\nReactivación de las PyMES Ocasionado por Contingencia COVID-19, serán turnadas al Periódico Oficial del Gobierno del Estado, para su publicación; dichas Reglas de Operación, estarán a disposición de la población en general en las oficinas de la dependencia y a través de su página web http://sefodeco.guerrero.gob.mx.\nLas instancias administrativas y normativas serán la Secretaría de Fomento y Desarrollo\nEconómico y la Secretaría Contraloría y Transparencia Gubernamental, en el ámbito de sus respectivas competencias, quienes darán seguimiento a los objetivos y metas del Programa.\n10.3. Delimitación de atribuciones\nSon atribuciones de la Secretaría de Fomento y Desarrollo Económico para el buen manejo y ejercicio de los recursos del Programa Gubernamental de Garantía para la Reactivación de las PyMES\nOcasionado por Contingencia COVID-19, las siguientes:\n● Organizar, dirigir y coordinar la operación del Programa, así como, los tiempos y modos de aplicación a la ´población objetivo.\n● Propiciar el cumplimiento de las metas, acciones y objetivos programados.\n● Instalación de los comités de contraloría social, así como la capacitación de sus integrantes.\n● Conformar el listado de personas beneficiarias del Programa.\n● Solicitar ante las instancias competentes la liberación de los recursos del Programa.\n● Integración de informes financieros y comprobación de los recursos ejercidos del Programa.\n● Realizar acciones de seguimiento, evaluación y monitoreo de las actividades que desarrolla el\nPrograma.\nPrograma y las acciones no se contrapongan, afecten o presenten duplicidades con otros programas o\nCONTINGENCIA COVID-19 Y SE EMITEN SUS REGLAS\nDE OPERACIÓN PARA EL EJERCICIO FISCAL 2020 acciones del gobierno estatal; la coordinación institucional y vinculación de acciones busca potenciar el impacto de los recursos, fortalecer la cobertura de las acciones, detonar la complementariedad y reducir gastos administrativos.\n11. Derechos, obligaciones y sanciones de las personas beneficiarias del programa\n11.1. Derechos\n● Información necesaria de manera clara y oportuna, para participar en el Programa.\n● Recibir trato digno, respetuoso y equitativo sin discriminación alguna, por el personal de las distintas áreas que participen dentro del Programa.\n● Reserva y privacidad de la información personal.\n● Acceder a la información necesaria del Programa, sus Reglas de Operación, recursos y cobertura.\n● Solicitar y recibir información sobre el estado que guarda su trámite o servicio.\n● Recibir los servicios y prestación del Programa conforme a las Reglas de Operación.\n● Seguridad sobre la reserva y privacidad de su información personal conforme a la Ley Número\n207 de Transparencia y Acceso a la Información Pública del Estado de Guerrero.\n11.2. Obligaciones\nLas personas beneficiarias del Programa Gubernamental de Garantía para la Reactivación de las\nPyMES Ocasionado por Contingencia COVID-19, tendrán las obligaciones siguientes:\n● Proporcionar la información que se les requiera de acuerdo a lo establecido en las presentes\nReglas de Operación.\n● Presentar quejas o inconformidades ante la Secretaría de Fomento y Desarrollo Económico, Programa.\n● Ser respetuoso del Programa, conducirse con respeto con cada uno de los participantes y autoridades involucradas, sujetarse y cumplir con cada una de las disposiciones legales que la normatividad establezca para con las personas beneficiarias.\n11.3. Sanciones\nCONTINGENCIA COVID-19 Y SE EMITEN SUS REGLAS\nDE OPERACIÓN PARA EL EJERCICIO FISCAL 2020 acceder a los beneficios que a través de este se otorga, perderán las prerrogativas que dichas disposiciones establezcan.\nLas personas beneficiarias que no se sujeten a la legalidad, al cumplimiento de estas Reglas de\nOperación, al respeto de los directivos, colaboradores y demás participantes del Programa, que agredan funcionarias públicas encargadas del buen desarrollo de este Programa en mención, podrán ser sancionadas o excluidas de manera definitiva en su participación y del acceso a los mismos.\n12. Interpretación\nEstas Reglas de Operación para sus efectos administrativos, estarán a cargo de la Secretaría de\nFomento y Desarrollo Económico, la Secretaría de Planeación y Desarrollo Regional, así como de la\nCONTINGENCIA COVID-19 Y SE EMITEN SUS REGLAS\nDE OPERACIÓN PARA EL EJERCICIO FISCAL 2020\nCONTINGENCIA COVID-19 Y SE EMITEN SUS REGLAS\nDE OPERACIÓN PARA EL EJERCICIO FISCAL 2020\nCONTINGENCIA COVID-19 Y SE EMITEN SUS REGLAS\nDE OPERACIÓN PARA EL EJERCICIO FISCAL 2020\nCONTINGENCIA COVID-19 Y SE EMITEN SUS REGLAS\nDE OPERACIÓN PARA EL EJERCICIO FISCAL 2020\nGuerrero.\nSegundo. Se abrogan todas las disposiciones que contravengan las presentes Reglas de\nOperación del Programa Gubernamental de Garantía para la Reactivación de las PyMES Ocasionado por\nContingencia COVID-19.\nTercero. A partir de la entrada en vigor del presente Acuerdo, las Reglas de Operación del\nPrograma Gubernamental de Garantía para la Reactivación de las PyMES Ocasionado por Contingencia\nCOVID-19, subsecuentes o sus modificaciones serán emitidos por la persona titular de la Secretaría de\nFomento y Desarrollo Económico.\nDado en la oficina del titular del Poder Ejecutivo, ubicada en el Edificio Centro de Palacio de\nGobierno, Boulevard René Juárez Cisneros No. 62, Ciudad de los Servicios en la ciudad de Chilpancingo de los Bravo, Capital del Estado de Guerrero, a los dos días del mes de abril de dos mil veinte.\nEL GOBERNADOR CONSTITUCIONAL DEL ESTADO DE GUERRERO.\nLIC. HÉCTOR ANTONIO ASTUDILLO FLORES.\nRúbrica.\nEL SECRETARIO GENERAL DEGOBIERNO.\nLIC. FLORENCIO SALAZAR ADAME.\nRúbrica.\nEL SECRETARIO DE FOMENTO Y DESARROLLO ECONÓMICO.\nLAE. ÁLVARO BURGOS BARRERA.\nRúbrica.",
  "ordenamiento": "REGLA",
  "jurisdiccion": "GUERRERO",
  "fuente_oficial": "DIARIO OFICIAL DE LA FEDERACION",
  "Fecha de Publicación": "14 DE MAYO DE 2021",
  "ULTIMA REFORMA PUBLICADA": null,
  "status": "VIGENTE",
  "es_escaneado": false,
  "tiene_tablas": true,
  "materia": [
    "económico"
  ]
}