{
  "titulo": "Acuerdo por el Que Se Emiten las Reglas de Operación del Programa Casa Digna Guerrero Cumple para el 1",
  "Contenido": "1. Introducción.............................................................................................................................. 7\n2. Objetivo..................................................................................................................................... 8\n2.1. Objetivo general..................................................................................................................... 8\n2.2. Objetivos Específicos............................................................................................................. 9\n2.3. Población Objetivo................................................................................................................. 9\n3. Misión....................................................................................................................................... 9\n4. Visión........................................................................................................................................ 10\n5. Reglas de Operatividad............................................................................................................. 10\n5.1. Lineamientos Generales........................................................................................................ 10\n5.1.1. Para ingresar al programa................................................................................................... 10\n5.2.1. Cantidad máxima que pueden adquirir................................................................................ 10\n5.1.3. Presupuesto de inversión del 2013..................................................................... 11\n5.1.4. Perspectiva de Género........................................................................................................ 11\n5.1.4. Fundamento Legal.............................................................................................................. 11\n5.1.5. Participantes....................................................................................................................... 12\n5.1. 6. Patrimonio del programa................................................................................................... 12\n5.1.7. Tipos de apoyo................................................................................................................... 12\n6. Información del programa......................................................................................................... 13\n6.1. De los proyectos.................................................................................................................... 13\n6.2. Exposición del programa........................................................................................................ 13\n6.3. Cobertura............................................................................................................................... 13\n6.4. Modo de entrega del beneficio............................................................................................... 13\n6.5. Criterios y requisitos de elegibilidad....................................................................................... 14\n6.6. Gastos de Operación............................................................................................................. 17\n7. Transparencia........................................................................................................................... 17\n7.1. Difusión.................................................................................................................................. 17\n7.2. Seguimiento de avances físicos y financieros........................................................................ 17\n7.3. Evaluación............................................................................................................................. 18\n7.3.1. Evaluación Interna.............................................................................................................. 18\n7.3.2. Evaluación Externa............................................................................................................. 18\n7.4. Indicadores............................................................................................................................ 18\n7.5. Auditoria................................................................................................................................ 18\n7.6. Recursos no devengados....................................................................................................... 19\n7.7. Blindaje electoral.................................................................................................................... 19\n7.8. Contraloría social................................................................................................................... 19\n7.9. Integración de los Comités..................................................................................................... 20\n7.10. Capacitación y Asesoría....................................................................................................... 20\n7.11. Seguimiento........................................................................................................................ 20\n7.12. Quejas y denuncias.............................................................................................................. 21\n8. Criterios de selección y elegibilidad.......................................................................................... 21\n9. Mecánica operativa................................................................................................................... 21\n9.1. Instancia Ejecutora................................................................................................................. 21\n9.2. Instancia Administrativa o normativa...................................................................................... 22\n9.3. Delimitación de atribuciones.................................................................................................. 22\n10. Derechos, obligaciones y sanciones de los beneficiarios........................................................ 22\n10.1. Derechos............................................................................................................................. 22\n10.2. Obligaciones........................................................................................................................ 22\n10.3. Sanciones............................................................................................................................ 23\n11. Cierre de Ejercicio................................................................................................................... 23\n12. Casos de Excepción............................................................................................................... 23\n13. Anexos.................................................................................................................................... 23\n13.1. Anexo 1. Glosario de Términos............................................................................................ 23\n13. 2. Anexo 2............................................................................................................................... 25\n13.4. Anexo 3................................................................................................................................ 26\n13. 5 Anexo 4................................................................................................................................ 27\n13.5. Anexo 5................................................................................................................................ 28\n13.6. Anexo 6................................................................................................................................ 29\n13.8. Anexo 7................................................................................................................................ 30\n13.9. Anexo 8................................................................................................................................ 31\n13.10. Anexo 9.............................................................................................................................. 32\n13.11. Anexo 10............................................................................................................................ 33\n13.12. Anexo 11............................................................................................................................ 37\n13.13. Anexo 12............................................................................................................................ 38\n13.13. Anexo 13............................................................................................................................ 39\nPARA EL EJERCICIO FISCAL 2014, PUBLICADO EN EL PERIÓDICO OFICIAL No. 58, EL 22 DE JULIO\nDE 2014.\nTEXTO ORIGINAL.\nAcuerdo publicado en el Periódico Oficial del Gobierno del Estado de Guerrero No 42 Alcance I, el Viernes 24 de Mayo de 2013.\nACUERDO POR EL QUE SE EMITEN LAS REGLAS DE OPERACIÓN DEL PROGRAMA CASA DIGNA\n\"GUERRERO CUMPLE\" PARA EL EJERCICIO FISCAL 2013.\nBeatriz Mojica Morga, Secretaría de Desarrollo Social, con fundamento en los artículos 117 de la\nOrgánica de la Administración Pública del Estado de Guerrero Número 433; lo., 2o., 3o., y 6o de la Ley\nNúmero 102 para el Desarrollo Social del Estado de Guerrero; lo., 2o fracción I, 18, 25, de la Ley Número\n454 de Presupuesto y Disciplina Fiscal del Estado de Guerrero; así como las estrategias y objetivos establecidos en el Plan Estatal de Desarrollo de Guerrero 2011-2015; y\nCONSIDERANDO\nQue las reglas de Operación establecen disposiciones a las que deben sujetarse los programas\nEstatales, con el objeto de otorgar transparencia y asegurar la aplicación eficiente, eficaz, oportuna y equitativa de los recursos públicos asignados al mismo.\nQue el marco de la ley Número 454 de presupuesto y Disciplina Fiscal del Estado de Guerrero y el Acuerdo emitido por el titular del Ejecutivo del Estado, el primero d abril del año 2011, se establecen los Lineamientos generales de legalidad, honestidad, eficiencia, eficacia, economía, racionalidad, austeridad, transparencia, control, rendición de cuentas, equidad de género e impacto social en grupos vulnerables y en la sociedad en general del gasto de la Administración Pública Estatal, para fortalecer el desarrollo, estableciendo como una estrategia el Programa; Casa Digna (Guerrero Cumple)\nQue bajo dicho contexto la Secretaría de Desarrollo Social del Estado de Guerrero, a través de la Dirección General De Gestión Social, será responsable de emitir las Reglas de Operación respecto al programa, para que inicie su operación en el ejercicio fiscal siguiente o en su caso, las modificaciones a aquéllas que continúen vigentes;\nÚNICO.- Se emiten las Reglas de Operación del Programa Casa Digna “Guerrero Cumple” para\nTRANSITORIOS\nPRIMERO.- El presente Acuerdo entrara al día siguiente de su publicación en el periódico Oficial del Estado.\nSEGUNDO.- Queda abrogado el Acuerdo por el que se emiten las Reglas de Operación del\nPrograma \"Casa Digna, Guerrero Cumple\" para el Ejercicio Fiscal 2012, publicado en el Diario Oficial del\nEstado de Guerrero el 24 de Febrero de 2012.\nDado en la Ciudad de Chilpancingo de los Bravo, Guerrero, a los veintidós días del mes de diciembre de 2012.\nSECRETARIA DE DESARROLLO SOCIAL.\nMTRA. BEATRIZ MOJICA MORGA.\nRúbrica.\nCP. LEODEGARIO YAÑEZ CRUZ.\nDIRECTOR GENERAL DE GESTIÓN SOCIAL.\nRúbrica.\nDIRECTOR DE LA UNIDAD DE ASUNTOS JURÍDICOS.\nLIC. FIDELMAR FLORES MÉNDEZ.\nRúbrica.\nContenido\n1. Introducción\n2. Objetivos\n2.1. Objetivo general\n2.2. Objetivo Específico\n2.3. Población Objetivo\nLos Materiales de bajo costo que se pueden adquirir:\n3. Misión\n4. Visión\n5. Reglas de Operatividad\n5.1. Lineamientos Generales\n5.1.1. Para ingresar al programa\n5.1.2. Cantidad máxima que pueden adquirir:\n5.1.4. Perspectiva de Género\n5.1.4. Fundamento Legal\n5.1.5. Participantes\n5.1.6. Patrimonio del programa\n5.1.7. Tipos de apoyo\n6. Información del programa\n6.1. De los proyectos\n6.2. Exposición del programa\n6.3. Cobertura\n6.4. Modo de entrega del beneficio\n6.5. Criterios y requisitos de elegibilidad\n6.6. Gastos de Operación\n7. Transparencia\n7.1. Difusión\n7.2. Seguimiento de avances físicos y financieros\n7.3. Evaluación\n7.3.1. Evaluación Interna\n7.3.2. Evaluación Externa\n7.4. Indicadores\n7.5. Auditoria\n7.6. Recursos no devengados\n7.7. Blindaje electoral\n7.8. Contraloría social\n7.9. Integración de los Comités\n7.10. Capacitación y Asesoría.\n7.11. Seguimiento\n7.12. Quejas y denuncias\n8. Criterios de selección y elegibilidad\n9. Mecánica operativa\n9.1. Instancia Ejecutora\n9.2. Instancia Administrativa o normativa\n9.3. Delimitación de atribuciones\n10. Derechos, obligaciones y sanciones de los beneficiarios\n10.1. Derechos\n10.2. Obligaciones\n10.3. Sanciones\n11. Cierre de Ejercicio\n12. Casos de Excepción\n13. Anexos\n13.1. Anexo 1. Glosario de Términos\n13.2. Anexo 2.\n13.3. Anexo 3.\n13.4. Anexo 4.\n13.5. Anexo 5\n13.6. Anexo 6\n13.7. Anexo 7\n13.8. Anexo 8\n13.9. Anexo 9\n13.10.Anexo 10\n13.11.Anexo 11\n13.12.Anexo 12\n12.13.Anexo 13\n1. Introducción\nLa constitución Política de los Estados Unidos Mexicanos en su artículo 4o, párrafo quinto, confiere a toda familia el derecho de disfrutar de una vivienda digna y decorosa.\nCon la finalidad de reducir la pobreza y contribuir a la igualdad de oportunidades para que todos los mexicanos mejoren su calidad de vida mediante el acceso a materiales de bajo costo para mejorar su vivienda, que de acuerdo al Presupuesto de Egresos del Estado de Guerrero para el ejercicio fiscal 2013, la política de gasto público se orienta al fortalecimiento de vivienda a hogares de menores ingresos económicos, mediante la aportación de materiales de construcción a bajo costo.\nAsimismo, se autoriza a la dependencia, bajo su responsabilidad a la adecuación a su respectivo presupuesto siempre y cuando éste se realice para permitir un mejor cumplimiento de los objetivos del programa autorizado a su cargo.\nLa Secretaría de Desarrollo Social, es parte imprescindible para el desarrollo social en beneficio de la población guerrerense, implementar acciones tendientes a contribuir a disminuir la pobreza patrimonial, siendo la directriz más importante en este rubro, por ello, como parte estratégica de combate a la pobreza, se estableció el Programa Casa Digna \"Guerrero Cumple\".\nAsimismo, en el Marco del Plan Estatal de Desarrollo 2011 -2015 en el programa contribuye en las estrategias:\nEstrategia 1.1.1 Ampliar la cobertura de programas sociales.\nEstrategia 1.1.2 Incrementar el acceso a servicios públicos básicos: agua potable, drenaje o fosas sépticas y electricidad.\nEstrategia 1.1.3 Adecuar los programas federales y estatales de combate a la pobreza, a las características de las regiones del Estado.\nEstrategia 1.1.4 Constituir comités de desarrollo comunitario de participación ciudadana, los cuales determinen planes comunitarios a largo plazo que atiendan los aspectos productivo, social, salud, educación y ambiental.\nEstrategia 1.1.5 Focalizar las acciones de gobierno en la atención a grupos vulnerables, así como a municipios con mayores rezagos.\nEstrategia 1.1.6 Generar políticas específicas de desarrollo, considerando el contexto territorial, histórico y social.\nCumpliendo con lo que establece el Plan Estatal de Desarrollo, se busca mejorar la calidad de vida, generar arraigo de la población en sus respectivas localidades prioritariamente la población en condiciones de pobreza patrimonial.\nEl Programa Casa Digna \"Guerrero cumple\", se aplica a los principios de equidad e inclusión social, de tal forma que toda persona en condiciones de pobreza en sus diferentes niveles de los 81 municipios del Estado de Guerrero, puedan acceder a los materiales de vivienda de bajo costo.\nAtendiendo que de acuerdo a la información emitida por el Consejo Nacional de Población en\n2009, para el año 2030 la población urbana representará el 76.2 por ciento de la población total del País.\nDe ahí la consideración de que México se encuentre en un acelerado proceso de urbanización, y en lo tocante al Estado de Guerrero, es la misma tendencia, pero marcado por un bajo valor o escasa infraestructura adecuada para la convivencia familiar.\nAunado a que de acuerdo al Consejo Nacional de Evaluación de la Política de Desarrollo Social\n(CONEVAL) la población guerrerense presenta las siguientes características:\n{\"tabla_1\":{\"columnas\":[\"TIPO DE CARENCIA\",\"(sin encabezado)\",\"% en\",\"(sin encabezado)\",\"(sin encabezado)\",\"% en\",\"(sin encabezado)\"],\"filas\":[{\"columna_1\":\"(sin dato)\",\"columna_2\":\"(sin dato)\",\"columna_3\":\"2000\",\"columna_4\":\"(sin dato)\",\"columna_5\":\"(sin dato)\",\"columna_6\":\"2010\",\"columna_7\":\"(sin dato)\"},{\"columna_1\":\"Carencia en la calidad y espacios de\\nla vivienda\",\"columna_2\":\"59.6\",\"columna_3\":\"(sin dato)\",\"columna_4\":\"(sin dato)\",\"columna_5\":\"41.8\",\"columna_6\":\"(sin dato)\",\"columna_7\":\"(sin dato)\"},{\"columna_1\":\"Carencia por material de pisos\",\"columna_2\":\"40.0\",\"columna_3\":\"(sin dato)\",\"columna_4\":\"(sin dato)\",\"columna_5\":\"18.1\",\"columna_6\":\"(sin dato)\",\"columna_7\":\"(sin dato)\"},{\"columna_1\":\"Carencia por material de muros\",\"columna_2\":\"10.5\",\"columna_3\":\"(sin dato)\",\"columna_4\":\"(sin dato)\",\"columna_5\":\"5.7\",\"columna_6\":\"(sin dato)\",\"columna_7\":\"(sin dato)\"},{\"columna_1\":\"Carencia por material de techos\",\"columna_2\":\"20.9\",\"columna_3\":\"(sin dato)\",\"columna_4\":\"(sin dato)\",\"columna_5\":\"11.6\",\"columna_6\":\"(sin dato)\",\"columna_7\":\"(sin dato)\"},{\"columna_1\":\"Carencia por hacinamiento\",\"columna_2\":\"41.4\",\"columna_3\":\"(sin dato)\",\"columna_4\":\"(sin dato)\",\"columna_5\":\"29.4\",\"columna_6\":\"(sin dato)\",\"columna_7\":\"(sin dato)\"}]}}\nCifras que demuestran la variedad de necesidades de la población en cuanto a infraestructura de vivienda, y, lo que es preocupante para la administración pública estatal, que el CONEVAL, señale que\nGuerrero, se encuentra entre las entidades con mayor incidencia de pobreza multidimensional, con un\n68.1 por ciento y 3.4 carencias en promedio. Entendida las carencias como las de acceso a la seguridad social, acceso a los servicios de salud, rezago educativo, acceso a la alimentación, servicios en la vivienda y, calidad y espacios de la vivienda, acceso a tecnologías de la información y comunicación.\n2. Objetivos\n2.1. Objetivo general\nContribuir a disminuir el rezago de vivienda en situación de vulnerabilidad, en condiciones precarias en las que habitan una gran parte de la población guerrerense, a través del mejoramiento de la misma con el acceso de materiales de construcción a bajo costo y de calidad, fortaleciendo el patrimonio de la población, motivando la organización y participación social e incidiendo en el mejoramiento del entorno urbano y rural del Estado de Guerrero.\n2.2. Objetivo Específico viviendas de los guerrerenses.\n2.3. Población Objetivo\nEste programa es de cobertura estatal, dando prioridad a hogares del Estado de Guerrero en situación de pobreza con ingresos por debajo de la línea de bienestar y con carencia por calidad y espacios de la vivienda que requieran mejorar las condiciones habitacionales.\na) El Programa tendrá cobertura en todo el Estado de Guerrero, con una visión de mejoramiento de la infraestructura urbana, marginada y rural.\nb) El beneficio a la población por parte de la Secretaría de Desarrollo Social, será el subsidio sobre los costos reales de material de construcción, como: lámina, cemento, tinaco y pintura, construcción de baños ecológicos, estufas ecológicas y el mejoramiento de la vivienda.\nc) Los recursos del programa de Casa Digna \"Guerrero Cumple\" podrán coinvertirse con los\nGobiernos Federal y Municipal u otras instancias estatales, a fin de aumentar las metas.\nd) Los Ayuntamientos y las Organizaciones Sociales legalmente constituidas podrán participar, en el caso de los ayuntamientos podrán hacerlo para obra pública que coadyuven a dignificar la vivienda de los guerrerenses y canalizarán sus solicitudes, con la corresponsabilidad de los lineamientos del programa.\nLos Materiales de bajo costo que se pueden adquirir:\n1. Tinaco\n2. Lámina\n3. Pintura\n4. Cemento\n3. Misión\nAtender a través del programa Casa Digna “Guerrero Cumple” a la población Guerrerense en condiciones de pobreza patrimonial por debajo de la línea de bienestar, proporcionando materiales para construcción de vivienda a bajo costo, para disminuir el rezago en el índice de hacinamiento estimulando el trabajo y la participación comunitaria en las localidades urbanas y rurales de los 81 municipios del estado.\n4. Visión mejoramiento y calidad de espacios de la vivienda, motivando el arraigo de la población guerrerense en sus lugares de origen.\n5. Reglas de Operatividad\n5.1. Lineamientos Generales\nEl programa consiste en la entrega de materiales de construcción a bajo costo como: lámina, cemento, tinaco y pintura, construcción de baños ecológicos, estufas ecológicas y el mejoramiento de la vivienda.\n5.1.1. Para ingresar al programa\na) Población en general\n1. Los beneficiarios deberán conformar un comité integrado por un presidente, secretario, tesorero y tres vocales.\n2. la adquisición mínima será de 20 tinacos por grupo;\n3. La adquisición mínima será de 100 piezas de lámina por grupo;\n4. La adquisición mínima será de 20 toneladas de cemento por grupo\n5. La adquisición mínima será de 10 cubetas por grupo\n6. Con la aclaración que no necesariamente deben de adquirir los cuatro materiales.\nb) Los H. ayuntamientos Municipales deberán firmar un convenio de colaboración con la\nSecretaria de Desarrollo Social. (ANEXO 10)\n5.2.1. Cantidad máxima que pueden adquirir:\na) Población en general:\n1.- Tinaco: La adquisición será de una pieza por familia.\n2.-Lámina: La adquisición será de 10 piezas máximo por familia\n3.-Cemento: La adquisición será de 4 toneladas máximo por familia\n4.-Pintura: La adquisición será de 2 cubetas máximo por familia\nb) H. ayuntamientos:\n1.-Tinaco: La adquisición será de 50 piezas máximo.\n2.-Lámina: La adquisición será de 200 piezas máximo.\n3.- Cemento: La adquisición será de 700 toneladas máximo.\n4.- Pintura: La adquisición será de 50 cubetas máximo.\nc) Organizaciones Sociales:\n1.- Tinaco: La adquisición será de 50 piezas máximo.\n2.- Lámina: La adquisición será de 100 piezas máximo.\n3.- Cemento: La adquisición será de 200 toneladas máximo.\n4.- Pintura: La adquisición será de 40 cubetas máximo.\n5.1.3. Presupuesto de inversión del 2013\nEl Congreso del Estado aprobó un presupuesto de $10, 000, 000.00 para el programa \"Casa\nDigna, Guerrero Cumple\", que serán destinados exclusivamente ha dicho programa.\nEl programa recuperará los recursos de los materiales a través de los depósitos bancarios que realicen los solicitantes, conforme a los precios y cantidades establecidos.\nSe manejaran donaciones de materiales para la construcción, estufas, baños ecológicos y mejoramiento de la vivienda, cuando así sea determinado por el titular del Ejecutivo y/o la titular de la\nSecretaría, de acuerdo a la solicitud, la disponibilidad de recursos, así como de la coinversión que se realice con los municipios.\n5.1.4. Perspectiva de Género\nLa Secretaría como una institución comprometida con la equidad de género, promoverá que las acciones o programas propios de la Dirección General de Acciones Prioritarias, garanticen la igualdad entre hombres y mujeres, eliminando cualquier forma de discriminación por razón de género, atendiendo en todo momento las recomendaciones de las instituciones y dependencias encargadas de la vigilancia a este principio fundamental, así como los acuerdos que suscriba el titular del Poder Ejecutivo del Estado en este tenor.\n5.1.4. Fundamento Legal\n1) Constitución Política de los Estados Unidos Mexicanos;\n3) Ley Orgánica de la Administración Pública del Estado de Guerrero Número 433;\n4) Ley Número 102 para el Desarrollo Social del Estado de Guerrero;\n6) Ley Número 674 de Responsabilidades de los Servidores Públicos del Estado de Guerrero;\n7) Ley Número 494 para la Igualdad entre Mujeres y Hombres del Estado de Guerrero;\n8) Código de Conducta de la Secretaría de Desarrollo Social;\n10) Plan Estatal de Desarrollo del Estado de Guerrero 2011-2015;\n11) Decreto Número de Presupuesto de Egresos del Estado de Guerrero para el Ejercicio Fiscal\nY todos aquellos ordenamientos normativos que sean aplicables.\n5.1.5. Participantes\nPara el cumplimiento, ampliación de los objetivos y metas del Programa se podrá realizar convenios, acuerdos de coinversión y/o colaboración con los H. Ayuntamientos, fundaciones y organizaciones de la sociedad civil así como dependencias e instituciones del Gobierno Federal.\nLos integrantes deberán conformar Comités de Desarrollo Comunitario y Contraloría Social, los cuales permitan organizar, planear y supervisar la correcta aplicación de los recursos otorgados por la\nSEDESOLG.\n5.1. 6. Patrimonio del programa\nRespecto al origen de los recursos que integra y aplica el programa, estos provienen de la\nInversión Estatal Directa (IED), y están contenidos en el Decreto Número 148 del Presupuesto de\nEgresos del Gobierno del Estado para el Ejercicio Fiscal 2013, los cuales serán radicados a la\nSEDESOLG para su correcta aplicación.\nEn caso de contar con recursos de coinversión federal, quedarán sujetos a lo establecido en los acuerdos y convenios concertados, a los ordenamientos federales y a los lineamientos específicos del origen del recurso.\n5.1.7. Tipos de apoyo\nLos apoyos que proporciona la Secretaría de Desarrollo Social en materiales de Bajo costo son:\n1. Grupos informales organizados y H. Ayuntamientos Municipales:\na) Cemento\nb) Tinaco.\nc) Pintura\nd) Lamina\n2. Donación de materiales para la construcción, estufas, baños ecológicos y mejoramiento de la vivienda, de acuerdo a la solicitud, la disponibilidad de recursos, así como de la coinversión que se realice con los municipios.\na) Los casos de donación del punto anterior señalado serán turnados a la Titular de la Secretaría y el Director encargado de la dirección que opera el programa, quienes serán los encargados de emitir el fallo correspondiente el cual será inapelable.\nb) Se proporcionarán los materiales necesarios para la construcción de estufas, baños ecológicos y mejoramiento de la vivienda, en donde el beneficiario participara con la mano de obra. que se considere para su pago.\nLos apoyos que otorga el programa serán orientados a los siguientes rubros de atención:\nEl programa dará prioridad a los guerrerenses de escasos recursos económicos y que su vivienda se encuentre en condiciones precarias que requieran mejorar las condiciones habitacionales.\nA las organizaciones constituidas debidamente y sin ninguna finalidad lucrativa, mismas que se les aplicará un estudio socio-económico.\nA grupos de vecinos y/o colonos que conformen un Comité exprofeso para la solicitud de dichos apoyos, a los cuales se les aplicará un Estudio socioeconómico.\nTodos los apoyos estarán sujetos a la disponibilidad presupuestaria del programa.\n6. Información del programa\n6.1. De los proyectos\nLa Secretaría de Desarrollo Social establecerá un formato único para el llenado de los requisitos y conformación de los proyectos, el cual estará a disposición de la población en general a través de la página de la SEDESOLG en la siguiente dirección; http://www.sedesol.guerrero. gob.mx, en el módulo de atención al público y en la Dirección General de Gestión Social.\n6.2. Exposición del programa\nLa SEDESOLG, será la encargada de difundir el programa a través de los diferentes medios de comunicación digitales como impresos necesarios, permitiendo la difusión del programa en todo el territorio, además a través de la Dirección General de Gestión Social, se proporcionará personal capacitado para brindar asesoría y orientación a la población que lo requiera.\n6.3. Cobertura\nEl programa Casa Digna \"Guerrero cumple\", operará a nivel estatal en los 81 municipios del estado, beneficiando principalmente a población que se encuentre por debajo de la línea de bienestar y con carencia por calidad y espacios de vivienda.\n6.4. Modo de entrega del beneficio\nLa SEDESOLG será el encargado de entregar los apoyos en especie a los beneficiarios, en los plazos y lugares acordados con el Comité de Desarrollo Local.\n6.5. Criterios y requisitos de elegibilidad\na) Población en general\n6.6. Gastos de Operación\nDel total de recursos autorizados al programa, podrán aplicarse hasta un 3% del presupuesto asignado al Programa para gastos de operación, destinados a las diversas acciones asociadas con la planeación, operación, supervisión, seguimiento, contraloría social y evaluación o asesoría externa del\nPrograma.\n7. Transparencia\n7.1. Difusión\nEstas Reglas de Operación, además de su publicación en el Periódico Oficial del Gobierno del\nEstado de Guerrero, estarán disponibles en la página de Internet de la SEDESOLG www,sedesol\n.guerrero.gob.mx. Asimismo, se establecerán las estrategias de difusión del Programa y realizar las acciones conducentes para dar a conocer los requisitos de participación, la corresponsabilidad de los beneficiarios y los apoyos a otorgar.\nLa SEDESOLG, en coordinación con los municipios, serán los encargados de realizar la promoción y difusión del Programa, darán a conocer las acciones a realizar y las comunidades beneficiadas.\nAsí mismo, con base en lo establecido en la Ley Número 374 de Transparencia y Acceso a la\nInformación Pública del Estado de Guerrero, la SEDESOLG publicará periódicamente en la página electrónica http://www.sedesol.guerrero.gob.mx la información relativa al Programa, incluyendo el avance en el cumplimiento de objetivos y metas respectivos de las presentes Reglas; para el caso de la publicación del padrón de beneficiarios en la página de internet, los datos personales que se recaben con motivo de la operación del presente programa, serán protegidos y serán incorporados y tratados en el\nSistema de datos personales el cual se denomina: Sistema de Información Estadística del Programa\nCasa Digna \"Guerrero Cumple\", con fundamento en las presentes reglas de operación para el ' ejercicio\n2013 y cuya finalidad es contar con un padrón de beneficiarios homogéneo y con la calidad necesaria para dar transparencia y poder dar seguimiento puntal de los beneficiarios y de los recursos que se otorgan a través del programa.\n7.2. Seguimiento de avances físicos y financieros\nCon el propósito de mejorar la operación del programa, la SEDESOLG llevará a cabo el seguimiento al ejercicio de recursos fiscales, acciones ejecutadas, resultados, indicadores y metas alcanzadas. Asimismo, realizarán el seguimiento en campo de las obras, proyectos y acciones conforme a lo que cada una determine.\nGestión Social deberá reportar trimestralmente al COPLADEG, durante los primeros 10 días hábiles del mes inmediato posterior al trimestre que se reporta, los avances físico-financieros de los proyectos y/o acciones autorizados.\nEn el caso de que el COPLADEG detecte información faltante, la dependencia ejecutora deberá presentar la documentación faltante, en un plazo que no exceda de 10 días hábiles contados a partir de la recepción del comunicado del COPLADEG. en un tanto original. La Dependencia verificará la congruencia de la información con la Cuenta Pública.\n7.3. Evaluación\n7.3.1. Evaluación Interna\nEl Programa Casa Digna \"Guerrero Cumple\", estará sujeto a procesos trimestrales de seguimiento y evaluación que permitan ajustar su ejecución y garantizar que los mecanismos de funcionamiento y administración, faciliten tanto la obtención de información como la evaluación de los beneficios económicos y sociales de su asignación y aplicación.\n7.3.2. Evaluación Externa\nLa Dependencia deberá realizar una evaluación de resultados de carácter externo del programa sujeto a las reglas de operación, para lo cual, la SEDESOLG, tendrá la facultad de designar en su caso a la instancia que realizará dicho análisis.\n7.4. Indicadores\nLa información correspondiente a estos indicadores será reportada por la Dirección General de\nGestión Social, a la unidad que designe la SEDESOLG, para la integración del seguimiento, informes y evaluación correspondientes.\nLa SEDESOLG será responsable de compilar e integrar un reporte estatal de resultados tomando como base los proyectos y/o acciones desarrollados por el Programa Casa Digna \"Guerrero\nCumple\", al finalizar el ejercicio fiscal.\n7.5. Auditoria\nLas ejecutoras serán responsables de la supervisión directa de los proyectos o acciones, así como de verificar que en su ejecución se cumpla con la normatividad aplicable.\nLos recursos asignados para la operación del Programa no pierden su carácter estatal, por lo que, la Secretaría de Finanzas, la Contraloría General del Estado y la Auditoria General del Estado, en el ámbito de sus respectivas competencias, realizarán actividades de fiscalización y auditoría.\nLa Instancia Ejecutora dará todas las facilidades a las instancias fiscalizadoras para realizar, en el momento en que lo juzguen pertinente, las auditorias que consideren necesarias; asimismo, efectuará el seguimiento y la solventación de las observaciones planteadas por los órganos de control. La inobservancia de esta disposición, independientemente de las sanciones a que hubiere lugar, limitará la ministración de los recursos estatales en el siguiente ejercicio presupuestal.\n7.6. Recursos no devengados\nLos recursos que al cierre del ejercicio se conserven o que no se hayan devengado al 31 de\nDiciembre del presente ejercicio, deberán ser reintegrados a la Secretaria de Finanzas del Estado.\nDentro del mismo plazo, deberán remitir copia del reintegro a la SEFINA para su registro correspondiente.\n7.7. Blindaje electoral\nLa SEDESOLG, para la operación y ejecución de los recursos estatales que opera el programa deberá observar y atender las medidas que emitan la Contraloría General del Estado, el Instituto de\nTransparencia y Acceso a la Información Pública del Estado de Guerrero (ITAI), el Instituto Estatal\nElectoral del Estado de Guerrero (IEEGRO) y las demás autoridades competentes, con la finalidad de impedir que los apoyos sean utilizados con fines políticos electorales.\nAdemás, la publicidad y la información relativa a este Programa deberán identificarse con el\nEscudo del Estado de Guerrero e incluir la siguiente leyenda:\n\"Este Programa es de carácter público, no es patrocinado ni promovido por partido político alguno y sus recursos provienen de los impuestos que pagan todos los contribuyentes, Está prohibido el uso de este programa con fines políticos, electorales, de lucro y otros distintos a los establecidos. Quien haga uso indebido de los recursos de este programa deberá ser denunciado y sancionado de acuerdo con la Ley aplicable y ante la autoridad competente\".\n7.8. Contraloría social\nCon la finalidad de incrementar la participación ciudadana, se crearán Comités de Contraloría\nSocial, como un órgano ciudadano de control, vigilancia y evaluación de las actividades del Programa, conformado por los beneficiarios, los sectores sociales, y los representantes de la localidad, quienes de manera específica supervisarán la gestión gubernamental, y que el manejo de los recursos públicos se realicen en términos de transparencia, eficacia, legalidad y honradez.\nLos objetivos específicos de este órgano de Contraloría Social son:\na) Hacer más transparentes las decisiones y la ejecución de los recursos;\nb) Incrementar la participación ciudadana;\nc) Fomenta la organización social;\nd) Inhibir los actos de corrupción y de cooptación social, política y electoral;\ne) Incrementar la eficiencia de los recursos públicos;\nf) Fortalecer la cultura de la legalidad;\ng) Mejorar la rendición de cuentas;\nh) Perfeccionar la democracia, e incorporar la evaluación ciudadana.\n7.9. Integración de los Comités beneficiada por el Programa, y fungirán como interlocutores con la Secretaría de Desarrollo Social, en el ejercicio de la contraloría social.\nEl Comité de Contraloría Social debe estar constituido por un Presidente, un Secretario y un\nVocal mínimamente, electos de entre la población beneficiada en donde se va a realizar la entrega del programa, y tendrá que ser vigilado por un solo comité.\nDicho Comité deberá revisar en conjunto con la población, los avances y resultados del programa, así como la detección de cualquier irregularidad.\nEl vocal del Comité de Contraloría Social será el responsable de hacer llegar las quejas o denuncias recibidas a la Secretaría de Desarrollo Social, quien dará respuesta en un plazo no mayor de\n15 días a partir de la fecha de recepción de la queja o denuncia.\n7.10. Capacitación y Asesoría\nPara impulsar la realización de las actividades de Contraloría Social se brindará capacitación y asesoría, a los servidores públicos que intervienen en la operación del Programa, así como a los integrantes de los Comités Locales, para que éstos realicen adecuadamente sus actividades de seguimiento y vigilancia.\n7.11. Seguimiento\nSe deberá integrar un Programa de Trabajo de acuerdo al programa. Debe incluir la descripción de las actividades, responsables de éstas, metas y calendarización de las actividades para su cumplimiento.\nSocial, serán los encargados de conformar los Comités de Contraloría Social, así mismo darán acompañamiento durante las actividades de control, seguimiento y vigilancia de los proyectos.\nEl Comité de Contraloría Social deberá controlar, vigilar y dar seguimiento al proyecto a través de los formatos que integran el expediente comunitario, integrado por:\na) Acta de Conformación del Comité Contraloría Social;\nb) Reunión con Beneficiarios;\nc) Ficha Informativa de Programa;\nd) Cédula de Vigilancia del Programa;\ne) Actividades de Difusión y Capacitación;\nf) Quejas, Denuncias o Reconocimientos; e\ng) Informe Anual. responsable de integrar los expedientes comunitarios emitidos por los Comités de Contraloría Social de cada uno de los proyectos beneficiarios y hacer entrega de los mismos al área correspondiente.\nLa Dirección General de Contraloría Social de la Contraloría General del Estado dará seguimiento a las actividades señaladas en el Programa de Trabajo de cada Comité de Contraloría\nSocial, una vez que la Dirección General de Gestión Social le dé aviso de inicio de dichas actividades.\n7.12. Quejas y denuncias\nLos beneficiarios pueden presentar sus quejas o denuncias directamente en las Oficinas de la\nSecretaría de Desarrollo Social sobre cualquier hecho, acto u omisión que produzca o pueda producir daños al ejercicio de sus derechos establecidos en las presentes Reglas o contravengan sus disposiciones y de la demás normatividad aplicable, debiendo contener como mínimo la narración de los hechos que constituyan la queja, acompañando los documentos o evidencias que comprueben los actos incurridos, presentando como mínimo nombre del quejoso, domicilio para recibir documentos y notificar la resolución, teléfono o correo electrónico, con la finalidad de dar respuesta a su inconformidad.\nLas quejas y denuncias de la ciudadanía derivadas de alguna irregularidad en la operación del programa deberán realizarse por escrito y ser entregadas de manera directa en el domicilio ubicado en\nEdificio Norte Planta Baja, Palacio de Gobierno, Sito en Boulevard René Juárez Cisneros No. 62, Chilpancingo, Gro. C.P. 039074, o bien podrá presentarse vía correo electrónico a la siguiente dirección: sedesol@guerrero.gob.mx a los Teléfonos: 01 (747) 47 1 98 63; 47 1 98 48 y 47 1 98 49.\n8. Criterios de selección y elegibilidad\nEl programa está diseñado para proporcionar apoyo a personas del estado de Guerrero, estableciendo como prioridad su condición de pobreza, marginación y vulnerabilidad en que se encuentre.\n9. Mecánica operativa\n9.1. Instancia Ejecutora de la Dirección General de Gestión Social, conforme a los lineamientos contenidos en las presentes\nReglas de Operación del programa y demás ordenamientos que le sean aplicables.\n9.2. Instancia Administrativa o normativa través de la Dirección General de Gestión Social, Dirección General de Administración y Finanzas, la\nContraloría General del Estado.\n9.3. Delimitación de atribuciones\nLa Secretaría de Desarrollo Social a través de la Dirección General de Gestión Social, de conformidad con las con las presentes Reglas de Operación y de acuerdo a los recursos autorizados en el Decreto de Presupuesto de Egresos del Estado, tendrá las siguientes atribuciones:\na) Coordinar y conducir la operación del programa, de acuerdo a los lineamientos establecidos en las presentes reglas;\nb) Administrar a través de la Dirección General de Administración y Finanzas de la SEDESOLG los recursos financieros autorizados;\nc) Diseñar los instrumentos técnicos necesarios para evaluar el impacto social del programa;\nd) La organización del personal técnico y operativo que resulte indispensable para garantizar el funcionamiento del programa;\ne) La Titular de la Secretaría y el director general de la dirección encargada de operar el programa serán los que evalúen y emitir el fallo con carácter de inapelable para todos aquellos casos que por su naturaleza no se ajusten a las presentes reglas y deban ser deliberados como excepción, así como ejecutar sus determinaciones y recomendaciones.\n10. Derechos, obligaciones y sanciones de los beneficiarios\n10.1. Derechos\nLos beneficiarios tendrán derecho a recibir:\na) La información necesaria de manera clara y oportuna para participar en el Programa;\nb) Un trato digno, respetuoso, oportuno, con calidad y equitativo, sin discriminación alguna;\nc) Recibir por parte del Estado, el apoyo del presente programa;\nd) La reserva y privacidad de su información personal; y\ne) Recibir en caso de que sea elegible su proyecto y/o acción el apoyo económico y en especie establecidas en estas Reglas de Operación.\n10.2. Obligaciones\nLos beneficiarios del Programa tendrán las siguientes obligaciones:\na) Proporcionar, bajo protesta de decir verdad, la información que se les requiera de acuerdo a lo establecido en las presentes Reglas de Operación;\nb) Cumplir con su corresponsabilidad en el proyecto autorizado y estar de acuerdo en conformar el Comité de Desarrollo Comunitario (ANEXO 4) respectivo para el propósito del proyecto o acción;\nc) Nombrar a un representante, para que, en caso de fallecimiento, imposibilidad física o enfermedad, alguno de sus integrantes pueda recibir el material de vivienda digna y\nd) Acatar en todo momento las determinaciones de la Secretaría y la Dirección General de\nGestión Social\n10.3. Sanciones\nSe suspenderán definitivamente los apoyos a los beneficiarios que:\na) No cumplan con alguna de las obligaciones estipuladas en las reglas de operación; y\nb) En el caso de que la Dependencia o algún Órgano de Fiscalización detecte desviaciones o incumplimiento en el ejercicio de los recursos a las presentes Reglas de Operación, por parte de los beneficiarios, por lo cual la SEDESOLG suspenderá los apoyos, y solicitará su reintegro total, de acuerdo a la normatividad aplicable.\n11. Cierre de Ejercicio\nLa Dirección Administrativa será la responsable de elaborar y emitir el cierre final del ejercicio fiscal los primeros quince días hábiles del mes de Enero del ejercicio próximo.\n12. Casos de Excepción\nEn todos aquellos casos no previstos en las presentes reglas de operación, serán sometidos a programa, para su análisis, discusión y determinación, tomando en cuenta las circunstancias del caso, sus particularidades, los riesgos sociales, los resultados que se podrían obtener, etc.\n13. Anexos\n13.1. Anexo 1. Glosario de Términos\nCorresponsabilidad: Se refiere a la ejecución por parte de los beneficiarios de las actividades que les corresponde de acuerdo a los proyectos o acciones que les fueron aprobados.\nCURP: Clave única de Registro de Población.\nMunicipios de Muy Alta, Alta o Media Marginación (MMAM): Son aquellos municipios identificados por CONAJPO como de muy alta, alta y media marginación en la publicación de índices de\nPerspectiva de género: Es una visión científica, analítica y política sobre las mujeres y los hombres. Se propone eliminar las causas de la opresión de género. -Promueve la igualdad entre los géneros a través de la equidad, el adelanto y el bienestar de las mujeres; contribuye a construir una sociedad en donde mujeres y hombres tengan el mismo valor, la igualdad de derechos y oportunidades decisiones.\nPrograma: programa casa Digna \"Guerrero Cumple\"\nReglas: las Reglas de Operación del Programa Casa Digna \"Guerrero Cumple\"\nSolicitante: Persona Físicas o Morales.",
  "ordenamiento": "REGLA",
  "jurisdiccion": "GUERRERO",
  "fuente_oficial": "DIARIO OFICIAL DE LA FEDERACION",
  "Fecha de Publicación": "22 DE JULIO \nDE 2014",
  "ULTIMA REFORMA PUBLICADA": null,
  "status": "VIGENTE",
  "es_escaneado": false,
  "tiene_tablas": true,
  "materia": [
    "general"
  ]
}