{
  "titulo": "Acuerdo por el Que Se Emiten las Reglas de Operación del Programa 2. Defensa y Asesoría Jurídica A P",
  "Contenido": "AFROMEXICANO, DE LA SECRETARÍA DE\nASUNTOS INDÍGENAS Y COMUNIDADES\nAFROMEXICANAS\nCOMUNIDADES AFROMEXICANAS PARA EL EJERCICIO FISCAL 2018, PUBLICADO EN EL PERIÓDICO OFICIAL\nDEL GOBIERNO DEL ESTADO DE GUERRERO No. 41, DE FECHA 22 DE MAYO DE 2018.\nÚLTIMA REFORMA PUBLICADA EN EL PERIÓDICO OFICIAL DEL GOBIERNO DEL ESTADO\nNo. 98, EL VIERNES 08 DE DICIEMBRE DE 2017.\nTEXTO ORIGINAL.\nAcuerdo publicado en el Periódico Oficial del Gobierno del Estado No. 48, el Viernes 16 de Junio de 2017.\nACUERDO POR EL QUE SE EMITEN LAS REGLAS DE OPERACIÓN\nDEL PROGRAMA 2. DEFENSA Y ASESORÍA JURÍDICA A PUEBLOS\nINDÍGENAS Y AFROMEXICANO, DE LA SECRETARÍA DE ASUNTOS\nINDÍGENAS Y COMUNIDADES AFROMEXICANAS\nPARA EL EJERCICIO FISCAL 2017\nLIC. GILBERTO SOLANO ARREAGA, Secretario de Asuntos Indígenas y Comunidades\nAfromexicanas, con fundamento en los Artículos 11, 14, 16 y 32 de la Ley Orgánica de la Administración\nPública del Estado de Guerrero número 8, por el que se crea la Secretaría de Asuntos Indígenas y\nComunidades Afromexicanas, publicado en el Periódico Oficial del Gobierno del Estado de Guerrero, número 85, de fecha 23 de Octubre de 2015, y\nCONSIDERANDO\nQue en el Decreto número 426 del Presupuesto de Egresos del Estado de Guerrero, para el\nEjercicio Fiscal 2017, se señala que se ejercitarán los recursos bajo una política de gasto público que permita dar cumplimiento a los seis ejes rectores del Plan Estatal de Desarrollo 2016 - 2021. Las políticas sociales.\nComunidades Afromexicanas, implementará el programa: 2. Defensa y Asesoría Jurídica a Pueblos\nIndígenas y Afromexicano, a fin de contribuir a la mejora de la calidad de vida de cada uno de las y los beneficiarios del programa.\nPor lo anterior expuesto y con fundamento en las disposiciones legales antes citadas, he tenido a bien expedir el siguiente:\nAFROMEXICANO, DE LA SECRETARÍA DE\nASUNTOS INDÍGENAS Y COMUNIDADES\nAFROMEXICANAS\nEJERCICIO FISCAL 2017.\nÚnico: se emiten las Reglas de Operación del Programa 2. Defensa y Asesoría Jurídica a\nPueblos Indígenas y Afromexicano, que implementará la Secretaria de Asuntos Indígenas y\nComunidades Afromexicanas, para el ejercicio fiscal 2017.\nTRANSITORIOS\nPrimero.- El presente acuerdo entrará en vigor al día siguiente de su publicación en el Periódico\nOficial del Gobierno del Estado de Guerrero.\nSegundo.- Quedan abrogadas las Reglas de Operación del Programa Defensa y Asesoría\nJurídica a Pueblos Indígenas y Afromexicano, publicadas en el Periódico Oficial del Estado de Guerrero, número 61, alcance I, de fecha 29 de julio del 2016.\nTercero.- Las Reglas de Operación del Programa de la Secretaría de Asuntos Indígenas y\nComunidades Afromexicanas: 2. Defensa y Asesoría Jurídica a Pueblos Indígenas y Afromexicano, para el ejercicio fiscal 2017, se publican en su totalidad para mejor entendimiento.\nDado en la ciudad de Chilpancingo de los Bravo, Guerrero, a dieciséis días del mes de marzo de dos mil diecisiete.\nEL SECRETARIO DE ASUNTOS INDÍGENAS Y COMUNIDADES AFROMEXICANAS.\nLIC. GILBERTO SOLANO ARREAGA.\nRúbrica.\nLIC. FELIPE SANCHEZ RAMIREZ, DIRECTOR GENERAL DE LA DEFENSA Y ASESORÍA\nNUMERAL 32, FRACCIÓN XVIII, DE LA LEY ORGÁNICA DE LA ADMINISTRACIÓN PÚBLICA DEL\nESTADO DE GUERRERO NÚMERO 08, ASÍ COMO EL NUMERAL 16 FRACCIONES V, XXI Y XXII DEL\nREGLAMENTO INTERNO VIGENTE DE ESTA DEPENDENCIA.\nHAGO CONSTAR Y CERTIFICO\nQUE LAS PRESENTES COPIAS FOTOSTÁTICAS, COMPUESTAS DE 2 FOJAS ÚTILES SON\nAFROMEXICANO, DE LA SECRETARÍA DE\nASUNTOS INDÍGENAS Y COMUNIDADES\nAFROMEXICANAS\nSECRETARÍA, MISMAS QUE SE EXPIDEN PARA LOS USOS LEGALES A QUE HAYA LUGAR, EN LA\nATENTAMENTE.\nLIC. FELIPE SÁNCHEZ RAMÍREZ.\nDIRECTOR GENERAL DE LA DEFENSA Y ASESORÍA JURÍDICA.\nRúbrica.\nAFROMEXICANO, DE LA SECRETARÍA DE\nASUNTOS INDÍGENAS Y COMUNIDADES\nAFROMEXICANAS\nAFROMEXICANO, DE LA SECRETARÍA DE\nASUNTOS INDÍGENAS Y COMUNIDADES\nAFROMEXICANAS\nÍndice\n1. Introducción\n1.1. Antecedentes\n1.2. Alineación Programática\n1.3. Diagnóstico\n2. Misión y Visión\n2.1. Misión\n2.2. Visión\n3. Dependencia o Entidad Responsable del Programa\n4. Fundamento legal\n5. Objetivos y Alcances\n5.1 Objetivo General\n5.2. Objetivos Específicos\n5.3. Alcances\n6. Metas Físicas\n7. Programación Presupuestal\n8. Requisitos y Procedimientos de Acceso\n8.1. Difusión\n8.2. Requisitos de Acceso\n8.3. Procedimientos de Acceso\n8.4 Requisitos de Permanencia, Causales de Baja o Suspensión Temporal\n8.5. Modos de entrega del beneficio\n9. Procedimientos de Instrumentación\n9.1. Operación\n9.2. Gastos de operación\n10. Transparencia\n10.1. Difusión\n10.2. Blindaje electoral\n10.3. Supervisión y Control\n10.4. Mecanismos de Evaluación e Indicadores\n10.4.1 Evaluación\n10.4.2. Indicadores\n10.5. Auditoría\n10.6. Recursos no devengados\n10.7 Contraloría social\n10.8 Procedimiento de Queja o Inconformidad Ciudadana\n10.9 Mecanismos de Exigibilidad 10.10. Acta de Entrega Recepción\n11. Criterios de selección y elegibilidad\n11.1 Método de selección de beneficiarios\n12. Mecánica de Operación\nAFROMEXICANO, DE LA SECRETARÍA DE\nASUNTOS INDÍGENAS Y COMUNIDADES\nAFROMEXICANAS\n12.1 Instancia ejecutora\n12.2. Instancia administrativa y/o normativas\n12.3. Delimitación de atribuciones\n13. Derechos, obligaciones y sanciones de los beneficiarios de programas sociales\n13.1 Derechos\n13.2. Obligaciones\n13.3. Sanciones\n14. Interpretación\n1. Introducción\nLas presentes Reglas de Operación tienen por objeto orientar a la población indígena y afromexicana acerca de los procedimientos y requisitos para acceder a los servicios que ofrece la\nSecretaría de Asuntos Indígenas y Comunidades Afromexicanas, relacionados con las acciones de defensa y asesoría jurídica, a través de las cuales se promueven los derechos de estos pueblos, consagrados en\nEste reglamento es la guía operativa del Programa Defensa y Asesoría Jurídica a Pueblos\nIndígenas y Afromexicano, el cual busca impulsar el pleno reconocimiento y vigencia a los derechos de este sector de la población y contribuir a su acceso pleno a una administración y procuración de justicia pronta y expedita, mediante la promoción de derechos, el acompañamiento de procesos legales de personas, organizaciones y comunidades, así como trámites ante el Registro Civil en favor de la población objetivo.\n1.1. Antecedentes\nGuerrero es un estado pluricultural en el que se asientan cuatro pueblos indígenas y el afromexicano. Los pueblos y las comunidades que dan origen y sustento a esta diversidad tienen como rasgos comunes el uso de lenguas originarias, sentido de pertenencia a un colectivo, así como culturas y sistemas sociales propios, mediante los cuales organizan su vida y toman decisiones.\nEl impulso al reconocimiento pleno de los derechos e inclusión social de los pueblos indígenas y afromexicano, continúa siendo una asignatura pendiente para el Estado mexicano; el cumplimiento de la norma constitucional y los tratados internacionales obligan a respetar y consolidar dicho reconocimiento, lo que implica también hacer efectivos sus derechos culturales y derechos sociales a la alimentación, la salud, la educación, la vivienda, el trabajo, el acceso pleno a la jurisdicción del Estado y al desarrollo pleno de sus capacidades.\nEn el caso particular del estado de Guerrero, los pueblos originarios han exigido el reconocimiento de sus derechos colectivos que posibiliten su permanencia y reproducción social, económica y cultural. En respuesta a estas demandas, en los últimos años se han registrado avances importantes en materia de de Reconocimiento, Derechos y Cultura de los Pueblos y Comunidades Indígenas del Estado de Guerrero\nAFROMEXICANO, DE LA SECRETARÍA DE\nASUNTOS INDÍGENAS Y COMUNIDADES\nAFROMEXICANAS al 14, en los que se eleva a rango constitucional el reconocimiento de los derechos de los pueblos indígenas, y se incluye el reconocimiento y respeto constitucional del pueblo afromexicano, bajo los mismos términos y beneficios que los pueblos indígenas.\nNo obstante estos adelantos, aún existen limitaciones jurídicas que generan lagunas legales, propiciando, así, la persistencia de discriminación y exclusión; en consecuencia, los pueblos indígenas y afromexicano continúan enfrentando serias dificultades para acceder a la jurisdicción del Estado. En este sentido, la Secretaría de Asuntos Indígenas y Comunidades Afromexicanas (SAICA) implementa el programa de Defensa y Asesoría Jurídica a Pueblos Indígenas y Afromexicano, el cual se ejecuta desde el año 2001 y busca contribuir al cumplimiento de los derechos de estos pueblos, a través de la prestación de diversos servicios jurídicos y la promoción de sus derechos individuales y colectivos.\n1.2. Alineación Programática\nDe acuerdo a lo estipulado por la Secretaría de Desarrollo y Planeación Regional (SEPLADER), el programa Defensa y Asesoría Jurídica a Pueblos Indígenas y Afromexicano se encuentra alineado al\nPlan Estatal de Desarrollo 2016-2021, específicamente al eje VI Estrategias Transversales, Objetivo 4\nAtender a los pueblos originarios y afromexicano, Estrategia 6.4.1. \"Generar oportunidades para los pueblos originarios y afromexicanos que permitan su desarrollo económico, político y social, respetando las manifestaciones de su cultura y el ejercicio de sus derechos\"\nLíneas de acción:\n✓ Fortalecer y ampliar el marco jurídico en materia de derechos de los pueblos originarios y afromexicano, así como el reconocimiento y la protección de su patrimonio y riqueza cultural.\n✓ Fomentar la participación de los pueblos originarios y afromexicano, en la planeación y la gestión de su propio desarrollo, asegurando el respeto a sus derechos y sus formas de vida propias de cada pueblo originario.\n✓ Fortalecer la Defensoría de Oficio para asegurar el respeto al derecho a una defensa adecuada, con especial prioridad en los defensores bilingües, para mejorar el apoyo a la población indígena y afromexicana.\nAsimismo, este Programa se alinea al Programa Especial Nacional de los Pueblos Indígenas 20142018, el cual define la política nacional en favor de estos pueblos, específicamente a la Meta Nacional\n\"México Incluyente\", Objetivo 1 \"Impulsar el reconocimiento, vigencia de derechos y el acceso a la justicia de los Pueblos Indígenas”; Estrategia 1.2. \"Proteger el derecho de acceso a la justicia de la población indígena y comunidades equiparables\"; y Líneas de Acción 1.2.1. \"Promover la coordinación de órdenes de gobierno para garantizar el acceso a la justicia de los Pueblos Indígenas\", y 1.2.3. \"Fortalecer el servicio de intérpretes-traductores especializados y defensores de oficio que acompañen a los indígenas sujetos a proceso\".\nAFROMEXICANO, DE LA SECRETARÍA DE\nASUNTOS INDÍGENAS Y COMUNIDADES\nAFROMEXICANAS\nIndígenas y Afromexicano 2016-2021, el cual busca una correcta implementación de políticas públicas orientadas a la atención de las comunidades y pueblos indígenas y afromexicano, establecidas en el Eje\nTrasversal 4 \"Atender a los Pueblos Originarios y Afromexicano\", Estrategia 6.4.1. \"Generar oportunidades para los pueblos originarios y afromexicano que permitan su desarrollo económico político y social, respetando las manifestaciones de su cultura y el ejercicio de sus derechos\".\nLíneas de acción:\n4.1.4 Brindar servicios de defensa y asesoría jurídica a personas, comunidades y organizaciones sociales indígenas y afromexicanas en las diversas ramas del derecho incluyendo traducciones en las cuatro lenguas indígenas.\n4.1.5 Realizar trámites ante la Coordinación Técnica del Sistema Estatal del Registro Civil, en favor de las personas indígenas y afromexicanas.\n4.1.6 Facilitar talleres comunitarios sobre derechos de los pueblos indígenas y afromexicano.\n1.3. Diagnóstico\nLos pueblos indígenas y afromexicano han enfrentado diversas situaciones que violan sus derechos humanos. En los últimos 30 años, el Estado mexicano ha mostrado cierta reticencia a reconocer los derechos colectivos de los pueblos indígenas, mientras que el pueblo afromexicano recién se ha posicionado en la escena nacional.\nEn el estado de Guerrero el reconocimiento de estos derechos ha transitado también por situaciones similares, y los logros alcanzados aunque han sido valiosos todavía son insuficientes. A lo anterior habría que agregar las barreras que la población indígena y afromexicana enfrenta para acceder a los bienes y servicios gubernamentales y a las instancias de procuración y administración de justicia; aunque son de diversa índole las causas de esta exclusión social, es posible afirmar que los factores lingüísticos y culturales influyen de manera importante en esta exclusión, por lo que es imperativo adecuar los programas y servicios a los contextos culturales de este sector de la población, y proporcionar intérpretes-traductores especializados y defensores de oficio que acompañen y asesoren a los indígenas sujetos a proceso, bajos los enfoques de interculturalidad e igualdad de género. profundos en los municipios con preponderancia de estas poblaciones, principalmente aquellos más apartados ubicados en las regiones Montaña y Costa Chica; las brechas de desarrollo social y económico existentes entre estos municipios con respecto a los no indígenas, son determinantes para que en el estado siga existiendo una marcada desigualdad social y un desarrollo muy heterogéneo en sus siete regiones.\nEn este sentido, la garantía de poder acceder a una justicia social y, en consecuencia, reducir las brechas en la materia, los cuales han sido conquistadas por los pueblos indígenas y afromexicano en un largo proceso histórico y de lucha.\nAFROMEXICANO, DE LA SECRETARÍA DE\nASUNTOS INDÍGENAS Y COMUNIDADES\nAFROMEXICANAS\nSi bien estas condiciones de desigualdad y rezago son patentes, esta situación se hace todavía más profunda entre las mujeres indígenas y afromexicanas, quienes padecen mayormente la pobreza, son discriminadas y violentadas fuera y dentro de sus comunidades, ya sea por su doble condición de mujer e indígena, o por prácticas culturales que vulneran sus derechos y limitan su acceso a la educación, la salud multifactorial, buena parte de esta situación se vincula con el desconocimiento o violación de los instrumentos jurídicos que garantizan la aplicación de los derechos de las mujeres, lo cual se verifica en los ámbitos de la familia, la comunidad y las instituciones de los tres niveles y órdenes de gobierno.\nEn este sentido, la SAICA implementa el programa Defensa y Asesoría Jurídica a Pueblos\nIndígenas y Afromexicano, el cual busca contribuir al cumplimiento de los derechos de estos pueblos, a través de la prestación de diversos servicios jurídicos y la promoción de sus derechos individuales y colectivos.\n2. Misión y Visión.\n2.1. Misión.\nContribuir al cumplimiento de los derechos conquistados por los pueblos indígenas y afromexicano, a través de coadyuvar para que accedan a la jurisdicción del Estado, y a un desarrollo integral y con identidad propia.\n2.2. Visión.\nSer el programa del Gobierno del Estado que acompañe a los pueblos indígenas y afromexicano en sus procesos de autonomía y libre determinación, desarrollando acciones conjuntas que fortalezcan sus sistemas normativos y los empoderen como sujetos individuales y colectivos de derecho.\n3. Dependencia o Entidad Responsable del Programa.\nLa ejecución del programa Defensa y Asesoría Jurídica para Pueblos Indígenas y Afromexicano, está bajo la responsabilidad de la SAICA, a través de la Dirección General de Defensa y Asesoría Jurídica; la ministración de recursos será comprobada por la Delegación Administrativa de esta Secretaría.\n4. Fundamento Legal.\n✓ Constitución Política de los Estados Unidos Mexicanos (Artículo 2°).\n✓ Ley Orgánica de la Administración Pública del Estado de Guerrero Número 08 (Artículo 32).\n✓ Ley número 701 de Reconocimiento, Derechos y Cultura Indígena de los Pueblos y Comunidades\nIndígenas de Guerrero.\n✓ Convenio 169 sobre Pueblos Indígenas y Tribales, de la Organización Internacional del Trabajo.\n✓ Declaración Universal de las Naciones Unidas sobre los Derechos de los Pueblos Indígenas.\n✓ Plan Estatal de Desarrollo 2016 - 2021.\n✓ Programa Especial Pueblos Indígenas y Afromexicanos 2016 -2021.\n✓ Decreto 426 de Presupuestos de Egresos, para el ejercicio fiscal 2017.\nAFROMEXICANO, DE LA SECRETARÍA DE\nASUNTOS INDÍGENAS Y COMUNIDADES\nAFROMEXICANAS\n5. Objetivos y Alcances.\n5.1. Objetivo General.\nContribuir al cumplimiento de los derechos de los pueblos indígenas y afromexicano, a través de la prestación de servicios jurídicos y trámites administrativos que permitan su pleno acceso a la jurisdicción del Estado y a la procuración y administración de justicia incluyente, con perspectiva intercultural y de género.\n5.2. Objetivos Específicos.\n✓ Brindar asesoría, gestoría y defensa jurídica a la población indígena y afromexicana que se encuentre bajo procedimientos legales.\n✓ Proporcionar servicios de traducción en las cuatro lenguas indígenas en los procesos legales y ante otras instancias gubernamentales, a través de enlaces interculturales competentes, con pleno conocimiento de sus culturas, lenguas y variantes dialectales.\n✓ Realizar trámites administrativos ante la Coordinación Técnica del Sistema Estatal del Registro\nCivil, para asegurar la identidad y el ejercicio de derechos de la población indígena y afromexicana.\n✓ Fortalecer las capacidades de la población indígena y afromexicana, para el conocimiento y ejercicio de los derechos, mediante talleres de sensibilización y capacitación que propicien la no violencia contra las mujeres y talleres que difundan los derechos de las niñas, niños y adolescentes.\n5.3. Alcances.\nEste Programa es el instrumento de política pública del Gobierno del Estado de Guerrero que orienta las acciones para la promoción del desarrollo de los pueblos indígenas y afromexicano, el cual establece los objetivos, estrategias, líneas de acción, indicadores y metas a realizar en este ejercicio fiscal\n2017.\n6. Metas Físicas.\nLos servicios y acciones estarán sujetos a la disponibilidad presupuestal del programa, y son los siguientes:\nI. Formación y Capacitación\n✓ 1 Proyecto “Producción de plantas medicinales y hortalizas en huertos escolares\nindígenas”. (REFORMADO PÁRRAFO SEGUNDO, P.O. 98, 08 DE DICIEMBRE DE 2017)\n✓ 1 Simposio y Exposición sobre el pueblo Afromexicano; 1 Taller de Medicina\nTradicional; 25 Instrumentos musicales para bandas de música de viento; y Equipo de\n✓ 9 Talleres dirigidos a 450 personas, para la capacitación y sensibilización sobre igualdad de género.\n✓ 4 Talleres dirigidos a 250 niñas, niños y adolescentes sobre la difusión y conocimiento de los derechos de la niñez y la adolescencia.\n✓ 1 Taller dirigido a 40 personas, para el fortalecimiento de derechos culturales (Medicina\nTradicional).\nAFROMEXICANO, DE LA SECRETARÍA DE\nASUNTOS INDÍGENAS Y COMUNIDADES\nAFROMEXICANAS\nII. Defensa y asesoría jurídica:\n✓ 1000 Traducciones en las lenguas náhuatl, na'savi, me'phaa y ñomndaa, ante los órganos de procuración, administración e impartición de justicia, además de otras instituciones de los tres niveles de gobierno.\n✓ 2500 Asesorías jurídicas y representaciones legales tanto individuales como colectivas, ante instancias federales y estatales, propiciando en todo momento alternativas de conciliación, en las distintas materias, civil, familiar, penal, agrario, administrativo y amparo.\n✓ 8 Visitas de diagnóstico a los Centros Penitenciarios del estado, para identificar el número y situación jurídica de los internos indígenas y afromexicanos.\n✓ 50 Trámites de libertad anticipada de internos sentenciados por delitos del fuero común y federal, en favor de los internos indígenas y afromexicanos y gestión de traslados a favor de los internos indígenas y afromexicanos de los Centros Penitenciarios estatales y federales, cuando lo solicite el interno.\n✓ 1 pago de fianza en favor de población indígena. (REFORMADO PÁRRAFO SEXTO, P.O. 98, 08 DE\nDICIEMBRE DE 2017)\n✓ 2500 Trámites ante la Coordinación Técnica del Sistema Estatal del Registro Civil, consistentes en: expedición de actas de nacimiento, matrimonio y defunción; registro de nacimientos ordinarios o extemporáneos; aclaraciones, rectificaciones y nulidades administrativas; anotaciones marginales, constancias de inexistencia de registro y trámites para la obtención de la Cedula Única de Registro de Población (CURP).\n7. Programación Presupuestal\nI. Proyecto “Producción de plantas medicinales y hortalizas en huertos escolares indígenas”. (REFORMADA TABLA I, P.O. 98, 08 DE DICIEMBRE DE 2017)\nUNIDAD DE\nCAPITULO CONCEPTO PARTIDA CONCEPTO CANTIDAD COSTO UNITARIO TOTAL\nMEDIDA\n2110 Papelería Paquete 2 $4,000.00 $8,000.00\n2100\n2000 2120 Consumibles Paquete 2 $4,000.00 $8,000.00\n2600 2610 Combustibles Litro 400 $18.00 $7,200.00\n3000 3300 3750 Viáticos Día 20 $1,000.00 $20,000.00\n2000 2100 2170 Materia prima Paquete 4 $110,325 $441,300.50\nSUBTOTAL $484,500.50\nII. Simposio y Exposición sobre el pueblo afromexicano; Taller de Medicina Tradicional;\nInstrumentos musicales para bandas de música de viento; Equipo de cómputo e impresoras.\n(REFORMADA TABLA II, P.O. 98, 08 DE DICIEMBRE DE 2017)\nUNIDAD\nCOSTO\nUNITARIO\nMEDIDA\n2110 PAPELERIA PAQUETE 3 $3,750.00 $11,250.00\n2100 2120 COMSUMIBLES PAQUETE 3 $3,750.00 $11,250.00\n2170 MATERIA PRIMA Y UTENSILIOS PAQUETE 6 $6,000.00 $36,000.00\n2600 2610 COMBUSTIBLE LITRO 834 $18.00 $15,000.00\n3200 3290 RENTA DE MAMPARAS PIEZA 20 $464.00 $9,280.00\nAFROMEXICANO, DE LA SECRETARÍA DE\nASUNTOS INDÍGENAS Y COMUNIDADES\nAFROMEXICANAS\n3000 3340 HONORARIOS DE INSTRUCTORES SERVICIO 4 $7,180.00 $28,720.00\n{\"tabla_1\":{\"columnas\":[\"CAPITULO\",\"CONCEPTO\",\"PARTIDA\",\"CONCEPTO\",\"(sin encabezado)\",\"(sin encabezado)\",\"UNIDAD\",\"(sin encabezado)\",\"CANTIDAD\",\"COSTO\\nUNITARIO\",\"(sin encabezado)\",\"TOTAL\",\"(sin encabezado)\",\"(sin encabezado)\"],\"filas\":[{\"columna_1\":\"(sin dato)\",\"columna_2\":\"(sin dato)\",\"columna_3\":\"(sin dato)\",\"columna_4\":\"(sin dato)\",\"columna_5\":\"(sin dato)\",\"columna_6\":\"(sin dato)\",\"columna_7\":\"DE\",\"columna_8\":\"(sin dato)\",\"columna_9\":\"(sin dato)\",\"columna_10\":\"(sin dato)\",\"columna_11\":\"(sin dato)\",\"columna_12\":\"(sin dato)\",\"columna_13\":\"(sin dato)\",\"columna_14\":\"(sin dato)\"},{\"columna_1\":\"(sin dato)\",\"columna_2\":\"(sin dato)\",\"columna_3\":\"(sin dato)\",\"columna_4\":\"(sin dato)\",\"columna_5\":\"(sin dato)\",\"columna_6\":\"(sin dato)\",\"columna_7\":\"MEDIDA\",\"columna_8\":\"(sin dato)\",\"columna_9\":\"(sin dato)\",\"columna_10\":\"(sin dato)\",\"columna_11\":\"(sin dato)\",\"columna_12\":\"(sin dato)\",\"columna_13\":\"(sin dato)\",\"columna_14\":\"(sin dato)\"},{\"columna_1\":\"2000\",\"columna_2\":\"2100\",\"columna_3\":\"2110\",\"columna_4\":\"PAPELERIA\",\"columna_5\":\"(sin dato)\",\"columna_6\":\"PAQUETE\",\"columna_7\":\"(sin dato)\",\"columna_8\":\"(sin dato)\",\"columna_9\":\"2\",\"columna_10\":\"$ 4,500.00\",\"columna_11\":\"(sin dato)\",\"columna_12\":\"$9,0000\",\"columna_13\":\"(sin dato)\",\"columna_14\":\"(sin dato)\"},{\"columna_1\":\"(sin dato)\",\"columna_2\":\"(sin dato)\",\"columna_3\":\"2120\",\"columna_4\":\"COMSUMIBLES\",\"columna_5\":\"(sin dato)\",\"columna_6\":\"PAQUETE\",\"columna_7\":\"(sin dato)\",\"columna_8\":\"(sin dato)\",\"columna_9\":\"1\",\"columna_10\":\"$4,000.00\",\"columna_11\":\"(sin dato)\",\"columna_12\":\"$4,000.00\",\"columna_13\":\"(sin dato)\",\"columna_14\":\"(sin dato)\"},{\"columna_1\":\"(sin dato)\",\"columna_2\":\"2600\",\"columna_3\":\"2610\",\"columna_4\":\"COMBUSTIBLES\",\"columna_5\":\"(sin dato)\",\"columna_6\":\"LITRO\",\"columna_7\":\"(sin dato)\",\"columna_8\":\"(sin dato)\",\"columna_9\":\"1489\",\"columna_10\":\"$18.00\",\"columna_11\":\"(sin dato)\",\"columna_12\":\"$26,784.00\",\"columna_13\":\"(sin dato)\",\"columna_14\":\"(sin dato)\"},{\"columna_1\":\"3000\",\"columna_2\":\"3300\",\"columna_3\":\"3340\",\"columna_4\":\"SERVICIOS DE CAPACITACIÓN\\n(HONORARIOS PARA\\nINSTRUCTORES)\",\"columna_5\":\"(sin dato)\",\"columna_6\":\"PERSONA\",\"columna_7\":\"(sin dato)\",\"columna_8\":\"(sin dato)\",\"columna_9\":\"2\",\"columna_10\":\"$5,000.00\",\"columna_11\":\"(sin dato)\",\"columna_12\":\"$10,000\",\"columna_13\":\"(sin dato)\",\"columna_14\":\"(sin dato)\"},{\"columna_1\":\"(sin dato)\",\"columna_2\":\"(sin dato)\",\"columna_3\":\"3360\",\"columna_4\":\"MANTAS Y/O LONAS\",\"columna_5\":\"(sin dato)\",\"columna_6\":\"PIEZA\",\"columna_7\":\"(sin dato)\",\"columna_8\":\"(sin dato)\",\"columna_9\":\"2\",\"columna_10\":\"$1,000.00\",\"columna_11\":\"(sin dato)\",\"columna_12\":\"$2,000.00\",\"columna_13\":\"(sin dato)\",\"columna_14\":\"(sin dato)\"},{\"columna_1\":\"(sin dato)\",\"columna_2\":\"(sin dato)\",\"columna_3\":\"(sin dato)\",\"columna_4\":\"IMPRESIÓN DE CARPETAS\",\"columna_5\":\"(sin dato)\",\"columna_6\":\"MILLAR\",\"columna_7\":\"(sin dato)\",\"columna_8\":\"(sin dato)\",\"columna_9\":\"1\",\"columna_10\":\"$12,000.00\",\"columna_11\":\"(sin dato)\",\"columna_12\":\"$12,000.00\",\"columna_13\":\"(sin dato)\",\"columna_14\":\"(sin dato)\"},{\"columna_1\":\"(sin dato)\",\"columna_2\":\"(sin dato)\",\"columna_3\":\"(sin dato)\",\"columna_4\":\"IMPRESIÓN DE TRIPTICOS\\nINFORMATIVO\",\"columna_5\":\"(sin dato)\",\"columna_6\":\"MILLAR\",\"columna_7\":\"(sin dato)\",\"columna_8\":\"(sin dato)\",\"columna_9\":\"1\",\"columna_10\":\"$3,000. 00\",\"columna_11\":\"(sin dato)\",\"columna_12\":\"$3,000.00\",\"columna_13\":\"(sin dato)\",\"columna_14\":\"(sin dato)\"},{\"columna_1\":\"(sin dato)\",\"columna_2\":\"(sin dato)\",\"columna_3\":\"(sin dato)\",\"columna_4\":\"COPIAS\",\"columna_5\":\"(sin dato)\",\"columna_6\":\"PIEZA\",\"columna_7\":\"(sin dato)\",\"columna_8\":\"(sin dato)\",\"columna_9\":\"1,000\",\"columna_10\":\"$1.00\",\"columna_11\":\"(sin dato)\",\"columna_12\":\"$1,000.00\",\"columna_13\":\"(sin dato)\",\"columna_14\":\"(sin dato)\"},{\"columna_1\":\"(sin dato)\",\"columna_2\":\"3700\",\"columna_3\":\"3720\",\"columna_4\":\"PASAJES\",\"columna_5\":\"(sin dato)\",\"columna_6\":\"VIAJE\",\"columna_7\":\"(sin dato)\",\"columna_8\":\"(sin dato)\",\"columna_9\":\"10\",\"columna_10\":\"$550.00\",\"columna_11\":\"(sin dato)\",\"columna_12\":\"$5,550.00\",\"columna_13\":\"(sin dato)\",\"columna_14\":\"(sin dato)\"},{\"columna_1\":\"(sin dato)\",\"columna_2\":\"(sin dato)\",\"columna_3\":\"3780\",\"columna_4\":\"SERVICIOS INTEGRALES DE\\nTRASLADO Y VIATICOS\",\"columna_5\":\"(sin dato)\",\"columna_6\":\"PERSONA\",\"columna_7\":\"(sin dato)\",\"columna_8\":\"(sin dato)\",\"columna_9\":\"10\",\"columna_10\":\"$3,000.00\",\"columna_11\":\"(sin dato)\",\"columna_12\":\"$30,000.00\",\"columna_13\":\"(sin dato)\",\"columna_14\":\"(sin dato)\"},{\"columna_1\":\"(sin dato)\",\"columna_2\":\"(sin dato)\",\"columna_3\":\"3750\",\"columna_4\":\"VIATICOS\",\"columna_5\":\"(sin dato)\",\"columna_6\":\"DÍA\",\"columna_7\":\"(sin dato)\",\"columna_8\":\"(sin dato)\",\"columna_9\":\"15\",\"columna_10\":\"$1,000.00\",\"columna_11\":\"(sin dato)\",\"columna_12\":\"$15,000.00\",\"columna_13\":\"(sin dato)\",\"columna_14\":\"(sin dato)\"},{\"columna_1\":\"4000\",\"columna_2\":\"4400\",\"columna_3\":\"4410\",\"columna_4\":\"ALIMENTACION\",\"columna_5\":\"(sin dato)\",\"columna_6\":\"COMIDA\",\"columna_7\":\"(sin dato)\",\"columna_8\":\"(sin dato)\",\"columna_9\":\"985\",\"columna_10\":\"$100.00\",\"columna_11\":\"(sin dato)\",\"columna_12\":\"$98,000.00\",\"columna_13\":\"(sin dato)\",\"columna_14\":\"(sin dato)\"},{\"columna_1\":\"(sin dato)\",\"columna_2\":\"(sin dato)\",\"columna_3\":\"(sin dato)\",\"columna_4\":\"PASAJE\",\"columna_5\":\"(sin dato)\",\"columna_6\":\"SALIDAS\",\"columna_7\":\"(sin dato)\",\"columna_8\":\"(sin dato)\",\"columna_9\":\"490\",\"columna_10\":\"$ 300.00\",\"columna_11\":\"(sin dato)\",\"columna_12\":\"$147,000.00\",\"columna_13\":\"(sin dato)\",\"columna_14\":\"(sin dato)\"},{\"columna_1\":\"(sin dato)\",\"columna_2\":\"(sin dato)\",\"columna_3\":\"(sin dato)\",\"columna_4\":\"CAFETERIA\",\"columna_5\":\"(sin dato)\",\"columna_6\":\"PAQUETE\",\"columna_7\":\"(sin dato)\",\"columna_8\":\"(sin dato)\",\"columna_9\":\"16\",\"columna_10\":\"$2,500.00\",\"columna_11\":\"(sin dato)\",\"columna_12\":\"$20,000.00\",\"columna_13\":\"(sin dato)\",\"columna_14\":\"(sin dato)\"},{\"columna_1\":\"(sin dato)\",\"columna_2\":\"(sin dato)\",\"columna_3\":\"(sin dato)\",\"columna_4\":\"(sin dato)\",\"columna_5\":\"SUBTOTAL\",\"columna_6\":\"(sin dato)\",\"columna_7\":\"(sin dato)\",\"columna_8\":\"(sin dato)\",\"columna_9\":\"(sin dato)\",\"columna_10\":\"(sin dato)\",\"columna_11\":\"(sin dato)\",\"columna_12\":\"(sin dato)\",\"columna_13\":\"$383,784.00\",\"columna_14\":\"(sin dato)\"}]}}\nAFROMEXICANO, DE LA SECRETARÍA DE\nASUNTOS INDÍGENAS Y COMUNIDADES\nAFROMEXICANAS\n{\"tabla_2\":{\"columnas\":[\"CAPITULO\",\"CONCEPTO\",\"PARTIDA\",\"CONCEPTO\",\"(sin encabezado)\",\"(sin encabezado)\",\"UNIDAD\",\"(sin encabezado)\",\"CANTIDAD\",\"COSTO\\nUNITARIO\",\"TOTAL\",\"(sin encabezado)\"],\"filas\":[{\"columna_1\":\"(sin dato)\",\"columna_2\":\"(sin dato)\",\"columna_3\":\"(sin dato)\",\"columna_4\":\"(sin dato)\",\"columna_5\":\"(sin dato)\",\"columna_6\":\"(sin dato)\",\"columna_7\":\"DE\",\"columna_8\":\"(sin dato)\",\"columna_9\":\"(sin dato)\",\"columna_10\":\"(sin dato)\",\"columna_11\":\"(sin dato)\",\"columna_12\":\"(sin dato)\"},{\"columna_1\":\"(sin dato)\",\"columna_2\":\"(sin dato)\",\"columna_3\":\"(sin dato)\",\"columna_4\":\"(sin dato)\",\"columna_5\":\"(sin dato)\",\"columna_6\":\"(sin dato)\",\"columna_7\":\"MEDIDA\",\"columna_8\":\"(sin dato)\",\"columna_9\":\"(sin dato)\",\"columna_10\":\"(sin dato)\",\"columna_11\":\"(sin dato)\",\"columna_12\":\"(sin dato)\"},{\"columna_1\":\"1000\",\"columna_2\":\"1200\",\"columna_3\":\"1210\",\"columna_4\":\"Enlace Interculturales\",\"columna_5\":\"(sin dato)\",\"columna_6\":\"Persona\",\"columna_7\":\"(sin dato)\",\"columna_8\":\"(sin dato)\",\"columna_9\":\"12\",\"columna_10\":\"$94,500.00\",\"columna_11\":\"$1,134,000.00\",\"columna_12\":\"(sin dato)\"},{\"columna_1\":\"2000\",\"columna_2\":\"2100\",\"columna_3\":\"2110\",\"columna_4\":\"Papelería\",\"columna_5\":\"(sin dato)\",\"columna_6\":\"Paquete\",\"columna_7\":\"(sin dato)\",\"columna_8\":\"(sin dato)\",\"columna_9\":\"6\",\"columna_10\":\"$4,500.00\",\"columna_11\":\"$27,000.00\",\"columna_12\":\"(sin dato)\"},{\"columna_1\":\"(sin dato)\",\"columna_2\":\"(sin dato)\",\"columna_3\":\"2120\",\"columna_4\":\"Consumibles\",\"columna_5\":\"(sin dato)\",\"columna_6\":\"Paquete\",\"columna_7\":\"(sin dato)\",\"columna_8\":\"(sin dato)\",\"columna_9\":\"6\",\"columna_10\":\"$4,500.00\",\"columna_11\":\"$27,000.00\",\"columna_12\":\"(sin dato)\"},{\"columna_1\":\"(sin dato)\",\"columna_2\":\"2600\",\"columna_3\":\"2610\",\"columna_4\":\"Combustible\",\"columna_5\":\"(sin dato)\",\"columna_6\":\"Litro\",\"columna_7\":\"(sin dato)\",\"columna_8\":\"(sin dato)\",\"columna_9\":\"2865\",\"columna_10\":\"$18.00\",\"columna_11\":\"$51,570.00\",\"columna_12\":\"(sin dato)\"},{\"columna_1\":\"3300\",\"columna_2\":\"3100\",\"columna_3\":\"3180\",\"columna_4\":\"Paquetería\",\"columna_5\":\"(sin dato)\",\"columna_6\":\"Envió\",\"columna_7\":\"(sin dato)\",\"columna_8\":\"(sin dato)\",\"columna_9\":\"10\",\"columna_10\":\"$420.00\",\"columna_11\":\"$4,200.00\",\"columna_12\":\"(sin dato)\"},{\"columna_1\":\"(sin dato)\",\"columna_2\":\"3300\",\"columna_3\":\"3360\",\"columna_4\":\"Fotocopias\",\"columna_5\":\"(sin dato)\",\"columna_6\":\"Pieza\",\"columna_7\":\"(sin dato)\",\"columna_8\":\"(sin dato)\",\"columna_9\":\"5006\",\"columna_10\":\"$1.00\",\"columna_11\":\"$5,006.00\",\"columna_12\":\"(sin dato)\"},{\"columna_1\":\"(sin dato)\",\"columna_2\":\"3700\",\"columna_3\":\"3720\",\"columna_4\":\"Pasajes terrestres\",\"columna_5\":\"(sin dato)\",\"columna_6\":\"Persona\",\"columna_7\":\"(sin dato)\",\"columna_8\":\"(sin dato)\",\"columna_9\":\"30\",\"columna_10\":\"$200.00\",\"columna_11\":\"$6,000.00\",\"columna_12\":\"(sin dato)\"},{\"columna_1\":\"(sin dato)\",\"columna_2\":\"(sin dato)\",\"columna_3\":\"(sin dato)\",\"columna_4\":\"Pasaje\",\"columna_5\":\"(sin dato)\",\"columna_6\":\"Viajes\",\"columna_7\":\"(sin dato)\",\"columna_8\":\"(sin dato)\",\"columna_9\":\"10\",\"columna_10\":\"$520.00\",\"columna_11\":\"$5,200.00\",\"columna_12\":\"(sin dato)\"},{\"columna_1\":\"(sin dato)\",\"columna_2\":\"(sin dato)\",\"columna_3\":\"3750\",\"columna_4\":\"Viáticos\",\"columna_5\":\"(sin dato)\",\"columna_6\":\"Día\",\"columna_7\":\"(sin dato)\",\"columna_8\":\"(sin dato)\",\"columna_9\":\"28\",\"columna_10\":\"$1,000.00\",\"columna_11\":\"$28,000.00\",\"columna_12\":\"(sin dato)\"},{\"columna_1\":\"4000\",\"columna_2\":\"4400\",\"columna_3\":\"4410\",\"columna_4\":\"Pago de fianza\",\"columna_5\":\"(sin dato)\",\"columna_6\":\"Fianza\",\"columna_7\":\"(sin dato)\",\"columna_8\":\"(sin dato)\",\"columna_9\":\"1\",\"columna_10\":\"$9,951.50\",\"columna_11\":\"$9,951.50\",\"columna_12\":\"(sin dato)\"},{\"columna_1\":\"(sin dato)\",\"columna_2\":\"(sin dato)\",\"columna_3\":\"(sin dato)\",\"columna_4\":\"(sin dato)\",\"columna_5\":\"SUBTOTAL\",\"columna_6\":\"(sin dato)\",\"columna_7\":\"(sin dato)\",\"columna_8\":\"(sin dato)\",\"columna_9\":\"(sin dato)\",\"columna_10\":\"(sin dato)\",\"columna_11\":\"1,297,829.50\",\"columna_12\":\"(sin dato)\"}]}}\nAPROBADO\n1.1 Diplomado\n484,500.00 120,000 107,500 105,000 50,000 102,00 para certificación\nAFROMEXICANO, DE LA SECRETARÍA DE\nASUNTOS INDÍGENAS Y COMUNIDADES\nAFROMEXICANAS de enlaces interculturales\n1.2 Diplomado sobre el nuevo sistema de 466,406.00 200,000 69,000 75,400 72,000 50,000 justicia penal acusatorio\n1.3 Capacitación y sensibilización\n383,784.00 150,000 30,500 55,284, 55,000 93,000 de equidad de genero\n1.4 Taller de difusión de los\n159,586.00 50,000 54,580 55,000 derechos de la niñez\n1.5 Taller para el fortalecimiento de Derechos\n112,748.00 10,748 50,000 52,000\nCulturales\n(Medicina\nTradicional)\nACTIVIDAD 2.\nServicios de defensa, asesoría jurídica y trámites\n1,692,978.00 668,252 100,500 157,224 161,000 100,000 205,000 106,000 186,000 administrativos a favor de la población indígena y afromexicana.\nTOTAL 3,300,000.00 1,200,000 200,000 500,000 500,000 200,000 400,000 105,000 195,000\nTOTALES\n3,300,000.00 0.00 1,900,000.00 1,100,000.00 300,000.00\nTRIMESTRALES\nCALENDARIO DE AVTIVIDADES\nTOTAL\nPROGRAMA ENE FEB MAR ABR MAY JUN JUL AGO SEP OCT NOV DIC\nAPROBADO\n1.1 Diplomado para certificación de enlaces interculturales.\n1.2 Diplomado sobre el nuevo sistema de justicia penal acusatorio.\n1.3\nCapacitación y sensibilización de equidad de genero.\nAFROMEXICANO, DE LA SECRETARÍA DE\nASUNTOS INDÍGENAS Y COMUNIDADES\nAFROMEXICANAS\n1.4 Taller de difusión de los derechos de la niñez.\n1.5 Taller para fortalecimiento de Derechos\nCulturales\n(Medicina\nTradicional)\nActividad 2.\nServicios de defensa, asesoría jurídica y trámites administrativos a favor de la población indígena y afromexicana.\nAFROMEXICANO, DE LA SECRETARÍA DE\nASUNTOS INDÍGENAS Y COMUNIDADES\nAFROMEXICANAS\n8. Requisitos y Procedimientos de Acceso.\nAplica a los apoyos en materia de defensa jurídica, excarcelación de indígenas y afromexicanos, Intérpretes-Traductores en lenguas Indígenas y trámites ante la Coordinación Técnica del Sistema Estatal del Registro Civil, los cuales se sujetarán al procedimiento siguiente:\nLa SAICA, proporcionará los apoyos en materia de:\n✓ Asesoría jurídica y representación legal.\n✓ Peritos-Traductores en las cuatro lenguas indígenas del estado.\n✓ Talleres de capacitación y sensibilización de igualdad de género.\n✓ Talleres difusión de los derechos de las niñas, niños y adolescentes.\n✓ Trámites administrativos ante la Coordinación Técnica del Sistema Estatal del Registro Civil.\n✓ Pago de fianzas y/o medidas cautelares económicas y/o reparación de daños en favor de la población indígena y afromexicana.\n✓ Excarcelaciones de personas indígenas y afromexicanas internas en los distintos centros penitenciarios, en los casos que jurídicamente proceda.\nLos interesados deberán presentar solicitud de apoyo mediante escrito libre en original, ante las unidades administrativas de las Delegaciones Regionales u oficinas centrales de la SAICA, en el que se plasme básicamente, el nombre de (los) posible(s) o la beneficiario (s), tipo de apoyo que requiere y datos de localización.\nLa solicitud puede ser presentada por cualquier persona, institución pública u organización de la sociedad civil. Las unidades administrativas receptoras al recibir la solicitud de apoyo deberán verificar que cumpla con los requisitos y deberán entregar acuse de recibo, en su caso, indicaran los datos faltantes para que sean entregados en un plazo no mayor a 5 días hábiles.\nConsiderando el tipo de apoyo requerido y los criterios y requisitos de elegibilidad aplicable, denominados Guías de Operación y Procedimiento, las unidades administrativas receptoras analizarán y dictaminarán la procedencia o improcedencia del apoyo institucional hasta en un plazo máximo de 8 días hábiles contados a partir de la recepción de la solicitud y atendiendo la urgencia.\nAl concluir este periodo se le notificará al peticionario la respuesta a su solicitud, para el caso de ser aprobada, los o las solicitantes acudirán a la unidad administrativa receptora para formalizar el apoyo.\n8.1. Difusión.\nOperación del Decreto Número 426 del Presupuesto de Egresos del Estado de Guerrero para el Ejercicio\nFiscal 2017, estas Reglas de Operación, además de ser publicadas en el Periódico Oficial del Gobierno del\nEstado, estarán disponibles para la población en general en las oficinas centrales de la Secretaria de\nAsuntos Indígenas y Comunidades Afromexicana, ubicadas en calle Dr. Guillermo Soberón Acevedo,\nAFROMEXICANO, DE LA SECRETARÍA DE\nASUNTOS INDÍGENAS Y COMUNIDADES\nAFROMEXICANAS número 8, colonia salubridad, en la ciudad de Chilpancingo de los Bravo, Guerrero, teléfono 01 (747) 137\n06 20 y en sus Delegaciones Regionales:\nChilapa de Álvarez: Calle tercera norte, número 108, Colonia Centro.\nOmetepec, Guerrero: Calle Vicente Guerrero, Numero 26, Barrio de San Nicolás; y\nTlapa de Comonfort: Calle Morelos, número 124, Colonia Centro.\nAsí como en la página electrónica del Gobierno del Estado: www.guerrero.gob.mx y www.asuntosindigenas.guerrero.gob.mx, y en Facebook Secretaría de Asuntos Indígenas y Comunidades\nAfromexicanas.\n8.2. Requisitos de acceso\n✓ Ser originario de comunidades y municipios indígenas y afromexicanos, o auto adscribirse como tales, independientemente de su sexo, edad y filiación política o religiosa.\n✓ Solicitud por escrito, dirigida al titular de la SAICA, especificando el trámite o servicio que se demanda.\n✓ Constancias de identidad, expedida por la autoridad del pueblo originario que desciendan, o dependencia que corresponda.\n✓ Para el pago de medidas cautelares económicas y pagos de acuerdos reparatorios, se deberá exhibir acuerdo certificado en el cual se especifique el monto impuesto por la autoridad judicial conocedora.\n✓ Copia certificada de la declaración preparatoria del procesado en la que se declare hablante de alguna lengua indígena o se auto reconozca como integrante de un pueblo indígena o del afromexicano.\n8.3. Procedimientos de acceso\nUna vez que las y los solicitantes hayan cubierto los requisitos establecidos para recibir los servicios y apoyos descritos, recibirán los beneficios del programa de manera gratuita, rápida y expedita, de acuerdo a la urgencia y complejidad del problema planteado.\n8.4. Requisitos de permanencia y causales de baja o suspensión temporal.\nLa SAICA, a través de la Dirección General de Defensa y Asesoría Jurídica, vigilará que se cumplan las reglas de operación del programa \"Defensa y Asesoría Jurídica a Pueblos Indígenas y\nAfromexicano\", así como las obligaciones impuestas por la autoridad judicial, tratándose de indígenas y afromexicanos procesados, como principal requisito para obtener los beneficios permanentes del programa.\nSe suspenderá el apoyo, cuando el solicitante incurra en las siguientes faltas:\na) Incumplir lo establecido en los lineamientos, guías de operación y procedimientos.\nb) Presentar información o documentación alterada o falsa.\nc) Aplicar incorrectamente los recursos recibidos, conforme a los conceptos autorizados.\nAFROMEXICANO, DE LA SECRETARÍA DE\nASUNTOS INDÍGENAS Y COMUNIDADES\nAFROMEXICANAS\n8.5. Modos de entrega del beneficio.\nLa entrega de los beneficios del programa, se hará de forma directa a los/as solicitantes; una vez que las personas solicitantes, grupos, organizaciones sociales o comunidades hayan cubierto los requisitos establecidos para recibir los servicios y apoyos descritos, accederán a los beneficios del programa de manera gratuita, rápida y expedita, de acuerdo a la urgencia y complejidad del asunto planteado, lo cual será responsabilidad del personal del área jurídica de la SAICA, quien estará a cargo del cumplimiento de estas reglas de operación.\n9. Procedimientos de instrumentación.\n9.1. Operación.\n9.1.1. Para la ejecución del Programa Defensa y Asesoría Jurídica a Pueblos Indígenas y\nAfromexicano, la SAICA elaborará las Reglas de Operación y programación presupuestal. Asimismo brindará el apoyo para pago de medidas cautelares económicas y de reparación de daños por acuerdos reparatorios en delitos no graves, así como acompañamiento y representación jurídica para población indígena y afromexicana.\n9.1.2. La implementación del Programa estará a cargo de la Dirección General de Defensa y\nAsesoría Jurídica, la cual será responsable del correcto seguimiento y cumplimiento a los servicios prestados.\nLa vigencia de los servicios se realizará a partir de la entrada en vigor de los presentes lineamientos y, de acuerdo a las características no previsibles de la demanda ciudadana de servicios jurídicos, no aplica un calendario definido en la prestación de estos apoyos.\n9.1.2.1. Las personas e instancias interesadas deberán entregar, en las unidades administrativas receptoras, la solicitud de apoyo mediante escrito libre en original, en el que se indique, el nombre del (los) solicitante(s), tipo de apoyo que requiere y datos de localización del o los solicitantes, acompañada por los requisitos y formatos establecidos.\n9.1.2.2. El personal de las unidades administrativas receptoras deberá orientar a las y los solicitantes, para la elaboración y presentación de las solicitudes y la documentación establecida en el programa.\n9.1.2.3. Las Unidades Administrativas Receptoras al recibir cada solicitud deberán verificar que el expediente cumpla con los requisitos señalados en estas Reglas de Operación y deberán entregar el acuse de recibo a quien solicita el servicio, señalando los documentos o datos faltantes para que sean entregados en un plazo no mayor de 5 días hábiles.\n9.1.2.4. Una vez publicados los resultados, en los casos que aplique según el tipo de apoyo, las instancias ejecutoras o personas beneficiarias contarán con plazo máximo de 30 días naturales para acudir a las unidades administrativas receptoras, a firmar el convenio o acuerdo en el que se formalizarán los derechos y obligaciones entre las partes para la ejecución, administración, seguimiento y evaluación.\n9.1.2.5. La entrega de los recursos fiscales para el pago de fianza, reparación de daño o medida cautelar, se realizará a través de transferencia electrónica y de acuerdo a los términos establecidos en el instrumento jurídico suscrito por las partes, a fin de acatar la normatividad del programa y garantizar la rendición de cuentas y transparencia de los recursos y erogaciones realizadas.\nAFROMEXICANO, DE LA SECRETARÍA DE\nASUNTOS INDÍGENAS Y COMUNIDADES\nAFROMEXICANAS\n9.1.3. Los datos de las personas beneficiarias del Programa Defensa y Asesoría Jurídica a\nPueblos Indígenas y Afromexicano, así como la información que éste genere y administre estará regida por lo que establece la Ley Número 207 de Transparencia y Acceso a la Información Pública del Estado de\nGuerrero.\n9.1.4. Todos los formatos y papelería que se entregue a los/as solicitantes y beneficiarios del\nPrograma, así como los trámites a realizar serán totalmente gratuitos.\n9.2. Gastos de operación.\nDerivado de los Lineamientos para el Ejercicio y Comprobación del Gasto de la Administración\nPública Estatal, los gastos de operatividad para la ejecución del programa \"Defensa y Asesoría Jurídica a\nPueblos Indígenas y Afromexicano\" ascienden al 3% del monto total del programa, mismo que será comprobado de acuerdo a los lineamientos establecidos para ello.\nLa Secretaria para la operación y ejecución de los recursos deberá observar y atender las medidas que emita la Secretaria de Contraloría y Transparencia Gubernamental, el Instituto de Transparencia\nAcceso a la Información y Protección de Datos Personales del Estado de Guerrero (ITAIGRO), Instituto\nElectoral y de Participación Ciudadana del Estado de Guerrero y las demás autoridades competentes con la finalidad de impedir que los apoyos sean utilizados con fines politicos electorales.\n10. Transparencia.\n10.1. Difusión.\nConforme a las disposiciones establecidas en el apartado del Programa Sujetos a Reglas de\nOperación del Decreto Número 426 del presupuesto de egresos del Estado de Guerrero para el Ejercicio\nFiscal 2017, estas Reglas de Operación, además de ser publicadas en el Periódico Oficial del Gobierno del\nEstado, estarán disponibles para la población en general en las Oficinas Centrales y Delegaciones\nRegionales de la SAICA, asi como en las páginas electrónicas: www.guerrero.gob.mx y www.asuntosindígenas.guerrero.gob.mx o en la página de Facebook: Secretaria de Asuntos indígenas y comunidades Afromexicanas\n10.2. Blindaje electoral. atender las medidas que emita la Fiscalía Especializada para la Atención de Delitos Electorales (FEPADE) políticos electorales en el desarrollo de procesos electorales federales, estatales y municipales.\n\"Este programa es de carácter público no es patrocinado ni promovido por partido político alguno y sus recursos provienen de los impuestos que pagan todos los contribuyentes. Está prohibido el uso de este programa con fines políticos, electorales, de lucro y otros distintos a los establecidos. Quién haga uso indebido de los recursos de este programa deberá ser denunciado y sancionado de acuerdo con la ley aplicable y ante la autoridad competente\".\nAFROMEXICANO, DE LA SECRETARÍA DE\nASUNTOS INDÍGENAS Y COMUNIDADES\nAFROMEXICANAS\nEn cuanto a la publicidad en medios electrónicos, impresos, complementarios o de cualquier otra índole, vinculados con los Programas de comunicación social, se deberá incluir la siguiente leyenda: \"Este\nPrograma es público y queda prohibido su uso con fines partidistas o de promoción personal\".\n10.3. Supervisión y control.\nLa supervisión, control y evaluación del Programa Defensa y Asesoría Jurídica a Pueblos\nIndígenas y Afromexicano, será interna y estará a cargo de la Dirección General de Defensa y Asesoría\nJurídica, para lo cual se utilizará la Metodología del Marco Lógico y los resultados de la evaluación serán compartidos cada trimestre con la Secretaría de Planeación y Desarrollo Regional y la Secretaría de\nContralaría y Transparencia Gubernamental, mismos que se deberán presentar a más tardar 15 días hábiles posteriores a la terminación de cada trimestre, así como los informes sobre el presupuesto ejercido y en base a los indicadores de resultados previstos en este precepto.\nTodos los gastos generados en cada una de las actividades y acciones estarán soportados con la comprobación respectiva.\nLas Delegaciones Regionales y el área administrativa de la SAICA, llevarán a cabo el seguimiento al trabajo desarrollado por las instancias ejecutoras con relación a las metas comprometidas, con el propósito de verificar la aplicación correcta de los recursos otorgados y el cumplimiento de objetivos y metas establecidas.\nEl seguimiento se realizará mediante la revisión de los reportes presentados por las instancias ejecutoras; así como a través de evaluación y acompañamiento en campo de las acciones desarrolladas.\nEste informe deberá remitirse en original al área administrativa responsable en Oficinas Centrales de la\nSAICA, debidamente firmado por los responsables de las delegaciones.\n10.4. Mecanismos de Evaluación e Indicadores.\n10.4.1. Evaluación.\nLa SAICA tendrá la obligación de revisar, de manera interna, la correcta operación y aplicación de las presentes reglas de operación y, en caso necesario, podrá solicitar una evaluación externa por parte de una instancia con experiencia en el tema. adecuado desarrollo del programa, a efecto de corregir desfases o efectuar reasignaciones financieras con mismo programa o de otros que no hayan sido ejercidos en su momento, o bien que provengan de ahorros presupuestales.\nAFROMEXICANO, DE LA SECRETARÍA DE\nASUNTOS INDÍGENAS Y COMUNIDADES\nAFROMEXICANAS\nAFROMEXICANO, DE LA SECRETARÍA DE\nASUNTOS INDÍGENAS Y COMUNIDADES\nAFROMEXICANAS\n10.5. Auditoría.\nEste programa podrá ser auditado, a través de las instancias correspondientes en el ámbito de sus respectivas competencias del gobierno del estado, encargadas de vigilar la correcta aplicación de los recursos del erario público.\n10.6. Recursos no devengados.\nEl presupuesto no ejercido para los fines autorizados al 31 de diciembre de 2017, será reintegrado a la Dirección General de Tesorería, de la Secretaría de Finanzas y Administración del Estado de Guerrero.\n10.7. Contraloría social.\nLa SAICA, como instancia ejecutora, promoverá la contraloría social, la cual comprende un conjunto de acciones de control, vigilancia y evaluación que realizan los beneficiarios, ya sea de manera organizada o independiente, bajo un esquema de derechos y compromisos ciudadanos con el propósito de contribuir a que la gestión gubernamental se realice en términos de transparencia, eficacia y honradez.\nEntre dichas acciones destacan las siguientes:\na) Informar a la ciudadanía acerca de los apoyos otorgados y su costo.\nb) Capacitar a los beneficiarios para que se constituyan en instancias de vigilancia y evaluación social.\nc) Establecer espacios de comunicación (reuniones vecinales, asambleas comunitarias, entre otros).\nd) Promover la integración de organizaciones de la sociedad civil para realizar acciones de contraloría social.\ne) Instrumentar mecanismos de recepción y atención de quejas y denuncias. El Órgano Estatal de\nControl verificará en lo correspondiente la realización de dichas acciones.\n10.8. Procedimiento de queja o inconformidad ciudadana.\n10.8.1. Las quejas, denuncias, peticiones y sugerencias relativas a este programa, se realizarán de manera escrita, por comparecencia del interesado, por correo electrónico o vía telefónica, y para aquellas que sean escritas se depositarán en los buzones instalados en las oficinas centrales de la SAICA, ubicadas en la ciudad de Chilpancingo, así como en las delegaciones regionales, situadas en las ciudades de Tlapa de Comonfort, Chilapa de Álvarez y Ometepec.\nLa o el denunciante o quejoso deberá proporcionar los siguientes datos: Nombre del servidor público, Departamento de adscripción, objeto de la denuncia, nombre y domicilio del quejoso e identificación oficial.\n10.8.2. Las quejas, denuncias, peticiones y sugerencias relativas a este programa, se atenderán respuesta en un término máximo de 20 días hábiles.\n10.8.3. En caso de que la SAICA no resuelva la queja de las y los aspirantes o beneficiarios (as), éstos (as) podrán presentarla ante la Contraloría Social de la Secretaría de Contraloría y Transparencia\nGubernamental del Estado de Guerrero.\nAFROMEXICANO, DE LA SECRETARÍA DE\nASUNTOS INDÍGENAS Y COMUNIDADES\nAFROMEXICANAS\n10.9. Mecanismos de Exigibilidad\nLa SAICA, a través de sus unidades administrativas, firmarán un convenio o acuerdo en el que se formalizarán los derechos y obligaciones entre las partes para la ejecución del programa, en donde se estipulara los lineamientos para el cumplimiento que obligue a los beneficiados a dar cabal cumplimiento con sus obligaciones impuestas por la autoridad judicial que imponga las medidas cautelar que corresponda, generando un antecedente para futuros apoyos que soliciten a la institución,\n10.10. Acta de Entrega-Recepción\nNo aplica.\n11. Criterios de Selección y Elegibilidad.\n11.1. Método de selección de beneficiarios.\nLa población indígena y afromexicana, que solicite el apoyo del programa Defensa y Asesoría\nJurídica a Pueblos Indígenas y Afromexicano, a fin de que sean beneficiados con el pago de fianza y/o medida cautelar y/o reparación de daño, deberán cumplir con los requisitos siguientes:\n✓ Ser originarios (as) de comunidades y municipios indígenas y afromexicanos, o auto adscribirse como tales, independientemente de su sexo, edad, filiación política, religiosa o de otro tipo de organización social o estudiantil.\n✓ Copia certificada de la declaración preparatoria del procesado en la que se autorreconozca como miembro de un pueblo originario o afromexicano.\n✓ se deberá exhibir acuerdo certificado en el cual se especifique el monto impuesto, por la autoridad judicial conocedora.\n12. Mecánica de Operación.\n12.1. Instancia ejecutora.\nLa Secretaría de Asuntos Indígenas y Comunidades Afromexicanas será la instancia ejecutora del\nPrograma Defensa y Asesoría Jurídica a Pueblos Indígenas y Afromexicano, a través de la Dirección\nGeneral de Defensa y Asesoría Jurídica, de acuerdo a los lineamientos establecidos en estas Reglas de\nOperación para el ejercicio fiscal 2017.\n12.2. Instancia administrativa y/o normativa.\nReglas de Operación.\n12.3. Delimitación de atribuciones.\nRespetando las presentes reglas de operación, las instancias ejecutoras y administradoras del presente programa, se limitaran a realizar sus funciones establecidas, así como lo señalado en el\nAFROMEXICANO, DE LA SECRETARÍA DE\nASUNTOS INDÍGENAS Y COMUNIDADES\nAFROMEXICANAS reglamento interno de la institución. Esto con el objeto de armonizar el correcto desempeño y aplicación de los recursos asignados por el estado para los fines del programa.\n13. Derechos, Obligaciones y Sanciones de los Beneficiarios de Programas Sociales.\n13.1. Derechos.\n✓ Recibir un trato digno, respetuoso, oportuno, equitativo y de calidad.\n✓ Acceder a los apoyos que otorga el Programa de acuerdo con lo establecido en estos lineamientos y según disponibilidad presupuestal.\n✓ Recibir orientación de la SAICA para la presentación de solicitudes de apoyo e integración de expedientes sin costo alguno.\n13.2. Obligaciones.\n✓ Conducirse con verdad y aportar la información personal que la SAICA requiera (edad, sexo, domicilio, grado máximo de estudios, ingreso, dependientes económicos, lugar de nacimiento, lengua indígena que habla, pueblo indígena al que pertenece, CURP, acta de nacimiento, copia de identificación oficial) los cuales estarán protegidos conforme a la legislación en la materia.\n✓ Cumplir con los requisitos establecidos en estos Lineamientos.\n✓ Aportar la información que la SAICA requiera sobre los proyectos o acciones que les fueron financiadas.\n13.3. Sanciones.\nSe cancelara el apoyo solicitado, cuando se incumpla con lo establecido con los lineamientos y reglas de operación, en los siguientes casos:\nb) Presentar información o documentación alterada o falsa.\nc) No aplicar los recursos que se reciban conforme a los conceptos autorizados.\n14. Interpretación.\nLas presentes reglas de operación, se interpretaran de forma unilateral y clara de acuerdo a su contenido, lo anterior en el sentido que son especificas, entendióles en su contenido y alcance, cualquier aclaración de las mismas es responsabilidad de la instancia ejecutora y administrativa, el disipar las dudas de la población indígena y afromexicana, con respecto a la adecuada presentación de sus proyectos con los requisitos idóneos y la adecuada aplicación de los recursos económicos asignados para el fin propuesto.\nEL SECRETARIO DE ASUNTOS INDÍGENAS Y COMUNIDADES AFROMEXI CANAS.\nLIC. GILBERTO SOLANO ARREAGA.\nRúbrica.\nLIC. FELIPE SANCHEZ RAMÍREZ, DIRECTOR GENERAL DE LA DEFENSA Y ASESORÍA\nAFROMEXICANO, DE LA SECRETARÍA DE\nASUNTOS INDÍGENAS Y COMUNIDADES\nAFROMEXICANAS\nNUMERAL 32, FRACCIÓN XVIII, DE LA LEY ORGÁNICA DE LA ADMINISTRACIÓN PÚBLICA DEL\nESTADO DE GUERRERO NÚMERO 08, ASÍ COMO EL NUMERAL 16 FRACCIONES V, XXI Y XXII DEL\nREGLAMENTO INTERNO VIGENTE DE ESTA DEPENDENCIA.\nHAGO CONSTAR Y CERTIFICO\nQUE LAS PRESENTES COPIAS FOTOSTÁTICAS, COMPUESTAS DE 28 FOJAS ÚTILES SON\nCOPIAS FIELES SACADAS DE SUS ORIGINALES QUE OBRAN EN LOS ARCHIVOS DE ESTA\nSECRETARÍA, MISMAS QUE SE EXPIDEN PARA LOS USOS LEGALES A QUE HAYA LUGAR, EN LA\nCIUDAD DE CHILPANCINGO, GUERRERO, A LOS 31 DÍAS DEL MES DE MAYO DE 2017.\nATENTAMENTE.\nLIC. FELIPE SÁNCHEZ RAMÍREZ.\nDIRECTOR GENERAL DE LA DEFENSA Y ASESORÍA JURÍDICA.\nN. DE E. A CONTINUACIÓN SE TRANSCRIBEN LOS ARTÍCULOS TRANSITORIOS DE LOS\nDECRETOS DE REFORMAS A LA PRESENTE LEY.\nACUERDO POR EL QUE SE REFORMA EL SIMILAR, MEDIANTE EL QUE SE EMITEN LAS REGLAS\nDE OPERACIÓN DEL PROGRAMA 2. DEFENSA Y ASESORÍA JURÍDICA A PUEBLOS INDÍGENAS Y\nAFROMEXICANO, DE LA SECRETARÍA DE ASUNTOS INDÍGENAS Y COMUNIDADES\nAFROMEXICANAS, PARA EL EJERCICIO FISCAL 2017.\nPrimero.- El presente acuerdo entrará en vigor al día siguiente de su publicación en el Periódico\nSegundo.- Quedan reformadas las reglas de operación del Programa 2. Defensa y Asesoría de Guerrero, número 48, de fecha 16 de junio del presente año, en lo referente a lo señalado en el artículo",
  "ordenamiento": "REGLA",
  "jurisdiccion": "GUERRERO",
  "fuente_oficial": "DIARIO OFICIAL DE LA FEDERACION",
  "Fecha de Publicación": "22 DE MAYO DE 2018",
  "ULTIMA REFORMA PUBLICADA": "22 DE MAYO DE 2018",
  "status": "ABROGADA",
  "es_escaneado": false,
  "tiene_tablas": true,
  "materia": [
    "general"
  ]
}