{
  "titulo": "Acuerdo Parlamentario por Medio del Cual con Pleno Respeto al Estado de Derecho, A la División de Po",
  "Contenido": "DOCTOR SALVADOR ROGELIO ORTEGA MARTÍNEZ,\nPARA QUE RECONSIDERE LA PERMANENCIA DEL\nPERSONAL DE CONFIANZA, ANTE LA PETICIÓN DE\nRENUNCIA SOLICITADA\nTEXTO ORIGINAL.\nAcuerdo Parlamentario publicado en el Periódico Oficial del Gobierno del Estado No. 92, el\nMartes 18 de Noviembre de 2014.\nACUERDO PARLAMENTARIO POR MEDIO DEL CUAL CON PLENO RESPETO AL ESTADO DE\nDERECHO, A LA DIVISIÓN DE PODERES Y COMPETENCIAS, SE EXHORTA AL TITULAR DEL\nPODER EJECUTIVO DOCTOR SALVADOR ROGELIO ORTEGA MARTÍNEZ, PARA QUE\nRECONSIDERE LA PERMANENCIA DEL PERSONAL DE CONFIANZA, ANTE LA PETICIÓN DE\nRENUNCIA SOLICITADA.\nGuerrero.- Poder Legislativo.\nLA SEXAGÉSIMA LEGISLATURA AL HONORABLE CONGRESO DEL ESTADO LIBRE Y\nSOBERANO DE GUERRERO, EN NOMBRE DEL PUEBLO QUE REPRESENTA, Y:\nQue en sesión de fecha 06 de noviembre del 2014, la Diputada y Diputados integrantes de la\nComisión de Gobierno, presentaron la Propuesta de Acuerdo Parlamentario por el que la Sexagésima pleno respeto al estado de derecho, a la división de poderes y competencias, se exhorta al Titular del\nPoder Ejecutivo Doctor Salvador Rogelio Ortega Martínez, para que reconsidere la permanencia del personal de confianza, ante la petición de renuncia solicitada, en los siguientes términos:\n\"Que con fecha treinta de enero del año dos mil once se celebró en el estado de Guerrero, la para el periodo constitucional 2011-2015, resultando electo el ciudadano Ángel Heladio Aguirre Rivero.\nQue derivado del resultado de la elección, con fecha 1º de abril del mismo año, el ciudadano\nÁngel Heladio Aguirre Rivero, rindió protesta constitucional como Gobernador ante el Honorable\nEstado de Guerrero, integro en el Gabinete de la administración pública del estado a hombres y mujeres en beneficio de la sociedad guerrerense.\nDOCTOR SALVADOR ROGELIO ORTEGA MARTÍNEZ,\nPARA QUE RECONSIDERE LA PERMANENCIA DEL\nPERSONAL DE CONFIANZA, ANTE LA PETICIÓN DE\nRENUNCIA SOLICITADA\nQue por decreto aprobado en sesión de fecha veinticinco de octubre del año dos mil catorce, el\nPleno de la Sexagésima Legislatura al Honorable Congreso del Estado, resolvió conceder al ciudadano\nÁngel Heladio Aguirre Rivero, licencia para separarse del cargo y funciones de Gobernador\nConstitucional del Estado de Guerrero, lo anterior en términos del artículo 61 fracciones XX y XXI en\nGuerrero.\nQue en términos de lo anterior, ante la ausencia de Gobernador Constitucional, de acuerdo a lo del artículo 8º de la Ley Orgánica del Poder Legislativo de Guerrero, el Honorable Congreso del Estado en su función de Colegio Electoral designó al Doctor Salvador Rogelio Ortega Martínez, como\nGobernador del Estado.\nQue dentro de las primeras acciones administrativas y de gobierno del Gobernador designado por este H. Congreso del Estado, fue la de solicitar mediante escrito de fecha 30 de octubre del presente año, del cual dieron cuenta las redes sociales y los medios de comunicación, así como el reconocimiento del propio Gobernador, la renuncia formal y material de todo el personal de confianza del Gobierno del\nEstado.\nQue dicho documento en la parte que interesa señala:\n\"... Asunto: Se solicita apoyo institucional.\n...atendiendo a los protocolos de cada cambio de gobierno y en estricto apego a la normatividad que rige a la administración pública estatal, le solicito a la brevedad posible instruir al personal que ostenta cargos directivos de primer y segundo nivel, así como a todos aquellos que ocupen espacios de confianza, staff, asesoría, etc.,...., presentar con esta fecha su renuncia con carácter de irrevocable o simple....\nFirma. Guadalupe Vélez Almazán. Secretaria Particular del C. Gobernador...\"\nQue es de reconocer, que efectivamente cada nueva administración su Titular debe contar con el la sociedad, sin embargo, también es de considerarse que la designación del gobernador otorgada por estatal no se puede estar sujeto a la simulación o aprendizaje de los nuevos funcionarios designados.\nDOCTOR SALVADOR ROGELIO ORTEGA MARTÍNEZ,\nPARA QUE RECONSIDERE LA PERMANENCIA DEL\nPERSONAL DE CONFIANZA, ANTE LA PETICIÓN DE\nRENUNCIA SOLICITADA\nQue atento a lo anterior, este Poder legislativo no puede verse ajeno a la solicitud de renuncia y el despido masivo obligatorio que se pretende, pues en los puestos de confianza no solamente son los titulares de las Dependencias (Secretarios, Subsecretarios, Directores, Subdirectores, entre otros), también lo son aquellos hombres y mujeres que realizan los trabajos más elementales como de limpieza, secretarios y secretarias mecanógrafas, saca copias, técnicos, auxiliares administrativos, entre otros muchos más, que tienen una antigüedad que rebasa no solamente la administración vigente, sino muchas más, los cuales se verán afectados por dicha determinación, atentando con sus derechos laborales y humanos.\nQue adicionalmente la afectación más grave repercutirá en el grueso del personal de confianza de bajo nivel, pues muchos son el motor económico familiar, madres y padres jefes de familia y cuyo único ingreso es el que obtienen de su trabajo en la administración pública estatal.\nQue atento a lo anterior, también debe considerarse la repercusión administrativa, financiera y legal a la que se enfrentaría la administración y servicio público, pues se tendrían que cubrir las indemnizaciones constitucionales y legales de todos aquellos trabajadores que son despedidos, además de que se estaría en la improvisación y aprendizaje de los nuevos funcionarios.\nEn merito de lo anterior, es procedente que con pleno respeto al estado de derecho, a la división de poderes y competencias, se exhorte al Doctor Salvador Rogelio Ortega Martínez, Titular del Poder\nEjecutivo del Estado, para que reconsidere la solicitud de renuncia realizada al personal de confianza de la administración pública estatal, en razón de atentar contra derechos laborales y humanos adquiridos\".\nQue vertido lo anterior, en sesión de fecha 06 de noviembre del 2014, la Sexagésima Legislatura términos, la propuesta de Acuerdo Parlamentario presentada por la Diputada y Diputados integrantes de la Comisión de Gobierno.\nPor lo anteriormente expuesto y con fundamento en lo dispuesto por los artículos 61 fracción I de expide el siguiente:\nDOCTOR SALVADOR ROGELIO ORTEGA MARTÍNEZ,\nPARA QUE RECONSIDERE LA PERMANENCIA DEL\nPERSONAL DE CONFIANZA, ANTE LA PETICIÓN DE\nRENUNCIA SOLICITADA\nACUERDO PARLAMENTARIO POR MEDIO DEL CUAL CON PLENO RESPETO AL ESTADO\nDE DERECHO, A LA DIVISIÓN DE PODERES Y COMPETENCIAS, SE EXHORTA AL TITULAR DEL\nPODER EJECUTIVO DOCTOR SALVADOR ROGELIO ORTEGA MARTÍNEZ, PARA QUE\nRECONSIDERE LA PERMANENCIA DEL PERSONAL DE CONFIANZA, ANTE LA PETICIÓN DE\nRENUNCIA SOLICITADA.\nGuerrero, con pleno respeto al estado de derecho, a la división de poderes y competencias, se exhorte al\nDoctor Salvador Rogelio Ortega Martínez, Titular del Poder Ejecutivo del Estado, para que reconsidere la solicitud de renuncia realizada al personal de confianza de la administración pública estatal, en razón de atentar contra derechos laborales y humanos adquiridos.\nPRIMERO.- El presente Acuerdo Parlamentario surtirá efectos a partir de la fecha de su aprobación.\nSEGUNDO.- Comuníquese al Titular del Poder Ejecutivo, para su conocimiento y efectos conducentes\nTERCERO.- Publíquese en el Periódico Oficial del Gobierno del Estado, para su conocimiento general y efectos legales procedentes.\nDado en el Salón de Sesiones del Honorable Poder Legislativo, a los seis días del mes de noviembre del año dos mil catorce.\nDIPUTADA PRIMERA VICEPRESIDENTA\nEN FUNCIONES DE PRESIDENTA.\nJULIETA FERNÁNDEZ MÁRQUEZ.\nDIPUTADO SECRETARIO.\nROGER ARELLANO SOTELO.\nDIPUTADO SECRETARIO.\nARTURO BONILLA MORALES.",
  "ordenamiento": "ACUERDO",
  "jurisdiccion": "GUERRERO",
  "fuente_oficial": "DIARIO OFICIAL DE LA FEDERACION",
  "Fecha de Publicación": "18 de Noviembre de 2014",
  "ULTIMA REFORMA PUBLICADA": null,
  "status": "VIGENTE",
  "es_escaneado": false,
  "tiene_tablas": false,
  "materia": [
    "parlamentario"
  ]
}