{
  "titulo": "Acuerdo de Coordinación para la Distribución y Ejercicio de los Subsidios del Programa Hábitat, Vert",
  "Contenido": "ADMINISTRATIVO 20 DESARROLLO SOCIAL, QUE\nSUSCRIBEN POR UNA PARTE EL EJECUTIVO FEDERAL,\nA TRAVÉS DE LA SECRETARÍA DE DESARROLLO\nSOCIAL; Y POR LA OTRA EL EJECUTIVO DEL ESTADO Y\n18 MUNICIPIOS\nABROGADO POR CONCLUIDA SU VIGENCIA EL 31 DE DICIEMBRE DE 2011.\nTEXTO ORIGINAL\nAcuerdo publicado en el Periódico Oficial del Gobierno del Estado No. 74, el\nViernes 16 de Septiembre de 2011.\nACUERDO DE COORDINACIÓN PARA LA DISTRIBUCIÓN Y EJERCICIO DE LOS\nSUBSIDIOS DEL PROGRAMA HÁBITAT, VERTIENTE GENERAL, DEL RAMO\nADMINISTRATIVO 20 DESARROLLO SOCIAL, QUE SUSCRIBEN POR UNA PARTE\nEL EJECUTIVO FEDERAL, A TRAVÉS DE LA SECRETARÍA DE DESARROLLO\nSOCIAL, EN LO SUCESIVO \"LA SEDESOL\", REPRESENTADA EN ESTE ACTO POR\nLA SUBSECRETARIA DE DESARROLLO URBANO Y ORDENACIÓN DEL\nTERRITORIO, ARQ. SARA HALINA TOPELSON FRIDMAN, ASISTIDA POR EL\nDELEGADO FEDERAL DE LA SECRETARÍA DE DESARROLLO SOCIAL EN EL\nESTADO DE GUERRERO, LIC. EDDY ALBERTO MARTÍNEZ ALARCÓN; POR OTRA\nPARTE, EL EJECUTIVO DEL ESTADO DE GUERRERO, EN LO SUCESIVO \"EL\nESTADO\", REPRESENTADO POR EL SECRETARIO DE DESARROLLO SOCIAL;\nLIC. DAVID JIMÉNEZ RUMBO; EL SECRETARIO DE DESARROLLO URBANO Y\nOBRAS PÚBLICAS; ING. JEOVEL GUINTO GONZÁLEZ; Y EL COORDINADOR\nGENERAL DEL COMITÉ DE PLANEACIÓN PARA EL DESARROLLO DEL ESTADO\nDE GUERRERO (COPLADEG), LIC. CARLOS SÁNCHEZ BARRIOS; Y LOS\nMUNICIPIOS DE ACAPULCO DE JUÁREZ, ARCELIA, ATOYAC DE ÁLVAREZ,\nCHILAPA DE ÁLVAREZ, CHILPANCINGO DE LOS BRAVO, COYUCA DE BENÍTEZ,\nEDUARDO NERI, HUITZUCO DE LOS FIGUEROA, IGUALA DE LA INDEPENDENCIA,\nJOSÉ AZUETA, OMETEPEC, PETATLÁN, PUNGARABATO, TAXCO DE ALARCÓN,\nTECPAN DE GALEANA, TELOLOAPAN, TIXTLA DE GUERRERO Y TLAPA DE\nCOMONFORT, EN LO SUCESIVO \"LOS MUNICIPIOS\", REPRESENTADOS POR SUS\nPRESIDENTES MUNICIPALES, LOS CC. DR. MANUEL AÑORVE BAÑOS, PROFR.\nFRANCISCO SÁNCHEZ BENÍTEZ, C.P. CARLOS ARMANDO BELLO GÓMEZ, LIC.\nSERGIO DOLORES FLORES, LIC. HÉCTOR ANTONIO ASTUDILLO FLORES, LIC.\nMERCED BALDOVINO DIEGO, PROFR. MODESTO PÉREZ LEYVA, C. ISIDRO\nMIRANDA MADRID, DR. RAÚL TOVAR TAVERA, ING. ALEJANDRO BRAVO\nADMINISTRATIVO 20 DESARROLLO SOCIAL, QUE\nSUSCRIBEN POR UNA PARTE EL EJECUTIVO FEDERAL,\nA TRAVÉS DE LA SECRETARÍA DE DESARROLLO\nSOCIAL; Y POR LA OTRA EL EJECUTIVO DEL ESTADO Y\n18 MUNICIPIOS\nABARCA, C. EFRÉN ADAME MONTALVÁN, ARQ. JOSÉ ALBINO LACUNZA\nSANTOS, DR. GUSTAVO ADOLFO JUANCHI QUIÑONES, L.A.E. ÁLVARO BURGOS\nBARRERA, PROFR. NADÍN TORRALBA MEJÍA, PROFR. MARINO MIRANDA\nSALGADO, PROFR. JORGE LUIS CAMPOS ESPÍRITU Y LIC. WILLY REYES RAMOS,\nAL TENOR DE LOS SIGUIENTES ANTECEDENTES Y CLÁUSULAS:\nANTECEDENTES\nI.- El Eje 3 del Plan Nacional de Desarrollo 2007-2012, denominado \"Igualdad de\nOportunidades\", establece que \"La finalidad de la política social de esta Administración es lograr el desarrollo humano y el bienestar de los mexicanos a través de la igualdad de oportunidades. Para conducir a México hacia un desarrollo económico y social sustentable hay que resolver a fondo las graves diferencias que imperan en el país.\nGobierno y sociedad deben ser capaces de mejorar significativamente las condiciones de vida de quienes viven en la pobreza, es decir, casi la mitad de la población.\"\nII.- El objetivo 4 del Programa Sectorial de Desarrollo Social 2007-2012, establece: Mejorar la calidad de vida en las ciudades, con énfasis en los grupos sociales en condición de pobreza, a través de la provisión de infraestructura social y vivienda digna, así como consolidar ciudades eficientes, seguras y competitivas.\nIII.- El artículo 33 de la Ley de Planeación establece que el Ejecutivo Federal podrá convenir con los Gobiernos de las entidades federativas, satisfaciendo las formalidades que en cada caso procedan, la coordinación que se requiera a efecto de que los Gobiernos participen en la planeación nacional del desarrollo.\nIV.- El artículo 32 del Decreto de Presupuesto de Egresos de la Federación para de 2010, establece que los programas de subsidios del Ramo Administrativo 20\nDesarrollo Social se destinarán, en las entidades federativas, en los términos de las disposiciones aplicables, exclusivamente a la población en condiciones de pobreza, de vulnerabilidad, rezago y de marginación de acuerdo con los criterios oficiales dados a\nADMINISTRATIVO 20 DESARROLLO SOCIAL, QUE\nSUSCRIBEN POR UNA PARTE EL EJECUTIVO FEDERAL,\nA TRAVÉS DE LA SECRETARÍA DE DESARROLLO\nSOCIAL; Y POR LA OTRA EL EJECUTIVO DEL ESTADO Y\n18 MUNICIPIOS conocer por la Secretaría de Desarrollo Social, el Consejo Nacional de Población y a las evaluaciones del Consejo Nacional de Evaluación de la Política de Desarrollo Social.\nAsimismo, este artículo señala que el Programa Hábitat es un programa de subsidios del\nRamo Administrativo 20 Desarrollo Social.\nV.- El párrafo sexto del artículo 32 del Decreto de Presupuesto de Egresos de la\nFederación para el Ejercicio Fiscal 2011, establece que \"...se suscribirán acuerdos y convenios específicos y Anexos de ejecución en los que se establecerán: la distribución de los recursos de cada programa o región de acuerdo con sus condiciones de rezago, marginación y pobreza, indicando en lo posible la asignación correspondiente a cada municipio; las atribuciones y responsabilidades de la Federación, las entidades federativas y municipios, y las asignaciones presupuestarias de los órdenes de gobierno en que concurran en sujeción a los programas concertados.\"\nVI.- El objetivo general del. Programa Hábitat, a cargo de la Secretaria de\nDesarrollo Social, es contribuir a la superación de la pobreza y al mejoramiento de la calidad de vida de los habitantes de zonas urbanas marginadas en las que se presenta concentración de hogares en situación de pobreza patrimonial, en lo sucesivo\n\"Polígonos Hábitat\", al fortalecer y mejorar la organización y participación social, así como el entorno urbano de dichos asentamientos. Los \"Polígonos Hábitat\" son identificados por \"LA SEDESOL\" y constituyen el ámbito de actuación del Programa\nHábitat.\nVII.- La Dirección General de Programación y Presupuesto de la Secretaría de\nDesarrollo Social, mediante su oficio número OM/400/0541/2010 de fecha 23 de fiscal 2011.\nVIII.- La Subsecretaría de Desarrollo Urbano y Ordenación del Territorio, mediante el Oficio de Distribución de Subsidios del Programa Hábitat, número\nADMINISTRATIVO 20 DESARROLLO SOCIAL, QUE\nSUSCRIBEN POR UNA PARTE EL EJECUTIVO FEDERAL,\nA TRAVÉS DE LA SECRETARÍA DE DESARROLLO\nSOCIAL; Y POR LA OTRA EL EJECUTIVO DEL ESTADO Y\n18 MUNICIPIOS\nSecretaría de Desarrollo Social la distribución de los subsidios federales del Programa\nHábitat por entidad federativa para el ejercicio fiscal 2011.\nCon base en lo expuesto, y con fundamento en los artículos 40, 41, 43, 90, 115 y\n116 de la Constitución Política de los Estados Unidos Mexicanos; 32 de la Ley Orgánica de la Administración Pública Federal; 33, 34, 36 y 44 de la Ley de Planeación; 1, 4, 45, 54, 74, 75 y 77 de la Ley Federal de Presupuesto y Responsabilidad Hacendaría y 1, 85 y 176 de su Reglamento; 1, 4, 24 y 43 de la Ley General de Desarrollo Social y 3 fracción\nIII, 23, 25, 27, 40 y 41 de su Reglamento; 7, 8, 9, 48, 49, 50 y 51 de la Ley General de\nAsentamientos Humanos; 7 y demás aplicables de la Ley Federal de Transparencia y\nAcceso a la Información Pública Gubernamental; 1, 30, 31 y 32 del Decreto de\nPresupuesto de Egresos de la Federación para el Ejercicio Fiscal 2011; 6, 8, 12, 16, 36, 37, 44 y 45 del Reglamento Interior de la Secretaría de Desarrollo Social; en el Acuerdo por el que se modifican las Reglas de Operación del Programa Hábitat para el ejercicio fiscal 2011; así como en lo previsto por los artículos 1, 2, 3, 4 primer párrafo, 11, 18 y 23 de la Ley Orgánica de la Administración Pública del Estado de Guerrero; 31, 32, 33 y 34 de la. Ley Número 994 de Planeación del Estado de Guerrero; 26, 46 y 65 fracción III de la Ley Orgánica del Municipio Libre del Estado de Guerrero, y 7 fracciones I, II, V y XX de la Ley de Desarrollo Urbano del. Estado de Guerrero Número 211; \"LA SEDESOL”, \"EL\nESTADO\" y \"LOS MUNICIPIOS\", en lo sucesivo \"LAS PARTES”, han decidido establecer sus compromisos con arreglo a las siguientes:\nCLÁUSULAS\nCAPÍTULO I. DEL OBJETO\nPRIMERA. El presente Acuerdo de Coordinación tiene por objeto coordinar las acciones entre \"LA SEDESOL”, \"EL ESTADO” y \"LOS MUNICIPIOS\", para la operación del Programa Hábitat en las ciudades, zonas metropolitanas y \"Polígonos\nHábitat\" seleccionados y para el ejercicio de los subsidios federales y los recursos locales aportados, con el propósito de contribuir a la superación de la pobreza y al mejoramiento de la calidad de vida de los habitantes de zonas urbanas marginadas, al\nADMINISTRATIVO 20 DESARROLLO SOCIAL, QUE\nSUSCRIBEN POR UNA PARTE EL EJECUTIVO FEDERAL,\nA TRAVÉS DE LA SECRETARÍA DE DESARROLLO\nSOCIAL; Y POR LA OTRA EL EJECUTIVO DEL ESTADO Y\n18 MUNICIPIOS fortalecer y mejorar la organización y participación social, así como el entorno urbano de dichos asentamientos.\nSEGUNDA. \"LAS PARTES\" acuerdan que en la operación del Programa Hábitat y en el ejercicio de sus subsidios, se sujetarán a lo que establece la normatividad federal y local aplicable, las Reglas de Operación del Programa Hábitat para el ejercicio fiscal\n2011, en lo sucesivo \"Reglas de Operación\", y los Lineamientos de Operación del\nPrograma Hábitat vigentes, en lo sucesivo \"Lineamientos de Operación\", así como los instrumentos técnicos que se deriven de estos dos últimos.\nCAPITULO II. DE LAS CIUDADES, ZONAS METROPOLITANAS Y \"POLÍGONOS\nHÁBITAT\" SELECCIONADOS\nTERCERA. \"LAS PARTES\" acuerdan que los subsidios federales y los recursos locales aportados en el marco del Programa Hábitat se ejercerán en las ciudades, zonas metropolitanas y \"Polígonos Hábitat\" seleccionados, que se señalan en el Anexo I de este Acuerdo de Coordinación, denominado \"Ciudades, Zonas Metropolitanas y\nPolígonos Hábitat Seleccionados\", el cual es suscrito únicamente por el Delegado\nFederal de \"LA SEDESOL\", el Secretario de Desarrollo Urbano y Obras Públicas del\nEstado de Guerrero, el Coordinador General del Comité de Planeación para el Desarrollo del Estado de Guerrero y por los Presidentes Municipales.\nCUARTA. \"LA SEDESOL\" promoverá la concurrencia de acciones de otras instituciones en los \"Polígonos Hábitat\" seleccionados, tanto del propio sector de\nFederal. \"LAS PARTES\" acuerdan apoyar la ejecución de dichas acciones.\nCAPÍTULO III. DE LOS SUBSIDIOS FEDERALES\nQUINTA. \"LAS PARTES\" acuerdan que los subsidios federales destinados a la entidad federativa se distribuyen por municipio, de conformidad con lo señalado en el\nAnexo II de este Acuerdo de Coordinación, denominado \"Subsidios Federales por\nADMINISTRATIVO 20 DESARROLLO SOCIAL, QUE\nSUSCRIBEN POR UNA PARTE EL EJECUTIVO FEDERAL,\nA TRAVÉS DE LA SECRETARÍA DE DESARROLLO\nSOCIAL; Y POR LA OTRA EL EJECUTIVO DEL ESTADO Y\n18 MUNICIPIOS\nMunicipio\", el cual es suscrito únicamente por el Delegado Federal de \"LA SEDESOL\", el Secretario de Desarrollo Urbano y Obras Públicas del Estado de Guerrero, el\nCoordinador General del Comité de Planeación para el Desarrollo del Estado de\nGuerrero y por los Presidentes Municipales firmantes.\nSEXTA. La ministración de los subsidios federales para el Programa Hábitat se efectuará considerando el calendario autorizado por la Secretaría de Hacienda y Crédito\nPúblico, a través del Sistema Integral de Administración Financiera Federal (SIAFF) y el\nSistema de Contabilidad y Presupuesto (SICOP).\nSÉPTIMA. De conformidad con lo establecido en las \"Reglas de Operación\", \"EL ESTADO\", \"LOS MUNICIPIOS\" y las Delegaciones Federales de \"LA SEDESOL\" podrán constituirse en ejecutores del Programa Hábitat. Los ejecutores serán los responsables del ejercicio y comprobación de los subsidios federales y de los recursos locales aportados al Programa.\nOCTAVA. \"LAS PARTES\" acuerdan que los subsidios federales destinados a la entidad federativa que no se comprometan en las fechas señaladas en el Oficio de\nDistribución de Subsidios del Programa Hábitat, podrán ser reasignados por \"LA\nSEDESOL\" a otros municipios del mismo Estado o de otras entidades federativas.\nDichas reasignaciones presupuestarias serán notificadas por la Delegación Federal de\n\"LA SEDESOL\" al Secretario de Desarrollo Urbano y Obras Públicas del Estado de\nGuerrero, al Coordinador General del Comité de Planeación para el Desarrollo del\nEstado de Guerrero y a \"LOS MUNICIPIOS\" que correspondan.\nCAPITULO IV. DE LOS RECURSOS APORTADOS\nPOR \"EL ESTADO\" Y POR \"LOS MUNICIPIOS\"\nNOVENA. \"EL ESTADO\" y \"LOS MUNICIPIOS\", se comprometen a aportar recursos financieros para las obras y acciones apoyadas por el Programa Hábitat, de conformidad con lo señalado en las \"Reglas de Operación\", los \"Lineamientos de\nOperación\" y el Anexo Técnico de cada proyecto (Formato PH-01). Estos recursos\nADMINISTRATIVO 20 DESARROLLO SOCIAL, QUE\nSUSCRIBEN POR UNA PARTE EL EJECUTIVO FEDERAL,\nA TRAVÉS DE LA SECRETARÍA DE DESARROLLO\nSOCIAL; Y POR LA OTRA EL EJECUTIVO DEL ESTADO Y\n18 MUNICIPIOS serán distribuidos conforme a lo señalado en el Anexo III de este Acuerdo de\nCoordinación, denominado \"Aportaciones de Recursos Locales por Municipio\", el cual es suscrito únicamente por el Delegado Federal de \"LA SEDESOL\", el Secretario de Desarrollo Urbano y Obras Públicas del Estado de Guerrero, el Coordinador General del Comité de Planeación para el Desarrollo del Estado de Guerrero y por los\nPresidentes Municipales.\nCAPITULO V. DE LAS RESPONSABILIDADES\nDECIMA. \"LA SEDESOL\" se compromete a:\na) Apoyar con subsidios federales la ejecución del Programa Hábitat en las ciudades, zonas metropolitanas y \"Polígonos Hábitat\" seleccionados, con la participación que corresponda a \"EL ESTADO\" y a \"LOS MUNICIPIOS\".\nb) Aprobar las obras y acciones, así como la radicación de los subsidios federales, de manera oportuna y por conducto de la Delegación Federal de \"LA, SEDESOL\" en la entidad federativa.\nc) Aplicar los subsidios federales y los recursos locales aportados, cuando funja como ejecutor, conforme a lo señalado en la Ley Federal de Presupuesto y\nResponsabilidad Hacendaría, el Decreto de Presupuesto de Egresos de la Federación para el Ejercicio Fiscal 2011, la Ley de Obras Públicas y Servicios Relacionados con las\nMismas, la Ley de Adquisiciones, Arrendamientos y Servicios del Sector Público Federal, las \"Reglas de Operación\", los \"Lineamientos de Operación\", el Anexo Técnico del proyecto (Formato PH-01), así como a lo dispuesto en otras normas federales y locales aplicables.\nd) Efectuar oportunamente, por conducto de la Delegación Federal de \"LA\nSEDESOL\", el seguimiento de avances y resultados físicos y financieros de los proyectos, con base en la información de los expedientes técnicos, la registrada en el\nSistema Integral de Información de los Programas Sociales (SII-PSO) y la obtenida en\nADMINISTRATIVO 20 DESARROLLO SOCIAL, QUE\nSUSCRIBEN POR UNA PARTE EL EJECUTIVO FEDERAL,\nA TRAVÉS DE LA SECRETARÍA DE DESARROLLO\nSOCIAL; Y POR LA OTRA EL EJECUTIVO DEL ESTADO Y\n18 MUNICIPIOS las verificaciones que realice en campo.\ne) Apoyar al ejecutor en la integración y operación de instancias de contraloría social, de conformidad con lo establecido en la Ley General de Desarrollo Social, su\nReglamento, las \"Reglas de Operación\" y en el Acuerdo por el que se establecen los\nLineamientos para la Promoción y Operación de la Contraloría Social, en los Programas\nFederales de Desarrollo Social emitidos por la. Secretaría de la Función Pública.\nDÉCIMA PRIMERA. \"EL ESTADO\" y \"LOS MUNICIPIOS\" se comprometen a:\na) Aplicar los subsidios federales y los recursos locales aportados del Programa\nHábitat, cuando funja como ejecutor, en las ciudades, zonas metropolitanas y \"Polígonos\nHábitat\" seleccionados, conforme a lo señalado en la Ley Federal de Presupuesto y\nResponsabilidad Hacendaría, el Decreto de Presupuesto de Egresos de la Federación para el Ejercicio Fiscal 2011, la Ley de Obras Públicas y Servicios Relacionados con las\nMismas, la ley de Adquisiciones, Arrendamientos y Servicios del Sector Público Federal, las \"Reglas de Operación\", los \"Lineamientos de Operación, el Anexo Técnico del proyecto (Formato PH-01), así como a lo dispuesto en otras normas federales y locales aplicables.\nb) Apoyar el cumplimiento de los objetivos y las metas del Programa Hábitat.\nc) Elaborar y mantener actualizado un registro de los subsidios federales y de los recursos locales aportados y ejercidos, de conformidad con la normatividad aplicable.\nd) Garantizar, en su caso, la aportación que corresponda a los beneficiarios, conforme a lo señalado en las \"Reglas de Operación\".\ne) Mantener en operación los Inmuebles Apoyados por Hábitat para los fines acordados con \"LA SEDESOL\", al menos durante los cinco años posteriores a la fecha en que recibieron los subsidios federales para su construcción, mejoramiento o equipamiento, con el fin de garantizar la permanencia de los servicios sociales que\nADMINISTRATIVO 20 DESARROLLO SOCIAL, QUE\nSUSCRIBEN POR UNA PARTE EL EJECUTIVO FEDERAL,\nA TRAVÉS DE LA SECRETARÍA DE DESARROLLO\nSOCIAL; Y POR LA OTRA EL EJECUTIVO DEL ESTADO Y\n18 MUNICIPIOS ofrecen.\nf) Reintegrar a la Tesorería de la Federación, conforme a lo establecido en la normatividad federal aplicable, los subsidios federales no ejercidos al cierre del ejercicio fiscal, los recursos no comprobados en la fecha límite establecida para este fin, así como los rendimientos financieros que, en su caso, se hubieran generado.\ng) Proporcionar oportunamente el mantenimiento de las obras o equipos financiados con recursos del Programa Hábitat; hacer explícito en el acta de entregarecepción o en el informe de resultados, cuando funjan como ejecutores, el compromiso de dar mantenimiento, conservar, vigilar y sufragar la continua y adecuada operación de las obras y/o equipos financiados con recursos de este Programa; realizar todas las acciones tendientes a conservar en buen estado los bienes muebles adquiridos y los bienes inmuebles construidos o mejorados, así como asegurar dichos bienes ante una institución de seguros autorizada.\nh) En caso de que los bienes muebles financiados con recursos del Programa sean sustraídos indebidamente del lugar donde se ubicaban o habían sido instalados, el ejecutor efectuará lo conducente para restituirlos en la misma cantidad, calidad y especie; independientemente de realizar las gestiones jurídicas y administrativas que procedan.\ni) Proporcionar a las instancias de fiscalización, control y auditoría, correspondientes, la información requerida, así como otorgarles las facilidades necesarias, para que lleven a cabo sus acciones en dichas materias.\nCAPÍTULO VI. DEL SEGUIMIENTO, CONTROL Y EVALUACIÓN DEL PROGRAMA\nDÉCIMA SEGUNDA. \"EL ESTADO\" y \"LOS MUNICIPIOS\", cuando sean ejecutores del Programa Hábitat, se comprometen a cumplir con las responsabilidades señaladas en las \"Reglas de Operación\" y en los \"Lineamientos de Operación\", y otorgar las facilidades necesarias a \"LA SEDESOL\" para que ésta realice visitas de\nADMINISTRATIVO 20 DESARROLLO SOCIAL, QUE\nSUSCRIBEN POR UNA PARTE EL EJECUTIVO FEDERAL,\nA TRAVÉS DE LA SECRETARÍA DE DESARROLLO\nSOCIAL; Y POR LA OTRA EL EJECUTIVO DEL ESTADO Y\n18 MUNICIPIOS seguimiento a las obras y acciones realizadas con subsidios federales, así como para tener acceso a equipos, materiales, información, registros y documentos que estime pertinente conocer y que estén relacionados con la ejecución de las mismas.\nCuando \"LA SEDESOL\" detecte que el ejecutor incurrió en desviaciones en el ejercicio de los subsidios federales o en incumplimiento a lo convenido, inclusive en ejercicios fiscales anteriores, \"LA SEDESOL\" podrá suspender la ministración de recursos autorizados al ejecutor en el ejercicio fiscal 2011, cancelar los proyectos aprobados y, en su caso, solicitar el reintegro de los subsidios, según corresponda. Lo anterior, sin menoscabo de que \"LA SEDESOL\" realice las acciones administrativas y legales que procedan.\nDÉCIMA TERCERA. \"EL ESTADO\" y \"LOS MUNICIPIOS\", cuando sean ejecutores del Programa Hábitat, asumen el compromiso de proporcionar a \"LA\nSEDESOL\" la información sobre los avances y resultados del Programa Hábitat, conforme a lo siguiente:\na) Actualizar mensualmente la información registrada en el SIIPSO sobre los avances físicos y financieros de todos los proyectos apoyados por el Programa.\nb) Reportar trimestralmente a la Delegación Federal de \"LA SEDESOL\", durante los primeros cinco días hábiles del mes inmediato al trimestre que concluye, los avances físico-financieros de los proyectos aprobados.\nc) Informar a la Delegación Federal de \"LA SEDESOL\", por conducto del\nSIIPSO, de las obras y acciones concluidas, así como de sus resultados físicos y financieros, a más tardar a los treinta días naturales a la fecha de su conclusión. federativa o al municipio correspondiente, al concluir la obra o acción, en un plazo que no exceda los treinta días naturales siguientes, copia del acta de entrega-recepción o del informe de resultados.\nADMINISTRATIVO 20 DESARROLLO SOCIAL, QUE\nSUSCRIBEN POR UNA PARTE EL EJECUTIVO FEDERAL,\nA TRAVÉS DE LA SECRETARÍA DE DESARROLLO\nSOCIAL; Y POR LA OTRA EL EJECUTIVO DEL ESTADO Y\n18 MUNICIPIOS\ne) Convocar oportunamente a la comunidad beneficiada, a la.Delegación Federal de \"LA SEDESOL\", así como al gobierno de la entidad federativa o al municipio, para que en los actos de entrega-recepción de las obras y acciones se encuentren presentes representantes de dichas instancias.\nf) Elaborar e imprimir, por conducto del SIIPSO, el informe de cierre de ejercicio.\nEn éste se considerarán todos aquellos movimientos presupuestarios de los subsidios en el ejercicio fiscal y deberá coincidir con lo registrado en el Sistema Integral de\nPresupuesto y Contabilidad (SIPREC) o el Sistema de Contabilidad y Presupuesto\n(SICOP).\nDÉCIMA CUARTA. \"LAS PARTES\" colaborarán, en el ámbito de sus respectivas competencias, en la operación de un sistema de información, administrado por \"LA\nSEDESOL\", que apoye las actividades de seguimiento, control y evaluación del\nPrograma Hábitat.\nDÉCIMA QUINTA. Las actividades de control y auditoría de los subsidios federales corresponderán al Órgano Interno de Control en la Secretaría de Desarrollo\nSocial; a la Secretaría de la Función Pública, en coordinación con los órganos de control de los gobiernos de las entidades federativas; así como a la Auditoria Superior de la\nFederación, conforme a las atribuciones que les confiere la Ley Orgánica de la\nAdministración Pública Federal, la Ley de Fiscalización y Rendición de Cuentas de la\nFederación y demás normatividad aplicable.\nDÉCIMA SEXTA. \"EL ESTADO\" y \"LOS MUNICIPIOS\" se comprometen a apoyar a \"LA SEDESOL\" en las acciones que se lleven a cabo para la evaluación externa del Programa Hábitat conforme lo establecen las \"Reglas de Operación\" y demás normatividad aplicable.\nADMINISTRATIVO 20 DESARROLLO SOCIAL, QUE\nSUSCRIBEN POR UNA PARTE EL EJECUTIVO FEDERAL,\nA TRAVÉS DE LA SECRETARÍA DE DESARROLLO\nSOCIAL; Y POR LA OTRA EL EJECUTIVO DEL ESTADO Y\n18 MUNICIPIOS\nCAPÍTULO VII.\nESTIPULACIONES FINALES\nDÉCIMA SÉPTIMA. Cuando las Secretarias de Hacienda y Crédito Público, de la\nFunción Pública o de Desarrollo Social, en el ámbito de sus respectivas competencias, detecten faltas de comprobación, desviaciones, incumplimiento a lo convenido, o incumplimiento en la entrega oportuna de información relativa a avances y metas alcanzadas, \"LA SEDESOL\", después de escuchar la opinión del gobierno de la entidad federativa correspondiente, podrá suspender la radicación de los recursos federales e inclusive solicitar su reintegro, así como los rendimientos financieros que, en su caso, se hubieran generado, sin perjuicio de lo establecido en la normatividad aplicable.\nEn caso de que \"LA SEDESOL\" detecte condiciones inadecuadas de mantenimiento o de operación en obras financiadas con recursos del Programa en el ejercicio en curso o en ejercicios anteriores, \"LA SEDESOL\" podrá suspender la ministración de recursos autorizados al ejecutor en el ejercicio fiscal 2011. En caso de persistir la situación detectada, \"LA SEDESOL\" podrá cancelar los proyectos aprobados en 2011 y solicitar el reintegro de los subsidios que hubieran sido ministrados.\nDÉCIMA OCTAVA. Los Anexos I, II y III del presente Acuerdo de Coordinación, se podrán modificar de común acuerdo por las partes, en tanto la Secretaría de Hacienda cada entidad federativa. su suscripción por parte del Delegado Federal de la “SEDESOL”, el Secretario de\nDesarrollo Urbano y Obras Publicas del Estado de Guerrero, el Coordinador General del\nMunicipales.\nDÉCIMA NOVENA. Para dar transparencia en el ejercicio de los recursos federales, “LA SEDESOL”, “EL ESTADO” Y “LOS MUNICIPIOS”, convienen que en\nADMINISTRATIVO 20 DESARROLLO SOCIAL, QUE\nSUSCRIBEN POR UNA PARTE EL EJECUTIVO FEDERAL,\nA TRAVÉS DE LA SECRETARÍA DE DESARROLLO\nSOCIAL; Y POR LA OTRA EL EJECUTIVO DEL ESTADO Y\n18 MUNICIPIOS todas las actividades de difusión y publicidad que lleven a cabo los ejecutores, relativas a obras y acciones del Programa Hábitat y apoyadas parcial o totalmente con subsidios federales, se deberá mencionar expresamente el monto de dicha aportación de recursos federales, así como incluir los logotipos de “LA SEDESOL”, de la Estrategia Vivir Mejor y del Programa Hábitat en los impresos y elementos gráficos y cualquier medio de difusión que sea utilizado para tal efecto, como son letrero, placas, mamparas, templetes, gallardetes, carteles, trípticos y otros similares. Los logotipos de “LA SEDESOL”, de la\nEstrategia Vivir Mejor y del Programa Hábitat deberán ser, al menos, del mismo tamaño que los logotipos de las instancias locales participantes.\nConforme a la Ley General de Desarrollo Social y el Decreto de Presupuesto de\nEgresos de la Federación para el Ejercicio Fiscal 2011, la publicidad y la información relativa a las asociaciones relacionadas deberá identificarse con el Escudo Nacional en los términos que establece la Ley sobre el Escudo, la Bandera y el Himno Nacionales e incluir la siguiente leyenda “Este programa es público, ajeno a cualquier partido político.\nQueda prohibido el uso para fines distintos al desarrollo social”.\nLos ejecutores deberán instalar letreros y placas en las obras y acciones apoyadas con recursos del Programa Hábitat, de conformidad con lo señalado en las\n“Reglas de operación” y en los “Lineamientos de Operación”. El costo de la elaboración y colocación de los letreros y las placas será con cargo a los recursos del proyecto correspondiente; el Ejecutor deberá mantenerlos en buenas condiciones. En el caso de que las placas sean dañadas o sustraídas, el Ejecutor, con cargo a sus recursos, deberá reponerlas.\nVIGÉSIMA. Con el propósito de impedir que el Programa Hábitat sea utilizado con fines político electorales durante el desarrollo de procesos electorales federales, estatales y municipales, “LAS PARTES” acuerdan que en la ejecución de este\nPrograma y en el ejercicio de sus recursos federales y locales, llevarán a cabo las\nGeneral y Comisionado para la Transparencia de \"LA SEDESOL\".\nADMINISTRATIVO 20 DESARROLLO SOCIAL, QUE\nSUSCRIBEN POR UNA PARTE EL EJECUTIVO FEDERAL,\nA TRAVÉS DE LA SECRETARÍA DE DESARROLLO\nSOCIAL; Y POR LA OTRA EL EJECUTIVO DEL ESTADO Y\n18 MUNICIPIOS\nVIGÉSIMA PRIMERA. El presente Acuerdo de Coordinación se podrá dar por terminado de manera anticipada por cualquiera de las siguientes causas:\na) No cumplir en tiempo y forma con los compromisos pactados en este Acuerdo de Coordinación y sus Anexos, lo establecido en la Ley Federal de Presupuesto y\nResponsabilidad Hacendaría, el Decreto de Presupuesto de Egresos de la Federación para el Ejercicio Fiscal 2011, la Ley de Obras Públicas y Servicios Relacionados con las\nMismas, la Ley de Adquisiciones, Arrendamientos y Servicios del Sector Público Federal, las \"Reglas de Operación\", los \"Lineamientos de Operación\", el Anexo Técnico del proyecto (Formato PH-01), así como a lo dispuesto en otras normas federales y locales aplicables.\nb) La aplicación de los subsidios federales asignados por medio de este Acuerdo de Coordinación a \"EL ESTADO\" y a \"LOS MUNICIPIOS\" a fines distintos de los pactados.\nc) La falta de entrega de información, reportes y demás documentación prevista en este Acuerdo de Coordinación y en los diversos instrumentos derivados del mismo.\nVIGÉSIMA SEGUNDA. Las partes realizarán las acciones necesarias para cumplir con los compromisos pactados en el presente Acuerdo de Coordinación. De presentarse casos fortuitos o de fuerza mayor, que motiven el incumplimiento, la correlativas, debiendo comunicar dichas circunstancias por escrito a la brevedad posible, a través de las instancias que suscriben el presente Acuerdo de Coordinación.\nVIGÉSIMA TERCERA. Las partes manifiestan su conformidad para que, en el caso de que se susciten controversias, con motivo de la operación, la interpretación o el incumplimiento del presente Acuerdo de Coordinación, las conozcan los Tribunales\nVIGÉSIMA CUARTA. Este Acuerdo de Coordinación y sus Anexos I, II y III surten\nADMINISTRATIVO 20 DESARROLLO SOCIAL, QUE\nSUSCRIBEN POR UNA PARTE EL EJECUTIVO FEDERAL,\nA TRAVÉS DE LA SECRETARÍA DE DESARROLLO\nSOCIAL; Y POR LA OTRA EL EJECUTIVO DEL ESTADO Y\n18 MUNICIPIOS sus efectos a partir de la fecha de su firma y hasta el treinta y uno de diciembre del año dos mil once. El presente Acuerdo de Coordinación y sus Anexos deberán publicarse, conforme lo establece el artículo 36 de la Ley de Planeación, en el Diario Oficial de la\nFederación y en el órgano oficial de difusión del Gobierno del Estado, con el propósito de que la población conozca las acciones coordinadas entre la Federación y el Estado.\nLeído que fue y debidamente enterados del alcance y contenido legal, se firma el presente Acuerdo de Coordinación en 4 ejemplares, en la Ciudad de Chilpancingo de los\nBravo, Guerrero, a los seis días del mes de abril del año dos mil once.\nPOR \"LA SEDESOL\"\nLA SUBSECRETARIA DE DESARROLLO URBANO Y ORDENACIÓN DEL\nTERRITORIO.\nARQ. SARA HALINA TOPELSON FRIDMAN.\nRúbrica.\nEL DELEGADO FEDERAL EN EL ESTADO DE GUERRERO.\nLIC. EDDY ALBERTO MARTÍNEZ ALARCÓN.\nPOR \"EL ESTADO\"\nEL SECRETARIO DE DESARROLLO SOCIAL.\nLIC. DAVID JIMÉNEZ RUMBO.\nEL SECRETARIO DE DESARROLLO URBANO Y OBRAS PÚBLICAS.\nING. JEOVEL GUINTO GONZÁLEZ.\nADMINISTRATIVO 20 DESARROLLO SOCIAL, QUE\nSUSCRIBEN POR UNA PARTE EL EJECUTIVO FEDERAL,\nA TRAVÉS DE LA SECRETARÍA DE DESARROLLO\nSOCIAL; Y POR LA OTRA EL EJECUTIVO DEL ESTADO Y\n18 MUNICIPIOS\nEL COORDINADOR GENERAL DEL COPLADEG.\nLIC. CARLOS SÁNCHEZ BARRIOS.\nRúbrica.\nPOR \"LOS MUNICIPIOS\"\nEL PRESIDENTE MUNICIPAL DE ACAPULCO DE JUÁREZ.\nDR. MANUEL AÑORVE BAÑOS.\nRúbrica.\nEL PRESIDENTE MUNICIPAL DE ATOYAC DE ÁLVAREZ.\nC.P. CARLOS ARMANDO BELLO GÓMEZ.\nRúbrica.\nEL PRESIDENTE MUNICIPAL DE CHILPANCINGO DE LOS BRAVO.\nLIC. HÉCTOR ANTONIO ASTUDILLO FLORES.\nRúbrica.\nEL PRESIDENTE MUNICIPAL DE EDUARDO NERI.\nPROFR. MODESTO PÉREZ LEYVA.\nEL PRESIDENTE MUNICIPAL DE IGUALA DE LA INDEPENDENCIA.\nDR. RAÚL TOVAR TAVERA.\nEL PRESIDENTE MUNICIPAL DE OMETEPEC.\nC. EFRÉN ADAME MONTALVAN.\nADMINISTRATIVO 20 DESARROLLO SOCIAL, QUE\nSUSCRIBEN POR UNA PARTE EL EJECUTIVO FEDERAL,\nA TRAVÉS DE LA SECRETARÍA DE DESARROLLO\nSOCIAL; Y POR LA OTRA EL EJECUTIVO DEL ESTADO Y\n18 MUNICIPIOS\nEL PRESIDENTE MUNICIPAL DE PUNGARABATO.\nDR. GUSTAVO ADOLFO JUANCHI QUIÑONES.\nRúbrica.\nEL PRESIDENTE MUNICIPAL DE ARCELIA.\nPROFR. FRANCISCO SÁNCHEZ BENITEZ.\nRúbrica.\nEL PRESIDENTE MUNICIPAL DE CHILAPA DE ÁLVAREZ.\nLIC. SERGIO DOLORES FLORES.\nRúbrica.\nEL PRESIDENTE MUNICIPAL DE COYUCA DE BENÍTEZ.\nLIC. MERCED BALDOVINO DIEGO.\nRúbrica.\nEL PRESIDENTE MUNICIPAL DE HUITZUCO DE LOS FIGUEROA.\nC. ISIDRO MIRANDA MADRID.\nRúbrica.\nEL PRESIDENTE MUNICIPAL DE JOSÉ AZUETA.\nING. ALEJANDRO BRAVO ABARCA.\nEL PRESIDENTE MUNICIPAL DE PETATLÁN.\nARQ. JOSÉ ALBINO LACUNZA SANTOS.\nEL PRESIDENTE MUNICIPAL DE TAXCO DE ALARCÓN.\nL.A.E. ALVARO BURGOS BARRERA.\nADMINISTRATIVO 20 DESARROLLO SOCIAL, QUE\nSUSCRIBEN POR UNA PARTE EL EJECUTIVO FEDERAL,\nA TRAVÉS DE LA SECRETARÍA DE DESARROLLO\nSOCIAL; Y POR LA OTRA EL EJECUTIVO DEL ESTADO Y\n18 MUNICIPIOS\nEL PRESIDENTE MUNICIPAL DE TECPAN DE GALEANA.\nPROFR. NADÍN TORRALBA MEJÍA.\nRúbrica.\nEL PRESIDENTE MUNICIPAL DE TIXTLA DE GUERRERO.\nPROFR. JORGE LUIS CAMPOS ESPÍRITU.\nRúbrica.\nEL PRESIDENTE MUNICIPAL DE TELOLOAPAN.\nPROFR. MARINO MIRANDA SALGADO.\nRúbrica.\nEL PRESIDENTE MUNICIPAL DE TLAPA DE COMONFORT.\nLIC. WILLY REYES RAMOS.\nRúbrica.\nAcuerdo de Coordinación para la Distribución y Ejercicio de los Subsidios del Programa\nHábitat, Vertiente General, correspondiente al Estado de Guerrero para el Ejercicio Fiscal\n2011\nAnexo I\n\"Ciudades, Zonas Metropolitanas y Polígonos Hábitat Seleccionados\"\n\"LA SEDESOL\", \"EL ESTADO\" y \"LOS MUNICIPIOS\" acuerdan que los recursos del\nPrograma Hábitat se ejercerán en las siguientes ciudades, zonas metropolitanas y\n\"Polígonos Hábitat\":\n12001, 12002, 12003, 12004, 12005, 12006, 12007, 12008, 12009, 12010, ZM Acapulco Acapulco de Juárez\n12013, 12014, 12015, 12016, 12017, 12018, 12019, 12020, 12021\nADMINISTRATIVO 20 DESARROLLO SOCIAL, QUE\nSUSCRIBEN POR UNA PARTE EL EJECUTIVO FEDERAL,\nA TRAVÉS DE LA SECRETARÍA DE DESARROLLO\nSOCIAL; Y POR LA OTRA EL EJECUTIVO DEL ESTADO Y\n18 MUNICIPIOS\n{\"tabla_1\":{\"columnas\":[\"Arcelia\",\"Arcelia\",\"12062\"],\"filas\":[{\"columna_1\":\"Atoyac\",\"columna_2\":\"Atoyac de Álvarez\",\"columna_3\":\"12058, 12506\"},{\"columna_1\":\"Chilapa de Álvarez\",\"columna_2\":\"Chilapa de Álvarez\",\"columna_3\":\"12050\"},{\"columna_1\":\"Chilpancingo\",\"columna_2\":\"Chilpancingo de los Bravo\",\"columna_3\":\"12023, 12024, 12025, 12026, 12027\"},{\"columna_1\":\"Coyuca de Benítez\",\"columna_2\":\"Coyuca de Benítez\",\"columna_3\":\"12507, 12509, 12510, 12511,\\n50912001\"},{\"columna_1\":\"Zumpango\",\"columna_2\":\"Eduardo Neri\",\"columna_3\":\"12054\"},{\"columna_1\":\"Huitzuco\",\"columna_2\":\"Huitzuco de los Figueroa\",\"columna_3\":\"12063, 12064, 12065\"},{\"columna_1\":\"Iguala\",\"columna_2\":\"Iguala de la Independencia\",\"columna_3\":\"12028, 12029, 12030, 12031, 12032,\\n12033, 12034, 12035\"},{\"columna_1\":\"Zihuatanejo\",\"columna_2\":\"José Azueta\",\"columna_3\":\"12036, 12037, 12038, 12039, 12040\"},{\"columna_1\":\"Ometepec\",\"columna_2\":\"Ometepec\",\"columna_3\":\"12059, 12060, 12061\"},{\"columna_1\":\"Petatlán\",\"columna_2\":\"Petatlán\",\"columna_3\":\"12056, 12057\"},{\"columna_1\":\"Cd. Altamirano-Rivapalacio\",\"columna_2\":\"Pungarabato\",\"columna_3\":\"12047, 12048, 12049\"},{\"columna_1\":\"Taxco\",\"columna_2\":\"Taxco de Alarcón\",\"columna_3\":\"12041, 12042, 12043,12044,12045,\\n30912001\"},{\"columna_1\":\"Tecpan de Galeana-El Suchil\",\"columna_2\":\"Tecpan de Galeana\",\"columna_3\":\"12512, 12513, 12514\"},{\"columna_1\":\"Teloloapan\",\"columna_2\":\"Teloloapan\",\"columna_3\":\"12051, 12052, 12053\"},{\"columna_1\":\"Tixtla\",\"columna_2\":\"Tixtla de Guerrero\",\"columna_3\":\"12055\"},{\"columna_1\":\"Tlapa\",\"columna_2\":\"Tlapa de Comonfort\",\"columna_3\":\"12046\"}]}} mes de abril del año dos mil once.\nPOR \"LA SEDESOL\"\nEL DELEGADO FEDERAL.\nLIC. EDDY ALBERTO MARTÍNEZ ALARCÓN.\nPOR \"EL ESTADO\"\nEL SECRETARIO DE DESARROLLO URBANO Y OBRAS PÚBLICAS.\nING. JEOVEL GUINTO GONZÁLEZ.\nADMINISTRATIVO 20 DESARROLLO SOCIAL, QUE\nSUSCRIBEN POR UNA PARTE EL EJECUTIVO FEDERAL,\nA TRAVÉS DE LA SECRETARÍA DE DESARROLLO\nSOCIAL; Y POR LA OTRA EL EJECUTIVO DEL ESTADO Y\n18 MUNICIPIOS\nEL COORDINADOR GENERAL DEL COPLADEG.\nLIC. CARLOS SÁNCHEZ BARRIOS.\nRúbrica.\nPOR “LOS MUNICIPIOS”\nEL PRESIDENTE MUNICIPAL DE ACAPULCO DE JUÁREZ.\nDR. MANUEL AÑORVE BAÑOS.\nRúbrica.\nEL PRESIDENTE MUNICIPAL DE ATOYAC DE ÁLVAREZ.\nC.P. CARLOS ARMANDO BELLO GÓMEZ.\nRúbrica.\nEL PRESIDENTE MUNICIPAL DE CHILPANCINGO DE LOS BRAVO.\nLIC. HÉCTOR ANTONIO ASTUDILLO FLORES.\nRúbrica.\nEL PRESIDENTE MUNICIPAL DE EDUARDO NERI.\nPROFR. MODESTO PÉREZ LEYVA.\nEL PRESIDENTE MUNICIPAL DE IGUALA DE LA INDEPENDENCIA.\nDR. RAÚL TOVAR TAVERA.\nEL PRESIDENTE MUNICIPAL DE OMETEPEC.\nC. EFRÉN ADAME MONTALVÁN.\nADMINISTRATIVO 20 DESARROLLO SOCIAL, QUE\nSUSCRIBEN POR UNA PARTE EL EJECUTIVO FEDERAL,\nA TRAVÉS DE LA SECRETARÍA DE DESARROLLO\nSOCIAL; Y POR LA OTRA EL EJECUTIVO DEL ESTADO Y\n18 MUNICIPIOS\nEL PRESIDENTE MUNICIPAL DE PUNGARABATO.\nDR. GUSTAVO ADOLFO JUANCHI QUIÑONES.\nRúbrica.\nEL PRESIDENTE MUNICIPAL DE ARCELIA.\nPROFR. FRANCISCO SÁNCHEZ BENÍTEZ.\nRúbrica.\nEL PRESIDENTE MUNICIPAL DE CHILAPA DE ÁLVAREZ.\nLIC. SERGIO DOLORES FLORES.\nRúbrica.\nEL PRESIDENTE MUNICIPAL DE COYUCA DE BENÍTEZ.\nLIC. MERCED BALDOVINO DIEGO.\nRúbrica.\nEL PRESIDENTE MUNICIPAL DE HUITZUCO DE LOS FIGUEROA.\nC. ISIDRO MIRANDA MADRID.\nRúbrica.\nEL PRESIDENTE MUNICIPAL DE JOSÉ AZUETA.\nING. ALEJANDRO BRAVO ABARCA.\nEL PRESIDENTE MUNICIPAL DE PETATLÁN.\nARQ. JOSÉ ALBINO LACUNZA SANTOS.\nEL PRESIDENTE MUNICIPAL DE TAXCO DE ALARCÓN.\nL.A.E. ÁLVARO BURGOS BARRERA.\nADMINISTRATIVO 20 DESARROLLO SOCIAL, QUE\nSUSCRIBEN POR UNA PARTE EL EJECUTIVO FEDERAL,\nA TRAVÉS DE LA SECRETARÍA DE DESARROLLO\nSOCIAL; Y POR LA OTRA EL EJECUTIVO DEL ESTADO Y\n18 MUNICIPIOS\nEL PRESIDENTE MUNICIPAL DE TECPAN DE GALEANA.\nPROFR. NADÍN TORRALBA MEJÍA.\nRúbrica.\nEL PRESIDENTE MUNICIPAL DE TIXTLA DE GUERRERO.\nPROFR. JORGE LUIS CAMPOS ESPÍRITU.\nRúbrica.\nEL PRESIDENTE MUNICIPAL DE TELOLOAPAN.\nPROFR. MARINO MIRANDA SALGADO.\nRúbrica.\nEL PRESIDENTE MUNICIPAL DE TLAPA DE COMONFORT.\nLIC. WILLY REYES RAMOS.\nRúbrica.\nAnexo II\n\"Subsidios Federales por Municipio\"\n\"LA SEDESOL\" aportará al Estado de Guerrero subsidios federales del\nPrograma Hábitat por la cantidad de $174’747,086.00 (Ciento setenta y cuatro millones setecientos cuarenta y siete mil ochenta y seis pesos 00/100 M.N.), que se distribuirán como sigue:\nMonto de Subsidios aportados por “LA\nMunicipio\nSEDESOL”\nAcapulco de Juárez $ 27,853,536.00\nArcelia $ 5,000,000.00\nAtoyac de Álvarez $ 8,000,000.00\nChilapa de Álvarez $ 9,000,000.00\nChilpancingo de los Bravo $ 13,000,000.00\nADMINISTRATIVO 20 DESARROLLO SOCIAL, QUE\nSUSCRIBEN POR UNA PARTE EL EJECUTIVO FEDERAL,\nA TRAVÉS DE LA SECRETARÍA DE DESARROLLO\nSOCIAL; Y POR LA OTRA EL EJECUTIVO DEL ESTADO Y\n18 MUNICIPIOS\nCoyuca de Benítez $ 13,000,000.00\nEduardo Neri $ 10,000,000.00\nHuitzuco de los Figueroa $ 7,000,000.00\nIguala de la Independencia $ 6,000,000.00\nJosé Azueta $ 12,000,000.00\nOmetepec $ 9,000,000.00\nPetatlán $ 9,000,000.00\nPungarabato $ 8,000,000.00\nTaxco de Alarcón $ 9,000,000.00\nTecpan de Galeana $ 4,000,000.00\nTeloloapan $ 5,000,000.00\nTixtla de Guerrero $ 9,000,000.00\nTlapa de Comonfort $ 10,000,000.00\nRecursos ejercidos por el Gobierno del Estado en el Municipio de Tlapa\n$ 893,550.00 de Comonfort\nTOTAL $ 174,747,086.00\nPOR \"LA SEDESOL\"\nEL DELEGADO FEDERAL.\nLIC. EDDY ALBERTO MARTÍNEZ ALARCÓN.\nPOR \"EL ESTADO\"\nEL SECRETARIO DE DESARROLLO URBANO Y OBRAS PÚBLICAS.\nING. JEOVEL GUINTO GONZÁLEZ.\nEL COORDINADOR GENERAL DEL COPLADEG.\nLIC. CARLOS SÁNCHEZ BARRIOS.\nADMINISTRATIVO 20 DESARROLLO SOCIAL, QUE\nSUSCRIBEN POR UNA PARTE EL EJECUTIVO FEDERAL,\nA TRAVÉS DE LA SECRETARÍA DE DESARROLLO\nSOCIAL; Y POR LA OTRA EL EJECUTIVO DEL ESTADO Y\n18 MUNICIPIOS\nPOR \"LOS MUNICIPIOS\"\nEL PRESIDENTE MUNICIPAL DE ACAPULCO DE JUÁREZ.\nDR. MANUEL AÑORVE BAÑOS.\nRúbrica.\nEL PRESIDENTE MUNICIPAL DE ATOYAC DE ÁLVAREZ.\nC.P. CARLOS ARMANDO BELLO GÓMEZ.\nRúbrica.\nEL PRESIDENTE MUNICIPAL DE CHILPANCINGO DE LOS BRAVO.\nLIC. HÉCTOR ANTONIO ASTUDILLO FLORES.\nRúbrica.\nEL PRESIDENTE MUNICIPAL DE EDUARDO NERI.\nPROFR. MODESTO PÉREZ LEYVA.\nRúbrica.\nEL PRESIDENTE MUNICIPAL DE IGUALA DE LA INDEPENDENCIA.\nDR. RAÚL TOVAR TAVERA.\nEL PRESIDENTE MUNICIPAL DE OMETEPEC.\nC. EFRÉN ADAME MONTALVÁN.\nEL PRESIDENTE MUNICIPAL DE PUNGARABATO.\nDR. GUSTAVO ADOLFO JUANCHI QUIÑONES.\nADMINISTRATIVO 20 DESARROLLO SOCIAL, QUE\nSUSCRIBEN POR UNA PARTE EL EJECUTIVO FEDERAL,\nA TRAVÉS DE LA SECRETARÍA DE DESARROLLO\nSOCIAL; Y POR LA OTRA EL EJECUTIVO DEL ESTADO Y\n18 MUNICIPIOS\nEL PRESIDENTE MUNICIPAL DE ARCELIA.\nPROFR. FRANCISCO SÁNCHEZ BENÍTEZ.\nRúbrica.\nEL PRESIDENTE MUNICIPAL DE CHILAPA DE ÁLVAREZ.\nLIC. SERGIO DOLORES FLORES.\nRúbrica.\nEL PRESIDENTE MUNICIPAL DE COYUCA DE BENÍTEZ.\nLIC. MERCED BALDOVINO DIEGO.\nRúbrica.\nEL PRESIDENTE MUNICIPAL DE HUITZUCO DE LOS FIGUEROA.\nC. ISIDRO MIRANDA MADRID.\nRúbrica.\nEL PRESIDENTE MUNICIPAL DE JOSÉ AZUETA.\nING. ALEJANDRO BRAVO ABARCA.\nRúbrica.\nEL PRESIDENTE MUNICIPAL DE PETATLÁN.\nARQ. JOSÉ ALBINO LACUNZA SANTOS.\nEL PRESIDENTE MUNICIPAL DE TAXCO DE ALARCÓN.\nL.A.E. ÁLVARO BURGOS BARRERA.\nEL PRESIDENTE MUNICIPAL DE TECPAN DE GALEANA.\nPROFR. NADÍN TORRALBA MEJÍA.\nADMINISTRATIVO 20 DESARROLLO SOCIAL, QUE\nSUSCRIBEN POR UNA PARTE EL EJECUTIVO FEDERAL,\nA TRAVÉS DE LA SECRETARÍA DE DESARROLLO\nSOCIAL; Y POR LA OTRA EL EJECUTIVO DEL ESTADO Y\n18 MUNICIPIOS\nEL PRESIDENTE MUNICIPAL DE TIXTLA DE GUERRERO.\nPROFR. JORGE LUIS CAMPOS ESPÍRITU.\nRúbrica.\nEL PRESIDENTE MUNICIPAL DE TELOLOAPAN.\nPROFR. MARINO MIRANDA SALGADO.\nRúbrica.\nEL PRESIDENTE MUNICIPAL DE TLAPA DE COMONFORT.\nLIC. WILLY REYES RAMOS.\nRúbrica.\nAnexo III\n\"Aportaciones de Recursos Locales por Municipio\"\n\"EL ESTADO\" y \"LOS MUNICIPIOS\" se comprometen a aportar recursos a la\nFederación para la operación del Programa Hábitat por la cantidad de $174'747,086.00\n(Ciento setenta y cuatro millones setecientos cuarenta y siete mil ochenta y seis pesos\n00/100 M.N.), que se distribuirán como sigue:\nRecursos\nRecursos aportados por\nMunicipio aportados por “EL Total de recursos\n“LOS MUNICIPIOS\"\nESTADO”\nAcapulco de Juárez $ 0.00 $ 27,853,536.00 $ 27,853,536.00\nArcelia $ 0.00 $ 5,000,000.00 $ 5,000,000.00\nAtoyac de Alvarez $ 0.00 $ 8,000,000.00 $ 8,000,000.00\nChilapa de Alvarez $ 0.00 $ 9,000,000.00 $ 9,000,000.00\nChilpancingo de los Bravo $ 0.00 $ 13,000,000.00 $ 13,000,000.00\nCoyuca de Benítez $ 0.00 $ 13,000,000.00 $ 13,000,000.00\nEduardo Neri $ 0.00 $ 10,000,000.00 $ 10,000,000.00\nHuitzuco de los Figueroa $ 0.00 $ 7,000,000.00 $ 7,000,000.00\nIguala de la Independencia $ 0.00 $ 6,000,000.00 $ 6,000,000.00\nADMINISTRATIVO 20 DESARROLLO SOCIAL, QUE\nSUSCRIBEN POR UNA PARTE EL EJECUTIVO FEDERAL,\nA TRAVÉS DE LA SECRETARÍA DE DESARROLLO\nSOCIAL; Y POR LA OTRA EL EJECUTIVO DEL ESTADO Y\n18 MUNICIPIOS\nJosé Azueta $ 0.00 $ 12,000,000.00 $ 12,000,000.00\nOmetepec $ 0.00 $ 9,000,000.00 $ 9,000,000.00\nPetatlán $ 0.00 $ 9,000,000.00 $ 9,000,000.00\nPungarabato $ 0.00 $ 8,000,000.00 $ 8,000,000.00\nTaxco de Alarcón $ 0.00 $ 9,000,000.00 $ 9,000,000.00\nTecpan de Galeana $ 0.00 $ 4,000,000.00 $ 4,000,000.00\nTeloloapan $ 0.00 $ 5,000,000.00 $ 5,000,000.00\nTixtla de Guerrero $ 0.00 $ 9,000,000.00 $ 9,000,000.00\nTlapa de Comonfort $ 0.00 $ 10,000,000.00 $ 10,000,000.00\nRecursos ejercidos por el Gobierno del\nEstado en el Municipio de Tlapa de $893,550.00 $ 0.00 $ 893,550.00\nComonfort\nTOTAL $893,550.00 $173,853,536.00 $174,747,086.00\nPOR \"LA SEDESOL\"\nEL DELEGADO FEDERAL.\nLIC. EDDY ALBERTO MARTÍNEZ ALARCÓN.\nPOR \"EL ESTADO”\nEL SECRETARIO DE DESARROLLO URBANO Y OBRAS PÚBLICAS.\nING. JEOVEL GUINTO GONZÁLEZ.\nEL COORDINADOR GENERAL DEL COPLADEG.\nLIC. CARLOS SÁNCHEZ BARRIOS.\nADMINISTRATIVO 20 DESARROLLO SOCIAL, QUE\nSUSCRIBEN POR UNA PARTE EL EJECUTIVO FEDERAL,\nA TRAVÉS DE LA SECRETARÍA DE DESARROLLO\nSOCIAL; Y POR LA OTRA EL EJECUTIVO DEL ESTADO Y\n18 MUNICIPIOS\nPOR \"LOS MUNICIPIOS\"\nEL PRESIDENTE MUNICIPAL DE ACAPULCO DE JUÁREZ.\nDR. MANUEL AÑORVE BAÑOS.\nRúbrica.\nEL PRESIDENTE MUNICIPAL DE ATOYAC DE ÁLVAREZ.\nC.P. CARLOS ARMANDO BELLO GÓMEZ.\nRúbrica.\nEL PRESIDENTE MUNICIPAL DE CHILPANCINGO DE LOS BRAVO.\nLIC. HÉCTOR ANTONIO ASTUDILLO FLORES.\nRúbrica.\nEL PRESIDENTE MUNICIPAL DE EDUARDO NERI.\nPROFR. MODESTO PÉREZ LEYVA.\nRúbrica.\nEL PRESIDENTE MUNICIPAL DE IGUALA DE LA INDEPENDENCIA.\nDR. RAÚL TOVAR TAVERA.\nEL PRESIDENTE MUNICIPAL DE OMETEPEC.\nC. EFRÉN ADAME MONTALVÁN.\nEL PRESIDENTE MUNICIPAL DE PUNGARABATO.\nDR. GUSTAVO ADOLFO JUANCHI QUIÑONES.\nADMINISTRATIVO 20 DESARROLLO SOCIAL, QUE\nSUSCRIBEN POR UNA PARTE EL EJECUTIVO FEDERAL,\nA TRAVÉS DE LA SECRETARÍA DE DESARROLLO\nSOCIAL; Y POR LA OTRA EL EJECUTIVO DEL ESTADO Y\n18 MUNICIPIOS\nEL PRESIDENTE MUNICIPAL DE ARCELIA.\nPROFR. FRANCISCO SÁNCHEZ BENÍTEZ.\nRúbrica.\nEL PRESIDENTE MUNICIPAL DE CHILAPA DE ÁLVAREZ.\nLIC. SERGIO DOLORES FLORES.\nRúbrica.\nEL PRESIDENTE MUNICIPAL DE COYUCA DE BENÍTEZ.\nLIC. MERCED BALDOVINO DIEGO.\nRúbrica.\nEL PRESIDENTE MUNICIPAL DE HUITZUCO DE LOS FIGUEROA.\nC. ISIDRO MIRANDA MADRID.\nRúbrica.\nEL PRESIDENTE MUNICIPAL DE JOSÉ AZUETA.\nING. ALEJANDRO BRAVO ABARCA.\nRúbrica.\nEL PRESIDENTE MUNICIPAL DE PETATLÁN.\nARQ. JOSÉ ALBINO LACUNZA SANTOS.\nEL PRESIDENTE MUNICIPAL DE TAXCO DE ALARCÓN.\nL.A.E. ÁLVARO BURGOS BARRERA.\nEL PRESIDENTE MUNICIPAL DE TECPAN DE GALEANA.\nPROFR. NADÍN TORRALBA MEJÍA.\nADMINISTRATIVO 20 DESARROLLO SOCIAL, QUE\nSUSCRIBEN POR UNA PARTE EL EJECUTIVO FEDERAL,\nA TRAVÉS DE LA SECRETARÍA DE DESARROLLO\nSOCIAL; Y POR LA OTRA EL EJECUTIVO DEL ESTADO Y\n18 MUNICIPIOS\nEL PRESIDENTE MUNICIPAL DE TIXTLA DE GUERRERO.\nPROFR. JORGE LUIS CAMPOS ESPÍRITU.\nRúbrica.\nEL PRESIDENTE MUNICIPAL DE TELOLOAPAN.\nPROFR. MARINO MIRANDA SALGADO.\nRúbrica.\nEL PRESIDENTE MUNICIPAL DE TLAPA DE COMONFORT.\nLIC. WILLY REYES RAMOS.\nRúbrica.\nEL SUSCRITO C.P. MARCOS EFREN PARRA GOMEZ, DELEGADO FEDERAL\nDE LA SECRETARIA DE DESARROLLO SOCIAL EN EL ESTADO DE GUERRRERO,\nCON FUNDAMENTO EN LOS ARTÍCULOS 2, 36 FRACCIÓN XII, 44 Y 45 DEL\nREGLAMENTO INTERIOR DE LA PROPIA DEPENDENCIA, PUBLICADO EN EL\nDIARIO OFICIAL DE LA FEDERACIÓN CON FECHA 19 DE JULIO DEL 2004 Y\nIMPRESAS POR EL ANVERSO, COINCIDE EN TODAS Y CADA UNA DE SUS\nPARTES, CON EL ORIGINAL QUE TUVO A LA VISTA Y QUE OBRA EN LOS\nARCHIVOS DE ESTA DELEGACION FEDERAL A MI CARGO, MISMO QUE\nCERTIFICO PARA LOS EFECTOS LEGALES CORRESPONDIENTES.\nCHILPANCINGO, GUERRERO, A OCHO DE AGOSTO DEL AÑO DOS MIL ONCE.\nADMINISTRATIVO 20 DESARROLLO SOCIAL, QUE\nSUSCRIBEN POR UNA PARTE EL EJECUTIVO FEDERAL,\nA TRAVÉS DE LA SECRETARÍA DE DESARROLLO\nSOCIAL; Y POR LA OTRA EL EJECUTIVO DEL ESTADO Y\n18 MUNICIPIOS\n\"Este programa es público, ajeno a cualquier partido político. Queda prohibido el uso para fines distintos al desarrollo social.\" Art. 28, Ley General de Desarrollo Social.\n\"Este programa es público, ajeno a cualquier partido político. Queda prohibido el uso para fines distintos a los establecidos en el programa\". Art. 30, fracción III, inciso a,)\nDecreto de presupuesto de Egresos de la Federación para el ejercicio Fiscal 2011.",
  "ordenamiento": "ACUERDO",
  "jurisdiccion": "GUERRERO",
  "fuente_oficial": "DIARIO OFICIAL DE LA FEDERACION",
  "Fecha de Publicación": "31 DE DICIEMBRE DE 2011",
  "ULTIMA REFORMA PUBLICADA": "16 de Septiembre de 2011",
  "status": "ABROGADA",
  "es_escaneado": false,
  "tiene_tablas": true,
  "materia": [
    "general"
  ]
}