{
  "titulo": "Acuerdo PGJCG0082011, del Procurador General de Justicia, por el Que Se Fija las Bases para la Búsqu",
  "Contenido": "BÚSQUEDA DE CIUDADANOS\nDESAPARECIDOS, SECUESTRADOS Y\nASESINADOS, EN EL ESTADO DE GUERRERO\nTEXTO ORIGINAL\nII, el Viernes 2 de Diciembre de 2011.\nACUERDO PGJ/CG/008/2011, DEL PROCURADOR GENERAL DE JUSTICIA, POR EL\nQUE SE FIJA LAS BASES PARA LA BÚSQUEDA DE CIUDADANOS\nDESAPARECIDOS, SECUESTRADOS Y ASESINADOS, EN EL ESTADO DE\nGUERRERO.\nLIC. ALBERTO LÓPEZ ROSAS, PROCURADOR GENERAL DE JUSTICIA DEL\nESTADO DE GUERRERO, EN EJERCICIO DE LAS FACULTADES QUE ME\nCONFIEREN LOS ARTÍCULOS 21 PÁRRAFO UNO DE LA CONSTITUCIÓN POLÍTICA\nDE LOS ESTADOS UNIDOS MEXICANOS; 78 PÁRRAFO UNO DE LA CONSTITUCIÓN\nFRACCIÓN V DE LA LEY ORGÁNICA DE LA PROCURADURÍA GENERAL DE\nJUSTICIA; 18 TERCER PÁRRAFO Y 35 FRACCIÓN I DE LA LEY ORGÁNICA DE LA\nADMINISTRACIÓN PÚBLICA DEL ESTADO; ASÍ COMO 5, 8, 11 FRACCIÓN I DEL\nREGLAMENTO DE LA LEY ORGÁNICA DE LA PROCURADURÍA GENERAL DE\nJUSTICIA, Y\nCONSIDERANDO relacionadas con la Desaparición de Personas, situación que ha Impactado a la Sociedad que sus pobladores también han resentido una situación de esta índole. del Estado de Guerrero, esta dependencia tiene como finalidad lograr una pronta, imparcial y gratuita Procuración de Justicia bajo principios de certeza, legalidad, objetividad imparcialidad, con la finalidad primordial de salvaguardar la integridad y derechos de las personas; así como preservar las libertades, el orden y la paz pública.\nBÚSQUEDA DE CIUDADANOS\nDESAPARECIDOS, SECUESTRADOS Y\nASESINADOS, EN EL ESTADO DE GUERRERO\nQue en el caso de las Personas Desaparecidas, Secuestradas o Asesinadas en el Estado de Guerrero, la Procuraduría General de Justicia en Coordinación con otras dependencias en materia de seguridad del Gobierno Estatal ha mostrado su voluntad política y ha realizado grandes esfuerzos para atender adecuadamente esta situación.\nAun así estamos conscientes de que persiste la demanda sentida y reiterada de la Sociedad para que el Gobierno mejore y fortalezca las acciones para la integridad y la libertad de sus ciudadanos, así como también para establecer los procedimientos que de manera eficaz y efectiva lleven a la Autoridad Investigadora a la pronta localización de\nPersonas Desaparecidas, Secuestradas, inclusive privadas de la vida.\nQue el suscrito Procurador General de Justicia del Estado de Guerrero en atención a las atribuciones y facultades que le confiere el articulo 29 fracción VIII de la\nLey Orgánica de la Procuraduría General de Justicia del Estado de Guerrero, está facultado para otorgar el presente acuerdo en beneficio de la Organización del sector social denominado Comité de Familiares y Amigos de Secuestrados, Desaparecidos y\nAsesinados del Estado de Guerrero A.C. con la finalidad de atender de manera pronta y expedita a la sociedad ejerciendo la función ministerial, policial y pericial conforme se requiera contando de manera fundamental con el acuerdo, autorización jurídica y voluntad de los familiares directos del agraviado.\nQue muestra de la voluntad del suscrito Procurador General de Justicia del las Indagatorias de las personas secuestradas, desaparecidas y asesinadas en el estado de Guerrero, para establecer los mecanismos y políticas y brindar un vigoroso impulso respeto a los derecho los ciudadanos, resulta conveniente expedir el siguiente:\nACUERDO PGJ/CG/008/2011, DEL PROCURADOR GENERAL DE JUSTICIA, POR EL\nQUE FIJA LAS BASES PARA LA BÚSQUEDA DE CIUDADANOS DESAPARECIDOS,\nSECUESTRADOS Y ASESINADOS, EN EL ESTADO DE GUERRERO.\nPRIMERO.- La Procuraduría General de Justicia del Estado de Guerrero, de manera preponderante, y para la aplicación del presente acuerdo para la búsqueda de\nBÚSQUEDA DE CIUDADANOS\nDESAPARECIDOS, SECUESTRADOS Y\nASESINADOS, EN EL ESTADO DE GUERRERO ciudadanos desaparecidos, secuestrados y privados de la vida, deberá obtener de\nMinisterio Público del Fuero común en el que deberán de quedar debidamente planteados de manera sucinta la forma y términos en que ocurrieron los hechos, en el que el agraviado hubiese sido secuestrado, desaparecido, o privado de la vida.\nSEGUNDO.- La Procuraduría General de Justicia del Estado de Guerrero, por conducto del personal autorizado por el C. Procurador General de Justicia del Estado deberá de recabar en la indagatoria el consentimiento expreso de los familiares de la victima, para aplicar el presente acuerdo, para investigar y perseguir los delitos que se actualicen con motivo de la Desaparición, Secuestro u Homicidio de personas; así como para coordinar y supervisar la investigación y persecución de éstos delitos e implementar las acciones de prevención y disuasión de los ilícitos relacionados con la Desaparición, Secuestro u Homicidio de personas en coordinación con las instancias competentes de los órdenes Federal estatal o municipal.\nTERCERO.- Los familiares de las Victimas de secuestrados, desaparecidos o privados de la vida, previa solicitud expresa y acreditación del parentesco podrán coadyuvar en la investigación en los términos previstos por el articulo 5 del Código de\nProcedimientos Penales vigente en el Estado de Guerrero.\nCUARTO.- Al frente de la investigación aplicada por el presente acuerdo estará los Agentes del Ministerio Público, quien serán adscritos y removido por el Procurador para su nombramiento.\nQUINTO.- Los Agentes del Ministerio Público designados para la aplicación del presente acuerdo, para la investigación de asuntos relacionados con personas secuestradas, desaparecidas o privadas de la vida en el estado de Guerrero, podrán:\nI.- Conocer las denuncias relacionadas con la desaparición, secuestro, u homicidio de personas;\nBÚSQUEDA DE CIUDADANOS\nDESAPARECIDOS, SECUESTRADOS Y\nASESINADOS, EN EL ESTADO DE GUERRERO\nII.- Integrar y continuar las averiguaciones previas correspondientes.\nIII.- Ejercitar, en su caso, la acción penal respecto a los delitos que pudiesen tipificarse;\nIV.- Intervenir en coordinación con los agentes del ministerio público adscritos en los procesos respectivos hasta su conclusión;\nV.- Intervenir en los juicios de amparo y cualesquiera otros procedimientos conexos.\nVI.- Las demás que le señalen los ordenamientos legales.\nSEXTO.- Los Agentes del Ministerio Público asignados, contará con la infraestructura, recursos materiales, Agentes del Ministerio Público Auxiliares, personal de Policía Ministerial, personal de la Dirección General de Servicios Periciales y\nAdministrativo, que las necesidades del servicio requiera para el cumplimiento de su función en la aplicación del presente acuerdo.\nSÉPTIMO.- El Director General de Control de Procesos Penales de la\nProcuraduría General de Justicia del Estado, deberá de comisionar a los Agentes del\nMinisterio Público adscritos a los órganos jurisdiccionales de cada Distrito Judicial, para que se encarguen de la revisión, y seguimiento de las consignaciones o pedimentos motivo de la comisión de los ilícitos por los que fue creado.\nOCTAVO.- Los Agentes del Ministerio Público designados para la aplicación y familiares reconocidos de las victimas de los delitos, por los cuales fue creado el presente, sobre los avances y pormenores obtenidos del resultado de la investigación correspondiente.\nBÚSQUEDA DE CIUDADANOS\nDESAPARECIDOS, SECUESTRADOS Y\nASESINADOS, EN EL ESTADO DE GUERRERO\nNOVENO.- Los Agentes del Ministerio Publico designados para la investigación de asuntos de personas desaparecidas, secuestradas o privadas de la vida en el estado de Guerrero, tendrá las siguientes atribuciones.\nI.- Planear, programar, organizar, dirigir, supervisar y evaluar el desarrollo de la función asignada, derivado de la investigación de los delitos por los cuales fue creado el presente acuerdo.\nII.- Coordinar al personal pericial, policial y administrativo a su cargo, en la investigación y persecución de los delitos relacionados con la desaparición, secuestro o privación de la vida de personas.\nIII.- Investigar las denuncias relativas a la desaparición, secuestro u homicidio de personas,\nIV.- Llevar el control de las averiguaciones previas iniciadas y turnadas a las\nAgencias del Ministerio Público que le sean asignadas por el C. Procurador, contando, con facultad de atraer derivado de su designación cualquier averiguación previa relacionada con la desaparición secuestro o privación de la vida de personas.\nV.- Vigilar la integración de la Averiguación Previa hasta su terminación.\nVI.- Establecer mecanismos de coordinación y de interrelación con las autoridades federales, y municipales, así como con las demás áreas de Procuración de acuerdo, y las demás leyes aplicables en la entidad.\nVII.- Declinar la competencia de las averiguaciones previas a su cargo cuando se advierta la competencia de otras autoridades.\nVIII.- Informar al C. Procurador General de Justicia del Estado de manera puntual y mediante oficio, desde el inicio, seguimiento y terminación de las averiguaciones previas por el encomendadas.\nBÚSQUEDA DE CIUDADANOS\nDESAPARECIDOS, SECUESTRADOS Y\nASESINADOS, EN EL ESTADO DE GUERRERO\nIX.- Las demás que sean consecuencia de sus funciones, necesarias para el de Justicia del Estado.\nX.- Crear la base de datos en forma especifica, la cual deberá contener:\na) Nombre de la (s) victima (s).\nb) Delito\nc) Nombre de los probables responsables.\nd) Nombre del denunciante.\ne) Fecha o probable en que se suscitaron los hechos que se denuncian.\nDÉCIMO.- Los Agentes del Ministerio Público del Fuero Común de la\nProcuraduría General de Justicia del Estado de Guerrero, contando con las funciones, facultades y obligaciones que corresponden al cargo que les fue conferido y conforme a la Constitución Política de los Estados Unidos Mexicanos, la Constitución Política del\nEstado de Guerrero, la Ley Orgánica y su Reglamento de la Procuraduría General de\nJusticia del Estado de Guerrero el Código Penal y de Procedimientos Penales vigente en el Estado de Guerrero, la Ley General Para Prevenir y Sancionar los Delitos en Materia de Secuestro, reglamentaria de la fracción XXI del articulo 73 de la Constitución Política de los Estados Unidos Mexicanos, de la Ley Para Prevenir y Sancionar la Desaparición\nForzadas de Personas en el Estado de Guerrero numero 549 y demás disposiciones legales y administrativas aplicables deberán:\nGuerrero de manera inmediata de las denuncias relativas a la desaparición, secuestro u homicidio de personas por cualquier vía, independientemente de que posteriormente se haga por oficio.\nBÚSQUEDA DE CIUDADANOS\nDESAPARECIDOS, SECUESTRADOS Y\nASESINADOS, EN EL ESTADO DE GUERRERO\nII.- Actuar de manera inmediata en la investigación de las Averiguaciones Previas en los que se denuncie la desaparición, secuestro u homicidio de personas cometidas en el Estado de Guerrero, solicitando el apoyo y colaboración de las autoridades que se requieran para su debida integración.\nIII.- Las demás que le sean encomendadas por el C. Procurador General de\nJusticia del Estado de Guerrero.\nIV.- Todas las determinaciones de No ejercicio de la acción penal, así como las escritos de inconformidad respecto de las mismas serán enviados directamente y de manera inmediata para su atención al Procurador General de Justicia del Estado, quien a su vez deberá de remitirlos a la Dirección General Jurídica Consultiva para su trámite correspondiente.\nTRANSITORIOS\nPRIMERO.- El presente convenio entrara en vigor al día siguiente de su publicación en el Periódico Oficial del Gobierno del Estado de Guerrero.\nSEGUNDO.- El Procurador General de Justicia del Estado de Guerrero, por conducto del Área competente, dotará al Agente del Ministerio Público designado para la investigación de asuntos de personas desaparecidas, secuestradas o privadas de la vida, funciones.\nChilpancingo, Guerrero, Noviembre 11 del 2011.\nSufragio Efectivo. No reelección.\nEl Procurador General de Justicia del Estado.\nLIC. ALBERTO LÓPEZ ROSAS.\nRúbrica.",
  "ordenamiento": "ACUERDO",
  "jurisdiccion": "GUERRERO",
  "fuente_oficial": "DIARIO OFICIAL DE LA FEDERACION",
  "Fecha de Publicación": "2 de Diciembre de 2011",
  "ULTIMA REFORMA PUBLICADA": null,
  "status": "VIGENTE",
  "es_escaneado": false,
  "tiene_tablas": false,
  "materia": [
    "judicial"
  ]
}