{
  "titulo": "Acuerdo por el Que Se Autoriza A la Secretaria de Planeación y Presupuesto Constituirse Como Fideico",
  "Contenido": "GUERRERO EN EL FIDEICOMISO GUERRERO\nINDUSTRIAL\nPOR EL QUE SE FUSIONA EL “FIDEICOMISO PARQUE INDUSTRIAL GUERRERO”,\nAL “FIDEICOMISO GUERRERO INDUSTRIAL”, PUBLICADO EN EL PERIÓDICO\nOFICIAL DEL GOBIERNO DEL ESTADO No. 38, EL VIERNES 09 DE MAYO DEL 2008\nAcuerdo publicado en el Periódico Oficial No. 61, el martes 27 de julio de 1999.\nACUERDO POR EL QUE SE AUTORIZA A LA SECRETARIA DE PLANEACION\nY PRESUPUESTO CONSTITUIRSE COMO FIDEICOMITENTE UNICO DEL GOBIERNO\nDEL ESTADO DE GUERRERO EN EL FIDEICOMISO GUERRERO INDUSTRIAL.\nAl margen un sello con el Escudo Nacional que dice: Gobierno del Estado Libre y\nSoberano de Guerrero.- Poder Ejecutivo.\nRENE JUAREZ CISNEROS, GOBERNADOR CONSTITUCIONAL DEL ESTADO\nCONFIEREN LOS ARTICULOS 74 FRACCION III Y 76 DE LA CONSTITUCION\nEN LOS ARTICULOS 2o., 3o. Y 39 DE LA LEY ORGANICA DE LA ADMINISTRACION\nPUBLICA DEL ESTADO DE GUERRERO; 1o., 5o. Y 6o. FRACCION III Y 26 DE LA LEY\nDE ENTIDADES PARAESTATALES DEL ESTADO DE GUERRERO; Y\nQue la Ley Orgánica de la Administración Pública del Estado de Guerrero, otorga al Ejecutivo del Estado la facultad de constituir en el ámbito de la Administración Pública del Estado, Fideicomisos Públicos como unidades empresariales que tengan estructura administrativa, con el firme propósito de impulsar las áreas prioritarias del desarrollo del\nEstado. empresariales y con estructura administrativa, la Ley de Entidades Paraestatales del\nEstado de Guerrero, dispone que el Ejecutivo Estatal, otorgue autorización a la del Estado de Guerrero.\nAdministración, se concede importancia prioritaria a la promoción de inversiones productivas -con compromiso y permanencia- con el claro objetivo de: generar un gran número de empleos bien remunerados; inducir un crecimiento sostenido de la economía\nGUERRERO EN EL FIDEICOMISO GUERRERO\nINDUSTRIAL guerrerense.\nQue el mundo se acerca al año 2000 y la globalización económica es una realidad. El Tratado de Libre Comercio de Norteamérica y la apertura comercial de\nMéxico con muchos países del mundo han modificado sustancialmente los viejos equilibrios e impulsan nuevas sinergias que inducen una transformación cuantitativa y cualitativa de la estructura económica del país.\nQue en los últimos años México se ha posicionado como uno de los principales países exportadores de manufacturas del mundo y receptores de inversiones de la industria maquiladora.\nQue la nueva dinámica de las grandes empresas manufactureras y maquiladoras que están entrando a nuestro país está influyendo positivamente en la generación de empleos, en el desarrollo económico y en la posición competitiva global de las entidades donde están asentando sus operaciones.\nQue es una realidad que hasta ahora Guerrero se encuentra al margen de las inversiones productivas que están entrando al país; sin embargo, es un hecho también que con un serio esfuerzo promotor de sociedad y gobierno, el Estado se puede convertir en un destacado actor de la industria manufacturera y maquiladora.\nQue Guerrero cuenta con grandes fortalezas y ventajas competitivas que sustentan una política promotora a favor de la industria manufacturera y maquiladora:\nMano de obra competitiva y con gran disposición a ser rápidamente capacitada; destreza nivel mundial en la fabricación de artesanías y productos manuales; excelentes vías de comunicación, así como apoyo y liderazgo gubernamental a favor de los empresarios locales, nacionales y extranjeros.\nAnte este nuevo entorno de globalización, de nuevas sinergias y ventajas competitivas, es necesario e imprescindible que sociedad y gobierno cuenten con un y maquiladoras.\nGUERRERO EN EL FIDEICOMISO GUERRERO\nINDUSTRIAL\nEn este sentido, se considera necesario y viable la constitución de un fideicomiso, que tenga como misión promover la instalación de empresas manufactureras y maquiladoras de las ramas: textil, electrónica, del juguete; del mueble, del mezcal y de cualquier otra manufactura o maquila que implique la generación de empleos permanentes y sustentables en Guerrero. Por lo que bajo el estricto cumplimiento de las disposiciones legales que rigen al fideicomiso, se requiere la formalización del contrato de fideicomiso por parte de la Secretaría de Planeación y Presupuesto a efecto de que rija el ámbito de actuación del Fideicomiso Guerrero Industrial.\nPor lo anterior, he tenido a bien emitir el siguiente:\nARTICULO PRIMERO.- Se constituye en el ámbito de la Administración Pública\nEstatal el fideicomiso público denominado Fideicomiso Guerrero Industrial, como unidad empresarial y con estructura administrativa propia, por lo que se autoriza a la Secretaría de Planeación y Presupuesto, constituir dicho fideicomiso; fungiendo como fideicomitente único del Gobierno del Estado de Guerrero.\nARTICULO SEGUNDO.- Los objetivos del Fideicomiso Guerrero Industrial, serán los siguientes:\nI. Promover la instalación de empresas manufactureras y maquiladoras en el\nEstado de Guerrero.\nII. Posicionar al Estado de Guerrero como una región realmente competitiva para el desarrollo de sectores industriales generadores de muchos empleos, tales como: el textil, la electrónica, el juguete, el mueble, el zapato, el mezcal, entre otros.\nARTICULO TERCERO.- Los fines del Fideicomiso Guerrero Industrial serán los siguientes:\nGUERRERO EN EL FIDEICOMISO GUERRERO\nINDUSTRIAL\nI. Diseñar, ejecutar, administrar y promover una iniciativa de “Política\nIndustrial Maquiladora del Estado de Guerrero”;\nII. Promover al Estado de Guerrero, como una alternativa para la industria manufacturera y maquiladora mediante: el diseño y elaboración de documentos promocionales (impresos y/o electrónicos); la participación en eventos, giras, conferencias y exposiciones nacionales e internacionales;\nIII. Diseñar, promover y administrar proyectos que incorporen al sector social sociales asociadas a grandes consorcios exportadores;\nIV. Asesorar, diseñar, promover, administrar, construir (según sea el caso) parques industriales especializados en manufactura y maquila;\nV. Identificar, negociar y promover naves industriales susceptibles a ser utilizadas por empresas manufactureras y maquiladoras;\nVI. Diseñar, ejecutar, administrar y promover un eficiente sistema de capacitación que incremente sustancialmente la competitividad de la mano de obra de los guerrerenses;\nVII. Diseñar, organizar y administrar el Instituto de Capacitación Maquilador del Estado de Guerrero y las unidades móviles necesarias;\nVIII. Diseñar y gestionar incentivos fiscales, financieros, comerciales, de infraestructura y de maquinaria y equipo en favor de la “Iniciativa de Política Industrial\nMaquiladora del Estado de Guerrero”;\nIX. Apoyar logísticamente a empresas manufactureras y maquiladoras locales, nacionales e internacionales en las etapas de prospección, instalación y operación;\nX. Adquirir, vender, administrar, arrendar, usar, dar en comodato y usufructuar todo tipo de bienes;\nGUERRERO EN EL FIDEICOMISO GUERRERO\nINDUSTRIAL\nXI. Celebrar contratos con terceros, con respecto a la adquisición de bienes, servicios, ejecución de obras, previa obtención de los permisos y licencias que se requieran, dando cumplimiento a todos los trámites y requisitos legales necesarios para llevar a cabo sus objetivos;\nXII. Celebrar convenios con la federación, entidades federativas, municipios, instituciones públicas y privadas, personas consideradas jurídicamente individuales y colectivas, en su propósito de aportar bienes y recursos por cualquier título al patrimonio del fideicomiso;\nXIII. Realizar las transacciones que se consideren pertinentes a efecto de acrecentar el patrimonio del fideicomiso;\nXIV. Otorgar garantías para la obtención de financiamientos aplicados directamente a proyectos y estudios relacionados con los objetivos y fines del fideicomiso;\nXV. Otorgar financiamientos a los proyectos que el Comité Técnico considere como sujetos de apoyo, en congruencia con los objetivos y fines del fideicomiso;\nXVI. Los demás actos y operaciones que sean consecuentes a los objetivos y fines del fideicomiso.\nARTICULO CUARTO.- El patrimonio del Fideicomiso se conformará de la siguiente forma:\nI. La cantidad inicial de $1’500,000.00 (UN MILLON QUINIENTOS MIL\nPESOS M/N).\nIII. Las aportaciones que autorice el Comité Técnico del presente fideicomiso consideradas jurídicamente individuales, colectivas, nacionales o extranjeras.\nGUERRERO EN EL FIDEICOMISO GUERRERO\nINDUSTRIAL\nIV. Los rendimientos netos que se obtengan de la inversión de los activos que integren el patrimonio del fideicomiso.\nV. Los ingresos que se obtengan por la realización de los objetivos y fines del fideicomiso.\nVI Los créditos que el Comité Técnico autorice obtener de fuentes de financiamiento para incremento del patrimonio fideicomitido.\nVII. Los demás bienes, derechos, servicios y obligaciones que se adquieran con y para el patrimonio en fideicomiso que se constituye y los productos que de ellos se deriven.\nARTICULO QUINTO.- El Fideicomiso tendrá como órganos directivos los siguientes:\nI. Un Comité Técnico, que será el órgano rector del fideicomiso, que se conformará de la siguiente manera:\nPRESIDENTE: GOBERNADOR DEL ESTADO DE GUERRERO.\nVICEPRESIDENTE: SECRETARIO DE DESARROLLO ECONOMICO Y\nTRABAJO.\nSECRETARIO: DIRECTOR GENERAL DEL FIDEICOMISO.\nVOCAL: SECRETARIO DE PLANEACION Y PRESUPUESTO.\nVOCAL: SECRETARIO DE DESARROLLO URBANO Y OBRAS PUBLICAS.\nVOCAL: SECRETARIO DE FINANZAS Y ADMINISTRACION.\nCOMISARIO: CONTRALOR GENERAL DEL ESTADO.\nGUERRERO EN EL FIDEICOMISO GUERRERO\nINDUSTRIAL\nII. Un Director General, que será designado por el Comité Técnico a propuestas de su Presidente.\nARTICULO SEXTO.- El Fideicomiso independientemente de las disposiciones previstas en el contrato correspondiente, se sujetará a las disposiciones que le sean compatibles de la Ley de Entidades Paraestatales del Estado de Guerrero.\nARTICULO SEPTIMO.- En el contrato correspondiente, se preverá las reglas de operación del fideicomiso, atribuciones del Comité Técnico, atribuciones y obligaciones del Director General y la duración del fideicomiso.\nUNICO.- El presente Acuerdo entrará en vigor al día siguiente de su publicación en el Periódico Oficial del Gobierno del Estado de Guerrero.\nDado en la residencia oficial del Poder Ejecutivo en Chilpancingo de los Bravo, Guerrero, a los veintitrés días del mes de junio de mil novecientos noventa y nueve.\nATENTAMENTE.\nSUFRAGIO EFECTIVO. NO REELECCION.\nEl Gobernador Constitucional del Estado de Guerrero.\nC. RENE JUAREZ CISNEROS.\nEl Secretario General de Gobierno.\nC. FLORENCIO SALAZAR ADAME.\nGUERRERO EN EL FIDEICOMISO GUERRERO\nINDUSTRIAL\nEl Secretario de Planeación y Presupuesto.\nC. CARLOS SANCHEZ BARRIOS.\nRúbrica.\nEl Secretario de Desarrollo Económico y Trabajo.\nC. CESAR MANUEL BAJOS VALVERDE.\nEl Secretario de Finanzas y Administración.\nC. RAFAEL ACEVEDO ANDRADE.\nLa Contralora General del Estado.\nC. ANA MARIA CASTILLEJA MENDIETA.",
  "ordenamiento": "ACUERDO",
  "jurisdiccion": "GUERRERO",
  "fuente_oficial": "DIARIO OFICIAL DE LA FEDERACION",
  "Fecha de Publicación": "27 de julio de 1999",
  "ULTIMA REFORMA PUBLICADA": "09 DE MAYO DEL 2008",
  "status": "ABROGADA",
  "es_escaneado": false,
  "tiene_tablas": false,
  "materia": [
    "fiscal"
  ]
}