{
  "titulo": "Acuerdo del Consejo de Premiación del Premio al Mérito Jurídico Licenciado Alberto Vázquez del Merca",
  "Contenido": "ACUERDO DEL CONSEJO DE PREMIACIÓN DEL\nPREMIO AL MÉRITO JURÍDICO \"LICENCIADO\nALBERTO VÁZQUEZ DEL MERCADO\" QUE\nPRORROGA EL PLAZO HASTA EL DÍA 5 DE JULIO DE\n2013, PARA LA ENTREGA DE PROPUESTAS DE\nCANDIDATOS PARA RECIBIR EL PREMIO AL MÉRITO\nJURÍDICO\nTEXTO ORIGINAL.\nAcuerdo publicado en el Periódico Oficial del Gobierno del Estado de Guerrero No 52, el Viernes\n28 de Junio de 2013.\nACUERDO DEL CONSEJO DE PREMIACIÓN DEL PREMIO AL MÉRITO JURÍDICO \"LICENCIADO\nALBERTO VÁZQUEZ DEL MERCADO\" QUE PRORROGA EL PLAZO HASTA EL DÍA 5 DE JULIO DE\n2013, PARA LA ENTREGA DE PROPUESTAS DE CANDIDATOS PARA RECIBIR EL PREMIO AL\nMÉRITO JURÍDICO.\nEn la Ciudad de Chilpancingo de los Bravo, Capital del Estado de Guerrero, el primer día del mes de julio del año 2013.\nACUERDO.- Con el objeto de brindar más oportunidad a participantes y continuar recepcionando propuestas de candidatos para participar para el Premio al Mérito Jurídico \"Licenciado Alberto Vázquez del Mercado\", instituido mediante Decreto del Ejecutivo Estatal, el Consejo de Premiación, acordó mayo del año dos mil trece, hasta el día cinco de julio del año en curso; en consecuencia, publíquese el en esta Entidad, para conocimiento de la ciudadanía en General.\nAsí lo acordaron y firman los integrantes del Consejo de Premiación.\nRúbricas.",
  "ordenamiento": "ACUERDO",
  "jurisdiccion": "GUERRERO",
  "fuente_oficial": "DIARIO OFICIAL DE LA FEDERACION",
  "Fecha de Publicación": "5 DE JULIO DE \n2013",
  "ULTIMA REFORMA PUBLICADA": "28 de Junio de 2013",
  "status": "ABROGADA",
  "es_escaneado": false,
  "tiene_tablas": false,
  "materia": [
    "general"
  ]
}