{
  "titulo": "Acuerdo por el Que Se Da A Conocer la Distribución de los Recursos del Fondo para la Infraestructura 4",
  "Contenido": "ENTRE LOS MUNICIPIOS DEL ESTADO DE\nGUERRERO PARA EL EJERCICIO FISCAL 2006,\nCORRESPONDIENTE AL RAMO 33\nAPORTACIONES FEDERALES PARA ENTIDADES\nFEDERATIVAS Y MUNICIPIOS.\nABROGADO POR CONCLUIDA SU VIGENCIA HASTA EL 31 DE\nOCTUBRE DE 2006.\nTEXTO ORIGINAL.\nAcuerdo publicado en el Periódico Oficial del Gobierno del Estado No. 9, el martes 31 de Enero de 2006.\nACUERDO POR EL QUE SE DA A CONOCER LA DISTRIBUCIÓN DE LOS\nRECURSOS DEL FONDO PARA LA INFRAESTRCTURA SOCIAL MUNICIPAL ENTRE\nLOS MUNICIPIOS DEL ESTADO DE GUERRERO PARA EL EJERCICIO FISCAL 2006,\nCORRESPONDIENTE AL RAMO 33 APORTACIONES FEDERALES PARA\nENTIDADES FEDERATIVAS Y MUNICIPIOS.\nAl margen un sello con el Escudo Nacional que dice: Gobierno del Estado Libre y\nSoberano de Guerrero.- Poder Ejecutivo.\nCARLOS ZEFERINO TORREBLANCA GALINDO, GOBERNADOR\nEJERCICIO DE LAS FACULTADES QUE ME CONFIERE EL ARTÍCULO 74 DE LA\n2o., 3o., 4o., 10, 12 Y 13 DE LA LEY DE PLANEACIÓN PARA EL ESTADO DE\nGUERRERO; 4o., 6o., 7o. Y 18 FRACCIÓN II Y 21 DE LA LEY ORGÁNICA DE LA\nADMINISTRACIÓN PÚBLICA DEL ESTADO; Y DE ACUERDO A LOS ARTÍCULOS 26 Y\n115 DE LA CONSTITUCIÓN POLÍTICA DE LOS ESTADOS UNIDOS MEXICANOS; 27,\n31, 32 Y 37 DE LA LEY ORGÁNICA DE LA ADMINISTRACIÓN PÚBLICA FEDERAL; 33,\n34, 35 Y 44 DE LA LEY DE PLANEACIÓN; 25, 32, 33, 34 Y 35 DE LA LEY DE\nCOORDINACIÓN FISCAL, 13 DEL DECRETO DEL PRESUPUESTO DE EGRESOS DE\nLA FEDERACIÓN PARA EL EJERCICIO FISCAL DEL 2006; Y\n2006, en su Artículo 13, prevé recursos en el Ramo 33 Aportaciones Federales para\nENTRE LOS MUNICIPIOS DEL ESTADO DE\nGUERRERO PARA EL EJERCICIO FISCAL 2006,\nCORRESPONDIENTE AL RAMO 33\nAPORTACIONES FEDERALES PARA ENTIDADES\nFEDERATIVAS Y MUNICIPIOS.\nEntidades Federativas y Municipios, para el Fondo para la Infraestructura Social\nMunicipal.\nQue los recursos de dicho Fondo deben ser distribuidos entre los Municipios mediante la fórmula y metodología señaladas en el Capítulo V de la Ley de Coordinación\nFiscal y con base en la información establecida en el Acuerdo publicado en el Diario\nOficial de la Federación del 13 de enero del 2006 por la Secretaría de Desarrollo Social.\nQue la misma Ley de Coordinación Fiscal establece que los Estados deben publicar antes del 31 de enero del 2006, previo convenio con la Secretaría de Desarrollo\nSocial, la distribución municipal de este Fondo para la Infraestructura Social Municipal, así como la fórmula y metodología aplicada, justificando cada uno de sus elementos.\nQue la fórmula debe ser igual a la indicada en la mencionada Ley, con el propósito de enfatizar el carácter redistributivo de estos recursos hacia aquellos\nMunicipios con mayor magnitud y profundidad de pobreza extrema.\nPor lo anteriormente expuesto y fundado, he tenido a bien expedir el siguiente:\nACUERDO POR EL QUE SE DA CONOCER LA DISTRIBUCIÓN DE LOS RECURSOS\nDEL FONDO PARA LA INFRAESTRUCTURA SOCIAL MUNICIPAL ENTRE LOS\nMUNICIPIOS DEL ESTADO DE GUERRERO PARA EL EJERCICIO FISCAL DEL 2006,\nCORRESPONDIENTE AL RAMO 33 APORTACIONES FEDERALES PARA\nENTIDADES FEDERATIVAS Y MUNICIPIOS.\nARTÍCULO PRIMERO.- El presente Acuerdo tiene por objeto dar a conocer la\nFiscal del 2006, así como las asignaciones presupuestales resultantes de la aplicación de dicha metodología. de Guerrero del Fondo para la Infraestructura Social Municipal es por..............\nENTRE LOS MUNICIPIOS DEL ESTADO DE\nGUERRERO PARA EL EJERCICIO FISCAL 2006,\nCORRESPONDIENTE AL RAMO 33\nAPORTACIONES FEDERALES PARA ENTIDADES\nFEDERATIVAS Y MUNICIPIOS.\n$1,963,875,103.00 (Un mil novecientos sesenta y tres millones ochocientos setenta y cinco mil ciento tres pesos 00/100 M. N.).\nARTÍCULO TERCERO.- Las aportaciones de este Fondo sólo podrán ser utilizadas en las obras y acciones sociales básicas y en inversiones, que beneficien directamente a sectores de la población que se encuentren en condiciones de rezago social y de pobreza extrema en los siguientes rubros: agua potable; drenaje y letrinas; urbanización municipal; electrificación rural y de colonias pobres; infraestructura básica de salud; infraestructura básica educativa; mejoramiento de vivienda; caminos rurales e infraestructura productiva rural, señaladas en el Artículo 33 del Capítulo V de la Ley de\nCoordinación Fiscal y deberán ser aprobadas por las comunidades y sus representantes o vocales al interior de los Comités para la Planeación del Desarrollo Municipal.\nARTÍCULO CUARTO.- Las variables y sus respectivas normas que sirven para determinar la situación social de los Municipios son las siguientes:\nR = Población ocupada del municipio que no percibe ingresos o que éstos son hasta de dos salarios mínimos, entre la población ocupada del Estado en la misma condición.\nR = Población municipal que no sabe leer y escribir a partir de los quince años, respecto de la población del Estado en igual condición.\nR = Población municipal que habita en viviendas particulares sin disponibilidad mismo tipo de servicio.\nR = Población municipal que habita en viviendas particulares sin disponibilidad de energía eléctrica, entre la población del Estado en igual condición. i1,..4 población estatal que muestra las mismas condiciones en cada una de las variables.\nENTRE LOS MUNICIPIOS DEL ESTADO DE\nGUERRERO PARA EL EJERCICIO FISCAL 2006,\nCORRESPONDIENTE AL RAMO 33\nAPORTACIONES FEDERALES PARA ENTIDADES\nFEDERATIVAS Y MUNICIPIOS.\nARTÍCULO QUINTO.- La fórmula aplicada para la distribución de este Fondo entre los Municipios es la siguiente suma ponderada que representa al Índice Municipal de Pobreza (IMP):\nDonde:\nR = Rezago asociado a cada una de las cuatro necesidades básicas i1,..4 consideradas por el IMP en el i-ésimo Municipio con respecto al rezago estatal en esa misma necesidad.\n = Ponderador cuyo valor es 0.25 en cada uno de los rezagos.\n1,..4\nUna vez estimado el IMP para todos los municipios del Estado de Guerrero, se suman y se calcula su distribución porcentual multiplicando cada valor índice por 100. La distribución resultante se aplica al techo financiero señalado en el artículo segundo punto de este Acuerdo, para obtener el monto que le corresponde a cada Municipio.\nARTÍCULO SEXTO.- Considerando el Decreto No. 571 del Periódico Oficial del\nGobierno del Estado de Guerrero, publicado el 25 de Noviembre de 2005 mediante el cual se crea el Municipio de Iliatenco, considerando comunidades de Malinaltepec y San\nLuis Acatlán.\nPara determinar la “población ocupada que recibe hasta dos salarios mínimos”, de los Municipios de Malinaltepec, San Luis Acatlán e Iliatenco, se utilizó la información disponible a nivel de localidad del XII Censo General de Población y Vivienda 2000 del\nInstituto Nacional de Estadística, Geografía e Informática (INEGI), se sumaron los conceptos “población ocupada que no recibe ingresos”, “población ocupada que recibe menos de un salario mínimo” y “población ocupada que recibe 1 y hasta 2 salarios mínimos”; agrupando las localidades que integran el nuevo Municipio.\nPara conocer la población de 15 años y más analfabeta, de los Municipios de\nMalinaltepec, San Luis Acatlán e Iliatenco se realizó en procedimiento similar al anterior.\nENTRE LOS MUNICIPIOS DEL ESTADO DE\nGUERRERO PARA EL EJERCICIO FISCAL 2006,\nCORRESPONDIENTE AL RAMO 33\nAPORTACIONES FEDERALES PARA ENTIDADES\nFEDERATIVAS Y MUNICIPIOS.\nLa información resultante es la siguiente:\nPOBLACIÓN\nOCUPADA DEL\nMUNICIPIO QUE POBL MUNICIPAL\nMUNICIPIO\nPERCIBA HASTA DE 15 AÑOS O MÁS\nDE DOS SALARIOS QUE NO SEPA LEER\nMÍNIMOS NI ESCRIBIR\nMALINALTEPEC 8,217 5,756\nLOCALIDADES SEGREGADAS 2,385 1,308\nSAN LUIS ACATLAN 6,892 7,180\nLOCALIDADES SEGREGADAS 200 114\nMALINALTEPEC NUEVO 5,832 4,448\nSAN LUIS ACATLAN NUEVO 6,692 7,066\nILIATENCO 2,585 1,422\nPara conocer la población que no dispone de drenaje conectado a red pública o fosa séptica o a la calle en los Municipios de Malinaltepec, San Luis Acatlán e Iliatenco; se utilizará la información disponible en la base de datos denominada Integración\nTerritorial (ITER), la cual contiene información del XII Censo General de Población y\nVivienda 2000 del INEGI, a nivel de localidad. A partir de esta base se pueden asignar los rezagos que presentan las localidades que conforman el nuevo Municipio.\nPara construir esta variable, el ITER proporciona las variables “población total”, “promedio de ocupantes en viviendas particulares” y “viviendas particulares habitadas que disponen de drenaje”. Debido a que a nivel de localidad no se cuenta con la variable exacta para esta población, ésta se estima de la siguiente forma:\nPoblación Total - (viviendas particulares habitadas que disponen de drenaje x promedio de ocupantes en vivienda particulares).\nLa información utilizada es la siguiente:\nENTRE LOS MUNICIPIOS DEL ESTADO DE\nGUERRERO PARA EL EJERCICIO FISCAL 2006,\nCORRESPONDIENTE AL RAMO 33\nAPORTACIONES FEDERALES PARA ENTIDADES\nFEDERATIVAS Y MUNICIPIOS.\nVIVIENDAS\nPOBLACIÓN PARTICULARES PROMEDIO DE\nTOTAL HABITADAS QUE OCUPANTES EN POBLACIÓN SIN\nLOCALIDADES DISPONEN DE VIVIENDAS DISPONIBILIDAD\nA DRENAJE PARTICULARES DE DRENAJE\nLOCALIDADES SEGREGADAS DE\nMALINALTEPEC\nILIATENCO 2,389 46 5.48 2,137\nALCHIPAHUAC 439 0 5.42 439\nARROYO SAN PEDRO DE MORELOS 708 4 6.29 683\nCERRO ARDILLA 221 0 5.14 221\nCERRO CUATE 576 0 5.43 576\nCERRO DEL GUAYABO 122 0 5.81 122\nCERRO TEJON 340 0 6.54 340\nCOLONIA ASERRADERO 558 7 6.27 514\nCOLONIA AVIACION 122 0 6.42 122\nCOLONIA LOMA ENCINO (ILIATENCO) 183 0 4.95 183\nCRUZ LA VILLA 253 0 5.88 253\nCRUZ VERDE 346 0 5.24 346\nCRUZ TOMAHUAC 617 0 6.11 617\nLOMA DE COAPINOLE 276 1 5.63 270\nOJO DE AGUA 288 4 5.05 268\nPORTEZUELO DEL CLARIN 397 1 6.14 391\nSAN ANTONIO ABAD (SAN ANTONIO) 68 0 4.53 68\nSAN ISIDRO 149 0 5.14 149\nSANTA CRUZ HERNANDEZ 131 2 5.95 119\nTLAHUITEPEC 362 1 6.35 356\nVISTA ALEGRE 65 0 5.00 65\nTOTAL 8,239\nLOCALIDAD SEGREGADA DE SAN LUIS\nACATLAN\nSAN JOSE VISTA HERMOSA 887 1 6.86 880\nTOTAL 880\nILIATENCO 9,119 población sin servicio de drenaje del Municipio de Iliatenco.\nMunicipio de nueva creación, se hace la sumatoria de ésta y se resta del total de la variable de los municipios cuyas localidades fueron segregadas. De esta manera se\nENTRE LOS MUNICIPIOS DEL ESTADO DE\nGUERRERO PARA EL EJERCICIO FISCAL 2006,\nCORRESPONDIENTE AL RAMO 33\nAPORTACIONES FEDERALES PARA ENTIDADES\nFEDERATIVAS Y MUNICIPIOS. obtiene la variable faltante para los municipios Malinaltepec y San Luis Acatlán. La diferencia aritmética se hace de la siguiente forma:\n(Población total del municipio que no dispone de drenaje conectado a fosa séptica\nLa información utilizada es la siguiente: de Malinaltepec, San Luis Acatlán e Iliatenco; se utilizará la información disponible en la base de datos denominada ITER, la cual contiene información del XII Censo General de\nPoblación y Vivienda 2000 del INEGI, a nivel de localidad. A partir de esta base se municipio.\nENTRE LOS MUNICIPIOS DEL ESTADO DE\nGUERRERO PARA EL EJERCICIO FISCAL 2006,\nCORRESPONDIENTE AL RAMO 33\nAPORTACIONES FEDERALES PARA ENTIDADES\nFEDERATIVAS Y MUNICIPIOS.\nPara construir esta variable, el ITER proporciona las variables “población total), “promedio de ocupantes en viviendas particulares” y “viviendas particulares habitadas que disponen de energía eléctrica”. Debido a que a nivel de localidad no se cuenta con la variable exacta para esta población, ésta se estima de la siguiente forma:\nPoblación total – (Viviendas particulares habitadas que disponen de energía eléctrica x promedio de ocupantes en viviendas particulares).\nLa información utilizada es la siguiente:\nVIVIENDAS PROMEDIO DE\nPOBLACIÓN PARTICULARES OCUPANTES EN POBLACIÓN SIN\nTOTAL HABITADAS QUE VIVIENDAS DISPONIBILIDAD\nDISPONEN DE PARTICULARES DE ENERGÍA\nLOCALIDADES A ENERGÍA C ELÉCTRICA\nELÉCTRICA A - (BxC)\nLOCALIDADES SEGREGADAS DE\nMALINALTEPEC\nILIATENCO 2,389 285 5.48 827\nALCHIPAHUAC 439 2 5.42 428\nARROYO SAN PEDRO DE MORELOS 708 67 6.29 287\nCERRO ARDILLA 221 0 5.14 221\nCERRO CUATE 576 11 5.43 516\nCERRO DEL GUAYABO 122 0 5.81 122\nCERRO TEJON 340 1 6.54 333\nCOLONIA ASERRADERO 558 39 6.27 313\nCOLONIA AVIACION 122 0 6.42 122\nCOLONIA LOMA ENCINO (ILIATENCO) 183 0 4.95 183\nCRUZ LA VILLA 253 1 5.88 247\nCRUZ VERDE 346 0 5.24 346\nCRUZ TOMAHUAC 617 0 6.11 617\nLOMA DE COAPINOLE 276 1 5.63 270\nOJO DE AGUA 288 35 5.05 111\nPORTEZUELO DEL CLARIN 397 0 6.14 397\nSAN ANTONIO ABAD (SAN ANTONIO) 68 1 4.53 63\nSAN ISIDRO 149 0 5.14 149\nSANTA CRUZ HERNANDEZ 131 1 5.95 125\nTLAHUITEPEC 362 29 6.35 178\nVISTA ALEGRE 65 0 5.00 65\nTOTAL 5,922\nLOCALIDAD SEGREGADA DE\nSAN LUIS ACATLAN\nSAN JOSE VISTA HERMOSA 887 94 6.86 242\nTOTAL 242\nILIATENCO 6,164\nENTRE LOS MUNICIPIOS DEL ESTADO DE\nGUERRERO PARA EL EJERCICIO FISCAL 2006,\nCORRESPONDIENTE AL RAMO 33\nAPORTACIONES FEDERALES PARA ENTIDADES\nFEDERATIVAS Y MUNICIPIOS.\nEn base a la tabla anterior se desarrolla el procedimiento para estimar la población sin disponibilidad de energía eléctrica de Iliatenco.\nUna vez estimada la variable faltante de cada una de las localidades para el\nMunicipio de nueva creación, se hace la sumatoria de ésta y se resta del total de la variable de los municipios cuyas localidades fueron segregadas. De esta manera se obtiene la variable faltante para los municipios Malinaltepec y San Luis Acatlán. La diferencia aritmética se hace de la siguiente forma:\n(Población total del municipio que no dispone de energía eléctrica) – (Población total estimada de las localidades segregadas que no dispone de energía eléctrica).\nLa información utilizada es la siguiente:\nPOBLACIÓN SIN\nDISPONIBILIDAD DE\nMUNICIPIO\nENERGÍA ELÉCTRICA\nMALINALTEPEC 18,849\nLOCALIDADES SECREGADAS DE MALINALTEPEC (A) 5,922\nMALINALTEPEC NUEVO 12,927\nSAN LUIS ACATLÁN 13,922\nLOCALIDADES SEGREGADAS DE SAN LUÍS ACATLAN (B) 242\nSAN LUIS ACATLÁN NUEVO 13,688\n6,164\nILIATENCO (A+B)\nARTÍCULO SÉPTIMO.- La información socioeconómica utilizada para el cálculo\nMunicipal, para el Ejercicio Fiscal 2006 es la siguiente:\nENTRE LOS MUNICIPIOS DEL ESTADO DE\nGUERRERO PARA EL EJERCICIO FISCAL 2006,\nCORRESPONDIENTE AL RAMO 33\nAPORTACIONES FEDERALES PARA ENTIDADES\nFEDERATIVAS Y MUNICIPIOS.\nPOBLACIÓN POBLACIÓN\nPOBLACIÓN MUNICIPAL QUE MUNICIPAL QUE\nOCUPADA DEL POBLACIÓN HABITE EN HABITE EN\nMUNICIPIO QUE MUNICIPAL DE 15 VIVIENDAS VIVIENDAS\nMUNICIPIO PERCIBA MENOS AÑOS O MÁS PARTICULARES SIN PARTICULARES\nDE DOS QUE NO SEPA DISPONIBILIDAD DE SIN\nSALARIOS LEER NI DRENAJE DISPONIBILIDAD\nMÍNIMOS ESCRIBIR CONECTADO A DE ENERGÍA\nFOSA SÉPTICA O A ELÉCTRICA\nLA CALLE\nGUERRERO 587,596 396,498 1,717,138 333,262\nACAPULCO 157,368 48,642 217,947 7,561\nACATEPEC 6,469 5,335 25,112 21,458\nAHUACUOTZINGO 1,828 4,416 15,755 3,158\nAJUCHITLÁN DEL PROGRESO 6,958 6,521 33,828 5,216\nALCOZAUCA DE GUERRERO 1,380 4,499 14,402 1,391\nALPOYECA 1,228 860 3,378 392\nAPAXTLA 1,545 1,639 7,103 1,024\nARCELIA 4,635 3,951 20,875 2,649\nATENANGO DEL RIO 891 1,316 6,095 431\nATLAMAJALCINGO DEL MONTE 449 1,155 4,532 1,152\nATLIXTAC 4,291 5,658 19,194 8,906\nATOYAC DE ALVAREZ 14,587 6,389 38,386 3,992\nAYUTLA DE LOS LIBRES 11,127 10,448 48,893 15,979\nAZOYU 3,074 2,598 11,676 1,389\nBENITO JUAREZ 3,375 1,594 5,313 771\nBUENAVISTA DE CUELLAR 2,846 1,170 4,186 332\nCOAHUAYUTLA DE JOSE MA. I. 2,587 2,417 14,266 6,739\nCOCHOAPA EL GRANDE 2,753 5,283 12,990 9,877\nCOCULA 2,619 2,001 7,308 665\nCOPALA 2,617 2,076 8,244 772\nCOPALILLO 1,779 3,212 11,327 1,902\nCOPANATOYAC 2,067 4,368 14,658 4,331\nCOYUCA DE BENITEZ 14,437 8,872 44,665 4,734\nCOYUCA DE CATALAN 5,637 7,438 33,361 7,621\nCUAJINICUILAPA 5,189 4,208 17,414 2,224\nCUALAC 605 1,132 5,228 1,027\nCUAUTEPEC 3,277 2,356 14,018 1,016\nCUETZALA DEL PROGRESO 1,887 1,588 7,624 384\nENTRE LOS MUNICIPIOS DEL ESTADO DE\nGUERRERO PARA EL EJERCICIO FISCAL 2006,\nCORRESPONDIENTE AL RAMO 33\nAPORTACIONES FEDERALES PARA ENTIDADES\nFEDERATIVAS Y MUNICIPIOS.\nCUTZAMALA DE PINZON 3,435 4,920 17,725 2,182\nCHILAPA DE ALVAREZ 18,661 20,455 64,793 11,399\nCHILPANCINGO DE LOS BRAVO 32,117 12,908 56,826 4,973\nEDUARDO NERI 7,193 5,836 18,145 2,058\nFLORENCIO VILLARREAL 3,171 2,563 12,530 990\nGENERAL CANUTO A. NERI 749 1,014 5,974 1,136\nGENERAL HELIODORO CASTILLO 6,014 4,488 31,532 15,500\nHUAMUXTITLAN 2,493 2,417 7,426 466\nHUITZUCO DE LOS FIGUEROA 5,216 4,233 21,395 1,141\nIGUALA DE LA INDEPENDENCIA 22,979 8,412 24,506 5,243\nIGUALAPA 2,084 1,754 9,226 1,412\nILIATENCO 2,585 1,422 9,119 6,164\nIXCATEOPAN DE CUAUHTEMOC 905 894 5,161 397\nJOSE AZUETA 15,930 6,647 22,561 3,403\nJOSE JOAQUIN DE HERRERA 3,324 4,592 13,324 5,357\nJUAN R. ESCUDERO 3,717 2,994 16,093 960\nJUCHITAN 1,204 1,208 5,434 970\nLEONARDO BRAVO 4,610 3,160 16,213 1,472\nMALINALTEPEC 5,832 4,448 25,129 12,927\nMARQUELIA 2,388 1,551 8,322 709\nMARTIR DE CUILAPAN 3,491 3,330 8,929 640\nMETLATONOC 2,803 5,623 16,100 9,567\nMOCHITLAN 1,786 1,483 5,352 1,354\nOLINALA 2,777 4,581 19,026 4,248\nOMETEPEC 10,845 8,633 36,406 7,516\nPEDRO ASCENCIO ALQUISIRAS 617 1,157 6,992 4,228\nPETATLAN 9,008 4,804 27,486 4,716\nPILCAYA 2,619 944 5,453 582\nPUNGARABATO 5,453 3,324 10,817 622\nQUECHULTENANGO 5,349 6,635 27,045 5,230\nSAN LUIS ACATLAN 6,692 7,066 32,400 13,680\nSAN MARCOS 9,536 7,403 36,642 2,688\nSAN MIGUEL TOTOLAPAN 5,297 3,911 27,231 13,022\nTAXCO DE ALARCON 20,500 8,664 55,959 2,523\nTECOANAPA 8,482 5,728 39,290 4,581\nTECPAN DE GALEANA 11,885 7,985 31,713 5,738\nENTRE LOS MUNICIPIOS DEL ESTADO DE\nGUERRERO PARA EL EJERCICIO FISCAL 2006,\nCORRESPONDIENTE AL RAMO 33\nAPORTACIONES FEDERALES PARA ENTIDADES\nFEDERATIVAS Y MUNICIPIOS.\nTELOLOAPAN 8,733 6,777 34,503 5,628\nTEPECOACUILCO DE TRUJANO 5,072 4,751 21,312 1,549\nTETIPAC 1,999 1,433 9,119 1,923\nTIXTLA DE GUERRERO 7,165 4,750 21,291 1,683\nTLACOACHISTLAHUACA 3,996 5,048 14,139 5,287\nTLACOAPA 1,779 1,583 8,362 5,943\nTLALCHAPA 1,954 2,182 8,158 666\nTLALIXTAQUILLA DE MALDONADO 982 1,231 6,241 261\nTLAPA DE COMONFORT 7,387 9,524 36,658 6,499\nTLAPEHUALA 3,945 3,667 13,216 907\nUNION DE I. MONTES DE OCA, LA 4,788 3,633 19,657 3,270\nXALPATLAHUAC 673 3,240 10,944 723\nXOCHIHUETLAN 868 1,582 6,136 213\nXOCHISTLAHUACA 7,748 8,004 20,027 10,608\nZAPOTITLAN TABLAS 2,793 2,292 9,158 4,483\nZIRANDARO 4,075 3,909 17,380 4,991\nZITLALA 4,387 4,563 14,784 1,741\nFuente: Principales Resultados por Localidad. ESTADOS UNIDOS MEXICANOS; Tabulados Básicos Nacionales y por Entidad\nFederativa, Base de Datos y Tabulados de la Muestra Censal XII Censo General de Población y Vivienda 2000, Instituto Nacional de\nEstadística Geografía e Informática. Aguascalientes, Ags. 20001.\nARTÍCULO OCTAVO.- De acuerdo al monto del Fondo para la Infraestructura\nSocial Municipal asignado al Estado de Guerrero por $1,963,875,103.00 (Un mil novecientos sesenta y tres millones ochocientos setenta y cinco mil ciento tres pesos\n00/100 M. N.) y al aplicar la fórmula establecida por la Secretaría de Desarrollo Social de la Federación, la asignación municipal resultante es la siguiente:\nASIGNACION 2006\nMUNICIPIO (pesos)\nTOTAL 1,963,875,103\nACAPULCO DE JUAREZ 265,176,233\nACATEPEC 50,803,819\nAHUACUOTZINGO 16,152,710\nAJUCHITLÁN DEL PROGRESO 31,245,022\nALCOZAUCA DE GUERRERO 12,891,121\nENTRE LOS MUNICIPIOS DEL ESTADO DE\nGUERRERO PARA EL EJERCICIO FISCAL 2006,\nCORRESPONDIENTE AL RAMO 33\nAPORTACIONES FEDERALES PARA ENTIDADES\nFEDERATIVAS Y MUNICIPIOS.\nALPOYECA 3,634,317\nAPAXTLA 6,859,933\nARCELIA 18,636,375\nATENANGO DEL RIO 4,751,691\nATLAMAJALCINGO DEL MONTE 4,798,311\nATLIXTAC 29,199,970\nATOYAC DE ALVAREZ 36,956,033\nAYUTLA DE LOS LIBRES 59,754,819\nAZOYU 11,169,965\nBENITO JUAREZ 7,448,751\nBUENAVISTA DE CUELLAR 5,512,739\nCOAHUAYUTLA DE JOSE MA. I. 19,161,476\nCOCHOAPA EL GRANDE 27,107,407\nCOCULA 7,735,298\nCOPALA 8,251,755\nCOPALILLO 11,504,467\nCOPANATOYAC 17,707,403\nCOYUCA DE BENITEZ 42,793,746\nCOYUCA DE CATALAN 34,686,313\nCUAJINICUILAPA 17,801,125\nCUALAC 4,915,027\nCUAUTEPEC 11,160,319\nCUETZALA DEL PROGRESO 6,288,646\nCUTZAMALA DE PINZON 17,244,935\nCHILAPA DE ALVAREZ 76,240,202\nCHILPANCINGO DE LOS BRAVO 66,393,194\nEDUARDO NERI 21,456,607\nFLORENCIO VILLARREAL 10,864,314\nGENERAL CANUTO A. NERI 5,263,111\nGENERAL HELIODORO CASTILLO 42,433,002\nHUAMUXTITLAN 7,885,704\nHUITZUCO DE LOS FIGUEROA 17,398,084\nIGUALA DE LA INDEPENDENCIA 44,347,409\nIGUALAPA 8,631,322\nILIATENCO 15,609,516\nIXCATEOPAN DE CUAUHTEMOC 3,923,700\nJOSE AZUETA 33,005,201\nJOSE JOAQUIN DE HERRERA 20,164,973\nENTRE LOS MUNICIPIOS DEL ESTADO DE\nGUERRERO PARA EL EJERCICIO FISCAL 2006,\nCORRESPONDIENTE AL RAMO 33\nAPORTACIONES FEDERALES PARA ENTIDADES\nFEDERATIVAS Y MUNICIPIOS.\nJUAN R. ESCUDERO 12,828,764\nJUCHITAN 5,485,048\nLEONARDO BRAVO 14,569,067\nMALINALTEPEC 36,609,785\nMARQUELIA 7,340,285\nMARTIR DE CUILAPAN 10,536,204\nMETLATONOC 28,002,244\nMOCHITLAN 6,853,646\nOLINALA 19,691,030\nOMETEPEC 41,233,554\nPEDRO ASCENCIO ALQUISIRAS 10,176,160\nPETATLAN 28,281,880\nPILCAYA 5,773,790\nPUNGARABATO 12,681,437\nQUECHULTENANGO 28,122,987\nSAN LUIS ACATLAN 43,758,392\nSAN MARCOS 31,571,513\nSAN MIGUEL TOTOLAPAN 36,239,035\nTAXCO DE ALARCON 47,574,075\nTECOANAPA 32,162,680\nTECPAN DE GALEANA 37,338,914\nTELOLOAPAN 33,845,093\nTEPECOACUILCO DE TRUJANO 18,496,528\nTETIPAC 8,885,040\nTIXTLA DE GUERRERO 20,435,513\nTLACOACHISTLAHUACA 21,421,213\nTLACOAPA 14,592,864\nTLALCHAPA 7,648,287\nTLALIXTAQUILLA DE MALDONADO 4,513,771\nTLAPA DE COMONFORT 38,021,283\nTLAPEHUALA 12,951,941\nUNION DE I. MONTES DE OCA, LA 18,937,064\nXALPATLAHUAC 8,768,578\nXOCHIHUEHUETLAN 4,752,412\nXOCHISTLAHUACA 37,739,046\nZAPOTITLAN TABLAS 14,394,736\nZIRANDARO 20,567,442\nZITLALA 16,107,734\nENTRE LOS MUNICIPIOS DEL ESTADO DE\nGUERRERO PARA EL EJERCICIO FISCAL 2006,\nCORRESPONDIENTE AL RAMO 33\nAPORTACIONES FEDERALES PARA ENTIDADES\nFEDERATIVAS Y MUNICIPIOS.\nARTÍCULO NOVENO.- Con fundamento en el artículo 33 inciso b) de la Ley de\nCoordinación Fiscal, los Municipios podrán disponer de hasta un dos por ciento del total de los recursos del Fondo para la Infraestructura Social Municipal para la realización de un Programa de Desarrollo Institucional. Este programa será convenido entre el Ejecutivo\nFederal a través de la Secretaría de Desarrollo Social, el Gobierno del Estado y cada\nMunicipio.\nLos Municipios podrán destinar hasta un tres por ciento del total de los recursos del Fondo para la Infraestructura Social Municipal asignado a cada uno de ellos para gastos indirectos a las obras señaladas en el mencionado artículo.\nRespecto de las aportaciones de este Fondo, los Municipios deberán:\nI.- Hacer del conocimiento de sus habitantes, los montos que reciban, las obras y acciones a realizar, el costo de cada una, su ubicación, metas y beneficiarios;\nII.- Promover la participación de las comunidades beneficiadas, en su destino, aplicación y vigilancia, así como en la programación, ejecución, control, seguimiento y evaluación de las obras y acciones que se vayan a realizar;\nIII.- Informar a sus habitantes, al término de cada ejercicio, sobre los resultados alcanzados;\nIV.- Proporcionar por conducto del Gobierno Estatal a la Secretaría de Desarrollo\nSocial, la información que sobre la utilización del Fondo para la Infraestructura Social Municipal le sea requerida; y\nV.- Procurar la preservación y protección del medio ambiente y que impulsen el desarrollo sustentable.\nARTÍCULO DÉCIMO.- La Secretaría de Finanzas y Administración, una vez radicada la\nCoordinación Fiscal, el Calendario de entrega de los recursos a los Municipios del Fondo para la\nInfraestructura Social Municipal para el Ejercicio Fiscal 2006 será:\nENTRE LOS MUNICIPIOS DEL ESTADO DE\nGUERRERO PARA EL EJERCICIO FISCAL 2006,\nCORRESPONDIENTE AL RAMO 33\nAPORTACIONES FEDERALES PARA ENTIDADES\nFEDERATIVAS Y MUNICIPIOS.\nMES FISM\nEnero 31\nFebrero 28\nMarzo 31\nAbril 28\nMayo 31\nJunio 30\nJulio 31\nAgosto 31\nSeptiembre 29\nOctubre 31\nÚNICO.- El presente Acuerdo entrará en vigor a partir del día siguiente de su publicación en el Periódico Oficial del Gobierno del Estado.\nDado en la Residencia Oficial del Poder Ejecutivo Estatal en Chilpancingo de los\nBravo, Guerrero, a los treinta y un días del mes de enero del año dos mil seis.\nGOBERNADOR CONSTITUCIONAL DEL ESTADO\nC. P. CARLOS ZEFERINO TORREBLANCA GALINDO\nRúbrica.\nSECRETARIO GENERAL DE GOBIERNO\nC. LIC. ARMANDO CHAVARRÍA BARRERA\nRúbrica.\nSECRETARIA DE DESARROLLO SOCIAL\nC. GLORIA MA. SIERRA LÓPEZ\nRúbrica.\nENTRE LOS MUNICIPIOS DEL ESTADO DE\nGUERRERO PARA EL EJERCICIO FISCAL 2006,\nCORRESPONDIENTE AL RAMO 33\nAPORTACIONES FEDERALES PARA ENTIDADES\nFEDERATIVAS Y MUNICIPIOS.\nSECRETARIO DE FINANZAS Y ADMINISTRACIÓN\nC. P. CARLOS ÁLVAREZ REYES\nRúbrica.",
  "ordenamiento": "ACUERDO",
  "jurisdiccion": "GUERRERO",
  "fuente_oficial": "DIARIO OFICIAL DE LA FEDERACION",
  "Fecha de Publicación": "25 de Noviembre de 2005",
  "ULTIMA REFORMA PUBLICADA": "31 de Enero de 2006",
  "status": "ABROGADA",
  "es_escaneado": false,
  "tiene_tablas": true,
  "materia": [
    "general"
  ]
}