{
  "titulo": "Acuerdo PGJDGELA0102012 de la Procuradora General de Justicia del Estado de Guerrero, por el Que Se",
  "Contenido": "PROCESAMIENTO DEL LUGAR DE LOS HECHOS O DEL\nHALLAZGO Y DE LOS INDICIOS, HUELLAS O VESTIGIOS\nDEL HECHO DELICTUOSO, ASÍ COMO DE LOS\nINSTRUMENTOS, OBJETOS O PRODUCTOS DEL DELITO\nTEXTO ORIGINAL.\nAcuerdo publicado en el Periódico Oficial del Gobierno del Estado No. 99 Alcance I, el Martes 11 de Diciembre de 2012.\nACUERDO PGJ/DGEL/A/010/2012 DE LA PROCURADORA GENERAL DE JUSTICIA DEL ESTADO\nDE GUERRERO, POR EL QUE SE ESTABLECEN LOS LINEAMIENTOS QUE DEBERÁN OBSERVAR\nTODOS LOS SERVIDORES PÚBLICOS DE LA INSTITUCIÓN PARA LA DEBIDA PRESERVACIÓN Y\nPROCESAMIENTO DEL LUGAR DE LOS HECHOS O DEL HALLAZGO Y DE LOS INDICIOS,\nHUELLAS O VESTIGIOS DEL HECHO DELICTUOSO, ASÍ COMO DE LOS INSTRUMENTOS,\nOBJETOS O PRODUCTOS DEL DELITO.\nLA MAESTRA MARTHA ELVA GARZÓN BERNAL, PROCURADORA GENERAL DE\nJUSTICIA DEL ESTADO DE GUERRERO, EN EJERCICIO DE LAS FACULTADES QUE ME\nCONFIEREN LOS ARTÍCULOS 21 PÁRRAFO PRIMERO DE LA CONSTITUCIÓN POLÍTICA DE LOS\nESTADOS UNIDOS MEXICANOS; 78 PÁRRAFO PRIMERO DE LA CONSTITUCIÓN POLÍTICA DEL\nXVIII DE LA LEY ORGÁNICA DE LA PROCURADURÍA GENERAL DE JUSTICIA; 18 TERCER\nPÁRRAFO Y 35 FRACCIÓN I DE LA LEY ORGÁNICA DE LA ADMINISTRACIÓN PÚBLICA DEL\nESTADO; ASÍ COMO 5 DEL REGLAMENTO DE LA LEY ORGÁNICA DE LA PROCURADURÍA\nGENERAL DE JUSTICIA, Y\nCONSIDERANDO\nQue la Ley Orgánica de la Procuraduría General de Justicia del estado de Guerrero, en su artículo 29 fracción XVIII, para el buen despacho de los asuntos, establece como facultad indelegable del\nTitular de la Procuraduría General de Justicia del Estado, expedir los acuerdos, circulares, instructivos, bases y manuales de organización y procedimientos que sean necesarios.\nQue en cumplimiento a la recomendación No. 1VG/2012, de la Comisión Nacional de Derechos\nHumanos, sobre la Investigación de violaciones graves a los Derechos Humanos, relacionada con los en la recomendación CUARTA, Fracción V del numeral 470, que en el caso de la preservación del lugar de los hechos, el Gobernador Constitucional del Estado de Guerrero instruya a quien corresponda, a fin genere en intervenciones policiales, con el propósito de garantizar a la institución del Ministerio Público una eficaz investigación de los acontecimientos.\nPROCESAMIENTO DEL LUGAR DE LOS HECHOS O DEL\nHALLAZGO Y DE LOS INDICIOS, HUELLAS O VESTIGIOS\nDEL HECHO DELICTUOSO, ASÍ COMO DE LOS\nINSTRUMENTOS, OBJETOS O PRODUCTOS DEL DELITO\nQue el Código de Procedimientos Penales es un ordenamiento general y abstracto, que establece normas de carácter obligatorio para el Ministerio Público del Fuero Común, los Servicios\nPericiales del estado, la Policía Investigadora Ministerial y para todos los integrantes de Instituciones\nPoliciales, incluso estatales y municipales, que por su cercanía al lugar de los hechos, entran en primera instancia en contacto con los elementos materiales objeto de la cadena de custodia, relacionada con delitos del orden Común y Federal.\nQue los artículos 1, 54 y 58 del invocado Código Procesal, prevén el deber de dictar todas las medidas y providencias necesarias para impedir que se pierdan, destruyan o alteren los indicios, huellas o vestigios del hecho delictuoso, así como los instrumentos, objetos o productos del delito, una vez que tengan la noticia del delito las policías o los funcionarios encargados de practicar las diligencias de averiguación previa en auxilio del Ministerio Público.\nQue los antes citados artículos, establecen expresamente que la preservación de los indicios, huellas o vestigios del hecho delictuoso, así como los instrumentos, objetos o productos del delito, es responsabilidad directa de los servidores públicos que entren en contacto con ellos.\nQue la Procuraduría General de Justicia, como Institución integrante del Sistema Estatal de\nSeguridad Pública, se encuentra comprometida a implementar las medidas conducentes para que la conducta de los servidores públicos que la integran, de manera especial la de los Agentes del Ministerio\nPúblico del Fuero Común, Policías Ministeriales y Peritos, se rija efectivamente por los principios previstos por la Constitución Política de los Estados Unidos Mexicanos, de legalidad, eficiencia, profesionalismo y honradez.\nQue con fundamento en la Ley General del Sistema Nacional de Seguridad Pública, en la XXIV\nAsamblea Plenaria de la Conferencia Nacional de Procuración de Justicia, a la cual pertenece la\nProcuraduría General de Justicia del Estado de Guerrero, se aprobó el Acuerdo CNPJ/XXIV/08/2010, por e Instrumentación de la Cadena de Custodia de los Indicios, Huellas o vestigios del Hecho Delictuoso, y de los Instrumentos, Objetos o Productos del Delito.\nGuerrero, número 36 alcance I, el \"ACUERDO PGJ/DGEL/001/2012 DEL SUBPROCURADOR DE\nCONTROL REGIONAL Y PROCEDIMIENTOS PENALES, ENCARGADO DE DESPACHO DE LA\nPROCURADURÍA GENERAL DE JUSTICIA DEL ESTADO DE GUERRERO, POR EL QUE SE\nPROCESAMIENTO DEL LUGAR DE LOS HECHOS O DEL\nHALLAZGO Y DE LOS INDICIOS, HUELLAS O VESTIGIOS\nDEL HECHO DELICTUOSO, ASÍ COMO DE LOS\nINSTRUMENTOS, OBJETOS O PRODUCTOS DEL DELITO\nO DEL HALLAZGO Y DE LOS INDICIOS, HUELLAS O VESTIGIOS DEL HECHO DELICTUOSO, ASÍ\nCOMO DE LOS INSTRUMENTOS, OBJETOS O PRODUCTOS DEL DELITO.\nQue como parte del mejoramiento de la procuración de justicia, es importante la actualización y modernización de los instrumentos normativos emitidos por la Procuraduría General de Justicia del\nEstado de Guerrero, en los que se le incorporen nuevos elementos que mejoren el cumplimiento de los objetivos de los mismos.\nQue es importante adecuar los diferentes formatos a las necesidades que se han generado en la práctica de la preservación y procesamiento del lugar de los hechos o del hallazgo y de los indicios, huellas o vestigios del hecho delictuoso, así como de los instrumentos, objetos o productos del delito, derivado del procesamiento actual llevado a cabo por los servidores públicos que intervienen en el esclarecimiento de un hecho.\nQue considerando lo anterior, y para el mejor cumplimiento del deber de preservar la cadena de custodia que prevé el ordenamiento adjetivo estatal, y que impone a los miembros de las Instituciones de\nSeguridad Pública y a todo aquel servidor público que entre en contacto con los indicios, objetos, instrumentos o productos del delito, así como para salvaguardar un estricto apego al principio de legalidad, se requiere contar con un instrumento que establezca directrices claras, precisas y fundamentadas adecuadamente.\nPor lo anteriormente expuesto y fundado, he tenido a bien expedir el siguiente:\nACUERDO PGJ/DGEL/A/010/2012 DE LA PROCURADORA GENERAL DE JUSTICIA DEL ESTADO\nDE GUERRERO, POR EL QUE SE ESTABLECEN LOS LINEAMIENTOS QUE DEBERÁN OBSERVAR\nOBJETOS O PRODUCTOS DEL DELITO.\nCAPÍTULO I\nDISPOSICIONES PRELIMINARES\nArtículo 1. El presente acuerdo tiene el objeto de establecer los lineamientos siguientes:\nI. Regular la actuación de los Agentes del Ministerio Público, Peritos, Agentes de la Policía\nMinisterial y todos aquellos servidores públicos que por obligación, deben de seguir al intervenir en la\nPROCESAMIENTO DEL LUGAR DE LOS HECHOS O DEL\nHALLAZGO Y DE LOS INDICIOS, HUELLAS O VESTIGIOS\nDEL HECHO DELICTUOSO, ASÍ COMO DE LOS\nINSTRUMENTOS, OBJETOS O PRODUCTOS DEL DELITO integración de la averiguación previa, específicamente relacionada con el aseguramiento oportuno de los instrumentos, objetos, productos, huellas y demás vestigios relacionados con el delito;\nII. Normar la obligación por parte de los servidores públicos que conozcan de un hecho ilícito, de comunicarlo de inmediato al Agente del Ministerio Público más próximo al lugar del evento, preservando el lugar de los hechos para evitar que personas ajenas puedan entrar en contacto con los instrumentos, objetos, productos, huellas y demás vestigios relacionados con el delito;\nIII. Establecer que el Ministerio Público debe hacer del conocimiento inmediato los hechos a la\nPolicía Ministerial para el efecto de que acordonen el área donde se haya suscitado el ilícito, con el fin de evitar que puedan ser alterados de cualquier forma; y\nIV. Regular la obligación del Ministerio Público, de dar aviso inmediato a los servicios periciales, para que éstos aseguren los objetos, productos, huellas y demás vestigios relacionados con el delito, y se puedan emitir los dictámenes periciales que del propio hecho ilícito se desprendan.\nArtículo 2. En términos del artículo 58 del Código de Procedimientos Penales del Estado de\nGuerrero y del artículo 11, fracción VI, de la Ley Orgánica de la Procuraduría General de Justicia del\nEstado, aplicados al presente acuerdo, el procedimiento para el aseguramiento oportuno de los instrumentos, objetos, productos, huellas y demás vestigios relacionados con el delito, tendrá los siguientes mecanismos que se definirán en la forma siguiente:\nI. Cadena de Custodia: Es el procedimiento de control que se aplica al indicio material, ya sea vestigio, medio de comisión, objeto material o producto relacionado con el delito, desde su localización por parte de una autoridad competente, el cual servirá para la integración y determinación de la averiguación previa y, en su caso, la consignación ante la autoridad judicial.\nII. Indicios o Evidencias: Son los hechos conocidos de los que se infiere lógicamente la existencia de los hechos que se pretende acreditar, así como los objetos, productos, huellas y demás vestigios relacionados a la comisión de un delito, que puedan encontrarse en el lugar de los hechos, lugar del hallazgo o en sitio diferente, y que por sus características existe la probabilidad de que tengan alguna relación con la comisión de los hechos que se investigan, y con el sujeto activo, probable responsable de la comisión del ilícito.\nIII. Preservación del lugar de los hechos y/o del lugar del hallazgo: Es la serie de actos llevados cometido el delito, o en donde se haya encontrado algún indicio o evidencia de su comisión, con el objeto\nPROCESAMIENTO DEL LUGAR DE LOS HECHOS O DEL\nHALLAZGO Y DE LOS INDICIOS, HUELLAS O VESTIGIOS\nDEL HECHO DELICTUOSO, ASÍ COMO DE LOS\nINSTRUMENTOS, OBJETOS O PRODUCTOS DEL DELITO de evitar cualquier intromisión indebida o inadecuada que dañe, altere, descomponga o contamine los indicios o evidencias que se puedan hallar.\nIV. Procesamiento de los indicios o evidencias: Es el Procedimiento tendente a preservar los indicios o evidencias, mismo que está constituido por las siguientes etapas: identificación, fijación, levantamiento, embalaje, traslado y entrega de los indicios a los servicios periciales para la emisión de los dictámenes periciales correspondientes, para posteriormente ponerlos a la vista del Agente del Ministerio\nPúblico para que de fe de los mismos, y se agreguen física o jurídicamente a la averiguación previa.\nHecho todo lo anterior, el Ministerio Público, de acuerdo a la naturaleza de las evidencias, determinará si quedan en su poder o se remiten a la Dirección General de Bienes Asegurados de la\nProcuraduría General de Justicia del Estado.\nV. Registro de Cadena de Custodia: Es el documento en el que se asentarán los nombres y firmas de:\na) Los Agentes de la Policía Ministerial que hayan localizado el lugar donde se hubiera cometido un delito o encontrado un indicio relacionado con el mismo;\nb) El Agente del Ministerio Público que haya conocido del hecho;\nc) El o los peritos que hubieren intervenido en el conocimiento y emisión de los dictámenes periciales, descripción de los bienes, características de los mismos, lugar de los hechos y/o del hallazgo y demás relativos para la integración de la averiguación previa; y\nd) Cualquier otro dato que fuere importante para los fines de preservación de indicios y evidencias.\nVI. Ubicación de testigos: Ubicar a personas que puedan aportar elementos de identificación, media filiación y/o retrato hablado.\nVII. Protocolo de Cadena de Custodia: Documento elaborado por el Grupo Nacional de\nDirectores de Servicios Periciales, en el marco de la Conferencia Nacional de Procuración de Justicia.\nVIII. Guía para la aplicación de Cadena de Custodia: Es el documento que especifica los protocolos a seguir para llevar a cabo correctamente la CADENA DE CUSTODIA (anexo 1).\nArtículo 3. Para los efectos del presente Acuerdo se entenderá por:\nPROCESAMIENTO DEL LUGAR DE LOS HECHOS O DEL\nHALLAZGO Y DE LOS INDICIOS, HUELLAS O VESTIGIOS\nDEL HECHO DELICTUOSO, ASÍ COMO DE LOS\nINSTRUMENTOS, OBJETOS O PRODUCTOS DEL DELITO\nI. Ministerio Público: El Agente del Ministerio Público del Fuero Común.\nII. Policía: El Agente de la Policía Ministerial o cualquier Corporación Policiaca facultada, que intervenga en la Cadena de Custodia.\nIII. Código: El Código de Procedimientos Penales del Estado de Guerrero.\nIV. Registro: El Registro de Cadena de Custodia.\nV. Guía: Guía para la aplicación de la Cadena de Custodia.\n(anexo 1).\nVI. Servicios Periciales: La Dirección de los Servicios Periciales, de la Procuraduría General de\nJusticia del Estado.\nCAPÍTULO II\nDEL REGISTRO DE CADENA DE CUSTODIA\nArtículo 4. Todas las actuaciones que se realicen por orden del Agente del Ministerio Público o del Juez, según sea el caso, para la preservación del lugar de los hechos y/o del hallazgo, y el procesamiento de los indicios o evidencias hasta que finalice el mismo, se asentarán en el Registro de\nCadena de Custodia.\nArtículo 5. A fin de evitar el rompimiento de la Cadena de Custodia, en términos de los artículos\n1º, 54º y 58º, del Código y en la forma y términos señalados en la Guía anexa para el Registro, deberán asentarse en este a todas las personas que entren en contacto con los indicios o evidencias, e intervengan en las distintas fases de su procesamiento, desde su búsqueda, su traslado a los Servicios\nPericiales para la realización de las pruebas correspondientes, y su almacenamiento o transferencia a la\nDirección General de Bienes Asegurados, según sea el caso.\nSe asentarán en el Registro los nombres completos y cargos de los servidores públicos, la información correspondiente a su intervención, su firma autógrafa y la razón de la entrega de unos a otros, así como cualquier otro dato que se requiera.\nAsimismo, en la forma y términos indicados en dicha Guía, deberán adherir al embalaje de los indicios o evidencias, las señalizaciones o rótulos correspondientes, con los datos que en ella se indican, así como quién se encarga del transporte, y las condiciones materiales y ambientales en que se dé su traslado. cadáveres en las que intervengan distintos servidores públicos, o cualquier persona, incluidos los familiares del fallecido.\nPROCESAMIENTO DEL LUGAR DE LOS HECHOS O DEL\nHALLAZGO Y DE LOS INDICIOS, HUELLAS O VESTIGIOS\nDEL HECHO DELICTUOSO, ASÍ COMO DE LOS\nINSTRUMENTOS, OBJETOS O PRODUCTOS DEL DELITO\nArtículo 6. El Registro deberá contener:\nI. El número de averiguación previa;\nII. La unidad administrativa responsable (área a la que pertenece el servidor público que interviene);\nIII. El número de registro (folio o llamado);\nIV. La ubicación e identificación del lugar incluyendo los croquis;\nV. La información sobre víctimas, detenidos, testigos o cualquier otra recabada en el lugar de los hechos y/o del hallazgo; y\nVI. El nombre completo, cargo y firma de los servidores públicos que intervinieron en la preservación del lugar.\nVII. Los datos sobre la identificación, ubicación, recolección o levantamiento, embalaje, traslado y entrega de los indicios o evidencias al Agente del Ministerio Público, y de éste a los servicios periciales;\nVIII. Las medidas tomadas por los peritos para conservar la Cadena de Custodia; y\nIX. La autoridad que ordena la disposición final, y los datos de los testigos de la destrucción de los indicios o evidencias, de ser necesario.\nCAPÍTULO III\nDE LA PRESERVACIÓN DEL LUGAR DE LOS HECHOS Y/O DEL HALLAZGO\nArtículo 7. Los autoridad policíaca o de las instituciones de seguridad pública, que tengan primer conocimiento del lugar de los hechos y/o del hallazgo, ya sea de delitos del orden común o del federal, lo harán saber de inmediato al Agente del Ministerio Público, para fines de la conducción y mando de la investigación del delito y de las instrucciones que dicte, en su caso, para la preservación del lugar.\nEn el lugar de los hechos y/o del hallazgo, los elementos de la Policía deberán:\nI. Delimitar la zona e impedir que personas ajenas a los peritos y Agentes del Ministerio Público, puedan acceder a ella;\nPROCESAMIENTO DEL LUGAR DE LOS HECHOS O DEL\nHALLAZGO Y DE LOS INDICIOS, HUELLAS O VESTIGIOS\nDEL HECHO DELICTUOSO, ASÍ COMO DE LOS\nINSTRUMENTOS, OBJETOS O PRODUCTOS DEL DELITO\nII. Verificar que no existan elementos o cualquier otro objeto que ponga en riesgo a las víctimas o el lugar de los hechos y/o del hallazgo, o a la ciudadanía en general, en el caso de que hayan ocurrido hechos delictivos con artefactos explosivos, u otro tipo de artefactos o sustancias peligrosas, procurando siempre preservar las evidencias en el estado en que se encontraban al momento de su llegada;\nIII. Fijar el lugar de los hechos y/o del hallazgo mediante cualquier medio que tengan a su alcance, ya sea a través de fotografías, videograbación, planos, y por escrito, además de detallar la ubicación en que ocurrieron los hechos delictivos.\nIV. Organizar a los Agentes de la Policía Ministerial y de otras corporaciones que arriben al lugar de los hechos y/o del hallazgo, con el objeto de que se les asignen tareas de custodia de las zonas delimitadas, alejadas de éste.\nV. Localizar, entrevistar y custodiar en su caso, a los posibles testigos presenciales de los hechos, bajo las instrucciones del Agente del Ministerio Público;\nVI. Detallar las condiciones en las que se encontraba el lugar de los hechos y/o del hallazgo al momento de su arribo y revisión, cuando informe al Agente del Ministerio Público sobre su intervención, sin perjuicio de la elaboración del informe policial homologado; y\nVII. Las demás acciones necesarias para la preservación del lugar de los hechos y/o del hallazgo.\nPara efectos de la Preservación del Lugar de los hechos y/o del hallazgo, los Agentes de la\nPolicía que intervengan, se estarán a lo previsto en la Guía anexa y demás disposiciones aplicables.\nCAPÍTULO IV\nArtículo 8. De conformidad con lo previsto en los artículos 1, 54, Y 58 del Código, cuando el constitutivos de un delito que deban perseguirse de oficio, o bien inmediatamente después de que la hechos y/o del hallazgo, procederá de la manera siguiente:\nI. Instruirá a la Policía para que preserve el lugar de los hechos y/o del hallazgo, instruyéndola para que permanezcan inalterados los indicios o evidencias, en el lugar y la forma en que se encuentren,\nPROCESAMIENTO DEL LUGAR DE LOS HECHOS O DEL\nHALLAZGO Y DE LOS INDICIOS, HUELLAS O VESTIGIOS\nDEL HECHO DELICTUOSO, ASÍ COMO DE LOS\nINSTRUMENTOS, OBJETOS O PRODUCTOS DEL DELITO de conformidad con lo previsto en el capítulo anterior, en la Guía anexa al presente y en las demás disposiciones aplicables, a efecto de que aquella pueda emitir el parte informativo correspondiente;\nII. Acudirá al lugar de los hechos y/o del hallazgo, asistido por el personal pericial, por los\nAgentes de la corporación policial que se encuentren preservando el lugar, por los elementos de los servicios de emergencia de ser el caso, así como de todo el personal que deba intervenir, de acuerdo a las circunstancias;\nIII. Revisará que la Policía haya preservado el lugar de los hechos y/o del hallazgo, conforme a lo dispuesto en este instrumento; asimismo, solicitará a la Policía, un informe detallado de las circunstancias ocurridas, además del informe policial homologado que rinda, y en su caso, sobre la puesta a disposición de los detenidos que hubiere;\nIV. Dará la orden a los Servicios Periciales que arriben al lugar, para que realicen el procesamiento de los indicios o evidencias, en términos de lo dispuesto en los artículos 54 y 58 del\nCódigo de Procedimientos Penales del Estado de Guerrero y la Guía anexa, procediendo, en lo conducente, en los términos previstos en el Código de Procesal Penales del Estado y en el Artículo 12 del presente Acuerdo.\nV. Se cerciorará de que los peritos que arriben al lugar de los hechos y/o del hallazgo, cuenten con Identificación oficial expedida por la Procuraduría, así como la vestimenta y el material necesario para llevar a cabo el procesamiento adecuado de los indicios o evidencias.\nArtículo 9. Si el lugar de los hechos y/o del hallazgo se encuentra en una localidad que cuente con Unidades de Policía facultadas, y éstas descubran indicios o evidencias, deberán informar de esta circunstancia de manera inmediata al Agente del Ministerio Público más cercano, debiendo proceder, en su caso, a la realización de las distintas etapas del procesamiento: búsqueda o identificación, fijación, recolección o levantamiento, embalaje, traslado de los indicios o evidencias, y entrega o puesta a disposición del Agente del Ministerio Público, de conformidad con lo dispuesto en los artículos 54 y 58 del protocolos que al efecto se emitan y demás disposiciones aplicables en el estado. De la misma forma indicios o evidencias.\nLos agentes de policía seguirán el mismo procedimiento en los casos en que, teniendo el Agente del Ministerio Público conocimiento directo de la comisión del delito, solicite su intervención para el procesamiento de los indicios o evidencias señaladas en el párrafo anterior.\nPROCESAMIENTO DEL LUGAR DE LOS HECHOS O DEL\nHALLAZGO Y DE LOS INDICIOS, HUELLAS O VESTIGIOS\nDEL HECHO DELICTUOSO, ASÍ COMO DE LOS\nINSTRUMENTOS, OBJETOS O PRODUCTOS DEL DELITO\nLa entrega o puesta a disposición de los indicios o evidencias al Agente del Ministerio Público, se hará en su totalidad, en sus respectivos contenedores cuando su volumen así lo permita, o bien mediante muestras representativas, cuando se trate de indicios o evidencias cuyo volumen o características físicas no permita un manejo adecuado de los mismos; estas circunstancias se harán constar en el Registro, en los partes policiales y en las actas circunstanciadas o complementarias correspondientes.\nArtículo 10. En los supuestos del primer párrafo del artículo anterior, el Agente del Ministerio\nPúblico podrá presentarse en el lugar de los hechos y/o del hallazgo cuando lo considere necesario, en cuyo caso tendrá que recabar todos los indicios o evidencias, en sus respectivos contenedores, por parte de las Unidades de Policía Facultadas; dicha entrega se hará constar en el Registro de las actas, partes policiales o en su defecto, de los documentos donde se haya dejado constancia del estado en que fueron hallados por los Agentes de Policía, para efectos de la averiguación previa y la práctica de las respectivas diligencias periciales.\nArtículo 11. Respecto de los efectos previstos en los artículos 54 y 58 del Código, el Agente del\nMinisterio Público podrá autorizar a las Unidades de Policía Facultadas para realizar la inspección policial a que se refieren los mencionados preceptos, cuando las circunstancias de la hora, de la lejanía del lugar, o del tiempo que tarde en llegar al lugar de los hechos y/o del hallazgo, pueda repercutir en la pérdida de los indicios o evidencias.\nEn el supuesto antes señalado, las Unidades de Policía Facultadas procederán con estricto apego tanto a lo previsto en los artículos del Código mencionados en el párrafo anterior, como en el presente Acuerdo, asentando los datos correspondientes en el Registro. En el caso de que las Unidades de Policía Facultadas carezcan de dicho formato, el acta circunstanciada de la inspección se anexará a la indagatoria de manera provisional y con posterioridad se hará constar en el Registro.\nArtículo 12. Una vez que las Unidades de Policía Facultadas hayan entregado los indicios o evidencias respecto del probable hecho delictuoso, el Agente del Ministerio Público procederá de la siguiente manera:\nI. Verificará inmediatamente, auxiliándose de los peritos necesarios, para que se sigan los y 58 del Código, con el objeto de darles una adecuada preservación a los indicios o evidencias;\nII. Hará constar en la respectiva Averiguación Previa, si ese fuera el caso, que no se observaron los artículos 54 y 58 del Código, el presente Acuerdo y su Guía anexa, para dar el adecuado\nPROCESAMIENTO DEL LUGAR DE LOS HECHOS O DEL\nHALLAZGO Y DE LOS INDICIOS, HUELLAS O VESTIGIOS\nDEL HECHO DELICTUOSO, ASÍ COMO DE LOS\nINSTRUMENTOS, OBJETOS O PRODUCTOS DEL DELITO procesamiento a los indicios o evidencias y de ser el caso, dará vista para los efectos procedentes a las autoridades que correspondan;\nIII. Resolverá, en términos de los dispuesto por los artículos 54, 58 y 73 del Código y demás disposiciones aplicables, y una vez que se hayan realizado los dictámenes periciales señalados en el párrafo anterior, sobre el aseguramiento de los indicios o evidencias, su devolución, o su destrucción.\nCualquiera de los supuestos anteriores, deberá asentarse en el Registro;\nIV. Determinará el aseguramiento de los medios probatorios recabados, indicios o evidencias, entre los que se podrán encontrar el objeto material o producto del delito;\nV. Deberá anexar a la Averiguación Previa una copia certificada del Registro en donde conste la identidad de las personas que intervinieron en la Cadena de Custodia, y estén autorizadas para dar el procesamiento adecuado a los indicios o evidencias, de acuerdo a lo dispuesto en el artículo 58 del\nCódigo;\nVI. Instruirá el traslado de los indicios o evidencias para que sean entregados a los Servicios\nPericiales, a efecto de llevar a cabo las pruebas y diligencias periciales respectivas; y\nVII. Transferirá los bienes asegurados, previa emisión de los dictámenes periciales correspondientes, a la Dirección General de Bienes Asegurados, cuando ésta deba de administrarlos, instruyéndole el cumplimiento de la Cadena de Custodia, con fundamento en los artículos 54, 58 y 72 del\nCódigo y 16 del Reglamento de la Ley Orgánica de la Procuraduría General de Justicia del Estado.\nDichos actos de entrega y recepción se asentarán en el Registro.\nArtículo 13. En el momento en que la Dirección General de los Servicios Periciales reciba en sus instalaciones los elementos materiales objeto de la Cadena de Custodia, se procederá a lo siguiente:\nI. El servidor público a quien corresponda recibirlos, lo hará con inmediatez, diligencia y cautela, evitando en todo momento la mínima alteración a los mencionados objetos, y los turnará al laboratorio o al perito correspondiente con el objeto de que se realicen las pruebas periciales a que haya lugar;\nII. El perito o grupo de ellos designados, tendrán que garantizar inmediatamente el correcto procesamiento de los indicios o evidencias;\nIII. Cuando el indicio o evidencia no haya sido resguardado debidamente conforme al Código, a este Acuerdo y su Guía, el perito o el encargado del grupo de peritos, sin perjuicio de practicar los\nPROCESAMIENTO DEL LUGAR DE LOS HECHOS O DEL\nHALLAZGO Y DE LOS INDICIOS, HUELLAS O VESTIGIOS\nDEL HECHO DELICTUOSO, ASÍ COMO DE LOS\nINSTRUMENTOS, OBJETOS O PRODUCTOS DEL DELITO peritajes que se le hayan instruido, deberá dar vista inmediata al Agente del Ministerio Público que corresponda;\nIV. Cuando el reconocimiento recaiga sobre objetos que sean susceptibles de ser consumidos al momento de ser analizados, de conformidad con el artículo 109 del Código, se procurará conservar una muestra de ellos, a menos que sea indispensable consumirlos durante el primer reconocimiento que se haga, circunstancia que deberá de hacerse constar en el acta respectiva;\nV. Los dictámenes respectivos deberán ser enviados al Agente del Ministerio Público para integrar la Averiguación Previa, junto con los indicios o evidencias restantes, los cuales deberán de ser almacenados para diligencias posteriores o, de ser el caso, deberán de ser destruidos. En el caso de sustancias tóxicas, peligrosas o dañinas para el ambiente, deberán ser almacenadas o destruidas, de conformidad con la legislación vigente en la materia;\nVI. En los casos señalados en el párrafo anterior, o cuando a juicio del perito los indicios o evidencias requieran de un procesamiento especial, el Agente del Ministerio Público deberá instruir a los servicios periciales para que se tomen las medidas y providencias necesarias para su custodia y conservación;\nVII. Cuando por disposición de la ley se deban conservar los indicios o evidencias para su identificación por testigos, o para la práctica de otras diligencias en la averiguación previa o en el proceso, se deberá ordenar su almacenamiento y su vigilancia en lugares adecuados, observando lo dispuesto en los dos párrafos anteriores.;\nVIII. Todas las actuaciones anteriores deberán quedar debidamente asentadas en el Registro.\nArtículo 14. Cuando se practiquen cateos, pruebas de inspección ministerial, inspección ocular y reconstrucción de hechos, cuando el Agente del Ministerio Público, peritos y quienes los auxilien en la diligencia, entren en contacto con los indicios o evidencias, deberán sujetarse a lo dispuesto en los artículos 1, 54, 58 y 72 del Código, en el presente Acuerdo, en la Guía anexa y en el Registro de Cadena de Custodia.\nArtículo 15. En los supuestos del artículo anterior, el Agente del Ministerio Público se asistirá de peritos de criminalística de campo, fotografía forense y, en su caso, de perito topógrafo, quienes emplearán dibujos, planos topográficos, fotografías generales, fotografías relacionadas, medianos acercamientos, grandes acercamientos y acercamientos con testigos métricos, moldeados, o cualquier otro medio para reproducir los indicios o evidencias, según sea el caso, haciendo constar en el acta cuál\nPROCESAMIENTO DEL LUGAR DE LOS HECHOS O DEL\nHALLAZGO Y DE LOS INDICIOS, HUELLAS O VESTIGIOS\nDEL HECHO DELICTUOSO, ASÍ COMO DE LOS\nINSTRUMENTOS, OBJETOS O PRODUCTOS DEL DELITO o cuáles de aquéllos se emplearon, en qué forma y con qué objeto. Para el nombramiento de los peritos, siempre se observará lo dispuesto por los artículos 108 y 110 del Código.\nDe la misma forma, con fundamento en los artículos 1º, 54 y 58 del Código, se hará la descripción por escrito de todo lo que no hubiere sido posible efectuar, procurando fijar con claridad las características, señales o vestigios que hubiese dejado la comisión del delito, el instrumento o medio que considere que probablemente se haya empleado y la forma en que se hubiere usado. La mencionada descripción será responsabilidad del servidor público que intervenga y se hará constar en el Registro, al cual se le podrán anexar tantas fojas como sean necesarias.\nCAPÍTULO V\nDE LAS RESPONSABILIDADES EN MATERIA DE CADENA DE CUSTODIA\nArtículo 16. Los servidores públicos que intervengan en la preservación del lugar de los hechos y/o del hallazgo, si en cualquier fase del procesamiento de los indicios o evidencias se causare la alteración, daño o pérdida de los elementos materiales o se quebrantare la Cadena de Custodia, quedarán sujetos a la responsabilidad administrativa o penal que por acción u omisión les corresponda.\nAdemás de lo dispuesto en el párrafo anterior, quienes no hagan constar en el Registro sus datos personales y los demás datos requeridos relacionados con su intervención en la Cadena de\nCustodia, de conformidad con este Acuerdo y su Guía, serán sometidos al procedimiento administrativo correspondiente.\nArtículo 17. En términos de lo dispuesto en los artículos 1º., 54 y 58 del Código, podrán intervenir en el proceso de Cadena de Custodia las Unidades de Policía Facultadas, los Agentes del\nMinisterio Público, los Peritos y cualquier otra autoridad que se requiera de acuerdo a sus atribuciones y a lo dispuesto por la normatividad aplicable. acuerdo al párrafo anterior, se tenga la necesidad de solicitar el auxilio de particulares durante cualquier etapa de la Cadena de Custodia, bajo su más estricta responsabilidad podrá ordenarlo, siempre y cuando quede detallada la forma, circunstancias y datos generales de las personas que intervinieron, así como la justificación del por qué no se pudo realizar por personal facultado.\nArtículo 18. El Ministerio Público podrá ordenar las medidas que sean necesarias para que los cuerpos policiales preserven el lugar de los hechos y/o del hallazgo.\nPROCESAMIENTO DEL LUGAR DE LOS HECHOS O DEL\nHALLAZGO Y DE LOS INDICIOS, HUELLAS O VESTIGIOS\nDEL HECHO DELICTUOSO, ASÍ COMO DE LOS\nINSTRUMENTOS, OBJETOS O PRODUCTOS DEL DELITO\nCAPÍTULO VI\nDE LA TERMINACIÓN DE LA CADENA\nDE CUSTODIA EN LA ETAPA DE AVERIGUACIÓN PREVIA.\nArtículo 19. En la etapa de averiguación previa, previa la realización de las pruebas y diligencias periciales necesarias, la Cadena de Custodia termina por resolución fundada y motivada emitida por el\nAgente del Ministerio Público, bajo su más estricta responsabilidad, en los siguientes casos:\nI. Cuando se acuerde transferir bienes que puedan ser objeto de prueba para su administración por la Dirección General de Bienes Asegurados DGBA, en los términos previstos por el artículo 72 del\nCódigo y 16 del Reglamento de la Ley Orgánica de la Procuraduría General de Justicia del Estado de\nGuerrero;\nII. Si la ley determina procedente la destrucción de los bienes, el cierre de la Cadena de\nCustodia deberá asentarse en el Registro, exponiendo las características que motivan tal acción.\nIII. Cuando proceda la devolución de bienes de acuerdo a la normatividad aplicable, deberá detallarse en el Registro junto con la firma de la entrega-recepción respectiva.\nIV. En los casos en que de la verificación de la preservación del indicio y/o evidencia tanto por parte del Agente del Ministerio Público responsable, como de los Peritos, resulte que estos han sido modificados de tal forma que perdieron su eficacia para acreditar el hecho o circunstancia de que se trate, deberá asentarlo en la averiguación previa y en el Registro, y se dará aviso a las autoridades competentes para efectos de fincar la responsabilidad que corresponda, en términos de la Ley de\nResponsabilidades de los Servidores Públicos del Estado de Guerrero y del Código Penal.\nV. Cuando lo disponga el Código, los bienes considerados indicios o evidencias, deberán ser entregados en depósito o por cualquier otro título, primeramente a su propietario, o en su defecto, a\nInstituciones públicas o privadas de asistencia social; y\nVI. Siempre y cuando el Agente del Ministerio Público ya haya valorado y realizado las pruebas y diligencias periciales correspondientes, en los casos en los que al ejercer la acción penal se ponga a disposición de la autoridad judicial competente el indicio o evidencia para fines del proceso penal, se ordenará el almacenamiento y custodia del indicio o evidencia, con el objeto de ser presentado en el momento que el juez lo requiera.\nArtículo 20. Para lo no previsto en el presente Acuerdo, se observará lo dispuesto en el Acuerdo\nA/078/12 de la Procuradora General de la República, por el que se establecen las directrices que deberán\nPROCESAMIENTO DEL LUGAR DE LOS HECHOS O DEL\nHALLAZGO Y DE LOS INDICIOS, HUELLAS O VESTIGIOS\nDEL HECHO DELICTUOSO, ASÍ COMO DE LOS\nINSTRUMENTOS, OBJETOS O PRODUCTOS DEL DELITO observar los Servidores Públicos para la debida preservación y procesamiento del lugar de los hechos y/o del hallazgo y de los indicios, huellas o vestigios del hecho delictuoso, así como de los instrumentos, objetos o productos del delito, además de los diversos protocolos federales e internacionales en la materia.\nTRANSITORIOS\nPRIMERO. El presente Acuerdo entrará en vigor al día siguiente de su publicación en el\nPeriódico Oficial del Gobierno del Estado de Guerrero.\nSEGUNDO. Queda abrogado el Acuerdo PGJ/DGEL/001/2012, de fecha 4 de mayo del 2012, del Subprocurador de Control Regional y Procedimientos Penales, Encargado del Despacho de la\nProcuraduría General de Justicia del Estado de Guerrero, por el que se establecen los lineamientos que deberán observar todos los servidores públicos para la debida preservación y procesamiento del lugar de los hechos o del hallazgo y de los indicios, huellas o vestigios del hecho delictuoso así como de los instrumentos, objetos o productos del delito.\nTERCERO. Se instruye a los titulares de las Subprocuradurías, Dirección General de\nAveriguaciones Previas, Dirección General de la Policía Ministerial, Dirección General de los Servicios\nPericiales, y Dirección General de Presupuesto y Administración, para que tomen las medidas necesarias para el debido cumplimiento del presente Acuerdo. La omisión del mismo será sancionada por la\nContraloría Interna.\nCUARTO. La Procuraduría General de Justicia del Estado de Guerrero, por medio de su\nDirección General de Presupuesto y Administración, elaborará los formatos del Registro, mismos que\nCadena de Custodia, sustituyendo los formatos anteriores.\nQUINTO. Hasta en tanto se publique la nueva Ley Orgánica de la Procuraduría General de\nJusticia del Estado de Guerrero, se denominará a las Unidades de Policía Facultada, como Policía\nMinisterial.\nSEXTO. Se derogan las disposiciones que se opongan al presente Acuerdo.\nFirmado en la ciudad de Chilpancingo, Gro., a los diez días del mes de diciembre del año dos mil doce.\nPROCESAMIENTO DEL LUGAR DE LOS HECHOS O DEL\nHALLAZGO Y DE LOS INDICIOS, HUELLAS O VESTIGIOS\nDEL HECHO DELICTUOSO, ASÍ COMO DE LOS\nINSTRUMENTOS, OBJETOS O PRODUCTOS DEL DELITO\nMtra. Martha Elva Garzón Bernal.\nProcuradora General de Justicia del Estado de Guerrero.\nRúbrica.\nANEXO UNO\nDel Acuerdo PGJ/DGEL/A/010/2012, POR EL QUE SE ESTABLECEN LOS LINEAMIENTOS QUE\nDEBERÁN OBSERVAR TODOS LOS SERVIDORES PÚBLICOS DE LA INSTITUCIÓN PARA LA\nDEBIDA PRESERVACIÓN Y PROCESAMIENTO DEL LUGAR DE LOS HECHOS O DEL HALLAZGO Y\nDE LOS INDICIOS, HUELLAS O VESTIGIOS DEL HECHO DELICTUOSO, ASÍ COMO DE LOS\nINSTRUMENTOS, OBJETOS O PRODUCTOS DEL DELITO.\nGUÍA PARA LA APLICACIÓN DE LA CADENA DE CUSTODIA\nÍNDICE\nIntroducción.\nObjetivo General.\nObjetivos Específicos.\nMarco Jurídico.\nDefiniciones.\nProceso 1.Conocimiento de la comisión de un delito.\nProceso 2. Preservación del lugar de los hechos y/o del hallazgo.\n2.1 Custodia del lugar de los hechos y/o del hallazgo\n2.2 Ubicación e Identificación del lugar de los hechos y/o del hallazgo.\n2.3 Localización de posibles testigos.\n2.4 Inscripción en el Registro de Cadena de Custodia.\nProceso 3. Procesamiento de los indicios o evidencias del delito.\n3.1 Identificación, ubicación y fijación de los indicios o evidencias\n3.2 Recolección, embalaje y traslado de los indicios o evidencias\nProceso 4. Integración en la averiguación previa de la Cadena de Custodia.\n4.1 De la entrega de los indicios o evidencias al Agente del Ministerio Público.\nPROCESAMIENTO DEL LUGAR DE LOS HECHOS O DEL\nHALLAZGO Y DE LOS INDICIOS, HUELLAS O VESTIGIOS\nDEL HECHO DELICTUOSO, ASÍ COMO DE LOS\nINSTRUMENTOS, OBJETOS O PRODUCTOS DEL DELITO\n4.2 Registro de la integración de la cadena de custodia en la averiguación previa.\nProceso 5. Responsabilidades en la cadena de custodia.\nProceso 6. Pérdida de los indicios o evidencias.\nProceso 7. Solicitud de Dictámenes Periciales de los indicios o evidencias.\nProceso 8. Realización de Pruebas Periciales.\n8.1 De los indicios o evidencias consistentes en muestras biológicas.\nProceso 9. Almacenamiento de los indicios o evidencias.\nProceso 10. Terminación de la cadena de custodia.\nDiagrama de flujo.\nINTRODUCCIÓN\nConsiderando las nuevas tendencias a nivel mundial para garantizar la preservación de lugar de los hechos y/o del hallazgo, la Reforma Constitucional al Sistema de Justicia Penal, así como el cumplimiento a la recomendación No. 1VG/2012, de la Comisión Nacional de Derechos Humanos, sobre la Investigación de violaciones graves a los Derechos Humanos, relacionada con los hechos ocurridos el\n12 de Diciembre de 2011 en la Ciudad de Chilpancingo, Guerrero, en la cual señala en la recomendación\nCUARTA, Fracción V del numeral 470, que en el caso de la preservación del lugar de los hechos, que en el caso de la preservación del lugar de los hechos, el Gobernador Constitucional del Estado de Guerrero instruya a quien corresponda a fin de que se proteja en todo momento el escenario del crimen y el material sensible significativo que se genere en intervenciones policiales, con el propósito de garantizar a la institución del Ministerio Público una eficaz investigación de los acontecimientos, se hace necesario formular un nuevo procedimiento para garantizar la preservación del lugar de los hechos y/o del hallazgo, y de los indicios, huellas o vestigios del hecho delictuoso, así como de los instrumentos, objetos o productos del delito, relacionados con la comisión de los delitos a nivel estatal, es decir, la salvaguarda de la cadena de custodia.\nPor lo anterior, es de urgente necesidad especificar los procesos mediante los cuales deben conducirse los elementos de las Instituciones Policiales de los tres órdenes de gobierno y/o los peritos, los elementos de Policía Ministerial, y los demás servidores públicos autorizados que van a intervenir bajo la conducción y mando del Ministerio Público del Fuero Común, durante el procedimiento de control que\nPROCESAMIENTO DEL LUGAR DE LOS HECHOS O DEL\nHALLAZGO Y DE LOS INDICIOS, HUELLAS O VESTIGIOS\nDEL HECHO DELICTUOSO, ASÍ COMO DE LOS\nINSTRUMENTOS, OBJETOS O PRODUCTOS DEL DELITO se aplica al indicio relacionado con el delito, así como al instrumento, objeto o producto, desde su localización, hasta que ha sido valorado por la autoridad ministerial o judicial competente, y que tiene como objeto no viciar el manejo que de él se haga, para evitar alteraciones, daños, sustitución, contaminación, destrucción, o cualquier acción que varíe su significado original.\nCon el objeto de cumplir con lo anterior, y derivado del Acuerdo de la Procuradora General de\nJusticia del Estado de Guerrero, por el que se establecen los lineamientos que deberán observar los\nAgentes del Ministerio Público del Fuero Común, Policías y Peritos para la debida preservación del lugar de los hechos y/o del hallazgo y de los indicios, en el que se detallan los datos e información necesaria para asegurar la integridad de los mismos, se emite la presente Guía, a efecto de facilitar la identificación y aplicación de los procedimientos técnico-jurídicos-científicos en el lugar de los hechos y/o del hallazgo, así como para el procesamiento de los indicios y evidencias, con el fin de custodiar el material probatorio.\nAsimismo, permitirá la identificación y aplicación de los formatos relativos al Registro de Cadena de\nCustodia.\nPor lo antes mencionado, los elementos de las corporaciones policiales de los tres órdenes de gobierno y los servidores públicos que intervengan en la escena de los hechos y/o hallazgo de delitos del orden estatal, contarán con medidas y procedimientos estandarizados que permitan un trabajo coordinado y eficiente, garantizando la adecuada Procuración de Justicia en el estado de Guerrero.\nOBJETIVO GENERAL\nDeterminar los procedimientos jurídicos, técnicos y científicos, que deberán aplicar los elementos de las corporaciones policiales y/o peritos, al momento de coadyuvar con el Agente del Ministerio Público del\nFuero Común para garantizar la adecuada preservación del lugar de los hechos y/o hallazgo de los\nIndicios o evidencias, en la integración de una Averiguación Previa que derive de un probable hecho delictuoso.\nOBJETIVOS ESPECÍFICOS\n1. Identificación del marco jurídico aplicable a la cadena de custodia.\n2. Orientación y capacitación del personal policial de los tres órdenes de gobierno que participen en la cadena de custodia, en términos de lo dispuesto por los artículos 1º. 54 y 58 del Código de\nProcedimientos Penales del Estado de Guerrero.\n3. Identificación en el Diagrama de Flujo del procedimiento en materia de Cadena de Custodia.\nPROCESAMIENTO DEL LUGAR DE LOS HECHOS O DEL\nHALLAZGO Y DE LOS INDICIOS, HUELLAS O VESTIGIOS\nDEL HECHO DELICTUOSO, ASÍ COMO DE LOS\nINSTRUMENTOS, OBJETOS O PRODUCTOS DEL DELITO\n4. Identificación y aplicación de los procesos, procedimientos legales y técnico-científicos en la\nCadena de Custodia.\n5. Conocimiento y aplicación los formatos relativos al Registro de la Cadena de Custodia.\n6. Conocimiento de las responsabilidades de los servidores públicos involucrados en la Cadena de\nCustodia.\nMARCO JURÍDICO\nI. Constitución Política de los Estados Unidos Mexicanos, publicada en el Diario Oficial de la\nFederación el 05-II-1917, y sus reformas y adiciones.\nII. Código de Procedimientos Penales, publicado en el Periódico Oficial del Gobierno del Estado de\nGuerrero el 14- XI-1986, y sus reformas y adiciones.\nIII. Ley Orgánica de la Procuraduría General de Justicia del Estado de Guerrero No. 193, publicada en el Diario Oficial del Gobierno del estado de Guerrero, el 13 de Febrero de 2004.\nIV. Reglamento de la Ley Orgánica de la Procuraduría General de Justicia No. 193, publicado en el\nPeriódico Oficial del Gobierno del Estado de Guerrero del 8 de Febrero de 2005.\nDEFINICIONES\nAcordonamiento. Es la acción de delimitar el lugar de los hechos o del hallazgo, como el área presumible en donde se cometió el delito, mediante el uso de cinta, cuerdas o barreras naturales.\nAlmacenamiento. Es el depósito de los indicios o evidencias en los lugares previamente establecidos, con características mínimas necesarias para la conservación de los mismos durante el tiempo necesario, o bien durante el tiempo que sea ordenado por la autoridad competente, para garantizar la Cadena de Custodia.\nAMPFC. Es el Agente del Ministerio Público del Fuero Común, que conoce de los hechos delictivos.\nCadena de Custodia. Es el procedimiento de control que se aplica al indicio o evidencia material, ya sea vestigio, huella, medio de comisión, objeto material o producto relacionado con el delito,\nPROCESAMIENTO DEL LUGAR DE LOS HECHOS O DEL\nHALLAZGO Y DE LOS INDICIOS, HUELLAS O VESTIGIOS\nDEL HECHO DELICTUOSO, ASÍ COMO DE LOS\nINSTRUMENTOS, OBJETOS O PRODUCTOS DEL DELITO desde su localización por parte de una autoridad, policía o Agente del Ministerio Público, hasta que la autoridad competente ordene su conclusión, según se trate de la averiguación previa o del proceso penal.\nCPP. Código de Procedimientos Penales del Estado de Guerrero.\nEmbalaje. Son las técnicas de conservación y de manejo adecuadas que se hacen para guardar, inmovilizar y proteger un indicio o evidencia, dentro de algún recipiente protector adecuado para la naturaleza del mismo, con el objeto de mantener su integridad para su posterior estudio y análisis.\nIndicio o evidencia. Son las huellas, vestigios y demás elementos materiales del hecho delictuoso, que puedan encontrarse en el lugar de los hechos y/o lugar del hallazgo, y que por sus características existe la probabilidad de que tenga alguna relación con la comisión del delito que se investiga.\nLugar de los hechos. Es el espacio material o escena del crimen donde presuntamente se cometió el delito que se investiga, y que por ello puede contar con evidencias relacionadas con la investigación.\nLugar del hallazgo. Es el espacio material donde se encuentran elementos que pueden ser considerados como evidencias, en la integración de una investigación por la comisión de un delito.\nPeritos. Especialistas o expertos en una ciencia arte u oficio.\nPolicías. Integrantes de todas las instituciones policiales, que tienen el deber de preservar el lugar de los hechos e indicios o huellas del delito.\nRCC. El Registro de Cadena de Custodia es el formato o formatos en el que se asientan cadena de custodia, desde su inicio hasta su final, así como la descripción de los indicios o evidencias y características de las mismas, tales como dueño, lugar de los hechos y/o del hallazgo, y demás relativos y relevantes para la averiguación previa.\nUnidades de Policía Facultades. Agentes de la Policía capacitados y facultados por los integrantes del Sistema Nacional de Seguridad Pública, para el procesamiento de los indicios o evidencias.\nPROCESAMIENTO DEL LUGAR DE LOS HECHOS O DEL\nHALLAZGO Y DE LOS INDICIOS, HUELLAS O VESTIGIOS\nDEL HECHO DELICTUOSO, ASÍ COMO DE LOS\nINSTRUMENTOS, OBJETOS O PRODUCTOS DEL DELITO\nPROCESO 1. CONOCIMIENTO DE LA COMISÓN DE UN DELITO.\nCuando los Agentes de Policía conozcan o descubran el posible lugar de los hechos y/o del hallazgo, de delitos presumiblemente del orden Común, lo harán saber inmediatamente al AMPFC o de quien legalmente lo sustituya, para que éste lo haga del conocimiento de aquél.\nCuando sea el AMPFC quien conozca directamente de los hechos delictivos, instruirá a la Policía el aseguramiento y preservación del lugar, así como de los indicios o evidencias.\nPROCESO 2. PRESERVACIÓN DEL LUGAR DE LOS HECHOS Y/O DEL HALLAZGO.\n2.1 Custodia del lugar de los hechos y/o del hallazgo.\nCualquier servidor público o Agente de la Policía, al llegar al lugar de los hechos y/o del hallazgo, deberá asegurar o custodiar el lugar empleando técnicas adecuadas de acordonamiento, a fin de impedir el acceso a personas ajenas al personal ministerial, pericial y/o unidades de policía facultadas.\n2.2 Ubicación e identificación del lugar de los hechos y/o del hallazgo.\nUna vez tomadas las medidas para la custodia del lugar, los Agentes de Policía, procederán a:\nI. Precisar la ubicación del lugar, con domicilio y croquis del mismo.\nII. Realizar una fijación fotográfica y/o de video descriptiva.\nIII. Describir de lo general a lo particular y detalladamente por escrito, mediante el uso de diagramas o planos del lugar de los hechos y/o del hallazgo.\nIV. Realizar una observación general del lugar, entendiendo a ésta como un proceso dentro de la investigación.\n2.3 Localización de posibles testigos.\nLos Agentes de Policía, bajo las instrucciones del Agente del Ministerio Público del Fuero Común, procederán, si existieran, a la localización de testigos presenciales de los hechos delictivos, y recabarán de ellos la información básica con la finalidad de identificarlos, contar con datos suficientes para su localización en caso de ser necesario su testimonio, y cualquier otro dato que pueda auxiliar en la identificación y ubicación de indicios o evidencias.\nPROCESAMIENTO DEL LUGAR DE LOS HECHOS O DEL\nHALLAZGO Y DE LOS INDICIOS, HUELLAS O VESTIGIOS\nDEL HECHO DELICTUOSO, ASÍ COMO DE LOS\nINSTRUMENTOS, OBJETOS O PRODUCTOS DEL DELITO\n2.4 Inscripción en el Registro de Cadena de Custodia.\nToda actuación correspondiente a las etapas señaladas en los puntos 2.1 al 2.3, deberá asentarse por los servidores públicos que intervinieron, en el Registro de Cadena de Custodia.\nPROCESO 3. PROCESAMIENTO DE LOS INDICIOS O EVIDENCIAS DEL DELITO.\n3.1 Ubicación, identificación y fijación de los indicios o evidencias en el lugar de los hechos y/o del hallazgo.\nLas Unidades de Policía Facultadas y/o Peritos deberán:\nI. Observar en forma metódica, completa, minuciosa y sistemática el lugar de los hechos y/o del hallazgo, con la finalidad de buscar o identificar la existencia de indicios o evidencias de la probable comisión de un hecho delictuoso.\nII. Efectuar la búsqueda de todo material sensible, significativo (indicio o evidencia) relacionado con la investigación, a través de los protocolos establecidos, así como de los métodos y técnicas de búsqueda recomendados por la investigación criminalística. Esta localización, búsqueda o rastreo debe hacerse en las mejores condiciones, preferentemente con luz natural o con una buena iluminación, así como con instrumentos ópticos adecuados.\nIII. Proceder a fijarlos mediante técnicas como la fotografía, videograbación, planimetría, cintas magnetofónicas y por escrito, posteriormente a la observación y ubicación de los indicios.\nIV. Iniciar el proceso para su registro una vez localizado cada indicio o evidencia, se deberá asignándole el número que le corresponderá durante todo el procedimiento penal, anotándolo en una tarjeta, etiqueta u otro medio con la leyenda \"INDICIO o EVIDENCIA N°\".\nV. Proteger los indicios o evidencias que se encuentran a la intemperie.\n3.2 Recolección, embalaje y traslado de los indicios o evidencias.\nLas unidades de policía y/o los peritos, una vez que ubicaron, fijaron e identificaron los indicios o evidencias, deberán:\nI. Realizar un inventario de los mismos, con su descripción y estado en que fueron encontrados.\nII. Realizar el levantamiento utilizando los protocolos establecidos y las técnicas adecuadas en la investigación criminalística.\nPROCESAMIENTO DEL LUGAR DE LOS HECHOS O DEL\nHALLAZGO Y DE LOS INDICIOS, HUELLAS O VESTIGIOS\nDEL HECHO DELICTUOSO, ASÍ COMO DE LOS\nINSTRUMENTOS, OBJETOS O PRODUCTOS DEL DELITO\nIII. Embalar las evidencias inventariadas en el empaque o contenedor adecuado, debidamente cerrado y etiquetado, y en su caso sellado. La etiqueta deberá contener los datos siguientes: a. Fecha y hora. b. Número de indicio o evidencia. c. Número de registro (folio o llamado). d. Domicilio exacto del lugar del hecho y/o hallazgo, ubicación exacta del lugar en donde el indicio fue recolectado y descripción del material. e. Observaciones. f. Nombre completo sin abreviaturas del Agente policial, perito o auxiliar responsable de la recolección y el embalaje.\nIV. Detallar en el RCC la forma en que se realizó la recolección, embalaje y etiquetado de las evidencias, así como las medidas implementadas para garantizar la integridad de las mismas, y las personas que intervinieron, recabando la firma de cada una de ellas.\nV. El traslado o transporte de los indicios o evidencias debe ser el adecuado, tomando en cuenta las condiciones climatológicas, la temperatura del transporte, la presión, el movimiento, así como la duración del mismo, ya que si es incorrecto, se puede producir la destrucción del indicio o evidencia.\nPROCESO 4. INTEGRACIÓN DE LA CADENA DE CUSTODIA EN LA AVERIGUACIÓN PREVIA.\n4.1 De la entrega de los indicios o evidencias al AMPFC y su recepción.\nUna vez concluida la recolección, embalaje y etiquetado, se procederá a la entrega de los indicios o evidencias al AMPFC para continuar con la Cadena de Custodia, realizándose un informe que contenga:\nI. La descripción de la intervención policial y/o pericial;\nII. La fecha de entrega;\nIII. La hora de entrega;\nIV. Nombre y cargo de la persona que entrega;\nV. El tipo de indicio o evidencia;\nVI. Indicar si no fueron fotografiadas los indicios o evidencias;\nPROCESAMIENTO DEL LUGAR DE LOS HECHOS O DEL\nHALLAZGO Y DE LOS INDICIOS, HUELLAS O VESTIGIOS\nDEL HECHO DELICTUOSO, ASÍ COMO DE LOS\nINSTRUMENTOS, OBJETOS O PRODUCTOS DEL DELITO\nVII. El tipo de embalaje empleado;\nVIII. Las observaciones al estado en que se reciben los indicios o evidencias;\nIX. La fecha de recepción;\nX. La hora de recepción;\nXI. Nombre y cargo de la persona que recibe; y\nXII. Firma de cada una de ellas.\nPara lo anterior, se deberá llenar el RCC correspondiente. Asimismo, al momento de recibir los bienes, conforme a las disposiciones aplicables y bajo su más estricta responsabilidad, el AMPFC resolverá sobre su aseguramiento, así como sobre la continuidad o no del procedimiento.\n4.2 Registro de la integración de la Cadena de Custodia en la averiguación previa.\nEl AMPFC hará constar dentro de la averiguación previa el RCC, el que contendrá ésta y la identificación de las personas que intervinieron en ella.\nPROCESO 5. RESPONSABILIDADES EN LA CADENA DE CUSTODIA.\nEl AMPFC deberá:\nI. Cerciorarse de que se hayan seguido los procedimientos técnicos adecuados para preservar los indicios o evidencia.\nII. Documentar en el RCC, el rompimiento del etiquetado o de los sellos para la verificación de su contenido.\nIII. Asentar en la averiguación previa lo conducente, en el caso de que no se haya efectuado adecuadamente la fijación, recolección o levantamiento, embalaje y traslado de los indicios o evidencias.\nIV. Dar vista a las autoridades competentes, en su caso, para efectos de las responsabilidades a que haya lugar.\nPROCESAMIENTO DEL LUGAR DE LOS HECHOS O DEL\nHALLAZGO Y DE LOS INDICIOS, HUELLAS O VESTIGIOS\nDEL HECHO DELICTUOSO, ASÍ COMO DE LOS\nINSTRUMENTOS, OBJETOS O PRODUCTOS DEL DELITO\nPROCESO 6. PÉRDIDA DE INDICIOS.\nCuando haya señales de que los indicios o evidencias sufrieron algún tipo de alteración, ya sea natural y provocada, independientemente de las responsabilidades que pudieren resultar, el AMPFC determinará si éstos han perdido su valor probatorio, y por tanto, se malogró su eficacia para acreditar el hecho delictivo; en este caso, los indicios que hubiesen podido rescatarse deberán concatenarse con otros medios probatorios, de conformidad con los peritajes requeridos.\nPROCESO 7. DE LOS SERVICIOS PERICIALES.\nLos Servicios Periciales deberán:\nI. Recibir del AMPFC la petición por escrito para dictaminar los indicios o evidencias recogidos en el lugar de los hechos y/o del hallazgo;\nII. Recibir los indicios y evidencias con base en los protocolos establecidos;\nIII. Cerciorarse del correcto manejo de los indicios o evidencias; y\nIV. Informar por escrito al AMPFC cuando estas no hayan sido debidamente resguardadas, sin perjuicio de la práctica de los peritajes que se les hubiere solicitado.\nPROCESO 8. REALIZACIÓN DE LAS PRUEBAS PERICIALES.\nLos Servicios Periciales deberán:\nI. Realizar las pruebas técnico-científicas requeridas de cada una de las evidencias;\nII. Informar cuando el peritaje recaiga sobre objetos que se consuman al ser analizados, para que conste en el acta respectiva; no se permitirá que se verifique el primer análisis sobre más de la mitad de la substancia, a no ser que su cantidad sea tan escasa, que los peritos no puedan emitir su opinión sin consumirla por completo;\nIII. Remitir los dictámenes u opiniones periciales correspondientes, por especialidad, para ser integrados a la averiguación previa;\nIV. Enviar las evidencias restantes al AMPFC, quien deberá almacenarlas para ser utilizadas en posteriores diligencias o en su caso, para su destrucción respectiva;\nV. Entregar en depósito o por cualquier otro título a su propietario, o a Instituciones públicas o privadas de asistencia social, cuando en términos del CPP así proceda; y\nPROCESAMIENTO DEL LUGAR DE LOS HECHOS O DEL\nHALLAZGO Y DE LOS INDICIOS, HUELLAS O VESTIGIOS\nDEL HECHO DELICTUOSO, ASÍ COMO DE LOS\nINSTRUMENTOS, OBJETOS O PRODUCTOS DEL DELITO\nVI. Anexar los documentos que garanticen la cadena de custodia, los cuales serán devueltos para su resguardo, de conformidad con el artículo 72 del CPP.\n8.1 De los indicios o evidencias consistentes en muestras biológicas.\nEn los casos en que el AMPFC requiera allegarse de elementos biológicos probatorios para la investigación, y el imputado acceda voluntariamente a proporcionar muestras de fluido corporal, vello o cabello, o en su defecto, obtenga la autorización judicial para hacerlo, tomará las muestras en coordinación con los servicios periciales y procederán a su procesamiento, sujetándose a lo previsto en el artículo 109 del CPP.\nPROCESO 9. ALMACENAMIENTO DE LOS INDICIOS.\nEl AMPFC deberá:\nI. Ordenar a los servicios periciales que se tomen las medidas y providencias necesarias para su custodia y conservación, en los casos en que la evidencia requiera por su propia naturaleza un tratamiento especial;\nII. Ordenar su almacenamiento con el empleo de los procedimientos correspondientes, en lugares adecuados y bajo vigilancia, cuando por disposición de la ley deba conservar las evidencias para su identificación por testigos o para la práctica de otras diligencias en la averiguación previa o en el proceso; y\nIII. Tener a la vista los bienes asegurados que así lo requieran, para lo cual se hará constar el estado en que se encontraba su embalaje en el momento en que fue asegurado y si éste ha sufrido alguna alteración voluntaria o accidental al momento de ser nuevamente requeridos, para lo cual se inscribirán en los registros, los signos o señales que lo hagan presumir.\nPROCESO 10. TERMINACIÓN DE LA CADENA DE CUSTODIA.\nEn la etapa de averiguación previa, la Cadena de Custodia termina por resolución fundada y motivada del\nAMPFC, bajo su más estricta responsabilidad, previa la realización de las pruebas periciales correspondientes y en los siguientes supuestos:\nI. Cuando se acuerde transferir bienes que puedan ser objeto de prueba, para su administración\nEstado de Guerrero, en los términos previstos por los artículos 72 del CPC, en relación con el de Guerrero;\nPROCESAMIENTO DEL LUGAR DE LOS HECHOS O DEL\nHALLAZGO Y DE LOS INDICIOS, HUELLAS O VESTIGIOS\nDEL HECHO DELICTUOSO, ASÍ COMO DE LOS\nINSTRUMENTOS, OBJETOS O PRODUCTOS DEL DELITO\nII. En los casos en que proceda en términos de ley la destrucción de los bienes, en cuyo caso deberá asentarse en el RCC;\nIII. Cuando proceda la devolución de bienes, por lo que dicha circunstancia y la firma de la entregarecepción, deberán hacerse constar en el RCC;\nIV. En los casos en que de la verificación de la preservación de las evidencias, tanto por parte del\nAMPFC responsable, como de los peritos, resulte que éstas han sido modificadas de tal forma que perdieron su eficacia para acreditar el hecho o circunstancia de que se trate, se asentará en la averiguación previa, en el RCC y se dará aviso a las autoridades competentes para efectos de las responsabilidades a que haya lugar, de conformidad con lo previsto en la Ley de\nPenal vigente en la entidad;\nV. En los supuestos en que el AMPFC, al ejercer acción penal, ponga los indicios o evidencias a valorado. En este caso, se ordenará el almacenamiento y custodia de los indicios o evidencias susceptibles de presentarse en el proceso penal.",
  "ordenamiento": "ACUERDO",
  "jurisdiccion": "GUERRERO",
  "fuente_oficial": "DIARIO OFICIAL DE LA FEDERACION",
  "Fecha de Publicación": "11 \nde Diciembre de 2012",
  "ULTIMA REFORMA PUBLICADA": null,
  "status": "VIGENTE",
  "es_escaneado": false,
  "tiene_tablas": false,
  "materia": [
    "judicial"
  ]
}