{
  "titulo": "Acuerdo por el Que Se Autoriza A la Coordinación Técnica del Sistema Estatal del Registro Civil, Cel",
  "Contenido": "CONVENIOS DE COORDINACIÓN CON LOS\nHONORABLES AYUNTAMIENTOS MUNICIPALES\nDEL ESTADO, PARA IMPLEMENTAR LA\nINTERCONEXIÓN CON LAS OFICIALÍAS DEL\nREGISTRO CIVIL DEL ESTADO DE GUERRERO\nTEXTO ORIGINAL\nAcuerdo publicado en el Periódico Oficial del Gobierno del Estado No. 102, el\nMartes 22 de Diciembre de 2009.\nACUERDO POR EL QUE SE AUTORIZA A LA COORDINACIÓN TÉCNICA DEL\nSISTEMA ESTATAL DEL REGISTRO CIVIL, CELEBRAR CONVENIOS DE\nCOORDINACIÓN CON LOS HONORABLES AYUNTAMIENTOS MUNICIPALES DEL\nESTADO, PARA IMPLEMENTAR LA INTERCONEXIÓN CON LAS OFICIALÍAS DEL\nREGISTRO CIVIL DEL ESTADO DE GUERRERO.\nAl margen un sello con el Escudo Oficial que dice: Gobierno del Estado Libre y\nSoberano de Guerrero.- Poder Ejecutivo.\nCARLOS ZEFERINO TORREBLANCA GALINDO, GOBERNADOR\nEJERCICIO DE LA FACULTAD QUE ME CONFIEREN LOS ARTÍCULOS 74,\nFUNDAMENTO EN LOS ARTÍCULOS 6, 10 Y 20, FRACCIÓN X, DE LA LEY ORGÁNICA\nDE LA ADMINISTRACIÓN PÚBLICA DEL ESTADO Y 3, INCISO A), DE LA LEY\nREGLAMENTARIA DEL REGISTRO CIVIL, Y\nPRIMERO.- Que el Plan Estatal de Desarrollo del Estado de Guerrero 2005-2011, en el apartado de modernización, administración integral y transparencia de la gestión pública señala como objetivo lograr que la organización, operación y gestión gubernamental cumpla con la función primaria de servir plenamente a la ciudadanía, con calidad, eficiencia, confiabilidad y cercanía.\nSEGUNDO.- Que con motivo de la implementación del Programa de\nCONVENIOS DE COORDINACIÓN CON LOS\nHONORABLES AYUNTAMIENTOS MUNICIPALES\nDEL ESTADO, PARA IMPLEMENTAR LA\nINTERCONEXIÓN CON LAS OFICIALÍAS DEL\nREGISTRO CIVIL DEL ESTADO DE GUERRERO generación con sistemas vanguardistas tendientes a mejorar la calidad de los servicios a la ciudadanía, es el propósito del actual Gobierno del Estado, la innovación y la actualización de los sistemas informáticos en beneficio de la sociedad, para ello, es necesario adecuar y modernizar las actividades y funciones de la administración pública centralizada, a las necesidades, deseos y aspiraciones de los guerrerenses, para servir y coordinarse con una sociedad organizada y participativa en los avances tecnológicos de vanguardia.\nTERCERO.- Que la Coordinación Técnica del Sistema Estatal del Registro Civil, observará en todo tiempo la operación del Sistema de Interconexión con las Oficialías del Registro Civil del Estado de Guerrero, así como la coordinación del servicio en los términos de la fracción III, penúltimo párrafo del artículo 115 de la Constitución Política de los Estados Unidos Mexicanos, CUARTO.- De conformidad con lo previsto por los artículos 291 y 293 del Código institución de carácter público y de interés social, por medio de la cual los Ayuntamientos\nMunicipales inscriben y dan publicidad a los actos constitutivos o modificatorios del estado civil de las personas, con la intervención que le corresponda al Gobierno del\nEstado, así como también que éste mismo estará integrado por los oficiales que\nCivil.\nQUINTO.- Que la Coordinación Técnica del Sistema Estatal del Registro Civil, es una unidad administrativa dependiente de la Secretaría General de Gobierno, y a su vez, es el órgano encargado de organizar, dirigir y vigilar el ejercicio de las funciones del\nRegistro Civil, incluyendo la implementación y operación de sistemas informáticos, de conformidad con lo dispuesto por el artículo 20 fracción X de la Ley Orgánica de la\nAdministración Pública del Estado, entre otros ordenamientos jurídicos.\nCONVENIOS DE COORDINACIÓN CON LOS\nHONORABLES AYUNTAMIENTOS MUNICIPALES\nDEL ESTADO, PARA IMPLEMENTAR LA\nINTERCONEXIÓN CON LAS OFICIALÍAS DEL\nREGISTRO CIVIL DEL ESTADO DE GUERRERO\nSEXTO.- Que en uso de las facultades que me confieren la Constitución Política del Estado, he considerado procedente autorizar a la Coordinación Técnica del Sistema\nEstatal del Registro Civil, para que celebre Convenios con los Honorables Ayuntamientos\nMunicipales, para la implementación de la Interconexión de las Oficialías del Registro\nCivil del Estado de Guerrero.\nPor lo anteriormente expuesto y fundado, he tenido a bien expedir el siguiente:\nACUERDO POR EL QUE SE AUTORIZA A LA COORDINACIÓN TÉCNICA DEL\nSISTEMA ESTATAL DEL REGISTRO CIVIL, CELEBRAR CONVENIOS DE\nCOORDINACIÓN CON LOS HONORABLES AYUNTAMIENTOS MUNICIPALES DEL\nESTADO, PARA IMPLEMENTAR LA INTERCONEXIÓN CON LAS OFICIALÍAS DEL\nREGISTRO CIVIL DEL ESTADO DE GUERRERO.\nARTÍCULO PRIMERO.- Se autoriza a la Coordinación Técnica del Sistema\nEstatal del Registro Civil, celebrar Convenios de Coordinación con los Honorables\nAyuntamientos Municipales del Estado, para implementar la Interconexión con las\nOficialías del Registro Civil del Estado de Guerrero.\nARTÍCULO SEGUNDO.- La operación de la interconexión de las Oficialías del\nCivil, con la finalidad de uniformar el uso y disponibilidad de los diferentes avances tecnológicos que en materia registral se tengan y se vallan obteniendo, con el objeto de brindar a la ciudadanía una adecuada prestación de los servicios.\nARTÍCULO TERCERO.- La Coordinación Técnica del Sistema Estatal del\nRegistro Civil, tendrá en todo tiempo la operación del Sistema de Interconexión con las\nOficialías del Registro Civil del Estado de Guerrero, así como la coordinación del servicio en los términos de la fracción III, penúltimo párrafo del artículo 115 de la Constitución\nCONVENIOS DE COORDINACIÓN CON LOS\nHONORABLES AYUNTAMIENTOS MUNICIPALES\nDEL ESTADO, PARA IMPLEMENTAR LA\nINTERCONEXIÓN CON LAS OFICIALÍAS DEL\nREGISTRO CIVIL DEL ESTADO DE GUERRERO\nOrgánica del Municipio Libre.\nARTÍCULO CUARTO.- La Coordinación Técnica del Sistema Estatal del Registro\nCivil, realizará los trámites necesarios para la celebración de los Convenios correspondientes con los Honorables Ayuntamientos Municipales, para llevar a cabo la operación del Sistema de Interconexión de las Oficialías del Registro Civil del Estado de\nGuerrero.\nÚNICO.- El presente Acuerdo entrará en vigor al día siguiente de su publicación, en el Periódico Oficial del Gobierno del Estado.\nChilpancingo de los Bravo, Capital del Estado de Guerrero, a los ocho días del mes de diciembre del año dos mil nueve.\nEL GOBERNADOR CONSTITUCIONAL DEL ESTADO.\nC.P. CARLOS ZEFERINO TORREBLANCA GALINDO.\nEL SECRETARIO GENERAL DE GOBIERNO.\nLIC. GUILLERMO RAMÍREZ RAMOS.",
  "ordenamiento": "ACUERDO",
  "jurisdiccion": "GUERRERO",
  "fuente_oficial": "DIARIO OFICIAL DE LA FEDERACION",
  "Fecha de Publicación": "22 de Diciembre de 2009",
  "ULTIMA REFORMA PUBLICADA": null,
  "status": "VIGENTE",
  "es_escaneado": false,
  "tiene_tablas": false,
  "materia": [
    "civil",
    "registral"
  ]
}