{
  "titulo": "Acuerdo por el Que Se Crea el Consejo Estatal de Armonización Contable de Guerrero",
  "Contenido": "TEXTO ORIGINAL\nACUERDO POR EL QUE SE CREA EL CONSEJO ESTATAL DE ARMONIZACIÓN\nCONTABLE DE GUERRERO.\nAl margen un sello con el Escudo Oficial que dice: Gobierno del Estado Libre y\nSoberano de Guerrero.- Poder Ejecutivo.\nC.P. CARLOS ZEFERINO TORREBLANCA GALINDO, GOBERNADOR\nCONFORMIDAD A LAS FACULTADES QUE ME OTORGAN LOS ARTÍCULOS 57, 58,\nADMINISTRACIÓN PÚBLICA DEL ESTADO DE GUERRERO NÚMERO 433; 42, 43, 44\ny 45 DE LA LEY NÚMERO 255 DEL PRESUPUESTO DE EGRESOS Y LA\nCONTABILIDAD GUBERNAMENTAL DEL ESTADO DE GUERRERO; Y 1, 2, 4\nFRACCIÓN XIII, 7, 9, 17 Y ARTÍCULO DÉCIMO TRANSITORIO DE LA LEY GENERAL\nDE CONTABILIDAD GUBERNAMENTAL.\nQue el gran compromiso que brinda el poder público estatal, comprende el buen funcionamiento de la administración y el ejercicio de los recursos públicos, los cuales van encaminados a la prestación de los servicios básicos, a la atención oportuna de las necesidades de la población, cumpliendo con los lineamientos de transparencia del gasto y destino de los recursos, procurando con ello el bienestar de las familias guerrerenses.\nQue para poder ejercer los recursos públicos, en pleno cumplimiento de eficiencia y eficacia con la que está comprometida la presente Administración Pública, los órganos estatales deben cumplir con los principios de legalidad, transparencia y rendición de cuentas de los recursos presupuestados y ejercidos, documentando en todo momento con la mayor responsabilidad desde el punto de vista presupuestal y contable, todas al Estado.\nEn este mismo contexto, se requiere contar con la armonización de la contabilidad gubernamental, para que facilite el control de todos los registros y fiscalización de los recursos, y así se contribuya a medir los avances en la ejecución de programas y proyectos, que permitan a su vez, medir la eficacia, economía y eficiencia del gasto público, con el propósito de que los poderes del Estado, así como los organismos autónomos y los municipios que integran nuestra entidad federativa lleven a cabo un registro presupuestal, financiero y contable homologado de todas las operaciones que realicen en el ámbito de su competencia y que el mismo facilite su comprobación mediante la rendición de la cuenta pública.\nQue de conformidad con las disposiciones contenidas en la Ley General de\nContabilidad Gubernamental, publicada en el Diario Oficial de la Federación el 31 de diciembre de 2008, la cual entró en vigor el primero de enero de 2009, y dada la naturaleza del ordenamiento en cita al establecer facultades concurrentes, el Titular del\nEjecutivo Estatal, con las facultades que le confiere la naturaleza de las leyes vigentes en el Estado, estima necesario crear el Consejo Estatal de Armonización Contable de\nGuerrero.\nQue la finalidad de la creación del Consejo Estatal de Armonización Contable de\nGuerrero, es el de impulsar a los Poderes Ejecutivo, Legislativo y Judicial, así como los organismos autónomos y los Municipios, para que lleven a cabo las adecuaciones de sus sistemas contables, para que sean armónicos entre ellos y con los de la Federación, permitiendo con ello una mejor revisión de los órganos fiscalizadores. Instrumentando a su vez, la aplicación de los lineamientos que expida el Consejo Nacional de\nArmonización Contable, que tenga la posibilidad de facilitar la coordinación entre los de información contables para los tres ámbitos de gobierno. previamente invocadas, he tenido a bien expedir el siguiente:\nCONTABLE DE GUERRERO.\nARTÍCULO 1. Se crea el Consejo Estatal de Armonización Contable del Estado de Guerrero, en adelante CEAC-GRO, como órgano de coordinación de la contabilidad gubernamental de los Poderes Ejecutivo, Legislativo y Judicial, organismos públicos descentralizados estatales y municipales, órganos autónomos y Ayuntamientos\nMunicipales del Estado de Guerrero, y que tendrá por objeto adecuar, armonizar, difundir y promover la aplicación en nuestra entidad federativa a las normas contables y lineamientos emitidos por el Consejo Nacional de Armonización Contable, con la finalidad de transparentar y armonizar la información financiera.\nARTÍCULO 2. El CEAC-GRO estará integrado de la siguiente manera:\nI.- El Gobernador del Estado, quien fungirá como Presidente;\n(REFORMADA, P.O. 22 DE\nAGOSTO DE 2014)\nII.- El Secretario de Finanzas y Administración, quien fungirá como\nVicepresidente;\n(REFORMADA, P.O. 22 DE AGOSTO DE 2014)\nIII.- El Presidente de la Comisión de Presupuesto y Cuenta Pública del H.\nCongreso del Estado, en representación del Poder Legislativo;\nIV.- El Magistrado Presidente del Tribunal Superior de Justicia, en representación del Poder Judicial;\nV.- Un representante por cada Órgano Autónomo del Estado de Guerrero;\nVI.- Un Tesorero municipal por cada región fiscal designado por la mayoría de los integrantes del CEAC-GRO;\nVII.- El Auditor General del Estado;\nVIII.- El Contralor General del Estado;\nIX.- El Titular de la Subsecretaría de Egresos de la Secretaría de Finanzas y\nAdministración; quien fungirá como Secretario Técnico;\nX.- El Titular de la Dirección General de Presupuesto y Contabilidad Sector\nParaestatal de la Secretaría de Finanzas y Administración;\nXI. El titular de la Dirección General de Contabilidad Gubernamental de la\nXII.- El Presidente del Instituto Mexicano de Contadores Públicos del Estado.\nLos integrantes del CEAC-GRO tendrán derecho a voz y voto a excepción de los señalados en las fracciones VII a la XII de este artículo los cuales únicamente tendrán derecho a voz.\n(REFORMADO, P.O. 29 DE NOVIEMBRE DE 2011)\nEn ausencia del Gobernador del Estado, será el Vicepresidente quién lo supla como Presidente del CEAC-GRO.\n(REFORMADO PÁRRAFO TERCERO, P.O. 22 DE AGOSTO DE 2014)\nCada integrante podrá designar a un suplente, el cual deberá ser un servidor público encargado de las áreas administrativas o contables. La designación de suplente deberá realizarse por escrito y dirigida al Presidente del CEAC-GRO o al Vicepresidente en su caso.\n(REFORMADO PÁRRAFO CUARTO, P.O. 22 DE AGOSTO DE 2014)\nARTÍCULO 3. La representación de las tesorerías municipales señalada en la fracción VI del artículo anterior, durará en su cargo un año, debiendo ser notificado el tesorero designado a más tardar con 30 días de anticipación a la sesión en que corresponda asumir la representación como integrante del CEAC-GRO. La notificación correrá a cargo del Secretario Técnico.\n(REFORMADO PRIMER PÁRRAFO, P.O. 22 DE AGOSTO DE 2014)\nEn el caso de los representantes de los Órganos Autónomos, será el titular de cada uno de ellos.\nLos cargos conferidos a los miembros integrantes del CEAC-GRO serán honoríficos.\nARTÍCULO 4. El CEAC-GRO tendrá las siguientes facultades y atribuciones:\nI.- Establecer las bases sobre las cuales se instrumentarán al interior del Estado los acuerdos emitidos por el Consejo Nacional de Armonización Contable;\nII.- Definir, proponer y elaborar los criterios, instrumentos y lineamientos necesarios que le requiera o solicite el Consejo Nacional de Armonización Contable;\nIII.- Difundir a través de la publicación en el Periódico Oficial del Gobierno del\nEstado de Guerrero los criterios, instrumentos y lineamientos de armonización en materia contable, así como los relativos a la armonización en materia presupuestal y aprobados al interior del CEAC-GRO;\nIV.- Establecer los lineamientos de los convenios de coordinación en materia de armonización contable;\nV.- Proporcionar al ente de gobierno que así lo requiera, los conceptos básicos que rigen a la contabilidad gubernamental, así como su respectivo sustento jurídico;\nVI.- Aprobar el reglamento interior del CEAC-GRO;\nVII.- Proponer las reformas al marco jurídico del Estado y los Municipios en materia de armonización contable gubernamental;\nVIII.- Difundir, a través del Sistema de Coordinación Hacendaria del Estado de\nGuerrero, los acuerdos logrados al interior del CEAC-GRO, así como los acuerdos emitidos por el Consejo Nacional de Armonización Contable;\nIX.- Orientar, a través del Sistema de Coordinación Hacendaria del Estado de\nGuerrero, a los Poderes, Órganos Autónomos, a los Ayuntamientos Municipales y a los organismos públicos descentralizados estatales y municipales, que requieran asesoría en materia de armonización contable y procurar la capacitación de los servidores públicos;\nX.- Establecer la creación de comisiones y grupos de trabajo al interior del CEACGRO;\nXI.- Dar a conocer los acuerdos que emita, mediante su publicación, por los\nConsejo Nacional de Armonización Contable;\nXII.- Diseñar e instrumentar programas y acciones que permitan ir desarrollando contable;\nXIII. Invitar a sus sesiones y grupos de trabajo, para tratar algún asunto específico, a representantes de las dependencias y entidades Federales, Estatales y\nMunicipales, así como a organizaciones de los sectores social y privado, cuyas acciones se vean relacionadas con los propósitos del CEAC-GRO; y\nXIV.- Las demás que sean necesarias conforme a las leyes de la materia para la organización y el cumplimiento de su objeto.\nARTÍCULO 5. El Presidente del CEAC-GRO tendrá las siguientes facultades:\nI.- Representar al CEAC-GRO;\nII.- Presidir, dirigir las sesiones del CEAC-GRO y, en su caso, tendrá el voto de calidad cuando así lo requiera el resultado de las sesiones;\nIII.- Solicitar a los integrantes del CEAC-GRO un informe del avance de sus actividades en materia de armonización contable;\nIV.- Instruir al Secretario Técnico para que proporcione la información necesaria a los integrantes del CEAC-GRO, para el buen manejo de la contabilidad de las personas morales de carácter público que representan;\nV.- Realizar observaciones a los trabajos de los integrantes del CEAC-GRO en materia de armonización contable gubernamental;\nVI.- Coordinar los trabajos técnicos, proponiendo grupos de trabajo para el armonización contable;\nVII.- Evaluar la participación de los integrantes del CEAC-GRO, conforme a las funciona-miento de su contabilidad gubernamental;\nVIII.- Ordenar se convoque a las sesiones ordinarias y extraordinarias del CEACGRO; y\nIX.- Las demás que sean necesarias conforme a las leyes de la materia para la organización y el cumplimiento de su objeto.\nARTÍCULO 5 bis. El Vicepresidente del CEAC-GRO ejercerá las más amplias atribuciones de representación del Presidente supliendo sus ausencias, para lo cual tendrá las facultades que al efecto señalan los artículos 5, 8 y 9 del Acuerdo.\n(ADICIONADO,\nP.O. 22 DE AGOSTO DE 2014)\nARTÍCULO 6. Los integrantes del CEAC-GRO tendrán las siguientes obligaciones y atribuciones:\nI.- Realizar propuestas y sugerencias para el desempeño de sus trabajos en materia de armonización contable gubernamental;\nII.- Dar cumplimiento a los acuerdos y lineamientos emitidos al interior del CEACGRO;\nIII.- Dar cumplimiento a las observaciones emitidas por el Presidente del CEACGRO;\nIV.- Difundir al interior de los Poderes, Órganos Autónomos y Ayuntamientos\nMunicipales que representan ante el CEAC-GRO, los trabajos a realizar en materia de armonización contable; trabajos al interior de los organismos públicos descentralizados municipales;\nV.- Instrumentar las acciones necesarias al interior de los Poderes, organismos públicos autónomos y Municipios que representan ante el CEAC-GRO para cumplimentar los acuerdos y lineamientos adoptados en el CEAC-GRO; acuerdos y lineamientos adoptados en el CEAC-GRO;\nVI.- Concientizar a sus representados que los trabajos realizados en materia de armonización contable gubernamental, son en cumplimiento a lo estipulado por la Ley\nGeneral de Contabilidad Gubernamental;\nVII.- Solicitar al Presidente del CEAC-GRO se convoque a sesión extraordinaria cuando la importancia y urgencia del tema así lo exija;\nVIII.- Asistir a las sesiones del CEAC-GRO y participar al interior de los grupos de trabajo que se conformen; y\nIX.- Las demás que sean necesarias conforme a las leyes de la materia para la organización y el cumplimiento de su objeto.\nARTÍCULO 7.- El Secretario Técnico será la instancia ejecutiva del CEAC-GRO y tendrá las siguientes facultades y atribuciones;\nI.- Convocar, previo acuerdo del Presidente, a las sesiones ordinarias y extraordinarias del CEAC-GRO;\nII.- Hacer llegar la información necesaria a los integrantes del CEAC-GRO para análisis y propuestas en las respectivas sesiones;\nIII.- Formular el orden del día para llevar a cabo las sesiones del CEAC-GRO;\nIV.- Pasar lista de asistencia y verificar la existencia del quórum legal, en caso necesario asentar la ausencia de los integrantes del CEAC-GRO en las respectivas sesiones;\nV.- Levantar el acta respectiva de las sesiones del CEAC-GRO;\nVI.- Tomar nota de los acuerdos emitidos en las sesiones del CEAC-GRO;\nVII.- Dar seguimiento a los acuerdos emitidos en las sesiones del CEAC-GRO;\nVIII.- Proporcionar la información que le requieran los integrantes del CEAC-GRO, respecto de los acuerdos tomados en las sesiones; y\nIX.- Presentar ante los integrantes del CEAC-GRO, los estudios, proyectos, planes, evaluaciones y acciones que se tengan para el adecuado manejo de la contabilidad gubernamental;\nX.- Informar a los integrantes del CEAC-GRO, sobre las observaciones emitidas a los organismos que representan;\nXI.- Auxiliar al Presidente del CEAC-GRO en el desempeño de sus funciones;\nXII.- Servir de vínculo entre el CEAC-GRO y el Consejo Nacional de Armonización\nContable, asistiendo a las sesiones y reuniones de trabajo que éste convoque, y acordar con el Presidente los asuntos ahí tratados, así como distribuir a los miembros del CEACGRO de forma oportuna dicha información; y\nXIII.- Las demás que le confiera el Presidente del CEAC-GRO.\nARTÍCULO 7 bis. El Secretario Ejecutivo del CEAC-GRO, contará con las atribuciones siguientes:\n(ADICIONADO, P.O. 22 DE AGOSTO DE 2014)\nI.- Asistir al Secretario Técnico en el desempeño de sus funciones;\nII.- Acordar con el Secretario Técnico los asuntos concernientes a sus funciones;\nIII.- Compilar y sistematizar toda la información generada al seno del CEAC-GRO;\nIV.- Fungir como enlace institucional con los integrantes del CEAC-GRO, en el seguimiento de los acuerdos y resoluciones adoptadas;\nV.- Formular propuestas, estudios, proyectos, planes, evaluaciones y acciones\nTécnico para su revisión;\nVI.- Mantener comunicación constante con los integrantes del CEAC-GRO, en los asuntos inherentes al cumplimiento de los acuerdos y resoluciones adoptadas;\nVII.- Organizar y mantener bajo su custodia el archivo general del CEAC-GRO;\nVIII.- Elaborar los informes que se requieran relacionados con el funcionamiento del CEAC-GRO;\nIX.- Suplir en su caso, las ausencias del Secretario Técnico; y\nX.- Las demás que le encomiende el Secretario Técnico.\nARTÍCULO 8. El Presidente del CEAC-GRO tendrá la representación del Consejo y coordinará las estrategias y acciones a emprender por parte del CEAC-GRO, tendrá voto de calidad y deberá convocar a sesión de manera cuatrimestral, precisando el día, hora y lugar en que se llevará a cabo la sesión, así como el orden del día, adjuntando el material de trabajo necesario de los asuntos a tratar.\nARTÍCULO 9. El Presidente del Consejo, podrá convocar de forma extraordinaria dada la naturaleza o importancia de los asuntos así lo requieran.\nTodas las convocatorias ordinarias o extraordinarias serán de manera escrita y podrán ser enviadas mediante cualquiera de las formas oficiales de notificación, incluido los medios electrónicos, con una anticipación de setenta y dos horas.\nPara que las sesiones sean válidas se requerirá de la asistencia del Presidente o\nVicepresidente del Consejo, así como por lo menos el cincuenta por ciento más uno de los integrantes del CEAC-GRO.\nEn caso de no existir quórum para la celebración de la sesión, se convocará a una segunda sesión dentro de los dos días hábiles siguiente; sesión que habrá de celebrarse con los miembros que se encuentren presentes.\nARTÍCULO 10.- De cada sesión se levantará un Acta debidamente circunstanciada, que contengan como mínimo los siguientes elementos:\nI. Pase de asistencia;\nII. Determinación de quórum;\nIII. Aprobación del orden del día;\nIV. Lectura y aprobación, en su caso, del acta anterior;\nV. Recepción de informes de los grupos de trabajo;\nVI. Desarrollo de los temas a tratar, discusión y en su caso aprobación de acuerdos;\nVII. Asuntos Generales;\nVIII. Cierre de la Sesión; y\nIX. Firma de los asistentes.\nLas decisiones y acuerdos del CEAC-GRO se tomarán por la mayoría simple de los integrantes presentes, en caso de empate se observará lo estipulado en el artículo 8 del presente Acuerdo.\nARTÍCULO 11.- Dentro de la primera sesión de cada año calendario se propondrá las fechas de las sesiones ordinarias.\nPRIMERO. El presente Acuerdo entrará en vigor al día siguiente de su publicación en el Periódico Oficial del Gobierno del Estado de Guerrero.\nSEGUNDO.- El Consejo Estatal de Armonización Contable de Guerrero deberá instalarse en un plazo no mayor a treinta días hábiles, contados a partir de la entrada en vigor del presente Acuerdo.\nTERCERO.- El Consejo Estatal de Armonización Contable de Guerrero deberá aprobar en su reglamento interior en un plazo no mayor a noventa días hábiles, contados a partir de su instalación.\nChilpancingo, Capital del Estado de Guerrero, a los 13 días del mes de Oct. del año dos mil diez.\nC.P. CARLOS ZEFERINO TORREBLANCA GALINDO.\nRúbrica.\nC.P. ISRAEL SOBERANIS NOGUEDA.\nEL SECRETARIO GENERAL DE GOBIERNO.\nRúbrica.\nLIC. RICARDO ERNESTO CABRERA MORÍN.\nEL SECRETARIO DE FINANZAS Y ADMINISTRACIÓN.\nRúbrica.\nN. DE E. A CONTINUACIÓN SE TRANSCRIBEN LOS ARTÍCULOS\nTRANSITORIOS DE REFORMAS AL PRESENTE ACUERDO.\nACUERDO POR EL QUE SE REFORMA LA FRACCIÓN IX DEL ARTÍCULO 2\nDEL ACUERDO POR EL QUE SE CREA EL CONSEJO ESTATAL DE ARMONIZACIÓN\nCONTABLE DE GUERRERO.\nArtículo Primero.- El presente Acuerdo entrará en vigor al día siguiente de su publicación en el Periódico Oficial del Estado de Guerrero.\nP.O. No. 43, EL 31 DE MAYO DE 2011\nACUERDO POR EL QUE SE REFORMA EL PÁRRAFO SEGUNDO Y SE\nADICIONA LA FRACCIÓN XII AL ARTÍCULO 2 DEL ACUERDO POR EL QUE SE CREA\nEL CONSEJO ESTATAL DE ARMONIZACIÓN CONTABLE DE GUERRERO.\nArtículo Único.- El presente Acuerdo entrará en vigor al día siguiente de su publicación en el Periódico Oficial del Estado de Guerrero.\nARMONIZACIÓN CONTABLE DE GUERRERO.\nÚnico. El presente Acuerdo entrará en vigor al día siguiente de su publicación en",
  "ordenamiento": "ACUERDO",
  "jurisdiccion": "GUERRERO",
  "fuente_oficial": "DIARIO OFICIAL DE LA FEDERACION",
  "Fecha de Publicación": "22 DE AGOSTO DE 2014",
  "ULTIMA REFORMA PUBLICADA": "22 DE AGOSTO DE 2014",
  "status": "VIGENTE",
  "es_escaneado": false,
  "tiene_tablas": false,
  "materia": [
    "fiscal"
  ]
}