{
  "titulo": "Acuerdo por el Que Se Crean las Oficialías Titulares del Registro Civil en el Campanario, el Arenal,",
  "Contenido": "LA MAQUINA, LA PROGRESO, COSTA AZUL Y\nSANTA CRUZ DEL MUNICIPIO DE ACAPULCO DE\nJUAREZ, GUERRERO.\nTEXTO ORIGINAL viernes 20 de abril de 2001.\nACUERDO POR EL QUE SE CREAN LAS OFICIALIAS TITULARES DEL REGISTRO\nCIVIL EN EL CAMPANARIO, EL ARENAL, PASO LIMONERO, LA MAQUINA, LA\nPROGRESO, COSTA AZUL Y SANTA CRUZ DEL MUNICIPIO DE ACAPULCO DE\nJUAREZ, GUERRERO.\nEL CIUDADANO CONTADOR PUBLICO CARLOS ZEFERINO TORREBLANCA\nGALINDO, PRESIDENTE MUNICIPAL CONSTITUCIONAL DE ACAPULCO DE\nJUAREZ, GUERRERO, CON BASE EN LOS ARTICULOS 72 Y 73 FRACCION V DE LA\nLEY ORGANICA DEL MUNICIPIO LIBRE NUMERO 364 A SUS HABITANTES\nHACE SABER\nQue habiéndose enterado por conducto de la Secretaría General del H.\nAyuntamiento de la petición de la Coordinadora Técnica del Sistema Estatal del Registro\nCivil para regularizar el funcionamiento de las Oficialías del Municipio de Acapulco y, PRIMERO.- Que en el Municipio de Acapulco existen actualmente treinta y nueve conformidad con las leyes en la materia vigentes.\nSEGUNDO.- Que a la Oficialía del Registro Civil de Santa Cruz, aprobada en la\nPrimera Sesión Ordinaria de Cabildo del mes de enero, celebrada el día veinte de ese mes, de mil novecientos noventa y siete, no se le tramitó la asignación de número de clave ante la Coordinación Estatal del Registro Civil.\nTERCERO.- Que las ubicadas en el Campanario, El Arenal, Paso Limonero, Tasajeras, La Libertad y, La Máquina, están clasificadas como auxiliares de las Oficialías\nLA MAQUINA, LA PROGRESO, COSTA AZUL Y\nSANTA CRUZ DEL MUNICIPIO DE ACAPULCO DE\nJUAREZ, GUERRERO.\n10, 11, 17, 22, 26 y 38, figura que no está contemplada en la Ley Reglamentaria del\nRegistro Civil.\nCUARTO.- Que de conformidad con los preceptos de la ordenanza citada en el considerando anterior, las Oficialías mencionadas en el segundo y tercero no existen, legalmente hablando, para la Coordinación Técnica del Sistema Estatal del Registro Civil, quien es la responsable de coordinar y supervisar técnicamente el servicio del registro civil en los municipios, según los artículos 2o. y 21 de la ley citada.\nQUINTO.- Que mediante Oficio número 436/2000 del catorce de abril próximo pasado, asunto: se comunican nuevas disposiciones; la Coordinadora Técnica del\nSistema Estatal del Registro Civil nos solicita en función de esta irregularidad descrita con anterioridad, no surtamos de material registral a las oficinas auxiliares ya que las actas por ellas expedidas serían irregulares también, en perjuicio del ciudadano que acude a ellas; nos invita a que le pidamos se les autorice clave para que funcionen como oficialías titulares, conforme a lo dispuesto por el artículo 7o. de la Ley Reglamentaria del\nRegistro Civil vigente y; que para subsanar la irregularidad de los registros que se hicieron en las oficialías, nos agradecería le indicáramos fecha para poder textar estos registros y sea su servidor quien las firme, de acuerdo con la misma ordenanza citada.\nSEXTO.- Que el artículo 7o. de la Ley Reglamentaria del Registro Civil dice textualmente que: las Oficialías del Registro Civil residirán en las cabeceras municipales respectivas, y en cada una de las comunidades autorizadas por el H. Ayuntamiento en sesión de Cabildo para su funcionamiento, conforme a las normas y disposiciones de la\nCoordinación Técnica del Sistema Estatal del Registro Civil.\nSEPTIMO.- Que algunos sectores poblacionales han solicitado a este H. fraccionamiento Costa Azul; peticiones que nuestra Dirección del Registro Civil considera civil de los habitantes de estos lugares y de sus zonas de influencia.\nPor lo anteriormente expuesto y fundado, el honorable cabildo de Acapulco ha tenido a bien expedir el siguiente:\nLA MAQUINA, LA PROGRESO, COSTA AZUL Y\nSANTA CRUZ DEL MUNICIPIO DE ACAPULCO DE\nJUAREZ, GUERRERO.\nUNO.- Se ratifica la necesidad del funcionamiento y la existencia para movimientos registrales de los ciudadanos del Municipio de Acapulco de las Oficialías del\nRegistro Civil titulares ubicadas en, y conocidas como: Centro; Texca; Huamuchitos;\nKilómetro 30; Puerto Marqués; Plan de los Amates; Cruces de Cacahuatepec;\nCacahuatepec; Altos del Camarón; San Pedro Cacahuatepec; Tres Palos; Xaltiánguis;\nSan Isidro; La Sabana; El Salto; Lomas de Chapultepec; Ciudad Renacimiento; Pie de la\nCuesta; Amatepec; Emiliano Zapata; La Zanja; Amatillo; Kilómetro 21; Aguas Calientes;\nLos Organos; Las Cruces; Dos Arroyos; La Estación; La Venta; La Garita; Llano Largo;\nEjido Nuevo; Jardín; Caleta; Centros Hospitalarios; Piedra Imán; Cayaco; El Coloso y;\nApanhuac.\nDOS.- Se crean las Oficialías Titulares del Registro Civil en El Campanario; El\nArenal; Paso Limonero; Tasajeras; La Libertad; La Máquina; La Progreso y Costa Azul.\nTRES.- Se instruye al Ciudadano Secretario General del H. Ayuntamiento para\nAcuerdo y tramite la asignación de clave a cada una de ellas, -incluyendo La de Santa\nCruz-; así como elaborar debidamente los requisitos necesarios para su creación en los términos del artículo 14 de la Ley Reglamentaria del Registro Civil.\n1.- El presente Acuerdo entrará en vigor en el momento de su aprobación por el\nHonorable Cabildo.\n2.- El presente Acuerdo abroga y revoca los convenios y acuerdos que pudieran haberse celebrado u otorgado anteriormente con relación a las Oficialías Auxiliares.\nLA MAQUINA, LA PROGRESO, COSTA AZUL Y\nSANTA CRUZ DEL MUNICIPIO DE ACAPULCO DE\nJUAREZ, GUERRERO.\n3.- Ordénese lo necesario para su publicación en la Gaceta Municipal, y en el\nDado en la Sala de Cabildo “Juan R. Escudero” del Palacio Municipal del H.\nAyuntamiento de Acapulco de Juárez, a los siete días del mes de septiembre del año dos mil.\n“SUFRAGIO EFECTIVO.\nNO RELEEECION”.\nEl Presidente Municipal Constitucional.\nC.P. CARLOS ZEFERINO TORREBLANCA GALINDO.\nRúbrica.\nEl Secretario General del H. Ayuntamiento.\nLIC. JUAN PEREA RODRIGUEZ. ya existentes.\nGLORIA MARIA SIERRA LOPEZ.\nJUAN CAMERINO ITURBIDE ARIAS.",
  "ordenamiento": "ACUERDO",
  "jurisdiccion": "GUERRERO",
  "fuente_oficial": "DIARIO OFICIAL DE LA FEDERACION",
  "Fecha de Publicación": "20 de abril de 2001",
  "ULTIMA REFORMA PUBLICADA": null,
  "status": "VIGENTE",
  "es_escaneado": false,
  "tiene_tablas": false,
  "materia": [
    "civil",
    "registral"
  ]
}