{
  "titulo": "Acuerdo Parlamentario por Medio del Cual el Pleno de la Sexagésima Legislatura al Honorable Congreso 3",
  "Contenido": "RESPETO A LA ESFERA DE COMPETENCIAS, A LA DIVISIÓN DE\nPODERES Y AL ESTADO DE DERECHO, RESPETUOSAMENTE\nAL GOBIERNO MUNICIPAL DE ACAPULCO, PARA QUE A TRAVÉS\nDE LA COMISIÓN NACIONAL DEL AGUA (CONAGUA), LA\nCOMISIÓN DE AGUA POTABLE, ALCANTARILLADO Y\nSANEAMIENTO DEL ESTADO DE GUERRERO (CAPASEG), Y LA\nCOMISIÓN DE AGUA POTABLE Y ALCANTARILLADO DEL\nMUNICIPIO DE ACAPULCO (CAPAMA) RESPECTIVAMENTE, SE\nESTABLEZCA Y EJECUTE EN COORDINACIÓN, UN PLAN DE\nINVERSIÓN DE INFRAESTRUCTURA HIDRÁULICA PREVENTIVA\nTEXTO ORIGINAL.\nAcuerdo Parlamentario publicado en el Periódico Oficial del Gobierno del Estado No. 83, el\nMartes 15 de Octubre de 2013.\nACUERDO PARLAMENTARIO POR MEDIO DEL CUAL EL PLENO DE LA SEXAGÉSIMA\nCON PLENO RESPETO A LA ESFERA DE COMPETENCIAS,A LA DIVISIÓN DE PODERES Y AL\nESTADO DE DERECHO, RESPETUOSAMENTE EXHORTA: AL GOBIERNO FEDERAL, AL\nGOBIERNO ESTATAL Y AL GOBIERNO MUNICIPAL DE ACAPULCO, PARA QUE A TRAVÉS DE LA\nCOMISIÓN NACIONAL DEL AGUA (CONAGUA), LA COMISIÓN DE AGUA POTABLE,\nALCANTARILLADO Y SANEAMIENTO DEL ESTADO DE GUERRERO (CAPASEG), Y LA COMISIÓN\nDE AGUA POTABLE Y ALCANTARILLADO DEL MUNICIPIO DE ACAPULCO (CAPAMA)\nRESPECTIVAMENTE, SE ESTABLEZCA Y EJECUTE EN COORDINACIÓN, UN PLAN DE INVERSIÓN\nDE INFRAESTRUCTURA HIDRÁULICA PREVENTIVA PARA EL SECTOR DIAMANTE, EL SECTOR\nVALLE DE LA SABANA, LLANO LARGO, ASÍ COMO EN LAS ZONAS DE ASENTAMIENTOS\nHUMANOS EN LAS INMEDIACIONES DEL RÍO DE LA SABANA Y ZONA DE HUMEDALES DE LA\nLAGUNA DE TRES PALOS EN EL MUNICIPIO DE ACAPULCO DE JUÁREZ, CON EL FIN DE\nPREVENIR FUTURAS INUNDACIONES, Y CONFORME A LO ESTABLECIDO EN LA LEY DE AGUAS\nSOBERANO DE GUERRERO, EN NOMBRE DEL PUEBLO QUE REPRESENTA, Y:\nQue en sesión de fecha 01 de octubre del 2013, el Diputado Alejandro Carabias Icaza, presentó\nRESPETO A LA ESFERA DE COMPETENCIAS, A LA DIVISIÓN DE\nPODERES Y AL ESTADO DE DERECHO, RESPETUOSAMENTE\nAL GOBIERNO MUNICIPAL DE ACAPULCO, PARA QUE A TRAVÉS\nDE LA COMISIÓN NACIONAL DEL AGUA (CONAGUA), LA\nCOMISIÓN DE AGUA POTABLE, ALCANTARILLADO Y\nSANEAMIENTO DEL ESTADO DE GUERRERO (CAPASEG), Y LA\nCOMISIÓN DE AGUA POTABLE Y ALCANTARILLADO DEL\nMUNICIPIO DE ACAPULCO (CAPAMA) RESPECTIVAMENTE, SE\nESTABLEZCA Y EJECUTE EN COORDINACIÓN, UN PLAN DE\nINVERSIÓN DE INFRAESTRUCTURA HIDRÁULICA PREVENTIVA\nGobierno Municipal de Acapulco, para que a través de la Comisión Nacional del Agua (CONAGUA), la\nComisión de Agua Potable, Alcantarillado y Saneamiento del Estado de Guerrero (CAPASEG), y la\nComisión de Agua Potable y Alcantarillado del Municipio de Acapulco (CAPAMA) respectivamente, se establezca y ejecute en coordinación, un plan de inversión de infraestructura hidráulica preventiva para el\nSector Diamante, el Sector Valle de la Sabana, Llano Largo, así como en las zonas de asentamientos humanos en las inmediaciones del Río de la Sabana y zona de humedales de la Laguna de Tres Palos en el Municipio de Acapulco de Juárez, con el fin de prevenir futuras inundaciones, y conforme a lo siguientes términos:\n\"Que sin lugar a dudas, como efecto del cambio climático global se han presentado fenómenos meteorológicos extraordinarios, que han rebasado los máximos históricos.\nQue en el Estado de Guerrero como en todo el país hemos vivido y padecido sus consecuencias, que son cada vez más devastadoras.\nQue la población Guerrerense y principalmente los Acapulqueños, aún tenemos en nuestra memoria lo ocurrido con el huracán Paulina, el cual fue un ciclón tropical que tocó tierra en el sur de\nMéxico la madrugada del 9 de octubre de 1997 siendo uno de los más mortíferos, destructivos y costosos, dejando al puerto de Acapulco prácticamente devastado.\nPaulina produjo una torrencial precipitación récord en Acapulco de 411.2 mm acumulados en menos de 24 horas. La cantidad exacta de muertes se desconoce. Se reportaron más de 200 en los derrumbes.\nEl paso del huracán dañó mayoritariamente casas, puentes y provocó la suspensión del suministro de electricidad y agua, 50 000 personas quedaron sin hogar en todo el Estado. Las inundaciones destruyeron miles de hectáreas de cultivos, se registraron pérdidas millonarias de ganado, olas fuertes produjeron erosión de las playas en el Estado, lo que afecto dos ciclos de desove de la tortuga golfina (Lepidochelys olivacea), destruyendo 40 millones de huevos.\nRESPETO A LA ESFERA DE COMPETENCIAS, A LA DIVISIÓN DE\nPODERES Y AL ESTADO DE DERECHO, RESPETUOSAMENTE\nAL GOBIERNO MUNICIPAL DE ACAPULCO, PARA QUE A TRAVÉS\nDE LA COMISIÓN NACIONAL DEL AGUA (CONAGUA), LA\nCOMISIÓN DE AGUA POTABLE, ALCANTARILLADO Y\nSANEAMIENTO DEL ESTADO DE GUERRERO (CAPASEG), Y LA\nCOMISIÓN DE AGUA POTABLE Y ALCANTARILLADO DEL\nMUNICIPIO DE ACAPULCO (CAPAMA) RESPECTIVAMENTE, SE\nESTABLEZCA Y EJECUTE EN COORDINACIÓN, UN PLAN DE\nINVERSIÓN DE INFRAESTRUCTURA HIDRÁULICA PREVENTIVA\nQue a una década del Paulina, el pasado 30 de agosto del 2007, nuevamente nuestro Estado y el Municipio de Acapulco de Juárez, sufrió el embate de la naturaleza, esta vez del huracán Henriette, donde se presentaron lluvias intensas durante dos días, prácticamente de manera ininterrumpida.\nQue a consecuencia de estas lluvias, se registraron deslaves e inundaciones en diversas zonas del municipio, causando la muerte de habitantes de Acapulco y, haciendo necesaria la evacuación de decenas de cientos de personas hacia albergues y estancias temporales para garantizar su seguridad.\nQue además de la pérdida de vidas humanas, se presentaron cuantiosos daños materiales en las casas habitación, pertenencias y patrimonio de habitantes establecidos principalmente en recientes desarrollos habitacionales de alta densidad, ubicados en Llano Largo y otras áreas de influencia de los canales meándricos, cauces naturales de agua y en general de la zona de influencia del humedal en las inmediaciones de la Laguna Negra de Puerto Márquez y la Laguna de Tres Palos.\nQue desafortunadamente, el pasado fin de semana el huracán Ingrid en el Atlántico, y la tormenta tropical Manuel en el Pacífico, embistieron territorio mexicano, según cifras de la Secretaría de\nGobernación, 171 municipios del país se encuentran en situación de desastre natural y decenas más en condiciones de emergencia.\nQue a la fecha, en nuestra Entidad según el reporte emitido el 23 de septiembre por la\nSecretaría de Seguridad Pública y Protección Civil del Estado, se tienen registrados 96 decesos, 102 personas desaparecidas, 65,593 viviendas con daños parciales o totales, 30,336 personas aún en refugios, 33 carreteras con graves deterioros (cuatro, en la región Acapulco; siete, en la Centro; cinco, en\nCosta Chica; tres, en Costa Grande; cuatro, en la Montaña; seis, en la región Norte, y cuatro, en la Tierra\nCaliente), y el desbordamiento de 28 ríos.\n25 de los 81 Municipios.\nSi bien, el acelerado crecimiento territorial de las ciudades en áreas cuya aptitud del suelo para el asentamiento de población es considerada como inadecuada, tiende a incrementar la vulnerabilidad de las viviendas frente a amenazas de origen natural. Agregado a esto, tenemos que las condiciones\nRESPETO A LA ESFERA DE COMPETENCIAS, A LA DIVISIÓN DE\nPODERES Y AL ESTADO DE DERECHO, RESPETUOSAMENTE\nAL GOBIERNO MUNICIPAL DE ACAPULCO, PARA QUE A TRAVÉS\nDE LA COMISIÓN NACIONAL DEL AGUA (CONAGUA), LA\nCOMISIÓN DE AGUA POTABLE, ALCANTARILLADO Y\nSANEAMIENTO DEL ESTADO DE GUERRERO (CAPASEG), Y LA\nCOMISIÓN DE AGUA POTABLE Y ALCANTARILLADO DEL\nMUNICIPIO DE ACAPULCO (CAPAMA) RESPECTIVAMENTE, SE\nESTABLEZCA Y EJECUTE EN COORDINACIÓN, UN PLAN DE\nINVERSIÓN DE INFRAESTRUCTURA HIDRÁULICA PREVENTIVA socioeconómicas de las familias asentadas en áreas carentes de infraestructura, servicios y en viviendas inseguras, son de alta marginalidad y la anarquía presente en el otorgamiento de los permisos de construcción y en los procesos de construcción realizados por las empresas; lo que provoca que el problema se vuelva mayor, porque el Estado carece además de instrumentos de control y seguimiento del cumplimiento de la normatividad urbana y ambiental, agregando con ello mayor vulnerabilidad a los escenarios de riesgo, en este caso ocasionados por las constructoras.\nEn años recientes empresas desarrolladoras, construyeron miles de viviendas de interés social e interés medio en zonas de humedales y en los márgenes de la Laguna de Tres Palos y Río de la Sabana provocando que en cada temporada de lluvias se registren calles, casas y colonias afectadas por encharcamientos, inundaciones y deslaves de lodo, tierra y agua en La Venta, Llano Largo, Tunzingo, La\nPoza, El Coloso y La Luis Donaldo Colosio, alterando los ciclos y desplazamientos naturales del agua generando nuevas inundaciones en núcleos poblacionales como Renacimiento.\nQue para poner de manifiesto la falta de infraestructura hidráulica en la zona más inundada y devastada en estos momentos en Acapulco, podemos mencionar que las tierras ejidales de Llano Largo fueron liberadas mediante el programa federal PROCEDE a finales de los 90´s, para preparar la construcción de esta zona, se rellenaron humedales y se canalizaron barrancas. A partir del año 2000 el antiguo ejido de Llano Largo experimento su mayor transformación. Según datos en solo siete años se vendieron el 70% de las tierras y se había completado la construcción de 10,600 viviendas. El resultado de esto fue la modificación no solo de la topografía, sino también del sistema natural de desalojo de las aguas pluviales que corrían hacia este espacio. De esta manera, era cosa de tiempo que lluvias extraordinarias generaran inundaciones que dañaran los bienes de la creciente población. En cuanto a la con servicios conectados a la red pública, incluidas plantas tratadoras de aguas residuales; mientras que los fraccionamientos construidos en Llano Largo no cuentan con este servicio, cada empresa ha perforado sus propios pozos profundos para suministrar el agua de uso doméstico. Las aguas residuales, se conectan a la red pública que conduce a la planta de tratamiento de Miramar, cuyo funcionamiento ha sido cuestionado. Así, las aguas residuales conectan directamente con los humedales localizados en ampliación Llano Largo, próximos al canal meandrico, lo que genera problemas sanitarios y ambientales\n(Riesgo y Vulnerabilidad en Llano Largo, Acapulco: La Tormenta Henriette. Red de Revistas Científicas\nRESPETO A LA ESFERA DE COMPETENCIAS, A LA DIVISIÓN DE\nPODERES Y AL ESTADO DE DERECHO, RESPETUOSAMENTE\nAL GOBIERNO MUNICIPAL DE ACAPULCO, PARA QUE A TRAVÉS\nDE LA COMISIÓN NACIONAL DEL AGUA (CONAGUA), LA\nCOMISIÓN DE AGUA POTABLE, ALCANTARILLADO Y\nSANEAMIENTO DEL ESTADO DE GUERRERO (CAPASEG), Y LA\nCOMISIÓN DE AGUA POTABLE Y ALCANTARILLADO DEL\nMUNICIPIO DE ACAPULCO (CAPAMA) RESPECTIVAMENTE, SE\nESTABLEZCA Y EJECUTE EN COORDINACIÓN, UN PLAN DE\nINVERSIÓN DE INFRAESTRUCTURA HIDRÁULICA PREVENTIVA de América Latina, el Caribe, España y Portugal. Vol. 12 No. 39 Mayo-Agosto 2012. El Colegio\nMexiquense A.C., México).\nQue contando con estos antecedentes, desde el año 2007, el Congreso del Estado aprobó un acuerdo parlamentario solicitando la investigación de las irregularidades que constituyen violaciones al\nPlan Director de Desarrollo Urbano del Puerto de Acapulco, así como el otorgamiento de licencias de construcción de manera ilegal y del impacto ambiental que se ocasiona con las construcciones y asentamientos irregulares.\nQue en Septiembre del 2007, tras el paso del huracán Henriette, nuevamente el Congreso del\nEstado, exhorto a la Secretaría de Medio Ambiente y al Gobierno Municipal de Acapulco a no extender autorizaciones y suspender licencias hasta que se tenga un ordenamiento ecológico territorial de la zona, entre otros puntos.\nCon las lluvias en verano del 2009 se inundó tres veces el Fraccionamiento Misión del Mar, desarrollado por Casas Ara; que la inundación provocada por la tormenta Arlene, donde 250 familias fueron desalojadas en la Colonia las Delicias de la Zona Diamante de Acapulco se debió al crecimiento del Río La Sabana.\nQue en el 2011 Protección Civil Municipal señalo que el Ayuntamiento de Acapulco cuenta con un Mapa propio de Riesgos, pues según declaraciones cada año son 4 las zonas que sufren más inundaciones en mayor o menor medida ubicadas: en la parte baja del Coloso; Llano Largo, la Colonia\nAgrícola y Coral, además de La Poza.\nQue asimismo, el Plan de Ordenamiento Ecológico Territorial del Municipio de Acapulco quedo en calidad de anteproyecto para el área que comprende, de la avenida Escénica Punta Diamante hasta la\nLaguna de Tres Palos y la desembocadura del río Papagayo-al mar (limite oriente del Municipio); pero debido a cambios políticos en la Administración Municipal, no se presentó oficialmente para su aprobación en el Cabildo; y por lo tanto no se instrumentó su aplicación. Ciertamente, algunos aspectos de las Unidades de Gestión Ambiental (UGA’S) de ese trabajo, fueron retomados en el Plan de Desarrollo\nUrbano del año 2002, pero otros no, como densidades; equipamiento urbano, sistemas de tratamiento de\nRESPETO A LA ESFERA DE COMPETENCIAS, A LA DIVISIÓN DE\nPODERES Y AL ESTADO DE DERECHO, RESPETUOSAMENTE\nAL GOBIERNO MUNICIPAL DE ACAPULCO, PARA QUE A TRAVÉS\nDE LA COMISIÓN NACIONAL DEL AGUA (CONAGUA), LA\nCOMISIÓN DE AGUA POTABLE, ALCANTARILLADO Y\nSANEAMIENTO DEL ESTADO DE GUERRERO (CAPASEG), Y LA\nCOMISIÓN DE AGUA POTABLE Y ALCANTARILLADO DEL\nMUNICIPIO DE ACAPULCO (CAPAMA) RESPECTIVAMENTE, SE\nESTABLEZCA Y EJECUTE EN COORDINACIÓN, UN PLAN DE\nINVERSIÓN DE INFRAESTRUCTURA HIDRÁULICA PREVENTIVA residuos sólidos y líquidos, ordenamiento de actividades económicas y particularmente, respeto a las áreas de protección ecológica.\nQue es necesario que los Municipios del Estado de Guerrero, particularmente aquellos cuya biodiversidad y su vulnerabilidad ante fenómenos meteorológicos extremos, cumplan con lo establecido por La ley General del Equilibrio Ecológico y Protección al ambiente, en el sentido de contar ya con su ordenamiento ecológico territorial local vigente, como un instrumento que ordene el uso del suelo de acuerdo a la vocación natural del mismo, y sirva como base para establecer, las políticas y criterios necesarios para elaborar y actualizar los planes de desarrollo urbano municipales.\nQue de acuerdo a lo anterior, en el caso del Municipio de Acapulco de Juárez, resulta particularmente impostergable que se retome el anteproyecto de Ordenamiento Ecológico Territorial iniciado en 2005 bajo un convenio de coordinación firmado en aquel entonces con la Secretaría de Medio\nAmbiente Recursos Naturales y Pesca (SEMARNAP). Dicho ordenamiento ecológico, quedó inconcluso y nunca fue sancionado y validado por el cabildo de Acapulco. Por lo que es de la mayor relevancia que se pueda establecer un nuevo convenio similar que permita y facilite la actualización, conclusión, validación y aprobación del mismo.\nQue el Reglamento del Plan Director Urbano de la Zona Metropolitana del Municipio de Acapulco de Juárez, contempla disposiciones que permiten el otorgamiento de cambios de uso de suelo, a promoventes inconformes con las características vigentes de sus predios establecidas por dicho plan. desarrollos en zonas no aptas para los mismos, y que han desvirtuado los objetivos y restricciones al desarrollo urbano contemplados en el Plan Director Original.\nQue ante lo anterior, el Estado de Guerrero requiere disposiciones de ley y reglamentarias, que garanticen una vigencia mínima de los Planes de Desarrollo Urbano en los Municipios, sin que estos planes sean desvirtuados, además de criterios mínimos bajo los cuales estos planes sean autorizados y modificados total o parcialmente, para acotar la discrecionalidad de la autoridad, y la posibilidad de que se permitan desarrollos en zonas no aptas para los mismos.\nRESPETO A LA ESFERA DE COMPETENCIAS, A LA DIVISIÓN DE\nPODERES Y AL ESTADO DE DERECHO, RESPETUOSAMENTE\nAL GOBIERNO MUNICIPAL DE ACAPULCO, PARA QUE A TRAVÉS\nDE LA COMISIÓN NACIONAL DEL AGUA (CONAGUA), LA\nCOMISIÓN DE AGUA POTABLE, ALCANTARILLADO Y\nSANEAMIENTO DEL ESTADO DE GUERRERO (CAPASEG), Y LA\nCOMISIÓN DE AGUA POTABLE Y ALCANTARILLADO DEL\nMUNICIPIO DE ACAPULCO (CAPAMA) RESPECTIVAMENTE, SE\nESTABLEZCA Y EJECUTE EN COORDINACIÓN, UN PLAN DE\nINVERSIÓN DE INFRAESTRUCTURA HIDRÁULICA PREVENTIVA\nQue una vez establecido el Ordenamiento Ecológico Territorial del Municipio de Acapulco, se debe revisar de forma integral su Plan Director Urbano, pues además de los cambios de uso de suelo al\nPlan Director Original, se ha demostrado que zonas originalmente contempladas con posibilidad de desarrollo habitacional y comercial, resultaron también propensas a inundaciones recurrentes y no aptas por sus condiciones naturales, y cuyo potencial podía ser desarrollado siempre y cuando se contara con la infraestructura necesaria que nunca se estableció\nQue en reconocimiento a las realidades derivadas del cambio climático global, el Congreso de la\nUnión aprobó La Ley General de Cambio Climático, misma que entro en vigor en el mes de octubre del año pasado y en donde se establecen las competencias de Estados y Municipios en las tareas de adaptación y mitigación al fenómeno de cambio climático, y en cuyo cuerpo de ley se establece la obligación de legislar localmente en la materia, y en cuanto a protección civil, de actualizar sus atlas de riesgo tomando en cuenta, escenarios climáticos extremos. Obligaciones que tienen fecha de cumplimiento para antes de que finalice este 2013 y que sin embargo, se encuentran actualmente en incumplimiento.\nLas experiencias vividas desde 1997 a la fecha, principalmente en el Puerto de Acapulco, sumándose ahora otros municipios, nos muestra que es indispensable, urgente y prioritario que se implemente y respeten políticas de atención a desastres en el estado de Guerrero, ya que las actuales carecen de instrumentos de control y seguimiento del cumplimiento de la normatividad urbana y ambiental, lo que agrega sin duda una mayor vulnerabilidad que incrementa potencialmente las posibilidades de ocurrencia de un desastre.\nQue es necesario atender las zonas históricamente propensas a inundaciones, donde las reubicaciones resulten inconvenientes, para dotarlas con la infraestructura hidráulica suficiente, como un naturales. Por lo que es necesario que se lleven a cabo los estudios de caracterización para formular un plan de inversión de infraestructura hidráulica de corto, mediano y largo plazo. paso de la Tormenta tropical Manuel y el Huracán Ingrid, durante el pasado 13, 14 y 15 de septiembre, una vez más, se hace necesario que esta Soberanía intervenga de manera enérgica en este asunto de\nRESPETO A LA ESFERA DE COMPETENCIAS, A LA DIVISIÓN DE\nPODERES Y AL ESTADO DE DERECHO, RESPETUOSAMENTE\nAL GOBIERNO MUNICIPAL DE ACAPULCO, PARA QUE A TRAVÉS\nDE LA COMISIÓN NACIONAL DEL AGUA (CONAGUA), LA\nCOMISIÓN DE AGUA POTABLE, ALCANTARILLADO Y\nSANEAMIENTO DEL ESTADO DE GUERRERO (CAPASEG), Y LA\nCOMISIÓN DE AGUA POTABLE Y ALCANTARILLADO DEL\nMUNICIPIO DE ACAPULCO (CAPAMA) RESPECTIVAMENTE, SE\nESTABLEZCA Y EJECUTE EN COORDINACIÓN, UN PLAN DE\nINVERSIÓN DE INFRAESTRUCTURA HIDRÁULICA PREVENTIVA mayor interés público que es la presunta violación sistemática de Leyes, Normas y Reglamentos por parte de Servidores Públicos de los tres órdenes de Gobierno y de particulares, y se determine dentro del ámbito de su competencia si han existido en este sentido, actos u omisiones que hayan afectado intereses públicos fundamentales como la vida, la integridad física y seguridad de la población, la salud, los recursos naturales y el medio ambiente, así como daños al patrimonio colectivo y demás análogos\".\nQue vertido lo anterior, en sesión de fecha 01 de octubre del 2013, la Sexagésima Legislatura al\nHonorable Congreso del Estado, aprobó por unanimidad de votos, en todos y cada uno de sus términos, la propuesta de Acuerdo Parlamentario presentada por el Diputado Alejandro Carabias Icaza.\nPor lo anteriormente expuesto y con fundamento en lo dispuesto por los artículos 47 fracción I de\nLey Orgánica del Poder Legislativo número 286, este Honorable Congreso del Estado de Guerrero, expide el siguiente:\nEl Pleno de la Sexagésima Legislatura al Honorable Congreso del Estado Libre y\nSoberano de Guerrero con pleno respeto a la esfera de competencias, a la división de poderes y al estado de derecho, respetuosamente exhorta: que a través de la Comisión Nacional del Agua (CONAGUA), la Comisión de Agua Potable, Alcantarillado y Saneamiento del Estado de Guerrero (CAPASEG), y la Comisión de Agua Potable y Alcantarillado del\nMunicipio de Acapulco (CAPAMA) respectivamente, se establezca y ejecute en coordinación, un plan de inversión de infraestructura hidráulica preventiva para el Sector Diamante, el Sector Valle de la Sabana, Llano Largo, así como en las zonas de asentamientos humanos en las inmediaciones del Río de la\nSabana y zona de humedales de la Laguna de Tres Palos en el Municipio de Acapulco de Juárez, con el fin de prevenir futuras inundaciones, y conforme a lo establecido en la Ley de Aguas para el Estado Libre\nRESPETO A LA ESFERA DE COMPETENCIAS, A LA DIVISIÓN DE\nPODERES Y AL ESTADO DE DERECHO, RESPETUOSAMENTE\nAL GOBIERNO MUNICIPAL DE ACAPULCO, PARA QUE A TRAVÉS\nDE LA COMISIÓN NACIONAL DEL AGUA (CONAGUA), LA\nCOMISIÓN DE AGUA POTABLE, ALCANTARILLADO Y\nSANEAMIENTO DEL ESTADO DE GUERRERO (CAPASEG), Y LA\nCOMISIÓN DE AGUA POTABLE Y ALCANTARILLADO DEL\nMUNICIPIO DE ACAPULCO (CAPAMA) RESPECTIVAMENTE, SE\nESTABLEZCA Y EJECUTE EN COORDINACIÓN, UN PLAN DE\nINVERSIÓN DE INFRAESTRUCTURA HIDRÁULICA PREVENTIVA\nSEGUNDO.- Al Gobierno Federal para que a través de la Secretaría de Medio Ambiente y\nRecursos Naturales (SEMARNAT), al Gobierno Estatal y al Gobierno Municipal de Acapulco, para que de manera urgente y de acuerdo a sus respectivas competencias, se refrende un convenio de colaboración para que se actualice, concluya, apruebe y valide el ante proyecto de Ordenamiento Ecológico Territorial del Municipio de Acapulco de Juárez elaborado a través de la Dirección General de Ordenamiento\nEcológico e Impacto Ambiental de SEMARNAT, inconcluso desde 1998, a efecto de que se garantice que los usos de suelo sean congruentes con la vocación natural de los mismos.\nTERCERO.- A la Secretaría de la Función Pública del Gobierno Federal (SFP) y a los órganos de control interno de la Secretaría de Medio Ambiente y Recursos Naturales (SEMARNAT), y de la\nComisión Nacional del Agua (CONAGUA) para que investiguen y determinen si servidores públicos del gobierno federal incurrieron en responsabilidades en el otorgamiento de autorizaciones, concesiones y/o permisos federales, que hicieron posible la construcción de unidades habitacionales y centros comerciales en zonas inundables del Municipio de Acapulco de Juárez, y en su caso se apliquen las sanciones correspondientes.\nCUARTO.- A la Secretaría de Gobernación del Gobierno Federal, para que tome conocimiento, y dé seguimiento de la respuesta de las Instancias del Gobierno Federal referidas en este acuerdo parlamentario.\nQUINTO.- Al Ayuntamiento de Acapulco de Juárez para que una vez vigente el Ordenamiento\nEcológico Territorial del Municipio de Acapulco, se revise de manera integral el Plan Director Urbano de la\nZona Metropolitana de Acapulco de Juárez, su reglamento y normas complementarias, particularmente sobre el Sector Diamante, Valle de la Sabana y Laguna de Tres Palos con el objeto de tener una son aptas para los mismos.\nSEXTO.- A la Auditoría General del Estado para que a través del Auditor, se conforme un grupo técnico especial para estudiar y determinar si derivado de las autorizaciones, licencias, permisos y\nRESPETO A LA ESFERA DE COMPETENCIAS, A LA DIVISIÓN DE\nPODERES Y AL ESTADO DE DERECHO, RESPETUOSAMENTE\nAL GOBIERNO MUNICIPAL DE ACAPULCO, PARA QUE A TRAVÉS\nDE LA COMISIÓN NACIONAL DEL AGUA (CONAGUA), LA\nCOMISIÓN DE AGUA POTABLE, ALCANTARILLADO Y\nSANEAMIENTO DEL ESTADO DE GUERRERO (CAPASEG), Y LA\nCOMISIÓN DE AGUA POTABLE Y ALCANTARILLADO DEL\nMUNICIPIO DE ACAPULCO (CAPAMA) RESPECTIVAMENTE, SE\nESTABLEZCA Y EJECUTE EN COORDINACIÓN, UN PLAN DE\nINVERSIÓN DE INFRAESTRUCTURA HIDRÁULICA PREVENTIVA zonas inundables, servidores públicos Municipales y/o Estatales incurrieron en responsabilidad por el incumplimiento o violación de disposiciones relativas al Plan Director Urbano de la Zona Metropolitana de\nAcapulco de Juárez, su reglamento y normas complementarias, así como de la legislación estatal aplicable, en detrimento de intereses públicos fundamentales.\nSÉPTIMO.- A los integrantes de la Comisión Legislativa de Protección Civil del Congreso del\nEstado, para que se revise la actuación de las Autoridades Estatales y Municipales, en relación a la respuesta y atención a la tormenta Manuel y sus efectos, con el fin de que en su caso, presenten una iniciativa de reformas y adiciones a la legislación pertinente, para regular e instrumentar de mejor forma los términos en que el Gobierno del Estado y los Ayuntamientos deban responder ante situaciones similares.\nOCTAVO.- A los integrantes de la Comisión Legislativa de Desarrollo Urbano y Obras Públicas del Congreso del Estado, para que se revise la legislación vigente referente a desarrollo urbano en el\nEstado de Guerrero, a fin de que en su caso, presenten una iniciativa de reformas y adiciones para regular de mejor forma los términos en que los Ayuntamientos establecen, revisan, actualizan y modifican los usos de suelo y los distintos aspectos de la zonificación en los Planes de Desarrollo Urbano, a efecto de que haya congruencia entre el desarrollo urbano y la vocación natural del suelo.\nNOVENO.- A los integrantes de la Comisión Legislativa de Recursos Naturales y Desarrollo\nSustentable del Congreso del Estado, para que se revise la situación que guardan los municipios de la entidad, en relación a sus Ordenamientos Ecológicos Territoriales, así como la revisión de la Ley General de Cambio Climático, con el fin de establecer el grado de cumplimento del Estado y los Municipios de las dicha Ley.\nY, Acuerda:\nDÉCIMO.- La conformación de una Comisión Especial Plural de Diputados y Diputadas de este parlamentario, debiendo presentar periódicamente al pleno, informes sobre los avances de los mismos.\nRESPETO A LA ESFERA DE COMPETENCIAS, A LA DIVISIÓN DE\nPODERES Y AL ESTADO DE DERECHO, RESPETUOSAMENTE\nAL GOBIERNO MUNICIPAL DE ACAPULCO, PARA QUE A TRAVÉS\nDE LA COMISIÓN NACIONAL DEL AGUA (CONAGUA), LA\nCOMISIÓN DE AGUA POTABLE, ALCANTARILLADO Y\nSANEAMIENTO DEL ESTADO DE GUERRERO (CAPASEG), Y LA\nCOMISIÓN DE AGUA POTABLE Y ALCANTARILLADO DEL\nMUNICIPIO DE ACAPULCO (CAPAMA) RESPECTIVAMENTE, SE\nESTABLEZCA Y EJECUTE EN COORDINACIÓN, UN PLAN DE\nINVERSIÓN DE INFRAESTRUCTURA HIDRÁULICA PREVENTIVA\nEsta Comisión Especial se mantendrá vigente hasta que se haya dado cumplimiento a cada uno de los resolutivos plasmados en el presente acuerdo.\nPRIMERO. El presente Acuerdo entrará en vigor a partir de la fecha de su aprobación.\nSEGUNDO. El Gobierno del Estado, dentro de sus posibilidades presupuestales, deberá establecer en el Proyecto de Presupuesto de Egresos para el Ejercicio Fiscal 2014 y subsecuentes, una partida multianual para aportar y comprometer recursos para la ejecución de proyectos que se deriven del\nPlan de Inversión de Infraestructura Hidráulica del que se hace mención en el resolutivo primero del presente acuerdo parlamentario.\nDado en el Salón de Sesiones del Honorable Poder Legislativo, al primer día del mes de octubre del año dos mil trece.\nDIPUTADA PRESIDENTA.\nMARÍA VERÓNICA MUÑOZ PARRA.\nRúbrica.\nDIPUTADA SECRETARIA.\nLAURA ARIZMENDI CAMPOS.\nRúbrica.\nDIPUTADA SECRETARIA.\nKAREN CASTREJÓN TRUJILLO.\nRúbrica.",
  "ordenamiento": "ACUERDO",
  "jurisdiccion": "GUERRERO",
  "fuente_oficial": "DIARIO OFICIAL DE LA FEDERACION",
  "Fecha de Publicación": "15 de Octubre de 2013",
  "ULTIMA REFORMA PUBLICADA": null,
  "status": "VIGENTE",
  "es_escaneado": false,
  "tiene_tablas": false,
  "materia": [
    "parlamentario"
  ]
}