{
  "titulo": "Acuerdo por el Que Se Delega A los Coordinadores General y General Adjunto del Comité de Planeación",
  "Contenido": "PARA EL DESARROLLO DEL ESTADO DE\nGUERRERO LA ATRIBUCIÓN DE EMITIR LA\nAUTORIZACIÓN DE RECURSOS EN EL\nMARCO DEL PRESUPUESTO DE INVERSIÓN\nAPROBADO PARA EL EJERCICIO FISCAL\nTEXTO ORIGINAL\nAcuerdo publicado en el Periódico Oficial del Gobierno del Estado No. 6 Alcance\nII, el Viernes 19 de enero de 2007.\nACUERDO POR EL QUE SE DELEGA A LOS COORDINADORES GENERAL Y\nGENERAL ADJUNTO DEL COMITÉ DE PLANEACIÓN PARA EL DESARROLLO DEL\nESTADO DE GUERRERO LA ATRIBUCIÓN DE EMITIR LA AUTORIZACIÓN DE\nRECURSOS EN EL MARCO DEL PRESUPUESTO DE INVERSIÓN APROBADO PARA\nEL EJERCICIO FISCAL.\nAl margen un sello con el Escudo Oficial que dice: Gobierno del Estado Libre y\nSoberano de Guerrero.- Poder Ejecutivo.\nCARLOS ÁLVAREZ REYES Y GLORIA MARÍA SIERRA LÓPEZ, SECRETARIOS\nDE FINANZAS Y ADMINISTRACIÓN Y DE DESARROLLO SOCIAL,\nRESPECTIVAMENTE, CON FUNDAMENTO EN LO QUE ESTABLECEN LOS\nSOBERANO DE GUERRERO; 1°, 3°, 7º, 8°, 11, 12, 16 FRACCIONES II Y III Y 19 DE LA\nLEY ORGÁNICA DE LA ADMINISTRACIÓN PÚBLICA DEL ESTADO DE GUERRERO\nNÚMERO 433; EN EJERCICIO DE LAS FACULTADES QUE NOS CONFIEREN LOS\nARTÍCULOS 21 FRACCIÓN XI Y 22 FRACCIÓN XXI BIS DE LA LEY ORGÁNICA DE LA\nADMINISTRACIÓN PÚBLICA EN CITA, ASÍ COMO EL 26 DE LA LEY DE OBRAS\nPÚBLICAS Y SUS SERVICIOS DEL ESTADO DE GUERRERO NÚMERO 266; Y\nAdministración Pública Estatal será centralizada y paraestatal, conforme a la Ley\nOrgánica de la Administración Pública, la que distribuirá los negocios del orden administrativo en dependencias y organismos, cuyas relaciones entre sí estarán definidas y reguladas por Leyes y Reglamentos.\nPARA EL DESARROLLO DEL ESTADO DE\nGUERRERO LA ATRIBUCIÓN DE EMITIR LA\nAUTORIZACIÓN DE RECURSOS EN EL\nMARCO DEL PRESUPUESTO DE INVERSIÓN\nAPROBADO PARA EL EJERCICIO FISCAL\nQue por su parte la vigente Ley Orgánica de la Administración Pública del Estado determina que para el despacho de los asuntos que le competen el Gobernador del\nEstado se auxiliará con las Dependencias y Entidades que señalan la Constitución\nPolítica Local, la propia Ley Orgánica de la Administración Pública del Estado, el\nPresupuesto de Egresos y las demás disposiciones jurídicas vigentes en la Entidad.\nQue en tal sentido, tanto la Secretaría de Finanzas y Administración como la\nSecretaría de Desarrollo Social, son Dependencias que forman parte de la estructura orgánica del Poder Ejecutivo del Estado, cuyas atribuciones se encuentran especificadas en la Ley Orgánica de la Administración Pública del Estado de Guerrero Número 433, así como en otras disposiciones y normas jurídicas vigentes en la Entidad.\nQue, en el marco de la competencia que le otorga la fracción XXI Bis del artículo\n22 de la Ley Orgánica de la Administración Pública del Estado, a la Secretaría de\nFinanzas y Administración le corresponde autorizar el ejercicio del presupuesto de inversión con base en los techos financieros establecidos.\nQue a su vez, de acuerdo con lo que establece el artículo 26 la vigente Ley de\nObras Públicas y sus Servicios del Estado, las Dependencias, Entidades y\nAyuntamientos podrán convocar, adjudicar o contratar obras públicas y sus servicios, inversión y de gasto corriente que emita la Secretaría de Desarrollo Social, conforme a los cuales deberán elaborarse los programas de ejecución y pago correspondientes.\nQue de manera similar, en el artículo 6 de la Ley de Administración de Recursos disponible en la partida correspondiente de su presupuesto.\nQue asimismo, de acuerdo con lo que dispone la fracción XI del artículo 21 de la vigente Ley Orgánica de la Administración Pública del Estado, a la Secretaría de\nPARA EL DESARROLLO DEL ESTADO DE\nGUERRERO LA ATRIBUCIÓN DE EMITIR LA\nAUTORIZACIÓN DE RECURSOS EN EL\nMARCO DEL PRESUPUESTO DE INVERSIÓN\nAPROBADO PARA EL EJERCICIO FISCAL\nDesarrollo Social le corresponde coordinar a los Órganos Administrativos\nDesconcentrados relacionados con la planeación del desarrollo estatal.\nQue, por otra parte, en la Ley de Planeación para el Estado de Guerrero se establece que el Comité de Planeación para el Desarrollo del Estado de Guerrero\n(Copladeg) es un Órgano Administrativo Desconcentrado, subordinado jerárquicamente al titular del Poder Ejecutivo Estatal, destacando de entre sus funciones la de formular y proponer a los Ejecutivos Federal y Estatal programas de inversión, gasto y financiamiento para la Entidad, resultantes de la coordinación, concertación e inducción con los Gobiernos Estatales y Municipales y con el Sector Social y Privado.\nQue con el objeto de contar con un instrumento propio para articular las atribuciones actualmente conferidas a diversas oficinas del Ejecutivo Estatal, así como a distintas Dependencias y Entidades de la Administración Pública, su titular emitió con fecha 16 de enero de 2007 el Acuerdo por el que se Crea la Coordinación General del\nEjecutivo del Estado, como una Dependencia directamente adscrita a la Oficina del\nGobernador del Estado.\nQue en dicho Acuerdo el Gobernador del Estado dispuso que para el cumplimiento de las atribuciones mencionadas en el mismo, la Coordinación General del\nEjecutivo del Estado conduzca y rija el funcionamiento del Comité de Planeación para el\nDesarrollo del Estado de Guerrero (Copladeg), precisando que su Titular será el\nCoordinador General del Copladeg.\nQue con fundamento en lo que establecen los artículos 74 fracción IX de la de la Administración Pública del Estado el Gobernador del Estado, con fecha 17 de enero de ese año, nombró al titular de la Coordinación General del Ejecutivo del Estado; así mismo, designó a quien a partir de esa fecha se desempeñaría como Coordinador\nGeneral Adjunto del Copladeg, adicionando a la estructura administrativa del Organismo esta nueva plaza.\nPARA EL DESARROLLO DEL ESTADO DE\nGUERRERO LA ATRIBUCIÓN DE EMITIR LA\nAUTORIZACIÓN DE RECURSOS EN EL\nMARCO DEL PRESUPUESTO DE INVERSIÓN\nAPROBADO PARA EL EJERCICIO FISCAL\nQue acorde a lo señalado, y atentos a lo que establece el segundo párrafo del artículo 11 de la vigente Ley Orgánica de la Administración Pública del listado de\nGuerrero, es atribución de los titulares de las dependencias delegar cualesquiera de sus facultades, salvo las que la Constitución, Leyes y Reglamentos estatales dispongan que deban ser ejercidas directamente por ellos.\nQue conforme a lo expuesto y fundado se ha considerado necesario delegar en los Titulares del Comité de Planeación para el Desarrollo del Estado de Guerrero la atribución de autorizar, de manera global o específica, el presupuesto de inversión aprobado para el Ejercicio Fiscal en curso, misma por la que las Dependencias y\nEntidades de la Administración Pública, así como los Ayuntamientos de la Entidad, podrán adjudicar o contratar obras, adquisiciones y servicios relacionados.\nQue tal delegación de facultades es con la finalidad de lograr una mejor distribución y desahogo de las atribuciones encomendadas, buscando un alto sentido de la oportunidad, la eficacia y la eficiencia en la toma de decisiones, así como la congruencia en el desempeño de la función asignada.\nPor lo anteriormente expuesto y fundado, ambos titulares en forma conjunta hemos tenido a bien expedir el siguiente:\nEL EJERCICIO FISCAL.\nARTÍCULO PRIMERO.- Se delega a los Coordinadores General y General de emitir, en el marco del Presupuesto de Inversión aprobado para el Ejercicio Fiscal, los\nPARA EL DESARROLLO DEL ESTADO DE\nGUERRERO LA ATRIBUCIÓN DE EMITIR LA\nAUTORIZACIÓN DE RECURSOS EN EL\nMARCO DEL PRESUPUESTO DE INVERSIÓN\nAPROBADO PARA EL EJERCICIO FISCAL\nAdministración Pública, así como los Ayuntamientos de la Entidad, podrán adjudicar o contratar obras, adquisiciones y servicios relacionados con las mismas.\nARTÍCULO SEGUNDO.- El ejercicio de la atribución que se delega en el presente\nAcuerdo se sujetará a lo dispuesto en los artículos 22 fracción XXI BIS de la Ley\nOrgánica de la Administración Pública del Estado de Guerrero Número 433 y 26 de la\nLey de Obras Públicas y sus Servicios del Estado de Guerrero Número 266 y demás ordenamientos legales vigentes en el Estado, así como a las políticas, lineamientos y criterios que emita en el ejercicio de sus facultades el Titular del Ejecutivo del Estado, en su carácter de superior jerárquico del Comité de Planeación para el Desarrollo del Estado de Guerrero.\nARTÍCULO TERCERO.- Los Coordinadores General y General Adjunto del\nComité de Planeación para el Desarrollo del Estado de Guerrero informarán periódicamente al Titular del Ejecutivo Estatal, o cuando él personalmente lo solicite, sobre el ejercicio de la atribución que a través del presente instrumento legal se les delega.\nARTÍCULO PRIMERO.- El presente Acuerdo entrará en vigor el día de su\nChilpancingo, Guerrero, a los diecisiete días del mes de enero de dos mil siete.\nSUFRAGIO EFECTIVO. NO REELECCIÓN.\nEL SECRETARIO DE FINANZAS Y ADMINISTRACIÓN.\nC. CARLOS ÁLVAREZ REYES.\nLA SECRETARIA DE DESARROLLO SOCIAL.\nPARA EL DESARROLLO DEL ESTADO DE\nGUERRERO LA ATRIBUCIÓN DE EMITIR LA\nAUTORIZACIÓN DE RECURSOS EN EL\nMARCO DEL PRESUPUESTO DE INVERSIÓN\nAPROBADO PARA EL EJERCICIO FISCAL\nC. GLORIA MARÍA SIERRA LÓPEZ.",
  "ordenamiento": "ACUERDO",
  "jurisdiccion": "GUERRERO",
  "fuente_oficial": "DIARIO OFICIAL DE LA FEDERACION",
  "Fecha de Publicación": "19 de enero de 2007",
  "ULTIMA REFORMA PUBLICADA": null,
  "status": "VIGENTE",
  "es_escaneado": false,
  "tiene_tablas": false,
  "materia": [
    "general"
  ]
}