{
  "titulo": "Acuerdo General de Auditoría de la Secretaría de Salud del Estado, Que Tiene Como Objeto la Implemen",
  "Contenido": "AUDITORÍAS, PROGRAMADAS EN LA CONTRALORÍA\nINTERNA DE DICHA SECRETARÍA\nTEXTO ORIGINAL\nACUERDO GENERAL DE AUDITORÍA DE LA SECRETARÍA DE SALUD DEL ESTADO, QUE TIENE\nCOMO OBJETO LA IMPLEMENTACIÓN DE AUDITORÍAS, PROGRAMADAS EN LA CONTRALORÍA\nINTERNA DE DICHA SECRETARÍA.\nExpediente Administrativo Núm. AGA/001/2011\nChilpancingo, Guerrero, a primero de abril del año dos mil once.\nSecretaría de Salud y/o Servicios Estatales de Salud para el ejercicio 2011 y con el propósito de verificar el grado de cumplimiento de la normatividad, de los objetivos y metas de manera eficaz y congruente, así como, el desempeño de cada uno de los programas por parte de los responsables y/o encargados del manejo de los recursos públicos federales y estatales, aplicación del gasto público y operaciones cualesquiera que sea su naturaleza, dentro de la Secretaría de Salud y/o Servicios Estatales de Salud en el Estado, así como aquéllos servidores públicos que intervengan en dichos procesos; Así mismo, considerando que el personal del Órgano Interno de Control deberá estar libre de cualquier impedimento para proceder con entera autonomía en todos los asuntos relacionados con las auditorías a su cargo, preservando por parte de su personal actuante independencia en sus opiniones, juicios y recomendaciones de manera imparcial. Esta autonomía, a su vez, descansa en las amplias facultades que confiere la Ley Federal de Presupuesto y Responsabilidad Hacendaria y Reglamento, Ley de\nResponsabilidades de los Servidores Públicos, vigente; y demás ordenamientos jurídicos y normativos aplicables para la práctica de auditorías de cualquier tipo, visitas, revisiones e inspecciones; haciendo uso de la normatividad, políticas, guías y procedimientos internos, como mecanismos e instrumentos coadyuvantes para control y evaluación de las operaciones que realicen las áreas y unidades dependientes de la Secretaría de Salud y/o Servicios Estatales de Salud en el Estado; así como revisar toda clase de documentos, libros, registros de forma digital e impresa, con total independencia de fiscalización de periodos tanto de ejercicios anteriores como posteriores, de igual forma para la selección y extensión de rubros a revisar; en general, recabar todos los elementos de información necesarios para el desempeño de sus funciones; así como cualquier tipo de objetos de cualquier índole; vigilando y constatando que se cumplan con los parámetros de certeza, eficiencia, eficacia, economía, tiempo y calidad en los procesos; así como resulta indispensable establecer los controles internos necesarios a fin de evitar irregularidades; Así como solicitar la información y documentación necesaria a cada una de las áreas y unidades adscritas, así como a los titulares y/o encargados, y en general a cada uno de los servidores públicos de la Secretaría de Salud y/o Servicios Estatales de Salud en el Estado que sean sujetos a revisión de auditoría. Lo anterior, en términos de lo establecido en los artículos 108, 109 y 134 de la Constitución Política de los Estados Unidos Mexicanos; 110 y 111 de la Constitución Política del\nPública del Estado de Guerrero número 433; 4° y 4° Bis fracciones XIV y XXV de la Ley General de Salud del Estado de Guerrero número 159; 1°, 45, 50, 57, 61, 64, 65, 74, 75, 82, 83, 84 y 115 de la Ley Federal\nAUDITORÍAS, PROGRAMADAS EN LA CONTRALORÍA\nINTERNA DE DICHA SECRETARÍA de Presupuesto y Responsabilidad Hacendaria y demás aplicables; 1°, 2°, 21, 64, 223, 224, 303, 304, Hacendaria y demás aplicables; y 1°, 2°, 3°, 45, 46, 47, 52 y 55 de la Ley de Responsabilidades de los\nServidores Públicos del Estado de Guerrero vigente.\nSe establece que el presente acuerdo es de aplicación general y obligatoria para todo el personal adscrito a la Secretaría de Salud y/o Servicios Estatales de Salud en el Estado de Guerrero, y en contravención se aplicaran las sanciones disciplinarias contempladas en la Ley de Responsabilidades de los Servidores Públicos del Estado de Guerrero vigente.\nEn consecuencia iníciense las auditorías implementadas para el ejercicio 2011, años anteriores y subsecuentes de manera programada, así también notifíquese el presente proveído al Contralor Interno de la Secretaría de Salud y/o Servicios Estatales de Salud en el Estado, para que éste por sí o por conducto de sus Auditores Analistas y personal adscrito, lleven a cabo la conducción de dichas auditorías; así también notifíquese el presente proveído a las áreas y unidades dependientes de la\nSecretaría de Salud y/o Servicios Estatales de Salud en el Estado sujetas a revisiones en modalidad de auditorías, en el momento en la conducción de las mismas.- NOTIFIQUESE Y CÚMPLASE\nAsí lo acordó y firma el Dr. Lázaro Mazón Alonso, Secretario de Salud y/o Director General de los Servicios Estatales de Salud en el Estado, ante el C.P. Raymundo García Gutiérrez, Contralor Interno de la Secretaría de Salud y/o Servicios Estatales de Salud en el Estado, quién actúa con los testigos de asistencia, los CC. L.C. Guadalupe Radilla Romero y Lic. Abel Santos\nHidalgo, quienes dan fe de la presente actuación.- DAMOS FE.\nDr. Lázaro Mazón Alonso.\nSecretario de Salud y/o Director General de los Servicios\nEstatales de Salud en el Estado.\nRúbrica.\nC. P. Raymundo García Gutiérrez.\nContralor Interno de la Secretaría de Salud y/o Servicios\nEstatales de Salud en el Estado.\nTestigos de Asistencia.\nL.C. Guadalupe Radilla Romero.\nLic. Abel Santos Hidalgo.\nAUDITORÍAS, PROGRAMADAS EN LA CONTRALORÍA\nINTERNA DE DICHA SECRETARÍA\nEl suscrito ING. LUIS ALBERTO AMARO SOTO, contralor Interno de la Secretaría de Salud en el Estado de Guerrero.\nLas presentes copias fotostáticas, concuerdan fielmente en toda y cada una de sus partes con su original, misma que obra en el archivo de este Órgano Interno de Control, consistente en dos fojas útiles por un solo lado, misma que tuve a la vista y previo cotejo, se realiza el foliadas y entreselladas, que corresponde al Acuerdo General de Auditoría de fecha primero de abril del año dos mil once, dictada por el Secretario de Salud en el Estado.\nLa que certifico para los usos y efectos legales a que haya lugar, el día dieciocho de julio del año dos mil trece, en la ciudad de Chilpancingo, Guerrero; ante los testigos de asistencia los CC. Fredy\nMiranda Balbuena y Domingo Abarca Villa, quienes dan fe a la presente.- DAMOS FE.\nING. LUIS ALBERTO AMARO SOTO.\nContralor Interno de la Secretaría de Salud en el Estado de Guerrero.\nTESTIGOS DE ASISTENCIA.\nLIC. FREDY MIRANDA BALBUENA.\nPersonal de la Contraloría Interna.\nLIC. DOMINGO ABARCA VILLA.\nPersonal de la Contraloría Interna.",
  "ordenamiento": "ACUERDO",
  "jurisdiccion": "GUERRERO",
  "fuente_oficial": "DIARIO OFICIAL DE LA FEDERACION",
  "Fecha de Publicación": "22 de \nNoviembre de 2013",
  "ULTIMA REFORMA PUBLICADA": null,
  "status": "VIGENTE",
  "es_escaneado": false,
  "tiene_tablas": false,
  "materia": [
    "salud",
    "auditoría"
  ]
}