{
  "titulo": "Acuerdo por el Que Se Delegan A los Delegados de Gobernación en Acapulco de Juárez, Costa Grande y Z",
  "Contenido": "DEPENDIENTES DE LA SECRETARIA GENERAL\nDE GOBIERNO, FACULTADES PARA LLEVAR EL\nREGISTRO DE AUTOGRAFOS, LEGALIZAR Y\nCERTIFICAR LAS FIRMAS DE LOS\nFUNCIONARIOS ESTATALES, DE LOS\nPRESIDENTES Y SECRETARIOS MUNICIPALES Y\nDE LOS DEMAS FUNCIONARIOS A QUIENES\nESTA ENCOMENDADA LA FE PUBLICA\nABROGADO POR EL ACUERDO POR EL QUE SE DELEGAN A LOS\nDELEGADOS DE GOBERNACIÓN EN ACAPULCO DE JUAREZ Y REGIONES COSTA\nGRANDE Y NORTE, DEPENDIENTES DE LA SECRETARIA GENERAL DE\nGOBIERNO, FACULTADES PARA LLEVAR EL REGISTRO DE AUTOGRAFOS,\nLEGALIZAR Y CERTIFICAR LAS FIRMAS DE LOS FUNCIONARIOS ESTATALES, DE\nLOS PRESIDENTES Y SECRETARIOS MUNICIPALES Y DE LOS DEMAS\nFUNCIONARIOS A QUIENES ESTA ENCOMENDADA LA FE PUBLICA; PUBLICADO\nEN EL PERIÓDICIO OFICIAL DEL GOBIERNO DEL ESTADO No. 74 EL VIERNES 13\nDE SEPTIEMBRE DE 2002.\nTEXTO ORIGINAL\nAcuerdo publicado en el Periódico Oficial del Gobierno del Estado No. 68, el viernes 23 de agosto de 2002.\nACUERDO POR EL QUE SE DELEGAN A LOS DELEGADOS DE GOBERNACION EN\nACAPULCO DE JUAREZ, COSTA GRANDE Y ZONA NORTE, DEPENDIENTES DE LA\nSECRETARIA GENERAL DE GOBIERNO, FACULTADES PARA LLEVAR EL\nREGISTRO DE AUTOGRAFOS, LEGALIZAR Y CERTIFICAR LAS FIRMAS DE LOS\nFUNCIONARIOS ESTATALES, DE LOS PRESIDENTES Y SECRETARIOS\nENCOMENDADA LA FE PUBLICA.\nMARCELINO MIRANDA AÑORVE, SECRETARIO GENERAL DE GOBIERNO,\nCON FUNDAMENTO EN LO DISPUESTO POR LOS ARTICULOS 50, FRACCION I, 58,\n74 FRACCION IV, 75, 76 DE LA CONSTITUCION POLITICA DEL ESTADO Y CON LAS\nDEPENDIENTES DE LA SECRETARIA GENERAL\nDE GOBIERNO, FACULTADES PARA LLEVAR EL\nREGISTRO DE AUTOGRAFOS, LEGALIZAR Y\nCERTIFICAR LAS FIRMAS DE LOS\nFUNCIONARIOS ESTATALES, DE LOS\nPRESIDENTES Y SECRETARIOS MUNICIPALES Y\nDE LOS DEMAS FUNCIONARIOS A QUIENES\nESTA ENCOMENDADA LA FE PUBLICA\nFACULTADES QUE ME OTORGAN LOS ARTICULOS 1o., 2o., 3o., 6o., 11, 14, 18 Y 20\nDE LA LEY ORGANICA DE LA ADMINISTRACION PUBLICA ESTATAL Y 1o., 2o., 3o.,\n4o., 6o. Y 7o. DEL REGLAMENTO INTERIOR DE LA SECRETARIA GENERAL DE\nGOBIERNO, Y\nQue las actividades del Ejecutivo Estatal y de los titulares de las distintas\nDependencias de Gobierno, están sujetas al orden jurídico y sus facultades se encuentran determinadas jerárquicamente a partir de la Constitución Política de los\nEstados Unidos Mexicanos, Constitución Política Local, Ley Orgánica de la\nAdministración Pública de la Entidad y demás leyes reglamentarias. en sus artículos 58 y 75, la facultad del Ejecutivo Estatal para delegar sus facultades a los titulares de las distintas Secretarías que auxilian en las diversas tareas que tienen encomendadas, siempre y cuando se encuentren previstas tanto en la Constitución como en las demás leyes de la Entidad.\nQue la Secretaría General de Gobierno, entre las facultades que le confiere el artículo 20, de la Ley Orgánica de la Administración Pública del Estado, se encuentra la de llevar el registro de autógrafos, legalizar y certificar las firmas de los funcionarios estatales, de los Presidentes y Secretarios Municipales y de los demás funcionarios a quienes está encomendada la fe pública.\nQue la Ley Orgánica de la Administración Pública del Estado, en sus artículos 10 y 11, establecen la posibilidad de que los titulares de las dependencias del Ejecutivo del\nDEPENDIENTES DE LA SECRETARIA GENERAL\nDE GOBIERNO, FACULTADES PARA LLEVAR EL\nREGISTRO DE AUTOGRAFOS, LEGALIZAR Y\nCERTIFICAR LAS FIRMAS DE LOS\nFUNCIONARIOS ESTATALES, DE LOS\nPRESIDENTES Y SECRETARIOS MUNICIPALES Y\nDE LOS DEMAS FUNCIONARIOS A QUIENES\nESTA ENCOMENDADA LA FE PUBLICA\nEstado, deleguen a sus subalternos cualquiera de sus facultades que a éstos les han sido otorgadas, para que coadyuven en el ejercicio de sus funciones.\nQue las Delegaciones de Gobernación en Acapulco de Juárez; Costa Grande y\nZona Norte, dependiente de la Secretaría General de Gobierno, cuentan con la experiencia y recursos humanos suficientes, para realizar tan delicada tarea, como lo exige la población, razón suficientemente para tener a bien acordar que sean los titulares de las mismas los encargados de llevar el registro de autógrafos, legalizar y certificar las firmas de los funcionarios estatales, de los Presidentes y Secretarios Municipales y de los demás funcionarios a quienes está encomendada la fe pública, en sus respectivas delimitaciones territoriales.\nQue el presente Acuerdo tiene como finalidad la de cumplir con uno de los compromisos del presente Gobierno, en el marco del programa de simplificación administrativa, que tiene por objeto, implementar acciones a corto plazo con el fin de que población en general de manera pronta y eficaz.\nPor todo lo anteriormente expuesto y fundado, el Secretario General de Gobierno ha considerado necesario delegar en los Delegados de Gobernación, dependientes de la legalizar y certificar las firmas de los funcionarios estatales, de los Presidentes y pública, en sus respectivas demarcaciones territoriales, por lo que he tenido a bien expedir el siguiente:\nDEPENDIENTES DE LA SECRETARIA GENERAL\nDE GOBIERNO, FACULTADES PARA LLEVAR EL\nREGISTRO DE AUTOGRAFOS, LEGALIZAR Y\nCERTIFICAR LAS FIRMAS DE LOS\nFUNCIONARIOS ESTATALES, DE LOS\nPRESIDENTES Y SECRETARIOS MUNICIPALES Y\nDE LOS DEMAS FUNCIONARIOS A QUIENES\nESTA ENCOMENDADA LA FE PUBLICA\nACUERDO POR EL QUE SE DELEGAN A LOS DELEGADOS DE GOBERNACION EN\nACAPULCO DE JUAREZ, COSTA GRANDE Y ZONA NORTE, DEPENDIENTES DE LA\nSECRETARIA GENERAL DE GOBIERNO, FACULTADES PARA LLEVAR EL\nREGISTRO DE AUTOGRAFOS, LEGALIZAR Y CERTIFICAR LAS FIRMAS DE LOS\nFUNCIONARIOS ESTATALES, DE LOS PRESIDENTES Y SECRETARIOS\nMUNICIPALES Y DE LOS DEMAS FUNCIONARIOS A QUIENES ESTA\nENCOMENDADA LA FE PUBLICA.\nARTICULO PRIMERO.- Se delegan a los Delegados de Gobernación en\nAcapulco de Juárez, Costa Grande con sede en Petatlán, Guerrero, y Zona Norte con sede en Iguala de la Independencia, Guerrero, dependientes de la Secretaría General de\nGobierno, facultades para llevar el registro de autógrafos, legalizar las firmas de los\nFuncionarios Estatales, de los Presidentes y Secretarios Municipales y de los demás funcionarios a quienes está encomendada la fe pública.\nARTICULO SEGUNDO.- Sin perjuicio de lo dispuesto en el artículo anterior las misma.\nARTICULO TERCERO.- Con fundamento en el artículo 27 fracción XIII de la Ley\nOrgánica de la Administración Pública Federal y 26 de la Ley Orgánica de la\nAdministración Pública Estatal, gírese el oficio correspondiente al Director General de\nDelegados de Gobernación de Acapulco de Juárez, Costa Grande y Zona Norte.\nDEPENDIENTES DE LA SECRETARIA GENERAL\nDE GOBIERNO, FACULTADES PARA LLEVAR EL\nREGISTRO DE AUTOGRAFOS, LEGALIZAR Y\nCERTIFICAR LAS FIRMAS DE LOS\nFUNCIONARIOS ESTATALES, DE LOS\nPRESIDENTES Y SECRETARIOS MUNICIPALES Y\nDE LOS DEMAS FUNCIONARIOS A QUIENES\nESTA ENCOMENDADA LA FE PUBLICA\nPRIMERO.- El presente Acuerdo entrará en vigor al día siguiente de su\nSEGUNDO.- Gírense los oficios correspondientes a que alude el Artículo Tercero de este Acuerdo.\nDado en la Ciudad de Chilpancingo de los Bravo, Capital del Estado de Guerrero, a los dieciséis días del mes de agosto del año dos mil dos.\nEl Secretario General de Gobierno.\nLIC. MARCELINO MIRANDA AÑORVE.\nRúbrica.",
  "ordenamiento": "ACUERDO",
  "jurisdiccion": "GUERRERO",
  "fuente_oficial": "DIARIO OFICIAL DE LA FEDERACION",
  "Fecha de Publicación": "13 \nDE SEPTIEMBRE DE 2002",
  "ULTIMA REFORMA PUBLICADA": "23 de agosto de 2002",
  "status": "ABROGADA",
  "es_escaneado": false,
  "tiene_tablas": false,
  "materia": [
    "general"
  ]
}