{
  "titulo": "Acuerdo por el Que Se Crea el Subcomité Sectorial de Ecología y Cambio Climático del Comité de Plane",
  "Contenido": "EL DESARROLLO DEL ESTADO DE GUERRERO\nABROGADO POR EL ARTÍCULO TERCERO TRANSITORIO DE LA LEY NÚMERO 845 DE\nCAMBIO CLIMÁTICO DEL ESTADO DE GUERRERO, PUBLICADA EN EL PERIÓDICO OFICIAL DEL\nESTADO DE GUERRERO No. 67 ALCANCE I, DE FECHA 21 DE AGOSTO DEL 2015.\nTEXTO ORIGINAL\nAcuerdo publicado en el Periódico Oficial del Gobierno del Estado No. 81, el\nViernes 08 de Octubre de 2010.\nACUERDO POR EL QUE SE CREA EL SUBCOMITÉ SECTORIAL DE ECOLOGÍA Y\nCAMBIO CLIMÁTICO DEL COMITÉ DE PLANEACIÓN PARA EL DESARROLLO DEL\nESTADO DE GUERRERO.\nAl margen un sello con el Escudo Oficial que dice: Gobierno del Estado Libre y\nSoberano de Guerrero.- Poder Ejecutivo.\nCARLOS ZEFERINO TORREBLANCA GALINDO, GOBERNADOR\nCONSTITUCIONAL DEL ESTADO DE GUERRERO, EN EJERCICIO DE LAS\nFACULTADES QUE ME CONFIEREN LOS ARTÍCULOS 57, 58, 59 Y 74 FRACCIÓN IV\nGUERRERO Y CON FUNDAMENTO EN LO QUE ESTABLECEN LOS ARTÍCULOS 31,\n33 Y 34 DE LA LEY NÚMERO 994 DE PLANEACIÓN DEL ESTADO, 5 FRACCIÓN VIII\nDEL REGLAMENTO INTERIOR DEL COMITÉ DE PLANEACIÓN DEL DESARROLLO\nDEL ESTADO DE GUERRERO; 2°, 3°, 6° Y 20 FRACCIÓN III DE LA LEY ORGÁNICA\nDE LA ADMINISTRACIÓN PÚBLICA DEL ESTADO DE GUERRERO NÚMERO 433; Y,\n1. Que de conformidad con lo que establece la Constitución Política Local, el\nPoder Ejecutivo del Estado se deposita en el Gobernador del Estado de Guerrero, quien a su vez es Jefe del Estado, del Gobierno y de la Administración Pública Estatal, teniendo las facultades, atribuciones y obligaciones que particularmente le señalan la en la Entidad.\n2. Que de acuerdo con lo que señala la Ley Orgánica de la Administración\nPública del Estado, para el despacho de los asuntos que le competen, el Gobernador del\nPolítica, la misma Ley Orgánica, el Presupuesto de Egresos y las demás disposiciones jurídicas vigentes en la Entidad.\nEL DESARROLLO DEL ESTADO DE GUERRERO\n3. Que en términos de lo que establece la vigente Ley de Planeación para el\n(Copladeg), es un órgano administrativo desconcentrado, subordinado jerárquicamente al\nTitular del Ejecutivo Estatal, teniendo entre otras la función de coordinar las actividades de planeación del Estado.\n4. Que el Comité de Planeación para el Desarrollo del Estado de Guerrero, de acuerdo con lo que señala su Reglamento Interior, dispone de órganos auxiliares para el desarrollo de sus actividades, de entre los cuales se destacan los Subcomités\nSectoriales.\n5. Que actualmente, y bajo la coordinación de la Secretaría de Medio Ambiente y\nRecursos Naturales, ha venido funcionando el Subcomité Sectorial de Ecología para atender las políticas y programas de ecología en la Entidad.\n6. Que en su desempeño como Coordinador del Subcomité Sectorial de Ecología el Titular de la Secretaría de Medio Ambiente y Recursos Naturales solicitó al Copladeg promover el cambio en la nomenclatura de dicho Subcomité, así como la ampliación en sus objetivos y funciones.\n7. Que específicamente los cambios que se proponen son:\nA). En el nombre, de Subcomité Sectorial de Ecología por el de Subcomité\nSectorial de Ecología y Cambio Climático.\nB). Objetivo General: Fungir como órgano de consulta de los Gobiernos Federal, Estatal y Municipales en la orientación del desarrollo sustentable, perspectivas y diagnóstico ambiental, así como la planificación estratégica del Programa Estatal de\nAcción ante el Cambio Climático (PEACC).\nC). A los Objetivos Específicos que actualmente tiene se adicionan los siguientes:\n1. Elaborar los términos de referencia entre el organismo financiero y el organismo responsable de elaborar el PEACC;\nEL DESARROLLO DEL ESTADO DE GUERRERO\n2. Presentar el proyecto ante los Consejos y los Sectores de Gobierno representados en la Entidad, para información y consulta; y,\n3. Identificar grupos expertos y separarlos en climatología descriptiva o física, química y energía, economía, cambios de uso de suelo, agricultura, ganadería, pesca, biodiversidad, transporte, urbanismo, demografía, hidrología, costas, vivienda y energía, legislación, aspectos sociales y culturales (incluyendo un enfoque de género).\n8. Que dichos cambios fueron analizados y comentados por los integrantes del\nSubcomité Sectorial de Ecología en su Sesión Extraordinaria celebrada el 9 de agosto de\n2010, habiendo acordando someter a la consideración del Ejecutivo Estatal la propuesta de modificar el nombre de dicho órgano auxiliar, así como la ampliación en sus objetivos y funciones, tal y como se describe en el considerando que antecede.\n9. Que al efecto, al Titular del Poder Ejecutivo del Estado se le otorga la competencia para expedir acuerdos y otras disposiciones legales y administrativas que regulen el funcionamiento de las dependencias y entidades de la Administración Pública\nEstatal; los cuales, una vez refrendados, serán de carácter obligatorio y de observancia general. De manera particular, es facultad del Ejecutivo Estatal autorizar los cambios que se proponen y crear el nuevo órgano auxiliar del Copladeg.\nPor lo anteriormente expuesto y fundado, he tenido a bien expedir el siguiente:\nESTADO DE GUERRERO.\nARTÍCULO ÚNICO.- Con fundamento en los artículos 33 de la Ley de Planeación del Estado y 5 fracción VIII del Reglamento Interior del Copladeg, se acuerda la creación del Subcomité Sectorial de Ecología y Cambio Climático, como órgano auxiliar del\nComité de Planeación para el Desarrollo del Estado de Guerrero, autorizándose también los Objetivos General y Específicos tal y como se describen en los incisos A), B) y C) del\nConsiderando 7 de este documento.\nEL DESARROLLO DEL ESTADO DE GUERRERO\nARTÍCULO PRIMERO.- El presente Acuerdo entrará en vigor al día siguiente de\nARTÍCULO SEGUNDO.- Los Titulares del Comité de Planeación para el\nDesarrollo del Estado de Guerrero y de la Secretaría de Medio Ambiente y Recursos\nNaturales deberán implementar lo necesario a fin de cumplir con lo determinado en el presente Acuerdo.\nDado en la Residencia Oficial del Poder Ejecutivo del Estado en la Ciudad de\nChilpancingo de los Bravo, Guerrero, a los doce días del mes de agosto de dos mil diez.\nSUFRAGIO EFECTIVO. NO REELECCIÓN.\nEL GOBERNADOR CONSTITUCIONAL DEL ESTADO.\nCARLOS ZEFERINO TORREBLANCA GALINDO.\nRúbrica.\nEL SECRETARIO GENERAL DE GOBIERNO\nISRAEL SOBERANIS NOGUEDA.\nRúbrica.\nEL COORDINADOR GENERAL DEL EJECUTIVO\nDEL ESTADO Y DEL COPLADEG.\nHUMBERTO SARMIENTO LUEBBERT.\nRúbrica.",
  "ordenamiento": "ACUERDO",
  "jurisdiccion": "GUERRERO",
  "fuente_oficial": "DIARIO OFICIAL DE LA FEDERACION",
  "Fecha de Publicación": "08 de Octubre de 2010",
  "ULTIMA REFORMA PUBLICADA": "21 DE AGOSTO DEL 2015",
  "status": "ABROGADA",
  "es_escaneado": false,
  "tiene_tablas": false,
  "materia": [
    "ambiental"
  ]
}