{
  "titulo": "Acuerdo de Coordinación para la Distribución y Operación de los Subsidios del Programa Hábitat, Vert",
  "Contenido": "VERTIENTE GENERAL, DEL RAMO\nADMINISTRATIVO 20 “DESARROLLO SOCIAL”,\nQUE CELEBRAN POR UNA PARTE EL EJECUTIVO\nFEDERAL, A TRAVÉS DE LA SECRETARÍA DE\nDESARROLLO SOCIAL Y POR LA OTRA, EL\nEJECUTIVO DEL ESTADO DE GUERRERO Y LOS\nMUNICIPIOS DE: ACAPULCO DE JUÁREZ;\nATOYAC DE ÁLVAREZ; CHILPANCINGO DE LOS\nABROGADO POR CONCLUIDA SU VIGENCIA EL 31 DE DICIEMBRE DE 2009.\nTEXTO ORIGINAL.\nAcuerdo publicado en el Periódico Oficial del Gobierno del Estado No. 39, el\nViernes 15 de Mayo de 2009.\nACUERDO DE COORDINACIÓN PARA LA DISTRIBUCIÓN Y OPERACIÓN DE LOS\nSUBSIDIOS DEL PROGRAMA HÁBITAT, VERTIENTE GENERAL, DEL RAMO\nADMINISTRATIVO 20 \"DESARROLLO SOCIAL\", QUE SUSCRIBEN POR UNA PARTE\nEL EJECUTIVO FEDERAL, A TRAVÉS DE LA SECRETARÍA DE DESARROLLO\nSOCIAL, EN LO SUCESIVO \"LA SEDESOL\", REPRESENTADA EN ESTE ACTO POR\nLA SUBSECRETARIA DE DESARROLLO URBANO Y ORDENACIÓN DEL\nTERRITORIO, ARQ. SARA HALINA TOPELSON FRIDMAN, ASISTIDA POR EL\nDELEGADO FEDERAL DE LA SECRETARÍA DE DESARROLLO SOCIAL EN EL\nESTADO DE GUERRERO ING. LUZ ANTONIO GONZÁLEZ JUSTO; POR OTRA\nPARTE, EL EJECUTIVO DEL ESTADO DE GUERRERO, EN LO SUCESIVO \"EL\nESTADO\" REPRESENTADO POR EL SECRETARIO DE DESARROLLO URBANO Y\nOBRAS PÚBLICAS; EL COORDINADOR GENERAL DEL EJECUTIVO ESTATAL Y\nPLANEACIÓN PARA EL DESARROLLO DEL ESTADO DE GUERRERO, LOS C. C.\nARQ. GUILLERMO TORRES MADRID, LIC. HUMBERTO SARMIENTO LUEBBERT Y\nLIC. ALFONSO BECERRIL ZARCO; Y LOS MUNICIPIOS DE ACAPULCO DE\nJUÁREZ, ATOYAC DE ÁLVAREZ, CHILPANCINGO DE LOS BRAVO, COYUCA DE\nBENÍTEZ, EDUARDO NERI, HUITZUCO DE LOS FIGUEROA, IGUALA DE LA\nINDEPENDENCIA, ZIHUATANEJO DE AZUETA, OMETEPEC, PETATLÁN,\nVERTIENTE GENERAL, DEL RAMO\nADMINISTRATIVO 20 “DESARROLLO SOCIAL”,\nQUE CELEBRAN POR UNA PARTE EL EJECUTIVO\nFEDERAL, A TRAVÉS DE LA SECRETARÍA DE\nDESARROLLO SOCIAL Y POR LA OTRA, EL\nEJECUTIVO DEL ESTADO DE GUERRERO Y LOS\nMUNICIPIOS DE: ACAPULCO DE JUÁREZ;\nATOYAC DE ÁLVAREZ; CHILPANCINGO DE LOS\nPUNGARABATO, TAXCO DE ALARCÓN, TECPAN DE GALEANA, TIXTLA DE\nGUERRERO Y TLAPA DE COMONFORT, EN LO SUCESIVO \"LOS MUNICIPIOS\",\nREPRESENTADOS POR SUS PRESIDENTES MUNICIPALES, LOS C. C. DR.\nMANUEL AÑORVE BAÑOS, C.P. CARLOS ARMANDO BELLO GÓMEZ, LIC. HÉCTOR\nANTONIO ASTUDILLO FLORES, LIC. MERCED BALDOVINO DIEGO, PROFR.\nMODESTO PÉREZ LEYVA, C. ISIDRO MIRANDA MADRID, DR. RAÚL TOVAR\nTAVERA, ING. ALEJANDRO BRAVO ABARCA, C. EFRÉN ADAME MONTALVAN,\nARQ. JOSÉ ALBINO LACUNZA SANTOS, DR. GUSTAVO ADOLFO JUANCHI\nQUIÑONES, L.A.E. ÁLVARO BURGOS BARRERA, PROFR. NADIN TORRALBA\nMEJIA, PROFR. JORGE LUIS CAMPOS ESPÍRITU Y LIC. WILLY REYES RAMOS.\nI. El Plan Nacional de Desarrollo 2007-2012, establece en su apartado denominado Eje 3 \"Igualdad de oportunidades\", que la finalidad de la política social de esta Administración es lograr el desarrollo humano y el bienestar de los mexicanos a través de la igualdad de oportunidades. Para conducir a México hacia un desarrollo imperan en el país. Gobierno y sociedad deben ser capaces de mejorar significativamente las condiciones de vida de quienes viven en la pobreza, es decir, casi la mitad de la población.\nII. El Programa Sectorial de Desarrollo Social 2007-2012, establece entre sus objetivos: Mejorar la calidad de vida en las ciudades, con énfasis en los grupos sociales en condición de pobreza, a través de la provisión de infraestructura social y vivienda digna, así como consolidar ciudades eficientes, seguras y competitivas.\nVERTIENTE GENERAL, DEL RAMO\nADMINISTRATIVO 20 “DESARROLLO SOCIAL”,\nQUE CELEBRAN POR UNA PARTE EL EJECUTIVO\nFEDERAL, A TRAVÉS DE LA SECRETARÍA DE\nDESARROLLO SOCIAL Y POR LA OTRA, EL\nEJECUTIVO DEL ESTADO DE GUERRERO Y LOS\nMUNICIPIOS DE: ACAPULCO DE JUÁREZ;\nATOYAC DE ÁLVAREZ; CHILPANCINGO DE LOS\nIII. El artículo 33 de la Ley de Planeación establece que el Ejecutivo Federal podrá convenir con los Gobiernos de las Entidades Federativas, satisfaciendo las formalidades que en cada caso procedan, la coordinación que se requiera a efecto de que los Gobiernos participen en el Plan Nacional de Desarrollo.\nIV. El artículo 29 fracción II del Decreto de Presupuesto de Egresos de la\nFederación para el Ejercicio Fiscal 2009, establece que tratándose de facultades concurrentes, cuando el Ejecutivo Federal por conducto de la dependencia competente decida suscribir convenios de coordinación en términos de la Ley de Planeación con las\nEntidades Federativas, procurará que éstos se celebren en condiciones de oportunidades y certeza para beneficio de la población objetivo.\nV. De acuerdo a lo establecido en el artículo 30 del Decreto de Presupuesto de\nEgresos de la Federación para el Ejercicio Fiscal 2009, los programas de subsidios del\nRamo Administrativo 20 Desarrollo Social se destinarán, en las entidades federativas, en los términos de las disposiciones aplicables, exclusivamente a la población en conocer por la Secretaría de Desarrollo Social.\nVI. El Ejecutivo Federal a través de la Secretaría de Desarrollo Social, ha instrumentado el Programa Hábitat. Conforme a lo establecido en las Reglas de\nOperación del Programa Hábitat para el ejercicio fiscal 2009, en lo sucesivo \"REGLAS\n2008, el objetivo general de Hábitat es contribuir a la superación de la pobreza y al mejoramiento de la calidad de vida de los habitantes de zonas urbano-marginadas,\nVERTIENTE GENERAL, DEL RAMO\nADMINISTRATIVO 20 “DESARROLLO SOCIAL”,\nQUE CELEBRAN POR UNA PARTE EL EJECUTIVO\nFEDERAL, A TRAVÉS DE LA SECRETARÍA DE\nDESARROLLO SOCIAL Y POR LA OTRA, EL\nEJECUTIVO DEL ESTADO DE GUERRERO Y LOS\nMUNICIPIOS DE: ACAPULCO DE JUÁREZ;\nATOYAC DE ÁLVAREZ; CHILPANCINGO DE LOS fortaleciendo y mejorando la organización y participación social, así como el entorno urbano de dichos asentamientos.\nVII. La Dirección General de Programación y Presupuesto de la Secretaría de\nDesarrollo Social, mediante el oficio número OM/DGPP/410.20/1696/08, de fecha 19 de\nDiciembre de 2008, le comunicó a la Subsecretaría de Desarrollo Urbano y Ordenación del Territorio el monto de los subsidios autorizados al Programa Hábitat para el presente año.\nVIII. La Subsecretaria de Desarrollo Urbano y Ordenación del Territorio, mediante oficio circular No. 300/001/2009 de fecha 02 de Enero de 2009, comunicó a los delegados federales de la Secretaría de Desarrollo Social la distribución de los subsidios federales del Programa Hábitat por entidad federativa para el ejercicio fiscal 2009.\nCon base en lo expuesto, y con fundamento en los artículos 32 de la Ley\nOrgánica de la Administración Pública Federal; 33, 34, 36 y 44 de la Ley de Planeación;\n1, 4, 45, 54, 74, 75 y 77, de la Ley Federal de Presupuesto y Responsabilidad\nHacendaria; 1, 4, 24, 32 y 43 de la Ley General de Desarrollo Social; 49, 50 y 51 de la\nLey General de Asentamientos Humanos; 7 y demás aplicables de la Ley Federal de\nDecreto de Presupuesto de Egresos de la Federación para el Ejercicio Fiscal 2009; 1, 85\n6, 8, 12, 16, 36, 37, 44 y 45 del Reglamento Interior de la Secretaría de Desarrollo Social; la Federación el 29 de Diciembre 2008, así como en lo previsto por los artículos 1, 2, 3, 4\nVERTIENTE GENERAL, DEL RAMO\nADMINISTRATIVO 20 “DESARROLLO SOCIAL”,\nQUE CELEBRAN POR UNA PARTE EL EJECUTIVO\nFEDERAL, A TRAVÉS DE LA SECRETARÍA DE\nDESARROLLO SOCIAL Y POR LA OTRA, EL\nEJECUTIVO DEL ESTADO DE GUERRERO Y LOS\nMUNICIPIOS DE: ACAPULCO DE JUÁREZ;\nATOYAC DE ÁLVAREZ; CHILPANCINGO DE LOS primer párrafo, 11, 18 y 23 de la Ley Orgánica de la Administración Pública del Estado de\nGuerrero; en los artículos 1 fracción IV, 29, 30, 31, 32, 33, 34 y 35 de la Ley de\nPlaneación del Estado de Guerrero; artículo 7 fracciones I, II. V y XX de la Ley de\nDesarrollo Urbano del Estado de Guerrero Número 211, Artículo Segundo del Acuerdo por el que se crea la Coordinación General del Ejecutivo del Estado, como una dependencia directamente adscrita a la Oficina del Gobernador, publicado en el\nPeriódico Oficial del Gobierno del Estado de Guerrero Número 5 de fecha 16 de Enero de 2007; la Ley Orgánica del Municipio Libre del Estado de Guerrero y el Reglamento de\nConstrucciones para los Municipios del Estado de Guerrero, las partes han decidido establecer sus compromisos con arreglo a las siguientes:\nCAPÍTULO I. DEL OBJETO\nPRIMERA. El presente Acuerdo de Coordinación tiene por objeto coordinar las acciones entre \"LA SEDESOL\", \"EL ESTADO\" y \"LOS MUNICIPIOS\", para la operación del Programa Hábitat en las ciudades, zonas metropolitanas y Polígonos\nHábitat seleccionados y para el ejercicio de los subsidios federales y las aportaciones locales, con el propósito de contribuir a la superación de la pobreza y al mejoramiento de la calidad de vida de los habitantes de zonas urbano-marginadas.\nLos Polígonos Hábitat son identificados por \"LA SEDESOL\", están integrados pobreza patrimonial y constituyen el ámbito de actuación del Programa Hábitat.\nVERTIENTE GENERAL, DEL RAMO\nADMINISTRATIVO 20 “DESARROLLO SOCIAL”,\nQUE CELEBRAN POR UNA PARTE EL EJECUTIVO\nFEDERAL, A TRAVÉS DE LA SECRETARÍA DE\nDESARROLLO SOCIAL Y POR LA OTRA, EL\nEJECUTIVO DEL ESTADO DE GUERRERO Y LOS\nMUNICIPIOS DE: ACAPULCO DE JUÁREZ;\nATOYAC DE ÁLVAREZ; CHILPANCINGO DE LOS\nSEGUNDA. \"LA SEDESOL\", \"EL ESTADO\" y \"LOS MUNICIPIOS\" acuerdan que en la operación del Programa Hábitat y en el ejercicio de sus subsidios, se sujetarán a lo que establece la legislación federal y aplicable, las \"REGLAS DE OPERACIÓN\" y los Lineamientos de Operación del Programa Hábitat vigentes, así como los instrumentos técnicos que se derivan de estos dos últimos.\nCAPÍTULO II. DE LAS CIUDADES, ZONAS METROPOLITANAS Y\nPOLÍGONOS HÁBITAT SELECCIONADOS\nTERCERA. \"LA SEDESOL\", \"ELESTADO\" y \"LOS MUNICIPIOS\" acuerdan que los recursos del Programa Hábitat se ejercerán en las ciudades, zonas metropolitanas y\nPolígonos Hábitat seleccionados, que se señalan en el Anexo I denominado \"Ciudades, Zonas Metropolitanas y Polígonos Hábitat Seleccionados\", el cual será suscrito por el Delegado Federal de \"LA SEDESOL\", el Coordinador General del Ejecutivo Estatal y\nPresidentes Municipales. Dicho Anexo formará parte del presente Acuerdo de\nCoordinación.\nCUARTA. \"LA SEDESOL\" promoverá la concurrencia de acciones de otras instituciones en los Polígonos Hábitat seleccionados, tanto de instancias del propio pública federal. \"EL ESTADO\" y \"LOS MUNICIPIOS\" acuerdan apoyar a \"LA\nSEDESOL\" en la ejecución de dichas acciones.\nVERTIENTE GENERAL, DEL RAMO\nADMINISTRATIVO 20 “DESARROLLO SOCIAL”,\nQUE CELEBRAN POR UNA PARTE EL EJECUTIVO\nFEDERAL, A TRAVÉS DE LA SECRETARÍA DE\nDESARROLLO SOCIAL Y POR LA OTRA, EL\nEJECUTIVO DEL ESTADO DE GUERRERO Y LOS\nMUNICIPIOS DE: ACAPULCO DE JUÁREZ;\nATOYAC DE ÁLVAREZ; CHILPANCINGO DE LOS\nCAPÍTULO III. DE LOS\nSUBSIDIOS FEDERALES\nQUINTA. \"LA SEDESOL\", \"EL ESTADO\" y \"LOS MUNICIPIOS\" acuerdan que los subsidios federales destinados a la entidad federativa se distribuyen por municipio, de conformidad con lo señalado en el Anexo II denominado \"Subsidios Federales por\nMunicipio\", el cual será suscrito por el Delegado Federal de \"LA SEDESOL\", el\nCoordinador General del Ejecutivo Estatal y del Comité de Planeación para el Desarrollo del Estado de Guerrero y por los Presidentes Municipales. Dicho Anexo formará parte del presente Acuerdo de Coordinación.\nSEXTA. La ministración de los subsidios federales para el Programa Hábitat se efectuará considerando el calendario autorizado por la Secretaría de Hacienda y Crédito\nPúblico, a través del Sistema Integral de Administración Financiera Federal (SIAFF).\nSÉPTIMA. De conformidad con lo establecido en las \"REGLAS DE\nOPERACIÓN\", \"EL ESTADO\", \"LOS MUNICIPIOS\" y las Delegaciones Federales de\n\"LA SEDESOL\" podrán constituirse como ejecutores del Programa Hábitat. Los federales y de los recursos locales aportados al Programa.\nOCTAVA. \"LA SEDESOL\", \"EL ESTADO\" y \"LOS MUNICIPIOS\" acuerdan que fechas señaladas en el Oficio de Distribución de Subsidios del Programa Hábitat, podrán entidades federativas del país. Dichas reasignaciones presupuestarias serán notificadas\nVERTIENTE GENERAL, DEL RAMO\nADMINISTRATIVO 20 “DESARROLLO SOCIAL”,\nQUE CELEBRAN POR UNA PARTE EL EJECUTIVO\nFEDERAL, A TRAVÉS DE LA SECRETARÍA DE\nDESARROLLO SOCIAL Y POR LA OTRA, EL\nEJECUTIVO DEL ESTADO DE GUERRERO Y LOS\nMUNICIPIOS DE: ACAPULCO DE JUÁREZ;\nATOYAC DE ÁLVAREZ; CHILPANCINGO DE LOS por la Delegación Federal de \"LA SEDESOL\" al Coordinador General del Ejecutivo\nEstatal y del Comité de Planeación para el Desarrollo del Estado de Guerrero y a \"LOS\nMUNICIPIOS\" que correspondan.\nCAPÍTULO IV. DE LOS RECURSOS APORTADOS POR \"EL ESTADO\"\nY POR \"LOS MUNICIPIOS\"\nNOVENA. \"EL ESTADO\" y \"LOS MUNICIPIOS\", se comprometen a aportar recursos financieros para las obras y acciones apoyadas por el Programa Hábitat, de conformidad con lo señalado en las \"REGLAS DE OPERACIÓN\". Estos recursos serán distribuidos conforme a lo señalado en el Anexo III denominado \"Aportaciones de\nRecursos Locales por Municipio\", el cual será suscrito por el Delegado Federal de \"LA\nSEDESOL\", el Coordinador General del Ejecutivo Estatal y del Comité de Planeación para el Desarrollo del Estado de Guerrero y por los Presidentes Municipales. Dicho\nAnexo formará parte del presente Acuerdo de Coordinación.\nCAPÍTULO V. DE LAS\nRESPONSABILIDADES\nDÉCIMA. \"LA SEDESOL\" se compromete a:\na) Apoyar con subsidios federales la ejecución del Programa Hábitat en las ciudades, zonas metropolitanas y Polígonos Hábitat seleccionados, con la participación que corresponda a \"EL ESTADO\" y a \"LOS MUNICIPIOS\".\nVERTIENTE GENERAL, DEL RAMO\nADMINISTRATIVO 20 “DESARROLLO SOCIAL”,\nQUE CELEBRAN POR UNA PARTE EL EJECUTIVO\nFEDERAL, A TRAVÉS DE LA SECRETARÍA DE\nDESARROLLO SOCIAL Y POR LA OTRA, EL\nEJECUTIVO DEL ESTADO DE GUERRERO Y LOS\nMUNICIPIOS DE: ACAPULCO DE JUÁREZ;\nATOYAC DE ÁLVAREZ; CHILPANCINGO DE LOS\nb) Aprobar las obras y acciones, así como la radicación de los subsidios federales, de manera oportuna y por conducto de la Delegación Federal de \"LA\nSEDESOL\" en la entidad federativa.\nc) Aplicar los subsidios federales y las aportaciones locales, cuando funja como ejecutor, conforme a lo señalado en las \"REGLAS DE OPERACIÓN\" y en la legislación federal aplicable.\nDÉCIMA PRIMERA. \"EL ESTADO\" Y \"LOS MUNICIPIOS\" se comprometen a:\na) Aplicar los recursos del Programa Hábitat en las ciudades, zonas metropolitanas y Polígonos Hábitat seleccionados, conforme a lo establecido en las\n\"REGLAS DE OPERACIÓN\".\nb) Aplicar los subsidios federales y las aportaciones locales, cuando funja como ejecutor, conforme a lo señalado en las \"REGLAS DE OPERACIÓN\" y en la legislación federal aplicable.\nc) Apoyar el cumplimiento de los objetivos y las metas del Programa Hábitat.\nd) Elaborar y mantener actualizado un registro de los subsidios federales y de los recursos locales asignados y ejercidos, de conformidad con la normatividad aplicable.\ne) Garantizar, en su caso, la aportación que corresponda a los beneficiarios, conforme a lo señalado en las \"REGLAS DE OPERACIÓN\".\nVERTIENTE GENERAL, DEL RAMO\nADMINISTRATIVO 20 “DESARROLLO SOCIAL”,\nQUE CELEBRAN POR UNA PARTE EL EJECUTIVO\nFEDERAL, A TRAVÉS DE LA SECRETARÍA DE\nDESARROLLO SOCIAL Y POR LA OTRA, EL\nEJECUTIVO DEL ESTADO DE GUERRERO Y LOS\nMUNICIPIOS DE: ACAPULCO DE JUÁREZ;\nATOYAC DE ÁLVAREZ; CHILPANCINGO DE LOS\nf) En el caso de \"LOS MUNICIPIOS\", mantener la operación de los inmuebles apoyados por el Programa, destinados a la prestación de servicios sociales, para los fines acordados con \"LA SEDESOL\".\ng) Reintegrar a la Tesorería de la Federación, conforme a lo establecido en la normatividad aplicable, los subsidios federales no ejercidos al cierre del ejercicio fiscal, los recursos no comprobados en la fecha límite establecida para este fin, así como los rendimientos financieros que, en su caso, se hubieren generado.\nh) Hacer explícito en el acta de entrega-recepción o en el informe de resultados, cuando funjan como ejecutores, el compromiso de dar mantenimiento, conservar, vigilar y sufragar la continua y adecuada operación de las obras y/o equipos financiados con recursos del Programa Hábitat.\ni) Proporcionar a las instancias correspondientes de control y auditoría, la información requerida, así como otorgarles las facilidades necesarias, para que lleven a cabo sus acciones en dichas materias.\nCAPÍTULO VI. DEL SEGUIMIENTO, CONTROL Y EVALUACIÓN\nDEL PROGRAMA\nDÉCIMA SEGUNDA. \"EL ESTADO\" y LOS MUNICIPIOS\", cuando sean ejecutores del Programa Hábitat, se comprometen a cumplir con las responsabilidades señaladas en el numeral 3.7.1 de las \"REGLAS DE OPERACIÓN\", así como otorgar las facilidades necesarias a \"LA SEDESOL\", para que ésta realice visitas de seguimiento de las obras y acciones realizadas con recursos del Programa, así como para tener acceso\nVERTIENTE GENERAL, DEL RAMO\nADMINISTRATIVO 20 “DESARROLLO SOCIAL”,\nQUE CELEBRAN POR UNA PARTE EL EJECUTIVO\nFEDERAL, A TRAVÉS DE LA SECRETARÍA DE\nDESARROLLO SOCIAL Y POR LA OTRA, EL\nEJECUTIVO DEL ESTADO DE GUERRERO Y LOS\nMUNICIPIOS DE: ACAPULCO DE JUÁREZ;\nATOYAC DE ÁLVAREZ; CHILPANCINGO DE LOS a equipos, materiales, información, registros y documentos que estime pertinente conocer y que estén relacionados con la ejecución de las mismas.\nDÉCIMA TERCERA. \"EL ESTADO\" y \"LOS MUNICIPIOS\", cuando sean ejecutores del Programa Hábitat, asumen el compromiso de proporcionar a \"LA\nSEDESOL\" la información sobre los avances y resultados del Programa Hábitat, conforme a lo siguiente:\na) Actualizar mensualmente la información registrada en el SIIPSO sobre los avances físicos y financieros de todos los proyectos apoyados por el Programa.\nb) Reportar trimestralmente a la Delegación Federal de \"LA SEDESOL\", durante los primeros cinco días hábiles del mes inmediato al trimestre que concluye, los avances físico-financieros de los proyectos autorizados.\nc) Informar a la Delegación Federal de \"LA SEDESOL\", por conducto del\nSIIPSO, de las obras y acciones concluidas, así como de sus resultados físicos y financieros, a más tardar a los treinta días naturales a la fecha de su conclusión. federativa y al del municipio, al concluir la obra o acción, en un plazo que no exceda los treinta días naturales siguientes, copia del acta de entrega-recepción o del informe de resultados.\ne) Comunicar oportunamente a la comunidad beneficiada, a la Delegación\nFederal de \"LA SEDESOL\", así como a los gobiernos de la entidad federativa y del\nVERTIENTE GENERAL, DEL RAMO\nADMINISTRATIVO 20 “DESARROLLO SOCIAL”,\nQUE CELEBRAN POR UNA PARTE EL EJECUTIVO\nFEDERAL, A TRAVÉS DE LA SECRETARÍA DE\nDESARROLLO SOCIAL Y POR LA OTRA, EL\nEJECUTIVO DEL ESTADO DE GUERRERO Y LOS\nMUNICIPIOS DE: ACAPULCO DE JUÁREZ;\nATOYAC DE ÁLVAREZ; CHILPANCINGO DE LOS municipio, para que en los actos para la entrega recepción de las obras y acciones se encuentren presentes representantes de dichas instancias.\nf) Elaborar e imprimir, por conducto del SIIPSO, el Informe de Cierre de Ejercicio.\nEn éste se considerarán todos aquellos movimientos presupuestarios de los subsidios en el ejercicio fiscal y debe coincidir con lo registrado en el Sistema Integral de Presupuesto y Contabilidad (SIPREC).\nDÉCIMA CUARTA. \"LA SEDESOL\", \"EL ESTADO\" y \"LOS MUNICIPIOS\" colaborarán, en el ámbito de sus respectivas competencias, en la operación de un sistema de información, administrado por \"LA SEDESOL\", que apoye las actividades de seguimiento, control y evaluación del Programa Hábitat.\nDÉCIMA QUINTA. Las actividades de control y auditoría de los subsidios federales corresponderán al Órgano Interno de Control en la Secretaría de Desarrollo\nSocial; a la Secretaría de la Función Pública, en coordinación con los órganos de control de los gobiernos de las entidades federativas; así como a la Auditoria Superior de la\nFederación, y la Secretaría de Hacienda y Crédito Público, conforme a las atribuciones que les confiere la Ley Orgánica de la Administración Pública Federal, la Ley de\nFiscalización Superior de la Federación y demás disposiciones aplicables.\nDÉCIMA SEXTA. \"EL ESTADO\" y \"LOS MUNICIPIOS\" se comprometen a apoyar a \"LA SEDESOL\" en las acciones que se lleven a cabo para la evaluación externa del Programa Hábitat conforme lo establecen las \"REGLAS DE OPERACIÓN\" y demás normatividad aplicable.\nVERTIENTE GENERAL, DEL RAMO\nADMINISTRATIVO 20 “DESARROLLO SOCIAL”,\nQUE CELEBRAN POR UNA PARTE EL EJECUTIVO\nFEDERAL, A TRAVÉS DE LA SECRETARÍA DE\nDESARROLLO SOCIAL Y POR LA OTRA, EL\nEJECUTIVO DEL ESTADO DE GUERRERO Y LOS\nMUNICIPIOS DE: ACAPULCO DE JUÁREZ;\nATOYAC DE ÁLVAREZ; CHILPANCINGO DE LOS\nCAPÍTULO VII.\nESTIPULACIONES FINALES\nDÉCIMA SÉPTIMA. Cuando las secretarías de Hacienda y Crédito Público, de la\nFunción Pública o de Desarrollo Social, en el ámbito de sus respectivas competencias, detecten faltas de comprobación, desviaciones, incumplimiento a lo convenido en el instrumento jurídico de coordinación que, en su caso, corresponda, o incumplimiento en la entrega oportuna de información relativa a avances y metas alcanzadas, \"LA\nSEDESOL\", después de escuchar la opinión del gobierno de la entidad federativa correspondiente y del Ejecutor, podrá suspender la radicación de los recursos federales e inclusive solicitar su reintegro, así como los rendimientos financieros que, en su caso, se hubieren generado, sin perjuicio de lo establecido en las disposiciones aplicables.\nEn caso de que la Delegación de la \"LA SEDESOL\" detecte condiciones inadecuadas de mantenimiento o de operación en obras financiadas con recursos del\nPrograma en el año en curso o en ejercicios anteriores, \"LA SEDESOL\" podrá fiscal. En caso de persistir la situación detectada, \"LA SEDESOL\" podrá cancelar los proyectos aprobados en 2009 y solicitar el reintegro de los subsidios que hubieren sido ministrados.\nDÉCIMA OCTAVA. Los Anexos I, II y III del presente Acuerdo de Coordinación, se podrán modificar de común acuerdo por las partes, en tanto la Secretaría de Hacienda cada Entidad Federativa.\nVERTIENTE GENERAL, DEL RAMO\nADMINISTRATIVO 20 “DESARROLLO SOCIAL”,\nQUE CELEBRAN POR UNA PARTE EL EJECUTIVO\nFEDERAL, A TRAVÉS DE LA SECRETARÍA DE\nDESARROLLO SOCIAL Y POR LA OTRA, EL\nEJECUTIVO DEL ESTADO DE GUERRERO Y LOS\nMUNICIPIOS DE: ACAPULCO DE JUÁREZ;\nATOYAC DE ÁLVAREZ; CHILPANCINGO DE LOS\nDichas modificaciones deberán constar por escrito y entrarán en vigor a partir de su suscripción por parte del Delegado Federal de \"LA SEDESOL\", Coordinador General del Ejecutivo Estatal y del Comité de Planeación para el Desarrollo del Estado de\nGuerrero y por los Presidentes Municipales.\nDÉCIMA NOVENA. Para dar transparencia en el ejercicio de los recursos federales, \"LA SEDESOL\", \"EL ESTADO\" y \"LOS MUNICIPIOS\", convienen que en todas las actividades de difusión y publicidad que lleven a cabo las Instancias Ejecutoras sobre la ejecución de obras y acciones del Programa Hábitat, apoyadas parcial o totalmente con subsidios federales, deberán mencionar expresamente dicha aportación de recursos federales, así como incluir los logotipos de \"LA SEDESOL\", de la Estrategia\nVivir Mejor y del Programa Hábitat en los impresos y elementos gráficos que sean utilizados para tal efecto, como son letreros, mamparas, templetes, gallardetes, carteles, trípticos y otros similares. Los logotipos de \"LA SEDESOL\", de la Estrategia Vivir Mejor y del Programa Hábitat deberán tener, al menos, el mismo tamaño que los logotipos de otras instancias locales participantes.\nLas partes acuerdan que, conforme a la Ley General de Desarrollo Social, así\n2009, la publicidad y la información relativa a las acciones realizadas deberá identificarse con el escudo nacional en los términos que establece la Ley sobre el Escudo, la Bandera y el Himno Nacionales e incluir la siguiente leyenda \"Este Programa es público, ajeno a cualquier partido político. Queda prohibido el uso para fines distintos al desarrollo social\".\nVIGÉSIMA. El presente Acuerdo se podrá dar por terminado de manera anticipada por cualquiera de las siguientes causas:\nVERTIENTE GENERAL, DEL RAMO\nADMINISTRATIVO 20 “DESARROLLO SOCIAL”,\nQUE CELEBRAN POR UNA PARTE EL EJECUTIVO\nFEDERAL, A TRAVÉS DE LA SECRETARÍA DE\nDESARROLLO SOCIAL Y POR LA OTRA, EL\nEJECUTIVO DEL ESTADO DE GUERRERO Y LOS\nMUNICIPIOS DE: ACAPULCO DE JUÁREZ;\nATOYAC DE ÁLVAREZ; CHILPANCINGO DE LOS\na) No cumplir en tiempo y forma con los compromisos pactados en este instrumento y en lo establecido en el Decreto de Presupuesto de Egresos de la\nFederación para el Ejercicio Fiscal 2009, en las \"REGLAS DE OPERACIÓN\" y en las demás disposiciones jurídicas y administrativas aplicables.\nb) La aplicación de los subsidios federales asignados por medio de este Acuerdo a \"EL ESTADO\" y a \"LOS MUNICIPIOS\" a fines distintos de los pactados.\nc) La falta de entrega de información, reportes y demás documentación prevista en este Acuerdo y en los diversos instrumentos derivados del mismo.\nVIGÉSIMA PRIMERA. Las partes realizarán las acciones necesarias para cumplir con los compromisos pactados en el presente Acuerdo de Coordinación. De presentarse casos fortuitos o de fuerza mayor, que motiven el incumplimiento a lo pactado, la contraparte quedará liberada del cumplimiento de las obligaciones que le son correlativas, debiendo comunicar dichas circunstancias por escrito a la brevedad posible, a las partes, a través de las instancias que suscriben el presente Acuerdo.\nVIGÉSIMA SEGUNDA. Las partes manifiestan su conformidad para que en caso de controversias, que se susciten en la operación, la interpretación o el incumplimiento del presente Acuerdo, las conozcan los Tribunales Federales con sede en la Ciudad de\nMéxico, Distrito Federal.\nVIGÉSIMA TERCERA. Este Acuerdo surte sus efectos a partir de la fecha de su firma y hasta el treinta y uno de diciembre del año dos mil nueve. El presente Acuerdo y sus Anexos deberán publicarse, conforme lo establece el artículo 36 de la Ley de\nVERTIENTE GENERAL, DEL RAMO\nADMINISTRATIVO 20 “DESARROLLO SOCIAL”,\nQUE CELEBRAN POR UNA PARTE EL EJECUTIVO\nFEDERAL, A TRAVÉS DE LA SECRETARÍA DE\nDESARROLLO SOCIAL Y POR LA OTRA, EL\nEJECUTIVO DEL ESTADO DE GUERRERO Y LOS\nMUNICIPIOS DE: ACAPULCO DE JUÁREZ;\nATOYAC DE ÁLVAREZ; CHILPANCINGO DE LOS\nPlaneación, en el Diario Oficial de la Federación y en el órgano oficial de difusión del\nGobierno del Esta-do, con el propósito de que la población conozca las acciones coordinadas de la Federación con el Estado.\nLeído que fue y debidamente enterados del alcance y contenido legal, se firma el presente Acuerdo de Coordinación en 4 ejemplares, en la Ciudad de Chilpancingo, Guerrero, a los 28 días del mes de Enero del año dos mil nueve.\nPOR \"LA SEDESOL\"\nLA SUBSECRETARIA DE DESARROLLO URBANO Y\nORDENACIÓN DEL TERRITORIO.\nARQ. SARA HALINA TOPELSON FRIDMAN.\nEL DELEGADO FEDERAL EN EL ESTADO DE GUERRERO.\nING. LUZ ANTONIO GONZÁLEZ JUSTO.\nPOR \"EL ESTADO\"\nEL SECRETARIO DE DESARROLLO URBANO Y OBRAS PÚBLICAS.\nARQ. GUILLERMO TORRES MADRID.\nVERTIENTE GENERAL, DEL RAMO\nADMINISTRATIVO 20 “DESARROLLO SOCIAL”,\nQUE CELEBRAN POR UNA PARTE EL EJECUTIVO\nFEDERAL, A TRAVÉS DE LA SECRETARÍA DE\nDESARROLLO SOCIAL Y POR LA OTRA, EL\nEJECUTIVO DEL ESTADO DE GUERRERO Y LOS\nMUNICIPIOS DE: ACAPULCO DE JUÁREZ;\nATOYAC DE ÁLVAREZ; CHILPANCINGO DE LOS\nEL COORDINADOR GENERAL DEL EJECUTIVO ESTATAL Y DEL COPLADEG.\nLIC. HUMBERTO SARMIENTO LUEB-BERT.\nRúbrica.\nEL COORDINADOR GENERAL ADJUNTO DEL COPLADEG.\nLIC. ALFONSO BECERRIL ZARCO.\nRúbrica.\nPOR \"LOS MUNICIPIOS\"\nEL PRESIDENTE MUNICIPAL DE ACAPULCO DE JUÁREZ.\nDR. MANUEL AÑORVE BAÑOS.\nRúbrica.\nEL PRESIDENTE MUNICIPAL DE ATOYAC DE ÁLVAREZ.\nC.P. CARLOS ARMANDO BELLO GÓMEZ.\nEL PRESIDENTE MUNICIPAL DE CHILPANCINGO DE LOS BRAVO.\nLIC. HÉCTOR ANTONIO ASTUDILLO FLORES.\nEL PRESIDENTE MUNICIPAL DE COYUCA DE BENÍTEZ.\nLIC. MERCED BALDOVINO DIEGO.\nVERTIENTE GENERAL, DEL RAMO\nADMINISTRATIVO 20 “DESARROLLO SOCIAL”,\nQUE CELEBRAN POR UNA PARTE EL EJECUTIVO\nFEDERAL, A TRAVÉS DE LA SECRETARÍA DE\nDESARROLLO SOCIAL Y POR LA OTRA, EL\nEJECUTIVO DEL ESTADO DE GUERRERO Y LOS\nMUNICIPIOS DE: ACAPULCO DE JUÁREZ;\nATOYAC DE ÁLVAREZ; CHILPANCINGO DE LOS\nEL PRESIDENTE MUNICIPAL DE EDUARDO NERI.\nPROFR. MODESTO PÉREZ LEYVA.\nRúbrica.\nEL PRESIDENTE MUNICIPAL DE HUITZUCO DE LOS FIGUEROA.\nC. ISIDRO MIRANDA MADRID.\nRúbrica.\nEL PRESIDENTE MUNICIPAL DE IGUALA DE LA INDEPENDENCIA.\nDR. RAÚL TOVAR TAVERA.\nRúbrica.\nEL PRESIDENTE MUNICIPAL DE ZIHUATANEJO DE AZUETA.\nING. ALEJANDRO BRAVO ABARCA.\nEL PRESIDENTE MUNICIPAL DE OMETEPEC.\nC. EFRÉN ADAME MONTALVAN.\nEL PRESIDENTE MUNICIPAL DE PETATLÁN.\nARQ. JOSÉ ALBINO LACUNZA SANTOS.\nVERTIENTE GENERAL, DEL RAMO\nADMINISTRATIVO 20 “DESARROLLO SOCIAL”,\nQUE CELEBRAN POR UNA PARTE EL EJECUTIVO\nFEDERAL, A TRAVÉS DE LA SECRETARÍA DE\nDESARROLLO SOCIAL Y POR LA OTRA, EL\nEJECUTIVO DEL ESTADO DE GUERRERO Y LOS\nMUNICIPIOS DE: ACAPULCO DE JUÁREZ;\nATOYAC DE ÁLVAREZ; CHILPANCINGO DE LOS\nEL PRESIDENTE MUNICIPAL DE PUNGARABATO.\nDR. GUSTAVO ADOLFO JUANCHI QUIÑONES.\nRúbrica.\nEL PRESIDENTE MUNICIPAL DE TAXCO DE ALARCÓN.\nL.A.E. ÁLVARO BURGOS BARRERA.\nRúbrica.\nEL PRESIDENTE MUNICIPAL DE TECPAN DE GALEANA.\nPROFR. NADIN TORRALBA MEJIA.\nEL PRESIDENTE MUNICIPAL DE TIXTLA DE GUERRERO.\nPROFR. JORGE LUIS CAMPOS ESPÍRITU.\nEL PRESIDENTE MUNICIPAL DE TLAPA DE COMONFORT.\nLIC. WILLY REYES RAMOS.\nVERTIENTE GENERAL, DEL RAMO\nADMINISTRATIVO 20 “DESARROLLO SOCIAL”,\nQUE CELEBRAN POR UNA PARTE EL EJECUTIVO\nFEDERAL, A TRAVÉS DE LA SECRETARÍA DE\nDESARROLLO SOCIAL Y POR LA OTRA, EL\nEJECUTIVO DEL ESTADO DE GUERRERO Y LOS\nMUNICIPIOS DE: ACAPULCO DE JUÁREZ;\nATOYAC DE ÁLVAREZ; CHILPANCINGO DE LOS\nAnexo I\n\"Ciudades, Zonas Metropolitanas y Polígonos Hábitat Seleccionados\"\nPrograma Hábitat, Vertiente General, correspondiente al Estado de Guerrero para el\nEjercicio Fiscal 2009\n\"LA SEDESOL\", \"EL ESTADO\" y \"LOS MUNICIPIOS\" acuerdan que los recursos del\nPrograma Hábitat se ejercerán en las ciudades, zonas metropolitanas y Polígonos\nHábitat seleccionados,\nVERTIENTE GENERAL, DEL RAMO\nADMINISTRATIVO 20 “DESARROLLO SOCIAL”,\nQUE CELEBRAN POR UNA PARTE EL EJECUTIVO\nFEDERAL, A TRAVÉS DE LA SECRETARÍA DE\nDESARROLLO SOCIAL Y POR LA OTRA, EL\nEJECUTIVO DEL ESTADO DE GUERRERO Y LOS\nMUNICIPIOS DE: ACAPULCO DE JUÁREZ;\nATOYAC DE ÁLVAREZ; CHILPANCINGO DE LOS\nCCCiiiuuudddaaaddd ooo ZZZooonnnaaa MMMuuunnniiiccciiipppiiiooo CCClllaaavvveee dddeee lllooosss PPPooolllííígggooonnnooosss\nMMMeeetttrrrooopppooollliiitttaaannnaaa\nZM Acapulco Acapulco de Juárez 12002\n12003\n12004\n12005\n12007\n12014\n12019\nAtoyac Atoyac de Álvarez 12058\n12506\nZM Acapulco Coyuca de Benítez 12511\nChilpancingo Chilpancingo de los Bravo 12023\n12025\n12026\nHuitzuco Huitzuco de los Figueroa 12063\n12064\n12065\nIguala de la Iguala de la Independencia\n12029\nIndependencia\n12031\n12033\n12034\nZihuatanejo Zihuatanejo de Azueta 12036\nOmetepec Ometepec 12059\nVERTIENTE GENERAL, DEL RAMO\nADMINISTRATIVO 20 “DESARROLLO SOCIAL”,\nQUE CELEBRAN POR UNA PARTE EL EJECUTIVO\nFEDERAL, A TRAVÉS DE LA SECRETARÍA DE\nDESARROLLO SOCIAL Y POR LA OTRA, EL\nEJECUTIVO DEL ESTADO DE GUERRERO Y LOS\nMUNICIPIOS DE: ACAPULCO DE JUÁREZ;\nATOYAC DE ÁLVAREZ; CHILPANCINGO DE LOS\n22 le a\n- ixlad r of\n11\n1111111\n11111\n22\n2222222\n22222\n00\n0000000\n55000\n55\n4444444\nLeído que fue y debidamente enterados del alcance y contenido legal, se firma el presente Anexo en la Ciudad de Chilpancingo, Guerrero a los 7 días del mes de Enero del año dos mil nueve.\nVERTIENTE GENERAL, DEL RAMO\nADMINISTRATIVO 20 “DESARROLLO SOCIAL”,\nQUE CELEBRAN POR UNA PARTE EL EJECUTIVO\nFEDERAL, A TRAVÉS DE LA SECRETARÍA DE\nDESARROLLO SOCIAL Y POR LA OTRA, EL\nEJECUTIVO DEL ESTADO DE GUERRERO Y LOS\nMUNICIPIOS DE: ACAPULCO DE JUÁREZ;\nATOYAC DE ÁLVAREZ; CHILPANCINGO DE LOS\nPOR \"LA SEDESOL\"\nEL DELEGADO FEDERAL EN EL ESTADO DE GUERRERO.\nING. LUZ ANTONIO GONZÁLEZ JUSTO.\nRúbrica.\nPOR \"EL ESTADO\"\nEL COORDINADOR GENERAL DEL EJECUTIVO ESTATAL Y DEL COPLADEG.\nLIC. HUMBERTO SARMIENTO LUEBBERT.\nRúbrica.\nEL COORDINADOR GENERAL ADJUNTO DEL COPLADEG.\nLIC. ALFONSO BECERRIL ZARCO.\nPOR \"LOS MUNICIPIOS\"\nEL PRESIDENTE MUNICIPAL DE ACAPULCO DE JUÁREZ.\nDR. MANUEL AÑORVE BAÑOS.\nEL PRESIDENTE MUNICIPAL DE ATOYAC DE ÁLVAREZ.\nC.P. CARLOS ARMANDO BELLO GÓMEZ.\nVERTIENTE GENERAL, DEL RAMO\nADMINISTRATIVO 20 “DESARROLLO SOCIAL”,\nQUE CELEBRAN POR UNA PARTE EL EJECUTIVO\nFEDERAL, A TRAVÉS DE LA SECRETARÍA DE\nDESARROLLO SOCIAL Y POR LA OTRA, EL\nEJECUTIVO DEL ESTADO DE GUERRERO Y LOS\nMUNICIPIOS DE: ACAPULCO DE JUÁREZ;\nATOYAC DE ÁLVAREZ; CHILPANCINGO DE LOS\nEL PRESIDENTE MUNICIPAL DE CHILPANCINGO DE LOS BRAVO.\nLIC. HÉCTOR ANTONIO ASTUDILLO FLORES.\nRúbrica.\nEL PRESIDENTE MUNICIPAL DE COYUCA DE BENÍTEZ.\nLIC. MERCED BALDOVINO DIEGO.\nRúbrica.\nEL PRESIDENTE MUNICIPAL DE EDUARDO NERI.\nPROFR. MODESTO PÉREZ LEYVA.\nRúbrica.\nEL PRESIDENTE MUNICIPAL DE HUITZUCO DE LOS FIGUEROA.\nC. ISIDRO MIRANDA MADRID.\nEL PRESIDENTE MUNICIPAL DE IGUALA DE LA INDEPENDENCIA.\nDR. RAÚL TOVAR TAVERA.\nEL PRESIDENTE MUNICIPAL DE ZIHUATANEJO DE AZUETA.\nING. ALEJANDRO BRAVO ABARCA.\nVERTIENTE GENERAL, DEL RAMO\nADMINISTRATIVO 20 “DESARROLLO SOCIAL”,\nQUE CELEBRAN POR UNA PARTE EL EJECUTIVO\nFEDERAL, A TRAVÉS DE LA SECRETARÍA DE\nDESARROLLO SOCIAL Y POR LA OTRA, EL\nEJECUTIVO DEL ESTADO DE GUERRERO Y LOS\nMUNICIPIOS DE: ACAPULCO DE JUÁREZ;\nATOYAC DE ÁLVAREZ; CHILPANCINGO DE LOS\nEL PRESIDENTE MUNICIPAL DE OMETEPEC.\nC. EFRÉN ADAME MONTALVAN.\nRúbrica.\nEL PRESIDENTE MUNICIPAL DE PETATLÁN.\nARQ. JOSÉ ALBINO LACUNZA SANTOS.\nRúbrica.\nEL PRESIDENTE MUNICIPAL DE PUNGARABATO.\nDR. GUSTAVO ADOLFO JUANCHI QUIÑONES.\nRúbrica.\nEL PRESIDENTE MUNICIPAL DE TAXCO DE ALARCÓN.\nL.A.E. ÁLVARO BURGOS BARRERA.\nEL PRESIDENTE MUNICIPAL DE TECPAN DE GALEANA.\nPROFR. NADIN TORRALBA MEJIA.\nEL PRESIDENTE MUNICIPAL DE TIXTLA DE GUERRERO.\nPROFR. JORGE LUIS CAMPOS ESPÍRITU.\nVERTIENTE GENERAL, DEL RAMO\nADMINISTRATIVO 20 “DESARROLLO SOCIAL”,\nQUE CELEBRAN POR UNA PARTE EL EJECUTIVO\nFEDERAL, A TRAVÉS DE LA SECRETARÍA DE\nDESARROLLO SOCIAL Y POR LA OTRA, EL\nEJECUTIVO DEL ESTADO DE GUERRERO Y LOS\nMUNICIPIOS DE: ACAPULCO DE JUÁREZ;\nATOYAC DE ÁLVAREZ; CHILPANCINGO DE LOS\nEL PRESIDENTE MUNICIPAL DE TLAPA DE COMONFORT.\nLIC. WILLY REYES RAMOS.\nVERTIENTE GENERAL, DEL RAMO\nADMINISTRATIVO 20 “DESARROLLO SOCIAL”,\nQUE CELEBRAN POR UNA PARTE EL EJECUTIVO\nFEDERAL, A TRAVÉS DE LA SECRETARÍA DE\nDESARROLLO SOCIAL Y POR LA OTRA, EL\nEJECUTIVO DEL ESTADO DE GUERRERO Y LOS\nMUNICIPIOS DE: ACAPULCO DE JUÁREZ;\nATOYAC DE ÁLVAREZ; CHILPANCINGO DE LOS\nAnexo II\n“Subsidios Federales por Municipio”\nAcuerdo de Coordinación para la Distribución y Operación de los Subsidios del\nPrograma Hábitat, Vertiente General, correspondiente al Estado de Guerrero para el Ejercicio Fiscal 2009\n“LA SEDESOL” aportará a “EL ESTADO” y, en su caso, por conducto de éste a “LOS\nMUNICIPIOS”, subsidios federales del Programa Hábitat por la cantidad de\n$86,136,946.00 (Ochenta y Seis Millones Ciento Treinta y Seis Mil Novecientos\nCuarenta y Seis Pesos 00/100 M.N.)\nSSSuuubbbsssiiidddiiiooosss aaapppooorrrtttaaadddooosss\nMMMuuunnniiiccciiipppiiiooo pppooorrr “““LLLAAA SSSEEEDDDEEESSSOOOLLL”””\nAcapulco de Juárez $ 26,602,467.00\nAtoyac de Álvarez $ 3,460,214.00\nCoyuca de Benítez $ 4,253,391.00\nChilpancingo de los Bravo $ 8,129,735.00\nHuitzuco de los Figueroa $ 4,372,451.00\nIguala de la Independencia $ 3,390,251.00\nJosé Azueta $ 4,295,961.00\nOmetepec $ 4,777,916.00\nPetatlan $ 3,000,404.00\nPungarabato $ 3,698,884.00\nTaxco de Alarcón $ 3,661,991.00\nTecpan de Galeana $ 3,037,532.00\nTixtla de Guerrero $ 3,437,974.00\nTlapa de Comonfort $ 5,384,839.00 27\nEduardo Neri $ 4,632,936.00\nTOTALES $ 86,136,946.00\nLeído que fue y debidamente enterados del alcance y contenido legal, se firma el presente Anexo en la Ciudad de Chilpancingo, Guerrero a los 28 días del mes de Enero del año dos mil nueve.\nVERTIENTE GENERAL, DEL RAMO\nADMINISTRATIVO 20 “DESARROLLO SOCIAL”,\nQUE CELEBRAN POR UNA PARTE EL EJECUTIVO\nFEDERAL, A TRAVÉS DE LA SECRETARÍA DE\nDESARROLLO SOCIAL Y POR LA OTRA, EL\nEJECUTIVO DEL ESTADO DE GUERRERO Y LOS\nMUNICIPIOS DE: ACAPULCO DE JUÁREZ;\nATOYAC DE ÁLVAREZ; CHILPANCINGO DE LOS\nPOR \"LA SEDESOL\"\nEL DELEGADO FEDERAL EN EL ESTADO DE GUERRERO.\nING. LUZ ANTONIO GONZÁLEZ JUSTO.\nRúbrica.\nPOR \"EL ESTADO\"\nEL COORDINADOR GENERAL DEL EJECUTIVO ESTATAL Y DEL COPLADEG.\nLIC. HUMBERTO SARMIENTO LUEB-BERT.\nRúbrica.\nEL COORDINADOR GENERAL ADJUNTO DEL COPLADEG.\nLIC. ALFONSO BECERRIL ZARCO.\nPOR \"LOS MUNICIPIOS\"\nEL PRESIDENTE MUNICIPAL DE ACAPULCO DE JUÁREZ.\nDR. MANUEL AÑORVE BAÑOS.\nEL PRESIDENTE MUNICIPAL DE ATOYAC DE ÁLVAREZ.\nC.P. CARLOS ARMANDO BELLO GÓMEZ.\nVERTIENTE GENERAL, DEL RAMO\nADMINISTRATIVO 20 “DESARROLLO SOCIAL”,\nQUE CELEBRAN POR UNA PARTE EL EJECUTIVO\nFEDERAL, A TRAVÉS DE LA SECRETARÍA DE\nDESARROLLO SOCIAL Y POR LA OTRA, EL\nEJECUTIVO DEL ESTADO DE GUERRERO Y LOS\nMUNICIPIOS DE: ACAPULCO DE JUÁREZ;\nATOYAC DE ÁLVAREZ; CHILPANCINGO DE LOS\nEL PRESIDENTE MUNICIPAL DE CHILPANCINGO DE LOS BRAVO.\nLIC. HÉCTOR ANTONIO ASTUDILLO FLORES.\nRúbrica.\nEL PRESIDENTE MUNICIPAL DE COYUCA DE BENÍTEZ.\nLIC. MERCED BALDOVINO DIEGO.\nRúbrica.\nEL PRESIDENTE MUNICIPAL DE EDUARDO NERI.\nPROFR. MODESTO PÉREZ LEYVA.\nRúbrica.\nEL PRESIDENTE MUNICIPAL DE HUITZUCO DE LOS FIGUEROA.\nC. ISIDRO MIRANDA MADRID.\nEL PRESIDENTE MUNICIPAL DE IGUALA DE LA INDEPENDENCIA.\nDR. RAÚL TOVAR TAVERA.\nEL PRESIDENTE MUNICIPAL DE ZIHUATANEJO DE AZUETA.\nING. ALEJANDRO BRAVO ABARCA.\nVERTIENTE GENERAL, DEL RAMO\nADMINISTRATIVO 20 “DESARROLLO SOCIAL”,\nQUE CELEBRAN POR UNA PARTE EL EJECUTIVO\nFEDERAL, A TRAVÉS DE LA SECRETARÍA DE\nDESARROLLO SOCIAL Y POR LA OTRA, EL\nEJECUTIVO DEL ESTADO DE GUERRERO Y LOS\nMUNICIPIOS DE: ACAPULCO DE JUÁREZ;\nATOYAC DE ÁLVAREZ; CHILPANCINGO DE LOS\nEL PRESIDENTE MUNICIPAL DE OMETEPEC.\nC. EFRÉN ADAME MONTALVAN.\nRúbrica.\nEL PRESIDENTE MUNICIPAL DE PETATLÁN\nARQ. JOSÉ ALBINO LACUNZA SANTOS.\nRúbrica.\nEL PRESIDENTE MUNICIPAL DE PUNGARABATO.\nDR. GUSTAVO ADOLFO JUANCHI QUIÑONES.\nRúbrica.\nEL PRESIDENTE MUNICIPAL DE TAXCO DE ALARCÓN.\nL.A.E. ÁLVARO BURGOS BARRERA.\nEL PRESIDENTE MUNICIPAL DE TECPAN DE GALEANA.\nPROFR. NADIN TORRALBA MEJIA.\nEL PRESIDENTE MUNICIPAL DE TIXTLA DE GUERRERO.\nPROFR. JORGE LUIS CAMPOS ESPÍRITU.\nVERTIENTE GENERAL, DEL RAMO\nADMINISTRATIVO 20 “DESARROLLO SOCIAL”,\nQUE CELEBRAN POR UNA PARTE EL EJECUTIVO\nFEDERAL, A TRAVÉS DE LA SECRETARÍA DE\nDESARROLLO SOCIAL Y POR LA OTRA, EL\nEJECUTIVO DEL ESTADO DE GUERRERO Y LOS\nMUNICIPIOS DE: ACAPULCO DE JUÁREZ;\nATOYAC DE ÁLVAREZ; CHILPANCINGO DE LOS\nEL PRESIDENTE MUNICIPAL DE TLAPA DE COMONFORT.\nLIC. WILLY REYES RAMOS.\nVERTIENTE GENERAL, DEL RAMO\nADMINISTRATIVO 20 “DESARROLLO SOCIAL”,\nQUE CELEBRAN POR UNA PARTE EL EJECUTIVO\nFEDERAL, A TRAVÉS DE LA SECRETARÍA DE\nDESARROLLO SOCIAL Y POR LA OTRA, EL\nEJECUTIVO DEL ESTADO DE GUERRERO Y LOS\nMUNICIPIOS DE: ACAPULCO DE JUÁREZ;\nATOYAC DE ÁLVAREZ; CHILPANCINGO DE LOS\nAnexo III\n“Aportaciones de Recursos Locales por Municipio”\nAcuerdo de Coordinación para la Distribución y Operación de los Subsidios del\nPrograma Hábitat, Vertiente General, correspondiente al Estado de Guerrero para el Ejercicio Fiscal 2009\n“EL ESTADO” y en su caso “LOS MUNICIPIOS” se comprometen a su vez a aportar recursos al Programa Hábitat por la cantidad total de $ 86,136,946.00 (Ochenta y Seis\nMillones Ciento Treinta y Seis Mil Novecientos Cuarenta y Seis Pesos 00/100 M.N.)\nRRReeecccuuurrrsssooosss RRReeecccuuurrrsssooosss aaapppooorrrtttaaadddooosss\nMMMuuunnniiiccciiipppiiiooo aaapppooorrrtttaaadddooosss pppooorrr pppooorrr “““LLLOOOSSS TTToootttaaalll dddeee rrreeecccuuurrrsssooosss\n“““EEELLL EEESSSTTTAAADDDOOO””” MMMUUUNNNIIICCCIIIPPPIIIOOOSSS”””\nAcapulco de Juárez $ 0.00 $ 26,602,467.00 $ 26,602,467.00\nAtoyac de Álvarez $ 0.00 $ 3,460,214.00 $ 3,460,214.00\nCoyuca de Benítez $ 0.00 $ 4,253,391.00 $ 4,253,391.00\nChilpancingo de los Bravo $ 0.00 $ 8,129,735.00 $ 8,129,735.00\nHuitzuco de los Figueroa $ 0.00 $ 4,372,451.00 $ 4,372,451.00\nIguala de la Independencia $ 0.00 $ 3,390,251.00 $ 3,390,251.00\nZihuatanejo de Azueta $ 0.00 $ 4,295,961.00 $ 4,295,961.00\nOmetepec $ 0.00 $ 4,777,916.00 $ 4,777,916.00\nPetatlan $ 0.00 $ 3,000,404.00 $ 3,000,404.00\nPungarabato $ 0.00 $ 3,698,884.00 $ 3,698,884.00\nTaxco de Alarcón $ 0.00 $ 3,661,991.00 $ 3,661,991.00\nTecpan de Galeana $ 0.00 $ 3,037,532.00 $ 3,037,532.00\nTixtla de Guerrero $ 0.00 $ 3,437,974.00 $ 3,437,974.00\nTlapa de Comonfort $ 0.00 $ 5,384,839.00 $ 5,384,839.00\nEduardo Neri $ 0.00 $ 4,632,936.00 $ 4,632,936.00 32\nTOTALES $ 0.00 $ 86,136,946.00 $ 86,136,946.00\nVERTIENTE GENERAL, DEL RAMO\nADMINISTRATIVO 20 “DESARROLLO SOCIAL”,\nQUE CELEBRAN POR UNA PARTE EL EJECUTIVO\nFEDERAL, A TRAVÉS DE LA SECRETARÍA DE\nDESARROLLO SOCIAL Y POR LA OTRA, EL\nEJECUTIVO DEL ESTADO DE GUERRERO Y LOS\nMUNICIPIOS DE: ACAPULCO DE JUÁREZ;\nATOYAC DE ÁLVAREZ; CHILPANCINGO DE LOS\nLeído que fue y debidamente enterados del alcance y contenido legal, se firma el presente Anexo en la Ciudad de Chilpancingo, Guerrero a los 7 días del mes de Enero del año dos mil nueve.\nPOR \"LA SEDESOL\"\nEL DELEGADO FEDERAL EN EL ESTADO DE GUERRERO.\nING. LUZ ANTONIO GONZÁLEZ JUSTO.\nRúbrica.\nPOR \"EL ESTADO\"\nEL COORDINADOR GENERAL DEL EJECUTIVO ESTATAL Y DEL COPLADEG.\nLIC. HUMBERTO SARMIENTO LUEBBERT.\nEL COORDINADOR GENERAL ADJUNTO DEL COPLADEG.\nLIC. ALFONSO BECERRIL ZARCO.\nPOR \"LOS MUNICIPIOS\"\nEL PRESIDENTE MUNICIPAL DE ACAPULCO DE JUÁREZ.\nDR. MANUEL AÑORVE BAÑOS.\nVERTIENTE GENERAL, DEL RAMO\nADMINISTRATIVO 20 “DESARROLLO SOCIAL”,\nQUE CELEBRAN POR UNA PARTE EL EJECUTIVO\nFEDERAL, A TRAVÉS DE LA SECRETARÍA DE\nDESARROLLO SOCIAL Y POR LA OTRA, EL\nEJECUTIVO DEL ESTADO DE GUERRERO Y LOS\nMUNICIPIOS DE: ACAPULCO DE JUÁREZ;\nATOYAC DE ÁLVAREZ; CHILPANCINGO DE LOS\nEL PRESIDENTE MUNICIPAL DE ATOYAC DE ÁLVAREZ.\nC.P. CARLOS ARMANDO BELLO GÓMEZ.\nRúbrica.\nEL PRESIDENTE MUNICIPAL DE CHILPANCINGO DE LOS BRAVO.\nLIC. HÉCTOR ANTONIO ASTUDILLO FLORES.\nRúbrica.\nEL PRESIDENTE MUNICIPAL DE COYUCA DE BENÍTEZ.\nLIC. MERCED BALDOVINO DIEGO.\nRúbrica.\nEL PRESIDENTE MUNICIPAL DE EDUARDO NERI.\nPROFR. MODESTO PÉREZ LEYVA.\nEL PRESIDENTE MUNICIPAL DE HUITZUCO DE LOS FIGUEROA.\nC. ISIDRO MIRANDA MADRID.\nEL PRESIDENTE MUNICIPAL DE IGUALA DE LA INDEPENDENCIA.\nDR. RAÚL TOVAR TAVERA.\nVERTIENTE GENERAL, DEL RAMO\nADMINISTRATIVO 20 “DESARROLLO SOCIAL”,\nQUE CELEBRAN POR UNA PARTE EL EJECUTIVO\nFEDERAL, A TRAVÉS DE LA SECRETARÍA DE\nDESARROLLO SOCIAL Y POR LA OTRA, EL\nEJECUTIVO DEL ESTADO DE GUERRERO Y LOS\nMUNICIPIOS DE: ACAPULCO DE JUÁREZ;\nATOYAC DE ÁLVAREZ; CHILPANCINGO DE LOS\nEL PRESIDENTE MUNICIPAL DE ZIHUATANEJO DE AZUETA.\nING. ALEJANDRO BRAVO ABARCA.\nRúbrica.\nEL PRESIDENTE MUNICIPAL DE OMETEPEC.\nC. EFRÉN ADAME MONTALVAN.\nRúbrica.\nEL PRESIDENTE MUNICIPAL DE PETATLÁN\nARQ. JOSÉ ALBINO LACUNZA SANTOS.\nRúbrica.\nEL PRESIDENTE MUNICIPAL DE PUNGARABATO.\nDR. GUSTAVO ADOLFO JUANCHI QUIÑONES.\nEL PRESIDENTE MUNICIPAL DE TAXCO DE ALARCÓN.\nL.A.E. ÁLVARO BURGOS BARRERA.\nEL PRESIDENTE MUNICIPAL DE TECPAN DE GALEANA.\nPROFR. NADIN TORRALBA MEJIA.\nVERTIENTE GENERAL, DEL RAMO\nADMINISTRATIVO 20 “DESARROLLO SOCIAL”,\nQUE CELEBRAN POR UNA PARTE EL EJECUTIVO\nFEDERAL, A TRAVÉS DE LA SECRETARÍA DE\nDESARROLLO SOCIAL Y POR LA OTRA, EL\nEJECUTIVO DEL ESTADO DE GUERRERO Y LOS\nMUNICIPIOS DE: ACAPULCO DE JUÁREZ;\nATOYAC DE ÁLVAREZ; CHILPANCINGO DE LOS\nEL PRESIDENTE MUNICIPAL DE TIXTLA DE GUERRERO.\nPROFR. JORGE LUIS CAMPOS ESPÍRITU.\nRúbrica.\nEL PRESIDENTE MUNICIPAL DE TLAPA DE COMONFORT.\nLIC. WILLY REYES RAMOS.\nRúbrica.\nEL SUSCRITO ING. LUZ ANTONIO GONZALEZ JUSTO, DELEGADO DE LA\nSECRETARIA DE DESARROLLO SOCIAL EN EL ESTADO DE GUERRERO, CON\nFUNDAMENTO EN LOS ARTICULOS 2, 36, 44 Y 45 DEL REGLAMENTO INTERIOR DE\nLA PROPIA DEPENDENCIA, PUBLICADO EN EL DIARIO OFICIAL DE LA\nFEDERACION CON FECHA 19 DE JULIO DE 2004, Y REFORMADO POR DECRETO\nUTILES IMPRESAS POR EL ANVERSO, COINCIDE EN TODAS Y CADA UNA DE SUS\nPARTES, CON EL ORIGINAL QUE SE TUVO A LA VISTA Y QUE OBRA EN LOS\nARCHIVOS DE ESTA DELEGACION ESTATAL A MI CARGO, MISMO QUE CERTIFICO\nPARA LOS EFECTOS LEGALES CORRESPONDIENTES.\nCHILPANCINGO, GUERRERO, A VEINTE DE ABRIL DEL AÑO DOS MIL NUEVE.",
  "ordenamiento": "ACUERDO",
  "jurisdiccion": "GUERRERO",
  "fuente_oficial": "DIARIO OFICIAL DE LA FEDERACION",
  "Fecha de Publicación": "31 DE DICIEMBRE DE 2009",
  "ULTIMA REFORMA PUBLICADA": "15 de Mayo de 2009",
  "status": "ABROGADA",
  "es_escaneado": false,
  "tiene_tablas": false,
  "materia": [
    "general"
  ]
}