{
  "titulo": "Acuerdo 029SE10 10 2014, Mediante el Cual Se Aprueba la Creación E Integración de las Comisiones Esp",
  "Contenido": "CIUDADANA USOS Y COSTUMBRES, VOTO EN EL\nEXTRANJERO Y DEL DIPUTADO MIGRANTE; PARA\nLA GESTIÓN Y ADQUISICIÓN DE INMUEBLE PROPIO\nY SEGURIDAD SOCIAL DE LOS TRABAJADORES DEL\nINSTITUTO ELECTORAL Y DE PARTICIPACIÓN\nCIUDADANA DEL ESTADO DE GUERRERO; Y DE\nVINCULACIÓN CON LA AUTORIDAD NACIONAL\nELECTORAL\nTEXTO ORIGINAL.\nAcuerdo Publicado en el Periódico Oficial del Gobierno del Estado No.91, el Viernes 14 de\nNoviembre de 2014.\nINSTITUTO ELECTORAL Y DE PARTICIPACION CIUDADANA DEL ESTADO DE GUERRERO\nAL MARGEN UN SELLO CON EL ESTADO DE GUERRERO Y UNA LEYENDA QUE DICE:\n\"INSTITUTO ELECTORAL\":\nINSTITUTO ELECTORAL Y DE PARTICIPACIÓN CIUDADANA DEL ESTADO\nACUERDO 029/SE/10-10-2014\nMEDIANTE EL CUAL SE APRUEBA LA CREACIÓN E INTEGRACIÓN DE LAS COMISIONES\nESPECIALES: DE PARTICIPACIÓN CIUDADANA USOS Y COSTUMBRES, VOTO EN EL\nEXTRANJERO Y DEL DIPUTADO MIGRANTE; PARA LA GESTIÓN Y ADQUISICIÓN DE INMUEBLE\nPROPIO Y SEGURIDAD SOCIAL DE LOS TRABAJADORES DEL INSTITUTO ELECTORAL Y DE\nPARTICIPACIÓN CIUDADANA DEL ESTADO DE GUERRERO; Y DE VINCULACIÓN CON LA\nAUTORIDAD NACIONAL ELECTORAL.\nANTECEDENTES\n1. El 10 de febrero de 2014, fueron publicadas en el Diario Oficial de la Federación, las reformas a la Constitución Política de los Estados Unidos Mexicanos en materia-política electoral, en la que se establecieron nuevas reglas para la organización de las elecciones federales y locales, como es la realice junto con la federal; la creación del Instituto Nacional Electoral que se encargará de la ubicación e integración de la casilla única en ocasión de los procesos electorales concurrentes, la designación y remoción de los consejeros electorales del órgano electoral local; así como la atribución del Senado de la\nRepública para designar a los magistrados del Tribunal Electoral del Estado, entre otros.\nInstituciones y Procedimientos Electorales, la Ley General de Partidos Políticos y la Ley General en\nMateria de Delitos Electorales, que vinieron a complementar y reglamentar las reformas realizadas a la\nCIUDADANA USOS Y COSTUMBRES, VOTO EN EL\nEXTRANJERO Y DEL DIPUTADO MIGRANTE; PARA\nLA GESTIÓN Y ADQUISICIÓN DE INMUEBLE PROPIO\nY SEGURIDAD SOCIAL DE LOS TRABAJADORES DEL\nINSTITUTO ELECTORAL Y DE PARTICIPACIÓN\nCIUDADANA DEL ESTADO DE GUERRERO; Y DE\nVINCULACIÓN CON LA AUTORIDAD NACIONAL\nELECTORAL\n3. Por Decreto número 453 publicado en el Periódico Oficial del Gobierno del Estado de fecha 29 de abril de 2014, se hicieron del conocimiento las reformas y adiciones realizadas de forma integral a la constitucionales federales en materia política-electoral.\n4. El 30 de junio de 2014, se publicó en el Periódico Oficial del Gobierno del Estado la Ley número 483 de Instituciones y Procedimientos Electorales del Estado, aprobada por la LX Legislatura del\nH. Congreso del Estado, en estricto acatamiento a las reformas constitucionales y legales en la materia.\n5. De la misma forma, se reformaron la Ley del Sistema de Medios de Impugnación en Materia\nElectoral del Estado, la Ley Orgánica del Tribunal Electoral, la Ley Orgánica del Municipio Libre, entre otras, en las que se destaca la armonización de las leyes generales con las locales de la materia; y\nCONSIDERANDO garantiza la autonomía e independencia de los órganos autónomos y sus integrantes, los cuales deberán observar como principios rectores en su actuación los de: certeza, legalidad, imparcialidad, objetividad, eficiencia, racionalidad presupuestaria, profesionalismo, responsabilidad, transparencia, máxima publicidad y rendición de cuentas, así como aquellos principios consustanciales a su específica función, en el marco de las leyes orgánicas y secundarias respectivas. Asimismo, los citados órganos autónomos tienen a su cargo el ejercicio de funciones públicas del Estado dirigidas a garantizar:\n1) La protección de los derechos humanos;\n2) La transparencia, el acceso a la información pública y la protección de datos personales;\n3) La organización de las elecciones y demás mecanismos de participación ciudadana;\n4) La protección de los derechos político-electorales, la constitucionalidad y legalidad de los actos y resoluciones en materia electoral;\n5) La constitucionalidad y legalidad de los actos de la administración pública; y,\n6) La investigación de los delitos, persecución de los delincuentes, y el derecho a ejercer la acción penal.\nCIUDADANA USOS Y COSTUMBRES, VOTO EN EL\nEXTRANJERO Y DEL DIPUTADO MIGRANTE; PARA\nLA GESTIÓN Y ADQUISICIÓN DE INMUEBLE PROPIO\nY SEGURIDAD SOCIAL DE LOS TRABAJADORES DEL\nINSTITUTO ELECTORAL Y DE PARTICIPACIÓN\nCIUDADANA DEL ESTADO DE GUERRERO; Y DE\nVINCULACIÓN CON LA AUTORIDAD NACIONAL\nELECTORAL\nII. Que el artículo 175 de la Ley 483 de Instituciones y Procedimientos Electorales del Estado, dispone que el Instituto Electoral, es un organismo público autónomo, de carácter permanente, independiente en sus decisiones y funcionamiento, con personalidad jurídica y patrimonio propio, responsable de vigilar el cumplimiento de las disposiciones constitucionales y reglamentarias en materia electoral; así como de velar porque los principios de certeza, legalidad, independencia, imparcialidad, máxima publicidad y objetividad, guíen las actividades de los organismos electorales; encargado de coordinar, preparar, desarrollar y vigilar los procesos electorales estatales y municipales, ordinarios y extraordinarios, así como los procesos de participación ciudadana, en los términos de la legislación aplicable.\nIII. Que los artículos 177, inciso a), 188, fracciones I, II, III, LXXII y LXXXI, 271, último párrafo, del ordenamiento legal antes mencionado, establecen que corresponde al Instituto Electoral y de\nParticipación Ciudadana del Estado de Guerrero, aplicar las disposiciones generales, reglas, lineamientos, criterios y formatos, que en ejercicio de sus facultades le confieren las constituciones políticas Federal y Local, las leyes de la materia y el Instituto Nacional Electoral; vigilar el cumplimiento de dichas legislaciones y las disposiciones que con base en ella se dicten; aclarar las dudas que se susciten con motivo de la interpretación y aplicación de la Ley y demás disposiciones relativas; expedir los reglamentos necesarios para el buen funcionamiento del Instituto Electoral y para el adecuado ejercicio de sus atribuciones y funciones, originarias o delegadas; aprobar los ajustes necesarios a los plazos establecidos en la ley, a fin de garantizar los plazos de solicitud de registro de candidatos y que la duración de las campañas se ciña a lo establecido en la misma y en la Constitución del Estado.\nIV.- A su vez el artículo 180 de la Ley Electoral establece que el Consejo General del Instituto\nElectoral, es un órgano de dirección superior, responsable de vigilar el cumplimiento de las disposiciones constitucionales y legales en materia electoral, así como de velar porque los principios de certeza, legalidad, independencia, imparcialidad, máxima publicidad y objetividad, guíen todas las actividades del instituto electoral y de participación ciudadana.\nV.- Asimismo, el artículo 184 de la Ley Electoral que se viene invocando dispone que el Consejo\nGeneral del Instituto electoral, independientemente de las comisiones permanentes establecidas en el artículo 192 de esta Ley, integrará las comisiones que considere necesarias para el desempeño de sus atribuciones, con el número de miembros que para cada caso acuerde, que siempre serán presididas por un consejero electoral.\nCIUDADANA USOS Y COSTUMBRES, VOTO EN EL\nEXTRANJERO Y DEL DIPUTADO MIGRANTE; PARA\nLA GESTIÓN Y ADQUISICIÓN DE INMUEBLE PROPIO\nY SEGURIDAD SOCIAL DE LOS TRABAJADORES DEL\nINSTITUTO ELECTORAL Y DE PARTICIPACIÓN\nCIUDADANA DEL ESTADO DE GUERRERO; Y DE\nVINCULACIÓN CON LA AUTORIDAD NACIONAL\nELECTORAL\nVI.-De conformidad con lo que establece el artículo 188 fracción LI de la multicitada Ley\nElectoral, el Consejo General del Instituto Electoral tiene las atribuciones entre otras, la de aprobar la integración de las comisiones y de los comités del Instituto Electoral.\nVII.- El artículo 193 de la precitada Ley Electoral estable entre otras cosas que las comisiones serán integradas con un máximo de tres consejeros electorales con voz y voto, quienes podrán participar hasta en tres de las comisiones permanentes por un periodo de tres años, la presidencia será rotativa de forma anual entre sus integrantes; además se podrán integrar las comisiones especiales que se consideren necesarias para el desempeño de las atribuciones del Consejo General del Instituto Electoral, integrándose con el número de miembros que acuerde el mismo Consejo; en todos los asuntos que les encomienden, las comisiones deberán presentar al Consejo General del Instituto un informe, dictamen o proyecto de resolución, según el caso dentro del plazo que determine la Ley o el Consejo General.\nVIII.- En consideración de que el día once de octubre de la presente anualidad, dará inicio formal el proceso electoral para elegir al Gobernador del Estado, Diputados Locales y Ayuntamientos, resulta imprescindible que el Instituto Electoral y de Participación Ciudadana del Estado de Guerrero, cuente con la estructura organizacional adecuada con la finalidad de que realice las atribuciones encomendadas por la legislación electoral de la mejor manera posible, con el objetivo de que el proceso electoral se lleve a cabo en una convivencia armónica de todos los actores y partidos políticos que en el intervienen, garantizando equidad en su desarrollo y reconocimiento de los resultados que cada partido político obtenga en la jornada electoral, bajo este contexto en reunión de trabajo celebrada el cuatro de octubre del año en curso, por los integrantes del Consejo General, se integraron las comisiones especiales del\nInstituto Electoral y de Participación Ciudadana del Estado de Guerrero, habiéndose incorporado en cada una de las comisiones los representantes de los partidos políticos que así lo determinaron, quedando integradas en la forma y términos siguientes:\nESPECIAL DE PARTICIPACIÓN CIUDADANA, USOS Y COSTUMBRES, VOTO EN EL EXTRANJERO\nY DEL DIPUTADO MIGRANTE.\nConsejeros:\n1.- C. Felipe Arturo Sánchez Miranda (Preside)\n2.- C. Marisela Reyes Reyes\n3.- C. Alma Delia Eugenio Alcaráz\n4.- C. Rosio Calleja Niño\n5.- C. Jorge Valdez Méndez\n6.- C. Leticia Martínez Velázquez\nCIUDADANA USOS Y COSTUMBRES, VOTO EN EL\nEXTRANJERO Y DEL DIPUTADO MIGRANTE; PARA\nLA GESTIÓN Y ADQUISICIÓN DE INMUEBLE PROPIO\nY SEGURIDAD SOCIAL DE LOS TRABAJADORES DEL\nINSTITUTO ELECTORAL Y DE PARTICIPACIÓN\nCIUDADANA DEL ESTADO DE GUERRERO; Y DE\nVINCULACIÓN CON LA AUTORIDAD NACIONAL\nELECTORAL\n7.- C. René Vargas Pineda\n8.- C. Carlos Alberto Villalpando Milián (Secretario Ejecutivo)\n9.- C. Alberto Granda Villalba (Secretario Técnico)\nPartidos Políticos:\nPartido Acción Nacional\nPartido de la Revolución Democrática\nPartido Revolucionario Institucional\nPartido del Trabajo\nPartido Verde Ecologista de México\nPartido Nueva Alianza\nPartido Movimiento Ciudadano.\nPartido Morena\nPartido Humanista\nPartido Encuentro Social\nPartido de los Pobres de Guerrero\nEsta comisión tendrá las atribuciones siguientes:\n1. Elaborar lineamientos relativos a la preparación, desarrollo de la votación, y declaración de los resultados de los procedimientos de Referéndum y Plebiscito;\n2. Elaborar los proyectos de Convocatoria para la realización de los procesos de Referéndum y\nPlebiscito, así como para la elección de los Comités Ciudadanos;\n3. Proponer al Consejo General las preguntas conforme a las que los electores expresarán su aprobación o rechazo de las consultas;\n4. Proponer convenios de apoyo y colaboración con instituciones de educación superior o de preguntas;\n5. Presentar los dictámenes de aprobación o rechazo de las solicitudes de Referéndum o\nPlebiscito dentro de los plazos establecidos en la Ley de Participación Ciudadana;\nCIUDADANA USOS Y COSTUMBRES, VOTO EN EL\nEXTRANJERO Y DEL DIPUTADO MIGRANTE; PARA\nLA GESTIÓN Y ADQUISICIÓN DE INMUEBLE PROPIO\nY SEGURIDAD SOCIAL DE LOS TRABAJADORES DEL\nINSTITUTO ELECTORAL Y DE PARTICIPACIÓN\nCIUDADANA DEL ESTADO DE GUERRERO; Y DE\nVINCULACIÓN CON LA AUTORIDAD NACIONAL\nELECTORAL\n6. Elaborar lineamientos a que se sujetará el proceso para la organización de la elección de los\nComités Ciudadanos;\n7. Proponer el Catálogo de las colonias, ciudades o de los lugares correspondientes a las demarcaciones territoriales;\n8. Proponer convenios de apoyo y colaboración con las instituciones afines a efecto de establecer las demarcaciones territoriales;\n9. Elaborar el calendario de actividades del proceso de elección de los Comités Ciudadanos;\n10. Dictaminar las controversias que se generen con motivo de la organización del proceso de elección en cualesquiera de sus etapas;\n11. Cuando así se requiera, gestionar estudios antropológicos y socioeconómicos de los municipios en que existan comunidades indígenas;\n12. Proponer al Consejo General las bases para llevar a cabo la elección de representantes u órganos de gobierno, por usos y costumbres, en atención a las solicitudes que se presenten;\n13. Fomentar la cultura democrática en las elecciones por usos y costumbres;\n14. Elaborar propuestas que coadyuven y fomenten la elección por usos y costumbres;\n15. Vigilar el cumplimiento de los lineamientos que emite el Instituto Nacional Electoral para garantizar el derecho al voto de los ciudadanos mexicanos residentes en el extranjero;\n16. Vigilar que lo que concierne al Instituto Electoral y de Participación Ciudadana del Estado de\nElectorales, se realice en términos de Ley;\n17. Vigilar que la asignación del Diputado Migrante o Binacional se realice en los términos en que se refieren los dos últimos párrafos del artículo 17; así como del numeral 18 de la Ley número 483 de\nInstituciones y Procedimientos Electorales del Estado y;\n18. Las demás que sean afines a la naturaleza de la Comisión.\nCIUDADANA USOS Y COSTUMBRES, VOTO EN EL\nEXTRANJERO Y DEL DIPUTADO MIGRANTE; PARA\nLA GESTIÓN Y ADQUISICIÓN DE INMUEBLE PROPIO\nY SEGURIDAD SOCIAL DE LOS TRABAJADORES DEL\nINSTITUTO ELECTORAL Y DE PARTICIPACIÓN\nCIUDADANA DEL ESTADO DE GUERRERO; Y DE\nVINCULACIÓN CON LA AUTORIDAD NACIONAL\nELECTORAL\nESPECIAL PARA LA GESTIÓN Y ADQUISICIÓN DE INMUEBLE PROPIO Y DE SEGURIDAD SOCIAL\nDE LOS TRABAJADORES DEL IEPC.\nConsejeros:\n1.- C. Marisela Reyes Reyes (preside)\n2.- C. Alma Delia Eugenio Alcaráz\n3.- C. Rosio Calleja Niño\n4.- C. Jorge Valdez Méndez\n5.- C. Leticia Martínez Velázquez\n6.- C. René Vargas Pineda\n7.- C. Felipe Arturo Sánchez Miranda\n8.- C. Carlos Alberto Villalpando Milián (Secretario Ejecutivo)\n9.- Dirección Ejecutiva de Administración (Secretario técnico)\nPartidos Políticos:\nPartido Acción Nacional\nPartido de la Revolución Democrática\nPartido Revolucionario Institucional\nPartido del Trabajo\nPartido Verde Ecologista de México\nPartido Nueva Alianza\nPartido Movimiento Ciudadano.\nPartido Morena\nPartido Humanista\nPartido Encuentro Social\nPartido de los Pobres de Guerrero\nEsta comisión tendrá las siguientes atribuciones:\n1.- Elaborar el plan de trabajo de la comisión;\n2.- Elaborar el proyecto de presupuesto de la comisión para los fines para los cuales fue creada e incorporarlos al proyecto del presupuesto del Instituto Electoral;\n3.- Dar seguimiento a las gestiones que se realicen para la adquisición del inmueble para la construcción del Edificio del Instituto electoral;\nCIUDADANA USOS Y COSTUMBRES, VOTO EN EL\nEXTRANJERO Y DEL DIPUTADO MIGRANTE; PARA\nLA GESTIÓN Y ADQUISICIÓN DE INMUEBLE PROPIO\nY SEGURIDAD SOCIAL DE LOS TRABAJADORES DEL\nINSTITUTO ELECTORAL Y DE PARTICIPACIÓN\nCIUDADANA DEL ESTADO DE GUERRERO; Y DE\nVINCULACIÓN CON LA AUTORIDAD NACIONAL\nELECTORAL\n4.- Informar periódicamente al Consejo General del avance de las gestiones que se realicen para la adquisición del inmueble;\n5.- Realizar visitas a Institutos Electorales del país a fin de contar con una mejor ilustración y propuestas para la construcción del edificio del Instituto, y\n6.- Elaborar convenios de colaboración con Instituciones de Educación Superior a fin de que elaboren la maqueta relativa al proyecto del edificio del Instituto y;\n7.- Vigilar que el personal del Instituto Electoral sea incorporado al Instituto Mexicano del Seguro\nSocial con la finalidad de garantizarles los beneficios que dicha institución ofrece a sus afiliados y;\n8.- Las demás que sean afines a la naturaleza de la Comisión.\nESPECIAL DE VINCULACIÓN CON LA AUTORIDAD NACIONAL ELECTORAL.\nConsejeros:\n1.- C. Felipe Arturo Sánchez Miranda (preside)\n2.- C. Marisela Reyes Reyes\n3.- C. Alma Delia Eugenio Alcaráz\n4.- C. Rosio Calleja Niño\n5.- C. Jorge Valdez Méndez\n6.- C. Leticia Martínez Velázquez\n7.- C. René Vargas Pineda\n8.- C. Carlos Alberto Villalpando Milián (Secretario técnico)\nPartidos Políticos:\nPartido Acción Nacional\nPartido de la Revolución Democrática\nPartido Revolucionario Institucional\nPartido del Trabajo\nPartido Nueva Alianza\nPartido Movimiento Ciudadano.\nPartido Morena\nPartido Humanista\nCIUDADANA USOS Y COSTUMBRES, VOTO EN EL\nEXTRANJERO Y DEL DIPUTADO MIGRANTE; PARA\nLA GESTIÓN Y ADQUISICIÓN DE INMUEBLE PROPIO\nY SEGURIDAD SOCIAL DE LOS TRABAJADORES DEL\nINSTITUTO ELECTORAL Y DE PARTICIPACIÓN\nCIUDADANA DEL ESTADO DE GUERRERO; Y DE\nVINCULACIÓN CON LA AUTORIDAD NACIONAL\nELECTORAL\nPartido Encuentro Social\nPartido de los Pobres de Guerrero\nEsta comisión tendrá las siguientes atribuciones:\n1.- Someter a la consideración del Consejo General los mecanismos de coordinación y de vinculación con el Instituto Nacional Electoral, para el debido ejercicio de sus atribuciones.\n2.- Proponer las disposiciones generales y lineamientos de observancia para las áreas del\nInstituto, referentes a la ejecución de programas con el Instituto Nacional Electoral y someterlas a la aprobación del Consejo General.\n3.- Informar al Consejo General sobre la vinculación, coordinación y seguimiento a las disposiciones generales, reglas, lineamientos y criterios que establezca el Instituto Nacional Electoral, así como de los informes recibidos de los Consejos Distritales Electorales referentes a la supervisión sobre el cumplimiento de actividades con motivo del proceso electoral.\n4.- Coordinar la elaboración de acuerdos de coordinación con el Instituto Nacional Electoral para dar cumplimiento a las disposiciones legales vigentes.\n5.- Elaborar el plan anual de trabajo de la comisión.\n6.- Establecer los mecanismos de coordinación con la Unidad Técnica de Vinculación del\nInstituto Nacional Electoral y;\n7.- Las demás que sean afines a la naturaleza de la Comisión.\nPor lo anteriormente expuesto y con fundamento en lo que disponen los artículos 175, 177, 180, 184, 188 fracción LI y 193 de la Ley número 483 de Instituciones y Procedimientos Electorales del Estado de Guerrero, es procedente legalmente emitir el siguiente:\nPRIMERO.- Se aprueba la integración de las comisiones especiales integradas en la forma y términos establecidos en el último considerando del presente acuerdo.\nCIUDADANA USOS Y COSTUMBRES, VOTO EN EL\nEXTRANJERO Y DEL DIPUTADO MIGRANTE; PARA\nLA GESTIÓN Y ADQUISICIÓN DE INMUEBLE PROPIO\nY SEGURIDAD SOCIAL DE LOS TRABAJADORES DEL\nINSTITUTO ELECTORAL Y DE PARTICIPACIÓN\nCIUDADANA DEL ESTADO DE GUERRERO; Y DE\nVINCULACIÓN CON LA AUTORIDAD NACIONAL\nELECTORAL\nSEGUNDO.- Las comisiones deberán realizar las atribuciones que se especifican en la parte final de cada una de la integración de dichas comisiones; así como las demás que sean afines a cada comisión.\nTERCERO.- Las comisiones deberán informar anualmente al Consejo General respecto de las actividades realizadas en cumplimiento al plan de trabajo previamente propuesto, en el que deberán señalar sus objetivos y metas a alcanzar, así como los requerimientos técnicos y económicos para el desarrollo de sus actividades.\nCUARTO.- Publíquese el presente acuerdo en el Periódico Oficial del Gobierno del Estado en términos que establece el artículo 189 fracción V de la Ley número 483 de Instituciones y Procedimientos\nElectorales del Estado de Guerrero.\nSe notifica a los representantes de los partidos políticos acreditados ante este órgano electoral, en términos de lo dispuesto por el artículo 34 de la Ley del Sistema de Medios de Impugnación en\nMateria Electoral del Estado de Guerrero.\nEl presente acuerdo fue aprobado por unanimidad de votos en la Séptima Sesión Extraordinaria celebrada el día diez de octubre del año dos mil catorce, por el Pleno del Consejo General del Instituto\nElectoral y de Participación Ciudadana del Estado de Guerrero.\nPARTICIPACIÓN CIUDADANA DEL ESTADO DE GUERRERO.\nC. MARISELA REYES REYES.\nRúbrica.\nSECRETARIO EJECUTIVO.\nC. CARLOS ALBERTO VILLALPANDO MILIÁN.\nRúbrica.",
  "ordenamiento": "ACUERDO",
  "jurisdiccion": "GUERRERO",
  "fuente_oficial": "DIARIO OFICIAL DE LA FEDERACION",
  "Fecha de Publicación": "14 de \nNoviembre de 2014",
  "ULTIMA REFORMA PUBLICADA": null,
  "status": "VIGENTE",
  "es_escaneado": false,
  "tiene_tablas": false,
  "materia": [
    "general"
  ]
}