{
  "titulo": "Acuerdo por el Que Se Deroga el Formato de Declaración de Pago de Impuestos del Régimen de Pequeños",
  "Contenido": "Y SE EMITE EL NUEVO FORMATO DE “DECLARACIÓN DE PAGO\nDE IMPUESTOS DEL RÉGIMEN DE PEQUEÑOS\nCONTRIBUYENTES SFA 03” Y SE EMITEN LAS “TABLAS DEL\nPAGO BIMESTRAL DEL IMPUESTO SOBRE LA RENTA, IMPUESTO\nAL VALOR AGREGADO E IMPUESTO EMPRESARIAL A TASA\nÚNICA DE LOS CONTRIBUYENTES” PARA EL EJERCICIO FISCAL\n2008\nABROGADO POR EL ARTÍCULO SEGUNDO DEL ACUERDO POR EL QUE SE ACTUALIZAN\nLAS “TABLAS PARA LA DETERMINACIÓN DE LA CUOTA FIJA INTEGRADA PARA EL PAGO\nBIMESTRAL DEL IMPUESTO SOBRE LA RENTA, IMPUESTO AL VALOR AGREGADO E IMPUESTO\nEMPRESARIAL A TASA ÚNICA DE LOS CONTRIBUYENTES DEL RÉGIMEN DE PEQUEÑOS\nCONTRIBUYENTES” PARA EL EJERCICIO FISCAL 2013; PUBLICADO EN EL PERIÓDICO OFICIAL\nDEL GOBIERNO DEL ESTADO No. 54 ALCANCE I, EL VIERNES 05 DE JULIO DE 2013.\nTEXTO ORIGINAL.\nAcuerdo publicado en el Periódico Oficial del Gobierno del Estado No. 45, el Martes 03 de Junio de 2008.\nACUERDO POR EL QUE SE DEROGA EL FORMATO DE \"DECLARACIÓN DE PAGO DE\nIMPUESTOS DEL RÉGIMEN DE PEQUEÑOS CONTRIBUYENTES SFA- 03\" PUBLICADO EN EL\nPERIÓDICO OFICIAL DEL GOBIERNO DEL ESTADO DE GUERRERO NÚMERO 90 DE FECHA 10 DE\nNOVIEMBRE DE 2006, Y SE EMITE EL NUEVO FORMATO DE \"DECLARACIÓN DE PAGO DE\nIMPUESTOS DEL RÉGIMEN DE PEQUEÑOS CONTRIBUYENTES SFA-03\" Y SE EMITEN LAS\n\"TABLAS PARA LA DETERMINACIÓN DE LA CUOTA FIJA INTEGRADA PARA EL PAGO\nBIMESTRAL DEL IMPUESTO SOBRE LA RENTA, IMPUESTO AL VALOR AGREGADO E IMPUESTO\nEMPRESARIAL A TASA ÚNICA DE LOS CONTRIBUYENTES DEL RÉGIMEN DE PEQUEÑOS\nCONTRIBUYENTES\" PARA EL EJERCICIO DE 2008.\nC.P. CARLOS ZEFERINO TORREBLANCA GALINDO, GOBERNADOR CONSTITUCIONAL\nARTÍCULOS 2° Y 6° DE LA LEY ORGÁNICA DE LA ADMINISTRACIÓN PÚBLICA DEL ESTADO DE\nGUERRERO NÚMERO 433.\nY SE EMITE EL NUEVO FORMATO DE “DECLARACIÓN DE PAGO\nDE IMPUESTOS DEL RÉGIMEN DE PEQUEÑOS\nCONTRIBUYENTES SFA 03” Y SE EMITEN LAS “TABLAS DEL\nPAGO BIMESTRAL DEL IMPUESTO SOBRE LA RENTA, IMPUESTO\nAL VALOR AGREGADO E IMPUESTO EMPRESARIAL A TASA\nÚNICA DE LOS CONTRIBUYENTES” PARA EL EJERCICIO FISCAL\n2008\nQue el Gobierno del Estado signó el 28 de diciembre de 1996, el Convenio de Colaboración\nAdministrativa en Materia Fiscal Federal con el Gobierno Federal por conducto de la Secretaría de\nHacienda y Crédito Público, en vigor a partir del 1 de enero de 1997.\nQue en el contexto de la Ley de Coordinación Fiscal se estableció la posibilidad de coadyuvar en el combate al comercio informal a través de la promoción de la colaboración administrativa de la autoridades locales y del Distrito Federal, en la incorporación al Registro Federal de Contribuyentes de las personas que realizan actividades dentro de ese tipo de economía, denominados \"pequeños contribuyentes\", lo cual dio lugar a la firma del Convenio de Colaboración Administrativa en Materia Fiscal\nFederal y sus anexos.\nQue mediante reformas a la Ley del Impuesto Sobre la Renta, vigentes a partir del 1 de enero de\n2003, el H. Congreso de la Unión estimó conveniente incluir la relativa a establecer en el artículo139 que en el régimen de pequeños contribuyentes, éstos puedan efectuar los pagos del impuesto en las entidades federativas donde obtengan sus ingresos, siempre que dichas entidades celebren convenio de coordinación para administrar dicho impuesto.\nQue dentro del marco señalado en los párrafos anteriores el Estado de Guerrero y el Gobierno\nFederal por conducto de la Secretaría de Hacienda y Crédito Público, con fundamento en la legislación federal a que se refiere el Convenio de Colaboración Administrativa en Materia Fiscal Federal, así como el artículo 139 de la Ley del Impuesto Sobre la Renta, suscribieron el Anexo No. 3 al Convenio de\nColaboración Administrativa en Materia Fiscal Federal, el cual se publicó en el Diario Oficial de la diversas reformas a la Ley del Impuesto al Valor Agregado, entre las que se encuentra la relativa al artículo 2o.-C, en el que se establece que las personas físicas que tributen conforme al régimen de pequeños contribuyentes (REPECO), de acuerdo a lo previsto en la Sección III del Capítulo II del Título IV de la Ley del Impuesto Sobre la Renta, pagarán el Impuesto al Valor Agregado mediante estimativa del valor de las actividades que practiquen las autoridades fiscales, en lugar de hacerlo en los términos generales que la Ley de la materia establece.\nY SE EMITE EL NUEVO FORMATO DE “DECLARACIÓN DE PAGO\nDE IMPUESTOS DEL RÉGIMEN DE PEQUEÑOS\nCONTRIBUYENTES SFA 03” Y SE EMITEN LAS “TABLAS DEL\nPAGO BIMESTRAL DEL IMPUESTO SOBRE LA RENTA, IMPUESTO\nAL VALOR AGREGADO E IMPUESTO EMPRESARIAL A TASA\nÚNICA DE LOS CONTRIBUYENTES” PARA EL EJERCICIO FISCAL\n2008\nQue con fecha 5 de abril de 2004, fue publicado en el Diario Oficial de la Federación el \"Decreto por el que se otorgan diversos beneficios fiscales a los contribuyentes que se mencionan\", a través del cual el Ejecutivo Federal en ejercicio de sus atribuciones, otorgó facilidades administrativas a los pequeños contribuyentes, entre otras, la consistente en permitir a las entidades federativas que en una sola cuota puedan recaudar el Impuesto Sobre la Renta (ISR) y el Impuesto al Valor Agregado (IVA) de dichos contribuyentes; requerir la presentación de la declaración informativa de los ingresos obtenidos en el ejercicio de 2003; así como revisar y ajustar los coeficientes de valor agregado a que se refiere el artículo 2o.-C de la Ley del Impuesto al Valor Agregado.\nQue por lo expuesto, se hizo necesaria la celebración de un nuevo Anexo 3 que substituya al anteriormente celebrado, por lo que la Secretaría y el Estado, con fundamento en las disposiciones señaladas en los párrafos anteriores, así como en el artículo 13 de la Ley de Coordinación Fiscal, suscribieron un nuevo Anexo 3 al Convenio de Colaboración Administrativa en Materia Fiscal Federal, el cual fue publicado, para producir efectos legales, en el Diario Oficial de la Federación y en el Periódico\nOficial del Estado de Guerrero del 16 de agosto y 16 de septiembre del 2005, respectivamente.\nQue con fecha 08 de diciembre del 2005, fue publicado en Diario Oficial de la Federación el\n\"Decreto por el que se otorgan diversos beneficios fiscales a los contribuyentes que se indican\", en el que se incluyen a los contribuyentes del REPECO, de las entidades federativas con las que la SHCP celebró el Convenio de Coordinación para la Administración del IVA y del ISR, a fin de simplificar el cumplimiento de sus obligaciones tributarias fiscales y para impulsar la creación de plazas comerciales en las que se reubiquen a los comerciantes que desarrollan su actividad en la vía pública, mediante el cual se establece que las entidades federativas, para la administración del ISR y del IVA, podrán establecer anualmente a los contribuyentes que se inscriban o estén inscritos en el Registro Fe eral de\nContribuyentes en el REPECO, con establecimientos, sucursales o agencias ubicados en su circunscripción, una cuota fija integrada aplicable para todo el ejercicio y que, en su caso, incluya a los impuestos Sobre la Renta y al Valor Agregado, cuyo pago se realizará bimestralmente. Dichas entidades federativas deberán proporcionar al Servicio de Administración Tributaria, la información sobre los pagos\nNo. 3 al Convenio de Colaboración Administrativa en Materia Fiscal Federal.\nY SE EMITE EL NUEVO FORMATO DE “DECLARACIÓN DE PAGO\nDE IMPUESTOS DEL RÉGIMEN DE PEQUEÑOS\nCONTRIBUYENTES SFA 03” Y SE EMITEN LAS “TABLAS DEL\nPAGO BIMESTRAL DEL IMPUESTO SOBRE LA RENTA, IMPUESTO\nAL VALOR AGREGADO E IMPUESTO EMPRESARIAL A TASA\nÚNICA DE LOS CONTRIBUYENTES” PARA EL EJERCICIO FISCAL\n2008\nQue el 1 de enero de 2008 entró en vigor la Ley del Impuesto Empresarial a Tasa Única, la cual establece que las entidades federativas que tengan celebrado con la Secretaría de Hacienda y Crédito\nPúblico Convenio de Coordinación para la administración del impuesto sobre la renta a cargo de las personas físicas que tributen conforme al Régimen de Pequeños Contribuyentes a que se refiere la Ley del Impuesto sobre la Renta, deberán, en una sola cuota, recaudar los impuestos sobre la renta, empresarial a tasa única y al valor agregado que, en su caso, causen dichos contribuyentes, así como para que considere el entero del impuesto estatal sobre remuneraciones al trabajo personal subordinado acorde a las disposiciones de la Ley de Hacienda del Estado de Guerrero vigentes para estos contribuyentes, por lo que es necesario realizar las adecuaciones pertinentes al formato de declaración de pago de impuestos del régimen de pequeños contribuyentes SFA-03 y a las tablas de cuota fija integrada a fin de precisar que la cuota fija integrada incluirá el impuesto empresarial a tasa única, considerando también que si la actividad que realicen los contribuyentes es objeto del impuesto al valor agregado y, en su caso, a qué tasa, o bien, si se encuentra exenta de tal gravamen.\nQue en el marco de la simplificación legal y administrativa, se hace necesario revisar y actualizar las leyes y procedimientos vigentes, para mantenerlos acordes a los cambios que la dinámica social demanda.\nQue con el fin de facilitar a los contribuyentes el cumplimiento de sus obligaciones fiscales, la\nSecretaría de Finanzas y Administración se mantiene atenta al cumplimiento del inciso c) de la fracción I del artículo 78 del Código Fiscal del Estado y en estrecha comunicación con los contribuyentes, captando administrativas que sean necesarias.\nQue en este contexto, la Secretaría de Finanzas y Administración ha visto la necesidad de derogar el formato de \"Declaración de pago de impuestos del régimen de pequeños contribuyentes SFA03\", emitir un nuevo formato de \"Declaración de pago de impuestos del régimen de pequeños contribuyentes SFA-03\" y elaborar las \"Tablas para la determinación de la cuota fija integrada para el pago bimestral del ISR, IVA e IETU para el ejercicio de 2008 de los contribuyentes del REPECO, con el fin de que cumplan con sus obligaciones fiscales federales ante las autoridades fiscales estatales.\nPor lo expuesto anteriormente, he tenido a bien expedir el siguiente:\nY SE EMITE EL NUEVO FORMATO DE “DECLARACIÓN DE PAGO\nDE IMPUESTOS DEL RÉGIMEN DE PEQUEÑOS\nCONTRIBUYENTES SFA 03” Y SE EMITEN LAS “TABLAS DEL\nPAGO BIMESTRAL DEL IMPUESTO SOBRE LA RENTA, IMPUESTO\nAL VALOR AGREGADO E IMPUESTO EMPRESARIAL A TASA\nÚNICA DE LOS CONTRIBUYENTES” PARA EL EJERCICIO FISCAL\n2008\nACUERDO POR EL QUE SE DEROGA EL FORMATO DE \"DECLARACION DE PAGO DE\nIMPUESTOS DEL RÉGIMEN DE PEQUEÑOS CONTRIBUYENTES SFA-03\" PUBLICADO EN EL\nPERIODICO OFICIAL DEL GOBIERNO DEL ESTADO DE GUERRERO NUMERO 90 DE FECHA 10 DE\nNOVIEMBRE DE 2006, Y SE EMITE EL NUEVO FORMATO DE \"DECLARACION DE PAGO DE\nIMPUESTOS DEL RÉGIMEN DE PEQUEÑOS CONTRIBUYENTES SFA-03\" Y SE EMITEN LAS\n\"TABLAS PARA LA DETERMINACIÓN DE LA CUOTA FIJA INTEGRADA PARA EL PAGO\nBIMESTRAL DEL IMPUESTO SOBRE LA RENTA, IMPUESTO AL VALOR AGREGADO E IMPUESTO\nEMPRESARIAL A TASA UNICA DE LOS CONTRIBUYENTES DEL RÉGIMEN DE PEQUEÑOS\nCONTRIBUYENTES\" PARA EL EJERCICIO DE 2008.\nARTÍCULO PRIMERO.- Se emite el formato \"DECLARACION DE PAGO DE IMPUESTOS DEL\nRÉGIMEN DE PEQUEÑOS CONTRIBUYENTES SFA-03\".\nARTÍCULO SEGUNDO.- Se deroga al formato \"DECLARACION DE PAGO DE IMPUESTOS\nDEL RÉGIMEN DE PEQUEÑOS CONTRIBUYENTES SFA-03\" publicado en el Periódico Oficial del\nGobierno del Estado de Guerrero No. 90 el 10 de noviembre de 2006.\nARTÍCULO TERCERO.- Se emiten las \"TABLAS PARA LA DETERMINACIÓN DE LA CUOTA\nFIJA INTEGRADA PARA EL PAGO BIMESTRAL DEL IMPUESTO SOBRE LA RENTA, IMPUESTO AL\nVALOR AGREGADO Y DEL IMPUESTO EMPRESARIAL A TASA UNICA DE LOS CONTRIBUYENTES\nDEL RÉGIMEN DE PEQUEÑOS CONTRIBUYENTES\" para el ejercicio de 2008.\nARTÍCULO CUARTO.- Con el presente Acuerdo publíquense los formatos y tablas que se precisan en los artículos que anteceden. Los formatos a que se refiere el presente Acuerdo son de impresión libre, con la obligación para los contribuyentes de que los mismos deberán contener todos y cada uno de los requisitos tanto en el tamaño como en los espacios correspondientes.\nPRIMERO.- El presente Acuerdo entrará en vigor a partir del día hábil siguiente de su\nSEGUNDO.- A partir de la entrada en vigor del presente Acuerdo quedará derogado el formato\n\"DECLARACION DE PAGO DE IMPUESTOS DEL RÉGIMEN DE PEQUEÑOS CONTRIBUYENTES\nY SE EMITE EL NUEVO FORMATO DE “DECLARACIÓN DE PAGO\nDE IMPUESTOS DEL RÉGIMEN DE PEQUEÑOS\nCONTRIBUYENTES SFA 03” Y SE EMITEN LAS “TABLAS DEL\nPAGO BIMESTRAL DEL IMPUESTO SOBRE LA RENTA, IMPUESTO\nAL VALOR AGREGADO E IMPUESTO EMPRESARIAL A TASA\nÚNICA DE LOS CONTRIBUYENTES” PARA EL EJERCICIO FISCAL\n2008\nSFA-03\" publicado en el Periódico Oficial del Gobierno del Estado de Guerrero No. 90 el 10 de noviembre de 2006.\nTERCERO.- A partir de la entrada en vigor del presente Acuerdo quedará vigente el formato\n\"DECLARACION DE PAGO DE IMPUESTOS DEL RÉGIMEN DE PEQUEÑOS CONTRIBUYENTES\nSFA-03\".\nGuerrero, a los 16 días del mes de abril del año dos mil ocho.\nEL GOBERNADOR CONSTITUCIONAL DEL ESTADO.\nC.P. CARLOS ZEFERINO TORREBLANCA GALINDO.\nRúbrica.\nEL SECRETARIO GENERAL DE GOBIERNO.\nLIC. ARMANDO CHAVARRÍA BARRERA.\nRúbrica.\nEL SECRETARIO DE FINANZAS Y ADMINISTRACIÓN.\nLIC. RICARDO ERNESTO CABRERA MORÍN.\nRúbrica.\nY SE EMITE EL NUEVO FORMATO DE “DECLARACIÓN DE PAGO\nDE IMPUESTOS DEL RÉGIMEN DE PEQUEÑOS\nCONTRIBUYENTES SFA 03” Y SE EMITEN LAS “TABLAS DEL\nPAGO BIMESTRAL DEL IMPUESTO SOBRE LA RENTA, IMPUESTO\nÚNICA DE LOS CONTRIBUYENTES” PARA EL EJERCICIO FISCAL\nY SE EMITE EL NUEVO FORMATO DE “DECLARACIÓN DE PAGO\nDE IMPUESTOS DEL RÉGIMEN DE PEQUEÑOS\nCONTRIBUYENTES SFA 03” Y SE EMITEN LAS “TABLAS DEL\nPAGO BIMESTRAL DEL IMPUESTO SOBRE LA RENTA, IMPUESTO\nÚNICA DE LOS CONTRIBUYENTES” PARA EL EJERCICIO FISCAL\nY SE EMITE EL NUEVO FORMATO DE “DECLARACIÓN DE PAGO\nDE IMPUESTOS DEL RÉGIMEN DE PEQUEÑOS\nCONTRIBUYENTES SFA 03” Y SE EMITEN LAS “TABLAS DEL\nPAGO BIMESTRAL DEL IMPUESTO SOBRE LA RENTA, IMPUESTO\nÚNICA DE LOS CONTRIBUYENTES” PARA EL EJERCICIO FISCAL\nY SE EMITE EL NUEVO FORMATO DE “DECLARACIÓN DE PAGO\nDE IMPUESTOS DEL RÉGIMEN DE PEQUEÑOS\nCONTRIBUYENTES SFA 03” Y SE EMITEN LAS “TABLAS DEL\nPAGO BIMESTRAL DEL IMPUESTO SOBRE LA RENTA, IMPUESTO\nAL VALOR AGREGADO E IMPUESTO EMPRESARIAL A TASA\nÚNICA DE LOS CONTRIBUYENTES” PARA EL EJERCICIO FISCAL\n2008\nRÉGIMEN DE PEQUEÑOS CONTRIBUYENTES (REPECOS)\nFIJA\nINTEGRADA PARA LOS PAGOS BIMESTRALES DE ISR, IVA E IETU DEL EJERCICIO 2008.\nEn el caso de que los Ingresos del bimestre sean superiores a $ 333,333.33 el Ingreso excedente se deberá ubicar en el renglón correspondiente para determinar el Impuesto a este, mlsmc que se sumara con el impuesto determinado a los $ 333,333.33 y el resultado será el impuesto a pagar, lo anterior siempre y cuando la suma de los ingresos anuales no rebase de la cantidad de $\n2'000,000.00.\nÁREA GEOGRÁFICA\nMONTO DE INGRESOS BIMESTRALES QUE SIRVEN DE BASE ÁREA GEOGRÁFICA \"C\" CUOTA\nPARA CALCULAR EL IMPUESTO\n\"\nIJ A\nFIJA INTEGRADA\nPara Ingresos de Hasta Ingresos de\n$ 0.01 $ 15,000.00 $ 150.00 $ 150.00\n$ 15,000.01 $ 20,000.00 $ 261.02 $ 283.30\n$ 20,000.01 $ 25,000.00 $ 421.02 $ 443.30\n$ 25,000.01 $ 30,000.00 $ 581.02 $ 603.30\n$ 30,000.01 $ 35,000.00 $ 741.02 $ 763.30\n$ 35,000.01 $ 40,000.00 $ 901.02 $ 923.30\n$ 40,000.01 $ 45,000.00 $ 1,061.02 $ 1,083.30\n$ 45,000.01 $ 50,000.00 $ 1,221.02 $ 1,243.30\n$ 50,000.01 $ 55,000.00 $ 1,381.02 $ 1,403.30\n$ 55,000.01 $ 60,000.00 $ 1,541.02 $ 1,563.30\n$ 60,000.01 $ 65,000.00 $ 1,701.02 $ 1,723.30\n$ 65,000.01 $ 70,000.00 $ 1,861.02 $ 1,883.30\n$ 70,000.01 $ 75,000.00 $ 2,021.02 $ 2,043.30\n$ 75,000.01 $ 80,000.00 $ 2,181.02 $ 2,203.30\n$ 80,000.01 $ 85,000.00 $ 2,341.02 $ 2,363.30\n$ 85,000.01 $ 90,000.00 $ 2,501.02 $ 2,523.30\n$ 90,000.01 $ 95,000.00 $ 2,661.02 $ 2,683.30\n$ 95,000.01 $ 100,000.00 $ 2,821.02 $ 2,843.30\n$ 100,000.01 $ 105,000.00 $ 2,981.02 $ 3,003.30\n$ 105,000.01 $ 110,000.00 $ 3,141.02 $ 3,163.30\n$ 110,000.01 $ 115,000.00 $ 3,301.02 $ 3,323.30\n$ 115,000.01 $ 120,000.00 $ 3,461.02 $ 3,483.30\n$ 120,000.01 $ 125,000.00 $ 3,621.02 $ 3,643.30\n$ 125,000.01 $ 130,000.00 $ 3,781.02 $ 3,803.30\n$ 130,000.01 $ 135,000.00 $ 3,941.02 $ 3,963.30\n$ 135,000.01 $ 140,000.00 $ 4,101.02 $ 4,123.30\n$ 140,000.01 $ 145,000.00 $ 4,261.02 $ 4,283.30\n$ 145,000.01 $ 150,000.00 $ 4,421.02 $ 4,443.30\n$ 150,000.01 $ 155,000.00 $ 4,581.02 $ 4,603.30\n$ 155,000.01 $ 160,000.00 $ 4,741.02 $ 4,763.30\n$ 160,000.01 $ 165,000.00 $ 4,901.02 $ 4,923.30\n$ 165,000.01 $ 170,000.00 $ 5,061.02 $ 5,083.30\n$ 170,000.01 $ 175,000.00 $ 5,221.02 $ 5,243.30\n$ 175,000.01 $ 180,000.00 $ 5,381.02 $ 5,403.30\n$ 180,000.01 $ 185,000.00 $ 5,541.02 $ 5,563.30\nY SE EMITE EL NUEVO FORMATO DE “DECLARACIÓN DE PAGO\nDE IMPUESTOS DEL RÉGIMEN DE PEQUEÑOS\nCONTRIBUYENTES SFA 03” Y SE EMITEN LAS “TABLAS DEL\nPAGO BIMESTRAL DEL IMPUESTO SOBRE LA RENTA, IMPUESTO\nAL VALOR AGREGADO E IMPUESTO EMPRESARIAL A TASA\nÚNICA DE LOS CONTRIBUYENTES” PARA EL EJERCICIO FISCAL\n2008\n$ 185,000.01 $ 190,000.00 $ 5,701.02 $ 5,723.30\n$ 190,000.01 $ 195,000.00 $ 5,861.02 $ 5,883.30\n$ 195,000.01 $ 200,000.00 $ 6,021.02 $ 6,043.30\n$ 200,000.01 $ 205,000.00 $ 6,181.02 $ 6,203.30\n$ 205,000.01 $ 210,000.00 $ 6,341.02 $ 6,363.30\n$ 210,000.01 $ 215,000.00 $ 6,501.02 $ 6,523.30\n$ 215,000.01 $ 220,000.00 $ 6,661.02 $ 6,683.30\n$ 220,000.01 $ 225,000.00 $ 6,821.02 $ 6,843.30\n$ 225,000.01 $ 230,000.00 $ 6,981.02 $ 7,003.30\n$ 230,000.01 $ 235,000.00 $ 7,141.02 $ 7,163.30\n$ 235,000.01 $ 240,000.00 $ 7,301.02 $ 7,323.30\n$ 240,000.01 $ 245,000.00 $ 7,461.02 $ 7,483.30\n$ 245,000.01 $ 250,000.00 $ 7,621.02 $ 7,643.30\n$ 250,000.01 $ 255,000.00 $ 7,781.02 $ 7,803.30\n$ 255,000.01 $ 260,000.00 $ 7,941.02 $ 7,963.30\n$ 260,000.01 $ 265,000.00 $ 8,101.02 $ 8,123.30\n$ 265,000.01 $ 270,000.00 $ 8,261.02 $ 8,283.30\n$ 270,000.01 $ 275,000.00 $ 8,421.02 $ 8,443.30\n$ 275,000.01 $ 280,000.00 $ 8,581.02 $ 8,603.30\n$ 280,000.01 $ 285,000.00 $ 8,741.02 $ 8,763.30\n$ 285,000.01 $ 290,000.00 $ 8,901.02 $ 8,923.30\n$ 290,000.01 $ 295,000.00 $ 9,061.02 $ 9,083.30\n$ 295,000.01 $ 300,000.00 $ 9,221.02 $ 9,243.30\n$ 300,000.01 $ 305,000.00 $ 9,381.02 $ 9,403.30\n$ 305,000.01 $ 310,000.00 $ 9,541.02 $ 9,563.30\n$ 310,000.01 $ 315,000.00 $ 9,701.02 $ 9,723.30\n$ 315,000.01 $ 320,000.00 $ 9,861.02 $ 9,883.30\n$ 320,000.01 $ 325,000.00 $ 10,021.02 $ 10,043.30\n$ 325,000.01 $ 330,000.00 $ 10,181.02 $ 10,203.30\n$ 330,000.01 $ 333,333.00 $ 10,287.68 $ 10,309.94\nY SE EMITE EL NUEVO FORMATO DE “DECLARACIÓN DE PAGO\nDE IMPUESTOS DEL RÉGIMEN DE PEQUEÑOS\nCONTRIBUYENTES SFA 03” Y SE EMITEN LAS “TABLAS DEL\nPAGO BIMESTRAL DEL IMPUESTO SOBRE LA RENTA, IMPUESTO\nAL VALOR AGREGADO E IMPUESTO EMPRESARIAL A TASA\nÚNICA DE LOS CONTRIBUYENTES” PARA EL EJERCICIO FISCAL\n2008\nREGIMEN DE PEQUEÑOS CONTRIBUYENTES (REPECOS)\nTABLA PARA LA DETERMINACION DE LA CUOTA FIJA INTEGRADA DE LOS PAGOS BIMESTRALES DE ISR E IETU\nDEL EJERCICIO 2008 PARA CONTRIBUYENTES CON INGRESOS EXCENTOS DE IVA Y TASA 0%\nEn el caso de que los Ingresos del bimestre sean superiores a $ 333,333.33 el Ingreso excedente se deberá ubicar en el renglón correspondiente para determinar el Impuesto a este, mismo que se sumara con el impuesto determinado a los $ 333,333.33 y el resultado será el impuesto a pagar, lo anterior siempre y cuando la suma de los ingresos anuales no rebase de la cantidad de $ 2'000,000.00.\nMONTO DE INGRESOS BIMESTRALES QUE SIRVEN DE BASE\nPARA CALCULAR EL IMPUESTO ÁREA ÁREA GEOGRÁFICA \"C\"\nGEOGRÁFICA \"A\"\nPara Ingresos de Hasta Ingresos de\n$ 0.01 $ 15,000.00 $ 75.00 $ 75.00\n$ 15,000.01 $ 20,000.00 $ 130.51 $ 141.65\n$ 20,000.01 $ 25,000.00 $ 210.51 $ 221.65\n$ 25,000.01 $ 30,000.00 $ 290.51 $ 301.65\n$ 30,000.01 $ 35,000.00 $ 370.51 $ 381.65\n$ 35,000.01 $ 40,000.00 $ 450.51 $ 461.65\n$ 40,000.01 $ 45,000.00 $ 530.51 $ 541.65\n$ 45,000.01 $ 50,000.00 $ 610.51 $ 621.65\n$ 50,000.01 $ 55,000.00 $ 690.51 $ 701.65\n$ 55,000.01 $ 60,000.00 $ 770.51 $ 781.65\n$ 60,000.01 $ 65,000.00 $ 850.51 $ 861.65\n$ 65,000.01 $ 70,000.00 $ 930.51 $ 941.65\n$ 70,000.01 $ 75,000.00 $ 1,010.51 $ 1,021.65\n$ 75,000.01 $ 80,000.00 $ 1,090.51 $ 1,101.65\n$ 80,000.01 $ 85,000.00 $ 1,170.51 $ 1,181.65\n$ 85,000.01 $ 90,000.00 $ 1,250.51 $ 1,261.65\n$ 90,000.01 $ 95,000.00 $ 1,330.51 $ 1,341.65\n$ 95,000.01 $ 100,000.00 $ 1,410.51 $ 1,421.65\n$ 100,000.01 $ 105,000.00 $ 1,490.51 $ 1,501.65\n$ 105,000.01 $ 110,000.00 $ 1,570.51 $ 1,581.65\n$ 110,000.01 $ 115,000.00 $ 1,650.51 $ 1,661.65\n$ 115,000.01 $ 120,000.00 $ 1,730.51 $ 1,741.65\n$ 120,000.01 $ 125,000.00 $ 1,810.51 $ 1,821.65\n$ 125,000.01 $ 130,000.00 $ 1,890.51 $ 1,901.65\n$ 130,000.01 $ 135,000.00 $ 1,970.51 $ 1,981.65\n$ 135,000.01 $ 140,000.00 $ 2,050.51 $ 2,061.65\n$ 140,000.01 $ 145,000.00 $ 2,130.51 $ 2,141.65\n$ 145,000.01 $ 150,000.00 $ 2,210.51 $ 2,221.65\n$ 150,000.01 $ 155,000.00 $ 2,290.51 $ 2,301.65\n$ 155,000.01 $ 160,000.00 $ 2,370.51 $ 2,381.65\n$ 160,000.01 $ 165,000.00 $ 2,450.51 $ 2,461.65\n$ 165,000.01 $ 170,000.00 $ 2,530.51 $ 2,541.65\n$ 170,000.01 $ 175,000.00 $ 2,610.51 $ 2,621.65\n$ 175,000.01 $ 180,000.00 $ 2,690.51 $ 2,701.65\nY SE EMITE EL NUEVO FORMATO DE “DECLARACIÓN DE PAGO\nDE IMPUESTOS DEL RÉGIMEN DE PEQUEÑOS\nCONTRIBUYENTES SFA 03” Y SE EMITEN LAS “TABLAS DEL\nPAGO BIMESTRAL DEL IMPUESTO SOBRE LA RENTA, IMPUESTO\nAL VALOR AGREGADO E IMPUESTO EMPRESARIAL A TASA\nÚNICA DE LOS CONTRIBUYENTES” PARA EL EJERCICIO FISCAL\n2008\n$ 180,000.01 $ 185,000.00 $ 2,770.51 $ 2,781.65\n$ 185,000.01 $ 190,000.00 $ 2,850.51 $ 2,861.65\n$ 190,000.01 $ 195,000.00 $ 2,930.51 $ 2,941.65\n$ 195,000.01 $ 200,000.00 $ 3,010.51 $ 3,021.65\n$ 200,000.01 $ 205,000.00 $ 3,090.51 $ 3,101.65\n$ 205,000.01 $ 210,000.00 $ 3,170.51 $ 3,181.65\n$ 210,000.01 $ 215,000.00 $ 3,250.51 $ 3,261.65\n$ 215,000.01 $ 220,000.00 $ 3,330.51 $ 3,341.65\n$ 220,000.01 $ 225,000.00 $ 3,410.51 $ 3,421.65\n$ 225,000.01 $ 230,000.00 $ 3,490.51 $ 3,501.65\n$ 230,000.01 $ 235,000.00 $ 3,570.51 $ 3,581.65\n$ 235,000.01 $ 240,000.00 $ 3,650.51 $ 3,661.65\n$ 240,000.01 $ 245,000.00 $ 3,730.51 $ 3,741.65\n$ 245,000.01 $ 250,000.00 $ 3,810.51 $ 3,821.65\n$ 250,000.01 $ 255,000.00 $ 3,890.51 $ 3,901.65\n$ 255,000.01 $ 260,000.00 $ 3,970.51 $ 3,981.65\n$ 260,000.01 $ 265,000.00 $ 4,050.51 $ 4,061.65\n$ 265,000.01 $ 270,000.00 $ 4,130.51 $ 4,141.65\n$ 270,000.01 $ 275,000.00 $ 4,210.51 $ 4,221.65\n$ 275,000.01 $ 280,000.00 $ 4,290.51 $ 4,301.65\n$ 280,000.01 $ 285,000.00 $ 4,370.51 $ 4,381.65\n$ 285,000.01 $ 290,000.00 $ 4,450.51 $ 4,461.65\n$ 290,000.01 $ 295,000.00 $ 4,530.51 $ 4,541.65\n$ 295,000.01 $ 300,000.00 $ 4,610.51 $ 4,621.65\n$ 300,000.01 $ 305,000.00 $ 4,690.51 $ 4,701.65\n$ 305,000.01 $ 310,000.00 $ 4,770.51 $ 4,781.65\n$ 310,000.01 $ 315,000.00 $ 4,850.51 $ 4,861.65\n$ 315,000.01 $ 320,000.00 $ 4,930.51 $ 4,941.65\n$ 320,000.01 $ 325,000.00 $ 5,010.51 $ 5,021.65\n$ 325,000.01 $ 330,000.00 $ 5,090.51 $ 5,101.65\n$ 330,000.01 $ 333,333.00 $ 5,143.84 $ 5,154.97",
  "ordenamiento": "ACUERDO",
  "jurisdiccion": "GUERRERO",
  "fuente_oficial": "DIARIO OFICIAL DE LA FEDERACION",
  "Fecha de Publicación": "1 de enero de \n2003",
  "ULTIMA REFORMA PUBLICADA": "05 DE JULIO DE 2013",
  "status": "ABROGADA",
  "es_escaneado": false,
  "tiene_tablas": true,
  "materia": [
    "fiscal"
  ]
}