{
  "titulo": "Acuerdo por el Que Se Autoriza por Única Ocasión Sin Que Siente Ningún Precedente Que Se Puede Hacer",
  "Contenido": "EN TÉRMINOS DE LEY A LOS OFICIALES DEL\nREGISTRO CIVIL QUE SE ENCUENTRAN EN\nFUNCIONES PARA QUE CONCLUYAN SU\nENCARGO HASTA EL 29 DE SEPTIEMBRE DE\nABROGADO POR CONCLUIDA SU VIGENCIA EL 29 DE SEPTIEMBRE DE\n2012.\nTEXTO ORIGINAL\nACUERDO PUBLICADO EN EL PERIÓDICO OFICIAL DEL GOBIERNO DEL ESTADO\nNo. 85, EL MARTES 25 DE OCTUBRE DE 2011.\nACUERDO POR EL QUE SE AUTORIZA POR ÚNICA OCASIÓN SIN QUE SIENTE\nNINGÚN PRECEDENTE QUE SE PUEDE HACER VALER EN TÉRMINOS DE LEY A\nLOS OFICIALES DEL REGISTRO CIVIL QUE SE ENCUENTRAN EN FUNCIONES\nPARA QUE CONCLUYAN SU ENCARGO HASTA EL 29 DE SEPTIEMBRE DE 2012.\nLICENCIADO HUMBERTO SALGADO GÓMEZ, SECRETARIO GENERAL DE\nGOBIERNO, CON FUNDAMENTO EN LOS ARTÍCULOS 3o. Y 20 FRACCIÓN X DE LA\nLEY ORGÁNICA DE LA ADMINISTRACIÓN PÚBLICA DEL ESTADO DE GUERRERO\nNÚMERO 433; 6 FRACCIÓN III LEY NÚMERO 495 DEL REGISTRO CIVIL DEL\nESTADO DE GUERRERO, Y 9 FRACCIÓN XII DEL REGLAMENTO INTERIOR DE LA\nSECRETARÍA GENERAL DE GOBIERNO; Y\nQue el Plan Estatal de Desarrollo del Estado de Guerrero 2011-2015, tiene como el derecho humano fundamental a la identidad, dando certeza y seguridad jurídica al ciudadano.\nQue el Registro Civil es una institución de carácter público y de interés social, por publicidad a los actos constitutivos o modificatorios del estado civil de las personas, con\nAyuntamientos, a propuesta de su Presidente Municipal.\nEN TÉRMINOS DE LEY A LOS OFICIALES DEL\nREGISTRO CIVIL QUE SE ENCUENTRAN EN\nFUNCIONES PARA QUE CONCLUYAN SU\nENCARGO HASTA EL 29 DE SEPTIEMBRE DE\nQue la Coordinación Técnica del Sistema Estatal del Registro Civil, depende del\nEjecutivo del Estado, a través de la Secretaría General de Gobierno, y a ésta última le corresponde ser el órgano encargado de organizar, dirigir y vigilar el ejercicio de las funciones del Registro Civil, de conformidad con lo dispuesto por el artículo 20 fracción X de la Ley Orgánica de la Administración Pública del Estado de Guerrero número 433.\nQue una de las políticas públicas del Gobierno del Estado, es que no existan en la entidad personas sin identificación oficial, como lo son las actas de nacimiento; por ser ésta la primera relación jurídica del Estado con las personas, creándose de esta manera una reciprocidad de derechos y obligaciones entre ambos.\nQue el Estado de Guerrero tiene la obligación de garantizar los derechos inherentes a todos los guerrerenses, entre ellos el de la identidad civil; por lo tanto, es menester que existan en todas las comunidades pertenecientes a los Municipios, una\nOficialía del Registro Civil para efectos de dar cumplimiento a dicho propósito.\nQue si bien es cierto que en algunos casos los Oficiales del Registro Civil en funciones no cuentan con título de Licenciado en Derecho legalmente expedido, he incluso no han concluido la educación media superior o su equivalente, como lo prevén los artículos 33 fracción II y 34 de la Ley número 495 del Registro Civil del Estado de\nGuerrero; por ello, no se puede dar cumplimiento a lo dispuesto en los citados preceptos legales, el Estado tiene la obligación de garantizar que desde su nacimiento los niños registro provocaría que una persona legalmente sea desconocida para la sociedad; por lo consiguiente, no se pueden dejar desprotegidas a las comunidades de los Municipios requisitos requeridos para ser Oficial del Registro Civil.\nCon sustento en lo anterior, y por única ocasión se autoriza a los Oficiales del las atribuciones que les confiere la Ley número 495 del Registro Civil del Estado de\nGuerrero, hasta el término del mandato de los Honorables Ayuntamientos Municipales a\nEN TÉRMINOS DE LEY A LOS OFICIALES DEL\nREGISTRO CIVIL QUE SE ENCUENTRAN EN\nFUNCIONES PARA QUE CONCLUYAN SU\nENCARGO HASTA EL 29 DE SEPTIEMBRE DE los que correspondan; considerando además que no se ha expedido el Reglamento mediante el cual se crearán las unidades administrativas encargadas de conocer y resolver los Procedimientos de Aclaración o Rectificación Administrativa que establece la\nLey, con el personal especializado en la materia.\nPor lo anteriormente expuesto y fundado, he tenido a bien expedir el siguiente:\nACUERDO POR EL QUE SE AUTORIZA POR ÚNICA OCASIÓN SIN QUE SIENTE\nNINGÚN PRECEDENTE QUE SE PUEDE HACER VALER EN TÉRMINOS DE LEY A\nLOS OFICIALES DEL REGISTRO CIVIL QUE SE ENCUENTRAN EN FUNCIONES\nPARA QUE CONCLUYAN SU ENCARGO HASTA EL 29 DE SEPTIEMBRE DE 2012.\nArtículo Único. Se autoriza por única ocasión sin que se siente ningún precedente que se puede hacer valer en términos de ley a los Oficiales del Registro Civil que se encuentran en funciones para que concluyan su encargo hasta el día 29 de septiembre de 2012, fecha en que concluirá el periodo constitucional del Ayuntamiento\nMunicipal al que correspondan.\nPrimero. El presente Acuerdo entrará en vigor al día siguiente de su publicación, Segundo. Comuníquese este Acuerdo a los Ayuntamientos Constitucionales\nRegistro Civil, para los efectos legales correspondientes.\nDado en la Ciudad de Chilpancingo de los Bravo, Capital del Estado de Guerrero, a los veintiséis días del mes de septiembre del año dos mil once.\nEL SECRETARIO GENERAL DE GOBIERNO.\nLIC. HUMBERTO SALGADO GÓMEZ.\nEN TÉRMINOS DE LEY A LOS OFICIALES DEL\nREGISTRO CIVIL QUE SE ENCUENTRAN EN\nFUNCIONES PARA QUE CONCLUYAN SU\nENCARGO HASTA EL 29 DE SEPTIEMBRE DE\nRúbrica.",
  "ordenamiento": "ACUERDO",
  "jurisdiccion": "GUERRERO",
  "fuente_oficial": "DIARIO OFICIAL DE LA FEDERACION",
  "Fecha de Publicación": "29 DE SEPTIEMBRE DE \n2012",
  "ULTIMA REFORMA PUBLICADA": "25 DE OCTUBRE DE 2011",
  "status": "ABROGADA",
  "es_escaneado": false,
  "tiene_tablas": false,
  "materia": [
    "general"
  ]
}