{
  "titulo": "Acuerdo Parlamentario por el Que la Sexagésima Legislatura al Honorable Congreso del Estado Libre y",
  "Contenido": "GUERRERO, CONVOCA A TODOS LOS CIUDADANOS\nY CIUDADANAS MEXICANOS RESIDENTES EN EL\nESTADO DE GUERRERO, INTERESADOS EN\nPARTICIPAR EN EL PROCEDIMIENTO DE\nSELECCIÓN Y DESIGNACIÓN DEL TITULAR DE LA\nFISCALÍA GENERAL DEL ESTADO DE GUERRERO,\nCONFORME A LAS BASES QUE SE DETALLAN\nABROGADO POR CONCLUIDA SU VIGENCIA EL 27 DE NOVIEMBRE DE 2014.\nTEXTO ORIGINAL.\nAcuerdo Publicado en el Periódico Oficial del Gobierno del Estado No. 102, el Martes 23 de\nDiciembre de 2014.\nPODER LEGISLATIVO\nACUERDO PARLAMENTARIO POR EL QUE LA SEXAGÉSIMA LEGISLATURA AL HONORABLE\nCIUDADANOS Y CIUDADANAS MEXICANOS RESIDENTES EN EL ESTADO DE GUERRERO,\nINTERESADOS EN PARTICIPAR EN EL PROCEDIMIENTO DE SELECCIÓN Y DESIGNACIÓN DEL\nTITULAR DE LA FISCALÍA GENERAL DEL ESTADO DE GUERRERO, CONFORME A LAS BASES\nQUE SE DETALLAN.\nGuerrero.- Poder Legislativo.\nLA SEXAGÉSIMA LEGISLATURA AL HONORABLE CONGRESO DEL ESTADO LIBRE Y\nSOBERANO DE GUERRERO, EN NOMBRE DEL PUEBLO QUE REPRESENTA, Y:\nQue en sesión de fecha 18 de noviembre del 2014, los Diputados integrantes de la Comisión de\nGobierno, presentaron la Propuesta de Acuerdo Parlamentario por el que la Sexagésima Legislatura al ciudadanas mexicanos residentes en el Estado de Guerrero, interesados en participar en el procedimiento de selección y designación del Titular de la Fiscalía General del Estado de Guerrero, conforme a las bases que se detallan, en los siguientes términos: correlación con los artículos 19, 20 y demás relativos de la Ley Orgánica de la Fiscalía General del\nEstado de Guerrero número 500, establecen que el Ministerio Público se organiza en una Fiscalía\nGeneral del Estado, como órgano público autónomo, dotado de personalidad jurídica y de patrimonios propios.\nQue la Fiscalía General del Estado, tiene a su cargo entre otras, las siguientes atribuciones:\nGUERRERO, CONVOCA A TODOS LOS CIUDADANOS\nY CIUDADANAS MEXICANOS RESIDENTES EN EL\nESTADO DE GUERRERO, INTERESADOS EN\nPARTICIPAR EN EL PROCEDIMIENTO DE\nSELECCIÓN Y DESIGNACIÓN DEL TITULAR DE LA\nFISCALÍA GENERAL DEL ESTADO DE GUERRERO,\nCONFORME A LAS BASES QUE SE DETALLAN\n- La representación social de los guerrerenses y la de naturaleza jurídica del Estado;\n- La persecución ante los Tribunales, de todos los delitos del orden común;\n- El ejercicio de la acción penal ante los Tribunales;\n- La procuración de que los juicios en materia penal se sigan con toda regularidad para que la impartición de justicia sea pronta y expedita;\n- La de pedir la aplicación de las penas e intervenir en todos los asuntos que la ley de la materia determine;\n- Tendrá bajo su mando y conducción a la policía investigadora del delito.\nQue los artículos 140 y 142 de la Constitución Local y los numerales 16, 19 y 20, de la Ley\nOrgánica de la Fiscalía General del Estado de Guerrero número 500, establecen que el Fiscal General del Estado, es el Titular de la Fiscalía General del Estado, designado por el Congreso del Estado de\nQue por decreto número 192, de fecha veinte de junio del año dos mil trece, el Honorable cargo y funciones de Procurador General de Justicia del Estado de Guerrero, de la terna propuesta por el\nTitular del Poder Ejecutivo del Estado.\nQue por decreto número 522, de fecha veintiséis de octubre del año en curso y conforme a lo fracción XXXI del artículo 8° de la Ley Orgánica del Poder Legislativo de Guerrero, el Honorable\nCongreso del Estado en su función de Colegio Electoral designó al Doctor Salvador Rogelio Ortega\nMartínez, como Gobernador del Estado.\nQue en sesión de fecha trece de noviembre del año 2014, el Pleno del Honorable Congreso del\nBlanco Cabrera, al cargo y funciones de Titular de la Fiscalía General del Estado de Guerrero.\nQue el día doce de junio del año que transcurre, entró en vigor el Decreto 453 de reformas y\nDécimo Sexto Transitorio establece que Procurador General de Justicia en el Estado, que cambia a\nFiscal General, continuará en funciones y el Congreso del Estado de Guerrero, a los 30 días posteriores a la toma de protesta del Gobernador electo en el año 2015, deberá instaurar el procedimiento de\nGUERRERO, CONVOCA A TODOS LOS CIUDADANOS\nY CIUDADANAS MEXICANOS RESIDENTES EN EL\nESTADO DE GUERRERO, INTERESADOS EN\nPARTICIPAR EN EL PROCEDIMIENTO DE\nSELECCIÓN Y DESIGNACIÓN DEL TITULAR DE LA\nFISCALÍA GENERAL DEL ESTADO DE GUERRERO,\nCONFORME A LAS BASES QUE SE DETALLAN\nQue asimismo, con fecha primero de agosto del año en curso, se publicó en el Periódico Oficial del Gobierno del Estado de Guerrero, la Ley Orgánica de la Fiscalía General del Estado de Guerrero número 500, la cual establece en su artículo cuarto transitorio, que el Congreso del Estado de Guerrero, a los 30 días posteriores a la toma de protesta del Gobernador electo en el año 2015, deberá instaurar el procedimiento de designación previstos en los numerales 1 al 6 del artículo 142 de la Constitución\nQue el artículo 142 de la Constitución Política Local, la Ley Orgánica de la Fiscalía General del\nEstado de Guerrero número 500 y la Ley Orgánica del Poder Legislativo en vigor, otorgan el marco constitucional y legal para designar al Titular de la Fiscalía General del Estado de Guerrero, la que regirá su actuación por los principios de legalidad, objetividad, eficiencia, profesionalismo, honradez y respeto a los derechos humanos.\nQue el artículo antes señalado contempla el procedimiento para la designación del Fiscal\nGeneral del Estado, servidor público que deberá reunir los requisitos establecidos en el artículo 111 de la\nQue ante la renuncia irrevocable del ciudadano Iñaky Blanco Cabrera, al cargo y funciones de\nFiscal General del Estado, en términos del artículo 142 de la en correlación con los artículos 111 y\nDécimo Sexto de la Constitución Política Local y cuarto transitorio de la Ley Orgánica de la Fiscalía\nGeneral del Estado de Guerrero número 500, esta Comisión de Gobierno propone para su aprobación del\nPleno del Congreso la propuesta de convocatoria para seleccionar y designar al Fiscal General del\nEstado, en el entendido que el periodo que cubrirá como Fiscal General del Estado, será hasta el 26 de noviembre del año 2015, pudiendo el Servidor Público designado participar en el proceso de selección y designación que se inicie en el 2015\".\nQue vertido lo anterior, en sesión de fecha 18 de noviembre del 2014, la Sexagésima Legislatura términos, la propuesta de Acuerdo Parlamentario presentada por los Diputados integrantes de la\nComisión de Gobierno.\nPor lo anteriormente expuesto y con fundamento en lo dispuesto por los artículos 61 fracción I de expide el siguiente:\nGUERRERO, CONVOCA A TODOS LOS CIUDADANOS\nY CIUDADANAS MEXICANOS RESIDENTES EN EL\nESTADO DE GUERRERO, INTERESADOS EN\nPARTICIPAR EN EL PROCEDIMIENTO DE\nSELECCIÓN Y DESIGNACIÓN DEL TITULAR DE LA\nFISCALÍA GENERAL DEL ESTADO DE GUERRERO,\nCONFORME A LAS BASES QUE SE DETALLAN\nACUERDO PARLAMENTARIO POR EL QUE LA SEXAGÉSIMA LEGISLATURA AL HONORABLE\nCIUDADANOS Y CIUDADANAS MEXICANOS RESIDENTES EN EL ESTADO DE GUERRERO,\nINTERESADOS EN PARTICIPAR EN EL PROCEDIMIENTO DE SELECCIÓN Y DESIGNACIÓN DEL\nTITULAR DE LA FISCALÍA GENERAL DEL ESTADO DE GUERRERO, CONFORME A LAS BASES\nQUE SE DETALLAN.\nARTÍCULO ÚNICO.- La Sexagésima Legislatura al Honorable Congreso del Estado Libre y\nSoberano de Guerrero, aprueba la Convocatoria para seleccionar y designar al Titular de la Fiscalía\nGeneral del Estado, en los términos siguientes:\n\"La Sexagésima Legislatura al H. Congreso del Estado de Guerrero, con fundamento en los correlación con los artículos 19, 20 y demás relativos de la Ley Orgánica de la Fiscalía General del\nEstado de Guerrero número 500:\nCONVOCA\nA las ciudadanas y ciudadanos mexicanos que cumplan los requisitos establecidos en los participar en el proceso de selección y designación del Titular de la Fiscalía General del Estado de\nGuerrero, a solicitar su registro y presentar su documentación de aspirante conforme a las siguientes:\nBASES:\nPRIMERA. - La Comisión de Gobierno del Congreso Local será el órgano encargado de recibir, cotejar, revisar e integrar expedientes; vigilar el debido cumplimiento en la entrega de la documentación necesaria establecida en la presente convocatoria; valorar los antecedentes curriculares de los aspirantes; en su caso, registrar a los aspirantes para ser Titular de la Fiscalía General del Estado de\nGuerrero, y formular la propuesta correspondiente, para el cumplimiento de sus funciones y atribuciones\nGUERRERO, CONVOCA A TODOS LOS CIUDADANOS\nY CIUDADANAS MEXICANOS RESIDENTES EN EL\nESTADO DE GUERRERO, INTERESADOS EN\nPARTICIPAR EN EL PROCEDIMIENTO DE\nSELECCIÓN Y DESIGNACIÓN DEL TITULAR DE LA\nFISCALÍA GENERAL DEL ESTADO DE GUERRERO,\nCONFORME A LAS BASES QUE SE DETALLAN\nDEL REGISTRO DE ASPIRANTES\nSEGUNDA.- Las solicitudes de registro de aspirantes a ocupar el cargo de Fiscal General del\nEstado se recibirán del día miércoles 19 al miércoles 26 de noviembre de 2014 en un horario de las 9:00 a las 15:00 horas, por la Presidencia de la Comisión de Gobierno a través del personal técnico que designe, en el Recinto Oficial del Poder Legislativo del Estado de Guerrero, Boulevard Vicente Guerrero, Trébol Sur, Sentimientos de la Nación S/N, Colonia Villa Moderna, C.P. 39075, en Chilpancingo de los\nBravo, Estado de Guerrero.\nDE LOS REQUISITOS\nTERCERA. - De conformidad con lo dispuesto por el artículo 111 de la Constitución Política del\nEstado de Guerrero, para poder ser designado como Titular de la Fiscalía General del Estado, se deberán cumplir los siguientes requisitos:\nI Ser ciudadano mexicano, en ejercicio de sus derechos civiles y políticos;\nII. Tener cuando menos treinta años cumplidos al día de la designación;\nIII. Gozar de buena reputación, no haber sido condenado por delito que amerite pena corporal, ni estar inhabilitado para el desempeño de cargos públicos;\nIV. Haber residido en el Estado durante cinco años anteriores al día de su nombramiento;\nV. Contar con conocimientos especializados y con experiencia debidamente comprobados en el ámbito de su competencia;\nVI. Poseer al día de su nombramiento, título y cédula profesional de licenciado en Derecho, expedidas por autoridad o institución legalmente facultada para ello;\nVII. No ser ministro de ningún culto religioso;\nVIII. No haber sido titular de ninguna dependencia, entidad u organismo de la administración pública estatal o municipal, o representante popular federal o estatal, durante dos años previos a su designación; y,\nGUERRERO, CONVOCA A TODOS LOS CIUDADANOS\nY CIUDADANAS MEXICANOS RESIDENTES EN EL\nESTADO DE GUERRERO, INTERESADOS EN\nPARTICIPAR EN EL PROCEDIMIENTO DE\nSELECCIÓN Y DESIGNACIÓN DEL TITULAR DE LA\nFISCALÍA GENERAL DEL ESTADO DE GUERRERO,\nCONFORME A LAS BASES QUE SE DETALLAN\nIX. No haber sido dirigente de algún partido político ni postulado para cargo de elección popular dentro de los tres años anteriores a su designación.\nDE LA DOCUMENTACIÓN COMPROBATORIA\nCUARTA.- Los aspirantes deberán presentar a la Comisión de Gobierno del H. Congreso del\nEstado, a través del personal técnico que designe, para su registro, los documentos siguientes:\na). Copia certificada del acta de nacimiento.\nb). Copia certificada del anverso y reverso de la credencial para votar con fotografía vigente.\nc). Copia certificada del título y de la cédula profesionales.\nd). Documento o documentos que acrediten que el solicitante ha residido durante los últimos 5 años en el territorio de la Entidad.\ne). Copia de comprobante de domicilio, con una antigüedad máxima de tres meses.\nf). Documentos que acrediten que el solicitante cuenta con conocimientos especializados y con experiencia debidamente comprobados en el ámbito de la competencia de la Fiscalía General.\ng). Copia simple de la cartilla del servicio militar nacional, en su caso;\nh). Carta con firma autógrafa en la que la o el aspirante manifieste, bajo protesta de decir verdad que no se encuentra en los supuestos previstos en las fracciones VII, VIII y IX de la base tercera que antecede. Así como, no estar suspendido ni haber sido destituido o inhabilitado por resolución firme como servidor público, ni estar sujeto a procedimiento de responsabilidad administrativa federal o local, en los términos de las normas aplicables, ni hacer uso de sustancias psicotrópicas, de estupefacientes u otras que produzcan efectos similares, ni padecer alcoholismo. El formato respectivo será expedido por la\nComisión de Gobierno al momento del registro.\ni) Carta con firma autógrafa en la que la o el aspirante manifieste, estar dispuesto a someterse a las evaluaciones de control de confianza que se requieran para el desempeño de su función. El formato respectivo será expedido por la Comisión de Gobierno al momento del registro.\nGUERRERO, CONVOCA A TODOS LOS CIUDADANOS\nY CIUDADANAS MEXICANOS RESIDENTES EN EL\nESTADO DE GUERRERO, INTERESADOS EN\nPARTICIPAR EN EL PROCEDIMIENTO DE\nSELECCIÓN Y DESIGNACIÓN DEL TITULAR DE LA\nFISCALÍA GENERAL DEL ESTADO DE GUERRERO,\nCONFORME A LAS BASES QUE SE DETALLAN\nj) Currículum vitae suscrito por la o el aspirante con soporte documental; el cual deberá contener, entre otros datos: nombre, domicilio, teléfonos y correo electrónico; estudios realizados, trayectoria laboral, académica, política, docente y profesional; publicaciones vinculadas con la materia de investigación, procuración de justicia y afines, actividad empresarial, cargos de elección popular, organizaciones de cualquier tipo a las que pertenezca y el carácter de su participación.\nk) Resumen curricular de máximo una cuartilla en formato de letra Arial 12, sin domicilio ni teléfono, para su eventual publicación.\nl). 4 fotografías a color tamaño credencial.\nm). Carta de intención de exposición de Motivos, y\nn) Plan de Trabajo\nEl registro y entrega de documentos deberá realizarse personalmente por el aspirante, la entrega y presentación de documentos no prejuzga sobre el cumplimiento de los requisitos.\nEn su caso, la Comisión de Gobierno, a través del funcionario que se designe, cotejará la documentación con los originales respectivos.\nEn cualquier momento la Comisión de Gobierno, podrá solicitar a los aspirantes la presentación de los documentos originales o de las copias certificadas, en su caso, para cotejo y revisión.\nLos documentos que exhiban los interesados deberán acompañarse con sus respectivas copias simples, en ocho tantos.\nETAPAS\nQUINTA.- REGISTRO DE ASPIRANTES. La Comisión de Gobierno a través de su Presidente o convocado, el Presidente de la Comisión de Gobierno con auxilio del personal técnico que designe, distribuirá los expedientes entre los integrantes de la comisión.\nSEXTA.- VERIFICACIÓN DE LOS REQUISITOS Y VALORACIÓN CURRICULAR. La Comisión de Gobierno, con el apoyo del personal que estime pertinente, verificará el cumplimiento de los requisitos.\nPara la valoración curricular de las y los aspirantes se considerarán los siguientes aspectos: historia\nGUERRERO, CONVOCA A TODOS LOS CIUDADANOS\nY CIUDADANAS MEXICANOS RESIDENTES EN EL\nESTADO DE GUERRERO, INTERESADOS EN\nPARTICIPAR EN EL PROCEDIMIENTO DE\nSELECCIÓN Y DESIGNACIÓN DEL TITULAR DE LA\nFISCALÍA GENERAL DEL ESTADO DE GUERRERO,\nCONFORME A LAS BASES QUE SE DETALLAN profesional y laboral; apego a los principios de legalidad, objetividad, eficiencia, profesionalismo, honradez y respeto a los derechos humanos.\nDicha evaluación estará a cargo de los Diputados integrantes de la Comisión de Gobierno. Una vez realizada la valoración curricular, se elaborará una lista de al menos diez candidatos que contenga en orden alfabético, los nombres de las y los aspirantes que se propondrá al Pleno del Congreso para su aprobación, para ser enviada al Gobernador del Estado.\nAprobada la lista anterior, se ordenará su publicación en el portal del Congreso del Estado, agregando un resumen curricular de dichos candidatos.\nDE LA PRESENTACIÓN Y APROBACIÓN DE LAS PROPUESTAS\nSÉPTIMA. DE LA LISTA DE CANDIDATOS. El Pleno de la Sexagésima Legislatura del H.\nCongreso del Estado, conocerá la lista de candidatos para ser enviada al Gobernador del Estado y, en su caso, procederá a su discusión y aprobación. La aprobación de la lista de candidatos requerirá del voto de las dos terceras partes de los miembros del Congreso del Estado, conforme lo dispuesto por el artículo\nOCTAVA. DE LA TERNA PROPUESTA POR EL GOBERNADOR. Recibida la lista de candidatos propuesta por el Congreso del Estado, el Gobernador dentro de los diez días siguientes formulará una terna y la enviará a la consideración del Congreso del Estado.\nNOVENA. COMPARECENCIA DE LAS PERSONAS PROPUESTAS. Una vez recibida la Terna, el Presidente de la Comisión de Gobierno, comunicará a cada uno de ellos, fecha y hora para la comparecencia y exposición de su plan de trabajo conforme lo señala el numeral 4 del artículo 142 de la\n1. En los días establecidos conforme a la terna propuesta y en términos del calendario aprobado por la Comisión de Gobierno, el Presidente de la Comisión de Gobierno instalará la reunión de trabajo a la que podrán asistir los diputados que deseen hacerlo;\n2. Las y los aspirantes a los que les corresponda comparecer en las fechas señaladas, deberán para su comparecencia, y serán llamados a la Sala Legislativa que se designe, en el orden alfabético en que fueron propuestos. Ninguno de las o los aspirantes podrá estar presente en cualquiera de las otras comparecencias que se realicen;\nGUERRERO, CONVOCA A TODOS LOS CIUDADANOS\nY CIUDADANAS MEXICANOS RESIDENTES EN EL\nESTADO DE GUERRERO, INTERESADOS EN\nPARTICIPAR EN EL PROCEDIMIENTO DE\nSELECCIÓN Y DESIGNACIÓN DEL TITULAR DE LA\nFISCALÍA GENERAL DEL ESTADO DE GUERRERO,\nCONFORME A LAS BASES QUE SE DETALLAN\n3. Las comparecencias se dividirán en dos partes: una primera parte expositiva, en la que la o el aspirante, contará con el tiempo razonable para presentar su propuesta de Plan de Trabajo, pudiendo hacer uso de los materiales que le resulten necesarios; y una segunda parte para comentarios, observaciones y preguntas y respuestas;\n4. Al término de la exposición, se elaborará una lista de la o los diputados que deseen hacer una primera intervención, otorgando la palabra a cada uno de ellos para hacer las preguntas o emitir las observaciones y/o comentarios que consideren pertinentes;\n5. La o el aspirante, al término de las intervenciones de la y/o los diputados, dará respuesta a las preguntas formuladas de manera muy concisa. En su caso, y de ser estrictamente prudente, se podrá abrir una segunda ronda de intervenciones, conforme al procedimiento anteriormente descrito;\n6. Al término de las comparecencias programadas, el Presidente dará por concluidos los trabajos y clausurará la reunión;\n7. Cualquier aspecto no previsto en el presente procedimiento, será resuelto por acuerdo de la\nComisión de Gobierno.\nDÉCIMA. DE LA PROPUESTA AL PLENO. La Comisión de Gobierno, una vez llevado a cabo el análisis y desahogadas las comparecencias de los integrantes de la terna formulada por el Gobernador, propondrá al Pleno del Congreso para su aprobación por las dos terceras partes de los miembros del\nCongreso, la propuesta correspondiente.\nDÉCIMA PRIMERA. DE LA TOMA DE PROTESTA. La o el ciudadano que resulte designado por las dos terceras partes de los miembros del Congreso, Fiscal General del Estado, deberá rendir protesta ante el Pleno de la Sexagésima Legislatura, en la sesión en que sea designado y entrará en funciones a partir del día siguiente de su toma de protesta para un periodo que concluirá el 26 de\nEl profesionista que resulte seleccionado y designado como Fiscal General del Estado, podrá año 2015.\nGUERRERO, CONVOCA A TODOS LOS CIUDADANOS\nY CIUDADANAS MEXICANOS RESIDENTES EN EL\nESTADO DE GUERRERO, INTERESADOS EN\nPARTICIPAR EN EL PROCEDIMIENTO DE\nSELECCIÓN Y DESIGNACIÓN DEL TITULAR DE LA\nFISCALÍA GENERAL DEL ESTADO DE GUERRERO,\nCONFORME A LAS BASES QUE SE DETALLAN\nDE LAS DISPOSICIONES GENERALES\nDÉCIMA SEGUNDA.- La Comisión de Gobierno y la Legislatura Local, se reservan la secrecía y confidencialidad de la información generada durante el proceso de selección y designación del Titular de la Fiscalía General del Estado de Guerrero.\nDÉCIMA TERCERA.- Los resultados emitidos por la Comisión de Gobierno y, en su caso, por el\nPleno de la Legislatura Estatal, serán definitivos.\nDÉCIMA CUARTA.- La Comisión de Gobierno de la Sexagésima Legislatura al Honorable convocatoria.\nDE LOS CASOS NO PREVISTOS\nDÉCIMA QUINTA. - Los casos no previstos en la presente convocatoria serán resueltos por la de Guerrero.\nÚNICO.- Désele la más amplia difusión para su conocimiento general y efectos legales procedentes\".\nPRIMERO. El presente acuerdo parlamentario surtirá sus efectos a partir de su aprobación.\nSEGUNDO. Désele la más amplia difusión para su conocimiento general y efectos legales procedentes. noviembre del año dos mil catorce.\nDIPUTADA PRESIDENTA.\nLAURA ARIZMENDI CAMPOS.\nGUERRERO, CONVOCA A TODOS LOS CIUDADANOS\nY CIUDADANAS MEXICANOS RESIDENTES EN EL\nESTADO DE GUERRERO, INTERESADOS EN\nPARTICIPAR EN EL PROCEDIMIENTO DE\nSELECCIÓN Y DESIGNACIÓN DEL TITULAR DE LA\nFISCALÍA GENERAL DEL ESTADO DE GUERRERO,\nCONFORME A LAS BASES QUE SE DETALLAN\nDIPUTADO SECRETARIO.\nROGER ARELLANO SOTELO.\nDIPUTADO SECRETARIO.\nARTURO BONILLA MORALES.",
  "ordenamiento": "ACUERDO",
  "jurisdiccion": "GUERRERO",
  "fuente_oficial": "DIARIO OFICIAL DE LA FEDERACION",
  "Fecha de Publicación": "27 DE NOVIEMBRE DE 2014",
  "ULTIMA REFORMA PUBLICADA": "23 de Diciembre de 2014",
  "status": "ABROGADA",
  "es_escaneado": false,
  "tiene_tablas": false,
  "materia": [
    "parlamentario"
  ]
}