{
  "titulo": "Acuerdo PGJDGEL0012012 del Subprocurador de Control Regional y Procedimientos Penales, Encargado de",
  "Contenido": "JUSTICIA DEL ESTADO DE GUERRERO, POR EL QUE SE\nTODOS LOS SERVIDORES PÚBLICOS PARA LA DEBIDA\nO DEL HALLAZGO Y DE LOS INDICIOS, HUELLAS O VESTIGIOS\nDEL HECHO DELICTUOSO, ASÍ COMO DE LOS INSTRUMENTOS,\nOBJETOS O PRODUCTOS DEL DELITO\nABROGADO POR EL ARTÍCULO SEGUNDO TRANSITORIO DEL ACUERDO\nPGJ/DGEL/A/010/2012 DE LA PROCURADORA GENERAL DE JUSTICIA DEL ESTADO DE\nGUERRERO, POR EL QUE SE ESTABLECEN LOS LINEAMIENTOS QUE DEBERÁN OBSERVAR\nTODOS LOS SERVIDORES PÚBLICOS DE LA INSTITUCIÓN PARA LA DEBIDA PRESERVACIÓN Y\nPROCESAMIENTO DEL LUGAR DE LOS HECHOS O DEL HALLAZGO Y DE LOS INDICIOS, HUELLAS\nO VESTIGIOS DEL HECHO DELICTUOSO, ASÍ COMO DE LOS INSTRUMENTOS, OBJETOS O\nPRODUCTOS DEL DELITO, PUBLICADO EN EL PERIÓDICO OFICIAL DEL GOBIERNO DEL ESTADO\nNo. 99 ALCANCE I, DE FECHA 11 DE DICIEMBRE DE 2012.\nTEXTO ORIGINAL\nAcuerdo publicado en el Periódico Oficial del Gobierno del Estado No. 36 Alcance I, el Viernes\n04 de Mayo de 2012.\nACUERDO PGJ/DGEL/001/2012 DEL SUBPROCURADOR DE CONTROL REGIONAL Y\nPROCEDIMIENTOS PENALES, ENCARGADO DE DESPACHO DE LA PROCURADURÍA GENERAL\nDE JUSTICIA DEL ESTADO DE GUERRERO, POR EL QUE SE ESTABLECEN LOS LINEAMIENTOS\nQUE DEBERÁN OBSERVAR TODOS LOS SERVIDORES PÚBLICOS PARA LA DEBIDA\nPRESERVACIÓN Y PROCESAMIENTO DEL LUGAR DE LOS HECHOS O DEL HALLAZGO Y DE LOS\nINDICIOS, HUELLAS O VESTIGIOS DEL HECHO DELICTUOSO, ASÍ COMO DE LOS\nINSTRUMENTOS, OBJETOS O PRODUCTOS DEL DELITO.\nDR. JUAN MANUEL HERRERA CAMPOS, SUBPROCURADOR DE CONTROL REGIONAL Y\nPROCEDIMIENTOS PENALES, ENCARGADO DE DESPACHO DE LA PROCURADURÍA GENERAL\nDE JUSTICIA DEL ESTADO DE GUERRERO, EN EJERCICIO DE LAS FACULTADES QUE ME\nCONFIEREN LOS ARTÍCULOS 21 PÁRRAFO UNO DE LA CONSTITUCIÓN POLÍTICA DE LOS\nESTADOS UNIDOS MEXICANOS; 78 PÁRRAFO UNO DE LA CONSTITUCIÓN POLÍTICA DEL\nLA ADMINISTRACIÓN PÚBLICA DEL ESTADO; 58 DEL CÓDIGO DE PROCEDIMIENTOS PENALES\nLA PROCURADURÍA GENERAL DE JUSTICIA, Y\nCONSIDERANDO\nQue la Ley Orgánica de la Procuraduría General de Justicia del estado de Guerrero, establece en su artículo 29 fracción XVIII, que como facultad indelegable del C. Procurador General de Justicia del\nEstado Expedirá los acuerdos, circulares, instructivos, bases y manuales de organización y\nJUSTICIA DEL ESTADO DE GUERRERO, POR EL QUE SE\nTODOS LOS SERVIDORES PÚBLICOS PARA LA DEBIDA\nO DEL HALLAZGO Y DE LOS INDICIOS, HUELLAS O VESTIGIOS\nDEL HECHO DELICTUOSO, ASÍ COMO DE LOS INSTRUMENTOS,\nOBJETOS O PRODUCTOS DEL DELITO procedimientos, para el buen despacho de los asuntos.\nQue en cumplimiento a la recomendación No. 1VG/2012, de la Comisión Nacional de Derechos\nHumanos, sobre la Investigación de violaciones graves a los Derechos Humanos, relacionada con los hechos ocurridos el 12 de Diciembre de 2011, en la Ciudad de Chilpancingo, Guerrero, en la cual se señala en la Fracción V del numeral 470, en la recomendación CUARTA, que en el caso de la preservación del lugar de los hechos, el Gobernador Constitucional del Estado de Guerrero instruya a quien corresponda, a fin de que se proteja en todo momento el escenario del crimen y el material sensible significativo que se genere en intervenciones policiales, con el propósito de garantizar a la institución del\nMinisterio Público una eficaz investigación de los acontecimientos.\nQue tomando en cuenta que el Código de Procedimientos Penales es un ordenamiento general, abstracto y obligatorio para el Ministerio Público del Fuero Común, los Servicios Periciales del estado y para los integrantes de las Instituciones Policiales, y que no sólo obliga al personal sustantivo adscrito a la Procuraduría General de Justicia del Estado de Guerrero, sino también a los agentes de las\nInstituciones Policiales, incluso estatales y municipales que por su cercanía al lugar de los hechos entran en primera instancia en contacto con los elementos materiales objeto de la cadena de custodia relacionada con delitos del orden Común y Federal.\nQue los artículos 1, 54 y 58 del invocado código procesal, prevé el deber del Ministerio Público, las policías o los funcionarios encargados de practicar en su auxilio diligencias de averiguación previa, de dictar todas las medidas y providencias necesarias para impedir que se pierdan, destruyan o alteren los indicios, huellas o vestigios del hecho delictuoso, así como los instrumentos, objetos o productos del delito, una vez que tengan la noticia del delito.\nQue los citados artículos del ordenamiento adjetivo citado, establece expresamente que la preservación de los indicios, huellas o vestigios del hecho delictuoso, así como los instrumentos, objetos ellos.\nSeguridad Pública, se encuentra comprometida a implementar las medidas conducentes para que la conducta de los servidores públicos que la integran, de manera especial la de los agentes del Ministerio\nPúblico del Fuero Común, Policías Ministeriales, y Peritos, efectivamente se rija por los principios de legalidad, eficiencia, profesionalismo y honradez, previstos por la Constitución Política de los Estados\nUnidos Mexicanos.\nJUSTICIA DEL ESTADO DE GUERRERO, POR EL QUE SE\nTODOS LOS SERVIDORES PÚBLICOS PARA LA DEBIDA\nO DEL HALLAZGO Y DE LOS INDICIOS, HUELLAS O VESTIGIOS\nDEL HECHO DELICTUOSO, ASÍ COMO DE LOS INSTRUMENTOS,\nOBJETOS O PRODUCTOS DEL DELITO\nQue con fundamento en la Ley General del Sistema Nacional de Seguridad Pública, la\nConferencia Nacional de Procuración de Justicia, a la cual pertenece la Procuraduría General de Justicia del Estado de Guerrero, adoptó el Acuerdo CNPJ/XXIV/08/2010, aprobado en la XXIV Asamblea\nPlenaria, por el que se impulsa la suscripción del Acuerdo Marco para la Homologación de Criterios para la Regulación e Instrumentación de la Cadena de Custodia de los Indicios, Huellas o vestigios del Hecho\nDelictuoso y de los Instrumentos, Objetos o Productos del Delito\nConsiderando lo anterior, y para el mejor cumplimiento del deber de preservar la cadena de custodia que prevé el ordenamiento adjetivo estatal, y que impone a los miembros de las Instituciones de\nSeguridad Pública y a todo aquel servidor público, a que entre en contacto con los indicios, objetos, instrumentos o productos del delito, así como para salvaguardar un estricto apego al principio de legalidad, he tenido a bien expedir el siguiente:\nACUERDO PGJ/DGEL/001/2012 DEL SUBPROCURADOR DE CONTROL REGIONAL Y\nPROCEDIMIENTOS PENALES, ENCARGADO DE DESPACHO DE LA PROCURADURÍA GENERAL\nDE JUSTICIA DEL ESTADO DE GUERRERO, POR EL QUE SE ESTABLECEN LOS LINEAMIENTOS\nQUE DEBERAN OBSERVAR TODOS LOS SERVIDORES PUBLICOS PARA LA DEBIDA\nPRESERVACION Y PROCESAMIENTO DEL LUGAR DE LOS HECHOS O DEL HALLAZGO Y DE LOS\nINDICIOS, HUELLAS O VESTIGIOS DEL HECHO DELICTUOSO, ASI COMO DE LOS\nINSTRUMENTOS, OBJETOS O PRODUCTOS DEL DELITO.\nCAPÍTULO I\nDISPOSICIONES PRELIMINARES\nARTÍCULO 1. El presente acuerdo tiene el objeto de establecer los lineamientos siguientes:\nI.- Regular la actuación, que por obligación, deben de seguir los agentes del Ministerio Público, Peritos, agentes de la Policía Ministerial y todos aquellos servidores públicos que deben de intervenir en la integración de la averiguación previa, específicamente en el aseguramiento oportuno de los instrumentos, objetos, productos, huellas y demás vestigios relacionados con el delito;\nII.- Para los efectos de este artículo, los servidores públicos que conozcan de un hecho ilícito, deberán comunicarlo de inmediato al agente del Ministerio Público más próximo al lugar del evento; instrumentos, objetos, productos, huellas y demás vestigios relacionados con el delito;\nIII.- El Ministerio Público, deberá de hacer del conocimiento inmediato a la Policía Ministerial\nJUSTICIA DEL ESTADO DE GUERRERO, POR EL QUE SE\nTODOS LOS SERVIDORES PÚBLICOS PARA LA DEBIDA\nO DEL HALLAZGO Y DE LOS INDICIOS, HUELLAS O VESTIGIOS\nDEL HECHO DELICTUOSO, ASÍ COMO DE LOS INSTRUMENTOS,\nOBJETOS O PRODUCTOS DEL DELITO para el efecto de que acordonen el área donde se haya suscitado el ilícito y evitar que los objetos, productos, huellas y demás vestigios relacionados con el ilícito puedan ser alterados de cualquier forma;\nIV.- En igual forma, el Ministerio Público dará aviso a los servicios periciales, para que éstos aseguren los objetos, productos, huellas y demás vestigios relacionados con el delito, y se puedan emitir los dictámenes periciales que del propio hecho ilícito se desprendan;\nARTÍCULO 2. En términos del artículo 58 del Código de Procedimientos Penales del Estado de\nGuerrero y del artículo 11, fracción VI, de la Ley Orgánica de la Procuraduría General de Justicia del\nEstado, aplicados al presente acuerdo, el procedimiento para el aseguramiento oportuno de los instrumentos, objetos, productos, huellas y demás vestigios relacionados con el delito, tendrá los siguientes mecanismos que se definirán en la forma siguiente:\nI.- Cadena de Custodia: Es el procedimiento de control que se aplica al indicio material, ya sea vestigio, medio de comisión, objeto material o producto relacionado con el delito, desde la localización por parte de una autoridad competente; el cual servirá para la integración y determinación de la averiguación previa y, en su caso, la consignación ante la autoridad judicial.\nII.- Indicios o Evidencias: Son los hechos conocidos de los que se infiere lógicamente la existencia de los hechos que se pretende acreditar, así como los objetos, productos, huellas y demás vestigios, relacionados a la comisión de un delito, que puedan encontrarse en el lugar de los hechos, lugar del hallazgo o en sitio diferente, y que por sus características existe la probabilidad de que tenga alguna relación con la comisión de los hechos que se investiguen, y con el sujeto activo probable responsable de la comisión del ilícito.\nIII.- Preservación del lugar de los hechos y/o del lugar del hallazgo: Es la serie de actos haya cometido el delito, o en donde se haya encontrado algún indicio o evidencia de su comisión, con el objeto de evitar cualquier intromisión indebida o inadecuada que pueda, dañe, altere, descomponga o contamine los indicios o evidencias que se puedan hallar.\nIV.- Procesamiento de los indicios o evidencias.- Es el Procedimiento tendiente a preservar los indicios o evidencias, mismo que está constituido por las siguientes etapas: identificación, fijación, levantamiento, embalaje, traslado, entrega de los indicios a los servicios periciales para la emisión de los dictámenes periciales correspondientes; hecho lo anterior se pondrán a la vista del agente del Ministerio\nPúblico para que de fe de los mismos y se agreguen física o jurídicamente a la averiguación previa.\nJUSTICIA DEL ESTADO DE GUERRERO, POR EL QUE SE\nTODOS LOS SERVIDORES PÚBLICOS PARA LA DEBIDA\nO DEL HALLAZGO Y DE LOS INDICIOS, HUELLAS O VESTIGIOS\nDEL HECHO DELICTUOSO, ASÍ COMO DE LOS INSTRUMENTOS,\nOBJETOS O PRODUCTOS DEL DELITO\nHecho todo lo anterior, el Ministerio Público de acuerdo a la naturaleza las evidencias, determinará si quedan en su poder o se remiten a la Dirección General de Bienes Asegurados de la\nProcuraduría General de Justicia del Estado.\nV.- Registro de Cadena de Custodia.- Es el documento en el que se asentarán, en primer lugar, los nombres y firmas de los agentes de la Policía Ministerial que hayan localizado el lugar donde se hubiera cometido un delito o encontrado un indicio relacionado con el mismo; del agente del Ministerio\nPúblico que haya conocido del hecho; y el o los peritos que hubieren intervenido en el conocimiento y emisión de los dictámenes periciales, descripción de los bienes, características de los mismos, lugar de los hechos y/o del hallazgo y demás relativos para la integración de la averiguación previa.\nVI.- Ubicación de testigos.- Ubicar a personas que puedan aportar elementos de identificación, media filiación y/o retrato hablado.\nVII.- Protocolo de Cadena de Custodia.- Documento elaborado por el Grupo Nacional de\nDirectores de Servicios Periciales en el marco de la Conferencia Nacional de Procuración de Justicia.\nVIII.- Guía para la aplicación de CADENA DE CUSTODIA.- Es el documento que especifica los protocolos a seguir para llevar a cabo correctamente la CADENA DE CUSTODIA (anexo 1).\nARTÍCULO 3. Para los efectos del presente Acuerdo se entenderá por:\nMinisterio Público: El Ministerio Público del Fuero Común.\nPolicía: Policía Ministerial.\nCódigo: El Código de Procedimientos Penales del Estado de Guerrero.\nRegistro: El Registro de CADENA DE CUSTODIA.\nGuía: Guía para la aplicación de la CADENA DE CUSTODIA (anexo 1).\nPolicía: Cualquier Corporación Policiaca que intervenga en la CADENA DE CUSTODIA.\nJUSTICIA DEL ESTADO DE GUERRERO, POR EL QUE SE\nTODOS LOS SERVIDORES PÚBLICOS PARA LA DEBIDA\nO DEL HALLAZGO Y DE LOS INDICIOS, HUELLAS O VESTIGIOS\nDEL HECHO DELICTUOSO, ASÍ COMO DE LOS INSTRUMENTOS,\nOBJETOS O PRODUCTOS DEL DELITO\nCAPÍTULO II\nDEL FUNCIONAMIENTO DEL REGISTRO\nDE CADENA DE CUSTODIA\nARTÍCULO 4. Las actuaciones que se realicen para la preservación del LUGAR DE LOS\nHECHOS Y/O DEL HALLAZGO, y el procesamiento de los indicios o evidencias, hasta que finalice la\nCADENA DE CUSTODIA por orden del agente del Ministerio Público o del Juez, según el caso, se asentarán en el Registro.\nARTÍCULO 5.- A fin de evitar el rompimiento de la CADENA DE CUSTODIA, los servidores públicos que intervengan en las distintas fases del procesamiento de los INDICIOS O EVIDENCIAS desde su búsqueda, traslado a los servicios periciales para la realización de las pruebas correspondientes, así como para su almacenamiento o transferencia a la Dirección General de Bienes\nAsegurados, según el caso, o que por cualquier circunstancia entren en contacto con los indicios o evidencias, deberán asentarse en el Registro, la información correspondiente a su intervención, así como su nombre completo y otros datos que se requieran, su firma autógrafa, así como la razón de la entrega de unos a otros.\nLo anterior, en términos de los artículos 1°, 54° y 58°, del Código y en la forma y términos señalados en la Guía anexa para el Registro.\nAsimismo, en la forma y términos indicados en la Guía, deberán adherir al embalaje de los\nINDICIOS O EVIDENCIAS, las señalizaciones o rótulos correspondientes con los datos que en ella se indican.\nEn el Registro se hará constar quién se encarga del transporte y las condiciones materiales y ambientales en que se dé el traslado de los INDICIOS O EVIDENCIAS. servidores públicos o cualquier persona, incluidos los familiares del fallecido, también se harán constar en el Registro.\nARTÍCULO 6.- El Registro deberá tener el número de averiguación previa, unidad administrativa responsable (área a la que pertenece el servidor público que interviene), número de registro (folio o llamado), ubicación e identificación del lugar incluyendo los croquis, información sobre víctimas, detenidos, testigos o cualquier otra recabada en el LUGAR DE LOS HECHOS Y/O DEL\nHALLAZGO; nombre completo, cargo y firma de los servidores públicos que intervinieron en la\nJUSTICIA DEL ESTADO DE GUERRERO, POR EL QUE SE\nTODOS LOS SERVIDORES PÚBLICOS PARA LA DEBIDA\nO DEL HALLAZGO Y DE LOS INDICIOS, HUELLAS O VESTIGIOS\nDEL HECHO DELICTUOSO, ASÍ COMO DE LOS INSTRUMENTOS,\nOBJETOS O PRODUCTOS DEL DELITO preservación del lugar.\nDe la misma forma, deberá contener datos sobre la identificación, ubicación, recolección o levantamiento, embalaje, traslado y entrega de los INDICIOS O EVIDENCIAS al agente del Ministerio\nPúblico, y de éste a los servicios periciales, medidas tomadas por los peritos para conservar la CADENA\nDE CUSTODIA; así como la autoridad que ordena la disposición final, testigos de la destrucción de los\nINDICIOS O EVIDENCIAS, de ser necesario.\nCAPÍTULO III\nDE LA PRESERVACIÓN DEL LUGAR\nDE LOS HECHOS Y/O DEL HALLAZGO\nARTÍCULO 7.- Los elementos de cualquier corporación policíaca o cualquier integrante de las instituciones de seguridad pública que tengan conocimiento del lugar de los HECHOS Y/O DEL\nHALLAZGO de delitos del orden común o federal, lo harán del conocimiento inmediato del agente del\nMinisterio Público, para fines de la conducción y mando de la investigación del delito y de las instrucciones que, en su caso, les dicte para la preservación del lugar.\nEn el lugar de los HECHOS Y/O DEL HALLAZGO, los elementos de la Policía, deberán:\na) Delimitar la zona e impedir que personas ajenas a los peritos y agentes del Ministerio Público, puedan acceder a ella;\nb) En el dado caso de que hayan ocurrido hechos delictivos con artefactos explosivos, artefactos o sustancias peligrosas, se cerciorarán de que no existan estos elementos o cualquier otro objeto que ponga en riesgo a las víctimas o el lugar de los HECHOS Y/O DEL HALLAZGO, o a la ciudadanía en general, procurando siempre preservar las evidencias en el estado en que se encontraban al momento de su llegada;\nc) Fijar el lugar de los HECHOS Y/O EL HALLAZGO mediante cualquier medio que tengan a su alcance, ya sea a través de fotografías, videograbación, planos, y por escrito, además de detallar la ubicación en que ocurrieron los hechos delictivos.\nd) Organizar a los agentes de la Policía Ministerial y de otras corporaciones que arriben al lugar de los HECHOS Y/O HALLAZGO, con el objeto de que se les asignen tareas de custodia de las zonas delimitadas alejadas de éste.\nJUSTICIA DEL ESTADO DE GUERRERO, POR EL QUE SE\nTODOS LOS SERVIDORES PÚBLICOS PARA LA DEBIDA\nO DEL HALLAZGO Y DE LOS INDICIOS, HUELLAS O VESTIGIOS\nDEL HECHO DELICTUOSO, ASÍ COMO DE LOS INSTRUMENTOS,\nOBJETOS O PRODUCTOS DEL DELITO\ne) Localizar, entrevistar y custodiar en su caso, a posibles testigos presenciales de los hechos, bajo las instrucciones del Agente del Ministerio Público;\nf) Detallar las condiciones en las que se encontraba el lugar de los HECHOS Y/O DEL\nHALLAZGO, al momento de su arribo y revisión, cuando informe al agente del Ministerio Público y redacte su informe; sin perjuicio de la elaboración del informe policial homologado, y\ng) Las demás acciones necesarias para la preservación del lugar de los HECHOS Y/O DEL\nHALLAZGO.\nPara efectos de la Preservación del Lugar de los HECHOS Y/O DEL HALLAZGO, los Agentes de la Policía que intervengan estarán a lo previsto en la Guía anexa y demás disposiciones aplicables.\nCAPÍTULO IV\nDEL PROCESAMIENTO Y TRATAMIENTO\nDE LOS INDICIOS O EVIDENCIAS\nARTÍCULO 8.- Cuando el agente del Ministerio Público tenga conocimiento directo de la comisión de hechos posiblemente constitutivos de un delito que deba perseguirse de oficio, o bien inmediatamente después de que la Policía le dé cuenta de la detención de individuos en flagrancia y de la existencia de un LUGAR DE LOS HECHOS Y/O DEL HALLAZGO, de conformidad con lo previsto en los artículos 1, 54, Y 58 del Código, el agente del Ministerio Público que prevenga, en caso de que pueda acudir sin retraso al lugar de los HECHOS Y/O DEL HALLAZGO, tendrá que proceder de la manera siguiente:\na) Instruirá a la Policía para que preserve el LUGAR DE LOS HECHOS Y/O DEL HALLAZGO, de conformidad a lo previsto en el capítulo anterior, a la Guía anexa al presente y demás disposiciones aplicables, instruyéndola para que permanezcan los INDICIOS O EVIDENCIAS en el lugar y la forma en que se encuentren, debiendo emitir esta última, el parte informativo correspondiente, evitando acceder a dicho lugar de los hechos.\nb) Acudirá al LUGAR DE LOS HECHOS Y/O DEL HALLAZGO asistido por el personal pericial correspondiente, así como con los agentes de la corporación policial que se encuentren en el lugar, elementos de los servicios de emergencia, de ser el caso, así como el personal que deberá intervenir de acuerdo a las circunstancias.\nc) Tendrá que revisar que la Policía haya preservado correctamente, y y conforme a lo dispuesto\nJUSTICIA DEL ESTADO DE GUERRERO, POR EL QUE SE\nTODOS LOS SERVIDORES PÚBLICOS PARA LA DEBIDA\nO DEL HALLAZGO Y DE LOS INDICIOS, HUELLAS O VESTIGIOS\nDEL HECHO DELICTUOSO, ASÍ COMO DE LOS INSTRUMENTOS,\nOBJETOS O PRODUCTOS DEL DELITO en este instrumento el lugar de los HECHOS Y/O DEL HALLAZGO, asimismo, le solicitará a la Policía además del informe policial homologado que rinda, un informe detallado de las circunstancias ocurridas, en su caso de la puesta a disposición de los detenidos.\nd) Dará la orden a los elementos de los Servicios Periciales que arriben al lugar, para que realicen el procesamiento de los indicios o evidencias, en términos de lo dispuesto en los artículos 54 y\n58 del Código de Procedimientos Penales del Estado de Guerrero y la Guía anexa, procediendo, en lo conducente, en los términos previstos en el Código de Procedimientos Penales del Estado de Guerrero y en el Artículo 12 del presente Acuerdo.\ne) Cerciorarse de que los peritos, que arriben al LUGAR DE LOS HECHOS Y/O HALLAZGO, cuenten con Identificación oficial expedida por la Procuraduría, así como la vestimenta y el material necesario para llevar a cabo adecuadamente el procesamiento de los INDICIOS O EVIDENCIAS.\nARTÍCULO 9. Si el lugar de los HECHOS Y/O HALLAZGO, se encuentra en una localidad que cuente con Unidades de Policía facultadas, y éstas descubran indicios o evidencias, deberán informar de esta circunstancia de manera inmediata al agente del Ministerio Público, debiendo proceder, en su caso, a la realización de las distintas etapas del procesamiento: búsqueda o identificación, fijación, recolección o levantamiento, embalaje, traslado de los indicios o evidencias, entrega o puesta a disposición al agente del Ministerio Público, de conformidad con lo dispuesto en los artículos 54 y 58 del Código de\nProcedimientos Penales del Estado de Guerrero y a lo señalado en la Guía anexa, los protocolos que al efecto se emitan y demás disposiciones aplicables en el estado. De la misma forma actuarán cuando el agente del Ministerio Público solicite su intervención para el conocimiento de los indicios o evidencias.\nLos agentes de policía harán lo mismo, en los casos en que, teniendo el agente del Ministerio\nPúblico conocimiento directo de la comisión del delito, solicite su intervención para el procesamiento de los indicios o evidencias señaladas en el párrafo anterior.\nEVIDENCIAS, se hará en su totalidad, en sus respectivos contenedores, cuando su volumen así lo permita, o bien, las muestras representativas, cuando se trate de indicios o evidencias cuyo volumen o características físicas no permita un manejo adecuado de los mismos; tales circunstancias se harán constar en el Registro, en los partes policiales y actas circunstanciadas o complementarias correspondientes.\nARTÍCULO 10. El agente del Ministerio Público, en los supuestos del primer párrafo del artículo anterior, podrá presentarse en el LUGAR DE LOS HECHOS Y/O DEL HALLAZGO cuando lo considere\nJUSTICIA DEL ESTADO DE GUERRERO, POR EL QUE SE\nTODOS LOS SERVIDORES PÚBLICOS PARA LA DEBIDA\nO DEL HALLAZGO Y DE LOS INDICIOS, HUELLAS O VESTIGIOS\nDEL HECHO DELICTUOSO, ASÍ COMO DE LOS INSTRUMENTOS,\nOBJETOS O PRODUCTOS DEL DELITO necesario, caso en el cual tendrá que recabar de las Unidades de Policía Facultadas, todos los INDICIOS\nO EVIDENCIAS, sus respectivos contenedores; dicha entrega se hará constar en el Registro de, las actas, partes policiales o en su defecto los documentos donde se haya dejado constancia del estado en que fueron hallados por los agentes de Policía, para efectos de la averiguación previa y la práctica de las respectivas diligencias periciales.\nArtículo 11. Respecto de los efectos previstos en los artículos 54 y 58 del Código, el Agente del\nMinisterio Público podrá autorizar a las Unidades de Policía facultadas, la realización de la inspección policial a que se refieren los mencionados preceptos, cuando por las circunstancias de la hora, la lejanía del lugar, el tiempo que tarde en llegar al LUGAR DE LOS HECHOS Y/O DEL HALLAZGO, pueda repercutir en la pérdida de los indicios o evidencias.\nEn el supuesto antes señalado, las unidades de Policía Facultadas procederán en estricto apego a lo previsto en los artículos del Código mencionados en el párrafo anterior y en el presente Acuerdo, asentando los datos correspondientes en el Registro. En el caso de que las Unidades de Policía facultadas, carezcan de dicho formato, el acta circunstanciada de la inspección se anexará a la indagatoria de manera provisional y con posterioridad la hará constar en el Registro.\nArtículo 12. Una vez que las Unidades de Policía Facultadas, hayan entregado los INDICIOS O\nEVIDENCIAS, respecto del probable hecho delictuoso, el agente del Ministerio Público deberá de proceder de la siguiente manera:\na) Verificará inmediatamente, auxiliándose de los peritos necesarios, para que, de conformidad con el presente Acuerdo, a su Guía anexa, y a los artículos 54 y 58 del Código, se sigan los procedimientos adecuados, con el objeto de darles una adecuada preservación a los INDICIOS O\nEVIDENCIAS;\nb) De ser el caso, que no se observen los artículos 54 y 58 del Código, el presente Acuerdo y su\nGuía anexa, para dar el adecuado procesamiento a los INDICIOS O EVIDENCIAS, lo hará constar en la respectiva Averiguación Previa, además de que deberá dar vista para los efectos procedentes, a las autoridades que correspondan;\nc) Una vez que se hayan realizado los dictámenes periciales correspondientes señalados en el párrafo anterior, resolverá, de ser procedente, el aseguramiento de los INDICIOS O EVIDENCIAS, su devolución o destrucción, en términos de los dispuesto por los artículos 54, 58 y 73 del Código y demás disposiciones aplicables. De darse los supuestos anteriores tendrá que ser asentado en el Registro;\nJUSTICIA DEL ESTADO DE GUERRERO, POR EL QUE SE\nTODOS LOS SERVIDORES PÚBLICOS PARA LA DEBIDA\nO DEL HALLAZGO Y DE LOS INDICIOS, HUELLAS O VESTIGIOS\nDEL HECHO DELICTUOSO, ASÍ COMO DE LOS INSTRUMENTOS,\nOBJETOS O PRODUCTOS DEL DELITO\nd) Tendrá que determinar el aseguramiento de los medios probatorios recabados, INDICIOS O\nEVIDENCIAS, entre los que se podrán encontrar, el objeto material o producto del delito.\ne) Deberá anexar a la Averiguación Previa, una copia certificada del Registro, en donde se tendrá que hacer constar la identidad de las personas que intervengan en la CADENA DE CUSTODIA y estén autorizadas para dar el procesamiento adecuado a los INDICIOS O EVIDENCIAS, de acuerdo a lo dispuesto con el artículo 58 del Código.\nf) Instruirá el traslado de los Indicios o Evidencias, para que sean entregados a los Servicios\nPericiales, para que se lleven a cabo las pruebas y diligencias periciales respectivas.\ng) Transferirá los bienes asegurados a la Dirección General de Bienes asegurados, cuando ésta deba de administrarlos, previa emisión de los dictámenes periciales correspondientes; instruyendo a dicha dirección, al cumplimiento de la CADENA DE CUSTODIA, con fundamento en los artículos 54, 58 y\n72 del Código y 16 del Reglamento de la Ley Orgánica de la Procuraduría General de Justicia del Estado.\nDichos actos de entrega y recepción se asentarán en el Registro.\nArtículo 13. En el momento en que la Dirección General de los Servicios Periciales reciba en sus instalaciones los elementos materiales, objeto de la CADENA DE CUSTODIA, se procederá a lo siguiente:\na) El servidor público que corresponda, con inmediatez, diligencia y cautela, evitará la mínima alteración a los mencionados objetos, y los turnará al laboratorio o al perito correspondiente con el objeto de que se realicen las pruebas periciales a que haya lugar.\nb) El perito o grupo de ellos designados, tendrán que garantizar inmediatamente el correcto procesamiento de los INDICIOS O EVIDENCIAS.\nc) Cuando el INDICIO O EVIDENCIA no haya sido resguardado debidamente conforme al\nCódigo, a este Acuerdo y su Guía, sin perjuicio de practicar los peritajes que se le hayan instruido, el perito o el encargado del grupo de peritos, deberá dar vista al agente del Ministerio Público que\nCorresponda.\nd) De conformidad con el artículo 109 del código, cuando el reconocimiento recaiga sobre objetos que se consuman al ser analizados, se procurará conservar una muestra de ellos, a menos que sea indispensable consumirlos durante el primer reconocimiento que se haga, lo anterior deberá de\nJUSTICIA DEL ESTADO DE GUERRERO, POR EL QUE SE\nTODOS LOS SERVIDORES PÚBLICOS PARA LA DEBIDA\nO DEL HALLAZGO Y DE LOS INDICIOS, HUELLAS O VESTIGIOS\nDEL HECHO DELICTUOSO, ASÍ COMO DE LOS INSTRUMENTOS,\nOBJETOS O PRODUCTOS DEL DELITO hacerse constar en el acta respectiva.\ne) Los Dictámenes respectivos deberán ser enviados al agente del Ministerio Público para integrar la Averiguación Previa, en conjunto con los INDICIOS O EVIDENCIAS restantes, los cuales deberán de ser almacenados para diligencias posteriores o, de ser el caso, deberán de ser destruidos. En el caso de sustancias tóxicas, peligrosas o dañinas para el ambiente, deberán ser almacenadas o destruidas, de conformidad a la legislación vigente en la materia.\nf) En los casos señalados en el párrafo anterior, o cuando a juicio del perito los Indicios o\nEvidencias requieran de un procesamiento especial, el Agente del Ministerio Público deberá instruir a los servicios periciales para que se tomen las medidas y providencias necesarias para su custodia y conservación.\ng) Cuando por disposición de la ley se deban conservar los INDICIOS O EVIDENCIAS para su identificación por testigos o para la práctica de otras diligencias en la averiguación previa o en el proceso, se deberá ordenar su almacenamiento en lugares adecuados y su vigilancia, observando lo dispuesto en los dos párrafos anteriores.\nh) Todas las actuaciones anteriores deberán quedar debidamente asentadas en el Registro.\nArticulo 14. Cuando se practiquen cateos, pruebas de inspección ministerial, inspección ocular y reconstrucción de hechos, el agente del Ministerio Público, peritos y quienes los auxilien en la diligencia, cuando entren en contacto con los INDICIOS O EVIDENCIAS, deberán sujetarse a lo dispuesto en los artículos 1, 54, 58 y 72 del Código, en el presente Acuerdo, en la GUIA anexa y el Registro.\nArticulo 15. En los supuestos del artículo anterior, el agente del Ministerio Público se asistirá de peritos de criminalística de campo, fotografía forense y, en su caso, de perito topógrafo, quienes emplearán, según sea el caso, dibujos, planos topográficos, fotografías generales, fotografías relacionadas, medianos acercamientos, grandes acercamientos y acercamientos con testigos métricos, moldeados, o cualquier otro medio para reproducir los INDICIOS O EVIDENCIAS, haciéndose constar en el acta cuál o cuáles de aquéllos, en qué forma y con qué objeto se emplearon. Para el nombramiento de los peritos siempre se observará lo dispuesto por los artículos 108 y 110 del Código.\nDe la misma forma, se hará la descripción por escrito de todo lo que no hubiere sido posible efectuar, procurando fijar con claridad las características, señales o vestigios que hubiese dejado la comisión del delito, el instrumento o medio que considere que probablemente se haya empleado y la forma en que se hubiere usado. La mencionada descripción será responsabilidad del servidor público que\nJUSTICIA DEL ESTADO DE GUERRERO, POR EL QUE SE\nTODOS LOS SERVIDORES PÚBLICOS PARA LA DEBIDA\nO DEL HALLAZGO Y DE LOS INDICIOS, HUELLAS O VESTIGIOS\nDEL HECHO DELICTUOSO, ASÍ COMO DE LOS INSTRUMENTOS,\nOBJETOS O PRODUCTOS DEL DELITO intervenga y se hará constar en el Registro al cual se le podrán anexar tantas fojas como sean necesarias. Todo lo anterior, con fundamento en los artículos 1o, 54 y 58 del Código.\nCAPÍTULO V\nDE LAS RESPONSABILIDADES\nEN MATERIA DE CADENA DE CUSTODIA\nArtículo 16. En cualquier fase del procesamiento de los INDICIOS O EVIDENCIAS, que causen la alteración, daño, o pérdida de los citados elementos materiales o quebranten la CADENA DE\nCUSTODIA, los servidores públicos que intervengan tanto en la PRESERVACION DEL LUGAR DE LOS\nHECHOS Y/O DEL HALLAZGO, quedarán sujetos a la responsabilidad administrativa o penal, que por acción u omisión les corresponda.\nAdemás de lo dispuesto en el párrafo anterior, serán sometidos al procedimiento administrativo correspondiente quienes no hagan constar en el Registro sus datos personales y los demás datos requeridos relacionados con su intervención en la CADENA DE CUSTODIA, de conformidad con este\nAcuerdo y su Guía.\nArtículo 17. Las Unidades de Policía Facultadas, agente del Ministerio Público, peritos y cualquier otra autoridad que de acuerdo a sus atribuciones y a lo dispuesto por la normatividad aplicable, podrán intervenir en el proceso de CADENA DE CUSTODIA, en términos de lo dispuestos en los artículos\n1o., 54 y 58 del Código.\nCuando a criterio del agente del Ministerio Público y por falta del personal facultado para ello de acuerdo al párrafo anterior, tenga la necesidad de solicitar el auxilio de particulares en cualquier etapa de la CADENA DE CUSTODIA, bajo su más estricta responsabilidad podrá hacerlo, siempre y cuando quede detallada la forma, las circunstancias y los datos generales de las personas que intervinieron, así como la justificación de por qué no lo pudo realizar personal facultado.\nArtículo 18. El Ministerio Público podrá ordenar las medidas que sean necesarias para que los cuerpos policiales preserven EL LUGAR DE LOS HECHOS Y/O DEL HALLAZGO.\nCapítulo VI\nDe la Terminación de la Cadena de Custodia en la etapa de Averiguación Previa.\nArtículo 19. En la etapa de averiguación previa, la CADENA DE CUSTODIA termina por\nJUSTICIA DEL ESTADO DE GUERRERO, POR EL QUE SE\nTODOS LOS SERVIDORES PÚBLICOS PARA LA DEBIDA\nO DEL HALLAZGO Y DE LOS INDICIOS, HUELLAS O VESTIGIOS\nDEL HECHO DELICTUOSO, ASÍ COMO DE LOS INSTRUMENTOS,\nOBJETOS O PRODUCTOS DEL DELITO resolución fundada y motivada del agente del Ministerio Público, bajo su estricta responsabilidad, previa la realización de las pruebas y diligencias periciales necesarias, en los siguientes casos:\na) Cuando acuerde transferir bienes que puedan ser objeto de prueba, para su administración por la Dirección General de Bienes Asegurados DGBA, en los términos previstos por el artículo 72 del\nCódigo y 16 del Reglamento de la Ley Orgánica de la procuraduría General de Justicia del Estado de\nGuerrero;\nb) En los casos en los que la ley determine la destrucción de los bienes, el cierre de la CADENA\nDE CUSTODIA deberá asentarse en el Registro, exponiendo las características que motivan tal acción.\nc) Para el efecto de que proceda la devolución de bienes, de acuerdo a la normatividad aplicable, deberá detallarse en el Registro en conjunto con la firma de la entrega-recepción.\nd) En los casos en que de la verificación de la PRESERVACION DEL INDICIO Y/O EVIDENCIA tanto por parte del Agente del Ministerio Público responsable, como de los Peritos, resulte que estos han sido modificados de tal forma que perdieron su eficacia para acreditar el hecho o circunstancia de que se trate, deberá asentarlo en la averiguación previa y en el Registro, y dando aviso a las autoridades competentes para efectos de fincar la responsabilidad que corresponda en términos de la Ley de\nResponsabilidades de los Servidores Públicos del Estado de Guerrero, y del Código Penal.\ne) Cuando lo disponga el Código, los bienes considerados INDICIOS O EVIDENCIAS, deberán ser entregados en depósito o por cualquier otro título a su propietario o a Instituciones públicas o privadas, y\nf) En los casos en los que al ejercer la acción penal ponga a disposición de la autoridad judicial competente el INDICIO O EVIDENCIA, para fines del proceso penal, siempre y cuando el agente del\nMinisterio Público ya los haya valorado y realizado las pruebas y diligencias periciales correspondientes.\nEn estos casos se ordenará el almacenamiento y custodia del INDICIO O EVIDENCIA, con el objeto de ser presentado en el proceso penal que corresponda.\nArtículo 20. Para lo no previsto en el presente Acuerdo, se observará lo dispuesto en el Acuerdo\nA/078/12 De la Procuradora General de la República, por el que se establecen las directrices que de los HECHOS O DEL HALLAZGO y de los indicios, huellas o vestigios del hecho delictuoso así como de los instrumentos, objetos o productos del delito, además de los diversos protocolos federales e internacionales en la materia.\nJUSTICIA DEL ESTADO DE GUERRERO, POR EL QUE SE\nTODOS LOS SERVIDORES PÚBLICOS PARA LA DEBIDA\nO DEL HALLAZGO Y DE LOS INDICIOS, HUELLAS O VESTIGIOS\nDEL HECHO DELICTUOSO, ASÍ COMO DE LOS INSTRUMENTOS,\nOBJETOS O PRODUCTOS DEL DELITO\nTRANSITORIOS\nPRIMERO.- El presente Acuerdo entrará en vigor al día siguiente de su publicación en el Diario\nOficial del Gobierno del Estado de Guerrero.\nSEGUNDO.- Se instruye a los titulares de las Subprocuradurías, Dirección General de\nAveriguaciones Previas, Dirección General de la Policía Ministerial, Dirección General de Servicios\nPericiales y Dirección General de Administración y Presupuesto, para que tomen las medidas necesarias para el debido cumplimiento del presente Acuerdo. La omisión será sancionada por la Contraloría interna.\nTERCERO.- La Procuraduría General de Justicia del Estado de Guerrero, por medio de su\nDirección General de Presupuesto y Administración, elaborará los formatos del Registro y distribuirá los ejemplares necesarios entre los servidores públicos y las instituciones de seguridad pública que intervengan en la CADENA DE CUSTODIA.\nCUARTO.- Hasta en tanto se publique el nuevo Reglamento de la Ley Orgánica de la\nProcuraduría General de Justicia del Estado de Guerrero, se denominará a la Policía Facultada, como\nPolicía Ministerial.\nQUINTO.- Se derogan las disposiciones que se opongan al presente Acuerdo.\nChilpancingo, Guerrero, a 30 de abril de 2012.\nEl Subprocurador de Control Regional y Procedimientos Penales, Encargado de Despacho de la\nProcuraduría General de Justicia del Estado de Guerrero.\nDr. Juan Manuel Herrera Campos.Rúbrica.\nANEXO UNO\nDel Acuerdo PGJ/DGEL/001/2012, POR EL QUE SE ESTABLECEN LOS LINEAMIENTOS QUE\nY PROCESAMIENTO DEL LUGAR DE LOS HECHOS O DEL HALLAZGO Y DE LOS INDICIOS,\nJUSTICIA DEL ESTADO DE GUERRERO, POR EL QUE SE\nTODOS LOS SERVIDORES PÚBLICOS PARA LA DEBIDA\nO DEL HALLAZGO Y DE LOS INDICIOS, HUELLAS O VESTIGIOS\nDEL HECHO DELICTUOSO, ASÍ COMO DE LOS INSTRUMENTOS,\nOBJETOS O PRODUCTOS DEL DELITO\nGUÍA PARA LA APLICACIÓN\nDE LA CADENA DE CUSTODIA\nÍNDICE\nIntroducción.\nObjetivo General.\nObjetivos Específicos.\nMarco Jurídico.\nDefiniciones.\nProceso 1. Conocimiento de la comisión de un delito.\nProceso 2. Preservación del lugar de los hechos y/o del hallazgo.\n2.1 Custodia del lugar de los hechos y/o del hallazgo\n2.2 Ubicación e Identificación del lugar de los hechos y/o del hallazgo.\n2.3 Localización de posibles testigos.\n2.4 Registro en el Registro de cadena de custodia.\nProceso 3. Procesamiento de los indicios o evidencias del delito.\n3.1 Identificación, ubicación y fijación de los indicios o evidencias.\n3.2 Recolección, embalaje y traslado de los indicios o evidencias.\nProceso 4. Integración en la averiguación previa de la cadena de custodia.\n4.1 De la entrega de los indicios o evidencias al agente del Ministerio Público.\nJUSTICIA DEL ESTADO DE GUERRERO, POR EL QUE SE\nTODOS LOS SERVIDORES PÚBLICOS PARA LA DEBIDA\nO DEL HALLAZGO Y DE LOS INDICIOS, HUELLAS O VESTIGIOS\nDEL HECHO DELICTUOSO, ASÍ COMO DE LOS INSTRUMENTOS,\nOBJETOS O PRODUCTOS DEL DELITO\n4.2 Registro de la integración de la cadena de custodia en la averiguación previa.\nProceso 5. Responsabilidades en la cadena de custodia.\nProceso 6. Pérdida de los indicios o evidencias.\nProceso 7. Solicitud de Dictámenes Periciales de los indicios o evidencias.\nProceso 8. Realización de Pruebas Periciales.\n8.1. De los indicios o evidencias consistentes en muestras biológicas.\nProceso 9. Almacenamiento de los indicios o evidencias.\nProceso 10. Terminación de la cadena de custodia.\nDiagrama de Flujo.\nINTRODUCCIÓN\nConsiderando las nuevas tendencias a nivel mundial para garantizar la preservación de lugar de los hechos y/o hallazgo, la Reforma Constitucional al Sistema de Justicia Penal, así como el cumplimiento a la recomendación No. 1VG/2012, de la Comisión Nacional de Derechos Humanos, sobre la\nInvestigación de violaciones graves a los Derechos Humanos, relacionada con los hechos ocurridos el 12 de Diciembre de 2011, en la Ciudad de Chilpancingo, Guerrero, en la cual se señala en la Fracción V del numeral 470, en la recomendación CUARTA, que en el caso de la preservación del lugar de los hechos, el Gobernador Constitucional del Estado de Guerrero instruya a quien corresponda, a fin de que se intervenciones policiales, con el propósito de garantizar a la institución del Ministerio Publico xana eficaz investigación de los acontecimientos, hace necesario formular un nuevo procedimiento para garantizar la preservación del lugar de los hechos, del hallazgo y de los indicios, huellas o vestigios del hecho delictuoso, así como de los instrumentos, objetos o productos del delito, relacionados con la comisión de los delitos a nivel estatal, es decir, la salvaguarda de la cadena de custodia.\nPor lo anterior, es de urgente necesidad especificar los procesos mediante los cuales deben conducirse, los elementos de las Instituciones Policiales de los tres órdenes de gobierno y/o los peritos,\nJUSTICIA DEL ESTADO DE GUERRERO, POR EL QUE SE\nTODOS LOS SERVIDORES PÚBLICOS PARA LA DEBIDA\nO DEL HALLAZGO Y DE LOS INDICIOS, HUELLAS O VESTIGIOS\nDEL HECHO DELICTUOSO, ASÍ COMO DE LOS INSTRUMENTOS,\nOBJETOS O PRODUCTOS DEL DELITO bajo la conducción y mando del Ministerio Público del Fuero Común, en el procedimiento de control que se aplica al indicio relacionado con el delito, así como al instrumento, objeto o producto, desde su localización, hasta que ha sido valorado por la autoridad ministerial o judicial competente, y que tiene como objeto no viciar el manejo que de él se haga, para evitar alteraciones, daños, sustitución, contaminación, destrucción, o cualquier acción que varíe su significado original.\nCon el objeto de cumplir con todo lo mencionado y derivado del Acuerdo del Subprocurador de\nControl Regional y Procedimientos Penales y Encargado de Despacho de la Procuraduría General de\nJusticia del Estado de Guerrero, por el que se establecen los lineamientos que deberán observar los\nAgentes del Ministerio Público del Fuero Común, Policías y Peritos para la debida preservación del lugar de los hechos y/o del hallazgo y de los indicios, en el que se detallan los datos e información necesaria para asegurar la integridad de los mismos, se emite la presente guía, a efecto de facilitar, la identificación y aplicación de los procedimientos técnico-jurídicos-científicos en el lugar de los hechos y/o del hallazgo, así como para el procesamiento de los indicios y evidencias, con el fin de custodiar el material probatorio.\nAsimismo, permitirá la identificación y aplicación de los formatos relativos al Registro de Cadena de\nCustodia.\nPor lo antes mencionado, los elementos de las corporaciones policiales de los tres órdenes de gobierno y los servidores públicos que intervengan en la escena de los HECHOS Y/O HALLAZGO de delitos del orden estatal, contarán con medidas y procedimientos estandarizados que permitan un trabajo coordinado y eficiente, garantizando la adecuada Procuración de Justicia en el estado de Guerrero.\nOBJETIVO GENERAL\nDeterminar y aplicar los procedimientos jurídicos, técnicos y científicos, que realizarán los elementos de las corporaciones policiales y/o peritos, mismos que coadyuvarán con el Agente del\nMinisterio Público del Fuero Común para garantizar la adecuada preservación del lugar de los hechos y/o hallazgo de los Indicios o evidencias, en la integración de una Averiguación Previa, que derive de un probable hecho delictuoso.\nOBJETIVOS ESPECÍFICOS\n1. Identificación del marco jurídico aplicable a la cadena de custodia.\n2. Orientación y capacitación del personal policial de los tres órdenes de gobierno, que participen en la cadena de custodia en términos de lo dispuesto por los artículos 1o, 54 y 58 del Código de\nProcedimientos Penales del Estado de Guerrero.\nJUSTICIA DEL ESTADO DE GUERRERO, POR EL QUE SE\nTODOS LOS SERVIDORES PÚBLICOS PARA LA DEBIDA\nO DEL HALLAZGO Y DE LOS INDICIOS, HUELLAS O VESTIGIOS\nDEL HECHO DELICTUOSO, ASÍ COMO DE LOS INSTRUMENTOS,\nOBJETOS O PRODUCTOS DEL DELITO\n3. Identificación en el Diagrama de Flujo del procedimiento en materia de Cadena de Custodia.\n4. Identificación y aplicación de los procesos, procedimientos legales y técnico-científicos en la\nCadena de Custodia.\n5. Conocimiento y aplicación los formatos relativos al Registro de la Cadena de Custodia.\n6. Conocimiento de las responsabilidades de los servidores públicos involucrados en la Cadena de Custodia.\nMARCO JURÍDICO\nI. Constitución Política de los Estados Unidos Mexicanos, publicada en el Diario Oficial de la\nFederación el 05-II-1917, y sus reformas y adiciones.\nII. Código de Procedimientos Penales, publicado en el Periódico Oficial del Gobierno del Estado de Guerrero el 14- XI-1986, y sus reformas y adiciones.\nIII. Ley Orgánica de la Procuraduría General de Justicia del Estado de Guerrero No. 193, publicada en el Diario Oficial del Gobierno del estado de Guerrero, el 13 de Febrero de 2004.\nIV. Reglamento de la Ley Orgánica de la Procuraduría General de Justicia No. 193, publicado en el Periódico Oficial del Gobierno del Estado de Guerrero del 8 de Febrero de 2005.\nDEFINICIONES\nACORDONAMIENTO.- Es la acción de delimitar el lugar de los hechos o del hallazgo, mediante el uso de cinta, cuerdas o barreras naturales, como el área presumible en donde se cometió el delito.\nALMACENAMIENTO.- Es el depósito de los indicios o evidencias en los lugares previamente establecidos con características mínimas necesarias, para la conservación de los mismos durante el autoridad competente.\nAMPFC. Es el agente del Ministerio Público del Fuero Común, que conoce de los hechos deictivos.\nJUSTICIA DEL ESTADO DE GUERRERO, POR EL QUE SE\nTODOS LOS SERVIDORES PÚBLICOS PARA LA DEBIDA\nO DEL HALLAZGO Y DE LOS INDICIOS, HUELLAS O VESTIGIOS\nDEL HECHO DELICTUOSO, ASÍ COMO DE LOS INSTRUMENTOS,\nOBJETOS O PRODUCTOS DEL DELITO\nCADENA DE CUSTODIA.- El procedimiento de control que se aplica al indicio o evidencia material ya sea vestigio, huella, medio de comisión, objeto material o producto relacionado con el delito, desde la localización por parte de una autoridad, policía o agente del Ministerio Público, hasta que la autoridad competente ordene su conclusión, según se trate de la averiguación previa o el proceso penal.\nCPP.- Código de Procedimientos Penales del Estado de Guerrero.\nEMBALAJE.- Son las técnicas de manejo adecuadas y de conservación que se hacen para guardar, inmovilizar y proteger un indicio o evidencia, dentro de algún recipiente protector adecuado para la naturaleza del mismo, con el objeto de mantener su integridad para su posterior estudio y análisis.\nINDICIO O EVIDENCIA.- Son las huellas, vestigios y demás elementos materiales del hecho delictuoso, que puedan encontrarse en el lugar de los hechos y/o lugar del hallazgo y que por sus características existe la probabilidad de que tenga alguna relación con la comisión del delito que se investiga.\nLUGAR DE LOS HECHOS.- Es el espacio material o escena del crimen, donde presuntamente se cometió el delito que se investiga y que por ello puede contar con evidencias relacionadas con la investigación.\nLUGAR DEL HALLAZGO.- Es el espacio material donde se encuentran elementos que pueden ser considerados como evidencias, en la integración de una investigación por la comisión de un delito.\nPERITO: Especialista o experto en una ciencia arte u oficio.\nPOLICIA.- Integrante de todas las instituciones policiales que tienen el deber de preservar el lugar de los hechos e indicios o huellas del delito.\nRCC.- Registro de cadena de custodia es el formato o formatos en el que se asentarán nombres de custodia desde su inicio hasta su final, así como la descripción de los indicios o evidencias, características de las mismas, tales como dueño, lugar de los hechos y/o del hallazgo y demás relativos y relevantes para la averiguación previa.\nUNIDADES DE POLICIA FACULTADAS.- Agentes de la Policía capacitados y facultados por los\nJUSTICIA DEL ESTADO DE GUERRERO, POR EL QUE SE\nTODOS LOS SERVIDORES PÚBLICOS PARA LA DEBIDA\nO DEL HALLAZGO Y DE LOS INDICIOS, HUELLAS O VESTIGIOS\nDEL HECHO DELICTUOSO, ASÍ COMO DE LOS INSTRUMENTOS,\nOBJETOS O PRODUCTOS DEL DELITO\nPROCESO 1. CONOCIMIENTO DE LA COMISÓN DE UN DELITO.\nCuando los agentes de POLICIA conozcan o descubran el posible lugar de los hechos y/o del hallazgo de delitos presumiblemente del orden Común, lo harán saber inmediatamente al agente del\nMinisterio Público del Fuero Común o a quien legalmente lo sustituya, para que éste lo haga del conocimiento del Agente del Ministerio Público del Fuero Común.\nO bien, cuando el agente del Ministerio Público del Fuero Común conozca directamente de los hechos delictivos, instruirá a la Policía el aseguramiento, preservación del lugar y de los indicios o evidencias.\nPROCESO 2. PRESERVACIÓN DEL LUGAR DE LOS HECHOS Y/O DEL HALLAZGO.\n2.1 Custodia del lugar de los hechos y/o del hallazgo.\nCualquier servidor público o agente de la policía, al llegar al lugar de los hechos y/o del hallazgo deberá asegurar o custodiar el lugar empleando técnicas adecuadas de acordonamiento a fin de impedir que personas ajenas al personal ministerial, pericial y/o unidades de policía facultadas accedan al lugar.\n2.2 Ubicación e identificación del lugar de los hechos y/o del hallazgo.\nUna vez tomadas las medidas para la custodia del lugar, los agentes de POLICIA, procederán a:\na) Precisar la ubicación del lugar, con domicilio y croquis del mismo.\nb) Realizar una fijación fotográfica y/o de video descriptiva.\nc) Describir de lo general a lo particular y detalladamente por escrito, mediante el uso de diagramas o planos del lugar de los hechos y/o del hallazgo.\nd) Realizar una observación general del lugar, entendiendo a ésta como un proceso dentro de la investigación.\n2.3 Localización de posibles testigos.\nLos agentes de Policía, bajo las instrucciones del agente del Ministerio Público del Fuero\nComún, procederán a la localización de testigos presenciales de los hechos delictivos, si existieran, y recabarán la información básica de los mismos con la finalidad de identificarlos, contar con datos suficientes para su localización, en caso de ser necesario su testimonio, así como con datos que puedan auxiliar en la identificación y ubicación de indicios o evidencias.\nJUSTICIA DEL ESTADO DE GUERRERO, POR EL QUE SE\nTODOS LOS SERVIDORES PÚBLICOS PARA LA DEBIDA\nO DEL HALLAZGO Y DE LOS INDICIOS, HUELLAS O VESTIGIOS\nDEL HECHO DELICTUOSO, ASÍ COMO DE LOS INSTRUMENTOS,\nOBJETOS O PRODUCTOS DEL DELITO\n2.4 Registro en el Registro de Cadena de Custodia.\nToda actuación correspondiente a las etapas señaladas en los puntos 2.1 a 2.3 deberán asentarse en el Registro de cadena de custodia, por los servidores públicos que intervinieron.\nPROCESO 3. PROCESAMIENTO DE LOS INDICIOS O EVIDENCIAS DEL DELITO.\n3.1 Ubicación, identificación y fijación de los indicios o evidencias en el lugar de los hechos y/o del hallazgo.\nLas UNIDADES DE POLICIA FACULTADAS y/o peritos deberán:\n1. Observar en forma metódica, completa, minuciosa y sistemática el lugar de los hechos y/o del hallazgo con la finalidad de buscar o identificar la existencia de indicios o evidencias de la probable comisión de un hecho delictuoso.\n2. Efectuar la búsqueda de todo material sensible, significativo (indicio o evidencia) relacionado con la investigación, a través de los protocolos establecidos, así como de los métodos y técnicas de búsqueda recomendados por la investigación criminalística.\nLa localización, búsqueda o rastreo debe hacerse en las mejores condiciones, se debe hacer preferentemente con luz natural o con una buena iluminación; así como con instrumentos ópticos adecuados.\n3. Posteriormente a la observación y ubicación de los indicios, se procederá a fijarlos mediante técnicas como la fotografía, videograbación, planimetría, cintas magnetofónicas y por escrito.\n4. Una vez localizado cada indicio o evidencia, se deberá iniciar el proceso para su registro, asignándole el número que le corresponderá durante todo el procedimiento penal, anotándolo en una tarjeta, etiqueta u otro medio con la leyenda \"INDICIO o EVIDENCIA N°\".\n5. Proteger los indicios o evidencias que se encuentran a la intemperie.\n3.2 Recolección, embalaje y traslado de los indicios o evidencias.\nLas unidades de policía y/o los peritos, una vez que ubicaron, fijaron e identificaron los indicios o evidencias, deberán:\n1. Realizar un inventario de los mismos, con su descripción y estado en que fueron encontrados.\n2. Realizar el levantamiento utilizando los protocolos establecidos y las técnicas adecuadas en la investigación criminalística.\n3. Embalar las evidencias inventariadas en el empaque o contenedor adecuado, debidamente cerrado y etiquetado, y en su caso sellado.\nLa etiqueta deberá contener los datos siguientes:\n- Fecha y hora.\nJUSTICIA DEL ESTADO DE GUERRERO, POR EL QUE SE\nTODOS LOS SERVIDORES PÚBLICOS PARA LA DEBIDA\nO DEL HALLAZGO Y DE LOS INDICIOS, HUELLAS O VESTIGIOS\nDEL HECHO DELICTUOSO, ASÍ COMO DE LOS INSTRUMENTOS,\nOBJETOS O PRODUCTOS DEL DELITO\n- Número de indicio o evidencia.\n- Número de registro (folio o llamado).\n- Domicilio exacto del lugar del hecho y/o hallazgo, ubicación exacta del lugar en donde el indicio fue recolectado, descripción del material.\n- Observaciones\n- Nombre completo sin abreviaturas del agente policial, perito o auxiliar responsable de la recolección y el embalaje.\n4. Detallar en el Registro de cadena de custodia la forma en que se realizó la recolección, embalaje y etiquetado de las evidencias; así como, las medidas implementadas para garantizar la integridad de las mismas, y las personas que intervinieron recabando la firma de cada una de ellas.\n5. El traslado o transporte de los indicios o evidencias debe ser el adecuado, tomando en cuenta las condiciones climatológicas, la temperatura del transporte, la presión, el movimiento, así como la duración del mismo, ya que pueden producir la destrucción del indicio o evidencia.\nPROCESO 4. INTEGRACIÓN EN LA AVERIGUACIÓN PREVIA DE LA CADENA DE CUSTODIA.\n4.1 De la entrega de los indicios o evidencias al AMPFC y su recepción.\nUna vez concluida la recolección, embalaje y etiquetado, se procederá a la entrega de los indicios o evidencias al agente del Ministerio Público del Fuero Común, para continuar con la cadena de custodia, realizándose un informe que contenga:\n1. La descripción de la intervención policial y/o pericial;\n2. La fecha de entrega;\n3. La hora de entrega;\n4. Nombre y cargo de la persona que entrega;\n5. El tipo de indicio o evidencia;\n6. Indicar si no fueron fotografiadas los indicios o evidencias;\n7. El tipo de embalaje empleado;\n8. Las observaciones al estado en que se reciben los indicios o evidencias;\n9. La fecha de recepción;\n10. La hora de recepción;\n11. Nombre y cargo de la persona que recibe, y\n12. Firma de cada una de ellas.\nPara lo anterior se deberá llenar el Registro de cadena de custodia correspondiente.\nAl momento de recibir los bienes, el agente del Ministerio Público del Fuero Común resolverá sobre su aseguramiento y sobre la continuidad o no del procedimiento, bajo su más estricta\nJUSTICIA DEL ESTADO DE GUERRERO, POR EL QUE SE\nTODOS LOS SERVIDORES PÚBLICOS PARA LA DEBIDA\nO DEL HALLAZGO Y DE LOS INDICIOS, HUELLAS O VESTIGIOS\nDEL HECHO DELICTUOSO, ASÍ COMO DE LOS INSTRUMENTOS,\nOBJETOS O PRODUCTOS DEL DELITO responsabilidad, conforme a las disposiciones aplicables.\n4.2 Registro de la integración de la cadena de custodia en la averiguación previa.\nEl agente del Ministerio Público del Fuero Común hará constar dentro de la averiguación previa, el Registro de cadena de custodia que contenga la cadena de custodia e identificación de las personas que intervinieron.\nPROCESO 5. RESPONSABILIDADES EN LA CADENA DE CUSTODIA.\nEl agente del Ministerio Público del Fuero Común deberá:\n1. Cerciorarse de que se hayan seguido los procedimientos técnicos adecuados para preservar los indicios o evidencias.\nEl rompimiento del etiquetado o de los sellos para la verificación de la cadena de custodia deberá quedar documentado en el Registro de cadena de custodia.\n2. Siendo el caso de que no se haya efectuado la fijación, recolección o levantamiento, embalaje y traslado adecuadamente lo asentará en la averiguación previa.\n3. Dará vista a las autoridades competentes en su caso para efectos de las responsabilidades a que haya lugar.\nPROCESO 6. PÉRDIDA DE INDICIOS.\nCuando los indicios o evidencias se alteren, el Agente del Ministerio Público del Fuero Común determinará con forme a los peritajes requeridos si estos han perdido su valor probatorio, verificando si han sido modificados de tal forma que haya perdido su eficacia para acreditar el hecho o circunstancia de que se trate, en este caso estos deberán concatenarse con otros medios probatorios para tal fin.\nPROCESO 7. DE LOS SERVICIOS PERICIALES.\nLos Servicios Periciales deberán:\n1. Recibir del agente del Ministerio Público del Fuero Común la petición por escrito de dictaminación de los indicios o evidencias.\n2. Recibir las evidencias en base a los protocolos establecidos.\n3. Cerciorarse del correcto manejo de los indicios o evidencias.\n4. Informar por escrito al Agente del Ministerio Público del Fuero Común cuando estas no hayan sido debidamente resguardadas, sin perjuicio de la práctica de los peritajes que se les hubiere instruido.\nJUSTICIA DEL ESTADO DE GUERRERO, POR EL QUE SE\nTODOS LOS SERVIDORES PÚBLICOS PARA LA DEBIDA\nO DEL HALLAZGO Y DE LOS INDICIOS, HUELLAS O VESTIGIOS\nDEL HECHO DELICTUOSO, ASÍ COMO DE LOS INSTRUMENTOS,\nOBJETOS O PRODUCTOS DEL DELITO\nPROCESO 8. REALIZACIÓN DE LAS PRUEBAS PERICIALES.\nLos Servicios Periciales deberán:\n1. Realizar las pruebas técnico-científicas requeridas de cada una de las evidencias.\n2. Informar, para que conste en el acta respectiva, cuando el peritaje recaiga sobre objetos que se consuman al ser analizados; no se permitirá que se verifique el primer análisis sino cuando sobre más de la mitad de la substancia, a no ser que su cantidad sea tan escasa, que los peritos no puedan emitir su opinión sin consumirla por completo.\n3. Remitir los dictámenes u opiniones periciales correspondientes por especialidad para ser integrados a la averiguación previa.\n4. Enviar las evidencias restantes al agente del Ministerio Público del Fuero Común, quien deberá almacenarlas para ser utilizadas en posteriores diligencias o en su caso destruirlos.\n5. Cuando en términos del Código de Procedimientos Penales del Estado de Guerrero, deba ser entregados en depósito o por cualquier otro título a su propietario o a Instituciones públicas o privadas, y\n6. Anexar los documentos que garanticen la cadena de custodia, los cuales serán devueltos para su resguardo de conformidad con el artículo 72 del Código de Procedimientos Penales del Estado de\nGuerrero.\n8.1. De los indicios o evidencias consistentes en muestras biológicas. elementos biológicos probatorios para la investigación, y el imputado acceda voluntariamente a proporcionar muestras de fluido corporal, vello o cabello, o en su defecto, obtenga la autorización judicial, sujeción a lo previsto en el artículo 109 del CPP.\nPROCESO 9. ALMACENAMIENTO DE LOS INDICIOS.\nEl agente del Ministerio Público del Fuero Común deberá:\n1. Ordenar a los servicios periciales en los casos en que la evidencia requiera por su propia\nJUSTICIA DEL ESTADO DE GUERRERO, POR EL QUE SE\nTODOS LOS SERVIDORES PÚBLICOS PARA LA DEBIDA\nO DEL HALLAZGO Y DE LOS INDICIOS, HUELLAS O VESTIGIOS\nDEL HECHO DELICTUOSO, ASÍ COMO DE LOS INSTRUMENTOS,\nOBJETOS O PRODUCTOS DEL DELITO naturaleza un tratamiento especial, que se tomen las medidas y providencias necesarias para su custodia y conservación.\n2. Ordenar su almacenamiento con el empleo de los procedimientos correspondientes, en lugares adecuados y su vigilancia, cuando por disposición de la ley deba conservar las evidencias para su identificación por testigos o para la práctica de otras diligencias en la averiguación previa o en el proceso.\n3. Siempre que sea necesario tener a la vista algunos de los bienes asegurados, se hará constar el estado en que se encontraba su embalaje en el momento en que fue asegurado y si éste ha sufrido alguna alteración voluntaria o accidental, al momento de ser nuevamente requeridos, para lo cual se inscribirán en los registros los signos o señales que lo hagan presumir.\nPROCESO 10. TERMINACIÓN DE LA CADENA DE CUSTODIA.\nLa cadena de custodia en la etapa de averiguación previa, termina por resolución fundada y motivada del Agente del Ministerio Público del Fuero Común, bajo su estricta responsabilidad, previa la realización de las pruebas periciales correspondientes y en los siguientes supuestos:\n1. Cuando acuerde transferir bienes que puedan ser objeto de prueba, para su administración por la Dirección General de Bienes Asegurados de la Procuraduría General de Justicia del Estado de\nGuerrero, en los términos previstos por los artículos 72 del Código de Procedimientos Penales del Estado de Guerrero, en relación con el artículo 16 del Reglamento de la Ley Orgánica de la Procuraduría\nGeneral de Justicia del estado de Guerrero.\n2. En los casos en que proceda en términos de ley la destrucción de los bienes, el cierre de la cadena de custodia deberá asentarse en el Registro de cadena de custodia.\n3. Cuando proceda la devolución de bienes, dicha circunstancia y la firma de la entregarecepción deberán hacerse constar en el Registro de cadena de custodia.\n4. En los casos en que de la verificación de la preservación de las evidencias, tanto por parte del agente del Ministerio Público del Fuero Común responsable, como de los peritos, resulte que éstas han trate, asentándolo en la averiguación previa, en el Registro de cadena de custodia y dando aviso a las\nJUSTICIA DEL ESTADO DE GUERRERO, POR EL QUE SE\nTODOS LOS SERVIDORES PÚBLICOS PARA LA DEBIDA y el Código Penal vigente en la entidad.\n5. En los supuestos procedentes en que el Agente del Ministerio Público del Fuero Común, al ejercer acción penal, ponga los indicios o evidencias a disposición de la autoridad judicial competente para fines del proceso penal y ésta los haya valorado. En estos casos ordenará el almacenamiento y custodia de los indicios o evidencias correspondientes a presentarse en su caso en el proceso penal.\nJUSTICIA DEL ESTADO DE GUERRERO, POR EL QUE SE\nTODOS LOS SERVIDORES PÚBLICOS PARA LA DEBIDA\nJUSTICIA DEL ESTADO DE GUERRERO, POR EL QUE SE\nTODOS LOS SERVIDORES PÚBLICOS PARA LA DEBIDA\nJUSTICIA DEL ESTADO DE GUERRERO, POR EL QUE SE\nTODOS LOS SERVIDORES PÚBLICOS PARA LA DEBIDA\nJUSTICIA DEL ESTADO DE GUERRERO, POR EL QUE SE\nTODOS LOS SERVIDORES PÚBLICOS PARA LA DEBIDA\nJUSTICIA DEL ESTADO DE GUERRERO, POR EL QUE SE\nTODOS LOS SERVIDORES PÚBLICOS PARA LA DEBIDA\nJUSTICIA DEL ESTADO DE GUERRERO, POR EL QUE SE\nTODOS LOS SERVIDORES PÚBLICOS PARA LA DEBIDA\nJUSTICIA DEL ESTADO DE GUERRERO, POR EL QUE SE\nTODOS LOS SERVIDORES PÚBLICOS PARA LA DEBIDA\nJUSTICIA DEL ESTADO DE GUERRERO, POR EL QUE SE\nTODOS LOS SERVIDORES PÚBLICOS PARA LA DEBIDA\nJUSTICIA DEL ESTADO DE GUERRERO, POR EL QUE SE\nTODOS LOS SERVIDORES PÚBLICOS PARA LA DEBIDA\nJUSTICIA DEL ESTADO DE GUERRERO, POR EL QUE SE\nTODOS LOS SERVIDORES PÚBLICOS PARA LA DEBIDA\nJUSTICIA DEL ESTADO DE GUERRERO, POR EL QUE SE\nTODOS LOS SERVIDORES PÚBLICOS PARA LA DEBIDA\nJUSTICIA DEL ESTADO DE GUERRERO, POR EL QUE SE\nTODOS LOS SERVIDORES PÚBLICOS PARA LA DEBIDA",
  "ordenamiento": "ACUERDO",
  "jurisdiccion": "GUERRERO",
  "fuente_oficial": "DIARIO OFICIAL DE LA FEDERACION",
  "Fecha de Publicación": "11 DE DICIEMBRE DE 2012",
  "ULTIMA REFORMA PUBLICADA": "11 DE DICIEMBRE DE 2012",
  "status": "ABROGADA",
  "es_escaneado": false,
  "tiene_tablas": false,
  "materia": [
    "penal",
    "administrativo"
  ]
}