{
  "titulo": "Acuerdo PGJDGEL0072011 del Procurador General de Justicia por el Cual Se Determinan las Políticas Po",
  "Contenido": "POR LAS QUE SE RESOLVERÁN LAS\nSOLICITUDES, PARA LA EMISIÓN DE LA\nEXPEDICIÓN DE CARTA DE ANTECEDENTES\nNO PENALES; Y DE LOS DATOS\nREGISTRALES QUE OBREN EN LOS\nARCHIVOS DE LA PROCURADURÍA GENERAL\nDE JUSTICIA DEL ESTADO DE GUERRERO\nTEXTO ORIGINAL\nAcuerdo publicado en el Periódico Oficial del Gobierno del Estado No. 96 Alcance\nII, el Viernes 2 de Diciembre de 2011.\nACUERDO PGJ/DGEL/007/2011 DEL PROCURADOR GENERAL DE JUSTICIA POR\nEL CUAL SE DETERMINAN LAS POLÍTICAS POR LAS QUE SE RESOLVERÁN LAS\nSOLICITUDES, PARA LA EMISIÓN DE LA EXPEDICIÓN DE CARTA DE\nANTECEDENTES NO PENALES; Y DE LOS DATOS REGISTRALES QUE OBREN EN\nLOS ARCHIVOS DE LA PROCURADURÍA GENERAL DE JUSTICIA DEL ESTADO DE\nGUERRERO.\nLIC. ALBERTO LÓPEZ ROSAS, PROCURADOR GENERAL DE JUSTICIA DEL\nESTADO DE GUERRERO, EN EJERCICIO DE LAS FACULTADES QUE ME\nCONFIEREN LOS ARTÍCULOS 20 INCISO B, FRACCIÓN I DE LA CONSTITUCIÓN\nPOLÍTICA DE LOS ESTADOS UNIDOS MEXICANOS; 1, 2, 10 FRACCIÓN V Y 29\nFRACCIÓN X DE LA LEY ORGÁNICA DE LA PROCURADURÍA GENERAL DE\nJUSTICIA; 18 TERCER PÁRRAFO Y 35 FRACCIÓN I DE LA LEY ORGÁNICA DE LA\nADMINISTRACIÓN PÚBLICA DEL ESTADO; ASÍ COMO 5 DEL REGLAMENTO DE LA\nLEY ORGÁNICA DE LA PROCURADURÍA GENERAL DE JUSTICIA, Y\nQue en un estado democrático y plural, debe prevalecer el estado de derecho, a través de normas establecidas en nuestra Carta Magna y leyes secundarias, plasmadas\nDerechos Civiles y Políticos, aprobado por la Asamblea General de las Naciones Unidas, inocencia, que literalmente dice: \"A) que se presuma su inocencia mientras no se declare su responsabilidad mediante sentencia emitida por el juez de la causa\" en razón de lo anterior la Procuraduría General de Justicia del Estado, y en cumplimiento a\nPOR LAS QUE SE RESOLVERÁN LAS\nSOLICITUDES, PARA LA EMISIÓN DE LA\nEXPEDICIÓN DE CARTA DE ANTECEDENTES\nNO PENALES; Y DE LOS DATOS\nREGISTRALES QUE OBREN EN LOS\nARCHIVOS DE LA PROCURADURÍA GENERAL\nDE JUSTICIA DEL ESTADO DE GUERRERO las obligaciones que le confiere la ley, debe ser garante del cumplimiento irrestricto de las garantías individuales y por ende los derechos humanos de los gobernados, por ser la presunción de inocencia un postulado básico de todo ordenamiento jurídico procesal, instituido generalmente como garantía constitucional en diversos paises, e incluso en los tratados internacionales, el principio está dirigido a conservar el estado de inocencia de la persona, durante el inicio de la investigación de una querella y/o denuncia hecha ante el Representante Social o ante el Órgano Jurisdiccional durante el trámite procesal.\nLa vigencia del principio determina que un procesado no puede ser considerado ni tratado como culpable, menos como delincuente, mientras no exista una sentencia condenatoria que adquiera la calidad de cosa juzgada formal y material, previo cumplimiento de los principios de publicidad, contradicción, concentración, continuidad e inmediación. Esto implica que únicamente la sentencia condenatoria firme es el instrumento idóneo capaz de vencer el estado de presunción de inocencia del procesado.\nQue con la finalidad de dar cabal cumplimiento a los objetivos planteados, es imperativo eliminar la práctica viciada de no extender la Carta de No Antecedentes\nPenales, salvo los casos en que exista sentencia condenatoria ejecutoriada, emitida por autoridad judicial competente, toda vez que, su omisión trasciende negativamente en las oportunidades que la sociedad le ofrece a los ciudadanos para incorporarse al trabajo, colectivo, en virtud de que no solamente estigmatiza al individuo, sino que impide en ocasiones, la reinserción a la sociedad.\nConstitucionales, la Procuraduría General de Justicia del Estado de Guerrero, tiene la conducta típica cometida, no deben afectar la libertad ocupacional de los individuos,\nPOR LAS QUE SE RESOLVERÁN LAS\nSOLICITUDES, PARA LA EMISIÓN DE LA\nEXPEDICIÓN DE CARTA DE ANTECEDENTES\nNO PENALES; Y DE LOS DATOS\nREGISTRALES QUE OBREN EN LOS\nARCHIVOS DE LA PROCURADURÍA GENERAL\nDE JUSTICIA DEL ESTADO DE GUERRERO respetando sus garantías individuales y por ende sus derechos humanos; en su caso, evitando con su divulgación injusta el pleno goce de ellas, cuando infortunadamente se hubieren visto involucrados en la investigación de hechos delictuosos que afecten su fama y prestigio personal ante la sociedad, o que habiendo cumplido con la sanción impuesta, eviten su reincorporación plena a la vida colectiva.\nPor lo que tengo a bien expedir el siguiente:\nACUERDO PGJ/DGEL/007/2011 DEL PROCURADOR GENERAL DE JUSTICIA POR\nEL CUAL SE DETERMINAN LAS POLÍTICAS POR LAS QUE SE RESOLVERÁN LAS\nSOLICITUDES, PARA LA EMISIÓN DE LA EXPEDICIÓN DE CARTA DE\nANTECEDENTES NO PENALES; Y DE LOS DATOS REGISTRALES QUE OBREN EN\nLOS ARCHIVOS DE LA PROCURADURÍA GENERAL DE JUSTICIA DEL ESTADO DE\nGUERRERO.\nPRIMERO.- De la conservación de los archivos.\nLos registros, anotaciones, grabaciones, inscripciones y demás datos de identificación y de antecedentes de carácter criminológico de la Procuraduría General de\nJusticia del Estado de Guerrero, en sus distintas unidades y archivos, deberán ser conservados íntegramente en la forma en que hubieren sido obtenidos, sin que puedan ser anulados, destruidos o invalidados sin la autorización prevista en el articulo 72 del\nReglamento de su Ley Orgánica, o por mandato fundado y motivado de autoridad judicial o administrativa competentes.\nSEGUNDO.- Datos RegistraIes.\nPara los efectos de este Acuerdo, se entiende por datos regístrales que no constituyen Antecedentes Penales, las fichas personales que integran el Casillero de\nIdentificación Criminalística de la Unidad de Archivo Criminalístico, que hayan sido\nPOR LAS QUE SE RESOLVERÁN LAS\nSOLICITUDES, PARA LA EMISIÓN DE LA\nEXPEDICIÓN DE CARTA DE ANTECEDENTES\nNO PENALES; Y DE LOS DATOS\nREGISTRALES QUE OBREN EN LOS\nARCHIVOS DE LA PROCURADURÍA GENERAL\nDE JUSTICIA DEL ESTADO DE GUERRERO captados con motivo de denuncias, acusaciones, querellas o investigaciones practicadas por el Ministerio Público, que no hubieren concluido con una Sentencia Condenatoria\nEjecutoriada emitida por autoridad judicial competente.\nTERCERO.- Contenido del Casillero de Identificación Criminalística.\nEl Casillero de Identificación Criminalística de la Unidad de Archivo Criminalístico estará integrado por las siguientes secciones:\n1).- Datos regístrales que constituyen Antecedentes Penales;\na).- Delincuentes primarios;\nb).- Delincuentes reincidentes; y,\nc).- Delincuentes habituales.\n2).- Datos regístrales que no constituyen Antecedentes Penales;\n3).- Datos regístrales sobre inimputables infractores: y,\n4).- Otros datos regístrales de identificación que se considere pertinente conservar.\nCUARTO.- Del auxilio de otras autoridades.\nPara integrar el Casillero a que alude el numeral anterior, la Unidad de Archivo\nCriminalístico y la Dirección General de Informática y Telecomunicaciones, recibirán de las Direcciones Generales de\nControl de Averiguaciones Previas y Control de Procesos penales, toda la información relativa al índice de criminalidad en el estado; misma que deberá quedar\nPOR LAS QUE SE RESOLVERÁN LAS\nSOLICITUDES, PARA LA EMISIÓN DE LA\nEXPEDICIÓN DE CARTA DE ANTECEDENTES\nNO PENALES; Y DE LOS DATOS\nREGISTRALES QUE OBREN EN LOS\nARCHIVOS DE LA PROCURADURÍA GENERAL\nDE JUSTICIA DEL ESTADO DE GUERRERO capturada en la base de datos de cada, unidad administrativa, y clasificada de conformidad con el presente acuerdo; pudiendo obtener datos criminales de otras autoridades administrativas y judiciales.\nQUINTO.- De la clasificación y archivo.\nObtenidos los datos y elementos de identificación, se clasificarán y archivarán de conformidad con lo establecido en este Acuerdo y bajo el procedimiento y sistemas adoptados por la Unidad de Archivo Criminalístico.\nSEXTO.- Antecedentes Penales.\nSe considerarán como Antecedentes Penales aquellos datos regístrales de identificación personal, sobre sujetos que hubieren sido condenados por autoridad judicial competente a sufrir una pena, sanción o medida de seguridad, en los términos a que hace referencia el articulo 55-A del Código Penal vigente para el Estado de Guerrero y esta resolución hubiere causado ejecutoria.\nSÉPTIMO.- De la expedición de Cartas de No Antecedentes Penales. de No Antecedentes Penales a toda persona que la solicite, previo pago de los derechos correspondientes, salvo los casos previstos en la Disposición Sexta de este Acuerdo.\nTratándose de mexicanos que radiquen en el extranjero, será necesario que el carta de no antecedentes penales.\nPOR LAS QUE SE RESOLVERÁN LAS\nSOLICITUDES, PARA LA EMISIÓN DE LA\nEXPEDICIÓN DE CARTA DE ANTECEDENTES\nNO PENALES; Y DE LOS DATOS\nREGISTRALES QUE OBREN EN LOS\nARCHIVOS DE LA PROCURADURÍA GENERAL\nDE JUSTICIA DEL ESTADO DE GUERRERO\nOCTAVO.- De la expedición o cancelación de Datos Regístrales.\nSolo a petición u orden expresa, fundada y motivada por autoridad judicial o administrativa competente, se podrá acceder a proporcionar información, otorgar constancias o certificaciones y/o a solicitar la cancelación de los datos regístrales que obren en el Archivo Criminalistico de esta Institución.\nToda solicitud deberá ser dirigida a la Dirección General de Control de Procesos, la que actuará coordinadamente con la Unidad de Archivo Criminalistico.\nNOVENO.- Obligación.\nLos Agentes del Ministerio Público Adscritos a los Juzgados están obligados a informar inmediatamente y por oficio, sobre las Sentencias Condenatorias Ejecutoriadas, dictadas por las autoridades judiciales competentes, para los efectos inherentes a la\nDisposición Séptima de éste instrumento jurídico. independiente de que se hubiere expedido o no, Carta de No Antecedentes Penales.\nPara efectos de evitar la homonimia, el personal de Archivo Criminalistico deberá gestionar del Centro de Readaptación Social correspondiente, copia certificada de la\nFicha Signalética del procesado que respondiera a un nombre similar.\nDÉCIMO.- Del respeto a los Principios. presente Acuerdo.\nPOR LAS QUE SE RESOLVERÁN LAS\nSOLICITUDES, PARA LA EMISIÓN DE LA\nEXPEDICIÓN DE CARTA DE ANTECEDENTES\nNO PENALES; Y DE LOS DATOS\nREGISTRALES QUE OBREN EN LOS\nARCHIVOS DE LA PROCURADURÍA GENERAL\nDE JUSTICIA DEL ESTADO DE GUERRERO\nPRIMERO.- Publíquese en Periódico Oficial del Estado.\nSEGUNDO.- Este Acuerdo entrará en vigor al día siguiente de su publicación oficial.\nTERCERO.- Se instruye a los Titulares de la Dirección General de Fiscalización y\nResponsabilidades, Visitaduría General y Contraloría Interna, para que en ejercicio de sus facultades vigilen el cumplimiento del presente instrumento jurídico.\nChilpancingo de los Bravo, Guerrero, Noviembre 11 del 2011.\nATENTAMENTE:\nEL PROCURADOR GENERAL DE JUSTICIA.\nLIC. ALBERTO LÓPEZ ROSAS.\nRúbrica.",
  "ordenamiento": "ACUERDO",
  "jurisdiccion": "GUERRERO",
  "fuente_oficial": "DIARIO OFICIAL DE LA FEDERACION",
  "Fecha de Publicación": "2 de Diciembre de 2011",
  "ULTIMA REFORMA PUBLICADA": null,
  "status": "VIGENTE",
  "es_escaneado": false,
  "tiene_tablas": false,
  "materia": [
    "judicial"
  ]
}