{
  "titulo": "Acuerdo por el Que Se Autoriza por Única Ocasión con Duración de Siete Años, la Validación de Estudi",
  "Contenido": "PREESCOLAR INDÍGENA Y EN EDUCACIÓN PRIMARIA\nINDÍGENA, PARA REGULARIZAR A 4,200 DOCENTES EN\nSERVICIO EN LAS REGIONES DE LA MONTAÑA, COSTA\nCHICA, CENTRO Y NORTE DEL ESTADO DE GUERRERO,\nGUERRERO, LA SECRETARÍA DE EDUCACIÓN GUERRERO, Y\nLA SUBSECRETARÍA DE EDUCACIÓN MEDIA SUPERIOR Y\nSUPERIOR, A TRAVÉS DE LOS CENTROS DE\nACTUALIZACIÓN DEL MAGISTERIO\nTEXTO ORIGINAL.\nAcuerdo Publicado en el Periódico Oficial del Gobierno del Estado No. 72, el Martes 09 de\nSeptiembre de 2014.\nACUERDO POR EL QUE SE AUTORIZA POR ÚNICA OCASIÓN CON DURACIÓN DE SIETE AÑOS,\nLA VALIDACIÓN DE ESTUDIOS DE LICENCIATURA EN EDUCACIÓN PREESCOLAR INDÍGENA Y\nEN EDUCACIÓN PRIMARIA INDÍGENA, PARA REGULARIZAR A 4,200 DOCENTES EN SERVICIO\nEN LAS REGIONES DE LA MONTAÑA, COSTA CHICA, CENTRO Y NORTE DEL ESTADO DE\nGUERRERO, VALIDADOS POR EL GOBIERNO DEL ESTADO DE GUERRERO, LA SECRETARÍA DE\nEDUCACIÓN GUERRERO, Y LA SUBSECRETARÍA DE EDUCACIÓN MEDIA SUPERIOR Y\nSUPERIOR, A TRAVÉS DE LOS CENTROS DE ACTUALIZACIÓN DEL MAGISTERIO.\nGuerrero.- Poder Ejecutivo.\nLICENCIADO ÁNGEL HELADIO AGUIRRE RIVERO, GOBERNADOR CONSTITUCIONAL\nSOBERANO DE GUERRERO Y EN USO DE LAS FACULTADES QUE LE CONFIEREN LOS\nARTÍCULOS 2o., 6o., 10 Y 20 FRACCIÓN III DE LA LEY ORGÁNICA DE LA ADMINISTRACIÓN\nPÚBLICA DEL ESTADO DE GUERRERO NÚMERO 433; 20 FRACCIÓN I, 38 Y 64 DE LA LEY DE\nEDUCACIÓN DEL ESTADO DE GUERRERO NÚM.158; Y\nQue el Plan Estatal de Desarrollo 2011-2015, establece en su objetivo 2.6, lograr una mayor calidad docente para la consolidación del sistema educativo, a través de los procesos de formación continua y superación profesional, con el fin de mejorar las capacidades académicas, éticas y sociales de los docentes.\nQue la educación es uno de los principales derechos de los mexicanos, como se refiere en el artículo 3o. de la Constitución Política de los Estados Unidos Mexicanos y es el factor determinante en el desarrollo económico, social, cultural y político de todas las sociedades del mundo.\nPREESCOLAR INDÍGENA Y EN EDUCACIÓN PRIMARIA\nINDÍGENA, PARA REGULARIZAR A 4,200 DOCENTES EN\nSERVICIO EN LAS REGIONES DE LA MONTAÑA, COSTA\nCHICA, CENTRO Y NORTE DEL ESTADO DE GUERRERO,\nGUERRERO, LA SECRETARÍA DE EDUCACIÓN GUERRERO, Y\nLA SUBSECRETARÍA DE EDUCACIÓN MEDIA SUPERIOR Y\nSUPERIOR, A TRAVÉS DE LOS CENTROS DE\nACTUALIZACIÓN DEL MAGISTERIO\nQue en la Declaración Universal de los Derechos Humanos se menciona que la educación tendrá por objeto el pleno desarrollo de la personalidad humana y el fortalecimiento del respeto a los derechos humanos y a las libertades fundamentales; favorecerá la comprensión, la tolerancia y la amistad entre todas las naciones y todos los grupos étnicos o religiosos.\nQue el Convenio Marco de Coordinación para el desarrollo de los programas, de registro SEGUAJ-053-2012 de fecha 1 de marzo de 2012, celebrado por el Gobierno Federal por conducto de la propósito impulsar las políticas públicas de educación conjuntamente con los gobiernos de las entidades federativas con el fin de obtener el progreso y bienestar para los alumnos de preescolar, primaria y secundaria, además de la profesionalización de los docentes frente a grupo.\nQue el Acuerdo número 679 por el que se emiten las Reglas de Operación del Programa Asesor\nTécnico Pedagógico y para la Atención Educativa a la Diversidad Social, Lingüística y Cultural, tiene como objetivo específico, mejorar la atención educativa de las niñas y niños de preescolar y primaria indígena.\nQue las dificultades de orografía, comunicaciones, bajo económico, además, del plurilingüismo y pluriculturalidad en el Estado, fueron elementos fundamentales para atender con recursos humanos no profesionalizados, los niveles educativos básicos (preescolar, primaria y secundaria) como medio para promover la igualdad de oportunidades educativas, especialmente en la educación de los pueblos indígenas de Guerrero.\nQue se considera como un acto de calidad y equidad, reconocer el esfuerzo de 4,200 profesores en el nivel básico que no han alcanzado estudios de nivel Licenciatura, mismos que requieren apoyo para superarse profesionalmente. Con ello, se busca impulsar la calidad docente en las regiones indígenas de la Montaña, Costa Chica, Centro y Norte, particularmente.\nDirección General de Educación Indígena en conjunto con la Dirección General de Acreditación, Incorporación y Revalidación de la Secretaría de Educación Pública, conjuntan esfuerzos y acciones para de Licenciatura, mediante estudios que serán proporcionados en la \"Modalidad Mixta y Plan de Estudios\nPREESCOLAR INDÍGENA Y EN EDUCACIÓN PRIMARIA\nINDÍGENA, PARA REGULARIZAR A 4,200 DOCENTES EN\nSERVICIO EN LAS REGIONES DE LA MONTAÑA, COSTA\nCHICA, CENTRO Y NORTE DEL ESTADO DE GUERRERO,\nGUERRERO, LA SECRETARÍA DE EDUCACIÓN GUERRERO, Y\nLA SUBSECRETARÍA DE EDUCACIÓN MEDIA SUPERIOR Y\nSUPERIOR, A TRAVÉS DE LOS CENTROS DE\nACTUALIZACIÓN DEL MAGISTERIO\nModular\", a cargo de la Dirección General de Educación Indígena de la Secretaría de Educación Pública y con validación de las Autoridades Educativas del Estado de Guerrero.\nPor lo anteriormente expuesto y fundado, he tenido a bien expedir el siguiente:\nACUERDO POR EL QUE SE AUTORIZA POR ÚNICA OCASIÓN CON DURACIÓN DE SIETE AÑOS,\nLA VALIDACIÓN DE ESTUDIOS DE LICENCIATURA EN EDUCACIÓN PREESCOLAR INDÍGENA Y\nEN EDUCACIÓN PRIMARIA INDÍGENA, PARA REGULARIZAR A 4,200 DOCENTES EN SERVICIO\nEN LAS REGIONES DE LA MONTAÑA, COSTA CHICA, CENTRO Y NORTE DEL ESTADO DE\nGUERRERO, VALIDADOS POR EL GOBIERNO DEL ESTADO DE GUERRERO, LA SECRETARÍA DE\nEDUCACIÓN GUERRERO, Y LA SUBSECRETARÍA DE EDUCACIÓN MEDIA SUPERIOR Y\nSUPERIOR, A TRAVÉS DE LOS CENTROS DE ACTUALIZACIÓN DEL MAGISTERIO.\nCAPÍTULO I\nDel objeto y operación\nArtículo 1. El presente Acuerdo tiene como objetivo primordial la autorización por única ocasión, y con una duración de siete años, la validación de estudios de la Licenciatura en Educación Preescolar\nIndígena y en Educación Primaria Indígena, por conducto de la Secretaría de Educación Guerrero y ésta a su vez, opere un Programa denominado \"Formación para la Certificación de Docentes en\nContextos Indígenas desde un Enfoque Intercultural y Bilingüe\".\nArtículo 2. Para la ejecución del programa en comento, se realizará conforme a lo dispuesto por el Acuerdo número 679 por el que se emiten las Reglas de Operación del Programa Asesor Técnico\nPedagógico y para la Atención Educativa a la Diversidad Social, Lingüística y Cultural.\nArtículo 3. Para la validación de los estudios, los maestros que ingresen al programa\n\"Formación para la Certificación de Docentes en Contextos Indígenas desde un Enfoque\nIntercultural y Bilingüe\", deberán acreditar los módulos que establece el Mapa Curricular, a través de evaluaciones bimestrales y registro de evaluaciones validadas por las autoridades involucradas.\nArtículo 4. La actividad docente será impartida por los profesionales de la Secretaría de\nEducación Guerrero que ostenten Cédula de Maestría y mínimo de Licenciatura, considerando su campo\nPREESCOLAR INDÍGENA Y EN EDUCACIÓN PRIMARIA\nINDÍGENA, PARA REGULARIZAR A 4,200 DOCENTES EN\nSERVICIO EN LAS REGIONES DE LA MONTAÑA, COSTA\nCHICA, CENTRO Y NORTE DEL ESTADO DE GUERRERO,\nGUERRERO, LA SECRETARÍA DE EDUCACIÓN GUERRERO, Y\nLA SUBSECRETARÍA DE EDUCACIÓN MEDIA SUPERIOR Y\nSUPERIOR, A TRAVÉS DE LOS CENTROS DE\nACTUALIZACIÓN DEL MAGISTERIO de formación en cada uno de los espacios curriculares de los Centros de Actualización del Magisterio del\nEstado y profesores de Educación Básica seleccionados.\nArtículo 5. Este programa aplica durante los ciclos comprendidos entre los años 20112012, 2012-2013, 2013-2014, 20142015, 2015-2016, 2016-2017 y 2017-2018.\nArtículo 6. La Secretaría de Educación Guerrero, impartirá la actualización haciendo uso de las instalaciones de los Centros de Actualización del Magisterio del Estado, los docentes participantes podrán elegir la sede de acuerdo a la ubicación geográfica de su lugar de adscripción o lugar de residencia.\nArtículo 7. La Secretaria de Educación Guerrero, presentará el programa de estudios ante la\nDirección General de Educación Superior para Profesionales de la Educación, así como a la Dirección\nGeneral de Profesiones y la Dirección General de Acreditación, Incorporación y Revalidación de la\nSecretaria de Educación Pública y el Centro Nacional de Evaluación para la Educación Superior, A.C., con el objetivo de solicitar su validación y autorización.\nArtículo 8. La Secretaría de Educación Guerrero, delegará las acciones de validación de estudios al Departamento de Desarrollo Profesional del Magisterio, a través de los Centros de\nActualización del magisterio.\nArtículo 9. La duración de la instrucción para la certificación será de un año y dos meses, distribuida en siete bimestres, compuestos cada uno de dos módulos y en modalidad mixta, (sábado y domingo). La distribución de los bimestres durante la duración del programa será de la siguiente manera:\n1er. bimestre: agosto - septiembre\n2do. bimestre: octubre -noviembre\n3er. bimestre: diciembre –enero\n4to. bimestre: febrero - marzo\n5to. bimestre: abril - mayo\nPREESCOLAR INDÍGENA Y EN EDUCACIÓN PRIMARIA\nINDÍGENA, PARA REGULARIZAR A 4,200 DOCENTES EN\nSERVICIO EN LAS REGIONES DE LA MONTAÑA, COSTA\nCHICA, CENTRO Y NORTE DEL ESTADO DE GUERRERO,\nGUERRERO, LA SECRETARÍA DE EDUCACIÓN GUERRERO, Y\nLA SUBSECRETARÍA DE EDUCACIÓN MEDIA SUPERIOR Y\nSUPERIOR, A TRAVÉS DE LOS CENTROS DE\nACTUALIZACIÓN DEL MAGISTERIO\n6to. bimestre: junio - julio\n7to. bimestre: agosto - septiembre\nPara las generaciones subsecuentes, establecidas conforme a lo dispuesto por el artículo 5° de este Acuerdo, se contabilizará conforme a las fechas de ingreso previa convocatoria.\nArtículo 10. Requisitos para ingresar al programa:\nI. Ser docente de Educación Indígena;\nII. Desempeñar sus funciones, frente a grupo, como directivo o de asesoría académica;\nIII. Demostrar con documentos, su experiencia docente de más de tres años como mínimo;\nIV. Tener estudios de Bachillerato concluido o equivalente a la Educación Media Superior; y\nV. Los demás que se establezcan en las convocatorias, para su ingreso al programa educativo.\nArtículo 11. La Secretarla de Educación Guerrero, no se obliga ni se compromete a otorgar plazas y/o realizar recategorizaciones para los egresados de dicho programa.\nArtículo 12. Para la validación de estudios, los docentes y directivos de los Centros de\nActualización del Magisterio de la entidad, estructurarán una Comisión Académica de Trabajo, coordinada por el Departamento de Desarrollo Profesional del Magisterio.\nCAPÍTULO II\nDe las facultades del\nDepartamento de Desarrollo\nProfesional del Magisterio\nArtículo 13. El Departamento de Desarrollo Profesional del Magisterio, tendrá las funciones de\nCoordinación General y tendrá las siguientes facultades:\nPREESCOLAR INDÍGENA Y EN EDUCACIÓN PRIMARIA\nINDÍGENA, PARA REGULARIZAR A 4,200 DOCENTES EN\nSERVICIO EN LAS REGIONES DE LA MONTAÑA, COSTA\nCHICA, CENTRO Y NORTE DEL ESTADO DE GUERRERO,\nGUERRERO, LA SECRETARÍA DE EDUCACIÓN GUERRERO, Y\nLA SUBSECRETARÍA DE EDUCACIÓN MEDIA SUPERIOR Y\nSUPERIOR, A TRAVÉS DE LOS CENTROS DE\nACTUALIZACIÓN DEL MAGISTERIO\nI. Realizar las gestiones necesarias para el registro y reconocimiento de validez de estudios;\nII. Coordinar el proceso de los espacios curriculares para su cumplimiento;\nIII. Elaborar los instrumentos para la evaluación de las competencias docentes;\nIV. Emitir la evaluación por cada uno de los módulos y acreditar el aprovechamiento individual de cada docente capacitado al finalizar los cursos de actualización;\nV. Tramitar el certificado de estudios y título ante el Departamento de Registro y Certificación dependiente de la Sub-secretaría de Planeación Educativa y la Cédula Profesional ante la Subdirección de Profesiones y Servicio Social de la Subsecretaría de Educación Media Superior y Superior;\nVI. Mantener un archivo de registro personalizado para cada uno de los docentes participantes, por un término no menor de diez años; y\nVII. Expedir duplicados o reposición de los documentos que obren en sus archivos.\nArtículo 14. La Dirección de Educación Indígena, a través de la Secretaría de Educación\nGuerrero, realizará las gestiones presupuestales necesarias para la operación y cumplimiento del programa, durante los ciclos que estipula el artículo 5 del presente Acuerdo. Así mismo, se encargará de dar seguimiento a los aspectos técnico-propios del programa.\nArtículo 15. La Secretaría de Educación Guerrero, a través de la Subsecretaría de\nEducación Media Superior y Superior, Departamento de Desarrollo Profesional del Magisterio y la\nDirección de Educación Indígena, administrará el recurso económico por medio de una cuenta mancomunada.\nArtículo 16. Los profesionales de la educación del programa se contratarán por honorarios y por tiempo determinado, en cada bimestre que atiendan el programa, a nombre de la Secretaría de\nEducación Guerrero. La relación laboral y las funciones como asesores, se darán por terminadas de acuerdo a lo estipulado en el clausulado del contrato de prestación de servicios, firmado por ambas partes.\nPREESCOLAR INDÍGENA Y EN EDUCACIÓN PRIMARIA\nINDÍGENA, PARA REGULARIZAR A 4,200 DOCENTES EN\nSERVICIO EN LAS REGIONES DE LA MONTAÑA, COSTA\nCHICA, CENTRO Y NORTE DEL ESTADO DE GUERRERO,\nGUERRERO, LA SECRETARÍA DE EDUCACIÓN GUERRERO, Y\nLA SUBSECRETARÍA DE EDUCACIÓN MEDIA SUPERIOR Y\nSUPERIOR, A TRAVÉS DE LOS CENTROS DE\nACTUALIZACIÓN DEL MAGISTERIO\nCAPÍTULO III\nDe los medios de evaluación y seguimiento\nArtículo 17. Las opciones de titulación, certificación, evaluación y acreditación se apegarán a lo estipulado en la Ley General de Educación, que otorga al Titular de la Secretaría de Educación Pública\n(SEP) la función de establecer procedimientos por medio de los cuales se expidan certificados, constancias, diplomas o títulos a quienes acrediten conocimientos terminales que correspondan a cierto nivel educativo o grado escolar, adquiridos en forma autodidacta o a través de la experiencia laboral.\nAdicionalmente se encuentra fundamentado en los acuerdos 286, 328, 357 y 379 publicados por la\nSecretaría de Educación Pública (SEP) en el Diario Oficial de la Federación, así como las Normas\nGenerales para la Acreditación y Certificación de Conocimientos Terminales publicadas por la Unidad de\nPlaneación y Evaluación de Políticas Educativas a través de la Dirección General de Acreditación\nIncorporación y Revalidación, en el que se establecen los mecanismos por los que se expedirá Título\nProfesional a los egresados de las escuelas que imparten educación normal.\nArtículo 18. Para la certificación del personal docente del área indígena, se creará una comisión académica que atenderá aspectos técnico-pedagógicos, conformada por representantes del personal docente y administrativo de los Centros de Actualización del Magisterio, Departamento de Desarrollo\nProfesional del Magisterio, Dirección de Educación Indígena de la Secretaría de Educación Pública, quienes definirán los procedimientos a aplicarse en el proceso de programa educativo.\nArtículo 19. Se creará la Comisión para la evaluación y seguimiento del programa educativo, integrada por representantes de las Subsecretarías: de Planeación Educativa, Educación Básica y\nEducación Media Superior y Superior, de la Secretaría de Educación, Guerrero, en coordinación con la\nDirección General de Educación Indígena de la Secretaría de Educación Pública, misma que sesionará amerite, previa convocatoria por cualquiera de los miembros de la comisión, con setenta y dos horas de anticipación.\nPrimero. El presente Acuerdo entrará en vigor al día siguiente de su publicación en el Periódico\nPREESCOLAR INDÍGENA Y EN EDUCACIÓN PRIMARIA\nINDÍGENA, PARA REGULARIZAR A 4,200 DOCENTES EN\nSERVICIO EN LAS REGIONES DE LA MONTAÑA, COSTA\nCHICA, CENTRO Y NORTE DEL ESTADO DE GUERRERO,\nGUERRERO, LA SECRETARÍA DE EDUCACIÓN GUERRERO, Y\nLA SUBSECRETARÍA DE EDUCACIÓN MEDIA SUPERIOR Y\nSUPERIOR, A TRAVÉS DE LOS CENTROS DE\nACTUALIZACIÓN DEL MAGISTERIO\nSegundo. Para el cumplimiento, del presente Acuerdo se sujetará a las Normas Académicas vigentes, establecidas por la Dirección General de Educación Superior para Profesionales de la\nEducación aplicables a los programas de Licenciatura.\nTercero. Los imprevistos al presente, se someterán a la consideración de la Secretaría de\nEducación Guerrero, a través de la Subsecretaría de Educación Media Superior y Superior.\nDado en la Residencia Oficial del Poder Ejecutivo Estatal, en la ciudad de Chilpancingo de los\nBravo, Capital del Estado de Guerrero, a los 13 días del mes de Marzo del año dos mil catorce.\nEL GOBERNADOR CONSTITUCIONAL DEL ESTADO\nLIC. ÁNGEL HELADIO AGUIRRE RIVERO.\nEL SECRETARIO GENERAL DE GOBIERNO.\nLIC. JESUS MARTINEZ GARNELO.\nLA SECRETARIA DE EDUCACION GUERRERO.\nPROFRA. SILVIA ROMERO SUÁREZ.",
  "ordenamiento": "ACUERDO",
  "jurisdiccion": "GUERRERO",
  "fuente_oficial": "DIARIO OFICIAL DE LA FEDERACION",
  "Fecha de Publicación": "09 de \nSeptiembre de 2014",
  "ULTIMA REFORMA PUBLICADA": null,
  "status": "VIGENTE",
  "es_escaneado": false,
  "tiene_tablas": false,
  "materia": [
    "general"
  ]
}