{
  "titulo": "Acuerdo por el Que Se Conceden Beneficios Fiscales A los Ciudadanos Que Desean Inscribir Sus Escritu",
  "Contenido": "RELACIONADAS CON LA ADQUISICIÓN, TRANSMISIÓN\nDE PROPIEDAD, YA SEA POR ADJUDICACIÓN CON\nMOTIVO DE JUICIOS SUCESORIOS ANTE NOTARIOS O\nPOR RESOLUCIÓN JUDICIAL, IGUALMENTE EN JUICIOS\nSUCESORIOS OTORGANDO APOYOS EN LA\nREDUCCIÓN DEL PAGO DE DERECHOS ANTE LA\nDIRECCIÓN GENERAL DEL REGISTRO PÚBLICO DE LA\nPROPIEDAD, DEL COMERCIO Y CRÉDITO AGRÍCOLA Y\nEL ARCHIVO DE NOTARÍAS\nABROGADO POR CONCLUIDA SU VIGENCIA EL 30 DE SEPTIEMBRE DE\n2009.\nTEXTO ORIGINAL\nAcuerdo publicado en el Periódico Oficial del Gobierno del Estado No. 72 Alcance\nI, el Martes 08 de Septiembre de 2009.\nACUERDO POR EL QUE SE CONCEDEN BENEFICIOS FISCALES A LOS\nCIUDADANOS QUE DESEAN INSCRIBIR SUS ESCRITURAS PÚBLICAS\nRELACIONADAS CON LA ADQUISICIÓN, TRANSMISIÓN DE PROPIEDAD, YA SEA\nPOR ADJUDICACIÓN CON MOTIVO DE JUICIOS SUCESORIOS ANTE NOTARIOS O\nPOR RESOLUCIÓN JUDICIAL, IGUALMENTE EN JUICIOS SUCESORIOS\nOTORGANDO APOYOS EN LA REDUCCIÓN DEL PAGO DE DERECHOS ANTE LA\nDIRECCIÓN GENERAL DEL REGISTRO PÚBLICO DE LA PROPIEDAD, DEL\nCOMERCIO Y CRÉDITO AGRÍCOLA Y EL ARCHIVO DE NOTARÍAS.\nAl margen un sello con el Escudo Oficial que dice: Gobierno del Estado Libre y\nCARLOS ZEFERINO TORREBLANCA GALINDO, GOBERNADOR\nFUNDAMENTO EN LOS ARTÍCULOS 74 FRACCIONES XI Y XXXVI Y 76 DE LA\nEJERCICIO DE LAS FACULTADES QUE ME CONFIEREN LOS ARTÍCULOS 6º. Y 10\nGUERRERO NÚMERO 433; 11 FRACCIÓN I, 18 PÁRRAFO SEGUNDO Y 44\nFRACCIÓN II DEL CÓDIGO FISCAL DEL ESTADO DE GUERRERO, NÚMERO 429; EN\nRELACIONADAS CON LA ADQUISICIÓN, TRANSMISIÓN\nDE PROPIEDAD, YA SEA POR ADJUDICACIÓN CON\nMOTIVO DE JUICIOS SUCESORIOS ANTE NOTARIOS O\nPOR RESOLUCIÓN JUDICIAL, IGUALMENTE EN JUICIOS\nSUCESORIOS OTORGANDO APOYOS EN LA\nREDUCCIÓN DEL PAGO DE DERECHOS ANTE LA\nDIRECCIÓN GENERAL DEL REGISTRO PÚBLICO DE LA\nPROPIEDAD, DEL COMERCIO Y CRÉDITO AGRÍCOLA Y\nEL ARCHIVO DE NOTARÍAS\nEL DECRETO NÚMERO 1008 DEL PRESUPUESTO DE EGRESOS DEL ESTADO DE\nGUERRERO PARA EL EJERCICIO FISCAL 2009, Y\nQue es facultad del titular del Poder Ejecutivo, cuidar los fondos públicos, así como, que los mismos se encuentren asegurados, y que por tanto, los ingresos como el ejercicio de los recursos del Estado, se realicen con apego a la Ley y se ejerzan con criterios de eficiencia y transparencia, debiendo, en todo caso, determinar estrategias que generen ahorros, aplicando medidas de austeridad en la gestión pública, para su orientación a las prioridades del desarrollo social, económico institucional de la Entidad.\nQue en la Ley de Ingresos y el Decreto de Presupuesto de Egresos para el ejercicio fiscal 2009 el H. Congreso estableció las asignaciones presupuestales considerando los datos proporcionados por la Federación, en específico de la Secretaría de Hacienda y Crédito Público, las cuales no han sido las suficientes para afrontar el grave problema económico mundial que ha contagiado a nuestro país. inmobiliaria, sobre todo a aquellos contribuyentes que desean formalizar sus escrituras públicas relacionadas con la adquisición, transmisión de propiedad, ya sea por judicial, igualmente en juicios sucesorios otorgando apoyos en la reducción del pago de derechos ante la Dirección General del Registro Público de la Propiedad, del Comercio y\nCrédito Agrícola y el Archivo de Notarías.\nRELACIONADAS CON LA ADQUISICIÓN, TRANSMISIÓN\nDE PROPIEDAD, YA SEA POR ADJUDICACIÓN CON\nMOTIVO DE JUICIOS SUCESORIOS ANTE NOTARIOS O\nPOR RESOLUCIÓN JUDICIAL, IGUALMENTE EN JUICIOS\nSUCESORIOS OTORGANDO APOYOS EN LA\nREDUCCIÓN DEL PAGO DE DERECHOS ANTE LA\nDIRECCIÓN GENERAL DEL REGISTRO PÚBLICO DE LA\nPROPIEDAD, DEL COMERCIO Y CRÉDITO AGRÍCOLA Y\nEL ARCHIVO DE NOTARÍAS\nQue por todo lo anteriormente expuesto fundado y motivado tengo a bien emitir la siguiente:\nACUERDO POR EL QUE SE CONCEDEN BENEFICIOS FISCALES A LOS\nCIUDADANOS QUE DESEAN INSCRIBIR SUS ESCRITURAS PÚBLICAS\nRELACIONADAS CON LA ADQUISICIÓN, TRANSMISIÓN DE PROPIEDAD, YA SEA\nPOR ADJUDICACIÓN CON MOTIVO DE JUICIOS SUCESORIOS ANTE NOTARIOS O\nPOR RESOLUCIÓN JUDICIAL, IGUALMENTE EN JUICIOS SUCESORIOS\nOTORGANDO APOYOS EN LA REDUCCIÓN DEL PAGO DE DERECHOS ANTE LA\nDIRECCIÓN GENERAL DEL REGISTRO PÚBLICO DE LA PROPIEDAD, DEL\nCOMERCIO Y CRÉDITO AGRÍCOLA Y EL ARCHIVO DE NOTARÍAS.\nARTÍCULO PRIMERO.- El Gobierno del Estado conforme a los alcances de las disposiciones legales vigentes aplicables, emite el presente Acuerdo en beneficio de las familias guerrerenses, a través del cual se otorgan beneficios sobre el pago de derechos en el Archivo de Notarías y en el Registro Público de la Propiedad, del Comercio y\nCrédito Agrícola, para la inscripción de testamento o su depósito, la búsqueda de testamentos, inscripción de escrituras públicas provenientes de resoluciones jurisdiccionales en materia de sucesiones.\nARTÍCULO SEGUNDO.- Se otorgan beneficios fiscales sobre el pago de los derechos de inscripción en el Registro Público de la Propiedad y del Comercio, que aluden las fracciones II, VIII, X, XII, XIV y XVIII del artículo 83 de la Ley de Hacienda del\nEstado de Guerrero, con un descuento del cincuenta por ciento.\nARTÍCULO TERCERO.- Se otorgan beneficios fiscales sobre el pago de los derechos que aluden las fracciones I del artículo 98 y XVII del artículo 83 de la Ley de\nHacienda del Estado de Guerrero, con un descuento del cincuenta por ciento respecto a\nRELACIONADAS CON LA ADQUISICIÓN, TRANSMISIÓN\nDE PROPIEDAD, YA SEA POR ADJUDICACIÓN CON\nMOTIVO DE JUICIOS SUCESORIOS ANTE NOTARIOS O\nPOR RESOLUCIÓN JUDICIAL, IGUALMENTE EN JUICIOS\nSUCESORIOS OTORGANDO APOYOS EN LA\nREDUCCIÓN DEL PAGO DE DERECHOS ANTE LA\nDIRECCIÓN GENERAL DEL REGISTRO PÚBLICO DE LA\nPROPIEDAD, DEL COMERCIO Y CRÉDITO AGRÍCOLA Y\nEL ARCHIVO DE NOTARÍAS los servicios que prestan el Registro Público de la Propiedad, del Comercio y Crédito\nAgrícola y el Archivo de Notarías.\nEste beneficio se otorgará al presentarse el requerimiento de búsqueda formulado por autoridad jurisdiccional competente, autoridad investigadora o notario público.\nARTÍCULO CUARTO.- La Secretaría de Finanzas y Administración, a través de las administraciones fiscales correspondientes tomará las medidas necesarias para que se tramiten los beneficios fiscales a que se refiere este Acuerdo.\nARTÍCULO QUINTO.- La interpretación de esta Resolución para efectos administrativos y fiscales corresponderá a la Secretaría de Finanzas.\nPRIMERO.- El presente Acuerdo entrará en vigor a partir del día de su emisión.\nSEGUNDO.- El presente Acuerdo tendrá una vigencia en los actos jurídicos detallados que se realicen del 1 al 30 de septiembre del año 2009, considerado como\n“Mes del Testamento”, independientemente de que se tengan que cubrir dichos derechos con posterioridad. conocimiento general.\nCapital del Estado de Guerrero, a uno de septiembre del año dos mil nueve.\nRELACIONADAS CON LA ADQUISICIÓN, TRANSMISIÓN\nDE PROPIEDAD, YA SEA POR ADJUDICACIÓN CON\nMOTIVO DE JUICIOS SUCESORIOS ANTE NOTARIOS O\nPOR RESOLUCIÓN JUDICIAL, IGUALMENTE EN JUICIOS\nSUCESORIOS OTORGANDO APOYOS EN LA\nREDUCCIÓN DEL PAGO DE DERECHOS ANTE LA\nDIRECCIÓN GENERAL DEL REGISTRO PÚBLICO DE LA\nPROPIEDAD, DEL COMERCIO Y CRÉDITO AGRÍCOLA Y\nEL ARCHIVO DE NOTARÍAS\nEL GOBERNADOR CONSTITUCIONAL DEL ESTADO.\nC.P. CARLOS ZEFERINO TORREBLANCA GALINDO.\nEL SECRETARIO GENERAL DE GOBIERNO.\nLIC. GUILLERMO RAMÍREZ RAMOS.\nEL SECRETARIO DE FINANZAS Y ADMINISTRACIÓN.\nL.A.E. RICARDO ERNESTO CABRERA MORÍN.",
  "ordenamiento": "ACUERDO",
  "jurisdiccion": "GUERRERO",
  "fuente_oficial": "DIARIO OFICIAL DE LA FEDERACION",
  "Fecha de Publicación": "30 DE SEPTIEMBRE DE \n2009",
  "ULTIMA REFORMA PUBLICADA": "08 de Septiembre de 2009",
  "status": "ABROGADA",
  "es_escaneado": false,
  "tiene_tablas": false,
  "materia": [
    "fiscal"
  ]
}