{
  "titulo": "Acuerdo del Fiscal General del Estado de Guerrero, por el Que Se Establecen los Criterios Generales",
  "Contenido": "AGENTES DEL MINISTERIO PÚBLICO LA APLICACIÓN\nDE LOS CRITERIOS DE OPORTUNIDAD; Y\nDELEGACIÓN DE LA FACULTAD PARA\nAUTORIZARLOS\nTEXTO ORIGINAL.\nAcuerdo Publicado en el Periódico Oficial del Gobierno del Estado No.30 Alcance I, el Martes 12 de Abril de 2016.\nACUERDO FGE/VFINV/A/006/2016.\nACUERDO DEL FISCAL GENERAL DEL ESTADO DE GUERRERO, POR EL QUE SE ESTABLECEN\nLOS CRITERIOS GENERALES QUE DEBE EMPLEAR LOS AGENTES DEL MINISTERIO PÚBLICO LA\nAPLICACIÓN DE LOS CRITERIOS DE OPORTUNIDAD; Y DELEGACIÓN DE LA FACULTAD PARA\nAUTORIZARLOS.\nJavier Ignacio Olea Peláez, Fiscal General del Estado de Guerrero, con fundamento en lo dispuesto por los artículos 21 de la Constitución Política de los Estados Unidos Mexicanos; 105, 139 y 140 me confieren los artículos 256, tercer párrafo del Código Nacional de Procedimientos Penales, 21, fracciones XI y XVI y 22, fracción II de la Ley Orgánica de la Fiscalía General del Estado de Guerrero, número 500; y 19 y 20, fracciones IX y XII del Reglamento de la Ley Orgánica referida; y\nQue con motivo de la Reforma a la Constitución Política de los Estados Unidos Mexicanos, publicada en el Diario Oficial de la Federación el 18 de junio del año 2008, se instaura un Nuevo Sistema de Justicia Penal Acusatorio, basado en la Justicia Adversarial y la implementación de los Juicios Orales en territorio nacional;\nQue los artículos 20 de la Constitución Política de los Estados Unidos Mexicanos, 92, numeral 2, General del Estado de Guerrero, número 500, disponen que el proceso penal será acusatorio y oral, y tendrá por objeto el esclarecimiento de los hechos, proteger al inocente, procurar que el culpable no quede impune y que los daños causados por el delito se reparen;\nQue el párrafo séptimo del artículo 21 de la Constitución Política de los Estados Unidos Mexicanos, penal, en los supuestos y condiciones que fije la ley; el que se expide el Código Nacional de Procedimientos Penal, con un ámbito de aplicación en toda la\nRepública Mexicana, por los delitos que sean competencia de los órganos jurisdiccionales federales y locales, en el marco de los principios y derechos consagrados en la Constitución Política de los Estados\nUnidos Mexicanos, además de que establece dicho Código, las normas que han de observarse en la\nAGENTES DEL MINISTERIO PÚBLICO LA APLICACIÓN\nDE LOS CRITERIOS DE OPORTUNIDAD; Y\nDELEGACIÓN DE LA FACULTAD PARA\nAUTORIZARLOS investigación, el procesamiento y la sanción de los delitos en toda la República, en los fueros federal y local;\nQue el artículo Octavo Transitorio del Decreto por el que se expide el Código Nacional de\nProcedimientos Penales, establece que la Federación y las Entidades Federativas deberán publicar las reformas a sus leyes y demás normatividad complementaria, que resulte necesaria para la implementación del Código Nacional de Procedimientos Penales;\nQue los artículos 221 y 256 del Código Nacional de Procedimientos Penales, otorgan al Ministerio\nPúblico la facultad de aplicar el criterio de oportunidad en los casos previstos por la ley y, establecen que podrá no ejercer la acción penal con base en la aplicación de criterios de oportunidad, los supuestos en que puede operarlos y la imperiosa necesidad de que se haya reparado o garantizado los daños causados a la víctima u ofendido o ésta manifieste su falta de interés jurídico en dicha reparación, de lo cual deberá dejarse constancia;\nQue es el Ministerio Público el órgano encargado de la investigación de los delitos y la persecución de los imputados; y, en atención al principio de legalidad, le corresponde solicitar la intervención de la autoridad judicial competente, en todos los casos en los que sea procedente;\nQue el Ministerio Público aplicará los criterios de oportunidad sobre la base de razones objetivas y sin discriminación, valorando las circunstancias especiales en cada caso, de conformidad con lo dispuesto en el Código Nacional de Procedimientos Penales, así como en los criterios generales que al efecto emita el Procurador o equivalente;\nQue el artículo 11 de la Ley Orgánica de la Fiscalía General del Estado de Guerrero número 500, establece que, entre las atribuciones del Ministerio Público, se encuentra la de solicitar la aplicación y aprobación de los criterios de oportunidad, los que deberán de ser autorizados por el Procurador o por el servidor público en quien se delegue esta facultad;\nCon la finalidad de brindar a la población en general un servicio adecuado basado en los principios de legalidad, honradez, lealtad, profesionalismo, imparcialidad, eficiencia, eficacia, certeza, objetividad, transparencia y respeto irrestricto de los derechos humanos, establecidos en los artículos 139 de la referida Ley, resulta indispensable implementar acciones que fortalezcan la Procuración de Justicia en el\nEstado, con el propósito de optimizar los recursos que se le asignan y mejorar los servicios que se proporcionan;\nAGENTES DEL MINISTERIO PÚBLICO LA APLICACIÓN\nDE LOS CRITERIOS DE OPORTUNIDAD; Y\nDELEGACIÓN DE LA FACULTAD PARA\nAUTORIZARLOS\nEstado de Guerrero;\nQue los criterios de oportunidad forman parte de una estrategia de política criminal que faculta al\nMinisterio Público a ponderar el ejercicio de la acción penal, bajo los supuestos y criterios que fija la ley procesal penal y con su aplicación se pueden optimizar recursos materiales, financieros y humanos, siempre en estricto apego al marco constitucional y legal vigente, sin generar espacios de impunidad, en su encomienda de investigar las conductas delictivas;\nQue para la aplicación de los criterios de oportunidad, es necesario contar con disposiciones claras y precisas que permitan establecer el procedimiento que debe observar el Ministerio Público, así como un registro de los mismos, a fin de llevar el adecuado control de su aplicación;\nPor todo lo considerado y expuesto anteriormente y para el efecto de que surta los efectos legales y administrativos a que haya lugar, tengo a bien expedir el siguiente:\nPRIMERO.- El presente Acuerdo tiene por objeto establecer los lineamientos que debe observar el Ministerio Público de la Fiscalía General del Estado de Guerreo, para la aplicación de los criterios de oportunidad.\nSe entenderá por criterio de oportunidad, la ponderación que hace el Ministerio Público respecto del ejercicio de la acción penal, en los casos que autoriza la Ley.\nLa aplicación de los criterios de oportunidad corresponde exclusivamente al Ministerio Público, y no estará sujeta a ninguna presión proveniente de cualquier fuente, sin perjuicio del control jurisdiccional que sobre la misma se lleve a cabo, conforme a lo previsto en la Legislación Procesal Penal aplicable.\nSEGUNDO.- La aplicación de un criterio de oportunidad se hará sobre la base de razones objetivas y sin discriminación, valorando las circunstancias especiales en cada caso; para ello, el Ministerio Público deberá verificar si existen en los registros de investigación, datos o medios de pruebas suficientes para determinar su procedencia, de conformidad con lo previsto en el artículo 256 del Código Nacional de\nProcedimientos Penales, y en los presentes lineamientos.\nTERCERO.- Podrá ordenarse la aplicación del criterio de oportunidad en cualquier momento a partir del inicio del procedimiento penal conforme a lo dispuesto por el artículo 256, del Código Nacional de\nProcedimientos Penales y hasta antes de que se dicte el auto de apertura a juicio;\nAGENTES DEL MINISTERIO PÚBLICO LA APLICACIÓN\nDE LOS CRITERIOS DE OPORTUNIDAD; Y\nDELEGACIÓN DE LA FACULTAD PARA\nAUTORIZARLOS\nCUARTO.- No podrá aplicarse el criterio de oportunidad en los casos de delitos contra el libre desarrollo de la personalidad, de violencia familiar ni en los casos de delitos fiscales o aquellos que afecten gravemente el interés público.\nQUINTO.- En todos los casos, previo a la aplicación de un criterio de oportunidad, el Ministerio\nPúblico deberá constatar:\nI. Que se hayan reparado o garantizado los daños causados, salvo que exista constancia de la manifestación de falta de interés jurídico en dicha reparación por la víctima u ofendido; y,\nII. Que al imputado no se le haya aplicado un criterio de oportunidad en cualquier fuero durante los cinco años anteriores.\nSEXTO.- Para la aplicación de un criterio de oportunidad, cuando se trate de un delito que no tenga pena privativa de libertad, tenga pena alternativa o tenga pena privativa de libertad cuya punibilidad máxima sea de cinco años de prisión, incluidas sus calificativas atenuantes o agravantes, siempre que el delito no se haya cometido con violencia física o moral, el Ministerio Público, deberá privilegiar la aplicación de un acuerdo reparatorio o la suspensión condicional del proceso, antes de aplicar un criterio de oportunidad en este supuesto, de lo cual deberá dejar registro.\nSÉPTIMO.- Para la aplicación de un criterio de oportunidad, cuando se trate de delitos de contenido patrimonial cometidos sin violencia física o moral sobre las personas o de delitos culposos, siempre que el imputado no hubiere actuado en estado de ebriedad, bajo el influjo de narcóticos o de cualquier otra sustancia que produzca efectos similares, el Ministerio Público deberá tomar en consideración que se establezca que el imputado no implica un riesgo en la seguridad de la víctima u ofendido, o de la sociedad.\nCuando ello resulte procedente, el Ministerio Público deberá privilegiar la celebración de un acuerdo reparatorio o la suspensión condicional del proceso, antes que la aplicación de un criterio de oportunidad en este supuesto, de lo cual deberá dejar registro.\nOCTAVO.- Para la aplicación de un criterio de oportunidad, cuando el imputado haya sufrido como consecuencia directa del hecho delictivo un daño físico o psicoemocional grave, o cuando el imputado haya una pena, el Ministerio Público, deberá tomar en consideración los siguientes criterios:\nI. Que de los dictámenes periciales correspondientes, se acredite que el estado físico o psicoemocional del imputado es grave, así como considerar el grado de afectación y la duración en el tiempo, de dicho estado, o bien que se acredite que el imputado contrajo una enfermedad terminal, de\nAGENTES DEL MINISTERIO PÚBLICO LA APLICACIÓN\nDE LOS CRITERIOS DE OPORTUNIDAD; Y\nDELEGACIÓN DE LA FACULTAD PARA\nAUTORIZARLOS\nII. Que se establezca que el imputado no implica un riesgo en la seguridad de la víctima u ofendido, o de la sociedad.\nUna vez que se haya acreditado que el estado físico o psicoemocional del imputado es grave o que contrajo una enfermedad terminal, el Ministerio Público deberá de llevar a cabo un análisis de la posible pena a imponer, con base en los criterios para la individualización de sanciones que prevé el Código\nNacional de Procedimientos Penales y ponderar si la aplicación de la pena resulta notoriamente innecesaria o desproporcional.\nNOVENO. Para la aplicación de un criterio de oportunidad, cuando la pena o medida de seguridad que pudiera imponerse por el hecho delictivo carezca de importancia en consideración a la pena o medida de seguridad ya impuesta al inculpado por otro delito, o la que podría aplicarse al mismo por otros delitos o bien, por la pena que previamente se le haya impuesto o podría llegar a imponérselo en virtud de diverso proceso tramitado en otro fuero, el Ministerio Público, deberá tomar en consideración los siguientes criterios:\nI. Que el delito en el que se aplique el criterio de oportunidad no sea de los delitos que ameritan prisión preventiva oficiosa; y\nII. Que se acredite que el imputado haya sido sentenciado por otro delito y deba cumplir una pena de prisión o que este siendo procesado por la comisión de otro delito, en este último caso será procedente cuando sea necesaria para el adecuado desarrollo del procedimiento penal diverso y cuando existan datos razonables que determinen la posibilidad de obtener en su contra una condena.\nEl Ministerio Público deberá de llevar a cabo un análisis de la posible pena a imponer por el delito por el que se pretende aplicar el criterio de oportunidad, con base en los criterios para la individualización de sanciones que prevé el Código Nacional de Procedimientos Penales, y a partir de ello, ponderar que la pena que se pudiera llegar a imponer sea menor a la cuarta parte de los que resta por cumplir en la sentencia por otro delito o de la pena que pudiera llegar a imponerse en el otro procedimiento.\nDÉCIMO.- Para la aplicación de un criterio de oportunidad, cuando el imputado aporte información esencial para la persecución de un delito más grave del que se le imputa, la información que proporcione derive en la detención de un imputado diverso y se comprometa a comparecer en juicio, el Ministerio\nPúblico, deberá tomar en consideración los siguientes criterios:\nI. Que la información que aporte el imputado coadyuve de forma eficaz para la investigación y persecución de otro hecho que la ley señale como delito con mayor punibilidad, o en el mismo hecho que o cuando haya tenido una intervención menor que otros imputados; y\nAGENTES DEL MINISTERIO PÚBLICO LA APLICACIÓN\nDE LOS CRITERIOS DE OPORTUNIDAD; Y\nDELEGACIÓN DE LA FACULTAD PARA\nAUTORIZARLOS\nII. Que el imputado acepte de forma expresa y en presencia de su defensor declarar en juicio respecto de la información proporcionada.\nEn este supuesto, los efectos del criterio de oportunidad y la prescripción, se suspenderán hasta en tanto el imputado beneficiado comparezca a rendir su declaración en la audiencia de juicio.\nDÉCIMO PRIMERO.- Para la aplicación de un criterio de oportunidad, cuando la afectación del bien jurídico tutelado resulte poco significativa, el Ministerio Público deberá tomar en consideración los siguientes criterios:\nI. Que el delito en el que se aplique el criterio de oportunidad no sea de los delitos que ameritan prisión preventiva oficiosa;\nII. Que el grado de afectación al bien jurídico haya resultado poco significativa; y\nIII. Que se establezca que el imputado no implica un riesgo en la seguridad de la víctima u ofendido o de la sociedad.\nAsimismo, para determinar insignificancia en el grado de afectación al bien jurídico a que se refiere la fracción segunda del presente lineamiento, el Ministerio Público deberá tomar en consideración el valor del bien jurídico tutelado, la naturaleza dolosa o culposa de la conducta, los medios empleados y las circunstancias de tiempo, modo, lugar u ocasión del hecho y la forma de intervención del imputado en la comisión del delito.\nDÉCIMO SEGUNDO.- Para la aplicación de un criterio de oportunidad, cuando la continuidad del proceso o la aplicación de la pena sea irrelevante para los fines preventivos de la política criminal, el\nMinisterio Público, deberá de tomar en consideración los siguientes criterios:\nI. Que el delito en el que se aplique el criterio de oportunidad no sea de los delitos que ameritan prisión preventiva oficiosa;\nII. Que se establezca que el imputado no implica un riesgo en la seguridad de la víctima u ofendido,\nIII. Que en razón de las causas o circunstancias que rodean la comisión de la conducta punible, resulte desproporcionada o irrazonable la persecución penal.\nDÉCIMO TERCERO.- La facultad para autorizar la aplicación de un criterio de oportunidad, se delega en el Vice fiscal de Investigación de la Fiscalía General del Estado de Guerrero, para lo cual la solicitud que formule el Ministerio Público que conozca de la Carpeta de Investigación, deberá contar con el visto bueno del Fiscal Especializado o Regional a cuya adscripción corresponda dicho Ministerio Público.\nAGENTES DEL MINISTERIO PÚBLICO LA APLICACIÓN\nDE LOS CRITERIOS DE OPORTUNIDAD; Y\nDELEGACIÓN DE LA FACULTAD PARA\nAUTORIZARLOS\nDÉCIMO CUARTO.- La solicitud de autorización para la aplicación de un criterio de oportunidad, que realice el Ministerio Público, deberá formularse por escrito y remitirse con el visto bueno del Fiscal\nEspecializado o Regional de la adscripción correspondiente, a través de cualquier medio que garantice su autenticidad, al Vice fiscal de Investigación; además, deberá acompañarse de un informe ejecutivo debidamente fundado y motivado, de los requisitos que sustenta la misma, conforme a los principios y criterios generales establecidos en el Código Nacional de Procedimientos Penales, en el presente Acuerdo y demás legislación relativa y aplicable, misma que deberá contener:\nI. El lugar y fecha de la solicitud;\nII. Nombre y adscripción del Ministerio Público que propone la aplicación del criterio de oportunidad, así como del Fiscal Regional de Adscripción;\nIII. Nombre del imputado a quien se le aplicará el criterio de oportunidad, así como de la víctima u ofendido;\nIV. Una breve descripción de los hechos y su clasificación jurídica;\nV. El razonamiento lógico jurídico por el que se justifica su aplicación; y,\nVI. Lo relativo a la reparación del daño ocasionado a la víctima u ofendido.\nDÉCIMO QUINTO.- La solicitud a que se refiere el lineamiento anterior, deberá ser resuelta y remitida al Ministerio Público solicitante, por escrito o a través de cualquier medio que garantice su autenticidad en un plazo no mayor a 72 horas, contados a partir del día siguiente de su recepción por el\nVice fiscal de Investigación.\nEn el caso de que sea autorizada la solicitud de la aplicación del criterio de oportunidad, el Agente del Ministerio Público que la formuló, realizará las actuaciones siguientes:\nI. Determinar la extinción de la acción penal a favor del o los imputados, precisando la clasificación jurídica correspondientes;\nII. Determinar el destino legal de los objetos o documentos que se encuentran relacionados con la investigación y que hayan sido puestos a su disposición;\nIII. Inscribir en el registro de aplicación de criterios de oportunidad, la determinación relativa; y,\nIV. Notificar a la víctima u ofendido y al imputado la determinación de aplicación del criterio de oportunidad, dentro de los tres días hábiles siguientes a su emisión. Dicha notificación deberá realizarse personalmente a la víctima u ofendido, informándole su derecho para impugnar dicha determinación.\nAGENTES DEL MINISTERIO PÚBLICO LA APLICACIÓN\nDE LOS CRITERIOS DE OPORTUNIDAD; Y\nDELEGACIÓN DE LA FACULTAD PARA\nAUTORIZARLOS\nDÉCIMO SEXTO.- Cuando el Agente del Ministerio Público reciba la solicitud de aplicación de un criterio de oportunidad y estime que el mismo no es procedente, emitirá de manera fundada y motivada la determinación correspondiente.\nEn este caso, el solicitante podrá inconformarse ante el titular de la Fiscalía Especializada o\nRegional a la que se encuentre adscrito el Agente del Ministerio Público, en un plazo de tres días hábiles contados a partir de la notificación respectiva.\nPara tal efecto, el Fiscal Especializado o Regional deberá analizar la determinación del Ministerio\nPúblico y resolverá en un plazo de cinco días hábiles, señalando si la confirma o, en su caso, la revoca; en este último supuesto el agente del ministerio público se avocara de nuevo al análisis de tal solicitud, tomando en cuenta las directrices emitidas por el Fiscal, y hecho lo anterior remitir la solicitud al Vice fiscal de Investigación conforme a lo establecido en los puntos Décimo Tercero y Décimo Cuarto del presente\nAcuerdo.\nDÉCIMO SÉPTIMO.- La aplicación de los criterios de oportunidad es procedente desde el momento en que el agente del Ministerio Público cuente con datos que establezcan que se ha cometido un hecho que la ley señala como delito y la probabilidad de que el imputado lo realizó o participó en su comisión, y hasta antes de que se ejerza la acción penal o en su caso, antes de que se dicte el auto de apertura a juicio oral.\nPara tal efecto, el agente del Ministerio Público que esté interviniendo en el procedimiento penal, será el que proponga o aplique el criterio de oportunidad, de acuerdo con la etapa procesal en que se encuentre.\nEn caso de que la víctima u ofendido y su asesor jurídico impugnen la determinación de la aplicación del criterio de oportunidad, el Fiscal o el Ministerio Público que reciba la notificación, de inmediato lo hará del conocimiento al Vice fiscal de Investigación, proporcionándole la carpeta de investigación y los\nJuez de Control, a exponer los motivos y fundamentos que se consideraron para la aplicación de esta forma de terminación de la investigación, solicitando su confirmación.\nDECIMO OCTAVO.- El registro de aplicación de criterios de oportunidad deberá contener los datos siguientes:\nI. Datos generales del imputado, la victima u ofendido, tales como:\na) Nombre, apellido, en su caso, el alias o sobre nombre;\nb) Lugar y fecha de nacimiento\nAGENTES DEL MINISTERIO PÚBLICO LA APLICACIÓN\nDE LOS CRITERIOS DE OPORTUNIDAD; Y\nDELEGACIÓN DE LA FACULTAD PARA\nAUTORIZARLOS\nc) Nacionalidad\nd) Sexo\ne) Estado civil\nf) Domicilio\ng) Ocupación\nh) Clave única de registro de población (opcional)\ni) Escolaridad\nj) Edad al momento de los hechos; y\nk) Edad al momento de la aplicación\nII-. El supuesto legal que origino la aplicación del criterio de oportunidad;\nIII-. Lugar y fecha en que se aplicó el criterio de oportunidad;\nIV-.Agente del Ministerio Publico que aplico el criterio y su adscripción\nV-.Superior Jerárquico que autorizo la aplicación y su adscrip0cion;\nVI-.La clasificación jurídica correspondiente;\nVII. Número de Carpeta de Investigación correspondiente;\nVIII. Pago o garantía de la reparación del daño, o en su caso manifestación de no tener interés jurídico en ella;\nIX. Fecha en que quedó firme la aplicación del criterio de oportunidad; y,\nX. Fecha en que se declaró la extinción de la pretensión punitiva.\nDECIMO NOVENO.- Los servidores públicos de la Fiscalía General del Estado de Guerrero, lineamientos, sin perjuicio de las demás responsabilidades que en su caso resulten procedentes.\nAGENTES DEL MINISTERIO PÚBLICO LA APLICACIÓN\nDE LOS CRITERIOS DE OPORTUNIDAD; Y\nDELEGACIÓN DE LA FACULTAD PARA\nAUTORIZARLOS\nVIGESIMO.- Los titulares de las Unidades Administrativas de la Fiscalía General, proveerán en la esfera de su competencia, la vigilancia del cumplimiento del presente Acuerdo.\nPRIMERO.- Publíquese el presente Acuerdo en el Periódico Oficial del Gobierno del Estado de\nGuerrero, para conocimiento general, y désele la difusión más amplia.\nSEGUNDO.- El presente Acuerdo entrará en vigor al día siguiente de su publicación en el Periódico\nOficial del Gobierno del Estado de Guerrero.\nTERCERO.- Se instruye a los servidores públicos previstos en el presente Acuerdo, a realizar las acciones necesarias para la aplicación del presente Instrumento Jurídico en el ámbito de sus atribuciones.\nCUARTO.- El Instituto de Formación y Capacitación Profesional, llevará a cabo la capacitación del presente Acuerdo.\nDado en la Ciudad de Chilpancingo de los Bravo, Guerrero; a los 06 días del mes de enero del\n2016.\nEL FISCAL GENERAL DEL ESTADO DE GUERRERO.\nLIC. JAVIER IGNACIO OLEA PELÁEZ.\nRúbrica.",
  "ordenamiento": "ACUERDO",
  "jurisdiccion": "GUERRERO",
  "fuente_oficial": "DIARIO OFICIAL DE LA FEDERACION",
  "Fecha de Publicación": "12 \nde Abril de 2016",
  "ULTIMA REFORMA PUBLICADA": null,
  "status": "VIGENTE",
  "es_escaneado": false,
  "tiene_tablas": false,
  "materia": [
    "fiscal"
  ]
}