{
  "titulo": "Acuerdo por el Que Se Da A Conocer el Monto de las Participaciones Entregadas A los Municipios del E 10",
  "Contenido": "FONDO COMÚN DE PARTICIPACIONES, DEL FONDO\nDE FOMENTO MUNICIPAL, DEL FONDO PARA LA\nINFRAESTRUCTURA A MUNICIPIOS Y DEL FONDO\nDE APORTACIONES ESTATALES PARA LA\nINFRAESTRUCTURA SOCIAL MUNICIPAL, EN EL\nTERCER TRIMESTRE DEL EJERCICIO FISCAL 2014\nABROGADO POR CONCLUIDA SU VIGENCIA EL 30 DE SEPTIEMBRE DE 2014.\nTEXTO ORIGINAL.\nAcuerdo publicado en el Periódico Oficial del Gobierno del Estado No. 81 Alcance II, el Viernes\n10 de Octubre de 2014.\nACUERDO POR EL QUE SE DA A CONOCER EL MONTO DE LAS PARTICIPACIONES\nENTREGADAS A LOS MUNICIPIOS DEL ESTADO DE GUERRERO, DEL FONDO COMÚN DE\nPARTICIPACIONES, DEL FONDO DE FOMENTO MUNICIPAL, DEL FONDO PARA LA\nINFRAESTRUCTURA A MUNICIPIOS Y DEL FONDO DE APORTACIONES ESTATALES PARA LA\nINFRAESTRUCTURA SOCIAL MUNICIPAL, EN EL TERCER TRIMESTRE DEL EJERCICIO FISCAL\n2014.\nGuerrero.- Poder Ejecutivo.\nÁNGEL HELADIO AGUIRRE RIVERO, GOBERNADOR CONSTITUCIONAL DEL ESTADO\nGUERRERO, 6o., 10, 20 FRACCION III Y 22 DE LA LEY ORGÁNICA DE LA ADMINISTRACIÓN\nPÚBLICA DEL ESTADO DE GUERRERO NÚMERO 433; 19 Y 21 DEL DECRETO NÚMERO 438 DEL\nPRESUPUESTO DE EGRESOS DEL ESTADO DE GUERRERO, PARA EL EJERCICIO FISCAL 2014;\n26, 27, 28, 29, 30, 31, 32, 33, 34 Y 48, DE LA LEY NÚMERO 427 DEL SISTEMA DE COORDINACION\nHACENDARIA DEL ESTADO DE GUERRERO, Y\nQue las participaciones asignadas al Estado de Guerrero para el Ejercicio Fiscal de 2014, deben ser redistribuidas entre los municipios en los porcentajes que señala el Capítulo I denominado \"De las\nParticipaciones de los Estados, Municipios y Distrito Federal en Ingresos Federales\" de la Ley de\nCoordinación Fiscal y de acuerdo a los criterios y fórmulas que se establecen en la Ley número 427, del\nSistema de Coordinación Hacendaria del Estado de Guerrero.\nQue la Ley de Coordinación Fiscal en el artículo 6o., penúltimo párrafo establece que \"Los\nGobiernos de las entidades, a más tardar el 15 de febrero, deberán publicar en su Periódico Oficial de la\nEntidad, así como en su página oficial de internet el calendario de entrega, porcentaje, fórmulas y variables utilizadas, así como los montos estimados de las participaciones que las entidades reciban y de las que tengan obligación de participar a sus municipios o demarcaciones territoriales. También deberán\nFONDO COMÚN DE PARTICIPACIONES, DEL FONDO\nDE FOMENTO MUNICIPAL, DEL FONDO PARA LA\nINFRAESTRUCTURA A MUNICIPIOS Y DEL FONDO\nDE APORTACIONES ESTATALES PARA LA\nINFRAESTRUCTURA SOCIAL MUNICIPAL, EN EL\nTERCER TRIMESTRE DEL EJERCICIO FISCAL 2014 publicar trimestralmente en el Periódico Oficial, así como en la página oficial de internet del gobierno de la entidad, el importe de las participaciones entregadas y, en su caso, el ajuste realizado al término de cada ejercicio fiscal. La Secretaría de Hacienda y Crédito Público publicará en el Diario Oficial de la Federación la lista de las Entidades que incumplan con esta disposición\".\nPor lo anteriormente expuesto y fundado, he tenido a bien expedir el siguiente:\nACUERDO POR EL QUE SE DA A CONOCER EL MONTO DE LAS PARTICIPACIONES\nENTREGADAS A LOS MUNICIPIOS DEL ESTADO DE GUERRERO, DEL FONDO COMÚN DE\nPARTICIPACIONES, DEL FONDO DE FOMENTO MUNICIPAL, DEL FONDO PARA LA\nINFRAESTRUCTURA A MUNICIPIOS Y DEL FONDO DE APORTACIONES ESTATALES PARA LA\nINFRAESTRUCTURA SOCIAL MUNICIPAL, EN EL TERCER TRIMESTRE DEL EJERCICIO FISCAL\n2014.\nARTÍCULO PRIMERO.- El presente Acuerdo tiene por objeto dar a conocer el monto de las\nParticipaciones Federales entregadas a cada uno de los Municipios del Estado de Guerrero, durante el tercer trimestre del año 2014. establecido en los artículos 2o., 2-A, 3-A, 4o., 4o.-A y 6o., de la Ley de Coordinación Fiscal y 26, 27, 28, 29, 30, 31, 32, 33, 34 y 48 de la Ley número 427, del Sistema de Coordinación Hacendaria del Estado de\nGuerrero.\nARTÍCULO TERCERO.- Los montos de cada uno de los conceptos que se transfirieron a los municipios, durante el tercer trimestre del ejercicio fiscal 2014, fueron los siguientes:\nFONDO COMÚN DE PARTICIPACIONES, DEL FONDO\nDE FOMENTO MUNICIPAL, DEL FONDO PARA LA\nFONDO COMÚN DE PARTICIPACIONES, DEL FONDO\nDE FOMENTO MUNICIPAL, DEL FONDO PARA LA\nFONDO COMÚN DE PARTICIPACIONES, DEL FONDO\nDE FOMENTO MUNICIPAL, DEL FONDO PARA LA\nFONDO COMÚN DE PARTICIPACIONES, DEL FONDO\nDE FOMENTO MUNICIPAL, DEL FONDO PARA LA\nINFRAESTRUCTURA A MUNICIPIOS Y DEL FONDO\nDE APORTACIONES ESTATALES PARA LA\nINFRAESTRUCTURA SOCIAL MUNICIPAL, EN EL\nTERCER TRIMESTRE DEL EJERCICIO FISCAL 2014\nÚNICO.- Publíquese el presente Acuerdo en el Periódico Oficial del Gobierno del Estado Libre y\nSoberano de Guerrero, para el conocimiento general y efectos legales procedentes.\nDado en la Residencia Oficial del Poder Ejecutivo del Estado, en la Ciudad de Chilpancingo de los Bravo, Capital del Estado de Guerrero, a los siete días del mes de octubre de dos mil catorce.\nEL GOBERNADOR CONSTITUCIONAL DEL ESTADO\nLIC. ÁNGEL HELADIO AGUIRRE RIVERO.\nEL SECRETARIO GENERAL DE GOBIERNO.\nDR. JESÚS MARTÍNEZ GARNELO.\nEL SECRETARIO DE FINANZAS Y ADMINISTRACIÓN.\nC.P. JORGE SILVERIO SALGADO LEYVA.",
  "ordenamiento": "ACUERDO",
  "jurisdiccion": "GUERRERO",
  "fuente_oficial": "DIARIO OFICIAL DE LA FEDERACION",
  "Fecha de Publicación": "30 DE SEPTIEMBRE DE 2014",
  "ULTIMA REFORMA PUBLICADA": "10 de Octubre de 2014",
  "status": "ABROGADA",
  "es_escaneado": false,
  "tiene_tablas": false,
  "materia": [
    "municipal"
  ]
}