{
  "titulo": "Acuerdo del Auditor General del Estado de Guerrero, por el Que Se Establecen los Criterios y Montos",
  "Contenido": "FIANZAS DE LOS SERVIDORES PÚBLICOS DE LAS\nENTIDADES FISCALIZABLES, QUE TIENEN A SU CARGO\nLA CUSTODIA Y ADMINISTRACIÓN DE RECURSOS\nPÚBLICOS, EN TÉRMINOS DE LO PREVISTO EN LOS\nARTÍCULOS 107, 108 Y 109 FRACCIÓN I DE LA LEY\nNÚMERO 1028 DE FISCALIZACIÓN SUPERIOR Y\nRENDICIÓN DE CUENTAS DEL ESTADO DE GUERRERO\nTEXTO ORIGINAL.\nAcuerdo publicado en el Periódico Oficial del Gobierno del Estado No. 77, el Martes 24 de\nSeptiembre de 2013.\nACUERDO DEL AUDITOR GENERAL DEL ESTADO DE GUERRERO, POR EL QUE SE\nESTABLECEN LOS CRITERIOS Y MONTOS PARA EL OTORGAMIENTO DE FIANZAS DE LOS\nSERVIDORES PÚBLICOS DE LAS ENTIDADES FISCALIZABLES, QUE TIENEN A SU CARGO LA\nCUSTODIA Y ADMINISTRACIÓN DE RECURSOS PÚBLICOS, EN TÉRMINOS DE LO PREVISTO EN\nLOS ARTÍCULOS 107, 108 Y 109 FRACCIÓN I DE LA LEY NÚMERO 1028 DE FISCALIZACIÓN\nSUPERIOR Y RENDICIÓN DE CUENTAS DEL ESTADO DE GUERRERO.\nEl suscrito Licenciado Certificado Arturo Latabán López, Auditor General del Estado, en uso de de Guerrero; 204 de la Ley Orgánica del Poder Legislativo del Estado número 286; 71, 90 fracción I y XII, XXXV y XXXVII, 107, 108 y 109 de la Ley numero 1028 de Fiscalización Superior y Rendición de Cuentas del Estado de Guerrero; y:\nPRIMERO.- Que en términos de lo establecido por los artículos 116 de la Constitución Política de los Estados Unidos Mexicanos; 107 fracción IV párrafos segundo y tercero de la Constitución Política\nGuerrero y 11 de la Ley de Fiscalización Superior del Estado de Guerrero numero 564, con fecha veinte de diciembre del año dos mil diez, fui nombrado Auditor General del Estado, por la Quincuagésima años contados a partir del día primero de enero de dos mil once. de Guerrero, primordialmente establecen, que todo servidor público o empleado, que tenga que manejar fondos, ya sea del estado o del municipio, deberá otorgar fianza en términos de ley; Asimismo que la autonomía financiera, técnica y de gestión en el ejercicio de sus atribuciones y para decidir sobre sus programas de trabajo, funcionamiento y emisión de sus resoluciones, en los términos que establezca la\nLey de Fiscalización Superior.\nEn ese sentido, la obligación establecida en el artículo 105 constitucional antes señalado, tiene por objeto que los servidores públicos o empleados que manejen fondos públicos, garanticen el buen\nFIANZAS DE LOS SERVIDORES PÚBLICOS DE LAS\nENTIDADES FISCALIZABLES, QUE TIENEN A SU CARGO\nLA CUSTODIA Y ADMINISTRACIÓN DE RECURSOS\nPÚBLICOS, EN TÉRMINOS DE LO PREVISTO EN LOS\nARTÍCULOS 107, 108 Y 109 FRACCIÓN I DE LA LEY\nNÚMERO 1028 DE FISCALIZACIÓN SUPERIOR Y\nRENDICIÓN DE CUENTAS DEL ESTADO DE GUERRERO manejo de los mismos, asegurando la reparación de cualquier daño o perjuicio que por la indebida custodia o administración de los recursos que se les confían pudieran generar a las haciendas publicas, sean estatales o municipales.\nTERCERO.- Que con fecha veintiocho de julio del dos mil nueve, fueron publicados en el\nPeriódico Oficial del Gobierno del Estado, los criterios y montos para el otorgamiento de fianzas por los servidores públicos de las entidades fiscalizables, que tengan a su cargo la custodia y administración de fondos públicos, mismos que fueron emitidos por la Auditoría General del Estado, en cumplimiento a lo establecido en la fracción XXVII del artículo 6 de la ley de Fiscalización Superior del Estado de Guerrero número 564.\nCUARTO.- El día 28 de febrero de 2012, fue publicada en el periódico oficial del Gobierno del\nEstado de Guerrero, la Ley número 1028 de Fiscalización Superior y Rendición de Cuentas del Estado de\nGuerrero, misma que abrogo a la ley de fiscalización superior del Estado de Guerrero número 564, la cual en su artículo 71, reitera que la Auditoría General del Estado, gozará de autonomía financiera, técnica y de gestión en el ejercicio de sus atribuciones y para decidir sobre su organización interna, funcionamiento y emisión de sus resoluciones de conformidad con las facultades que le confiere dicha Ley. Asimismo en la fracción XXX del artículo 77 de la referida Ley, le otorga competencia a la Auditoría General del\nEstado, para establecer los criterios y montos a los que debe sujetarse el otorgamiento de fianzas de los servidores públicos que tengan a su cargo la custodia y administración de fondos públicos, verificando su cumplimiento a efecto de garantizar el buen manejo de los recursos públicos;\nEn ese sentido, el artículo 78 y las fracciones I, II, IX, XII, XXXV Y XXXVII del artículo 90 de la\nLey número 1028 de Fiscalización Superior y Rendición de Cuentas del Estado de Guerrero, medularmente establecen, que el titular de la Auditoría General del Estado, tendrá a su cargo la representación institucional de la Auditoría General del Estado, su administración y gobierno interior; asimismo que es legítimo representante de la Auditoría General del Estado, teniendo entre sus facultades la de expedir los reglamentos, manuales de organización y de procedimientos administrativos necesarios para el buen funcionamiento de la Auditoría General; para verificar que se hayan otorgado las garantías por quienes administren o custodien fondos públicos, y fincar las sanciones administrativas que correspondan por su incumplimiento.; así como para presidir y administrar el fondo de afianzamiento de los servidores públicos y las demás que señala dicho ordenamiento legal y otras disposiciones legales.\nPor su parte, los artículos 107, 108 y 109 de la Ley número 1028 de Fiscalización Superior y\nRendición de Cuentas del Estado de Guerrero, a letra establecen:\nFIANZAS DE LOS SERVIDORES PÚBLICOS DE LAS\nENTIDADES FISCALIZABLES, QUE TIENEN A SU CARGO\nLA CUSTODIA Y ADMINISTRACIÓN DE RECURSOS\nPÚBLICOS, EN TÉRMINOS DE LO PREVISTO EN LOS\nARTÍCULOS 107, 108 Y 109 FRACCIÓN I DE LA LEY\nNÚMERO 1028 DE FISCALIZACIÓN SUPERIOR Y\nRENDICIÓN DE CUENTAS DEL ESTADO DE GUERRERO\n\" Artículo 107.- Los servidores públicos de las entidades fiscalizables que reciban, recauden, administren, custodien o apliquen por cualquier título recursos públicos deberán garantizar su manejo.\"\n\" Artículo 108.- Las garantías que los servidores públicos de las entidades fiscalizables deben otorgar en términos del artículo anterior, se ajustarán a los criterios y montos que para tales efectos expida la Auditoria General.\"\n\" Artículo 109.- Para garantizar el manejo de los recursos públicos que se les confíen para su custodia y administración, los servidores públicos de los entes fiscalizables podrán:\nI.- Entregar a la Auditoria General, fianza expedida por institución afianzadora debidamente autorizada conforme a la Ley; y\nII.- Realizar aportaciones en efectivo al Fondo de Afianzamiento de los Servidores Públicos a que se refiere este capítulo.\"\nQUINTO.- En virtud de lo anterior, atendiendo a lo antes señalado, se estima conveniente emitir\nlos CRITERIOS Y MONTOS PARA EL OTORGAMIENTO DE LA GARANTÍA A QUE SE REFIERE LA\nFRACCION I DEL ARTÍCULO 109 DE LA LEY NÚMERO 1028 DE FISCALIZACIÓN SUPERIOR Y\nRENDICIÓN DE CUENTAS DEL ESTADO DE GUERRERO, lo anterior con el propósito fundamental de que los servidores públicos estén en posibilidad de garantizar, los posibles daños y perjuicios que pudieren ocasionar en su ejercicio a las haciendas públicas Estatales y Municipales, razón por lo que con base en los estudios técnicos realizados por esta Auditoría General del Estado, así como a la situación económica que prevalece a nivel nacional, se estima conveniente, para establecer los criterios y montos para el otorgamiento de las referidas garantías, tomar en cuenta, que el otorgamiento de las mismas, se realice por ejercicio fiscal, estableciendo los montos conforme a factores de riesgo reales o de conformidad con el presupuesto que administren las entidades fiscalizables durante el ejercicio correspondiente, asimismo se prevé que para el primer ejercicio fiscal de cada Administración\nGubernamental, los servidores públicos de las entidades fiscalizables, otorguen sus garantías por un monto inicial de conformidad con el presente acuerdo, lo anterior tomando en cuenta, que al inicio de cada administración gubernamental, se desconoce el grado de riesgo que les corresponde, en el públicas, el monto de la garantía podría verse incrementado para el ejercicio fiscal siguiente, según las irregularidades que sean detectadas por este Órgano de Fiscalización Superior, el que para tales efectos, al inicio de cada ejercicio subsecuente, dará a conocer oportunamente a cada entidad fiscalizable, los montos que deberán ser garantizados por sus servidores públicos, lo anterior tomando en cuenta, que\nFIANZAS DE LOS SERVIDORES PÚBLICOS DE LAS\nENTIDADES FISCALIZABLES, QUE TIENEN A SU CARGO\nLA CUSTODIA Y ADMINISTRACIÓN DE RECURSOS\nPÚBLICOS, EN TÉRMINOS DE LO PREVISTO EN LOS\nARTÍCULOS 107, 108 Y 109 FRACCIÓN I DE LA LEY\nNÚMERO 1028 DE FISCALIZACIÓN SUPERIOR Y\nRENDICIÓN DE CUENTAS DEL ESTADO DE GUERRERO cada administración gubernamental representa un riesgo diferente en el manejo de los recursos públicos que se le confieren.\nEn ese sentido, el mecanismo previsto, permitirá inhibir el uso indebido de los recursos públicos, ya que determinados conforme al factor de riesgo señalado, se incentivará a los entes fiscalizables a no incurrir en irregularidades que puedan incrementar el monto a garantizar.\nPor otra parte, resulta necesario, establecer los alcances que tendrán las fianzas que se hubieren contratado por las entidades fiscalizables con anterioridad a la emisión del presente acuerdo y que se hubieren presentado ante la Auditoría General del Estado, en cumplimiento a los preceptos constitucionales y legales antes relacionados.\nPor las anteriores consideraciones, el Auditor General del Estado de Guerrero, ACUERDA:\nPRIMERO.- Con fundamento en los preceptos constitucionales y legales relacionados en los considerandos del presente acuerdo, para el otorgamiento de la garantía prevista en la fracción I del artículo 109 de la Ley número 1028 de Fiscalización Superior y Rendición de Cuentas del Estado de\nGuerrero, los servidores públicos de las entidades fiscalizables, deberán observar los siguientes criterios y montos:\n1).- Tipo de Afianzamiento.- Los servidores públicos de las entidades fiscalizables, que por cualquier causa reciban, recauden, administren, custodien o apliquen recursos públicos en el ejercicio de su función, podrán garantizar su manejo, mediante el otorgamiento de fianza de fidelidad emitida por institución legalmente autorizada para ello.\n2).- Concepto de Fianza.- Es un contrato mercantil accesorio mediante el cual una Institución\nAfianzadora a título oneroso, se compromete a garantizar mediante la emisión de una póliza, el moral, pública o privada, en caso de que aquella no cumpliere;\n3).- Contrato de Fianza de Fidelidad.- Es un contrato mercantil accesorio, cuyo objetivo primordial es el de garantizar a una persona física o moral, pública o privada, la reparación del daño comprobada.\na) La contratación puede ser de manera individual, es decir cubre las responsabilidades de una sola persona en un puesto o cargo determinado hasta por una suma determinada.\nFIANZAS DE LOS SERVIDORES PÚBLICOS DE LAS\nENTIDADES FISCALIZABLES, QUE TIENEN A SU CARGO\nLA CUSTODIA Y ADMINISTRACIÓN DE RECURSOS\nPÚBLICOS, EN TÉRMINOS DE LO PREVISTO EN LOS\nARTÍCULOS 107, 108 Y 109 FRACCIÓN I DE LA LEY\nNÚMERO 1028 DE FISCALIZACIÓN SUPERIOR Y\nRENDICIÓN DE CUENTAS DEL ESTADO DE GUERRERO\nb) La contratación puede ser de manera colectiva o global y garantiza el cumplimiento de las responsabilidades de todo el personal administrativo y por un monto global para todos y cada uno de los empleados o funcionarios sujetos a caución por ley.\nCada una de las entidades fiscalizables, deberá contratar la póliza de fianza de fidelidad, ya sea de manera individual o colectiva con cualquier compañía afianzadora, siempre y cuando la póliza contenga las características previstas en la legislación aplicable y en estos criterios. Asimismo los referidos contratos deberán ser firmados con toda oportunidad a la fecha de presentación de la garantía, entregando a la Auditoría General del Estado, copia debidamente certificada de la póliza y del referido contrato de fianza.\n4).- Cobertura de la Fianza Fidelidad.- La fianza que otorguen los servidores públicos, deberá cubrir la responsabilidad derivada de la comisión de los siguientes ilícitos:\n- Robo.- Comete el delito de robo, el que se apodera de una cosa ajena mueble, sin derecho y sin consentimiento de la persona que pueda disponer de ella con arreglo en la Ley.\n- Fraude.- Comete el delito de fraude, el que engañando a otro o aprovechándose del error en que este se halla, se haga ilícitamente de alguna cosa o alcance un lucro indebido para sí o para otro.\n- Abuso de Confianza.- Comete el delito de abuso de confianza, quien el que con perjuicio de alguien, disponga para sí o para otro, de una cantidad de dinero en numerario, en billetes de banco, de un documento que impone obligación, liberación o transmisión de derechos o de cualquier otra cosa ajena mueble, de la cual se haya transmitido la tenencia, custodia o uso, pero no el dominio.\n- Peculado.- Comete el delito de peculado, todo servidor público que, para usos propios o ajenos distraiga de su objeto dinero, valores, fincas o cualquier otra cosa perteneciente al estado, municipio, organismo auxiliar, organismo público descentralizado, empresa de participación municipal mayoritaria, fideicomiso público o de la entidad pública en donde ejerza su función o cargo.\n5).- Sujetos Afianzados.- Cualquier servidor público responsable de la recepción, manejo, custodia, administración o aplicación de recursos públicos de las entidades fiscalizables.\n6).- Montos de la Fianza.- Para determinar el monto de las fianzas de los servidores públicos del Estado de Guerrero y de sus Municipios, se tomará como base, la que resulte de las siguientes opciones:\nFIANZAS DE LOS SERVIDORES PÚBLICOS DE LAS\nENTIDADES FISCALIZABLES, QUE TIENEN A SU CARGO\nLA CUSTODIA Y ADMINISTRACIÓN DE RECURSOS\nPÚBLICOS, EN TÉRMINOS DE LO PREVISTO EN LOS\nARTÍCULOS 107, 108 Y 109 FRACCIÓN I DE LA LEY\nNÚMERO 1028 DE FISCALIZACIÓN SUPERIOR Y\nRENDICIÓN DE CUENTAS DEL ESTADO DE GUERRERO\na).- Al inicio de la administración de cada entidad fiscalizable, los servidores públicos podrán garantizar al comienzo del primer ejercicio fiscal que les corresponda, la custodia y administración de los recursos públicos, mediante el otorgamiento de fianza por un monto mínimo de $100,000.00 (CIEN MIL\nPESOS 00/100 M.N.).\nb).- Para los ejercicios subsecuentes, el monto de la fianza podrá determinarse, en razón del que resulte de aplicar el 4% al presupuesto de egresos autorizado a la entidad fiscalizable para el ejercicio anual anterior, sin que dicho monto pueda exceder de $10’000,000.00 (DIEZ MILLONES DE PESOS\n00/100 M.N.), ni ser menor a $1’000,000.00 (Un millón de pesos 00/100 M.N.), o bien, por el monto que resulte de las observaciones derivadas de la fiscalización de la cuenta pública correspondiente al último ejercicio fiscalizado o en su defecto, las que resulten de las evaluaciones que se realicen a los informes financieros presentados por la entidad fiscalizable durante el primer ejercicio y que sean determinadas para tales efectos, por la Auditoría General del Estado, conforme a la siguiente:\nTABLA DE APLICACIÓN\nObservaciones Monto\nMayores de Hasta de la Fianza\n$ 0.00 $ 200,000.00 $ 100,000.00\n200,001.00 400,000.00 300,000.00\n400,001.00 600,000.00 500,000.00\n600,000.00 800,000.00 700,000.00\n800,001.00 1’000,000.00 900,000.00\n1’000,001.00 2’000,000.00 1’500,000.00\n2’000,001.00 3’000,000.00 2’500,000.00\n3’000,001.00 4’000,000.00 3’500,000.00\n4’000,001.00 5’000,000.00 4’500,000.00\n5’000,001.00 en adelante 5’000,000.00\nPara el otorgamiento de las fianzas conforme a los montos señalados en la tabla anterior, los servidores públicos de las entidades fiscalizables, deberán solicitar a la Auditoria General del Estado a corresponda, el monto total por el que habrán de otorgar la fianza respectiva, lo que será determinado atendiendo al monto que le corresponda conforme a lo establecido en la tabla de aplicación.\n6).- Beneficiarios de la Fianza.- Los beneficiarios de la fianza que otorguen los servidores\nFIANZAS DE LOS SERVIDORES PÚBLICOS DE LAS\nENTIDADES FISCALIZABLES, QUE TIENEN A SU CARGO\nLA CUSTODIA Y ADMINISTRACIÓN DE RECURSOS\nPÚBLICOS, EN TÉRMINOS DE LO PREVISTO EN LOS\nARTÍCULOS 107, 108 Y 109 FRACCIÓN I DE LA LEY\nNÚMERO 1028 DE FISCALIZACIÓN SUPERIOR Y\nRENDICIÓN DE CUENTAS DEL ESTADO DE GUERRERO\nEstado, con la finalidad de que en caso de hacer efectiva la fianzas, la entidad fiscalizable reciba el apoyo de este Órgano de Fiscalización Superior del H. Congreso del Estado, para la recuperación de su patrimonio.\n7).- Vigencia de la Fianza.- La fianza tendrá como vigencia mínima el periodo que abarque cada ejercicio fiscal (del 1 de enero al 31 de diciembre de cada año), excepto el presente ejercicio fiscal\n(2013), cuya vigencia tendrá como inicio la fecha en que surta sus efectos el presente acuerdo y hasta el\n31 de diciembre del año en que se publiquen.\n8).- Pago de la Prima de la Fianza.- Cada una de las entidades fiscalizables, deberá de contratar la póliza de fianza de fidelidad por el monto que corresponda y estarán obligados a cumplir con el pago de la prima puntualmente y por todo el periodo cubierto, con la finalidad de no poner en riesgo la efectividad de esta caución.\nSerá responsabilidad del titular o funcionario de más alto rango dentro de cada entidad fiscalizable cada servidor público efectuar los pagos de prima respectivos, para mantener vigentes las pólizas de fianzas.\n9).- Plazo para la presentación de la fianza.- Los servidores públicos de las entidades fiscalizables que elijan garantizar su manejo, mediante fianza expedida por institución afianzadora legalmente autorizada para ello, deberán presentar las copias certificadas de la póliza y del contrato de fianza respectivo, dentro de los dos primeros meses del ejercicio fiscal que corresponda.\nPor cuanto hace al ejercicio fiscal 2013, la fianza deberá ser presentada a la Auditoría General del Estado en los términos antes indicados, a más tardar dentro de los treinta días naturales después de que surta sus efectos el presente acuerdo. observancia general.\nSEGUNDO.- En alcance a lo establecido en los artículos 105 y 107 de la Constitución Política\n115 y 116 de la ley número 1028 de Fiscalización Superior y Rendición de Cuentas del Estado de\n78 y las fracciones I, V y XXXVII del artículo 90 de dicha ley, mediante el presente acuerdo se crea el\nFIANZAS DE LOS SERVIDORES PÚBLICOS DE LAS\nENTIDADES FISCALIZABLES, QUE TIENEN A SU CARGO\nLA CUSTODIA Y ADMINISTRACIÓN DE RECURSOS\nPÚBLICOS, EN TÉRMINOS DE LO PREVISTO EN LOS\nARTÍCULOS 107, 108 Y 109 FRACCIÓN I DE LA LEY\nNÚMERO 1028 DE FISCALIZACIÓN SUPERIOR Y\nRENDICIÓN DE CUENTAS DEL ESTADO DE GUERRERO\nFONDO PARA EL AFIANZAMIENTO DE LOS SERVIDORES PUBLICOS, cuyo patrimonio deberá integrarse y aplicarse en términos de lo establecido en los preceptos legales antes señalados.\nTERCERO.- Los criterios y montos que en el presente acuerdo se establecen, se emiten sin perjuicio de modificaciones que pudieran sufrir, según se considere necesario para la regulación de las garantías que los servidores públicos deban otorgar en términos de los preceptos constitucionales y legales que en los considerandos del presente acuerdo se invocan.\nCUARTO.- El presente acuerdo revoca cualquier otro acuerdo, lineamiento o criterio establecido para el otorgamiento de garantías de los servidores públicos del Estado o de los Municipios, que se hubiere emitido con anterioridad por la Auditoría General del Estado.\nPRIMERO.- El presente acuerdo comenzará a surtir sus efectos al día siguiente al de su publicación en el Periódico Oficial del Estado de Guerrero.\nSEGUNDO.- Todas aquellas fianzas contratadas por las entidades fiscalizables, que se hayan exhibido a la Auditoria General del Estado, con anterioridad a la entrada en vigor del presente acuerdo, se tendrán por cumplimentadas en los términos de ley, siempre y cuando dichas garantías se hayan otorgado de conformidad con los criterios y montos establecidos con anterioridad a los que en este acuerdo se establecen.\nASÍ LO ACORDÓ Y FIRMA EL CIUDADANO LICENCIADO CERTIFICADO ARTURO\nLATABÁN LÓPEZ, AUDITOR GENERAL DEL ESTADO DE GUERRERO, EN LA CIUDAD DE\nCHILPANCINGO DE LOS BRAVO, GUERRERO, A LOS VEINTIDOS DÍAS DEL MES DE AGOSTO DEL\nAÑO DOS MIL TRECE.\nPUBLÍQUESE Y CÚMPLASE.\nRúbrica.\nEL SUSCRITO LICENCIADO MARCO ANTONIO CRUZ MANJARREZ SALGADO, DIRECTOR\nDE ASUNTOS JURÍDICOS DE LA AUDITORÍA GENERAL DEL ESTADO DE GUERRERO, EN\nEJERCICIO DE LA FACULTAD QUE ME CONFIEREN LOS ARTÍCULOS 90 FRACCIÓN III Y 96\nFRACCIÓN III DE LA LEY NÚMERO 1028, DE FISCALIZACIÓN SUPERIOR Y RENDICIÓN DE\nCUENTAS DEL ESTADO DE GUERRERO, POR DELEGACIÓN EXPRESA DEL C. LICENCIADO\nFIANZAS DE LOS SERVIDORES PÚBLICOS DE LAS\nENTIDADES FISCALIZABLES, QUE TIENEN A SU CARGO\nLA CUSTODIA Y ADMINISTRACIÓN DE RECURSOS\nPÚBLICOS, EN TÉRMINOS DE LO PREVISTO EN LOS\nARTÍCULOS 107, 108 Y 109 FRACCIÓN I DE LA LEY\nNÚMERO 1028 DE FISCALIZACIÓN SUPERIOR Y\nRENDICIÓN DE CUENTAS DEL ESTADO DE GUERRERO\nCERTIFICADO ARTURO LATABÁN LÓPEZ, AUDITOR GENERAL DEL ESTADO DE GUERRERO,\nREALIZADA EN ACUERDO DE FECHA DIECIOCHO DE JUNIO DEL AÑO DOS MIL DOCE Y\nPUBLICADO EN EL PERIÓDICO OFICIAL DEL GOBIERNO DEL ESTADO DE GUERRERO EL DÍA\nVEINTE DE JULIO DEL MISMO AÑO.\nQUE LAS COPIAS FOTOSTÁTICAS CERTIFICADAS, FOLIADAS, RUBRICADAS Y\nENTRESELLADAS, COMPUESTAS DE NUEVE FOJAS ÚTILES, CONCUERDAN FIELMENTE CON\nLOS ORIGINALES QUE TUVE A LA VISTA, Y QUE OBRAN EN LOS ARCHIVOS DE ESTA AUDITORÍA\nGENERAL DEL ESTADO, RELATIVO AL ACUERDO DEL AUDITOR GENERAL DEL ESTADO DE\nGUERRERO, POR EL QUE SE ESTABLECEN LOS CRITERIOS Y MONTO PARA EL OTORGAMIENTO\nDE FIANZAS DE LOS SERVIDORES PÚBLICOS DE LAS ENTIDADES FISCALIZABLES, QUE TIENEN\nSU CARGO LA CUSTODIA Y ADMINISTRACIÓN DE RECURSOS PÚBLICOS, EN TÉRMINOS DE LO\nPREVISTO EN LOS ARTÍCULOS 107, 108 Y 109 FRACCIÓN I, DE LA LEY NÚMERO 1028 DE\nFISCALIZACIÓN SUPERIOR Y RENDICIÓN DE CUENTAS DEL ESTADO DE GUERRERO; LO QUE\nCERTIFICO PRÉVIO COTEJO, PARA LOS EFECTOS LEGALES A QUE HAYA LUGAR, EN LA CIUDAD\nDE CHILPANCINGO DE LOS BRAVO, GUERRERO, A LOS VEINTISEIS DÍAS DEL MES DE AGOSTO\nDEL AÑO DOS MIL TRECE.- CONSTE.\nRúbrica.",
  "ordenamiento": "ACUERDO",
  "jurisdiccion": "GUERRERO",
  "fuente_oficial": "DIARIO OFICIAL DE LA FEDERACION",
  "Fecha de Publicación": "24 de \nSeptiembre de 2013",
  "ULTIMA REFORMA PUBLICADA": null,
  "status": "VIGENTE",
  "es_escaneado": false,
  "tiene_tablas": false,
  "materia": [
    "auditoría"
  ]
}