{
  "titulo": "Acuerdo por el Que Se Aprueba E Instituye el Programa de Zona Metropolitana de Chilpancingo Yo Plan",
  "Contenido": "METROPOLITANO DE CHILPANCINGO, QUE INCLUYE\nA LOS MUNICIPIOS DE CHILPANCINGO DE LOS\nBRAVO Y EDUARDO NERI DE LA REGIÓN CENTRO\nDEL ESTADO DE GUERRERO\nTEXTO ORIGINAL.\nAcuerdo publicado en el Periódico Oficial del Gobierno del Estado No. 24 Alcance I, el Viernes 24 de Marzo de 2023.\nACUERDO POR EL QUE SE APRUEBA E INSTITUYE EL PROGRAMA DE ZONA\nMETROPOLITANA DE CHILPANCINGO Y/O PLAN DE DESARROLLO METROPOLITANO DE\nCHILPANCINGO, QUE INCLUYE A LOS MUNICIPIOS DE CHILPANCINGO DE LOS BRAVO Y\nEDUARDO NERI DE LA REGIÓN CENTRO DEL ESTADO DE GUERRERO.\nGuerrero.- Poder Ejecutivo.\nArq. Urb. Irene Jiménez Montiel, Secretaria de Desarrollo Urbano, Obras Públicas y\nOrdenamiento Territorial, esta es una dependencia integrante de la administración pública centralizada del gobierno del estado de Guerrero de conformidad con los artículos 1, 22, fracción V y 27 de la Ley Orgánica de la Administración Pública del estado de Guerrero Número 242 y con fundamento a la facultad que me confieren los artículos 4, 14, 27 fracción II, III, VII y IX de la Ley Orgánica de la Administración Pública del\nEstado de Guerrero, 9, fracción VII y 10, fracción VIII, IX, XII, XIV y XXX de la Ley Número 790 de\nAsentamientos Humanos, Ordenamiento Territorial y Desarrollo Urbano del Estado de Guerrero; así como el artículo 11, fracción II y XIV del Reglamento Interior de esta Secretaría, puede celebrar convenios para promover el desarrollo urbano y metropolitano en beneficio de la población, y\nPRIMERO. El Marco Jurídico Constitucional Urbano establece ordenar los asentamientos humanos y establecer adecuadas provisiones, usos, reservas y destinos de tierras, aguas y bosques, a efecto de ejecutar obras públicas y de planear y regular la fundación, conservación, mejoramiento y crecimiento de los centros de población; dando cumplimiento el municipio con el marco jurídico urbano, regulando los asentamientos humanos con el Programa de Zona Metropolitana y/o Plan de Desarrollo\nMetropolitano.\n(SEGOB, SEDATU, INEGI y CONAPO; 2018) es el documento oficial en México mediante el cual se delimitan las zonas metropolitanas. En particular se determina que con la clave 12.02 se encuentra delimitada la Zona Metropolitana de Chilpancingo, en los municipios de Chilpancingo de los Bravo y de\nEduardo Neri del estado de Guerrero.\nTERCERO. El Marco Jurídico Estatal en materia de Ordenamiento Territorial y Desarrollo Urbano confiere a la Secretaría de Desarrollo Urbano, Obras Públicas y Ordenamiento Territorial del gobierno del estado de Guerrero, la facultad de participar en la planeación y regulación de las zonas metropolitanas y conurbaciones, así como coordinar sus acciones con la federación, con otras entidades federativas y\nMETROPOLITANO DE CHILPANCINGO, QUE INCLUYE\nA LOS MUNICIPIOS DE CHILPANCINGO DE LOS\nBRAVO Y EDUARDO NERI DE LA REGIÓN CENTRO\nDEL ESTADO DE GUERRERO municipios, de manera intraestatal e interestatal, según corresponda, para el ordenamiento territorial de los asentamientos humanos y la planeación del desarrollo urbano, metropolitano y de conurbaciones. Entre estas acciones de planeación se encuentra el Programa de Zona Metropolitana de Chilpancingo y/o Plan de Desarrollo Metropolitano de Chilpancingo.\nCUARTO. La Ley Número 790 de Asentamientos Humanos, Ordenamiento Territorial y Desarrollo\nUrbano del Estado de Guerrero, en sus Artículos 28 y 29, establecen que el Sistema Estatal de Planeación\nTerritorial comprende la planeación, regulación y evaluación del ordenamiento territorial de los asentamientos humanos y del desarrollo urbano de los centros de población, como una política de carácter global, sectorial y regional que coadyuvará al logro de los objetivos del Plan Estatal de Desarrollo, de los programas y planes estatales y municipales de desarrollo urbano; así también que se llevarán a cabo sujetándose al Programa Estatal de Ordenamiento Territorial y Desarrollo Urbano.\nQUINTO. De acuerdo a las nuevas disposiciones en materia federal y estatal, es necesaria la implementación de los instrumentos de planeación urbana de carácter Metropolitano, que permita solucionar los problemas urbanos y de ordenamiento territorial que se incrementan cada día en esas zonas de influencia, por lo que con la finalidad de armonizar los instrumentos de planeación con las disposiciones jurídicas se realizaron las actividades para crear el primer instrumento de planeación de la Zona\nMetropolitana de Chilpancingo.\nSEXTO. La administración estatal se propuso planear y administrar el desarrollo urbano de la Zona\nMetropolitana de Chilpancingo, acorde a los nuevos lineamientos de la Nueva Agenda Urbana establecida en la Declaratoria sobre Ciudades y Asentamientos Humanos Sostenibles, resultado de la Conferencia de las Naciones Unidas Hábitat III sobre la Vivienda y el Desarrollo Urbano Sostenible.\nSÉPTIMO. En la formulación del Programa de Zona Metropolitana de Chilpancingo y/o Plan de\nDesarrollo Metropolitano de Chilpancingo, se alinea con la Agenda 2030 de los Objetivos de Desarrollo\nSostenible aplicables al ordenamiento territorial: 1) Erradicar la pobreza, 5) Igualdad de género, 9) Industria e infraestructura, 11) Ciudades y comunidades sostenibles; los Objetivos de Desarrollo Sostenible (ODS) fueron aprobados en septiembre de 2015 por la Asamblea General de las Naciones Unidas, estableciendo una visión transformadora hacia la sostenibilidad económica, social y ambiental, los 17 Objetivos de\nDesarrollo Sostenible (ODS) permitirán evaluar, analizar y formular los medios para alcanzar la nueva visión del desarrollo sostenible. conjunta los organismos de gobernanza metropolitana siguientes: la Comisión de Ordenamiento\nMetropolitano de Chilpancingo y el Consejo Consultivo de Desarrollo Metropolitano de Chilpancingo. Como resultado de estas sesiones se aprobaron por unanimidad los siguientes puntos: Acuerdo para dar inicio a los trabajos del Programa de Zona Metropolitana de Chilpancingo y/o Plan de Desarrollo Metropolitano de\nChilpancingo; y la creación de la Subcomisión Técnica de Ordenamiento Metropolitano de Chilpancingo, con la finalidad de apoyar técnicamente a los dos organismos de gobernanza metropolitanos. También se\nMETROPOLITANO DE CHILPANCINGO, QUE INCLUYE\nA LOS MUNICIPIOS DE CHILPANCINGO DE LOS\nBRAVO Y EDUARDO NERI DE LA REGIÓN CENTRO\nDEL ESTADO DE GUERRERO acordó que debido a la contingencia sanitaria del CoVid-19, se podrían llevar a cabo las reuniones de los organismos de gobernanza metropolitana de forma virtual, vía videoconferencia. Asimismo, se informó que la creación de la página web https://bitacorametropolitanachilpancingo.org/inicio/ con la finalidad de difundir al público en general todo el proceso de elaboración del Plan.\nNOVENO. Con fecha 9 de febrero de 2021, sesionó a través de videoconferencia la Subcomisión\nTécnica de Ordenamiento Metropolitano de Chilpancingo, en donde se acordó llevar a cabo un proceso de participación ciudadana, mediante una serie de foros talleres para escuchar a los expertos y a la ciudadanía en general, sobre las problemáticas y las soluciones para la Zona Metropolitana.\nDÉCIMO. Los foros talleres referidos en el considerando anterior se llevaron a cabo vía videoconferencia del 17 al 19 de febrero y del 7 al 10 de abril de 2021, para las etapas de diagnóstico y estrategia, respectivamente, mediante convocatoria a los miembros de la Subcomisión Técnica de\nOrdenamiento Metropolitano de Chilpancingo y al público en general.\nDÉCIMO PRIMERO. Que con fecha 08 de junio de 2021, sesionó a través de videoconferencia el\nConsejo Consultivo de Desarrollo Metropolitano de Chilpancingo, en donde se presentó el Proyecto del\nPrograma de Zona Metropolitana de Chilpancingo y/o Plan de Desarrollo Metropolitano de Chilpancingo. A partir de ello, los miembros del Consejo acordaron dar inicio al proceso de Consulta Pública que establece la Ley Número 790 de Asentamientos Humanos, Ordenamiento Territorial y Desarrollo Urbano del Estado de Guerrero., así como solicitar una opinión técnica del Proyecto a la Subcomisión Técnica de\nOrdenamiento Metropolitano.\nDÉCIMO SEGUNDO. Que con fecha 8 de junio de 2021, la persona titular de la Secretaria de\nDesarrollo Urbano, Obras Públicas y Ordenamiento Territorial del Gobierno del Estado de Guerrero, en su carácter de Presidente del Consejo Consultivo de Desarrollo Metropolitano de Chilpancingo, publicó en el periódico Vértice de Chilpancingo con fecha del miércoles 09 de junio del 2021; de circulación regional la convocatoria pública del Proyecto del Programa de Zona Metropolitana de Chilpancingo y/o Plan de\nDesarrollo Metropolitano de Chilpancingo, estableciendo que se llevaría a cabo del 9 de junio al 22 de julio de 2021, para recibir los planteamientos de la ciudadanía con respecto al Proyecto. hicieron algún planteamiento al Proyecto del Programa de Zona Metropolitana de Chilpancingo y/o Plan de\nDesarrollo Metropolitano de Chilpancingo.\nTécnica de Ordenamiento Metropolitano de Chilpancingo, en donde se aprobó por mayoría de votos la\nOpinión Técnica favorable del Proyecto del Programa de Zona Metropolitana de Chilpancingo y/o Plan de\nDesarrollo Metropolitano de Chilpancingo.\nMETROPOLITANO DE CHILPANCINGO, QUE INCLUYE\nA LOS MUNICIPIOS DE CHILPANCINGO DE LOS\nBRAVO Y EDUARDO NERI DE LA REGIÓN CENTRO\nDEL ESTADO DE GUERRERO\nOrdenamiento Metropolitano de Chilpancingo, en donde se informó sobre la Opinión Técnica favorable de la Subcomisión Técnica de Ordenamiento Metropolitano de Chilpancingo. A partir de ello, los miembros de la Comisión aprobaron por unanimidad de votos el Programa de Zona Metropolitana de Chilpancingo y/o\nPlan de Desarrollo Metropolitano de Chilpancingo.\nDÉCIMO SEXTO. Que a las 12:24 horas del día 09 de agosto de 2022, se reinstalo la Comisión de Ordenamiento Metropolitano de Chilpancingo, y donde los miembros de la Comisión aprobaron por unanimidad de votos el seguimiento de publicación e inscripción del Programa de Zona Metropolitana de\nChilpancingo y/o Plan de Desarrollo Metropolitano de Chilpancingo.\nDÉCIMO SÉPTIMO. Que el Programa de Zona Metropolitana de y/o Plan de Desarrollo\nMetropolitano de Chilpancingo, emerge del seguimiento del Plan Estatal de Desarrollo 2022 - 2027; del Eje\n2, Objetivo 2.3, Estrategia 2.3.2 y Línea de Acción 2.3.2.3.\nDÉCIMO OCTAVO. Que con fecha 27 de febrero del año dos mil veintitrés, la Mtra. Evelyn Cecia\nSalgado Pineda, Gobernadora Constitucional del Estado de Guerrero, firma el Acuerdo por el cual se emite la Declaratoria de Zona Metropolitana de Chilpancingo, que incluye a los municipios de Chilpancingo de los Bravo y Eduardo Neri del estado de Guerrero; con el propósito de promover la integración de las políticas y acciones estatales y municipales que incidan en la planeación conjunta y ordenada de la Zona\nMetropolitana de Chilpancingo.\nDÉCIMO NOVENO. Que con fecha 28 del mes de febrero del dos mil veintitrés, se firma el\nConvenio de Intención, que celebran por una parte el gobierno del estado de Guerrero; representado por la Arq. Urb. Irene Jiménez Montiel, Secretaria de Desarrollo Urbano, obras Publicas y Ordenamiento\nTerritorial y los H. Ayuntamientos de Chilpancingo de los Bravo y Eduardo Neri, esto con la finalidad de hacer constar la voluntad de las partes para unificar y coordinar esfuerzos y acciones en el ámbito de sus respectivas competencias.\nVIGÉSIMO. Por lo que, de conformidad con lo expuesto con anterioridad, he tenido a bien expedir el siguiente:\nDE CHILPANCINGO Y/O PLAN DE DESARROLLO METROPOLITANO DE CHILPANCINGO, QUE\nCENTRO DEL ESTADO DE GUERRERO.\nARTÍCULO 1°. Se aprueba el Programa de Zona Metropolitana de Chilpancingo y/o Plan de\nDesarrollo Metropolitano de Chilpancingo, en los municipios de Chilpancingo de los Bravo y de Eduardo\nNeri del estado de Guerrero, incluyendo sus documentos y Anexos descriptivos y gráficos, mediante los\nMETROPOLITANO DE CHILPANCINGO, QUE INCLUYE\nA LOS MUNICIPIOS DE CHILPANCINGO DE LOS\nBRAVO Y EDUARDO NERI DE LA REGIÓN CENTRO\nDEL ESTADO DE GUERRERO el desarrollo urbano de los centros de población, ubicados en el territorio de los municipios de la zona metropolitana, a través de acciones de conservación, mejoramiento y crecimiento de interés común de la zona en cuestión, de conformidad con el artículo 40 de la Ley Número 790 de Asentamientos Humanos, Ordenamiento Territorial y Desarrollo Urbano del Estado de Guerrero.\nARTÍCULO 2°. El Programa de Zona Metropolitana de Chilpancingo y/o Plan de Desarrollo\nMetropolitano de Chilpancingo, se integra por los siguientes contenidos:\nDocumento en extenso del Programa de Zona Metropolitana de Chilpancingo y/o Plan de\nDesarrollo Metropolitano de Chilpancingo. Que se integra por once capítulos en el orden siguiente; los siguientes once capítulos: 1. ANTECEDENTES; 2. DINÁMICAS METROPOLITANAS; 3. MODELO\nTERRITORIAL METROPOLITANO; 4. VISIÓN Y OBJETIVOS METROPOLITANOS; 5. ESTRATEGIA\nMETROPOLITANA; 6. NORMAS GENERALES DE ORDENACIÓN METROPOLITANA INTERNACIONAL,\nNACIONAL Y REGIONAL; 7. AGENDA METROPOLITANA; 8. EVALUACIÓN Y SEGUIMIENTO; 9.\nESTRATEGIAS DE DIFUSIÓN PARA LA POBLACIÓN; 10. BIBLIOGRAFÍA, y; 11. ANEXOS.\nANEXOS:\nAnexo 1: Anexo cartográfico; con los siguientes 20 mapas de diagnóstico: D-01 Pendientes topográficas; D-02 Hidrología Superficial; D-03 Uso de suelo y vegetación; D-04 Susceptibilidad de inundaciones; D-05 Susceptibilidad de deslizamiento de taludes; D-06 Concentración de actividades educativas; D-07 Concentración de actividades económicas; D-08 Uso específico del suelo urbano; D-09\nDensidad de población neta; D-10 Densidad urbana; D-11 Suelo vacante; D-12 Régimen de tenencia de la tierra; D-13 Viviendas deshabitadas; D-14 Viviendas que disponen de automóvil; D-15 Asentamientos informales; D-16 Estructura vial; D-17 Centralidades urbanas; D-18 Aptitud territorial para el desarrollo urbano: condiciones naturales; D-19 Aptitud territorial para el desarrollo urbano: condicionantes físicas; D20 Sistema Urbano Rural de Chilpancingo (SUR); Y los siguientes 8 mapas de estrategia: E- 01 Visión; E-\n02 Modelo de Ordenamiento Territorial - Dimensión Metropolitana; E-03 Modelo de Ordenamiento Territorial\n- Asentamientos Humanos; E-04 Zonificación Primaria - Asentamientos Humanos; E-05 Zonificación\nPrimaria - Dimensión Metropolitana; E-06 Zonificación Secundaria - Asentamientos Humanos; E-07\nCorredores Viales, y; E-08 Proyectos estratégicos de ordenamiento urbano y sectorial.\nAnexo 2: Los reglamentos de funcionamiento de los siguientes tres organismos de gobernanza metropolitana: Comisión de Ordenamiento Metropolitano de Chilpancingo; Consejo Consultivo de\nDesarrollo Metropolitano de Chilpancingo, y; Subcomisión Técnica de Ordenamiento Metropolitano de\nChilpancingo.\nChilpancingo y/o Plan de Desarrollo Metropolitano de Chilpancingo, de conformidad con los siguientes artículos.\nMETROPOLITANO DE CHILPANCINGO, QUE INCLUYE\nA LOS MUNICIPIOS DE CHILPANCINGO DE LOS\nBRAVO Y EDUARDO NERI DE LA REGIÓN CENTRO\nDEL ESTADO DE GUERRERO\nARTÍCULO 3°. El Programa de Zona Metropolitana de Chilpancingo y/o Plan de Desarrollo\nMetropolitano de Chilpancingo, define la Visión de la Zona Metropolitana de Chilpancingo, mediante tres enfoques de planeación: jerarquía metropolitana, dimensiones de intervención territorial y gobernanza metropolitana.\nARTÍCULO 4°. En el enfoque de jerarquía metropolitana, la Visión se define en dos momentos diferentes: Visión de la ciudad central: En un primer momento, el Plan de Desarrollo Metropolitano de\nChilpancingo y/o Programa de Zona Metropolitana de Chilpancingo, reconoce la Visión de la cabecera municipal de Chilpancingo de los Bravo.\nLa vocación de Chilpancingo como la capital política, administrativa y educativa del estado de\nGuerrero la hace receptora de ciudadanos que vienen a realizar actividades laborales; que se adaptan a la vida en las montañas y se desplazan hacia las actividades económicas que se desarrollan en la planicie aluvial mediante la consolidación de un eje de movilidad sustentable sobre el río Huacapa; que brinda accesibilidad y consolida la ocupación de su territorio de forma compacta, con la finalidad de dotar los servicios públicos de calidad; posiciona y recupera el espacio público para coadyuvar y facilitar la movilidad y para brindar una calidad de vida adecuada a todos sus habitantes en localidades urbanas y rurales seguras y limpias.\nVisión de la Zona Metropolitana: En un segundo momento, la Zona Metropolitana de Chilpancingo se visualiza desde tres dimensiones en diferentes escalas de intervención territorial para determinar una agenda metropolitana para la gestión y ejecución de proyectos, que no intervienen con los aspectos propios de la facultad de los municipios metropolitanos; en donde se toman acuerdos por los organismos de gobernanza para alcanzar una metrópoli ordenada y competitiva en el concierto regional del sur del país.\nARTÍCULO 5°. En el enfoque territorial, la Visión se define en tres dimensiones de intervención:\nMetropolitana: que considera el ordenamiento del territorio en los municipios metropolitanos de\nChilpancingo de los Bravo y Eduardo Neri, que focaliza su intervención mediante el ordenamiento territorial.\nRegional: que considera al Sistema Urbano Rural de Chilpancingo como base para la movilidad\nMetrópoli - Ciudad: entendida como la conurbación física y próxima con las localidades inmediatas a la ciudad central, en las localidades de Chilpancingo de los Bravo, Petaquillas, Zumpango del Río y Tixtla de Guerrero.\nARTÍCULO 6°. En el enfoque de gobernanza metropolitana, la Visión se institucionaliza mediante los siguientes tres organismos de gobernanza metropolitana con las funciones correspondientes:\nMETROPOLITANO DE CHILPANCINGO, QUE INCLUYE\nA LOS MUNICIPIOS DE CHILPANCINGO DE LOS\nBRAVO Y EDUARDO NERI DE LA REGIÓN CENTRO\nDEL ESTADO DE GUERRERO\n1. Comisión de Ordenamiento Metropolitano de Chilpancingo. Coordinar la formulación y aprobación de los programas metropolitanos, su gestión, evaluación y cumplimiento; asimismo, contribuirán al financiamiento e instrumentación del ordenamiento territorial, desarrollo urbano, metropolitano y de conurbación en condiciones de equidad y la recuperación de inversiones públicas y del incremento del valor de la propiedad inmobiliaria generado por la consolidación y crecimiento urbano.\n2. Consejo Consultivo de Desarrollo Metropolitano de Chilpancingo. Promover los procesos de participación ciudadana, consulta pública e interinstitucional en las diversas fases de la formulación, aprobación, ejecución y seguimiento de los programas.\n3. Subcomisión Técnica de Ordenamiento Metropolitano de Chilpancingo. Apoyar a la\nComisión de Ordenamiento Metropolitano de Chilpancingo en la elaboración de estudios, opiniones y propuestas técnicas en la formulación, monitoreo, evaluación y seguimiento de los programas metropolitanos; y apoyar al Consejo Consultivo de Desarrollo Metropolitano, en los procesos de participación ciudadana durante la formulación del Programa de Zona Metropolitana de Chilpancingo y/o\nPlan de Desarrollo Metropolitano de Chilpancingo y sucesivamente.\nLos primeros dos organismos se encuentran contenidos en la Ley Número 790 de Asentamientos\nHumanos, Ordenamiento Territorial y Desarrollo Urbano del Estado de Guerrero; mientras que el tercero obedece a la necesidad de incorporar con mayor profundidad la participación ciudadana y lograr así, trascender en el cambio de administraciones públicas de los tres niveles de gobierno.\nEn el enfoque del ordenamiento territorial, la Visión o imagen objetivo se particulariza en el territorio mediante el Modelo de Ordenamient o Territorial (MOT) con las Áreas de Actuación.\nARTÍCULO 7°. Como parte de la estrategia metropolitana, se instrumentan Áreas de Actuación mediante un Modelo de Ordenamiento Territorial (MOT).\nPara la conformación del Modelo de Ordenamiento Territorial (MOT) se constituyen las Áreas de\nActuación (AA); que son unidades mínimas territoriales con características homogéneas preponderantes, en donde se aplican tanto políticas como estrategias urbanas, de política territorial y sectorial, aunado con programas, proyectos y acciones estratégicas, orientados a un desarrollo que transite a la equidad, sustentabilidad y Competitividad de los asentamientos humanos de la Zona Metropolitana de Chilpancingo, Guerrero.\nLa delimitación de las Áreas de Actuación (AA) surge a partir de la conjunción y análisis integral de los diagnósticos físico, social, económico, territorial y urbano. Se identifican las problemáticas y características preponderantes del territorio de los asentamientos humanos y su entorno, según la información disponible y contenida en el diagnóstico; debido a que esta información se encuentra a diferentes escalas (manzanas, colonias, AGEBs, etc.), se estandariza y se lleva a colonia, con la finalidad\nMETROPOLITANO DE CHILPANCINGO, QUE INCLUYE\nA LOS MUNICIPIOS DE CHILPANCINGO DE LOS\nBRAVO Y EDUARDO NERI DE LA REGIÓN CENTRO\nDEL ESTADO DE GUERRERO municipios en zonas que reconoce y delimita la población en general.\nEstas Áreas de Actuación (AA) se alinean y parten de aquellas del Plan Municipal de Desarrollo\nUrbano de Chilpancingo de los Bravo, Guerrero 2021, publicado en el Periódico Oficial del Estado de\nGuerrero, mediante la Edición No. 78, Alcance I, de fecha 28 de septiembre del 2021, y el cual fue elaborado y enviado por el Ayuntamiento a la Secretaría de Desarrollo Urbano, Obras Publicas y Ordenamiento\nTerritorial, trabajos de planeación que deben ser considerados en la formulación del Programa de Zona\nMetropolitana de Chilpancingo y/o Plan de Desarrollo Metropolitano de Chilpancingo.\nEl Programa de Zona Metropolitana de Chilpancingo y/o Plan de Desarrollo Metropolitano de\nChilpancingo ya acoge las políticas de la Nueva Agenda Urbana (ONU Hábitat, 2016) y la Nueva Ley\nGeneral de Asentamientos Humanos, Ordenamiento Territorial y Desarrollo Urbano (2016).\nPara el caso de los asentamientos humanos de Eduardo Neri, que no cuentan con un Plan\nActualizado; el Programa de Zona Metropolitana de Chilpancingo y/o Plan de Desarrollo Metropolitano de\nChilpancingo propone a manera de recomendación utilizar la metodología que utilizó en la elaboración de este mismo documento.\nExisten un total de 16 tipos de Áreas de Actuación (AA) que se constituyen en el Área urbana y en el Área rural de la siguiente forma: En Área urbana, Área rural y Corredores viales:\nEn el Área Urbana: 1. Centralidades urbanas; 2. Áreas económicas de baja intensidad de uso del suelo; 3. Habitacionales; 4. Impulso a nuevas centralidades urbanas; 5. Áreas de integración metropolitana;\n6. Crecimiento urbano; 7. Corredores viales; 8. Espacio público y equipamiento urbano, y;\n9. Cauces urbanos.\nEn el Área Rural: 10. Vivienda rural; 11. Protección agropecuaria; 12. Protección de inundaciones, y; 13. Áreas de valor ambiental y paisajístico.\nEn el Área No Urbanizable: 14. Protección; 15. Conservación, y; 16. Aprovechamiento.\nCorredores Viales: Son las Áreas de Actuación que se conforman a partir de los ejes de las principales vías de comunicación en los asentamientos humanos, junto con las centralidades urbanas, conforman la estructura urbana. En ellos también tienden a concentrarse las actividades económicas y educativas y son la columna vertebral de la movilidad. Los corredores se conforman no solamente en la vialidad que los origina, sino en franjas de hasta 800 metros hacia ambos lados de su eje, ya que generan accesibilidad al peatón de forma directa. las políticas de movilidad sustentable, espacio público y de densificación.\nMETROPOLITANO DE CHILPANCINGO, QUE INCLUYE\nA LOS MUNICIPIOS DE CHILPANCINGO DE LOS\nBRAVO Y EDUARDO NERI DE LA REGIÓN CENTRO\nDEL ESTADO DE GUERRERO\nSe constituyen dos tipos de corredores viales: los de la red del sistema integral de transporte y la red de corredores urbanos de vehículos automotores.\nLas Áreas de Actuación (AA) no representan una normatividad de uso del suelo, sino una política de intervención de política pública en el territorio. La normatividad urbana y el resto de las estrategias deben permitir que se instrumenten las políticas urbanas y territoriales de las Áreas de Actuación. En todos los casos, las estrategias deben ser socializadas con la ciudadanía y los actores locales para su instrumentación en la operación del Plan y/o Programa.\nARTÍCULO 8°. El Programa de Zona Metropolitana de Chilpancingo y/o Plan de Desarrollo\nMetropolitano de Chilpancingo, contiene una serie de estrategias sectoriales que complementan las determinaciones de la estrategia de ordenamiento territorial del Modelo de Ordenamiento Territorial.\nLa mayoría de las estrategias sectoriales se encuentran institucionalizadas por un marco jurídico e institucional propios, diferentes al de los Asentamientos Humanos, Ordenamiento Territorial y Desarrollo\nUrbano. Por ello, las estrategias planteadas en este apartado del Plan son respetuosas de los instrumentos de planificación institucional correspondiente, y sugieren la necesidad de ser incorporadas en los mismos, debido a la necesidad de incorporar una visión del territorio de forma integral en la planificación de los asentamientos humanos.\nLas estrategias sectoriales espacio público, estrategia vial, movilidad sustentable, equipamiento urbano, abasto de agua tratada y saneamiento y gestión de riesgos naturales, medio ambiente, residuos sólidos urbanos, ciudad post COVID-19 y financiamiento, se desarrollan cada una de ellas en un apartado particular.\nARTÍCULO 9°. La zonificación de usos del suelo es una de las normas más importantes del\nPrograma y/o Plan, debido a que establece las reglas y condiciones de ocupación espacial del territorio de los asentamientos humanos del territorio metropolitano. La normatividad debe permitir que se puedan desarrollar cada una de las determinaciones de las Áreas de Actuación que, en conjunto, coadyuvarán para alcanzar la Visión de la Zona Metropolitana de Chilpancingo. general del suelo, en las distintas zonas del área objeto de ordenamiento y regulación. La estrategia de\nZonificación de Uso del Suelo se estructura con los siguientes componentes, que son el resultado de las estrategias territoriales anteriores y de las directrices que proporcionan las Áreas de Actuación: Área\nUrbana actual, Área Urbanizable, Área Rural y Área No Urbanizable. una responsabilidad municipal, las normas establecidas en la zonificación primaria y secundaria del\nPrograma de Zona Metropolitana de Chilpancingo y/o Plan de Desarrollo Metropolitano de Chilpancingo\nMETROPOLITANO DE CHILPANCINGO, QUE INCLUYE\nA LOS MUNICIPIOS DE CHILPANCINGO DE LOS\nBRAVO Y EDUARDO NERI DE LA REGIÓN CENTRO\nDEL ESTADO DE GUERRERO responden a una estrategia de inducción, en función de las problemáticas metropolitanas y locales que deben considerar los municipios de la Zona Metropolitana para sus responsabilidades correspondientes.\nLa zonificación secundaria de usos del suelo no forma parte de la normatividad del Plan, puesto que es una facultad de los municipios. Sin embargo, el Programa de Zona Metropolitana de Chilpancingo y/o Plan de Desarrollo Metropolitano de Chilpancingo retoma las consideraciones del Plan Municipal de\nDesarrollo Urbano de Chilpancingo de los Bravo y de forma similar, se homóloga hacia el territorio del municipio de Eduardo Neri, bajo la misma metodología; ello permitirá establecer actuaciones de forma conjunta, para la mejor operación urbana.\nLa normatividad debe permitir que se puedan desarrollar cada una de las determinaciones de las\nÁreas de Actuación, que, en conjunto, coadyuvarán para alcanzar la Visión de la Zona Metropolitana de\nChilpancingo.\nARTÍCULO 10°. Para el logro de los objetivos del Programa de Zona Metropolitana de\nChilpancingo y/o Plan de Desarrollo Metropolitano de Chilpancingo, se constituye una Agenda\nMetropolitana que permite organizar los temas reconocidos para el desarrollo metropolitano que se caracterizan por su naturaleza, escala, complejidad y tiempo. Se concibe también como un mecanismo de actualización periódica en función de prioridades y materias de interés para la zona metropolitana. La\nAgenda Metropolitana está a cargo de la Comisión de Ordenamiento Metropolitano de la Zona\nMetropolitana de Chilpancingo, con apoyo de los órganos colegiados como el Consejo Consultivo de\nDesarrollo Metropolitano y la Subcomisión Técnica de Ordenamiento Metropolitano de la Zona\nMetropolitana de Chilpancingo.\nEsta Agenda permite priorizar los proyectos, o cartera de proyectos, a través de una temporalidad para realizar en el corto, mediano y largo plazo. Para ello, se genera una ficha descriptiva que busca recopilar información de los proyectos, por ejemplo, características físicas, sociales y económicas.\nARTÍCULO 11°. La cartera de proyectos de la Agenda Metropolitana se agrupa en los siguientes sectores estratégicos: gobernanza metropolitana, reciclamiento urbano, espacio público, equipamiento urbano, movilidad sustentable, nuevas vialidades, abasto de agua y saneamiento, medio ambiente, y riesgos naturales.\nEs necesario que las administraciones públicas municipales, la estatal y la federal participen en la promoción y ejecución de los siguientes proyectos estratégicos, mismos que se deben ejecutar en función y/o Plan:\nProyectos de gobernanza metropolitana:\nGO-1 Estudio y decreto de delimitación de límites territoriales Chilpancingo y Eduardo Neri.\nMETROPOLITANO DE CHILPANCINGO, QUE INCLUYE\nA LOS MUNICIPIOS DE CHILPANCINGO DE LOS\nBRAVO Y EDUARDO NERI DE LA REGIÓN CENTRO\nDEL ESTADO DE GUERRERO\nGO-2 Creación del Instituto Municipal de Planeación de Chilpancingo (IMPLAN).\nGO-3 Elaboración del Plan Municipal de Desarrollo Urbano de Eduardo Neri.\nGO-4 Elaboración trianual de dictámenes de impacto metropolitano para la gestión de proyectos.\nProyectos de reciclamiento urbano:\nR-1 Reciclamiento Urbano Aeropuerto (a Área de Integración Regional) Costo en ficha AIR-1.\nR-2 Reciclamiento Urbano Zona Militar SEDENA (a Parque Urbano).\nR-3 Reciclamiento Urbano Relleno Sanitario (a Parque Urbano).\nR-4 Reciclamiento Urbano Central de Autobuses.\nR-5 Reciclamiento Urbano Zoológico (a Parque Urbano).\nR-6 Reciclamiento Urbano Rastro.\nR-7 Reciclamiento Urbano Feria y Plaza de Toros (a parque urbano).\nProyectos de Espacio Público:\nEP-1 Elaboración de Manual de Diseño y Construcción de los Componentes del Espacio Público.\nEP-2 Estrategia para la Desapropiación de Espacio Público.\nEP-3 Estrategia para la Desafectación de Espacio Público.\nProyectos de parques lineales:\nPL-1 Parque Lineal Corregidora (longitud 1.4 km).\nPL-2 Parque Lineal La Floresta-Nuevo Horizonte (longitud 1.2 km).\nPL-3 Parque Lineal Guerrerense (longitud 1.7 km).\nPL-4 Parque Lineal Jardines del Sur (longitud 1.1 km).\nPL-5 Parque Lineal Vivero El Sabino (Longitud 2.5 km).\nMETROPOLITANO DE CHILPANCINGO, QUE INCLUYE\nA LOS MUNICIPIOS DE CHILPANCINGO DE LOS\nBRAVO Y EDUARDO NERI DE LA REGIÓN CENTRO\nDEL ESTADO DE GUERRERO\nPL-6 Parque Lineal Pensadores (Longitud 1.1 km).\nProyectos de espacios abiertos:\nEA-1 Una plaza cívica de 16 mil m2 Chilpancingo.\nEA-2 Una plaza cívica de 16 mil m2 Zumpango.\nEA-3 Parque Omiltemi.\nProyectos de equipamiento urbano:\nEU-1 Una central de abastos de 9,903 m2 en Chilpancingo.\nEU-2 Una central de autobuses de 80 cajones de abordaje en Chilpancingo.\nEU-3 Una unidad deportiva de 41,520 m2 en Chilpancingo.\nEU-4 Un centro de readaptación social de 1000 espacios para internos en Chilpancingo.\nProyectos del sistema de transporte estructurado:\nSIT-1 BRT Aeropuerto - Galerías (longitud 8.7 km).\nSIT-2 BRT Galerías - Petaquillas (longitud 4.7 km).\nSIT-3 Cablebús Oriente-Poniente (longitud 4.6 km).\nSIT-4 Centro de Transferencia Modal CETRAM.\nAIR-1 Área de integración regional metropolitana Norte.\nAIR-2 Área de integración regional metropolitana Sur.\nAIR-3 Área de integración regional metropolitana Petaquillas.\nProyectos de circuitos de movilidad sustentable:\nCM-1 Circuito de Movilidad Sustentable Poniente (longitud 16.5 km).\nCM-2 Circuito de Movilidad Sustentable Oriente (longitud 15.8 km).\nMETROPOLITANO DE CHILPANCINGO, QUE INCLUYE\nA LOS MUNICIPIOS DE CHILPANCINGO DE LOS\nBRAVO Y EDUARDO NERI DE LA REGIÓN CENTRO\nDEL ESTADO DE GUERRERO\nProyectos de liberación de vialidades:\nLV-1 Liberación de vialidad - tránsito vehicular desde 13 de Marzo-Col, Villa del Roble (longitud\n2.5 km).\nLV-2 Liberación de vialidades - Peatonalización/ciclovía Tramo Autopista del Sol 95D-Federal 95\n(longitud 13.8 km).\nProyectos de puentes peatonales sustentables:\nPPS-1 Puente Peatonal Sustentable Aeropuerto.\nPPS-2 Puente Peatonal Sustentable Mercado Benito Juárez.\nPPS-3 Puente Peatonal Sustentable Panteón Central.\nPPS-4 Puente Peatonal Sustentable Prosperidad.\nPPS-5 Puente Peatonal Sustentable La Avispa.\nPPS-6 Puente Peatonal Sustentable Sam´s Club.\nPPS-7 Puente Peatonal Sustentable Galerías.\nProyectos de ampliación de distribuidores viales:\nDV-1 Ampliación de distribuidor vial Aeropuerto.\nDV-2 Ampliación de distribuidor vial Cuartel Militar.\nDV-3 Ampliación de distribuidor vial Museo La Avispa.\nProyectos de nuevas vialidades:\nVP-1 Vialidad primaria Las Torres (CFE) (longitud 2.5 km).\nProyectos de paradores turísticos:\nPT-1 Parador turístico de Ocotito.\nPT-2 Parador turístico de Huitziltepec.\nMETROPOLITANO DE CHILPANCINGO, QUE INCLUYE\nA LOS MUNICIPIOS DE CHILPANCINGO DE LOS\nBRAVO Y EDUARDO NERI DE LA REGIÓN CENTRO\nDEL ESTADO DE GUERRERO\nProyectos de abasto de agua potable y saneamiento:\nAPS-1 Elaboración del Plan Maestro de Infraestructura Hidráulica y Diagnóstico y Planeación\nIntegral DPI.\nAPS-2 Nueva fuente de abastecimiento de agua potable para Chilpancingo.\nAPS-3 Rehabilitación de sectores cubiertos para abatir pérdidas.\nAPS-4 Estructuración de red troncal en sectores mayores para regular presiones y abatir pérdidas.\nAPS-5 Construcción de red nueva para zona de crecimiento urbano.\nAPS-6 Ampliación de la infraestructura troncal de alcantarillado sanitario.\nAPS-7 Ampliación de la PTAR del sur.\nAPS-8 Construcción de tres nuevas PTAR en función de crecimiento urbano futuro.\nAPS-9 Rehabilitación de la red de agua potable en Zumpango del Río.\nAPS-10 Nueva fuente de agua potable para la zona de crecimiento urbano.\nProyectos de medio ambiente:\nMA-1 Elaboración de los POETs de Chilpancingo y Eduardo Neri.\nMA-2 Sitio de disposición final de residuos sólidos de Matlalapa.\nProyectos de mitigación de riesgos naturales:\nINU-1 Construcción del interceptor pluvial y colector oriente.\nINU-2 Construcción del interceptor pluvial y colectores poniente.\nINU-3 Rectificación aguas abajo en el río Huacapa.\nDE-1 Elaboración de planes de protección de laderas de Chilpancingo y Eduardo Neri.\nMETROPOLITANO DE CHILPANCINGO, QUE INCLUYE\nA LOS MUNICIPIOS DE CHILPANCINGO DE LOS\nBRAVO Y EDUARDO NERI DE LA REGIÓN CENTRO\nDEL ESTADO DE GUERRERO\nARTÍCULO 12°. Para la difusión del Programa de Zona Metropolitana de Chilpancingo y/o Plan de Desarrollo Metropolitano de Chilpancingo, se creó una página web, que es la principal estrategia para este fin.\nLa Bitácora Metropolitana de Chilpancingo es un mecanismo que permite dar seguimiento al desarrollo de la formulación del Programa de Zona Metropolitana de Chilpancingo y/o Plan de Desarrollo\nMetropolitano de Chilpancingo, así como para registrar e informar a la opinión pública del proceso de planeación en la etapa de formulación y sus etapas subsecuentes.\nLa Bitácora Metropolitana contiene la información generada en el proceso de elaboración del estudio, así como los resultados, y está disponible en la página de la Secretaría de Desarrollo Urbano, Obras Públicas y Ordenamiento Territorial del Estado de Guerrero. En la Bitácora Metropolitana se incluye la información pertinente que sustenta el proceso de planeación.\nEl dominio de la página web y las redes sociales del Programa de Zona Metropolitana de\nChilpancingo y/o Plan de Desarrollo Metropolitano de Chilpancingo es el siguiente: www.bitacorametropolitanachilpancingo.org y estará vigente y será administrado por la Secretaría de\nDesarrollo Urbano, Obras Públicas y Ordenamiento Territorial del Gobierno del Estado de Guerrero:\nEl uso de redes utilizadas para la difusión del proceso de planeación en la etapa de formulación del plan, así como para la interacción en los foros-talleres, corresponde a YouTube Live y Facebook Live y son los siguientes sitios web: https://www.facebook.com/PDMChilpancingo/; Canal: PDMCH 2021 https://www.youtube.com; Canal: PDMChilpancingo_Diagnóstico-2021\nARTÍCULO 13°. El Programa de Zona Metropolitana de Chilpancingo y/o Plan de Desarrollo\nMetropolitano de Chilpancingo, estará sujeto a un proceso constante de revisión, de conformidad con lo establecido en la Ley Estatal 790 de Asentamientos Humanos, Ordenamiento Territorial y Desarrollo\nUrbano del Estado de Guerrero.\nARTÍCULO 14°. La Secretaría de Desarrollo Urbano, Obras Púbicas y Ordenamiento Territorial\nPrograma y/o Plan, mediante la convocatoria de forma periódica a los organismos de gobernanza metropolitana, mismos que sesionarán de conformidad como los establecen los reglamentos de funcionamiento que forman parte integrante del Programa de Zona Metropolitana de Chilpancingo y/o Plan de Desarrollo Metropolitano de Chilpancingo.\nMETROPOLITANO DE CHILPANCINGO, QUE INCLUYE\nA LOS MUNICIPIOS DE CHILPANCINGO DE LOS\nBRAVO Y EDUARDO NERI DE LA REGIÓN CENTRO\nDEL ESTADO DE GUERRERO\nARTÍCULO PRIMERO: Este Acuerdo y una vez aprobado el Programa de Zona Metropolitana de\nChilpancingo y/o Plan de Desarrollo Metropolitano de Chilpancingo en la sesión de la Comisión de\nOrdenamiento Metropolitano de Chilpancingo, firmado y requisitado en todas sus partes deberá ser enviado de manera impresa y digitalizada por la Secretaría de Desarrollo Urbano, Obras Públicas y Ordenamiento\nTerritorial del Gobierno del Estado, a la Secretaría General de Gobierno para proceder a su publicación en el Periódico Oficial.\nARTÍCULO SEGUNDO: El presente Acuerdo entrará en vigor al día siguiente de su publicación en el Periódico Oficial del Gobierno del Estado; para posteriormente inscribirlo en el Registro Público de la\nPropiedad y del Comercio.\nARTÍCULO TERCERO: Se derogan todas las disposiciones jurídicas que se opongan al presente\nPrograma de Zona Metropolitana de Chilpancingo y/o Plan de Desarrollo Metropolitano de Chilpancingo.\nARTÍCULO CUARTO: Una vez entrado en vigor el presente acuerdo, remítase a los H.\nAyuntamientos de Chilpancingo de los Bravo y Eduardo Neri para que estos lo publiquen en su gaceta municipal y en caso de no contar con esta, lo hagan por medio de edictos que se fijen en lugares públicos y conocidos en las localidades, así como se publiquen en los diarios locales de mayor circulación.\nDado en el “Recinto de las Oficinas del Poder Ejecutivo del Gobierno del Estado” el inmueble ubicado en el número 62, en Boulevard René Juárez Cisneros de la Ciudad de los Servicios, en la Ciudad de Chilpancingo de los Bravo, Guerrero a los 28 días del mes de febrero de dos mil veintitrés.\nRúbrica.\nLa Secretaria de Desarrollo Urbano, Obras Públicas y Ordenamiento Territorial, y Presidenta de la Comisión de Ordenamiento (sic)etropolitano de Chilpancingo.\nArq. Urb. Irene Jiménez Montiel.\nRúbrica.\nEl Subsecretario de Desarrollo Urbano, y Ordenamiento Territorial, y Secretario Técnico de la Comisión de\nOrdenamiento Metropolitano de Chilpancingo.\nDr. Francisco Javier Romero Pérez.",
  "ordenamiento": "ACUERDO",
  "jurisdiccion": "GUERRERO",
  "fuente_oficial": "DIARIO OFICIAL DE LA FEDERACION",
  "Fecha de Publicación": "24 \nde Marzo de 2023",
  "ULTIMA REFORMA PUBLICADA": null,
  "status": "VIGENTE",
  "es_escaneado": false,
  "tiene_tablas": false,
  "materia": [
    "general"
  ]
}