{
  "titulo": "Acuerdo por el Que Se Actualizan las Tablas para la Determinación de la Cuota Fija Integrada para el",
  "Contenido": "IMPUESTO SOBRE LA RENTA, IMPUESTO AL VALOR\nAGREGADO E IMPUESTO EMPRESARIAL A TASA\nÚNICA DE LOS CONTRIBUYENTES DEL RÉGIMEN DE\nPEQUEÑOS CONTRIBUYENTES\"\nTEXTO ORIGINAL\nAcuerdo publicado en el Periódico Oficial del Gobierno del Estado No. 54 Alcance I, el Viernes\n05 de Julio de 2013.\nACUERDO POR EL QUE SE ACTUALIZAN LAS \"TABLAS PARA LA DETERMINACIÓN DE LA\nCUOTA FIJA INTEGRADA PARA EL PAGO BIMESTRAL DEL IMPUESTO SOBRE LA RENTA,\nIMPUESTO AL VALOR AGREGADO E IMPUESTO EMPRESARIAL A TASA ÚNICA DE LOS\nCONTRIBUYENTES DEL RÉGIMEN DE PEQUEÑOS CONTRIBUYENTES\".\nGuerrero.- Poder Ejecutivo.\nLIC. ÁNGEL HELADIO AGUIRRE RIVERO, GOBERNADOR CONSTITUCIONAL DEL\nSOBERANO DE GUERRERO Y EN EJERCICIO DE LAS FACULTADES QUE ME CONFIEREN LOS\nARTÍCULOS 2O Y 6O DE LA LEY ORGÁNICA DE LA ADMINISTRACIÓN PÚBLICA DEL ESTADO DE\nGUERRERO NÚMERO 433.\nQue la Secretaría de Finanzas y Administración es la Dependencia encargada de la administración de la Hacienda Pública del Estado y por lo tanto de recaudar los ingresos estatales, entre ellos, los impuestos, derechos, productos y aprovechamientos, cuidando el estricto cumplimiento de las leyes, reglamentos y demás disposiciones fiscales aplicables.\nQue el Gobierno del Estado signó el 28 de diciembre de 1996, el Convenio de Colaboración\nAdministrativa en Materia Fiscal Federal con el Gobierno Federal, por conducto de la Secretaría de\nHacienda y Crédito Público, en vigor a partir del 1o de enero de 1997. autoridades locales y del Distrito Federal, en la incorporación al Registro Federal de Contribuyentes de las personas que realizan actividades dentro de este tipo de economía, denominados \"Pequeños\nContribuyentes\", lo cual dio lugar a la firma del Convenio de Colaboración Administrativa en Materia\nFiscal Federal y sus anexos.\nQue mediante reformas a la Ley del Impuesto Sobre la Renta, vigente a partir del 1o de enero del\nIMPUESTO SOBRE LA RENTA, IMPUESTO AL VALOR\nAGREGADO E IMPUESTO EMPRESARIAL A TASA\nÚNICA DE LOS CONTRIBUYENTES DEL RÉGIMEN DE\nPEQUEÑOS CONTRIBUYENTES\"\nEntidades Federativas donde obtenga sus ingresos, siempre que dichas entidades celebren convenio de coordinación para administrar dicho impuesto.\nQue dentro del marco señalado en los párrafos anteriores el Estado de Guerrero y el Gobierno\nFederal por conducto de la Secretaría de Hacienda y Crédito Público, con fundamento en la legislación federal a que se refiere el Convenio de Colaboración Administrativa en Materia Fiscal Federal, así como el artículo 139 de la Ley del Impuesto Sobre la Renta suscribieron el Anexo número 3 al Convenio de\nColaboración Administrativa en Materia Fiscal Federal, el cual se publicó en el Diario Oficial de la\nFederación el 10 de septiembre de 2003.\nQue de igual manera el H. Congreso de la Unión mediante Decreto publicado en el Diario Oficial de la Federación del 31 de diciembre de 2003, con vigencia a partir del 1o de enero de 2004, aprobó diversas reformas a la Ley del Impuesto al Valor Agregado, entre las que se encuentra la relativa al artículo 2o-C, en el que se establece que las personas físicas que tributen conforme al régimen de pequeños contribuyentes (REPECO), de acuerdo a lo previsto en la Sección III del capítulo II del Título IV de la Ley del Impuesto Sobre la Renta, pagarán el Impuesto al Valor Agregado mediante estimativa del valor de las actividades que practiquen las autoridades fiscales, en lugar de hacerlo en los términos generales que la ley de la materia establece.\nQue con fecha 5 de abril del 2004, fue publicado en el Diario Oficial de la Federación el \"Decreto por el que se otorgan diversos beneficios fiscales a los contribuyentes que se mencionan\" a través del cual el Ejecutivo Federal en ejercicio de sus atribuciones, entre otras, la consistente en permitir a las\nEntidades Federativas que en una sola cuota puedan recaudar el Impuesto Sobre la Renta (ISR) y el\nImpuesto al Valor Agregado (IVA) de dichos contribuyentes; requerir la presentación de la declaración informativa de los ingresos obtenidos en el ejercicio 2003; así como resolver, revisar y ajustar los coeficientes de valor agregado a que se refiere el artículo 2°-C de la Ley del Impuesto al Valor Agregado.\nQue por lo expuesto, se hizo necesaria la celebración de un nuevo anexo 3 que substituya al anterior celebrado, por lo que la Secretaría y el Estado, con fundamento en las disposiciones señaladas en los párrafos anteriores, así como en el artículo 13 de la Ley de Coordinación Fiscal, suscribieron un nuevo anexo 3 al Convenio de Colaboración Administrativa en materia fiscal federal, el cual fue\nEstado de Guerrero del 16 de agosto y 16 de septiembre del 2005, respectivamente.\n\"Decreto por el que se otorgan diversos beneficios fiscales a los contribuyentes que se indican\", en el que se incluyen a los contribuyentes del REPECO, de las Entidades Federativas con las que la Secretaría de\nHacienda y Crédito Público celebró el convenio de coordinación para la administración del IVA y del ISR,\nIMPUESTO SOBRE LA RENTA, IMPUESTO AL VALOR\nAGREGADO E IMPUESTO EMPRESARIAL A TASA\nÚNICA DE LOS CONTRIBUYENTES DEL RÉGIMEN DE\nPEQUEÑOS CONTRIBUYENTES\" pública, mediante el cual se establece que las Entidades Federativas, para la administración del ISR y del\nIVA, podrán establecer anualmente a los contribuyentes que se inscriban o estén inscritos en el Registro\nFederal de Contribuyentes en el REPECO, con establecimientos, sucursales o agencias ubicados en sus circunscripción, una cuota fija integrada aplicable para todo el ejercicio y que, en su caso, incluya a los\nImpuestos Sobre la Renta y al Valor Agregado, cuyo pago se realizaría bimestralmente, dichas Entidades\nFederativas deberán proporcionar al Servicio de Administración Tributaria, la información sobre los pagos señalados con la periodicidad y cumpliendo con las condiciones técnicas que se establezcan en el anexo\n3 al Convenio de colaboración Administrativa en Materia Fiscal Federal.\nQue el Gobierno del Estado de Guerrero y el Gobierno Federal, por conducto de la Secretaría de\nHacienda y Crédito Público tienen celebrado Convenio de Colaboración Administrativa en Materia\nFederal, el cual entró en vigor el 29 de noviembre de 2006.\nQue el 1o de enero de 2008 entró en vigor la Ley del Impuesto Empresarial a Tasa Única, la cual establece que las Entidades Federativas que tengan celebrado con la Secretaría de Hacienda y Crédito\nPúblico Convenio de Coordinación para la administración del Impuesto Sobre la Renta a cargo de las personas físicas que tributen conforme al Régimen de Pequeños Contribuyentes a que se refiere la Ley del Impuesto Sobre la Renta, deberán en una sola cuota, recaudar los impuestos Sobre la Renta, Empresarial a Tasa Única y al Valor Agregado que, en su caso, causen dichos contribuyentes.\nQue en el marco de la simplificación legal y administrativa, se hace necesario revisar y actualizar las leyes y procedimientos vigentes, para mantenerlos acordes a los cambios que la dinámica social demanda.\nQue con el fin de facilitar a los contribuyentes el cumplimiento de sus obligaciones fiscales, la\nSecretaría de Finanzas y Administración se mantiene atenta y en estrecha comunicación con la población, captando sus inquietudes y sugerencias canalizándolas para llevar a cabo las reformas legales o administrativas que se consideren necesarias. necesario la adecuación de los valores de acuerdo a las áreas geográficas en que, para fines salariales se ha dividido la República Mexicana.\nQue en este contexto, la Secretaría de Finanzas y Administración, ha actualizado las \"Tablas para la determinación de la cuota fija integrada para el pago bimestral del ISR, IVA e IETU para el ejercicio 2013 de los contribuyentes del REPECO\" con el fin de que cumplan con sus obligaciones fiscales federales ante las autoridades fiscales estatales a través de pago referenciado.\nPor lo anteriormente expuesto, he tenido a bien expedir el siguiente:\nIMPUESTO SOBRE LA RENTA, IMPUESTO AL VALOR\nAGREGADO E IMPUESTO EMPRESARIAL A TASA\nÚNICA DE LOS CONTRIBUYENTES DEL RÉGIMEN DE\nCUOTA FIJA INTEGRADA PARA EL PAGO BIMESTRAL DEL IMPUESTO SOBRE LA RENTA,\nFISCAL 2013.\nARTÍCULO PRIMERO.- Se actualizan las tablas para la determinación de la cuota fija integrada para el pago del Impuesto Sobre la Renta, Impuesto al Valor Agregado e Impuesto Empresarial a Tasa\nÚnica de los contribuyentes del régimen de pequeños contribuyentes:\nIMPUESTO SOBRE LA RENTA, IMPUESTO AL VALOR\nAGREGADO E IMPUESTO EMPRESARIAL A TASA\nÚNICA DE LOS CONTRIBUYENTES DEL RÉGIMEN DE\nIMPUESTO SOBRE LA RENTA, IMPUESTO AL VALOR\nAGREGADO E IMPUESTO EMPRESARIAL A TASA\nÚNICA DE LOS CONTRIBUYENTES DEL RÉGIMEN DE\nPEQUEÑOS CONTRIBUYENTES\"\nARTICULO SEGUNDO.- Se derogan las tablas publicadas en el Periódico Oficial del Gobierno del Estado de Guerrero Número 45, el 3 de junio de 2008.\nÚNICO.- El presente acuerdo entrará en vigor a partir del día hábil siguiente de su publicación en el Periódico Oficial del Gobierno del Estado de Guerrero. los Bravo, Capital del Estado de Guerrero, a los tres días del mes de julio del año dos mil trece.\nEL GOBERNADOR CONSTITUCIONAL DEL ESTADO\nLIC. ÁNGEL HELADIO AGUIRRE RIVERO.\nEL SECRETARIO GENERAL DE GOBIERNO.\nM.C. FLORENTINO CRUZ RAMIREZ.\nIMPUESTO SOBRE LA RENTA, IMPUESTO AL VALOR\nAGREGADO E IMPUESTO EMPRESARIAL A TASA\nÚNICA DE LOS CONTRIBUYENTES DEL RÉGIMEN DE\nEL SECRETARIO DE FINANZAS Y ADMINISTRACIÓN.\nC. P. JORGE SILVERIO SALGADO LEYVA.",
  "ordenamiento": "ACUERDO",
  "jurisdiccion": "GUERRERO",
  "fuente_oficial": "DIARIO OFICIAL DE LA FEDERACION",
  "Fecha de Publicación": "29 de noviembre de 2006",
  "ULTIMA REFORMA PUBLICADA": null,
  "status": "VIGENTE",
  "es_escaneado": false,
  "tiene_tablas": false,
  "materia": [
    "general"
  ]
}