{
  "titulo": "Acuerdo por el Cual Se Crea la Comisión Consultiva Estatal de Seguridad y Salud en el Trabajo del Es",
  "Contenido": "LAS BASES DE SU ORGANIZACIÓN Y\nFUNCIONAMIENTO\nTEXTO ORIGINAL de 2018.\nACUERDO POR EL CUAL SE CREA LA COMISIÓN CONSULTIVA ESTATAL DE SEGURIDAD Y\nSALUD EN EL TRABAJO DEL ESTADO DE GUERRERO Y SE FIJAN LAS BASES DE SU\nORGANIZACIÓN Y FUNCIONAMIENTO.\nGuerrero.- Poder Ejecutivo.\nLICENCIADO HÉCTOR ANTONIO ASTUDILLO FLORES, GOBERNADOR CONSTITUCIONAL\nDEL ESTADO DE GUERRERO, EN EJERCICIO DE LAS FACULTADES QUE ME CONFIEREN LOS\nARTÍCULOS 71, 87, 88, 90 NUMERAL 2 Y 91 FRACCIÓN VI DE LA CONSTITUCIÓN POLÍTICA DEL\n18 APARTADO A FRACCIÓN XVIII, 20 FRACCIÓN III Y 37 DE LA LEY ORGÁNICA DE LA\nADMINISTRACIÓN PÚBLICA DEL ESTADO DE GUERRERO NÚMERO 08; 512-B Y 512-C DE LA LEY\nFEDERAL DEL TRABAJO Y 93, 94 Y 95 DEL REGLAMENTO FEDERAL DE SEGURIDAD Y SALUD EN\nEL TRABAJO, Y\nQue el 30 de noviembre de 2012, se publicó en el Diario Oficial de la Federación el Decreto por el que se reforman, adicionan y derogan diversas disposiciones de la Ley Federal del Trabajo, mediante el cual se modificó el artículo 512-B el cual dispone que en cada entidad federativa se constituirá una\nComisión Consultiva Estatal de Seguridad y Salud en el Trabajo, cuya finalidad será la de coadyuvar en la definición de la política estatal en materia de seguridad, salud y medio ambiente de trabajo, proponer reformas y adiciones al reglamento y a las normas oficiales mexicanas en la materia, así como estudiar y proponer medidas preventivas para abatir los riesgos en los centros de trabajo establecidos en su jurisdicción.\nQue el referido ordenamiento establece, que dichas Comisiones Consultivas Estatales serán presididas por los Ejecutivos Estatales y el Jefe de Gobierno del Distrito Federal (actualmente Ciudad de\nMéxico) y en su integración participarán representantes de las Secretarías del Trabajo y Previsión Social; de Salud; de Gobernación, y de Medio Ambiente y Recursos Naturales; del Instituto Mexicano del Seguro\nSocial; así como los que designen las organizaciones de trabajadores y de patrones a las que convoquen.\nQue en el artículo 512-C de la Ley Federal del Trabajo, establece que la organización de las\nSalud en el Trabajo, será señalada en el reglamento que se expida en materia de seguridad, salud y medio ambiente de trabajo.\nLAS BASES DE SU ORGANIZACIÓN Y\nFUNCIONAMIENTO\nQue el Reglamento Federal de Seguridad y Salud en el Trabajo, al que se refiere la Ley Federal establece en los artículos 93 al 95, su organización, integración y funcionamiento.\nQue de acuerdo con el Artículo Primero Transitorio del citado Reglamento, sus disposiciones están vigentes a partir del día 13 de febrero de 2015, por lo que a partir de esta fecha, los Presidentes están en posibilidad de realizar las acciones para instalar la citadas Comisiones Consultivas con el apoyo de los\nSecretarios Técnicos.\nQue la Secretaría del Trabajo y Previsión Social del Gobierno del Estado de Guerrero, es el órgano encargado de conducir las políticas, programas y acciones en materia de trabajo y de armonizar las relaciones entre las diferentes fuerzas productivas de la Entidad, así como generar y consolidar una nueva cultura laboral, que impulse la productividad y la competitividad, que mejore las condiciones de trabajo y dé impulso al fomento y promoción del empleo.\nQue en cumplimiento a lo anterior, el titular del Poder Ejecutivo Estatal, ha considerado procedente crear la Comisión Consultiva Estatal de Seguridad y Salud en el Trabajo de Estado de Guerrero, con el objeto de coadyuvar en la definición de la política estatal en materia de seguridad, salud y medio ambiente de trabajo, proponer reformas y adiciones al Reglamento Federal de Seguridad y Salud en el Trabajo y a las normas oficiales mexicanas en la materia, así como estudiar y proponer medidas preventivas para abatir los riesgos en los centros de trabajo establecidos en su jurisdicción.\nPor lo anteriormente expuesto y fundado, he tenido a bien expedir el siguiente:\nACUERDO POR EL CUAL SE CREA LA COMISIÓN CONSULTIVA ESTATAL DE SEGURIDAD Y\nSALUD EN EL TRABAJO DEL ESTADO DE GUERRERO Y SE FIJAN LAS BASES DE SU\nORGANIZACIÓN Y FUNCIONAMIENTO.\nCapítulo I\nDisposiciones Generales\nArtículo 1. Se crea la Comisión Consultiva Estatal de Seguridad y Salud en el Trabajo del Estado de Guerrero y se fijan las bases de su organización y funcionamiento.\nArtículo 2. La Comisión Consultiva Estatal de Seguridad y Salud en el Trabajo del Estado de\nGuerrero, tiene por objeto coadyuvar en la definición de la política estatal en materia de seguridad, salud y medio ambiente de trabajo, proponer reformas y adiciones al Reglamento Federal de Seguridad y Salud preventivas para abatir los riesgos en los centros de trabajo establecidos en la jurisdicción.\nLAS BASES DE SU ORGANIZACIÓN Y\nFUNCIONAMIENTO\nArtículo 3. Para los efectos del presente Acuerdo se entenderá por:\nI. Comisión: La Comisión Consultiva Estatal de Seguridad y Salud en el Trabajo del Estado de\nGuerrero;\nII. Grupos de trabajo: El conjunto de especialistas multidisciplinarios de carácter técnico que tendrán a su cargo la elaboración de estudios y anteproyectos de normas en materia de seguridad, salud y medio ambiente de trabajo;\nIII. Organizaciones: Las instituciones representativas de los trabajadores y del sector empresarial con carácter estatal; y\nIV. Subcomisiones: Aquellos grupos de representación tripartita designados por la Comisión, que tendrán a su cargo revisar los estudios y anteproyectos de los grupos de trabajo.\nCapítulo II\nIntegración y organización de la Comisión\nArtículo 4. De conformidad con lo dispuesto por el artículo 512-B de la Ley Federal del Trabajo, la Comisión se integrará por:\nI. El Gobernador Constitucional del Estado de Guerrero, quien lo presidirá;\nII. El Secretario del Trabajo y Previsión Social;\nIII. El Secretario de Salud;\nIV. El Secretario General de Gobierno;\nV. El Secretario de Medio Ambiente y Recursos Naturales;\nVI. El Delegado Federal del Trabajo en el Estado de Guerrero;\nVII. El Representante del Instituto Mexicano del Seguro Social;\nVIII. Tres representantes de las organizaciones de trabajadores, y\nIX. Tres de las organizaciones de patrones, a las que convoque el Presidente de la Comisión.\nLAS BASES DE SU ORGANIZACIÓN Y\nFUNCIONAMIENTO\nPor cada miembro propietario a que se refiere el artículo anterior se designará un suplente, quienes podrán concurrir a las reuniones de la Comisión con derecho a voz y voto.\nLa Comisión será presidida por el Gobernador Constitucional del Estado de Guerrero y, en ausencia del mismo, por el Secretario del Trabajo y Previsión Social.\nLa Comisión, contará con un Secretario Técnico que será el Delegado Federal del Trabajo en el\nEstado de Guerrero.\nArtículo 5. El Presidente de la Comisión podrá invitar a participar en sus sesiones, con voz y voto, si así lo aceptara la Comisión, a representantes de los sectores público, social o privado, instituciones académicas, colegios de profesionistas o expertos, cuando se traten temas de su competencia, especialidad o interés.\nCapítulo III\nFacultades de la Comisión y de sus integrantes\nArtículo 6. La Comisión, además de las facultades que le confiere el artículo 94 del Reglamento\nFederal de Seguridad y Salud en el Trabajo, tendrá las siguientes:\nI. Proponer estrategias, políticas y acciones en materia de seguridad, salud y medio ambiente de trabajo, a fin de que sean consideradas por las Secretarías, Dependencias y Entidades de la Administración\nPública Estatal, en el ámbito de sus respectivas competencias;\nII. Proponer mecanismos de coordinación entre las Secretarías, Dependencias y Entidades de la\nAdministración Pública Estatal, así como entre los sectores público, social y privado para el diseño, ejecución y evaluación en materia de Seguridad, Salud y Medio Ambiente de Trabajo;\nIII. Proponer la realización de eventos que tengan por objeto, cuidar la vida y salud de los trabajadores y mejorar el medio ambiente de trabajo;\nIV. Promover la difusión entre trabajadores y patrones de información estadística y medidas preventivas sobre riesgos de trabajo;\nV. Constituir subcomisiones y grupos de trabajo con el fin de elaborar estudios para abatir riesgos en los centros de trabajo, así como anteproyectos para la creación, modificación o extinción de las disposiciones reglamentarias en la materia que se encuentren en vigor;\nVI. Aprobar el Reglamento de la Comisión;\nLAS BASES DE SU ORGANIZACIÓN Y\nFUNCIONAMIENTO\nVII. Aprobar los Programas de actividades en materia de seguridad y salud en el trabajo;\nVIII. Proponer las medidas que se juzguen necesarias para el mejor desarrollo de sus funciones;\nIX. Las demás de carácter consultivo que les encomiende el Presidente de la Comisión.\nArtículo 7. El Presidente de la Comisión tendrá las facultades siguientes:\nI. Presidir y, en su caso, convocar las sesiones ordinarias y extraordinarias de la Comisión;\nII. Representar y dirigir los trabajos de la Comisión;\nIII. Decidir con voto de calidad los casos de empate;\nIV. Proponer la constitución de subcomisiones y grupos de trabajo para el estudio de asuntos específicos;\nV. Designar a los Coordinadores de las subcomisiones;\nVI. Otorgar reconocimientos de participación a los integrantes de la Comisión, de las subcomisiones y grupos de trabajo;\nVII. Observar y vigilar el cumplimiento del Reglamento Interior; y\nVIII. Las demás necesarias para el cumplimiento de las funciones de la Comisión.\nArtículo 8. El Secretario Técnico tendrá las facultades siguientes:\nI. Comunicar las convocatorias para las sesiones de la Comisión;\nII. Realizar el recuento de la asistencia para verificar el quórum en las sesiones de la Comisión;\nIII. Levantar las actas de las sesiones que celebre la Comisión;\nIV. Enviar el acta para su revisión a los integrantes de la Comisión, dentro de los quince días naturales siguientes a la sesión;\nV. Proporcionar a los representantes propietarios y suplentes de la Comisión los informes que éstos soliciten sobre los asuntos relativos a la misma;\nLAS BASES DE SU ORGANIZACIÓN Y\nFUNCIONAMIENTO\nVI. Dar seguimiento a los acuerdos adoptados por la Comisión, las subcomisiones y grupos de trabajo;\nVII. Supervisar las labores que desarrollan las subcomisiones y grupos de trabajo;\nVIII. Informar al Presidente acerca del funcionamiento de las subcomisiones y grupos de trabajo;\nIX. Desarrollar el proyecto de diagnóstico de riesgos del Estado para que sirva de base en la formulación de actividades de la Comisión;\nX. Elaborar el proyecto de programa anual de actividades, ponerlo a consideración del Presidente de la Comisión para que sea presentado y aprobado por los demás integrantes, así como darle seguimiento;\nXI. Poner a disposición del público en general, en el portal electrónico \"Comisiones Consultivas de\nSeguridad y Salud en el Trabajo\", la información sobre los integrantes de las Comisión; su Reglamento\nInterior; el programa anual de actividades y sus avances; los diagnósticos, estudios y propuestas efectuados en materia de seguridad y salud en el trabajo; las sesiones ordinarias y extraordinarias que celebren; los asuntos que se aborden en las mismas, con su consiguiente respaldo documental, entre otros aspectos; y\nXII. Las demás que le encomiende la Comisión, el Presidente, el Reglamento Interior de la\nComisión y otras disposiciones.\nArtículo 9. Los integrantes de la Comisión tendrán las facultades siguientes:\nI. Asistir a las sesiones de la Comisión;\nII. Participar en el análisis, discusión y votación de los asuntos que sean competencia de la\nComisión;\nIII. Solicitar la inclusión de asuntos específicos en los órdenes del día de sesiones posteriores de la Comisión;\nIV. Solicitar se convoque a la Comisión para la celebración de sesiones extraordinarias, en los términos del Reglamento Interior de la Comisión;\nV. Presentar en forma oportuna los comentarios y observaciones a los documentos que se sometan a su consideración;\nLAS BASES DE SU ORGANIZACIÓN Y\nFUNCIONAMIENTO\nVI. Informar oportunamente a las dependencias u organizaciones que representen para el mejor funcionamiento de la Comisión;\nVII. Dar cumplimiento a los acuerdos de la Comisión; y\nVIII. Las demás que les encomiende la Comisión, el Reglamento Interior y otras disposiciones legales aplicables.\nCapítulo IV\nSesiones de la Comisión\nArtículo 10. La Comisión celebrará sesiones ordinarias cada cuatro meses y las extraordinarias las veces que sean necesarias. Las sesiones ordinarias se convocarán con al menos cinco días de anticipación y las extraordinarias con al menos dos días.\nArtículo 11. Las convocatorias para las reuniones de la Comisión deberán contener el orden del día; la minuta de la sesión anterior, y los documentos soporte de los asuntos que se someterán a consideración de la Comisión.\nArtículo 12. Las sesiones de la Comisión serán válidas cuando se encuentren representados la mitad más uno de sus integrantes y exista representación de los tres sectores.\nEn caso de que no pudiera celebrarse la sesión por falta de quórum en el día y hora señalados en la convocatoria, se considerará desierta y se realizará una segunda convocatoria para una sesión que podrá celebrarse con la presencia de al menos un representante de la Administración Pública Estatal y sendos representantes de las organizaciones estatales de trabajadores y de patrones. siguientes a que haya sido declarada desierta la primera.\nLos acuerdos que se adopten en ella serán obligatorios para todos los integrantes de la Comisión.\nArtículo 13. Las resoluciones y acuerdos que adopte la Comisión deberán tomarse por mayoría de votos de sus integrantes que asistan a la sesión. En caso de empate el Presidente tendrá voto de calidad.\nArtículo 14. Los integrantes de la Comisión que tengan observaciones derivadas de la revisión de los documentos que son puestos a su consideración, deberán presentarlas por escrito al Secretario Técnico con la debida justificación.\nLAS BASES DE SU ORGANIZACIÓN Y\nFUNCIONAMIENTO\nArtículo 15. La Comisión podrá modificar los documentos que presenten para su aprobación de la Comisión Consultiva Nacional.\nArtículo 16. De cada sesión de la Comisión se levantará un acta circunstanciada que deberá contener: fecha y hora de la sesión, asistentes a la misma, orden del día y los acuerdos que se adopten.\nEl acta se enviará para su revisión a los integrantes de la Comisión, dentro de los quince días naturales siguientes a la sesión. Una vez aprobada el acta deberá ser firmada por el Presidente y el Secretario\nTécnico.\nArtículo 17. La organización y funcionamiento de la Comisión y lo no previsto en el presente acuerdo, se establecerá en el Reglamento Interior de la Comisión que al efecto se expida.\nPrimero. El presente Acuerdo entrará en vigor el día siguiente de su publicación en el Periódico\nOficial, órgano de difusión del Gobierno del Estado de Guerrero.\nSegundo. La Comisión deberá celebrar sesión de instalación el día de la suscripción del presente\nAcuerdo o dentro de los treinta días naturales siguientes a la fecha de la firma del presente.\nTercero. En un plazo no mayor a noventa días naturales contados a partir de la integración de la\nComisión, se deberá expedir el Reglamento Interior de la misma.\nCuarto. Se derogan todas las disposiciones que se opongan al presente Acuerdo.\nDado en el Palacio de Gobierno, ubicado en Boulevard René Juárez, Cisneros número 62, Colonia\nCiudad de los Servicios, en la Ciudad de Chilpancingo de los Bravos, Capital del Estado de Guerrero, a los\n04 días del mes de marzo del año dos mil dieciséis.\nEl Gobernador Constitucional del Estado de Guerrero.\nLic. Héctor Antonio Astudillo Flores.\nEl Secretario General de Gobierno.\nLic. Florencio Salazar Adame.\nEl Secretario del Trabajo y Previsión Social.\nLic. Oscar Ignacio Rangel Miravete.",
  "ordenamiento": "ACUERDO",
  "jurisdiccion": "GUERRERO",
  "fuente_oficial": "DIARIO OFICIAL DE LA FEDERACION",
  "Fecha de Publicación": "13 de febrero de 2015",
  "ULTIMA REFORMA PUBLICADA": null,
  "status": "VIGENTE",
  "es_escaneado": false,
  "tiene_tablas": false,
  "materia": [
    "laboral",
    "salud"
  ]
}