{
  "titulo": "Acuerdo 005SE27 02 2014, Mediante el Cual Se Aprueba la Ampliación del Plazo para Emitir el Dictamen",
  "Contenido": "OBTENIDOS EN LA ETAPA DE MEDIDAS\nPREPARATORIAS QUE MANDATA LA RESOLUCIÓN\nSUP JDC-1740/2012, EMITIDA POR LA SALA\nSUPERIOR DEL TRIBUNAL ELECTORAL DEL PODER\nJUDICIAL DE LA FEDERACIÓN\nABROGADO POR CONLUIDA SU VIGENCIA EL 25 DE MARZO DE 2014.\nTEXTO ORIGINAL\nAcuerdo publicado en el Periódico Oficial del Gobierno del Estado No. 21, el\nViernes 14 de Marzo de 2014.\nINSTITUTO ELECTORAL DEL ESTADO DE GUERRERO\nAL MARGEN UN SELLO CON EL ESTADO DE GUERRERO Y UNA LEYENDA QUE DICE:\n\"INSTITUTO ELECTORAL\":\nINSTITUTO ELECTORAL DEL ESTADO\nACUERDO 005/SE/27-02-2014\nMEDIANTE EL CUAL SE APRUEBA LA AMPLIACIÓN DEL PLAZO PARA EMITIR EL DICTAMEN DE\nLOS RESULTADOS OBTENIDOS EN LA ETAPA DE MEDIDAS PREPARATORIAS QUE MANDATA\nLA RESOLUCIÓN SUP-JDC-1740/2012, EMITIDA POR LA SALA SUPERIOR DEL TRIBUNAL\nELECTORAL DEL PODER JUDICIAL DE LA FEDERACIÓN.\n1. Con fecha trece de marzo de dos mil trece, la Sala Superior del Tribunal Electoral del Poder\nJudicial de la Federación, resolvió el Juicio para la Protección de los Derechos Político Electorales del\nCiudadano, identificado con la clave SUP-JDC-1740/2012, promovido por BRUNO PLACIDO VALERIO, por su propio derecho, en contra de la respuesta emitida el treinta y uno de mayo del dos mil doce, por el\nConsejo General del Instituto Electoral del Estado de Guerrero, dentro del expediente IEEG/CG/01/2012, respecto a su petición para elegir autoridades en diversos municipios del Estado de Guerrero, mediante el modelo de usos y costumbres.\n2. El aludido órgano Jurisdiccional Electoral Federal en los puntos resolutivos de la mencionada ejecutoria literalmente ordena:\nPRIMERO.- Se sobresee en el juicio para la protección de los derechos político-electorales del ciudadano promovido por Bruno Plácido Valerio, por lo que hace a la petición relacionada con los municipios de Acatepec, Alcozauca de Guerrero, Ayutla de los Libres, Azoyú, Chilapa de\nÁlvarez, Cuautepec, Iliatenco, José Joaquín de Herrera, Malinaltepec, Marquelia, Quechultenango,\nOBTENIDOS EN LA ETAPA DE MEDIDAS\nPREPARATORIAS QUE MANDATA LA RESOLUCIÓN\nSUP JDC-1740/2012, EMITIDA POR LA SALA\nSUPERIOR DEL TRIBUNAL ELECTORAL DEL PODER\nJUDICIAL DE LA FEDERACIÓN\nTlacoapa, Tecoanapa, Tlacoachistlahuaca, San Marcos, Xochistlahuaca y Zapotitlán Tablas, todos ellos del Estado de Guerrero.\nSEGUNDO.- Se revoca la respuesta 0894/2012, derivada del expediente IEEG/CG/01/2012, de treinta y uno de mayo del dos mil doce emitida por el Consejo General del Instituto Electoral del Estado de Guerrero, únicamente por lo que hace al municipio de San Luis Acatlán, Guerrero.\nTERCERO.- Se determina que los integrantes de la comunidad indígena del municipio de\nSan Luis Acatlán, Guerrero, tienen derecho a solicitar la elección de sus propias autoridades, siguiendo para ello sus normas, procedimientos y prácticas tradicionales, con pleno respeto a los derechos humanos.\nCUARTO.- Se ordena al Consejo General del Instituto Estatal Electoral del Estado de\nGuerrero y al Congreso del Estado de Guerrero realizar todas las acciones ordenadas en el considerando Octavo de la presente resolución.\n3. Con el propósito de dar cumplimiento a lo mandatado por la Sala Superior del Tribunal\nElectoral del Poder Judicial de la Federación, en el cuarto punto resolutivo de la sentencia emitida el trece de marzo del año en curso, en el sentido de realizar todas las acciones ordenadas en el considerando octavo de la sentencia antes señalada, la Comisión Especial de Participación Ciudadana, Usos y\nCostumbres, realizó diversas reuniones de trabajo, en las que se consideró la elaboración de lineamientos para dar cumplimiento a las medidas preparatórias de la resolución SUP-JDC-1740/2012, mismos que fueron aprobados mediante acuerdo 015/SO/24-04-2013.\n4. Mediante acuerdo 019/SO/28-05-2013 se facultó al Consejero Presidente del Instituto\nElectoral del Estado de Guerrero para que formulara solicitudes de apoyo y colaboración con\nInstituciones que estén en posibilidades de ejecutar lo dispuesto en el artículo 8 de los lineamientos para dar cumplimiento a las medidas preparatorias de la resolución SUP-JDC-1740/2012.\n5. Con fecha veintiuno de junio del presente año, el Instituto suscribió convenio de apoyo y colaboración con el Centro de Investigaciones y Estudios Superiores en Antropología Social (CIESAS), Luis Acatlán, en especial de los usos y costumbres en la elección de sus autoridades; incluyendo las comunidades indígenas y los barrios de la cabecera municipal.\n6. Con fecha veintiséis de junio de dos mil trece, la Dra. María Teresa Sierra Camacho, Investigadora del CIESAS, se trasladó al Municipio de San Luis Acatlán, Guerrero, para dar inicio con los trabajos de campo en la elaboración del dictamen, recorriendo diversas comunidades que integran dicho\nOBTENIDOS EN LA ETAPA DE MEDIDAS\nPREPARATORIAS QUE MANDATA LA RESOLUCIÓN\nSUP JDC-1740/2012, EMITIDA POR LA SALA\nSUPERIOR DEL TRIBUNAL ELECTORAL DEL PODER\nJUDICIAL DE LA FEDERACIÓN\nMunicipio, así como los cuatro barrios y dieciocho colonias que integran la cabecera municipal. El trabajo de campo culminó el día siete de julio de dos mil trece.\n7. Con fecha veinte de agosto de 2013, se recibió en este Organismo Electoral, en vía de notificación el oficio número DG/233/13 de fecha dieciséis de agosto de dos mil trece, que suscribe la\nDra. Virginia Acosta Camacho; Directora General del CIESAS, el Informe del Dictamen Antropológico denominado \"Dictamen Pericial Antropológico y los Sistemas Normativos Indígenas en el Municipio de\nSan Luis Acatlán, Guerrero\". Mismo que fue turnado con sus anexos a la Comisión Especial de\nParticipación Ciudadana, Usos y Costumbres para su trámite y efectos legales correspondientes.\n8. En virtud de lo previsto en el artículo 10 de los lineamientos para dar cumplimiento a las medidas preparatorias, se solicitó el apoyo y colaboración de una consultora experta en integración y entrevista a grupos focales, mismos que quedaron integrados en cuatro grupos de la manera siguiente:\nGrupo A- Autoridades Civiles.- Conformado por representantes del cabildo municipal y expresidentes municipales.\nGrupo B Autoridades Agrarias.- Conformado por comisariados ejidales y comisariados de bienes comunales.\nGrupo C Autoridades Civiles/Figuras tradicionales.- Conformado por comisarios municipales y principales.\nGrupo D Sociedad Civil.- Conformado por cronistas, organizaciones y ciudadanos destacados.\nLas sesiones de entrevistas a grupos focales, se efectuaron en la Cabecera Municipal, los días\n28, 29 de septiembre y 01 de octubre del dos mil trece y se entregaron los resultados de dichas entrevistas a la Comisión Especial de Participación Ciudadana, Usos y Costumbres, en reunión de trabajo efectuada el día 29 de octubre del 2013 para su análisis e integración correspondiente.\n9. En cuanto a la recopilación de información relativa a los usos y costumbres del Municipio de\nSan Luis Acatlán Guerrero, que prevé el artículo 11 de los Lineamientos, el Instituto giró solicitudes de informes a diversas dependencias como son: H. Ayuntamiento de San Luis Acatlán; Coordinación\nGeneral de Fortalecimiento Municipal; Centro del Instituto Nacional de Antropología e Historia, Guerrero;\nComisión Nacional para el Desarrollo de los Pueblos Indígenas, Delegación Guerrero y la Secretaria de\nAsuntos Indígenas del Estado de Guerrero.\n10. En seguimiento a las solicitudes antes mencionadas, se recibió un informe del H.\nAyuntamiento de San Luis Acatlán; materiales accesorios de información por parte de la Coordinación\nGeneral de Fortalecimiento Municipal; un oficio donde se designó a un antropólogo por parte del Instituto\nNacional de Antropología e Historia para rendir tal informe; un oficio de la Comisión Nacional para el\nDesarrollo de los Pueblos Indígenas Delegación Guerrero, donde el Delegado Estatal solicita la\nOBTENIDOS EN LA ETAPA DE MEDIDAS\nPREPARATORIAS QUE MANDATA LA RESOLUCIÓN\nSUP JDC-1740/2012, EMITIDA POR LA SALA\nSUPERIOR DEL TRIBUNAL ELECTORAL DEL PODER\nJUDICIAL DE LA FEDERACIÓN intervención del Director General de Asuntos Jurídicos de dicha Institución, para emitir el informe y por parte de la Secretaría de Asuntos indígenas, recibimos el informe respectivo.\n11. Con el objeto de informar y establecer una constante retroalimentación con la comunidad interesada, la Comisión Especial de Participación Ciudadana, Usos y Costumbres puso en marcha una estrategia operativa de información y retroalimentación que tuvo una duración de treinta días, culminando el día 22 de noviembre del 2013.\n12. En seguimiento a lo dispuesto en el artículo 8 de los lineamientos para dar cumplimiento a las medidas preparatórias de la resolución SUP-JDC-1740/2012, en un marco de colaboración interinstitucional, a través de oficio 0993 fechado el 11 de noviembre del año 2013, el Presidente del\nConsejo General del Instituto solicitó a la Titular de la Comisión Nacional para el Desarrollo de los\nPueblos Indígenas (CDI) la emisión de un dictamen pericial en materia de antropología para el caso que nos ocupa.\n13. En fecha 25 de noviembre del año 2013, mediante oficio número DGAJ/2013/OF/1531, por instrucciones de la Titular del referido organismo, el Lic. Francisco Javier Cedillo Tecayéhuatl; Director de\nAsuntos Jurídicos de la CDI, designó al Licenciado Emeterio Cruz García, para que realizara el peritaje en materia de antropología, quien se presentó a desahogar las diligencias de campo. los días 28, 29 y 30 del mes de enero del año en curso.\n14. En fecha 20 de febrero del presente año, mediante oficio DGAJ/2014/OF/243 que suscribe el\nLicenciado Francisco Javier Cedillo Tecayéhuatl, fue recibido en este órgano Electoral, el dictamen en materia de antropología social presentado por el Licenciado Emeterio Cruz García.\nI. Que de conformidad con lo dispuesto por el articulo 25 párrafo segundo de la Constitución función estatal, que se realiza a través de un organismo público autónomo, de carácter permanente, denominado Instituto Electoral del Estado de Guerrero, dotado de personalidad jurídica y patrimonio propio, en cuya integración concurren los partidos políticos, coaliciones y ciudadanos, en los términos que ordene la Ley. En el ejercicio de esa función estatal, la certeza, la legalidad, independencia, imparcialidad y objetividad serán principios rectores.\nII. De acuerdo a lo dispuesto por el artículo 85 fracciones I, III, IV, VIII y IX de la Ley de\nInstituciones y Procedimientos Electorales del Estado de Guerrero Número 571, el Instituto Electoral del\nEstado, tiene entre otros fines, el de garantizar la celebración periódica y pacifica de las elecciones para renovar a los integrantes de los Poderes Legislativo, Ejecutivo del Estado y Ayuntamientos; llevar a cabo\nOBTENIDOS EN LA ETAPA DE MEDIDAS\nPREPARATORIAS QUE MANDATA LA RESOLUCIÓN\nSUP JDC-1740/2012, EMITIDA POR LA SALA\nSUPERIOR DEL TRIBUNAL ELECTORAL DEL PODER\nJUDICIAL DE LA FEDERACIÓN la promoción del voto y coadyuvar a la difusión de la cultura democrática, rigiéndose por los principios señalados en el considerando primero.\nIII. A su vez el artículo 86 señala entre otras cosas que el Instituto Electoral es un Organismo\nPúblico autónomo de carácter permanente, independiente en sus decisiones y funcionamiento, con personalidad jurídica y patrimonio propio responsable de vigilar el cumplimiento de las disposiciones constitucionales y reglamentarias en materia electoral; así como de velar por que los principios de certeza, legalidad, independencia, imparcialidad y objetividad, guíen las actividades de los organismos electorales; encargados de coordinar, preparar, desarrollar y vigilar los procesos electorales estatales y municipales, ordinarios y extraordinarios, en los términos de la legislación aplicable.\nIV. Asimismo, el artículo 87 de la mencionada Ley Electoral dispone entre otras cosas, que el\nInstituto Electoral administrará su patrimonio ajustándose a los principios de honestidad, disciplina, racionalidad, transparencia, y austeridad.\nV. El Artículo 90 de la Ley Electoral establece que el Consejo General del Instituto Electoral, es el Órgano Superior de Dirección, responsable de vigilar el cumplimiento de las disposiciones constitucionales y legales en materia electoral, así como de velar porque los principios de certeza, legalidad, in-dependencia, imparcialidad y objetividad, guíen todas las actividades del Instituto Electoral.\nVI. La Sala Superior del Tribunal Electoral del Poder Judicial de la Federación en la sentencia emitida en el precitado expediente ordenó la realización de medidas preparatorias en una primera etapa en la que se determinará la procedencia de una segunda correspondiente a la consulta a los ciudadanos del Municipio de San Luis Acatlán, Guerrero, para determinar si la elección de sus autoridades municipales se lleva a cabo a través del sistema de usos y costumbres; dichas medidas preparatorias ordenadas por la autoridad Jurisdiccional electoral federal son:\na) Verificar y determinar la existencia histórica del sistema normativo Interno, constituido por el comunidades indígenas reconocen como válidas y utilizan para regular sus actos públicos, organización, actividades y que sus autoridades aplican para la resolución de sus conflictos.\nb) Recopilar información y generar los procedimientos que permitan obtener datos trascendentales en torno a los usos y costumbres que rigen a esa comunidad.\nc) Realización de dictámenes periciales, entrevistas con los habitantes, informes de las autoridades municipales legales y tradicionales, con el objetivo de determinar la viabilidad de la implementación de los usos y costumbres de dicha comunidad para la elección de sus autoridades.\nOBTENIDOS EN LA ETAPA DE MEDIDAS\nPREPARATORIAS QUE MANDATA LA RESOLUCIÓN\nSUP JDC-1740/2012, EMITIDA POR LA SALA\nSUPERIOR DEL TRIBUNAL ELECTORAL DEL PODER\nJUDICIAL DE LA FEDERACIÓN\nVII. Con fundamento en el artículo 100, fracción XIII, de la Ley de Instituciones y Procedimientos\nElectorales del Estado de Guerrero, se establece que es facultad del Consejero Presidente del Consejo\nGeneral del Instituto Electoral, establecer los vínculos entre el Instituto Electoral y las autoridades federales, estatales y municipales, para lograr su apoyo y colaboración, en sus respectivos ámbitos de competencia, cuando esto sea necesario para el cumplimiento de los fines del Instituto Electoral.\nVIII. Con el objeto de dar seguimiento y estricto cumplimiento a la actividades establecidas en los\nLineamientos para dar Cumplimiento a las Medidas Preparatorias de la Resolución SUP-JDC-1740/2012, consistentes en: dictamen pericial, estudios especializados, entrevistas a grupos focales, informes de las autoridades legales y tradicionales e investigación documental (material hemerográfico, bibliográfico, videográfico, legislación, internet, entre otros), se han venido realizando de manera simultánea tal como se detalla en los referidos antecedentes.\nIX. El artículo 14 de los Lineamientos en comento, establece que el inicio de las actividades que se enuncian, se realizarán en forma inmediata y para su consecución final, se cuenta con un plazo de hasta 90 días hábiles, a partir del día siguiente de su aprobación por el Consejo General.\nX. En la Novena Sesión Ordinaria celebrada por el Consejo General del Instituto Electoral del\nEstado de Guerrero, el día veintisiete de septiembre del año dos mil trece, mediante acuerdo\n027/SO/2709-2013 se aprobó la ampliación del plazo por un periodo de 60 días hábiles, a partir del día siguiente de vencido el plazo que prevé el artículo 14 de los lineamientos para dar cumplimiento a las medidas preparatorias de la resolución SUP-JDC-1740/2012, emitida por la Sala Superior del Tribunal\nElectoral del Poder Judicial de la Federación, en términos de los considerandos XIII y XIV del acuerdo de referencia.\nXI. En virtud de las diligencias que se encontraba efectuando la Comisión Nacional para el\nDesarrollo de los Pueblos Indígenas, el Consejo General del Instituto, valoró la necesidad de ampliar el plazo establecido por un periodo de 30 días hábiles, a partir del día siguiente de vencido el plazo de la primera ampliación que feneció el día 17 de enero del 2014.\nXII. Considerando que en fecha 20 de febrero del presente año, mediante oficio\nDGAJ/2014/OF/243 que suscribe el Licenciado Francisco Javier Cedillo Tecayéhuatl, fue recibido en este\nÓrgano Electoral, el dictamen en materia de antropología social presentado por el Licenciado Emeterio\nCruz García y en virtud de la debida valoración de dicho dictamen, que está efectuando el Consejo\nGeneral de este Órgano Electoral, se acuerda la ampliación del plazo establecido por un periodo de 15 días hábiles, a partir del día siguiente de vencido el plazo de la segunda ampliación que fenece el día 3 de marzo del 2014, es decir a partir del 4 de marzo, culminando el día 25 del mismo mes y año.\nOBTENIDOS EN LA ETAPA DE MEDIDAS\nPREPARATORIAS QUE MANDATA LA RESOLUCIÓN\nSUP JDC-1740/2012, EMITIDA POR LA SALA\nSUPERIOR DEL TRIBUNAL ELECTORAL DEL PODER\nJUDICIAL DE LA FEDERACIÓN\nPor las consideraciones antes expuestas y con fundamento en los artículos 25, párrafo segundo, 90, 99 fracciones XXXII y LXXVIII de la Ley de Instituciones y Procedimientos Electorales del Estado de\nGuerrero, número 571, el Consejo General del Instituto Electoral del Estado emite el siguiente:\nPRIMERO.- Se aprueba la ampliación del plazo por un periodo de 15 días hábiles, a partir del día siguiente de vencido el plazo de ampliación que se aprobó en la Décima Segunda Sesión Ordinaria celebrada por el Consejo General del Instituto Electoral del Estado de Guerrero, ampliación que inicia a partir del día 4 de marzo y culmina el 25 del mismo mes y año, en términos del considerando XII del presente acuerdo.\nSEGUNDO.- Notifíquese a la Sala Superior del Tribunal Electoral del Poder Judicial de la\nFederación; Gobierno del Estado de Guerrero, a través de la Secretaría General de Gobierno; H.\nCongreso del Estado de Guerrero; H. Ayuntamiento del Municipio de San Luis Acatlán, Guerrero y al\nActor C. Bruno Plácido Valerio, con copia debidamente certificada del presente acuerdo, dentro del plazo de tres días hábiles posteriores a la aprobación del presente, en cumplimiento a la sentencia dictada en el expediente SUP-JDC-1740/2012, para los efectos legales a que haya lugar.\nTERCERO.- Publíquese el presente acuerdo y el calendario anexo, en el Periódico Oficial del\nGobierno del Estado en términos del artículo 98 de la Ley de Instituciones y Procedimientos Electorales del Estado de Guerrero.\nSe notifica a los representantes de los partidos políticos acreditados ante este Instituto Electoral, en términos de lo dispuesto por el artículo 34 de la Ley del Sistema de Medios de Impugnación en\nMateria Electoral. celebrada por el Consejo General del Instituto Electoral del Estado de Guerrero, el día veintisiete de febrero del año dos mil catorce.\nEL PRESIDENTE DEL CONSEJO GENERAL\nDEL INSTITUTO ELECTORAL DEL ESTADO.\nC. JOSÉ GUADALUPE SALGADO ROMÁN.\nRúbrica.\nOBTENIDOS EN LA ETAPA DE MEDIDAS\nPREPARATORIAS QUE MANDATA LA RESOLUCIÓN\nSUP JDC-1740/2012, EMITIDA POR LA SALA\nSUPERIOR DEL TRIBUNAL ELECTORAL DEL PODER\nJUDICIAL DE LA FEDERACIÓN\nEL SECRETARIO GENERAL.\nC. CARLOS ALBERTO VILLALPANDO MILIÁN.\nRúbrica.\nOBTENIDOS EN LA ETAPA DE MEDIDAS\nPREPARATORIAS QUE MANDATA LA RESOLUCIÓN\nSUP JDC-1740/2012, EMITIDA POR LA SALA\nSUPERIOR DEL TRIBUNAL ELECTORAL DEL PODER\nJUDICIAL DE LA FEDERACIÓN",
  "ordenamiento": "ACUERDO",
  "jurisdiccion": "GUERRERO",
  "fuente_oficial": "DIARIO OFICIAL DE LA FEDERACION",
  "Fecha de Publicación": "25 DE MARZO DE 2014",
  "ULTIMA REFORMA PUBLICADA": "14 de Marzo de 2014",
  "status": "ABROGADA",
  "es_escaneado": false,
  "tiene_tablas": false,
  "materia": [
    "general"
  ]
}