{
  "titulo": "Acuerdo Administrativo por el Que Se Declara A la Procuraduría de Defensa de los Campesinos del Esta",
  "Contenido": "ADMINISTRATIVO DESCONCENTRADO AUTÓNOMO QUE\nES, SE ENCUENTRA ADSCRITO DIRECTAMENTE A LA\nFUNCIONAMIENTO, SE COORDINARÁ CON LA\nDEPENDIENTE DE LA SECRETARÍA GENERAL DE GOBIERNO\nABROGADO POR EL ARTÍCULO CUARTO TRANSITORIO DEL REGLAMENTO INTERIOR DE\nLA SECRETARÍA GENERAL DE GOBIERNO, PUBLICADO EN EL PERIÓDICO OFICIAL DEL\nGOBIERNO DEL ESTADO No. 52 ALCANCE I, DE FECHA 01 DE JULIO DE 2014.\nTEXTO ORIGINAL\nAcuerdo publicado en el Periódico Oficial del Gobierno del Estado No. 71 Alcance I, el Martes 03 de Septiembre de 2013.\nACUERDO ADMINISTRATIVO POR EL QUE SE DECLARA A LA PROCURADURÍA DE DEFENSA DE\nLOS CAMPESINOS DEL ESTADO DE GUERRERO (PRODECAM), QUE COMO ÓRGANO\nADMINISTRATIVO DESCONCENTRADO AUTÓNOMO QUE ES, SE ENCUENTRA ADSCRITO\nDIRECTAMENTE A LA SECRETARÍA GENERAL DE GOBIERNO, Y PARA SU MEJOR\nFUNCIONAMIENTO, SE COORDINARÁ CON LA SUBSECRETARÍA DE GOBIERNO PARA ASUNTOS\nAGRARIOS DEPENDIENTE DE LA SECRETARÍA GENERAL DE GOBIERNO.\nACUERDO ADMINISTRATIVO.- Chilpancingo Guerrero, a veintiocho de agosto de dos mil trece.\nCon el objeto de dar cumplimiento al artículo 1º del Decreto publicado en el Periódico Oficial del\nGobierno del Estado de Guerrero, número 1º, de fecha cuatro de enero del dos mil, por el que se crea la\nProcuraduría de Defensa de los Campesinos del Estado de Guerrero (PRODECAM), cuyo objetivo es atender eficiente y oportunamente las demandas de los campesinos del Estado proporcionándoles la asistencia jurídica necesaria, con fundamento en lo dispuesto por los artículos 8 y 12 de la Ley Orgánica de la Administración Pública del Estado de Guerrero, número 433, 5 fracción VII, 9 fracción VII y 42 fracción XVIII del Reglamento Interior de la Secretaría General de Gobierno, se declara a la\nProcuraduría de Defensa de los Campesinos del Estado de Guerrero (PRODECAM), que como\nÓrgano Administrativo Desconcentrado Autónomo que es, se encuentra adscrito directamente a la\nSecretaría General de Gobierno, y para su mejor funcionamiento, se coordinará con la\nGobierno, dado que la relación operativa que guarda la PRODECAM respecto de la Subsecretaría de\nGobierno para Asuntos Agrarios, dependiente de la Secretaría de Gobierno, es una relación de coordinación y no una relación de subordinación total y directa, a fin de que la Procuraduría de Defensa de los Campesinos, bajo su naturaleza de Órgano Administrativo Desconcentrado por función, siga ejerciendo en forma parcial, oportuna y objetiva las funciones que le competen en apego al instrumento normativo que sustenta su actuación.\nAsí lo acordó y firma el C. Licenciado RÁUL EFRAÍN CARDOSO MIRANDA, Director General de\nAsuntos Jurídicos de la Secretaría General de Gobierno, quien actúa ante los CC. Licenciados JOSE\nADMINISTRATIVO DESCONCENTRADO AUTÓNOMO QUE\nES, SE ENCUENTRA ADSCRITO DIRECTAMENTE A LA\nFUNCIONAMIENTO, SE COORDINARÁ CON LA\nLUIS DEL VALLE ESPINOSA Y ORALIA SALGADO CASTRO, quienes autorizan y dan fe para debida constancia legal.- CONSTE.\nRúbricas.",
  "ordenamiento": "ACUERDO",
  "jurisdiccion": "GUERRERO",
  "fuente_oficial": "DIARIO OFICIAL DE LA FEDERACION",
  "Fecha de Publicación": "01 DE JULIO DE 2014",
  "ULTIMA REFORMA PUBLICADA": "01 DE JULIO DE 2014",
  "status": "ABROGADA",
  "es_escaneado": false,
  "tiene_tablas": false,
  "materia": [
    "penal",
    "administrativo",
    "agrario"
  ]
}