{
  "titulo": "Acuerdo PGJESJAVDDGELA0032013, por el Cual Establece la Obligación A Todos los Fiscales Especiales,",
  "Contenido": "DE LA PROCURADURÍA GENERAL DE JUSTICIA DEL\nESTADO DE GUERRERO, ASÍ COMO TODO SERVIDOR\nDILIGENCIAS DE AVERIGUACIÓN PREVIA, DE REMITIR A\nLA DIRECCIÓN GENERAL DE LOS SERVICIOS PERICIALES\nDE ESTA PROCURADURÍA, TODO EL MATERIAL BALÍSTICO\nDERIVADO DE UN HECHO DELICTIVO\nTEXTO ORIGINAL.\nAcuerdo publicado en el Periódico Oficial del Gobierno del Estado No. 2, el Martes 07 de Enero de 2014.\nACUERDO PGJE/SJAVD/DGEL/A/003/2013, POR EL CUAL ESTABLECE LA OBLIGACIÓN A TODOS\nLOS FISCALES ESPECIALES, REGIONALES, AGENTES DEL MINISTERIO PÚBLICO TITULARES Y\nAUXILIARES Y TODO EL PERSONAL DE LA PROCURADURÍA GENERAL DE JUSTICIA DEL\nESTADO DE GUERRERO, ASÍ COMO TODO SERVIDOR PÚBLICO QUE FUNJA COMO AUXILIAR\nEN LA PRÁCTICA DE DILIGENCIAS DE AVERIGUACIÓN PREVIA, DE REMITIR A LA DIRECCIÓN\nGENERAL DE LOS SERVICIOS PERICIALES DE ESTA PROCURADURÍA, TODO EL MATERIAL\nBALÍSTICO DERIVADO DE UN HECHO DELICTIVO.\nLICENCIADO IÑAKY BLANCO CABRERA, PROCURADOR GENERAL DE JUSTICIA DEL\nESTADO DE GUERRERO, CON FUNDAMENTO EN LO DISPUESTO POR LOS ARTÍCULOS 21\nPÁRRAFO PRIMERO DE LA CONSTITUCIÓN POLÍTICA DE LOS ESTADOS UNIDOS MEXICANOS;\nPÁRRAFO TERCERO, 35 FRACCIONES I Y IV DE LA LEY ORGÁNICA DE LA ADMINISTRACIÓN\nPÚBLICA DEL ESTADO DE GUERRERO NÚMERO 433; 1, 2, 10 FRACCIONES I, II, V Y IX, 11, 29\nFRACCIÓN VIII, Y 30 FRACCIONES I Y XIII DE LA LEY ORGÁNICA DE LA PROCURADURÍA\nGENERAL DE JUSTICIA DEL ESTADO DE GUERRERO NÚMERO 193, ASI COMO 5, 42 Y 43, DEL\nREGLAMENTO DE LA LEY ORGÁNICA DE LA PROCURADURÍA GENERAL DE JUSTICIA, Y\nQue el Plan Estatal de Desarrollo 2011-2015, dispone como uno de sus objetivos reorganizar la administración pública para hacerla más eficaz y eficiente. Así como también contar con una renovada administración de justicia.\nQue la Constitución Política de los Estados Unidos Mexicanos, dispone en su artículo 21 párrafos noveno y décimo que la seguridad pública es una función a cargo de la federación, el Distrito\nFederal, los Estados y los Municipios, que comprende la prevención de los delitos, la investigación y persecución para hacerla efectiva, así como la sanción de las infracciones administrativas en los términos de la ley en las respectivas competencias que la propia Constitución prevé y, que el Ministerio Público y objetivos de la seguridad pública y conformar el sistema nacional de seguridad pública. Asimismo, en\nDE LA PROCURADURÍA GENERAL DE JUSTICIA DEL\nESTADO DE GUERRERO, ASÍ COMO TODO SERVIDOR\nDILIGENCIAS DE AVERIGUACIÓN PREVIA, DE REMITIR A\nLA DIRECCIÓN GENERAL DE LOS SERVICIOS PERICIALES\nDE ESTA PROCURADURÍA, TODO EL MATERIAL BALÍSTICO\nDERIVADO DE UN HECHO DELICTIVO este artículo se hace mención en el inciso b) del párrafo décimo que una de las bases del sistema es el establecimiento de datos criminalísticos y de personal para las instituciones de seguridad pública.\nQue el 2 de enero de 2009, se publicó en el Diario Oficial de la Federación la Ley General del\nSistema Nacional de Seguridad Pública, cuyo objeto es regular la integración, organización y funcionamiento del Sistema Nacional de Seguridad Pública, así como establecer la distribución de competencias y las bases de coordinación entre la Federación, los Estados, el Distrito Federal y los\nMunicipios en esta materia. la Procuraduría General de Justicia del Estado de Guerrero Número 193, establece el Procurador\nGeneral de Justicia del Estado es el titular del Ministerio Público y en su artículo 29, fracción XVIII prevé la facultad indelegable del C. Procurador General de Justicia del Estado para expedir los acuerdos, circulares, instructivos, bases y manuales de organización y procedimientos, para el buen despacho de los asuntos de la Institución.\nPor su parte, el Código de Procedimientos Penales para el Estado de Guerrero, número 357, es un ordenamiento legal, general y de aplicación obligatoria para el Ministerio Público del Fuero Común, los\nServicios Periciales del Estado y los integrantes de las instituciones policiales de los dos niveles de gobierno (Estatal y Municipal), que prevé la obligación de éstos, de recolectar materiales balísticos para la integración de las averiguaciones previas en el lugar de los hechos.\nQue los artículos 1, 54 y 58 de dicho ordenamiento legal, imponen al Ministerio Público, a las policías y a los servidores públicos quienes fungen como auxiliares en la práctica de diligencias de averiguación previa, el deber y responsabilidad de dictar todas las medidas y providencias necesarias para impedir que se pierdan, destruyan o alteren los indicios, huellas o vestigios del hecho delictuoso, así como los instrumentos, objetos o productos del delito.\nQue para dar cumplimiento a la normatividad vigente, la Procuraduría General de Justicia del\nEstado de Guerrero, como institución integrante del Sistema Estatal de Seguridad Pública, de conformidad con lo dispuesto en los artículos 1, 2, 3 y 14 de la Ley 281 de Seguridad Pública del Estado de Guerrero, se encuentra comprometida a implementar acciones de mejora para la persecución del delito, considerando la necesidad de contar con sistemas de información.\nQue desde hace más de 20 años, a nivel mundial se han implementado sistemas y tecnologías para la identificación balística automatizada y de armas de fuego, generando la asociación de cientos de\nDE LA PROCURADURÍA GENERAL DE JUSTICIA DEL\nESTADO DE GUERRERO, ASÍ COMO TODO SERVIDOR\nDILIGENCIAS DE AVERIGUACIÓN PREVIA, DE REMITIR A\nLA DIRECCIÓN GENERAL DE LOS SERVICIOS PERICIALES\nDE ESTA PROCURADURÍA, TODO EL MATERIAL BALÍSTICO\nDERIVADO DE UN HECHO DELICTIVO organismos de seguridad pública en más de 50 países, con la finalidad de aportar soluciones rentables y sostenibles mediante el uso de ingenierías, ciencias forenses y seguridad del Estado.\nQue en el mundo se ha implementado el Sistema Integrado de Identificación Balística (IBIS por sus siglas en inglés), resultando una solución confiable para identificar en poco tiempo y con certeza, los problemas planteados por la balística forense, en particular, el concerniente al tipo de arma de fuego utilizada en la comisión del delito basado su uso en la alimentación de imágenes digitales de las marcas microscópicas únicas detectadas en los casquillos y balas empleados en un hecho delictivo, creando con ello una base de datos compartida con otras instituciones de seguridad pública, a nivel estatal nacional e incluso internacional, permitiendo el intercambio de información y exactitud de resultados, la cual, mediante el uso de métodos comparativos realizados entre el material almacenado y el encontrado en el lugar de los hechos y/o del hallazgo, permite saber si el arma que disparó el material balístico, fue ya ocupada en algún acontecimiento anterior.\nDicha base de datos es compartida con otras instituciones de Seguridad Pública, a nivel estatal, nacional e internacional, permitiendo con ello, el intercambio de información y exactitud de resultados.\nQue en el Grupo de Directores Generales de Servicios Periciales del país, así como en la\nConferencia Nacional de Procuración de Justicia, se planteó la necesidad de contar con una base de datos nacional, que permita en forma automatizada, el registro, comparación e intercambio de información balística entre todos los peritos de la República Mexicana, que facilite la persecución del delito y la resolución de casos.\nAnte el incremento del uso de armas de fuego en nuestro país, el 30 de junio de 2011 el Consejo\nNacional de Seguridad Pública, en sesión ordinaria, acordó dar cumplimiento al Acuerdo 05/XXX/11, sólida y de manera sistemática, sobre el tráfico y uso de armas en la comisión de delitos, lo que trajo como resultado la implementación de los sistemas E-TRACE (rastreo de armas de fuego) y el Sistema\nIntegrado de Identificación Balística (IBIS) con el que se creó la base nacional de huella balística.\nCon la implementación de los citados sistemas, nuestro país se encuentra a la vanguardia en la implementación y uso de herramientas automatizadas de identificación balística, siendo el Estado de\nGuerrero una de las entidades que poseen dichas tecnologías. cadena de custodia del material balístico, tengo a bien expedir el siguiente:\nDE LA PROCURADURÍA GENERAL DE JUSTICIA DEL\nESTADO DE GUERRERO, ASÍ COMO TODO SERVIDOR\nDILIGENCIAS DE AVERIGUACIÓN PREVIA, DE REMITIR A\nLA DIRECCIÓN GENERAL DE LOS SERVICIOS PERICIALES\nDE ESTA PROCURADURÍA, TODO EL MATERIAL BALÍSTICO\nDERIVADO DE UN HECHO DELICTIVO\nACUERDO PGJE/SJAVD/DGEL/A/003/2013, POR EL CUAL ESTABLECE LA OBLIGACIÓN A TODOS\nLOS FISCALES ESPECIALES, REGIONALES, AGENTES DEL MINISTERIO PÚBLICO TITULARES Y\nAUXILIARES Y TODO EL PERSONAL DE LA PROCURADURÍA GENERAL DE JUSTICIA DEL\nESTADO DE GUERRERO, ASÍ COMO TODO SERVIDOR PÚBLICO QUE FUNJA COMO AUXILIAR\nEN LA PRÁCTICA DE DILIGENCIAS DE AVERIGUACIÓN PREVIA, DE REMITIR A LA DIRECCIÓN\nGENERAL DE LOS SERVICIOS PERICIALES DE ESTA PROCURADURÍA, TODO EL MATERIAL\nBALÍSTICO DERIVADO DE UN HECHO DELICTIVO.\nARTÍCULO 1. Todos los Fiscales Especiales, Regionales, agentes del Ministerio Público\nTitulares y Auxiliares, y todo el personal de la Procuraduría General de Justicia del Estado de Guerrero, así como de todo servidor público que funja como auxiliar en la práctica de diligencias de averiguación previa, tendrá la obligación de poner a disposición de la Dirección General de los Servicios Periciales de la Procuraduría General de Justicia del Estado de Guerrero, el material o elementos balísticos que sean encontrados o identificados en cualquier lugar en el que se haya cometido algún delito.\nARTÍCULO 2. Por material o elementos balísticos se entenderá: cartuchos, casquillos, balas, esquirlas o vestigios de éstos que encuentren en el lugar de los hechos y/o del hallazgo en el que se presuma se haya cometido algún delito.\nARTÍCULO 3. La Dirección General de los Servicios Periciales inmediatamente que haya recibido el material o elementos balísticos deberá de incorporar la descripción, imágenes y demás datos de identificación al Sistema Integrado de Identificación Balística (IBIS).\nARTÍCULO 4. Una vez incorporado al Sistema Integrado de Identificación Balística (IBIS), el material o elementos balísticos, conforme a lo dispuesto en el artículo anterior, la Dirección General de ello el acervo físico de muestras balísticas útiles para futuros estudios comparativos confirmativos, regresando a la autoridad competente, anexo al dictamen los elementos balísticos restantes.\nNota: si en la investigación correspondiente solo existiera un solo elemento balístico, este será resguardado con el mismo procedimiento por el laboratorio de balística.\nARTÍCULO 5. El acervo físico de muestras balísticas, estará bajo la custodia y administración de la Dirección General de los Servicios Periciales, quien se encargará de realizar los estudios técnicos y proporcionar a las autoridades y entidades competentes, los resultados correspondientes a las instancias\nDE LA PROCURADURÍA GENERAL DE JUSTICIA DEL\nESTADO DE GUERRERO, ASÍ COMO TODO SERVIDOR\nDILIGENCIAS DE AVERIGUACIÓN PREVIA, DE REMITIR A\nLA DIRECCIÓN GENERAL DE LOS SERVICIOS PERICIALES\nDE ESTA PROCURADURÍA, TODO EL MATERIAL BALÍSTICO\nDERIVADO DE UN HECHO DELICTIVO primera y ulteriores instancias cuidando siempre los principios de pronta, expedita y justa administración de justicia.\nARTÍCULO 6. Sí del estudio del posterior material o elementos balísticos entregados a la\nDirección General de los Servicios Periciales, se detecta que éstos provienen de una misma arma de fuego cuyo material balístico se encuentra ya en el acervo físico de muestras balísticas, la citada\nDirección General tomará nota de ello y devolverá el material con el resultado correspondiente.\nARTÍCULO 7. Los Fiscales Especiales, Regionales, agentes del Ministerio Público Titulares y\nAuxiliares y todo el personal de la Procuraduría General de Justicia del Estado de Guerrero, así como todo servidor público que funja como auxiliar en la práctica de diligencias de averiguación previa que omita el cumplimiento del presente acuerdo, será acreedor de las sanciones que establecen las leyes de responsabilidades administrativas y/o penales establecidas por la legislación aplicable.\nPRIMERO.- Publíquese en el Periódico Oficial del Gobierno del Estado de Guerrero.\nSEGUNDO.- El presente acuerdo entrará en vigor a partir del día siguiente al de su publicación\nDado en la ciudad de Chilpancingo de los Bravo, Guerrero a los 7 días del mes de diciembre de\n2013.\nEl PROCURADOR GENERAL DE JUSTICIAL\nDEL ESTADO DE GUERRERO.\nLICENCIADO IÑAKY BLANCO CABRERA.\nRúbrica.",
  "ordenamiento": "ACUERDO",
  "jurisdiccion": "GUERRERO",
  "fuente_oficial": "DIARIO OFICIAL DE LA FEDERACION",
  "Fecha de Publicación": "07 de Enero \nde 2014",
  "ULTIMA REFORMA PUBLICADA": null,
  "status": "VIGENTE",
  "es_escaneado": false,
  "tiene_tablas": false,
  "materia": [
    "fiscal"
  ]
}