{
  "titulo": "Código DE CONDUCTA DE LOS CENTROS DE JUSTICIA PARA LAS MUJERES DEL ESTADO.",
  "Contenido": "ACUERDO NÚMERO A/006/2018 DEL FISCAL GENERAL DEL ESTADO DE CAMPECHE, POR\nMUJERES DEL ESTADO.\nDr. Juan Manuel Herrera Campos, Fiscal General del Estado de Campeche, con fundamento en los artículos 21 de la Constitución Política de los Estados Unidos Mexicanos; 75 y 76 de la del Estado de Campeche y en ejercicio de las facultades que me confieren los artículos 19 fracción\nIV de la Ley Orgánica de la Fiscalía General del Estado de Campeche y 11 fracción V del Reglamento\nInterior de la Fiscalía General del Estado de Campeche; y\nCONSIDERANDO\nQue con las reformas a la Constitución Política de los Estados Unidos Mexicanos de fechas 18 de junio de 2008 y 10 de junio de 2011, publicadas en el Diario Oficial de la Federación, el Estado\nMexicano dio un paso firme y tenaz en el cambio de paradigma en el Sistema de Justicia Penal y en materia de Derechos Humanos, por tal motivo, es importante mencionar, nuestro actual artículo 1° que medularmente señala “…todas las personas gozaran de los derechos humanos reconocidos en esta Constitución y en los Tratados Internacionales de los que el Estado Mexicano sea parte…”, y que entre otros aspectos reconoció el principio Pro Persona como rector de la interpretación y aplicación de las normas jurídicas, en aquellos que favorezcan y brinden mayor protección a las personas, por lo que es deber del Estado tomar las medidas necesarias para cumplir con los compromisos asumidos en los instrumentos internacionales suscritos por nuestro país, en el sentido de brindar asistencia y atención oportuna a las víctimas de delitos.\nQue por imperativo del artículo 21 de la Constitución Política de los Estados Unidos Mexicanos, el\nMinisterio Público tiene bajo su responsabilidad la función investigadora y persecutora de los delitos, la cual realiza desde el momento en que tiene conocimiento de un hecho de carácter delictivo.\nQue el Plan Estatal de Desarrollo 2015-2021, en su eje Transversal Perspectiva de Género, señala en su línea de acción 6.6.1.1.1. Modernizar y actualizar el marco jurídico y normativo estatal que fomente la transversalidad, la asignación y ejecución de recursos públicos destinados a las mujeres\nQue para el cumplimiento de sus atribuciones la Fiscalía General del Estado contara con unidades administrativas para el correcto funcionamiento y mejor organización de la Institución, entre ellas, con los Centros de Justicia para las Mujeres que tiene como objetivo toral, brindarle a las mujeres y a sus familias todos los servicios que sean necesarios para que ellas mismas tomen decisiones informadas, para que se reduzcan las posibilidades de que continúen siendo víctimas de la violencia y sean capaces de ejercer todos sus derechos, incluido el derecho a las garantías procesales y al acceso a la justicia, cuyo bien jurídico que se tutela son las mujeres y sus derechos humanos, entendidos en el sentido más amplio, claro está con perspectiva de género y desde el enfoque de la seguridad ciudadana y humana.\nQue para aumentar la confianza de la sociedad, es indispensable contar con criterios éticos que orienten a las y los servidores públicos para conducir su actuación con transparencia, honestidad, a la legalidad y del papel ejemplar que deben desempeñar, propiciando una plena vocación de servicio público en beneficio de la colectividad, con la observancia de principios y valores que dignifiquen su labor, a efecto de consolidar un sistema de procuración de justicia profesional, transparente y respetuoso a los derechos humanos, por lo que dicho referente ético pretende ser una invitación directa a las conciencias de las y los servidores públicos, a transformar y/o seguir incentivando de manera adecuada las conductas desempeñadas diariamente.\nde la Ley Orgánica de la Administración Pública del Estado de Campeche; 19 fracción IV de la Ley\nOrgánica de la Fiscalía General del Estado de Campeche y 11 fracción V del Reglamento Interior de la Fiscalía General del Estado de Campeche, entre las atribuciones del Fiscal General del Estado se encuentra la de emitir circulares, acuerdos, directrices, protocolos, instructivos, manuales de organización y de procedimientos, así como las disposiciones técnicas y administrativas de su competencia.\nPor lo anteriormente expuesto, sea tenido a bien emitir:\nEL CÓDIGO DE CONDUCTA DE LOS CENTROS DE JUSTICIA PARA LAS MUJERES DEL\nESTADO.\nCONTENIDO\nINTRODUCCIÓN.\nJUSTIFICACION.\nTITULO PRIMERO.\nCAPITULO I.\n1. DISPOSICIONES GENERALES.\n2. GLOSARIO.\n3. MARCO NORMATIVO.\n4. OBJETIVO.\n5. MISIÓN.\n6. VISIÓN.\n7. ÁMBITO DE APLICACIÓN.\nCAPITULO II.\nPRINCIPIOS Y VALORES.\n1. PRINCIPIOS.\n2. VALORES.\nCAPÍTULO III.\nDECÁLOGO DE CONDUCTAS.\n1. CONOCIMIENTO Y APLICACIÓN DEL MARCO JURÍDICO.\n2. USO DEL CARGO PÚBLICO.\n3. UTILIZACIÓN Y MANEJO TRANSPARENTE DE LA INFORMACIÓN.\n4. TOMA DE DECISIONES Y CONFLICTOS DE INTERES.\n5. MANTENER UN CLIMA LABORAL RESPETUOSO Y COLABORATIVO.\n6. PROMOVER LA IGUALDAD Y NO DISCRIMINACIÓN POR MOTIVO DE GÉNERO Y RESPETAR\nEL DERECHO DE DIVERSIDAD SEXUAL.\n7. RESPETO A LOS DERECHOS HUMANOS.\n8. COMBATE A LA CORRUPCION.\n9. RELACION CON LA CIUDADANÍA.\n10. RELACIONES CON OTRAS DEPENDENCIAS DE LOS GOBIERNOS FEDERAL, ESTATAL Y\nMUNICIPAL.\n11. CAPACITACIÓN Y PROFESIONALIZACIÓN.\n12. ADAPTACIÓN AL CAMBIO.\n13. USOS Y ASIGNACIÓN DE RECURSOS HUMANOS, MATERIALES, FINANCIEROS Y\nTECNOLÓGICOS.\n14. CUMPLIMIENTO AL CÓDIGO DE CONDUCTA.\nINTRODUCCIÓN de la violencia y la dignificación de las mujeres, a través de un proceso integral de atención, estrategias eficaces e innovadoras de prevención, atención, seguimiento y el empoderamiento de las mujeres que viven violencia; concentrando a las distintas instancias bajo un mismo techo, y contando con el apoyo de las Redes de Colaboración internas y externas.\nley, lo que significa que todas las personas, sin distingo alguno tenemos los mismos derechos y deberes frente al Estado y la sociedad en su conjunto.\nPor tanto, toda mujer tiene derecho al reconocimiento, goce, ejercicio y protección de todos los derechos humanos y a las libertades consagradas por los instrumentos internacionales, nacionales y estatales sobre derechos humanos.\nEl artículo Octavo de la Ley General de Acceso de las Mujeres a una Vida Libre de Violencia establece que los modelos de atención, prevención y sanción son el conjunto de medidas y acciones para proteger a la víctima de violencia familiar, como parte de la obligación del Estado.\nLas y los operadores de los Centros de Justicia para las Mujeres del Estado, tienen la obligación de promover, respetar, proteger y garantizar los derechos humanos de las personas víctimas de violencia de género, de conformidad con los principios de universalidad, interdependencia, indivisibilidad y progresividad, así como promover acciones que eliminen prácticas discriminatorias y de violencia contra las mujeres; por ello debemos esforzarnos permanentemente para tener una conducta integra y ética en el desempeño de nuestro trabajo.\nDe ahí, la importancia que los Centros de Justicia para las Mujeres, cuenten con un Código de\nConducta que contribuya a la sensibilización de las y los operadores, en torno al alto valor social que tienen cada una de las acciones que realizan y el impacto que reflejan a la ciudadanía.\nEste Código contiene la misión, visión, principios y valores de los Centros de Justicia para las Mujeres del Estado, así como el decálogo de conductas que, durante el ejercicio de sus actividades deba observar el personal.\nJUSTIFICACIÓN individuo y cómo éstas permiten su adecuada interacción con la sociedad. Para lograr una buena convivencia se adoptan normas y valores que marquen la pauta para crear vínculos personales, profesionales y laborales.\nde lo que es permitido o no dentro del ámbito laboral, de ahí, que es necesario establecer un código de conducta, donde se describa los principios en que debe conducirse en el entorno laboral, bajo aspectos de un clima laboral armónico, libre de discriminación y violencia, así como para que la atención ciudadana que se brinde sea congruente con los valores y objetivos del Centro.\ncumplidos por todos los que integran la Administración Pública Estatal; asimismo, y ante cualquier\nPlan Estatal de Desarrollo, imperará el respeto de los derechos humanos y la igualdad de género.\nAunado que, la Suprema Corte de Justicia de la Nación, ha pronunciado: “…que la dignidad humana no se identifica ni se confunde con un precepto meramente moral, sino que se proyecta en nuestro ordenamiento como un bien jurídico circunstancial al ser humano, merecedor de la más amplia protección jurídica, reconocido actualmente en los artículos 1o., último párrafo; 2o., apartado A, fracción II; 3o., fracción II, inciso c); y 25 de la Constitución Política de los Estados Unidos Mexicanos.\nEn efecto, el Pleno de esta Suprema Corte ha sostenido que la dignidad humana funge como un principio jurídico que permea en todo el ordenamiento, pero también como un derecho fundamental que debe ser respetado en todo caso, cuya importancia resalta al ser la base y condición para el disfrute de los demás derechos y el desarrollo integral de la personalidad. Así las cosas, la dignidad humana no es una simple declaración ética, sino que se trata de una norma jurídica que consagra un derecho fundamental a favor de la persona y por el cual se establece el mandato constitucional a todas las autoridades, e incluso particulares, de respetar y proteger la dignidad de todo individuo, entendida ésta -en su núcleo más esencial- como el interés inherente a toda persona, por el mero hecho de serlo, a ser tratada como tal y no como un objeto, a no ser humillada, degradada, envilecida o cosificada…” 1.\nTITULO PRIMERO\nCAPITULO I\n1. DISPOSICIONES GENERALES\nLos Centros de Justicia para las Mujeres son organismos con autonomía técnica y de gestión, dependiente de la Fiscalía General del Estado, que tiene por objeto coordinar la prestación de servicios interinstitucionales y especializados para facilitar el acceso a la justicia, brindando atención integral con perspectiva de género para prevenir, atender y erradicar la violencia contra las mujeres en el Estado.\n2. GLOSARIO\nPara efectos del presente Código de Conducta se entenderá por:\nI) Código de Ética: Código de Ética de las y los Servidores Públicos de las Dependencias y\nEntidades de la Administración Pública del Estado de Campeche, a que se refiere el Acuerdo publicado en el Periódico Oficial del Estado de Campeche, el 13 de septiembre de 2017.\nII) Código de Conducta: Instrumento emitido por el titular de la dependencia o entidad a propuesta de los Comités de Ética y de Prevención de conflicto de intereses.\nIII) Comité: Comité de Ética y de Prevención de Conflictos de Interés de los Centros de Justicia para las Mujeres.\nIV) Conflicto de Interés: La situación que se presenta, cuando los intereses personales, familiares de sus empleos, cargos, comisiones o funciones.\nV) Delación: La narrativa que formula cualquier persona ante el Comité, sobre un hecho o conducta atribuida a una o un servidor público y que resulta presuntamente contraria al Código de Ética, a las\nCampeche.\nVI) Centros o CJM: Centro de Justicia para las Mujeres, institución que concentra servicios violencia de género.\nVII) Lineamientos Generales: Lineamientos generales para propiciar la integridad de las y los ético, a través de los Comités de Ética y de Prevención de Conflictos de Interés, señalados en el\nVIII) Reglas de Integridad: Las Reglas de Integridad para el ejercicio de la función pública, señaladas en el Acuerdo publicado en el Periódico Oficial del Estado de Campeche, el 13 de septiembre de 2017.\nIX) Discriminación por razón de género: Trato desigual y desventajoso que sufren las personas, en virtud del conjunto de normas de conducta, de estereotipos, de valores, de significaciones que en una sociedad determinada se otorga al hecho biológico de ser mujeres o de ser hombres.\nX) Igualdad de Género: Situación en la cual mujeres y hombres acceden con las mismas posibilidades y oportunidades al uso, control y beneficio de bienes, servicios y recursos de la sociedad, así como a la toma de decisiones en todos los ámbitos de la vida social, económica, política, cultural y familiar.\nXI) Igualdad Sustantiva: Es el acceso al mismo trato y oportunidades para el reconocimiento, goce o ejercicio de los derechos humanos y las libertades fundamentales.\nXII) Perspectiva de Género: Concepto que se refiere a la metodología y los mecanismos que permiten identificar, cuestionar y valorar la discriminación, desigualdad y exclusión de las mujeres, que se pretende justificar con base en las diferencias biológicas entre mujeres y hombres, así como las acciones que deben emprenderse para actuar sobre los factores de género y crear las condiciones de cambio que permitan avanzar en la construcción de la igualdad de género.\nXIII) Transversalidad: Es el proceso que permite garantizar la incorporación de la perspectiva de género con el objetivo de valorar las implicaciones que tiene para las mujeres y los hombres cualquier acción que se programe, tratándose de normas jurídicas, políticas públicas, actividades administrativas, económicas y culturales, en las instituciones públicas y privadas.\nXIV) Operadoras y Operadores: Son los profesionales internos, llámense personal administrativo, técnico, especialista, etc., que participan en los procesos que se llevan a cabo en el Centro de\nJusticia para las Mujeres.\n3. MARCO NORMATIVO\nEn la comunidad internacional, con motivo de la evolución del problema de la violencia contra la la Mujer, por sus siglas (CEDAW), así como la Convención Interamericana para Prevenir, Sancionar y Erradicar la Violencia contra la Mujer, conocida como (Convención de Belém do Pará). Destacan las mujeres.\nEn lo referente, al marco normativo nacional lo integran tanto la Constitución Política de los Estados\nUnidos Mexicanos, la Ley General del Sistema Nacional de Seguridad Pública, Ley General para la\nIgualdad entre Mujeres y Hombres, la Ley Federal para Prevenir y Eliminar la Discriminación, como la ley General de Acceso a las Mujeres a una Vida Libre de Violencia, que por sus objetivos se han de género. Este marco permite definir las actividades y competencias de estos Centros en dos vertientes: una para la atención directa a las usuarias, y otra para generar un cambio en la realidad social de los estados y municipios del país.\nMujeres y Hombres del Estado de Campeche, Ley para Prevenir, Combatir y Sancionar toda forma de Discriminación en el Estado de Campeche y la Ley Estatal de Acceso de las Mujeres a una Vida\nLibre de Violencia, en congruencia con el Plan Estatal de Desarrollo 2015-2021, establece en el Eje\n4 “Sociedad Fuerte y Protegida”, en el objetivo 6.4.1. “Impartición y Procuración de Justicia”, el compromiso de formar servidores públicos más comprometidos con su responsabilidad social.\nA Fin de dar cumplimiento al Plan Estatal de Desarrollo 2015-2021 se estableció en el objetivo cuarto del Programa Sectorial de Justicia 2015-2021, dentro de la Estrategia 4.1 “Fomentar una cultura institucional dirigida a promover los valores que sirvan de guía para el comportamiento ético en el personal” como Línea de acción 4.1.1. “Definir un Código de Ética para las y los servidores públicos que tienen a su cargo la procuración de justicia en el Estado”.\nSe suma a ello, que con fecha 13 de septiembre de 2017, fue publicado en el Periódico Oficial del\nEstado, el Acuerdo que tiene por objeto emitir el Código de Ética de los Servidores Públicos de las\nDependencias y Entidades de la Administración Pública del Estado de Campeche, las Reglas de\nIntegridad para el ejercicio de la función pública y los Lineamientos Generales para propiciar la integridad de las y los servidores públicos y para implementar acciones permanentes que favorezcan su comportamiento ético, a través de los Comités de Ética y de Prevención de Conflictos de Interés.\n4. OBJETIVO\nEstablecer acciones que fomenten la legalidad, honradez, lealtad, imparcialidad y eficiencia en el desempeño de las funciones, empleos, cargos y comisiones que tiene cada persona, con el fin de mejorar la calidad de los servicios que brindan en los Centros.\n5. MISIÓN\nOfrecer servicios especializados, interdisciplinarios e integrales a mujeres víctimas de violencia de género, favoreciendo su empoderamiento e inclusión social; contribuyendo así a su acceso a la justicia, de forma justa, transparente, honesta, eficiente y de resultados, apegada al marco legal.\n6. VISIÓN\nSer una institución especializada en perspectiva de género, con estrategias de prevención, atención y empoderamiento que erradiquen la violencia contra las mujeres, velando por el respeto de los derechos humanos.\n7. ÁMBITO DE APLICACIÓN\nLos principios, valores y las demás disposiciones previstas en el presente Código de Conducta son de observancia general para las y los operadores de los Centros del Estado, cualquiera que sea su nivel jerárquico, especialidad o función, sin perjuicio de lo establecido en otras normas o disposiciones que regulan su función.\nPor lo tanto, toda persona que ingrese o se encuentre adscrita a los Centros, deberá conocer y asumir el compromiso de su debido cumplimiento.\nCAPITULO II\nPRINCIPIOS Y VALORES\n1. PRINCIPIOS del Estado de Campeche, las Reglas de Integridad para el ejercicio de la función pública, así como para las Mujeres, siendo ambos de observancia obligatoria para sus integrantes en el ejercicio de su encargo.\nEl Código de Conducta contiene doce principios básicos acordes a las necesidades y el desarrollo del Modelo de los Centros, buscando en todo momento inspirar una vocación de servicio público en beneficio de las usuarias, hijas e hijos, y mujeres en general que viven violencia.\nA continuación, se presentan los doce principios contemplados en el Código de Conducta de los\nCentros de Justicia para las Mujeres:\n1. Solidaridad. Nos adherimos en todo momento a las causas de las mujeres, analizando de manera profesional el comportamiento, sus manifestaciones y el impacto de nuestra atención.\n2. Eficacia. Ofrecemos ser eficaces en las acciones emprendidas, para lograr atender de manera profesional y personalizada a las mujeres, con la mayor calidad y calidez humana.\n3. Servicio. Aspiramos a establecer el acceso inmediato, oportuno y efectivo, manteniendo una actitud permanente de colaboración hacia la sociedad y las usuarias, manteniendo en todo momento una mejora continua.\n4. Confidencialidad. Haremos un adecuado uso de la información y datos personales (que podamos ver, sentir o intuir) sobre las mujeres, protegiendo su intimidad y sus derechos.\n5. Respeto a la dignidad humana. Reconoceremos siempre la diversidad de las mujeres de ser merecedoras de respeto.\n6. Ética. Fijar una directriz de conducta recta en beneficio propio, de los Centros y de las mujeres.\n7. Privacidad. Garantizar el resguardo de su privacidad y respetar que datos personales o información desea compartir con otras personas y cuál hacer pública.\n8. Compromiso. Nos comprometemos a dar todo nuestro esfuerzo y capacidad para lograr el bienestar de las usuarias.\n9. Competencia. Nos comprometemos a mantener el nivel de conocimientos, habilidades y actitudes adecuados, aspirando constantemente a mejorar en nuestro trabajo diario.\n10. Trabajo en equipo. Integraremos todo nuestro esfuerzo y colaboración para el logro de los objetivos, normas y metas, compartiendo los valores y principios éticos mínimos.\n11. Responsabilidad. Todos nuestros actos serán realizados de acuerdo con la ley y de cumplimiento del deber para con la sociedad, en particular con las mujeres en todos los sentidos.\n12. Transparencia. Establecer los criterios y procedimientos institucionales que garanticen la transparencia, la protección de datos personales y el acceso a la información en posesión de los\nCentros, conforme a los principios y bases establecidos en la Constitución Política de los Estados\nUnidos Mexicanos y la Ley en la materia.\n2. VALORES\nCon el objeto de cumplir con la noble Misión de los Centros, las operadoras y los operadores adoptan como fundamentales para lograr con ellos la consecución de los objetivos los siguientes valores:\n1. Respeto: Actuar con equilibrio y consideración hacia los demás, otorgando un trato digno y cordial a las personas en general y a sus compañeras o compañeros de trabajo, superiores y subordinados, considerando sus derechos, propiciando el dialogo cortés y la aplicación armónica de instrumentos que conduzcan al entendimiento, a través de la eficacia y el interés público.\n2. Igualdad: Las y los servidores públicos deben prestar los servicios que se les han encomendado, a todos los miembros de la sociedad que tengan derecho a recibirlos sin importar su sexo, edad, raza, credo, religión o preferencia política o sexual, no debe permitir que influyan en su actuación circunstancias ajenas que propicien el incumpliendo de la responsabilidad que tiene, para brindar a quien le corresponde los servicios públicos a su cargo.\n3. No Discriminación: Es el respeto a los derechos y libertades de las personas sin importar su origen, nacionalidad, color de piel, sexo, genero, edad, discapacidad, condición social, económica, de salud o jurídica, religión, apariencia física, características genéticas, situación migratoria, embarazo, lengua, opiniones, preferencias sexuales, identidad, filiación política, estado civil, situación familiar, idioma, antecedentes penales o cualquier otro motivo.\n4. Respeto a los Derechos Humanos: Respetar los derechos de toda persona y principalmente los de las mujeres con quien tengan relación por razón de su cargo público, así como de proteger y garantizar los derechos humanos de conformidad con los principios de universalidad, interdependencia, indivisibilidad y progresividad.\n5. Igualdad de Género: Promover y proteger que tanto mujeres como hombres accedan a las mismas condiciones, posibilidades y oportunidades a los bienes y servicios públicos.\n6. Compromiso: Trabajar con entusiasmo, disciplina, tenacidad, visión estratégica y orientación a resultados.\n7. Flexibilidad: Modificar criterios y prácticas ante la crítica y la autocrítica constructivas, para responder dinámicamente a los desafíos de una sociedad cambiante.\n8. Cooperación: Las y los operadores deben colaborar entre sí y propiciar el trabajo en equipo para alcanzar los objetivos comunes previstos en los planes y programas gubernamentales, generando víctimas de violencia de género.\n9. Integridad: En el desarrollo de sus actividades las y los operadores que conforman los Centros deberán actuar con la máxima rectitud posible, sin pretender obtener con base en el cargo, empleo o comisión que desempeñan ventaja o provecho alguno, para sí o para terceros.\nAsimismo, deberán abstenerse de aceptar o buscar prestaciones o compensaciones provenientes de cualquier persona, evitando de esta manera la realización de conductas que pudieran poner en duda su integridad o disposición para el cumplimiento de los deberes propios del cargo.\n10. Transparencia: Promover el libre acceso a la información pública gubernamental, con información clara, oportuna y veraz, de tal forma que las responsabilidades, procedimientos y reglas establecidas estén abiertas a la participación y escrutinio público, sin más límites que los que el mismo interés público y las leyes establezcan, impidiendo la sustracción, destrucción, ocultamiento o utilización indebida de la misma.\n11. Rendición de Cuentas: Las y los operadores de los Centros rendirán cuentas claras de sus acciones. Utilizarán los recursos públicos únicamente para cumplir la misión institucional, adoptando criterios de racionalidad, asignándolos de manera transparente e imparcial.\nEl personal que integra los Centros deberá proteger y conservar los bienes que se le asignen, utilizando los que le fueran asignados para el desempeño de sus funciones de manera racional, evitando su abuso, derroche o desaprovechamiento; utilizarlos exclusivamente para los fines a que estén afectos, sin que pueda emplearlos o permitir que otros lo hagan para fines particulares o propósitos que no sean aquellos para los que hubieran sido específicamente destinados.\nEn ningún caso, las y los operadores deberán usar su cargo público para transgredir las leyes o para afectar los intereses de la sociedad, de los Centros y de quienes en ellos laboran o para obtener un beneficio personal.\nCAPÍTULO III\nDECÁLOGO DE CONDUCTAS\n1. CONOCIMIENTO Y APLICACIÓN DEL MARCO JURÍDICO.\n1. Compromisos:\n1.1 Es obligación del personal conocer, observar y aplicar correctamente el marco normativo y los protocolos de actuación que rige a los Centros, así como a la unidad administrativa a la que se encuentre adscrito de conformidad a su empleo, cargo o comisión.\n1.2 Las y los Operadores deberán mostrar siempre una actitud de interés y diligencia para conocer las leyes, reglamentos y demás normatividad aplicable a su función.\n1.3 Documentarse en temas relativos con perspectiva de género, violencia de género, derechos humanos de las mujeres y todos aquellos que contribuyan en mejorar la calidad de su encargo.\n1.4 Organizarse para encontrar el tiempo necesario para familiarizarse con el marco jurídico de manera autodidacta, atendiendo a su vez los cursos de capacitación que correspondan, siempre que cuenten con la autorización de su superior jerárquico.\nresponsabilidad administrativa, por lo que el personal sustantivo de los Centros se debe caracterizar por conocimiento en derechos humanos, violencia de género y perspectiva de género.\n2. Abstenciones:\n2.1 Aplicar indebidamente las disposiciones legales, normativas y protocolos de actuación.\n2.2 Las y los operadores no deberán interpretar la normatividad buscando un beneficio personal o familiar, o para beneficiar o perjudicar a un tercero, conduciéndose con imparcialidad y objetividad, en todo tiempo.\n2.3 Permitir la aplicación de normas y procedimientos que propicien acciones discrecionales y que además afecten el desempeño de las áreas de los Centros.\n2. USO DEL CARGO PÚBLICO.\n1. Compromisos:\n1.1 Las y los operadores de los Centros, deberán desempeñar su cargo con honradez, probidad e imparcialidad, evitando abusar del mismo para obtener beneficios personales a favor de tercera persona; procurar o conseguir privilegios de cualquier tipo, entre ellos, los económicos, profesionales o de influencia; ordenar, realizar o solicitar favores de cualquier índole para perjudicar a cualquier persona, así como hacer uso de su nivel, instancia o jerarquía para imponer doctrinas, ideologías o creencias políticas, religiosas o culturales, ya que constituyen faltas graves a este compromiso.\n1.2 Cumplir responsablemente las labores cotidianas, así como coadyuvar en la obtención de las metas y objetivos del área, a que se encuentre asignada o asignado, y por ende, contribuir al logro de la misión y visión de los Centros.\n1.3 Mantener un ambiente de respeto y colaboración en donde la actitud de servicio sea constante.\n1.4 Cumplir con los horarios establecidos, asistiendo puntualmente a las jornadas laborales, reuniones, eventos y demás compromisos institucionales.\n1.5 Ser ejemplo de colaboración y de unidad, fomentando el trabajo en equipo, tratando con respeto y sin hacer distinciones entre los demás servidoras o servidores públicos.\n1.6 Fomentar el incremento de la productividad del área de adscripción, desarrollando los procesos que contribuyan a fortalecer la eficiencia, eficacia y la imagen institucional de los Centros.\n1.7 Establecer los controles internos necesarios para atender en tiempo y forma los asuntos de competencia.\n1.8 Mantener con orden y limpieza el área de trabajo, preocupándose porque esté despejada de obstáculos que puedan ocasionar accidentes o que dificulten el tránsito de personas alrededor, así trabajo, mostrando preocupación por evitar su deterioro, y prestando especial atención a las áreas de uso común, como pueden ser sanitarios o sala de espera.\nLas y los operadores de los Centros durante sus funciones, deberán utilizar el uniforme del área que corresponda con el simbolismo de CJM.\n2. Abstenciones:\n2.1 Identificarse con cargo distinto y acreditarse con títulos o grados académicos, cuando no se disposiciones aplicables en la materia.\n2.2 Influir en decisiones de otras u otros servidores públicos, para lograr un beneficio personal, familiar o para terceros.\n2.3 Solicitar u obligar a las o los compañeros para favorecer o perjudicar a algún partido político, utilizando recursos públicos (financieros, materiales o humanos).\n2.4 Realizar al interior de los Centros compra o venta de cualquier tipo de mercancía, ni participar o propiciar tandas, rifas y sorteos que los distraigan de las labores encomendadas.\n2.5 Presentarse a laborar bajo los efectos del alcohol o cualquier otra sustancia indebida o no permitida.\n2.6 Falta de disposición, desidia y en general la apatía ante la importancia del orden y la limpieza, así como aquellas acciones que conlleven el abandono, maltrato, o desvalorización tanto de los bienes muebles e inmuebles, e incluso la desvalorización de la imagen personal.\n2.7 Realizar cualquier conducta ilícita o contraria a lo establecido en las leyes de la materia.\n3. UTILIZACIÓN Y MANEJO TRANSPARENTE DE LA INFORMACIÓN.\n1. Compromisos:\n1.1 Resguardar y mantener en confidencialidad toda la información, que por razón de su empleo, cargo o comisión tengan conocimiento, especialmente tratándose del manejo de datos personales o estrictamente relacionados con la intimidad y la seguridad de las personas, salvo en aquellos casos en que se determine que la misma sea de interés público, de conformidad con lo establecido en la legislación que en materia de transparencia y acceso a la información pública resulte aplicable o lo que ordene la autoridad competente.\n1.2 Actuar con imparcialidad y dedicación en la elaboración, preparación e integración de la información interna.\n1.3 Garantizar la organización y conservación de los documentos y archivos a su cargo, con el objeto de facilitar el ejercicio del derecho de acceso a la información; evitando la sustracción, destrucción, ocultamiento o la utilización indebida de la misma.\n1.4 Efectuar con diligencia y cuando corresponda los actos relativos a la entrega-recepción de los recursos que se tengan asignados.\n1.5 Mantener actualizada la información relativa a trámites y servicios, proporcionándola a los usuarios de manera oportuna.\n1.6 Entregar a los superiores los documentos, expedientes, fondos, valores o bienes cuya atención separación temporal o definitiva.\n1.7 Actuar con confidencialidad, imparcialidad y cuidado en la elaboración y manejo de información interna, así como en la atención de las solicitudes hechas en el marco legal correspondiente que garantice la transparencia.\n1.8 En su caso, generar información clara, veraz, oportuna y confiable en el ejercicio de sus funciones.\n2. Abstenciones:\n2.1 Difundir, entorpecer, detener, obstaculizar registros y demás información interna con el fin de obtener beneficios personales de cualquier índole.\n2.2 Utilizar con fines distintos los documentos elaborados internamente.\n2.3 Colocar carteles, fotos u otro tipo de información en tableros y cualquier sitio a la vista sin la autorización del uso de la imagen correspondiente de los Centros.\n2.4 Utilizar la información o el puesto asignado como medio de presunción, posicionamiento social o para obtener algún beneficio personal.\n2.5 Sustraer, destruir, ocultar o utilizar de manera indebida la información que conozca con motivo de sus actividades diarias de los Centros.\n4. TOMA DE DECISIONES Y CONFLICTO DE INTERESES.\n1. Compromisos:\n1.1 Evitar encontrarse en situaciones en la que el interés personal pueda entrar en conflicto con los intereses de los Centros, por lo tanto, todas las decisiones que tomen las y los operadores deberán estar apegadas al orden jurídico.\n1.2 Tomar decisiones basadas en la honestidad, congruencia, transparencia, justicia e igualdad, sin hacer distinción de ningún tipo por motivos personales y anteponiendo siempre el interés público a los intereses particulares.\n1.3 Evitar intervenir con motivo de su empleo, cargo o comisión en cualquier asunto en el que exista conflicto de interés, informando de inmediato a su superior jerárquico acerca de los asuntos para que sea relevado.\n1.4 Cumplir y obedecer órdenes e instrucciones emitidas por quienes ejerzan autoridad jerárquica en cualquier grado, siempre que estén apegadas a derecho y coherentes con los principios y valores contenidos en el presente Código.\n1.5 Respetar y hacer respetar los ordenamientos jurídicos, al momento de tomar cualquier decisión, en el ejercicio de sus funciones.\n2. Abstenciones:\n2.1 Aprovecharse de los servicios contratados o proporcionados por los Centros de Justicia para las\nMujeres del Estado de Campeche.\n2.2 Aceptar regalos o estímulos de cualquier tipo que pretendan influir en las decisiones como servidor público de los Centros.\n2.3 Tomar decisiones, sin tener la facultad o autorización correspondiente.\n2.4 Conceder preferencias o privilegios a personas, empresas o institución alguna.\n2.5 Evadir responsabilidad en la toma de decisiones necesarias.\n2.6 Obstaculizar el flujo de los asuntos que se encuentren bajo su responsabilidad anteponiendo el interés personal.\n5. MANTENER UN CLIMA LABORAL RESPETUOSO Y COLABORATIVO.\n1. Compromisos:\n1.1 Conducirse con dignidad y respeto hacia sus compañeros de trabajo, promoviendo un trato amable y cordial con independencia del género, discapacidad, edad, religión, lugar de nacimiento o nivel jerárquico, evitando conductas y actitudes ofensivas, lenguaje soez, prepotente o abusivo.\n1.2 Identificar, repudiar y denunciar cualquier acto de hostigamiento laboral, entendido como violencia física o psicológica en el ejercicio de poder en una relación de subordinación, o bien, cuando no exista dicha jerarquía, en las expresiones verbales o físicas que se traduzcan en dicha violencia.\n1.3 Reconocer los méritos obtenidos de las o los operadores sin apropiarse de sus ideas o iniciativas y, en su caso, proporcionar la información, asesoría u orientación que requieran para la realización oportuna del trabajo bajo su responsabilidad, particularmente al personal de nuevo ingreso, con el objeto de contribuir con su buen desempeño.\n1.4 Observar una conducta honrada y respetuosa hacía las pertenencias de las y los compañeros de trabajo, sean de índole personal o bienes de la institución.\n1.5 Promover una comunicación efectiva, de manera clara, abierta, cordial, de fácil entendimiento y respetuosa, ya sea del tipo formal o informal, en relación con sus compañeras, compañeros y superiores.\n1.6 Fomentar la interacción y participación de personas ubicadas en diferentes niveles jerárquicos para la exposición de programas, proyectos e ideas que permitan conseguir objetivos comunes e institucionales.\n2. Abstenciones:\n2.1 Amenazar o tratar injustamente a cualquier persona haciendo ostentación del cargo, puesto o comisión dentro o fuera de la dependencia.\n2.2 Provocar conflictos con y entre compañeras o compañeros.\n2.3 Realizar actos que atenten contra la integridad física y emocional o la dignidad humana en los espacios laborales o cometer cualquier acto de violencia.\n2.4 Permitir prácticas abusivas y denigrantes entre las/ los compañeros de trabajo.\n2.5 Limitar o menoscabar la libre expresión de ideas o de pensamientos de las/ los compañeros.\n2.6 Retrasar innecesariamente las tareas asignadas o utilizar el tiempo de trabajo para atender asuntos que no se relacionen con el respectivo empleo, cargo o comisión.\n2.7 Evitar acciones que distraigan, molesten o perturben a las/los compañeros, absteniéndose de fumar, escuchar música con volumen alto, consumir alimentos en las oficinas, usar lenguaje ofensivo tendiente a humillar, el uso de estereotipos y efectuar operaciones de compraventa dentro de las instalaciones de los Centros.\n2.8 Propagar rumores o comentarios que puedan lesionar la integridad moral y la reputación de las o los compañeros, respetando la privacidad y los derechos de los servidores públicos.\n6. PROMOVER LA IGUALDAD Y NO DISCRIMINACIÓN POR MOTIVO DE GÉNERO Y\nRESPETAR EL DERECHO DE DIVERSIDAD SEXUAL.\n1. Compromisos:\n1.1 Fomentar en todo momento un ambiente laboral interno basado en el respeto mutuo, sin discriminación, distinción, exclusión, restricción o preferencia motivada por el origen étnico o nacional, el color de la piel, la cultura, el sexo, el género, la edad, las discapacidades, la condición social, económica, de salud o jurídica, la religión, la apariencia física, las características genéticas, la situación migratoria, el embarazo, el idioma, las opiniones, las preferencias sexuales, la identidad o filiación política, el estado civil, la situación familiar, las responsabilidades familiares, los antecedentes penales o cualquier otra característica o condición.\n1.2 Conducirse siempre conforme a la normatividad aplicable en materia de igualdad y no discriminación por motivo de género.\n1.3 Promover enfáticamente el uso de un lenguaje incluyente, con enfoque de género dentro de la\nInstitución, en todos sus ámbitos y niveles, con el objetivo de fomentar la igualdad sustantiva entre mujeres y hombres.\n1.4 Propiciar un clima laboral en el que se garantice la igualdad en el trato y en las oportunidades entre mujeres y hombres.\n1.5 Promover el respeto a los derechos humanos, así como garantizar el acceso a un entorno laboral libre de violencia.\n1.6 Promover la inclusión laboral, creando condiciones favorables para la participación de personas en situaciones de vulnerabilidad, sin discriminación y con igualdad de oportunidades en el acceso, permanencia, remuneración y ascenso.\n1.7 Conocer, respetar y difundir los derechos de las personas de la comunidad lésbico, gay, bisexual, transexual, transgénero, travesti e intersexual.\n2. Abstenciones:\n2.1 De realizar conductas no deseadas de naturaleza sexual en el lugar de trabajo, tales como acoso y hostigamiento sexual, especialmente tratándose de las mujeres que laboran en la Institución, que provocan que la persona que lo sufre se sienta ofendida, humillada y/o intimidada, las que además de resultar violatorias al presente Código, podrán ser motivo de sanciones administrativas y de tipo penal.\n2.2 De realizar conductas discriminatorias motivadas por género y preferencias sexuales que atente personas.\n7. RESPETO A LOS DERECHOS HUMANOS.\n1. Compromisos:\n1.1 Promover, respetar, garantizar y actuar con estricto apego a los derechos humanos reconocidos materia de derechos humanos de los que México sea parte.\n1.2 Brindar apoyo y asesoría a las víctimas u ofendidos del delito, así como brindar protección a sus bienes y derechos.\n1.3 Procurar la efectiva reparación del daño causado a las víctimas u ofendidos del delito.\n1.4 Prestar auxilio a las personas amenazadas por algún peligro con motivo de un hecho ilícito, implementando inmediatamente las medidas de protección necesarias.\n1.5 Velar por la integridad física de las o los detenidos, así como la debida observancia de los derechos humanos, consagrados a favor de todo inculpado en la Constitución Política de los Estados\nUnidos Mexicanos y en los Tratados Internacionales en materia de derechos humanos ratificados por México.\n1.6 Promover y respetar los principios que rigen el Sistema de Justicia Penal de corte acusatorio, así como coadyuvar en su debida implementación.\n1.7 Informar a la autoridad competente las violaciones a los derechos humanos de que se tenga conocimiento.\n2. Abstenciones:\n2.1 Abstenerse de interferir en el ejercicio de los derechos humanos de las personas o ponerlos en peligro ya sea por acción u omisión.\n2.2 Realizar o tolerar actos de tortura, tratos crueles, inhumanos o degradantes.\n2.3 Llevar a cabo acciones que impliquen actos de incomunicación de las personas detenidas.\n8. COMBATE A LA CORRUPCIÓN.\n1. Compromisos:\n1.1 Salvaguardar los intereses de la Institución y buscar siempre su beneficio actuando con honestidad, integridad y transparencia en la función pública.\n1.2 Anticipar, identificar, evitar y denunciar cualquier acto de corrupción, falta administrativa o uso inadecuado de los recursos.\n2. Abstenciones:\n2.1 Abusar del cargo para obtener beneficios personales de tipo económico, privilegios, favores de cualquier índole y/o perjudicar a terceros.\n2.2 Recibir dinero, comidas, bebidas, ropa, armas, favores o cualquier otra gratificación que resulte del desempeño de las funciones asignadas.\ncompensación a cambio de agilizar o autorizar algún trámite, o de otorgar información confidencial, reservada o sensible.\n2.4 Presentar documentación apócrifa con la finalidad de obtener un beneficio personal, toda vez que la realización de esta conducta es considerada como un delito.\n9. RELACIÓN CON LA CIUDADANÍA\n1. Compromisos:\n1.1 Otorgar un trato profesional, justo, imparcial, digno, humano, cordial y respetuoso, tanto entre compañeras o compañeros como hacia la ciudadanía en general.\n1.2 Atender con eficiencia y cortesía a las personas en sus trámites, servicios y solicitudes.\n2. Abstenciones:\n2.1 Brindar tratos prepotentes y humillantes.\n2.2 Utilizar la identificación, la papelería oficial o los símbolos de identidad institucional que se asignen a los servidores públicos, en forma indebida o para beneficio personal o familiar o para beneficiar o perjudicar a terceros.\n2.3 Realizar actos o conductas que puedan poner en peligro los derechos, bienes jurídicos o la integridad de los usuarios.\n2.4 Recibir y solicitar cualquier tipo de compensación, dádiva, obsequio o regalo durante el servicio.\n10. RELACIONES CON OTRAS DEPENDENCIAS DE LOS GOBIERNOS FEDERAL, ESTATAL Y\nMUNICIPAL.\n1. Compromisos:\n1.1 Brindar a otras dependencias y entidades gubernamentales el servicio, apoyo e información que requieran con oportunidad, imparcialidad y eficiencia, a través de los mecanismos y vías que exprofeso se establezcan para tales fines.\n1.2 Respetar el ámbito de competencia de las autoridades de los tres niveles de gobierno.\n1.3 Respetar los procedimientos administrativos y legales establecidos para la realización de trámites institucionales con otras dependencias y/o entidades.\n2. Abstenciones:\n2.1 Dilatar la atención de los requerimientos de alguna dependencia de los tres órdenes de gobierno.\n11. CAPACITACIÓN Y PROFESIONALIZACIÓN.\n1. Compromisos:\n1.1 Tomar cursos de capacitación para la actualización de los conocimientos a fin de realizar mejor las funciones encomendadas.\n1.2 Desarrollar al máximo las competencias, habilidades y capacidades como servidora o servidor público de los Centros.\n1.3 Propiciar el intercambio de conocimientos y aprovechar la experiencia de los integrantes que se han distinguido en el cumplimiento de su deber.\n1.4 Fomentar la participación del personal sobre el que se tenga una jerarquía inferior en los cursos de capacitación y profesionalización necesarios para el cumplimiento de los objetivos de los Centros, así mismo como para su crecimiento profesional.\n1.5 Respetar en todo momento el desarrollo profesional de las o los compañeros, sus aportaciones y sus propuestas.\n2. Abstenciones:\n2.1 Interrumpir, sin causa justificada, los cursos de capacitación en los que sea participe.\n2.2 Realizar acciones que demeriten los métodos, procedimientos y objetivos de los cursos de formación, actualización, especialización, alta dirección o promoción en los que participe, con el fin de lograr ventajas ilegales u objetivos incorrectos en detrimento del Servicio de Carrera de\nProcuración de Justicia.\n2.3 Realizar acciones u omisiones que perjudiquen el Servicio de Carrera de Procuración de Justicia.\n12. ADAPTACIÓN AL CAMBIO.\n1. Compromisos:\n1.1 Tener una actitud positiva ante los cambios que se generen dentro de la institución con motivo del empleo, cargo o comisión.\n1.2 Adaptarse a los cambios profundos que permitan brindar una capacidad de respuesta suficiente para atender las necesidades del personal, así como de la sociedad.\n1.3 Mantener abierta la disposición a aprender de las experiencias de otras personas para adecuarlas, en su caso, al contexto de las funciones que se realicen con la convicción de que siempre es posible mejorar.\n2. Abstenciones:\n2.1 Ignorar las propuestas de transformación y permanecer estático ante los procesos de cambios positivos que se presenten en la Fiscalía General del Estado.\n2.2 Anteponer la negativa a cualquier propuesta de cambio.\n13. USOS Y ASIGNACIÓN DE RECURSOS HUMANOS, MATERIALES, FINANCIEROS Y\nTECNOLÓGICOS.\n1. Compromisos:\n1.1 Usar o asignar los recursos humanos, materiales, financieros y tecnológicos propiedad de los\nCentros, únicamente para el cumplimiento de los objetivos de la misma.\n1.2 Realizar de manera oportuna, la comprobación de los recursos financieros que sean proporcionados, ya sea para cumplir una comisión oficial o para realizar alguna adquisición, de conformidad con la normatividad correspondiente.\n2. Abstenciones:\n2.1 Utilizar recursos humanos, materiales o financieros institucionales para fines distintos a los asignados.\n2.2 Realizar pagos indebidos a proveedores y empleados.\n2.3 Negar los servicios que requieran las diferentes áreas para el desempeño de la función que realizan.\n2.4 Utilizar el servicio de Internet para revisar páginas o sitios que sean inapropiados, tales como los pornográficos o para beneficiarse económicamente por una actividad distinta al trabajo.\n14. CUMPLIMIENTO AL CÓDIGO DE CONDUCTA.\nAnte el incumplimiento al presente Código de Conducta, al Código de Ética, o a las Reglas de\nIntegridad para el ejercicio de la función pública, los ciudadanos o servidores públicos de los Centros podrán acudir ante el Comité para presentar una delación.\nEn este caso, el Comité se conducirá de conformidad con lo dispuesto en el Protocolo que establece el Procedimiento de Recepción y Atención de Delaciones por Incumplimiento al Código de Ética, a\nCódigo de Conducta de los Centros.\nComité de Ética.\nTRANSITORIOS\nPRIMERO.- El presente Código de Conducta entrará en vigor al día siguiente de su suscripción.\nSEGUNDO.- El presente Código de Conducta, deberá publicarse en el Periódico Oficial del Estado y difundirse al interior de los Centros de Justicia para las Mujeres en el Estado de Campeche.\nTERCERO: Las circunstancias no previstas en este Acuerdo, serán resueltas oportunamente por el\nFiscal General del Estado.\nCUARTO: Se derogan todos los acuerdos, circulares, instructivos, bases, manuales de organización\nEstado de Campeche, en lo que se opongan al contenido del presente Acuerdo.\nQUINTO: Se instruye a los Vice Fiscales, Directores, Coordinadores, para que, en el ámbito de su competencia, instrumenten las medidas necesarias para el debido cumplimiento de lo establecido en este Acuerdo.\nSEXTO: El presente acuerdo deberá ser publicado en el Periódico Oficial del Estado de Campeche.\nDado en la Ciudad de San Francisco de Campeche, del Municipio y Estado de Campeche, el 11 de\nCampeche. Rúbrica.-",
  "ordenamiento": "ACUERDO",
  "jurisdiccion": "CAMPECHE",
  "fuente_oficial": "DIARIO OFICIAL DE LA FEDERACION",
  "Fecha de Publicación": "18 de \njunio de 2008",
  "es_escaneado": false,
  "tiene_tablas": true,
  "materia": [
    "penal",
    "género",
    "ética"
  ]
}