{
  "titulo": "Eglamento INTERIOR DE LA SECRETARÍA DE LA CONTRALORÍA DE LA ADMINISTRACIÓN PÚBLICA DEL ESTADO DE CAM",
  "Contenido": "EGLAMENTO INTERIOR DE LA SECRETARÍA DE LA\nCONTRALORÍA DE LA ADMINISTRACIÓN PÚBLICA DEL\nESTADO DE CAMPECHE\nLIC. RAFAEL ALEJANDRO MORENO CÁRDENAS, Gobernador del Estado de Campeche, en ejercicio de la facultad que me confiere el artículo 71, fracción XIX de la Constitución propia Constitución; 3, 8, 10, 12, 14, 15, 16 fracción IV, y 24 de la Ley Orgánica de la\nAdministración Pública del Estado de Campeche, y:\nCONSIDERANDO:\npara el despacho de los asuntos que correspondan al Gobernador del Estado existirán las\nSecretarías de los ramos de Administración Pública y el número de dependencias que establezca la Ley Orgánica relativa, misma que distribuirá las funciones que a cada una deba corresponder y señalará los requisitos que el Gobernador observará para nombrar a los\nTitulares de estas.\nQue con fundamento en el artículo antes señalado, el día 13 de julio de 2017 se publicó el decreto número 189 en el Periódico Oficial del Estado el cual contiene las modificaciones a la\nLey Orgánica de la Administración Pública del Estado de Campeche; dicho decreto entró en vigor el día 19 de julio del año 2017, de conformidad con su Artículo Transitorio Primero.\nQue en la fracción IV del artículo 16 de la Ley Orgánica de la Administración Pública del Estado de Campeche, se consideró a la Secretaría de la Contraloría como una Dependencia de la\nAdministración Pública Centralizada, estableciéndose sus atribuciones en el artículo 24 de la citada Ley.\nconsecuencia de las modificaciones.\nPública del Estado de Campeche, y una vez analizada la estructura orgánica actual de la reformar el reglamento interior con el objeto de redistribuir las unidades administrativas.\ny para implementar acciones permanentes que favorezcan su comportamiento ético, a través de los Comités de Ética y de Prevención de Conflicto de Interés, con el propósito de promover acciones para mejorar la gestión gubernamental, fortalecer la transparencia, prevenir y erradicar la corrupción.\nQue el numeral 3 de los Lineamientos Generales para propiciar la integridad de los servidores a través de los Comités de Ética y de Prevención de Conflicto de Interés, indica que la\nPrevención de Conflicto de Interés.\nQue en virtud de lo anterior, se determinó la necesidad de crear una nueva unidad administrativa que tenga por objeto la evaluación de la integración de los Comités de Ética y de Prevención de Conflicto de Interés de las dependencias y entidades, así como la consistencia entre los Códigos de Conducta y los principios y valores del Código de Ética y las Reglas de Integridad; por ello, se establece dentro de la estructura de este Reglamento\nInterior de la Secretaría de la Contraloría, la Unidad Especializada en Ética y Prevención de\nConflicto de Interés.\nQue la Unidad Especializada en Ética y Prevención de Conflicto de Interés se suma a la estructura orgánica de esta Secretaría, con la finalidad de fungir como vínculo entre la\nSecretaría de la Contraloría y cada Comités de Ética y de Prevención de Conflicto de Interés de las dependencias y entidades de la Administración Pública Estatal para la capacitación, asesoría y consulta, así como también para evaluar las acciones que realicen las dependencias y las entidades en materia de ética, integridad y prevención de Conflicto de\nInterés.\nQue en congruencia con las reformas constitucionales en materia de combate a la corrupción, publicadas con fecha 27 de mayo de 2015 en el Diario Oficial de la Federación, de las cuales derivan las obligaciones de las entidades federativas para diseñar, crear y construir estructuras, normas, procesos y políticas públicas que minimicen los riesgos de corrupción y hagan posible su identificación y administración; nace la necesidad de crear una unidad interinstitucional y, además, que cuente con la participación de la ciudadanía mediante cuentas.\nQue teniendo en consideración lo anterior, es de suma importancia incluir una Unidad de\nPrevención a la Corrupción y, en consecuencia, es menester realizar las adecuaciones al\nReglamento Interior de esta Secretaría, determinando las facultades específicas que le permitan establecer, coordinar y ejecutar acciones de prevención y medición de los actos de corrupción, en el marco del nuevo modelo de combate a este fenómeno.\nQue, por otra parte, resulta de vital importancia la transversalización de la perspectiva de sus áreas de trabajo. Es por ello, que se requiere establecer mecanismos de acción, que de acuerdo con sus capacidades y no a su sexo o género.\nQue en materia de igualdad de género, México ha avanzado notablemente y hoy existen diversos compromisos internacionales como la Convención sobre la Eliminación de todas las formas de Discriminación Contra la Mujer (CEDAW, 1979); la Convención Interamericana para\nPrevenir, Sancionar y Erradicar la Violencia contra la Mujer “Convención de Belem Do Para”;\nPacto Internacional de Derechos Económicos, Sociales y Culturales, ONU, 1966; Convenio 111 sobre la discriminación (empleo y ocupación), OIT, 1958; la Declaración Universal de los\nDerechos Humanos (ONU, 1948); y los Resolutivos y recomendaciones derivados de las cuatro Conferencias Internacionales sobre la Mujer: México 1975; Copenhague 1980; Nairobi 1985 y Beijing 1995.\nQue en el marco jurídico nacional existen diversos ordenamientos que resguardan la igualdad de género, tales como la Constitución Política de los Estados Unidos Mexicanos; la Ley\nFederal para Prevenir y Eliminar la Discriminación, la Ley General para la Igualdad entre\nMujeres y Hombres, la Ley de Acceso a las Mujeres a una Vida Libre de Violencia del Estado de Campeche y la Ley de Igualdad entre Mujeres y Hombres del Estado de Campeche.\nsustantiva en los ámbitos público y privado promoviendo el empoderamiento de las mujeres, la Política Nacional en Materia de Igualdad entre Mujeres y Hombres, y que de modo particular establece en los artículos 7, 9, 12, 14, 15, 20, 21, 23 y 24, la generación de instancias entidades, con alto nivel en la toma de decisiones.\nQue el Plan Estatal de Desarrollo 2015-2021, contempla el Eje Transversal denominado\nPerspectiva de Género, que establece en su apartado 6.6.1 “Lograr que las Acciones del\nGobierno contribuyan a la Equidad entre hombres y mujeres”, mediante el cual, por medio de las Líneas de Acción 6.6.1.1.2 y 6.6.1.2.4, se busca institucionalizar las políticas de equidad de género y propiciar la igualdad de oportunidades entre hombres y mujeres, en todos los ámbitos de la actuación del gobierno; y fomentar la no discriminación por género en la actuación del servicio público estatal y municipal.\nQue en éste sentido el artículo 8 fracción XXIV de la Ley del Instituto de la Mujer del Estado de Campeche, señala que esta institución debe promover dentro de los órganos de gobierno la creación de Unidades de Igualdad de Género, las cuales se implementan a través del\nProyecto “Fortalecimiento Normativa y de Capacidades Institucionales para Incorporar la\nPerspectiva de Género en las acciones de la Administración Pública del Estado de Campeche\n2017”.\nQue toda vez que reducir las brechas de género es un compromiso del Estado Mexicano y del\nGobierno del Estado a través de la Conferencia Nacional de Gobernadores (CONAGO), el cual tiene como propósito el de prevenir, sancionar y erradicar la violencia de género contra las Mujeres, se determinó la necesidad de crear una nueva unidad administrativa que tenga por objeto crear una cultura política de reconocimiento y respeto a la diversidad, en donde el género no implique desigualdad de oportunidades, que garantice la participación de mujeres y hombres en condiciones de igualdad en todos los campos de servicio público; por lo cual, motivado en lo anteriormente expuesto, se establece dentro de la estructura de la Secretaría de la Contraloría la Unidad de Igualdad de Género.\nQue en cumplimiento de las acciones a implementar, se determinó que la Unidad de\nTecnologías de la Información y Estadística, la cual se desprenderá como unidad de apoyo de la Oficina de la/del Titular y pase a formar parte de la estructura orgánica de la Coordinación\nAdministrativa, lo anterior con la finalidad de dar una atención oportuna a las necesidades\nEstado de Campeche.\nsiguiente:\nADMINISTRACIÓN PÚBLICA DEL ESTADO DE CAMPECHE.\nCAPÍTULO I\nDE LA COMPETENCIA Y ORGANIZACIÓN\nArtículo 1.- El presente Reglamento tiene por objeto definir las atribuciones y competencias de la Secretaría de la Contraloría y de las unidades administrativas que la integran.\nArtículo 2.- La Secretaría de la Contraloría es una Dependencia de la Administración Pública\nEstatal centralizada que tiene a su cargo las funciones previstas en el artículo 24 de la Ley\nOrgánica de la Administración Pública del Estado de Campeche; así como las demás atribuciones que le confieren las leyes generales y locales vigentes, los reglamentos, decretos, acuerdos, circulares y órdenes del Gobernador del Estado.\nArtículo 3.- Al frente de la Secretaría de la Contraloría habrá una persona Titular de la misma, quien tendrá rango de Secretario/a de la Administración Pública Centralizada del Estado de\nCampeche en términos de los artículos 10, 12 y 16 fracción IV, de la Ley Orgánica de la\nAdministración Pública del Estado de Campeche, quien, para el despacho de los asuntos de su competencia, se auxiliará de las unidades administrativas siguientes:\nI. Oficina del Titular;\nII. Dirección General de Evaluación y Fortalecimiento Institucional;\nIII. Dirección General de Auditoría Gubernamental;\nIV. Dirección General de Contraloría Social;\nV. Dirección General de Asuntos Jurídicos;\nVI. Dirección General de Investigación Administrativa;\nVII. Coordinación General de Órganos Internos de Control, y\nVIII. Coordinación Administrativa.\nArtículo 4.- Para el despacho de los asuntos, la Secretaría de la Contraloría contará con la siguiente estructura administrativa:\nA. En la Oficina del Titular:\nI. La Coordinación Administrativa.\nSecretaría y que permita el presupuesto.\nB. En la Dirección General de Evaluación y Fortalecimiento Institucional;\nI. Las unidades administrativas que autorice el Titular de la dependencia y que permita el presupuesto.\nC. En la Dirección General de Auditoría Gubernamental;\nI. Las unidades administrativas que autorice el Titular de la dependencia y que permita el presupuesto.\nD. En la Dirección General de Contraloría Social;\nI. Las unidades administrativas que autorice el Titular de la dependencia y que permita el presupuesto.\nE. En la Dirección General de Asuntos Jurídicos;\nI. Las unidades administrativas que autorice el Titular de la dependencia y que permita el presupuesto.\nF. En la Dirección General de Investigación Administrativa;\nI. Las unidades administrativas que autorice el Titular de la dependencia y que permita el presupuesto.\nG. En la Coordinación General de Órganos Internos de Control;\nI. Las unidades administrativas que autorice el Titular de la dependencia y que permita el presupuesto.\nH. En la Coordinación Administrativa.\nI. Las unidades administrativas que autorice el Titular de la dependencia y que permita el presupuesto.\nPara el mejor desempeño de sus actividades, la Oficina del Titular contará con las siguientes unidades de apoyo: la Unidad de Transparencia, la Secretaría Particular, la Unidad de\nComunicación Social, la Unidad Coordinadora de Archivos, la Unidad Especializada en Ética y Prevención de Conflicto de Interés, la Unidad de Prevención a la Corrupción y la Unidad de\nIgualdad de Género, las cuales tendrán la estructura administrativa que requieran y que se encuentre autorizada en el presupuesto de la Secretaría.\nArtículo 5.- La Secretaría de la Contraloría contará también con las unidades administrativas subalternas que figuren en su presupuesto, cuyas funciones deberán especificarse y regularse en el manual de organización de la propia Secretaría.\nArtículo 6.- La Secretaría de la Contraloría, a través de sus unidades administrativas, planeará y conducirá sus actividades conforme a los objetivos, estrategias y programas establecidos en el marco jurídico vigente en el Estado, en el Sistema Estatal de Planeación, en el Plan Estatal de Desarrollo, así como de acuerdo con los mecanismos, bases y principios programas que determine el Gobernador del Estado.\nArtículo 7.- La Secretaría de la Contraloría contará con un Órgano Interno de Control, cuyo\nTitular y personal estará adscrito presupuestal y orgánicamente a la misma, por lo que\nTrabajo del Órgano Interno de Control a su cargo, y tendrá a su cargo el ejercicio de las facultades que le confiere la Ley General de Responsabilidades Administrativas, la Ley\nOrgánica de la Administración Pública del Estado de Campeche y las demás atribuciones que le señale el presente Reglamento.\nCAPÍTULO II\nDE LAS FACULTADES DEL TITULAR DE LA SECRETARÍA\nArtículo 8.- La representación de la Secretaría de la Contraloría y las facultades que las leyes le confieren corresponden originalmente al Secretario, y su delegación procede en razón de la distribución de competencias que disponen los ordenamientos legales, este Reglamento o por acuerdo del Titular.\nEn todo caso, la delegación surtirá efectos sin perjuicio del ejercicio directo por la persona\nTitular de la facultad respectiva, cuando éste lo considere conveniente.\nArtículo 9.- Al Titular de la Secretaría de la Contraloría corresponde el despacho de los siguientes asuntos:\nI. Autorizar la organización y funcionamiento de la Secretaría, así como aprobar los manuales de organización y procedimientos de trámites y servicios a la ciudadanía, relaciones interdepartamentales y manejo presupuestal de la dependencia;\nII. Intervenir en la materia que sea de su competencia en la elaboración del Plan Estatal de Desarrollo;\nIII. Aprobar y someter a la autorización del Gobernador del Estado, a través del Comité de Planeación para el Desarrollo del Estado de Campeche (COPLADECAM), los en su calidad de Dependencia Coordinadora de Sector y, en su caso, los Programas\nInstitucionales a cargo de la Entidades Paraestatales que correspondan;\nIV. Aprobar el Programa Operativo Anual para la ejecución de los Programas previstas, procurando su congruencia con los objetivos y prioridades de los planes\nV. Aprobar el Presupuesto de Egresos de la Secretaría atendiendo a los principios de racionalidad, austeridad y disciplina de Gasto Público, teniendo como base el Plan\nEstatal de Desarrollo y los Programas que de él se deriven, de conformidad con las conducto de la Secretaría de Finanzas y, en su calidad de ejecutores, serán responsables del ejercicio y aplicación de los recursos que les sean autorizados;\nVI. Organizar, supervisar y coordinar el Sistema Estatal de Control Interno y la\nEvaluación de la Gestión Gubernamental;\nVII. Representar al Gobernador del Estado, cuando éste así lo disponga, en los asuntos de la competencia de la Secretaría;\nVIII. Fijar y dirigir, previo acuerdo del Gobernador del Estado, la política de control y evaluación gubernamental, así como de la Secretaría;\nIX. Informar periódicamente al Gobernador del Estado sobre los asuntos de la competencia de la Secretaría e informarle sobre el desarrollo de las actividades y las modificaciones a la estructura orgánica de la dependencia, así como del desempeño de las comisiones y funciones que se le confieran;\nX. Proponer al Gobernador del Estado los anteproyectos de leyes, reglamentos, decretos, acuerdos y demás normatividad sobre los asuntos que son competencia de la Secretaría;\nXI. Someter a la consideración del Gobernador del Estado los manuales administrativos de la dependencia y, en su caso, expedirlos cuando sean aprobados por éste;\nXII. Ordenar el control, vigilancia y fiscalización, en el ámbito de sus atribuciones, de las políticas que fije el Gobernador del Estado, así como realizar su evaluación;\nXIII. Ordenar y autorizar la realización de auditorías a los recursos que ejerzan las dependencias y entidades de la Administración Pública Estatal, así como evaluar el resultado de acciones y programas a su cargo;\nXIV. Proponer al Gobernador del Estado el nombramiento y remoción de las personas\nGeneral; así como nombrar y remover a las y los Titulares de las demás unidades administrativas y al personal necesario para el desarrollo de sus funciones;\nXV. Conceder licencia a las personas Titulares de las unidades administrativas de la dependencia;\nXVI. Autorizar, específicamente a las unidades administrativas, el ejercicio del presupuesto de egresos conforme a las disposiciones aplicables, a las autorizaciones globales y al calendario que haya emitido la Secretaría de Finanzas;\nXVII. Aprobar los lineamientos, normas y políticas conforme a las cuales la Secretaría proporcionará los informes mediante solicitud previa, los datos y el apoyo técnico que le sean requeridos, en el ámbito de sus atribuciones;\nXVIII. Designar y remover, con las salvedades que establezcan las leyes respectivas, a dependencias y entidades de la Administración Pública Estatal, así como de las comisarías en las juntas de gobierno, vigilancia o sus homólogos en las entidades de la Administración Pública Paraestatal, los cuales le estarán presupuestal y orgánicamente adscritos a la Secretaría, tendrán el carácter de autoridad y administrativa y ante los Tribunales Estatales, o bien, representando al Titular de la\nSecretaría;\nXIX. Designar y remover para el mejor desarrollo del sistema de control y evaluación de la gestión gubernamental, delegados de la propia Secretaría ante las dependencias y órganos desconcentrados de la Administración Pública Estatal Centralizada y comisarías públicas de los órganos de vigilancia de las entidades de la\nAdministración Pública Paraestatal, así como normar y controlar su desempeño;\nXX. Designar y remover auditores externos en las dependencias de la Administración\nPública Estatal; en las entidades del sector paraestatal, y en todos aquellos organismos y entes que ejerzan recursos públicos, así como normar y controlar su desempeño;\nXXI. Acordar con los Titulares de las unidades administrativas la resolución de los asuntos que sean de su competencia;\nXXII. Informar anualmente al Gobernador del Estado sobre el resultado de las revisiones, fiscalizaciones y evaluaciones realizadas a las dependencias y entidades de la\nAdministración Pública Estatal;\nXXIII. Proporcionar la información sobre las actividades realizadas por la Secretaría para la formulación del informe anual de labores del Gobernador del Estado;\nXXIV. Comparecer ante el H. Congreso del Estado, tantas y cuantas veces sea requerido;\nXXV. Verificar que, en el ámbito de su competencia, se apliquen o ejecuten las sanciones que correspondan al servidor público estatal con motivo de los actos u omisiones disposiciones conducentes;\nXXVI. Designar al servidor público que represente a la Secretaría en las licitaciones que se celebren en materia de obras públicas y de adquisiciones, arrendamientos y prestación de servicios, de conformidad con la normatividad federal y estatal vigente;\nXXVII. Coordinarse con la Secretaría de la Función Pública, para el desempeño de las tareas de control de los recursos federales transferidos al Estado, y en general, de las que se deriven del Sistema Nacional de Control y Evaluación Gubernamental;\nXXVIII. Coordinarse con la Auditoría Superior del Estado para la unificación de criterios y compatibilización de mecanismos en materia de revisión y fiscalización;\nXXIX. Fungir como enlace ante las instancias de fiscalización en las revisiones que se realicen a las dependencias y entidades de la Administración Pública Estatal;\nXXX. Celebrar, dentro del ámbito de sus atribuciones, convenios de colaboración con las personas físicas o morales que participen en contrataciones públicas, cámaras empresariales u organizaciones industriales o de comercio;\nXXXI. Celebrar convenios con las distintas autoridades que tengan a su disposición datos, personas que pertenecen al servicio público estatal, así como solicitar información a las autoridades competentes en materia fiscal o relacionadas con operaciones de depósito, ahorro, administrativo o inversión de recursos monetarios;\nXXXII. Impulsar, en coordinación con la Secretaría de Finanzas, medidas para alcanzar mayor eficiencia y racionalidad en el ejercicio del gasto público;\nXXXIII. Expedir las normas que regulen los instrumentos y procedimientos de control interno de la Administración Pública del Estado, para lo cual podrá requerir de las dependencias y entidades competentes, la expedición de normas complementarias para el ejercicio del control administrativo; lo anterior, sin menoscabo de las bases y principios de coordinación y recomendaciones emitidas por el Comité Coordinador del Sistema Anticorrupción del Estado de Campeche y la ley relativa;\nXXXIV. Vigilar, en colaboración con las autoridades que integren el Comité Coordinador del\nSistema Anticorrupción del Estado de Campeche, el cumplimiento de las normas de control interno y fiscalización, así como asesorar y apoyar a los órganos internos de control de las dependencias y entidades de la Administración Pública del Estado;\nXXXV. Establecer las bases generales para la realización de auditorías internas, transversales y externas, así como expedir las normas que regulen los instrumentos y procedimientos en dichas materias en las dependencias y entidades de la\nAdministración Pública Estatal, y realizar las auditorías que se requieran en éstas, en sustitución o en apoyo a sus propios órganos internos de control;\nXXXVI. Colaborar, en el marco del Sistema Anticorrupción del Estado, en el establecimiento de las bases y principios de coordinación necesarios que permitan el mejor cumplimiento de las responsabilidades de sus integrantes;\nXXXVII. Informar periódicamente al Comité Coordinador del Sistema Anticorrupción del\nEstado y al Gobernador del Estado, sobre los resultados de la evaluación de gestión de las dependencias y entidades de la Administración Pública Estatal, así como del resultado de la revisión del ingreso, manejo, custodia y ejercicio de recursos públicos estatales, y promover ante las autoridades competentes, las acciones que procedan para corregir las irregularidades detectadas;\nXXXVIII. Conocer e investigar las conductas de los servidores públicos de la Administración\nPública del Estado que puedan constituir responsabilidades administrativas, así en la Legislación en la materia, por sí, o por conducto de los órganos internos de control que correspondan a cada área de la Administración Pública Estatal, para lo cual, podrán aplicar las sanciones que correspondan en los casos que no sean de la competencia del Tribunal de Justicia Administrativa del Estado de Campeche y, cuando se trate de faltas administrativas graves, ejercer la acción de responsabilidad ante ese Tribunal, así como presentar las denuncias aplicables;\nXXXIX. Formular y conducir en apego y de conformidad con las bases de coordinación que establezca el Comité Coordinador del Sistema Anticorrupción del Estado, la política general de la Administración Pública Estatal para establecer acciones que propicien la integridad y la máxima publicidad en la gestión gubernamental, la rendición de cuentas y el acceso por parte de las y los particulares a la información pública; así como promover dichas acciones hacia la sociedad;\nXL. Establecer y conducir, en coordinación con la Secretaría de Administración e\nInnovación Gubernamental, la política general de las contrataciones públicas, reguladas por la Ley de Adquisiciones, Arrendamientos y Prestación de Servicios\nRelacionados con Bienes Muebles del Estado de Campeche; la Ley de Obras\nPúblicas del Estado de Campeche; la Ley de Contratos de Colaboración Público\nPrivada para el Estado de Campeche y demás normatividad aplicable, propiciando las mejores condiciones de contratación conforme a los principios de eficiencia, eficacia, economía, transparencia, imparcialidad y honradez. Emitir las normas, lineamientos, manuales, procedimientos y demás Instrumentos análogos que se requieran en materia de dichas contrataciones públicas; proporcionar, en su caso, asesoría normativa con carácter preventivo en los procedimientos de contratación regulados por las mencionadas leyes que realicen las dependencias y entidades de la Administración Pública Estatal y promover, con la intervención que corresponda a otras dependencias de la Administración Pública Estatal, la coordinación y cooperación de los Poderes Ejecutivo, Legislativo y Judicial del Estado, los órganos constitucionales autónomos, los municipios y demás entes públicos encargados de regímenes de contratación pública, a efecto de propiciar en lo procedente la homologación de políticas, normativas y criterios en materia de contrataciones públicas, que permitan contar con un sistema de contrataciones públicas articulados a nivel estatal de contrataciones;\nXLI. Establecer y conducir en coordinación con la Secretaría de Administración e\nInnovación Gubernamental, la política de gobierno digital, gobierno abierto y datos\nEstatal;\nXLII. Implementar las políticas que promueva el Comité Coordinador del Sistema\nAdministración Estatal;\nXLIII. Emitir normas, lineamientos específicos y manuales que, dentro del ámbito de su competencia, integran disposiciones y criterios que impulsen la simplificación administrativa, para lo cual deberán tomar en consideración las bases y principios o el Comité Coordinador del Sistema Anticorrupción del Estado;\nXLIV. Seleccionar a los integrantes de los órganos internos de control, garantizando la igualdad de oportunidades en el acceso a la función pública, atrayendo a las y los mejores candidatos para ocupar los puestos, a través de procedimientos transparentes, objetivos y equitativos;\nXLV. Emitir el Código de Ética de los servidores públicos de las Dependencias y\nEntidades de la Administración Pública del Estado de Campeche y las reglas de integridad para el ejercicio de la función pública;\nXLVI. Implementar las acciones que acuerde el Sistema Anticorrupción del Estado, en términos de las disposiciones aplicables; y\nXLVII. Las demás que le otorgue el Gobernador del Estado y las que le confiera la\nCAPÍTULO III\nDE LAS ATRIBUCIONES GENÉRICAS DE LAS UNIDADES ADMINISTRATIVAS\nArtículo 10.- Al frente de cada unidad administrativa habrá un Titular que asumirá la responsabilidad de su funcionamiento ante las autoridades superiores y se auxiliará en el ejercicio de sus funciones por el personal técnico y administrativo que por las necesidades del servicio se requieran y que figuren en el presupuesto de egresos de la Secretaría.\nArtículo 11.- Las Unidades Administrativas tendrán las atribuciones genéricas siguientes:\nI. Planear, programar y presupuestar las actividades concernientes a su cargo, así como formular, ejecutar, controlar y evaluar los programas y presupuestos necesarios para el ejercicio de sus atribuciones;\nII. Acordar con el Secretario los asuntos y la ejecución de los programas que le sean encomendados;\nIII. Ejercer las funciones que se les deleguen, realizar los actos que les correspondan por suplencia y aquellos otros que les instruya el Secretario;\nIV. Formular los dictámenes, opiniones e informes que les sean solicitados por el Titular de la Secretaría, de aquellos asuntos que sean de su competencia;\nV. Proponer la suscripción de contratos y convenios relativos al ejercicio de sus atribuciones;\nVI. Coordinar y evaluar el funcionamiento de las unidades administrativas bajo su adscripción, e informar al Secretario de las actividades que éstas realicen;\nVII. Supervisar el cumplimiento de las políticas, normas, criterios, sistemas y procedimientos que deban regir en las unidades administrativas de su adscripción;\nVIII. Coordinar la elaboración del Programa Operativo Anual y del anteproyecto de supervisar su correcta y oportuna ejecución;\nIX. Participar en la formulación, ejecución, control y evaluación de los programas sectoriales de la Secretaría;\nX. Proponer al Secretario, en los casos procedentes, el nombramiento y remoción del personal a su cargo;\nXI. Acordar y gestionar con el Titular de la Secretaría los movimientos del personal bajo su adscripción en lo referente a altas, cambios de nivel, adscripciones, comisiones, permisos, sanciones, bajas, reingresos, licencias, vacaciones, expedición de nombramientos y similares, de conformidad a la normatividad vigente;\nXII. Proponer al Titular de la Secretaría, las acciones de modernización, desconcentración y simplificación administrativa que sean necesarias en las unidades administrativas de su adscripción;\nXIII. Suscribir los documentos relativos al ejercicio de sus atribuciones y aquellos que les sean señalados por delegación o les correspondan por suplencia;\nXIV. Formular el levantamiento de actas administrativas del personal a su cargo o de las unidades administrativas bajo su adscripción, cuando así se requiera, en términos de la Ley de los Trabajadores al Servicio del Gobierno del Estado de Campeche;\nXV. Expedir y aplicar las notas de méritos y sanciones a que se refieren las Condiciones\nGenerales del Trabajo del Poder Ejecutivo del Gobierno del Estado de Campeche;\nXVI. Coordinar y dirigir los proyectos de manuales de organización, manuales de procedimientos de trámites y servicios a la ciudadanía, manuales de relaciones interdepartamentales y de manejo presupuestal, memoria de gestión y todo informe adscripción;\nXVII. Proponer a su superior jerárquico los anteproyectos de leyes, reglamentos, decretos, acuerdos, circulares y órdenes sobre asuntos de su competencia;\nXVIII. Proporcionar la información y auxilio que les requieran las demás Unidades\nAdministrativas de la Secretaría para el desempeño de sus funciones;\nXIX. Representar a la Secretaría en los eventos o reuniones que por mandato expreso les encomiende el Titular e informarle los resultados de estos;\nXX. Recibir al personal de su unidad y al de las demás unidades administrativas, y conceder audiencias al público sobre los asuntos de su competencia, de conformidad con las políticas establecidas al respecto;\nXXI. Proporcionar la información o la cooperación que les sean requeridas por otras dependencias y entidades de la Administración Pública Estatal, en el ámbito de su competencia, previo acuerdo con el Secretario;\nXXII. Respetar las obligaciones señaladas en la Ley General de Responsabilidades\nAdministrativas;\nXXIII. Respetar y conducirse conforme al Código de Conducta y al Código de Ética de los del Estado de Campeche; y\nXXIV. Las demás que le atribuyan otras disposiciones legales y reglamentarias, así como las que le confiera el Titular.\nCAPÍTULO IV\nDE LAS ATRIBUCIONES ESPECÍFICAS DE LAS UNIDADES ADMINISTRATIVAS\nArtículo 12.- A la Dirección General de Evaluación y Fortalecimiento Institucional le competen las atribuciones siguientes:\nI. Coordinar las acciones encomendadas a la Secretaría para la instalación y funcionamiento del Comité Estratégico y Subcomité Sectorial que se establezcan dentro del Comité de Planeación para el Desarrollo del Estado de Campeche;\nII. Coordinar y dar seguimiento a las evaluaciones que realicen las dependencias y entidades de la Administración Pública Estatal, que permita conocer los resultados de la aplicación de los recursos públicos;\nIII. Evaluar el cumplimiento de los objetivos y metas con base en indicadores estratégicos y de gestión que permitirán conocer los resultados de la aplicación de los recursos públicos derivado del Presupuesto Basado en Resultados y el Sistema de Evaluación del Desempeño de Campeche;\nIV. Establecer normas, lineamientos, criterios, guías y procedimientos que regulen los procesos de evaluación de programas de la Administración Pública Estatal, proceso interno;\nV. Elaborar en el ámbito de su competencia proyectos de normas, lineamientos y que corresponda a la Secretaría de Finanzas, así como emitir opiniones de los proyectos que en esa materia elabore la citada dependencia;\nVI. Efectuar la evaluación del ejercicio del Presupuesto de Egresos del Estado\nOperativo Anual Estatal;\nVII. Realizar evaluaciones a fideicomisos, dependencias y entidades de la en el cumplimiento de sus funciones y atribuciones;\nVIII. Concertar y coordinar con la Secretaría de la Función Pública la Revisión de\nPública Estatal y en su caso, los HH. Ayuntamientos de los Municipios del Estado, ejerzan con recursos federales en el marco de los acuerdos y convenios vigentes;\nIX. Coordinar la formulación y entrega del informe anual de actividades realizadas por la Secretaría para la elaboración del Informe Anual de Gobierno y, con la participación de las dependencias coordinadoras de los subcomités sectoriales, integrar y enviar el informe correspondiente del Eje Estratégico correspondiente;\nX. Coordinar la integración del Programa Estratégico Institucional con la participación de las Unidades Administrativas de la Secretaría, verificando que los programas y acciones estén alineados al Plan Estatal de Desarrollo y de los programas sectorial, institucional o especial; que las metas e indicadores contribuyan al logro de los objetivos estratégicos de la dependencia, y someterlo a la aprobación del o de la\nTitular;\nXI. Coordinar acciones con las dependencias y entidades de la Administración Pública\nEstatal que contribuyan al fortalecimiento institucional mediante acciones de coordinación con los poderes Legislativo y Judicial, y los HH. Ayuntamientos de los\nMunicipios del Estado;\nXII. Promover y ejecutar acciones que contribuyan a la mejora de los procesos de gestión pública estatal y brindar atención y servicios de calidad a la ciudadanía;\nXIII. Coordinar con la Secretaría de Finanzas la evaluación que permita conocer los resultados de la aplicación de los recursos públicos estatales;\nXIV. Concertar con las dependencias y entidades de la Administración Pública del los términos de las disposiciones aplicables; y\nXV. Las demás que le atribuyan otras disposiciones legales y reglamentarias, así como las que le confiera el Titular de la Secretaría.\nArtículo 13.- A la Dirección General de Auditoría Gubernamental le competen las atribuciones siguientes:\nI. Elaborar y someter a la aprobación del Titular de la Secretaría el Programa Anual\nGeneral de Supervisión, Fiscalización y Vigilancia de la Administración Pública\nEstatal Centralizada y Paraestatal y, cuando legalmente proceda, a los HH.\nacuerdos y convenios respectivos;\nII. Fiscalizar la correcta aplicación de los recursos autorizados para ejercer dentro del instrumentos jurídicos celebrados por el Estado con la Federación y los Municipios;\nIII. Establecer la normatividad para la realización de auditorías a la Administración\nPública Estatal Centralizada y Paraestatal y, cuando legalmente proceda, a los HH.\nAyuntamientos de los Municipios del Estado;\nnormas y disposiciones en materia de sistemas de registro y contabilidad, contratación y remuneraciones de personal, contratación de adquisiciones, arrendamientos, arrendamiento financiero, servicios y ejecución de obra pública, conservación, uso, destino, afectación enajenación y baja de bienes muebles e inmuebles, almacenes y demás activos y recursos materiales de la Administración\nPública Estatal;\nV. Vigilar la debida aplicación de los recursos federales y estatales que ejerzan las dependencias y entidades de la Administración Pública Estatal y, en su caso, los que ejerzan los HH. Ayuntamientos conforme a lo estipulado en los acuerdos y convenios respectivos;\nVI. Verificar el cumplimiento de las disposiciones en materia de planeación, programación, adjudicación, contratación, ejecución, presupuesto, entrega de la obra pública, ingresos, financiamiento, inversión, deuda, patrimonio, fondos y valores de propiedad o bajo el resguardo del Estado;\nVII. Realizar, en el ámbito de su competencia, acciones de coordinación con la Auditoría\nSuperior del Estado para efectuar visitas, inspecciones, consultas y auditorías a la\nAdministración Pública Estatal Centralizada y Paraestatal y, cuando legalmente proceda, a los HH. Ayuntamientos de los Municipios del Estado;\nVIII. Emitir informes mensuales sobre el cumplimiento de los programas de auditoría a su cargo y enviarlos a la Dirección General de Evaluación y Fortalecimiento\nInstitucional para que se integren al informe anual de gobierno;\nIX. Elaborar los informes de auditoría que se remitan a la Secretaría de la Función\nPública de la Federación, conforme a lo estipulado en los acuerdos y convenios respectivos;\nX. Turnar a la Dirección General de Investigación Administrativa las observaciones aplicables, para proceder conforme a sus facultades;\nXI. Coordinar con la Secretaría de Finanzas la uniformidad de las normas, procedimientos y sistemas de registro contable, así como el adecuado control de\nParaestatal;\nXII. Realizar por sí, o a solicitud de la Secretaría de Finanzas o la coordinadora de sector correspondiente, auditorías, revisiones y evaluaciones a las dependencias y entidades de la Administración Pública del Estado, con el objeto de examinar, fiscalizar y promover la eficiencia y legalidad en su gestión y encargo;\nXIII. A petición expresa, brindar apoyo técnico en materia de fiscalización y verificación del gasto a las autoridades municipales;\nXIV. Formular las respectivas denuncias o querellas ante la Fiscalía Especializada en\nCombate a la Corrupción del Estado y ante otras autoridades competentes, en términos de la normatividad aplicable, y\nXV. Las demás que le atribuyan otras disposiciones legales y reglamentarias, así como las que le confiera el Titular de la Secretaría.\nArtículo 14.- A la Dirección General de Contraloría Social le competen las atribuciones siguientes:\nI. Promover la participación ciudadana en la vigilancia y control de las acciones y programas convenidos de las dependencias y entidades de la Administración\nPública Estatal y Federal;\nII. Difundir los programas de contraloría social entre los diversos sectores de la población mediante la instrumentación de diversos mecanismos de comunicación, estableciendo el diseño, elaboración y distribución de los materiales que para el caso se requieran;\nIII. Capacitar y proporcionar a las y los representantes comunitarios y beneficiarios de obras y acciones de gobierno, la información y asistencia técnica suficiente y necesaria para el establecimiento y consolidación de la contraloría social;\nIV. Capacitar y proporcionar a las personas que pertenecen al servicio público de la administración estatal información en materia de contraloría social;\nV. Impartir platicas de inducción de valores y acciones, relativos a la contraloría social dirigidas al público en general de todas las edades;\nVI. Dar seguimiento a los resultados que deriven de la práctica de la contraloría social privilegien la corresponsabilidad ciudadana;\nVII. Coordinar el diseño y aplicación de programas específicos tendientes a prevenir\nVIII. Participar en los órganos de análisis, deliberación y decisión de políticas y programas de bienestar social, federales, estatales y municipales conforme a las disposiciones reglamentarias de dichos órganos;\nIX. Establecer acciones de coordinación con los HH. Ayuntamientos de los Municipios del Estado, para la implementación y mejora de la contraloría social en sus ámbitos de acción respectivos;\nX. Fomentar la participación organizada de la sociedad civil en actividades relacionadas con los procesos de contraloría social;\nXI. Promover y ejecutar acciones que contribuyan a mejorar los procesos de gestión pública estatal, y brindar atención y servicios de calidad a la ciudadanía; y\nXII. Las demás que le atribuyan otras disposiciones legales y reglamentarias, así como las que le confiera el Titular de la Secretaría.\nArtículo 15.- La Dirección General de Asuntos Jurídicos tendrá las atribuciones siguientes:\nI. Atender, dirigir y supervisar los asuntos jurídicos de la Secretaría y proponer al Titular los cambios que resulten adecuados en la normatividad interna de la dependencia;\nII. Fungir como órgano de consulta, asesoría, apoyo y asistencia jurídica en las materias de su competencia para todas las unidades administrativas y al personal adscrito a la\nSecretaría en los asuntos que deriven del ejercicio de sus atribuciones; así como procurar la unificación de criterios en la aplicación de normas y el cumplimiento de las formalidades previstas en los procedimientos administrativos;\nIII. Formular los anteproyectos de leyes, reglamentos, decretos, acuerdos, órdenes y demás disposiciones normativas que correspondan o sean materias de competencia de la Secretaría que el Titular o, en su caso, el Gobernador del Estado propongan;\nIV. Coadyuvar con otras dependencias o entidades de la Administración Pública Estatal en la formulación y revisión de anteproyectos de leyes, reglamentos y decretos que corresponda refrendar al Titular, o en aquellos casos en que deba intervenir la\nSecretaría;\nV. Elaborar los documentos jurídicos, convenios y contratos que resulten necesarios para el ejercicio de las atribuciones de la Secretaría o, en su caso, revisar y emitir opinión sobre los proyectos ya elaborados y de aquellos que ya se encuentren en ejecución;\nVI. Compilar, ordenar y actualizar el acervo legal de la dependencia, incluyendo las leyes, decretos, reglamentos, contratos, acuerdos, convenios, circulares y demás disposiciones vigentes relacionadas con sus atribuciones y funciones, e informar a las del Estado, relacionadas con las atribuciones de su competencia;\nVII. Auxiliar a las unidades administrativas de la Secretaría en la elaboración de los\nManuales de Organización, de Estructuras y de Procedimientos, y vigilar que éstos se apeguen a la legislación, reglamentación y demás normatividad vigente y, ordenar, en su caso, su corrección o ajuste;\nadministrativas de la Secretaría, con todas las facultades generales y las especiales que requieran cláusula especial conforme a la legislación que resulte aplicable, ante los órganos administrativos o jurisdiccionales competentes federales y estatales, en toda clase de juicios, procedimientos, investigaciones y cualquier otra controversia en que aquella sea parte. Así mismo, ejercitar las acciones, excepciones y defensas que correspondan, actuando en todas las instancias del juicio, procedimiento o recurso de que se trate hasta su total conclusión y, en su caso, interponer los medios de de las resoluciones dictadas en los juicios, procedimientos y controversias en los que la Secretaría sea parte;\nIX. Ser el enlace en los asuntos jurídicos de la Secretaría con otras áreas y dependencias de la Administración Pública Estatal;\nX. Levantar las actas administrativas y otros documentos similares que correspondan con respecto al desempeño de las funciones del personal a su cargo y remitirlas a la\nCoordinación Administrativa conforme a la normatividad aplicable;\nXI. Expedir certificaciones de documentos y expedientes que obren en los archivos de trámite de todas las unidades administrativas de la Secretaría, en estricto apego a las disposiciones en materia de transparencia y protección de datos personales y la procedencia de la certificación;\nXII. Participar en la Comisión de Estudios Jurídicos del Poder Ejecutivo del Estado que preside la Consejería Jurídica de la Administración Pública Estatal;\nXIII. Conocer la presunta responsabilidad administrativa de las personas que pertenecen al servicio público e instruir, en su caso, el correspondiente procedimiento administrativo disciplinario para el deslinde de responsabilidades previsto en la Ley\nGeneral de Responsabilidades Administrativas;\nXIV. Llevar un registro de los todos los procedimientos administrativos disciplinarios instruidos y de las sanciones impuestas;\nXV. Llevar y mantener actualizado un concentrado de la información de datos más importantes para los registros de las licitaciones convocadas por la Administración\nPública Estatal, además de realizar el control y seguimiento de incidencias con motivo de procesos licitatorios en materia de Obras Públicas, Adquisiciones, Arrendamientos, y Prestación de Servicios que se lleven a cabo en el Estado;\nXVI. Asesorar jurídicamente a las Unidades Administrativas y demás áreas de la Secretaría, actuar como órgano de consulta y fijar, sistematizar y difundir los criterios de funcionamiento de esta;\nXVII. Coordinar la instrumentación y el cumplimiento de los convenios, acuerdos y otros vigilancia y control de la aplicación de los recursos federales y estatales convenidos;\nXVIII. Participar en los actos de entrega-recepción de las personas que pertenecen al servicio público de las dependencias y entidades de la Administración Pública Estatal;\nXIX. Vigilar los actos de afectación y de baja de bienes muebles e inmuebles propiedad del\nEstado;\nXX. Resguardar y operar el Padrón de Servidores Públicos Inhabilitados, y expedir las constancias de No Inhabilitación a la ciudadanía solicitante;\nXXI. Resguardar y operar el Registro Estatal de Contratistas en el Ramo de Obras Públicas y Servicios Relacionados con las mismas, y expedir la Cédula de Registro Estatal de\nContratistas a la ciudadanía solicitante;\nXXII. Aplicar las medidas de apremio de acuerdo con lo estipulado en la Ley General de\nResponsabilidades Administrativas, y en caso de incumplimiento dar vista a la autoridad penal competente para que proceda en los términos de la legislación aplicable;\nXXIII. Decretar las medidas cautelares previstas en la Ley General de Responsabilidades\nAdministrativas cuando lo solicite la autoridad investigadora;\nXXIV. Llevar a cabo, por su titular o personal adscrito a la Dirección, las notificaciones que deriven de la instauración del procedimiento administrativo disciplinario en los términos que establece la Ley General de Responsabilidades Administrativas;\nXXV. Integrar los expedientes conforme a lo establecido en la Ley General de\nResponsabilidades Administrativas;\nXXVI. Recepcionar, llevar y normar el registro de las declaraciones de situación patrimonial y de intereses, y constancia de presentación de declaración fiscal de las personas que pertenecen al servicio público de la Administración Pública Estatal, así como verificar su contenido mediante las investigaciones que resulten pertinentes de acuerdo con las disposiciones aplicables; y, en su caso, registrar la información sobre las sanciones administrativas que, en su caso, les haya sido impuesta;\nXXVII. Inscribir y mantener actualizada en el sistema de evolución patrimonial, de declaración de intereses y constancia de presentación de declaración fiscal, la información correspondiente a los declarantes a su cargo;\nXXVIII. Solicitar a las personas que pertenecen al servicio público en el ámbito de su competencia, una copia de la declaración del impuesto sobre la renta, o en su caso, los entes públicos;\nXXIX. Verificar la digitalización e inclusión en el sistema de evolución patrimonial y de declaración de intereses, aquellas declaraciones que sean presentadas en formatos necesarios;\nXXX. Verificar las actas de entrega-recepción de las dependencias y entidades de la\nAdministración Pública Estatal;\nXXXI. Desarrollar todas aquellas funciones inherentes al área de su competencia; y\nXXXII. Las demás que le atribuyan otras disposiciones legales y reglamentarias, así como las que le confiera el Titular de la Secretaría.\nArtículo 16.- A la Dirección General de Investigación Administrativa le competen las atribuciones siguientes:\nI. Realizar investigaciones debidamente fundadas y motivadas, derivadas de auditorías, competencia;\nII. Proponer la normativa que deba regir la administración del Sistema Informático de\nQuejas y Denuncias del Estado de Campeche, así como la atención y seguimiento de estas;\nIII. Coordinar, administrar y operar el Sistema Informático de Quejas y Denuncias del\nEstado de Campeche y llevar el registro de éstas;\nIV. Atender y dar seguimiento a las quejas y denuncias recibidas por los diversos medios de captación y, en su caso, turnarla al área competente;\nV. Analizar las quejas y denuncias recibidas para determinar la apertura de la investigación y, en su caso, su inadmisibilidad;\nVI. Mantener una vinculación permanente con la Coordinación General de Órganos\nInternos de Control para la investigación de las quejas y denuncias recibidas;\nVII. Determinar la existencia o inexistencia de actos u omisiones que la Ley General de\nResponsabilidades Administrativas señale como falta administrativa y, en su caso, calificarla como grave o no grave;\nVIII. Elaborar el Informe de Presunta Responsabilidad Administrativa y remitirlo a la\nDirección General de Asuntos Jurídicos para su substanciación, resolución o trámite correspondiente;\nIX. Formular las respectivas denuncias ante la Fiscalía Especializada en Combate a la\nCorrupción del Estado y ante otras autoridades competentes, en términos de la normatividad aplicable;\nX. Coadyuvar en el procedimiento penal con las autoridades correspondientes en el ámbito de su competencia;\nXI. Colaborar con las autoridades estatales, nacionales e internacionales en el procedimiento de investigación por posibles hechos de corrupción;\nXII. Expedir, por conducto del Titular de la Dirección, las certificaciones de documentos y\nInvestigación Administrativa, en estricto apego a las disposiciones en materia de transparencia y protección de datos personales y la procedencia de la certificación;\nXIII. Asesorar y coadyuvar con los órganos internos de control de las dependencias y investigación;\nXIV. Ordenar prácticas de visitas de verificación, de acuerdo con lo que establece la Ley de\nProcedimiento Administrativo para el Estado y los Municipios de Campeche;\nXV. Solicitar información o documentación a cualquier persona física o moral con el objeto administrativas, con inclusión de aquella que las disposiciones legales en la materia consideren con carácter de reservada o confidencial;\nXVI. Llevar a cabo, por su titular o por el personal adscrito a la Dirección, las notificaciones necesarias con motivo del procedimiento de investigación administrativa;\nXVII. Imponer las medidas correspondientes previstas en el artículo 97 de la Ley General de\nResponsabilidades Administrativas;\nXVIII. Emitir, en su caso, el acuerdo de conclusión y archivo del expediente si no se encontraren elementos suficientes para demostrar la existencia de la infracción y la presunta responsabilidad del infractor, sin perjuicio de que pueda abrirse nuevamente la investigación si se presentan nuevos indicios o pruebas suficientes para determinar la existencia de la falta administrativa;\nXIX. Generar la información estadística en relación con las quejas y denuncias, que permita detectar las áreas de oportunidad para el combate a la corrupción;\nXX. Solicitar el auxilio de las diversas dependencias y entidades de gobierno, instituciones académicas, asociaciones civiles, entre otras que pudieran coadyuvar en la investigación de faltas administrativas.\nXXI. Promover, en coordinación con las demás dependencias y entidades de la\nAdministración Pública Estatal, la habilitación de módulos de atención a quejas, denuncias y sugerencias; y\nXXII. Las demás que le atribuyan otras disposiciones legales y reglamentarias, así como las que le confiera el Titular de la Secretaría.\nArtículo 17.- A la Coordinación General de Órganos Internos de Control le competen las atribuciones siguientes:\nI. Coordinar y supervisar a los Titulares de los órganos internos de control de las óptimo ejercicio de sus atribuciones;\nII. Aprobar el Programa Anual de Trabajo de los órganos internos de control con base en los lineamientos políticas y prioridades que dicte el Titular de la Secretaría;\nIII. Supervisar y evaluar la ejecución del Programa Anual de Trabajo de los Órganos\nInternos de Control, de conformidad con los lineamientos establecidos y las políticas y prioridades que genere el Titular de la Secretaría;\nIV. Evaluar el desempeño de los Titulares de los órganos internos de control, con base en los parámetros que dicte el Titular de la Secretaría e informar a ésta/e el resultado de la evaluación;\nV. Someter a la consideración del Titular de la Secretaría el establecimiento o control, con atención a las prioridades y necesidades del servicio de la Secretaría, con base en la normatividad establecida;\nVI. Promover la capacitación y el apoyo técnico que requiera el personal adscrito a los órganos internos de control;\nVII. Apoyar a los Titulares de los órganos internos de control en el seguimiento, evaluación y dictaminación de la solventación de las recomendaciones y observaciones que se formulen con motivo de los procesos de revisión, investigación y verificación;\nVIII. Asesorar y apoyar a los Titulares de los órganos internos de control en la elaboración de los informes por las revisiones, verificaciones e investigaciones efectuadas a los recursos públicos estatales y federales que ejercen las dependencias y entidades de la Administración Pública Estatal;\nIX. Turnar a los correspondientes órganos internos de control para su investigación y resolución, las quejas y denuncias que se interpongan en contra de los servidores públicos de la dependencia o entidad en la que se encuentre asignado e informar a la\nDirección General de Investigación Administrativa; y\nX. Las demás que le confieran expresamente las disposiciones legales y reglamentarias aplicables, así como las que le confiera el Titular de la Secretaría.\nArtículo 18.- La Coordinación Administrativa tendrá las atribuciones siguientes:\nI. Tramitar viáticos, gastos de alimentación, transportación terrestre, marítima o aérea de personas y demás servicios de proveeduría que requieran las unidades administrativas de la Secretaría, a solicitud de éstas, para el desempeño de sus funciones;\nII. Tramitar ante la Secretaría de Administración e Innovación Gubernamental, los movimientos que genere el personal de la Secretaría, que incluyan la propuesta y expedición de nombramientos, dentro del marco de su competencia;\nIII. Llevar un registro interno de los activos inventariables asignados a la Secretaría y de los resguardos;\nIV. Integrar y validar los anteproyectos presupuestales de las unidades administrativas de la Secretaría y someterlos a la consideración de la Secretaría de Finanzas;\nV. Administrar el fondo revolvente asignado a la Secretaría y, transferir o ministrar, en su caso, los recursos de éste a las unidades administrativas autorizadas por el Titular de la Secretaría, para su ejercicio directo;\nVI. Controlar, conforme a la disponibilidad financiera, el ejercicio del presupuesto que tengan asignado las unidades administrativas de la Secretaría;\nVII. Controlar y elaborar conciliaciones bancarias correspondientes a las cuentas que tenga asignadas, en materia de su competencia;\nVIII. Gestionar y controlar el gasto por comprobar de las unidades administrativas de la\nSecretaría;\nIX. Llevar un control de inventario del software instalado y sus licencias respectivas;\nX. Proponer al Titular de la Secretaría las políticas, normas, sistemas y procedimientos para la organización y administración de los recursos humanos, materiales y financieros de la dependencia, de acuerdo con los programas y objetivos fijados, afines con la normatividad vigente;\nXI. Coordinar la elaboración del anteproyecto del presupuesto de egresos de las Unidades\nAdministrativas y con previo conocimiento del Titular de la Secretaría, validar el envío electrónico y documental a la Secretaría de Finanzas para su autorización e integración a la iniciativa de Ley de Presupuesto de Egresos del Estado;\nXII. Tramitar ante la Secretaría de Finanzas la radicación de los recursos federales y estatales, conforme a los calendarios de ejercicio aprobados;\nXIII. Vigilar y controlar las erogaciones del ejercicio del gasto que se apeguen al presupuesto aprobado; en estricto apego a los principios de eficiencia, eficacia, economía, transparencia y honradez para satisfacer los objetivos a los que estén destinados;\nXIV. Implementar medidas de control interno que permitan mejorar el funcionamiento administrativo en la aplicación del gasto del presupuesto autorizado a la Secretaría;\nque permita revisar permanentemente los sistemas, métodos y procedimientos de trabajo que se requiera para lograr una modernización administrativa que responda a criterios de calidad y promueva la certificación de procesos;\nXV. Vigilar el cumplimiento de los criterios de racionalidad, austeridad y selectividad, que al respecto leyes y normativas emitan con el objeto de reducir los gastos de administración; sin detrimento de la realización oportuna de los programas y el cumplimiento de los servicios competencia de la Secretaría;\nXVI. Previa autorización de la Secretaría de Finanzas, gestionar las transferencias, reducciones y ampliaciones de las partidas presupuestales asignadas a la Secretaría, a través de los medios electrónicos implementados;\nXVII. Llevar el seguimiento, control financiero y contable del presupuesto anual autorizado de la Secretaría de acuerdo con las leyes, normas, convenios establecidos al respecto;\nXVIII. Elaborar e integrar el Plan Anual de Adquisiciones de la Secretaría mediante el análisis y seguimiento estadístico del mismo, así como el trámite correspondiente de adquisición, arrendamiento y contratación de los recursos materiales, suministros, al respecto;\nXIX. Coordinar en materia de su competencia a las unidades administrativas con el fin de bienes y servicios que el personal requiera o utilice en el ejercicio de sus funciones, como el ahorro por concepto de energía eléctrica, combustibles, telefonía, agua potable, materiales de oficina, impresión y fotocopiado;\nXX. Coordinar y controlar el resguardo de los bienes muebles, informáticos y vehiculares destinados a la Secretaría, de acuerdo con las disposiciones legales y administrativas estatal y federal que sean aplicables, y fungir como enlace con la Secretaría de\nAdministración e Innovación Gubernamental o la Secretaría de la Función Pública para la verificación respectiva;\nXXI. Desarrollar las políticas para la administración, control, mantenimiento preventivo y correctivo de bienes muebles y del parque vehicular en propiedad o uso de la\nSecretaría; así como el emplacamiento, seguros, tenencia, registro público vehicular y verificaciones que así corresponda;\nXXII. Organizar, dirigir y ejecutar los servicios de intendencia, mantenimiento de bienes muebles e inmuebles, reparaciones, transportes, vigilancia y demás servicios generales que requieran las unidades administrativas de la Secretaría;\nXXIII. Vigilar el cumplimiento de las políticas y procedimientos que la Ley determina en materia de seguridad e higiene en el trabajo de las instalaciones que ocupa la\nSecretaría; así como vigilar la correcta identificación de los señalamientos y logotipos autorizados de la imagen institucional vigente, en los inmuebles y vehículos;\nXXIV. Promover la capacitación del personal que integra la Secretaría;\nXXV. Acordar con el Titular de la Secretaría los movimientos de personal y gestionar ante la\nSecretaría de Administración e Innovación Gubernamental los movimientos de altas, bajas, reingresos, cambios de nivel, modificación de datos en nómina, comisiones, permisos, capacitaciones, sanciones, licencias, incapacidades, vacaciones y similares, llevando el debido control de estos;\nXXVI. Seleccionar y contratar al personal que, con carácter de temporal, por tiempo fijo u obra determinada, requiera la Secretaría para el desarrollo de sus funciones y, en su caso, identificar las necesidades de prestantes de servicio social y prácticas del Estado;\nXXVII. Realizar la suscripción y control de contratos para la prestación de servicios profesionales, con autorización del Titular de la Secretaría, en materia de obra pública y servicios relacionados con las mismas; considerando que dichos instrumentos\nConvenio de Colaboración Administrativa en Materia Fiscal Federal, mediante un sistema de reclutamiento, selección, contratación, remuneraciones, control y desarrollo, así como disponer lo necesario para su instrumentación, ejecución, seguimiento, control y evaluación;\nXXVIII. Tramitar y dar seguimiento a los pagos que, por efectos de nombramientos, reclasificaciones, horas extras, licencias y cambios de personal se generen en la\nSecretaría, así como el pago a los proveedores de bienes y servicios;\nXXIX. Apoyar a la Dirección General de Asuntos Jurídicos en la atención de los conflictos que en materia laboral se susciten en la Secretaría;\nXXX. Promover y coordinar la ejecución de los programas de capacitación y desarrollo del personas que pertenecen al servicio público de la Administración Pública Estatal;\nXXXI. Promover y coordinar la elaboración y actualización de los manuales administrativos;\nXXXII. Mantener informado permanentemente al Titular de la Secretaría de todos los asuntos relacionados con las actividades administrativas;\nXXXIII. Proponer la implementación de proyectos tecnológicos para la automatización de los procesos y las comunicaciones de las unidades administrativas de la Secretaría;\nXXXIV. Coordinar la prestación del servicio de soporte técnico de los equipos y sistemas informáticos, así como la administración del sitio de internet y la red de voz y datos de la Secretaría, para garantizar el buen funcionamiento de la infraestructura informática;\nXXXV. Proporcionar las asesorías, capacitaciones y asistencia técnica en materia de desarrollo tecnológico y comunicaciones a las unidades administrativas de la\nSecretaría, a fin de orientar al personal sobre el uso adecuado de los equipos y sistemas informáticos;\nXXXVI. Verificar periódicamente la infraestructura informática, red de voz y datos de la\nSecretaría con el objeto de garantizar sus condiciones de operación;\nXXXVII. Establecer mecanismos de control para el respaldo de la información digital que generan las diferentes unidades administrativas de la Secretaría;\nXXXVIII. Generar y actualizar el registro de control interno de los bienes informáticos, licencias y comunicaciones de las unidades administrativas de la Secretaría;\nXXXIX. Implementar políticas para el uso y administración de los servidores con los que cuenta la Secretaría, ya sean físicos o virtuales;\nXL. Generar, actualizar y vigilar el cumplimiento de las disposiciones en materia de tecnologías de la información, servicios electrónicos y de informática en las acciones de las unidades administrativas de la Secretaría;\nXLI. Elaborar y proponer al Titular de la Secretaría el método que funja como plataforma de integración de la información de la comparecencia;\nXLII. Instrumentar los mecanismos y estudios que permitan mantener el nivel requerido de\nSecretaría, así como sus servicios correspondientes;\nXLIII. Proporcionar a las unidades administrativas y demás áreas que integran la Secretaría, el respaldo necesario en materia de informática para el desarrollo de sus funciones;\nXLIV. Gestionar ante la dependencia correspondiente para efectos de coordinar los servicios de mantenimiento, asesoría, apoyo preventivo y correctivo en materia de informática en la operación de los sistemas de seguridad y equipos electrónicos de la Secretaría;\nXLV. Analizar las necesidades presentes y futuras con respecto a la optimización de programas, productos, sistemas operativos, equipos informáticos y de infraestructura de la Secretaría;\nXLVI. Capacitar y asesorar a los usuarios de la Secretaría respecto a sus requerimientos de servicios informáticos y de aplicaciones de cómputo a desarrollarse;\nXLVII. Evaluar la operación en las materias de su competencia y proponer en su caso las medidas que procedan;\nXLVIII. Actualizar la información pública de esta Secretaría en los portales electrónicos del\nGobierno del Estado de Campeche;\nXLIX. Diseñar sistemas, procedimientos y soluciones informáticas atendiendo las necesidades de la Secretaría;\nL. Participar en el Comité de Informática de la Administración Pública Estatal con el cargo y atribuciones que se le asignen;\nLI. Desarrollar el Plan Anual de Tecnologías de Información de la Secretaría, en el marco del Programa de Modernización Gubernamental y vigilar que la infraestructura de esas tecnologías sean utilizadas en el cumplimiento de los objetivos para los cuales fueron adquiridos o desarrollados y, cuando sea necesario, orientar oportunamente su utilización para un mejor aprovechamiento de las mismas y, en su caso, aplicar medidas de seguridad para salvaguardar la integridad, disponibilidad y confidencialidad de los sistemas de información y bases de datos, para proteger los bienes de tecnologías de la información;\nLII. En materia de su competencia, participar en la elaboración, difusión y actualización del programa de gobierno electrónico del Poder Ejecutivo Estatal; y\nLIII. Las demás que le confieran expresamente las disposiciones legales y reglamentarias aplicables, así como las que le confiera el Titular de la Secretaría.\nCAPÍTULO V\nDE LAS UNIDADES DE APOYO DE LA\nOFICINA DEL TITULAR DE LA SECRETARÍA\nArtículo 19.- La Unidad de Transparencia, dependerá directamente del Titular y tendrá las atribuciones que le confieran la normatividad vigente en materia de transparencia, acceso a la información, protección de datos personales y gestión documental.\nArtículo 20.- La Secretaría Particular tendrá las atribuciones siguientes:\nI. Proporcionar asistencia técnica y asesoría al Titular de la Secretaría;\nII. Acordar la agenda diaria con el Titular;\nIII. Apoyar al Titular en la atención y control de los asuntos que le encomiende;\nIV. Organizar y despachar la correspondencia a las áreas competentes de los asuntos recibidos en la Oficina del Titular para su debida gestión;\nV. Organizar y turnar la información a las distintas áreas que conforman la Secretaría y dar seguimiento de los asuntos relacionados con su gestión;\nVI. Dar seguimiento a los acuerdos tomados en las reuniones de trabajo del Titular;\nVII. Supervisar el desahogo de los asuntos atendidos directamente por el Titular que por su importancia requieren de atención urgente y extraordinaria;\nVIII. Supervisar y coordinar las actividades del personal adscrito a la Oficina del Titular; y\nIX. Las demás que le confieran el Titular de la Secretaría.\nArtículo 21.- La Unidad de Comunicación Social tendrá las atribuciones siguientes:\nI. Elaborar, coordinar y aplicar la estrategia y los programas de comunicación social de la Secretaría de conformidad con las políticas y lineamientos establecidos para la\nAdministración Pública Estatal;\nII. Observar y ejecutar la política de comunicación social que determine el Titular de conformidad con las políticas y lineamientos aplicables en la materia;\nIII. Coordinar y autorizar el diseño y producción de materiales de difusión impresos y electrónicos respecto de las actividades de la Secretaría de conformidad con las disposiciones jurídicas aplicables;\nIV. Coordinar y atender las relaciones públicas de la Secretaría con los medios de comunicación;\nV. Difundir los objetivos, programas y acciones de la Secretaría;\nVI. Vigilar el uso adecuado de la imagen institucional de la Secretaría;\nVII. Conservar y actualizar el archivo de comunicados, fotografía y de video de las actividades relevantes de la Secretaría;\nVIII. Captar, analizar y procesar la información que difunden los medios de comunicación acerca de la Secretaría y proponer, en su caso, acciones preventivas para evitar desinformación en la opinión pública, y\nIX. Las demás que le confieran el Titular de la Secretaría.\nArtículo 22.- La Unidad Coordinadora de Archivos, dependerá directamente del Titular, y promoverá que todas las unidades administrativas de la Secretaría, realicen acciones de gestión documental y administración de los archivos, de conformidad con las disposiciones legales aplicables.\nArtículo 23.- La Unidad Coordinadora de Archivos tendrá las funciones siguientes:\nI. Elaborar, con la colaboración de los responsables de los archivos de trámite y de concentración, los instrumentos de control y consulta archivística previstos en este\nReglamento y demás normatividad aplicable, contemplando el acceso a la información y la protección de los datos personales;\nII. Elaborar criterios específicos y recomendaciones en materia de organización y conservación de archivos, cuando la especialidad así lo requiera;\nIII. Emitir el Programa Operativo Anual, previa autorización de su superior jerárquico e informar de ello al Titular de la Secretaría;\nIV. Coordinar los procedimientos de valoración y disposición documental que realicen las unidades administrativas;\nV. Coordinar las actividades destinadas a la modernización y automatización de los procesos archivísticos y a la gestión de documentos electrónicos de las unidades administrativas;\nVI. Autorizar la transferencia de los archivos cuando algún área o unidad del sujeto obligado sea sometida a procesos de fusión, escisión, extinción o cambio de adscripción o cualquier modificación de conformidad con las disposiciones legales aplicables; y\nVII. Las demás que le confieran expresamente las disposiciones legales y reglamentarias aplicables, así como las que le confiera el Titular de la Secretaría.\nArtículo 24.- La Unidad Especializada en Ética y Prevención de Conflicto de Interés tendrá las siguientes atribuciones:\nI. Formular y someter a la consideración del Titular de la Secretaría, las políticas, lineamientos, estrategias y demás instrumentos de carácter general, para establecer acciones en materia de ética e integridad a fin de prevenir conductas contrarias a las disposiciones que rigen el ejercicio de la función pública, así como Conflicto de Interés de las personas que pertenecen al servicio público, en las dependencias y las entidades;\nII. Ejercer las atribuciones que las disposiciones jurídicas y administrativas confieren a la\nSecretaría en materia de ética, integridad y prevención de Conflicto de Interés, excepto\nTitular de la Secretaría o por alguna unidad administrativa de la Secretaría;\nIII. Coordinar, dar seguimiento y evaluar las acciones que realicen las dependencias y entidades en materia de ética, integridad pública y prevención de conflictos de intereses, en cumplimiento en lo establecido en las Convenciones Internacionales\nAnticorrupción ratificadas por el Estado Mexicano, en el Plan Estatal de Desarrollo o en los programas que en él deriven;\nIV. Diseñar y establecer un sistema para programar, coordinar, dar seguimiento y evaluar las acciones que realicen las dependencias y las entidades en materia de ética, integridad y prevención de Conflicto de Interés, así como para la operación y funcionamiento de los Comités de Ética y de Prevención de Conflicto de Interés, emitir las observaciones que en su caso procedan;\nV. Coordinar y llevar el registro y seguimiento de las observaciones y recomendaciones en las materias de ética, integridad y prevención de Conflicto de Interés;\nVI. Proponer a la Coordinación General de Órganos Internos de Control la metodología de participación de los órganos internos de control en el seguimiento de las acciones que realicen las dependencias y las entidades en cumplimiento de las materias competencia de esta Unidad;\nVII. Fungir como órgano de asesoría y consulta en materia de ética, integridad y prevención de Conflicto de Interés en el desempeño del servicio público;\nVIII. Emitir opinión respecto de la posible actualización de Conflicto de Interés a cargo de las y los servidores públicos sujetos a investigación cuando así se le solicite por parte de las unidades administrativas competentes de la Secretaría;\nIX. Requerir para el adecuado cumplimiento de sus atribuciones, información y documentación a las dependencias y entidades, a efecto de emitir opinión respecto de la posible actualización de Conflicto de Interés;\nX. Requerir información del avance y conclusión de los procedimientos disciplinarios que se instauren por las autoridades competentes para sancionar los Conflicto de Interés;\nXI. Elaborar recomendaciones a fin de prevenir Conflicto de Interés en el ejercicio de la función pública, para lo cual podrá apoyarse de las unidades administrativas competentes y de los órganos internos de control en las dependencias y entidades;\nXII. Elaborar y promover programas de capacitación y sensibilización en materia de ética, integridad y prevención de Conflicto de Interés dirigidos a las y los servidores públicos estatales y municipales, así como a las y los integrantes de los Comités de Ética y de\nPrevención de Conflicto de Interés en las dependencias y entidades;\nXIII. Promover y coadyuvar con otros poderes, órdenes de gobierno y demás entes públicos, así como con los sectores privado y social, en coordinación con las unidades administrativas competentes de la Secretaría, en la adopción de estrategias enfocadas a fortalecer la ética, la integridad y la prevención de Conflicto de Interés;\nXIV. Establecer bases permanentes para reconocer, premiar y estimular acciones, medidas o conductas ejemplares de áreas o personas en materia de ética, integridad y prevención de Conflicto de Interés, para su respectiva aplicación por parte de los\nComités de Ética y de Prevención de Conflicto de Interés;\nXV. Formular propuestas para el fortalecimiento del control de la gestión pública, a partir de las evaluaciones que realice en materia de ética, integridad y prevención de\nConflicto de Interés, así como de la operación y funcionamiento de los Comités de\nÉtica y de Prevención de Conflicto de Interés;\nXVI. Emitir los criterios, conforme a la normatividad aplicable, para que las dependencias publiquen en sus páginas de internet su Código de Conducta, los informes anuales y la demás información relacionada con su Comité;\nXVII. Recabar, analizar y evaluar la información para la elaboración de los diagnósticos que realicen en materia de ética, integridad pública y prevención de conflicto de intereses en las dependencias y entidades de la Administración Pública Estatal;\nXVIII. Interpretar para efectos administrativos, las disposiciones que en materia de ética, Secretaría en términos de las disposiciones aplicables, considerando la opinión de las demás unidades administrativas competentes; y\nXIX. Las demás que le confieran expresamente las disposiciones legales y reglamentarias aplicables, así como las que le confiera el Titular de la Secretaría.\nArtículo 25.- La Unidad de Prevención a la Corrupción tendrá las siguientes atribuciones:\nI. Establecer y coordinar el cumplimiento de las políticas y acciones en materia de prevención de los actos de corrupción en las dependencias y entidades de la Administración Pública Estatal;\nII. Elaborar e integrar el Programa Estatal para la prevención y combate a la\nCorrupción, y someterlo a consideración del Secretario a fin de que gestione lo necesario para su aprobación y ejecución;\nIII. Promover programas y acciones, dirigidos a la sociedad civil, en materia de prevención y combate a la corrupción;\nIV. Organizar campañas de difusión para promover la prevención y combate a la corrupción;\nV. Ejecutar políticas y acciones para prevenir y erradicar las prácticas de corrupción e impunidad que se detecten en la Administración Pública\nEstatal;\nVI. Establecer e implementar programas de difusión y capacitación para fortalecer la cultura de transparencia, honestidad y apego a la legalidad;\nVII. Desarrollar y coordinar acciones que promuevan una cultura de buen los servidores públicos;\nVIII. Fomentar mecanismos de vinculación interinstitucional y de participación ciudadana en la prevención y combate a la corrupción;\nIX. Propiciar que los servidores públicos adscritos a las dependencias y y se apeguen a los principios de legalidad, profesionalismo y honradez en el ejercicio de sus atribuciones; y\nX. Las demás que le confieran expresamente las disposiciones legales y reglamentarias aplicables, así como las que confiera el Titular de la Secretaría.\nArtículo 26.- La Unidad de Igualdad de Género tendrá las siguientes atribuciones:\nI. Contribuir al cumplimiento de la normativa vigente en materia de igualdad entre mujeres y hombres en todo quehacer institucional;\nII. Fortalecer la igualdad entre mujeres y hombres, la no discriminación y la inclusión en la Secretaría;\nIII. Consolidar una cultura laboral y organizacional de igualdad de oportunidades, sin violencia y libre de discriminación al interior de la Secretaría;\nIV. Planificar, verificar y dar seguimiento a la introducción de la perspectiva y transversalidad de género en la planeación, programación, ejecución y evaluación de programas, proyectos, acciones y políticas públicas al interior de la Secretaría;\nV. Organizar y coordinar la capacitación, formación y certificación del personal en materia de género, transversalidad e igualdad sustantiva entre mujeres y hombres;\nVI. Asegurar que la prestación de atención y servicios a la población se lleve a cabo con perspectiva de género, sin violencia y sin discriminación;\nVII. Proponer cambios a la normatividad interna y a las estructuras organizacionales que aseguren la incorporación de la perspectiva y transversalidad de género entre mujeres y hombres;\nVIII. Difundir información referente al proceso y resultados de la incorporación de la perspectiva y transversalidad de género en la cultura organizacional y en las políticas públicas de la Secretaría;\nIX. Diseñar un Programa Anual de Trabajo que contemple una agenda institucional para incorporar la perspectiva de género;\nX. Participar en los procesos de planeación, programación y presupuesto de la Secretaría perspectiva de género;\nXI. Planear, ejecutar y evaluar acciones enfocadas a disminuir las brechas de desigualdad entre mujeres y hombres en la Secretaría; y\nXII. Las demás que le confieran expresamente las disposiciones legales y reglamentarias aplicables, así como las que confiera el Titular de la Secretaría.\nCAPÍTULO VI\nDE LAS ATRIBUCIONES DE LOS TITULARES\nDE LOS ÓRGANOS INTERNOS DE CONTROL\nArtículo 27.- Los Titulares de los Órganos Internos de Control tendrán las atribuciones siguientes:\nI. Formular para su aprobación en el mes de noviembre, el proyecto de Programa Anual de Trabajo del Órgano Interno de Control a su cargo, con base en los lineamentos, políticas y prioridades que dicte el Titular de la Secretaría;\nII. Cumplir el Programa Anual de Trabajo autorizado;\nIII. Planear y realizar las revisiones, verificaciones y acciones de control interno en la dependencia o entidad en la que se encuentre asignado;\nIV. Elaborar y remitir mensualmente a la Coordinación General de Órganos Internos de\nControl los informes sobre el avance y cumplimiento del Programa Anual de Trabajo del Órgano Interno de Control a su cargo;\nV. Formular, fundar y motivar los requerimientos de información necesarios para el desempeño de sus funciones y emitir los informes de resultados derivados de sus procesos de revisión y/o verificación; así como requerir y obtener duplicado de los documentos que tengan a la vista y certificarlos;\nVI. Mantener y evaluar los sistemas de control interno de la dependencia o entidad en la que se encuentre asignado, a efecto de proponer las medidas que permitan el fortalecimiento de ese control;\nVII. Vigilar el cumplimiento de las normas y acciones de control interno gubernamental, así como el de las demás disposiciones vigentes en materia de planeación, programación, presupuesto y gestión; ingresos, egresos y patrimonio; inversión y obra pública; financiamiento y deuda; sistemas de registros y control de contabilidad;\nadquisiciones, arrendamientos y prestación de servicios; recursos humanos, materiales, financieros y servicios generales; conservación, uso y destino, afectación, enajenación y baja de bienes y recursos materiales, así como los sistemas de contratación y pago de personal de la Administración Pública Estatal;\nVIII. Dar seguimiento, evaluar y dictaminar la solventación de las recomendaciones y que practique el Órgano Interno de Control, así como dar seguimiento a la atención\nGeneral de Auditoría Gubernamental;\nIX. Apoyar a las Direcciones Generales de Auditoría Gubernamental y de Investigación\nAdministrativa, cuando éstas se lo requieran en el desarrollo de sus funciones;\nX. Fungir como enlace de la Secretaría en los procesos de auditoría que efectúen las instancias de fiscalización, federales y estatales;\nXI. Informar bimestralmente a la Dirección General de Asuntos Jurídicos los movimientos de altas y bajas de personal, a efecto de contar con un padrón actualizado de las personas obligadas a presentar declaraciones de situación patrimonial y de intereses;\nXII. Recepcionar, tramitar, investigar y resolver, en términos de lo dispuesto por la Ley\nGeneral de Responsabilidades Administrativas, las quejas y denuncias que se\nGeneral de Investigación Administrativa;\nXIII. Coadyuvar en los actos de entrega-recepción de las personas que pertenecen al servicio público que inicien o concluyan sus funciones en la dependencia o entidades en la que se encuentren asignadas, en términos de lo que dispone la Ley que Regula los Procedimientos de Entrega Recepción del Estado de Campeche y sus Municipios;\nXIV. Coadyuvar en los procedimientos licitatorios para la vigilancia y cumplimiento de la legislación federal y estatal en materia de obra pública y de adquisiciones, arrendamientos y prestación de servicios;\nXV. Coadyuvar en la vigilancia y cumplimiento de la normatividad vigente en materia de acceso a la información, protección de datos personales y gestión documental;\nXVI. Llevar a cabo investigaciones debidamente motivadas o auditorías respecto de las conductas de las personas que pertenecen al servicio público que puedan constituir responsabilidades administrativas; así mismo podrán comprobar el cumplimiento de las obligaciones del personal del servicio público a través de operativos específicos de verificación, en los que participen en su caso los particulares que reúnan los requisitos que aquellos establezcan;\nXVII. Vigilar la debida aplicación de los recursos federales y estatales que ejerzan las dependencias y entidades de la Administración Pública Estatal, conforme a lo estipulado en los acuerdos y convenios respectivos;\nXVIII. Vigilar el cumplimiento de las obligaciones adquiridas por proveedores y contratistas con las dependencias y entidades de la Administración Pública Estatal;\nXIX. Identificar, investigar, determinar y calificar, las responsabilidades en que incurra el personal de las dependencias y entidades de la Administración Pública Estatal, Responsabilidades Administrativas y, en su caso, formular las respectivas denuncias ante otras autoridades competentes, en términos de las disposiciones aplicables;\nXX. Elaborar el Informe de Presunta Responsabilidad Administrativa y remitirlo a la\nDirección General de Asuntos Jurídicos para su substanciación, resolución o trámite correspondiente\nXXI. Requerir durante el desarrollo de las revisiones, a terceros que hubieran contratado con las dependencias y entidades de la Administración Pública Estatal obra pública, bienes o servicios mediante cualquier título legal y, en general, a cualquier Ente\nPúblico o Entidad, persona física o moral, pública o privada, que haya ejercido recursos públicos, la documentación e información relacionada con la adjudicación, contratación, ejecución, justificación y comprobación de las operaciones, a efecto de realizar las compulsas correspondientes;\nXXII. Requerir y obtener, durante el desarrollo de las revisiones, inspecciones y verificaciones, la información que las disposiciones legales consideren como de carácter reservado, confidencial o que deba mantenerse en secreto, cuando esté relacionada directamente con la recepción, captación, recaudación, administración, manejo, custodia, ejercicio, aplicación de los ingresos y egresos, y la deuda pública, estando obligada a mantener la misma confidencialidad o secrecía, hasta en tanto no se derive de su revisión el fincamiento de responsabilidades;\nXXIII. Elaborar los oficios para realizar revisiones, visitas domiciliarias, revisiones de gabinete, inspecciones y verificaciones;\nXXIV. Evaluar de manera periódica el cumplimiento final de los objetivos y metas fijados en los programas estatales, mediante la estimación o cálculo de los resultados obtenidos en términos cualitativos o cuantitativos, mediante los indicadores estratégicos y de gestión establecidos en los mismos programas, o ambos, a efecto de verificar el desempeño de estos y, en su caso, el uso de recursos públicos conforme a las disposiciones legales;\nXXV. Verificar que las dependencias y entidades de la Administración Pública Estatal que hubieren recibido, captado, recaudado, custodiado, manejado, administrado, aplicado o ejercido recursos públicos, lo hayan realizado conforme a los programas aprobados y montos autorizados, así como en el caso de los egresos, con cargo a las partidas correspondientes; además, con apego a las disposiciones legales, reglamentarias y administrativas aplicables;\nXXVI. Verificar que las operaciones y actos que realicen las dependencias y entidades de la\nAdministración Pública Estatal sean acordes con la Ley de Ingresos y la Ley de\nPresupuesto de Egresos respectivos y se efectúen con apego a las disposiciones legales, reglamentarias y administrativas aplicables;\nXXVII. Verificar obras públicas, bienes adquiridos, servicios públicos y servicios contratados, y en general cualquier acción, para comprobar si las inversiones y gastos autorizados y eficientemente al logro de los objetivos y metas de los programas;\nXXVIII. Verificar obras públicas, bienes adquiridos, servicios públicos, servicios contratados y acciones, así como la verificación de la información, libros, papeles, contratos, convenios, nombramientos, dispositivos magnéticos o electrónicos de almacenamiento de datos o información, documentos y archivos;\nXXIX. Revisar y fiscalizar los recursos públicos federales que hayan recibido las dependencias y entidades de la Administración Pública Estatal, cuando dicha revisión celebrados con el propósito de apoyar y hacer más eficiente la revisión;\nXXX. Constatar la existencia, procedencia y registro de los activos y pasivos de las dependencias y entidades de la Administración Pública Estatal, de los fideicomisos, fondos y mandatos o cualquier otra figura jurídica análoga, para verificar la particulares;\nXXXI. Verificar y fiscalizar que la deuda pública, en su contratación, registro, renegociación, administración y pago, se ajuste a las disposiciones legales vigentes;\nXXXII. Realizar, durante el desarrollo de las revisiones, inspecciones y verificaciones, entrevistas y reuniones con particulares o con los servidores públicos de las dependencias y entidades de la Administración Pública Estatal, necesarias para conocer directamente el ejercicio de sus funciones;\nXXXIII. Requerir y tener acceso a los equipos de cómputo en los que dependencias y entidades de la Administración Pública Estatal lleven su contabilidad, así como a los microfilmes, discos ópticos y a cualquier otro medio autorizado por las disposiciones fiscales en que la almacenen, con el auxilio de los operadores de dichos equipos;\nXXXIV. Emitir citatorios durante el desarrollo de las revisiones; levantar actas circunstanciadas para hacer constar hechos y omisiones; así como requerir la designación de testigos y, en su caso, designarlos, haciendo constar esta situación en el acta que levanten durante el desarrollo de las revisiones, inspecciones y verificaciones; así como realizar, en términos de la normatividad aplicable, las notificaciones que se requieran para el desarrollo de sus funciones;\nXXXV. Elaborar y revisar los papeles de trabajo para asegurar que soporten adecuadamente las observaciones, conclusiones y recomendaciones del trabajo;\nXXXVI. Integrar, organizar, clasificar, archivar y salvaguardar, de acuerdo con las disposiciones aplicables, los expedientes de las revisiones, inspecciones y verificaciones en las que participen, con los papeles de trabajo, cédulas de observaciones y la documentación que se derive de las mismas;\nXXXVII. Integrar la documentación y comprobación necesaria para promover las acciones legales en el ámbito penal y de otra naturaleza que procedan, como resultado de las irregularidades que se detecten en las revisiones, revisiones de gabinete, haya efectuado en forma completa y correcta;\nXXXVIII. Coadyuvar con la Fiscalía General del Estado y la Fiscalía Especializada en Combate materia;\nXXXIX. Vigilar permanentemente la aplicación del presupuesto, realizar las inspecciones, revisiones, verificaciones o auditorías que resulten necesarias, así como para que se penales y demás disposiciones aplicables;\nXL. Entregar en los meses de mayo y noviembre, al Titular de la Secretaría, los informes correctivas, preventivas y oportunidades de mejora;\nXLI. Implementar mecanismos internos que prevengan actos u omisiones que puedan constituir responsabilidades administrativas, en los términos establecidos por el\nSistema Anticorrupción del Estado de Campeche;\nXLII. Continuar, en el ámbito de su competencia, las investigaciones de las posibles faltas administrativas no graves que las Entidades de Fiscalización Superior le remitan y, en su caso, promover las acciones procedentes;\nXLIII. Implementar, en coordinación con el Sistema Anticorrupción del Estado de\nCampeche, acciones para orientar el criterio que en situaciones específicas deberán observar las personas que pertenecen al servicio público en el desempeño de sus empleos, cargos o comisiones, para prevenir la comisión de faltas administrativas y hechos de corrupción;\nXLIV. Evaluar anualmente el resultado de las acciones específicas que hayan implementado conforme a los mecanismos generales de prevención en la comisión de faltas administrativas y hechos de corrupción, e informar a la Secretaría;\nXLV. Valorar las recomendaciones que emita el Comité Coordinador del Sistema\nAnticorrupción del Estado de Campeche, para el fortalecimiento institucional en su desempeño y control interno para la prevención de faltas administrativas y hechos de corrupción;\nXLVI. Llevar a cabo investigaciones o auditorías para verificar la evolución del patrimonio de los declarantes, de conformidad con lo establecido en la Ley General de\nResponsabilidades Administrativas;\nXLVII. Atender las quejas e inconformidades que presenten los particulares con motivo de\nAdministración Pública Estatal, salvo los casos en que otras leyes establezcan procedimientos de impugnación diferentes;\nlos órganos internos de control para revisar, mediante las auditorías, el ingreso, manejo, custodia y ejercicio de recursos públicos estatales;\nXLIX. Establecer mecanismos internos para la Administración Pública Estatal que permitan prevenir actos u omisiones que pudieran constituir responsabilidades administrativas;\nL. Las demás que le confieran expresamente otras disposiciones legales y reglamentarias aplicables.\nCAPÍTULO VII\nDE LAS OBLIGACIONES DEL PERSONAL\nArtículo 28.- El personal de la Secretaría de la Contraloría, sin distinción de la función que realice, tendrá las obligaciones siguientes:\nI. Verificar que los trabajos ejecutados por sus subordinados cumplan los requisitos establecidos en los lineamientos técnicos, y criterios emitidos por la Secretaría en las normas técnicas adoptadas por esta;\nII. Cumplir con las disposiciones del Código de Ética, Código de Conducta y de las\nDirectrices para Prevenir el Conflicto de Intereses, y demás normativa que genere la\nSecretaría;\nIII. Informar al Titular de la unidad administrativa a la que se encuentre adscrito cuando el trabajo que deba ejecutar motive un conflicto de interés, esto es, que tenga un interés personal o profesional en competencia con otros intereses;\nIV. Asistir a las actividades de capacitación, que le sean comunicados por el Titular de la unidad administrativa a la que se encuentra adscrito o por la Coordinación\nAdministrativa;\nV. Mantener actualizados y perfeccionar sus conocimientos, aptitudes y competencias en los temas relevantes para el desempeño de sus funciones con independencia de la capacitación que reciba de la Secretaría;\nVI. Cumplir su trabajo con eficacia y eficiencia;\nVII. Custodiar, resguardar, usar prudente y adecuadamente los bienes y equipo propiedad de la Secretaría que le sean asignados para el cumplimiento de sus funciones, además de gestionar el mantenimiento de estos;\nVIII. Reportar en forma inmediata a la Coordinación Administrativa cualquier avería o para el cumplimiento de sus funciones, en el formato establecido para ello;\nIX. Conducir con prudencia y precaución los vehículos oficiales que se le asignen para el cumplimiento de sus labores y comisiones, y respetar las señales de tránsito y los reglamentos de vialidad; y\nX. Las demás que en el ámbito de su competencia les establezcan las disposiciones jurídicas y normativas aplicables o sus superiores jerárquicos.\nCAPÍTULO VIII\nDE LA SUPLENCIA DE LOS TITULARES\nArtículo 29.- El Titular de la Secretaría será suplido en sus ausencias temporales y accidentales no mayores de 15 días por la o el servidor público subalterno que para tal efecto designe, previo informe al Gobernador del Estado. Si la ausencia excede de este término, el o del servidor público que cubra dicha falta. En caso de que la ausencia por el motivo que fuere se convierta, en definitiva, entretanto se nombra al nuevo o la nueva Titular de la del Despacho lo sustituya.\nArtículo 30.- Las ausencias temporales y accidentales, de las y los directores generales y\nTitulares de las coordinaciones, serán suplidas por las y los directores de área que de ellos dependan o del personal del nivel jerárquico inmediato inferior que de ellos dependan, conforme lo disponga el Titular de la Secretaría.\nArtículo 31.- Las ausencias temporales y accidentales, de las y los Titulares de las direcciones, subdirecciones y jefaturas de departamento, serán suplidas por el personal del nivel jerárquico inmediato inferior que de ellos dependan, conforme lo disponga el Titular de la Secretaría.\nArtículo 32.- Las ausencias temporales y accidentales del resto del personal de la Secretaría se suplirán conforme lo disponga su superior jerárquico inmediato, previa consulta al Titular de la Secretaría.\nArtículo 33.- Las ausencias definitivas de cualquiera de las personas adscritas a la Secretaría se suplirán con un nuevo nombramiento, en tanto se otorgue nuevo nombramiento, el Titular\nDespacho.\nCAPÍTULO IX\nINTERPRETACIÓN\nArtículo 34.- Para los casos no previstos en este Reglamento y en caso de presentarse alguna controversia sobre su interpretación y/o aplicación de su contenido, el Titular de la\nSecretaría resolverá lo conducente.\nTRANSITORIOS\nPrimero. - El presente Reglamento entrará en vigor al día siguiente de su publicación en el\nPeriódico Oficial del Estado.\nSegundo. - Se abroga el Reglamento Interior de la Secretaría de la Contraloría de la\nTercero. - Se derogan todas las disposiciones legales y reglamentarias de igual o menor jerarquía del marco jurídico estatal, en lo que se opongan al contenido del presente reglamento interior.\nSan Francisco de Campeche, Municipio y Estado de Campeche, a los treinta y un días del mes de julio del año dos mil dieciocho.\nLIC. RAFAEL ALEJANDRO MORENO CÁRDENAS\nGOBERNADOR DEL ESTADO DE CAMPECHE\nMTRO. JOSÉ ROMÁN RUIZ CARRILLO\nSECRETARIO DE LA CONTRALORÍA",
  "ordenamiento": "REGLAMENTO",
  "jurisdiccion": "CAMPECHE",
  "fuente_oficial": "DIARIO OFICIAL DE LA FEDERACION",
  "Fecha de Publicación": "27 de mayo de 2015",
  "es_escaneado": false,
  "tiene_tablas": false,
  "materia": [
    "administrativo",
    "anticorrupción"
  ]
}