{
  "titulo": "Reglamento INTERIOR DE LA SECRETARIA EJECUTIVA DEL SISTEMA ANTICORRUPCIÓN DEL ESTADO DE CAMPECHE",
  "Contenido": "ANTICORRUPCIÓN DEL ESTADO DE CAMPECHE en ejercicio de la facultad que le confiere el artículo 14 de la Ley de la Administración\nPública Paraestatal del Estado de Campeche, con fundamento en lo establecido en los artículos 24, 25, 26, 27, 28 y 29 de la Ley del Sistema Anticorrupción del Estado de Campeche, y\nCONSIDERANDO de la Federación el Decreto por el que se reforman, adicionan y derogan diversas disposiciones de la Constitución Política de los Estados Unidos Mexicanos en materia de combate a la corrupción, mediante el cual se reformó, entre otros, el artículo 113 Constitucional, incluyéndose las bases mínimas de Sistema Nacional\nAnticorrupción, así como la obligación de las Entidades Federativas de establecer sistemas locales anticorrupción con el objeto de coordinar a las autoridades locales competentes en la prevención, detección y sanción de responsabilidades administrativas y hechos de corrupción, estableciendo en el artículo Transitorio\nSéptimo que los sistemas anticorrupción de las Entidades Federativas deberán conformarse de acuerdo con las leyes generales que resulten aplicables, las constituciones y leyes locales.\nQue el dieciocho de julio del año dos mil dieciséis se publicó en el Diario Oficial de la Federación la Ley General del Sistema Nacional Anticorrupción, que en su\nCapítulo V del Título Segundo estableció las bases para la integración, atribuciones y funcionamiento de los sistemas anticorrupción de las Entidades Federativas.\nQue en congruencia con la Ley General del Sistema Nacional Anticorrupción, mediante Decreto Número 162 de la LXII Legislatura del H. Congreso del Estado de\nCampeche, publicado en el Periódico Oficial el veintisiete de junio de dos mil diecisiete, se reformaron y adicionaran diversas disposiciones a la Constitución de todos los órdenes de gobierno competentes en la prevención, detección y sanción de responsabilidades administrativas, actos y hechos de corrupción, así como en la fiscalización y control de recursos públicos. Sistema que para el a la ley respectiva.\nQue en consecuencia, mediante el Decreto número 188 de la LXII Legislatura del\nAnticorrupción del Estado de Campeche, cuyo artículo 24 dispone la creación de un organismo descentralizado, no sectorizado, con personalidad jurídica y patrimonio propios, con autonomía técnica y de gestión, mismo que tendrá su sede en la ciudad de San Francisco de Campeche, denominado Secretaría Ejecutiva del Sistema\nAnticorrupción.\nQue en términos del artículo Transitorio Tercero del citado Decreto número 188, la\nSecretaría Ejecutiva deberá iniciar sus operaciones, a más tardar a los treinta días siguientes a la sesión de instalación del Comité Coordinador del Sistema\nAnticorrupción del Estado de Campeche.\nQue en términos de lo dispuesto por los artículos 28 y 29 de la Ley del Sistema\nAnticorrupción del Estado de Campeche, la Secretaría Ejecutiva contará con un\nÓrgano de Gobierno el cual tendrá las atribuciones indelegables previstas en la Ley del Sistema Anticorrupción del Estado de Campeche y deberá contar con un\nReglamento Interior.\nQue en su segunda sesión ordinaria de fecha 11 de diciembre de 2019, el Órgano de Gobierno aprobó la expedición del Reglamento Interior de la Secretaria Ejecutiva del Sistema Anticorrupción del Estado.\nQue, con fundamento en lo anteriormente expuesto, se tiene a bien expedir el siguiente:\nREGLAMENTO INTERIOR DE LA SECRETARIA EJECUTIVA DEL SISTEMA\nANTICORRUPCIÓN DEL ESTADO DE CAMPECHE\nCAPÍTULO I\nDISPOSICIONES GENERALES.\nARTÍCULO 1. El presente Reglamento establece las bases de organización y\nCampeche, en el ejercicio de sus funciones, atribuciones y facultades, en términos en la materia.\nARTÍCULO 2. La Secretaría Ejecutiva del Sistema Anticorrupción del Estado de\nCampeche es un organismo público descentralizado, no sectorizado, con personalidad jurídica y patrimonio propio, con autonomía técnica y de gestión, mismo que tendrá su sede en la ciudad de San Francisco de Campeche, Municipio de Campeche, capital del Estado de Campeche.\nContará con un logotipo como símbolo de identidad, el cual no podrá ser cambiado\nAnticorrupción del Estado de Campeche.\nAnticorrupción del Estado de Campeche en las oficinas y documentos oficiales, así como en los bienes que integran su patrimonio.\nARTÍCULO 3. La Secretaría Ejecutiva del Sistema Anticorrupción del Estado de\nCampeche tiene por objeto fungir como órgano de apoyo técnico del Comité\nCoordinador, a efecto de proveerle la asistencia técnica, así como los insumos necesarios para el desempeño de sus atribuciones, de conformidad con lo dispuesto en la Ley del Sistema Anticorrupción del Estado de Campeche y demás ordenamientos aplicables.\nARTÍCULO 4. Para los efectos de este Reglamento se entenderá por:\nI. Comisión Ejecutiva: al órgano técnico auxiliar de la Secretaría\nEjecutiva;\nII. Comité Coordinador: al Comité Coordinador del Sistema\nAnticorrupción del Estado de Campeche, instancia establecida en coordinación y eficacia del Sistema Anticorrupción;\nIII. Comité de Participación Ciudadana: a la instancia colegiada\nAnticorrupción del Estado de Campeche;\nIV. Días: a los días hábiles;\nV. Entes Públicos: a los Poderes Legislativo, Ejecutivo y Judicial, los organismos constitucionales autónomos, las Dependencias y\nEntidades de la Administración Pública Estatal; Fiscal General del\nEstado; los Municipios y sus Dependencias y Entidades\nParamunicipales; los órganos jurisdiccionales que no formen parte poderes y órganos públicos antes citados;\nVI. Ley: a la Ley del Sistema Anticorrupción del Estado de\nCampeche;\nVII. Órgano Interno de Control: al órgano interno de control de la\nSecretaria Ejecutiva;\nVIII. Secretaría Ejecutiva: a la Secretaría Ejecutiva del Sistema\nAnticorrupción del Estado de Campeche, misma que es el\nCoordinador;\nIX. Secretario Técnico: a la o el servidor público a cargo de las funciones de dirección de la Secretaría Ejecutiva, así como de las demás que le confiere la Ley del Sistema Anticorrupción del\nEstado de Campeche y la Ley de la Administración Publica\nParaestatal del Estado;\nX. Servidores Públicos: a cualquier persona que se ubique en alguno de los supuestos establecidos en el artículo 89 de la\nXI. Sistema de Información Estatal: al sistema receptor e integrador de la información que las autoridades conformantes del Sistema\nAnticorrupción incorporen para su transmisión e integración a la\nPlataforma Digital Nacional;\nXII. Sistema Anticorrupción: al Sistema Anticorrupción del Estado de Campeche;\nXIII. Sistema Nacional Anticorrupción: a la instancia de coordinación entre las autoridades de todos los órdenes de gobierno competentes en la prevención, detección y sanción de responsabilidades administrativas y hechos de corrupción, así como en la fiscalización y control de recursos públicos;\nXIV. Sistema Nacional de Fiscalización: al conjunto de mecanismos interinstitucionales de coordinación entre los órganos gubernamental en los distintos órdenes de gobierno, con el en todo el país, con base en una visión estratégica, la aplicación de estándares profesionales similares, la creación de capacidades y el intercambio efectivo de información, en incurrir en duplicidades u omisiones.\nARTÍCULO 5. El ejercicio de la administración de la Secretaría Ejecutiva corresponde a la o el Secretario Técnico, quien tendrá las atribuciones establecidas en la Ley del Sistema Anticorrupción del Estado de Campeche, en el presente\nReglamento y demás disposiciones relativas aplicables.\nCAPÍTULO II\nDE LOS ÓRGANOS DE LA SECRETARÍA EJECUTIVA\nARTÍCULO 6. Para el estudio y planeación de los asuntos que le competen, la\nSecretaría Ejecutiva contará con los siguientes órganos:\nI. Un Órgano de Gobierno,\nII. Una o un Secretario Técnico;\nIII. Una Comisión Ejecutiva; y\nIV. Un Órgano Interno de Control.\nARTÍCULO 7. El Órgano de Gobierno es la máxima autoridad de la Secretaría\nEjecutiva y sus determinaciones serán obligatorias para la o el Secretario Técnico y las unidades administrativas que integran al organismo.\nARTÍCULO 8. El Órgano de Gobierno acordará las bases generales para la distribución del Presupuesto autorizado y facultará a la o el Secretario Técnico para realizar las modificaciones necesarias para su ejercicio, de conformidad con las disposiciones jurídicas, debiendo este último informar a este Órgano.\nARTÍCULO 9. Para el uso y conservación de los archivos de la Secretaría Ejecutiva se procurará la utilización de dispositivos digitales y tecnológicos, por lo que en cualquier solicitud, requerimiento y entrega de información, se privilegiará que se haga través de los medios digitales que disponga la Secretaria Ejecutiva.\nARTÍCULO 10. El Órgano de Gobierno, además de las atribuciones establecidas en el articulo 67 de Ley de la Administración Pública Paraestatal del Estado de\nCampeche y demás ordenamientos jurídicos aplicables, contará con las atribuciones siguientes:\nI. Aprobar el Reglamento Interior de la Secretaría Ejecutiva, así como, en su caso, sus modificaciones;\nII. Autorizar el calendario anual de sesiones del ejercicio fiscal siguiente a más tardar en la última sesión ordinaria de cada ejercicio;\nIII. Autorizar los métodos o lineamientos que permitan el óptimo aprovechamiento de los bienes y recursos de la Secretaría Ejecutiva;\nIV. Autorizar y modificar, cuando sea necesario, la estructura y bases de organización de la Secretaría Ejecutiva en los términos previstos por Ley, para mejorar el desempeño de sus funciones, el cumplimiento de sus fines y la coordinación de sus actividades, previa opinión de la Secretaría de\nFinanzas;\nV. Previa propuesta del Secretario Técnico, nombrar y remover a las y los servidores públicos de la Secretaría Ejecutiva, con excepción del Órgano\nInterno de Control;\nVI. Analizar y aprobar, en su caso, los informes periódicos que rinda la o el\nSecretario Técnico;\nVII. Aprobar los manuales de organización y procedimientos que resulten necesarios para el cumplimiento de las funciones de la Secretaría Ejecutiva;\nVIII. Conocer los informes de gestión y desempeño de las actividades de la\nSecretaría Ejecutiva, incluido el ejercicio de los presupuestos, ingresos y egresos y los estados financieros correspondientes, así como, en su caso, formular observaciones de mejora;\nIX. Ratificar las donaciones de bienes muebles e inmuebles, en especie o dinero, que, a través de contrato o convenio respectivo, haya suscrito la o el\nSecretario Técnico;\nX. Expedir la normatividad complementaria o reglamentaria específica que derive del presente Reglamento, así como la que resulte necesaria para el adecuado funcionamiento de la Secretaría Ejecutiva; y\nXI. Las demás que le confiera la Ley y otras disposiciones legales, reglamentarias y normativas aplicables.\nARTÍCULO 11. Las sesiones del Órgano de Gobierno podrán ser ordinarias o extraordinarias. Las sesiones ordinarias se llevarán a cabo, cuando menos, una vez cada tres meses, a solicitud por escrito o por cualquier medio electrónico por parte de la o el Presidente de dicho órgano. Las sesiones extraordinarias serán convocadas por la o el Presidente del Órgano de Gobierno o a propuesta, por escrito o por cualquier medio electrónico, de cuatro integrantes de dicho órgano.\nPara la celebración de las sesiones, la convocatoria deberá acompañarse del orden del día y de la documentación correspondiente, las cuales deberán ser enviadas por la o el Secretario Técnico, por escrito o por los medios electrónicos que disponga la\nSecretaría Ejecutiva, y recibidas por las y los integrantes del Órgano de Gobierno, con una anticipación no menor de cinco días naturales, en el caso de las sesiones ordinarias, y con una anticipación no menor de dos días naturales, en el caso de las sesiones extraordinarias.\nSi la reunión convocada no pudiera llevarse a cabo en la fecha programada, se levantará el acta correspondiente asentándose los motivos, y aquélla deberá celebrarse dentro de los cinco días naturales siguientes.\nARTÍCULO 12. Para la celebración de las sesiones del Órgano de Gobierno será necesaria la asistencia de, por lo menos, la mitad más uno de sus integrantes.\nLas y los integrantes del Órgano de Gobierno podrán nombrar a sus suplentes, quienes tendrán las mismas funciones de sus titulares. Sus participaciones deberán asentarse en el acta que al efecto se levante, misma que deberá contener los acuerdos y determinaciones, así como la firma autógrafa de los participantes. En este rubro la o el Secretario Técnico tendrá voz, pero no voto. Los acuerdos y determinaciones del Órgano de Gobierno se tomarán siempre por mayoría de votos;\nen caso de empate, la o el Presidente del Órgano de Gobierno tendrá el voto de calidad.\nARTÍCULO 13. Para el despacho de los asuntos que competen a la Secretaría\nEjecutiva, además de los órganos señalados en el artículo 6 del presente\nReglamento, ésta contará con las siguientes unidades administrativas, mismas que estarán subordinadas jerárquicamente a la o el Secretario Técnico:\nI. Unidad de Vinculación, Evaluación y Administración;\nII. Unidad de Evaluación de Riesgos y Política Anticorrupción;\nIII. Unidad de Tecnologías y de Plataforma Digital;\nIV. Unidad Administrativa;\nV. Unidad Jurídica; y\nVI. Unidad de Transparencia.\nLa Secretaría Ejecutiva podrá contar con el personal de apoyo y administrativo que le permita su Presupuesto.\nCAPÍTULO III\nDE LA O EL SECRETARIO TÉCNICO\nARTÍCULO 14. Para la administración de la Secretaria Ejecutiva del Sistema\nAnticorrupción del Estado de Campeche, el Órgano de Gobierno nombrará una o un Secretario Técnico, conforme a lo señalado en el artículo 33 de la Ley del\nSistema Anticorrupción del Estado de Campeche, quien durará en su cargo por un periodo improrrogable de 5 años.\nARTÍCULO 15. La o el Secretario Técnico es la o el servidor público que tiene a su cargo las funciones de dirección de la Secretaría Ejecutiva.\nLa o el Secretario Técnico, además de las facultades que le señalan la Ley del\nPública Paraestatal del Estado de Campeche, tendrá las siguientes atribuciones:\nI. Planear, dirigir y controlar, técnica y administrativamente, el funcionamiento de la Secretaría Ejecutiva, de conformidad con las disposiciones legales aplicables;\nII. Ejercer el presupuesto anual de egresos de la Secretaria Ejecutiva, de conformidad con las disposiciones legales aplicables;\nIII. Elaborar y proponer al Órgano de Gobierno las modificaciones al Reglamento\nInterior de la Secretaría Ejecutiva;\nIV. Coordinar la comunicación del Sistema Estatal Anticorrupción;\nV. Actuar como secretaria o secretario del Comité Coordinador y del Órgano de\nGobierno;\nVI. Ejecutar y dar seguimiento a los acuerdos y resoluciones del Comité\nCoordinador y del Órgano de Gobierno;\nVII. Expedir certificaciones de los actos y documentos que emitan dentro de los procedimientos las unidades administrativas a cargo de la Secretaría\nEjecutiva, o que consten a los expedientes y archivos de las mismas;\nVIII. Elaborar los anteproyectos de metodologías, indicadores y políticas integrales para ser discutidas en la Comisión Ejecutiva y, en su caso, sometidas a la consideración del Comité Coordinador;\nIX. Realizar el trabajo técnico para la preparación de documentos que se llevarán como propuestas de acuerdo al Comité Coordinador, al Órgano de Gobierno\nX. Preparar el proyecto de calendario de los trabajos del Comité Coordinador, del Órgano de Gobierno y de la Comisión Ejecutiva;\nXI. Elaborar los anteproyectos de informes del Sistema Anticorrupción, someterlos a la revisión y observación de la Comisión Ejecutiva y remitirlos al Comité Coordinador para su aprobación;\nXII. Realizar estudios especializados en materias relacionadas con la prevención, detección y disuasión de hechos de corrupción y de faltas administrativas, Coordinador;\nXIII. Administrar el sistema estatal de información que establecerá, en términos de la Ley, el Comité Coordinador, así como asegurar el acceso al mismo de las y los miembros del Comité Coordinador y la Comisión Ejecutiva;\nXIV. Integrar los sistemas de información necesarios para que los resultados de política anticorrupción;\nXV. Suscribir y recibir todo tipo de donaciones, de bienes muebles e inmuebles, en especie o dinero, a través del contrato o convenio respectivo, que deberá ser ratificado por el órgano de gobierno, sin establecer obligación alguna con el donante, salvo en los casos estipulados por el Código Civil del Estado de\nCampeche y demás disposiciones aplicables.\nXVI. Autorizar y supervisar el buen uso del Fondo Fijo de la Secretaría Ejecutiva, de conformidad con las Políticas y los lineamientos establecidos al respecto;\nXVII. Representar legalmente a la Secretaría Ejecutiva con Poder Especial para pleitos y cobranzas, así como para actos de administración en términos del\nXVIII. Las demás facultades que las disposiciones legales le confieran expresamente, así como aquellas otras que con el carácter de no delegables le asigne el Órgano de Gobierno.\nARTÍCULO 16. Corresponde originariamente a la o el Secretario Técnico el trámite y la resolución de los asuntos de la competencia de la Secretaría Ejecutiva, quien, para la mayor distribución y desarrollo del trabajo, podrá delegar sus facultades a los responsables de las unidades administrativas, con excepción de las señaladas expresamente como indelegables en la Ley de la Administración Pública Paraestatal y en el presente Reglamento.\nCAPÍTULO IV\nDE LAS UNIDADES ADMINISTRATIVAS\nARTÍCULO 17. Las unidades administrativas tendrán las atribuciones generales siguientes:\nI. Proporcionar a la o el Secretario Técnico la información y el apoyo que les sean requeridos;\nII. Acordar con la o el Secretario Técnico la resolución de los asuntos a su cargo;\nIII. Ejercer las atribuciones que les sean delegadas y aquellas que les correspondan por suplencia, así como realizar los actos que les instruyan sus superiores;\nIV. Formular los dictámenes, opiniones e informes que les sean solicitados por la superioridad; y\nV. Las demás que le confiera la Ley y otras disposiciones legales y reglamentarias aplicables, y aquellas que le encomiende la o el Secretario\nTécnico.\nARTÍCULO 18. La Unidad de Vinculación, Evaluación y Administración tendrá las atribuciones siguientes:\nI. Planear, programar, organizar, dirigir, ejecutar, controlar y evaluar el desarrollo de los programas, proyectos y acciones de la Secretaría Ejecutiva e informar sobre los avances correspondientes a la o el Secretario Técnico;\nII. Rendir los informes necesarios y generar reportes sobre las actividades que se realicen en su ámbito de competencia, con la periodicidad que indique la o el Secretario Técnico;\nIII. Observar y ejecutar las normas, lineamientos y programas de trabajo que apruebe el Órgano de Gobierno;\nIV. Elaborar y ejecutar el Programa Anual de Trabajo que corresponda a la\nSecretaría Técnica;\nV. Elaborar y remitir a la Unidad de Planeación y Transparencia los informes trimestrales del avance de metas del Programa Anual de Trabajo; y\nVI. Las demás que le confiera la Ley y otras disposiciones legales y reglamentarias aplicables, y aquellas que le encomiende la o el Secretario\nTécnico.\nARTÍCULO 19. La Unidad de Evaluación de Riesgos y Política Anticorrupción tendrá las atribuciones siguientes:\nI. Elaborar y proponer los lineamientos en materia de Evaluación de Riesgos;\nII. Proponer a la o el Secretario Técnico políticas encaminadas a la prevención, detección y disuasión de hechos de corrupción y faltas administrativas;\nIII. Elaborar y someter a consideración de la o el Secretario Técnico los anteproyectos de metodologías, indicadores y políticas integrales a que hace referencia la Ley del Sistema Anticorrupción del Estado de Campeche;\nIV. Diseñar y someter a consideración de la o el Secretario Técnico las propuestas de las evaluaciones de las políticas integrales que se lleven a cabo;\nV. Realizar estudios especializados en materias relacionadas con la prevención, detección y disuasión de hechos de corrupción y faltas administrativas, Técnico;\nVI. Elaborar, impulsar y participar en la ejecución de los programas conjuntos y coordinados de promoción, difusión y vinculación que impulse la Secretaría\nEjecutiva como parte de la agenda del Sistema Estatal Anticorrupción;\nVII. Elaborar el anteproyecto de informe anual a cargo del Comité Coordinador, presentarlo ante la o el Secretario Técnico;\nVIII. Diseñar políticas de ética e integridad en el servicio público y coordinar las acciones institucionales de la Secretaría Ejecutiva para tal efecto; y\nIX. Las demás que le confiera la Ley y otras disposiciones legales, reglamentarias y normativas aplicables, y aquellas que le encomiende la o el\nSecretario Técnico.\nARTÍCULO 20. La Unidad de Tecnologías y Plataforma Digital tendrá las atribuciones siguientes:\nI. Proponer a la o el Secretario Técnico la implementación de las tecnologías\nEstatal Anticorrupción y de la Secretaría Ejecutiva, para el debido cumplimiento de sus atribuciones;\nII. Desarrollar y proponer a la o el Secretario Técnico los sistemas de información necesarios para que los resultados de las evaluaciones sean públicos y reflejen los avances o retrocesos en la política estatal anticorrupción;\nIII. Diseñar, establecer e implementar mecanismos de interoperabilidad e interconexión entre la Plataforma Digital Estatal, la Plataforma Digital\nNacional y demás plataformas digitales, sistemas y aplicaciones informáticas con las que se suministre o intercambie información;\nIV. Desarrollar, mantener, actualizar y evaluar los servicios de las plataformas digitales cuya administración corresponda a la o el Secretario Técnico;\nV. Proponer la instauración de mecanismos de organización de la información que permitan la adecuada interacción entre los diversos sistemas de las entidades integrantes del Sistema Estatal Anticorrupción;\nVI. Promover la implementación de sistemas de información al interior de la\nSecretaría Ejecutiva, en coordinación con el resto de las unidades administrativas;\nVII. Desarrollar proyectos estratégicos en materia de informática y tecnologías de la información y comunicación para el cumplimiento de los objetivos institucionales;\nVIII. Elaborar programas institucionales en materia de informática, tecnologías de\nAnticorrupción, de conformidad con la normatividad aplicable;\nIX. Difundir lineamientos, catálogos y normatividad informática de manera\nAnticorrupción;\nX. Diseñar, coordinar y supervisar la aplicación, el desarrollo y la difusión de políticas y estándares en materia de seguridad informática, de telecomunicaciones y ciberseguridad para la Secretaría Ejecutiva, Anticorrupción;\nXI. Diseñar, coordinar e implementar mecanismos de transparencia proactiva, datos abiertos, minería de datos, procesamiento masivo e inteligencia que incrementen el valor, análisis y efectos de la información contenida en la\nPlataforma Digital Estatal;\nXII. Diseñar, coordinar y supervisar mecanismos tecnológicos para la recepción, gestión y trámite de denuncias, de conformidad con la Ley;\nXIII. Brindar la asesoría y el apoyo técnico a las instancias que integran el Sistema\nEstatal y Municipal Anticorrupción, que se requiera con motivo de la operación de la Plataforma Digital Estatal;\nXIV. Fungir como enlace ante unidades de tecnologías de la información y comunicación o equivalentes de las instancias que participan en la integración y operación de la Plataforma Digital Estatal y su conexión con otras plataformas, conforme a la normatividad aplicable;\nXV. Administrar y proporcionar las tecnologías de la información y comunicación para alcanzar las metas y objetivos de la Secretaría Ejecutiva;\nXVI. Proponer y participar, en coordinación con las demás unidades administrativas de la Secretaría Ejecutiva, la automatización de los procesos sustantivos y de apoyo susceptibles de ser soportados por tecnologías de la información y comunicación;\nXVII. Diseñar, desarrollar, implementar y actualizar la imagen gráfica, institucional y multimedia para proyectos dirigidos a las tecnologías de la información y comunicación, en coordinación con la Dirección General de Vinculación\nInterinstitucional del Sistema Nacional Anticorrupción, de conformidad con la normatividad aplicable;\nXVIII. Administrar y proporcionar las tecnologías de la información y comunicación necesarias para mantener actualizada la Información Digital Estatal con la\nPlataforma Digital Nacional, conforme a la normatividad aplicable;\nXIX. Coordinar los trabajos en materia de gobierno digital que resulten exigibles a la Secretaría Ejecutiva; y\nXX. Las demás que le confiera la Ley y otras disposiciones legales, reglamentarias y normativas aplicables, y aquellas que le encomiende la o el\nSecretario Técnico.\nARTÍCULO 21. La Unidad Administrativa tendrá las atribuciones siguientes:\nI. Dirigir, ejecutar y valuar las políticas, lineamientos y programas de la\nSecretaría Ejecutiva en materia de administración de personal, recursos materiales, financieros y servicios generales de acuerdo a la normatividad aplicable;\nII. Integrar el anteproyecto anual de presupuesto y estuctura programática de la\nSecretaría Ejecutiva, de acuerdo a la normativa aplicable y controlar la aplicación del ejercicio presupuestal;\nIII. Controlar y evaluar la contabilidad y tesorería de la Secretaría Ejecutiva;\nIV. Ejercer las políticas de pago, así como planear y evaluar la programación de programado;\nV. Llevar el proceso para el reclutamiento, selección y contratación del personal adscrito a la Secretaría Ejecutiva;\nVI. Proponer a la o el Secretario Técnico, el proceso de estructura o restructuración de la Secretaría Ejecutiva, y en su caso dirigir el proceso que se autorice;\nVII. Realizar las modificaciones de la plantilla de personal; así como coordinar la administración del personal de la Secretaría Ejecutiva;\nVIII. Administrar los procesos relativos a la gestión de los recursos humanos de la Secretaría Ejecutiva;\nIX. Coordinar la elaboración y actualización de los manuales administrativos, lineamientos, programas y demás disposiciones necesarias para el debido funcionamiento de la Secretaría Ejecutiva, en colaboración con las áreas de la misma que resulten competentes;\nX. Coordinar y supervisar el proceso de capacitación del personal adscrito a la\nSecretaría Ejecutiva;\nXI. Elaborar la propuesta del Programa Anual de Adquisiciones, Arrendamientos y Servicios de cada ejercicio fiscal, en términos de las disposiciones aplicables;\nXII. Gestionar la adquisición de bienes y servicios necesarios para el debido funcionamiento de la Secretaría Ejecutiva, así como suministrar los mismos;\nXIII. Llevar el registro y control interno de los bienes muebles e inmuebles asignados a la Secretaría Ejecutiva, asi como proponer y llevar a cabo la baja\nXIV. Analizar y jerarquizar las necesidades de bienes muebles e inmuebles de la\nSecretaría Ejecutiva, para hacer las propuestas correspondientes, en función a la disponibilidad presupuestal;\nXV. Establecer los mecanismos de control necesarios que coadyuven a la obtención de los resultados programados, a la protección de los recursos de la Secretaría Ejecutiva;\nXVI. Coordinar el proceso de manejo y control de archivo de la Secretaría\nEjecutiva, de acuerdo con la normatividad en la materia y en apego a los lineamientos establecidos por el organismo descentralizado normativo;\nXVII. Integrar el Programa Operativo Anual de la Secretaría Ejecutiva y presentar\nXVIII. Administrar y controlar los recursos humanos, financieros y materiales, con base al presupuesto de Egresos autorizado;\nXIX. Tramitar, previo acuerdo con la o el Secretario Técnico, los movimientos de alta, baja o cambios de adscripción del personal adscrito a la Secretaria\nEjecutiva, integrando y resguardando los expedientes de los mismos;\nXX. Gestionar cursos de capacitación del personal adscrito, así como de personal de servicio social o prácticas profesionales;\nXXI. Hacer del conocimiento al Órgano Interno de Control, las conductas que puedan constituir faltas administrativas por parte de los servidores públicos adscritos.\nXXII. Recibir, revisar y validar las facturas y demás documentos que consignen obligaciones de pago con cargo a la Secretaría Ejecutiva, con motivo de la adquisición de bienes, contratación de servicios, arrendamientos y servicios relacionados con la misma, así como los que se generen por la tramitación de viáticos, pasajes, entre otros;\nXXIII. Supervisar la elaboración de informes sobre los estados mensuales de contabilidad, balances ordinarios y extraordinarios y rendir los estados financieros que le sean requeridos;\nXXIV. Resguardar copia de la información financiera, presupuestal y contable para la comprobación y justificación del origen y aplicación del gasto;\nXXV. Atender las revisiones de auditoría interna y externa, proporcionando información contable;\nXXVI. Elaborar el control del presupuesto de Ingresos y Egresos de la Secretaría\nEjecutiva, en coordinación con todas áreas;\nXXVII. Elaborar y proponer el Programa Anual de Adquisiciones, Arrendamientos y\nServicios, así como sus respectivos presupuestos, con base en los requerimientos de las unidades administrativas;\nXXVIII. Supervisar y realizar la actualización de los inventarios y resguardos de bienes muebles, inmuebles, de consumo, equipo de cómputo, comunicación y parque vehicular, así como tramitar en su caso, la depreciación y baja en el padrón respectivo;\nXXIX. Coordinar las actividades de entrega-recepción, solicitando al Órgano Interno de Control su intervención.\nXXX. Realizar los pagos de Impuestos y Derechos Federales y Estatales; y\nXXXI. Las demás que le señale este reglamento, otras disposiciones jurídicas y la o el Secretario Técnico.\nARTÍCULO 22. La Unidad Jurídica tendrá las atribuciones siguientes:\nI. Asesorar a las Coordinaciones en los lineamientos jurídicos para la formulación de Contratos, Convenios, Planes y Programas;\nII. Efectuar análisis jurídicos de los proyectos que genere la Secretaria\nEjecutiva;\nIII. Asesorar en la elaboración de sus Matrices de Indicadores, respecto al marco legal;\nIV. Dar contestación a los diferentes requerimientos que se hagan a la Secretaría\nEjecutiva por los diferentes órganos de fiscalización;\nV. Coadyuvar con la Secretaría Ejecutiva en los juicios de amparo cuando tenga el carácter de quejoso la autoridad responsable o intervenir como tercero interesado y, en general, formular todas las promociones que a dichos juicios se refieran;\nVI. Coadyuvar con la Secretaría Ejecutiva en la presentación de denuncias y/o querellas que legalmente procedan por la comisión de delitos cometidos por servidores públicos o particulares, cuando afecten sus intereses jurídicos o legítimos;\nVII. Emitir opinión sobre los ordenamientos legales aplicables en el ámbito de competencia de la Secretaría Ejecutiva, así como los criterios de interpretación administrativa y aplicación jurídica que soliciten las unidades administrativas;\nVIII. Asesorar jurídicamente a las unidades administrativas de la Secretaría\nEjecutiva, cuándo éstas lo soliciten;\nIX. Compilar y promover la difusión de normas jurídicas relacionadas con las funciones de la Secretaría Ejecutiva.\nX. Coadyuvar con la Secretaría Ejecutiva, o demás unidades administrativas que la conforman, en los procedimientos en los que sea parte o intervenga la\nSecretaría Ejecutiva; y\nXI. Las demás que le señale este reglamento, otras disposiciones jurídicas y la o el Secretario Técnico.\nARTÍCULO 23. La Unidad de Transparencia tendrá las atribuciones que le confieran la normatividad vigente en materia de transparencia, acceso a la información, protección de datos personales y gestión documental.\nCAPÍTULO IV\nDEL ÓRGANO INTERNO DE CONTROL\nARTÍCULO 24. Al frente del Órgano Interno de Control habrá un titular designado quien, para el ejercicio de sus atribuciones, se auxiliará por las o los servidores públicos que se requieran para satisfacer las necesidades del servicio, de conformidad con la estructura orgánica aprobada y presupuesto autorizado, quien aplicables.\nartículo 27 de la Ley.\nCAPÍTULO V\nDE LA COMISIÓN EJECUTIVA\nARTÍCULO 25.- Para poder sesionar válidamente, la Comisión Ejecutiva requerirá de la asistencia de, por lo menos, dos miembros del Comité de Participación\nCiudadana que lo integran y de la o el Secretario Técnico.\nARTÍCULO 26. Las sesiones de la Comisión Ejecutiva podrán ser ordinarias y extraordinarias, y deberá llevarse a cabo, por lo menos, una sesión ordinaria cada tres meses. Las sesiones ordinarias serán convocadas por la o el Secretario\nTécnico, por escrito o cualquier medio electrónico. Las sesiones extraordinarias serán convocadas por la o el Secretario Técnico o a solicitud por escrito o cualquier medio electrónico de los cuatro integrantes del Comité de Participación Ciudadana, expresando los motivos de la sesión.\nPara la celebración de las sesiones, la convocatoria deberá de acompañarse del orden del día y de la documentación correspondiente, las cuales deberán ser\nComité de Participación Ciudadana con una anticipación, tratándose de sesiones ordinarias, de cuando menos cinco días naturales, y en el caso de las sesiones extraordinarias con una anticipación no menor de dos días naturales.\nSi la reunión convocada no pudiera llevarse a cabo en la fecha programada, deberá dentro de los cinco días naturales siguientes.\ninjustificadamente a las sesiones convocadas, tratándose de alguna o algún miembro del Comité de Participación Ciudadana, será motivo para rescindir la prestación establecida en el artículo 17 de la Ley. En el caso de la o el Secretario\nTécnico, se sujetará a lo señalado en el artículo 33 de la Ley.\nARTÍCULO 27. Las y los miembros, bajo causa justificada, con excepción de la o el\nSecretario Técnico, podrán participar en las sesiones de la Comisión Ejecutiva vía remota, lo que deberá ser asentado en el acta que al efecto se levante, misma que deberá contener los acuerdos y determinaciones aprobados, la cual se perfeccionará con la firma autógrafa de los participantes.\nLa participación vía remota se llevará a cabo conforme a los lineamientos que al efecto emita la Comisión Ejecutiva.\nLos acuerdos y determinaciones de la Comisión Ejecutiva se tomarán siempre por mayoría de votos; en caso de empate, el Secretario Técnico tendrá el voto de calidad.\nCAPÍTULO VI\nDE LAS SUPLENCIAS\nARTÍCULO 28. Las ausencias de la o el Secretario Técnico serán suplidas por la o el titular de la Unidad de Vinculación, Evaluación y Administración, quien fungirá como encargada o encargado de despacho por el tiempo que dure la ausencia y tendrá las facultades inherentes a las de aquella o aquél. Si la ausencia de la o el\nSecretario Técnico excede del plazo de 15 dias naturales, será suplido por la o el servidor público que designe el Órgano de Gobierno.\nsuplidas por la o el servidor público que designe la o el Secretario Técnico.\nCAPÍTULO VI\nDEL PROCEDIMIENTO DE ENTREGA RECEPCIÓN\nARTÍCULO 29. Los procedimientos de Entrega-Recepción de la Secretaría\nProcedimientos de Entrega Recepción del Estado de Campeche y sus Municipios.\nTRANSITORIOS\nPRIMERO. Este Reglamento entrará en vigor al día siguiente de su publicación en el Periódico Oficial del Estado.\nSEGUNDO. Los casos no previstos en el presente Reglamento serán resueltos por la o el Secretario Técnico, quien deberá elaborar un dictamen jurídico al Órgano de\nGobierno a más tardar en la siguiente sesión ordinaria del dicho órgano, el cual determinará si resulta necesaria la modificación al Reglamento, o en su caso, la emisión de normatividad complementaria.\nTERCERO. Se derogan todas las disposiciones legales y reglamentarias de igual o menor jerarquía del marco jurídico estatal, en lo que se opongan al contenido del presente Acuerdo.\nDado en la ciudad de San Francisco de Campeche, Municipio y Estado de\nCampeche, a los siete días del mes de febrero del año dos mil veinte.\nINTEGRANTES DEL ÓRGANO DE\nDEL SISTEMA ANTICORRUPCIÓN DEL\nESTADO DE CAMPECHE\nMtra. María de los Dolores Ortiz Lanz\nMtro. Jorge Alejandro Arcila R. de la Gala\nAuditor Superior del Estado\nDra. Silvia del Carmen Moguel Ortiz\nMtra. Elvira de los Ángeles López González\nMtra. Fabiola Irasema Barrera González\nLic. José Echavarría Trejo\nPública del Estado\nMtra. Alfa Omega Burgos Che\nCampeche\nTABLA DE REFORMA, MODIFICACIÓN, ADICIÓN, ABROGACIÓN, FE DE ERRATAS y\nACLARACIÓN\nPeriódico Oficial del Estado 03 DE MARZO 2020 DEROGACIÓN de Campeche\nInterior de la Secretaria Ejecutiva del Sistema Anticorrupción del Estado de Campeche.",
  "ordenamiento": "REGLAMENTO",
  "jurisdiccion": "CAMPECHE",
  "fuente_oficial": "DIARIO OFICIAL DE LA FEDERACION",
  "Fecha de Publicación": "11 de diciembre de 2019",
  "es_escaneado": false,
  "tiene_tablas": true,
  "materia": [
    "municipal",
    "anticorrupción"
  ]
}