{
  "titulo": "Reglamento Interior de la Secretaría de Finanzas de la Administración Pública del Estado de Campeche",
  "Contenido": "en ejercicio de la facultad que me confieren los artículos 71, fracción XIX y 73 de la Constitución Política del\nEstado de Campeche y, con fundamento en lo que disponen los artículos 3, 8, 10, 12, 14, 15, 16 fracción II, 17, 19 y 22 de la Ley Orgánica de la Administración Pública del Estado de Campeche; y\nCONSIDERANDO:\nAdministración Pública y el número de dependencias que establezca la Ley Orgánica relativa, que distribuirá las nombrar a los Titulares de las mismas”.\nQue con fundamento en el artículo antes señalado se reformó la Ley Orgánica de la Administración Pública del\nEstado de Campeche, misma que fue publicada el día 22 de diciembre de 2016 mediante decreto número 100 en el Periódico Oficial del Estado, y que entró en vigor al día siguiente de su publicación, de conformidad con su\nArtículo Transitorio Primero.\nQue en el capítulo segundo de la Ley Orgánica de la Administración Pública del Estado de Campeche se establecen las disposiciones relacionadas con la administración pública centralizada, considerándose a la\nSecretaría de Finanzas como una de estas dependencias, como se desprende de la fracción II del artículo 16 y señalándose sus atribuciones generales en el artículo 22 de la citada Ley.\nQue la Ley del Servicio de Administración Fiscal del Estado de Campeche expedida mediante Decreto número 100 de fecha 22 de diciembre de 2016, crea y regula la organización y funcionamiento del órgano desconcentrado denominado “Servicio de Administración Fiscal del Estado de Campeche”.\nQue el “Servicio de Administración Fiscal del Estado de Campeche” es un órgano desconcentrado adscrito a la\nSecretaría de Finanzas, que se constituye como una autoridad fiscal responsable de aplicar la legislación fiscal del Estado, de recaudar los impuestos y contribuciones y aprovechamientos a que tiene derecho a percibir el\nEstado de Campeche, incluyendo la administración de los ingresos fiscales federales y municipales, en virtud de los convenios celebrados, en su caso, con uno y otro ámbito de gobierno.\nQue en cumplimiento de su objeto, el “Servicio de Administración Fiscal del Estado de Campeche” se integrará por las unidades administrativas necesarias que le sean aprobadas por parte de las autoridades competentes.\nQue el Reglamento Interior del “Servicio de Administración Fiscal del Estado de Campeche” fundamenta y regula su estructura y funcionamiento, señalando las áreas administrativas que lo integran, mismas cuyas\nAtención y Servicios al Contribuyente; Dirección Jurídica de Ingresos; Dirección Jurídica; y Dirección de\nInformática, en lo que respecta a la administración de ingresos.\nde Finanzas, basado en una normatividad actualizada, armonizada y congruente con las funciones operativas de administración fiscal que hoy recaen en el “Servicio de Administración Fiscal del Estado de Campeche”.\nQue con base en lo anterior, tengo a bien expedir el siguiente:\nCAPÍTULO I\nDE LA COMPETENCIA Y ORGANIZACIÓN\nArtículo 1.- El presente Reglamento tiene por objeto definir las atribuciones y competencias de la Secretaría de\nFinanzas y de las unidades administrativas que la conforman y para los efectos del mismo se entenderá por:\nI. La Secretaría: Secretaría de Finanzas; y\nII. El Servicio: El Servicio de Administración Fiscal del Estado de Campeche.\nArtículo 2.- La Secretaría es una dependencia de la Administración Pública Estatal centralizada que tiene a su cargo las funciones previstas en el artículo 22 de la Ley Orgánica de la Administración Pública del Estado de\nCampeche; así como las demás atribuciones que le confieren las leyes locales vigentes, reglamentos, decretos, acuerdos, convenios y anexos, circulares y órdenes del Ejecutivo del Estado.\nArtículo 3.- Al frente de La Secretaría habrá un titular quien tendrá rango de Secretario de la Administración\nPública centralizada del Estado de Campeche, en términos de la Ley Orgánica de la Administración Pública del\nEstado de Campeche, quien para el desahogo de los asuntos de su competencia, se auxiliará de los servidores públicos y unidades administrativas siguientes:\nA. Unidades Administrativas:\nI. Oficina del Secretario;\nII. Subsecretaría de Ingresos;\nIII. Subsecretaría de Egresos;\nIV. Subsecretaría de Programación y Presupuesto;\nV. Procuraduría Fiscal;\nVI. Dirección de Contabilidad Gubernamental;\nVII. Dirección de Egresos;\nVIII. Dirección de Programación;\nIX. Dirección de Presupuesto;\nX. Dirección de Política Financiera;\nXI. Dirección de Enlace en Proyectos de Inversión;\nXII. Dirección de Informática;\nXIII. Unidad de Política de Ingresos y Coordinación Fiscal;\nXIV. Coordinación Administrativa;\nXV. Secretaría Técnica; y\nXVI. Unidad de Transparencia.\nB. Órganos Desconcentrados:\nI. Servicio de Administración Fiscal del Estado de Campeche.\nLa Secretaría y sus unidades administrativas tendrán su sede en la ciudad de San Francisco de Campeche, Municipio de Campeche, perteneciente al Estado de Campeche, y ejercerán sus facultades dentro de la circunscripción territorial del Estado de Campeche.\nArtículo 4.- Las unidades administrativas de La Secretaría quedan adscritas de la siguiente forma:\nI. A la Oficina del Titular de La Secretaría:\na) La Dirección de Enlace en Proyectos de Inversión;\nb) La Dirección de Informática;\nc) La Coordinación Administrativa;\nd) La Secretaría Técnica; y\ne) La Unidad de Transparencia.\nII. A la Subsecretaría de Ingresos:\na) La Unidad de Política de Ingresos y Coordinación Fiscal;\nIII. A la Subsecretaría de Egresos:\na) La Dirección de Política Financiera;\nb) La Dirección de Egresos; y\nc) La Dirección de Contabilidad Gubernamental.\nIV. A la Subsecretaría de Programación y Presupuesto:\na) La Dirección de Programación; y\nb) La Dirección de Presupuesto.\nV. Procuraduría Fiscal.\nArtículo 5.- Para el desempeño de sus actividades, La Secretaría contará también con las unidades subalternas que figuren en su presupuesto, cuyas funciones deberán especificarse y regularse en el manual de organización de la propia Secretaría y, en su caso, en los de sus órganos administrativos desconcentrados.\nAl frente de las Subsecretarías, Direcciones, Secretaría Técnica y demás unidades administrativas habrá un titular que asumirá la responsabilidad de su funcionamiento y ejercerá sus atribuciones de conformidad con lo establecido en este Reglamento, los lineamientos, normas y políticas que fije el titular de la Secretaría, así como con en las demás disposiciones legales y reglamentarias aplicables; y serán auxiliados en sus funciones por los Subdirectores, Asesores, Coordinadores, Jefes de Departamento, Jefes de Unidad, Analistas\nEspecializados, Analistas, Cajeros, y demás servidores públicos que señale el Tabulador de Puestos cualquiera que fuere la denominación del cargo, así como por el personal que se requiera para satisfacer las necesidades del servicio.\nLa Procuraduría Fiscal tendrá administrativamente el rango de subsecretaría, la Unidad de Política de Ingresos y Coordinación Fiscal tendrá administrativamente el rango de subdirección para todos los efectos de este\nReglamento.\nArtículo 6.- La Secretaría, a través de sus unidades administrativas, planeará y conducirá sus actividades conforme a los objetivos, estrategias y programas establecidos en el marco jurídico que rige en el Estado, el\nSistema Estatal de Planeación, el Plan Estatal de Desarrollo, así como la política y programas que determine el\nGobernador del Estado.\nArtículo 7.- La Secretaría contará con un órgano interno de control, cuyo titular y personal estará adscrito presupuestal y orgánicamente a la Secretaría de Contraloría, y tendrá a su cargo el ejercicio de las facultades que le confiera la legislación en materia de responsabilidades administrativas y las atribuciones que le señale el reglamento interior de la Secretaría de la Contraloría.\nArtículo 8.- Las facultades ejecutivas, estructura organizacional y demás atribuciones del Servicio de\nAdministración Fiscal del Estado de Campeche SEAFI, serán las que expresamente se señalen en la Ley del\nServicio de Administración Fiscal del Estado de Campeche, así como en su reglamento interior.\nCAPÍTULO II\nDE LAS FACULTADES DEL SECRETARIO\nArtículo 9.- El Secretario podrá delegar sus facultades en los servidores públicos de la dependencia a su cargo, de conformidad al presente Reglamento, a excepción de las facultades establecidas en las fracciones I, III, VII, VIII, XIII, XVII, XVIII XIX XX y XXI, del artículo 10 de este Reglamento, que con arreglo al mismo deban ser ejercidas directamente por él.\nTodas las facultades que en este Reglamento competen a La Secretaría, incluidas sus unidades administrativas enlistadas en el artículo 4, corresponden originalmente al Secretario, quien podrá ejercerlas en cualquier tiempo.\nArtículo 10.- El Secretario tendrá las siguientes facultades:\nI. Representar al Gobernador del Estado cuando se requiera, en los asuntos de su competencia;\nII. Representar legalmente a La Secretaría, tanto en su carácter de autoridad fiscal, como de autoridad administrativa, así como a las unidades administrativas que la conforman, con la suma de facultades generales y especiales que, en su caso, requiera conforme a la legislación aplicable;\nIII. Fijar y dirigir, previo acuerdo del Ejecutivo del Estado, las políticas de la administración financiera y tributaria de la Hacienda Pública del Estado;\nIV. Proponer al Ejecutivo del Estado los proyectos de leyes, reglamentos, decretos, acuerdos y demás disposiciones sobre los asuntos que son de la competencia de La Secretaría y de las entidades del sector;\nV. Someter a consideración del Gobernador del Estado los asuntos cuyo despacho corresponde a La\nSecretaría e informarle sobre el desarrollo de las actividades de la dependencia, así como del desempeño de las comisiones y funciones que le confiera;\nVI. Autorizar presupuestalmente las estructuras orgánicas y ocupacionales de las dependencias y entidades de la administración pública estatal y sus modificaciones;\nVII. Refrendar los acuerdos, reglamentos, órdenes y demás disposiciones que expida el Ejecutivo, cuando se refieran a asuntos de la competencia de La Secretaría;\nVIII. Suscribir, previo acuerdo del Gobernador, los contratos, convenios, anexos, títulos de crédito y demás actos jurídicos en representación del Estado, en la materia de su competencia;\nIX. Someter a consideración del Gobernador del Estado la expedición de los manuales administrativos de la dependencia;\nX. Establecer los lineamientos para difundir la información sobre las funciones y actividades de La\nSecretaría;\nXI. Proponer al Gobernador del Estado la proyección y cálculo de los ingresos del Estado, considerando las necesidades del gasto público estatal así como la utilización razonable del crédito público y el saneamiento de las finanzas públicas del propio Estado;\nXII. Formular la cuenta pública anual de la Hacienda Estatal, incluyendo la glosa de los ingresos y egresos del Estado y someterlas a la consideración del Gobernador; así como mantener las relaciones procedentes con la Auditoría Superior del Estado;\nXIII. Dictar las normas relacionadas con la administración de fondos y valores de las dependencias de la\nAdministración Pública Estatal y fideicomisos constituidos por el Estado; vigilar, evaluar la operación y autorizar la constitución o incremento del patrimonio de esos fideicomisos, así como la modificación de sus estructuras, sin perjuicio de lo que establezcan las leyes aplicables en materia de fideicomisos, así como custodiar los documentos que constituyen valores, acciones y demás derechos que formen parte del patrimonio del Estado;\nXIV. Integrar el Programa General de Gasto Público y el anteproyecto de Presupuesto de Egresos en términos de la Ley General de Contabilidad Gubernamental y la Ley de Disciplina Financiera para las\nEntidades Federativas y los Municipios;\nXV. Verificar los resultados de los programas y presupuestos de las dependencias y, en su caso, de las entidades de la Administración Pública Paraestatal;\nXVI. Analizar y autorizar las modificaciones y transferencias programáticas y presupuestales conforme a la normatividad que se emita al respecto;\nXVII. Llevar a cabo la negociación y contratación de financiamientos, obligaciones y deuda pública del\nEstado, llevar su registro y control, así como vigilar y registrar la de las entidades paraestatales, municipios y Paramunicipales, en los términos de la ley estatal en la materia;\nXVIII. Representar al Estado en los foros, comisiones y reuniones internacionales, nacionales, regionales, zonales o de grupo establecidos en la Ley de Coordinación Fiscal;\nXIX. Proponer al Gobernador el nombramiento y la remoción de los titulares de las Subsecretarías;\nconcederles licencia y aceptarles su renuncia;\nXX. Nombrar y remover a los titulares de las Direcciones, Coordinación Administrativa y Secretaría Técnica, y demás personal de La Secretaría; así como concederles licencia y aceptarles su renuncia;\nXXI. Designar a los representantes de La Secretaría en las comisiones, congresos, consejos, organizaciones, instituciones y entidades municipales, estatales y federales en los que participe;\nXXII. Prestar a los municipios, cuando así se lo soliciten, la asesoría y el apoyo técnico necesarios en materia hacendaria;\nXXIII. Dictar la normatividad necesaria para el control, supervisión, vigilancia y evaluación de las actividades de El Servicio;\nXXIV. Llevar el sistema de registros y control de las erogaciones de servicios personales;\nXXV. Emitir la relación de las entidades paraestatales de la Administración pública estatal, con base en lo dispuesto por el artículo 10 de la Ley de la Administración Pública Paraestatal y el artículo 53 de la Ley\nOrgánica de la Administración Pública del Estado de Campeche; y\nXXVI. Las demás que le señalen otras disposiciones legales o reglamentarias y el depositario del Poder\nEjecutivo Estatal.\nCAPÍTULO III\nDE LAS ATRIBUCIONES GENÉRICAS DE LOS SUBSECRETARIOS\nArtículo 11.- Los Subsecretarios tendrán las siguientes facultades de carácter general:\nI. Acordar con el Secretario los asuntos de su competencia;\nII. Recibir en acuerdo a los titulares de las unidades administrativas de su adscripción y resolver los asuntos que sean competencia de las mismas; así como conceder audiencias al público;\nIII. Someter a la consideración del Secretario los anteproyectos de leyes, reglamentos, decretos, acuerdos, circulares, convenios, contratos y órdenes en los asuntos de la competencia de las unidades administrativas adscritas a su responsabilidad;\nIV. Coordinarse con las demás unidades administrativas de La Secretaría para mejorar el desempeño de sus facultades;\nV. Programar, organizar, dirigir y evaluar las actividades de las unidades administrativas a ellos adscritas, conforme a los lineamientos que determine el Secretario;\nVI. Formular el anteproyecto de presupuesto de las unidades administrativas adscritas a su responsabilidad;\nVII. Hacer estudios sobre la organización de las unidades administrativas adscritas a su cargo y proponer las medidas que procedan, para el mejor desempeño de sus funciones;\nVIII. Proporcionar la información y la cooperación técnica que le sean solicitadas por otras dependencias de la Administración Pública Estatal, de acuerdo con las políticas establecidas al respecto;\nIX. Proponer los datos de las labores desarrolladas por sus áreas, para la formulación del informe anual del Gobernador;\nX. Expedir certificaciones de los documentos y expedientes relativos a los asuntos de su competencia o de las unidades administrativas que tengan adscritas a sus áreas;\nXI. Proponer al Secretario la designación del personal de las unidades administrativas a su cargo y el otorgamiento de las licencias;\nXII. Cumplimentar las resoluciones, autos, mandamientos y ejecutorias de autoridades judiciales y/o administrativas en el ámbito federal o estatal, que le sean hechos del conocimiento por conducto de esas mismas autoridades o a través de la Procuraduría Fiscal; y\nXIII. Las demás que les señalen otras disposiciones legales o reglamentarias.\nCAPÍTULO IV\nDE LAS ATRIBUCIONES ESPECÍFICAS DE LOS SUBSECRETARIOS\nArtículo 12.- Compete a la Subsecretaría de Ingresos:\nI. Proponer para aprobación superior los proyectos de política de ingresos del Estado;\nII. Formular las alternativas de política de ingresos, así como analizar su impacto por regiones y sectores económicos, estimar las metas de recaudación y evaluar los resultados obtenidos;\nIII. Proponer, vigilar y coordinar la aplicación de las políticas, directrices, normas y criterios técnicos que administrativas de la Subsecretaría, para la mejor organización y funcionamiento de la misma;\nIV. Formular en coordinación con El Servicio, el anteproyecto del presupuesto anual de ingresos, para la aprobación del Secretario; para lo cual deberá tomar en consideración el gasto público estatal, la corresponda;\nV. Estudiar y proponer al Secretario modificaciones al Sistema de Coordinación Fiscal Estatal;\nVI. Proponer al Secretario, en cuanto a las participaciones federales a que tenga derecho el Estado, la aplicación de las bases legales para el reparto de aquellas a las que tengan derecho los Municipios, en términos de lo establecido por la Ley del Sistema de Coordinación Fiscal del Estado de Campeche; y\nVII. Las demás que le señalen otras disposiciones legales y reglamentarias, o contenidas en los convenios y sus anexos celebrados en materia fiscal en que el Estado sea parte.\nadscritas a la Subsecretaría de Ingresos, se entenderán conferidas también al Subsecretario de Ingresos, quien podrá ejercerlas directamente en cualquier tiempo.\nArtículo 13.- Compete a la Subsecretaría de Egresos:\nI. Concentrar, custodiar, vigilar y situar los fondos provenientes de la aplicación de la Ley de Ingresos del\nEstado de Campeche, y otros conceptos que deba percibir éste, por cuenta propia o ajena, afectando los depósitos diarios correspondientes en las cuentas que para el efecto tenga dicho Estado;\nII. Participar en la formulación de la Política de Ingresos, tanto del Estado como de los fideicomisos constituidos por éste, y formular el programa financiero estatal y la política de endeudamiento, sometiéndolos a la consideración del Secretario;\nIII. Ejercer, previo acuerdo del Secretario, y conforme a las disposiciones legales aplicables las facultades en materia de análisis, estudios, programación, negociación, contratación, autorización y registro de las operaciones Financiamientos, Obligaciones y de Deuda Pública Estatal;\nIV. Supervisar que se elaboren los informes de la situación financiera de la Deuda Pública del Estado para proceder a solicitar la publicación en el Periódico Oficial del Estado e informar al H.Congreso Estatal;\nV. Supervisar el suministro de la información financiera y económica a las empresas calificadoras que se contraten con la finalidad de evaluar la calidad crediticia del Estado;\nVI. Programar y hacer los pagos autorizados que afectan el presupuesto de Egresos del Estado, y los demás que legalmente deba efectuar éste, en función de las disponibilidades financieras y los programas de flujo de efectivo, manteniendo actualizada la información relativa;\nVII. Analizar y proponer, previo acuerdo del Secretario, la gestión y contratación de financiamientos con recursos estatales a los fideicomisos constituidos por el Estado, en los términos de la legislación aplicable;\nVIII. Dictaminar y proponer al Secretario el otorgamiento de aval del Estado para garantizar el cumplimiento de las obligaciones contraídas por las entidades a que se refiera la ley de la materia, así como tramitar la afectación de participaciones como fuente de pago o en garantía de las obligaciones contraídas por el Estado y sus Municipios;\nIX. Diseñar y aplicar el sistema de control de disponibilidades financieras del Estado, y evaluar sus resultados; formular políticas respecto al manejo de disponibilidades de los fideicomisos del Estado y vigilar la aplicación de los fondos provenientes de las operaciones de deuda pública;\nX. Participar en la formulación de los convenios financieros y ejercer las atribuciones que le correspondan en el ámbito de su competencia;\nXI. Administrar y comprobar las transferencias federales recibidas, conforme a las disposiciones legales aplicables y a las disposiciones jurídicas o administrativas correspondientes, efectuando las ministraciones a las instancias ejecutoras;\nXII. Concentrar, custodiar y, en su caso, requerir las garantías que se otorguen en favor del Estado o de la\nTesorería de la Federación, según el caso para registrarlas o cancelarlas, conforme a las disposiciones legales aplicables y, en su caso, turnarlas al área competente para hacerlas efectivas;\nXIII. Intervenir en el otorgamiento de garantías y avales que impliquen erogaciones a cargo del Estado y llevar su registro;\nrecauden o manejen fondos propiedad o al cuidado del Estado;\nXV. Concentrar los títulos de crédito expedidos a favor del Estado y, en su caso, de terceros, y reponer los mismos cuando hayan sido expedidos por el Estado, previos los trámites de cancelación correspondientes;\nXVI. Recibir, custodiar y llevar el registro clasificado y control de los valores que representen inversiones financieras directas del Estado, guardar los certificados de custodia cuando se disponga que su administración se encomiende a alguna institución de crédito, y ejercer oportunamente los derechos patrimoniales derivados de esos valores;\nXVII. Llevar el registro de las cuentas corrientes de depósito de dinero u otro tipo de operaciones financieras del Estado y fideicomisos del sector;\nXVIII. Asesorar a las entidades sujetas de financiamientos que afecten la deuda pública estatal, en todo lo relativo a la obtención de recursos crediticios;\nXIX. Tramitar el pago por concepto de devolución de cantidades cubiertas indebidamente al fisco, aprobadas por autoridad competente;\nXX. Diseñar y aplicar el sistema de transferencia en favor de las autoridades federales y municipales, de aquellos recursos financieros que les correspondan, de conformidad con las disposiciones legales aplicables;\nXXI. Presentar al Secretario la formulación de la cuenta pública de la Hacienda Estatal;\nXXII. Recibir, solicitar, en su caso, y administrar la información presupuestal, contable, financiera y de otra índole que proporcionen las dependencias y entidades de la Administración Pública Estatal a La\nSecretaría en la forma y con la periodicidad que al efecto se señale;\nXXIII. Someter al Secretario, para su aprobación, el diseño de un sistema de normas aplicables en el seguimiento del control de fondos y valores provenientes de las dependencias y fideicomisos del sector, sin perjuicio de lo que al efecto establezcan las leyes de la materia;\nXXIV. Revisar, cuando proceda, las operaciones que se hayan realizado con recursos económicos del\nEstado, conforme al Sistema de Contabilidad Gubernamental, así como formular los estados financieros y documentar la aplicación de los recursos financieros y tributarios del Estado, conforme a las disposiciones normativas aplicables;\nXXV. Invertir los recursos financieros buscando optimizarlos mediante la obtención de las mejores tasas de rendimiento que ofrezca el mercado financiero, ya sea en instrumentos de renta fija emitidos por el\nGobierno Federal o las instituciones bancarias, sociedades de inversión de renta fija cuyo fondeo sea únicamente de papeles gubernamentales y bancarios denominados en moneda nacional del sistema financiero mexicano; y\nXXVI. Las demás que le señalen otras disposiciones legales o reglamentarias.\nTodas las facultades que en este Reglamento competen a las Direcciones que se encuentran adscritas a la\nSubsecretaría de Egresos, se entenderán conferidas también al Subsecretario de Egresos, quien podrá ejercerlas directamente en cualquier tiempo.\nArtículo 14.- Compete a la Subsecretaría de Programación y Presupuesto:\nI. Formular, previo acuerdo del Secretario, normas y políticas a que se sujetará el diseño e implementación de la programación, presupuestación y seguimiento del Presupuesto de Egresos del\nEstado;\nII. Someter a la consideración del Subsecretario de Egresos y Secretario el programa general del gasto público y el anteproyecto de Ley de Presupuesto de Egresos;\nIII. Acordar con el Secretario los lineamientos programáticos-presupuestales para la integración de las propuestas de inversión anual y, en su caso, los correspondientes a programas especiales, programas de inversión y financiamiento de la obra pública;\nIV. Proponer la calendarización del Presupuesto de Egresos acorde al calendario de los ingresos estimados;\nV. Proponer al Secretario la normatividad aplicable para la gestión y trámite de las adecuaciones presupuestales;\nVI. Establecer sistemas de registro y control presupuestal por fuente de financiamiento, dependencia y proyecto, para llevar el seguimiento de los programas de inversión pública derivados del Decreto de\nPresupuesto de Egresos de la Federación, de los contenidos en los diversos instrumentos que suscriba el Estado con el Ejecutivo Federal, y a los programas derivados de la Ley de Presupuesto de Egresos del Estado;\nVII. Analizar y tramitar las adecuaciones presupuestales de transferencias y ampliaciones conforme a la normatividad que se emita al respecto;\nVIII. Elaborar informes de seguimiento de los programas presupuestarios;\nIX. Apoyar a las dependencias y entidades de la administración pública estatal en los procedimientos y trámites relacionados con la programación presupuestación;\nX. Coadyuvar con la Subsecretaría de Egresos para la atención de las auditorías, y proporcionar la información y documentación de la competencia de la Subsecretaría;\nXI. Revisar el Informe del Formato Único en el Portal Aplicativo de la Secretaría de Hacienda y Crédito\nPúblico, registrado por las dependencias y entidades de la Administración Pública Estatal y Municipal;\nXII. Las demás que le señalen otras disposiciones legales o reglamentarias.\nProgramación y Presupuesto, quien podrá ejercerlas directamente en cualquier tiempo.\nArtículo 15. Compete a la Procuraduría Fiscal:\nI. Ser el asesor y asistir jurídicamente a la Secretaría;\nII. Establecer su organización interna e instruir a los servidores públicos de su adscripción para que, de acuerdo con las necesidades del servicio, proporcionen la orientación y asesoría jurídica que se requiera, independientemente de sus áreas de adscripción;\nIII. Compilar, ordenar y actualizar el acervo legal de la dependencia, incluyendo las leyes, decretos, reglamentos, acuerdos, circulares y demás disposiciones vigentes relacionada con sus atribuciones y darlas a conocer, a través de medios electrónicos, a los titulares de las unidades administrativas de la\nSecretaría respecto de las disposiciones publicadas en el Diario Oficial de la Federación y en el\nPeriódico Oficial del Estado, relacionadas con atribuciones de su competencia;\nIV. Pedir las constancias de identificación del personal a su cargo y del personal de las unidades administrativas que tenga adscritas, así como designarlos y habilitarlos para la práctica de los actos de la competencia de la Procuraduría Fiscal;\nV. Solicitar información a las unidades administrativas y órganos administrativos desconcentrados de la\nSecretaría, de las propuestas de iniciativa de decretos, reformas, adiciones, derogaciones y abrogaciones a las disposiciones legales en las materias de su respectiva competencia que en su caso se requieran, y coordinar con dichas unidades administrativas la elaboración y presentación de las citadas propuestas ante las instancias correspondientes;\nVI. Realizar estudios comparados de los sistemas de hacienda pública, de los administrativos y de los de justicia administrativa, para apoyar la modernización de la hacienda pública;\nVII. Formular la documentación relativa a los proyectos de iniciativas de leyes o decretos y los proyectos de reglamentos, decretos, acuerdos y órdenes que el Secretario proponga al Gobernador del Estado y de las demás disposiciones de observancia general en las materias competencia de la Secretaría, verificando que en tales proyectos exista congruencia con el Plan Estatal de Desarrollo y sus programas;\nVIII. Tramitar la publicación en el Periódico Oficial del Estado de las disposiciones de carácter general y particular relativas a las materias competencia de la propia Secretaría y requerir a los solicitantes de publicaciones las modificaciones, aclaraciones o confirmaciones respectivas;\nIX. Ser el enlace en asuntos jurídicos con las áreas correspondientes de las dependencias de la\nAdministración Pública estatal y municipal;\nX. Coordinarse con las autoridades fiscales de la Federación, del Estado o de las demás Entidades\nFederativas, en las materias de su competencia, para eficientar el ejercicio de sus facultades;\nXI. Intervenir y ejercer facultades en la materia de su competencia conferidas en los convenios y sus\nHacienda y Crédito Público y, en su caso, con los municipios;\nXII. Revisar los informes periódicos que El Servicio entregue a La Secretaría en materia de juicios por el\nConvenio de Colaboración Administrativa en Materia Fiscal Federal y sus Anexos, celebrado entre el\nEstado y la Federación, en los que El Servicio represente a La Secretaría y/o al Estado, como parte en los que se susciten con motivo del ejercicio de las facultades delegadas al Estado; y, en su caso, intervenir y asumir la defensa de los mismos, sin perjuicio de la intervención que corresponda a la hubiera correspondido a la Procuraduría Fiscal respecto de los que sean de su competencia;\nXIII. Representar el interés del Estado en controversias fiscales del fuero federal, estatal o municipal; a la investigaciones o procedimientos ante los tribunales de la República, tribunales del Estado, ante la\nComisión Nacional de los Derechos Humanos, y ante otras autoridades competentes, en que sean parte, o cuando sin ser parte, sea requerida su intervención por la autoridad que conoce del juicio o procedimiento, o tenga interés para intervenir conforme a sus atribuciones; y, en su caso, poner en conocimiento del Órgano Interno de Control en la Secretaría, los hechos respectivos; ejercitar los derechos, acciones, excepciones y defensas de las que sean titulares, transigir cuando así convenga a los intereses de la Secretaría, e interponer los recursos que procedan ante los citados tribunales y autoridades, siempre que dicha representación no corresponda a otra unidad administrativa de la propia\nSecretaría o al Ministerio Público y, en su caso, proporcionarle los elementos que sean necesarios;\nXIV. Resolver los recursos administrativos que se interpongan en contra de actos de la Secretaría cuando no corresponda a otra unidad administrativa u órgano administrativo desconcentrado de la misma;\nXV. Representar al Secretario ante el Tribunal Federal de Justicia Administrativa o ante el Tribunal de\nJusticia Administrativa del Estado, en los juicios que se interpongan en contra de las resoluciones que se dicten en los términos de la fracción anterior;\nXVI. En el caso de los juicios de amparo podrá representar a La Secretaría, a su titular y a cualquiera de sus unidades administrativas u órganos administrativos desconcentrados, con cualquier carácter con el que intervengan en el juicio, para lo cual podrá rendir en su representación, por la vía de suplencia, los informes que les soliciten, así como interponer los recursos que correspondan durante la tramitación de tales juicios, actuando en todas sus instancias, incluso pedir los sobreseimientos y manifestar las causales de improcedencia que se adviertan, para ese efecto las unidades administrativas u órganos administrativos desconcentrados, señalados como partes deberán proporcionarle, dentro del término de ley, las pruebas documentales que resulten necesarias para acreditar la constitucionalidad de sus actos, así como proponer los contenidos que deban rendirse en los informes;\nXVII. Denunciar o querellarse ante el Ministerio Público, salvo que sea atribución de otra dependencia o instancia, por los hechos que puedan constituir delitos de los servidores públicos de la Secretaría en el desempeño de sus funciones, allegarse de los elementos probatorios del caso, darle la intervención que corresponda al Órgano Interno de Control en la Secretaría y a la Secretaría de la Contraloría; denunciar o querellarse ante el Ministerio Público competente de los hechos delictuosos en que la Secretaría resulte ofendida o en aquéllos en que tenga conocimiento o interés jurídico, coadyuvar en estos casos con el propio Ministerio Público, en representación de la Secretaría, y formular la petición de sobreseimiento del proceso penal u otorgar el perdón, siempre y cuando las áreas competentes de la\nSecretaría que tengan injerencia o interés jurídico en el asunto de que se trate manifiesten no tener objeción en su otorgamiento y, en su caso, podrá considerar los elementos que se establezcan en las disposiciones y lineamientos que se emitan para tal efecto;\nXVIII. Realizar, en el ámbito de su competencia, el seguimiento y control de los procesos originados por las querellas, declaratorias de perjuicio, denuncias y peticiones formuladas por la Secretaría, así como de aquéllas en que la misma tenga interés en las materias que no estén expresamente asignadas por este\nReglamento a otras unidades administrativas de la propia Secretaría o, a sus órganos desconcentrados;\nXIX. Coordinar las actividades relativas al Registro Público de Entidades Paraestatales; y\nXX. Las demás que le señalen las leyes, reglamentos, convenios y sus anexos celebrados en la materia en los que el Estado sea parte.\nCAPÍTULO V\nDE LAS ATRIBUCIONES GENÉRICAS DE LAS\nDIRECCIONES Y UNIDADES\nArtículo 16.- Corresponde a los Directores y Secretario Técnico las siguientes facultades de carácter general:\nI. Acordar con el superior jerárquico inmediato los asuntos de su competencia;\nII. Formular, para aprobación superior, los programas de actividades y los anteproyectos de presupuesto de las unidades administrativas a su cargo; así como organizar, dirigir y evaluar dichas actividades;\nIII. Acordar y resolver los asuntos de la competencia de las unidades administrativas a su cargo;\nIV. Proponer los datos de las labores desarrolladas por sus áreas, para la formulación del informe anual del Gobernador;\nV. Coordinarse con las demás unidades administrativas de La Secretaría, así como conceder audiencia al público;\nVI. Proponer al Secretario la designación del personal de las unidades administrativas a su cargo y el otorgamiento de las licencias;\nVII. Expedir certificaciones de documentos y expedientes relativos a los asuntos de su competencia;\nVIII. Representar a La Secretaría en los foros, eventos, reuniones nacionales en materia de impuestos estatales como federales convenidos y dar cumplimiento a los acuerdos y convenios que se celebren en los asuntos de su competencia;\nIX. Levantar el acta administrativa al personal de la unidad administrativa a su cargo, a que se refiere el artículo 50 de la Ley de los Trabajadores al Servicio del Gobierno del Estado de Campeche;\nX. Cumplimentar las resoluciones, autos, mandamientos y ejecutorias de autoridades judiciales y/o administrativas en el ámbito federal o estatal, que le sean hechos del conocimiento por conducto de esas mismas autoridades o a través de la Procuraduría Fiscal; y\nXI. Las demás que les señalen otras disposiciones legales o reglamentarias.\nCAPÍTULO VI\nDE LAS ATRIBUCIONES ESPECÍFICAS DE LAS DIRECCIONES\nY UNIDADES\nArtículo 17.- Compete a la Dirección de Egresos:\nI. Llevar un control financiero de la deuda pública;\nII. Proponer, para aprobación, a la Subsecretaría de Egresos, los lineamientos de política del Estado en las materias financieras, crediticia, bancaria, monetaria y específicas para servicios del sector público en coordinación con las unidades competentes de La Secretaría a fin de aportar elementos para la participación que a ésta última y a las entidades coordinadas por ella les corresponde;\nIII. Proponer para aprobación superior, la política financiera del Estado en congruencia con la política económica general del país, en coordinación con las unidades administrativas de La Secretaría y otras autoridades competentes;\nIV. Establecer un registro de las cuentas corrientes de depósito en dinero y valores y de las demás operaciones financieras que el Estado tenga en instituciones de crédito que operen en la Entidad o en el país, conforme a las normas que dicte la propia Secretaría;\nV. Estudiar los asuntos económicos que permitan formular lineamientos de políticas y el empleo de instrumentos financieros, crediticios, bancarios y monetarios, de la Administración Pública Estatal y del sector público;\nVI. Evaluar el avance y cumplimiento de los programas financieros de las entidades paraestatales apoyadas con crédito público, en los que el Estado actúe como aval;\nVII. Ejercer, previo acuerdo superior, las facultades que en materia de negociación, contratación y autorización del crédito público competan a esta Dirección;\nVIII. Realizar los trámites de registro ante la Secretaría de Hacienda y Crédito Público de la afectación de participaciones del Estado y Municipios, cuando hayan sido dadas en garantía respecto a créditos que hubieren contraído dentro de sus facultades;\nIX. Programar y hacer los pagos autorizados que afectan el presupuesto de egresos de la Entidad y las demás que legalmente deba efectuar el Estado, en función de las disponibilidades y los programas de flujo de efectivo, manteniendo actualizada la información relativa;\nX. Recibir, custodiar y llevar el registro clasificado y control de los valores que representen inversiones financieras directas del Estado, guardar los certificados de custodia cuando se disponga que su patrimoniales derivados de esos valores;\nXI. Diseñar y aplicar el sistema de control de disponibilidades del Estado, y evaluar sus resultados, formular la aplicación de los fondos provenientes de las operaciones de deuda pública;\nXII. Llevar la administración, control, operación, registro, inscripción y demás actos que correspondan al\nRegistro de Empréstitos y Obligaciones del Estado;\nXIII. Llevar el registro de las cuentas corrientes de depósito de dinero a otro tipo de operaciones financieras del Estado, así como llevar el control de la deuda pública del Estado y el de las entidades paraestatales sólo cuando ése sea aval de las mismas;\nXIV. Diseñar y aplicar el sistema de transferencia a favor de las autoridades federales y municipales de aquellos recursos financieros que les correspondan, de conformidad con las disposiciones legales aplicables;\nXV. Recibir de las dependencias y entidades, poderes para trámite, autorización de pago y calendarización de los documentos que afecten el presupuesto de egresos del Estado;\nXVI. Vigilar que los documentos que afecten el presupuesto de egresos del Estado cumplan con la normatividad y disposiciones fiscales vigentes;\nXVII. Efectuar el corte diario de caja y llevar los registros necesarios para el control de los movimientos de las cuentas bancarias y los saldos de las mismas e informar al Secretario y al Subsecretario de Egresos;\nXVIII. Organizar, verificar y remitir para su contabilización la documentación comprobatoria remitida para su pago;\nXIX. Intervenir en el proceso de calificación de la calidad crediticia del Estado;\nXX. Administrar la colocación de los recursos en los mejores instrumentos de inversión que ofrece el sistema financiero mexicano;\nXXI. Vigilar la cancelación y, en su caso, la reposición de títulos de crédito expedidos por el Estado, a través de quienes ostenten legalmente su representación, de acuerdo con las disposiciones jurídicas aplicables;\nXXII. Rendir los informes que solicite el Secretario y el Subsecretario de Egresos; y\nXXIII. Las demás que le sean conferidas por las leyes y reglamentos vigentes.\nArtículo 18.- Compete a la Dirección de Contabilidad Gubernamental:\nI. Llevar la contabilidad de la Hacienda Pública Estatal, de conformidad con la legislación estatal y federal que corresponda;\nII. Proponer para aprobación del Subsecretario de Egresos los procedimientos a que debe apegarse el registro contable de los ingresos y egresos de la Hacienda Pública, así como las cuentas de control de bienes, obligaciones y patrimonio del Estado;\nIII. Efectuar la glosa y registro de las operaciones que se hayan llevado a cabo con los recursos económicos del Estado;\nIV. Formular los estados financieros contables, incluyendo los correspondientes a los Criterios para la elaboración y presentación homogénea de la información financiera y de los formatos a que hace referencia la Ley de Disciplina Financiera de las Entidades Federativas y los Municipios;\nV. Llevar el registro de la deuda pública, dando expresión contable a ésta, así como a las obligaciones fiscales y contingentes a cargo del Estado;\nVI. Realizar los trámites de presentación de declaraciones a que obliguen las disposiciones fiscales ante la\nSecretaría de Hacienda y Crédito Público, que correspondan a la esfera de su competencia;\nVII. Elaborar estadísticas que muestren la situación financiera del Estado;\nVIII. Presentar a la Subsecretaría de Egresos el Catálogo de Cuentas del Estado, para el registro contable de las operaciones;\nIX. Requerir la información contable financiera a las dependencias y entidades de la Administración Pública del Estado, dentro del marco jurídico aplicable;\nX. Rendir informes de índole contable y financiera que solicite el Secretario;\nXI. Documentar, compilar y mantener actualizada la información que sea de su competencia, para integrar el informe gubernamental;\nXII. Elaborar los informes de finanzas públicas para dar cumplimiento a los ordenamientos legales vigentes para ser presentados ante la instancia correspondiente;\nXIII. Integrar y elaborar la cuenta pública y proponerla a la Subsecretaría de Egresos para que, en su oportunidad, sea sometida a la consideración del Secretario;\nXIV. Operar en La Secretaría, en materia de contabilidad gubernamental y archivo contable con sujeción a la\nConstitución Federal y las leyes que de ella emanen; y\nXV. Las demás que le sean conferidas por las leyes y reglamentos vigentes.\nArtículo 19.- Compete a la Dirección de Programación:\nejercicio de los programas de inversión;\nII. Revisar los documentos de obras y acciones derivados de los programas previstos en el Decreto de\nPresupuesto de Egresos de la Federación, de los contenidos en los diversos instrumentos que suscriba el Estado con el Ejecutivo Federal; así como los autorizados en el presupuesto de egresos del Estado de conformidad con la normatividad aplicable; y en su caso, solicitar a las dependencias ejecutoras, la corrección, adecuación o complemento de los documentos referidos, para tramitar su pago;\nIII. Participar en el seguimiento del Formato Único en el Portal Aplicativo de la Secretaría de Hacienda y\nCrédito Público, registrado por las dependencias y entidades de la Administración Pública Estatal y\nMunicipal;\nIV. Establecer sistemas de registro y control presupuestal por fuente de financiamiento, dependencia y proyecto, para llevar el seguimiento de los programas de inversión pública derivados del Decreto de\nPresupuesto de Egresos de la Federación, de los contenidos en los diversos instrumentos que suscriba el Estado con el Ejecutivo Federal y a los programas derivados de la Ley de Presupuesto de Egresos del Estado;\nV. Apoyar a la representación de La Secretaría en la Comisión Intersecretarial Gasto-Financiamiento, en el análisis para el establecimiento de lineamientos a los que se sujetarán las dependencias y entidades de la Administración Pública Estatal, en materia de programas y proyectos de inversión, respecto de la suficiencia presupuestal con que cuentan durante el ejercicio fiscal, verificando que el uso de los recursos sea aplicado en cumplimiento con las disposiciones de racionalidad, austeridad y disciplina presupuestal en coordinación con la dependencia correspondiente;\nVI. Intervenir en los trabajos de registro correspondiente a la programación y presupuestación del financiamiento de la obra pública;\nVII. Participar dentro del ámbito de su competencia en el análisis del comportamiento de las fuentes de recursos financieros internos y externos necesarios para la programación-presupuestación del gasto en inversión;\nVIII. Participar en la formulación de proyectos, normas y reglamentos que regulen la programación del gasto en la obra pública;\nIX. Revisar las fuentes y montos de los programas de inversión de las dependencias y entidades de la administración pública estatal y municipal, que se autoricen durante el ejercicio fiscal;\nX. Rendir los informes que solicite el Secretario; y\nXI. Las demás que le sean conferidas por las leyes y reglamentos vigentes.\nArtículo 20.- Compete a la Dirección de Presupuesto:\nI. Proponer a la Subsecretaría de Programación y Presupuesto, normas y políticas a las que se sujetará el diseño e implementación de los programas, así como la presupuestación de las dependencias y entidades de la Administración Pública Estatal;\nII. Revisar la aplicación del ejercicio presupuestal de las dependencias a través de la implementación de sistemas de control;\nIII. Elaborar el informe del ejercicio del presupuesto estatal;\nIV. Analizar e integrar el anteproyecto de Ley de Presupuesto de Egresos del Estado de acuerdo con el marco económico y social que establezca el Plan Estatal de Desarrollo, los programas que deriven de él y las políticas del Ejecutivo Estatal, y presentarlo al Subsecretario de Programación y Presupuesto y al\nSecretario, considerando los requerimientos de cada una de las dependencias y entidades de la\nAdministración Pública Estatal, con base en los ingresos;\nV. Requerir a las dependencias y entidades de la Administración Pública Estatal la información presupuestal y de cualquier otra naturaleza que sea necesaria para el cumplimiento de sus facultades;\nVI. Analizar las solicitudes de modificaciones y transferencias programáticas y presupuestales que\nSubsecretario de Programación y Presupuesto y ante el Secretario para su autorización; conforme a la normatividad que se emita al respecto;\nVII. Analizar la procedencia presupuestal de las estructuras orgánicas y ocupacionales de las dependencias y entidades de la Administración Pública Estatal y sus modificaciones, para someterlo a la aprobación del Subsecretario de Programación y Presupuesto y del Secretario;\nVIII. Estimar y proponer al Subsecretario de Programación y Presupuesto y al Secretario, el monto global y calendarización provisional del presupuesto para el siguiente ejercicio fiscal, para que a su vez lo den a conocer a los diversos ramos que conforman la Administración Pública Estatal; a fin de posibilitar las atribuciones de La Secretaría en materia de programación-presupuestación en congruencia con los ingresos estimados;\nIX. Participar en la formulación de proyectos de iniciativas de leyes, normas y reglamentos que regulen y orienten el manejo del gasto público;\nX. Efectuar la regularización presupuestal de documentos que por error u omisión sean clasificados de manera incorrecta, a solicitud de la dependencia o entidad;\nXI. Efectuar la apertura de claves presupuestales con base en la normatividad establecida;\nXII. Efectuar las transferencias y ajustes en el presupuesto de las dependencias cuando éstas habiendo solicitado ampliación, conserven recursos disponibles en otras partidas;\nXIII. Rendir los informes que solicite el Secretario;\nXIV. Elaborar informes de seguimiento de los programas presupuestarios;\nXV. Apoyar a la representación de La Secretaría en la Comisión Intersecretarial Gasto-Financiamiento, en el análisis para el establecimiento de lineamientos a los que se sujetarán las dependencias y entidades de la Administración Pública Estatal, respecto de la suficiencia presupuestal con que cuentan durante el ejercicio fiscal, verificando que el uso de los recursos sea aplicado en cumplimiento con las disposiciones de racionalidad, austeridad y disciplina presupuestal en coordinación con la dependencia correspondiente; y\nXVI. Las demás que le sean conferidas por las leyes y reglamentos vigentes.\nArtículo 21.- Compete a la Dirección de Política Financiera:\nI. Coadyuvar y apoyar la gestión de proyectos financieros estratégicos de La Secretaría;\nII. Recopilar estadísticas económicas y financieras para apoyar la toma de decisiones de la Subsecretaría de Egresos y del Secretario;\nIII. Analizar la actividad y condiciones económicas generales del Estado y realizar estudios que sirvan a La\nSecretaría como marco de referencia para formular los programas financieros de la Administración\nPública Estatal, así como prever su impacto en las finanzas públicas;\nIV. Analizar la información financiera que se desprenda de las comparecencias del Secretario ante el H.\nCongreso del Estado;\nV. Coadyuvar en la integración de informes que le sean requeridos en el ámbito de su competencia;\nVI. Participar en la elaboración de oficios, circulares y demás disposiciones que en materia financiera emita el Secretario;\nVII. Analizar programas que por su relevancia requieran un seguimiento específico e informar el resultado a la Subsecretaría de Egresos;\nVIII. Emitir opinión sobre el impacto presupuestal de los proyectos de iniciativas de leyes o Decretos que formulen las dependencias, unidades administrativas, órganos administrativos desconcentrados, y entidades, cuando éstos incidan en materia financiera;\nIX. Participar en las reuniones que se celebren con dependencias de la Administración Pública Estatal, Federal y Municipales e informar al titular de La Secretaría;\nX. Apoyar en la formulación de las políticas y programas de los fideicomisos coordinados por La\nSecretaría;\nXI. Fungir como representante del Secretario en las entidades paraestatales de las que éste forme parte; y\nXII. Las demás que le fijen expresamente las Leyes y Reglamentos, así como las que les sean conferidas por el Secretario.\nArtículo 22.- Compete a la Dirección de Enlace en Proyectos de Inversión:\nI. Fungir como enlace de La Secretaría con la Unidad de Programas y Proyectos de Inversión Pública;\nII. Coadyuvar en la evaluación de la rentabilidad social de los programas y proyectos de inversión pública;\nIII. Llevar el seguimiento de los acuerdos de gestión realizados por el Secretario;\nIV. Asesorar al Secretario en los mecanismos de financiamiento de los proyectos de inversión pública;\nV. Asesorar al Secretario en materia de registro de contratos y convenios de proyectos de inversión pública que hayan sido autorizados por las instancias competentes;\nVI. Coordinarse con la Dirección de Política Financiera en temas de impacto presupuestal respecto de proyectos de iniciativas de leyes o decretos y en casos de proyectos y programas de inversión pública;\nVII. Las demás que le señalen las leyes, reglamentos, convenios, lineamientos, reglas de operación y demás marco jurídico aplicable, así como aquellas que le confiera el Secretario.\nArtículo 23.- Compete a la Dirección de Informática:\nI. Asesorar, apoyar y/o proponer a las unidades administrativas de la Secretaría, en materia de adquisición de bienes informáticos, licencias de software y servicios informáticos que requieran;\nII. Proporcionar a las unidades administrativas que integran la Secretaría el soporte técnico necesario en materia de informática;\nIII. Gestionar ante la dependencia correspondiente la realización de los dictámenes técnicos para efectos de mantenimiento correctivo o baja de bienes y servicios informáticos;\nIV. Gestionar ante la dependencia correspondiente los servicios de instalación, reparación y/o mantenimiento de redes y telecomunicaciones;\nV. Gestionar ante la dependencia correspondiente a efecto de coordinar los servicios de mantenimiento preventivo y/o correctivo de los bienes informáticos de la Secretaría;\nVI. Proponer al titular de la Secretaría, las necesidades de fortalecimiento de infraestructura tecnológica en materia de redes, telecomunicaciones, seguridad, respaldo, servicios, servidores de almacenamiento y procesamiento de información, que permitan unificar una plataforma enlazada, eficaz y eficiente para el óptimo desempeño en las funciones de las unidades administrativas de la\nSecretaría;\nVII. Supervisar, mejorar y procurar el óptimo funcionamiento de la infraestructura tecnológica en materia de redes, telecomunicaciones, seguridad, respaldo, servicios, servidores de almacenamiento y procesamiento de información de la Secretaría;\nVIII. Instrumentar los mecanismos y estudios especializados que permitan mantener el nivel requerido de las configuraciones físicas y lógicas de los bienes y servicios informáticos, de acuerdo a las necesidades presentes y futuras para el óptimo funcionamiento de los equipos y programas de cómputo, asignados a la Secretaría;\nIX. Evaluar la operación en las materias de su competencia y proponer, en su caso, las medidas que procedan para mejorar la calidad de los servicios de tecnologías de información;\nX. Instrumentar los sistemas, lineamientos, manuales, estándares y/o medidas necesarias para salvaguardar la seguridad e integridad de los equipos, sistemas e información a su cargo;\nXI. Diseñar, implementar y dar mantenimiento a las páginas web y portales electrónicos de la Secretaría;\nXII. Recepcionar y llevar un control de los requerimientos de servicios de tecnologías de información de las unidades administrativas de la Secretaría, para analizarlos y determinar la factibilidad de su realización, ya sea un cambio, nuevo módulo, publicación de información en internet, soporte técnico o nuevo proyecto tecnológico. En virtud de esto, diseñar los sistemas, soluciones tecnológicas y/o brindar los servicios de tecnologías de información que den cumplimiento a los requerimientos para el adecuado funcionamiento de la Secretaría;\nXIII. Llevar el control de las licencias informáticas y el registro de programas de cómputo de la Secretaría;\nXIV. Participar en los comités de tecnología, modernización, informática o innovación gubernamental de la\nAdministración Pública Estatal, con el cargo y atribuciones que se le asignen;\nXV. Desarrollar el Plan Anual de Tecnologías de Información de la Secretaría, y vigilar que se cumplan los compromisos y metas establecidos, en congruencia con el Plan Estatal de Desarrollo;\nXVI. En materia de competencia, participar en la elaboración, difusión y actualización del programa de\nXVII. Mantener permanente coordinación con la Unidad de Tecnologías de la Información y Comunicación de El Servicio;\nXVIII. Las demás que le confieran las disposiciones legales y reglamentarias o que le sean encomendadas por el titular de la Secretaría.\nArtículo 24.- Es competencia de la Unidad de Política de Ingresos y Coordinación Fiscal:\nI. Coadyuvar con el Subsecretario de Ingresos en la elaboración de las políticas de ingresos y de coordinación fiscal aplicable en cada ejercicio fiscal;\nII. Analizar el comportamiento de la economía nacional y del Estado para evaluar y prever los posibles efectos en las finanzas públicas;\nIII. Realizar estudios económicos y de política de ingresos que coadyuven al fortalecimiento, regulación y supervisión de los ingresos locales;\nIV. Integrar un banco de datos con información económica y fiscal de las fuentes disponibles en materia, que permita apoyar en la toma de decisiones en materia de política de ingresos y de coordinación fiscal;\nV. Apoyar al Subsecretario en materia de estadística y política de ingresos;\nVI. Colaborar con el Subsecretario en los trabajos que le correspondan en los Sistemas Nacional de\nCoordinación Fiscal y Estatal de Coordinación Fiscal;\nVII. Verificar los montos de las participaciones en ingresos federales e incentivos económicos y aportaciones que conforme a las leyes fiscales y los convenios de adhesión y de colaboración administrativa en materia fiscal federal suscritos con el Gobierno Federal le corresponden al Estado y a sus Municipios;\nVIII. Analizar las asignaciones, coeficientes y montos de participaciones, incentivos económicos y aportaciones provenientes de la Federación y hacerlos del conocimiento del Subsecretario de Ingresos;\nIX. Estudiar el comportamiento de la recaudación y del sistema de participaciones federales a fin de mejorar los coeficientes de participación del Estado en los fondos distribuibles;\nX. Coordinar, en el ámbito de su competencia, el intercambio de información con la Secretaría de\nHacienda y Crédito Público y con las Entidades Federativas;\nXI. Aplicar los trámites correspondientes para ingresar las cantidades provenientes de los Fondos General de Participaciones y Fomento Municipal, en atención a lo que establece el Convenio de Colaboración\nAdministrativa en Materia Fiscal Federal, celebrado entre el Estado y la Federación; así como enterar, en los términos que también establece dicho Convenio, la diferencia resultante entre la constancia de participaciones del mes corriente y la correspondiente a la recaudación de ingresos federales del mes inmediato anterior;\nXII. Elaborar el calendario de entrega, porcentaje, fórmulas y variables utilizadas, así como los montos estimados, de las participaciones que el Estado reciba y de las que tenga obligación de participar a sus municipios. Del mismo modo elaborar los cuadros que contengan el importe de las participaciones entregadas trimestralmente y, en su caso, el ajuste realizado al término de cada ejercicio fiscal y proponerlo a su superior jerárquico para la obtención de las firmas y correspondiente publicación en el\nPeriódico Oficial, así como en la página oficial de Internet del gobierno del Estado conforme a los lineamientos que al efecto emita la Secretaría de Hacienda y Crédito Público;\nXIII. Aplicar los trámites correspondientes para ingresar los incentivos provenientes de las actividades de administración que realice el Estado, conforme lo dispuesto en el Convenio de Colaboración\nAdministrativa en Materia Fiscal Federal, celebrado entre el Estado y la Federación;\nXIV. Enterar y rendir ante las autoridades competentes de la Federación, en los plazos, procedimientos y formas que establece el Convenio de Colaboración Administrativa en Materia Fiscal Federal, el importe de los ingresos federales captados y la Cuenta Mensual Comprobada de Ingresos Coordinados;\nXV. Verificar el comportamiento de la recaudación de la administración del Impuesto Predial y otros impuestos y derechos municipales, en términos del Convenio de Colaboración celebrado o que se celebre con los municipios del Estado; y\nXVI. Las demás que le sean conferidas por las leyes y reglamentos o en los convenios vigentes en materia fiscal en que el Estado sea parte.\nArtículo 25.- Compete a la Coordinación Administrativa:\nI. Tramitar viáticos, gastos de alimentación, transportación terrestre, marítima o aérea de personas y de La Secretaría, a solicitud de éstas, para el desempeño de sus funciones;\nII. Tramitar ante la Secretaría de Administración e Innovación Gubernamental, los movimientos que genere el personal de La Secretaría, que incluyan la propuesta y expedición de nombramientos, dentro del marco de su competencia;\nIII. Llevar un registro interno de los activos inventariables asignados a La Secretaría y vigilar su actualización conforme a la información que le proporcionen los responsables de los resguardos;\nIV. Integrar y validar los anteproyectos presupuestales de las unidades administrativas y órganos desconcentrados de La Secretaría y someterlos a la consideración del Secretario;\nV. Administrar el fondo revolvente asignado a La Secretaría y, transferir o ministrar, en su caso, los recursos de éste, a las unidades administrativas y órganos desconcentrados autorizados por el titular de La Secretaría, para su ejercicio directo;\nVI. Controlar, conforme a la disponibilidad financiera, el ejercicio del presupuesto que tengan asignado las unidades administrativas y órganos desconcentrados de La Secretaría;\nVII. Controlar y elaborar conciliaciones bancarias correspondientes a las cuentas que tenga asignadas, en materia de su competencia;\nVIII. Gestionar y controlar el gasto por comprobar de las unidades administrativas y órganos desconcentrados de La Secretaría;\nIX. Proporcionar los informes que en materia presupuestal requiera el Administrador General de El\nServicio;\nX. Llevar el control y vigilar el adecuado mantenimiento de los vehículos asignados a las unidades administrativas de La Secretaría o al órgano desconcentrado, verificando que cuenten con los seguros correspondientes;\nXI. Administrar el Servicio Fiscal de Carrera conforme a lo establecido en el Estatuto del Servicio Fiscal de\nCarrera, e impulsar la profesionalización del personal de El Servicio;\nXII. Controlar y registrar la asistencia, incapacidades, nombramientos, remociones, renuncias, licencias, cambios de adscripción, promociones, vacaciones, días no laborables y demás incidencias del personal de La Secretaría y de El Servicio;\nXIII. Emitir los gafetes que acrediten como trabajadores al personal de El Servicio, para el correcto cumplimiento de sus funciones; y\nXIV. Las demás que le confieran el Secretario, así como las disposiciones legales o reglamentarias aplicables.\nArtículo 26.- La unidad administrativa encargada de auxiliar directamente al Titular de La Secretaría proporcionándole el apoyo técnico, asesoría y coordinación que requiera para el despacho de los asuntos de su competencia, será la Secretaría Técnica, que tendrá las siguientes funciones:\nI. Proporcionar asistencia técnica al Secretario en materia hacendaria, así como a las demás unidades administrativas de La Secretaría, cuando se lo requieran;\nII. Coordinar y apoyar las reuniones de trabajo de La Secretaría;\nIII. Coordinar los asuntos de interés del Secretario, de manera organizada con los titulares de las diversas unidades administrativas a quienes el asunto competa;\nIV. Mantener informado al Secretario sobre el avance de gestión que lleve cada asunto a su cargo;\nV. Participar en la elaboración de los proyectos de iniciativas de leyes, reglamentos, acuerdos y demás disposiciones jurídicas o contractuales que se requieran, con la participación de la Procuraduría Fiscal y las áreas involucradas;\nVI. Llevar el control de los convenios que suscriba La Secretaría que contengan paripassus, transferencias, reasignaciones y demás aportaciones presupuestales;\nVII. Atender y, en su caso, distribuir para su solventación la correspondencia dirigida al Secretario; y\nVIII. Las demás que le sean conferidas por las leyes y reglamentos vigentes, así como por el Secretario.\nArtículo 27.- La Unidad de Transparencia tendrá las atribuciones que le confieran la Ley General de\nTransparencia y Acceso a la Información Pública y la legislación local en la materia y tendrá competencia tanto para La Secretaría como para su órgano administrativo desconcentrado denominado Servicio de\nAdministración Fiscal del Estado de Campeche.\nCAPÍTULO VII\nDE LA SUPLENCIA DE LOS TITULARES\nArtículo 28.- El Secretario de Finanzas, será suplido en sus ausencias temporales no mayores de quince días por el servidor público subalterno que para tal efecto designe, previo informe al Gobernador del Estado; si la ausencia excede de este término, el Secretario deberá someter a la consideración del Ejecutivo la designación del servidor público que cubra la ausencia. En caso de que la ausencia, por el motivo que fuere, se convierta, en definitiva, entretanto se nombra al nuevo titular de la dependencia, el Gobernador designará al servidor público que con carácter de Encargado del Despacho lo sustituya.\nArtículo 29.- Las ausencias temporales y accidentales menores de quince días de los subsecretarios, serán suplidas por el Director de área que de ellos dependan y designen, conforme lo disponga el Secretario.\nArtículo 30.- Las ausencias temporales y accidentales menores de quince días de los Directores, Subdirectores, Coordinador, Secretario Técnico y Jefes de Departamento serán suplidas por el servidor público de la jerarquía inmediata inferior que de ellos dependan y designen, conforme lo disponga el Secretario.\nla ley, reglamento o acuerdo respectivo; para el caso de no existir previsión alguna se aplicará la regla señalada en el primer párrafo de este artículo.\nArtículo 31.- Las ausencias temporales y accidentales menores de quince días de los demás servidores públicos de La Secretaría se suplirán conforme lo disponga su superior jerárquico inmediato, previa consulta al\nCoordinador Administrativo.\nArtículo 32.- Las ausencias definitivas de cualquiera de los servidores públicos de La Secretaría se suplirán con un nuevo nombramiento.\nCAPÍTULO VIII\nINTERPRETACIÓN\nArtículo 33.- En los casos no previstos en este Reglamento y en caso de presentarse alguna controversia sobre su interpretación y/o aplicación de su contenido, el Secretario resolverá lo conducente.\nTRANSITORIOS\nPrimero. - El presente Reglamento entrará en vigor el día 1 de abril de 2017.\nSegundo. - Se abroga el Reglamento Interior de la Secretaría de Finanzas de la Administración Pública del\nEstado de Campeche publicado en el Periódico Oficial del Estado el día 17 de febrero de 2016.\nTercero. - Se derogan todas las disposiciones reglamentarias y administrativas de igual o menor jerarquía del marco jurídico estatal, en lo que se opongan al contenido del presente Reglamento.\nCuarto. - Hasta en tanto entre en funcionamiento el Tribunal de Justicia Administrativa del Estado, todas las menciones hechas a éste, se entenderán hechas a la Sala Administrativa del H. Tribunal Superior de Justicia del Estado de Campeche.\nFrancisco de Campeche, Municipio y Estado de Campeche, a los veintisiete días del mes de marzo del año dos mil diecisiete.\nLic. Rafael Alejandro Moreno Cárdenas, Gobernador del Estado de Campeche.- C.P. América del Carmen\nAzar Pérez, Secretaria de Finanzas.- Rúbricas.",
  "ordenamiento": "REGLAMENTO",
  "jurisdiccion": "CAMPECHE",
  "fuente_oficial": "DIARIO OFICIAL DE LA FEDERACION",
  "Fecha de Publicación": "22 de diciembre de 2016",
  "es_escaneado": false,
  "tiene_tablas": false,
  "materia": [
    "administrativo",
    "fiscal",
    "municipal"
  ]
}