{
  "titulo": "Ley DE FOMENTO COOPERATIVO PARA EL DISTRITO FEDERAL",
  "Contenido": "PUBLICADA EN LA GACETA OFICIAL DEL DISTRITO FEDERAL\nEL 20 DE ENERO DE 2006\nTEXTO VIGENTE\nÚLTIMA REFORMA PUBLICADA EN LA G.O.C.D.M.X.\nEL 27 DE ABRIL DE 2023\nDECRETO QUE CREA LA LEY DE FOMENTO COOPERATIVO PARA EL DISTRITO FEDERAL\n(Al margen superior izquierdo dos escudos que dicen: GOBIERNO DEL DISTRITO FEDERAL. - México, la\nCiudad de la Esperanza. - JEFE DE GOBIERNO DEL DISTRITO FEDERAL)\nDECRETO QUE CREA LA LEY DE FOMENTO COOPERATIVO PARA EL DISTRITO FEDERAL\nALEJANDRO DE JESÚS ENCINAS RODRÍGUEZ Jefe de Gobierno del Distrito Federal, a sus habitantes sabed:\nQue la Honorable Asamblea Legislativa del Distrito Federal, III Legislatura, se ha servido dirigirme el siguiente:\nDECRETO\n(Al margen superior izquierdo el Escudo Nacional que dice: ESTADOS UNIDOS MEXICANOS. - ASAMBLEA\nLEGISLATIVA DEL DISTRITO FEDERAL. - III LEGISLATURA)\nASAMBLEA LEGISLATIVA DEL DISTRITO FEDERAL III LEGISLATURA.\nD E C R E T A\nDECRETO QUE CREA LA\n\nLEY DE FOMENTO COOPERATIVO PARA EL DISTRITO\nFEDERAL\nCAPÍTULO PRIMERO\nDISPOSICIONES GENERALES\nArtículo 1.- La presente Ley es de orden público, interés social y de observancia general en la Ciudad de\nMéxico.\nTiene por objeto el establecimiento, la regulación y la coordinación de políticas, programas y acciones de fomento cooperativo para el desarrollo económico, sin perjuicio de los programas, estímulos y acciones que a nivel federal se establezcan para el mismo fin\nLa aplicación de este ordenamiento estará a cargo de las autoridades del Gobierno de la Ciudad de México, quienes ejercerán las atribuciones que les correspondan, favoreciendo la coordinación interinstitucional para el fortalecimiento del desarrollo económico.\nArtículo modificado y publicado en la GOCDMX el 27 de abril de 2023\nArtículo 2.- Definición del fomento cooperativo.\nPara los efectos de la presente Ley, se entiende como fomento cooperativo el conjunto de normas jurídicas y acciones del Gobierno de la Ciudad de México, para la difusión, promoción, organización, expansión y desarrollo del sector y movimiento cooperativo y que deberá orientarse conforme a los siguientes fines:\nI. Apoyo a la organización, constitución, registro, desarrollo e integración de las propias\nSociedades Cooperativas y a la organización social del trabajo, como medios de generación de empleos y redistribución del ingreso;\nII. Promoción de la economía cooperativista en la producción, distribución y comercialización de los bienes y servicios que generan y que son socialmente necesarios;\nIII. Otorgamiento de mecanismos que aseguren la igualdad entre sectores y clases sociales, por lo que se prohíbe solicitar a los organismos del sector social mayores requisitos que los exigidos a otras entidades económicas para el concurso u otorgamiento de créditos o cualquier otro contrato con cualquier organismo de la Administración Pública de la Ciudad de México;\n\nIII Bis. Impulsar la participación de las personas mexicanas residentes en el extranjero en la constitución e inversión para el desarrollo de sociedades cooperativas.\nArtículo adicionado y publicado en la GOCDMX el 27 de abril de 2023\nIV. El Gobierno de la Ciudad de México procurará proveerse de los bienes y servicios que produzcan las sociedades cooperativas, siempre y cuando cumplan con lo dispuesto en la normatividad en materia de Adquisiciones vigente en la Ciudad de México.\nV. Acceso a estímulos e incentivos para la integración de las Sociedades Cooperativas, entre otras acciones, mediante apoyos fiscales y de simplificación administrativa;\nVI. Fortalecer entre la población la comercialización, consumo y disfrute de los bienes y servicios producidos por las cooperativas;\nVII. Participación del sector cooperativo en el Sistema de Planeación del Desarrollo de la Ciudad de México y en el Consejo Económico, Social y Ambiental de la Ciudad de México y demás que establezcan las Leyes vigentes en la Ciudad de México;\nFracción modificada y publicada en la GOCDMX el 27 de abril de 2023\nVIII. Impulsar la educación, capacitación y en general la cultura cooperativa y la participación de la población en la promoción, divulgación y financiamiento de proyectos cooperativos, de tal manera que se impulse la cultura del ahorro, mediante cajas populares y las cooperativas de ahorro y préstamo;\nIX. Garantizar el respeto por la organización social para el trabajo y hacer efectiva la participación de la población en el sector social de la economía;\nX. Difusión de la cultura cooperativista, basada en la organización social, autogestiva y democrática del trabajo;\nXI. Apoyar a las Sociedades Cooperativas con planes y programas de financiamiento para proyectos productivos y de generación de servicios;\nFracción modificada y publicada en la GOCDMX el 27 de abril de 2023\n\nXII. Las autoridades impulsarán la constitución y funcionamiento de sociedades cooperativas, que contribuyan al desarrollo económico de la Ciudad y el mejoramiento de las condiciones de vida de sus habitantes; y\nXIII. Los demás que establezcan las Leyes.\nArtículo 3.- Definiciones para los efectos de esta Ley, se entenderá por:\nPara los efectos de esta Ley, se entenderá por:\nI. Sociedad Cooperativa: a la forma de organización social integrada por personas físicas con base en intereses comunes y en los principios de solidaridad, esfuerzo propio y ayuda mutua, con el propósito de satisfacer necesidades individuales y colectivas, a través de la realización de actividades económicas de producción, distribución y consumo de bienes y servicios;\nII. Empleo: derecho humano consagrado por la Constitución federal, de dedicarse libremente a la profesión, industria, comercio o trabajo socialmente útil y de forma remunerada;\nIII. Movimiento cooperativo: todas las organizaciones e instituciones de asistencia técnica del cooperativismo registradas de conformidad con las leyes de la Ciudad de México;\nIV. Sistema cooperativo: estructura económica y social que integran las Sociedades Cooperativas y sus organismos;\nV. Sector cooperativo: población que desarrolla o es beneficiada por los actos cooperativos.\nArtículo 4.- Actos cooperativos\nLos actos cooperativos pueden ser subjetivos, objetivos, relativos y accesorios o conexos.\nI. Son actos cooperativos subjetivos, aquellos cuyo contenido proviene de los usos y las costumbres de las personas que los desarrollen y que las partes en ellos implicados decidan someterlos a la regulación y privilegios de esta ley;\nII. Son actos cooperativos objetivos, aquellos cuya característica proviene de la ley, independientemente de las personas que los realicen y que tengan por objeto:\n\na) Alguno de los señalados en esta ley, en las disposiciones que sobre ella se establezcan, así como todas las acciones de gobierno en materia cooperativa;\nb) Los que revistan formas que la legislación exige calificarlos de cooperativos, incluyendo los incorporados o derivados de los certificados de aportación;\nIII. Son actos cooperativos relativos aquellos cuyo fin sea participar en el mercado cooperativo; y,\nIV. Son actos accesorios o conexos aquellos que se deriven de otros actos cooperativos, siempre que las partes que los generen pacten expresamente someterlos a las prevenciones que establece esta ley.\nLa constitución, organización y capacidad jurídica de las sociedades cooperativas se rigen por las disposiciones de la legislación federal aplicable.\nArtículo 5.- Acciones de Gobierno\nLas acciones de gobierno en materia de fomento cooperativo se orientarán por los siguientes principios:\nI. Fomento de la educación cooperativa y de la educación en la economía solidaria;\nII. Respeto a los derechos humanos laborales, al empleo, la libertad de profesión e industria y a la organización social para el trabajo, como una de las bases de la existencia, convivencia y bienestar de la sociedad;\nIII. Respeto a la adhesión voluntaria y abierta al sector cooperativo sin discriminaciones, atendiendo a la composición pluricultural de sectores, géneros, manifestaciones y valores de los individuos y grupos sociales que componen la población de la Ciudad de México;\nIV. Respeto a la autonomía y gestión democrática en las sociedades cooperativas, a la integración y solidaridad entre éstas y su interés y servicio social por la comunidad;\nV. Respeto al derecho individual de los integrantes de las sociedades cooperativas a pertenecer a cualquier partido político o asociación religiosa;\n\nVI. Promover y facilitar la localización y el establecimiento de sociedades cooperativas y su participación en proyectos de reciclamiento del suelo y de desarrollo sustentable;\nFracción modificada y publicada en la GOCDMX el 27 de abril de 2023\nVII. Protección, conservación, consolidación y uso racional del patrimonio social del sistema cooperativo por parte de las autoridades del Gobierno;\nVIII. Organización social para el trabajo mediante el reconocimiento de las sociedades cooperativas como organismos de utilidad pública para el bienestar común y sujetas al fin social que establecen nuestras leyes;\nIX. Simplificación, agilidad, información, precisión, legalidad, transparencia, rendición de cuentas e imparcialidad en los actos y procedimientos administrativos;\nFracción modificada y publicada en la GOCDMX el 27 de abril de 2023\nX. Otorgar estímulos fiscales y apoyo económico a las sociedades cooperativas que cuenten con su plan anual de trabajo, en los términos que establezca esta Ley y el Código Fiscal de la Ciudad de México; y\nFracción modificada y publicada en la GOCDMX el 27 de abril de 2023\nXI. Fomentar la creación y adecuado desarrollo de sociedades cooperativas de vivienda, como canales sociales para garantizar el cumplimiento del derecho humano a una habitación digna y accesible. En el otorgamiento de estímulos fiscales y apoyos económicos tendrán prioridad aquellas que atiendan sectores vulnerables y contribuyan a la adquisición de vivienda de interés social.\nArtículo 6.- Interpretación\nTodo acto de interpretación de las disposiciones de la presente Ley, deberá atender a las garantías sociales y los derechos humanos reconocidos en la Constitución Política de los Estados Unidos Mexicanos y en la\nConstitución Política de la Ciudad de México.\nSon supletorias de la presente Ley, en materia administrativa, las disposiciones de la legislación local de la\nCiudad de México y en materia cooperativa, las de carácter federal vigentes.\n\nCAPÍTULO SEGUNDO\nDE LAS AUTORIDADES EN MATERIA DE FOMENTO COOPERATIVO DE LA\nCIUDAD DE MÉXICO\nArtículo 7.- Autoridades competentes\nLa organización y distribución de los negocios del orden administrativo en los términos de esta ley, corresponde a la persona titular de la Jefatura de Gobierno, a la Secretaría de Trabajo y Fomento al\nEmpleo, a la Secretaría de Desarrollo Económico, a la Secretaría de Inclusión y Bienestar Social, a la\nSecretaría de Administración y Finanzas y a la persona titular de cada una de las alcaldías en la forma y términos que determinen las Leyes correspondientes.\nArtículo 8.- Corresponde a la persona titular de la Jefatura de Gobierno:\nI. Aprobar el Programa General de Fomento Cooperativo de la Ciudad de México;\nII. Emitir las declaratorias de exención de contribuciones a las Sociedades Cooperativas, a excepción de las expresamente señaladas;\nIII. Emitir la convocatoria para la constitución del Consejo Consultivo de Fomento Cooperativo de la Ciudad de México, así como presidirlo;\nIV. Celebrar con las autoridades competentes los convenios para acceder al uso de los tiempos de transmisión que por ley le corresponden al Estado en radio y televisión, a fin de transmitir mensajes y programas de fomento cooperativo en la Ciudad de México;\nV. Suscribir con las instancias del Gobierno Federal o Estatal y con instituciones públicas y privadas del país o del extranjero, los convenios necesarios para lograr los fines de la presente\nLey; y\nVI. Autorización de estímulos fiscales para la integración de las Sociedades Cooperativas.\nArtículo 9.- Atribuciones específicas\nCorresponde a las siguientes Secretarías, sin perjuicio de lo dispuesto en otros ordenamientos, lo siguiente:\n\nA) A la Secretaría de Trabajo y Fomento al Empleo:\nI. Formular, difundir y ejecutar las políticas y programas de fomento cooperativo en la\nCiudad de México;\nII. Impulsar las actividades de fomento cooperativo en la Ciudad de México y proporcionar, por si o a través de personas bajo su revisión, físicas o morales, asesoría, capacitación y adiestramiento para la constitución, consolidación, administración y desarrollo de la Sociedades Cooperativas, así como para la producción, comercialización y consumo de los bienes y servicios necesarios para los actos que establece el artículo 4° de esta Ley;\nIII. Coordinar acciones de apoyo para el fortalecimiento del sistema, sector y movimiento cooperativo de la Ciudad de México; y\nIV. Garantizar el respeto por la organización social para el trabajo y hacer efectiva la participación de la población en la economía.\nB) A la Secretaría de Inclusión y Bienestar Social de la Ciudad de México:\nI. Procurar la expansión del sector cooperativo para que este pueda responder a las necesidades de la sociedad;\nII. Establecer programas de desarrollo social, a través de los cuales se puedan potenciar las actividades de las sociedades cooperativas en el ámbito territorial donde actúan para, de ser posible, generar polos regionales de desarrollo;\nIII. Promover la transformación de actividades marginales de la economía informal hacia grupos productivos organizados;\nIV. Consolidar las políticas públicas en la materia; y\nV. Acrecentar la conciencia y modelo cooperativo, como una opción viable de desarrollo económico y social para los habitantes.\n\nC) A la Secretaría de Desarrollo Económico:\nI. Ejecutar los apoyos económicos que el Gobierno de la Ciudad de México otorgue a las empresas sociales, a las micro empresas y a los sectores empresariales, así como los financiamientos y prerrogativas, a través del Fondo de Desarrollo Social;\nII. Apoyar servicios de investigación y asesoría en materia de gestión cooperativa, administrativa y tecnológica;\nIII. Promover el financiamiento ante las instancias públicas y privadas correspondientes para la producción, comercialización e inversión; y\nIV. Impulsar la cultura del ahorro, mediante las sociedades cooperativas de ahorro y préstamo en términos de lo dispuesto en la Ley para regular las actividades de las\nSociedades Cooperativas de Ahorro y Préstamo.\nD) A la Secretaría de Administración y Finanzas:\nI. Aplicar y ejecutar los estímulos fiscales en los términos de la presente Ley, las\nAutoridades y el Código Fiscal;\nII. Diseñar estímulos fiscales que para la creación de nuevas sociedades cooperativas;\nIII. Diseñar estímulos fiscales para proyectos de actualización, educación capacitación en favor de las sociedades cooperativas; y\nIV. Evaluar y diseñar nuevos estímulos fiscales que se adecuan a las necesidades de las sociedades cooperativas.\nArtículo 10.- Son atribuciones de las personas titulares de las Alcaldías.\nI. Participar en la elaboración y ejecución de los programas de fomento cooperativo de su demarcación, vigilar su implementación y dar seguimiento al desarrollo de las sociedades cooperativas;\nFracción modificada y publicada en la GOCDMX el 27 de abril de 2023\n\nII. Impulsar las actividades de fomento cooperativo, por si y en coordinación con las dependencias del ramo;\nIII. Promover la concertación, con otras instancias de Gobierno y con los sectores social y privado, para impulsar el desarrollo cooperativo en la Alcaldía;\nIV. Cada Alcaldía contará con una Dirección o área de Fomento Cooperativo;\nV. Fortalecer entre la población la comercialización, consumo y disfrute de los bienes y servicios producidos por las sociedades cooperativas; y\nVI. Implementar a través del área referida en la fracción IV del presente artículo, un programa de formación en cooperativismo, economía social y solidaria y consumo local.\nFracción modificada y publicada en la GOCDMX el 27 de abril de 2023\nArtículo 11.- Auxilio notarial.\nTodos los actos relativos a la constitución y registro de las sociedades cooperativas citados en esta Ley, estarán exentos de impuestos y derechos fiscales de carácter local, conforme a lo establezca el Código Fiscal de la Ciudad de México y las declaratorias que al efecto emita la autoridad competente.\nEn las escrituras públicas, para los efectos señalados en el párrafo anterior, los notarios cobrarán el arancel reducido que al efecto se establezca.\nCAPÍTULO TERCERO\nDEL FOMENTO COOPERATIVO\nArtículo 12.- Acciones de fomento\nEl fomento cooperativo en la Ciudad de México comprende, entre otras acciones, las siguientes:\nI. Acciones jurídicas, administrativas y de carácter socioeconómico que tengan como fin abrir, conservar, fomentar, proteger, y expandir las fuentes de empleo en el sector social, procurando\n\notorgar condiciones de factibilidad y simplificación administrativa para su apertura, desarrollo y legal funcionamiento;\nII. Acciones de registro, investigación, análisis y estudio para el exacto conocimiento de la situación del sistema, sector y movimiento cooperativo para mejorar, planear y consolidar las políticas públicas en la materia;\nFracción modificada y publicada en la GOCDMX el 27 de abril de 2023\nIII. Acciones de fomento y difusión del cooperativismo, para acrecentar la conciencia y modelo cooperativo, como una opción viable de desarrollo económico, social y sustentable para las personas habitantes de la Ciudad de México;\nIV. Acciones de capacitación y adiestramiento para la formación de personas aptas para desarrollar empresas sociales;\nV. Acciones de apoyo diverso para la organización, la protección y el impulso de los modos tradicionales solidarios de producción colectiva, de las culturas de los pueblos y barrios originarios, comunidades indígenas, rurales y populares residentes en la Ciudad de México;\nVI. Acciones de cooperación en materia cooperativa con la federación, los estados y municipios, y con otros países u organismos internacionales públicos y privados;\nVII. Acciones de fomento de las empresas cooperativas de participación estatal;\nVIII. Acciones que aseguren la igualdad entre sectores y las Sociedades Cooperativas en el concurso u otorgamiento de créditos o cualquier otro contrato con cualquier organismo de la\nAdministración Pública; y\nIX. Los demás conceptos a los que esta Ley y otros ordenamientos jurídicos les den ese carácter.\nArtículo 13.- Fomento organizativo\nCon el fin de fomentar la organización social para el trabajo, el Gobierno de la Ciudad de México promoverá:\nI. La creación de estímulos, becas y cualquier otra clase de reconocimientos y apoyos;\n\nII. La creación de fondos para posibilitar el fomento al desarrollo de Sociedades Cooperativas y la producción cooperativa en la Ciudad de México; y\nIII. La celebración de convenios con entidades públicas y los sectores social y privado.\nArtículo 14.- Fomento regional\nEl Gobierno de la Ciudad de México fomentará las formas de empleo socialmente útiles, así como la formación de Sociedades Cooperativas de los habitantes de la Ciudad de México en sus barrios, colonias, unidades habitacionales, pueblos o comunidades.\nArtículo 15.- Valores sociales\nSon materia de protección y consolidación en los términos de la presente Ley, el fomento y desarrollo de\nSociedades Cooperativas que tengan por objeto promover, difundir, publicar y desarrollar el conjunto de los bienes y valores de interés público señalados en este ordenamiento, en particular los relacionados con actividades de equidad de género, desarrollo sustentable, cultura indígena, jóvenes, cultura, discapacitados y adultos mayores que se produzcan.\nCAPÍTULO CUARTO\nDE LA FORMACIÓN COOPERATIVA\nArtículo 16.- Convenios de formación\nLas autoridades señaladas en esta Ley podrán celebrar convenios de todo tipo con instituciones autorizadas legalmente para la capacitación académica o técnica de los cooperativistas residentes en la\nCiudad de México, para lo cual se preferirán en igualdad de circunstancias a las sociedades cooperativas que registren sus programas y proyectos ante la Secretaría de Trabajo y Fomento al Empleo.\nArtículo 17.- Formación y capacitación\nEl Gobierno de la Ciudad de México fomentará la formación y capacitación continua de las personas que se desempeñen como administradores, promotores o gestores de sociedades cooperativas, a fin de lograr el óptimo aprovechamiento en la coordinación del esfuerzo en común.\n\nAsimismo, deberá acordar con las autoridades e instituciones educativas la inclusión en los planes de estudio los principios y valores cooperativos, así como de las actividades cooperativas.\nCAPÍTULO QUINTO\nDE LA FORMACIÓN DE LA POLÍTICA Y DE LOS PROGRAMAS DE\nFOMENTO COOPERATIVO\nArtículo 18.- Formación de Políticas y Programas\nEn la formación de las políticas generales y los programas de fomento cooperativo, el Gobierno de la\nCiudad de México elaborará anualmente las acciones y programas en la materia.\nLas políticas públicas deberán estar sujetas a mecanismos de medición y evaluación en su desempeño.\nSe reforzarán las políticas que cuenten con rezago en su crecimiento, con el objeto de generar oportunidades de igualdad entre los distintos sectores económicos de conformidad con la Ley de Desarrollo\nSocial vigente en la Ciudad de México.\nArtículo 19.- Contenido de los Programas\nLos programas de fomento cooperativo de carácter general, sectorial y por Alcaldía a los que se refiere la presente Ley, deberán contener y precisar:\nI. Antecedentes, marco y justificación legal;\nII. Análisis y diagnóstico de la situación económica y social de la región, sector o demarcación territorial correspondiente;\nIII. Objetivos generales y específicos;\nIV. Metas y políticas;\nV. Estrategias, proyectos y programas específicos;\n\nVI. Financiamiento y estímulos;\nVII. Acciones generales y actividades prioritarias;\nVIII. Criterios para su seguimiento y evaluación;\nIX. Cronograma y responsabilidades; y\nX. Soporte estadístico, bibliográfico, de campo u otros.\nArtículo 20.- Programación y fomento\nEn la programación del fomento cooperativo para la Ciudad de México se tomará en cuenta:\nI. La diversidad económica y cultural de los habitantes de la Ciudad de México;\nII. La equidad en la distribución geográfica de los beneficios económicos, a fin de lograr un eficiente y justo equilibrio de dichos beneficios entre la población de la Ciudad de México; y\nIII. Los principios a los que se refiere el artículo 3 º de la presente Ley, así como la solidaridad, el esfuerzo propio y la ayuda mutua con el propósito de satisfacer necesidades individuales y colectivas a través de la realización de actividades socioeconómicas de producción, distribución y consumo de bienes y servicios.\nArtículo 21.- Se constituirá un Consejo Consultivo de Fomento Cooperativo de la Ciudad de México, como órgano de consulta en la materia, mismo que presidirá la persona titular de la Jefatura de Gobierno o la persona que ésta designe.\nEl Reglamento de la presente Ley regulará el procedimiento de elección, así como la organización y el funcionamiento de este Consejo.\nCAPÍTULO SEXTO\nDEL FINANCIAMIENTO DEL FOMENTO DE LA ACTIVIDAD COOPERATIVA\nArtículo 22.- Financiamiento\n\nCorresponde al Gobierno de la Ciudad de México financiar el fomento cooperativo, sin perjuicio de celebrar convenios o contratos que apoyen la realización de actividades y proyectos concretos.\nLos donativos que se reciban para el fomento de la actividad cooperativa estarán amparados por recibos oficiales y no podrán ser destinados a fines distintos de los establecidos en la presente Ley.\nArtículo 23.- Presupuestos\nEn los Programas Operativos Anuales y en el Presupuesto de Egresos de la Ciudad de México, quedarán definidas las partidas necesarias para el fomento cooperativo de conformidad con la presente Ley, incluyendo los programas y actividades generales.\nArtículo 24.- Estímulos\nLas sociedades cooperativas gozarán de la exención de impuestos, contribuciones y derechos a las que estén obligadas durante sus dos primeros años de existencia, sin perjuicio de las declaratorias que al respecto emita la persona titular de la Jefatura de Gobierno, siempre que cumpla con los requisitos que se establezcan de conformidad con lo siguiente:\nI. Las sociedades cooperativas de consumidores dedicadas a suministrar exclusivamente a sus socios, víveres, ropa y calzado, mientras el capital no exceda de veinte mil pesos;\nII. Las sociedades cooperativas de productores, mientras el capital social no exceda de quince mil pesos y estén integradas en su totalidad por obreros o campesinos o por los dos. Para efectos del siguiente artículo no se contabilizará como parte del capital de la sociedad, el capital amortizado de los muebles, maquinaria y demás bienes necesarios para los fines económicos de la sociedad cooperativa; y\nIII. Las sociedades cooperativas mixtas de productores y consumidores, mientras su capital no exceda la cantidad de doce mil pesos.\nCuando el capital de las sociedades cooperativas a las que se refiere el artículo anterior, exceda el límite señalado, sin que sobrepase el doble de las sumas indicadas, cubrirá el 70% de los impuestos, contribuciones y derechos que estén obligadas a cubrir.\n\nTRANSITORIOS\nPRIMERO.- La presente Ley entrará en vigor al día siguiente de su publicación en la Gaceta Oficial del\nDistrito Federal y para su mayor difusión también se publicará en el Diario Oficial de la Federación.\nSEGUNDO.- A partir de la entrada en vigor de la presente Ley se derogan todos los acuerdos, circulares, disposiciones administrativas y legales que en el Distrito Federal se le opongan al presente decreto.\nTERCERO.- Dentro de los siguientes noventa días a la vigencia de la presente Ley, el Jefe de Gobierno del\nDistrito Federal dictará las disposiciones necesarias para delegar en la Subsecretaría de Trabajo y Previsión\nSocial de la Secretaría de Gobierno las facultades indicadas, así como para dictar las resoluciones fiscales que de acuerdo a esta Ley procedan. Asimismo, el Jefe de Gobierno del Distrito federal deberá expedir el\nReglamento de la presente Ley dentro del término de noventa días siguientes a la publicación del presente decreto.\nCUARTO.- El Gobierno del Distrito Federal adecuará dentro de los 15 días siguientes a la publicación del presente decreto, sus ordenamientos de adquisiciones, arrendamientos y obra pública para que las cooperativas accedan en igualdad de circunstancias a los procedimientos de licitación, invitación y asignación de los bienes y servicios que produzcan o comercien.\nQUINTO.- El Gobierno del Distrito Federal instrumentando el cumplimiento de la Recomendación 193 de la Organización Internacional del Trabajo, dictará las medidas necesarias para la organización, promoción, desarrollo y protección de las cooperativas en condiciones de equidad entre los sectores.\nRecinto de la Asamblea Legislativa del Distrito Federal, a los cuatro días del mes de octubre del año dos mil cinco.- POR LA MESA DIRECTIVA.- DIP. HÉCTOR MAURICIO LÓPEZ VELÁZQUEZ, PRESIDENTE.- DIP. PABLO\nTREJO PÉREZ, SECRETARIO.- DIP. MARÍA TERESITA DE JESÚS AGUILAR MARMOLEJO, SECRETARIA.- (Firmas)\nEn cumplimiento de lo dispuesto por los artículos 122, apartado C, Base Segunda, fracción II, inciso b), de la Constitución Política de los Estados Unidos Mexicanos; 48, 49 y 67, fracción II del Estatuto de Gobierno del Distrito Federal, y para su debida publicación y observancia, expido el presente Decreto Promulgatorio, en la Residencia Oficial del Jefe de Gobierno del Distrito Federal, en la Ciudad de México a los seis días del mes de enero de dos mil seis.- EL JEFE DE GOBIERNO DEL DISTRITO FEDERAL, ALEJANDRO DE JESÚS\nENCINAS RODRÍGUEZ.- FIRMA.- EL SECRETARIO DE GOBIERNO, RICARDO RUIZ SUÁREZ.- FIRMA.- LA\nSECRETARIA DE DESARROLLO CONÓMICO, JENNY SALTIEL COHEN.- FIRMA.- LA SECRETARIA DE\n\nDESARROLLO SOCIAL, MARTHA PÉREZ BEJARANO.- FIRMA.- EL SECRETARIO DE FINANZAS, ARTURO\nHERRERA GUTIÉRREZ.- FIRMA.\nTRANSITORIOS DEL DECRETO POR EL QUE SE REFORMAN, ADICIONAN Y DEROGAN DIVERSOS ARTÍCULOS\nDE LA LEY ORGÁNICA DE LA ADMINISTRACIÓN PÚBLICA DEL DISTRITO FEDERAL, LEY DE FOMENTO PARA EL\nDESARROLLO ECONÓMICO DEL DISTRITO FEDERAL, LEY DE ASISTENCIA E INTEGRACIÓN SOCIAL PARA EL\nDISTRITO FEDERAL, LEY DE FOMENTO COOPERATIVO PARA EL DISTRITO FEDERAL, LEY DE DESARROLLO\nSOCIAL PARA EL DISTRITO FEDERAL, LEY DE FOMENTO CULTURAL DEL DISTRITO FEDERAL, LEY PARA\nPREVENIR Y ERRADICAR LA DISCRIMINACIÓN EN EL DISTRITO FEDERAL Y LA LEY DE EDUCACIÓN DEL\nDISTRITO FEDERAL, PUBLICADO EN LA GACETA OFICIAL DEL DISTRITO FEDERAL EL 6 DE FEBRERO DE 2007\nPRIMERO.- Publíquese en la Gaceta Oficial del Distrito Federal, y en el Diario Oficial de la Federación para su mayor difusión.\nSEGUNDO.- Las presentes reformas y adiciones entrarán en vigor al día siguiente de su publicación en la\nGaceta Oficial del Distrito Federal.\nTERCERO.- El personal que de una dependencia que, en aplicación del presente decreto, se transfiera a otra, en ninguna forma resultará afectado en los derechos que haya adquirido en virtud de su relación laboral con la administración pública local del Distrito Federal. Si por cualquier circunstancia algún grupo de trabajadores resultare afectado con la aplicación del presente Decreto, se dará previamente intervención a la Oficialía Mayor del Distrito Federal y a las organizaciones sindicales respectivas.\nCUARTO.- Cuando alguna Unidad Administrativa de las establecidas por las leyes anteriores a la vigencia del presente decreto pase, con motivo de éste, a otra Dependencia, el traspaso se hará incluyendo al personal de servicio, mobiliario, vehículos, instrumentos, aparatos, maquinaria, archivos y en general, el equipo que la Unidad Administrativa de que se trate haya utilizado para la atención de los asuntos a su cargo.\nQUINTO.- Los asuntos que con motivo del presente Decreto deban pasar de una dependencia a otra, permanecerán en el último trámite que hubieren alcanzado hasta que las Unidades Administrativas que los tramiten se incorporen a la Dependencia que señale el presente Decreto, a excepción de los trámites urgentes o sujetos a plazo improrrogable\n\nSEXTO.- El Titular de la Jefatura de Gobierno por conducto de la Secretaría de Finanzas, y de conformidad con la normatividad aplicable, dotará de recursos a las Secretarías de reciente creación, adecuando el presupuesto autorizado para las dependencias en el ejercicio 2007, mediante movimientos programáticospresupuestarios compensados.\nTRANSITORIO DEL DECRETO POR EL QUE SE MODIFICA LA DENOMINACIÓN, SE REFORMAN Y ADICIONAN\nDIVERSOS ARTÍCULOS DE LA LEY DE FOMENTO COOPERATIVO PARA EL DISTRITO FEDERAL, PUBLICADO EN\nLA GACETA OFICIAL EL DÌA 19 DE MARZO DE 2021.\nPRIMERO. - Remítase a la persona titular de la Jefatura de Gobierno, para su promulgación y publicación en la Gaceta Oficial de la Ciudad de México.\nSEGUNDO. El presente Decreto entrará en vigor al día siguiente de su publicación.\nPalacio Legislativo del Congreso de la Ciudad de México, a los dieciséis días del mes de febrero del año dos mil veintiuno. POR LA MESA DIRECTIVA.-DIPUTADA MARGARITA SALDAÑA HERNÁNDEZ, PRESIDENTA.-\nDIPUTADA DONAJI OFELIA OLIVERA REYES, SECRETARIA.- DIPUTADO PABLO MONTES DE OCA DEL OLMO,\nSECRETARIO.- (FIRMAS)\nCon fundamento en lo dispuesto por los artículos 122, apartado A, fracción III de la Constitución Política de los Estados Unidos Mexicanos; 32, apartado C, numeral 1, inciso a) de la Constitución Política de la Ciudad de México; 2 párrafo segundo, 3 fracciones XVII y XVIII, 7 párrafo primero, 10 fracción II, 12 y 21 párrafo primero de la Ley Orgánica del Poder Ejecutivo y de la Administración Pública de la Ciudad de México; para su debida publicación y observancia, expido el presente Decreto Promulgatorio en la Residencia Oficial de la Jefatura de Gobierno de la Ciudad de México, a los dieciocho días del mes de marzo del año dos mil veintiuno.- LA JEFA DE GOBIERNO DE LA CIUDAD DE MÉXICO, DRA. CLAUDIA SHEINBAUM PARDO.- FIRMA-\nEL SECRETARIO DE GOBIERNO, JOSÉ ALFONSO SUÁREZ DEL REAL Y AGUILERA.- FIRMA.--LA SECRETARIA DE\nADMINISTRACIÓN Y FINANZAS, LUZ ELENA GONZÁLEZ ESCOBAR.- FIRMA.- EL SECRETARIO DE DESARROLLO\nECONÓMICO, FADLALA AKABANI HNEIDE.- FIRMA.- LA SECRETARIA DE INCLUSIÓN Y BIENESTAR SOCIAL,\nALMUDENA OCEJO ROJO.- FIRMA.- LA SECRETARIA DE TRABAJO Y FOMENTO AL EMPLEO, HAYDEÉ SOLEDAD\nARAGÓN MARTÍNEZ.- FIRMA.- EL CONSEJERO JURÍDICO Y DE SERVICIOS LEGALES, NÉSTOR VARGAS\nSOLANO.- FIRMA.\n\nTRANSITORIOS DEL DECRETO POR EL QUE SE MODIFICAN LAS FRACCIONES IX Y X, Y SE ADICIONA LA\nFRACCIÓN XI AL ARTÍCULO 5 DE LA LEY DE FOMENTO COOPERATIVO PARA LA CIUDAD DE MÉXICO,\nPUBLICADO EN LA GACETA OFICIAL DE LA CIUDAD DE MÉXICO, EL 27 DE OCTUBRE DE 2022.\nPRIMERO.- Remítase a la Jefatura de Gobierno de la Ciudad de México para su promulgación y publicación en la Gaceta Oficial de la Ciudad de México.\nSEGUNDO.- El presente Decreto entrará en vigor al día siguiente de su publicación en la Gaceta Oficial de la Ciudad de México.\nPalacio Legislativo del Congreso de la Ciudad de México, a los trece días del mes de septiembre del año dos mil veintidós.- POR LA MESA DIRECTIVA.- DIPUTADO FAUSTO MANUEL ZAMORANO ESPARZA,\nPRESIDENTE.- DIPUTADA MARCELA FUENTE CASTILLO, SECRETARIA.- DIPUTADA MARIA GABRIELA SALIDO\nMAGOS, SECRETARIA.- (Firmas)\nCon fundamento en lo dispuesto por los artículos 122, apartado A, fracción III de la Constitución Política de los Estados Unidos Mexicanos; 32, apartado C, numeral 1, inciso a) de la Constitución Política de la Ciudad de México; 2 párrafo segundo, 3 fracciones XVII y XVIII, 7 párrafo primero, 10 fracción II, 12 y 21 párrafo primero de la Ley Orgánica del Poder Ejecutivo y de la Administración Pública de la Ciudad de México; para su debida publicación y observancia, expido el presente Decreto Promulgatorio en la Residencia Oficial de la Jefatura de Gobierno de la Ciudad de México, a los veintiséis días del mes de octubre del año dos mil veintidós.-LA JEFA DE GOBIERNO DE LA CIUDAD DE MÉXICO, DRA. CLAUDIA SHEINBAUM PARDO.- FIRMA.-\nEL SECRETARIO DE GOBIERNO, MARTÍ BATRES GUADARRAMA.- FIRMA.- LA SECRETARIA DE\nADMINISTRACIÓN Y FINANZAS, LUZ ELENA GONZÁLEZ ESCOBAR.- FIRMA.- SECRETARIO DE DESARROLLO\nECONÓMICO, FADLALA AKABANI HNEIDE.- FIRMA.- EL SECRETARIO DE DESARROLLO URBANO Y VIVIENDA,\nCARLOS ALBERTO ULLOA PÉREZ.- FIRMA.-\nDECRETO POR EL QUE SE ADICIONA UN TERCER PÁRRAFO AL ARTÍCULO 1, SE ADICIONA UNA FRACCIÓN III\nBIS Y SE REFORMAN LAS FRACCIONES VII Y XI, DEL ARTÍCULO 2, SE REFORMAN LAS FRACCIONES VI, IX Y X\nDEL ARTÍCULO 5; SE REFORMAN LAS FRACCIONES I Y VI DEL ARTÍCULO 10 Y SE REFORMA LA FRACCIÓN III\nDEL ARTÍCULO 12 DE LA LEY DE FOMENTO COOPERATIVO PARA LA CIUDAD DE MÉXICO, PUBLICADO EN LA\nGACETA OFICIAL DE LA CIUDAD DE MÉXICO EL 27 DE ABRIL DE 2023.\nPRIMERO.- Remítase a la persona titular de la Jefatura de Gobierno de la Ciudad de México, para su promulgación y publicación en la Gaceta Oficial de la Ciudad de México.\n\nSEGUNDO.- El presente Decreto entrará en vigor al día siguiente de su publicación en la Gaceta Oficial de la Ciudad de México.\nPalacio Legislativo del Congreso de la Ciudad de México, a los diecinueve días del mes de abril del año dos mil veintitrés..- POR LA MESA DIRECTIVA.- DIPUTADO FAUSTO MANUEL ZAMORANO ESPARZA, PRESIDENTE.-\nDIPUTADA MARCELA FUENTE CASTILLO, SECRETARIA.- DIPUTADA MARIA GABRIELA SALIDO MAGOS,\nSECRETARIA.- (Firmas)\nCon fundamento en lo dispuesto por los artículos 122, apartado A, fracción III de la Constitución Política de los Estados Unidos Mexicanos; 32, apartado C, numeral 1, inciso a) de la Constitución Política de la Ciudad de México; 2 párrafo segundo, 3 fracciones XVII y XVIII, 7 párrafo primero, 10 fracción II, 12 y 21 párrafo primero de la Ley Orgánica del Poder Ejecutivo y de la Administración Pública de la Ciudad de México; para su debida publicación y observancia, expido el presente Decreto Promulgatorio en la Residencia Oficial de la Jefatura de Gobierno de la Ciudad de México, a los veintiséis días del mes de abril del año dos mil veintitrés.- LA JEFA DE GOBIERNO DE LA CIUDAD DE MÉXICO, DRA. CLAUDIA SHEINBAUM PARDO.- FIRMA.-\nEL SECRETARIO DE GOBIERNO, MARTÍ BATRES GUADARRAMA.- FIRMA.- LA SECRETARIA DE ADMINISTRACIÓN\nY FINANZAS, LUZ ELENA GONZÁLEZ ESCOBAR.- FIRMA.- EL SECRETARIO DE DESARROLLO ECONÓMICO,\nFADLALA AKABANI HNEIDE.- FIRMA.- LA SECRETARIA DEL MEDIO AMBIENTE, MARINA ROBLES GARCÍA.-\nFIRMA.- EL SECRETARIO DE TRABAJO Y FOMENTO AL EMPLEO, JOSÉ LUIS RODRÍGUEZ DÍAZ DE LEÓN.- FIRMA.",
  "ordenamiento": "Marco Jurídico",
  "jurisdiccion": "CIUDAD DE MEXICO",
  "fuente_oficial": "Congreso de la Ciudad de México",
  "status": "Vigente",
  "Fecha de Publicación": "05-05-2023",
  "Fecha de Última Reforma": "27 de abril de 2023",
  "numero_paginas": 20,
  "es_escaneado": false,
  "tiene_tablas": false,
  "url": "https://www.congresocdmx.gob.mx/archivo-e42509ab2bd667d2837a38701e993734f49d56f6.pdf",
  "materia": [
    "económico",
    "cooperativismo"
  ]
}