{
  "titulo": "Ley DE RESIDUOS SÓLIDOS DEL DISTRITO FEDERAL",
  "Contenido": "PUBLICADA EN LA GACETA OFICIAL DEL DISTRITO FEDERAL\nEL 22 DE ABRIL DE 2003\nTEXTO VIGENTE\nÚLTIMA REFORMA PUBLICADA EN LA G.O.C.D.M.X.\nEL 03 DE ABRIL DE 2023\nASAMBLEA LEGISLATIVA DEL DISTRITO FEDERAL\nDECRETO POR EL QUE SE CREA LA LEY DE RESIDUOS SÓLIDOS DEL DISTRITO FEDERAL\nDECRETO\n(Al margen superior izquierdo el escudo nacional que dice: ESTADOS UNIDOS MEXICANOS. - ASAMBLEA\nLEGISLATIVA DEL DISTRITO FEDERAL. - II LEGISLATURA)\nLA ASAMBLEA LEGISLATIVA DEL DISTRITO FEDERAL,\nII LEGISLATURA\nD E C R E T A:\nDECRETO POR EL QUE SE CREA LA LEY DE RESIDUOS SÓLIDOS DEL DISTRITO FEDERAL\n\nTÍTULO PRIMERO\nDE LAS DISPOSICIONES GENERALES\nCAPÍTULO ÚNICO\nDEL OBJETO DE LEY\nArtículo 1º.- La presente Ley es de observancia general en la Ciudad de México, sus disposiciones son de orden público e interés social, y tiene por objeto regular la gestión integral de los residuos sólidos considerados como no peligrosos, así como la prestación del servicio público de limpia.\nReforma publicada en la GOCDMX el 03 de Abril de 2023\nArtículo 2º.- Son de aplicación supletoria las disposiciones contenidas en otras leyes, reglamentos, normas y demás ordenamientos jurídicos relacionados con las materias que regula la presente Ley.\nArtículo 3º.- Para los efectos de la presente Ley se entiende por:\nI. Acopio: La acción tendiente a reunir residuos sólidos en un lugar determinado y apropiado para su recolección, tratamiento o disposición final;\nII. Almacenamiento: El depósito temporal de los residuos sólidos en contenedores previos a su recolección, tratamiento o disposición final;\nIII. Almacenamiento selectivo o separado: La acción de depositar los residuos sólidos en los contenedores diferenciados;\nIV. Aprovechamiento del valor o valorización: El conjunto de acciones cuyo objetivo es mantener los materiales contenidos en los residuos en los ciclos económicos, productivos o comerciales, mediante su recuperación, reutilización, remanufactura, reparación, rediseño, reprocesamiento, reciclaje, tratamiento y coprocesamiento;\nFracción reformada y publicada en la GOCDMX el 03 de Abril de 2023\nIV BIS. Biodegradable: Material que es capaz de descomponerse en dióxido de carbono, metano, agua, componentes inorgánicos o biomasa, como resultado de la acción de microorganismos;\n\nV. Biogás: El conjunto de gases generados por la descomposición microbiológica de la materia orgánica;\nVI. Biopolímero: Es un polímero de origen natural que puede ser sintetizado por microorganismos u obtenido de fuentes animales o plantas. Son básicamente generados de recursos renovables tales como el Ácido Poliláctico (PLA) y el Polihidroxialcanoato (PHA) de forma enunciativa, más no limitativa, y por regla general son fácilmente biodegradables y compostables, pero pueden no serlo;\nVII. Biogás: El conjunto de gases generados por la descomposición microbiológica de la materia orgánica;\nVII Bis.- Centros de acopio instalaciones autorizadas por la Secretaría para la prestación de servicios a terceros en donde se reciben, cuantifican, reúnen, separan, trasvasan y almacenan temporalmente residuos de la construcción y demolición de una o diferentes fuentes para ser recuperados y reutilizados en los términos de la normatividad aplicable, o enviados a instalaciones autorizadas para su tratamiento, reciclaje, reutilización, coprocesamiento o disposición final.\nFracción adicionada y publicada en la GOCDMX el 03 de Abril de 2023\nVIII. Composta: El producto resultante del proceso de composteo;\nVIII BIS. Compostable: Material susceptible a biodegradarse como mínimo al 90 por ciento en 6 meses, si es sometido a un ambiente rico de dióxido de carbono o en contacto con materiales orgánicos, al cabo de 3 meses la masa del material debe estar constituida como mínimo por el\n90% de fragmentos de dimensiones inferiores a 2 milímetros;\nIX. Composteo: El proceso de descomposición aeróbica de la materia orgánica mediante la acción de microorganismos específicos;\nX. Consumo Sustentable: El uso de bienes y servicios que responde a necesidades básicas y proporciona una mejor calidad de vida, al tiempo que minimizan el uso de recursos naturales, materiales tóxicos y emisiones de desperdicios y contaminantes durante todo el ciclo de vida, de tal manera que se origina una forma responsable de disminuir riesgos en las necesidades de de futuras generaciones;\nXI. Contenedor: El recipiente destinado al depósito temporal de los residuos sólidos;\n\nXII. Criterios: Los lineamientos obligatorios contenidos en la presente Ley para orientar las acciones de gestión integral de los residuos sólidos, que tendrán el carácter de instrumentos de política ambiental;\nXII Bis.- Daño al ambiente: Pérdida, cambio, deterioro, menoscabo, afectación o modificación adversos y mesurables de los hábitats, de los ecosistemas, de los elementos y recursos naturales, de sus condiciones químicas, físicas y biológicas, de las relaciones e interacción que se dan entre éstos, así como de los servicios ambientales que proporcionan.\nXIII. Alcaldías: Los órganos político administrativos de cada demarcación territorial en las que se divide la Ciudad de México;\nFracción reformada y publicada en la GOCDMX el 21 de Octubre de 2022\nXIV. Disposición final: La acción de depositar o confinar permanentemente residuos sólidos en sitios o instalaciones cuyas características prevean afectaciones a la salud de la población y a los ecosistemas y sus elementos;\nXV. Estaciones de transferencia: Las instalaciones para el trasbordo de los residuos sólidos de los vehículos de recolección a los vehículos de transferencia;\nXV Bis. Certificado de Empresas Ambientalmente Responsables: El certificado otorgado por la\nSecretaría, a empresas y prestadores de servicio en cuya actividad aplica métodos, prácticas, técnicas y procesos que ayudan a reutilizar, reusar, reciclar, tratar y minimizar los residuos sólidos, donde todas estas actividades son compatibles y aceptadas como amigables para el medio ambiente, son seguras, de bajo riesgo para la población en general y beneficio de la misma, en términos de la Ley Ambiental del Distrito Federal, su Reglamento y demás disposiciones aplicables.\nXVI. Generación: La acción de producir residuos sólidos a través de procesos productivos o de consumo;\nXVII. Generadores de alto volumen: Las personas físicas o morales que generen un promedio igual o superior a 50 kilogramos diarios en peso bruto total de los residuos sólidos o su equivalente en unidades de volumen;\nXVIII. Gestión integral: El conjunto articulado e interrelacionado de acciones y normas operativas,\n\nfinancieras, de planeación, administrativas, sociales, educativas, de monitoreo, supervisión y evaluación para el manejo de los residuos sólidos, desde su generación hasta la disposición final;\nXIX. Impactos ambientales significativos: Aquellos realizados por las actividades humanas que sobrepasen los límites permisibles en las normas oficiales mexicanas, las normas ambientales para el Distrito Federal, la ley ambiental, la ley General, los reglamentos y demás disposiciones jurídicas aplicables, o bien aquellos producidos por efectos naturales que implique daños al ambiente;\nXX. Ley General: La Ley General del Equilibrio Ecológico y la Protección al Ambiente;\nXXI. Ley Ambiental: La Ley Ambiental del Distrito Federal;\nXXII. Lixiviados: Los líquidos que se forman por la reacción, arrastre o filtrado de los materiales que constituyen los residuos sólidos y que contienen sustancias en forma disuelta o en suspensión que pueden infiltrarse en los suelos o escurrirse fuera de los sitios en los que se depositen residuos sólidos y que puede dar lugar a la contaminación del suelo y de cuerpos de agua;\nXXIII. Manejo Integral: Las actividades de reducción en la fuente, separación, reutilización, reciclaje, co-procesamiento, tratamiento biológico, químico, físico o térmico, acopio, almacenamiento, transporte y disposición final de residuos, individualmente realizadas o combinadas de manera apropiada, para adaptarse a las condiciones y necesidades de cada lugar, cumpliendo objetivos de valorización, eficiencia sanitaria, ambiental, tecnológica, económica y social;\nXXIII Bis.- Manifiesto de entrega – recepción: Es el documento\nFracción adicionada y publicada en la GOCDMX el 03 de Abril de 2023\nXXIII Ter.-Materiales reciclados: Aquellos materiales contenidos en los residuos que son transformados y reincorporados en los ciclos productivos mediante un proceso de reciclaje.\nFracción adicionada y publicada en la GOCDMX el 03 de Abril de 2023\nXXIII Quáter.- Microplásticos: Fragmentos de plástico de tamaño inferior a 5 milímetros.\nFracción modificada y publicada en la GOCDMX el 03 de Abril de 2023\nXXIV. Minimización: El conjunto de medidas tendientes a evitar la generación de los residuos\n\nsólidos y aprovechar, tanto sea posible, el valor de aquellos cuya generación no sea posible evitar;\nXXV. Plan de Manejo: El Instrumento cuyo objetivo es minimizar la generación y maximizar la valorización de residuos sólidos urbanos y residuos de manejo especial, bajo criterios de eficiencia ambiental, tecnológica, económica y social, diseñado bajo los principios de responsabilidad compartida y manejo integral, que considera el conjunto de acciones, procedimientos y medios viables e involucra a productores, importadores, exportadores, distribuidores, comerciantes, consumidores, usuarios de subproductos y grandes generadores de residuos, según corresponda, así como a los tres niveles de gobierno;\nXXV Bis.- Planta de Reciclaje de Residuos de la Construcción y de la Demolición (PR-RCD):\nInstalación cuyo objetivo es transformar los residuos de la construcción, demolición y excavación en agregados reciclados y subproductos para reincorporarlos a un ciclo de vida, a fin de evitar que se desperdicien estos residuos potencialmente útiles, reducir el consumo de materiales naturales, así como el uso de energía;\nFracción adicionada y publicada en la GOCDMX el 03 de Abril de 2023\nXXV Ter.-Plataforma digital de trazabilidad: Plataforma informática que permite establecer la gestión integral de los residuos de manejo especial a partir de los datos registrados en los manifiestos de entrega-recepción.\nFracción adicionada y publicada en la GOCDMX el 03 de Abril de 2023\nXXV Quáter.- Prestador de servicios para el manejo de residuos: personas físicas o morales que cuentan con el respectivo permiso, licencia o autorización otorgado por la Secretaría, para cualquiera de las siguientes actividades: recolectar, transportar, acopiar y/o reciclar residuos sólidos y de manejo especial;\nFracción adicionada y publicada en la GOCDMX el 03 de Abril de 2023\nXXVI. Planta de selección y tratamiento: La instalación donde se lleva a cabo cualquier proceso de selección y tratamiento de los residuos sólidos para su valorización o, en su caso, disposición final;\nXXVI BIS. Plástico. Material fabricado a partir de una amplia gama de polímeros orgánicos, fósiles y no fósiles, tales como el tereftalato de polietileno (PET), el polipropileno (PP), el polietileno de baja densidad (PEBD), el polietileno de alta densidad (PEAD), el poliestireno (PS), poliestireno expandido (PSE), el policloruro de vinilo (PVC) y policarbonato que pueden moldearse mientras\n\nes suave y luego volverse a su forma rígida o ligeramente rígida e incluso elástica;\nXXVI TER. Plásticos degradables: Materiales plásticos a los que se incluyen aditivos catalizadores que propician su descomposición en múltiples etapas. Incluye los plásticos oxodegradables, fotodegradables, hidrodegradables y termodegradables, de manera enunciativa más no limitativa;\nXXVI QUATER. Productos plásticos de un solo uso: Productos que se fabrican total o parcialmente a partir de plástico y que no están concebidos para lograr, dentro de su vida útil, múltiples rotaciones al ser devueltos al productor para su recarga o ser reutilizados para el mismo propósito con que fueron concebidos, tales como bolsas, tenedores, cuchillos, cucharas, palitos mezcladores, platos, popotes o pajitas, bastoncillos para hisopos de algodón, globos y varillas para globos, vasos y sus tapas, charolas para transportar alimentos, aplicadores de tampones, fabricados total o parcialmente de plásticos, de manera enunciativa más no limitativa;\nXXVII. Pepena: La acción de recoger entre los residuos sólidos aquellos que tengan valor en cualquier etapa del sistema de manejo;\nXXVIII. Procuraduría: La Procuraduría Ambiental y del Ordenamiento Territorial del Distrito\nFederal;\nXXIX. Producción Sustentable: Aquella que incluye aspectos de reducción en el uso de energía, materias primas y materiales tóxicos, así como procesos más eficientes para la obtención de beneficios ambientales y económicos y una producción más limpia;\nXXX. Recolección: La acción de recibir los residuos sólidos de sus generadores y trasladarlos a las instalaciones para su transferencia, tratamiento o disposición final;\nXXXI. Recolección selectiva o separada: La acción de recolectar los residuos sólidos de manera separada en orgánicos, inorgánicos y de manejo especial;\nXXXII. Reciclaje: La transformación de los materiales o subproductos contenidos en los residuos sólidos a través de distintos procesos que permiten restituir su valor económico;\nXXXIII. Relleno sanitario: La obra de infraestructura que aplica métodos de ingeniería para la disposición final de los residuos sólidos ubicados en sitios adecuados al ordenamiento ecológico, mediante el cual los residuos sólidos se depositan y compactan al menor volumen práctico\n\nposible y se cubren con material natural o sintético para prevenir y minimizar la generación de contaminantes al ambiente y reducir los riesgos a la salud;\nXXXIII Bis.- Residuos de la construcción y demolición: Materiales, productos o subproductos generados durante las actividades de construcción tales como: construcción, modificación, remodelación, ampliación, adecuación, rehabilitación, restauración, reparación, sustitución de infraestructura, conservación, mantenimiento, instalación demolición u otras; así como el producto proveniente de la excavación cuando se haya alterado en sus condiciones físicas, químicas y biológicas originales.\nFracción adicionada y publicada en la GOCDMX el 03 de Abril de 2023\nXXXIV. Residuos urbanos: Los generados en casa habitación, unidad habitacional o similares que resultan de la eliminación de los materiales que utilizan en sus actividades domésticas, de los productos que consumen y de sus envases, embalajes o empaques, los provenientes de cualquier otra actividad que genere residuos sólidos con características domiciliarias y los resultantes de la limpieza de las vías públicas y áreas comunes, siempre que no estén considerados por esta Ley como residuos de manejo especial;\nXXXV. Residuos Orgánicos: Todo residuo sólido biodegradable;\nXXXVI. Residuos Inorgánicos: Todo residuo que no tenga características de residuo orgánico y que pueda ser susceptible a un proceso de valorización para su reutilización y reciclaje, tales como vidrio, papel, cartón, plásticos, laminados de materiales reciclables, aluminio y metales no peligrosos y demás no considerados como de manejo especial;\nXXXVII. Residuos sólidos: El material, producto o subproducto que sin ser considerado como peligroso, se descarte o deseche y que sea susceptible de ser aprovechado o requiera sujetarse a métodos de tratamiento o disposición final;\nXXXVIII. Responsabilidad Compartida: El principio mediante el cual se reconoce que los residuos sólidos urbanos y de manejo especial son generados a partir de la realización de actividades que satisfacen necesidades de la sociedad, mediante cadenas de valor tipo producción, proceso, envasado, distribución, consumo de productos, y que, en consecuencia, su manejo integral es una corresponsabilidad social y requiere la participación conjunta, coordinada y diferenciada de productores, distribuidores, consumidores, usuarios de subproductos, y de los tres órganos de gobierno según corresponda, bajo un esquema de factibilidad de mercado y eficiencia ambiental, tecnológica, económica y social;\n\nXXXIX. Reciclaje: La transformación de los materiales o subproductos contenidos en los residuos sólidos a través de distintos procesos que permiten restituir su valor económico;\nXL. Reutilización: El empleo de un residuo sólido sin que medie un proceso de transformación;\ncon la función que desempeñaba anteriormente o con otros fines;\nXLI. Secretaría: La Secretaría del Medio Ambiente del Distrito Federal;\nXLII. Tratamiento: El procedimiento mecánico, físico, químico, biológico o térmico, mediante el cual se cambian las características de los residuos sólidos, con la posibilidad de reducir su volumen o peligrosidad; y\nFracción reformada y publicada en la GOCDMX el 03 de Abril de 2023\nXLII BIS.- Unidad de inspección: Persona física o moral que realiza actos de verificación debidamente acreditada por alguna Entidad de Acreditación autorizada por la Secretaría de\nEconomía y aprobada por la Secretaría.\nFracción adicionada y publicada en la GOCDMX el 03 de Abril de 2023\nXLIII. Valorización: El principio y conjunto de acciones asociadas cuyo objetivo es recuperar el valor remanente o el contenido energético de los materiales que componen los residuos, mediante su reincorporación en procesos productivos, bajo criterios de eficiencia ambiental, tecnológica y económica.\nTÍTULO SEGUNDO\nDE LA COMPETENCIA\nCAPÍTULO I\nDE LAS FACULTADES\nArtículo 4º.- Son autoridades competentes para la aplicación de la presente Ley, y ejercerán las atribuciones de conformidad con la distribución de facultades que este ordenamiento, su reglamento y demás disposiciones jurídicas aplicables establecen:\nI. La o el Jefe de Gobierno del Distrito Federal;\n\nII. La Secretaría;\nIII. La Secretaría de Obras y Servicios;\nIV. La Secretaría de Salud;\nV. La Procuraduría; y\nVI. Las delegaciones.\nArtículo 5º.- Corresponde a la o el Jefe de Gobierno el ejercicio de las siguientes facultades:\nI. Prestar el servicio público de limpia a través de las entidades, dependencias y órganos que al efecto señale la presente Ley;\nII. Aprobar el Programa de Gestión Integral de los Residuos Sólidos, de conformidad con lo dispuesto en la Ley de Planeación del Desarrollo del Distrito Federal;\nIII. Expedir los ordenamientos que se deriven de la presente ley;\nIV. Celebrar convenios de coordinación en materia de manejo de los residuos sólidos y prestación del servicio público de limpia con la Federación, entidades federativas y municipios;\nV. Proponer el pago de derechos por la prestación del servicio público de limpia correspondiente en las disposiciones del Código Financiero del Distrito Federal; y\nVI. Las demás que en la materia le otorguen esta Ley y otros ordenamientos jurídicos aplicables.\nArtículo 6º.- Corresponde a la Secretaría el ejercicio de las siguientes facultades:\nI. Integrar a la política ambiental las disposiciones complementarias que esta Ley establece en materia de gestión integral de los residuos sólidos, así como su aplicación;\nII. Formular, evaluar y cumplir, en el marco de su competencia, con las disposiciones del\nPrograma de Gestión Integral de los Residuos Sólidos que esta Ley establece;\nIII. Coordinarse con la Secretaría de Obras y Servicios en la aplicación de las disposiciones\n\ncomplementarias para la restauración, prevención y control de la contaminación del suelo generada por el manejo de los residuos sólidos que establecen esta Ley y demás disposiciones jurídicas aplicables;\nIV. Emitir opinión sobre el diseño, construcción, operación y cierre de estaciones de transferencia, plantas de selección y tratamiento, plantas de reciclaje y sitios de disposición final de los residuos sólidos.\nFracción reformada y publicada en la GOCDMX el 03 de Abril de 2023\nV. Integrar un inventario de los residuos sólidos y sus fuentes generadoras, en coordinación con la Secretaría de Obras y Servicios y las delegaciones;\nVI. Integrar a la política de información y difusión en materia ambiental los asuntos derivados de la generación y manejo de los residuos sólidos;\nVII. Promover la investigación, desarrollo y aplicación de tecnologías, equipos, sistemas y procesos que eliminen, reduzcan o minimicen la liberación al ambiente y la transferencia de uno a otro de sus elementos, de contaminantes provenientes del manejo de los residuos sólidos;\nVII Bis.- Fomentar, en coordinación con la Secretaría de Obras y Servicios, la valorización y retorno de los materiales recuperados a los ciclos productivos;\nFracción adicionada y publicada en la GOCDMX el 03 de Abril de 2023\nVII Ter.- Promover la investigación, desarrollo y aplicación de tecnologías, equipos, sistemas informáticos y procesos que permita identificar y establecer la gestión integral de los residuos sólidos urbanos y los de manejo especial;\nFracción adicionada y publicada en la GOCDMX el 03 de Abril de 2023\nVIII. Emitir los criterios, lineamientos, reglas y/o normas ambientales para el Distrito Federal con relación a la operación, recolección, transporte, almacenamiento, reciclaje, tratamiento, industrialización y disposición final de residuos sólidos, así como para establecer las condiciones de seguridad, requisitos y limitaciones en el manejo de los residuos sólidos que presenten riesgo para el ser humano, el equilibrio ecológico y el ambiente;\nVIII Bis. Implementar Sistemas de información, que permita conocer el origen, ruta y destino final de los residuos;\nFracción adicionada y publicada en la GOCDMX el 03 de Abril de 2023\n\nIX. Suscribir convenios o acuerdos con cámaras industriales, comerciales y de otras actividades productivas, con grupos sociales, organizaciones no gubernamentales, así como con dependencias públicas u organismos privados, para llevar a cabo acciones tendientes a cumplir con los objetivos de la presente ley y su reglamento;\nX. Implementar permanentemente, entre la población, programas de difusión y promoción de la cultura de la separación de los residuos, así ́como su reducción, reutilización y reciclaje, en los que participen los sectores industriales y comerciales.\nDichos programas de difusión y promoción deberán incluir, de forma provisional, el manejo de los residuos sólidos o de manejo especial que deriven de un evento, contingencia o emergencia sanitaria.\nXI. Establecer los criterios, lineamientos y normas ambientales para la Ciudad de México referentes a la producción y el consumo sustentable de plásticos, los cuales deberán atender a las características específicas requeridas para cada producto y sujetarse a lineamientos técnicos y científicos, basados en un proceso de análisis de las tecnologías vigentes; éstos deberán emitirse considerando la opinión de los productores y distribuidores.\nDichos criterios, lineamientos y normas ambientales para la Ciudad de México deberán garantizar la disminución de los impactos ambientales asociados a la extracción de materiales, transformación, manufactura, distribución, uso y destino de estos plásticos, promoviendo el uso de materias primas provenientes de productos reciclados post consumo y de recursos naturales renovables, para que una vez terminada la vida útil de estos, sus residuos se incorporen en los procesos productivos para su reciclaje y reutilización, minimizando su disposición final.\nXI BIS. Establecer precios de garantía a cargo de los fabricantes, distribuidores y comercializadores de productos elaborados con plásticos, para promover su reciclaje una vez que se convierten en residuos;\nXII. Promover la investigación y el desarrollo de tecnologías que permitan prevenir, controlar y abatir la contaminación causada por la generación de residuos sólidos, incluyendo el causado por el uso de bolsas de plástico y de productos plásticos de poliestireno expandido; se deberá fomentar la participación de todos los sectores de la sociedad mediante la difusión de información y promoción de actividades de cultura, educación y capacitación ambientales sobre el manejo integral de residuos sólidos;;\n\nXIII. Llevar un registro actualizado de los planes de manejo a los que esta Ley y su reglamento hacen referencia;\nXIV. Inspeccionar y vigilar, en el ámbito de su competencia, el cumplimiento de las disposiciones de la presente Ley, su reglamento y demás aplicables;\nXV. Aplicar las medidas de seguridad e imponer las sanciones que correspondan por violaciones o incumplimiento a este ordenamiento, en el ámbito de su competencia;\nXVI. La atención de los demás asuntos que en materia de los residuos sólidos le conceda esta Ley y otros ordenamientos en concordancia con ella y que no estén expresamente atribuidos a la\nFederación;\nXVII. Promover la certificación de empresas ambientalmente responsables para aquellas que por su convicción, autorregulación, mejora continua en sus procesos productivos, comercialización y venta de servicios, minimicen o reduzcan la generación de residuos. Esta certificación también deberá ser atribuible a los recolectores, acopiadores y comercializadores de residuos, que promuevan un manejo ambientalmente adecuado de los residuos y que no representen riesgos a la población;\nFracción reformada y publicada en la GOCDMX el 21 de Octubre de 2022\nXVIII. Autorizar y registrar a los establecimientos mercantiles y de servicios relacionados con la recolección, manejo, tratamiento, reutilización, reciclaje y disposición final de los residuos sólidos y vigilar su funcionamiento; y\nFracción reformada y publicada en la GOCDMX el 21 de Octubre de 2022\nXIX. Fomentar el aprovechamiento de los residuos sólidos urbanos en procesos de generación de energía limpia, en coordinación con la Secretaría de Obras y Servicios y las alcaldías.\nFracción reformada y publicada en la GOCDMX el 21 de Octubre de 2022\nArtículo 7º.- Corresponde a la Secretaría de Obras y Servicios el ejercicio de las siguientes facultades:\nI. Planear, organizar, normar, controlar y vigilar la prestación del servicio público de limpia en sus etapas de barrido y recolección en vías primarias, transferencia, tratamiento y disposición final de los residuos sólidos;\n\nII. Formular, ejecutar, vigilar y evaluar el Programa para la Prestación de los Servicios de Limpia de su competencia con base en los lineamientos establecidos en el Programa de Gestión Integral de los Residuos Sólidos;\nIII. Planear y ejecutar las obras y prestación del servicio público de limpia en más de una demarcación territorial o cuando se trate de alta especialidad técnica, de conformidad con las disposiciones jurídicas aplicables;\nIV. Establecer los criterios y normas técnicas para la construcción, conservación y mantenimiento de la infraestructura y equipamiento para el manejo, tratamiento y disposición final de los residuos sólidos;\nV. (Derogada);\nVI. Llevar a cabo los estudios que sustenten la necesidad de otorgar concesiones para la prestación del servicio público de limpia y, en los casos viables otorgar la concesión correspondiente con base en las disposiciones jurídicas aplicables;\nVII. Realizar los estudios y proyectos de obras de infraestructura para el manejo integral de los residuos sólidos de su competencia;\nVIII. Diseñar, construir, organizar, operar y mantener las estaciones de transferencia, plantas de selección y tratamiento, y sitios para la disposición final de los residuos sólidos, con base en el\nPrograma de Gestión Integral de los Residuos Sólidos;\nVIII Bis. Recuperar, clasificar, especificar y utilizar materiales reciclados de la construcción y demolición en la ejecución de obras de su competencia.\nFracción adicionada y publicada en la GOCDMX el 03 de Abril de 2023\nIX. Participar en la celebración de convenios para el traslado de los residuos sólidos desde o hacia otras entidades federativas, así como la inspección y vigilancia de dicho traslado;\nX. Restaurar y recuperar el suelo contaminado por las actividades del manejo integral de los residuos sólidos y prestación del servicio público de limpia de su competencia, en concordancia con las disposiciones complementarias o lineamientos técnicos, establecidos por la Secretaría;\nXI. Inspeccionar y vigilar, en el ámbito de su competencia, el cumplimiento de las disposiciones\n\nde la presente Ley, su Reglamento y demás aplicables;\nXII. Aplicar las medidas de seguridad e imponer las sanciones que correspondan por violaciones o incumplimiento a este ordenamiento, en el ámbito de su competencia;\nXIII. Atender los asuntos en materia de los residuos sólidos que se generen entre el Distrito\nFederal y una o más entidades federativas, en coordinación con las autoridades competentes; y\nXIV. Atender los demás asuntos que en materia de los residuos sólidos le concedan esta Ley y otros ordenamientos jurídicos aplicables y que no estén expresamente atribuidos a la Federación o a otras dependencias o entidades de la administración pública del Distrito Federal.\nArtículo 8º.- Corresponde a la Secretaría de Salud del Distrito Federal, en el ámbito de su competencia, emitir recomendaciones y, en coordinación con la Secretaría y la Secretaría de Obras y Servicios, determinar la aplicación de las medidas de seguridad, dirigidas a evitar riesgos y daños a la salud de la población, derivados del manejo integral, almacenamiento, tratamiento y disposición final de los residuos sólidos.\nArtículo 9º.- Corresponde a la Procuraduría la atención de las denuncias ciudadanas que cualquier persona le presente por violaciones o incumplimiento a las disposiciones de la presente Ley, dándole curso legal en los términos de su Ley Orgánica.\nArtículo 10.- Corresponde a las Delegaciones el ejercicio de las siguientes facultades:\nI. Formular, ejecutar, vigilar y evaluar el programa delegacional de prestación del servicio público de limpia de su competencia, con base en los lineamientos establecidos en el Programa de\nGestión Integral de los Residuos Sólidos;\nII. Prestar el servicio público de limpia en sus etapas de barrido de las áreas comunes y vialidades secundarias, la recolección de los residuos sólidos, su transporte a las estaciones de transferencia, plantas de tratamiento y selección o a sitios de disposición final, de conformidad con las normas ambientales en la materia y los lineamientos que al efecto establezca la Secretaría de Obras y Servicios;\nIII. Erradicar la existencia de tiraderos clandestinos de los residuos sólidos;\nIV. Orientar a la población sobre las prácticas de reducción, reutilización y reciclaje, separación en la fuente y aprovechamiento y valorización de los residuos sólidos;\n\nV. Promover programas de capacitación a los servidores públicos, así como de fomento y orientación a la población sobre la gestión integral de los residuos sólidos;\nVI. Instalar el equipamiento para el depósito separado y selectivo de los residuos sólidos en áreas públicas, áreas comunes y espacios públicos, así como en lugares donde técnicamente se determine viable o necesario la instalación de los mismos y garantizar periódicamente su buen estado y funcionamiento;\nVII. Organizar administrativamente el servicio público de limpia de su competencia, el nombramiento del personal necesario y proporcionar los elementos, equipos, útiles y, en general, todo el material indispensable para la prestación de dicho servicio;\nVIII. Establecer las rutas, horarios y frecuencias en que debe prestarse el servicio de recolección selectiva de los residuos sólidos de su competencia pudiendo, una vez escuchados los vecinos, modificarlos de acuerdo a las necesidades de dicho servicio;\nIX. Atender oportunamente las quejas del público sobre la prestación del servicio público de limpia de su competencia y dictar las medidas necesarias para su mejor y pronta solución;\nX. Solicitar autorización de la Secretaría de Obras y Servicios para el otorgamiento de las declaraciones de apertura, licencias y autorizaciones de funcionamiento de los establecimientos mercantiles y de servicios relacionados con el manejo, tratamiento, reutilización, reciclaje y disposición final de los residuos sólidos, definidos en el reglamento de la presente Ley;\nXI. Solicitar a la Secretaría de Obras y Servicios la realización de estudios con relación a las propuestas que éstas le envíen para otorgar concesiones para la prestación del servicio público de limpia de competencia de la delegación y, en su caso, aprobar dichas concesiones;\nXII. Participar, bajo la coordinación de la Secretaría de Obras y Servicios, en la atención de los asuntos de los efectos que genere la realización de los servicios de limpia que se realicen en la delegación y que afecten o puedan afectar a otra delegación o municipio;\nXIII. Inspeccionar y vigilar, en el ámbito de su competencia, el cumplimiento de las disposiciones de la presente Ley, su reglamento y demás aplicables;\nXIV. Aplicar las medidas de seguridad e imponer las sanciones que correspondan por violaciones\n\no incumplimiento a este ordenamiento, en el ámbito de su competencia;\nXV. Integrar a la política delegacional de información y difusión en materia ambiental los asuntos relacionados con la realización del servicio público de limpia de su competencia; y\nXVI. Atender los demás asuntos que en materia de los residuos sólidos le conceda esta Ley y otros ordenamientos jurídicos aplicables.\nCAPÍTULO I BIS\nDE LA COMISIÓN PARA LA GESTIÓN INTEGRAL DE RESIDUOS SÓLIDOS\nDE LA CIUDAD DE MÉXICO\nArtículo 10 Bis. El Jefe de Gobierno creará la Comisión para la Gestión Integral de Residuos Sólidos de la\nCiudad de México, como órgano interinstitucional de coordinación, monitoreo, seguimiento y evaluación de las políticas, acciones y programas instrumentados por la Administración Pública del Distrito Federal en materia de generación, encierro, acopio, transferencia, selección, tratamiento, manejo, aprovechamiento, valorización y disposición final de residuos.\nArtículo 10 Bis 1. La Comisión será presidida por el Jefe de Gobierno y estará integrada por los titulares de:\nI. La Secretaría del Medio Ambiente;\nII. La Secretaría de Obras y Servicios;\nIII. La Secretaría de Salud;\nIV. La Secretaría de Finanzas;\nV. La Secretaría de Ciencia, Tecnología e Innovación del Distrito Federal;\nVI. La Procuraduría Ambiental y del Ordenamiento Territorial;\nVII. El Jefe de Gobierno del Distrito Federal podrá invitar a dos integrantes de la Comisión de\nPreservación del Medio Ambiente, Protección Ecológica y Cambio Climático de la Asamblea\nLegislativa del Distrito Federal, quienes participarán únicamente con derecho a voz.\n\nLos integrantes de la Comisión, deberán designar a un representante con cargo mínimo en la\nAdministración Pública del Distrito Federal de Director General o su homólogo, quien participará en sus sesiones de manera permanente, con derecho de voz y voto.\nCuando a juicio de la Comisión resulte conveniente contar con la opinión o asesoría de las dependencias y entidades federales, estatales o municipales, así como de especialistas, instituciones educativas y de investigación, organizaciones sociales e internacionales, este órgano colegiado podrá invitarlas a participar en sus sesiones y actividades de forma permanente o temporal, únicamente con derecho de voz.\nEn ausencia del Jefe de Gobierno del Distrito Federal fungirá como Presidente quien determine. Los representantes de los titulares de las Dependencias y Entidades serán el enlace entre éstas y la Comisión, a efecto de lograr una mayor eficiencia y eficacia en el cumplimiento de los acuerdos asumidos.\nArtículo 10 Bis 2. Corresponde a la Comisión para la Gestión Integral de los Residuos Sólidos de la Ciudad de México entre otras el ejercicio de las siguientes facultades:\nI. Proponer y, en su caso, definir los mecanismos y criterios de coordinación y transversalidad de los programas y acciones de la administración pública del Distrito Federal que se vinculen con la generación, manejo, tratamiento, minimización, aprovechamiento y disposición final de residuos, así como revisar y dar seguimiento al cumplimiento de los objetivos y metas establecidos en ellos;\nII. Proponer a las instancias federales y estatales la adopción de estrategias y políticas metropolitanas enfocadas a atender de manera integral el tema de los residuos;\nIII. Presentar al Jefe de Gobierno los resultados de las investigaciones, estudios y diagnósticos elaborados por los integrantes o invitados de la Comisión, cuyo objeto consista en mejorar el diseño, planeación y generación de proyectos, programas y acciones gubernamentales en materia de generación, manejo, tratamiento, aprovechamiento y disposición final de residuos;\nIV. Proponer a las dependencias y entidades de la administración pública del Distrito Federal, la suscripción de convenios, contratos o cualquier instrumento jurídico con los sectores público, privado y social, que contribuyan a la solución de los problemas creados por los residuos sólidos, desde su generación hasta su disposición final;\n\nV. Proponer y, en su caso, presentar a las autoridades competentes los proyectos de modificaciones legislativas, reglamentarias y administrativas que actualicen y hagan más eficiente el marco normativo aplicable en materia de generación, encierro, acopio, transferencia, selección, tratamiento, manejo, aprovechamiento, valorización y disposición final de residuos.\nVI. Fomentar la participación de los sectores público, privado y social en la instrumentación de los programas, proyectos y acciones gubernamentales en materia de generación, encierro, acopio, transferencia, selección, tratamiento, manejo, aprovechamiento, valorización y disposición final de residuos.\nVII. Diseñar estrategias financieras que generen recursos al Gobierno del Distrito Federal, a través de los mecanismos económicos previstos en los instrumentos nacionales e internacionales y, en su caso, proponer su ejecución a las autoridades competentes;\nVIII. Informar periódicamente al Jefe de Gobierno del Distrito Federal y a la Asamblea Legislativa del Distrito Federal, los avances de los programas, acciones y resultados de la Comisión;\nIX. Aprobar la creación, modificación o cancelación de las subcomisiones que considere necesarias para el mejor cumplimiento de sus atribuciones;\nX. Conocer, revisar y, en su caso, dar seguimiento a las acciones y programas de gestión integral de los residuos que diseñen o ejecuten las dependencias y entidades de la administración pública del Distrito Federal;\nXI. Acordar la planeación y ejecución de programas o proyectos que por su grado de especificidad técnica requieran ser atendidos por la Comisión y sus integrantes;\nXII. Fomentar la participación ciudadana mediante campañas educativas, informativas y de manejo responsable de los residuos sólidos;\nXIII. Aprobar su Reglamento Interno; y\nXIV. Las demás que el Jefe de Gobierno le asigne.\nArtículo 10 Bis 3. La Comisión se reunirá en sesiones ordinarias bimestrales y en sesiones extraordinarias cuando las circunstancias así lo ameriten. La convocatoria de la sesión respectiva deberá ser notificada a los\n\nmiembros de la Comisión por su Presidente o Secretario Técnico, a más tardar cinco días hábiles antes de la celebración de la misma.\nCAPÍTULO II\nDE LAS DISPOSICIONES COMPLEMENTARIAS DE LA POLÍTICA\nAMBIENTAL\nArtículo 11.- La Secretaría, en coordinación con la Secretaría de Obras y Servicios y con opinión de las delegaciones, formulará y evaluará el Programa de Gestión Integral de los Residuos Sólidos, mismo que integrará los lineamientos, acciones y metas en materia de manejo integral de los residuos sólidos y la prestación del servicio público de limpia con base en los siguientes criterios:\nI. Adoptar medidas para la reducción de la generación de los residuos sólidos, su reutilización y reciclaje, su separación en la fuente de origen, su recolección y transporte separados, así como su adecuado aprovechamiento, tratamiento y disposición final;\nII. Promover la reducción de la cantidad de los residuos sólidos que llegan a disposición final;\nIII. Adoptar medidas preventivas, considerando los costos y beneficios de la acción u omisión, cuando exista evidencia científica que compruebe que la liberación al ambiente de residuos sólidos pueden causar daños a la salud o al ambiente;\nIV. Prevenir la liberación de los residuos sólidos que puedan causar daños al ambiente o a la salud humana y la transferencia de contaminantes de un medio a otro;\nV. Prever la infraestructura necesaria para asegurar que los residuos sólidos se manejen de manera ambientalmente adecuada;\nVI. Promover la cultura, educación y capacitación ambientales, así como la participación del sector social, privado y laboral, para el manejo integral, la reutilización y el reciclaje de los residuos sólidos;\nVII. Fomentar la responsabilidad compartida entre productores, distribuidores y consumidores en la reducción de la generación de los residuos sólidos y asumir el costo de su manejo integral;\nVIII. Fomentar la participación activa de las personas, la sociedad civil organizada y el sector\n\nprivado en el manejo integral de los residuos sólidos;\nIX. Armonizar las políticas de ordenamiento territorial y ecológico con el manejo integral de los residuos sólidos, identificando áreas apropiadas para la ubicación de infraestructura;\nX. Fomentar la generación, sistematización y difusión de información del manejo integral de los residuos sólidos para la toma de decisiones;\nXI. Definir las estrategias sectoriales e intersectoriales para la minimización y prevención de la generación y el manejo integral de los residuos sólidos, conjugando las variables económicas, sociales, culturales, tecnológicas, sanitarias y ambientales en el marco de la sustentabilidad;\nXII. Promover medidas para evitar el depósito, descarga, acopio y selección de los residuos sólidos en áreas o en condiciones no autorizadas;\nXIII. Promover sistemas de reutilización y reciclaje, depósito retorno u otros similares que reduzcan la generación de residuos, en el caso de productos o envases que después de ser utilizados generen residuos en alto volumen o que originen impactos ambientales significativos;\nXIII BIS. Establecer las medidas adecuadas entre los diversos sectores productivos, a fin de que se realice previo a su disposición final, la destrucción o la inutilización de los envases que contuvieron sustancias nocivas para la salud, una vez que estos han terminado su vida útil, evitando su posterior uso para almacenar o transportar productos de consumo humano;\nXIV. Establecer las medidas adecuadas para reincorporar al ciclo productivo materiales o sustancias reutilizables o reciclables y para el desarrollo de mercados de subproductos para la valorización de los residuos sólidos;\nXV. Fomentar el desarrollo y uso de tecnologías sustentables o amigables con el medio ambiente, así como métodos, prácticas, procesos de producción, comercialización, reutilización y reciclaje que favorezcan la minimización y valorización de los residuos sólidos.\nXVI. Establecer acciones orientadas a recuperar los sitios contaminados por el inadecuado manejo de los residuos sólidos;\nXVII. Establecer las condiciones que deberán cumplirse para el cierre de estaciones de transferencia, plantas de selección y tratamiento y rellenos sanitarios, de manera que no existan\n\nsuelos contaminados por el manejo de los residuos sólidos y medidas para monitorear dichos sitios, ulterior al cierre, con plazos no menores a diez años posteriores a su cierre;\nXVIII. Evitar el manejo y disposición de residuos de manejo especial líquidos o semisólidos, sin que hayan sido sometidos a procesos para deshidratarlos, neutralizarlos y estabilizarlos;\nXVIII. BIS Fomentar que la producción y el consumo de productos plásticos y poliestireno expandido se sujeten a los criterios y normas de sustentabilidad establecidos en la fracción XI del artículo 6º de la presente ley;\nXIX. Evitar la disposición final de los residuos sólidos que sean incompatibles y puedan provocar reacciones que liberen gases, provoquen incendios o explosiones o que pueden solubilizar las sustancias potencialmente tóxicas contenidas en ellos;\nFracción reformada y publicada en la GOCDMX el 21 de Octubre de 2022\nXIX BIS. El aprovechamiento de los residuos sólidos urbanos en procesos de generación de energía limpia; y\nFracción reformada y publicada en la GOCDMX el 21 de Octubre de 2022\nXX. Los demás que establezca el Reglamento y otros ordenamientos aplicables.\nFracción reformada y publicada en la GOCDMX el 21 de Octubre de 2022\nLa Secretaría, la Secretaría de Obras y Servicios y las Alcaldías ejecutarán, en el marco de su competencia, los contenidos del Programa de Gestión Integral de los Residuos Sólidos.\nPárrafo reformado y publicado en la GOCDMX el 21 de Octubre de 2022\nLos programas de carácter metropolitano que acuerde el Gobierno de la Ciudad de México consideraran las disposiciones que esta Ley establece para la gestión integral de los residuos sólidos.\nPárrafo reformado y publicado en la GOCDMX el 21 de Octubre de 2022\nArtículo 11 BIS.- Derogado.\nArtículo 12.- La Secretaría de Obras y Servicios y las delegaciones formularán, ejecutarán y evaluarán los programas correspondientes a la prestación de los servicios de limpia de sus respectivas competencias con base en el Programa de Gestión Integral de los Residuos Sólidos, así como en las disposiciones que establecen esta Ley, su reglamento y demás disposiciones jurídicas aplicables.\n\nEn la elaboración de los programas a los que se refiere el presente Capítulo, las autoridades competentes promoverán la participación de la sociedad.\nArtículo 13.- La Secretaría de Obras y Servicios, al elaborar el programa de prestación del servicio público de limpia de su competencia, deberá considerar las disposiciones contendidas en esta Ley, su reglamento, las normas oficiales mexicanas, las normas ambientales para el Distrito Federal, el Programa de Gestión\nIntegral de los Residuos Sólidos, los criterios y normas técnicas para la prestación del servicio público de limpia, y otros ordenamientos jurídicos aplicables.\nArtículo 14.- La Secretaría de Obras y Servicios, en coordinación con la Secretaría y las Secretarías de\nDesarrollo Económico y de Finanzas, promoverá incentivos económicos para aquellas personas que desarrollen acciones de prevención, minimización, valorización, reutilización y reciclaje, así como para la inversión en tecnología y utilización de prácticas, métodos o procesos que coadyuven a mejorar el manejo integral de los residuos sólidos.\nArtículo 15.- En aquellos casos en que sea técnica y económicamente factible, la o el Jefe de Gobierno del\nDistrito Federal, a través de las autoridades competentes, promoverá la creación de mercados de subproductos que establezcan mecanismos que involucren la participación de los productores, distribuidores, comercializadores y consumidores en la valorización de los materiales y productos que se conviertan en residuos sólidos.\nArtículo 15 Bis. La Secretaría promoverá e implementará la formación y operación de sistemas y mecanismos de intercambio de residuos sólidos generados por los habitantes del Distrito Federal, por productos agrícolas que provean los productores autorizados por aquélla.\nAsimismo, la Secretaría, en coordinación con la Secretaría de Obras y Servicios, la Secretaría de Desarrollo\nEconómico y las Delegaciones, determinará los criterios y medios necesarios para que dichos mecanismos conlleven a un mayor aprovechamiento de los residuos sólidos, favorezcan la economía de la población participante y garanticen el consumo sustentable en la Ciudad.\nAunado a lo anterior, la Secretaría deberá crear, actualizar y difundir el catálogo de bienes que podrán ser motivo de cambio por los residuos sólidos que la población entregue en los sitios que se definan para tal efecto.\nArtículo 16.- Los programas de educación formal y no formal que desarrollen o fomenten los centros o instituciones educativas de competencia del Distrito Federal, así como las asociaciones o instituciones\n\nlegalmente constituidas, establecerán mecanismos orientados a fomentar una cultura de manejo integral de los residuos sólidos que promuevan, además, la separación seleccionada de dichos residuos y su valorización.\nArtículo 17.- Los programas de difusión en materia ambiental de la Secretaría y de las delegaciones incluirán campañas periódicas para fomentar la reducción de la cantidad y peligrosidad, la separación obligatoria y la valorización de los residuos sólidos.\nArtículo 18.- La Secretaría, la Secretaría de Obras y Servicios y las delegaciones, en el ámbito de sus respectivas competencias, promoverán la participación de todos los sectores de la sociedad mediante:\nI. Su participación en el fomento y apoyo en la conformación, consolidación y operación de grupos intersectoriales para el diseño e instrumentación de los programas en materia de los residuos sólidos;\nII. La difusión de información y promoción de actividades de cultura, educación y capacitación ambientales relacionados con el manejo integral de los residuos sólidos;\nIII. La promoción de proyectos pilotos y de demostración destinados a generar elementos de información para sustentar programas en materia de los residuos sólidos; y\nIV. La promoción de las demás acciones que determine el reglamento de la presente Ley.\nArtículo 19.- Las autoridades establecidas en el artículo 4º de la presente Ley sistematizarán y pondrán a disposición del público la información obtenida en el ejercicio de sus funciones vinculadas a la generación y manejo integral de los residuos sólidos, y la prestación de los servicios de limpia a su cargo, mediante los mecanismos establecidos en el capítulo correspondiente de la Ley Ambiental, sin perjuicio de la debida reserva de aquella información protegida por las leyes.\nArtículo 20.- La Secretaría solicitará periódicamente a la autoridad federal toda la información que considere necesaria sobre el manejo y transporte de residuos peligrosos en el territorio del Distrito Federal.\nDicha información la incluirá en el Sistema de Información Ambiental.\nTÍTULO TERCERO\nDE LA PREVENCIÓN Y MINIMIZACIÓN DE LA GENERACIÓN DE LOS\nRESIDUOS SÓLIDOS\n\nCAPÍTULO I\nDE LAS DISPOSICIONES GENERALES\nArtículo 21. Toda persona que genere residuos sólidos tiene la propiedad y responsabilidad del manejo integral de estos, así como de los perjuicios y daños que puedan ocasionar, hasta el momento en que son entregados al servicio de recolección, o depositados en los contenedores o sitios autorizados para tal efecto por la autoridad competente.\nArtículo 22.- Para la prevención de la generación, valorización y manejo de los residuos sólidos, se incluirá en el reglamento las disposiciones para formular planes de manejo, guías y lineamientos para generadores de alto volumen de los residuos sólidos.\nArtículo 23. Las personas físicas o morales responsables de la producción, recolección, manejo, tratamiento, reciclaje, reutilización, distribución o comercialización de bienes que, una vez terminada su vida útil, originen residuos sólidos en alto volumen, de manejo especial o que produzcan desequilibrios significativos al medio ambiente, cumplirán, además de las obligaciones que se establezcan en el\nReglamento, con las siguientes disposiciones:\nI. Instrumentar planes de manejo de los residuos sólidos en sus procesos de producción, prestación de servicios o en la utilización de envases y embalajes, así como su fabricación o diseño, comercialización o utilización que contribuyan a la minimización de los residuos sólidos y promuevan la reducción de la generación en la fuente, su valorización o disposición final, que ocasionen el menor impacto ambiental posible;\nII. Adoptar sistemas eficientes de recuperación o retorno de los residuos sólidos derivados de la comercialización de sus productos finales;\nIII. Privilegiar el uso de envases y embalajes para que una vez utilizados sean susceptibles de valorización mediante procesos de reutilización y reciclaje.\nEl Reglamento determinará los bienes a los que se refiere este artículo; y\nIV. Cumplir con lo establecido las normas ambientales emitidas por la Secretaría.\nArtículo 24.- Es responsabilidad de toda persona, física o moral, en el Distrito Federal:\n\nI. Separar, reducir y evitar la generación de los residuos sólidos;\nII. Barrer diariamente las banquetas, andadores y pasillos y mantener limpios de residuos sólidos los frentes de sus viviendas o establecimientos industriales o mercantiles, así como los terrenos de su propiedad que no tengan construcción, a efecto de evitar contaminación y molestias a los vecinos;\nIII. Fomentar la reutilización y reciclaje de los residuos sólidos;\nIII. Bis. Entregar sus residuos de la construcción y de la demolición a un prestador de servicio de manejo de transporte.\nFracción adicionada y publicada en la GOCDMX el 03 de Abril de 2023\nIV. Cumplir con las disposiciones específicas, criterios, normas y recomendaciones técnicas;\nV. Almacenar los residuos sólidos con sujeción a las normas sanitarias y ambientales para evitar daño a terceros y facilitar la recolección;\nVI. Poner en conocimiento de las autoridades competentes las infracciones que se estimen se hubieran cometido contra la normatividad de los residuos sólidos;\nVI Bis. Informar de los tipos y cantidades de residuos sólidos generados en los formatos que la autoridad determine;\nVI Ter. Disponer de información probatoria e informar a la autoridad competente sobre el manejo adecuado de sus residuos en los casos que la recolección de estos sea realizada por un establecimiento mercantil privado relacionado con la recolección, manejo, tratamiento reutilización, reciclaje y disposición final de los residuos sólidos; y\nVII. Las demás que establezcan los ordenamientos jurídicos aplicables.\nArtículo 25.- Queda prohibido por cualquier motivo:\nI. Arrojar o abandonar en la vía pública, áreas comunes, parques, barrancas, y en general en sitios no autorizados, residuos sólidos de cualquier especie;\nII. Depositar animales muertos, residuos sólidos que despidan olores desagradables o aquellos\n\nprovenientes de la construcción en los contenedores instalados en la vía pública para el arrojo temporal de residuos sólidos de los transeúntes;\nIII. Quemar a cielo abierto o en lugares no autorizados, cualquier tipo de los residuos sólidos;\nIV. Arrojar o abandonar en lotes baldíos, a cielo abierto o en cuerpos de aguas superficiales o subterráneas, sistemas de drenaje, alcantarillado o en fuentes públicas, residuos sólidos de cualquier especie;\nV. Pepenar residuos sólidos de los recipientes instalados en la vía pública y dentro de los sitios de disposición final y sus alrededores;\nVI. Instalar contenedores de los residuos sólidos en lugares no autorizados;\nVII. Fijar propaganda comercial o política en el equipamiento urbano destinado a la recolección de los residuos sólidos, así como fijar en los recipientes u otro mobiliario urbano destinado al depósito y recolección colores alusivos a algún partido político;\nVIII. Fomentar o crear basureros clandestinos;\nIX. Confinar residuos sólidos fuera de los sitios destinados para dicho fin en parques, áreas verdes, áreas de valor ambiental, áreas naturales protegidas, zonas rurales o áreas de conservación ecológica;\nX. Tratar térmicamente los residuos sólidos recolectados, sin considerar las disposiciones jurídicas aplicables;\nXI. Diluir o mezclar residuos sólidos o industriales peligrosos en cualquier líquido y su vertimiento al sistema de alcantarillado, a cualquier cuerpo de agua o sobre suelos con o sin cubierta vegetal;\nXI. BIS. La comercialización, distribución y entrega de bolsas de plástico al consumidor, en los puntos de venta de bienes o productos, excepto si son compostables. Se excluyen, las bolsas de plástico necesarias por razones de higiene o que prevengan el desperdicio de alimentos siempre y cuando no existan alternativas compostables.\nLa comercialización, distribución y entrega de tenedores, cuchillos, cucharas, palitos\n\nmezcladores, platos, popotes o pajitas, bastoncillos para hisopos de algodón, globos y varillas para globos, vasos y sus tapas, charolas para transportar alimentos, aplicadores de tampones, fabricados total o parcialmente de plásticos, diseñados para su desecho después de un solo uso, excepto los que sean compostables.\nQueda excluida la comercialización, distribución y entrega de popotes para asistencia médica.\nLa comercialización, distribución y entrega de productos que contengan microplásticos añadidos intencionalmente.\nLa comercialización, distribución y entrega de cápsulas de café de un solo uso fabricadas con materiales plásticos de bajo potencial de aprovechamiento.\nXII. Mezclar residuos peligrosos con residuos sólidos e industriales no peligrosos; y\nXIII. Confinar o depositar en sitios de disposición final residuos en estado líquido o con contenidos líquidos que excedan los máximos permitidos por las normas oficiales mexicanas o las normas ambientales del Distrito Federal.\nXIV. Utilizar envases que hayan contenido sustancias tóxicas con fines distintos para los que fueron creados, como almacenar o trasportar productos para consumo humano.\nLas violaciones a lo establecido en este artículo se sancionarán de conformidad con lo dispuesto en esta\nLey, sin perjuicio de lo establecido en la Ley de Justicia Cívica del Distrito Federal y demás ordenamientos jurídicos aplicables.\nArtículo 26.- Los propietarios, directores responsables de obra, contratistas y encargados de inmuebles en construcción o demolición, son responsables solidarios en caso de provocarse la diseminación de materiales, escombros y cualquier otra clase de residuos sólidos, así como su mezcla con otros residuos ya sean de tipo orgánico o peligrosos.\nEl frente de las construcciones o inmuebles en demolición deberán mantenerse en completa limpieza, quedando prohibido almacenar escombros y materiales en la vía pública.\nLos responsables deberán transportar los escombros en vehículos adecuados que eviten su dispersión durante el transporte a los sitios que determine la Secretaría de Obras y Servicios.\n\nLas personas físicas o morales que se señalan en el artículo anterior, deben contar con un convenio o contrato vigente con una planta de reciclaje de residuos de la construcción y demolición que garantice el reciclaje de los residuos a generar en sus procesos productivos y deberá presentarlo ante la Secretaría y la\nAlcaldía correspondiente, para la obtención de los permisos de construcción o demolición pertinentes.\nPárrafo adicionada y publicada en la GOCDMX el 03 de Abril de 2023\nLos residuos generados en obras de construcción, tales como: construcción, modificación, remodelación, amplificación, restauración, reparación, sustitución de infraestructura, conservación, mantenimiento, instalación, demolición u otras deberán separarse en la fuente generadora y ser objeto de una Plan de\nManejo, conforme a lo establecido en el marco jurídico aplicable.\nPárrafo adicionada y publicada en la GOCDMX el 03 de Abril de 2023\nArtículo 26 BIS.- Las bolsas de plástico que se entreguen a título gratuito, de manera onerosa o con motivo de cualquier acto comercial, para transportación, carga o traslado del consumidor final, deberán cumplir con los criterios y normas de producción y consumo sustentable señalados en la fracción XI del artículo 6º de la presente ley.\nProductores, distribuidores, y usuarios de las bolsas a las que se refiere este artículo, deberán propiciar las acciones relativas a la maximización en la valorización o reciclaje mediante la participación en los programas que para tal efecto establezca la Secretaría.\nArtículo 26 BIS1.- Derogado.\nArtículo 26 Ter.- La Secretaría, implementará Sistemas de información que permitan conocer el origen, ruta y destino final de los residuos de la construcción y demolición\nArtículo adicionado y publicado en la GOCDMX el 03 de Abril de 2023\nCAPÍTULO II\nDEL INVENTARIO DE LOS RESIDUOS SÓLIDOS Y SUS FUENTES\nGENERADORAS\nArtículo 27.- La Secretaría elaborará y mantendrá actualizado, en los términos del reglamento, un inventario que contenga la clasificación de los residuos sólidos y sus tipos de fuentes generadoras, con la finalidad de:\nI. Orientar la toma de decisiones tendientes a la prevención, control y minimización de dicha\n\ngeneración;\nII. Proporcionar a quien genere, recolecte, trate o disponga finalmente los residuos sólidos, indicadores acerca de su estado físico y propiedades o características inherentes que permitan anticipar su comportamiento en el ambiente;\nIII. Dar a conocer la relación existente entre las características físicas, químicas o biológicas inherentes a los residuos sólidos, y la probabilidad de que ocasionen o puedan ocasionar efectos adversos a la salud humana, al ambiente o a los bienes en función de sus volúmenes, sus formas de manejo y la exposición que de éste se derive; y\nIV. Identificar las fuentes generadoras, los diferentes tipos de los residuos sólidos, los distintos materiales que los constituyen y los aspectos relacionados con su valorización.\nArtículo 28.- Para los efectos del artículo anterior, la categorización de los residuos sólidos que deberá contener dicho inventario podrá considerar las características físicas, químicas o biológicas que los hacen:\nI. Inertes;\nII. Fermentables;\nIII. De alto valor calorífico y capaces de combustión;\nIV. Volátiles;\nV. Solubles en distintos medios;\nVI. Capaces de salinizar suelos;\nVII. Capaces de provocar incrementos excesivos de la carga orgánica en cuerpos de agua y el crecimiento excesivo de especies acuáticas que ponga en riesgo la supervivencia de otras;\nVIII. Persistentes; y\nIX. Bioacumulables.\n\nCAPÍTULO III\nDE LA CLASIFICACIÓN DE LOS RESIDUOS SÓLIDOS\nArtículo 29.- Para los efectos de esta Ley, los residuos sólidos se clasifican en:\nI. Residuos urbanos; y\nII. Residuos de manejo especial considerados como no peligrosos y sean competencia del Distrito\nFederal.\nArtículo 30.- Son residuos urbanos los que se refiere la fracción XXXI del artículo 3º de la presente Ley, así como los residuos provenientes de las actividades de limpieza y cuidado de áreas verdes a las que se refiere la Ley Ambiental.\nArtículo 31.- Son residuos de manejo especial, siempre y cuando no estén considerados como peligrosos de conformidad con las disposiciones federales aplicables, y sean competencia del Distrito Federal, los siguientes:\nI. Los provenientes de servicios de salud, generados por establecimientos que realicen actividades médico-asistenciales a las poblaciones humanas o animales, centros de investigación, desarrollo o experimentación en el área de farmacología y salud;\nII. Los cosméticos y alimentos no aptos para el consumo generados por establecimientos comerciales, de servicios o industriales;\nIII. Los generados por las actividades agrícolas, forestales y pecuarias, incluyendo los residuos de insumos utilizados en esas actividades;\nIV. Los de servicios de transporte, generados como consecuencia de las actividades que se realizan en terminales de transporte;\nV. Los residuos de la demolición, mantenimiento y construcción civil en general;\nVI. Los residuos tecnológicos provenientes de las industrias de informática, fabricantes de productos electrónicos o de vehículos automotores y otros que al transcurrir su vida útil y que, por sus características, requieran de un manejo específico;\n\nVII. Los lodos deshidratados;\nVIII. Los neumáticos usados, muebles, enseres domésticos usados en gran volumen, plásticos y otros materiales de lenta degradación;\nIX. Los de laboratorios industriales, químicos, biológicos, de producción o de investigación;\nX. Los demás que determine el Reglamento.\nArtículo 32.- Los residuos de manejo especial estarán sujetos a los planes de manejo conforme a las disposiciones que establezca esta Ley, su reglamento y los ordenamientos jurídicos de carácter local y federal que al efecto se expidan para su manejo, tratamiento y disposición final.\nLos generadores de residuos de manejo especial deberán instrumentar planes de manejo, mismos que deberán ser autorizados por la Secretaría y contemplar programas de postconsumo para aquellos residuos cuya naturaleza así lo permita.\nLos planes de manejo a que hace referencia el párrafo anterior deberán instrumentarse e implementarse de acuerdo a la normatividad aplicable, con acciones concretas que permitan el correcto tratamiento de los residuos de manejo especial que se generen.\nLa Secretaría promoverá la participación de la ciudadanía, a través de campañas de difusión, para prevenir la generación de residuos de manejo especial, así como para la prevención de la contaminación por este tipo de residuos.\nArtículo 32 Bis.- En la ejecución de obra pública que realice la administración pública de la Ciudad de\nMéxico, así como en la privada se deberán utilizar materiales reciclados, productos del reciclaje de los residuos de construcción y demolición de conformidad con la normativa aplicables.\nAsimismo, deberán recolectar y transportar los residuos de la construcción y demolición autorizadas por la\nSecretaría, debiendo cumplir con las disposiciones que establecen las normas ambientales de la Ciudad de México en esta materia.\nArtículo adicionado y publicado en la GOCDMX el 03 de Abril de 2023\nCAPÍTULO IV\n\nDE LA SEPARACIÓN DE LOS RESIDUOS SÓLIDOS\nArtículo 33. Todo generador de residuos sólidos debe separarlos en orgánicos e inorgánicos, dentro de sus domicilios, empresas, establecimientos mercantiles, industriales y de servicios, instituciones públicas y privadas, centros educativos y dependencias gubernamentales y similares, para ello deberán separar sus residuos sólidos de manera diferenciada y selectiva, de acuerdo a la subclasificación de residuos que establece el reglamento de la presente Ley.\nEstos residuos sólidos, deben depositarse en contenedores separados para su recolección por el servicio público de limpia, con el fin de facilitar su aprovechamiento, tratamiento y disposición final, o bien, llevar aquellos residuos sólidos valorizables directamente a los establecimientos de reutilización y reciclaje.\nEl Reglamento definirá la subclasificación que deberá aplicar para la separación obligatoria de residuos sólidos, con base a las disposiciones del presente artículo para cada una de las clasificaciones establecidas, así como para los distintos tipos de generadores.\nArtículo 33 Bis. La Secretaría y las Alcaldías deberán aplicar el método de separación de residuos en orgánicos e inorgánicos y de manera selectiva para el servicio de recolección, la cual será diferenciada conforme a los criterios señalados por las autoridades.\nLa Administración Pública de la Ciudad de México establecerá campañas de difusión sobre los métodos de separación y recolección y recolección de residuos aplicables en cada una de las Alcaldías.\nPárrafo reformado y publicado en la GOCDMX el 21 de Octubre de 2022\nArtículo 33 Bis 1. La Secretaría y la Secretaría de Obras y Servicios, en conjunto con las delegaciones, fomentarán que las instituciones educativas, empresas, establecimientos mercantiles, industriales y de servicios, instituciones públicas y privadas, centros educativos y dependencias gubernamentales y similares, lleven a cabo la separación de residuos, mediante el sistema de recolección diferenciada y selectiva.\nArtículo 34.- La Secretaría de Obras y Servicios y las Alcaldías, en el marco de sus respectivas competencias, instrumentarán los sistemas de depósito y recolección separada de los residuos sólidos, así ́ como de aprovechamiento, tratamiento y disposición final, de conformidad con lo señalado en el Reglamento y el\nPrograma de Gestión Integral de los Residuos Sólidos.\nLos recipientes y contenedores que las autoridades dispongan en la vía pública deberán ser diferenciados para residuos urbanos en orgánicos e inorgánicos.\n\nAsimismo, dichas autoridades se coordinarán para colocar conforme a las necesidades de la demarcación territorial, contenedores diferenciados para depositar las heces de animales de compañía y mascotas en parques y jardines\nPárrafo reformado y publicado en la GOCDMX el 21 de Octubre de 2022\nArtículo 35.- Los residuos de manejo especial, deberán separarse conforme a la clasificación establecida en el artículo 31 de la presente Ley, dentro de las instalaciones donde se generen, así como en las plantas de selección y tratamiento, con la finalidad de identificar aquellos que sean susceptibles de valorización.\nTÍTULO CUARTO\nDEL SERVICIO PÚBLICO DE LIMPIA\nCAPÍTULO I\nDE LAS DISPOSICIONES GENERALES\nArtículo 36.- La prestación del servicio de limpia en el Distrito Federal constituye un servicio público que estará a cargo de la Administración Pública del Distrito Federal, a través de la Secretaría de Obras y Servicios y las Delegaciones, en los términos de esta Ley y demás ordenamientos jurídicos aplicables.\nEl servicio público de limpia comprende:\nI. El barrido de vías públicas, áreas comunes y vialidades, así como la recolección de los residuos sólidos; y\nII. La transferencia, aprovechamiento, tratamiento y disposición final de los residuos sólidos.\nArtículo 36 Bis. En lo que refiere al servicio público de limpia a cargo de las Delegaciones, particularmente en el barrido manual y recolección domiciliaria y en el entendido de lo dispuesto en el artículo 36 de esta\nLey, queda absolutamente prohibido a terceros bajo cualquier figura, agrupación, organización, razón social o a título individual y que no estén debidamente registrados y autorizados ante la Secretaría que presten, ofrezcan y ejecuten cualquier acción o actividad relacionada con el servicio público de limpia, toda vez que este, corresponde única y exclusivamente a las autoridades competentes de la Administración\nPública del Distrito Federal, a través de los lineamientos y organización que se tiene para el manejo integral de los residuos sólidos urbanos, la recolección selectiva y todas aquellas medidas y coordinación que sostienen los trabajadores de limpia con las autoridades. La contravención a este artículo será sancionada conforme a lo previsto en esta Ley, y en los ordenamientos aplicables vigentes.\n\nArtículo 36 Ter. Quedan exceptuados de la disposición contenida en el Artículo 36 Bis las empresas que hayan obtenido su registro, actualización y vigencia en el padrón autorizado por la Secretaría y que se dediquen a servicios relacionados con la recolección a grandes generadores, recolección especializada y recolección de residuos de la construcción, en cuyo caso es indispensable, comprobar mensualmente, los controles inherentes a la recolección, manejo, transferencia, tratamiento y disposición final, a efecto de validar que su operación se enmarque en las disposiciones ambientales adecuadas y establecidas para tal propósito.\nArtículo 36 Quater. Los grandes generadores de residuos sólidos urbanos están obligados a:\nI. Contratar los servicios de recolección con las empresas autorizadas para tal efecto, a las cuales se hace mención en el artículo 36 Ter; mismas que a su vez deberán cubrir el pago de derechos establecidos en el Código Fiscal para el Distrito Federal, si hacen uso de la infraestructura del\nGobierno del Distrito Federal;\nII. Cubrir el pago de derechos establecidos en el Código Fiscal para el Distrito Federal y cumplir con los lineamientos de traslado de residuos sólidos urbanos si es que lo hacen mediante sus propios medios; y\nIII. Solicitar a la Delegación correspondiente o a la Secretaría de Obras y Servicios, la recolección respectiva, cubriendo en todo momento el pago de derechos establecidos en el Código Fiscal para el Distrito Federal.\nLo anterior, en términos de lo dispuesto en el artículo 243 y demás disposiciones aplicables del Código\nFiscal del Distrito Federal.\nArtículo 36 Quintus. La Secretaría de Obras y Servicios respecto de su ámbito de competencia en el servicio público de limpia, particularmente en las etapas de barrido manual y mecánico, recolección de residuos sólidos urbanos y limpieza de vialidades primarias, operación de estaciones de transferencia, sistema de acarreos y operación de la disposición final, en cuanto a su quehacer cotidiano, mantenimiento y proyectos específicos, podrá ejecutarlo con recursos propios en cuanto a personal, maquinaria y equipo o a través de contratos con empresas especializadas en la materia.\nArtículo 36 Sextus. Cualquier otra problemática o particularidad que se presente de manera emergente, no prevista en la ley y relacionada con el servicio público de limpia que sea necesario resolver y determinar, será facultad de las autoridades competentes y de la Comisión según sea el caso.\n\nArtículo 37.- En la prestación del servicio público de limpia se deberán cumplir las disposiciones de esta\nLey, su reglamento, los programas correspondientes y demás disposiciones jurídicas aplicables, haciéndolas del conocimiento de su personal de servicio y a quienes se lo presten. Asimismo, se deberán establecer medidas preventivas para atender emergencias en caso de riesgos de acuerdo con las disposiciones jurídicas aplicables.\nCAPÍTULO II\nDEL BARRIDO Y LA RECOLECCIÓN DE RESIDUOS SÓLIDOS\nArtículo 38.- Todo generador de los residuos sólidos tiene la obligación de entregarlos al servicio de limpia.\nEl servicio de recolección domiciliaria en casa habitación, unidades habitacionales y demás edificaciones destinadas a vivienda, así como los establecimientos mercantiles considerados como contribuyentes de ingresos menores, se realizará de manera gratuita.\nLos establecimientos mercantiles y de servicios distintos a los establecidos en el párrafo anterior, empresas, fábricas, tianguis, mercados sobre ruedas autorizados, mercados públicos, centros de abasto, concentraciones comerciales, industrias y similares, así como las dependencias y entidades federales, que generen residuos sólidos en alto volumen, deberán pagar las tarifas correspondientes por los servicios de recolección y recepción de residuos sólidos que establece el Código Financiero del Distrito Federal.\nArtículo 39.- Los camiones recolectores de los residuos sólidos, así como los destinados para la transferencia de dichos residuos a las plantas de selección y tratamiento o a los sitios de disposición final, deberán disponer de contenedores seleccionados conforme a la separación selectiva que esta Ley establece.\nArtículo 40.- Las delegaciones dispondrán contenedores para el depósito de los residuos sólidos de manera separada conforme a lo establecido en la presente Ley, en aquellos sitios que por su difícil accesibilidad o por su demanda así lo requiera, procediendo a su recolección.\nNinguna persona podrá disponer de los residuos sólidos depositados en dichos contenedores y quien lo realice será sancionado y remitido a la autoridad competente.\nAsimismo, los generadores de los residuos sólidos a los que se refiere este artículo tienen la obligación de trasladar dichos residuos hasta el sitio que se determine para la prestación del servicio de recolección. Si los usuarios no cumplen con esta obligación serán infraccionados en los términos de la presente Ley.\n\nArtículo 41.- Las delegaciones deberán colocar en las vías y áreas públicas los contenedores para el depósito separado de residuos sólidos producidos por los transeúntes o usuarios de los sitios citados, en número y capacidad acordes a las necesidades pertinentes. Asimismo, se obliga a las delegaciones a dar mantenimiento a los contenedores y proceder a la recolección de dichos residuos en forma constante y permanente, conforme lo que establezca el Reglamento y el Programa de Prestación del Servicio público de limpia correspondiente.\nArtículo 42.- Los contenedores de residuos urbanos deberán mantenerse dentro del predio de la persona que lo habita o del establecimiento de que se trate y sólo se sacarán a la vía pública o áreas comunes el tiempo necesario para su recolección el día y hora señalados por el servicio público de limpia. Dichos contenedores deberán satisfacer las necesidades de servicio del inmueble, y cumplir con las condiciones de seguridad e higiene, de conformidad con la Ley de Salud para el Distrito Federal y demás ordenamientos aplicables.\nArtículo 42 Bis.- Para su operación en la Ciudad de México, los prestadores de servicio para el manejo de residuos deberán de contar con la autorización correspondiente por parte de la Secretaría. La contravención a lo dispuesto en el presente artículo será motivo de las medidas de seguridad y/o sanciones que resulten aplicables.\nArtículo modificado y publicado en la GOCDMX el 03 de Abril de 2023\nArtículo 42 Ter. Los prestadores de servicio de recolección privada de otros Estados que operen en el Distrito\nFederal, deberán registrarse ante la Secretaría y deberán presentar su plan de manejo en los formatos que esta autoridad determine.\nCAPÍTULO III\nDE LA TRANSFERENCIA Y TRATAMIENTO DE RESIDUOS SÓLIDOS\nArtículo 43.- La Secretaría de Obras y Servicios diseñará el sistema de transferencia, selección y tratamiento de los residuos sólidos, procurando la construcción y operación en número suficiente en cada delegación conforme a la cantidad de residuos que se generan en cada demarcación territorial, contando con el personal suficiente para su manejo.\nArtículo 44.- El ingreso de personas o vehículos a las estaciones de transferencia y plantas de selección y tratamiento de los residuos sólidos tienen acceso restringido conforme a lo que el Reglamento y las normas ambientales establezcan y no podrán convertirse en centros de almacenamiento permanente.\n\nArtículo 45.- Para la operación y mantenimiento de las estaciones de transferencia y plantas de selección y tratamiento, así como centros de composteo, se deberá contar con:\nI. Personal previamente capacitado para reconocer la peligrosidad y riesgo de los residuos que manejan y darles un manejo integral, seguro y ambientalmente adecuado;\nII. Programa de preparación y respuesta a emergencias y contingencias que involucren a los residuos sólidos urbanos;\nIII. Bitácora en la cual se registren los residuos que se reciben, indicando tipo, peso o volumen, destino y fecha de entrada y salida de los mismos;\nIV. Área para segregar y almacenar temporalmente los residuos, por tiempos acordes con lo que establezcan las disposiciones respectivas; y\nV. Los demás requisitos que determine el Reglamento y normas aplicables.\nArtículo 46.- Las plantas de selección y tratamiento de los residuos sólidos que pertenezcan al Distrito\nFederal, deberán contar con la infraestructura tecnológica de vanguardia necesaria, para la realización del trabajo especializado que permita generar energía renovable y limpia.\nAsimismo, deberán contar con básculas y sistemas para llevar el control de los residuos depositados, así como con un sistema adecuado de control de ruidos, olores y emisión de partículas que garantice el adecuado manejo integral de los residuos sólidos y minimicen los impactos al ambiente y a la salud humana.\nArtículo 47.- El personal que labore en las estaciones de transferencia y plantas de selección y tratamiento deberá estar debidamente acreditado por la Secretaría de Obras y Servicios.\nArtículo 48.- Las instalaciones de tratamiento térmico autorizadas deberán cumplir con lo establecido por la legislación vigente, sus reglamentos, las normas oficiales mexicanas y demás ordenamientos jurídicos aplicables.\nLos administradores o propietarios de dichas plantas deberán realizar reportes mensuales y enviar dicha información a la autoridad competente para su evaluación y control.\nLa Secretaría emitirá norma ambiental para el Distrito Federal en los términos establecidos en el artículo\n\n37 de la Ley Ambiental del Distrito Federal y demás aplicables, que establezca los requisitos o especificaciones, condiciones, parámetros y límites permisibles en el desarrollo de una actividad humana relacionada con el tratamiento térmico de los residuos sólidos y que sus emisiones puedan causar daños al ambiente y la salud humana, quedando restringida la emisión de dioxinas y furanos a la atmósfera que rebasen los límites establecidos en la normatividad federal y del Distrito Federal aplicable, derivadas de tratamientos térmicos e incineradores.\nCualquier persona puede denunciar ante la autoridad correspondiente cuando se trate de violaciones a las disposiciones del presente artículo en los términos del Capítulo IV del Título Séptimo de esta Ley.\nCAPÍTULO IV\nDE LA DISPOSICIÓN FINAL\nArtículo 49.- Los residuos sólidos que no puedan ser tratados por medio de los procesos establecidos por esta Ley, deberán ser enviados a los sitios de disposición final.\nArtículo 50.- La selección de los sitios para disposición final, así como la construcción y operación de las instalaciones deberá sujetarse a lo estipulado en las normas oficiales mexicanas y demás ordenamientos jurídicos aplicables.\nArtículo 51. Los sitios de disposición final tendrán un acceso restringido a materiales reutilizables o reciclables y deberá recibir un menor porcentaje de residuos orgánicos. Además, emplearán mecanismos para instalar sistemas de extracción de biogás y tratamiento de lixiviados para su recolección.\nLos sitios de disposición final de los residuos sólidos que pertenezcan al Distrito Federal, deberán contar con infraestructura tecnológica de vanguardia necesaria, para la realización del trabajo especializado que permita generar energía renovable y limpia.\nArtículo 52.- Queda prohibida la selección o pepena de los residuos sólidos en los sitios destinados para relleno sanitario.\nArtículo 53.- La Secretaría de Obras y Servicios deberá establecer programas de capacitación periódica a los trabajadores que laboren en los sitios de disposición final.\nEl personal que labore en los sitios de disposición final deberá estar debidamente acreditado por la\nSecretaría de Obras y Servicios.\n\nArtículo 54.- Los rellenos sanitarios que hayan cumplido su vida útil se destinarán únicamente como parques, jardines, centros de educación ambiental o sitios para el fomento de la recreación y la cultura.\nTÍTULO QUINTO\nDE LA VALORIZACIÓN Y COMPOSTEO DE LOS RESIDUOS SÓLIDOS\nCAPÍTULO I\nDEL RECICLAJE\nArtículo 55.- Los productores y comercializadores cuyos productos y servicios generen residuos sólidos susceptibles de valorización mediante procesos de reutilización o reciclaje realizarán planes de manejo que establezcan las acciones para minimizar la generación de sus residuos sólidos, su manejo responsable y para orientar a los consumidores sobre las oportunidades y beneficios de dicha valorización para su aprovechamiento.\nArtículo 56.- La Secretaría de Obras y Servicios, en coordinación con la Secretaría y la Secretaría de\nDesarrollo Económico, en cumplimiento a lo señalado en el programa de Gestión Integral de los Residuos\nSólidos, instrumentarán programas para la utilización de materiales o subproductos provenientes de los residuos sólidos a fin de promover mercados para su aprovechamiento, vinculando al sector privado, organizaciones sociales y otros agentes económicos.\nArtículo 57.- Las dependencias y entidades del Gobierno de la Ciudad de México, las Alcaldías, el Congreso de la Ciudad de México, el Tribunal Superior de Justicia de la Ciudad de México y demás órganos autónomos, establecerán en sus oficinas y dependencias sistemas de manejo ambiental, los cuales tendrán por objeto prevenir, minimizar y evitar la generación de residuos y aprovechar su valor.\nPara tal efecto, se promoverá la adquisición y uso de objetos desechables elaborados a partir de materia orgánica, biodegradable o de bajo impacto ecológico.\nArtículo 58.- Las autoridades fomentarán programas para que los establecimientos de mayoristas, tiendas de departamentos y centros comerciales se cuente con espacios y servicios destinados a la recepción de materiales y subproductos de los residuos sólidos valorizables.\nArtículo 59.- Todo establecimiento mercantil, industrial y de servicios que se dedique a la reutilización o reciclaje de los residuos sólidos deberán:\n\nI. Obtener autorización de las autoridades competentes;\nII. Ubicarse en lugares que reúnan los criterios que establezca la normatividad aplicable;\nIII. Instrumentar un plan de manejo aprobado por la Secretaría para la operación segura y ambientalmente adecuada de los residuos sólidos que valorice;\nIV. Contar con programas para prevenir y responder a contingencias o emergencias ambientales y accidentes;\nV. Contar con personal capacitado y continuamente actualizado; y\nVI. Contar con garantías financieras para asegurar que, al cierre de las operaciones en sus instalaciones, éstas queden libres de residuos y no presenten niveles de contaminación que puedan representar un riesgo para la salud humana y el ambiente.\nArtículo 60.- Los residuos sólidos que hayan sido seleccionados y remitidos a los mercados de valorización y que por sus características no puedan ser procesados, deberán enviarse para su disposición final.\nCAPÍTULO II\nDEL COMPOSTEO\nArtículo 61.- La Secretaría de Obras y Servicios diseñará, construirá, operará y mantendrá centros de composteo o de procesamiento de residuos urbanos orgánicos, de conformidad con lo que establece el\nPrograma de Gestión Integral de los Residuos Sólidos y el Programa de Prestación del Servicio de Limpia correspondiente.\nLas delegaciones podrán encargarse de las actividades señaladas en el párrafo anterior, procurando que la composta producida se utilice, preferentemente, en parques, jardines, áreas verdes, áreas de valor ambiental, áreas naturales protegidas y otras que requieran ser regeneradas.\nArtículo 62.- La Secretaría de Desarrollo Económico, en coordinación con la Secretaría de Obras y Servicios y con las delegaciones que tengan autorización de operar centros de composteo, promoverá el fomento de mercados para la comercialización del material que resulte de los composteros.\n\nArtículo 63.- Los controles sobre las características apropiadas de los materiales para la producción de composta o criterios para cada tipo de composta, se fijarán en el reglamento, debiendo identificar las particularidades de los tipos de que por sus características pueda ser comercializada o donada.\nLa composta que no pueda ser aprovechada deberá ser enviada a los rellenos sanitarios para su disposición final.\nArtículo 64.- Toda persona que lleve a cabo procesos de tratamiento de residuos urbanos orgánicos para composta debe cumplir con las disposiciones que establecen las normas oficiales mexicanas y las normas ambientales para el Distrito Federal en esta materia.\nTÍTULO SEXTO\nDE LAS DISPOSICIONES COMPLEMENTARIAS DE LA RESTAURACIÓN,\nPREVENCIÓN Y CONTROL DE LA CONTAMINACIÓN DEL SUELO\nCAPÍTULO ÚNICO\nDE LA CONTAMINACIÓN DEL SUELO POR RESIDUOS SÓLIDOS\nArtículo 65.- Es responsabilidad de toda persona que genere y maneje residuos sólidos, hacerlo de manera que no implique daños a la salud humana ni al ambiente.\nCuando la generación, manejo y disposición final de los residuos sólidos produzca contaminación del suelo, independientemente de las sanciones penales o administrativas que procedan, quien preste el servicio está obligado a:\nI. Llevar a cabo las acciones necesarias para restaurar y recuperar las condiciones del suelo, de acuerdo a lo establecido en las disposiciones jurídicas aplicables; y\nII. En caso de que la recuperación o restauración no fueran factibles, a indemnizar por los daños causados a terceros o al ambiente de conformidad con la legislación aplicable.\nTÍTULO SÉPTIMO\nDE LAS MEDIDAS DE SEGURIDAD, SANCIONES, RECURSO DE\nINCONFORMIDAD Y DENUNCIA CIUDADANA\n\nCAPÍTULO I\nDE LAS MEDIDAS DE SEGURIDAD\nArtículo 66.- Las autoridades competentes podrán aplicar las siguientes medidas de seguridad cuando las operaciones y procesos empleados durante la recolección, transporte, transferencia, tratamiento, o disposición final representen riesgos significativos para la salud humana o el ambiente:\nI. Asegurar los materiales, residuos o sustancias contaminantes, vehículos, utensilios e instrumentos directamente relacionados con la conducta a que da lugar la imposición de la medida de seguridad, según lo previsto en el párrafo primero de este artículo;\nII. Asegurar, aislar, suspender o retirar temporalmente en forma parcial o total, según corresponda, los bienes, equipos y actividades que generen riesgo significativo o daño;\nIII. Clausurar temporal, parcial o totalmente las instalaciones en que se manejen o se preste el servicio correspondiente que den lugar a los supuestos a que se refiere el primer párrafo de este artículo; y\nIV. Suspender las actividades, en tanto no se mitiguen los daños causados.\nV. Imponer el monto de la garantía en lo referente a los residuos de la construcción, su manejo se apegue a lo establecido en la Ley Ambiental, la presente Ley y los ordenamientos aplicables\nLa autoridad correspondiente podrá solicitar el auxilio de la fuerza pública para ejecutar cualquiera de las acciones anteriores.\nLas medidas de seguridad previstas en este capítulo, se sujetarán a lo dispuesto en la Ley del Procedimiento\nAdministrativo del Distrito Federal y demás ordenamientos aplicables.\nCAPÍTULO II\nDE LAS SANCIONES\nArtículo 67.- Los infractores de la presente Ley, o quienes induzcan directa o indirectamente a alguien a infringirla, serán sancionados con arreglo a lo dispuesto en este Capítulo, de acuerdo a lo siguiente:\n\nI. Cuando los daños causados al ambiente se produzcan por actividades debidas a diferentes personas, la autoridad competente imputará individualmente esta responsabilidad y sus efectos económicos;\nII. Cuando el generador o poseedor de los residuos, o prestador del servicio, los entregue a persona física o jurídica distinta de las señaladas en esta Ley; o\nIII. Cuando sean varios los responsables y no sea posible determinar el grado de participación de cada uno en la realización de la infracción, solidariamente compartirán la responsabilidad.\nLa imposición de cualquier sanción prevista por la presente Ley no excluye la responsabilidad civil o penal y la eventual indemnización o reparación de daños y perjuicios que puedan recaer sobre el sancionado.\nArtículo 68.- Las sanciones administrativas podrán ser:\nI. Amonestación;\nII. Multa;\nIII. Arresto; y\nIV. Las demás que señalen las leyes o reglamentos.\nArtículo 69.- Las sanciones cometidas por la violación de las disposiciones de la presente Ley, se aplicarán conforme a lo siguiente:\nI. Amonestación cuando por primera vez se incumplan con las disposiciones contenidas en los artículos 25 fracción V y 33 de esta Ley;\nII. Multa de 20 a 200 veces la Unidad de Cuenta de la Ciudad de México vigente contra quien por segunda ocasión realice alguna de las conductas descritas en la fracción anterior o por violaciones a lo dispuesto por los artículos 25 fracciones I, II y VI; 26 segundo y tercer párrafos;\n40 segundo y tercer párrafos; y 42 de la presente Ley;\n\nIII. Multa de 150 a mil veces la Unidad de Cuenta de la Ciudad de México vigente las violaciones a lo dispuesto por los artículos 25 fracciones III, IV, VII y VIII; 38 tercer párrafo; 55 y 59 de la presente Ley y la ley Federal de Responsabilidades de los Servidores Públicos; y\nIII Bis. Multa de 500 a dos mil veces la Unidad de Cuenta de la Ciudad de México vigente por la violación a lo dispuesto en el artículo 25 fracción XI BIS; y\nIV. Multa de 500 a 20,000 veces la Unidad de Medida y Actualización vigente por la violación a lo dispuesto por los artículos 25 fracción IX, X, XI, XII Y XIII; 32 Bis, 36 Bis, 36 Ter y 36 Quáter de la presente ley.\nFracción modificada y publicada en la GOCDMX el 03 de Abril de 2023\nArtículo 70.- En la imposición de sanciones se tomarán en cuenta los siguientes criterios:\nI. La trascendencia social, sanitaria o ambiental y el perjuicio causado por la infracción cometida;\nII. El ánimo de lucro ilícito y la cuantía del beneficio obtenido en la comisión de la infracción;\nIII. El carácter intencional o negligente de la acción u omisión constitutiva de la infracción;\nIV. La reincidencia en la comisión de infracciones, la gravedad de la conducta y la intención con la cual fue cometida; y\nV. Los casos en que el monto de la multa impuesta será conmutada por medidas de compensación las cuales serán destinadas al Fondo Ambiental Público del Distrito Federal.\nArtículo 71.- Independientemente de la responsabilidad de reparar el daño de conformidad con las normas aplicables, los infractores de esta ley estarán sujetos a las sanciones previstas en esta Ley, de conformidad con lo dispuesto en la Ley de Procedimiento Administrativo. En todo caso, tratándose de los asuntos de esta\nLey, las actas que levante la autoridad correspondiente por violaciones a ésta, podrán ser en el lugar o en el momento en que se detecte la falta.\nArtículo 72.- Cuando proceda la clausura, el personal comisionado para ejecutarla procederá a levantar acta circunstanciada de la diligencia, observando las disposiciones aplicables a la realización de inspecciones.\nEn los casos en que se imponga como sanción la clausura temporal, la autoridad deberá indicar al infractor las medidas de mitigación y acciones que debe llevar a cabo para subsanar las irregularidades que\n\nmotivaron dicha sanción, así como los plazos para su realización.\nArtículo 73.- En caso de que se expidan licencias, permisos, autorizaciones o concesiones contraviniendo esta Ley, serán nulas y no producirán efecto legal alguno, y los servidores públicos responsables serán sancionados conforme a lo dispuesto en la legislación de la materia.\nCAPÍTULO III\nDEL RECURSO DE INCONFORMIDAD\nArtículo 74.- Las resoluciones dictadas en los procedimientos administrativos con motivo de la aplicación de esta Ley, su reglamento, y disposiciones que de ella emanen, podrán ser impugnadas, mediante el recurso de inconformidad conforme a las reglas establecidas en la Ley de Procedimiento Administrativo del\nDistrito Federal.\nCAPÍTULO IV\nDE LA DENUNCIA CIUDADANA\nArtículo 75.- Toda persona, grupos sociales, organizaciones no gubernamentales, asociaciones y sociedades podrán denunciar ante la Procuraduría y autoridades competentes todo hecho, acto u omisión que produzca o pueda producir desequilibrio ecológico o daños al ambiente o a los recursos naturales derivados del manejo inadecuado de los residuos sólidos, o contravenga las disposiciones de la presente\nLey y de los demás ordenamientos que regulen materias relacionadas con la misma.\nArtículo 76.- La denuncia ciudadana, podrá ejercitarse por cualquier persona, basta que se presente por escrito y contenga:\nI. El nombre o razón social, domicilio completo y teléfono si lo tiene, del denunciante o, en su caso, de su representante legal;\nII. Los actos, hechos u omisiones denunciados;\nIII. Los datos que permitan identificar al presunto infractor o localizar la fuente contaminante, y\nIV. Las pruebas que el denunciante pueda ofrecer.\n\nAsimismo, podrá formularse la denuncia por vía telefónica, en cuyo supuesto el servidor público que la reciba, levantará acta circunstanciada, y el denunciante deberá ratificarla por escrito, cumpliendo con los requisitos establecidos en el presente artículo, en un término de tres días hábiles siguientes a la formulación de la denuncia, sin perjuicio de que la Procuraduría, investigue de oficio los hechos constitutivos de la denuncia.\nArtículo 77.- La Procuraduría deberá manifestar las consideraciones adoptadas respecto de la información proporcionada por el denunciante, al momento de resolver la denuncia.\nARTÍCULOS TRANSITORIOS\nPRIMERO.- Esta Ley entrará en vigor el día siguiente de su publicación en la Gaceta Oficial del Distrito\nFederal.\nSEGUNDO.- Se abroga el Reglamento para el Servicio Público de Limpia en el Distrito Federal, publicado en el Diario Oficial de la Federación, el 27 de julio de 1989 y se derogan todas las disposiciones que se opongan a la presente Ley. El Reglamento para el Servicio Público de Limpia en el Distrito Federal permanecerá vigente en todo lo que no se oponga a la presente Ley y en tanto el Gobierno del Distrito\nFederal expide el Reglamento de la presente Ley.\nTERCERO.- Las disposiciones que esta Ley establece en materia de separación de los residuos sólidos, recolección selectiva de dichos residuos y la instrumentación de planes de manejo, así como las sanciones previstas a este respecto en el artículo 69 de la presente Ley se aplicarán a partir del 1 de octubre de 2004.\nEn consecuencia, la Secretaría, la Secretaría de Obras y Servicios y las Delegaciones iniciarán paulatinamente a partir del 1 de enero de 2004 la implantación de medidas y mecanismos tendientes a organizar la estructura e instalar la infraestructura necesaria para cumplir estas disposiciones e iniciarán una campaña masiva para difundir entre la población las disposiciones de esta Ley y educar cívicamente a la población en cuanto a las ventajas de su cumplimiento, de acuerdo a los recursos presupuéstales asignados.\nEl calendario de aplicación de estas disposiciones deberá publicarse en el programa de gestión integral de residuos sólidos al que se refiere el artículo 11 de la presente Ley, durante el primer semestre de 2004.\nPara la elaboración de dicho calendario de aplicación y vigilar el cumplimiento de sus acuerdos, se constituirá un Comité Técnico conformado por siete Diputados de la Asamblea Legislativa designados por la Comisión de Gobierno y por un representante de cada una de las siguientes entidades: Secretaría de\n\nGobierno, Secretaría del Medio Ambiente, Secretaría de Obras y Servicios, Secretaría de Salud y\nProcuraduría Ambiental y de Ordenamiento Territorial.\nDicho Comité Técnico efectuará su primera sesión durante los primeros quince días del mes de enero de\n2004, a convocatoria de la Secretaría del Medio Ambiente del Gobierno del Distrito Federal.\nLos días 28 de febrero, 30 de abril y 30 de junio de 2004 la Secretaría informará a la Asamblea Legislativa del Distrito Federal de los avances concretos realizados en la aplicación y promoción de los programas mencionados.\nCUARTO.- La Secretaría de Obras y Servicios deberá concluir a más tardar el 30 de abril de 2004 la elaboración del registro de los establecimientos mercantiles y de servicios relacionados con la recolección, manejo, tratamiento, reutilización, reciclaje y disposición final de los residuos sólidos.\nQUINTO.- En tanto se expiden las disposiciones administrativas que se deriven de la presente Ley, seguirán en vigor las que han regido hasta ahora en lo que no la contravengan.\nSEXTO- Todos los actos, procedimientos y recursos administrativos relacionados con la materia de esta Ley, que se hubieren iniciado bajo la vigencia de otros ordenamientos, se tramitarán y resolverán conforme a los mismos.\nSÉPTIMO.- El Jefe de Gobierno expedirá el reglamento de la presente Ley a más tardar el día 30 de mayo de 2004.\nOCTAVO.- La Secretaría, la Secretaría de Obras y Servicios y las Delegaciones deberán expedir a más tardar el 30 de mayo de 2004 los programas que esta Ley establece.\nNOVENO.- Publíquese en el Diario Oficial de la Federación para su mayor difusión.\nRecinto Legislativo a 20 de marzo de 2003.\nPOR LA MESA DIRECTIVA.- DIP. ALEJANDRO DIEZ BARROSO REPIZO, PRESIDENTE.- DIP. ROLANDO ALFONSO\nSOLÍS OBREGÓN, SECRETARIO.- (Firmas).\nEn cumplimiento de lo dispuesto por los artículos 122, apartado C, Base Segunda, fracción II, inciso b), de la Constitución Política de los Estados Unidos Mexicanos; 48, 49 y 67 fracción II, del Estatuto de Gobierno del Distrito Federal, y para su debida publicación y observancia, expido el presente Decreto Promulgatorio,\n\nen la Residencia Oficial del Jefe de Gobierno del Distrito Federal, en la Ciudad de México, a los cinco días del mes de abril del dos mil tres.- EL JEFE DE GOBIERNO DEL DISTRITO FEDERAL, LIC. ANDRÉS MANUEL\nLÓPEZ OBRADOR.- FIRMA.- EL SECRETARIO DE GOBIERNO, ALEJANDRO ENCINAS RODRÍGUEZ.- FIRMA.- LA\nSECRETARIA DEL MEDIO AMBIENTE, CLAUDIA SHEINBAUM PARDO.- FIRMA.- EL SECRETARIO DE OBRAS Y\nSERVICIOS, CÉSAR BUENROSTRO HERNÁNDEZ.- FIRMA.- LA SECRETARIA DE SALUD, ASA CRISTINA LAURELL.-\nFIRMA.\nTRANSITORIOS DEL DECRETO POR EL QUE SE REFORMAN LOS ARTÍCULOS TERCERO, CUARTO, SÉPTIMO Y\nOCTAVO TRANSITORIOS DE LA LEY DE RESIDUOS SÓLIDOS DEL DISTRITO FEDERAL; PUBLICADO EN LA\nGACETA OFICIAL DEL DISTRITO FEDERAL EL 10 DE FEBRERO DE 2004.\nPRIMERO.- El presente Decreto entrará en vigor el día siguiente de su aprobación por el Pleno de la\nAsamblea Legislativa del Distrito Federal.\nSEGUNDO.- Túrnese al jefe de Gobierno del Distrito Federal única y exclusivamente para su publicación en la Gaceta Oficial del Distrito Federal y publíquese también en el Diario Oficial de la Federación para su mayor difusión.\nTRANSITORIOS DEL DECRETO POR EL QUE SE ADICIONAN DIVERSAS DISPOSICIONES DE LA LEY DE\nRESIDUOS SÓLIDOS DEL DISTRITO FEDERAL, PUBLICADO EN LA GACETA OFICIAL DEL DISTRITO FEDERAL EL\n18 DE AGOSTO DE 2009.\nPRIMERO. El presente decreto entrará en vigor al día siguiente de su publicación en la Gaceta Oficial del\nDistrito Federal.\nSEGUNDO. Las sanciones por la violación a disposiciones del presente decreto se aplicarán a los doce meses siguientes de su entrada en vigor.\nTERCERO.- El programa de sustitución de plástico a que hace referencia el presente decreto deberá crearse con la participación de la comunidad científica y académica a través del Instituto de Ciencia y Tecnología, el sector productivo, asociaciones civiles y organismos representativos en un término máximo de seis meses contados a partir de la entrada en vigor del presente decreto.\n\nCUARTO. La Asamblea Legislativa del Distrito Federal deberá implementar una campaña permanente para dar a conocer a la ciudadanía en general, los derechos y obligaciones que se derivan por la entrada en vigor del presente decreto. Para tal fin, se deberá prever en el Presupuesto de Egresos una partida suficiente para poder llevar a cabo acciones de promoción y publicidad en medios electrónicos e impresos.\nQUINTO. El Gobierno del Distrito Federal a través de la Secretaría del Medio Ambiente y de Desarrollo\nEconómico ambas del Distrito Federal, deberán implementar un programa de apoyos a efecto de que las empresas que actualmente producen las bolsas y empaques de plástico, puedan adecuar las tecnologías que tienen a efecto de atender las demandas ambientales y legales implementadas en la presente reforma.\nSEXTO. El Gobierno del Distrito Federal y las Delegaciones efectuarán una campaña de difusión del presente decreto.\nSÉPTIMO. El Jefe de Gobierno del Distrito Federal deberá actualizar las disposiciones reglamentarias a más tardar noventa días después de la entrada en vigor del presente decreto.\nOCTAVO. El Instituto de Ciencia y Tecnología del Distrito Federal instrumentará un programa de asesoramiento al sector productivo para el desarrollo de materiales sustitutos del plástico a más tardar en\n120 días de la entrada en vigor del presente decreto.\nTRANSITORIOS DEL DECRETO POR EL QUE SE REFORMAN DIVERSAS DISPOSICIONES DE LA LEY DE\nRESIDUOS SÓLIDOS DEL DISTRITO FEDERAL, PUBLICADO EN LA GACETA OFICIAL DEL DISTRITO FEDERAL EL\n26 DE NOVIEMBRE DE 2010.\nPRIMERO. El presente Decreto entrará en vigor al siguiente día de su publicación en la Gaceta Oficial del\nDistrito Federal.\nSEGUNDO. Las disposiciones reglamentarias de la presente ley deberán ser publicadas después de los noventa días naturales a la entrada en vigor de este Decreto.\nTERCERO. La Secretaria contará con un plazo de seis meses contados a partir de la entrada en vigor del presente decreto para emitir los criterios y las normas a los que se refiere la fracción XI del artículo 6º del presente Decreto; dichos criterios y normas entraran en vigor doce meses después de su publicación.\nCUARTO. Se derogan todas aquellas disposiciones que contravengan el contenido del presente Decreto.\n\nQUINTO. Publíquese el presente Decreto en la Gaceta Oficial del Distrito Federal y para su mayor difusión en el Diario Oficial de la Federación.\nTRANSITORIOS DEL DECRETO POR EL QUE SE REFORMAN LOS ARTÍCULOS 46 Y 51 DE LA LEY DE RESIDUOS\nSÓLIDOS DEL DISTRITO FEDERAL, PUBLICADO EN LA GACETA OFICIAL DEL DISTRITO FEDERAL EL 23 DE\nDICIEMBRE DE 2010.\nPRIMERO.- El presente decreto entrará en vigor a partir del día siguiente de su publicación en la Gaceta\nOficial del Distrito Federal.\nSEGUNDO.- Publíquese en la Gaceta Oficial del Distrito Federal y, para su mayor difusión, en el Diario Oficial de la Federación.\nTRANSITORIOS DEL DECRETO POR EL QUE SE ADICIONA LA FRACCIÓN XIII BIS AL ARTÍCULO 11 Y LA\nFRACCIÓN XIV AL ARTÍCULO 25 DE LA LEY DE RESIDUOS SÓLIDOS DEL DISTRITO FEDERAL, PUBLICADO EN\nLA GACETA OFICIAL DEL DISTRITO FEDERAL EL 24 DE JULIO DE 2012.\nPRIMERO.- El presente Decreto entrará en vigor al día siguiente de su publicación en la Gaceta Oficial del\nDistrito Federal.\nSEGUNDO.- Publíquese para su mayor difusión en el Diario Oficial de la Federación.\nTRANSITORIOS DEL DECRETO POR EL QUE SE REFORMAN Y ADICIONAN DIVERSAS DISPOSICIONES DE LA\nLEY DE RESIDUOS SÓLIDOS DEL DISTRITO FEDERAL Y DE LA LEY DE CULTURA CÍVICA DEL DISTRITO FEDERAL,\nPUBLICADOS EN LA GACETA OFICIAL DEL DISTRITO FEDERAL EL 8 DE SEPTIEMBRE DE 2014.\nPRIMERO.- Publíquese en la Gaceta Oficial del Distrito Federal, para su debida observancia y aplicación.\nSEGUNDO.- El presente Decreto entrará en vigor al día siguiente de su publicación.\nTERCERO.- La Secretaría del Medio Ambiente del Distrito Federal contará con un plazo de 60 días hábiles contados a partir de la entrada en vigor del presente Decreto para llevar a cabo la implementación del\n\nRegistro de establecimientos mercantiles y de servicios que se refiere la fracción XVIII del artículo 6º del presente Decreto.\nCUARTO.- Una vez transcurridos los 60 días hábiles señalados en el artículo TERCERO transitorio del presente Decreto; los titulares de establecimientos mercantiles y de servicios contarán con un plazo de 90 días para efectuar ante la Secretaría del Medio Ambiente del Distrito Federal su registro.\nQUINTO.- En consecuencia, la Secretaría del Medio Ambiente, la Secretaría de Obras y Servicios y las\nDelegaciones iniciarán en el ámbito de su respectiva competencia y de manera coordinada la implementación de medidas y mecanismos tendientes a organizar la estructura e instalar la infraestructura necesaria para el cumplimiento a estas disposiciones e iniciarán una campaña para difundirlas entre la población.\nSEXTO.- El Jefe de Gobierno del Distrito Federal contará con un plazo de 90 días hábiles contados a partir de la entrada en vigor del presente Decreto para realizar los cambios necesarios a la normatividad en la materia y adecuarlos al contenido del presente Decreto.\nSÉPTIMO.- Se derogan todas aquellas disposiciones que contravengan el contenido del presente Decreto.\nTRANSITORIOS DEL DECRETO POR EL QUE SE REFORMAN DIVERSOS ARTÍCULOS DE CÓDIGOS Y LEYES\nLOCALES, QUE DETERMINAN SANCIONES Y MULTAS ADMINISTRATIVAS, CONCEPTOS DE PAGO Y MONTOS\nDE REFERENCIA, PARA SUSTITUIR AL SALARIO MÍNIMO POR LA UNIDAD DE CUENTA DE LA CIUDAD DE\nMÉXICO, DE MANERA INDIVIDUAL O POR MÚLTIPLOS DE ÉSTA, PUBLICADO EN LA GACETA OFICIAL DEL\nDISTRITO FEDERAL EL 28 DE NOVIEMBRE DE 2014.\nPRIMERO.- Publíquese en la Gaceta Oficial del Distrito Federal.\nSEGUNDO.- El presente Decreto se tomará como referencia para el diseño e integración del paquete económico correspondiente al ejercicio fiscal 2015 y entrará en vigor junto con dicho paquete, a excepción de lo dispuesto en los artículos SEGUNDO y CUADRAGÉSIMO OCTAVO del presente Decreto relacionado con la materia Electoral, que entrarán en vigor al día siguiente a aquél en que concluya el proceso electoral\n2014-2015 del Distrito Federal.\nTERCERO.- Las reformas contenidas en el presente decreto no se aplicarán de manera retroactiva en perjuicio de persona alguna, respecto de las sanciones y multas administrativas, conceptos de pago,\n\nmontos de referencia y demás supuestos normativos que se hayan generado o impuesto de manera previa a la entrada en vigor del presente decreto.\nCUARTO.- Las referencias que se hagan del salario mínimo en las normas locales vigentes, incluso en aquellas pendientes de publicar o de entrar en vigor, se entenderán hechas a la Unidad de Cuenta de la\nCiudad de México, a partir de la entrada en vigor del presente Decreto.\nTRANSITORIOS DEL DECRETO POR EL QUE SE REFORMAN Y ADICIONAN DIVERSAS DISPOSICIONES A LA LEY\nAMBIENTAL DE PROTECCIÓN A LA TIERRA DEL DISTRITO FEDERAL Y A LA LEY DE RESIDUOS SÓLIDOS DEL\nDISTRITO FEDERAL, PUBLICADOS EN LA GACETA OFICIAL DEL DISTRITO FEDERAL EL 18 DE NOVIEMBRE DE\n2015.\nPRIMERO.- Túrnese el presente Decreto, al Jefe de Gobierno del Distrito Federal para su publicación en la\nGaceta Oficial del Distrito Federal.\nSEGUNDO.- El presente Decreto entrará en vigor el 30 de enero del 2015. La entrada en vigor quedará sujeta a la suficiencia presupuestal que para tal efecto describe el presente Decreto, y que apruebe la\nAsamblea Legislativa del Distrito Federal, en el siguiente Presupuesto de Egresos del Distrito Federal para el Ejercicio Fiscal 2015.\nTERCERO.- El Jefe de Gobierno del Distrito Federal contará con sesenta días posteriores a la entrada en vigor de dicho Decreto, para expedir las modificaciones reglamentarias y administrativas necesarias aplicables.\nCUARTO.- Las Secretarías del Medio Ambiente y de Desarrollo Económico del Gobierno del Distrito Federal así como las Delegaciones, deberán diseñar e implementar una campaña permanente para dar a conocer a la ciudadanía en general, la forma de operación y participación en los sistemas de intercambio de residuos sólidos por productos en especie tratados en el presente Decreto; previéndose las partidas presupuestales pertinentes para llevar a cabo las mencionadas acciones en medios electrónicos e impresos.\nQUINTO.- La Secretaría de Medio Ambiente del Gobierno del Distrito Federal, deberá solicitar la suficiencia presupuestal suficiente con el fin de iniciar y hacer cumplir las modificaciones que indica el presente\nDecreto.\n\nRecinto de la Asamblea Legislativa del Distrito Federal, a los diez días del mes de junio del año dos mil catorce.- POR LA MESA DIRECTIVA.- DIP. SANTIAGO TABOADA CORTINA, PRESIDENTE.- DIP. JORGE AGUSTÍN\nZEPEDA CRUZ, SECRETARIO.- DIP. ALBERTO EMILIANO CINTA MARTÍNEZ, SECRETARIO.- (Firmas)\nEn cumplimiento de lo dispuesto por los artículos 122, apartado C, Base Segunda, fracción II, inciso b), de la Constitución Política de los Estados Unidos Mexicanos; 48, 49 y 67, fracción II, del Estatuto de Gobierno del Distrito Federal, para su debida publicación y observancia, expido el presente Decreto Promulgatorio en la Residencia Oficial del Jefe de Gobierno del Distrito Federal, en la Ciudad de México, a los veinticuatro días del mes de agosto del año dos mil quince.- EL JEFE DE GOBIERNO DEL DISTRITO FEDERAL, MIGUEL\nÁNGEL MANCERA ESPINOSA.- FIRMA.- LA SECRETARIA DE GOBIERNO, DORA PATRICIA MERCADO CASTRO.-\nFIRMA.- LA SECRETARIA DEL MEDIO AMBIENTE, TANYA MÜLLER GARCÍA.- FIRMA.- EL SECRETARIO DE\nDESARROLLO ECONÓMICO, SALOMÓN CHERTORIVSKI WOLDENBERG.- FIRMA.- EL SECRETARIO DE\nFINANZAS, ÉDGAR ABRAHAM AMADOR ZAMORA.- FIRMA.- EL SECRETARIO DE OBRAS Y SERVICIOS, EDGAR\nOSWALDO TUNGÜÍ RODRÍGUEZ.- FIRMA.\nTRANSITORIOS DEL DECRETO POR EL QUE SE REFORMAN Y ADICIONAN DIVERSAS DISPOSICIONES DE LA\nLEY DE RESIDUOS SÓLIDOS DEL DISTRITO FEDERAL, PUBLICADOS EN LA GACETA OFICIAL DE LA CIUDAD DE\nMÉXICO EL 02 DE NOVIEMBRE DE 2017.\nPRIMERO. El presente Decreto entrará en vigor al día siguiente hábil de su publicación en la Gaceta Oficial de la Ciudad de México.\nSEGUNDO. Publíquese en la Gaceta Oficial de la Ciudad de México, para su conocimiento y en el Diario\nOficial de la Federación para su mayor difusión.\nRecinto de la Asamblea Legislativa del Distrito Federal, a los veinticinco días del mes de julio del año dos mil diecisiete.- POR LA MESA DIRECTIVA, DIP. MAURICIO ALONSO TOLEDO GUTIÉRREZ, PRESIDENTE.- DIP.\nREBECA PERALTA LEÓN, SECRETARIA.- DIP. LUCIANO JIMENO HUANOSTA, SECRETARIO.- (Firma)\nCon fundamento en lo dispuesto por los artículos 122, Apartado A, Base III, de la Constitución Política de los Estados Unidos Mexicanos; Transitorios Primero y Segundo del Decreto por el que se declaran reformadas y derogadas diversas disposiciones de la Constitución Política de los Estados Unidos Mexicanos, en materia de la Reforma Política de la Ciudad de México; 48, 49 y 67, fracción II, del Estatuto de Gobierno del Distrito Federal, para su debida publicación y observancia, expido el presente Decreto Promulgatorio en la Residencia Oficial del Jefe de Gobierno de la Ciudad de México, a los treinta días del mes de octubre\n\ndel año dos mil diecisiete.- EL JEFE DE GOBIERNO DE LA CIUDAD DE MÉXICO, MIGUEL ÁNGEL MANCERA\nESPINOSA.- FIRMA.-\nLA SECRETARIA DE GOBIERNO, DORA PATRICIA MERCADO CASTRO.- FIRMA.- LA SECRETARIA DEL MEDIO\nAMBIENTE, TANYA MÜLLER GARCÍA.- FIRMA.- EL SECRETARIO DE OBRAS Y SERVICIOS, EDGAR OSWALDO\nTUNGÜI RODRÍGUEZ.- FIRMA.\nTRANSITORIOS DEL DECRETO POR EL QUE SE REFORMA EL ARTÍCULO 57 DE LA LEY DE RESIDUOS SÓLIDOS\nDEL DISTRITO FEDERAL, PUBLICADA EN LA GACETA OFICIAL DE LA CIUDAD DE MÉXICO, EL 26 DE ABIRL DE\n2019.\nPRIMERO.- El presente Decreto entrará en vigor al día siguiente de su publicación en la Gaceta Oficial de la Ciudad de México.\nSEGUNDO.- Dentro de un plazo de 90 días naturales, posteriores a la entrada en vigor del presente Decreto, el Gobierno de la Ciudad de México deberá realizar las adecuaciones reglamentarias y normativas con la finalidad de dar cumplimiento al mismo.\nTERCERO.- El Gobierno de la Ciudad de México, las Alcaldías, el Congreso de la Ciudad de México, el\nTribunal Superior de Justicia de la Ciudad de México y demás órganos autónomos, cubrirán las erogaciones que, en su caso se generen con motivo de la entrada en vigor del presente decreto con cargo al presupuesto aprobado por el Congreso de la Ciudad de México para el presente ejercicio fiscal y los subsecuentes.\nPalacio Legislativo del Congreso de la Ciudad de México, a los veintiocho días del mes de marzo del año dos mil diecinueve.- POR LA MESA DIRECTIVA.- DIPUTADO JOSÉ DE JESÚS MARTÍN DEL CAMPO\nCASTAÑEDA, PRESIDENTE.- DIPUTADA ISABELA ROSALES HERRERA, SECRETARIA.- DIPUTADA ANA PATRICIA\nBAEZ GUERRERO.- SECRETARIA.- (\nTRANSITORIOS DEL DECRETO POR EL QUE SE ADICIONAN LAS FRACCIONES IV BIS, VIII BIS, XXIII BIS, XXVI\nBIS, XXVI TER, XXVI QUATER AL ARTÍCULO 3 Y UNA FRACCIÓN XI BIS AL ARTÍCULO 6; ASIMISMO, SE\nREFORMAN LAS FRACCIONES VI DEL ARTÍCULO 3, XI DEL ARTÍCULO 6 Y XI BIS DEL ARTÍCULO 25, TODAS EN\nLA LEY DE RESIDUOS SÓLIDOS DEL DISTRITO FEDERAL, PUBLICADOS EN LA GACETA OFICIAL DE LA CIUDAD\nDE MÉXICO, EL 25 DE JUNIO DE 2019.\n\nPrimero. El presente decreto entrará en vigor al día siguiente de su publicación en la Gaceta Oficial del\nGobierno de la Ciudad de México.\nSegundo. Dentro de los doce meses siguientes a la publicación del presente Decreto, la Secretaría de Medio\nAmbiente de la Ciudad de México, realizará la actualización y armonización de la normatividad aplicable en materia de Residuos Sólidos en la Ciudad de México, así como de los criterios de producción y consumo sustentable de los productos plásticos biodegradables y de los compostables.\nAsimismo, dentro de los 180 días siguientes a la publicación del presente decreto, la Secretaría de Medio\nAmbiente de la Ciudad de México iniciará la elaboración de la Norma Ambiental para la producción y consumo sustentable de los productos plásticos biodegradables y de los compostables.\nTercero. Las modificaciones al Artículo 25 fracción XI BIS surtirán efecto de acuerdo al siguiente calendario.\nLa prohibición de:\nLa comercialización, distribución y entrega de bolsas de plástico al consumidor, en los puntos de venta de bienes o productos, excepto si son compostables. Se excluyen, las bolsas de plástico necesarias por razones de higiene o que prevengan el desperdicio de alimentos siempre y cuando no existan alternativas de plástico compostable, a partir de 2020.\nLa comercialización, distribución y entrega de tenedores, cuchillos, cucharas, palitos mezcladores, platos, popotes o pajitas, bastoncillos para hisopos de algodón, globos y varillas para globos, vasos y sus tapas, charolas para transportar alimentos, aplicadores de tampones, fabricados total o parcialmente de plásticos, diseñados para su desecho después de un solo uso, excepto los que sean compostables, a partir del 1 de enero de 2021.\nLa comercialización, distribución y entrega de productos que contengan microplásticos añadidos intencionalmente, a partir del 1 enero de 2021.\nLa comercialización, distribución y entrega de cápsulas de café de un solo uso fabricadas con materiales plásticos de bajo potencial de aprovechamiento, a partir del 1 enero de 2021.\nCuarto. A partir de la publicación del presente Decreto, la Secretaría de Medio Ambiente de la Ciudad de\nMéxico iniciará, promoverá e implementará programas de cultura ambiental y concientización dirigidos a la ciudadanía sobre el impacto negativo del abuso en el consumo de los plásticos de un solo uso, y las alternativas que existen para evitarlo, incluyendo su reutilización y reciclaje. Para tal efecto el Congreso de\n\nla Ciudad de México, deberá considerar en el Presupuesto de Egresos una partida suficiente para llevar a cabo dichas acciones.\nQuinto. La Secretaría de Educación, Ciencia, Tecnología e Innovación de la Ciudad de México deberá instrumentar dentro de los 180 días posteriores a la publicación del presente decreto, un programa de asesoramiento a los productores de plástico de un solo uso, a efecto de que realicen una reconversión tecnológica, en la que se desarrollen alternativas de plásticos compostables. Para tal efecto se deberá prever en el Presupuesto de Egresos una partida suficiente para llevar a cabo dichas acciones.\nSexto. Se derogan todas aquellas disposiciones que contravengan el contenido del presente decreto.\nPalacio Legislativo del Congreso de la Ciudad de México, a los nueve días del mes de mayo del año dos mil diecinueve. - POR LA MESA DIRECTIVA. - DIPUTADO JOSÉ DE JESÚS MARTÍN DEL CAMPO CASTAÑEDA,\nPRESIDENTE. - DIPUTADA ISABELA ROSALES HERRERA, SECRETARIA. - DIPUTADA ANA PATRICIA BAEZ\nGUERRERO, SECRETARIA. - (Firma)\nCon fundamento en lo dispuesto por los artículos 122, Apartado A, fracción III, de la Constitución Política de los Estados Unidos Mexicanos; 32 apartado C, numeral 1, inciso a) de la Constitución Política de la\nCiudad de México; 2, 3, fracciones XVII y XVIII, 7, 10 fracción II, 12 y 21 párrafo primero de la Ley Orgánica del Poder Ejecutivo y de la Administración Pública de la Ciudad de México; para su debida publicación y observancia, expido el presente Decreto Promulgatorio en la Residencia Oficial de la Jefatura de Gobierno de la Ciudad de México, a los veinte días del mes de mayo del año dos mil diecinueve.- LA JEFA DE\nGOBIERNO DE LA CIUDAD DE MÉXICO, DRA. CLAUDIA SHEINBAUM PARDO.- FIRMA.- LA SECRETARIA DEL\nMEDIO AMBIENTE, MARINA ROBLES GARCÍA.- FIRMA.\nTRANSITORIOS DEL DECRETO POR EL QUE SE ADICIONA UN PÁRRAFO A LA FRACCIÓN X DEL ARTÍCULO 6 DE\nLA LEY DE RESIDUOS SÓLIDOS DEL DISTRITO FEDERAL, PUBLICADO EN LA GACETA OFICIAL DE LA CIUDAD\nDE MÉXICO EL 18 DE ABRIL DE 2022\nPrimero. - Remítase a la persona titular de la Jefatura de Gobierno para su promulgación y publicación en la Gaceta Oficial de la Ciudad de México.\nSegundo. - El presente Decreto entrará en vigor al día siguiente de su publicación en la Gaceta Oficial de la\nCiudad de México.\n\nPalacio Legislativo del Congreso de la Ciudad de México, a los siete días del mes de abril del año dos mil veintidós. POR LA MESA DIRECTIVA, DIPUTADO HÉCTOR DIAZ POLANCO, PRESIDENTE. - DIPUTADA\nMARCELA FUENTE CASTILLO, SECRETARIA. - DIPUTADA FRIDA JIMENA GUILLÉN ORTIZ, SECRETARIA. -\n(Firmas)\nCon fundamento en lo dispuesto por los artículos 122, apartado A, fracción III de la Constitución Política de los Estados Unidos Mexicanos; 32, apartado C, numeral 1, inciso a) de la Constitución Política de la Ciudad de México; 2 párrafo segundo, 3 fracciones XVII y XVIII, 7 párrafo primero, 10 fracción II, 12 y 21 párrafo primero de la Ley Orgánica del Poder Ejecutivo y de la Administración Pública de la Ciudad de México; para su debida publicación y observancia, expido el presente Decreto Promulgatorio en la Residencia Oficial de la Jefatura de Gobierno de la Ciudad de México, a los dieciocho días del mes de abril del año dos mil veintidós.- LA JEFA DE GOBIERNO DE LA CIUDAD DE MÉXICO, DRA. CLAUDIA SHEINBAUM PARDO.- FIRMA.-\nEL SECRETARIO DE GOBIERNO, MARTÍ BATRES GUADARRAMA.- FIRMA.- SECRETARIA DEL MEDIO AMBIENTE,\nMARINA ROBLES GARCÍA.- FIRMA.\nTRANSITORIOS DEL DECRETO POR EL QUE SE ADICIONA UNA FRACCIÓN VIII BIS AL ARTÍCULO 42 DE LA LEY\nORGÁNICA DE ALCALDÍAS DE LA CIUDAD DE MÉXICO SE REFORMA LA FRACCIÓN XIII DEL ARTÍCULO 3º; SE\nREFORMA EL PRIMER PÁRRAFO Y SE ADICIONA UN TERCER PÁRRAFO AL ARTÍCULO 34, AMBOS DE LA LEY\nDE RESIDUOS SÓLIDOS DEL DISTRITO FEDERAL, PUBLICADO EN LA GACETA OFICIAL DE LA CIUDAD DE\nMÉXICO, EL 21 DE OCTUBRE DE 2022.\nPRIMERO. Remítase a la persona titular de la Jefatura de Gobierno, para su promulgación y publicación en la Gaceta Oficial de la Ciudad de México.\nSEGUNDO. El presente Decreto entrará en vigor, al día siguiente de su publicación en la Gaceta Oficial de la Ciudad de México.\nPalacio Legislativo del Congreso de la Ciudad de México, a los veintisiete días del mes de septiembre del año dos mil veintidós. POR LA MESA DIRECTIVA DIPUTADO FAUSTO MANUEL ZAMORANO ESPARZA,\nPRESIDENTE.- DIPUTADA MARCELA FUENTE CASTILLO, SECRETARIA.- DIPUTADA MARIA GABRIELA SALIDO\nMAGOS, SECRETARIA.- (Firmas)\nCon fundamento en lo dispuesto por los artículos 122, apartado A, fracción III de la Constitución Política de los Estados Unidos Mexicanos; 32, apartado C, numeral 1, inciso a) de la Constitución Política de la Ciudad de México; 2 párrafo segundo, 3 fracciones XVII y XVIII, 7 párrafo primero, 10 fracción II, 12 y 21 párrafo primero de la Ley Orgánica del Poder Ejecutivo y de la Administración Pública de la Ciudad de México; para\n\nsu debida publicación y observancia, expido el presente Decreto Promulgatorio en la Residencia Oficial de la Jefatura de Gobierno de la Ciudad de México, a los veinte días del mes octubre del año dos mil veintidós.-\nLA JEFA DE GOBIERNO DE LA CIUDAD DE MÉXICO, DRA. CLAUDIA SHEINBAUM PARDO.- FIRMA.- EL\nSECRETARIO DE GOBIERNO, MARTÍ BATRES GUADARRAMA.- FIRMA.- LA SECRETARIA DEL MEDIO AMBIENTE,\nMARINA ROBLES GARCÍA.- FIRMA.- EL SECRETARIO DE OBRAS Y SERVICIOS, JESÚS ANTONIO ESTEVA\nMEDINA.- FIRMA.\nTRANSITORIOS DEL DECRETO POR EL QUE SE MODIFICAN LAS FRACCIONES XVII Y XVIII DEL ARTÍCULO 6;\nLA FRACCIÓN XIX Y LOS PÁRRAFOS SEGUNDO Y TERCERO DEL ARTÍCULO 11; EL ARTÍCULO 33 BIS; Y SE\nADICIONA UNA FRACCIÓN XIX AL ARTÍCULO 6; ASÍ COMO UNA FRACCIÓN XIX BIS AL ARTÍCULO 11, TODOS\nDE LA LEY DE RESIDUOS SÓLIDOS DEL DISTRITO FEDERAL, PUBLICADO EN LA GACETA OFICIAL DE LA CIUDAD\nDE MÉXICO, EL 21 DE OCTUBRE DE 2022.\nPRIMERO. Remítase a la persona titular de la Jefatura de Gobierno para su promulgación y publicación en la Gaceta Oficial de la Ciudad de México.\nSEGUNDO. El presente Decreto entrará en vigor al siguiente día de su publicación en la Gaceta Oficial de la\nCiudad de México.\nTERCERO. El Gobierno de la Ciudad de México emitirá los lineamientos necesarios para instrumentar el presente Decreto en un plazo no mayor a 120 días naturales. Dado a los 30 días del mes de agosto de 2022 y firmado para constancia y conformidad de los integrantes de la Comisión de Preservación del Medio\nAmbiente, Cambio Climático y Protección Ecológica.\nPalacio Legislativo del Congreso de la Ciudad de México, a los veintiséis días del mes de septiembre del año dos mil veintidós. POR LA MESA DIRECTIVA DIPUTADO FAUSTO MANUEL ZAMORANO ESPARZA,\nPRESIDENTE.- DIPUTADA MARCELA FUENTE CASTILLO, SECRETARIA.- DIPUTADA MARIA GABRIELA SALIDO\nMAGOS, SECRETARIA.- (Firmas)\nCon fundamento en lo dispuesto por los artículos 122, apartado A, fracción III de la Constitución Política de los Estados Unidos Mexicanos; 32, apartado C, numeral 1, inciso a) de la Constitución Política de la Ciudad de México; 2 párrafo segundo, 3 fracciones XVII y XVIII, 7 párrafo primero, 10 fracción II, 12 y 21 párrafo primero de la Ley Orgánica del Poder Ejecutivo y de la Administración Pública de la Ciudad de México; para su debida publicación y observancia, expido el presente Decreto Promulgatorio en la Residencia Oficial de la Jefatura de Gobierno de la Ciudad de México, a los veinte días del mes octubre del año dos mil veintidós.-\nLA JEFA DE GOBIERNO DE LA CIUDAD DE MÉXICO, DRA. CLAUDIA SHEINBAUM PARDO.- FIRMA.- EL\n\nSECRETARIO DE GOBIERNO, MARTÍ BATRES GUADARRAMA.- FIRMA.- LA SECRETARIA DEL MEDIO AMBIENTE,\nMARINA ROBLES GARCÍA.- FIRMA.- EL SECRETARIO DE OBRAS Y SERVICIOS, JESÚS ANTONIO ESTEVA\nMEDINA.- FIRMA.\nTRANSITORIOS DEL DECRETO POR EL QUE SE MODIFICA EL ARTÍCULO 1; SE MODIFICA LA FRACCIÓN IV Y SE\nADICIONAN LAS FRACCIONES VII BIS, XXIII BIS, XXIII TER, XXIII QUATER, XXV BIS, XXV TER, XXV QUATER,\nXXXIII BIS Y XLII BIS DEL ARTÍCULO 3; SE MODIFICA LA FRACCIÓN IV Y SE ADICIONAN LAS FRACCIONES\nVII BIS, VII TER, VIII BIS DEL ARTÍCULO 6; SE ADICIONA LA FRACCIÓN VIII BIS DEL ARTÍCULO 7; SE MODIFICA\nEL ARTÍCULO 24 Y SE ADICIONA UNA FRACCIÓN III BIS; SE MODIFICA EL ARTÍCULO 26; SE ADICIONAN LOS\nARTÍCULO 26 TER Y 32 BIS; SE MODIFICA EL ARTÍCULO 42 BIS Y SE MODIFICA LA FRACCIÓN\nIV DEL ARTÍCULO 69; TODOS DE LA LEY DE RESIDUOS SÓLIDOS DEL DISTRITO FEDERAL, EL 03 DE ABRIL DE\n2023.\nPRIMERO. Remítase a la persona titular de la Jefatura de Gobierno para su promulgación y publicación en la Gaceta Oficial de la Ciudad de México.\nSEGUNDO. El presente Decreto entrará en vigor al siguiente día de su publicación en la Gaceta Oficial de la\nCiudad de México.\nTERCERO. La Secretaría de Obras y Servicios de la Ciudad de México tendrá un plazo de 90 días, contados a partir de la entrada en vigor del presente Decreto, para actualizar y armonizar la normatividad aplicable y el tabulador de precios para especificar los conceptos que deberán incorporar materiales reciclados y eliminar aquellos que contemplen el uso de materiales de minas.\nCUARTO. La Secretaría del Medio Ambiente de la Ciudad de México tendrá un plazo de 90 días, contados a partir de la entrada en vigor del presente Decreto, para actualizar y armonizar la normatividad aplicable en materia de Residuos Sólidos en la Ciudad de México.\nQUINTO. La Secretaría del Medio Ambiente de la Ciudad de México tendrá un plazo de 90 días, contados a partir de la entrada en vigor del presente Decreto, para establecer y aplicar las bases para la implementación de la plataforma digital de trazabilidad para la gestión integral de los residuos de la construcción y demolición. La plataforma será supervisada y vigilada por la misma.\n\nSEXTO. La Plataforma digital de trazabilidad deberá garantizar la trazabilidad en todas las fases del proceso de gestión de los residuos de manejo especial. La plataforma deberá contar con la información necesaria y en su caso información adicional.\nPalacio Legislativo del Congreso de la Ciudad de México, a los dieciséis días del mes de marzo del año dos mil veintitrés.- POR LA MESA DIRECTIVA.- DIPUTADO FAUSTO MANUEL ZAMORANO ESPARZA, PRESIDENTE.-\nDIPUTADA MARCELA FUENTE CASTILLO, SECRETARIA.- DIPUTADA MARIA GABRIELA SALIDO MAGOS,\nSECRETARIA.- (Firmas)\nCon fundamento en lo dispuesto por los artículos 122, apartado A, fracción III de la Constitución Política de los Estados Unidos Mexicanos; 32, apartado C, numeral 1, inciso a) de la Constitución Política de la Ciudad de México; 2 párrafo segundo, 3 fracciones XVII y XVIII, 7 párrafo primero, 10 fracción II, 12 y 21 párrafo primero de la Ley Orgánica del Poder Ejecutivo y de la Administración Pública de la Ciudad de México; para su debida publicación y observancia, expido el presente Decreto Promulgatorio en la Residencia Oficial de la Jefatura de Gobierno de la Ciudad de México, a los treinta y un días del mes de marzo del año dos mil veintitrés.- LA JEFA DE GOBIERNO DE LA CIUDAD DE MÉXICO, DRA. CLAUDIA SHEINBAUM PARDO.- FIRMA.-\nEL SECRETARIO DE GOBIERNO, MARTÍ BATRES GUADARRAMA.- FIRMA.- LA SECRETARIA DEL MEDIO\nAMBIENTE, MARINA ROBLES GARCÍA.- FIRMA.- EL SECRETARIO DE OBRAS Y SERVICIOS, JESÚS ANTONIO\nESTEVA MEDINA.- FIRMA.",
  "ordenamiento": "Marco Jurídico",
  "jurisdiccion": "CIUDAD DE MEXICO",
  "fuente_oficial": "Congreso de la Ciudad de México",
  "status": "Vigente",
  "Fecha de Publicación": "12-04-2023",
  "Fecha de Última Reforma": "03 de abril de 2023",
  "numero_paginas": 53,
  "es_escaneado": false,
  "tiene_tablas": true,
  "url": "https://www.congresocdmx.gob.mx/archivo-5e9cfdc1fa63fdf6120fd92f434a3e407d58af30.pdf",
  "materia": [
    "ambiental"
  ]
}