{
  "titulo": "Ley DE LOS DERECHOS DE NIÑAS, NIÑOS y ADOLESCENTES DE LA CIUDAD DE MÉXICO",
  "Contenido": "PUBLICADO EN LA GACETA OFICIAL DE LA CIUDAD DE MÉXICO\nEL 12 DE NOVIEMBRE DE 2015\nTEXTO VIGENTE\nÚLTIMA REFORMA PUBLICADA EN LA G.O.C.D.M.X.\nEL 19 DE JULIO DE 2024\nADMINISTRACIÓN PÚBLICA DEL DISTRITO FEDERAL\nJEFATURA DE GOBIERNO\nDECRETO POR EL QUE SE EXPIDE LA LEY DE LOS DERECHOS DE NIÑAS, NIÑOS Y ADOLESCENTES DE LA\nCIUDAD DE MÉXICO\n(Al margen superior un escudo que dice: CIUDAD DE MÉXICO. Decidiendo Juntos)\nMIGUEL ÁNGEL MANCERA ESPINOSA, Jefe de Gobierno del Distrito Federal, a sus habitantes sabed:\nQue la H. Asamblea Legislativa del Distrito Federal, VI Legislatura se ha servido dirigirme el siguiente\nD E C R E T O\n(Al margen superior izquierdo el Escudo Nacional que dice: ESTADOS UNIDOS MEXICANOS. ASAMBLEA\nLEGISLATIVA DEL DISTRITO FEDERAL. VI LEGISLATURA)\nASAMBLEA LEGISLATIVA DEL DISTRITO FEDERAL\nVI LEGISLATURA.\nDECRETO POR EL QUE SE EXPIDE LA LEY DE LOS DERECHOS DE NIÑAS, NIÑOS Y ADOLESCENTES DE LA\nCIUDAD DE MÉXICO\nARTÍCULO ÚNICO. Se expide la Ley de los Derechos de Niñas, Niños y Adolescentes de la Ciudad de México, para quedar como sigue:\n\nLEY DE LOS DERECHOS DE NIÑAS, NIÑOS Y\nADOLESCENTES DE LA CIUDAD DE MÉXICO\nTÍTULO PRIMERO\nDISPOSICIONES GENERALES\nCAPÍTULO ÚNICO\nOBJETO Y ÁMBITO DE APLICACIÓN DE LA LEY\nArtículo 1. La presente ley es de orden público, interés social y de observancia general en la Ciudad de\nMéxico. Todas las autoridades locales en el ámbito de sus competencias están obligadas a promover, respetar, proteger y garantizar los derechos humanos de las niñas, niños y adolescentes que habitan y/o transiten en la Ciudad de México. En consecuencia deberá prevenir, investigar sancionar y reparar las violaciones a sus derechos humanos en los términos que establece la ley.\nEsta ley tiene por objeto:\nI. Reconocer a las niñas, niños y adolescentes que habitan o transitan en la Ciudad de México como sujetos de derechos humanos, de conformidad con lo dispuesto en la Constitución Política de los Estados Unidos Mexicanos, la Constitución Política de la Ciudad de México, los tratados e instrumentos internacionales de los que el Estado mexicano es parte y las normas generales y locales aplicables;\nFracción modificada y publicada en la GOCDMX el 29 de abril de 2024\nII. Establecer las políticas, parámetros, lineamientos y configurar el marco legal que permita a las autoridades garantizar el pleno goce y ejercicio de los derechos de niñas, niños y adolescentes que habitan y transitan en la Ciudad de México;\nFracción modificada y publicada en la GOCDMX el 29 de abril de 2024\nIII. Crear y regular la integración, organización y funcionamiento del Sistema de Protección\nIntegral de los Derechos de Niñas, Niños y Adolescentes de la Ciudad de México, a efecto de garantizar la protección, prevención y restitución integral de los derechos humanos de niñas, niños y adolescentes;\nFracción modificada y publicada en la GOCDMX el 29 de abril de 2024\n\nIV. Normar y orientar la política pública con un enfoque de derechos humanos en la Ciudad de\nMéxico para niñas, niños y adolescentes, así como las facultades, competencias y bases de coordinación y colaboración entre las autoridades de la Ciudad de México y los órganos político administrativos; así como la actuación de los órganos Legislativo y Judicial, y de los órganos públicos autónomos;\nV. Garantizar que las personas encargadas de la atención directa de niñas, niños y adolescentes, en el sector público y privado, así como aquellos encargados de la administración o de la implementación de políticas públicas en la materia, estén debidamente capacitados y sensibilizados en temas de derechos humanos de niñas, niños y adolescentes;\nFracción modificada y publicada en la GOCDMX el 29 de abril de 2024\nVI. Regular la participación de los sectores privado y social en las acciones tendentes a garantizar la protección y el ejercicio de los derechos de niñas, niños y adolescentes en la Ciudad de México y prevenir su vulneración y violación, así como para promover la crianza positiva, e\nFracción modificada y publicada en la GOCDMX el 29 de abril de 2024\nVII. Impulsar y consolidar la atención integral y la generación de oportunidades de manera igualitaria para las niñas, niños y adolescentes.\nFracción modificada y publicada en la GOCDMX el 29 de abril de 2024\nArtículo 2. Para garantizar la protección de los derechos humanos de niñas, niños y adolescentes en la\nCiudad de México, las autoridades realizarán las acciones y tomarán medidas, de conformidad con los principios establecidos en la presente Ley. Para tal efecto, deberán:\nI. Garantizar su derecho a la vida, la paz, a la supervivencia y al desarrollo integral;\nII. Garantizar un enfoque integral, transversal y con perspectiva de derechos humanos, género y niñez, en el diseño y la instrumentación de políticas y programas de gobierno;\nIII. Promover la participación de todos los sectores de la sociedad, tomando en cuenta la opinión de niñas, niños y adolescentes considerando los aspectos culturales, éticos, afectivos, educativos y de salud, en todos aquellos asuntos de su incumbencia, de acuerdo a su edad, desarrollo evolutivo, cognoscitivo y madurez;\n\nIV. Implementar los mecanismos para el diseño, ejecución, seguimiento y evaluación de políticas públicas, programas sociales y gubernamentales, legislación y compromisos derivados de las normas constitucionales y de los tratados internacionales celebrados por el Estado mexicano de manera transparente y accesible;\nV. Establecer mecanismos para prevenir el abuso y maltrato, o explotación laboral o sexual; y\nVI. Garantizar la implementación de mecanismos de comunicación, para reportar casos de maltrato hacia niñas, niños y adolescentes en la Ciudad de México.\nReforma publicada en la GOCDMX el 03 de marzo de 2023\nLas autoridades administrativas, así como de los órganos político administrativos y el Congreso, todos de la Ciudad de México, en el ámbito de sus respectivas competencias, deberán incluir en sus proyectos de presupuesto la asignación de recursos que permita dar cumplimiento a las acciones ordenadas por la presente Ley.\nLas niñas, niños y adolescentes en orfandad por feminicidio tendrán acceso prioritario a los programas sociales que otorga el Gobierno de la Ciudad de México y que por su naturaleza puedan acceder.\nPárrafo adicionado y publicado en la GOCDMX el 29 de abril de 2024\nEl DIF-CDMX, con apoyo de la Fiscalía General de Justicia de la Ciudad de México, llevarán un registro de las niñas, niños y adolescentes en esta condición para garantizar con las autoridades responsables de los programas sociales su acceso.\nPárrafo adicionado y publicado en la GOCDMX el 29 de abril de 2024\nEl DIF-CDMX enviará en coordinación con las autoridades responsables de los programas sociales, un informe al Congreso de la Ciudad de México en febrero de cada año sobre los resultados de las niñas, niños y adolescentes en estado de orfandad por feminicidio.\nPárrafo adicionado y publicado en la GOCDMX el 29 de abril de 2024\nArtículo 3. Las políticas públicas que implementen las autoridades de la Ciudad de México, en el ámbito de sus respectivas competencias, deben garantizar el ejercicio, respeto, protección, promoción y reparación de los derechos humanos de niñas, niños y adolescentes privilegiando su interés superior.\n\nLa protección deberá garantizar la seguridad sexual de las víctimas y potenciales víctimas de cualquier tipo de violencia sexual, por lo cual, las niñas, niños y adolescentes tendrán para dicha seguridad, conocer y ubicar a las personas que hayan sido sentenciadas por delitos vinculados con esa violencia.\nA través de la adopción de las medidas estructurales, legales, administrativas y presupuestales conducentes, dichas autoridades deben buscar contribuir al desarrollo integral de niñas, niños y adolescentes.\nLos sectores social y privado, concurrirán con las autoridades locales en el cumplimiento del objeto de esta\nLey, para el diseño, ejecución, seguimiento y evaluación de políticas públicas.\nArtículo 4. Para los efectos de esta Ley, se entenderá por:\nI. Accesibilidad: Medidas que debe cumplir el entorno físico, el transporte, la información y las comunicaciones, incluidos los sistemas y las tecnologías y otros servicios e instalaciones abiertos al público o de uso público para que las niñas, niños y adolescentes con discapacidad puedan participar plenamente en todos los aspectos de la vida en igualdad de condiciones.\nII. Acciones Afirmativas: Acciones de carácter temporal, de políticas y prácticas de índole legislativa, administrativa y jurisdiccional que son correctivas, compensatorias y de promoción, encaminadas a acelerar la igualdad sustantiva entre niñas, niños y adolescentes;\nIII. Abandonado: Se considera abandonado a la niña, niño o adolescente que se encuentre en situación de desamparo por quienes conforme a la Ley estén obligados a su custodia, protección y cuidado y cuyo origen se conoce;\nIV. Abandono: La situación de desamparo que vive una niña, niño o adolescente cuando los progenitores, tutores o responsables de su cuidado dejan de proporcionales los medios básicos de subsistencia y los cuidados necesarios para su desarrollo integral sin perjuicio de lo que prevengan otras leyes;\nV. Acciones y mecanismos de Participación: Aquéllas que deben realizarse por las autoridades o servidores públicos de la Ciudad de México, familia y sociedad a fin de que las niñas, niños y adolescentes estén informados, se formen una opinión propia, que la expresen y puedan participar y organizarse en torno a sus intereses;\n\nVI. Acciones de Prevención: Aquéllas que deben realizarse por las autoridades o servidores públicos de la Ciudad de México, familia y sociedad a fin de evitar el deterioro de las condiciones de vida de las niñas, niños y adolescentes, así como las situaciones que pongan en riesgo su supervivencia y desarrollo, siendo importante la prevención de cualquier tipo de victimización de carácter sexual que pudiese presentarse por personas sentenciadas por tales conductas delictivas;\nVII. Acciones de Protección: Aquéllas que deben realizarse por las autoridades o servidores públicos de la Ciudad de México, familia y sociedad a fin de garantizar la vida, la paz, la sobrevivencia, bienestar y desarrollo integral de las niñas, niños y adolescentes para dar satisfacción a sus derechos;\nVIII. Acciones de Provisión: Aquéllas que deben realizarse por las autoridades o servidores públicos de la Ciudad de México, familia y sociedad a fin de garantizar la sobrevivencia, bienestar y desarrollo pleno de las niñas, niños y adolescentes para dar satisfacción a sus derechos;\nIX. Acogimiento o cuidados alternativos: es la institución o figura jurídica mediante la cual una persona asume, de manera temporal, el cuidado y atención integral de un niño, niña o adolescente en situación de desamparo, en estricto respeto a sus derechos;\nX. Acogimiento Residencial: Aquél brindado por Centros de Asistencia Social como una medida especial de protección de carácter subsidiario, que será de último recurso y por el menor tiempo posible, priorizando las opciones de cuidado en un entorno familiar;\nXI. Ajustes Razonables: Las modificaciones y adaptaciones necesarias y adecuadas que no impongan una carga desproporcionada o indebida, cuando se requieran en un caso particular, para garantizar a niñas, niños y adolescentes con discapacidad el goce o ejercicio, en igualdad de condiciones con las demás personas, de todos los derechos humanos y libertades fundamentales;\nXII. Atención integral: Conjunto de acciones que deben realizar autoridades o servidores públicos de la Ciudad de México, familia y sociedad a favor de las niñas, niños y adolescentes, tendentes a satisfacer sus necesidades básicas, propiciar su pleno desarrollo y garantizar sus derechos;\nXIII. Autoridades: Las autoridades y servidores públicos de los órganos ejecutivo, legislativo y judicial de la Ciudad de México, así como de los órganos autónomos;\n\nXIII Bis. Castigo corporal o físico: Es todo aquel acto cometido en contra de niñas, niños y adolescentes en el que se utilice la fuerza física, incluyendo golpes con la mano o con algún objeto, empujones, pellizcos, mordidas, tirones de cabello o de las orejas, obligar a sostener posturas incómodas, quemaduras, ingesta de alimentos hirviendo u otros productos o cualquier otro acto que tenga como objeto causar dolor o malestar, aunque sea leve;\nXIII Ter. Castigo humillante: Es cualquier trato ofensivo, denigrante, desvalorizador, estigmatizante, ridiculizador y de menosprecio, y cualquier acto que tenga como objetivo provocar dolor, amenaza, molestia o humillación cometido en contra de niñas, niños y adolescentes;\nXIV. Centro de Asistencia Social: El establecimiento, lugar o espacio de cuidado alternativo o acogimiento residencial para niñas, niños y adolescentes sin cuidado parental o familiar que brindan instituciones públicas, privadas y asociaciones;\nXV. Certificado de Idoneidad: Documento expedido por la Procuraduría de Protección, previa opinión positiva del Comité Técnico de Adopción en el que consta que la persona solicitante es apta para adoptar;\nXVI. Código Civil: Código Civil para el Distrito Federal;\nXVII. Código de Procedimientos: Código de Procedimientos Civiles para el Distrito Federal;\nXVIII. Comité Técnico de Adopción: Órgano Colegiado de la Procuraduría de Protección encargado de evaluar a los solicitantes de adopción y, en su caso opinar favorablemente a la\nProcuraduría de Protección para que ésta emita el Certificado de Idoneidad correspondiente, así como intervenir en los procedimientos de adopción de niñas, niños y adolescentes de conformidad con lo establecido en esta Ley y su Reglamento;\nXVIII Bis. Crianza positiva: Conjunto de prácticas de cuidado, protección, formación y guía que benefician el desarrollo, bienestar, crecimiento saludable y armonioso, y autonomía progresiva de las niñas, niños y adolescentes, tomando en cuenta su edad, facultades, características, cualidades, intereses, motivaciones, límites y aspiraciones, sin recurrir a castigos corporales o físicos ni castigos humillantes, salvaguardando el interés superior con un enfoque de respeto a sus derechos humanos;\n\nFracción adicionada y publicada en la GOCDMX el 29 de abril de 2024\nXIX. Órganos político administrativos: Las 16 Alcaldías de la Ciudad de México;\nXX. DIF-CDMX: Sistema para el Desarrollo Integral de la Familia de la Ciudad de México;\nXXI. Diseño Universal: El diseño de productos, entornos, programas y servicios que puedan utilizar niñas, niños y adolescentes, en la mayor medida posible, sin necesidad de adaptación ni diseño especializado. El diseño universal no excluirá las ayudas técnicas para niñas, niños y adolescentes con discapacidad cuando se necesiten;\nXXII. Discriminación Múltiple: La situación de vulnerabilidad específica en la que se encuentran niñas, niños y adolescentes que, al ser discriminados por tener simultáneamente diversas condiciones, ven anulados o menoscabados sus derechos;\nXXIII. EVALUA CDMX: Consejo de Evaluación del Desarrollo Social de la Ciudad de México;\nXXIV. Expósito: Aquella niña, niño o adolescente que es colocado en una situación de desamparo por quienes conforme a la Ley estén obligados a su custodia, protección y cuidado y no pueda determinarse su origen;\nXXV. Familia de Acogida: Aquélla que cuente con la certificación de la autoridad competente y que brinde cuidado, protección, crianza positiva y la promoción del bienestar social de niñas, niños y adolescentes por un tiempo limitado hasta que se pueda asegurar una opción permanente con la familia de origen, extensa o adoptiva;\nXXVI. Familia de Origen: Aquélla compuesta por titulares de la patria potestad, tutela, guarda o custodia, respecto de quienes niñas, niños y adolescentes tienen parentesco ascendente hasta segundo grado;\nXXVII. Familia Extensa o Ampliada: Aquélla compuesta por los ascendientes de niñas, niños y adolescentes en línea recta sin limitación de grado, y los colaterales hasta el cuarto grado;\nXXVIII. Igualdad Sustantiva: El acceso al mismo trato y a las mismas oportunidades para el reconocimiento, goce o ejercicio de los derechos humanos;\n\nXXIX. Informe de adoptabilidad: Documento de carácter técnico emitido por el DIF CDMX a través de la Procuraduría de Protección, que contiene la información sobre la identidad, medio social, evolución personal y familiar en el que consta la adoptabilidad de niñas, niños y adolescentes;\nXXX. Interés superior: Interés superior de la niña, el niño, la o el adolescente;\nXXXI. Ley: Ley de los Derechos de Niñas, Niños y Adolescentes de la Ciudad de México;\nXXXII. Ley de Cuidados Alternativos: Ley de Cuidados Alternativos de Niñas, Niños y Adolescentes en el Distrito Federal;\nXXXIII. Ley General: Ley General de los Derechos de Niñas, Niños y Adolescentes;\nXXXIV. Medidas de protección especial: Conjunto de acciones, programas y actividades institucionales orientadas a reconocer, proteger, garantizar y resguardar los derechos humanos de las niñas, niños y adolescentes conforme a su Interés superior, dirigidas a la prevención, atención, asistencia, restitución y reparación, con la finalidad de salvaguardar el goce y ejercicio de sus derechos;\nXXXV. Órgano Jurisdiccional: Los juzgados o tribunales de la Ciudad de México;\nXXXV Bis. Orfandad: La situación de desamparo en que se encuentra una niña, niño o adolescente cuando la madre, padre, o ambos, han fallecido;\nFracción añadida y publicada en la GOCDMX el 10 de octubre de 2023\nXXXVI. Procuraduría de Protección: La Procuraduría de Protección de Derechos de Niñas, Niños y\nAdolescentes de la Ciudad de México;\nXXXVII. Procuraduría de Protección Federal: Procuraduría Federal de Protección de Niñas, Niños y Adolescentes;\nXXXVIII. Programa: El Programa de Protección Integral de Niñas, Niños y Adolescentes de la\nCiudad de México;\nXXXIX. Programa Nacional: El Programa Nacional de Protección de Niñas, Niños y Adolescentes;\n\nXL.Protección Integral: Conjunto de mecanismos y acciones compensatorias y restitutivas que se ejecuten en la Ciudad de México por los tres órdenes de gobierno, así como la familia y sociedad, con el fin de garantizar de manera universal y especializada en cada una de las materias relacionadas con los derechos humanos de niñas, niños y adolescentes de conformidad con los principios rectores de esta Ley, la Ley General, la Constitución Política de los Estados Unidos\nMexicanos y los tratados internacionales de los que el Estado mexicano forma parte;\nXLI. Reglamento: Reglamento de la Ley de los Derechos de Niñas, Niños y Adolescentes de la\nCiudad de México;\nXLII. Representación Coadyuvante: El acompañamiento y defensa de niñas, niños y adolescentes en los procedimientos jurisdiccionales y administrativos que, de manera oficiosa, quedará a cargo de la Procuraduría de Protección, sin perjuicio de la intervención que corresponda al\nMinisterio Público;\nXLIII. Representación Originaria: La representación de niñas, niños y adolescentes a cargo de quienes ejerzan la patria potestad o tutela, de conformidad con lo dispuesto en esta Ley y demás disposiciones aplicables;\nXLIV. Representación en Suplencia: La representación de niñas, niños y adolescentes a cargo de la Procuraduría de Protección, conforme a sus respectivos ámbitos de competencia, sin perjuicio de la intervención que corresponda al Ministerio Público;\nXLV. Sistema de Protección: Sistema de Protección Integral de los Derechos de las Niñas, Niños y Adolescentes de la Ciudad de México;\nXLVI. Sistema de Protección Delegacional: Sistema de Protección Integral de los Derechos de\nNiñas, Niños y Adolescentes en cada una de los 16 órganos políticos administrativos;\nXLVII. Sistema Nacional DIF: El Sistema Nacional para el Desarrollo Integral de la Familia;\nXLVIII. Sistema Nacional de Protección: El Sistema Nacional de Protección Integral de Niñas,\nNiños y Adolescentes;\nXLIX. Violencia Física: Todo acto de agresión que cause daño a la integridad física de las niñas, niños y adolescentes; y,\n\nL. Violencia Psicoemocional: Los actos u omisiones cuyas formas de expresión pueden ser silencios, prohibiciones, coacciones, condicionamientos, intimidaciones, amenazas, insultos, actitudes de descuido, devaluatorias o de abandono que provoquen en la niña, niño o adolescente daño en cualquiera de sus esferas cognoscitiva, conductual, afectiva y social.\nArtículo 5. Niñas, niños y adolescentes gozarán de los derechos que reconoce esta Ley, sin detrimento de los derechos, responsabilidades y obligaciones de los padres y/o tutores que para ellos contiene la\nConvención sobre los Derechos del Niño, la presente Ley y demás disposiciones jurídicas aplicables, por lo que se reconoce la obligación que tienen las autoridades del Distrito Federal de promover, respetar, proteger y garantizar sus derechos, atendiendo a los principios pro persona, interés superior del niño y de autonomía progresiva en el ejercicio de los mismos, tomándose en cuenta el grado de desarrollo cognoscitivo y evolutivo de sus facultades.\nSon niñas y niños las personas menores a doce años de edad. Se encuentran en primera infancia las niñas y niños menores de seis años.\nSon adolescentes las personas que se encuentran entre los doce años cumplidos y menores de dieciocho años de edad.\nCuando exista la duda de si se trata de una persona menor de dieciocho años de edad, se presumirá que es adolescente, hasta que se pruebe fehacientemente lo contrario. Cuando exista la duda de si se trata de una persona mayor o menor de doce años, se presumirá que es niña o niño.\nArtículo 6. Son principios rectores de esta ley:\nI. El interés superior;\nII. La universalidad, interdependencia, indivisibilidad, complementariedad, integralidad, progresividad y no regresividad de los derechos de niñas, niños y adolescentes;\nIII. La igualdad sustantiva;\nIV. La no discriminación;\nV. La inclusión;\n\nVI. El derecho a la vida, a la paz, a la supervivencia y al desarrollo integral;\nVII. La participación;\nVIII. La interculturalidad;\nIX. La corresponsabilidad de los miembros de la familia, la sociedad y las autoridades;\nX. La transversalidad en la legislación, políticas públicas, actividades administrativas, económicas y culturales;\nXI. La autonomía progresiva;\nXII. El principio pro persona;\nXIII. El acceso a una vida libre de violencia;\nXIV. La accesibilidad, y\nXV. La debida diligencia estricta.\nArtículo 7. El interés superior de la niña, niño y adolescente, es el derecho sustantivo que exige adoptar un enfoque proactivo basado en los derechos humanos, en el que colaboren todos los responsables de garantizar el bienestar, físico, psicológico, cultural y espiritual de manera integral de niñas, niños y adolescentes, así como reconocer su dignidad humana. Asimismo, debe ser considerado como principio interpretativo fundamental y como una norma de procedimiento siempre que se tenga que tomar una decisión que afecte a una niña, niño o adolescente en concreto.\nDicho principio debe aplicarse para efectos de la seguridad más amplia de niñas, niños y adolescentes, en especial la que se refiere a la violencia sexual, de la que pueden ser víctimas o potenciales víctimas, por lo que se establecerá un capítulo especial en el Registro Público de Personas Agresoras Sexuales, que prevén los artículos 69 Ter y 69 Quater del Código Penal para el Distrito Federal, en concordancia a lo establecido en la Ley de Acceso de las Mujeres a una Vida libre de violencia de la Ciudad de México.\n\nArtículo 8. Toda autoridad en la Ciudad de México, por el principio del interés superior, debe en todo caso, atender de manera prioritaria de los derechos humanos de niñas, niños y adolescentes, respecto de cualquier otro derecho en conflicto. Lo anterior, para efectos de la ponderación de dichos derechos.\nArtículo 9. Las autoridades en la Ciudad de México y de los órganos político administrativos, en el ámbito de sus respectivas competencias, impulsarán la cultura de respeto, promoción y protección de derechos de niñas, niños y adolescentes, basada en los principios rectores de esta Ley y los establecidos en los tratados internacionales.\nArtículo 10. A falta de disposición expresa en la Constitución Política de los Estados Unidos Mexicanos, en los tratados internacionales, en esta Ley o en las demás disposiciones aplicables, se estará a los principios generales que deriven de dichos ordenamientos y a falta de éstos, a los principios generales del derecho.\nArtículo 11. Es obligación de toda persona que tenga conocimiento de casos de niñas, niños y adolescentes que sufran o hayan sufrido, en cualquier forma, violación de sus derechos, hacerlo del conocimiento inmediato de las autoridades competentes, de manera que pueda seguirse la investigación correspondiente y, en su caso, instrumentar las medidas cautelares, de protección y de restitución integrales procedentes en términos de las disposiciones aplicables.\nArtículo 12. Las autoridades en la Ciudad de México y de los órganos político administrativos garantizarán el establecimiento de los mecanismos necesarios para que cualquier persona, así como niñas, niños y adolescentes, puedan hacer del conocimiento de las autoridades correspondientes los hechos presuntamente constitutivos de violaciones a los derechos establecidos en la presente ley.\nAsimismo, lo anterior se garantizará conforme a la Ley de Protección de Datos Personales en Posesión de\nSujetos Obligados de la Ciudad de México y de la Ley de Transparencia, Acceso a la Información Pública y\nRendición de Cuentas de la Ciudad de México, mismas que podrán utilizarse de manera supletoria en los casos que se requiera, mediante el mecanismo que el reglamento establezca.\nTÍTULO SEGUNDO\nDE LOS DERECHOS DE NIÑAS, NIÑOS Y ADOLESCENTES\nArtículo 13. Todas las niñas, niños y adolescentes son iguales ante la ley y merecen un trato igual y equitativo. De manera enunciativa más no limitativa, en la Ciudad de México gozarán de los siguientes derechos:\n\nI. Derecho a la vida, a la paz, a la supervivencia y al desarrollo;\nII. Derecho de prioridad;\nIII. Derecho a la identidad;\nIV. Derecho a vivir en familia;\nV. Derecho a la igualdad sustantiva;\nVI. Derecho a no ser discriminado;\nVII. Derecho a vivir en condiciones de bienestar y a un sano desarrollo integral;\nVIII. Derecho a una vida libre de violencia y a la integridad personal;\nIX. Derecho a la protección de la salud física y mental, y a la seguridad social;\nX. Derechos de niñas, niños y adolescentes con discapacidad;\nXI. Derecho a la educación;\nXII. Derecho al descanso, al juego y al esparcimiento;\nXIII. Derecho a la libertad de convicciones éticas, pensamiento, conciencia, religión y cultura;\nXIV. Derecho a la libertad de expresión y de acceso a la información;\nXV. Derecho de participación;\nXVI. Derecho de asociación y reunión;\nXVII. Derecho a la intimidad;\nXVIII. Derecho a la seguridad jurídica, acceso a la justicia y al debido proceso;\n\nXIX. Derecho a recibir protección especial cuando se encuentre en situación de discriminación múltiple; y\nXX. Derecho de acceso a la información y a las tecnologías de la información y comunicación;\nXXI. Derecho a la protección y seguridad sexual;\nXXII. Derecho a conocer los datos de los sentenciados con ejecutoria por delitos vinculados con violencia sexual contra niñas, niños y adolescentes; y,\nXXIII. Derechos de niñas, niños y adolescentes migrantes.\nArtículo 14. En la aplicación de la presente Ley se tomarán en cuenta las condiciones particulares de niñas, niños y adolescentes en situación de vulnerabilidad, a fin de proteger y garantizar el ejercicio pleno de todos sus derechos.\nLas autoridades de la Ciudad de México y los órganos político administrativos, en el ámbito de sus respectivas competencias, adoptarán medidas de protección especial de derechos humanos de niñas, niños y adolescentes que se encuentren en situación de vulnerabilidad de conformidad con lo previsto en el artículo 115 de la presente ley.\nCAPÍTULO PRIMERO\nDEL DERECHO A LA VIDA, A LA PAZ, A LA SUPERVIVENCIA Y AL\nDESARROLLO\nArtículo 15. Niñas, niños y adolescentes tienen derecho a la paz, a que se les preserve la vida y a disfrutarla en condiciones que aseguren su dignidad y un nivel de vida adecuado para su desarrollo integral óptimo físico, mental, material, espiritual, ético, cultural y social.\nNiñas, niños y adolescentes tienen derecho a la paz, a no ser privados de la vida bajo ninguna circunstancia, ni ser utilizados en conflictos armados o violentos, ni en cualquier tipo de experimento o ensayo que atente contra su dignidad humana.\n\nA efecto de garantizar lo dispuesto en el párrafo primero del presente artículo, así como en el artículo 77;\nel Gobierno de la Ciudad de México, emitirá los protocolos de actuación a seguir por parte de las personas servidoras públicas de las instituciones de Seguridad Ciudadana, cuando en los mítines o marchas públicas se cuente con la presencia de niñas, niños y/o adolescentes.\nArtículo 16. Las autoridades y los órganos político administrativos, en el ámbito de sus respectivas competencias, deberán llevar a cabo las acciones necesarias para garantizar el desarrollo y prevenir cualquier conducta que atente contra su supervivencia, así como para investigar y sancionar efectivamente los actos de privación de la vida.\nDe igual manera, se encuentran obligadas a coadyuvar y apoyar a las personas que ejerzan la patria potestad, tutela, guarda y custodia, o acogimiento en términos de las disposiciones aplicables, a fin de garantizar las condiciones necesarias de supervivencia que les permita vivir y alcanzar el máximo bienestar posible con base en el desarrollo de sus potencialidades.\nAsimismo, las personas titulares de los órganos políticos administrativos deberán:\nI. Participar en la elaboración y ejecución de los programas dirigidos a solucionar la problemática que les afecte en su respectiva demarcación territorial;\nII. Impulsar dentro de su demarcación las acciones de defensa y representación jurídica, protección, acciones de provisión, prevención, participación y atención en coordinación con las\nSecretarías del ramo;\nIII. Promover la concertación entre los sectores público, privado y social, para mejorar su calidad de vida en la demarcación territorial.\nCAPÍTULO SEGUNDO\nDERECHO DE PRIORIDAD\nArtículo 17. Las niñas, niños y adolescentes tienen derecho a que se les garantice prioridad en el ejercicio o goce de todos derechos, especialmente a que:\nI. Se les brinde protección y socorro en cualquier circunstancia y con la oportunidad necesaria;\n\nII. Se les atienda antes que a las personas adultas en todos los servicios, en igualdad de condiciones,\nIII. Se les escuche y considere para el diseño y ejecución de las políticas públicas necesarias para la protección de sus derechos.\nIV. Se garantice la prevalencia de sus derechos ante una situación de conflicto con los derechos e intereses de las personas adultas.\nV. Se actúe bajo el principio de debida diligencia estricta en todos los procedimientos judiciales y administrativos que conciernen a la protección de sus derechos humanos; particularmente, en aquellos procesos judiciales relacionados con la adopción y la guarda y custodia de las niñas y niños que se encuentran en su primera infancia. De igual manera, en los procesos judiciales de adolescentes en conflicto con la ley penal.\nCAPÍTULO TERCERO\nDEL DERECHO A LA IDENTIDAD\nArtículo 18. Niñas, niños y adolescentes, en términos de la legislación civil aplicable, desde su nacimiento, tienen derecho a:\nI. Contar con nombre y los apellidos que les correspondan, así como a ser inscritos en el Registro\nCivil respectivo de forma inmediata y gratuita, y a que se les expida en forma ágil y sin costo la primera copia certificada del acta correspondiente, en los términos de las disposiciones aplicables. Es obligación de los padres o tutores registrar a niñas y niños inmediatamente y posterior a la recepción de la hoja de alumbramiento;\nII. Contar con nacionalidad, de conformidad con lo dispuesto en la Constitución Política de los\nEstados Unidos Mexicanos y los tratados internacionales;\nIII. Conocer su filiación y su origen, en la medida de lo posible y siempre que ello sea acorde con el interés superior;\nIV. Preservar su identidad, incluidos el nombre, la nacionalidad y su pertenencia cultural, así como sus relaciones familiares, y\n\nV. Pertenecer a un grupo cultural o nacional y compartir con sus integrantes costumbres, religión, idioma; siempre y cuando no constituyan violaciones a sus derechos humanos.\nLas autoridades y los órganos político administrativos, en el ámbito de sus respectivas competencias, deberán colaborar en la búsqueda, localización y obtención de la información necesaria para acreditar o restablecer la identidad de niñas, niños y adolescentes.\nLa Procuraduría de Protección, en el ámbito de sus respectivas competencias, orientará a las autoridades que correspondan para que den debido cumplimiento al presente artículo.\nCuando haya procesos o procedimientos que deriven en cambio de apellidos de niñas, niños y adolescentes, éstos tendrán el derecho a opinar y a ser tomados en cuenta, conforme a su edad, desarrollo evolutivo, cognoscitivo y madurez. La falta de documentación para acreditar la identidad de niñas, niños y adolescentes no será obstáculo para acceder y garantizar sus derechos.\nArtículo 19. Niñas, niños y adolescentes de nacionalidad extranjera que se encuentren en territorio de la\nCiudad de México, tienen derecho a comprobar su identidad con los documentos emitidos por la autoridad competente u otros medios previstos en la Ley de Migración y demás disposiciones aplicables.\nArtículo 20. Para efectos del reconocimiento de maternidad y paternidad de niñas, niños y adolescentes, así como en relación con los derechos y obligaciones derivados de la filiación y parentesco, se estará a la legislación civil aplicable. Ante la negativa de la prueba de paternidad o maternidad, la autoridad competente, salvo prueba en contrario, presumirá que es el padre o la madre respectivamente.\nCAPÍTULO CUARTO\nDEL DERECHO A VIVIR EN FAMILIA\n\nArtículo 21. Las niñas, niños y adolescentes tienen derecho a vivir en familia y en comunidad, ya que son grupos fundamentales para el desarrollo, el crecimiento y el bienestar de todos sus integrantes en un ambiente de pleno respeto a su dignidad.\nLas autoridades y los órganos político administrativos respetarán las responsabilidades, los derechos y deberes de quienes ejercen la patria potestad, tutela, guarda y custodia o acogimiento, para que en consonancia con la evolución de las facultades de niñas, niños y adolescentes les brinden dirección y orientación apropiadas para el ejercicio de sus derechos.\nArtículo 22. La falta de recursos no podrá considerarse como razón suficiente para justificar la separación de una niña, niño o adolescente de su núcleo familiar de origen o de los familiares con los que conviva.\nNiñas, niños y adolescentes no podrán ser separados de las personas que ejerzan la patria potestad o de sus tutores y, en términos de las disposiciones aplicables, de las personas que los tengan bajo su guarda, custodia o cuidado, salvo que medie orden de autoridad competente, en la que se determine la procedencia de la separación, en cumplimiento a la preservación del interés superior, de conformidad con las causas previstas en las leyes y mediante el debido proceso en el que se garantice el derecho de audiencia de todas las partes involucradas. En todos los casos, se tendrá en cuenta la opinión de niñas, niños y adolescentes conforme a su edad, desarrollo evolutivo, cognoscitivo y madurez, garantizando la valoración de la opinión por personal especializado y observando en todo momento si existe algún riesgo o peligro para las niñas, niños y adolescentes.\nArtículo 23. Los casos en que las personas que ejerzan la patria potestad, por extrema pobreza o por necesidad de ganarse el sustento lejos del lugar de residencia, tengan dificultades para atender a niñas, niños y adolescentes de manera permanente, no serán considerados como supuestos de exposición o estado de abandono, siempre que los mantengan al cuidado de otras personas, libres de violencia y provean su subsistencia.\nLas autoridades y de los órganos político administrativos, en el ámbito de sus respectivas competencias, están obligadas a establecer políticas de fortalecimiento familiar para evitar la separación de niñas, niños y adolescentes de quienes ejerzan la patria potestad, tutela o guarda y custodia, siempre que no sea contrario a su interés superior.\nArtículo 24. Niñas, niños y adolescentes cuyas familias estén separadas, tendrán derecho a convivir o mantener relaciones personales y contacto directo con sus familiares de modo regular, así como mantener sus vínculos comunitarios, excepto en los casos en que la autoridad jurisdiccional competente determine\n\nque ello es contrario al interés superior, sin perjuicio de las medidas cautelares y de protección que se dicten por las autoridades competentes en los procedimientos respectivos, en los que se deberá garantizar el derecho de audiencia de todas las partes involucradas, en especial de niñas, niños y adolescentes.\nEn todo momento se buscará la restitución del derecho de la niña, niño o adolescente a una vida familiar y comunitaria.\nArtículo 25. Niñas, niños y adolescentes tienen derecho a convivir con sus familiares cuando éstos se encuentren privados de su libertad. Las autoridades competentes en materia jurisdiccional y penitenciaria deberán garantizar este derecho y establecer las condiciones necesarias para que esta convivencia se realice en forma adecuada, conforme a las disposiciones aplicables. La Procuraduría de Protección deberá coadyuvar con esas autoridades para tales efectos.\nEste derecho sólo podrá ser restringido por resolución del órgano jurisdiccional competente, siempre y cuando no sea contrario a su interés superior.\nEn caso de que la autoridad judicial así lo requiera, la Procuraduría de Protección deberá emitir un dictamen de pertinencia sobre la convivencia familiar, previos estudios psicológicos tanto de la niña, niño o adolescente como de los familiares, por conducto de peritos psicológicos especialistas en materia de infancia.\nArtículo 26. La Procuraduría General de Justicia de forma coordinada con los distintos órganos político administrativos y con la coadyuvancia de la Procuraduría de Protección en el ámbito de sus respectivas competencias, establecerán las normas y los mecanismos necesarios para facilitar la localización y reunificación de la familia de niñas, niños y adolescentes, cuando hayan sido privados de ella, siempre y cuando no sea contrario a su interés superior.\nDurante la localización de la familia, niñas, niños y adolescentes tienen derecho a acceder a las modalidades de cuidados alternativos de carácter temporal, en tanto se incorporan a su familia. La\nProcuraduría de Protección deberá garantizar la modalidad de acogimiento correspondiente, atendiendo a la situación particular de cada niña, niño o adolescente de conformidad con lo previsto en la Ley de\nCuidados Alternativos, esta Ley y demás disposiciones aplicables.\nArtículo 27. Las leyes de la Ciudad de México contendrán disposiciones para prevenir y sancionar el traslado o retención ilícita de niñas, niños y adolescentes cuando se produzcan en violación de los derechos atribuidos individual o conjuntamente a las personas o instituciones que ejerzan la patria potestad, la\n\ntutela, la guarda y custodia, o cuidado alternativo y preverán procedimientos expeditos para garantizar el ejercicio de esos derechos.\nEn los casos de traslados o retenciones ilícitas de niñas, niños y adolescentes fuera del territorio nacional, la persona interesada o la Procuraduría de Protección podrán presentar la solicitud de restitución respectiva ante la Secretaría de Relaciones Exteriores, para que ésta lleve a cabo las acciones correspondientes en el marco de sus atribuciones, de conformidad con lo dispuesto en los instrumentos internacionales y demás disposiciones aplicables.\nCuando las autoridades tengan conocimiento de casos de niñas, niños y adolescentes de nacionalidad mexicana trasladados o retenidos de manera ilícita en el extranjero, se coordinarán con las autoridades federales competentes, conforme a las demás disposiciones aplicables, para su localización y restitución.\nCuando una niña, niño o adolescente sea trasladado o retenido ilícitamente en territorio nacional, o haya sido trasladado legalmente pero retenido ilícitamente, las autoridades, en el ámbito de sus respectivas competencias, estarán obligadas a coadyuvar en su localización, a través de los programas para la búsqueda, localización y recuperación, así como en la adopción de todas las medidas necesarias para prevenir que sufran mayores daños y en la sustanciación de los procedimientos de urgencia necesarios para garantizar su restitución inmediata, cuando la misma resulte procedente conforme a los tratados internacionales en materia de sustracción de niñas, niños y adolescentes.\nArtículo 28. El DIF-CDMX a través de la Procuraduría de Protección deberá otorgar las medidas especiales para la protección de los derechos de las niñas, niños y adolescentes que hayan sido separados de su familia de origen por resolución judicial.\nA fin de garantizar y restituir los derechos de niñas, niños y adolescentes en desamparo en la Ciudad de\nMéxico, se actuará conforme lo dispone la Ley de Cuidados Alternativos.\nArtículo 29. Las personas interesadas en adoptar niñas, niños y adolescentes que se encuentren bajo la tutela del DIFCDMX podrán presentar ante la Procuraduría de Protección la solicitud correspondiente.\nLos procedimientos de adopción se desahogarán de conformidad con lo dispuesto por la Ley General, el\nCódigo Civil, el Código de Procedimientos, la presente Ley y su Reglamento.\n\nArtículo 30. En materia de adopción, corresponde a la Procuraduría de Protección, en el ámbito de sus respectivas competencias:\nI. Prestar servicios de asesoría, asistencia jurídica y capacitación obligatoria a las personas que deseen asumir el carácter de familia adoptiva.\nII. Expedir los certificados de idoneidad como resultado de las evaluaciones y valoraciones psicológicas, económicas, de trabajo social y todas aquellas que sean necesarias, mismas que serán válidas para iniciar el procedimiento de adopción ante autoridad jurisdiccional en la\nCiudad de México y, en su caso, formular las recomendaciones pertinentes al órgano jurisdiccional.\nIII. Contar con un sistema de información y registro detallado de carácter confidencial y de acceso exclusivo por orden de autoridad judicial o administrativa competente, permanentemente actualizado, que incluya:\na) En el caso de niñas, niños y adolescentes cuya situación jurídica o familiar permita sean susceptibles de adopción: nombre completo, fecha de nacimiento, edad, sexo, escolaridad, domicilio en el que se encuentra, situación jurídica, diagnóstico médico y psicológico, condición pedagógica, información social, perfil de necesidades de atención familiar, información biométrica y de ser el caso, número de hermanos, tipo y severidad de la discapacidad con la que vive y requerimientos de atención a necesidades especiales de los menores de edad;\nb) Tratándose de personas interesadas en adoptar: nombre completo, edad, nacionalidad, país de residencia habitual, estado civil, ocupación, escolaridad, domicilio, perfil y número de menores de edad que tienen la capacidad de adoptar y si cuentan con\nCertificado de Idoneidad;\nc) Adopciones concluidas: divididas en nacionales e internacionales especificando el número de menores de edad adoptados;\nd) Adopciones en trámite: especificará los menores de edad que ya se encuentren en proceso de adopción y la etapa en la que se ubican; y, e) Adopciones no concluidas: se detallarán las causas y motivos por los cuales no pudieron concretarse.\nEl registro de adopción, deberá ser resguardado de forma permanente, conservando toda la información y cada uno de los datos de niñas, niños y adolescentes que ingresen al mismo a fin de garantizar el derecho que tienen los mismos a conocer su origen, cada\n\nactualización deberá enterarse a la Procuraduría de Protección Federal, de conformidad con lo establecido en la Ley General.\nLo anterior sin perjuicio de lo dispuesto en materia de conservación de archivos por la ley de la materia en la Ciudad de México.\nIV. Contar con un registro de familias de acogida y de las niñas, niños y adolescentes acogidos por éstas.\nV. Registrar, capacitar, evaluar y certificar a las familias que resulten idóneas, considerando los requisitos señalados para el acogimiento temporal y preadoptivo, de conformidad con lo establecido en esta Ley y su reglamento, a fin de garantizar su idoneidad.\nArtículo 31. En materia de adopción todas las autoridades, en el ámbito de su competencia, velarán porque en los procesos de adopción se respeten las normas que los rijan y deberán observar las disposiciones mínimas que comprenda lo siguiente:\nI. Garantizar que niñas, niños y adolescentes sean adoptados con pleno respeto de sus derechos humanos, y de conformidad con el principio de interés superior de la niñez, sin que medien intereses de particulares o colectivos que se contrapongan a los mismos;\nII. Garantizar el derecho a la participación de niñas, niños y adolescentes dentro de sus procedimientos de adopción, asegurando que su opinión sea recabada y tomada en cuenta a través de los mecanismos y procedimientos adecuados de acuerdo con su edad, desarrollo evolutivo, cognoscitivo y grado de madurez, en términos de la presente Ley.\nAsimismo, que en los procesos de adopción se respeten las normas que los rijan de conformidad con lo dispuesto en la Convención de La Haya sobre la Protección de Menores y la Cooperación en materia de Adopción Internacional, Ley General, el Código Civil, el Código de Procedimientos y la presente Ley, según corresponda;\nIII. Tomar las medidas necesarias a fin de evitar presiones indebidas o coacción a las familias de origen para para renunciar a la patria potestad y entregar a la niña, niño o adolescente en adopción. Lo anterior sin perjuicio de las acciones penales que pudieran derivarse de dichas conductas;\n\nIV. El Poder Judicial de la Ciudad de México garantizará que el proceso de adopción se realice de conformidad con lo establecido en Ley General, el Código Civil, el Código de Procedimientos, la\nConvención de La Haya sobre la Protección de Menores y la Cooperación en materia de Adopción\nInternacional y la presente Ley;\nV. Establecimiento y ejecución de procesos adecuados, precisos y eficaces de acuerdo a la situación jurídica de cada niña, niño y adolescente en los plazos y términos establecidos en la presente Ley en cada fase del procedimiento de adopción permitiendo su pronta liberación para la adopción en pleno respeto de sus derechos, previa determinación de su interés superior;\nVI. Asegurar en todo momento la atención y cuidados de forma integral de la niña, niño o adolescente durante el proceso de adopción;\nVII. En igualdad de circunstancias se dará preferencia en la adopción a los solicitantes mexicanos sobre extranjeros. Asimismo, se dará preferencia a la adopción nacional sobre la adopción internacional;\nVIII. Garantizar en todo momento la observancia y pleno respeto de los derechos humanos de las personas solicitantes de adopción, procurando, si fuere posible que la familia adoptante establezca continuidad con los rasgos de identidad cultural de la niña, niño o adolescente sujeto a adopción, sin que ello implique distinción discriminatoria de ninguna clase, con pleno apego a lo dispuesto por esta Ley y en estricta observancia del interés superior;\nIX. Priorizar en todo momento la unidad familiar entre hermanos, promoviendo que puedan ser adoptados dentro del mismo núcleo familiar, en caso de no ser posible, procurar el mantenimiento de la convivencia entre ellos, siempre que no sea contrario a su interés superior;\nX. Garantizar que se informe y asesore jurídicamente de forma gratuita y profesional, tanto a quienes consientan la adopción, como a quienes la acepten, a fin de que conozcan los alcances jurídicos, familiares y sociales de la misma; y,\nXI. Disponer las acciones necesarias para verificar que la adopción no sea motivada por beneficios económicos o diversos al interés superior de la niñez, para quienes participen en ella.\nArtículo 31 Bis. La persona que encontrare una niña, niño o adolescente en estado de indefensión, situación de calle, trabajo infantil desempeñado en calles, avenidas, ejes viales, espacios públicos o privados, medios\n\nde transporte o cualquier vía de circulación, en cualquiera de sus formas o que hubiere sido puesto en situación de desamparo familiar, deberá dar aviso o presentarlo ante la Procuraduría de Protección y al DIF-\nCDMX, con las prendas valores o cualesquiera otros objetos encontrados en su persona, señalando las circunstancias de tiempo, modo y lugar en que lo hubiere hallado. La Procuraduría de Protección y el DIF–\nCDMX, darán parte de la presentación al Ministerio Público para que en el marco de sus atribuciones realice la investigación correspondiente.\nArtículo modificado y publicado en la GOCDMX el 15 de marzo de 2024\nArtículo 31 Bis 1. El DIF-CDMX y la Procuraduría de Protección, establecerán políticas de fortalecimiento familiar a fin de prevenir y evitar la separación de niñas, niños y adolescentes de su entorno familiar.\nArtículo 31 Bis 2. En los casos en que niñas, niños o adolescentes se encuentren en situación de desamparo familiar, el DIFCDMX a través de la Procuraduría de Protección implementará las medidas especiales de protección siguientes:\nI. Cuando se desconozca el origen de niñas, niños y adolescentes y se presuma su procedencia de una entidad federativa distinta a la Ciudad de México, la Procuraduría de Protección deberá, realizar una ficha única de aviso a las autoridades del Sistema de Protección DIF de las entidades\nFederativas y al DIF Nacional; a fin de que se dé publicidad a dichos casos y permita conocer el origen de las o los menores. La ficha única de aviso deberá remitirse, en un lapso que no excederá de sesenta días desde el ingreso de la niña, niño o adolescente al Acogimiento\nResidencial o su ubicación con Familia de Acogida;\nII. Cuando la autoridad investigadora haya iniciado procedimiento alguno en el ámbito de su competencia por la presunción de la comisión de un delito y se configure o se pudiera configurar el abandono, la Procuraduría de Protección, garantizará las medidas de protección especiales determinadas en este artículo, asimismo, tomará las acciones necesarias para lograr la reintegración o acogimiento, según sea el caso.\nSi de la valoración que realice la Procuraduría de Protección se desprende que no es posible la reintegración, la Procuraduría de Protección promoverá la pérdida de la patria potestad apegándose estrictamente a lo establecido en el artículo 31 Bis 3 de esta Ley.\nLas autoridades competentes garantizarán que reciban todos los cuidados que se requieran por su situación de desamparo familiar;\n\nIII. Se asegurará de que las niñas, niños y adolescentes sean ubicados con su familia de origen, extensa o ampliada para su cuidado, siempre que ello sea posible, que las mismas sean evaluadas e idóneas a consideración de la Procuraduría de Protección y no sea contrario a su interés superior;\nIV. En caso de que la reinserción con la familia de origen, extensa o ampliada no fuera posible, se asegurará que las niñas, niños y adolescentes sean recibidos por una familia de acogida de forma temporal;\nV. En caso de que no sea posible ubicar a la niña, niño o adolescente con una familia de acogida se asegurará que sean recibidos, dadas las características específicas de cada caso, en acogimiento residencial brindado por Centros de Asistencia Social o instituciones que brinden cuidados alternativos, en y por el menor tiempo posible;\nVI. Procurará resolver con prontitud la situación jurídica de niñas, niños y adolescentes para acceder a un proceso de adopción expedito, ágil, simple y guiado por el interés superior de la niñez;\nVII. Procurará siempre que sea posible que las, niñas, niños y adolescentes sean sujetos de acogimiento temporal pre – adoptivo como una fase dentro del procedimiento de adopción, que supone la vinculación de niñas, niños y adolescentes, con su nuevo entorno y con su nueva familia, misma a la que se le haya determinado como idónea para adoptar, y que deberá ser registrada, capacitada y certificada por la procuraduría de Protección; y,\nVIII. Acompañar la adaptación de niñas, niños y adolescentes que hayan sido adoptados a su nueva familia y entorno; para conocer la evolución de su desarrollo, el DIF-CDMX en coordinación con la Procuraduría de Protección, realizarán su seguimiento cada seis meses durante los tres años posteriores a la adopción contados a partir de que la sentencia judicial de adopción quede firme.\nLos reportes de seguimiento deberán ser realizados por las personas profesionales de trabajo social autorizados y registrados por el DIF CDMX, donde se aprecie la convivencia familiar y el desarrollo cotidiano de niñas, niños y adolescentes, en su entorno.\nLa intervención que represente el seguimiento será lo menos invasiva posible a efecto de no alterar negativamente el entorno familiar.\n\nCon el propósito de procurar la menor afectación y garantizar el bienestar y el desarrollo de niñas, niños y adolescentes, las medidas especiales previamente señaladas en las fracciones anteriores, serán de carácter subsidiario, priorizando las opciones de cuidado en un entorno familiar definitivo.\nLa Procuraduría de Protección establecerá un sistema de cooperación y coordinación en el que se mantenga de forma permanente comunicación e intercambio de información a efecto de que en todos sus procesos y actuaciones se observe en todo momento el interés superior de la niñez, se procure la protección de niñas, niños y adolescentes a fin de garantizar el desarrollo evolutivo y formación de su personalidad, así como materializar su derecho a vivir en familia.\nLas autoridades administrativas y jurisdiccionales locales, en el ámbito de sus respectivas competencias, dispondrán lo conducente a efecto de que niñas, niños y adolescentes vean restituido su derecho a vivir en familia y su derecho a recibir formación y protección de quien ejerce la patria potestad, la tutela, guarda o custodia, interpretando de manera sistemática y funcional la normatividad correspondiente y observando en todo momento el principio de interés superior de la niñez.\nArtículo 31 Bis 3. Los Centros de Asistencia Social y todas las instituciones que brinden cuidados alternativos que reciban niñas, niños y adolescentes en situación de indefensión, desamparo familiar, víctimas de violencia o por cualquier otra circunstancia, deberán dar aviso inmediato tanto del ingreso, egreso y de la situación jurídica de los menores a la Procuraduría de Protección, asimismo, podrán recibirlos por disposición y orden girada por escrito de esta última o de autoridad competente.\nEn los procedimientos de adopción se observará lo siguiente:\nI. Las niñas, niños, y adolescentes ubicados con familias de acogida o ingresados en Centros de\nAsistencia o instituciones que brinden cuidados alternativos, serán considerados expósitos una vez que hayan transcurrido sesenta días naturales sin que se reclamen derechos sobre ellos y no se tenga información que permita conocer su origen, dejando constancia de que ninguna persona compareció para solicitar convivencia o su reintegración, dicho plazo correrá a partir del día en que la niña, niño o adolescente haya sido acogido con una familia de acogida o ingresado en un Centro de Asistencia Social o en una Institución que brinde cuidados alternativos.\nII. Cuando la Procuraduría de Protección no cuente con los elementos suficientes que den certeza sobre la situación de expósito de las niñas, niños o adolescentes; se podrá extender el plazo hasta por setenta días naturales más a fin de que se determine fehacientemente su condición jurídica.\n\nIII. La Procuraduría de Protección realizará las acciones conducentes para la reintegración al núcleo familiar de las niñas, niños, o adolescentes cuyo origen se conozca y que se encuentren ubicados con familias de acogida o ingresados en Centros de Asistencia o instituciones que brinden cuidados alternativos, en un plazo de sesenta días naturales contados desde su ingreso.\nIV. Cuando la reintegración al seno familiar no fuera posible por representar un riesgo a su bienestar o por ser contrario al interés superior de la niñez, la Procuraduría de Protección, o en su caso los Centros de Asistencia Social o instituciones que brinden cuidados alternativos enterando previamente a la Procuraduría de Protección y previo pronunciamiento de esta última, iniciarán el procedimiento de pérdida de patria potestad; en este supuesto se otorgarán setenta días naturales adicionales al plazo referido en la fracción anterior para su acogimiento a fin de que se resuelva la situación jurídica de la niña, niño o adolescente.\nV. En los casos en los que exista la presunción de la comisión de un delito en el que la autoridad investigadora haya iniciado un procedimiento en el ámbito de su competencia y se configure o se pudiera configurar el abandono, se otorgarán noventa días naturales adicionales a los plazos referidos en las fracciones anteriores a fin de desahogar los procedimientos a que haya lugar.\nDurante los plazos establecidos en el presente artículo se investigará el origen de niñas, niños y adolescentes, se realizarán las acciones conducentes que les permitan reintegrarse al núcleo familiar, siempre que dicha reintegración no represente un riesgo a su bienestar o por ser contrario al interés superior de la niñez; lo anterior en coordinación con los Centros de Asistencia Social y con el auxilio de cualquier autoridad que se considere necesaria, sin exponer, exhibir o poner en riesgo alguno a la niña, niño o adolescente.\nUna vez concluidos los plazos establecidos, sin obtener información respecto del origen de niñas, niños, o adolescentes, o no habiendo logrado su reintegración al seno familiar, y en el caso de los abandonados, previa sentencia de perdida de patria potestad, la Procuraduría de Protección, levantará un acta circunstanciada en la que conste la certificación de expósito o abandonado correspondiente. A partir de ese momento niñas, niños o adolescentes serán susceptibles de adopción.\nArtículo 31 Bis 4. Para los fines de esta Ley queda prohibido:\nI. La promesa de adopción durante el proceso de gestación;\n\nII. La adopción privada, entendiéndose ésta como el acto mediante el cual quienes ejercen la patria potestad, tutela o guarda y custodia o sus representantes legales, pacten dar en adopción de manera directa a niñas, niños o adolescentes sin que intervengan las autoridades competentes de conformidad con Ley General, el Código Civil, el Código de Procedimientos y la presente Ley;\nIII. Realizar adopción para fines de venta, sustracción, retención u ocultación ilícita, tráfico, trata de personas, explotación, trabajo infantil o cualquier otro ilícito. Si se presentare cualquiera de los supuestos referidos una vez concluida judicialmente la adopción, la Procuraduría de\nProtección, presentará denuncia ante el Ministerio Público, y tomará las medidas necesarias para asegurar el bienestar integral de niñas niños y adolescentes;\nIV. El contacto de las madres o padres biológicos que entregaron en adopción a una niña, un niño o un adolescente con la persona adoptante, con excepción de los casos en que los adoptantes sean familiares biológicos de la familia extensa o cuando el adoptado desee conocer sus antecedentes familiares y sea mayor de edad. Las niñas, niños y adolescentes menores de edad que deseen conocer sus antecedentes familiares deberán contar con el consentimiento de los adoptantes, y siempre que ello atienda al interés superior de la niñez;\nV. La inducción a través de cualquier forma de compensación o pago para influenciar o favorecer la decisión de otorgar a la niña, el niño o el adolescente en adopción;\nVI. La obtención directa o indirecta de beneficios indebidos, materiales o de cualquier otra índole, por la familia de origen o extensa de la o el adoptado, o por cualquier persona; así como por personas funcionarias o trabajadoras de instituciones públicas o privadas y autoridades involucradas en el proceso de adopción;\nVII. La obtención de lucro o beneficio personal ilícito como resultado de la adopción;\nVIII. El matrimonio entre la persona adoptante y la o el adoptado o sus descendientes, así como el matrimonio entre la o el adoptado con los familiares del adoptante o sus descendientes;\nIX. La adopción por más de dos personas, en cuyo caso se requiere el consentimiento de ambos;\nX. La adopción por discriminación, entendida como aquella donde se considera a la niña, niño o adolescente como un valor supletorio o reivindicatorio de la persona adoptante;\n\nXI. La alienación o asimilación cultural forzada, en caso de que la niña, niño o adolescente provenga de un pueblo originario o una comunidad indígena en términos de las Leyes aplicables;\nXII. Que la autoridad omita garantizar el derecho de niñas niños y adolescentes a emitir su opinión y ser escuchados, de acuerdo con su edad, evolución y desarrollo cognoscitivo en cualquier procedimiento donde participen;\nXIII. Que la autoridad se abstenga en dar atención, asistencia o información previa identificación y registro a las madres, padres, tutores o familiares que detenten o pudieran detentar la patria potestad de una niña, niño o adolescente que se encuentre bajo el resguardo y protección del\nDIF CDMX a través de la Procuraduría de Protección.\nXIV. Toda adopción contraria a las disposiciones Constitucionales, a los Tratados Internacionales ratificados por el Estado Mexicano, a la Constitución de la Ciudad de México a la Ley General, el\nCódigo Civil, el Código de Procedimientos, la presente Ley, el reglamento correspondiente y al interés superior de la niñez y a su adecuado desarrollo evolutivo.\nLa autoridad jurisdiccional deberá dar intervención a la Procuraduría de Protección en los procesos de adopción para los efectos legales a que haya lugar.\nA la actualización de los supuestos contenidos en las fracciones de este artículo corresponderán las sanciones previstas en la esta Ley sin perjuicio de las determinadas en la Ley General, la Ley de\nResponsabilidades Administrativas de la Ciudad de México, y el Código Penal para el Distrito Federal según sea el caso.\nArtículo 31 Bis 5. Pueden ser adoptadas niñas, niños y adolescentes que:\nI. No tengan quien ejerza sobre ellas o ellos la patria potestad;\nII. Cuenten con certificación de expósitos o abandonados;\nIII. Se encuentren en alguno de los supuestos anteriores y estén acogidos en los Centros de\nAsistencia Social, alguna institución que brinde cuidados alternativos, con familias de acogida o bajo la tutela del DIF CDMX a través de la Procuraduría de Protección;\n\nIV. Cuyos padres o quienes ejerzan patria potestad, manifiesten por escrito de forma libre y clara su consentimiento para iniciar el procedimiento de adopción ante la Procuraduría de Protección mismos que deberán ratificar su consentimiento ante el juez de lo familiar correspondiente; y,\nV. Las niñas, niños o adolescentes entregados voluntariamente para su adopción a Centros de\nAsistencia Social legalmente acreditados según las disposiciones de la presente Ley y demás ordenamientos aplicables. En cualquiera de los supuestos anteriores, se deberá contar con el informe de adoptabilidad correspondiente.\nArtículo 31 Bis 6. El Informe de adoptabilidad que emita la Procuraduría de Protección deberá de elaborarse de conformidad con el Reglamento y deberá contener, por lo menos los siguientes elementos:\na) Nombre completo de la niña, niño o adolescente;\nb) Lugar y fecha de nacimiento;\nc) Fecha de ingreso al Acogimiento Residencial o con Familia de Acogida;\nd) Edad;\ne) Sexo;\nf) Media Filiación;\ng) Antecedentes familiares;\nh) Situación jurídica;\ni) Condición e historia médica;\nj) Condición psicológica;\nk) Evolución pedagógica; y, l) Requerimiento de atención especial de ser el caso.\n\nLa Procuraduría de Protección podrá solicitar a los Centros de Asistencia Social o a la Familia de Acogida que tengan bajo su cuidado al niño, niña o adolescente cualquier información adicional a la prevista en ese artículo que considere necesaria para salvaguardar el interés superior de la niñez, misma que se incluirá en el Informe de Adoptabilidad.\nArtículo 31 Bis 7. Las personas solicitantes deberán acudir de forma personal a la Procuraduría de\nProtección para realizar el trámite de adopción.\nArtículo 31 Bis 8. El Comité Técnico de Adopción es el Órgano Colegiado de consulta, análisis, evaluación y autorización de las modalidades de acogimiento previstas en la Ley, y en su caso, de opinión para la designación de la familia idónea en el trámite administrativo de adopción.\nEl Comité Técnico de Adopción se integrará y funcionará de conformidad con lo dispuesto en el Reglamento y con los lineamientos que emita la Procuraduría de Protección.\nEn las Sesiones del Comité Técnico de Adopción deberán participar de forma permanente cuando menos una persona especialista en medicina pediátrica, una en psicología y una en trabajo social.\nArtículo 31 Bis 9. La expedición del certificado de idoneidad deberá realizarse previa valoración del expediente y del análisis de la evaluación psicológica y socioeconómica de los solicitantes, a reserva de lo establecido por el Reglamento correspondiente contendrá al menos los siguientes elementos:\nI. Nombre de la institución;\nII. Nombre, sexo y edad de la persona o personas solicitantes;\nIII. Tipo de adopción nacional o internacional, según sea el caso;\nIV. Nacionalidad de las personas o personas solicitantes;\nV. Temporalidad del matrimonio o concubinato, según el caso;\nVI. Temporalidad de convivencia según el caso;\nVII. Lugar de residencia;\n\nVIII. Diagnostico psicológico, médico y social correspondiente;\nIX. Carta de ingresos o comprobante de ingresos, y constancia de antigüedad en el trabajo;\nX. El número de hijas o hijos que tengan las personas solicitantes; y,\nXI. Constancia de no estar en el registro de Personas Agresoras Sexuales.\nUna vez cumplidos los requisitos establecidos en la Ley y el Reglamento, la Procuraduría de Protección contará con un término que no excederá de cuarenta y cinco días naturales para que previa opinión del\nComité Técnico de Adopción, se pronuncie con relación a la solicitud, misma que en todo caso deberá fundar y motivar.\nEn caso de estimarse procedente, la Procuraduría de Protección expedirá los certificados de idoneidad en un término que no excederá de diez días naturales.\nArtículo 31 Bis 10. La jueza o juez de lo familiar, contará con un plazo de 90 días hábiles improrrogables para emitir la sentencia en el juicio de pérdida de patria potestad de la niña, niño o adolescente. Dicho término será contado a partir del día siguiente de la presentación del escrito inicial.\nArtículo 31 Bis 11. La jueza o juez de lo familiar, contará con un plazo de 15 días hábiles improrrogables, contados a partir del día siguiente de la entrega, por parte de la autoridad administrativa, del expediente de adopción completo para emitir sentencia. Dicha autoridad administrativa contará con cinco días hábiles improrrogables para la entrega del expediente al juzgado familiar que conociere de la causa una vez cumplimentando lo dispuesto en el artículo 31 Bis 9 de la presente Ley.\nArtículo 31 Bis 12. Para que la adopción pueda tener lugar deberán consentirla, por escrito y ante la Jueza o Juez de lo familiar que conozca del procedimiento, la Procuraduría de Protección, la persona solicitante, en su caso la madre, padre, tutores o quien posea la patria potestad y la niña, niño o adolescente sujeto de adopción según su edad, evolución o desarrollo cognoscitivo.\nPara el caso de que las personas solicitantes sean cónyuges o concubinos, ambos deberán consentir la adopción de forma escrita ante la jueza o juez que conozca del procedimiento.\n\nEn el caso de niñas, niños y adolescentes con discapacidad, será necesario su consentimiento, siempre y cuando fuese posible la expresión indubitable de su voluntad.\nArtículo 31 Bis 13. Los Centros de Asistencia Social y todas las instituciones que brinden cuidados alternativos a niñas, niños y adolescentes que cumplan la mayoría de edad deberán garantizarles los servicios de atención que les permitan una óptima inclusión al entorno social.\nPara el efecto, se implementará el plan de restitución de derechos con dos años de anticipación previos al egreso de las y los adolescentes, con el fin de que desarrollen habilidades, conocimientos y capacidades que fortalezcan su autonomía progresiva y el ejercicio pleno de sus derechos.\nArtículo 31 Bis 14. La Procuraduría de Protección, en Coordinación con el Sistema Nacional DIF, dispondrán las medidas necesarias a fin de establecer e implementar el procedimiento único de adopción al que se refiere la Ley General, que permita a los solicitantes que el trámite de adopción sea rápido, eficaz y transparente.\nArtículo 31 Bis 15. En ningún caso se solicitará certificado médico de infertilidad como requisito para adoptar.\nArtículo 31 Bis 16. En caso de que la persona adoptante sea extranjera con residencia permanente en el territorio nacional, la Procuraduría de Protección, garantizará que el certificado de idoneidad contenga la comprobación de la situación migratoria regular en el territorio nacional de la o el solicitante.\nArtículo 31 Bis 17. La adopción será plena e irrevocable.\nArtículo 31 Bis 18. El DIF CDMX a través la Procuraduría de Protección celebrarán con el Sistema Nacional\nDIF y la Procuraduría de Protección Federal, así como con sus pares locales y con los Centros de Asistencia\nSocial y todas las instituciones que brinden cuidados alternativos debidamente registrados y autorizados por el DIF-CDMX, los convenios de colaboración que se consideren necesarios para garantizar el derecho a vivir en familia, el bienestar integral de las niñas, niños y adolescentes y prevaleciendo siempre el interés superior de la niñez.\nArtículo 31 Bis 19. Tratándose de adopción internacional, se estará a lo establecido en Ley General, el\nCódigo Civil, el Código de Procedimientos, la presente Ley y el Reglamento correspondiente, a efecto de que se asegure que los derechos de niñas, niños y adolescentes que sean adoptados se garanticen en todo\n\nmomento y se ajuste al interés superior de la niñez. Siempre y cuando no contravenga la Convención de La\nHaya sobre la Protección de Menores y la Cooperación en materia de Adopción Internacional.\nLas autoridades involucradas en el proceso de adopción internacional, tomarán las medidas necesarias a efecto de que se garantice que la misma no sea realizada con fines de venta, sustracción, retención u ocultación ilícita, asimilación cultural forzada, desplazamiento forzado tráfico o trata de personas, explotación, trabajo infantil o cualquier otra índole diversa al bienestar integral de las niñas, niños y adolescentes y al interés superior de la niñez.\nLas autoridades competentes deberán establecer medidas de prevención y protección para evitar adopciones ilegales. Para tal efecto, podrán requerir en colaboración con el Sistema de Protección Nacional y la Procuraduría de Protección Federal, así como la colaboración de las autoridades centrales del país de que se trate, a fin de obtener información o supervisar las medidas preventivas que se hayan dictado, en términos del tratado internacional de la materia, Ley General, el Código Civil, el Código de Procedimientos, la presente Ley y el Reglamento.\nEn los procedimientos judiciales de adopción internacional deberá requerirse el informe de adoptabilidad correspondiente a la Procuraduría de Protección, y una vez que la jueza o el juez de lo familiar que conozca del procedimiento otorgue la adopción, previa solicitud de las personas adoptantes la Secretaría de\nRelaciones Exteriores de conformidad con lo dispuesto en la Ley General y los tratados internacionales en la materia, expedirá la certificación correspondiente.\nLas personas que ejerzan profesiones de trabajo social y psicología en las instituciones públicas y privadas que intervengan en los procedimientos de adopción internacional, en términos de lo dispuesto en los tratados internacionales, y la legislación de la materia, deberá contar con la autorización y registro del DIF-\nCDMX.\nLa adopción internacional de una niña, niño o adolescente de nacionalidad mexicana procederá cuando se haya constatado por las autoridades correspondientes que ésta responde al interés superior, y su bienestar integral habiendo previamente examinado y agotado la posibilidad de asignación de la niña, niño o adolescente para adopción nacional.\nEl DIF-CDMX a través la Procuraduría de Protección tiene la obligación de conservar cualquier información que dispongan relativa a niñas, niños, y adolescentes que hayan sido adoptados internacionalmente, así como de sus orígenes.\n\nArtículo 32. Los Centros de Asistencia Social y todas las instituciones que brinden cuidados alternativos deberán ser registrados y autorizados por DIF-CDMX y estarán sujetos a los mecanismos de autorización, supervisión y vigilancia previstos en la Ley de Cuidados Alternativos.\nLas personas titulares o representantes legales de los Centros de Asistencia Social y todas las instituciones que brinden cuidados alternativos, además deberán:\nI. Inscribirse en el Registro Nacional de Centros de Asistencia Social del Sistema Nacional DIF y del DIF CDMX;\nII. Tomar las medidas necesarias que permitan a niñas, niños y adolescentes, a quienes les brindan alojamiento, contar con un plan de restitución de sus derechos, en coordinación con la\nProcuraduría de Protección, a fin de garantizar el pleno respeto y ejercicio de los mismos;\nIII. Contar con un registro de niñas, niños y adolescentes a quienes brindan alojamiento que contendrá la información de su situación jurídica que será actualizada permanentemente, la cual será informada a la Procuraduría de Protección;\nIII Bis. Contar con un registro del personal que labora, incluyendo a la persona titular y/o representante legal. El registro deberá contar con al menos la información personal, formación académica que incluya cursos, diplomados u otros que los acrediten sus capacidades para cumplir sus funciones, experiencia laboral, funciones o actividades que realizan o cumplen con las niñas, niños y adolescentes. Dicho personal no deberá haber sido sentenciado por los delitos cometidos contra niñas, niños y adolescentes. Será actualizada cada seis meses y deberá informarse a la Procuraduría de Protección;\nPárrafo adicionado y publicado en la GOCDMX el 21 de abril de 2023\nIV. Brindar la información que le requiera la Procuraduría de Protección respecto de la atención integral que otorga a niñas, niños y adolescentes canalizados por cualquier autoridad del orden local, federal o municipal, o por su familia de origen o extensa;\nV. Ingresar información y mantenerla actualizada en el Sistema que prevé la Ley de Cuidados\nAlternativos conforme a las disposiciones emitidas por la Procuraduría de Protección;\n\nVI. Proporcionar los datos que le requiera la Procuraduría de Protección, que permitan comprobar la integración y sistematización del Registro de Centros de Asistencia Social, Nacional y de la Ciudad de México;\nVII. Asegurar que las instalaciones tengan en lugar visible, la constancia de registro de incorporación al Registro Nacional de Centros de Asistencia Social y de la Ciudad de México;\nVIII. Contar con un Reglamento Interno, aprobado por el DIF-CDMX;\nIX. Contar con un programa interno de protección civil en términos de la legislación de la materia;\nX. Brindar las facilidades a la Procuraduría de Protección para que en el ámbito de su competencia realice la verificación periódica de la situación jurídica y social, así como la atención médica y psicológica de la niña, niño o adolescente y el proceso de reincorporación familiar o social, así como el cumplimiento de la legislación en la materia; y, en su caso atender las recomendaciones realizadas;\nXI. Informar de manera oportuna a la jueza o el juez de lo familiar, al DIF CDMX y a la Procuraduría de Protección cuando el ingreso de una niña, niño o adolescente al Centro de Asistencia Social, corresponda a una situación distinta a las establecidas en esta Ley o se tenga conocimiento de que peligra su integridad física estando bajo su custodia, a fin de iniciar los procedimientos de protección especial de forma oportuna;\nXII. Proporcionar atención médica a las niñas, niños y adolescentes bajo su custodia a través del personal capacitado para ello;\nXIII. Dar cumplimiento a los requerimientos y recomendaciones que realicen las autoridades en el ámbito de su competencia;\nXIV. Realizar las acciones necesarias para la profesionalización del personal de los Centros de\nAsistencia Social; y,\nXV. Brindar las facilidades a la Procuraduría de Protección a fin de dar seguimiento al cumplimiento del plan de restitución de derechos a favor de niñas, niños y adolescentes y atender las recomendaciones que, en su caso, emita para tales efectos.\n\nEn caso de incumplimiento, se solicitarán las medidas de apremio y sanciones administrativas que correspondan.\nCAPÍTULO QUINTO\nDEL DERECHO A LA IGUALDAD SUSTANTIVA\nArtículo 33. Las niñas y las adolescentes en igualdad de condiciones con los niños y los adolescentes, tienen derecho al acceso al mismo trato y oportunidades para el reconocimiento, goce o ejercicio de los derechos humanos y las libertades fundamentales.\nArtículo 34. Las autoridades y los órganos político administrativos, para garantizar la igualdad sustantiva deberán:\nI. Transversalizar la perspectiva de género en todas sus actuaciones y procurar la utilización de un lenguaje no sexista en sus documentos oficiales;\nII. Diseñar, implementar y evaluar programas y, políticas públicas, a través de acciones afirmativas tendientes a eliminar los obstáculos que impiden la igualdad de acceso y de oportunidades a la alimentación, a la educación y a la atención médica entre las niñas y las adolescentes;\nIII. Implementar acciones específicas para alcanzar la eliminación de costumbres, tradiciones, prejuicios, roles y estereotipos sexistas o de cualquier otra índole que estén basadas en la idea de inferioridad o superioridad de cualquiera de los sexos;\nIV. Establecer medidas dirigidas de manera preferente a las niñas y las adolescentes que pertenezcan a grupos y regiones con mayor rezago educativo o que enfrenten condiciones económicas y sociales de desventaja para el ejercicio o goce de los derechos contenidos en esta\nLey;\n\nV. Establecer los mecanismos institucionales que orienten a las autoridades hacia el cumplimiento de la igualdad sustantiva en los ámbitos público y privado, promoviendo el empoderamiento de las niñas y las adolescentes;\nVI. Desarrollar campañas permanentes de sensibilización de los derechos de las niñas y las adolescentes;\nVII. Promover un entorno educativo en el que se eliminen las barreras sociales y culturales que impiden la asistencia a las escuelas de adolescentes embarazadas;\nVIII. Impulsar campañas, que de manera científica y veraz brinden información sobre el ejercicio de sus derechos sexuales y reproductivos. Dichas campañas deberán diseñarse e implementarse de acuerdo con la edad, desarrollo evolutivo, cognoscitivo y grado de madurez de los segmentos de población de niñas y adolescentes a las que van dirigidas;\nIX. Generar mecanismos y campañas para alentar a las niñas y a las adolescentes a ejercer su opinión en todos los asuntos que las afecten, garantizando que sus opiniones sean respetadas y valoradas deacuerdo con la edad, desarrollo evolutivo, cognoscitivo y grado de madurez;\nparticularmente, en cualquier procedimiento judicial o administrativo que afecte sus derechos y;\nX. Elaborar y aplicar protocolos de investigación, que tengan perspectiva de género, sobre los delitos que se cometen con mayor incidencia en contra de las niñas y las adolescentes.\nPrimordialmente, para la investigación de los delitos que atenten contra la vida, la seguridad, libertad, el libre desarrollo de la personalidad y la dignidad.\nArtículo 35. Las normas aplicables a las niñas y a las adolescentes deberán estar dirigidas a visibilizar, promover, respetar, proteger, garantizar y restituir en su caso, sus derechos en aras de alcanzar la igualdad sustantiva con respecto a los niños y a los adolescentes; y, en general, con toda la sociedad.\nCAPÍTULO SEXTO\nDEL DERECHO A NO SER DISCRIMINADO\nArtículo 36. Niñas, niños y adolescentes tienen derecho a no ser sujetos de discriminación alguna ni de limitación o restricción de sus derechos, en razón de su raza, origen étnico, nacional o social, idioma o\n\nlengua, color de piel, edad, género, discapacidad; situación jurídica, condición social, económica o cultural;\nde salud, embarazo, religión, opinión, orientación sexual e identidad de género, estado civil, calidad de persona migrante, refugiada, desplazada,o cualquier otra condición atribuible a ellas o ellos mismos o a su madre, padre, tutor o persona que los tenga bajo guarda y custodia, o a otros miembros de su familia.\nArtículo 37. Las autoridades están obligadas a llevar a cabo medidas especiales para prevenir, atender y erradicar la discriminación múltiple de la que son objeto niñas, niños y adolescentes en situación de exclusión social, en situación de calle, en conflicto con la ley, afrodescendientes, privadas de su libertad, víctima de trata y explotación humana, víctima de las peores formas de trabajo infantil, turismo sexual, lenocinio, pornografía, reclutamiento y utilización en conflictos armados, trabajo infantil o cualquier otra condición de marginalidad.\nLa adopción de estas medidas y la realización de acciones afirmativas formarán parte de la perspectiva antidiscriminatoria, la cual será incorporada de manera transversal y progresiva en el quehacer público, y de manera particular en el diseño, implementación y evaluación de las políticas públicas.\nArtículo 38. Las instancias públicas de los órganos de gobierno, así como los órganos autónomos deberán reportar semestralmente al Consejo para Prevenir y Eliminar la Discriminación de la Ciudad de México, las medidas de nivelación, medidas de inclusión y Acciones afirmativas que adopten, para su registro y monitoreo, en términos de la Ley para Prevenir y Eliminar la Discriminación del Distrito Federal. Dichos reportes deberán desagregar la información, por lo menos, en razón de edad, sexo, escolaridad y tipo de discriminación.\nArtículo 39. Las autoridades y los órganos político administrativos, en el ámbito de sus respectivas competencias, adoptarán medidas para la eliminación de usos, costumbres, prácticas culturales o prejuicios que atenten contra la igualdad de niñas, niños y adolescentes por razón de género o que promuevan cualquier tipo de discriminación, atendiendo al interés superior.\nCAPÍTULO SÉPTIMO\nDEL DERECHO A VIVIR EN CONDICIONES DE BIENESTAR Y A\nUN SANO DESARROLLO INTEGRAL\nArtículo 40. Niñas, niños y adolescentes tienen derecho a vivir en un medio ambiente sano y sustentable, y en condiciones que permitan su desarrollo, bienestar, crecimiento saludable y armonioso, tanto físico como mental, material, espiritual, ético, cultural y social.\n\nArtículo 41. Corresponde a quienes ejerzan la patria potestad, tutela o guarda y custodia de niñas, niños y adolescentes, la obligación primordial de proporcionar, dentro de sus posibilidades y medios económicos, las condiciones de vida suficientes para su sano desarrollo. Las autoridades y los órganos político administrativos, en el ámbito de sus respectivas competencias, coadyuvarán a dicho fin mediante la adopción de las medidas apropiadas.\nArtículo modificado y publicado en la GOCDMX el 29 de abril de 2024\nArtículo 42. La edad mínima para contraer matrimonio en la Ciudad de México, serán los 18 años de edad cumplidos, en términos de la legislación civil aplicable.\nCAPÍTULO OCTAVO\nDEL DERECHO DE ACCESO A UNA VIDA LIBRE DE\nVIOLENCIA Y A LA INTEGRIDAD PERSONAL\nArtículo 43. Niñas, niños y adolescentes tienen derecho a vivir una vida libre de toda forma de violencia y a que se resguarde su integridad personal, a fin de lograr las mejores condiciones de bienestar y el libre desarrollo de su personalidad.\nLas niñas, niños y adolescentes tienen derecho a recibir orientación, educación, cuidado y crianza de su madre, su padre o de quienes ejerzan la patria potestad, tutela o guarda y custodia, así como de los encargados y el personal de instituciones educativas, deportivas, religiosas, de salud, de asistencia social, y de cualquier otra índole que brinde asistencia a niñas, niños y adolescentes, sin que, en modo alguno, se autorice a estos el uso del castigo corporal ni el castigo humillante.\nArtículo modificado y publicado en la GOCDMX el 29 de abril de 2024\nArtículo 44. Las autoridades y los órganos político administrativos, en el ámbito de sus respectivas competencias, están obligadas a tomar las medidas necesarias para prevenir, atender investigar, perseguir y sancionar conforme a derecho corresponda, los casos en que niñas, niños o adolescentes se vean afectados por:\n\nI. El descuido, negligencia, abandono o abuso físico, psicológico o sexual;\nI Bis. La obstrucción sin causa jurídicamente válida del derecho de visita o convivencia conforme a los términos y horarios establecidos en una resolución judicial de carácter familiar;\nFracción modificada y publicada en la GOCDMX el 22 de mayo de 2023\nII. La corrupción de personas menores de dieciocho años de edad;\nIII. Trata de personas menores de dieciocho años de edad, las formas de explotación humana, especialmente abuso sexual infantil, explotación sexual infantil con o sin fines comerciales, o cualquier otro tipo de explotación, y demás conductas punibles establecidas en las disposiciones aplicables;\nIV. El tráfico de personas menores de dieciocho años de edad;\nV. El tráfico de órganos;\nVI. La tortura, tratos crueles, inhumanos o degradantes;\nVII. La desaparición forzada de personas;\nVIII. El trabajo antes de la edad mínima de quince años, y particularmente el trabajo infantil desempeñado en las calles, avenidas, ejes viales, espacios públicos o privados, medios de transporte o cualquier vía de circulación;\nFracción modificada y publicada en la GOCDMX el 15 de marzo de 2024\nIX. El trabajo en adolescentes mayores de quince años que pueda perjudicar su salud, su educación o impedir su desarrollo físico o mental, explotación laboral, las peores formas de trabajo infantil, así como el trabajo forzoso;\nSe entiende por las peores formas de trabajo infantil a las relativas a: la esclavitud, trata infantil, servidumbre por deudas, la condición de siervo, trabajo forzoso, explotación sexual y la participación en actividades ilícitas;\n\nX. La incitación o coacción para que participen en la comisión de delitos o en asociaciones delictuosas, en conflictos armados o en cualquier otra actividad que impida su desarrollo integral;\nFracción modificada y publicada en la GOCDMX el 21 de abril de 2023\nXI. El castigo corporal y/o humillante; y\nFracción modificada y publicada en la GOCDMX el 21 de abril de 2023\nXII. Contenidos en los medios de comunicación y redes sociales que afecten o impidan objetivamente el desarrollo integral de niñas, niños y adolescentes, o que hagan apología del delito, en contravención al principio de interés superior de la niñez; y\nFracción modificada y publicada en la GOCDMX el 19 de julio de 2024\nXIII. Actos de violencia física, psicoemocional, moral y/o amenazas en contra o en presencia de niñas, niños o adolescentes, derivados de incidentes por el tránsito de vehículos.\nFracción adicionada y publicada en la GOCDMX el 19 de julio de 2024\nLas autoridades competentes deberán considerar la perspectiva de género en las situaciones de violencia.\nLas leyes de la Ciudad de México deberán establecer las disposiciones que orientarán las políticas de prevención, protección, atención, sanción y erradicación de los supuestos a que se refieren las fracciones anteriores.\nPara lo cual el Registro Público de Agresores Sexuales, registrará a las personas sentenciadas con ejecutoria por los delitos señalados en la legislación penal, que hayan sido cometidos contra niñas, niños y adolescentes y, que la autoridad jurisdiccional, haya determinado su inscripción en dicho registro.\nDe manera específica, para lo relacionado con el trabajo infantil mencionado en la fracción VIII del presente artículo, la Procuraduría de Protección y el DIF-CDMX, deberán llevar a cabo la vigilancia e inspecciones de manera permanente en los sitios mencionados en la misma fracción, con el fin de detectar, atender y erradicar el mismo.\nPárrafo adicionado y publicado en la GOCDMX el 15 de marzo de 2024\nLas autoridades competentes, están obligadas a implementar medidas especiales de protección para prevenir, sancionar y reparar las conductas previstas en este artículo para niñas, niños y adolescentes con discapacidad.\n\nArtículo 45. Las autoridades y los órganos político administrativos, en el ámbito de sus respectivas competencias, están obligadas a adoptar las medidas apropiadas para promover la recuperación física y psicológica y la restitución de derechos de niñas, niños y adolescentes para lograr el pleno ejercicio de sus derechos y garantizar su reincorporación a la vida cotidiana.\nLa recuperación y restitución de derechos a que se refiere el párrafo anterior se llevarán a cabo en un ambiente que fomente la salud física y psicológica, el respeto y la dignidad de niñas, niños y adolescentes.\nArtículo 46. En los casos en que niñas, niños y adolescentes sean víctimas de delitos, se aplicarán las disposiciones de la Ley General de Víctimas, la Ley de Atención y Apoyo a Víctimas del Delito para el Distrito\nFederal y demás disposiciones que resulten aplicables. En todo caso, los protocolos de atención deberán considerar su edad, desarrollo evolutivo, cognoscitivo y madurez para la implementación de las acciones de asistencia y protección respectivas, así como la reparación integral del daño.\nPara el cumplimiento de lo dispuesto en el párrafo anterior, el Sistema de Protección a que se refiere la presente Ley, deberá coordinarse con el Sistema de Atención a Víctimas Local o Federal según sea el caso, los cuales procederán en los términos de la legislación aplicable.\nVerificando con toda oportunidad que los sentenciados a que se refiere la legislación penal, por delitos vinculados a la violencia sexual, en dichas sentencias, el juez penal ordene su inscripción al Registro\nPúblico de Personas Agresores Sexuales.\nCAPÍTULO NOVENO\nDEL DERECHO A LA PROTECCIÓN DE LA SALUD\nY A LA SEGURIDAD SOCIAL\nArtículo 47. Niñas, niños y adolescentes tienen derecho a disfrutar del más alto nivel posible de salud, así como a recibir la prestación de servicios de atención médica integral gratuita y de calidad, de conformidad con la legislación aplicable, con el fin de prevenir, proteger y restaurar su salud física y mental. Las autoridades y los órganos político administrativos, en el ámbito de sus respectivas competencias, en relación con los derechos de niñas, niños y adolescentes, se coordinarán a fin de:\nI. Reducir la morbilidad y mortalidad;\n\nII. Garantizarla prestación de la asistencia médica y sanitaria que sean necesarias a niñas, niños y adolescentes, haciendo hincapié en la atención primaria;\nIII. Promover en todos los grupos de la sociedad y, en particular, en quienes ejerzan la patria potestad, tutela o guarda y custodia, de niños, niñas y adolescentes, los principios básicos de la salud y la nutrición, la higiene y el saneamiento ambiental y las medidas de prevención de accidentes;\nIV. Adoptar medidas tendentes a la erradicación de las prácticas culturales, usos y costumbres que sean perjudiciales para la salud de niñas, niños y adolescentes;\nV. Desarrollar la atención sanitaria preventiva y crear mecanismos para la orientación a quienes ejerzan la patria potestad, tutela o guarda y custodia de niñas, niños y adolescentes;\nVI. Garantizar la prestación de servicios de atención médica respetuosa, efectiva e integral durante el embarazo, parto y puerperio, así como para sus hijas e hijos y promover la lactancia materna exclusiva dentro de los primeros seis meses y complementaria hasta los dos años;\nVII. Implementar estrategias de información y educación sexual y reproductiva para niñas, niños y adolescentes garantizando el acceso a los servicios de salud sexual y reproductiva, así como a métodos anticonceptivos;\nVIII. Combatir la desnutrición crónica y aguda, sobrepeso y obesidad, así como otros trastornos de conducta alimentaria, mediante la promoción de una alimentación equilibrada, el consumo de agua potable, el fomento del ejercicio físico, e impulsar programas de prevención e información sobre estos temas;\nIX. Fomentar y ejecutar los programas de vacunación y el control de la niñez y adolescencia sana para vigilar su crecimiento y desarrollo en forma periódica;\nPara tales efectos, y conforme los lineamientos que al respecto establezca la Secretaría de Salud\nFederal, realizarán la difusión permanente de las campañas de vacunación;\nReforma publicada en la GOCDMX el 12 de diciembre de 2022\n\nX. Atender de manera eficaz las enfermedades respiratorias, renales, gastrointestinales, epidémicas, cáncer, VIH/SIDA, Virus de Papiloma Humano y otras enfermedades de transmisión sexual e impulsar programas de prevención, vacunación e información sobre éstas;\nX Bis. Establecer medidas, políticas públicas, estrategias y acciones, enfocadas al estudio, detección, prevención y tratamiento del cáncer en la infancia y en la adolescencia, en sus diferentes etapas;\nFracción añadida y publicada en la GOCDMX el 04 de marzo de 2024\nXI. Disponer lo necesario para que niñas, niños y adolescentes con discapacidad reciban la atención apropiada a su condición, que mejore su calidad de vida, facilite su interacción e inclusión social y permita un ejercicio igualitario de sus derechos;\nXII. Prohibir, sancionar y erradicar la esterilización de niñas, niños y adolescentes, la asignación forzada de la identidad sexo genérica y cualquier forma de violencia obstétrica;\nXIII. Establecer las medidas para que en los servicios de salud se detecten y atiendan de manera especial los casos de víctimas de delitos o violaciones a sus derechos, o sujetos de violencia sexual y familiar, de conformidad con las disposiciones aplicables en la materia;\nXIV. Establecer medidas tendentes a la prevención, atención y rehabilitación en las situaciones ocasionadas por el uso problemático de drogas, armónicas con las políticas de Cortes de Drogas nacional y local;\nXV. Establecer medidas tendentes a que en los servicios de salud se detecten y atiendan de manera especial los casos de niñas, niños y adolescentes con situaciones de salud mental;\nXVI. Establecer medidas para la detección temprana de discapacidades a efecto de prevenir y reducir al máximo la aparición de nuevas y asegurar los mayores niveles de atención y rehabilitación;\nXVII. Coadyuvar en el acceso a los bienes, servicios, ayudas técnicas y rehabilitación que requieren niñas, niños y adolescentes con discapacidaD;\nFracción modificada y publicada en la GOCDMX el 29 de abril de 2024\n\nXVIII. Fomentar, promover y proteger la práctica de lactancia materna como medida para combatir la mortalidad por desnutrición de las niñas y los niños que se encuentran en la primera infancia; y\nFracción modificada y publicada en la GOCDMX el 29 de abril de 2024\nXIX. Establecer programas y campañas permanentes de información y concientización orientadas a la prevención oportuna del suicidio en niñas, niños y adolescentes.\nFracción adicionada y publicada en la GOCDMX el 29 de abril de 2024\nEn todos los casos que proporcionen los servicios de salud se respetará el derecho a la intimidad de niñas, niños y adolescentes y a un trato digno.\nArtículo 47 BIS. Para apoyar en la eliminación de las formas de malnutrición de niñas, niños y adolescentes, la distribución de alimentos y bebidas preparadas y procesadas dentro de los planteles educativos, tanto públicos y privados de educación básica y educación media superior, deberá sujetarse a lo dispuesto por los lineamientos establecidos por la Secretaría de Educación Pública.\nLa aplicación, vigilancia y cumplimiento de esta disposición estará a cargo de las autoridades educativas.\nArtículo añadido y publicado en la GOCDMX el 17 de noviembre de 2023\nArtículo 48. Las autoridades y los órganos político administrativos, en el ámbito de sus respectivas competencias y de conformidad con las disposiciones aplicables, deberán garantizar el derecho y acceso a la seguridad social.\nPárrafo modificado y publicado en la GOCDMX el 10 de octubre de 2023\nSe dará prioridad de acceso a las políticas públicas de seguridad social a las niñas, niños y adolescentes en situación de orfandad, víctimas indirectas de la comisión de algún delito en términos de la Ley de Víctimas para la Ciudad de México; o con motivo de una Declaración Especial de ausencia respecto de sus progenitores o cuidadores en los términos de la Ley de la materia.\nPárrafo añadido y publicado en la GOCDMX el 10 de octubre de 2023\nArtículo 49. Las autoridades y las alcaldías, en el ámbito de sus respectivas competencias, deben desarrollar políticas para fortalecer la salud materno infantil, prácticas de lactancia materna y aumentar la esperanza de vida.\n\nArtículo 50. Las autoridades y los órganos político administrativos, en el ámbito de sus respectivas competencias impulsarán las acciones necesarias para garantizar los derechos sexuales y reproductivos de niñas, niños y adolescentes, estableciendo entre otras medidas las siguientes:\nI. Proporcionar asesoría y orientación gratuita sobre salud sexual y reproductiva,\nII. Prevenir embarazos de las niñas y las adolescentes;\nIII. Proporcionar servicios gratuitos y profesionales en materia de salud sexual y reproductiva.\nIV. Desarrollar campañas de comunicación masiva para prevenir el abuso sexual de niñas, niños y adolescentes, así como para el normal desarrollo psicosexual de las niñas y niños.\nArtículo 51. Las autoridades deben disponer lo necesario a fin de que el cuerpo médico, de enfermería, trabajo social y administrativo de clínicas, establecimientos de salud y hospitales del sector público y privado que atienden a niñas, niños y adolescentes, estén debidamente capacitados y sensibilizados en materia de sus derechos humanos.\nCAPÍTULO DÉCIMO\nDE LOS DERECHOS DE NIÑAS, NIÑOS Y ADOLESCENTES CON\nDISCAPACIDAD\nArtículo 52. Niñas, niños y adolescentes con discapacidad tienen derecho a la igualdad sustantiva y a disfrutar de los derechos contenidos en la presente Ley, la Constitución Política de los Estados Unidos\nMexicanos, los tratados internacionales y demás instrumentos jurídicos aplicables.\nCuando exista duda o percepción si una niña, niño o adolescente es persona con discapacidad, se presumirá que es una niña, niño o adolescente con discapacidad.\nSon niñas, niños o adolescentes con discapacidad quienes por razón congénita o adquirida presentan una o más deficiencias de carácter físico, mental, intelectual o sensorial, ya sea permanente o temporal y que al interactuar con las barreras que le impone el entorno social, pueda impedir su inclusión plena y efectiva, en igualdad de condiciones con los demás.\n\nArtículo 53. Niñas, niños y adolescentes con discapacidad tienen derecho a vivir en una sociedad inclusiva, a ser parte de una familia, a la atención, el respeto de los derechos sexuales y reproductivos, incluido el derecho a mantener su fertilidad, en igualdad de condiciones con las demás personas.\nLa atención de las niñas, niños y adolescentes con discapacidad mental, sea por causa psíquica o intelectual, buscará el desarrollo al máximo de sus capacidades y aptitudes.\nEn ninguna circunstancia, las niñas, niños y adolescentes con discapacidad podrán ser sometidas a prácticas o terapias que atenten contra su dignidad, integridad, derechos o formen parte de experimentos médicos o científicos.\nArtículo 54. Las autoridades y los órganos político administrativos, en el ámbito de sus respectivas competencias, están obligadas a implementar políticas públicas con enfoques de derechos humanos, perspectiva de género e igualdad sustantiva y no discriminación, además de medidas de nivelación, de inclusión y acciones afirmativas en términos de las disposiciones aplicables, considerando los principios de participación e inclusión plenas y efectivas en la sociedad, respeto por la diferencia de niñas, niños y adolescentes con discapacidad como parte de la diversidad, condición humana y la evolución de sus facultades.\nLa falta o negación de ajustes razonables es discriminación por motivos de discapacidad.\nLas autoridades y los órganos político administrativos, en el ámbito de sus respectivas competencias, están obligadas a realizar lo necesario para fomentar la inclusión social y deberán establecer la accesibilidad de niñas, niños y adolescentes con discapacidad, y desarrollar la implementación del diseño universal, en términos de la legislación aplicable.\nNo se podrá negar o restringir la inclusión de niñas, niños y adolescentes con discapacidad, el derecho a la educación ni su participación en actividades recreativas, deportivas, lúdicas o culturales en instituciones públicas, privadas y sociales.\nNo se considerarán discriminatorias las medidas específicas que sean necesarias para acelerar o lograr la igualdad sustantiva de las niñas, niños y adolescentes con discapacidad.\nArtículo 55. Las autoridades y los órganos político administrativos, en el ámbito de sus respectivas competencias y en coordinación con el Sistema para el Desarrollo Integral de la Familia, deberán impulsar, promover y garantizar el reconocimiento, ejercicio y defensa de los derechos de las niñas, niños y\n\nadolescentes con discapacidad. A efecto de prevenir la ocultación, abandono, negligencia y segregación.\nAdemás impulsarán y fomentarán el desarrollo de la independencia, autonomía e inclusión, promoviendo el desarrollo de sus capacidades, a través de acciones interinstitucionales y conforme a la perspectiva de género y el principio de progresividad.\nPara tales efectos, el DIF-CDMX a través de su Dirección Ejecutiva de los Derechos de las Personas con\nDiscapacidad se coordinará con dichas autoridades y órganos político administrativos, para realizar las siguientes acciones:\nI. Diseñar y realizar campañas de sensibilización orientadas a respetar y promover los derechos de las niñas, niños y adolescentes con discapacidad, así como combatir los estereotipos y prejuicios respecto de su discapacidad; la que deberán considerar la diversidad de personas con discapacidad, por lo que deberán contemplar el enfoque de género y todos los tipos de discapacidad;\nII. Promover acciones interinstitucionales de apoyo educativo, acceso a la cultura y de impulso de mecanismos que contribuyan al desarrollo de la independencia, autonomía, así como la inclusión social de las niñas, niños y adolescentes;\nEstas acciones se enfocarán también para la formación de quienes ejerzan la patria potestad, tutela o guarda y custodia de niñas, niños y adolescentes con discapacidad;\nIII. Promover acciones interdisciplinarias para el estudio, diagnóstico temprano, tratamiento y rehabilitación de las discapacidades de niñas, niños y adolescentes que en cada caso se necesiten, asegurando que sean accesibles a las posibilidades económicas de sus familiares o tutores;\nIV. Realizar acciones que permitan ofrecerles cuidados elementales gratuitos, acceso a programas de estimulación temprana, servicios de salud, rehabilitación, esparcimiento, actividades ocupacionales, así como a la capacitación para el trabajo y habilidades para la vida independiente;\nV. Establecer mecanismos que faciliten la recopilación periódica y sistemática de información y estadística de niñas, niños y adolescentes con discapacidad, que permita una adecuada formulación de políticas públicas en la materia para seguimiento y evaluación del desempeño gubernamental en el tema de niñas, niños y adolescentes con discapacidad;\n\nDichos reportes, informes o análisis estadísticos deberán desagregarse, al menos, por sexo, edad, escolaridad y tipo de discapacidad;\nVI. Crear y promover programas y proyectos con otras dependencias e instancias gubernamentales, así como con asociaciones civiles e iniciativa privada que busquen fomentar y promover el derecho a la accesibilidad, los cuales impulsen y fomenten el desarrollo de las capacidades de las niña, niños y adolescentes con discapacidad a sus familias y de la comunidad en inmuebles, espacios y transportes públicos y privados en igualdad de condiciones;\nVII. Establecer centros de información y denuncias de abuso y violación a sus derechos las niñas, niños y adolescentes con discapacidad; e\nVIII. Impulsar políticas, programas y acciones específicos que amplíen y mejoren la cobertura de servicios, la accesibilidad, la movilidad y la vida independiente de las niñas, niños y adolescentes con discapacidad principalmente las de escasos recursos.\nArtículo 56. Niñas, niños y adolescentes con discapacidad tienen derecho en todo momento a que se les facilite un intérprete o aquellos medios tecnológicos que les permitan obtener información de forma comprensible en los diversos aspectos de la vida cotidiana.\nCAPÍTULO DÉCIMO PRIMERO\nDEL DERECHO A LA EDUCACIÓN\nArtículo 57. Las niñas, niños y adolescentes tienen derecho a una educación de calidad que contribuya al conocimiento de sus propios derechos, basada en un enfoque de derechos humanos y de igualdad sustantiva, que garantice el respeto a su dignidad humana; el desarrollo armónico de sus potencialidades y personalidad y a las libertades fundamentales.\nQuienes ejerzan la patria potestad, tutela o guarda y custodia, tendrán derecho a participar en la educación que habrá de darse a niñas, niños y adolescentes, en términos de lo previsto por el artículo 89 de esta ley.\nArtículo 58. Las autoridades y los órganos político administrativos, en el ámbito de sus respectivas competencias garantizarán la consecución de una educación de calidad y la igualdad sustantiva en el acceso y permanencia en los servicios educativos que presten, para lo cual deberán:\n\nI. Proporcionar la atención educativa que las niñas, niños y adolescentes requieran para su pleno desarrollo, para lo cual, los programas respectivos deberán considerar la edad, madurez, circunstancias particulares y tradiciones culturales;\nII. Adoptar medidas orientadas hacia el pleno ejercicio del derecho a la educación;\nIII. Establecer medidas para garantizar la impartición de la educación pública, obligatoria y gratuita; así como procurar la accesibilidad material, económica y geográfica a la educación, sin discriminación;\nIV. Establecer las condiciones necesarias para fortalecer la calidad educativa, tales como la disposición de la infraestructura y equipamiento adecuados para el aprendizaje y para las prácticas de enseñanza, la evaluación docente, entre otras;\nV. Administrar los recursos destinados a la educación pública en la Ciudad de México para garantizar la educación de calidad de niñas, niños y adolescentes;\nVI. Establecer acciones afirmativas para garantizar el derecho a la educación de niñas, niños y adolescentes de grupos y regiones con mayor rezago educativo, dispersos o que enfrentan situaciones de vulnerabilidad por circunstancias específicas de carácter socioeconómico, físico, mental, de identidad cultural, origen étnico o nacional, situación migratoria, de orfandad, entorno familiar o bien, relacionadas con aspectos de género, preferencia sexual, creencias religiosas o prácticas culturales;\nFracción modificada y publicada en la GOCDMX el 10 de octubre de 2023\nVII. Prestar servicios educativos en condiciones de normalidad mínima, entendida ésta como el conjunto de condiciones indispensables que deben cumplirse en cada escuela para el buen desempeño de la tarea docente y el logro del aprendizaje de los educandos;\nVIII. Implementar mecanismos para la atención, canalización y seguimiento de los casos que constituyan violaciones al derecho a la educación de niñas, niños y adolescentes;\nIX. Fomentar la convivencia escolar armónica y la generación de mecanismos para la discusión, debate y resolución pacífica de conflictos;\n\nX. Establecer mecanismos para la prevención, atención y canalización para eliminar y erradicar los casos de maltrato, perjuicio, daño, agresión, abuso, acoso y/o violencia sexual o cualquier otra forma de violencia en contra de niñas, niños y adolescentes que se suscite en dentro y fuera de los centros educativos;\nFracción modificada y publicada en la GOCDMX el 10 de octubre de 2023\nXI. Se elaboren protocolos de actuación sobre situaciones de acoso o violencia escolar para el personal y para quienes ejerzan la patria potestad, tutela o guarda y custodia;\nXII. Adoptar medidas para responder a las necesidades de niñas, niños y adolescentes con aptitudes sobresalientes, de tal manera que se posibilite su desarrollo progresivo e integral, conforme a sus capacidades y habilidades personales;\nXIII. Establecer mecanismos para la expresión y participación de niñas, niños y adolescentes, conforme a su edad, desarrollo evolutivo, cognoscitivo y madurez que permita atender y tomar en cuenta sus intereses y preocupaciones en materia educativa;\nXIV. Contribuir a garantizar la permanencia y conclusión de la educación obligatoria de niñas, niños y adolescentes, para abatir el ausentismo, abandono y deserción escolares;\nXV. Promover la disciplina escolar de modo compatible con la dignidad humana, impidiendo la imposición de medidas de disciplina que no estén previamente establecidas, atenten contra la vida, la integridad física o mental de niñas, niños y adolescentes;\nXVI. Procurar la erradicación de las prácticas pedagógicas discriminatorias o excluyentes que atenten contra la dignidad humana o integridad, especialmente los tratos humillantes y degradantes;\nXVII. Educar a niñas, niños y adolescentes en el respeto al medio ambiente, inculcando en ellos la adopción de estilos de vida saludables y sustentables, así como concientizarlos sobre las causas y efectos del cambio climático;\nFracción modificada y publicada en la GOCDMX el 12 de junio de 2023\nXVIII. Establecer mecanismos y programas; que fomenten el uso responsable, respetuoso y seguro de las tecnologías de información y comunicación; mismos que serán adaptados\n\nconforme a la edad y tomando en cuenta el grado de desarrollo cognoscitivo y evolutivo de niñas, niños y adolescentes;\nXIX. Establecer acciones afirmativas que garanticen el acceso y permanencia de niñas y adolescentes embarazadas, faciliten su reingreso y promuevan su egreso del sistema educativo nacional;\nXX. Fortalecer la infraestructura tecnológica de las escuelas públicas para fomentar la formación científica y tecnológica de las niñas, niños y adolescentes;\nXXI. Establecer mecanismos para detectar los casos de niñas, niños y adolescentes que requieran atención especializada y coordinarse con las autoridades competentes a fin de que les sea garantizado el derecho de atención especializada en los sistemas de salud correspondientes; e\nXXII. Implementar acciones para proporcionar a las niñas, niños y adolescentes formación de inteligencia emocional.\nArtículo 59. La educación en su ámbito de competencia de las autoridades, además de lo dispuesto en las disposiciones aplicables, tendrá los siguientes fines:\nI. Fomentar en niñas, niños y adolescentes los valores fundamentales y el respeto de la identidad propia, así como a las diferencias culturales y opiniones diversas;\nII. Desarrollar la personalidad, las aptitudes y las potencialidades de niñas, niños y adolescentes;\nIII. Inculcar a niñas, niños y adolescentes sentimientos de identidad y pertenencia a su escuela, comunidad y nación, así como su participación activa en el proceso educativo y actividades cívicas en términos de las disposiciones aplicables;\nIV. Orientar a niñas, niños y adolescentes respecto a la formación profesional, las oportunidades de empleo y las posibilidades de carrera;\nV. Apoyar a niñas, niños y adolescentes que sean víctimas de maltrato y la atención especial de quienes se encuentren en situación de riesgo;\nVI. Prevenir el delito mediante el diseño y ejecución de programas;\n\nFracción modificada y publicada en la GOCDMX el 12 de junio de 2023\nVI Bis. Prevenir las adicciones mediante el diseño, ejecución de programas y campañas de información y concientización con carácter permanente dirigidas a niñas, niños y adolescentes, sobre los daños que provoca a la salud física, mental, emocional y su rendimiento escolar el consumo de sustancias psicoactivas;\nFracción añadida y publicada en la GOCDMX el 12 de junio de 2023\nVII. Emprender, en cooperación con quienes ejerzan la patria potestad, tutela o guarda y custodia, así como con grupos de la comunidad, la planificación, organización y desarrollo de actividades extracurriculares que sean de interés para niñas, niños y adolescentes;\nVIII. Promover la educación integral, científica, veraz, oportuna, incluyendo educación sexual conforme a su edad, el desarrollo evolutivo, cognoscitivo y madurez de las niñas, niños y adolescentes que les permitan ejercer de manera informada y responsable sus derechos humanos.\nIX. Promover el valor de la justicia, de la observancia de la ley y de la igualdad de las personas ante ésta, propiciar la cultura de la legalidad, de la paz y la no violencia en cualquier tipo de sus manifestaciones, así como el conocimiento de los derechos humanos y el respeto a los mismos;\nFracción modificada y publicada en la GOCDMX el 26 de diciembre de 2023\nX. Difundir los derechos humanos de niñas, niños y adolescentes y las formas de protección con que cuentan para ejercerlos; y\nFracción modificada y publicada en la GOCDMX el 26 de diciembre de 2023\nXI. Promover e inculcar en las niñas, niños y adolescentes la cultura de protección al medio ambiente, el aprovechamiento racional del agua y otros recursos naturales, así como la disminución de residuos plásticos de un solo uso.\nFracción añadida y publicada en la GOCDMX el 26 de diciembre de 2023\nArtículo 60. En materia de educación y cultura las niñas, niños y adolescentes tienen el derecho inalienable a las mismas oportunidades de acceso y permanencia a la educación obligatoria.\nCAPÍTULO DÉCIMO SEGUNDO\n\nDE LOS DERECHOS AL DESCANSO, AL JUEGO Y AL ESPARCIMIENTO\nArtículo 61. Niñas, niños y adolescentes tienen derecho al descanso, al esparcimiento, al juego y a las actividades recreativas propias de su edad, así como a participar libremente en actividades culturales, deportivas y artísticas, como factores primordiales de su desarrollo y crecimiento.\nQuienes ejerzan la patria potestad, tutela o guarda y custodia de niñas, niños y adolescentes protegerán el ejercicio de estos derechos y, por lo tanto, no podrán imponerles regímenes de vida, estudio, trabajo o reglas de disciplina desproporcionadas a su edad, desarrollo evolutivo, cognoscitivo y madurez.\nArtículo 62. Las autoridades y de los órganos político administrativos, en el ámbito de sus respectivas competencias, están obligadas a garantizar el derecho de niñas, niños y adolescentes al descanso y el esparcimiento y a fomentar oportunidades apropiadas, espacios adecuados y seguros en barrios, pueblos y colonias, en condiciones de igualdad, para su participación en actividades culturales, artísticas y deportivas dentro de su comunidad. Están obligadas también a fomentar el derecho al juego en espacios públicos y otros, como en ludotecas.\nArtículo 63. En materia de deporte y recreación, las autoridades y servidores públicos de la Ciudad de\nMéxico, competentes propiciarán:\nI. La inclusión en los programas, actividades, convenios, bases de colaboración, intercambios, apoyos, permisos, estímulos y demás actos similares o equivalentes que suscriba el Instituto del\nDeporte en ejercicio de sus atribuciones, la participación y presencia de niñas, niños y adolescentes, cuidando que no se afecte, menoscabe, excluya o restrinja el goce de sus derechos;\nII. La admisión gratuita de niñas, niños y adolescentes de escasos recursos en:\na) Establecimientos de la Administración Pública y privados que presten servicios de talleres, cursos o enseñanza deportiva apropiada para niñas, niños y adolescentes;\nb) Espectáculos Públicos Deportivos a los que se refiere la Ley de Espectáculos Públicos del Distrito Federal;\nIII. La elaboración de programas deportivos, actividades físicas y recreativas, para niñas, niños y adolescentes preferentemente de escasos recursos, para ser aplicados en espacios públicos y privados, poniendo dichos programas a disposición de instituciones gubernamentales y privadas;\n\nIV. Las actividades de recreación en las Delegaciones gestionadas por grupos vecinales o asociaciones con la colaboración de las niñas, niños y adolescentes;\nV. El deporte y las actividades de tiempo libre, tanto en el medio escolar como a través de la acción comunitaria y;\nVI. El desarrollo de grupos infantiles y juveniles para la recreación.\nArtículo 64. La Secretaría de Turismo fomentará el turismo de las niñas, niños y adolescentes dentro de la\nCiudad de México.\nCAPÍTULO DÉCIMO TERCERO\nDE LOS DERECHO DE LA LIBERTAD DE CONVICCIONES ÉTICAS,\nPENSAMIENTO, CONCIENCIA, RELIGIÓN Y CULTURA\nArtículo 65. Niñas, niños y adolescentes tienen derecho a la libertad de convicciones éticas, pensamiento, conciencia, religión y cultura. Las autoridades de los órganos político administrativos, en el ámbito de sus respectivas competencias garantizarán este derecho en el marco del Estado laico.\nLa libertad de profesar la propia religión o creencias estará sujeta únicamente a las limitaciones prescritas por la ley que sean necesarias para proteger los derechos y libertades fundamentales de los demás y garantizando el interés superior.\nNiñas, niños y adolescentes no podrán ser discriminados de forma alguna por ejercer su libertad de convicciones éticas, pensamiento, conciencia, religión y cultura.\nArtículo 66. Niñas, niños y adolescentes tienen derecho a ejercer libremente de su lengua, cultura, usos, costumbres, prácticas culturales, religión, recursos y formas específicas de organización social y todos los elementos que constituyan su identidad cultural; priorizando el interés superior.\nLas autoridades y de los órganos político administrativos, en el ámbito de sus respectivas competencias, estarán obligados a establecer políticas tendentes a garantizar la promoción, difusión y protección de la diversidad de las expresiones culturales, regionales y universales, de niñas, niños y adolescentes.\n\nLo dispuesto en este artículo no será limitativo del ejercicio del derecho a la educación, según lo dispuesto en el artículo 3o. de la Constitución Política de los Estados Unidos Mexicanos, ni de los principios rectores de esta Ley.\nArtículo 67. El derecho a la cultura propia de las niñas, niños y adolescentes pertenecientes a un grupo indígena, o en su caso, a un Pueblo originario de la Ciudad de México, comprende el derecho al reconocimiento y protección de los usos y costumbres heredados de sus ascendientes, barrio, pueblo o comunidad; la reivindicación de su historia y origen étnico; sus concepciones religiosas, musicales, educativas, estéticas, festivas; de vestido, lengua, y en general, de toda forma de expresión cultural propia de su origen histórico y étnico.\nComo un derecho fundamental de estas niñas, niños y adolescentes, y en términos del artículo 5º de la Ley\nGeneral de Derechos Lingüísticos de los Pueblos Indígenas, en la Ciudad de México con carácter prioritario se reconocerá, protegerá y promoverá la preservación, desarrollo y uso de la lengua materna indígena nacional entre niñas, niños y adolescentes etnohablantes de origen, residentes o huéspedes de la Ciudad de México; y como parte de las acciones afirmativas prescritas en el Capítulo Sexto de esta ley, el Gobierno de la Ciudad les proporcionará un intérprete o traductor de la misma, con el solo requisito de que así lo justifique su necesidad o circunstancia.\nCAPÍTULO DÉCIMO CUARTO\nDE LOS DERECHOS A LA LIBERTAD DE EXPRESIÓN Y DE ACCESO A LA\nINFORMACIÓN\nArtículo 68. Las autoridades y de los órganos político administrativos, en el ámbito de sus respectivas competencias deberán garantizar el derecho de niñas, niños y adolescentes a expresar su opinión libremente, así como a buscar, recibir y difundir información e ideas de toda índole, adecuada a su edad y desarrollo y por cualquier medio, sin más limitaciones que las establecidas en el artículo 6o. de la\nConstitución Política de los Estados Unidos Mexicanos.\nLa libertad de expresión de niñas, niños y adolescentes conlleva el derecho a que se tome en cuenta su opinión respecto de los asuntos que les afecten directamente, o a sus familias o comunidades. Dichas autoridades, en el ámbito de sus respectivas competencias, deberán establecer las acciones que permitan escucha efectiva, por medio de entrevistas o cualquier otro mecanismo, a niñas, niños y adolescentes sobre temas de interés general para ellas y ellos, así como la recopilación de opiniones, la sistematización y los mecanismos para tomar en cuenta dichas opiniones.\n\nEn poblaciones predominantemente indígenas, las autoridades a que se refiere este artículo, tienen la obligación de difundir la información institucional y la promoción de los derechos en la lengua indígena local.\nAsimismo, las autoridades a que se refiere este artículo dispondrán lo necesario para garantizar que niñas, niños y adolescentes con discapacidad cuenten con la accesibilidad para ejercer su derecho a la libertad de expresión, acceso a la información y expresión de su voluntad.\nArtículo 69. Niñas, niños y adolescentes tienen derecho al libre acceso a la información. Las autoridades y los órganos político administrativos, en el ámbito de sus respectivas competencias promoverán la difusión de información y material que tengan por finalidad asegurar su bienestar social y ético, así como su desarrollo cultural y salud física y mental, incluyendo la perspectiva de género y el lenguaje no sexista.\nIncluyendo el debido acceso a consultar el Registro Público de Personas Agresores Sexuales, en sus diversos apartados.\nEl Sistema de Protección acordará lineamientos generales sobre los contenidos de la información y materiales para difusión entre niñas, niños y adolescentes, conforme a lo dispuesto en esta Ley.\nArtículo 70. Las autoridades y los órganos político administrativos, en el ámbito de sus respectivas competencias, promoverán mecanismos para la protección de los intereses de niñas, niños y adolescentes, respecto de los riesgos derivados del acceso a medios de comunicación y uso de sistemas de información que afecten o impidan objetivamente su desarrollo integral.\nArtículo 71. Cualquier persona interesada, por conducto de la Procuraduría de Protección, podrá promover ante las autoridades administrativas competentes la imposición de sanciones a los medios de comunicación local, en los términos que establece esta Ley y demás disposiciones aplicables.\nAsimismo, la Procuraduría de Protección estará facultada para promover acciones colectivas ante el órgano jurisdiccional competente, con objeto de que éste ordene a los medios de comunicación que se abstengan de difundir información o contenidos que pongan en peligro de forma individual o colectiva, la vida, la integridad, la dignidad o cualquier otro derecho de niñas, niños y adolescentes, y, en su caso, reparen los daños que se hubieren ocasionado, sin menoscabo de las atribuciones que sobre esta materia tengan las autoridades competentes.\n\nLo anterior, sin perjuicio de cualquier otra responsabilidad a la que hubiere lugar de conformidad con las disposiciones aplicables.\nCAPÍTULO DÉCIMO QUINTO\nDEL DERECHO A LA PARTICIPACIÓN\nArtículo 72. Niñas, niños y adolescentes tienen derecho a ser escuchados y tomados en cuenta en los asuntos de su interés, conforme a su edad, desarrollo evolutivo, cognoscitivo y madurez y que estos sean reconocidos por su entorno familiar y comunitario.\nArtículo 73. Las autoridades y los órganos político administrativos, en el ámbito de sus respectivas competencias, están obligadas a disponer e implementar, acciones, mecanismos y condiciones que garanticen la participación permanente y activa de niñas, niños y adolescentes en las decisiones que se toman en los ámbitos familiar, escolar, social, comunitario o cualquier otro en el que se desarrollen. Los mecanismos deberán considerar los aspectos culturales, éticos, afectivos, educativos y de salud de niñas, niños y adolescentes, de acuerdo a su edad, desarrollo evolutivo, cognoscitivo y madurez.\nLa familia, sociedad y comunidad promoverán las acciones tendientes al ejercicio del derecho de participación en sus respectivos ámbitos.\nArtículo 74. Las autoridades y servidores públicos en sus respectivas competencias fomentarán la creación de espacios de participación para que las niñas, niños y adolescentes:\nI. Se organicen de conformidad con sus intereses y en los términos de las disposiciones jurídicas aplicables;\nII. Opinen, analicen, y en general, puedan expresar su punto de vista y propuestas, de forma individual o colectiva, en todos aquellos asuntos de su interés y éstos sean tomados en cuenta;\nIII. Participen en el fomento a la cultura de respeto a sus derechos; y\nIV. Participen en programas de educación para la democracia y la tolerancia.\nArtículo 75. Niñas, niños y adolescentes tienen derecho a participar, a ser escuchados y tomados en cuenta conforme a su edad, desarrollo evolutivo, cognoscitivo y madurez, en todos los procesos judiciales y de\n\nprocuración de justicia donde se diriman controversias que les afectan, estando obligadas las autoridades correspondientes a informarles en formatos de lectura fácil y/u otros medios, que les permitan comprender los procesos de forma sencilla y clara.\nAdemás, tienen derecho a conocer la sentencia que decida sobre sus derechos, debiendo la autoridad judicial o quien ejerza la representación jurídico procesal, comunicar o justificar en su caso, la razón por la que no se informó la resolución a la niña, niño o adolescente.\nArtículo modificado y publicado en la GOCDMX el 29 de abril de 2024\nArtículo 76. Niñas, niños y adolescentes también tienen derecho a que las autoridades de la Ciudad de\nMéxico les informen, con el mismo criterio de formatos mencionados en el artículo anterior, de qué manera su opinión ha sido valorada y tomada en cuenta su solicitud.\nArtículo modificado y publicado en la GOCDMX el 29 de abril de 2024\nCAPÍTULO DÉCIMO SEXTO\nDEL DERECHO DE ASOCIACIÓN Y REUNIÓN\nArtículo 77. Niñas, niños y adolescentes tienen derecho a asociarse y reunirse, sin más limitaciones que las establecidas en la Constitución Política de los Estados Unidos Mexicanos.\nQuienes ejerzan la patria potestad, tutela o guarda y custodia representarán a niñas, niños y adolescentes para el ejercicio del derecho de asociación, cuando ello sea necesario para satisfacer las formalidades que establezcan las disposiciones aplicables.\nLas autoridades y de los órganos político administrativos fomentarán el ejercicio del derecho de asociación y reunión; asimismo establecerán las condiciones para que puedan hacer efectivo este derecho en un marco de seguridad y respeto a su integridad.\nCAPÍTULO DÉCIMO SÉPTIMO\nDEL DERECHO A LA INTIMIDAD\nArtículo 78. Niñas, niños y adolescentes tienen derecho a la intimidad personal y familiar, y a la protección de sus datos personales.\n\nMadres, padres, así como cualquier otra persona que tenga bajo su cuidado a niñas, niños y adolescentes, se abstendrán de compartir en redes sociales o plataformas digitales, desnudos de éstos. Por desnudo para efectos del presente artículo se entenderá:\nPárrafo adicionado y publicado en la GOCDMX el 21 de abril de 2023\nI. Primeros planos de genitales.\nII. Desnudos reales en los que se muestren:\na. Genitales visibles, incluso si están cubiertos u ocultos por ropa transparente o por vello púbico.\nb. Ano o primeros planos de glúteos completamente desnudos.\nc. Pezones de niñas, niños y adolescentes al descubierto.\nFracciones adicionadas y publicadas en la GOCDMX el 21 de abril de 2023\nQuien tenga conocimiento de estas acciones dará vista a la Procuraduría de Protección para efectos del artículo 83 de esta Ley.\nPárrafo adicionado y publicado en la GOCDMX el 21 de abril de 2023\nNiñas, niños y adolescentes no podrán ser objeto de injerencias arbitrarias o ilegales en su vida privada, su familia, su domicilio o su correspondencia; tampoco de divulgaciones o difusiones ilícitas de información o datos personales, incluyendo aquélla que tenga carácter informativo a la opinión pública o de noticia que permita identificarlos y que atenten contra su honra, imagen o reputación.\nQuienes ejerzan la patria potestad, tutela o guarda y custodia, deberán orientar, supervisar y, en su caso, restringir, las conductas y hábitos de niñas, niños y adolescentes, siempre que atiendan al interés superior.\nArtículo 79. Se considerará violación a la intimidad de niñas, niños o adolescentes cualquier manejo directo de su imagen, nombre, datos personales o referencias que permitan su identificación en cualquier medio de comunicación, que menoscabe su dignidad, honra o reputación, sea contrario a sus derechos o que los ponga en riesgo, conforme al principio de interés superior, aun cuando esta acción sea realizada por sus madres, padres, tutores o sus personas representantes.\nPárrafo modificado y publicado en la GOCDMX el 21 de abril de 2023\n\nEn estos supuestos las niñas, niños y adolescentes a través de su representante, podrán promover las acciones civiles de reparación del daño e iniciar los procedimientos por la responsabilidad administrativa a que haya lugar ante las autoridades competentes; así como dar seguimiento a los procedimientos hasta su conclusión.\nArtículo 80. Cualquier medio de comunicación local que difunda entrevistas a niñas, niños y adolescentes, procederá como sigue:\nI. Deberá recabar el consentimiento por escrito o cualquier otro medio, de quienes ejerzan la patria potestad o tutela, así como la opinión de la niña, niño o adolescente, respectivamente, siempre que ello no implique una afectación a sus derechos, en especial su derecho a la privacidad; y\nII. La persona que realice la entrevista será respetuosa y no podrá mostrar actitudes ni emitir comentarios que afecten o impidan objetivamente el desarrollo integral de niñas, niños y adolescentes.\nEn el caso de que no sea posible recabar el consentimiento de quienes ejerzan la patria potestad o tutela de un adolescente, éste podrá otorgarlo siempre que ello no implique una violación a su derecho a la intimidad. En caso de haberse otorgado bajo este supuesto, se deberá proceder en términos de lo establecido por el artículo 79, último párrafo.\nArtículo 81. Las autoridades y los órganos político administrativos, en el ámbito de sus respectivas competencias, garantizarán la protección de la identidad e intimidad de niñas, niños y adolescentes que sean víctimas, ofendidos, testigos o que estén relacionados de cualquier manera en la comisión de un delito, a fin de evitar su identificación pública. Por lo que ningún dato que permita localizar e identificar a las víctimas de delitos vinculados con la violencia sexual, deberá incluirse en el Registro Público de\nPersonas Agresores Sexuales.\nArtículo 82. Los medios de comunicación locales deberán asegurarse que las imágenes, voz o datos a difundir, no pongan en peligro, de forma individual o colectiva, la vida, integridad, dignidad o vulneren el ejercicio de los derechos de niñas, niños y adolescentes, aun cuando se modifiquen, se difuminen o no se especifiquen sus identidades, y evitarán la difusión de imágenes o noticias que propicien o sean tendentes a su discriminación, criminalización o estigmatización, en contravención a las disposiciones aplicables.\n\nEn caso de incumplimiento a lo establecido en el presente artículo, niñas, niños o adolescentes afectados, considerando su edad, grado de desarrollo cognoscitivo y madurez, podrán acudir ante la Procuraduría de\nProtección de manera directa o por conducto de su representante legal o, en su caso, la Procuraduría de\nProtección, actuando de oficio o en representación sustituta, podrá promover las acciones civiles de reparación del daño e iniciar los procedimientos por la responsabilidad administrativa a que haya lugar ante la autoridad competente; así como dar seguimiento a los procedimientos hasta su conclusión.\nEn los procedimientos civiles o administrativos que sean iniciados o promovidos por quienes ejerzan la patria potestad, tutela o guarda y custodia de niñas, niños y adolescentes, la Procuraduría de Protección ejercerá su representación coadyuvante.\nArtículo 83. Las niñas, niños o adolescentes, a través de persona de su confianza, podrán solicitar ante la autoridad competente, el retiro inmediato de su información, imágenes o videos de los medios de comunicación o plataformas digitales o electrónicas y redes sociales de sus madres, padres, tutores o personas representantes que contravengan su interés superior.\nPárrafo modificado y publicado en la GOCDMX el 21 de abril de 2023\nLa autoridad competente, con base en este artículo y en las disposiciones aplicables, podrá requerir a las empresas de prestación de servicios en materia de medios electrónicos que realicen las acciones necesarias para el cumplimiento de las medidas cautelares que ordene.\nCAPÍTULO DÉCIMO OCTAVO\nDEL DERECHO A LA SEGURIDAD JURÍDICA, ACCESO A LA JUSTICIA Y\nAL DEBIDO PROCESO\nArtículo 84. Niñas, niños y adolescentes gozan de los derechos y garantías de acceso a la justicia, seguridad jurídica y debido proceso establecidos en la Constitución Política de los Estados Unidos Mexicanos, los tratados internacionales, esta Ley y demás disposiciones aplicables.\nArtículo 85. Las autoridades y los órganos político administrativos, que sustancien procedimientos de carácter jurisdiccional o administrativo o que realicen cualquier acto de autoridad en los que estén relacionados niñas, niños o adolescentes, de conformidad con su edad, desarrollo evolutivo, cognoscitivo y grado de madurez estarán obligadas a observar, cuando menos:\n\nI. Garantizar la protección y prevalencia del interés superior a que se refiere el artículo 7 de la presente Ley;\nII. Garantizar el ejercicio o el goce de los derechos de niñas, niños y adolescentes, establecidos en la Constitución Política de los Estados Unidos Mexicanos, los tratados internacionales, la Ley\nGeneral, esta Ley y demás disposiciones aplicables en esta materia;\nIII. Proporcionar información clara, sencilla y comprensible para las niñas, niños y adolescentes sobre el procedimiento judicial o administrativo de que se trate y la importancia de su participación en el mismo, así como darles a conocer la sentencia que decida sobre sus derechos.\nPara garantizar lo anterior, se incluirán, en su caso, formatos accesibles de fácil comprensión y lectura, así como otros mecanismos de apoyo que requieran niñas, niños y adolescentes, especialmente quienes tengan una discapacidad;\nFracción modificada y publicada en la GOCDMX el 29 de abril de 2024\nIV. Implementar mecanismos de apoyo necesarios al presentar una denuncia, participar en una investigación o en un proceso judicial, garantizando que sean eficaces, accesibles y seguros para las víctimas, asimismo las autoridades deberán implementar en todo momento medidas para proteger la identidad y datos personales de quien presente una denuncia;\nFracción modificada y publicada en la GOCDMX el 29 de abril de 2024\nV. Garantizar el derecho de niñas, niños y adolescentes a ser representados en términos de lo dispuesto en el Título Cuarto, Capítulo Segundo, Sección Tercera, de la presente Ley, así como información sobre las medidas de protección disponibles;\nVI. Proporcionar asistencia de profesionales especializados cuando la naturaleza del procedimiento lo requiera;\nVII. Proporcionar la asistencia de un traductor o intérprete;\nVIII. Ponderar, antes de citar a una niña, niño o adolescente a alguna audiencia, la pertinencia de la misma, considerando su edad, madurez, estado psicológico, así como cualquier otra condición específica;\n\nIX. Garantizar el acompañamiento de quien ejerza sobre ellos la patria potestad, tutela, guarda o custodia durante la sustanciación de todo el procedimiento, salvo disposición judicial en contrario;\nX. Mantener a niñas, niños o adolescentes apartados de los adultos que puedan influir en su comportamiento o estabilidad emocional, cuando así lo determine la autoridad competente, antes y durante la realización de la audiencia o comparecencia respectiva;\nXI. Destinar espacios lúdicos de descanso y aseo para niñas, niños y adolescentes en los recintos en que se lleven a cabo procedimientos en que deban intervenir;\nXII. Ajustarse al tiempo de participación máximo para la intervención de niñas, niños o adolescentes durante la sustanciación de los procedimientos de conformidad con los principios de autonomía progresiva y celeridad procesal y;\nXIII. Implementar medidas para proteger a niñas, niños o adolescentes de sufrimientos durante su participación y garantizar el resguardo de su intimidad y datos personales.\nArtículo 86. Cuando la Procuraduría de Protección tenga conocimiento de la presunta comisión o participación de una niña o niño en un hecho que la ley señale como delito, en el marco de sus atribuciones, solicitará a la autoridad competente de manera inmediata las medidas necesarias para la protección integral, de asistencia social y en su caso, restitución de sus derechos y garantizar que niñas y niños no sean objeto de discriminación.\nArtículo 87. Las autoridades y los órganos político administrativos, en el ámbito de sus respectivas competencias, garantizarán que en los procedimientos jurisdiccionales en que estén relacionadas niñas, niños o adolescentes como probables víctimas de violación a sus derechos humanos, de algún delito o sean testigos, de conformidad con su edad, desarrollo evolutivo, cognoscitivo y grado de madurez, tengan al menos los siguientes derechos:\nPárrafo modificado y publicado en la GOCDMX el 29 de abril de 2024\nI. Se les informe con un lenguaje claro, sencillo y sin tecnicismos sobre la naturaleza del procedimiento y el carácter de su participación en el mismo, el que en ningún caso podrá ser el de imputado o probable responsable;\nFracción modificada y publicada en la GOCDMX el 29 de abril de 2024\n\nI.BIS. Contar con mecanismos claros, sencillos y de fácil acceso para presentar denuncias cuando sean víctimas de violación de sus derechos humanos o de algún delito;\nFracción adicionada y publicada en la GOCDMX el 29 de abril de 2024\nII. Que su participación en un procedimiento se lleve a cabo de la manera más expedita, asistidos por un profesional en derecho y atendiendo a lo dispuesto por la fracción XI del artículo 85 de esta Ley;\nIII. Garantizar el acompañamiento de quien ejerza sobre ellos la patria potestad, tutela o guarda y custodia durante la sustanciación de todo el procedimiento, salvo disposición judicial en contrario, con base en el interés superior;\nIV. Que se preserve su derecho a la intimidad, que no se divulguen sus datos de identificación en los términos de esta Ley y las demás aplicables;\nV. Tener acceso gratuito a asistencia jurídica, psicológica y cualquier otra necesaria atendiendo a las características del caso, a fin de salvaguardar sus derechos, en términos de las disposiciones aplicables, y\nVI. Adoptar en todas las etapas del procedimiento las medidas necesarias para evitar la revictimización de niñas, niños y adolescentes que presuntamente son víctimas de la comisión de un delito o violación a sus derechos humanos.\nFracción modificada y publicada en la GOCDMX el 29 de abril de 2024\nArtículo 88. Siempre que se encuentre una niña, niño o adolescente en el contexto de la comisión de un delito, se notificará de inmediato a quienes ejerzan la patria potestad, tutela o guarda y custodia, así como a la Procuraduría de Protección.\nCAPÍTULO DÉCIMO NOVENO\nDERECHO DE ACCESO A LAS TECNOLOGÍAS DE LA INFORMACIÓN Y\nCOMUNICACIÓN\nArtículo 88 Bis. Niñas, niños y adolescentes gozan del derecho de acceso universal a las Tecnologías de la\nInformación y Comunicación, así como a los servicios de radiodifusión y telecomunicaciones, incluido el de banda ancha e Internet.\n\nArtículo 88 Ter. Las autoridades garantizarán a niñas, niños y adolescentes su integración a la sociedad de la información y el conocimiento e impulsarán el uso de las tecnologías de la información y la comunicación mediante una política de inclusión digital universal y de conformidad con la Agenda Digital Educativa en condiciones de equidad, asequibilidad, disponibilidad, accesibilidad, calidad. El reglamento y las reglas de operación determinarán los criterios para establecer las acciones y la progresividad de este derecho.\nLas autoridades correspondientes, rendirán un informe escrito anual ante la Comisión de Atención al\nDesarrollo de la Niñez del Congreso de la Ciudad de México, respecto de la situación que guarda el Derecho de Acceso a las Tecnologías de la información y la Comunicación de niñas, niños y adolescentes en la Ciudad de México.\nArtículo 88 Quáter. Niñas, niños y adolescentes tienen derecho al acceso y uso seguro del Internet como medio efectivo para ejercer los derechos a la información, comunicación, educación, salud, esparcimiento, no discriminación, de conformidad con el principio de interdependencia, en términos de las disposiciones aplicables. Asimismo, tendrán derecho a recibir información suficiente y necesaria sobre el uso responsable, respetuoso y adecuado de las tecnologías.\nTÍTULO TERCERO\nDE LAS OBLIGACIONES\nCAPÍTULO ÚNICO\nDE QUIENES EJERCEN LA PATRIA POTESTAD, TUTELA O GUARDA Y\nCUSTODIA O CUIDADOS ALTERNATIVOS DE NIÑAS, NIÑOS Y\nADOLESCENTES\nArtículo 89. Son obligaciones de quienes ejercen la patria potestad, tutela o guarda y custodia, así como de las demás personas que por razón de sus funciones o actividades tengan bajo su cuidado niñas, niños o adolescentes, en proporción a su responsabilidad y, cuando sean instituciones públicas, conforme a su ámbito de competencia, las siguientes:\nI. Realizar y tomar todas las medidas necesarias a fin de garantizar que niñas, niños y adolescentes gocen plenamente del derecho a la vida, a la paz, a la supervivencia y al desarrollo integral;\n\nII. Garantizar sus derechos alimentarios, el libre desarrollo de su personalidad y el ejercicio de sus derechos, de conformidad con lo dispuesto en la presente Ley y demás disposiciones aplicables.\nPara los efectos de esta fracción, los derechos alimentarios comprenden esencialmente la satisfacción de las necesidades de alimentación y nutrición, habitación, educación, vestido, atención médica y psicológica preventiva integrada a la salud, asistencia médica y recreación;\nIII. Registrarlos dentro de los primeros sesenta días de vida;\nIV. Asegurar que cursen la educación obligatoria, participar en su proceso educativo y proporcionarles las condiciones para su continuidad y permanencia en el sistema educativo;\nV. Asegurar un entorno afectivo, comprensivo y sin violencia para el pleno, armonioso y libre desarrollo de su personalidad;\nVI. Fomentarles el respeto a todas las personas, así como el cuidado de los bienes propios, de la familia y de la comunidad, y el aprovechamiento de los recursos que se dispongan para su desarrollo integral;\nVII. Protegerles contra toda forma de violencia, maltrato, perjuicio, daño, agresión, abuso, venta, trata de personas y cualquier forma de explotación;\nVIII. Abstenerse de cualquier atentado contra su integridad física, psicológica o actos que menoscaben su desarrollo integral. El ejercicio de la patria potestad, la tutela o la guarda y custodia no podrá ser justificación para incumplir la obligación prevista en la presente fracción;\nVIII BIS. Transportar a niñas, niños y adolescentes, conforme a las normas en materia de movilidad.\nIX. Evitar conductas que puedan vulnerar el ambiente de respeto y generar violencia o rechazo en las relaciones entre niñas, niños y adolescentes, y de éstos con quienes ejercen la patria potestad, tutela o guarda y custodia, así como con los demás miembros de su familia;\nX. Considerar su opinión y preferencia para la toma de decisiones que les conciernan de manera directa conforme a su edad, desarrollo evolutivo, cognoscitivo y madurez;\n\nXI. Educar en el conocimiento, respeto y uso responsable de las tecnologías de la información y comunicación y;\nXII. Promover y fomentar acciones libres de prejuicios, roles, estereotipos que denigren a las niñas, niños y las adolescentes; y\nXIII. Sensibilizar sobre los riesgos y amenazas respecto del contenido generado al utilizar medios de comunicación digitales.\nEn casos de controversia, el órgano jurisdiccional competente determinará el grado de responsabilidad de quien tenga a su cargo y cuidado a niñas, niños o adolescentes, atendiendo a los principios rectores de esta\nLey.\nArtículo 90. Quienes ejerzan la patria potestad, tutela o cuidado alternativo o guarda y custodia de niñas, niños y adolescentes, independientemente de que habiten en domicilios distintos, darán cumplimiento a las obligaciones a su cargo de manera coordinada y respetuosa.\nLas autorizaciones a que se refiere esta Ley deberán ser otorgadas por quienes ejerzan la patria potestad o tutela, en los mismos términos y con las mismas formalidades.\nArtículo 91. Quienes ejerzan la patria potestad, tutela o cuidado alternativo o guarda y custodia de niñas, niños y adolescentes, independientemente de que habiten en domicilios distintos, darán cumplimiento a las obligaciones a su cargo de manera coordinada y respetuosa.\nLas autorizaciones a que se refiere esta Ley deberán ser otorgadas por quienes ejerzan la patria potestad o tutela, en los mismos términos y con las mismas formalidades.\nArtículo 92. Quienes ejerzan la patria potestad, tutela o guarda y custodia de niñas, niños y adolescentes, los cuiden y atiendan; deberán protegerlos contra toda forma de abuso; tratarlos con respeto a su dignidad y orientarlos, a fin de que conozcan sus derechos, aprendan a defenderlos y a respetar los de otras personas.\nArtículo 93. Las autoridades, previa consulta a la autoridad migratoria, verificarán la existencia de la autorización de quienes ejerzan la patria potestad, tutela o, en su caso, del órgano jurisdiccional competente, que permita la entrada y salida de niñas, niños o adolescentes del territorio nacional, conforme a las disposiciones aplicables.\n\nArtículo 94. Las personas que laboran y apoyan en instituciones de salud, asistencia social, académicas, deportivas, religiosas o de cualquier otra índole, se abstendrán de ejercer cualquier forma de violencia, maltrato, perjuicio, agresión, daño, abuso, acoso y explotación en contra de niñas, niños o adolescentes, y formularan programas e impartirán cursos de formación permanente para prevenirlas y erradicarlas.\nArtículo 95. Quienes tengan trato con niñas, niños y adolescentes se abstendránde ejercer cualquier tipo de violencia y se prohíbe el uso del castigo corporal como método correctivo o disciplinario.\nArtículo 96. A falta de quienes ejerzan la representación originaria de niñas, niños y adolescentes, o cuando por otra causa así lo determine el órgano jurisdiccional o autoridad administrativa competente, con base en el interés superior, la representación en suplencia corresponderá a la Procuraduría de Protección.\nLas autoridades y de los órganos político administrativos garantizarán que en cualquier procedimiento jurisdiccional o administrativo se dé intervención a la Procuraduría de Protección para que ejerza la representación coadyuvante, de conformidad con lo dispuesto en esta Ley y en las demás disposiciones aplicables.\nAsimismo, el Ministerio Público o la Procuraduría de Protección en los casos que existan indicios de conflicto de intereses entre quienes ejerzan la representación originaria o de éstos con niñas, niños y adolescentes o por una representación deficiente o dolosa, solicitarán al órgano jurisdiccional o administrativo que conozca del asunto que se sustancie por vía incidental, un procedimiento sumario de restricción, suspensión o revocación de la representación originaria, según sea el caso, para efectos de que la Procuraduría de Protección de la Ciudad de México ejerza la representación en suplencia\nEl Ministerio Público tendrá la intervención que las leyes dispongan en los procedimientos jurisdiccionales o administrativos en que niñas, niños o adolescentes estén relacionados. En materia de justicia penal, se estará a lo dispuesto en la Constitución Política de los Estados Unidos Mexicanos, esta Ley y demás disposiciones aplicables.\nNo podrá declararse la caducidad ni la prescripción en perjuicio de niñas, niños y adolescentes.\nTÍTULO CUARTO\nDE LA PROTECCIÓN Y RESTITUCIÓN INTEGRAL DE LOS DERECHOS DE\nNIÑAS, NIÑOS Y ADOLESCENTES\n\nCAPÍTULO PRIMERO\nDE LAS AUTORIDADES\nArtículo 97. Las autoridades, de los órganos político administrativos y de los organismos públicos autónomos, en el ámbito de su competencia, deberán establecer y garantizar el cumplimiento de la política local en materia de derechos de niñas, niños y adolescentes.\nLas políticas públicas emprendidas por dichas autoridades garantizarán el ejercicio de los derechos de niñas, niños y adolescentes, para lo cual deberán observar el interés superior y asegurar la asignación prioritaria de recursos en términos de las disposiciones aplicables.\nArtículo 98. Las autoridades y los órganos político administrativos coadyuvarán para el cumplimiento de los objetivos de esta Ley, de conformidad con las competencias previstas en el presente ordenamiento y demás disposiciones legales aplicables.\nArtículo 99. Corresponde a las autoridades y sus órganos político administrativos en el ámbito de su competencia, las atribuciones siguientes:\nI. Coordinar la implementación y ejecución de las acciones y políticas públicas que deriven de la presente Ley;\nII. Impulsar el conocimiento de los derechos de niñas, niños y adolescentes, así como la cultura de respeto, promoción y protección de los mismos, de conformidad con los principios rectores de esta Ley;\nIII. Garantizar el cabal cumplimiento de la presente Ley y de los instrumentos internacionales aplicables;\nIV. Adoptar medidas de protección especial de derechos de niñas, niños y adolescentes que se encuentren en situación de vulnerabilidad por circunstancias específicas de carácter socioeconómico, psicológico, físico, discapacidad, identidad cultural, origen étnico o nacional, situación migratoria o bien, relacionadas con aspectos de género, preferencia sexual, creencias religiosas o prácticas culturales, u otros que restrinjan o limiten sus derechos;\n\nV. Proporcionar asistencia médica, psicológica y atención preventiva integrada a la salud, así como asesoría jurídica y orientación social a quienes ejerzan la patria potestad, tutela o guarda y custodia de niñas, niños y adolescentes o personas que los tengan bajo su responsabilidad, en relación a las obligaciones que establece esta Ley;\nVI. Realizar las medidas necesarias a fin de garantizar el derecho a la vida, a la paz, al desarrollo y la supervivencia, así como investigar, sancionar efectivamente los actos de privación de la vida en perjuicio de niñas, niños y adolescentes y garantizar la reparación del daño que corresponda;\nVII. Investigar y en su caso sancionar efectivamente los actos constitutivos de delitos en agravio de niñas, niños y adolescentes;\nVIII. Colaborar en la búsqueda, localización y obtención de la información necesaria para acreditar o restablecer la identidad de niñas, niños y adolescentes;\nIX. Establecer políticas de fortalecimiento familiar para evitar la separación de niñas, niños y adolescentes de quienes ejerzan la patria potestad, tutela o guarda y custodia;\nX. Establecer las normas y los mecanismos necesarios para facilitar la localización y reunificación de la familia de niñas, niños y adolescentes, cuando hayan sido privados de ella, siempre que no sea contrario a su interés superior;\nXI. Coadyuvar en la localización de niñas, niños y adolescentes sustraídos, trasladados o retenidos ilícitamente;\nXII. Implementar medidas de inclusión plena y realizar las acciones afirmativas para garantizar a niñas, niños y adolescentes la igualdad de oportunidades y de trato, así como a no ser discriminados;\nXIII. Promover medidas para la eliminación de usos, costumbres, prácticas culturales, religiosas, estereotipos sexistas o prejuicios que atenten contra la igualdad de niñas, niños y adolescentes por razón de género o que promuevan cualquier tipo de discriminación, garantizando el interés superior;\nXIV. Adoptar las medidas apropiadas para promover la recuperación física y psicológica y la restitución de derechos de niñas, niños y adolescentes, víctimas de cualquier forma de violencia;\n\nXV. Garantizar que todos los sectores de la sociedad tengan acceso a educación y asistencia en materia de principios básicos de salud y nutrición, ventajas de la lactancia materna, así como la prevención de embarazos, higiene, medidas de prevención de accidentes y demás aspectos relacionados con la salud de niñas, niños y adolescentes;\nXVI. Propiciar las condiciones idóneas para crear un ambiente libre de violencia en las instituciones educativas, centros de asistencia, centros de atención y cuidado, así como instituciones que tengan a su disposición a niñas, niños y adolescentes mientras se resuelve su situación jurídica;\nXVII. Establecer el diseño universal, la accesibilidad y políticas para la prevención, atención y rehabilitación de niñas, niños y adolescentes con discapacidad, en términos de la legislación aplicable;\nXVIII. Realizar acciones a fin de sensibilizar a la sociedad, para que tome mayor conciencia respecto de las niñas, niños y adolescentes con discapacidad y fomentar el respeto a sus derechos y dignidad, así como combatir los estereotipos y prejuicios respecto de su discapacidad;\nXIX. Disponer e implementar los mecanismos que garanticen la participación permanente y activa de niñas, niños y adolescentes en las decisiones que se toman en los ámbitos familiar, escolar, social, comunitario o cualquier otro en el que se desarrollen;\nXX. Garantizar la consecución de una educación de calidad y la igualdad sustantiva en el acceso y permanencia en la misma dentro del sistema educativo que imparta la Ciudad de México;\nXXI. Impulsar la formación y actualización de acuerdos interinstitucionales de coordinación entre las diferentes instancias de gobierno;\nXXII. Celebrar convenios de cooperación, coordinación y concertación en la materia;\nXXIII. Coadyuvar con las instituciones públicas o privadas dedicadas a la atención de niñas, niños y adolescentes;\n\nXXIV. Garantizar la protección de los derechos de niñas, niños y adolescentes y asegurar que las violaciones a los mismos sean atendidas de forma preferente por todas las autoridades, en el ámbito de sus respectivas competencias;\nXXV. Desarrollar todos los mecanismos necesarios para el cumplimiento de la presente Ley, y\nXXVI. Garantizar que niñas, niños y adolescentes tengan acceso a agua potable para su consumo e higiene.\nArtículo 100. Sin perjuicio de las atribuciones señaladas en el artículo anterior, corresponden a las autoridades de la Ciudad de México, en sus respectivas competencias, las atribuciones siguientes:\nI. Instrumentar y articular sus políticas públicas tomando en consideración el Programa Nacional y el Programa General de Desarrollo para la adecuada garantía y protección de los derechos de niñas, niños y adolescentes;\nII. Elaborar el Programa y participar en el diseño del Programa Nacional;\nIII. Establecer, utilizar, supervisar y mantener todos los instrumentos y acciones encaminados al mejoramiento del Programa;\nIV. Promover, en coordinación con el Gobierno Federal, programas y proyectos de atención, educación, investigación y cultura de los derechos humanos de niñas, niños y adolescentes;\nV. Impulsar programas locales para el desarrollo de niñas, niños y adolescentes en situación de vulnerabilidad;\nVI. Difundir por todos los medios de comunicación el contenido de esta Ley;\nVII. Elaborar y aplicar el Programa a que se refiere esta Ley, así como rendir ante el Sistema\nNacional de Protección Integral un informe anual sobre los avances;\nVIII. Revisar y valorar la eficacia de las acciones, las políticas públicas, los programas locales en la materia, con base en los resultados del monitoreo y las evaluaciones que al efecto se realicen;\n\nIX. Impulsar la participación de las organizaciones privadas dedicadas a la promoción y defensa de los derechos humanos de niñas, niños y adolescentes, en la ejecución del Programa;\nX. Recibir de las organizaciones privadas, las propuestas y recomendaciones sobre protección de derechos de niñas, niños y adolescentes, a fin de mejorar los mecanismos en la materia;\nXI. Proporcionar a las instancias encargadas de realizar estadísticas y de integrar el sistema nacional de información, la información necesaria para la elaboración de éstas;\nXII. Implementar y ejecutar de las acciones y políticas públicas que deriven de la presente Ley;\nXIII. Impulsar reformas, en el ámbito de su competencia, para el cumplimiento de los objetivos de la presente Ley;\nXIV. Promover e impartir la capacitación, sensibilización y formación de las personas servidoras públicas sobre las políticas públicas orientadas a garantizar y proteger los derechos de niñas, niños y adolescentes, y\nXV. Cualquier otra prevista para el cumplimiento de esta Ley.\nArtículo 101. Corresponde a los órganos político administrativos las atribuciones siguientes:\nI. Establecer instrumentos, políticas, procedimientos, servicios y acciones de protección de los derechos de niñas, niños y adolescentes a través de la implementación del Sistema de Protección\nDelegacional.\nII. Elaborar su programa delegacional y participar en el diseño del Programa;\nIII. Realizar acciones de difusión que promuevan los derechos de niñas, niños y adolescentes en las delegaciones políticas, para que sean plenamente conocidos y ejercidos;\nIV. Promover la libre manifestación de ideas de niñas, niños y adolescentes en los asuntos concernientes a su delegación;\nV. Ser enlace entre la administración pública delegacional y niñas, niños y adolescentes que deseen manifestar inquietudes;\n\nVI. Coadyuvar en la efectiva protección y restitución de los derechos de las niñas, niños y adolescentes.\nVII. Recibir quejas y denuncias por violaciones a los derechos contenidos en la presente Ley y demás disposiciones aplicables, así como canalizarlas de forma inmediata a la Procuraduría de\nProtección, sin perjuicio que ésta pueda recibirla directamente;\nVIII. Auxiliar a la Procuraduría de Protección en las medidas urgentes de protección que ésta determine, y coordinar las acciones que correspondan en el ámbito de sus atribuciones;\nIX. Promover la celebración de convenios de coordinación con las autoridades competentes, así como con otras instancias públicas o privadas, para la atención y protección de niñas, niños y adolescentes;\nX. Difundir y aplicar los protocolos específicos sobre niñas, niños y adolescentes que autoricen las instancias competentes de la Ciudad de México;\nXI. Coordinarse con las autoridades para la implementación y ejecución de las acciones y políticas públicas que deriven de la presente Ley;\nXII. Coadyuvar en la integración del sistema de información de la Ciudad de México de niñas, niños y adolescentes;\nXIII. Impulsar la participación de las organizaciones privadas dedicadas a la promoción y defensa de los derechos humanos de niñas, niños y adolescentes, en la ejecución de los programas delegacionales y;\nXIV. Las demás que establezcan los ordenamientos locales y aquéllas que deriven de los acuerdos que, de conformidad con la presente Ley.\nSección Primera\nDel DIF de la Ciudad de México\n\nArtículo 102. Sin perjuicio de las atribuciones que establezcan las demás disposiciones aplicables, corresponde al DIFCDMX:\nI. Proteger los derechos de niñas, niños y adolescentes, cuando los mismos se encuentren restringidos o vulnerados, en términos de esta Ley y las demás disposiciones aplicables. La institucionalización procederá como último recurso y por el menor tiempo posible, priorizando las opciones de cuidado en un entorno familiar;\nII. Impulsar la cooperación y coordinación de las autoridades y de los órganos político administrativos, en el ámbito de sus respectivas competencias en materia de protección y restitución de derechos de niñas, niños y adolescentes para establecer los mecanismos necesarios para ello;\nIII. Celebrar los convenios de colaboración con el Sistema Nacional de Protección, los Sistemas de las Entidades y los Sistemas Delegacionales, así como con organizaciones e instituciones de los sectores público, privado y social;\nIV. Promover la formación, capacitación y profesionalización del personal de instituciones vinculadas con la protección y restitución de los derechos de niñas, niños y adolescentes, así como para realizar y apoyar estudios e investigaciones en la materia;\nV. Prestar apoyo y colaboración técnica y administrativa en las materias reguladas en esta Ley, a los órganos político administrativos y;\nVI. Coordinarse con las instancias de los sectores público, social y privado que determine, para el cumplimiento de estas atribuciones;\nVII. Realizar las actividades de asistencia social así como fomentar y promover la estabilidad y el bienestar familiar;\nVIII. Habilitar albergues o espacios de alojamiento para recibir a niñas, niños y adolescentes migrantes; observando en todo momento lo dispuesto por esta Ley, la Ley General, la Ley de\nMigración y demás disposiciones jurídicas aplicables;\n\nVIII Bis. Promover y difundir medidas de disciplina adecuadas, positivas y no violentas, elaboradas con la participación de niñas, niños y adolescentes, a efecto de garantizar sus derechos; y\nIX. Las demás que establezcan otras disposiciones en relación con la protección de niñas, niños y adolescentes que sean del ámbito de su competencia.\nCAPÍTULO SEGUNDO\nDEL SISTEMA DE PROTECCIÓN INTEGRAL DE NIÑAS, NIÑOS Y\nADOLESCENTES DE LA CIUDAD DE MÉXICO\nArtículo 103. Para asegurar una adecuada protección de los derechos de niñas, niños y adolescentes, se crea el Sistema de Protección, como instancia encargada de establecer instrumentos, políticas, procedimientos, servicios y acciones de protección de los derechos de niñas, niños y adolescentes.\nEl Sistema de Protección tiene los siguientes objetivos:\nI. Difundir el marco jurídico local, nacional e internacional de protección a los derechos de niñas, niños y adolescentes;\nII. Integrar la participación de los sectores público, social y privado y de la sociedad civil en la definición e instrumentación de políticas para la garantía y protección integral de los derechos de niñas, niños y adolescentes;\nIII. Generar los mecanismos necesarios para garantizar la participación directa y efectiva de niñas, niños y adolescentes en los procesos de elaboración de programas y políticas para la protección integral de sus derechos;\nIV. Promover, el establecimiento de presupuestos destinados a la protección de los derechos de niñas, niños y adolescentes;\nV. Impulsar la incorporación de la perspectiva de derechos de niñas, niños y adolescentes en la planeación del desarrollo de la Ciudad de México;\n\nVI. Garantizar la transversalidad de la perspectiva de derechos de niñas, niños y adolescentes en la elaboración de programas, así como en las políticas y acciones de las dependencias y entidades de la Administración Pública del Distrito Federal;\nVII. Elaborar y ejecutar el Programa con la participación de los sectores público, social y privado, así como de niñas, niños y adolescentes;\nVIII. Asegurar la ejecución coordinada del Programa por parte de los integrantes del Sistema, con la participación de los sectores público, social y privado, así como de niñas, niños y adolescentes;\nIX. Asegurar la colaboración y coordinación de las autoridades y los órganos político administrativos, para la formulación, ejecución e instrumentación de políticas, programas, estrategias y acciones en materia de protección y ejercicio de los derechos de niñas, niños y adolescentes, con su participación y la de los sectores público, social y privado;\nX. Hacer efectiva la vinculación y congruencia de los programas y acciones del Gobierno del\nDistrito Federal y de sus órganos político administrativos, con los objetivos, estrategias y prioridades de la política pública del Gobierno del Distrito Federal de protección de los derechos de niñas, niños y adolescentes;\nXI. Garantizar la participación de niñas, niños y adolescentes en el ejercicio de sus derechos humanos, tomando en consideración las medidas especiales que se requieran;\nXII. Fortalecer los vínculos familiares con el fin de proteger los derechos de niñas, niños y adolescentes;\nXIII. Fortalecer las acciones de corresponsabilidad y cercanía entre las instancias públicas y privadas con niñas, niños y adolescentes;\nXIV. Promover la celebración de instrumentos de colaboración y coordinación, así como acciones de concertación con instancias públicas y privadas, locales, nacionales e internacionales, que contribuyan al cumplimiento de la presente Ley;\nXV. Auxiliar a la Procuraduría de Protección en las medidas urgentes de protección que ésta determine, y coordinar las acciones que correspondan en el ámbito de sus atribuciones;\n\nXVI. Conformar el sistema de información de la Ciudad de México sobre los progresos alcanzados en el cumplimiento de los derechos de niñas, niños y adolescentes, incluyendo indicadores cualitativos y cuantitativos, y coadyuvar en la integración del sistema de información a nivel nacional;\nXVII. Conformar el sistema de seguimiento y monitoreo de los objetivos, metas y líneas de acción que integran el Programa de Protección Integral;\nXVIII. Realizar acciones de formación y capacitación de manera sistémica y continua sobre el conocimiento y respeto de los derechos humanos de niñas, niños y adolescentes, principalmente con aquellas personas que trabajan desde los diversos ámbitos en la garantía de sus derechos;\nXIX. Promover políticas públicas y revisar las ya existentes relacionadas con los derechos de carácter programático previstos en esta Ley;\nXX. Llevar a cabo el seguimiento, monitoreo y evaluación de la ejecución del Programa de\nProtección Integral;\nXXI. Impulsar reformas, en el ámbito de su competencia, para el cumplimiento de los objetivos de la presente Ley;\nXXII. Emitir un informe anual sobre los avances del Programa de Protección Integral y remitirlo al Sistema Nacional de Protección;\nXXIII. Instrumentar y articular las políticas públicas del Gobierno del Distrito Federal en concordancia con la política nacional;\nXXIV. Coadyuvar en la adopción y consolidación del Sistema Nacional de Protección;\nXXV. Participar en la elaboración del Programa Nacional, y\nXXVI. Las demás que sean necesarias para el cumplimiento de esta Ley.\nArtículo 104. La coordinación, en un marco de respeto a las atribuciones entre las instancias del Gobierno del Distrito Federal y sus órganos político administrativos, será el eje del Sistema de Protección.\n\nSección Primera\nDe los Integrantes\nArtículo 105. El Sistema de Protección está conformado por las personas titulares de las siguientes instituciones:\nA. Del Gobierno de la Ciudad de México:\nI. Jefatura de Gobierno, quien lo presidirá;\nII. Secretaría de Gobierno;\nIII. Secretaría de Finanzas;\nIV. Secretaría de Desarrollo Social;\nV. Secretaría de Educación;\nVI. Secretaría de Salud;\nVII. Secretaría del Trabajo y Fomento al Empleo;\nVIII. Sistema para el Desarrollo Integral de la Familia DIF- CDMX;\nIX. Procuraduría de Protección de Derechos de Niñas, Niños y Adolescentes de la Ciudad de México;\nX. Procuraduría General de Justicia de la Ciudad de México, y\nXI. Instituto de la Juventud de la Ciudad de México.\nB. Órgano Judicial del Distrito Federal:\nI. Presidencia del Tribunal Superior de Justicia del Distrito Federal.\nC. Órgano Legislativo\nI. Comisión de Atención al Desarrollo de la Niñez\nII. Comisión de Presupuesto y Cuenta Pública\nIII. Comisión de Hacienda\nD. Organismos Públicos:\nI. Presidencia de la Comisión de Derechos Humanos del Distrito Federal, y\n\nE. Representantes de la sociedad civil, academia, líderes de opinión, especialistas en la materia, que serán nombrados en los términos del reglamento de esta Ley.\nF. Serán invitados permanentes:\nl. Titulares los órganos político administrativos.\nII. Consejería Jurídica y de Servicios Legales;\nIII. Secretaría de Seguridad Pública;\nIV. Secretaría de Cultura;\nV. Instituto de las Mujeres del Distrito Federal;\nVI. Secretaría de Desarrollo Rural y Equidad para las Comunidades y;\nVII. Escuela de Administración Pública del Distrito Federal.\nVIII. Consejo para la Evaluación del Desarrollo Social del Distrito Federal\nIX. Derogado;\nLos integrantes señalados en los incisos A, B, C, D y E tendrán voz y voto.\nLas y los representantes comprendidos en el inciso F sólo participarán con voz, pero sin voto.\nPara efectos de lo previsto en el apartado E, el reglamento deberá prever los términos para la emisión de una convocatoria pública, que contendrá las etapas completas para el procedimiento, sus fechas límites y plazos.\nEl titular de la Jefatura de Gobierno, en casos excepcionales, podrá ser suplido por el servidor público que designe. Los integrantes del Sistema de Protección nombrarán un suplente que deberá tener el nivel de subsecretario o equivalente.\nLa presidencia del Sistema podrá invitar a las sesiones respectivas a representantes de otras dependencias y entidades de la Administración Pública de la Ciudad de México y de los órganos públicos autónomos según la naturaleza de los asuntos a tratar quienes intervendrán con voz, pero sin voto.\nDe igual forma, se podrá invitar a personas o instituciones, locales, nacionales o internacionales, especializadas en la materia.\n\nArtículo 106. En el ejercicio de las funciones del Sistema de Protección Integral se escuchará y tomará en consideración la opinión de niñas, niños y adolescentes que viven o transitan por la Ciudad de México, especialmente en lo que corresponde a las fracciones XIX, XXI, y XXV del artículo 103.\nEl reglamento de la presente ley desarrollará los mecanismos específicos de participación, que deberán tener como mínimo las siguientes características: ser amplios y representativos, garantizar previamente el derecho a la información sobre los asuntos que serán consultados, garantizar la accesibilidad a todas las personas participantes y garantizar la respuesta de las autoridades a las opiniones de niñas, niños y adolescentes en los espacios donde habitualmente se desarrollan.\nLas consultas podrán ser:\nI. Anteriores a las sesiones del Sistema de Protección, cuya finalidad será la generación de propuestas para discusión en las sesiones;\nII. Posteriores a las sesiones del Sistema de Protección, cuya finalidad es validar las decisiones tomadas; y\nIII. En cualquier otro momento respecto a temas de su interés.\nFrente a las opiniones expresadas por las niñas, niños y adolescentes, las autoridades del Sistema de\nProtección tendrán las siguientes obligaciones:\na) Incorporar el resultado de las consultas a la toma de decisiones, ya sea anteriores a la sesión o posteriores a ellas.\nb) Fundamentar la forma en que se tomó en cuenta la opinión de niñas, niños y adolescentes.\nc) Informar, de manera accesible y amplia, tanto la decisión como la forma en que se incorporaron las opiniones de niñas, niños y adolescentes.\nd) Deberán rendir cuentas respecto a la incorporación de sus opiniones.\nArtículo 107. El Sistema de Protección se reunirá de manera ordinaria al menos dos veces al año. Para sesionar válidamente se requerirá un quórum de la mayoría simple de sus integrantes; sus decisiones se\n\ntomarán por mayoría simple de votos de quienes estén presentes y, en caso de empate, el Presidente tendrá voto de calidad.\nSi acude en representación una persona que no cumpla con los requisitos previstos en el artículo 105, sólo tendrá derecho a voz.\nArtículo 108. Para el mejor cumplimiento de sus funciones, el Sistema de Protección podrá constituir comisiones encargadas de atender asuntos o materias específicas y emitirá los lineamientos para su integración, organización y funcionamiento, las cuales deberán ser publicadas en la Gaceta Oficial del\nGobierno del Distrito Federal.\nSección Segunda\nDe la Secretaria Ejecutiva\nArtículo 109. La coordinación operativa del Sistema de Protección recaerá en una Secretaría Ejecutiva que ejercerá las atribuciones siguientes:\nI. Coordinar las acciones entre las autoridades competentes de la Administración Pública del\nGobierno del Distrito Federal que deriven de la presente Ley;\nII. Elaborar el anteproyecto del Programa para someterlo a consideración de los miembros del\nSistema;\nIII. Llevar a cabo el seguimiento y monitoreo de la ejecución del Programa de Protección, para lo cual se auxiliará de la Escuela de Administración Pública del Distrito Federal;\nIV. Elaborar y mantener actualizado el Manual Administrativo de Organización y Operación del\nSistema de Protección;\nV. Compilar los acuerdos que se tomen en el Sistema de Protección, llevar el archivo de éstos y de los instrumentos jurídicos que deriven, y expedir constancia de los mismos;\nVI. Apoyar al Sistema de Protección en la ejecución y seguimiento de los acuerdos y resoluciones emitidos;\n\nVII. Celebrar convenios de coordinación, colaboración y concertación con instancias públicas y privadas, locales, nacionales e internacionales;\nVIII. Administrar el sistema de información de la Ciudad de México a que se refiere la fracción\nXVI del artículo 103;\nIX. Realizar y promover estudios e investigaciones para fortalecer las acciones en favor de la atención, defensa y protección de niñas, niños y adolescentes con el fin de difundirlos a las autoridades competentes y a los sectores social y privado para su incorporación en los programas respectivos;\nX. Difundir entre las autoridades correspondientes y la población en general los resultados de los trabajos que realice, así como toda aquella información pública que tienda a la generación, desarrollo y consolidación de perspectiva en la materia, desagregada por lo menos, en razón de edad, sexo, órgano político administrativo, escolaridad y discapacidad;\nXI. Asesorar y apoyar a los órganos político administrativos que lo requieran para el ejercicio de sus atribuciones;\nXII. Informar cada cuatro meses al Sistema de Protección y a su Presidencia, sobre sus actividades;\nXIII. Proporcionar la información necesaria a EVALUA CDMX, para la evaluación de las políticas de desarrollo social vinculadas con la protección de niñas, niños y adolescentes;\nXIV. Fungir como instancia de interlocución con organizaciones de la sociedad civil, academia y demás instituciones de los sectores social y privado;\nXV. Coordinar con las Secretarías Ejecutivas de los órganos político administrativos la articulación de la política local, así como el intercambio de información necesaria a efecto de dar cumplimiento con el objeto de esta Ley, y\nXVI. Las demás que le encomiende el Presidente del Sistema o el Sistema de Protección.\nArtículo 110. El titular de la Secretaría Ejecutiva será nombrado y removido libremente por el Presidente del Sistema y deberá cumplir con los siguientes requisitos:\n\nI. Tener ciudadanía mexicana en pleno goce de sus derechos civiles y políticos;\nII. Tener más de 30 años de edad;\nIII. Contar con título profesional de nivel licenciatura debidamente registrado;\nIV. Contar con al menos cinco años de experiencia en las áreas correspondientes a su función, y\nV. No haber sido sentenciado por delito doloso o inhabilitado como servidor público.\nSección Tercera\nDe la Procuraduría de Protección\nArtículo 111. Para una efectiva protección y restitución de los derechos de niñas, niños y adolescentes, el\nGobierno del Distrito Federal, dentro de la estructura del DIF-DF, contará con una Procuraduría de\nProtección.\nLa Procuraduría de Protección es un órgano adscrito del Sistema para el Desarrollo Integral de la Familia del Distrito Federal con las atribuciones y facultades que señala esta Ley, el Sistema para el Desarrollo\nIntegral de la Familia del Distrito Federal, dotara de los recursos necesarios a la Procuraduría de Protección para la consecución de su objeto.\nEn el ejercicio de sus funciones, la Procuraduría de Protección podrá solicitar el auxilio de autoridades de los tres órdenes de gobierno, las que estarán obligadas a proporcionarlo de conformidad con las disposiciones aplicables.\nPara la debida determinación, coordinación de la ejecución y seguimiento de las medidas de protección integral y restitución de los derechos de niñas, niños y adolescentes, la Procuraduría de Protección deberá establecer contacto y trabajar conjuntamente con las autoridades administrativas de asistencia social, de servicios de salud, de educación, de protección social, de cultura, deporte y con todas aquellas con las que sea necesario para garantizar los derechos de niñas, niños y adolescentes.\nArtículo 112. La Procuraduría de Protección, en su ámbito de competencia, tendrá las atribuciones siguientes:\n\nI. Procurar la protección integral de los derechos de niñas, niños y adolescentes que prevé la\nConstitución Política de los Estados Unidos Mexicanos, los tratados internacionales, la Ley\nGeneral, esta Ley y demás disposiciones aplicables. Dicha protección integral deberá abarcar, por lo menos:\na) Atención médica, psicológica, jurídica y de trabajo social;\nb) Seguimiento a las actividades escolares y entorno social y cultural, y c) La inclusión, en su caso, de quienes ejerzan la patria potestad, tutela o guarda y custodia de niñas, niños y adolescentes en las medidas de rehabilitación y asistencia;\nII. Prestar asesoría y representación en suplencia a niñas, niños y adolescentes involucrados en procedimientos judiciales o administrativos, sin perjuicio de las atribuciones que le correspondan al Ministerio Público, así como intervenir oficiosamente, con representación coadyuvante, en todos los procedimientos jurisdiccionales y administrativos en que participen niñas, niños y adolescentes, de conformidad con lo dispuesto en la presente Ley y demás disposiciones aplicables;\nIII. Coordinar la ejecución y dar seguimiento a las medidas de protección para la restitución integral de los derechos de niñas, niños y adolescentes, a fin de que las instituciones competentes actúen de manera oportuna y articulada;\nIV. Fungir como conciliador y mediador en casos de conflicto familiar, cuando los derechos de niñas, niños y adolescentes hayan sido restringidos o vulnerados, conforme a las disposiciones aplicables. La conciliación no procederá en casos de violencia;\nV. Recibir, atender y dar seguimiento de manera inmediata y profesional los reportes de maltrato hacia niñas, niños y adolescentes, denunciando ante la autoridad ministerial aquellos hechos que se presuman constitutivos de delito en contra de esta población;\nReforma publicada en la GOCDMX el 03 de marzo de 2023\nVI. Solicitar a la autoridad ministerial competente la imposición de medidas precautorias, cautelares, de seguridad y de protección, cuando exista un riesgo inminente contra la vida, integridad o libertad de niñas, niños y adolescentes, quien deberá decretarlas a más tardar, durante las siguientes 3 horas a la recepción de la solicitud, dando aviso de inmediato a la autoridad jurisdiccional competente. Son medidas urgentes de protección especial en relación\n\ncon niñas, niños y adolescentes, además de las establecidas en el Código Nacional de\nProcedimientos Penales, las siguientes:\na) El ingreso de una niña, niño o adolescente a un centro de asistencia social, y b) La atención médica inmediata por parte de alguna institución del Sistema de Salud de la Ciudad de México, y\nFracción modificada y publicada en la GOCDMX el 15 de marzo de 2024 c) El acogimiento, cuidado y protección de niñas, niños y adolescentes en situación de trabajo infantil desempeñado en las calles, avenidas, ejes viales, espacios públicos o privados, medios de transporte o cualquier vía de circulación.\nFracción adicionada y publicada en la GOCDMX el 15 de marzo de 2024\nDentro de las 24 horas siguientes a la imposición de la medida urgente de protección, el órgano jurisdiccional competente deberá pronunciarse sobre la cancelación, ratificación o modificación de la medida que se encuentre vigente;\nVII. Ordenar, fundada y motivadamente, bajo su más estricta responsabilidad, la aplicación de medidas urgentes de protección especial, concretamente para el ingreso de una niña, niño o adolescentes a un centro de asistencia social, y para la atención médica inmediata por parte de alguna institución del Sistema de Salud de la Ciudad de México; lo anterior, cuando exista riesgo inminente contra la vida, integridad o libertad de niñas, niños o adolescentes, dando aviso de inmediato a la autoridad ministerial y jurisdiccional competente.\nDentro de las 24 horas siguientes a la imposición de la medida urgente de protección el órgano jurisdiccional competente deberá pronunciarse sobre la cancelación, ratificación o modificación de la medida que se encuentre vigente.\nPara la imposición de las medidas urgentes de protección, la Procuraduría de Protección podrá solicitar el auxilio de las instituciones policiales competentes.\nEn caso de incumplimiento de las medidas urgentes de protección, la Procuraduría de Protección podrá solicitar la imposición de las medidas de apremio correspondientes a la autoridad competente.\n\nLa implementación de las medidas urgentes de protección especial, se regirá por el procedimiento establecido para tal efecto.\nVIII. Promover, impulsar y suscribir convenios de participación y colaboración, de los sectores público, social y privado en la planificación y ejecución de acciones a favor de la atención, defensa y protección de los derechos de las niñas, niños y adolescentes, que contribuyan al cumplimiento de estas atribuciones;\nIX. Asesorar a las autoridades competentes y a los sectores público, social y privado en el cumplimiento del marco normativo relativo a la protección de niñas, niños y adolescentes, conforme a las disposiciones aplicables;\nX. Elaborar los lineamentos y procedimientos a los que se sujetarán para la restitución de los derechos de niñas, niños y adolescentes;\nXI. Coadyuvar con el DIF-CDMX en la elaboración de los lineamientos y procedimientos para registrar, capacitar y evaluar a las familias que pretenden adoptar de acuerdo con lo previsto en el Artículo 30 de esta Ley;\nXII. Proporcionar información para integrar y sistematizar el Registro de Centros de Asistencia\nSocial del Distrito Federal;\nXIII. Colaborar en la supervisión de la ejecución de las medidas especiales de protección, precautorias, cautelares y de seguridad de niñas, niños y adolescentes que hayan sido separados de su familia de origen por resolución judicial;\nXIV. Colaborar en la realización y promoción de estudios e investigaciones para fortalecer las acciones a favor de la atención, defensa y protección de niñas, niños y adolescentes, con el fin de difundirlos entre las autoridades competentes y los sectores público, social y privado para su incorporación en los programas respectivos,\nXV. Para el desarrollo de estas atribuciones, la Procuraduría contará con personal especializado para la defensa, protección y restitución de los derechos de niñas, niños y adolescentes.\nDentro del personal especializado se contará con personal jurídico en ejercicio de la representación en suplencia, en coadyuvancia y originaria.\n\nLas actuaciones que realice el personal jurídico, tendrán el valor que se le otorga a los testimonios investidos de fe pública.\nXVI. Las demás que les confieran otras disposiciones aplicables.\nArtículo 113. Para solicitar la protección y restitución integral de los derechos de niñas, niños y adolescentes, la Procuraduría de Protección deberá seguir el siguiente procedimiento:\nI. Detectar o recibir casos de restricción y vulneración de derechos de niñas, niños y adolescentes;\nII. Acercarse a la familia o lugares en donde se encuentren las niñas, niños y adolescentes para diagnosticar la situación de sus derechos cuando exista información sobre posible restricción o vulneración de los mismos;\nIII. Determinar en cada uno de los casos identificados los derechos que se encuentran restringidos o vulnerados;\nIV. Elaborar, bajo el principio del interés superior, un diagnóstico sobre la situación de vulneración y un plan de restitución de derechos, que incluya las propuestas de medidas para su protección;\nV. Acordar y coordinar con las instituciones que corresponda el cumplimiento del plan de restitución de derechos, y\nVI. Dar seguimiento a cada una de las acciones del plan de restitución de derechos, hasta cerciorarse de que todos los derechos de la niña, niño o adolescente se encuentren garantizados.\nArtículo 113 BIS. En materia de trabajo infantil desempeñado en las calles, avenidas, ejes viales, espacios públicos o privados, medios de transporte o cualquier vía de circulación, la Procuraduría de Protección, en el ámbito de sus respectivas competencias deberá:\nI. Contar con un sistema de información y registro detallado de carácter confidencial y de acceso exclusivo por orden de autoridad judicial o administrativa competente, actualizado al menos una vez cada dos meses, que permita integrar un Padrón de Niñas, Niños y Adolescentes que laboran en calles, avenidas, ejes viales, espacios públicos o privados, medios de transporte o\n\ncualquier vía de circulación. Dicho Padrón deberá elaborarse con base en caso concreto, denunciado y atendido por la Procuraduría en coordinación con el DIF-CDMX.\nEl padrón que deberá incluir:\na) La situación jurídica y familiar de las niñas, niños o adolescentes, debiendo especificar si se encuentra en estado de orfandad o bajo la tutela o cuidado de padre o madre, o ambos;\nb) Nombre completo del infante, fecha de nacimiento, edad, género, escolaridad;\nc) Ubicación en la que se encontró a la niña, niño o adolescente laborando, y d) Diagnóstico médico y psicológico, condición pedagógica, información social, perfil de necesidades de atención familiar, información biométrica y de ser el caso, número de hermanos, tipo y severidad de la discapacidad con la que vive y requerimientos de atención a necesidades especiales de las niñas, niños y adolescentes.\nArtículo adicionado y publicado en la GOCDMX el 15 de marzo de 2024\nArtículo 114. Los requisitos para ser titular de la Procuraduría de Protección, son los siguientes:\nI. Tener ciudadanía mexicana en pleno goce de sus derechos civiles y políticos;\nII. Tener más de 35 años de edad;\nIII. Contar con título profesional de licenciatura en derecho debidamente registrado;\nIV. Contar con al menos cinco años de experiencia en defensa de los derechos de niñas, niños y adolescentes;\nV. No tener sentencia por delito doloso o inhabilitación como servidor público;\nEl nombramiento de la persona Titular de la Procuraduría de Protección deberá ser aprobado por la Junta de Gobierno del DIF-CDMX, a propuesta de su Titular.\nSección Cuarta\n\nDe las Medidas de Protección Especial\nArtículo 115. Las medidas de protección especial que adopten las autoridades y los órganos político administrativos, serán aquellas necesarias para garantizar y restituir los derechos de niñas, niños y adolescentes en condiciones de vulnerabilidad o discriminación múltiple.\nSe consideran de manera enunciativa, mas no limitativa, las siguientes condiciones o situaciones de vulnerabilidad: discapacidad, identidad cultural, origen étnico o nacional, situación migratoria o apátrida, víctimas de delito, hijas e hijos de personas en reclusión, en situación de calle, embarazo adolescente, adolescentes en conflicto con la ley, uso de drogas, trabajo infantil, trabajo infantil desempeñado en las calles, avenidas, ejes viales, espacios públicos o privados, medios de transporte o cualquier vía de circulación, en situación de abandono, por orientación y preferencia sexual, y cualquier otra condición o situación que impida a niñas, niños y adolescentes el ejercicio efectivo de sus derechos.\nPárrafo modificado y publicado en la GOCDMX el 15 de marzo de 2024\nArtículo 116. Las medidas de protección especial deberán ajustarse a las situaciones específicas de cada niña, niño y adolescente.\nArtículo 117. Las autoridades y de los órganos político administrativos, están obligadas a presentar ante el\nSistema de Protección un informe anual sobre las medidas de protección especial que hayan adoptado de conformidad con las facultades señaladas en esta sección.\nSección Quinta\nDe la Evaluación y Diagnóstico\nArtículo 118. Corresponde a EVALUA CDMX la evaluación de las políticas de desarrollo social vinculadas con la protección de los derechos de niñas, niños y adolescentes, en términos de lo establecido por la\nConstitución Política de los Estados Unidos Mexicanos, la Ley General, esta Ley, el Programa de Protección\nIntegral y las demás disposiciones aplicables.\nArtículo 119. La evaluación consistirá en analizar y valorar los resultados e impactos de las políticas públicas orientadas al cumplimiento de esta Ley y del Programa de Protección Integral.\nArtículo 120. De acuerdo con los resultados de las evaluaciones, el EVALUA CDMX emitirá, en su caso, las sugerencias y recomendaciones que considere pertinentes al Sistema de Protección.\n\nArtículo 121. Los resultados de las evaluaciones serán entregados a la Asamblea Legislativa del Distrito\nFederal y presentados en sesión ordinaria del Sistema de Protección para la revisión de sus indicadores de cumplimiento.\nSección Sexta\nDe la Comisión de Derechos Humanos del Distrito del Federal\nArtículo 122. La Comisión de Derechos Humanos del Distrito Federal a través de sus áreas especializadas según las atribuciones que su propia ley establece, apoyará los trabajos para la transversalización de la protección efectiva, observancia, promoción, estudio y divulgación de los derechos de niñas, niños y adolescentes.\nSección Séptima\nDel Programa de Protección Integral\nArtículo 123. Las autoridades y los órganos político administrativos, a través del Sistema de Protección, así como los sectores privado y social, participarán en la elaboración y ejecución del Programa de Protección\nIntegral, el cual deberá ser acorde con el Programa Nacional de Desarrollo y el Programa General de\nDesarrollo del Distrito Federal y con la presente Ley.\nArtículo 124. El Programa contendrá las estrategias, políticas, objetivos, metas y líneas de acción prioritarias en materia de ejercicio, respeto, promoción y protección integral de niñas, niños y adolescentes, asimismo preverá acciones de mediano y largo alcance, indicará las estrategias, los objetivos, metas y líneas de acción prioritarias.\nArtículo 125. El Programa deberá incluir líneas estratégicas específicas sobre las medidas de protección especial de los derechos de niñas, niños y adolescentes que se encuentren en condición o situación de vulnerabilidad, señalados en el artículo 115, con el propósito de visibilizar, atender y garantizar el cumplimiento efectivo de sus derechos humanos.\nArtículo 126. El Programa de Protección Integral incluirá mecanismos transparentes que permitan su evaluación y seguimiento, así como de participación ciudadana y será publicado en la Gaceta Oficial del\nGobierno del Distrito Federal.\n\nCAPÍTULO TERCERO\nDE LOS SISTEMAS DE PROTECCIÓN DE LOS ÓRGANOS POLÍTICO\nADMINISTRATIVOS\nArtículo 127. Los Sistemas de Protección de los órganos político administrativos serán presididos por sus titulares, y estarán integrados por las dependencias e instituciones vinculadas con la protección de los derechos de niñas, niños y adolescentes en el ámbito de su competencia. Y contarán con una Secretaría\nEjecutiva y garantizarán la participación de los sectores social y privado, así como de niñas, niños y adolescentes.\nArtículo 128. Los órganos político administrativos, deberán contar con un programa de atención y con un área o servidores públicos que fungirán como autoridad de primer contacto con niñas, niños o adolescentes y que serán el enlace con las dependencias y entidades competentes.\nLa instancia a que se refiere el presente artículo se coordinará con los servidores públicos de los órganos político administrativos, cuando en la operación, verificación y supervisión de las funciones y servicios que les corresponden, detecten casos de violación a los derechos contenidos en la presente Ley, a efecto de que se dé vista a la Procuraduría de Protección de forma inmediata.\nLas instancias a que se refiere este artículo deberán ejercer, sin perjuicio de otras que dispongan las leyes del Distrito Federal, las atribuciones previstas en el artículo 101 de esta Ley.\nArtículo 129. El Sistema de Protección de la Ciudad de México y los Sistemas de Protección Delegacionales contarán con órganos consultivos de apoyo, en los que participarán las autoridades competentes y representantes de los sectores social y privado, para la implementación y aplicación de los programas.\nTÍTULO QUINTO\nDE LAS INFRACCIONES ADMINISTRATIVAS\nCAPÍTULO PRIMERO\nDE LAS SANCIONES ADMINISTRATIVAS\n\nArtículo 130. Sin perjuicio de lo establecido por otros ordenamientos jurídicos, serán sujetas de sanción en los términos del presente capítulo y de la Ley de Responsabilidades Administrativas de la Ciudad de\nMéxico, las personas servidoras públicas de la Administración Pública, Alcaldías y órganos autónomos de la Ciudad de México, así como las personas trabajadoras o empleadas de Centros de Asistencia Social, instituciones y establecimientos sujetos a control, administración o coordinación con las dependencias, órganos y entidades del Gobierno de la Ciudad de México que en el ejercicio de sus funciones o actividades, o con motivo de ellas:\nI. Impidan el ejercicio de algún derecho o nieguen la prestación del servicio al que están obligados a niñas, niños y adolescentes;\nII. Conozcan de la violación de algún derecho a niñas, niños o adolescentes y se abstengan de hacerlo del conocimiento de la autoridad competente;\nIII. Propicien, toleren o se abstengan de impedir, cualquier tipo de abuso, acoso, agresión, daño, intimidación, violencia, maltrato, discriminación o perjuicio en contra de niñas, niños y adolescentes del que tengan conocimiento;\nIV. Quien, estando obligado por mandato de esta Ley, no cuente con las autorizaciones correspondientes para participar en los procedimientos de adopción; y,\nV. La realización de alguna de las conductas prohibidas en materia de adopción establecidas en esta Ley.\nArtículo 131. A quienes incurran en las infracciones previstas en las fracciones I, II y III del artículo anterior, se les impondrá una multa hasta por la cantidad equivalente de cien a ciento cincuenta veces el valor diario de la Unidad de Cuenta vigente en la Ciudad de México.\nArtículo 132. A quienes incurran en las infracciones previstas en las fracciones IV y V del artículo 130, se les impondrá una multa hasta por la cantidad equivalente de ciento cincuenta a trescientas veces el valor diario de la Unidad de Cuenta vigente en la Ciudad de México.\nArtículo 133. En casos de reincidencia, la multa podrá aplicarse hasta por el doble de lo previsto en los artículos 131 y 132 de esta Ley según sea el caso.\n\nPara efectos del presente artículo se considerará reincidencia cuando habiendo incurrido en una infracción que haya sido sancionada, el sujeto activo realice otra violación del mismo precepto de esta Ley, sin importar el lapso de tiempo que transcurra entre ambas conductas u omisiones.\nArtículo 134. Para la determinación de la sanción se deberá considerar lo siguiente:\nI. La gravedad de la infracción;\nII. Si la conducta sancionable fue realizada con carácter intencional, omisión o negligencia;\nIII. Los daños producidos o que puedan producirse;\nIV. La condición socio económica de la persona infractora; y,\nV. La reincidencia infractora.\nArtículo 135. Las sanciones previstas en este capítulo, serán substanciadas de acuerdo a la normatividad aplicable e impuestas de la siguiente forma:\nI. Cuando alguna de las conductas previstas en las fracciones I, II y III del artículo 130 sea cometida por una persona servidora pública, la sanción será impuesta por el órgano interno de control de la dependencia, entidad, del Poder Judicial de la Ciudad de México, el Congreso de la Ciudad de México u órganos con autonomía constitucional, a la cual se encuentre adscrita.\nII. Las infracciones previstas en las fracciones IV, y V del artículo 130 las aplicará la Procuraduría de Protección.\nArtículo 136. Contra las sanciones impuestas con motivo de esta Ley, se podrá interponer recurso de inconformidad previsto en la Ley de Procedimiento Administrativo de la Ciudad de México.\nArtículo 137. Para los efectos de este capítulo, a falta de disposición expresa y en lo que no contravenga esta Ley, se aplicará supletoriamente la Ley de Procedimiento Administrativo de la Ciudad de México.\nCAPÍTULO SEGUNDO\n\nDEL FIDEICOMISO DE RESTITUCIÓN DE DERECHOS DE NIÑAS, NIÑOS\nY ADOLESCENTES\nArtículo 138. Los recursos generados de la aplicación de las sanciones establecidas en este Título serán dirigidos al Fideicomiso de Restitución de Derechos de Niñas, Niños y Adolescentes, cuyo objeto será la implementación de las acciones y políticas establecidas en el Plan de Restitución de derechos a favor de niñas, niños y adolescentes.\nArtículo 139. El Plan de Restitución de derechos a favor de niñas, niños y adolescentes será elaborado y supervisado por la Procuraduría de Protección de conformidad con lo dispuesto por esta Ley y tendrá las siguientes obligaciones:\nI. Publicar trimestralmente en su página de internet y en la Gaceta Oficial, los ingresos, rendimientos financieros, egresos, destino y saldo del Fideicomiso de Restitución derechos de niñas, niños adolescentes.\nII. Enviar de manera trimestral al Congreso de la Ciudad de México por conducto de la Secretaría de Administración y Finanzas de la Ciudad de México los informes del estado que guarda el\nFideicomiso de Restitución de Derechos de Niñas, Niños y Adolescentes, así como una relación del uso de sus recursos por destino y tipo de gasto.\nEl Fideicomiso de Restitución de Derechos de Niñas, Niños y Adolescentes se constituirá, operará y se registrará de conformidad con lo dispuesto en la Ley de Austeridad, Transparencia en Remuneraciones,\nPrestaciones y Ejercicio de Recursos de la Ciudad de México y su Reglamento.\nARTÍCULOS TRANSITORIOS\nPRIMERO. Publíquese en la Gaceta Oficial del Gobierno del Distrito Federal.\nSEGUNDO. El presente Decreto entrará en vigor a los ciento ochenta días posteriores a su publicación, dentro de este plazo, la Asamblea Legislativa del Distrito Federal deberá realizar la armonización legislativa correspondiente al Marco Jurídico del Distrito Federal, de acuerdo con lo establecido en el presente\nDecreto.\n\nTERCERO. El Sistema de Protección y los Sistemas de Protección Delegacionales deberán integrarse a más tardar dentro de los noventa días hábiles siguientes a la entrada en vigor de las modificaciones legislativas a que se refiere el transitorio anterior.\nCUARTO. La Ley de los Derechos de Niñas y Niños en el Distrito Federal quedará abrogada a la entrada en vigor del presente Decreto.\nQUINTO. Los recursos materiales, humanos y financieros de la Dirección Ejecutiva de la Defensoría de los\nDerechos de la Infancia del Sistema para el Desarrollo Integral de la Familia del Distrito Federal, se transferirán a la Procuraduría de Protección de Derechos de Niñas, Niños y Adolescentes en la Ciudad de\nMéxico, en los términos de la normatividad aplicable.\nEl Jefe de Gobierno del Distrito Federal, a través del Sistema para el Desarrollo Integral de la Familia del\nDistrito Federal, realizará las gestiones y/o procesos administrativos correspondientes para la implementación de la Procuraduría de Protección. Para tal efecto la Secretaría de Finanzas del Distrito\nFederal asignará los recursos financieros necesarios que garanticen su adecuada operación.\nEl Sistema para el Desarrollo Integral de la Familia del Distrito Federal deberá reformar su Estatuto Orgánico a fin de formalizar la implementación de la Procuraduría de Protección de los Derechos de Niñas, Niños y\nAdolescentes, con sus respectivas unidades administrativas.\nSEXTO. En su primera sesión, el Presidente del Sistema de Protección someterá a consideración y aprobación del mismo los lineamientos para su integración, organización y funcionamiento, así como la designación del Titular de la Secretaría Ejecutiva del Sistema de Protección.\nEl Titular de la Secretaría Ejecutiva del Sistema de Protección, una vez instalado el Sistema de Protección, dentro de los siguientes treinta días hábiles, deberá presentar a consideración y en su caso aprobación de los integrantes del Pleno, el proyecto de lineamientos a que se refiere el artículo 108 de la Ley de Derechos de Niñas, Niños y Adolescentes.\nEl Presidente del Sistema de Protección realizará las acciones necesarias para la elaboración del Programa, el cual deberá aprobarse dentro de los ciento veinte días hábiles siguientes a la instalación del Sistema de\nProtección.\n\nSÉPTIMO. Las modificaciones que deban realizarse a los ordenamientos administrativos y la creación de manuales, lineamientos y demás disposiciones legales deberán expedirse y publicarse a más tardar dentro de ciento ochenta días hábiles a partir de la vigencia de la presente Ley.\nOCTAVO. Para la ejecución de la presente Ley, la Asamblea Legislativa del Distrito Federal aprobará el presupuesto necesario y suficiente que permita a las distintas instancias involucradas llevar a cabo de manera óptima sus responsabilidades de conformidad con las atribuciones que les han sido conferidas en la presente Ley y demás normatividad aplicable.\nRecinto de la Asamblea Legislativa del Distrito Federal, a los nueve días del mes de julio del año dos mil quince.- POR LA MESA DIRECTIVA.- DIP. EFRAIN MORALES LÓPEZ, PRESIDENTE.- DIP. ALEJANDRO RAFAEL\nPIÑA MEDINA, SECRETARIO.- DIP. SAMUEL RODRÍGUEZ TORRES, SECRETARIO.- (Firmas)\nEn cumplimiento de lo dispuesto por los artículos 122, apartado C, Base Segunda, fracción II, inciso b), de la Constitución Política de los Estados Unidos Mexicanos; 48, 49 y 67, fracción II, del Estatuto de Gobierno del Distrito Federal, para su debida publicación y observancia, expido el presente Decreto Promulgatorio en la Residencia Oficial del Jefe de Gobierno del Distrito Federal, en la Ciudad de México, a los trece días del mes de agosto del año dos mil quince.- EL JEFE DE GOBIERNO DEL DISTRITO FEDERAL, MIGUEL ÁNGEL\nMANCERA ESPINOSA.- FIRMA.- LA SECRETARIA DE GOBIERNO, DORA PATRICIA MERCADO CASTRO.- FIRMA.-\nEL SECRETARIO DE DESARROLLO SOCIAL, JOSÉ RAMÓN AMIEVA GÁLVEZ.- FIRMA.- EL SECRETARIO DE\nSEGURIDAD PÚBLICA, HIRAM ALMEIDA ESTRADA.- FIRMA.- LA SECRETARIA DE TRABAJO Y FOMENTO AL\nEMPLEO, AMALIA DOLORES GARCÍA MEDINA.- FIRMA.- LA SECRETARIA DE DESARROLLO RURAL Y EQUIDAD\nPARA LAS COMUNIDADES, ROSA ÍCELA RODRÍGUEZ VELÁZQUEZ.- FIRMA.- EL SECRETARIO DE MOVILIDAD,\nHÉCTOR SERRANO CORTÉS, FIRMA.- EL SECRETARIO DE DESARROLLO URBANO Y VIVIENDA, FELIPE DE\nJESÚS GUTIÉRREZ GUTIÉRREZ.- FIRMA.- EL SECRETARIO DE DESARROLLO ECONÓMICO, SALOMÓN\nCHERTORIVSKI WOLDENBERG.- FIRMA.- LA SECRETARIA DEL MEDIO AMBIENTE, TANYA MÜLLER GARCÍA.-\nFIRMA.- EL SECRETARIO DE OBRAS Y SERVICIOS, EDGAR OSWALDO TUNGÜÍ RODRÍGUEZ.- FIRMA.- EL\nSECRETARIO DE TURISMO, MIGUEL TORRUCO MÁRQUES.- FIRMA.- EL SECRETARIO DE CULTURA, EDUARDO\nVÁZQUEZ MARTÍN.- FIRMA.- EL SECRETARIO DE PROTECCIÓN CIVIL, FAUSTO LUGO GARCÍA.- FIRMA.- LA\nSECRETARIA DE EDUCACIÓN, MARÍA ALEJANDRA BARRALES MAGDALENO.- FIRMA.- EL SECRETARIO DE\nFINANZAS, ÉDGAR ABRAHAM AMADOR ZAMORA.- FIRMA.- EL SECRETARIO DE SALUD, JOSÉ ARMANDO\nAHUED ORTEGA.- FIRMA.- EL SECRETARIO DE CIENCIA, TECNOLOGÍA E INNOVACIÓN, RENÉ RAÚL DRUCKER\nCOLÍN.- FIRMA.\n\nTRANSITORIOS DEL DECRETO POR EL QUE SE ADICIONAN Y REFORMAN DIVERSAS DISPOSICIONES DE LA\nLEY DE LOS DERECHOS DE LAS NIÑAS, NIÑOS Y ADOLESCENTES DE LA CIUDAD DE MÉXICO, PUBLICADO EN\nLA GACETA OFICIAL DE LA CIUDAD DE MÉXICO EL 04 DE NOVIEMBRE DE 2016.\nPRIMERO.- El presente Decreto entrará en vigor el día siguiente de su publicación en la Gaceta Oficial de la\nCiudad de México.\nSEGUNDO.- Publíquese en la Gaceta Oficial de la Ciudad de México para su conocimiento y en el Diario\nOficial de la Federación para su mayor difusión.\nRecinto de la Asamblea Legislativa del Distrito Federal, a los veintidós días del mes de septiembre del año dos mil dieciséis.- POR LA MESA DIRECTIVA.- DIP. LEONEL LUNA ESTRADA, PRESIDENTE.- DIP. NURY DELIA\nRUIZ OVANDO.- SECRETARIA.- DIP. LUIS ALBERTO MENDOZA ACEVEDO, SECRETARIO.- (Firmas)\nCon fundamento en lo dispuesto por los artículos 122, Apartado A, Base III, de la Constitución Política de los Estados Unidos Mexicanos; Transitorios Primero y Segundo del Decreto por el que se declaran reformadas y derogadas diversas disposiciones de la Constitución Política de los Estados Unidos Mexicanos, en materia de la Reforma Política de la Ciudad de México; 48, 49 y 67, fracción II, del Estatuto de Gobierno del Distrito Federal, para su debida publicación y observancia, expido el presente Decreto Promulgatorio en la Residencia Oficial del Jefe de Gobierno de la Ciudad de México, a los tres días del mes de noviembre del año dos mil dieciséis.- EL JEFE DE GOBIERNO DE LA CIUDAD DE MÉXICO, MIGUEL ÁNGEL MANCERA\nESPINOSA.- FIRMA.- LA SECRETARIA DE GOBIERNO, DORA PATRICIA MERCADO CASTRO.- FIRMA.- EL\nSECRETARIO DE DESARROLLO SOCIAL, JOSÉ RAMÓN AMIEVA GÁLVEZ.- FIRMA.\nTRANSITORIOS DEL DECRETO POR EL QUE SE REFORMAN DIVERSAS DISPOSICIONES DE LA LEY DE CULTURA\nCÍVICA DEL DISTRITO FEDERAL, DE LA LEY PARA PREVENIR Y ELIMINAR LA DISCRIMINACIÓN EN EL DISTRITO\nFEDERAL, DE LA LEY DE SALUD DEL DISTRITO FEDERAL Y DE LA LEY DE LOS DERECHOS DE LOS NIÑOS, NIÑAS\nY ADOLESCENTES DE LA CIUDAD DE MÉXICO, PUBLICADO EN LA GACETA OFICIAL DE LA CIUDAD DE MÉXICO\nEL 24 DE ABRIL DE 2017.\nARTÍCULO ÚNICO.- El presente decreto entrará en vigor al día siguiente de su publicación en la Gaceta\nOficial del Distrito Federal.\n\nRecinto de la Asamblea Legislativa del Distrito Federal, a los trece días del mes de diciembre del año dos mil dieciséis. POR LA MESA DIRECTIVA, DIP. ADRIÁN RUBALCAVA SUÁREZ, PRESIDENTE.- DIP. EVA ELOISA\nLESCAS HERNÁNDEZ, SECRETARIA.- DIP. NURY DELIA RUIZ OVANDO, SECRETARIA.- (FIRMAS).\nCon fundamento en lo dispuesto por los artículos 122, Apartado A, Base III, de la Constitución Política de los Estados Unidos Mexicanos; Transitorios Primero y Segundo del Decreto por el que se declaran reformadas y derogadas diversas disposiciones de la Constitución Política de los Estados Unidos Mexicanos, en materia de la Reforma Política de la Ciudad de México; 48, 49 y 67, fracción II, del Estatuto de Gobierno del Distrito Federal, para su debida publicación y observancia, expido el presente Decreto Promulgatorio en la Residencia Oficial del Jefe de Gobierno de la Ciudad de México, a los treinta y un días del mes de marzo del año dos mil diecisiete.- EL JEFE DE GOBIERNO DE LA CIUDAD DE MÉXICO, MIGUEL ÁNGEL\nMANCERA ESPINOSA.- FIRMA.- LA SECRETARIA DE GOBIERNO, DORA PATRICIA MERCADO CASTRO.- FIRMA.-\nEL SECRETARIO DE DESARROLLO SOCIAL, JOSÉ RAMÓN AMIEVA GÁLVEZ.- FIRMA.- EL SECRETARIO DE\nSALUD, JOSÉ ARMANDO AHUED ORTEGA.- FIRMA.-\nTRANSITORIOS DEL DECRETO POR EL QUE SE REFORMAN Y ADICIONAN DIVERSAS DISPOSICIONES DE LA\nLEY DE LOS DERECHOS DE NIÑAS, NIÑOS Y ADOLESCENTES DE LA CIUDAD DE MÉXICO, PUBLICADO EN LA\nGACETA OFICIAL DE LA CIUDAD DE MÉXICO EL 10 DE MAYO DE 2017.\nArtículo Primero.- El presente decreto entrará en vigor al día siguiente de su publicación en la Gaceta Oficial del Distrito Federal.\nArtículo Segundo.- Túrnese el presente Decreto al Jefe de Gobierno del Distrito Federal para su publicación.\nArtículo Tercero.- Se derogan todas aquellas disposiciones que se opongan al presente decreto.\nRecinto de la Asamblea Legislativa del Distrito Federal, a los dieciocho días del mes de octubre del año dos mil dieciséis. POR LA MESA DIRECTIVA, DIP. A. XAVIER LÓPEZ ADAME, PRESIDENTE.- DIP. SOCORRO MEZA\nMARTÍNEZ.- SECRETARIA.- DIP. RAYMUNDO MARTÍNEZ VITE.- PROSECRETARIO.- (Firmas)\nCon fundamento en lo dispuesto por los artículos 122, Apartado A, Base III, de la Constitución Política de los Estados Unidos Mexicanos; Transitorios Primero y Segundo del Decreto por el que se declaran reformadas y derogadas diversas disposiciones de la Constitución Política de los Estados Unidos Mexicanos, en materia de la Reforma Política de la Ciudad de México; 48, 49 y 67, fracción II, del Estatuto de Gobierno del Distrito Federal, para su debida publicación y observancia, expido el presente Decreto Promulgatorio\n\nen la Residencia Oficial del Jefe de Gobierno de la Ciudad de México, a los quince días del mes de marzo del año dos mil diecisiete.- EL JEFE DE GOBIERNO DE LA CIUDAD DE MÉXICO, MIGUEL ÁNGEL MANCERA\nESPINOSA.- FIRMA.- LA SECRETARIA DE GOBIERNO, DORA PATRICIA MERCADO CASTRO.- FIRMA.- EL\nSECRETARIO DE DESARROLLO SOCIAL.- JOSÉ RAMÓN AMIEVA GÁLVEZ.- FIRMA.- EL SECRETARIO DE\nSEGURIDAD PÚBLICA, HIRAM ALMEIDA ESTRADA.- FIRMA.- EL SECRETARIO DE CULTURA, EDUARDO\nVÁZQUEZ MARTÍN.- FIRMA.- LA SECRETARIA DE DESARROLLO RURAL Y EQUIDAD PARA LAS COMUNIDADES,\nROSA ÍCELA RODRÍGUEZ VELÁZQUEZ.-FIRMA.- EL SECRETARIO DE FINANZAS, EDGAR ABRAHAM AMADOR\nZAMORA.- FIRMA.- EL SECRETARIO DE EDUCACIÓN, MAURICIO RODRÍGUEZ ALONSO.-FIRMA.- EL\nSECRETARIO DE SALUD, JOSÉ ARMANDO AHUED ORTEGA.- FIRMA.- LA SECRETARIA DE TRABAJO Y\nFOMENTO AL EMPLEO, AMALIA DOLORES GARCÍA MEDINA.- FIRMA.\nTRANSITORIOS DEL DECRETO POR EL QUE SE REFORMA, ADICIONAN Y DEROGAN DIVERSAS\nDISPOSICIONES DE LA LEY DE LOS DERECHOS DE NIÑAS, NIÑOS Y ADOLESCENTES DE LA CIUDAD DE\nMÉXICO, PUBLICADO EN LA GACETA OFICIAL DE LA CIUDAD DE MÉXICO EL 12 DE MAYO DE 2017.\nPRIMERO.- El presente Decreto entrará en vigor el día siguiente de su publicación en la Gaceta Oficial de la\nCiudad de México.\nSEGUNDO.- Publíquese en la Gaceta Oficial del Gobierno de la Ciudad de México para su conocimiento y en el Diario Oficial de la Federación para su mayor difusión.\nTERCERO.- Se deberán hacer las adecuaciones normativas respectivas para adaptar a la presente ley, en un plazo no mayor a noventa días.\nRecinto de la Asamblea Legislativa del Distrito Federal, a los trece días del mes de diciembre del año dos mil dieciséis.- POR LA MESA DIRECTIVA.- DIP. ADRIÁN RUBALCAVA SUÁREZ, PRESIDENTE.- DIP. EVA ELOISA\nLESCAS HERNÁNDEZ, SECRETARIA.- DIP. NURY DELIA RUIZ OVANDO, SECRETARIA.- (Firmas)\nCon fundamento en lo dispuesto por los artículos 122, Apartado A, Base III, de la Constitución Política de los Estados Unidos Mexicanos; Transitorios Primero y Segundo del Decreto por el que se declaran reformadas y derogadas diversas disposiciones de la Constitución Política de los Estados Unidos Mexicanos, en materia de la Reforma Política de la Ciudad de México; 48, 49 y 67, fracción II, del Estatuto de Gobierno del Distrito Federal, para su debida publicación y observancia, expido el presente Decreto Promulgatorio en la Residencia Oficial del Jefe de Gobierno de la Ciudad de México, a los treinta días del mes de marzo del año dos mil diecisiete.- EL JEFE DE GOBIERNO DE LA CIUDAD DE MÉXICO, MIGUEL ÁNGEL MANCERA\n\nESPINOSA.- FIRMA.- LA SECRETARIA DE GOBIERNO, DORA PATRICIA MERCADO CASTRO.- FIRMA.- EL\nSECRETARIO DE DESARROLLO SOCIAL, JOSÉ RAMÓN AMIEVA GÁLVEZ.- FIRMA.- EL SECRETARIO DE\nCULTURA, EDUARDO VÁZQUEZ MARTÍN.- FIRMA.- EL SECRETARIO DE SEGURIDAD PÚBLICA, HIRAM\nALMEIDA ESTRADA.- FIRMA.- LA SECRETARIA DE DESARROLLO RURAL Y EQUIDAD PARA LAS COMUNIDADES,\nROSA ÍCELA RODRÍGUEZ VELÁZQUEZ.- FIRMA.\nTRANSITORIOS DEL DECRETO POR EL QUE SE REFORMA EL ARTÍCULO 111 DE LA LEY DE LOS DERECHOS DE\nNIÑAS, NIÑOS Y ADOLESCENTES DE LA CIUDAD DE MÉXICO, PUBLICADO EN LA GACETA OFICIAL DE LA\nCIUDAD DE MÉXICO EL 12 DE MAYO DE 2017.\nArtículo Primero.- El presente decreto entrara en vigor el día siguiente de su publicación en la Gaceta Oficial del Distrito Federal y para su mayor difusión en el Diario Oficial de la Federación.\nArtículo Segundo.- A efecto de dar cumplimiento al último párrafo del artículo 124 de la Ley General de los derechos de niñas, niños y adolescentes se establece al órgano legislativo de la Ciudad de México un plazo de 180 días para hacer las modificaciones legales conducentes.\nRecinto de la Asamblea Legislativa del Distrito Federal, a los trece días del mes de diciembre del año dos mil dieciséis.- POR LA MESA DIRECTIVA.- DIP. ADRIÁN RUBALCAVA SUÁREZ, PRESIDENTE.- DIP. EVA ELOISA\nLESCAS HERNÁNDEZ, SECRETARIA.- DIP. NURY DELIA RUIZ OVANDO, SECRETARIA.- (Firmas)\nCon fundamento en lo dispuesto por los artículos 122, Apartado A, Base III, de la Constitución Política de los Estados Unidos Mexicanos; Transitorios Primero y Segundo del Decreto por el que se declaran reformadas y derogadas diversas disposiciones de la Constitución Política de los Estados Unidos Mexicanos, en materia de la Reforma Política de la Ciudad de México; 48, 49 y 67, fracción II, del Estatuto de Gobierno del Distrito Federal, para su debida publicación y observancia, expido el presente Decreto Promulgatorio en la Residencia Oficial del Jefe de Gobierno de la Ciudad de México, a los treinta días del mes de marzo del año dos mil diecisiete.- EL JEFE DE GOBIERNO DE LA CIUDAD DE MÉXICO, MIGUEL ÁNGEL MANCERA\nESPINOSA.- FIRMA.- LA SECRETARIA DE GOBIERNO, DORA PATRICIA MERCADO CASTRO.- FIRMA.- EL\nSECRETARIO DE DESARROLLO SOCIAL, JOSÉ RAMÓN AMIEVA GÁLVEZ.- FIRMA.- EL SECRETARIO DE\nCULTURA, EDUARDO VÁZQUEZ MARTÍN.- FIRMA.- EL SECRETARIO DE EDUCACIÓN, MAURICIO RODRÍGUEZ\nALONSO.- FIRMA.- EL SECRETARIO DE SALUD, JOSÉ ARMANDO AHUED ORTEGA.- FIRMA.\n\nTRANSITORIOS DEL DECRETO POR EL QUE SE REFORMAN DIVERSAS DISPOSICIONES DE LA LEY DE SALUD\nDEL DISTRITO FEDERAL Y DE LA LEY DE LOS DERECHOS DE NIÑAS, NIÑOS Y ADOLESCENTES DE LA CIUDAD\nDE MÉXICO, PUBLICADO EN LA GACETA OFICIAL DE LA CIUDAD DE MÉXICO EL 29 DE DICIEMBRE DE 2017.\nPRIMERO.- El presente Decreto entrará en vigor el día siguiente a su publicación en la Gaceta Oficial de la\nCiudad de México.\nSEGUNDO.- Publíquese en la Gaceta Oficial de la Ciudad de México para su conocimiento, y en el Diario\nOficial de la Federación para su mayor difusión.\nTERCERO.- El Órgano Legislativo de la Ciudad de México considerará los recursos suficientes en el\nPresupuesto de Egresos de la Ciudad de México para el ejercicio 2018, para la aplicación del presente\nDecreto.\nCUARTO.- Los derechos, erogaciones y acciones previstas en este ordenamiento jurídico que impliquen erogaciones de carácter presupuestal, deberán realizarse de manera gradual y sujetarse a la capacidad financiera del Gobierno de la Ciudad de México, con el objeto de garantizar el equilibrio presupuestal.\nQUINTO.- La Secretaría de Salud de la Ciudad de México, continuará aplicando la vacuna tetravalente hasta que se descubra una vacuna que pueda cubrir más serotipos de Virus de Papiloma Humano, de conformidad con los avances médicos y científicos que pudieran surgir en un futuro y que estuvieran avalados por las instituciones competentes para dichos efectos.\nSEXTO.- El Jefe de Gobierno de la Ciudad de México contará con un plazo de 120 días hábiles contados a partir de la entrada en vigor de la presente Ley, para modificar al Reglamento de esta Ley acorde con las reformas del presente decreto.\nRecinto de la Asamblea Legislativa del Distrito Federal, a los treinta días del mes de noviembre del año dos mil diecisiete.- POR LA MESA DIRECTIVA.- DIP. FERNANDO ZÁRATE SALGADO, PRESIDENTE.- DIP. FRANCIS\nIRMA PIRIN CIGARRERO, SECRETARIA.- DIP. EVA ELOISA LESCAS HERNÁNDEZ, SECRETARIA. (Firmas)\nCon fundamento en lo dispuesto por los artículos 122, Apartado A, Base III, de la Constitución Política de los Estados Unidos Mexicanos; Transitorios Primero y Segundo del Decreto por el que se declaran reformadas y derogadas diversas disposiciones de la Constitución Política de los Estados Unidos Mexicanos, en materia de la Reforma Política de la Ciudad de México; 48, 49 y 67, fracción II, del Estatuto de Gobierno del Distrito Federal, para su debida publicación y observancia, expido el presente Decreto Promulgatorio\n\nen la Residencia Oficial del Jefe de Gobierno de la Ciudad de México, a los veintiséis días del mes de diciembre del año dos mil diecisiete.- EL JEFE DE GOBIERNO DE LA CIUDAD DE MÉXICO, MIGUEL ÁNGEL\nMANCERA ESPINOSA.- FIRMA.- LA SECRETARIA DE GOBIERNO, DORA PATRICIA MERCADO CASTRO.- FIRMA.-\nEL SECRETARIO DE DESARROLLO SOCIAL, JOSÉ RAMÓN AMIEVA GALVEZ.- FIRMA.- EL SECRETARIO DE\nFINANZAS, EDGAR ABRAHAM AMADOR ZAMORA.- FIRMA.- EL SECRETARIO DE SALUD, ROMÁN ROSALES\nAVILÉS.- FIRMA.- EL SECRETARIO DE EDUCACIÓN, MAURICIO RODRÍGUEZ ALONSO.- FIRMA.\nTRANSITORIOS DEL DECRETO POR EL QUE SE REFORMA Y ADICIONA, DIVERSAS DISPOSICIONES DEL\nCÓDIGO PENAL DEL DISTRITO FEDERAL, DE LA LEY DE ACCESO DE LAS MUJERES A UNA VIDA LIBRE DE\nVIOLENCIA DE LA CIUDAD DE MEXICO Y DE LA LEY DE LOS DERECHOS DE NIÑAS, NIÑOS Y ADOLESCENTES\nDE LA CIUDAD DE MÉXICO, PUBLICADO EN LA GACETA OFICIAL DE LA CIUDAD DE MÉXICO EL 20 DE MARZO\nDE 2020.\nPRIMERO.- Publíquese en la Gaceta Oficial de la Ciudad de México.\nSEGUNDO.- El presente Decreto entrará en vigor al día siguiente de su publicación en la Gaceta Oficial de la Ciudad de México.\nTERCERO.- A efecto de dar cumplimiento a lo dispuesto en el presente decreto, la persona Titular de la\nJefatura de Gobierno de la Ciudad de México, contará con un plazo que no excederá de 30 días hábiles, para armonizar el contenido del Reglamento de la Ley de Acceso de las Mujeres una Vida libre de Violencia de la Ciudad de México con el presente decreto.\nCUARTO.- La Secretaria de Gobierno de la Ciudad de México, contará con un término máximo de 90 días naturales para crear el Registro Público de Personas Agresoras Sexuales de la Ciudad de México, mismo que entrara en vigor al día siguiente de su publicación en la Gaceta Oficial de la Ciudad de México.\nQUINTO.- A partir de la entrada en vigor del presente decreto, la Secretaria de Gobierno, deberá incluir en la base de datos del Registro, todas aquellas personas sentenciadas que hayan adquirido ese carácter con fecha posterior a la entrada del presente decreto.\nSEXTO.- Envíese el presente decreto a la Jefa de Gobierno de la Ciudad de México para sus efectos legales.\nPalacio Legislativo del Congreso de la Ciudad de México, a los diez días del mes de marzo del año dos mil veinte.- POR LA MESA DIRECTIVA.- DIPUTADA ISABELA ROSALES HERRERA, PRESIDENTA.- DIPUTADA DONAJI\n\nOFELIA OLIVERA REYES, SECRETARIA.- DIPUTADA MARGARITA SALDAÑA HERNÁNDEZ, SECRETARIA.-\n(Firmas)\nCon fundamento en lo dispuesto por los artículos 122, apartado A, fracción III de la Constitución Política de los Estados Unidos Mexicanos; 32, apartado C, numeral 1, inciso a) de la Constitución Política de la Ciudad de México; 2 párrafo segundo, 3 fracciones XVII y XVIII, 7 párrafo primero, 10 fracción II, 12 y 21 párrafo primero de la Ley Orgánica del Poder Ejecutivo y de la Administración Pública de la Ciudad de México; para su debida publicación y observancia, expido el presente Decreto Promulgatorio en la Residencia Oficial de la Jefatura de Gobierno de la Ciudad de México, a los diecinueve días del mes marzo del año dos mil veinte.- LA JEFA DE GOBIERNO DE LA CIUDAD DE MÉXICO, DRA. CLAUDIA SHEINBAUM PARDO.- FIRMA.- LA\nSECRETARIA DE GOBIERNO, ROSA ICELA RODRÍGUEZ VELÁZQUEZ.- FIRMA.- LA SECRETARIA DE INCLUSIÓN\nY BIENESTAR SOCIAL, ALMUDENA OCEJO ROJO.- FIRMA.\nTRANSITORIOS DEL DECRETO POR EL QUE SE ADICIONA UN TERCER PÁRRAFO AL ARTÍCULO 15 DE LA LEY\nDE LOS DERECHOS DE NIÑAS, NIÑOS Y ADOLESCENTES DE LA CIUDAD DE MÉXICO, PUBLICADO EN LA\nGACETA OFICIAL DE LA CIUDAD DE MÉXICO EL 12 DE OCTUBRE DE 2020.\nPRIMERO.- El presente decreto entrará en vigor al día siguiente de su publicación en la Gaceta Oficial de la\nCiudad de México.\nSEGUNDO.- El Gobierno de la Ciudad de México emitirá los protocolos de actuación a que hace referencia el último párrafo del artículo 15, en un término no mayor de 90 días naturales a partir de la entrada en vigor del presente decreto.\nPalacio Legislativo del Congreso de la Ciudad de México, a los diez días del mes de septiembre del año dos mil veinte. POR LA MESA DIRECTIVA.- DIPUTADA MARGARITA SALDAÑA HERNÁNDEZ, PRESIDENTA.-\nDIPUTADA DONAJI OFELIA OLIVERA REYES, SECRETARIA.- DIPUTADO HÉCTOR BARRERA MARMOLEJO,\nSECRETARIO.- (Firmas)\nCon fundamento en lo dispuesto por los artículos 122, apartado A, fracción III, de la Constitución Política de los Estados Unidos Mexicanos; 32 apartado C, numeral 1, inciso a) de la Constitución Política de la\nCiudad de México; 3 fracciones XVII y XVIII, 7 párrafo primero, 10 fracción II, 12 y 21, párrafo primero de la\nLey Orgánica del Poder Ejecutivo y de la Administración Pública de la Ciudad de México, para su debida publicación y observancia, expido el presente Decreto Promulgatorio en la Residencia Oficial de la Jefatura de Gobierno de la Ciudad de México, a los nueve días del mes de octubre del año dos mil veinte.- LA JEFA\n\nDE GOBIERNO DE LA CIUDAD DE MÉXICO, DRA. CLAUDIA SHEINBAUM PARDO.- FIRMA.- LA SECRETARIA DE\nINCLUSIÓN Y BIENESTAR SOCIAL, ALMUDENA OCEJO ROJO.- FIRMA.- EL SECRETARIO DE SEGURIDAD\nCIUDADANA, OMAR HAMID GARCÍA HARFUCH.- FIRMA.\nTRANSITORIO DEL DECRETO POR EL QUE SE ADICIONA UN PÁRRAFO SEGUNDO A LA FRACCIÓN IX DEL\nARTÍCULO 44 DE LA LEY DE LOS DERECHOS DE NIÑAS, NIÑOS Y ADOLESCENTES DE LA CIUDAD DE MÉXICO,\nPUBLICADO EN LA GACETA OFICIAL DE LA CIUDAD DE MÉXICO EL 01 DE DICIEMBRE DE 2020.\nÚNICO. El presente decreto entrará en vigor al día siguiente de su publicación en la Gaceta Oficial de la\nCiudad de México.\nPalacio Legislativo del Congreso de la Ciudad de México, a los diez días del mes de noviembre del año dos mil veinte.- POR LA MESA DIRECTIVA.- DIPUTADA MARGARITA SALDAÑA HERNÁNDEZ, PRESIDENTA.-\nDIPUTADA DONAJI OFELIA OLIVERA REYES, SECRETARIA.- DIPUTADO HÉCTOR BARRERA MARMOLEJO,\nSECRETARIO.- (Firmas)\nCon fundamento en lo dispuesto por los artículos 122, apartado a, fracción III, de la Constitución Política de los Estados Unidos Mexicanos; 32 apartado C, numeral 1, inciso a) de la Constitución Política de la\nCiudad de México; 3 fracciones XVII y XVIII, 7 párrafo primero, 10 fracción II, 12 y 21, párrafo primero de la\nLey Orgánica del Poder Ejecutivo y de la Administración Pública de la ciudad de México, para su debida publicación y observancia, expido el presente decreto Promulgatorio en la Residencia Oficial de la Jefatura de Gobierno de la Ciudad de México, a los veintisiete días del mes de noviembre del año dos mil veinte.-\nLA JEFA DE GOBIERNO DE LA CIUDAD DE MÉXICO, DRA. CLAUDIA SHEINBAUM PARDO.- FIRMA.- LA\nSECRETARIA DE INCLUSIÓN Y BIENESTAR SOCIAL, ALMUDENA OCEJO ROJO. FIRMA.\nTRANSITORIO DEL DECRETO POR EL QUE SE ADICIONA UNA FRACCIÓN XXIII AL ARTÍCULO 13; Y, UNA\nFRACCIÓN VIII AL ARTÍCULO 102, RECORRIENDO LA ACTUAL FRACCIÓN VIII PARA CONVERTIRSE EN IX;\nAMBOS DE LA LEY DE LOS DERECHOS DE NIÑAS, NIÑOS Y ADOLESCENTES DE LA CIUDAD DE MÉXICO,\nPUBLICADO EN LA GACETA OFICIAL DE LA CIUDAD DE MÉXICO EL 01 DE DICIEMBRE DE 2020.\nPRIMERO. El presente decreto entrará en vigor al día siguiente de su publicación en la Gaceta Oficial de la\nCiudad de México.\n\nSEGUNDO. El Sistema para el Desarrollo Integral de la Familia de la Ciudad de México, contará con un término de 180 días naturales a partir de la entrada en vigor del presente decreto, para el cumplimiento de las obligaciones previstas en virtud del mismo.\nPalacio Legislativo del Congreso de la Ciudad de México, a los diez días del mes de noviembre del año dos mil veinte.- POR LA MESA DIRECTIVA.- DIPUTADA MARGARITA SALDAÑA HERNÁNDEZ, PRESIDENTA.-\nDIPUTADA DONAJI OFELIA OLIVERA REYES, SECRETARIA.- DIPUTADO HÉCTOR BARRERA MARMOLEJO,\nSECRETARIO.- (Firmas)\nCon fundamento en lo dispuesto por los artículos 122, apartado a, fracción III, de la Constitución Política de los Estados Unidos Mexicanos; 32 apartado C, numeral 1, inciso a) de la Constitución Política de la\nCiudad de México; 3 fracciones XVII y XVIII, 7 párrafo primero, 10 fracción II, 12 y 21, párrafo primero de la\nLey Orgánica del Poder Ejecutivo y de la Administración Pública de la ciudad de México, para su debida publicación y observancia, expido el presente decreto Promulgatorio en la Residencia Oficial de la Jefatura de Gobierno de la Ciudad de México, a los veintisiete días del mes de noviembre del año dos mil veinte.-\nLA JEFA DE GOBIERNO DE LA CIUDAD DE MÉXICO, DRA. CLAUDIA SHEINBAUM PARDO.- FIRMA.- LA\nSECRETARIA DE INCLUSIÓN Y BIENESTAR SOCIAL, ALMUDENA OCEJO ROJO.-FIRMA.\nTRANSITORIO DEL DECRETO POR EL SE REFORMAN Y ADICIONAN DIVERSOS ARTÍCULOS DE LA LEY DE LOS\nDERECHOS DE NIÑAS, NIÑOS Y ADOLESCENTES DE LA CIUDAD DE MÉXICO PUBLICADO EN LA GACETA\nOFICIAL EL DÍA 10 DE FEBRERO DE 2021\nPrimero. El presente Decreto entrará en vigor el día siguiente de su publicación en la Gaceta Oficial de la\nCiudad de México.\nSegundo. El DIF CDMX y la Procuraduría de Protección, dispondrán las medidas necesarias a fin de implementar el procedimiento único de adopción.\nTercero. Los procedimientos administrativos y los procesos jurisdiccionales de adopción que se encuentren en trámite a la fecha de la entrada en vigor del presente Decreto se seguirán conforme a la normatividad aplicable al momento de su inicio, pero se podrá aplicar lo dispuesto en este decreto en todo aquello que beneficie al interés superior de la niñez.\nCuarto. El Protocolo Interinstitucional para la Atención de Niñas, Niños y Adolescentes en Situación de\nDesamparo en la Ciudad de México conserva su vigencia en todo lo que no se oponga al presente decreto.\n\nEl poder Ejecutivo Local realizará la actualización al Protocolo Interinstitucional para la Atención de Niñas,\nNiños y Adolescentes en Situación de Desamparo en la Ciudad de México, así como las adecuaciones correspondientes al Reglamento de la Ley de los Derechos de Niñas, Niños y Adolescentes de la Ciudad de\nMéxico y expedirá Los lineamientos de integración y funcionamiento del Comité Técnico de Adopción de la Ciudad de México en un plazo que no excederá de 120 días naturales posteriores a la entrada en vigor del presente decreto.\nQuinto. El DIF CDMX atenderá las convocatorias del Sistema Nacional DIF con la finalidad de actualizar el registro de niñas, niños y adolescentes que actualmente sean susceptibles de adopción, las personas solicitantes de adopción en proceso, así como los que hayan obtenido certificado de idoneidad.\nSexto. El DIF CDMX realizará lo conducente para favorecer el interés superior de la niñez y se reduzca al máximo la estancia de las niñas, niños o adolescentes en Centros de Asistencia Social o instituciones que brinden cuidados alternativos, o con familias de acogida.\nSéptimo. Respecto del Registro del registro de adopción establecido en el artículo 40 de la Ley de Derechos de Niñas, Niños y Adolescentes de la Ciudad de México el DIF CDMX, tomará las medidas necesarias para coordinar los trabajos con el DIF Nacional a fin de que los parámetros y campos de registro local mantengan homogeneidad y compatibilidad de formato con los del registro nacional y que puedan ser incorporados de forma eficaz.\nOctavo. Se derogan todas las disposiciones que se opongan al presente Decreto.\nPalacio Legislativo del Congreso de la Ciudad de México, a los dos días del mes de febrero del año dos mil veintiuno. POR LA MESA DIRECTIVA.-DIPUTADA MARGARITA SALDAÑA HERNÁNDEZ, PRESIDENTA.-\nDIPUTADA DONAJI OFELIA OLIVERA REYES, SECRETARIA.- DIPUTADO PABLO MONTES DE OCA DEL OLMO,\nSECRETARIO.- (Firmas)\nCon fundamento en lo dispuesto por los artículos 122, apartado A, fracción III de la Constitución Política de los Estados Unidos Mexicanos; 32, apartado C, numeral 1, inciso a) de la Constitución Política de la Ciudad de México; 2 párrafo segundo, 3 fracciones XVII y XVIII, 7 párrafo primero, 10 fracción II, 12 y 21 párrafo primero de la Ley Orgánica del Poder Ejecutivo y de la Administración Pública de la Ciudad de México; para su debida publicación y observancia, expido el presente Decreto Promulgatorio en la Residencia Oficial de la Jefatura de Gobierno de la Ciudad de México, a los nueve días del mes de febrero del año dos mil veintiuno.- LA JEFA DE GOBIERNO DE LA CIUDAD DE MÉXICO, DRA. CLAUDIA SHEINBAUM PARDO.- FIRMA.-\nEL SECRETARIO DE GOBIERNO, JOSÉ ALFONSO SUÁREZ DEL REAL Y AGUILERA.- FIRMA.- EL SECRETARIO DE\n\nLA CONTRALORÍA GENERAL, JUAN JOSÉ SERRANO MENDOZA.- FIRMA.-LA SECRETARIA DE INCLUSIÓN Y\nBIENESTAR SOCIAL, ALMUDENA OCEJO ROJO.- FIRMA.- EL CONSEJERO JURÍDICO Y DE SERVICIOS\nLEGALES.- NÉSTOR VARGAS SOLANO.-FIRMA.\nTRANSITORIO DEL DECRETO POR EL QUE SE ADICIONA AL ARTÍCULO 2 UNA FRACCIÓN I RECORRIENDO EN\nSU ORDEN LAS SUBSECUENTES, AL ARTÍCULO 89 UNA FRACCIÓN I RECORRIENDO EN SU ORDEN LAS\nSUBSECUENTES; SE REFORMA EL ARTÍCULO 2 EN SU ÚLTIMO PÁRRAFO, ARTÍCULO 4 FRACCIÓN VIII,\nARTÍCULO 6 FRACCIÓN VI, ARTÍCULO 13 FRACCIÓN I, ARTÍCULO 15 EN SU PÁRRAFO PRIMERO Y SEGUNDO,\nARTÍCULO 99 FRACCIÓN VI, ASÍ COMO LA DENOMINACIÓN DEL CAPÍTULO PRIMERO DEL TÍTULO SEGUNDO;\nTODOS ELLOS DE LA LEY DE LOS DERECHOS DE NIÑAS, NIÑOS Y ADOLESCENTES DE LA CIUDAD DE MÉXICO,\nPUBLICADO EN LA GACETA OFICIAL DE LA CIUDAD DE MÉXICO EL DÍA 07 DE MAYO DE 2021.\nÚNICO. El presente Decreto entrará en vigor al día siguiente de su publicación en la Gaceta Oficial de la\nCiudad de México.\nPalacio Legislativo del Congreso de la Ciudad de México, a los seis días del mes de abril del año dos mil veintiuno. POR LA MESA DIRECTIVA, DIPUTADA YURIRI AYALA ZUÑIGA, PRESIDENTA, DIPUTADA DONAJI\nOFELIA OLIVERA REYES, SECRETARIA, DIPUTADO PABLO MONTES DE OCA DEL OLMO, SECRETARIO (FIRMAS)\nCon fundamento en lo dispuesto por los artículos 122, apartado A, fracción III de la Constitución Política de los Estados Unidos Mexicanos; 32, apartado C, numeral 1, inciso a) de la Constitución Política de la Ciudad de México; 2 párrafo segundo, 3 fracciones XVII y XVIII, 7 párrafo primero, 10 fracción II, 12 y 21 párrafo primero de la Ley Orgánica del Poder Ejecutivo y de la Administración Pública de la Ciudad de México; para su debida publicación y observancia, expido el presente Decreto Promulgatorio en la Residencia Oficial de la Jefatura de Gobierno de la Ciudad de México, a los seis días del mes de mayo del año dos mil veintiuno.\nLA JEFA DE GOBIERNO DE LA CIUDAD DE MÉXICO, DRA. CLAUDIA SHEINBAUM PARDO.- FIRMA.- EL\nSECRETARIO DE GOBIERNO, JOSÉ ALFONSO SUÁREZ DEL REAL Y AGUILERA.- FIRMA.- LA SECRETARIA DE\nINCLUSIÓN Y BIENESTAR SOCIAL, ALMUDENA OCEJO ROJO.- FIRMA.\nTRANSITORIO DEL DECRETO POR EL QUE SE REFORMA LA FRACCIÓN XX DEL ARTÍCULO 13; LA FRACCIÓN\nXVIII DEL ARTÍCULO 58; LA FRACCIÓN XI Y XII DEL ARTÍCULO 89 Y SE ADICIONA: UN CAPÍTULO DÉCIMO\nNOVENO TITULADO “DERECHO DE ACCESO A LAS TECNOLOGÍAS DE LA INFORMACIÓN Y COMUNICACIÓN”\nQUE CONTIENE LOS ARTÍCULOS 88 BIS, 88 TER, 88 QUÁTER;Y, LA FRACCIÓN XIII AL ARTÍCULO 89 DE LA LEY\n\nDE LOS DERECHOS DE NIÑAS, NIÑOS Y ADOLESCENTES, PUBLICADO EN LA GACETA OFICIAL DE LA CIUDAD\nDE MÉXICO EL DÍA 09 JUNIO DE 2021.\nPRIMERO. El presente Decreto entrará en vigor al día siguiente de su publicación en la Gaceta Oficial de la\nCiudad de México.\nSEGUNDO.- El establecimiento de política de inclusión digital universal se realizará de acuerdo a las disposiciones reglamentarias y en su caso por las reglas de operación del programa emitidas por la Jefatura de Gobierno de la Ciudad de México, y se sujetarán a la disponibilidad presupuestaria con la que se cuente.\nTERCERO.- El primer informe a que hace referencia el segundo párrafo del artículo 88 Ter, deberá ser presentado al Congreso de la Ciudad de México al año siguiente de la entrada en vigor del presente\nDecreto.\nPalacio Legislativo del Congreso de la Ciudad de México, a los veinticinco días del mes de mayo del año dos mil veintiuno. POR LA MESA DIRECTIVA, DIPUTADA ANA PATRICIA BAEZ GUERRERO, PRESIDENTA,\nDIPUTADA DONAJI OFELIA OLIVERA REYES, SECRETARÍA, DIPUTADO PABLO MONTES DE OCA DEL OLMO,\nSECRETARIO (Firmas)\nCon fundamento en lo dispuesto por los artículos 122, apartado A, fracción III de la Constitución Política de los Estados Unidos Mexicanos; 32, apartado C, numeral 1, inciso a) de la Constitución Política de la Ciudad de México; 2 párrafo segundo, 3 fracciones XVII y XVIII, 7 párrafo primero, 10 fracción II, 12 y 21 párrafo primero de la Ley Orgánica del Poder Ejecutivo y de la Administración Pública de la Ciudad de México; para su debida publicación y observancia, expido el presente Decreto Promulgatorio en la Residencia Oficial de la Jefatura de Gobierno de la Ciudad de México, a los siete días del mes de junio del año dos mil veintiuno.-\nLA JEFA DE GOBIERNO DE LA CIUDAD DE MÉXICO, DRA. CLAUDIA SHEINBAUM PARDO.- FIRMA.- EL\nSECRETARIO DE GOBIERNO, JOSÉ ALFONSO SUÁREZ DEL REAL Y AGUILERA.- FIRMA.- LA SECRETARIA DE\nEDUCACIÓN, CIENCIA, TECNOLOGÍA E INNOVACIÓN, ROSAURA RUIZ GUTIÉRREZ.- FIRMA.- LA SECRETARIA\nDE INCLUSIÓN Y BIENESTAR SOCIAL, ALMUDENA OCEJO ROJO.- FIRMA.\nDECRETO POR EL QUE SE REFORMAN LOS ARTÍCULOS 13, FRACCIÓN IX 47, PRIMER PÁRRAFO Y, SE\nADICIONAN LAS FRACCIONES XXI Y XXII AL ARTÍCULO 58, TODOS DE LA LEY DE LOS DERECHOS DE NIÑAS,\nNIÑOS Y ADOLESCENTES DE LA CIUDAD DE MÉXICO, PUBLICADO EN LA GACETA OFICIAL DE LA CIUDAD DE\nMÉXICO EL DÍA 11 DE JUNIO DE 2021.\n\nÚNICO. El presente Decreto entrará en vigor al día siguiente de su publicación en la Gaceta Oficial de la\nCiudad de México.\nPalacio Legislativo del Congreso de la Ciudad de México, a los veinticinco días del mes de mayo del año dos mil veintiuno. POR LA MESA DIRECTIVA, DIPUTADA ANA PATRICIA BAEZ GUERRERO, PRESIDENTA,\nDIPUTADA DONAJI OFELIA OLIVERA REYES, SECRETARÍA, DIPUTADO PABLO MONTES DE OCA DEL OLMO,\nSECRETARIO (Firmas)\nCon fundamento en lo dispuesto por los artículos 122, apartado A, fracción III de la Constitución Política de los Estados Unidos Mexicanos; 32, apartado C, numeral 1, inciso a) de la Constitución Política de la Ciudad de México; 2 párrafo segundo, 3 fracciones XVII y XVIII, 7 párrafo primero, 10 fracción II, 12 y 21 párrafo primero de la Ley Orgánica del Poder Ejecutivo y de la Administración Pública de la Ciudad de México; para su debida publicación y observancia, expido el presente Decreto Promulgatorio en la Residencia Oficial de la Jefatura de Gobierno de la Ciudad de México, a los diez días del mes de junio del año dos mil veintiuno.-\nLA JEFA DE GOBIERNO DE LA CIUDAD DE MÉXICO, DRA. CLAUDIA SHEINBAUM PARDO.- FIRMA.- EL\nSECRETARIO DE GOBIERNO, JOSÉ ALFONSO SUÁREZ DEL REAL Y AGUILERA.- FIRMA.- LA SECRETARIA DE\nINCLUSIÓN Y BIENESTAR SOCIAL, ALMUDENA OCEJO ROJO.- FIRMA\nTRANSITORIOS DEL DECRETO POR EL QUE SE ADICIONAN LAS FRACCIONES XIII BIS Y XIII TER AL ARTÍCULO\n4; ASÍ COMO UN TERCER PÁRRAFO AL ARTÍCULO 43; SE MODIFICA LA FRACCIÓN X Y SE ADICIONA UNA\nFRACCIÓN XI AL ARTÍCULO 44; SE MODIFICA LA FRACCIÓN VIII Y SE ADICIONA LA FRACCIÓN VIII BIS AL\nARTÍCULO 102 DE LA LEY DE LOS DERECHOS DE NIÑAS, NIÑOS Y ADOLESCENTES DE LA CIUDAD DE MÉXICO,\nPUBLICADO EN LA GACETA OFICIAL DE LA CIUDAD DE MÉXICO EL DÍA 23 DE FEBRERO DE 2022.\nPRIMERO.- Remítase a la persona titular de la Jefatura de Gobierno para su promulgación y publicación en la Gaceta Oficial de la Ciudad de México.\nSEGUNDO.- El presente Decreto entrará en vigor al día siguiente de su publicación en la Gaceta Oficial de la Ciudad de México.\nPalacio Legislativo del Congreso de la Ciudad de México, a los veintidós días del mes de febrero del año dos mil veintidós. POR LA MESA DIRECTIVA.- DIPUTADO HÉCTOR DIAZ POLANCO, PRESIDENTE.- DIPUTADA\nMARCELA FUENTE CASTILLO, SECRETARIA.- DIPUTADA FRIDA JIMENA GUILLÉN ORTIZ, SECRETARIA.- (Firmas)\n\nCon fundamento en lo dispuesto por los artículos 122, apartado A, fracción III de la Constitución Política de los Estados Unidos Mexicanos; 32, apartado C, numeral 1, inciso a) de la Constitución Política de la Ciudad de México; 2 párrafo segundo, 3 fracciones XVII y XVIII, 7 párrafo primero, 10 fracción II, 12 y 21 párrafo primero de la Ley Orgánica del Poder Ejecutivo y de la Administración Pública de la Ciudad de México; para su debida publicación y observancia, expido el presente Decreto Promulgatorio en la Residencia Oficial de la Jefatura de Gobierno de la Ciudad de México, a los veintitrés días del mes febrero del año dos mil veintidós.- LA JEFA DE GOBIERNO DE LA CIUDAD DE MÉXICO, DRA. CLAUDIA SHEINBAUM PARDO.- FIRMA.-\nEL SECRETARIO DE GOBIERNO, MARTÍ BATRES GUADARRAMA.- FIRMA.- EL SECRETARIO DE INCLUSIÓN Y\nBIENESTAR SOCIAL, CARLOS ALBERTO ULLOA PÉREZ.- FIRMA.\nTRÁNSITORIO DEL DECRETO POR EL QUE SE REFORMAN LA FRACCIÓN V DEL ARTÍCULO 2; SE REFORMA LA\nFRACCIÓN II DEL ARTÍCULO 6; Y SE MODIFICA EL PÁRRAFO SEGUNDO DEL ARTÍCULO 12 DE LA LEY DE LOS\nDERECHOS DE NIÑAS, NIÑOS Y ADOLESCENTES DE LA CIUDAD DE MÉXICO, PUBLICADO EN LA GACETA\nOFICIAL DE LA CIUDAD DE MÉXICO, EL 27 DE MAYO DE 2022.\nPRIMERO. - Remítase a la persona titular de la Jefatura de Gobierno para su promulgación y publicación en la Gaceta Oficial de la Ciudad de México.\nSEGUNDO. - El presente Decreto entrará en vigor al día siguiente de su publicación en la Gaceta Oficial de la Ciudad de México.\nPalacio Legislativo del Congreso de la Ciudad de México, a los doce días del mes de mayo del año dos mil veintidós. POR LA MESA DIRECTIVA, DIPUTADO HÉCTOR DIAZ POLANCO, PRESIDENTE. - DIPUTADA\nMARCELA FUENTE CASTILLO, SECRETARIA. - DIPUTADA FRIDA JIMENA GUILLÉN ORTIZ, SECRETARIA. -\n(Firmas)\nCon fundamento en lo dispuesto por los artículos 122, apartado A, fracción III de la Constitución Política de los Estados Unidos Mexicanos; 32, apartado C, numeral 1, inciso a) de la Constitución Política de la Ciudad de México; 2 párrafo segundo, 3 fracciones XVII y XVIII, 7 párrafo primero, 10 fracción II, 12 y 21 párrafo primero de la Ley Orgánica del Poder Ejecutivo y de la Administración Pública de la Ciudad de México; para su debida publicación y observancia, expido el presente Decreto Promulgatorio en la Residencia Oficial de la Jefatura de Gobierno de la Ciudad de México, a los veintiséis días del mes de mayo del año dos mil veintidós.- LA JEFA DE GOBIERNO DE LA CIUDAD DE MÉXICO, DRA. CLAUDIA SHEINBAUM PARDO.- FIRMA.-\nSECRETARIO DE INCLUSIÓN Y BIENESTAR SOCIAL, CARLOS ALBERTO ULLOA PÉREZ.- FIRMA.- EL SECRETARIO\nDE TRABAJO Y FOMENTO AL EMPLEO, JOSÉ LUIS RODRIGUEZ DÍAZ DE LEÓN.- FIRMA.\n\nTRÁNSITORIO DEL DECRETO POR EL QUE SE ADICIONA UNA FRACCIÓN VIII BIS AL ARTÍCULO 89 DE LA LEY\nDE LOS DERECHOS DE NIÑAS, NIÑOS Y ADOLESCENTES DE LA CIUDAD DE MÉXICO, PUBLICADO EN LA\nGACETA OFICIAL DE LA CIUDAD DE MÉXICO, EL 21 DE OCTUBRE DE 2022.\nPRIMERO. - Remítase a la persona titular de la Jefatura de Gobierno para su promulgación y publicación en la Gaceta Oficial de la Ciudad de México.\nSEGUNDO. - El presente Decreto entrará en vigor al día siguiente de su publicación en la Gaceta Oficial de la Ciudad de México.\nPalacio Legislativo del Congreso de la Ciudad de México, a los veintinueve días del mes de septiembre del año dos mil veintidós. POR LA MESA DIRECTIVA DIPUTADO FAUSTO MANUEL ZAMORANO ESPARZA,\nPRESIDENTE.- DIPUTADA MARCELA FUENTE CASTILLO, SECRETARIA.- DIPUTADA MARIA GABRIELA SALIDO\nMAGOS, SECRETARIA.- (Firmas)\nCon fundamento en lo dispuesto por los artículos 122, apartado A, fracción III de la Constitución Política de los Estados Unidos Mexicanos; 32, apartado C, numeral 1, inciso a) de la Constitución Política de la Ciudad de México; 2 párrafo segundo, 3 fracciones XVII y XVIII, 7 párrafo primero, 10 fracción II, 12 y 21 párrafo primero de la Ley Orgánica del Poder Ejecutivo y de la Administración Pública de la Ciudad de México; para su debida publicación y observancia, expido el presente Decreto Promulgatorio en la Residencia Oficial de la Jefatura de Gobierno de la Ciudad de México, a los veinte días del mes octubre del año dos mil veintidós.-\nLA JEFA DE GOBIERNO DE LA CIUDAD DE MÉXICO, DRA. CLAUDIA SHEINBAUM PARDO.- FIRMA.- EL\nSECRETARIO DE GOBIERNO, MARTÍ BATRES GUADARRAMA.- FIRMA.- EL ENCARGADO DE DESPACHO DE LA\nSECRETARÍA DE INCLUSIÓN Y BIENESTAR SOCIAL, RIGOBERTO SALGADO VÁZQUEZ.- FIRMA.- EL SECRETARIO\nDE MOVILIDAD, ANDRÉS LAJOUS LOAEZA.- FIRMA.- EL SECRETARIO DE SEGURIDAD CIUDADANA, OMAR\nHAMID GARCÍA HARFUCH.- FIRMA.\nTRÁNSITORIO DEL DECRETO POR EL QUE SE ADICIONA UN PÁRRAFO SEGUNDO A LA FRACCIÓN IX DEL\nARTÍCULO 47 DE LA LEY DE LOS DERECHOS DE NIÑAS, NIÑOS Y ADOLESCENTES LA CIUDAD DE MÉXICO,\nPUBLICADO EN LA GACETA OFICIAL DE LA CIUDAD DE MÉXICO, EL 12 DE DICIEMBRE DE 2022.\nPRIMERO. - Remítase a la persona titular de la Jefatura de Gobierno para su promulgación y publicación en la Gaceta Oficial de la Ciudad de México.\n\nSEGUNDO. - El presente Decreto entrará en vigor al día siguiente de su publicación en la Gaceta Oficial de la Ciudad de México.\nPalacio Legislativo del Congreso de la Ciudad de México, a los veintinueve días del mes de noviembre del año dos mil veintidós.- POR LA MESA DIRECTIVA.- DIPUTADO FAUSTO MANUEL ZAMORANO ESPARZA,\nPRESIDENTE.- DIPUTADA MARCELA FUENTE CASTILLO, SECRETARIA.- DIPUTADA MARIA GABRIELA SALIDO\nMAGOS, SECRETARIA.- (Firmas)\nCon fundamento en lo dispuesto por los artículos 122, apartado A, fracción III de la Constitución Política de los Estados Unidos Mexicanos; 32, apartado C, numeral 1, inciso a) de la Constitución Política de la Ciudad de México; 2 párrafo segundo, 3 fracciones XVII y XVIII, 7 párrafo primero, 10 fracción II, 12 y 21 párrafo primero de la Ley Orgánica del Poder Ejecutivo y de la Administración Pública de la Ciudad de México; para su debida publicación y observancia, expido el presente Decreto Promulgatorio en la Residencia Oficial de la Jefatura de Gobierno de la Ciudad de México, a los nueve días del mes de diciembre del año dos mil veintidós.- LA JEFA DE GOBIERNO DE LA CIUDAD DE MÉXICO, DRA. CLAUDIA SHEINBAUM PARDO.- FIRMA.-\nEL SECRETARIO DE GOBIERNO, MARTÍ BATRES GUADARRAMA.- FIRMA.- EL SECRETARIO DE INCLUSIÓN Y\nBIENESTAR SOCIAL, RIGOBERTO SALGADO VÁZQUEZ.- FIRMA.- LA SECRETARIA DE SALUD, OLIVA LÓPEZ\nARELLANO.- FIRMA.\nTRÁNSITORIO DEL DECRETO POR EL QUE SE REFORMAN LAS FRACCIONES III, IV, V Y SE ADICIONA UNA\nFRACCIÓN VI AL ARTÍCULO 2; SE REFORMA LAS FRACCIONES V Y EL INCISO B) DE LA FRACCIÓN VI DEL\nARTÍCULO 112 DE LA LEY DE LOS DERECHOS DE NIÑAS, NIÑOS Y ADOLESCENTES DE LA CIUDAD DE MÉXICO,\nPUBLICADO EN LA GACETA OFICIAL DE LA CIUDAD DE MÉXICO EL 03 DE MARZO DE 2023.\nPRIMERO.- Remítase a la persona titular de la Jefatura de Gobierno para su promulgación y publicación en la Gaceta Oficial de la Ciudad de México.\nSEGUNDO.- El presente Decreto entrará en vigor al día siguiente de su publicación en la Gaceta Oficial de la Ciudad de México. FIRMAS DEL DECRETO POR EL QUE SE REFORMAN LAS FRACCIONES III, IV, V Y SE\nADICIONA UNA FRACCIÓN VI AL ARTÍCULO 2; SE REFORMA LAS FRACCIONES V Y EL INCISO B) DE LA\nFRACCIÓN VI DEL ARTÍCULO 112 DE LA LEY DE LOS DERECHOS DE NIÑAS, NIÑOS Y ADOLESCENTES DE LA\nCIUDAD DE MÉXICO.\n\nPalacio Legislativo del Congreso de la Ciudad de México, a los veintiún días del mes de febrero del año dos mil veintitrés.- POR LA MESA DIRECTIVA.- DIPUTADO FAUSTO MANUEL ZAMORANO ESPARZA, PRESIDENTE.-\nDIPUTADA MARCELA FUENTE CASTILLO, SECRETARIA.- DIPUTADA MARIA GABRIELA SALIDO MAGOS,\nSECRETARIA.- (Firmas)\nCon fundamento en lo dispuesto por los artículos 122, apartado A, fracción III de la Constitución Política de los Estados Unidos Mexicanos; 32, apartado C, numeral 1, inciso a) de la Constitución Política de la Ciudad de México; 2 párrafo segundo, 3 fracciones XVII y XVIII, 7 párrafo primero, 10 fracción II, 12 y 21 párrafo primero de la Ley Orgánica del Poder Ejecutivo y de la Administración Pública de la Ciudad de México; para su debida publicación y observancia, expido el presente Decreto Promulgatorio en la Residencia Oficial de la Jefatura de Gobierno de la Ciudad de México, a los dos días del mes de marzo del año dos mil veintitrés.-\nLA JEFA DE GOBIERNO DE LA CIUDAD DE MÉXICO, DRA. CLAUDIA SHEINBAUM PARDO.- FIRMA.- EL\nSECRETARIO DE GOBIERNO, MARTÍ BATRES GUADARRAMA.- FIRMA.- EL SECRETARIO DE INCLUSIÓN Y\nBIENESTAR SOCIAL, RIGOBERTO SALGADO VÁZQUEZ.- FIRMA.\nDECRETO POR EL QUE SE REFORMAN LAS FRACCIONES X Y XI, Y SE ADICIONA UNA FRACCIÓN XII DEL\nARTÍCULO 44; SE ADICIONA UN PÁRRAFO SEGUNDO, TERCERO Y CUARTO, RECORRIENDOSE LOS\nSUBSECUENTES, DEL ARTÍCULO 78; SE REFORMA EL PARRAFO PRIMERO DEL ARTÍCULO 79; Y SE ADICIONA\nUN PÁRRAFO SEGUNDO, RECORRIENDOSE EL SUBSECUENTE, DEL ARTÍCULO 83; TODOS DE LA LEY DE LOS\nDERECHOS DE NIÑAS, NIÑOS Y ADOLESCENTES DE LA CIUDAD DE MÉXICO, PUBLICADO EN LA GACETA\nOFICIAL DE LA CIUDAD DE MÉXICO EL 21 DE ABRIL DE 2023.\nPRIMERO. Remítase a la persona titular de la Jefatura de Gobierno para su publicación en la Gaceta Oficial de la Ciudad de México.\nSEGUNDO. El presente Decreto entrará en vigor al siguiente día de su publicación en la Gaceta Oficial de la\nCiudad de México.\nPalacio Legislativo del Congreso de la Ciudad de México, a los veintiocho días del mes de marzo del año dos mil veintitrés.- POR LA MESA DIRECTIVA.- DIPUTADO FAUSTO MANUEL ZAMORANO ESPARZA,\nPRESIDENTE.- DIPUTADA MARCELA FUENTE CASTILLO, SECRETARIA.- DIPUTADA MARIA GABRIELA SALIDO\nMAGOS, SECRETARIA.- (Firmas)\nCon fundamento en lo dispuesto por los artículos 122, apartado A, fracción III de la Constitución Política de los Estados Unidos Mexicanos; 32, apartado C, numeral 1, inciso a) de la Constitución Política de la Ciudad\n\nde México; 2 párrafo segundo, 3 fracciones XVII y XVIII, 7 párrafo primero, 10 fracción II, 12 y 21 párrafo primero de la Ley Orgánica del Poder Ejecutivo y de la Administración Pública de la Ciudad de México; para su debida publicación y observancia, expido el presente Decreto Promulgatorio en la Residencia Oficial de la Jefatura de Gobierno de la Ciudad de México, a los veinte días del mes de abril del año dos mil veintitrés.-\nLA JEFA DE GOBIERNO DE LA CIUDAD DE MÉXICO, DRA. CLAUDIA SHEINBAUM PARDO.- FIRMA.- EL\nSECRETARIO DE GOBIERNO, MARTÍ BATRES GUADARRAMA.- FIRMA.- EL SECRETARIO DE INCLUSIÓN Y\nBIENESTAR SOCIAL, RIGOBERTO SALGADO VÁZQUEZ.- FIRMA.- LA SECRETARIA DE LAS MUJERES, INGRID\nGÓMEZ SARACÍBAR.- FIRMA.- EL SECRETARIO DE SEGURIDAD CIUDADANA, OMAR HAMID GARCÍA\nHARFUCH.- FIRMA.- EL CONSEJERO JURÍDICO Y DE SERVICIOS LEGALES, NÉSTOR VARGAS SOLANO.- FIRMA.\nTRANSITORIOS DEL DECRETO POR EL QUE SE ADICIONA UNA FRACCIÓN III BIS AL ARTÍCULO 32 DE LA LEY DE\nLOS DERECHOS DE NIÑAS, NIÑOS Y ADOLESCENTES DE LA CIUDAD DE MÉXICO, PUBLICADO EN LA GACETA\nOFICIAL DE LA CIUDAD DE MÉXICO EL 21 DE ABRIL DE 2023.\nPrimero. Remítase a la Jefa de Gobierno de la Ciudad de México para su promulgación y publicación en la\nGaceta Oficial de la Ciudad de México.\nSegundo. El presente Decreto entra en vigor al día siguiente de su publicación.\nTercero. Las personas titulares o representantes legales de los Centros de Asistencia Social y todas las instituciones que brinden cuidados alternativos contarán con un plazo de 120 días para cumplir con la disposición del presente Decreto.\nCuarto. El DIF-CDMX realizará las adecuaciones administrativas y reglamentarias para el debido cumplimento del presente Decreto.\nPalacio Legislativo del Congreso de la Ciudad de México, a los veintiocho días del mes de marzo del año dos mil veintitrés.- POR LA MESA DIRECTIVA.- DIPUTADO FAUSTO MANUEL ZAMORANO ESPARZA,\nPRESIDENTE.- DIPUTADA MARCELA FUENTE CASTILLO, SECRETARIA.- DIPUTADA MARIA GABRIELA SALIDO\nMAGOS, SECRETARIA.- (Firmas)\nCon fundamento en lo dispuesto por los artículos 122, apartado A, fracción III de la Constitución Política de los Estados Unidos Mexicanos; 32, apartado C, numeral 1, inciso a) de la Constitución Política de la Ciudad de México; 2 párrafo segundo, 3 fracciones XVII y XVIII, 7 párrafo primero, 10 fracción II, 12 y 21 párrafo primero de la Ley Orgánica del Poder Ejecutivo y de la Administración Pública de la Ciudad de México; para su debida publicación y observancia, expido el presente Decreto Promulgatorio en la Residencia Oficial de\n\nla Jefatura de Gobierno de la Ciudad de México, a los veinte días del mes de abril del año dos mil veintitrés.-\nLA JEFA DE GOBIERNO DE LA CIUDAD DE MÉXICO, DRA. CLAUDIA SHEINBAUM PARDO.- FIRMA.- EL\nSECRETARIO DE GOBIERNO, MARTÍ BATRES GUADARRAMA.- FIRMA.- EL SECRETARIO DE INCLUSIÓN Y\nBIENESTAR SOCIAL, RIGOBERTO SALGADO VÁZQUEZ.- FIRMA.\nTRANSITORIOS DEL DECRETO POR EL QUE SE ADICIONA UNA FRACCIÓN I BIS AL ARTÍCULO 44 DE LA LEY DE\nLOS DERECHOS DE NIÑAS, NIÑOS Y ADOLESCENTES DE LA CIUDAD DE MÉXICO, PUBLICADO EN LA GACETA\nOFICIAL DE LA CIUDAD DE MÉXICO EL 22 DE MAYO DE 2023.\nPRIMERO.- Remítase a la persona titular de la Jefatura de Gobierno para su promulgación y publicación en la Gaceta Oficial de la Ciudad de México.\nSEGUNDO.- El presente Decreto entrará en vigor al día siguiente de su publicación en la Gaceta Oficial de la Ciudad de México. TERCERO. Se derogan todas aquellas disposiciones que contravengan el presente decreto.\nPalacio Legislativo del Congreso de la Ciudad de México, a los nueve días del mes de mayo del año dos mil veintitrés.- POR LA MESA DIRECTIVA.- DIPUTADO FAUSTO MANUEL ZAMORANO ESPARZA, PRESIDENTE.-\nDIPUTADA MARCELA FUENTE CASTILLO, SECRETARIA.- DIPUTADA MARIA GABRIELA SALIDO MAGOS,\nSECRETARIA.- (Firmas)\nCon fundamento en lo dispuesto por los artículos 122, apartado A, fracción III de la Constitución Política de los Estados Unidos Mexicanos; 32, apartado C, numeral 1, inciso a) de la Constitución Política de la Ciudad de México; 2 párrafo segundo, 3 fracciones XVII y XVIII, 7 párrafo primero, 10 fracción II, 12 y 21 párrafo primero de la Ley Orgánica del Poder Ejecutivo y de la Administración Pública de la Ciudad de México; para su debida publicación y observancia, expido el presente Decreto Promulgatorio en la Residencia Oficial de la Jefatura de Gobierno de la Ciudad de México, a los diecinueve días del mes de mayo del año dos mil veintitrés.-LA JEFA DE GOBIERNO DE LA CIUDAD DE MÉXICO, DRA. CLAUDIA SHEINBAUM PARDO.- FIRMA.-\nEL SECRETARIO DE GOBIERNO, MARTÍ BATRES GUADARRAMA.- FIRMA.- SECRETARIO DE INCLUSIÓN Y\nBIENESTAR SOCIAL, RIGOBERTO SALGADO VÁZQUEZ.- FIRMA.- EL CONSEJERO JURÍDICO Y DE SERVICIOS\nLEGALES, NÉSTOR VARGAS SOLANO.- FIRMA.\n\nTRANSITORIOS DEL DECRETO POR EL QUE SE REFORMA LA FRACCIÓN XVII DEL ARTÍCULO 58 DE LA LEY DE\nLOS DERECHOS DE NIÑAS, NIÑOS Y ADOLESCENTES DE LA CIUDAD DE MÉXICO, PUBLICADO EN LA\nGACETAOFICIAL DE LA CIUDAD DE MÉXICO EL 12 DE JUNIO DE 2023.\nPRIMERO.- Remítase a la persona titular de la Jefatura de Gobierno de la Ciudad de México para su promulgación y publicación en la Gaceta Oficial de la Ciudad de México.\nSEGUNDO.- El presente Decreto entra en vigor al día siguiente de su publicación.\nPalacio Legislativo del Congreso de la Ciudad de México, a los treinta y un días del mes de mayo del año dos mil veintitrés.- POR LA MESA DIRECTIVA.- DIPUTADO FAUSTO MANUEL ZAMORANO ESPARZA,\nPRESIDENTE.- DIPUTADA MARCELA FUENTE CASTILLO, SECRETARIA.- DIPUTADA MARIA GABRIELA SALIDO\nMAGOS, SECRETARIA.- (Firmas)\nCon fundamento en lo dispuesto por los artículos 122, apartado A, fracción III de la Constitución Política de los Estados Unidos Mexicanos; 32, apartado C, numeral 1, inciso a) de la Constitución Política de la Ciudad de México; 2 párrafo segundo, 3 fracciones XVII y XVIII, 7 párrafo primero, 10 fracción II, 12 y 21 párrafo primero de la Ley Orgánica del Poder Ejecutivo y de la Administración Pública de la Ciudad de México; para su debida publicación y observancia, expido el presente Decreto Promulgatorio en la Residencia Oficial de la Jefatura de Gobierno de la Ciudad de México, a los nueve días del mes de junio del año dos mil veintitrés.- LA JEFA DE GOBIERNO DE LA CIUDAD DE MÉXICO, DRA. CLAUDIA SHEINBAUM PARDO.- FIRMA.-\nEL SECRETARIO DE GOBIERNO, MARTÍ BATRES GUADARRAMA.- FIRMA.- LA SECRETARIA DE EDUCACIÓN,\nCIENCIA, TECNOLOGÍA E INNOVACIÓN, JESÚS OFELIA ANGULO GUERRERO.- FIRMA.- LA SECRETARIA DEL\nMEDIO AMBIENTE, MARINA ROBLES GARCÍA.- FIRMA.\nTRANSITORIOS DEL DECRETO POR EL QUE SE REFORMA LA FRACCIÓN VI Y SE ADICIONA UNA FRACCIÓN VI\nBIS AL ARTÍCULO 59 DE LA LEY DE LOS DERECHOS DE NIÑAS, NIÑOS Y ADOLESCENTES DE LA CIUDAD DE\nMÉXICO, PUBLICADO EN LA GACETAOFICIAL DE LA CIUDAD DE MÉXICO EL 12 DE JUNIO DE 2023.\nPRIMERO.- Remítase a la persona titular de la Jefatura de Gobierno para su promulgación y publicación en la Gaceta Oficial de la Ciudad de México.\nSEGUNDO.- El presente Decreto entrará en vigor al día siguiente de su publicación en la Gaceta Oficial de la Ciudad de México.\n\nPalacio Legislativo del Congreso de la Ciudad de México, a los treinta y un días del mes de mayo del año dos mil veintitrés.- POR LA MESA DIRECTIVA.- DIPUTADO FAUSTO MANUEL ZAMORANO ESPARZA,\nPRESIDENTE.- DIPUTADA MARCELA FUENTE CASTILLO, SECRETARIA.- DIPUTADA MARIA GABRIELA SALIDO\nMAGOS, SECRETARIA.- (Firmas)\nCon fundamento en lo dispuesto por los artículos 122, apartado A, fracción III de la Constitución Política de los Estados Unidos Mexicanos; 32, apartado C, numeral 1, inciso a) de la Constitución Política de la Ciudad de México; 2 párrafo segundo, 3 fracciones XVII y XVIII, 7 párrafo primero, 10 fracción II, 12 y 21 párrafo primero de la Ley Orgánica del Poder Ejecutivo y de la Administración Pública de la Ciudad de México; para su debida publicación y observancia, expido el presente Decreto Promulgatorio en la Residencia Oficial de la Jefatura de Gobierno de la Ciudad de México, a los nueve días del mes de junio del año dos mil veintitrés.- LA JEFA DE GOBIERNO DE LA CIUDAD DE MÉXICO, DRA. CLAUDIA SHEINBAUM PARDO.- FIRMA.-\nEL SECRETARIO DE GOBIERNO, MARTÍ BATRES GUADARRAMA.- FIRMA.- LA SECRETARIA DE EDUCACIÓN,\nCIENCIA, TECNOLOGÍA E INNOVACIÓN,.- FIRMA.- EL SECRETARIO DE INCLUSIÓN Y BIENESTAR SOCIAL.-\nFIRMA.- LA SECRETARIA DE SALUD, OLIVA LÓPEZ ARELLANO.- FIRMA.\nTRANSITORIOS DEL DECRETO POR EL QUE SE REFORMA LA FRACCIÓN X DEL ARTÍCULO 58 DE LA LEY DE LOS\nDERECHOS DE NIÑAS, NIÑOS Y ADOLESCENTES DE LA CIUDAD DE MÉXICO, PUBLICADO EN LA GACETA\nOFICIAL DE LA CIUDAD DE MÉXICO EL 10 DE OCTUBRE DE 2023.\nPRIMERO.- Remítase a la persona titular de la Jefatura de Gobierno para su promulgación y publicación en la Gaceta Oficial de la Ciudad de México.\nSEGUNDO. - El presente Decreto entrará en vigor al día siguiente de su publicación en la Gaceta Oficial de la Ciudad de México.\nPalacio Legislativo del Congreso de la Ciudad de México, a los siete días del mes de septiembre del año dos mil veintitrés.- POR LA MESA DIRECTIVA.- DIPUTADA MARÍA GABRIELA SALIDO MAGOS, PRESIDENTA.-\nDIPUTADA MARCELA FUENTE CASTILLO, SECRETARIA.- DIPUTADA ANA JOCELYN VILLAGRÁN VILLASANA,\nSECRETARIA.- (Firmas)\nCon fundamento en lo dispuesto por los artículos 122, apartado A, base III, de la Constitución Política de los Estados Unidos Mexicanos; 32, apartado C, numeral 1, inciso a), de la Constitución Política de la Ciudad de México; 2, párrafo segundo, 3, fracciones XVII y XVIII, 7, párrafo primero, 10, fracción II, 12 y 21, párrafo primero, de la Ley Orgánica del Poder Ejecutivo y de la Administración Pública de la Ciudad de México;\n\npara su debida publicación y observancia, expido el presente Decreto Promulgatorio en la Residencia\nOficial de la Jefatura de Gobierno de la Ciudad de México, a los nueve días del mes de octubre del año dos mil veintitrés.- EL JEFE DE GOBIERNO DE LA CIUDAD DE MÉXICO, MTRO. MARTÍ BATRES GUADARRAMA.-\nFIRMA.- EL SECRETARIO DE GOBIERNO, RICARDO RUIZ SUÁREZ.- FIRMA.- LA SECRETARIA DE EDUCACIÓN,\nCIENCIA, TECNOLOGÍA E INNOVACIÓN, JESÚS OFELIA ANGULO GUERRERO.- FIRMA.- EL SECRETARIO DE\nINCLUSIÓN Y BIENESTAR SOCIAL, RIGOBERTO SALGADO VÁZQUEZ.- FIRMA.\nTRANSITORIOS DEL DECRETO POR EL QUE SE REFORMA EL PRIMER PÁRRAFO Y SE ADICIONA UN SEGUNDO\nPÁRRAFO AL ARTÍCULO 48 DE LA LEY DE LOS DERECHOS DE NIÑAS, NIÑOS Y ADOLESCENTES DE LA CIUDAD\nDE MÉXICO, PUBLICADO EN LA GACETA OFICIAL DE LA CIUDAD DE MÉXICO EL 10 DE OCTUBRE DE 2023.\nPRIMERO.- Remítase a la persona titular de la Jefatura de Gobierno de la Ciudad de México para su promulgación y publicación en la Gaceta Oficial de la Ciudad de México.\nSEGUNDO.- El presente Decreto entrará en vigor al día siguiente de su publicación en la Gaceta Oficial de la Ciudad de México.\nPalacio Legislativo del Congreso de la Ciudad de México, a los siete días del mes de septiembre del año dos mil veintitrés.- POR LA MESA DIRECTIVA.- DIPUTADA MARÍA GABRIELA SALIDO MAGOS, PRESIDENTA.-\nDIPUTADA MARCELA FUENTE CASTILLO, SECRETARIA.- DIPUTADA ANA JOCELYN VILLAGRÁN VILLASANA,\nSECRETARIA.- (Firmas)\nCon fundamento en lo dispuesto por los artículos 122, apartado A, base III, de la Constitución Política de los Estados Unidos Mexicanos; 32, apartado C, numeral 1, inciso a), de la Constitución Política de la Ciudad de México; 2, párrafo segundo, 3, fracciones XVII y XVIII, 7, párrafo primero, 10, fracción II, 12 y 21, párrafo primero, de la Ley Orgánica del Poder Ejecutivo y de la Administración Pública de la Ciudad de México;\npara su debida publicación y observancia, expido el presente Decreto Promulgatorio en la Residencia\nOficial de la Jefatura de Gobierno de la Ciudad de México, a los nueve días del mes de octubre del año dos mil veintitrés.- EL JEFE DE GOBIERNO DE LA CIUDAD DE MÉXICO, MTRO. MARTÍ BATRES GUADARRAMA.-\nFIRMA.- EL SECRETARIO DE GOBIERNO, RICARDO RUIZ SUÁREZ.- FIRMA- EL SECRETARIO DE INCLUSIÓN Y\nBIENESTAR SOCIAL, RIGOBERTO SALGADO VÁZQUEZ.- FIRMA.- LA SECRETARIA DE SALUD, OLIVA LÓPEZ\nARELLANO.- FIRMA.\n\nTRANSITORIOS DEL DECRETO POR EL QUE SE ADICIONA UNA FRACCIÓN XXXV BIS AL ARTÍCULO 4 Y SE\nMODIFICA LA FRACCIÓN VI DEL ARTÍCULO 58, AMBOS DE LA LEY DE LOS DERECHOS DE NIÑAS, NIÑOS Y\nADOLESCENTES DE LA CIUDAD DE MÉXICO, PUBLICADO EN LA GACETA OFICIAL DE LA CIUDAD DE MÉXICO\nEL 10 DE OCTUBRE DE 2023.\nPRIMERO.- Remítase a la persona titular de la Jefatura de Gobierno de la Ciudad de México para su promulgación y publicación en la Gaceta Oficial de la Ciudad de México.\nSEGUNDO.- El presente Decreto entrará en vigor al día siguiente de su publicación en la Gaceta Oficial de la Ciudad de México.\nPalacio Legislativo del Congreso de la Ciudad de México, a los siete días del mes de septiembre del año dos mil veintitrés.- POR LA MESA DIRECTIVA.- DIPUTADA MARÍA GABRIELA SALIDO MAGOS, PRESIDENTA.-\nDIPUTADA MARCELA FUENTE CASTILLO, SECRETARIA.- DIPUTADA ANA JOCELYN VILLAGRÁN VILLASANA,\nSECRETARIA.- (Firmas)\nCon fundamento en lo dispuesto por los artículos 122, apartado A, base III, de la Constitución Política de los Estados Unidos Mexicanos; 32, apartado C, numeral 1, inciso a), de la Constitución Política de la Ciudad de México; 2, párrafo segundo, 3, fracciones XVII y XVIII, 7, párrafo primero, 10, fracción II, 12 y 21, párrafo primero, de la Ley Orgánica del Poder Ejecutivo y de la Administración Pública de la Ciudad de México;\npara su debida publicación y observancia, expido el presente Decreto Promulgatorio en la Residencia\nOficial de la Jefatura de Gobierno de la Ciudad de México, a los nueve días del mes de octubre del año dos mil veintitrés.- EL JEFE DE GOBIERNO DE LA CIUDAD DE MÉXICO, MTRO. MARTÍ BATRES GUADARRAMA.-\nFIRMA.- EL SECRETARIO DE GOBIERNO, RICARDO RUIZ SUÁREZ.- FIRMA.- LA SECRETARIA DE EDUCACIÓN,\nCIENCIA, TECNOLOGÍA E INNOVACIÓN, JESÚS OFELIA ANGULO GUERRERO.- EL SECRETARIO DE INCLUSIÓN\nY BIENESTAR SOCIAL, RIGOBERTO SALGADO VÁZQUEZ.- FIRMA.\nTRANSITORIOS DEL DECRETO POR EL QUE SE ADICIONA UN ARTÍCULO 47 BIS A LA LEY DE LOS DERECHOS DE\nNIÑAS, NIÑOS Y ADOLESCENTES DE LA CIUDAD DE MÉXICO, PUBLICADO EN LA GACETA OFICIAL DE LA\nCIUDAD DE MÉXICO EL 17 DE NOVIEMBRE DE 2023.\nPRIMERO.- Remítase a la persona titular de la Jefatura de Gobierno para su promulgación y publicación en la Gaceta Oficial de la Ciudad de México.\n\nSEGUNDO.- El presente Decreto entrará en vigor al día siguiente de su publicación en la Gaceta Oficial de la Ciudad de México.\nPalacio Legislativo del Congreso de la Ciudad de México, al primer día del mes de diciembre del año dos mil veintidós. POR LA MESA DIRECTIVA.- DIPUTADO FAUSTO MANUEL ZAMORANO ESPARZA, PRESIDENTE.-\nDIPUTADA MARCELA FUENTE CASTILLO, SECRETARIA.- DIPUTADA MARIA GABRIELA SALIDO MAGOS,\nSECRETARIA.- (Firmas)\nCon fundamento en lo dispuesto por los artículos 122, apartado A, base III, de la Constitución Política de los Estados Unidos Mexicanos; 32, apartado C, numeral 1, inciso a), de la Constitución Política de la Ciudad de México; 2, párrafo segundo, 3, fracciones XVII y XVIII, 7, párrafo primero, 10, fracción II, 12 y 21, párrafo primero, de la Ley Orgánica del Poder Ejecutivo y de la Administración Pública de la Ciudad de México;\npara su debida publicación y observancia, expido el presente Decreto Promulgatorio en la Residencia\nOficial de la Jefatura de Gobierno de la Ciudad de México, a los diecisiete días del mes de noviembre del año dos míl veintitrés. EL JEFE DE GOBIERNO DE LA CIUDAD DE MÉXICO, MTRO. MARTÍ BATRES\nGUADARRAMA.- FIRMA.- EL SECRETARIO DE GOBIERNO, RICARDO RUIZ SUÁREZ.- FIRMA.- LA SECRETARIA DE\nEDUCACIÓN, CIENCIA, TECNOLOGÍA E INNOVACIÓN,JESÚS OFELIA ANGULO GUERRERO.- FIRMA.- EL\nSECRETARIO DE INCLUSIÓN Y BIENESTAR SOCIAL, RIGOBERTO SALGADO VÁZQUEZ.- FIRMA.\nTRANSITORIOS DEL DECRETO POR EL QUE SE MODIFICA LA FRACCIÓN IX Y X, Y SE ADICIONA LA FRACCIÓN\nXI AL ARTÍCULO 59 DE LA LEY DE DERECHOS DE NIÑAS, NIÑOS Y ADOLESCENTES DE LA CIUDAD DE MÉXICO,\nPUBLICADO EN LA GACETA OFICIAL DE LA CIUDAD DE MÉXICO EL 26 DE DICIEMBRE DE 2023.\nPRIMERO. Remítase a la Jefatura de Gobierno para su promulgación y publicación en la Gaceta Oficial de la Ciudad de México.\nSEGUNDO. El presente decreto entrará en vigor al día siguiente de su publicación en la Gaceta Oficial de la\nCiudad de México.\nPalacio Legislativo del Congreso de la Ciudad de México, a los catorce días del mes de noviembre del año dos mil veintitrés. POR LA MESA DIRECTIVA.- DIPUTADA MARÍA GABRIELA SALIDO MAGOS, PRESIDENTA.-\nDIPUTADA MARCELA FUENTE CASTILLO, SECRETARIA.- DIPUTADA ANA JOCELYN VILLAGRÁN VILLASANA,\nSECRETARIA.- (Firmas)\n\nCon fundamento en lo dispuesto por los artículos 122, apartado A, base III, de la Constitución Política de los Estados Unidos Mexicanos; 32, apartado C, numeral 1, inciso a), de la Constitución Política de la Ciudad de México; 2, párrafo segundo, 3, fracciones XVII y XVIII, 7, párrafo primero, 10, fracción II, 12 y 21, párrafo primero, de la Ley Orgánica del Poder Ejecutivo y de la Administración Pública de la Ciudad de México;\npara su debida publicación y observancia, expido el presente Decreto Promulgatorio en la Residencia\nOficial de la Jefatura de Gobierno de la Ciudad de México, a los veintidós días del mes de diciembre del año dos mil veintitrés.- EL JEFE DE GOBIERNO DE LA CIUDAD DE MÉXICO, DR. MARTÍ BATRES GUADARRAMA.-\nFIRMA.- EL SECRETARIO DE GOBIERNO, RICARDO RUIZ SUÁREZ.- FIRMA.- LA SECRETARIA DE EDUCACIÓN,\nCIENCIA, TECNOLOGÍA E INNOVACIÓN, JESÚS OFELIA ANGULO GUERRERO.- FIRMA.- LA SECRETARIA DEL\nMEDIO AMBIENTE, MARINA ROBLES GARCÍA.- FIRMA.\nTRANSITORIOS DEL DECRETO POR EL QUE SE SE ADICIONA UNA FRACCIÓN X BIS AL ARTÍCULO 47 DE LA LEY\nDE LOS DERECHOS DE NIÑAS, NIÑOS Y ADOLESCENTES DE LA CIUDAD DE MÉXICO, PUBLICADO EN LA\nGACETA OFICIAL DE LA CIUDAD DE MÉXICO EL 04 DE MARZO DE 2024..\nPRIMERO. - Remítase a la Jefatura de Gobierno para su promulgación y publicación en la Gaceta Oficial de la Ciudad de México.\nSEGUNDO. - El presente Decreto entrará en vigor al día siguiente de su publicación en la Gaceta Oficial de la Ciudad de México.\nPalacio Legislativo del Congreso de la Ciudad de México, a los seis días del mes de febrero del año dos mil veinticuatro. POR LA MESA DIRECTIVA.- DIPUTADA MARÍA GABRIELA SALIDO MAGOS, PRESIDENTA.-\nDIPUTADA MARCELA FUENTE CASTILLO, SECRETARIA.- DIPUTADA ANA JOCELYN VILLAGRÁN VILLASANA,\nSECRETARIA.- (Firmas)\nCon fundamento en lo dispuesto por los artículos 122, apartado A, base III, de la Constitución Política de los Estados Unidos Mexicanos; 32, apartado C, numeral 1, inciso a), de la Constitución Política de la Ciudad de México; 2, párrafo segundo, 3, fracciones XVII y XVIII, 7, párrafo primero, 10, fracción II, 12 y 21, párrafo primero, de la Ley Orgánica del Poder Ejecutivo y de la Administración Pública de la Ciudad de México;\npara su debida publicación y observancia, expido el presente Decreto Promulgatorio en la Residencia\nOficial de la Jefatura de Gobierno de la Ciudad de México, al primer día del mes de marzo del año dos mil veinticuatro.- EL JEFE DE GOBIERNO DE LA CIUDAD DE MÉXICO, DR. MARTÍ BATRES GUADARRAMA.- FIRMA.-\nEL SECRETARIO DE GOBIERNO, RICARDO RUIZ SUÁREZ.- FIRMA.-EL SECRETARIO DE INCLUSIÓN Y BIENESTAR\n\nSOCIAL, JUAN GERARDO LÓPEZ HERNÁNDEZ.- FIRMA.- LA SECRETARIA DE SALUD, OLIVA LÓPEZ ARELLANO.-\nFIRMA.\nTRANSITORIOS DEL DECRETO POR EL QUE SE MODIFICA EL PÁRRAFO PRIMERO DEL ARTÍCULO 31 BIS; SE\nMODIFICA LA FRACCIÓN VIII Y SE ADICIONA UN QUINTO PÁRRAFO, RECORRIENDO EL SUBSECUENTE DEL\nARTÍCULO 44; SE MODIFICA EL INCISO B) Y SE ADICIONA UN INCISO C) A LA FRACCIÓN VI DEL ARTÍCULO\n112; SE ADICIONA UN ARTÍCULO 113 BIS, Y SE MODIFICA EL SEGUNDO PÁRRAFO DEL ARTÍCULO 115, TODOS\nDE LA LEY DE LOS DERECHOS DE LAS NIÑAS, NIÑOS Y ADOLESCENTES DE LA CIUDAD DE MÉXICO,\nPUBLICADO EN LA GACETA OFICIAL DE LA CIUDAD DE MÉXICO EL 15 DE MARZO DE 2024..\nPRIMERO. - Remítase a la Jefatura de Gobierno para su promulgación y publicación en la Gaceta Oficial de la Ciudad de México.\nSEGUNDO. - El presente Decreto entrará en vigor al día siguiente de su publicación en la Gaceta Oficial de la Ciudad de México.\nTERCERO.- La Jefatura del Gobierno de la Ciudad de México deberá realizar las adecuaciones complementarias y necesarias al Reglamento de la Ley de los Derechos de las Niñas, Niños y Adolescentes de la Ciudad de México, en un plazo no mayor a 90 días hábiles una vez la entrada en vigor del presente decreto.\nPalacio Legislativo del Congreso de la Ciudad de México, a los seis días del mes de febrero del año dos mil veinticuatro. POR LA MESA DIRECTIVA.- DIPUTADA MARÍA GABRIELA SALIDO MAGOS, PRESIDENTA.-\nDIPUTADA MARCELA FUENTE CASTILLO, SECRETARIA.- DIPUTADA ANA JOCELYN VILLAGRÁN VILLASANA,\nSECRETARIA.- (Firmas)\nCon fundamento en lo dispuesto por los artículos 122, apartado A, base III, de la Constitución Política de los Estados Unidos Mexicanos; 32, apartado C, numeral 1, inciso a), de la Constitución Política de la Ciudad de México; 2, párrafo segundo, 3, fracciones XVII y XVIII, 7, párrafo primero, 10, fracción II, 12 y 21, párrafo primero, de la Ley Orgánica del Poder Ejecutivo y de la Administración Pública de la Ciudad de México;\npara su debida publicación y observancia, expido el presente Decreto Promulgatorio en la Residencia\nOficial de la Jefatura de Gobierno de la Ciudad de México, a los catorce días del mes de marzo del año dos mil veinticuatro.- EL JEFE DE GOBIERNO DE LA CIUDAD DE MÉXICO, DR. MARTÍ BATRES GUADARRAMA.-\nFIRMA.- EL SECRETARIO DE GOBIERNO, RICARDO RUIZ SUÁREZ.- FIRMA.- EL SECRETARIO DE INCLUSIÓN Y\nBIENESTAR SOCIAL, JUAN GERARDO LÓPEZ HERNÁNDEZ.- FIRMA.- LA SECRETARIA DE MUJERES, INGRID\nAURORA GÓMEZ SARACÍBAR.- FIRMA..\n\nTRANSITORIOS DEL DECRETO POR EL QUE SE REFORMA EL PRIMER PÁRRAFO Y SE ADICIONA UN SEGUNDO\nPÁRRAFO AL ARTÍCULO 75; SE REFORMA EL ARTÍCULO 76; LAS FRACCIONES III Y IV DEL ARTÍCULO 85; EL\nPRIMER PÁRRAFO, LAS FRACCIONES I Y VI Y SE ADICIONA UNA FRACCIÓN I BIS, AL ARTÍCULO 87, DE LA LEY\nDE LOS DERECHOS DE NIÑAS, NIÑOS Y ADOLESCENTES DE LA CIUDAD DE MÉXICO, PUBLICADO EN LA\nGACETA OFICIAL DE LA CIUDAD DE MÉXICO EL 29 DE ABRIL DE 2024..\nPRIMERO.- Remítase a la Jefatura de Gobierno de la Ciudad de México para su promulgación y publicación en la Gaceta Oficial de la Ciudad de México.\nSEGUNDO.- El presente decreto entrará en vigor el día siguiente de su publicación en la Gaceta Oficial de la Ciudad de México.\nPalacio Legislativo del Congreso de la Ciudad de México, a los diecinueve días del mes de marzo del año dos mil veinticuatro.- POR LA MESA DIRECTIVA.- DIPUTADA MARÍA GABRIELA SALIDO MAGOS, PRESIDENTA.-\nDIPUTADA MARCELA FUENTE CASTILLO, SECRETARIA.- DIPUTADA ANA JOCELYN VILLAGRÁN VILLASANA,\nSECRETARIA.- (Firmas)\nCon fundamento en lo dispuesto por los artículos 122, apartado A, base III, de la Constitución Política de los Estados Unidos Mexicanos; 32, apartado C, numeral 1, inciso a), de la Constitución Política de la Ciudad de México; 2, párrafo segundo, 3, fracciones XVII y XVIII, 7, párrafo primero, 10, fracción II, 12 y 21, párrafo primero, de la Ley Orgánica del Poder Ejecutivo y de la Administración Pública de la Ciudad de México;\npara su debida publicación y observancia, expido el presente Decreto Promulgatorio en la Residencia\nOficial de la Jefatura de Gobierno de la Ciudad de México, a los veintinueve días del mes de abril del año dos mil veinticuatro.- EL JEFE DE GOBIERNO DE LA CIUDAD DE MÉXICO, DR. MARTÍ BATRES GUADARRAMA.-\nFIRMA.- EL SECRETARIO DE GOBIERNO, RICARDO RUIZ SUÁREZ.- FIRMA.- EL SECRETARIO DE INCLUSIÓN Y\nBIENESTAR SOCIAL, JUAN GERARDO LÓPEZ HERNÁNDEZ.- FIRMA.- FIRMA.- EL CONSEJERO JURÍDICO Y DE\nSERVICIOS LEGALES, NÉSTOR VARGAS SOLANO.- FIRMA.\nTRANSITORIOS DEL DECRETO POR EL QUE SE MODIFICAN LAS FRACCIONES XVII Y XVIII, Y SE ADICIONA UNA\nFRACCIÓN XIX, DEL ARTÍCULO 47 DE LA LEY DE LOS DERECHOS DE NIÑAS, NIÑOS Y ADOLESCENTES DE LA\nCIUDAD DE MÉXICO, EN MATERIA DE SUICIDIO, PUBLICADO EN LA GACETA OFICIAL DE LA CIUDAD DE\nMÉXICO EL 29 DE ABRIL DE 2024..\n\nPRIMERO. Remítase a la Jefatura de Gobierno para su promulgación y publicación en la Gaceta Oficial de la Ciudad de México.\nSEGUNDO. El presente decreto entrará en vigor al día siguiente de su publicación en la Gaceta Oficial de la\nCiudad de México.\nPalacio Legislativo del Congreso de la Ciudad de México, a los diecinueve días del mes de marzo del año dos mil veinticuatro.- POR LA MESA DIRECTIVA.- DIPUTADA MARÍA GABRIELA SALIDO MAGOS, PRESIDENTA.-\nDIPUTADA MARCELA FUENTE CASTILLO, SECRETARIA.- DIPUTADA ANA JOCELYN VILLAGRÁN VILLASANA,\nSECRETARIA.- (Firmas)\nCon fundamento en lo dispuesto por los artículos 122, apartado A, base III, de la Constitución Política de los Estados Unidos Mexicanos; 32, apartado C, numeral 1, inciso a), de la Constitución Política de la Ciudad de México; 2, párrafo segundo, 3, fracciones XVII y XVIII, 7, párrafo primero, 10, fracción II, 12 y 21, párrafo primero, de la Ley Orgánica del Poder Ejecutivo y de la Administración Pública de la Ciudad de México;\npara su debida publicación y observancia, expido el presente Decreto Promulgatorio en la Residencia\nOficial de la Jefatura de Gobierno de la Ciudad de México, a los veintinueve días del mes de abril del año dos mil veinticuatro.- EL JEFE DE GOBIERNO DE LA CIUDAD DE MÉXICO, DR. MARTÍ BATRES GUADARRAMA.-\nFIRMA.- EL SECRETARIO DE GOBIERNO, RICARDO RUIZ SUÁREZ.- FIRMA.- EL SECRETARIO DE INCLUSIÓN Y\nBIENESTAR SOCIAL, JUAN GERARDO LÓPEZ HERNÁNDEZ.- FIRMA.\nTRANSITORIOS DEL DECRETO POR EL QUE SE REFORMAN LAS FRACCIONES I, II, III, V, VI Y VII DEL ARTÍCULO\n1, SE ADICIONA UNA FRACCIÓN XVIII BIS AL ARTÍCULO 4, Y SE REFORMAN LOS ARTÍCULOS 41 Y 43 DE LA\nLEY DE LOS DERECHOS DE NIÑAS, NIÑOS Y ADOLESCENTES DE LA CIUDAD DE MÉXICO, PUBLICADO EN LA\nGACETA OFICIAL DE LA CIUDAD DE MÉXICO EL 29 DE ABRIL DE 2024..\nPRIMERO.- Remítase a la Jefatura de Gobierno de la Ciudad de México para su promulgación y publicación en la Gaceta Oficial de la Ciudad de México.\nSEGUNDO.- El presente decreto entrará en vigor el día siguiente de su publicación en la Gaceta Oficial de la Ciudad de México.\nPalacio Legislativo del Congreso de la Ciudad de México, a los diecinueve días del mes de marzo del año dos mil veinticuatro.- POR LA MESA DIRECTIVA.- DIPUTADA MARÍA GABRIELA SALIDO MAGOS, PRESIDENTA.-\n\nDIPUTADA MARCELA FUENTE CASTILLO, SECRETARIA.- DIPUTADA ANA JOCELYN VILLAGRÁN VILLASANA,\nSECRETARIA.- (Firmas)\nCon fundamento en lo dispuesto por los artículos 122, apartado A, base III, de la Constitución Política de los Estados Unidos Mexicanos; 32, apartado C, numeral 1, inciso a), de la Constitución Política de la Ciudad de México; 2, párrafo segundo, 3, fracciones XVII y XVIII, 7, párrafo primero, 10, fracción II, 12 y 21, párrafo primero, de la Ley Orgánica del Poder Ejecutivo y de la Administración Pública de la Ciudad de México;\npara su debida publicación y observancia, expido el presente Decreto Promulgatorio en la Residencia\nOficial de la Jefatura de Gobierno de la Ciudad de México, a los veintinueve días del mes de abril del año dos mil veinticuatro.- EL JEFE DE GOBIERNO DE LA CIUDAD DE MÉXICO, DR. MARTÍ BATRES GUADARRAMA.-\nFIRMA.- EL SECRETARIO DE GOBIERNO, RICARDO RUIZ SUÁREZ.- FIRMA.- EL SECRETARIO DE INCLUSIÓN Y\nBIENESTAR SOCIAL, JUAN GERARDO LÓPEZ HERNÁNDEZ.- FIRMA.\nTRANSITORIOS DEL DECRETO POR EL QUE SE ADICIONAN TRES ÚLTIMOS PÁRRAFOS AL ARTÍCULO 2 DE LA\nLEY DE LOS DERECHOS DE NIÑAS, NIÑOS Y ADOLESCENTES DE LA CIUDAD DE MÉXICO, PUBLICADO EN LA\nGACETA OFICIAL DE LA CIUDAD DE MÉXICO EL 29 DE ABRIL DE 2024..\nPRIMERO.- Remítase a la Jefatura de Gobierno de la Ciudad de México para su promulgación y publicación en la Gaceta Oficial de la Ciudad de México.\nSEGUNDO.- El presente decreto entrará en vigor el día siguiente de su publicación en la Gaceta Oficial de la Ciudad de México.\nPalacio Legislativo del Congreso de la Ciudad de México, a los diecinueve días del mes de marzo del año dos mil veinticuatro.- POR LA MESA DIRECTIVA.- DIPUTADA MARÍA GABRIELA SALIDO MAGOS, PRESIDENTA.-\nDIPUTADA MARCELA FUENTE CASTILLO, SECRETARIA.- DIPUTADA ANA JOCELYN VILLAGRÁN VILLASANA,\nSECRETARIA.- (Firmas)\nCon fundamento en lo dispuesto por los artículos 122, apartado A, base III, de la Constitución Política de los Estados Unidos Mexicanos; 32, apartado C, numeral 1, inciso a), de la Constitución Política de la Ciudad de México; 2, párrafo segundo, 3, fracciones XVII y XVIII, 7, párrafo primero, 10, fracción II, 12 y 21, párrafo primero, de la Ley Orgánica del Poder Ejecutivo y de la Administración Pública de la Ciudad de México;\npara su debida publicación y observancia, expido el presente Decreto Promulgatorio en la Residencia\nOficial de la Jefatura de Gobierno de la Ciudad de México, a los veintinueve días del mes de abril del año dos mil veinticuatro.- EL JEFE DE GOBIERNO DE LA CIUDAD DE MÉXICO, DR. MARTÍ BATRES GUADARRAMA.-\n\nFIRMA.- EL SECRETARIO DE GOBIERNO, RICARDO RUIZ SUÁREZ.- FIRMA.- EL SECRETARIO DE INCLUSIÓN Y\nBIENESTAR SOCIAL, JUAN GERARDO LÓPEZ HERNÁNDEZ.- FIRMA.\nTRANSITORIOS DECRETO POR EL QUE SE MODIFICA EL PÁRRAFO ÚNICO DE LA FRACCIÓN VII Y SE ADICIONA\nUNA FRACCIÓN VIII DEL ARTÍCULO 135; SE MODIFICA LA FRACCIÓN II DEL ARTÍCULO 240; SE MODIFICA EL\nÚNICO PÁRRAFO DE LA FRACCIÓN II Y SE ADICIONA UNA FRACCIÓN III DEL ARTÍCULO 242, AMBOS DEL\nCÓDIGO PENAL PARA EL DISTRITO FEDERAL Y SE MODIFICA EL PÁRRAFO ÚNICO DE LA FRACCIÓN XII Y SE\nADICIONA UNA FRACCIÓN XIII AL ARTÍCULO 44 DE LA LEY DE LOS DERECHOS DE NIÑAS, NIÑOS Y\nADOLESCENTES DE LA CIUDAD DE MÉXICO, PÚBLICADO EN LA GACETA OFICIAL DE LA CIUDAD DE MÉXICO\nEL 19 DE JULIO DE 2024.\nPRIMERO.- Remítase a la persona titular de la Jefatura de Gobierno de la Ciudad de México, para su promulgación y publicación en la Gaceta Oficial de la Ciudad de México.\nSEGUNDO.- El presente Decreto entrará en vigor al día siguiente de su publicación en la Gaceta Oficial de la Ciudad de México.\nPalacio Legislativo del Congreso de la Ciudad de México, a los trece días del mes de junio del año dos mil veinticuatro..- POR LA MESA DIRECTIVA.- DIPUTADA MARÍA GABRIELA SALIDO MAGOS, PRESIDENTA.-\nDIPUTADA MARCELA FUENTE CASTILLO, SECRETARIA.- DIPUTADA FRIDA FERNANDA ALCÁNTARA CABRERA,\nSECRETARIA.- (Firmas)\nCon fundamento en lo dispuesto por los artículos 122, apartado A, base III, de la Constitución Política de los Estados Unidos Mexicanos; 32, apartado C, numeral 1, inciso a), de la Constitución Política de la Ciudad de México; 2, párrafo segundo, 3, fracciones XVII y XVIII, 7, párrafo primero, 10, fracción II, 12 y 21, párrafo primero, de la Ley Orgánica del Poder Ejecutivo y de la Administración Pública de la Ciudad de México;\npara su debida publicación y observancia, expido el presente Decreto Promulgatorio en la Residencia\nOficial de la Jefatura de Gobierno de la Ciudad de México, a los diecisiete días del mes de julio del año dos mil veinticuatro.- EL JEFE DE GOBIERNO DE LA CIUDAD DE MÉXICO, DR. MARTÍ BATRES GUADARRAMA.-\nFIRMA.- EL SECRETARIO DE GOBIERNO, RICARDO RUIZ SUÁREZ.- FIRMA.- EL SECRETARIO DE INCLUSIÓN Y\nBIENESTAR SOCIAL, JUAN GERARDO LÓPEZ HERNÁNDEZ.-FIRMA.- EL SECRETARIO DE MOVILIDAD, ANDRÉS\nLAJOUS LOAEZA.- FIRMA.- EL SECRETARIO DE SEGURIDAD CIUDADANA, PABLO VÁZQUEZ CAMACHO.- FIRMA.",
  "ordenamiento": "Marco Jurídico",
  "jurisdiccion": "CIUDAD DE MEXICO",
  "fuente_oficial": "Congreso de la Ciudad de México",
  "status": "Vigente",
  "Fecha de Publicación": "20-08-2024",
  "Fecha de Última Reforma": "19 de julio de 2024",
  "numero_paginas": 130,
  "es_escaneado": false,
  "tiene_tablas": false,
  "url": "https://www.congresocdmx.gob.mx/archivo-0198c0e2ce8907ae6d7f12c9f2ec5f74385a6d2b.pdf"
}