{
  "titulo": "Ley AMBIENTAL DE PROTECCIÓN A LA TIERRA EN LA CIUDAD DE MÉXICO",
  "Contenido": "PUBLICADO EN LA GACETA OFICIAL DEL DISTRITO FEDERAL\nEL 13 DE ENERO DE 2000\nTEXTO VIGENTE\nÚLTIMA REFORMA PUBLICADA EN LA G.O.C.D.M.X.\nEL 28 DE NOVIEMBRE DE 2023\nASAMBLEA LEGISLATIVA DEL DISTRITO FEDERAL\nLEY AMBIENTAL DE PROTECCIÓN A LA TIERRA EN EL DISTRITO FEDERAL\n(Al margen superior izquierdo un escudo que dice: Ciudad de México. - JEFE DE GOBIERNO DEL DISTRITO\nFEDERAL)\nDECRETO DE LEY AMBIENTAL DEL DISTRITO FEDERAL\nROSARIO ROBLES BERLANGA, Jefa de Gobierno del Distrito Federal, a sus habitantes sabed:\nQue la Honorable Asamblea Legislativa del Distrito Federal, I Legislatura, se ha servido dirigirme el siguiente\nDECRETO\n(Al margen superior izquierdo el escudo nacional que dice: ESTADOS UNIDOS MEXICANOS. - ASAMBLEA\nLEGISLATIVA DEL DISTRITO FEDERAL, I LEGISLATURA)\nLA ASAMBLEA LEGISLATIVA DEL DISTRITO FEDERAL, I LEGISLATURA\nDECRETA\n\nLEY AMBIENTAL DE PROTECCIÓN A LA TIERRA EN LA\nCIUDAD DE MÉXICO\nReforma publicada en la GOCDMX el 24 de Marzo de 2023\nTÍTULO PRIMERO\nDISPOSICIONES GENERALES\nARTÍCULO 1° La presente Ley es de orden público e interés social y tiene por objeto:\nI. Definir los principios mediante los cuales se habrá de formular, conducir y evaluar la política ambiental en el Distrito Federal, así como los instrumentos y procedimientos para su protección, vigilancia y aplicación;\nII. Regular el ejercicio de las facultades de las autoridades de la Administración Pública del\nDistrito Federal en materia de conservación del ambiente, protección ecológica y restauración del equilibrio ecológico;\nIII. Conservar y restaurar el equilibrio ecológico, así como prevenir los daños al ambiente, de manera que la obtención de beneficios económicos y las actividades sociales se generen en un esquema de desarrollo sustentable;\nIV. Establecer y regular las áreas verdes, áreas de valor ambiental y áreas naturales protegidas de competencia del Distrito Federal, y en general regular el suelo de conservación para la preservación de los ecosistemas y recursos naturales de la Tierra, así como manejar y vigilar aquellas cuya administración se suma por convenio con la Federación, estados o municipios;\nV. Prevenir y controlar la contaminación del aire, agua y suelo en el Distrito Federal en aquellos casos que no sean competencia de la Federación;\nVI. Establecer las medidas de control, de seguridad y las sanciones administrativas que correspondan, para garantizar el cumplimiento y la aplicación de esta ley y de las disposiciones que de ella se deriven;\nVII. Regular la responsabilidad por daños al ambiente y establecer los mecanismos adecuados para garantizar la incorporación de los costos ambientales en los procesos productivos;\n\nVIII. Establecer el ámbito de participación de la sociedad en el desarrollo y la gestión Ambiental;\nIX. Reconocer las obligaciones y deberes tanto del Gobierno como de la sociedad, para garantizar el respeto a la Tierra; y\nX. Promover y establecer el ámbito de participación ciudadana individual, colectiva o a través de los órganos de representación ciudadana e instrumentos de participación ciudadana en los términos de la ley, en el desarrollo sustentable y de gestión ambiental.\nARTÍCULO 2° Esta ley se aplicará en el territorio del Distrito Federal en los siguientes casos:\nI. En la prevención y control de la contaminación atmosférica proveniente de fuentes fijas o móviles que de conformidad con la misma estén sujetas a la jurisdicción local;\nII. En la prevención y control de la contaminación de las aguas de competencia local conforme a la ley federal en la materia;\nIII. En la conservación y control de la contaminación del suelo;\nIV. En la conservación, restauración y aprovechamiento sustentable de los recursos naturales de jurisdicción del Distrito Federal;\nV. En la conservación, protección y preservación de la flora y fauna en el suelo de conservación y suelo urbano y en las áreas verdes, áreas de valor ambiental, áreas naturales protegidas competencia del Distrito Federal;\nVI. En la evaluación y autorización del impacto ambiental y riesgo de obras y actividades.\nVII. En la política de desarrollo sustentable y los instrumentos para su aplicación;\nVIII. En el establecimiento de las competencias de las autoridades ambientales;\nIX. En la prevención, control y acciones contra la contaminación ambiental;\nX. En la vigilancia y protección de los recursos naturales de la Tierra;\n\nXI. En la prestación de servicios ambientales; y\nXII. En el establecimiento de medidas de control, seguridad y sanciones.\nARTÍCULO 3° Se consideran de utilidad pública:\nI. El ordenamiento ecológico del territorio del Distrito Federal;\nII.- El establecimiento, protección, preservación, restauración mejoramiento y vigilancia de las áreas verdes, áreas de valor ambiental, áreas naturales protegidas de competencia del Distrito\nFederal, las zonas de restauración ecológica y en general del suelo de conservación y suelo urbano para la preservación de los ecosistemas y elementos naturales;\nIII. El establecimiento de zonas intermedias de salvaguarda; las áreas de producción agropecuaria, y la zona federal de las barrancas, humedales, vasos de presas, cuerpos y corrientes de aguas;\nIV. La prevención y control de la contaminación ambiental del aire, agua y suelo, así como el cuidado, restauración y aprovechamiento de los elementos naturales y de los sitios necesarios para asegurar la conservación e incremento de la flora y fauna silvestres;\nV. Las actividades vinculadas con la prestación del servicio público de suministro de agua potable;\nVI. La Ejecución de programas destinados a fomentar la educación ambiental y a otorgar incentivos para la aplicación de tecnología ambiental y para la conservación de servicios ambientales en las áreas naturales protegidas de competencia del Distrito Federal, las áreas comunitarias de conservación ecológica y el suelo de conservación;\nVII. La participación social encaminada al desarrollo sustentable del Distrito Federal; y\nVIII. La elaboración y aplicación de planes y programas que contengan políticas de desarrollo integral de la entidad bajo criterios ambientales.\n\nIX. La celebración de convenios o acuerdos de coordinación entre autoridades ambientales y otras autoridades administrativas para la realización coordinada y conjunta de acciones de protección, vigilancia, conservación y preservación de los ecosistemas y sus elementos naturales.\nARTÍCULO 4º. En todo lo no previsto en la presente Ley, se aplicarán las disposiciones contenidas en otras leyes, reglamentos, normas y demás ordenamientos jurídicos relacionados con las materias que regula este ordenamiento.\nARTÍCULO 5º.- Para los efectos de esta Ley, se estará a las definiciones de conceptos que se contienen en la\nLey General del Equilibrio Ecológico y la Protección al Ambiente, la Ley de Aguas nacionales, la Ley General de Desarrollo Forestal Sustentable, la Ley de Residuos Sólidos del Distrito Federal y la Ley del Derecho al\nAcceso Disposición y Saneamiento del Agua de la Ciudad de México, así como las siguientes:\nÁREAS NATURALES PROTEGIDAS: toda acción u omisión que ponga en peligro la integridad de las personas o del ambiente, en virtud de la naturaleza, características o volumen de los materiales o residuos que se manejen, de conformidad con las normas oficiales mexicanas, los criterios o listados en materia ambiental que publiquen las autoridades competentes en el Diario\nOficial de la Federación y la Gaceta Oficial del Distrito Federal;\nADMINISTRACIÓN: La planeación, instrumentación, promoción, ejecución, control y evaluación de las acciones que en el ámbito público y en materia de protección, preservación, restauración y desarrollo se realicen en las áreas verdes, áreas de valor ambiental y áreas naturales protegidas, así como la coordinación de la investigación científica, monitoreo ambiental, capacitación y asesoría técnica que respecto a dichas áreas y sus elementos se lleven a cabo;\nADMINISTRACIÓN PÚBLICA DEL DISTRITO FEDERAL: conjunto de órganos, centrales, desconcentrados y paraestatales, conforme a la Ley Orgánica que expida la Asamblea Legislativa, la cual distribuirá los negocios del orden administrativo del Distrito Federal;\nAGUAS RESIDUALES: Son las provenientes de actividades domésticas, industriales, comerciales, agrícolas, pecuarias o de cualquier otra actividad que, por el uso de que han sido objeto, contienen materia orgánica y otras sustancias químicas que alteran su calidad original;\nALUMBRADO PÚBLICO.- Servicio público consistente en la iluminación de las vías públicas, parques públicos, y demás espacios de libre circulación que no se encuentren a cargo de ninguna\n\npersona física o moral, con el objeto de proporcionar la visibilidad adecuada para el normal desarrollo de las actividades y seguridad de los habitantes de la Ciudad.\nAMBIENTE: El conjunto de elementos naturales y artificiales o inducidos por el hombre que hacen posible la existencia y desarrollo de los seres humanos y demás organismos vivos que interactúan en un espacio y tiempo determinados. Deberá entenderse también como medio ambiente;\nAPROVECHAMIENTO SUSTENTABLE DE LA ENERGÍA. - El uso y aprovechamiento óptimo de la energía.\nÁREAS COMUNITARIAS DE CONSERVACIÓN ECOLÓGICA. Superficies del suelo de conservación, cubiertas de vegetación natural, establecidas por acuerdo del ejecutivo local con los ejidos y comunidades, en terrenos de su propiedad, que se destinan a la preservación, protección y restauración de la biodiversidad y los servicios ambientales, sin modificar el régimen de propiedad de dichos terrenos.\nÁREAS NATURALES PROTEGIDAS: Los espacios físicos naturales en donde los ambientes originales no han sido significativamente alterados por actividades antropogénicas, o que requieren ser preservadas y restauradas, por su estructura y función para la recarga del acuífero y la preservación de la biodiversidad. Son áreas que por sus características ecogeográficas, contenido de especies, bienes y servicios ambientales y culturales que proporcionan a la población, hacen imprescindible su preservación;\nÁREAS DE VALOR AMBIENTAL: Las áreas verdes en donde los ambientes originales han sido modificados por las actividades antropogénicas y que requieren ser restauradas o preservadas, en función de que aún mantienen ciertas características biofísicas y escénicas, las cuales les permiten contribuir a mantener la calidad ambiental de la Ciudad;\nAREAS DE VALOR AMBIENTAL: Las áreas verdes y los cuerpos de agua dentro del territorio y bajo las competencias de la Ciudad de México, en donde los ambientes originales han sido modificados por las actividades antropogénicas y que requieren ser restauradas o preservadas, en función de que aún mantienen ciertas características biofísicas y escénicas, las cuales les permiten contribuir a mantener la calidad ambiental de la Ciudad.\nReforma publicada en la GOCDMX el 27 de octubre de 2022\n\nÁREA VERDE: Toda superficie cubierta de vegetación, natural o inducida que se localice en el\nDistrito Federal;\nARMONÍA: Las actividades humanas, que, en el marco de la pluralidad y la diversidad, deben lograr equilibrios dinámicos con los ciclos y procesos inherentes a la Tierra;\nASAMBLEA: Se deroga\nAUDITORÍA AMBIENTAL: Examen metodológico de las actividades, operaciones y procesos, respecto de la contaminación y el riesgo ambiental, así como del grado de cumplimiento de la normatividad ambiental y de los parámetros internacionales y de buenas prácticas de operación e ingeniería aplicables, con el objeto de definir las medidas preventivas y correctivas necesarias para proteger los recursos naturales y el ambiente;\nAUTORIZACIÓN DE IMPACTO AMBIENTAL: Autorización otorgada por la Secretaría del Medio\nAmbiente como resultado de la presentación y evaluación de una declaratoria de cumplimiento ambiental, informe preventivo, manifestación o estudio de impacto ambiental y riesgo según corresponda cuando previamente a la realización de una obra o actividad se cumplan los requisitos establecidos en esta Ley para evitar o en su defecto minimizar y restaurar o compensar los daños ambientales que las mismas puedan ocasionar;\nBARRANCAS: Depresión geográfica que por sus condiciones topográficas y geológicas se presentan como hendiduras y sirven de refugio de vida silvestre, de cauce de los escurrimientos naturales de ríos, riachuelos y precipitaciones pluviales, que constituyen zonas importantes del ciclo hidrológico y biogeoquímico\nCENTRO COMERCIAL: Instalaciones que se destinen a la venta al público de bienes y servicios.\nCENTRO DE VERIFICACION: Local determinado por las autoridades competentes y autorizado por éstas, para llevar a cabo la medición de emisiones contaminantes con el equipo autorizado, provenientes de los vehículos automotores en circulación.\nCONGRESO: El Congreso de la Ciudad de México;\n\nCONJUNTO HABITACIONAL: Conjunto de viviendas concebidas dentro de un concepto integral, generalmente aprobado como un único proyecto o programa por la autoridad pública pertinente, casi siempre dentro del formato de propiedad horizontal compartida;\nCONJUNTO HABITACIONAL MIXTO: Conjunto de viviendas que permite una mezcla más intensa de usos de suelo, pudiendo coexistir edificios de uso puramente habitacional, con otros de uso de oficinas, administrativos y de industria no contaminante.\nCOMPENSACIÓN: el resarcimiento del deterioro ocasionado por cualquier obra o actividad en un elemento natural distinto al afectado, cuando no se pueda restablecer la situación anterior en el elemento afectado;\nCONDICIONES PARTICULARES DE DESCARGA: Aquellas fijadas por la Secretaría que establecen respecto del agua residual límites físicos, químicos y biológicos más estrictos que las normas oficiales mexicanas y las normas ambientales para el Distrito Federal, respecto de un determinado uso, usuario o grupo de usuarios o de un cuerpo receptor de jurisdicción local, de acuerdo con esta Ley;\nCONSERVACIÓN: El conjunto de políticas, planes, programas, normas y acciones, de detección, rescate, saneamiento y recuperación, destinadas a asegurar que se mantengan las condiciones que hacen posible la evolución o el desarrollo de las especies y de los ecosistemas propios del\nDistrito Federal;\nCONTAMINACIÓN: la presencia en el ambiente de toda substancia que en cualquiera de sus estados físicos y químicos al incorporarse o actuar en la atmósfera, agua, suelo, flora, fauna o cualquier elemento natural, altere o modifique su composición y condición natural, causando desequilibrio ecológico;\nCONTAMINACIÓN LUMÍNICA: El exceso de flujo lumínico, iluminación o resplandor luminoso en ambientes nocturnos o brillo producido por la difusión y reflexión de la luz en los gases, aerosoles y partículas en suspensión en la atmósfera, provenientes de fuentes artificiales, con intensidades, direcciones o rangos espectrales inadecuados para la realización de las actividades previstas en la zona alumbrada que altera las condiciones naturales de luminosidad en horas nocturnas provocando afectación a los patrones de descanso o condiciones de molestia en las personas sometidas al campo luminoso producido por las fuentes emisoras.\nFracción añadida y publicada en la GOCDMX el 04 de mayo de 2023\n\nCONTINGENCIA AMBIENTAL O EMERGENCIA ECOLÓGICA: situación eventual y transitoria declarada por las autoridades competentes cuando se presenta o se prevé con base en análisis objetivos o en el monitoreo de la contaminación ambiental, una concentración de contaminantes o un riesgo ecológico derivado de actividades humanas o fenómenos naturales que afectan la salud de la población o al ambiente de acuerdo con las normas oficiales mexicanas;\nCONTROL: Inspección, vigilancia y aplicación de las medidas necesarias para el cumplimiento de las disposiciones establecidas en este ordenamiento;\nCOSMOVISIÓN DE LOS GRUPOS INDÍGENAS: Es la manera de ver e interpretar a la Tierra. Se trata del conjunto de creencias que permiten analizar y reconocer la realidad a partir de la propia existencia.\nCUENCA DE MÉXICO: El ámbito geográfico comprendido por los estados de México, Puebla,\nTlaxcala, Hidalgo y el Distrito Federal en la que tienen lugar los ciclos naturales del agua, aire, suelo y especies vivas que determinan las condiciones ambientales del Distrito Federal;\nCUERPOS DE AGUA: Masa o extensión de agua que en asociación con el terreno circundante genera nichos ecosistémicos con funciones únicas e imprescindibles para la vida humana.\nReforma publicada en la GOCDMX el 27 de octubre de 2022\nCUERPO RECEPTOR: La corriente, depósito de agua, el cauce o bien del dominio público del\nDistrito Federal en donde se descargan, infiltran o inyectan aguas residuales;\nDECLARATORIA DE CUMPLIMIENTO AMBIENTAL: Instrumento de evaluación ambiental por virtud del cual los interesados declaran bajo protesta de decir verdad, que sus proyectos, obras o actividades no requieren de la presentación de una manifestación de impacto ambiental, informe preventivo, estudio de riesgo dado que los impactos ambientales y medidas de mitigación, control y compensación han sido tipificadas por la Secretaría y se encuentran regulados a través del cumplimiento de la normatividad aplicable vigente.\nDEMARCACIÓN TERRITORIAL: Cada una de las part es en que se divide el territorio del Distrito\nFederal para efectos de la organización político-administrativa;\n\nDELEGACIONES: Los Órganos Político Administrativos establecidos en cada una de las\nDemarcaciones Territoriales;\nDAÑO AL AMBIENTE: Perdida, daño, deterioro, menoscabo, afectación o modificación adversos y mensurables de los hábitat, de los ecosistemas, de los recursos naturales, de sus condiciones químicas, físicas o biológicas de las relaciones de interacción que se dan entre estos, así como de los servicios ambientales que proporcionan, de conformidad con lo que establece la Ley.\nDERECHO COLECTIVO: La facultad de los individuos para ejercitar el cumplimiento a sus garantías, en el marco de protección a los recursos naturales de la Tierra;\nDESARROLLO SUSTENTABLE: El proceso evaluable mediante criterios e indicadores de carácter ambiental, económico y social que tiende a mejorar la calidad de vida y la productividad de las personas, que se funda en medidas apropiadas de conservación del equilibrio ecológico, protección del ambiente y aprovechamiento de recursos naturales, de manera que no se comprometa la satisfacción de las necesidades de las generaciones futuras;\nDISPOSICIÓN FINAL: Acción de depositar permanentemente los residuos en sitios y condiciones adecuadas para evitar daños a los ecosistemas y al ambiente;\nECOCIDIO: la conducta dolosa determinada por las normas penales, consistente en causar un daño grave al ambiente por la emisión de contaminantes, la realización de actividades riesgosas o la afectación de recursos naturales, en contravención a lo dispuesto en la presente ley o en las normas oficiales ambientales mexicanas\nECOSISTEMA: La unidad funcional básica de interacción de los organismos vivos entre sí y de éstos con el ambiente, en un espacio y tiempo determinados;\nEDUCACIÓN AMBIENTAL: El proceso permanente de carácter interdisciplinario, orientado a la formación de una ciudadanía que reconozca valores, aclare conceptos y desarrolle las habilidades y actitudes necesarias para una convivencia armónica entre seres humanos, su cultura y su medio biofísico circundante;\nEMISIONES CONTAMINANTES: La generación o descarga de materia o energía, en cualquier cantidad, estado físico o forma, que al incorporarse, acumularse o actuar en los seres vivos, en la\n\natmósfera, agua, suelo, subsuelo o cualquier elemento natural, afecte negativamente su salud, composición o condición natural;\nENERGÍA SOLAR.- Radiación electromagnética emitida por el sol.\nESTUDIO DE RIESGO: Documento mediante el cual se dan a conocer, con base en el análisis de las acciones proyectadas para el desarrollo de una obra o actividad, los riesgos que éstas representan para los ecosistemas, la salud o el ambiente, así como las medidas técnicas preventivas, correctivas y de seguridad, tendientes a mitigar, reducir o evitar los efectos adversos que se causen al ambiente, en caso de un posible accidente durante la realización u operación normal de la obra o actividad de que se trate;\nEVALUACIÓN AMBIENTAL ESTRATÉGICA: Procedimiento que incluye el conjunto de estudios e informes técnicos que permiten estimar los efectos de un plan o programa de gran trascendencia de desarrollo sectorial e institucional sobre el medio ambiente, con el fin de prevenirlos, compensarlos y mitigarlos.\nFAUNA SILVESTRE: las especies animales que subsisten sujetas a los procesos de selección natural y que se desarrollan libremente, incluyendo sus poblaciones menores, que se encuentran bajo control del hombre, así como los animales domésticos, que por abandono se tornen salvajes y por ello sean susceptibles de captura y apropiación;\nFLORA SILVESTRE: las especies vegetales que subsisten sujetas a los procesos de selección natural y que se desarrollan libremente, incluyendo las poblaciones o especímenes de estas especies que se encuentran bajo control del hombre;\nFUENTES FIJAS: los establecimientos industriales, mercantiles y de servicio y los espectáculos públicos que emitan contaminantes al ambiente, ubicados o realizados, según corresponda, en el Distrito Federal\nFUENTES MÓVILES: los vehículos automotores que emitan contaminantes al ambiente.\nFUENTES NATURALES DE CONTAMINACIÓN: las de origen biogénico, de fenómenos naturales y erosivos.\n\nGARANTÍA DE REGENERACIÓN DE LA TIERRA: Responsabilidad a cargo de las autoridades competentes en la materia y de la sociedad, en armonía consistente en garantizar las condiciones necesarias para que los diversos sistemas de vida de la Tierra puedan absorber, daños, adaptarse a las perturbaciones y regenerarse sin alterar significativamente sus características de estructura y funcionalidad, reconociendo que los sistemas de vida tienen límites en su capacidad de regenerarse, y que la humanidad tienen límites en su capacidad de revertir sus acciones;\nGACETA OFICIAL: La Gaceta Oficial del Distrito Federal;\nHUELLA ECOLÓGICA: Es el indicador de sustentabilidad que mide el grado de impacto que ejerce cierta comunidad humana, persona, organización, país, región o ciudad sobre el ambiente. Es considerada además una herramienta para determinar los espacios terrestres, aéreos, acuáticos y marinos que se necesitan para producir todos los recursos y bienes, así como la superficie para absorber todos los desechos que se generan, usando la tecnología actual.\nIMPACTO AMBIENTAL: Modificación del ambiente, ocasionado por la acción del hombre o de la naturaleza;\nINCINERACIÓN: Combustión controlada de cualquier sustancia o material, cuyas emisiones se descargan a través de una chimenea;\nINTERCULTURALIDAD: El ejercicio de respeto a los recursos naturales de la Tierra requiere del reconocimiento, recuperación, respeto, protección, y dialogo de la diversidad de sentires, valores, saberes, conocimientos, prácticas, habilidades, trascendencias, transformaciones, ciencias, tecnologías y normas, de todas las culturas del mundo que buscan un convivir en armonía con la naturaleza;\nJARDÍN POLINIZADOR: Espacio público o privado en el que se colocan plantas nativas de la región, que proveen alimento, refugio, agua y espacio para los polinizadores.\nFracción añadida y publicada en la GOCDMX el 04 de mayo de 2023\nLABORATORIO AMBIENTAL: aquellos que acrediten contar con los elementos necesarios para analizar contaminantes en el aire, agua, suelo, subsuelo, materiales o residuos;\nLEY: Ley Ambiental del Distrito Federal;\n\nLEY GENERAL: Ley General del Equilibrio Ecológico y la Protección al Ambiente;\nLIXIVIADOS: Los líquidos que se forman por la reacción, arrastre o filtrado de los materiales que constituyen los residuos sólidos y que contienen sustancias en forma disuelta o en suspensión que pueden infiltrarse en los suelos o escurrirse fuera de los sitios en los que se depositen residuos sólidos y que puede dar lugar a la contaminación del suelo y de cuerpos de agua;\nLUZ INTRUSA: Parte de la luz de una instalación con fuente de iluminación que no cumple la función para la que fue diseñada, que no previene la contaminación lumínica y que incluye:\nA. La luz que cae indebidamente fuera de la zona que se requiere iluminar;\nB. La luz difusa en las proximidades de la instalación de iluminación;\nC. La luminiscencia del cielo, es decir, la iluminación del cielo nocturno que resulta del reflejo directo e indirecto de la radiación visible e invisible, dispersa por los constituyentes de la atmósfera, moléculas de gas, aerosoles y partículas en la dirección de la observación;\nD.La luz difusa que se esparce en las proximidades de la fuente artificial de iluminación;\ny\nE. La luz que se proyecta en varias direcciones fuera de la zona terrestre a iluminar.\nFracción añadida y publicada en la GOCDMX el 04 de mayo de 2023\nMANEJO: Conjunto de actividades que incluyen, tratándose de recursos naturales, la extracción, utilización, explotación, aprovechamiento, administración, preservación, restauración, desarrollo, mantenimiento y vigilancia; o tratándose de materiales o residuos, el almacenamiento, recolección, transporte, alojamiento, reuso, tratamiento, reciclaje, incineración y disposición final;\nMANIFESTACIÓN DE IMPACTO AMBIENTAL: El documento mediante el cual se da a conocer, con base en estudios, el impacto ambiental, significativo y potencial que generaría una obra o actividad, así como la forma de evitarlo o atenuarlo en caso de que sea negativo;\nMATERIALES Y RESIDUOS PELIGROSOS: Las substancias, compuestos o residuos y sus mezclas, que por sus características corrosivas, tóxicas, reactivas, explosivas, inflamables o biológicas\n\ninfecciosas, representan un riesgo para el ambiente, de conformidad con las normas oficiales mexicanas aplicables;\nMERCADO DE TRUEQUE: Programa que opera la Secretaría donde se efectúa el intercambio de residuos sólidos adecuadamente separados tales como: papel, vidrio, cartón, latas de aluminio,\nPET, tetrapack y electrónicos en desuso, por productos agrícolas producidos en el Distrito Federal.\nNORMAS AMBIENTALES PARA EL DISTRITO FEDERAL: Las que emita la autoridad competente en ésta materia, en función de las atribuciones que esta ley y otros ordenamientos legales le confiere;\nNORMAS OFICIALES: Las normas oficiales mexicanas aplicables en materia ambiental;\nORDENAMIENTO ECOLÓGICO: La regulación ambiental obligatoria respecto de los usos del suelo fuera del suelo urbano, del manejo de los recursos naturales y la realización de actividades para el suelo de conservación y barrancas integradas a los programas de desarrollo urbano;\nPARQUES: Las áreas verdes o espacios abiertos jardinados de uso público, ubicados dentro de suelo urbano o dentro de los límites administrativos de la zona urbana de los centros de población y poblados rurales en suelo de conservación, que contribuyen a mantener el equilibrio ecológico dentro de las demarcaciones en que se localizan, y que ofrecen fundamentalmente espacios recreativos para sus habitantes;\nPARQUES LOCALES: Se deroga\nPARQUES URBANOS: Se deroga\nPLAN RECTOR DE LAS ÁREAS NATURALES PROTEGIDAS DEL DISTRITO FEDERAL: Instrumento de planeación y normatividad que establece lineamientos, criterios y políticas para la administración y manejo de las Áreas Naturales Protegidas;\nPLATAFORMA DIGITAL: Sistema informático desarrollado por la Agencia Digital de Innovación\nPública, y operado por la Secretaría, a través de la cual se realizan los trámites establecidos en la presente Ley;\nReforma publicada en la GOCDMX el 27 de febrero de 2023\n\nPLATAFORMAS O PUERTOS DE MUESTREO: Instalaciones que permiten el análisis y medición de las descargas de contaminantes o materiales de una fuente fija a la atmósfera, agua, suelo o subsuelo, de acuerdo con las Normas Oficiales;\nPOLINIZADORES: Animales como abejas, avispas, hormigas, murciélagos, colibríes, mariposas, polillas, escarabajos, entre otros, que se alimentan del néctar de las flores y durante sus visitas transportan accidentalmente polen de una flor a otra, permitiendo que las plantas produzcan frutos.\nFracción añadida y publicada en la GOCDMX el 04 de mayo de 2023\nPRECAUCIÓN: Exige tomar medidas que reduzcan la posibilidad de sufrir un daño ambiental grave. La falta de certeza científica absoluta no deberá utilizarse como razón para postergar la adopción de medidas eficaces en función de los costos para impedir la degradación del ambiente.\nPRESTADORES DE SERVICIOS AMBIENTALES: Prestador de servicios de impacto ambiental es la persona que elabora informes preventivos, manifestaciones o estudios de impacto ambiental o de riesgo por cuenta propia o de terceros y que es responsable del contenido de los mismos;\nPRESTADORES DE SERVICIOS DE IMPACTO AMBIENTAL Y RIESGO: La persona física o moral que elabora informes preventivos, manifestaciones de impacto ambiental, estudios de riesgo, daño ambiental, evaluaciones ambientales estratégicas, declaratorias de cumplimiento ambiental, informes de cumplimiento de condicionantes y/o de disposiciones ambientales.\nPREVENCIÓN: El conjunto de disposiciones y medidas anticipadas para evitar el deterioro del ambiente;\nPROCURADURÍA: La Procuraduría Ambiental y del Ordenamiento Territorial de la Ciudad de\nMéxico;\nReforma publicada en la GOCDMX el 24 de Marzo de 2023\nPROGRAMA DE MANEJO: Instrumento rector de planeación y regulación que establece las actividades, acciones y lineamientos básicos para el manejo y la administración de las áreas de valor ambiental;\n\nPROGRAMA GENERAL DE ORDENAMIENTO ECOLÓGICO DEL DISTRITO FEDERAL: Instrumento de política ambiental que regula los usos de suelo en el suelo de conservación.\nPROGRAMA SECTORIAL AMBIENTAL: Instrumento de planeación en el cual se integran las estrategias y acciones prioritarias para la ejecución de la política ambiental del Distrito Federal, así como las acciones de los diferentes sectores, en congruencia con el Programa General de\nDesarrollo del Distrito Federal y la Ley de Planeación del Desarrollo Distrito Federal;\nPROTECCIÓN ECOLÓGICA: El conjunto de políticas, planes, programas, normas y acciones destinados a mejorar el ambiente y a prevenir y controlar su deterioro;\nRESILIENCIA. La capacidad de las personas, asentamientos humanos, comunidades, empresas y sistemas que se encuentran dentro de una ciudad para sobrevivir, resistir, recuperarse rápidamente, adaptarse y crecer ante cualquier peligro factible, independientemente de los tipos de tensiones crónicas, impactos agudos o amenazas múltiples que experimente;\nQUEMA: Combustión inducida de cualquier sustancia o material;\nRECICLAJE: Método de tratamiento que consiste en la transformación de los residuos con fines productivos y de reutilización;\nRECONOCIMIENTO TÉCNICO: El reconocimiento que se realiza en el sitio donde pretende desarrollarse el programa, obra o actividad por los evaluadores de impacto ambiental y/o riesgo autorizados por la Secretaría para comprobar y constatar el contenido de los estudios de impacto ambiental en sus diferentes modalidades, o de evaluación de daño ambiental.\nRECURSOS NATURALES: El elemento natural susceptible de ser aprovechado en beneficio del hombre;\nREPARACIÓN DEL DAÑO AMBIENTAL O ECOLÓGICO: El restablecimiento de la situación anterior y, en la medida en que esto no sea posible, la compensación o el pago del daño ocasionado por el incumplimiento de una obligación establecida en esta Ley o en las normas oficiales;\nRESIDUO: Cualquier material generado en los procesos de extracción, beneficio, transformación, producción, consumo, utilización, control o tratamiento cuya calidad no permita usarlo nuevamente en el proceso que lo generó;\n\nRESIDUOS INDUSTRIALES NO PELIGROSOS: Todos aquéllos residuos en cualquier estado físico generados en los procesos industriales que no contengan las características que los hagan peligrosos;\nRESIDUOS SÓLIDOS: Todos aquellos residuos en estado sólido que provengan de actividades domésticas o de establecimientos industriales, mercantiles y de servicios. que no posean las características que los hagan peligrosos;\nRESPETO Y DEFENSA DE LOS RECURSOS NATURALES DE LA TIERRA: Las autoridades del Distrito\nFederal en sus respectivos ámbitos competenciales y cualquier persona individual o colectiva respetan, protegen y garantizan los recursos naturales de la Tierra;\nRESTAURACIÓN DEL EQUILIBRIO ECOLÓGICO: Conjunto de actividades tendientes a la recuperación y restablecimiento de las condiciones que propician la evolución y continuidad de los procesos naturales;\nRIESGO AMBIENTAL: Peligro al que se expone el ecosistema como consecuencia de la realización de actividades riesgosas;\nRUIDO: Sonido indeseable en niveles que produce alteraciones, vibraciones, molestias riesgos o daños para la salud de las personas y sus bienes, o que causan impactos negativos sobre el ambiente.\nSECRETARÍA: Secretaría del Medio Ambiente del Gobierno del Distrito Federal;\nSERVICIOS AMBIENTALES: Aquellos derivados de los ecosistemas o sus elementos, cuyos valores o beneficios son económicos, ecológicos o socioculturales y que inciden directamente en la protección y mejoramiento del medio ambiente, propiciando una mejor calidad de vida de los habitantes y que justifican la necesidad de desarrollar acciones para promover la preservación, recuperación y uso racional de aquellos elementos relevantes para la generación de estos servicios en beneficio de las generaciones presentes y futuras;\nSUELO DE CONSERVACIÓN: Las zonas que por sus características ecológicas proveen servicios ambientales necesarios para el mantenimiento de la calidad de vida de los habitantes del Distrito\n\nFederal y cuyas poligonales están determinadas por el Programa General de Ordenamiento\nEcológico del Distrito Federal;\nSUELO URBANO: La clasificación establecida en la fracción I del artículo 30 de la Ley de Desarrollo\nUrbano del Distrito Federal, incluidas las áreas verdes dentro de los límites administrativos de la zona urbana de los centros de población y poblados rurales localizados en suelo de conservación que establece el programa general de ordenamiento ecológico;\nSUELO DE CONSERVACIÓN: La clasificación establecida en la fracción II del artículo 30 de la Ley de Desarrollo Urbano del Distrito Federal;\nTRÁFICO DE ESPECIES: Flora y fauna cuyo comercio está prohibido en la Legislación aplicable;\nTRATAMIENTO: Acción de transformar las características de los residuos;\nVERIFICADORES AMBIENTALES: Los prestadores de servicio de verificación de emisiones contaminantes autorizados por la Secretaría.\nVOCACIÓN NATURAL: Condiciones que presenta un ecosistema para sostener una o varias actividades sin que se produzcan desequilibrios ecológicos.\nZONA DE CALIDAD ACÚSTICA: Aquella parte del territorio que presenta una vulnerabilidad a la emisión de ruidos y sonidos que puedan afectar de manera significativa la salud de las personas y el medio ambiente y sobre la cual la autoridad puede emitir opiniones o restricciones por las emisiones de ruido;\nZONAS DE RECARGA DE MANTOS ACUÍFEROS: Las zonas en predios no construidos que por su ubicación reciben una precipitación pluvial superior a la media para el Distrito Federal y que por las características de suelo y subsuelo son permeables para la captación de agua de lluvia que contribuye a la recarga de los mantos acuíferos.\nZONAS DE RECARGA DE MANTOS ACUIFEROS: Toda pérdida, disminución, detrimento o menoscabo significativo inferido al ambiente o a uno o más de sus componentes;\n\nTÍTULO SEGUNDO\nDE LAS AUTORIDADES AMBIENTALES\nARTÍCULO 6° Son autoridades en materia ambiental en el Distrito Federal:\nI. La persona titular de la Jefatura de Gobierno;\nII. La persona titular de la Secretaría del Medio Ambiente;\nII. La persona titular de la Secretaría de Educación, Ciencia, Tecnología e Innovación;\nIV. Las personas titulares de las Alcaldías; y\nV. La persona titular de la Procuraduría Ambiental y del Ordenamiento Territorial de la Ciudad de\nMéxico.\nFracciones modificadas y publicadas en la GOCDMX el 24 de Marzo de 2023\nPara efectos de lo dispuesto en la fracción III, en cada órgano político administrativo existirá una unidad administrativa encargada del área ambiental y de aplicar las disposiciones que esta Ley le señalan como de su competencia.\nLa administración pública local será la encargada de formular la política de desarrollo sustentable para el\nDistrito Federal así como de realizar las acciones necesarias para proteger y restaurar el ambiente y los elementos naturales en forma coordinada, concertada y corresponsable con la sociedad en general, así como con las dependencias federales competentes.\nLa Ley Orgánica del Poder Ejecutivo y de la Administración Pública de la Ciudad de México y su Reglamento, establecerán el sistema de delegación de facultades.\nPárrafo modificado y publicado en la GOCDMX el 24 de Marzo de 2023\nDe conformidad con lo que dispone el artículo 22 de la Ley de Planeación del Desarrollo del Distrito Federal, el Comité de Planeación establecerá la Comisión del Ordenamiento Territorial del Distrito Federal, copresidida por los Titulares de las Secretarías de Medio Ambiente, Desarrollo Urbano y Vivienda y\nDesarrollo Rural y Equidad para las Comunidades.\n\nEsta Comisión, de conformidad con la Ley de Planeación del Desarrollo del Distrito Federal, será el órgano de coordinación para la aplicación del ordenamiento ecológico territorial, de sus programas y del Programa\nGeneral de Desarrollo Urbano y demás programas de Desarrollo Urbano, disposiciones que serán el elemento territorial que esa Ley prevé para el Programa General de Desarrollo del Distrito Federal.\nARTÍCULO 7° La Administración Pública del Distrito Federal podrá celebrar todo tipo de instrumentos de coordinación y concertación de acciones con autoridades federales, estatales y municipales, así como con los sectores social y privado, en materia de protección, conservación, mejoramiento y restauración del ambiente del Distrito Federal y Cuenca de México.\nARTÍCULO 8° Corresponde al Jefe de Gobierno del Distrito Federal, en materia ambiental, el ejercicio de las siguientes atribuciones:\nI. Formular, conducir y evaluar la política ambiental en el Distrito Federal, conforme al Plan\nNacional de Desarrollo, el Programa General de Desarrollo del Distrito Federal y los programas sectoriales correspondientes;\nII. Establecer el fondo ambiental a que se refiere la presente Ley para la investigación, estudio y atención de aquellos asuntos que en materia ambiental se consideren de interés para el Distrito\nFederal;\nIII. Promover la participación ciudadana en materia ambiental individual, colectiva o a través de los órganos de representación ciudadana e instrumentos de participación ciudadana, así como de las organizaciones sociales, civiles y empresariales e instituciones académicas;\nIV. Proponer que en las disposiciones del Código Financiero del Distrito Federal, se establezca el pago de derechos por la prestación de los servicios públicos en materia ambiental;\nV. Establecer, o en su caso proponer, la creación de instrumentos económicos que incentiven el cumplimiento de los objetivos de la política ambiental en el Distrito Federal;\nVI. Celebrar convenios o acuerdos de coordinación con la Federación, con el objeto de que el\nDistrito Federal asuma el ejercicio de las funciones que señala la Ley General;\nVII. Celebrar convenios o acuerdos de coordinación y colaboración administrativa con otras entidades federativas, con el propósito de atender y resolver problemas ambientales comunes y\n\nejercer las atribuciones a que se refiere esta Ley, a través de las instancias que al efecto se determinen, atendiendo a lo dispuesto en las leyes locales que resulten aplicables;\nVIII. Celebrar convenios mediante los cuales se obtengan recursos materiales y económicos para realizar investigaciones pertinentes a la problemática ambiental del Distrito Federal;\nIX. Expedir los decretos que establezcan áreas de valor ambiental, zonas de restauración ecológica, zonas intermedias de salvaguarda y áreas naturales protegidas de jurisdicción del\nDistrito Federal;\nX. Expedir el programa sectorial ambiental y el programa de ordenamiento ecológico del Distrito\nFederal;\nX Bis. Promover la instalación de tecnologías para el aprovechamiento de energía solar en viviendas, comercios y servicios, así como el establecimiento de los mecanismos financieros para tal fin;\nFracción añadida y publicada en la GOCDMX el 04 de mayo de 2023\nXI. Expedir los ordenamientos y demás disposiciones necesarias para proveer el cumplimiento de la presente Ley; y\nXII. Las demás que conforme a esta Ley le correspondan.\nARTÍCULO 9° Corresponde a la Secretaría, además de las facultades que le confiere la Ley Orgánica de la\nAdministración Pública del Distrito Federal, el ejercicio de las siguientes atribuciones:\nI. Formular, conducir y evaluar la política ambiental en el Distrito Federal, así como los planes y programas que de esta se deriven, en congruencia con la que en su caso hubiere formulado la\nFederación;\nII. Formular, ejecutar y evaluar el programa sectorial ambiental del Distrito Federal;\nIII. Formular y ejecutar el Programa General de Ordenamiento Ecológico del Distrito Federal, y los programas que de él se deriven, así como vigilar su cumplimiento. La formulación y ejecución será en coordinación con las instancias de la Administración Pública del Distrito Federal y las\nDelegaciones con atribuciones y territorio en el Suelo de Conservación.\n\nLa Secretaría evaluará las propuestas de adecuaciones al Programa General de Ordenamiento\nEcológico que formulen la Secretaría de Desarrollo Urbano y Vivienda y la Secretaría de\nDesarrollo Rural y Equidad para las Comunidades, las que se efectuarán en el ámbito de sus atribuciones;\nIV. Aplicar los instrumentos de política ambiental previstos en esta Ley, para conservar y restaurar el equilibrio ecológico, proteger al ambiente e impulsar la construir resiliencia en materias de su competencia;\nV. Evaluar las manifestaciones de impacto ambiental de su competencia, y en su caso, autorizar condicionadamente o negar la realización de proyectos, obras y actividades;\nVI. Evaluar y resolver sobre los estudios de riesgo;\nVI Bis. Dictaminar los estudios de daño ambiental y en su caso, determinar e imponer las disposiciones ambientales que deberán observarse durante la realización de proyectos, obras o actividades; en las etapas correspondientes.\nVI. Ter. Ordenar la realización de los reconocimientos técnicos para comprobar y constatar el contenido de los estudios de impacto ambiental en sus diferentes modalidades o de evaluación de daño ambiental.\nVII. Expedir normas ambientales para el Distrito Federal en materias de competencia local;\nVIII. Desarrollar programas que fomenten la autorregulación y la auditoría ambiental;\nIX. Convenir con los productores y grupos empresariales el establecimiento de procesos voluntarios de autorregulación y expedir, en su caso, la certificación de la reducción de emisiones contaminantes, contando con la opinión de la Procuraduría;\nX. Establecer los criterios ambientales a que deberán sujetarse los programas, adquisiciones y obras de las dependencias del Gobierno del Distrito Federal;\nXI. Promover junto con la Procuraduría la creación de estándares e indicadores de calidad ambiental;\n\nXII. Establecer o en su caso proponer la creación de instrumentos económicos que incentiven el cumplimiento de los objetivos de la política ambiental en el Distrito Federal contando con la opinión de la Procuraduría;\nXII Bis. Promover y establecer la operación del mercado de trueque, en la que los habitantes del\nDistrito Federal puedan intercambiar sus residuos sólidos generados y adecuadamente separados, por productos agrícolas, cultivados en el Distrito Federal;\nXIII. Administrar, ejecutar y controlar el fondo ambiental así como informar sobre el uso de los recursos y presentar los resultados dentro del informe anual que rinda a la Asamblea;\nXIV. Proponer la creación de áreas de valor ambiental, áreas naturales protegidas, y las áreas comunitarias de conservación ecológica, así como regularlas, vigilarlas y administrarlas en el ámbito de su competencia y en términos de esta Ley, a fin de lograr la preservación y el aprovechamiento sustentable de los recursos naturales presentes en dichas áreas; asimismo procurará crear programas de reforestación permanente en suelo de conservación y en suelo urbano en coordinación con la Secretaría de Desarrollo Urbano y Vivienda, para su preservación.\nXIV Bis. Celebrar convenios con las delegaciones para que éstas se encarguen de la administración, preservación y reforestación de las áreas de valor ambiental y de las áreas naturales protegidas de competencia de la Secretaría, así como para delegar facultades en estas materias que estén conferidas por esta Ley y demás ordenamientos aplicables a la Secretaría;\nXIV Bis 1. Formular y conducir la política de la flora y fauna silvestres en el ámbito de competencia del Distrito Federal, así como ejercer las atribuciones federales que sean objeto de convenio;\nXIV Ter. Crear Jardines Polinizadores administrados en el ámbito de su competencia, así como promover su creación en los ámbitos público, privado y social, a fin de contribuir a la conservación de la biodiversidad y la resiliencia de los ecosistemas.\nFracción añadida y publicada en la GOCDMX el 04 de mayo de 2023\nXV. Proponer la declaración de zonas de restauración ecológica;\nXVI. Proponer la declaración de zonas intermedias de salvaguarda;\n\nXVII. Promover la participación ciudadana en materia ambiental individual, colectiva o a través de los órganos de representación ciudadana e instrumentos de participación ciudadana;\nXVIII. Realizar y promover en forma coordinada, concertada y corresponsable, acciones relacionadas con la conservación del ambiente, la protección ecológica y la restauración del equilibrio ecológico, entre las organizaciones sociales, civiles y empresariales, así como con los ciudadanos interesados, a fin de desarrollar en la población, una mayor cultura ambiental, y promover el mejor conocimiento de esta Ley;\nXIX. Coordinar la participación de las dependencias y entidades de la administración pública del\nDistrito Federal, y de las delegaciones en las acciones de educación ambiental, de prevención y control del deterioro ambiental, conservación, protección y restauración del ambiente en el territorio del Distrito Federal, así como celebrar con éstas y con la sociedad, los acuerdos que sean necesarios con el propósito de dar cumplimiento a la presente Ley;\nXIX. Bis. Establecer las políticas y lineamientos de integración y operación del cuerpo de Policías\nAmbientales; en coordinación con la Secretaría de Seguridad Pública del Distrito Federal en las acciones de conservación, vigilancia, restauración y protección de los ecosistemas y sus elementos naturales, en suelo de conservación y urbano;\nXIX. Bis 1. Realizar acciones de control, supervisión y vigilancia ambiental, con auxilio de la\nSecretaría de Seguridad Pública del Distrito Federal y de la Procuraduría, en suelo de conservación y suelo urbano, tendientes a prevenir actos o hechos constitutivos de violación a esta ley, al Código Penal para el Distrito Federal, en materia de delitos ambientales y de las disposiciones que de ella emanen;\nXIX. Bis 2. Con el auxilio de la Secretaría de Seguridad Pública del Distrito Federal y en coordinación con las autoridades competentes, retirar a las personas y bienes que integren asentamientos humanos establecidos en contravención con los programas de desarrollo urbano o de ordenamiento ecológico del territorio; así como ejecutar las acciones necesarias para evitar el establecimiento de dichos asentamientos humanos irregulares, en áreas verdes, áreas de valor ambiental, áreas naturales protegidas y en suelo de conservación, que sean competencia de la\nSecretaría;\nXX. Realizar y promover programas para el desarrollo de técnicas, ecotecnias y procedimientos que permitan prevenir, controlar y abatir el deterioro ambiental, propiciar el aprovechamiento\n\nsustentable de los recursos naturales y la conservación de los ecosistemas, con instituciones de educación superior, centros de investigación, instituciones privadas y grupos civiles, con los sectores industrial, comercial y de servicio;\nXXI. Conducir la política del Distrito Federal relativa a la información y difusión en materia ambiental;\nXXII. Participar en coordinación con la Federación, en asuntos que afecten el equilibrio ecológico, el ambiente y la salud en el Distrito Federal y los municipios conurbados;\nXXIII. Promover y celebrar, convenios de coordinación, concertación y colaboración con el gobierno federal, de las entidades federativas y de los municipios de la zona conurbada, así como con los particulares, para la realización conjunta y coordinada de acciones de protección ambiental;\nXXIV. Refrendar y ejecutar los convenios relacionados con la salvaguarda del suelo de conservación que celebre el Jefe de Gobierno del Distrito Federal; y, asimismo, promover y participar, en la elaboración y celebración de convenios o acuerdos de coordinación que se lleven a cabo entre el Ejecutivo Local y la Federación, con el objeto de que el Distrito Federal asuma el ejercicio de las funciones que señala la Ley General;\nXXV. Ejercer las funciones que le transfiera la Federación al Distrito Federal en materia ambiental, en los términos que establezcan los convenios o acuerdos de coordinación correspondientes;\nXXVI. Emitir recomendaciones a las autoridades federales y del Distrito Federal, con el propósito de promover el cumplimiento de la legislación ambiental;\nXXVII. Ejercer todas aquellas acciones tendientes a la conservación y restauración del equilibrio ecológico, así como la regulación, prevención y control de la contaminación del aire, agua y suelo que no sean de competencia federal;\nXXVIII. Hacer efectivas las obligaciones derivadas de la Ley General, esta Ley, y disposiciones que de éstas emanen, en el ámbito de su competencia; y en su caso, hacer uso de las medidas de seguridad;\n\nXXIX. Ordenar la realización de visitas de inspección para verificar el cumplimiento de los preceptos de esta ley, su reglamento, normas aplicables en materia ambiental, ordenamiento ecológico del territorio, declaratorias de áreas naturales protegidas, programas de manejo, creación e incremento de áreas verdes en suelo urbano, las condicionantes que en materia de impacto y riesgo ambiental se impongan, así como todas las disposiciones legales aplicables al suelo de conservación;\nXXIX Bis. Realizar acciones de vigilancia y supervisión para verificar el cumplimiento de los preceptos de esta ley y las disposiciones que de ella emanen en suelo de conservación y suelo urbano, con el auxilio de la Secretaría de Seguridad Pública del Distrito Federal y la Procuraduría;\nXXX. Aplicar las sanciones administrativas, medidas correctivas y de seguridad correspondientes por infracciones a la Ley General, en materias de competencia local, esta Ley y sus reglamentos;\nXXXI. Otorgar y revocar los permisos, licencias, autorizaciones y certificaciones establecidas en la presente Ley;\nXXXII. Clausurar o suspender las obras o actividades y, en su caso solicitar la revocación y cancelación de las licencias de construcción y uso de suelo cuando se transgredan las disposiciones de esta Ley y demás aplicables;\nLa manifestación de construcción dejará de surtir sus efectos, cuando los promoventes hubieren declarado con falsedad o transgredido las disposiciones de esta Ley y demás aplicables.\nAsimismo, se declarará la nulidad del registro, que dejará de surtir sus efectos, independientemente de las sanciones administrativas, penales y civiles que correspondan.\nXXXIII. Emitir las resoluciones que pongan fin al procedimiento de inspección y vigilancia, así como cualquier resolución que sea necesaria de conformidad con la Ley;\nXXXIV. Admitir y resolver los recursos de inconformidad que se interpongan con motivo de la aplicación de la presente Ley, en los términos de la Ley de Procedimiento Administrativo;\nXXXV. Expedir las copias certificadas y proporcionar la información que le sea solicitada en los términos de esta Ley;\n\nXXXVI. Interpretar y aplicar para efectos administrativos las disposiciones de esta Ley, así como las de los programas, emitiendo para tal efecto los dictámenes, circulares y recomendaciones necesarios, siempre y cuando no contravenga lo dispuesto en los ordenamientos citados;\nXXXVII. Elaborar, publicar y aplicar, en el ámbito de las atribuciones del Distrito Federal y con la participación que corresponda a las demás autoridades competentes, los programas y medidas para prevenir, controlar y minimizar las contingencias ambientales o emergencias ecológicas;\nXXXVIII. Establecer y actualizar el registro de emisiones y transferencia de contaminantes, así como el registro de las fuentes fijas de la competencia del Distrito Federal y el registro de descargas de aguas residuales que se viertan en los sistemas de drenaje y alcantarillado o a cuerpos receptores de la competencia del Distrito Federal.\nLa Secretaría debe integrar el registro de emisiones y transferencia de contaminantes al aire, agua, suelo y subsuelo, materiales, y residuos de su competencia, así como de aquellas sustancias que determine la autoridad correspondiente, cuya información se integrará con los datos e información contenida en las autorizaciones, cédulas, informes, reportes, licencias, permisos, y concesiones en materia ambiental que se tramiten ante la Secretaría o autoridades competentes del Distrito Federal y sus demarcaciones territoriales.\nLas personas físicas y morales responsables de fuentes contaminantes, están obligadas a proporcionar la información, datos y documentos necesarios para la integración del registro, mismo que será integrado con datos desagregados por sustancia y fuente, anexa nombre y dirección de los establecimientos sujetos a registro.\nLa información registrada será pública y tendrá efectos declarativos. La Secretaría permitirá el acceso a dicha información en los términos de esta Ley y demás disposiciones jurídicas aplicables y la difundirá de manera preactiva.\nXXXIX. Establecer y operar de manera directa, o indirectamente a través de autorización, el sistema de monitoreo de la contaminación ambiental, así como los sistemas de verificación de fuentes de competencia local, y determinar las tarifas máximas aplicables por concepto de dichas verificaciones;\nXL. Promover el uso de fuentes de energías alternas, de igual forma que sistemas y equipos para prevenir o minimizar las emisiones contaminantes en los vehículos en los que se preste el\n\nservicio público local de transporte de pasajeros o carga en el Distrito Federal, así como fomentar su uso en los demás automotores.\nEn concordancia con lo establecido en el artículo 10 fracción VI de la presente Ley, referente al servicio de alumbrado público, supervisar el cumplimiento de la citada disposición, así como, realizar las pruebas suficientes a los sistemas de ahorro de energía de tecnologías existentes, nuevas ó tecnologías que permitan el aprovechamiento de energía solar, para verificar que generen un aprovechamiento sustentable de la energía.\nXLI. Restringir y sujetar a horarios nocturnos, el tránsito y las maniobras en la vía pública de los vehículos de carga, en coordinación con las autoridades correspondientes;\nXLII. Prevenir o controlar la contaminación visual, así como la originada por ruido, vibraciones, energía térmica, lumínica, olores, vapores o cualquier otro tipo de actividad que pueda ocasionar daños a la salud de personas expuestas así como a la población, al ambiente o los elementos naturales, en fuentes de competencia del Distrito Federal;\nXLIII. Regular, prevenir y controlar las actividades ambientales riesgosas no reservadas a la\nFederación;\nXLIV. Promover el establecimiento y la aplicación de programas de educación ambiental y capacitación ecológica;\nXLIV Bis. Diseñar e implementar programas, acciones, talleres y cursos de educación ambiental dirigidos a la ciudadanía para concientizar su importancia para la sostenibilidad de los ecosistemas, así como para la resignificación y desmitificación de las especies de polinizadores.\nFracción añadida y publicada en la GOCDMX el 04 de mayo de 2023\nXLV. Regular y determinar la restauración ambiental de las áreas que hayan sido objeto de explotación de minerales u otros depósitos del subsuelo;\nXLVI. Verificar el cumplimiento de las Normas Oficiales Mexicanas y de las normas ambientales para el Distrito Federal; y\n\nXLVII. Crear y regular el Sistema de Certificación y Acreditación Ambiental, que tendrá por objeto determinar la conformidad sobre el cumplimiento de la normatividad ambiental, así como los esfuerzos adicionales de las personas a favor del medio ambiente;\nXLVIII. Administrar, coordinar y supervisar la operación y funcionamiento de los zoológicos y unidades de manejo de vida silvestre a cargo de la Secretaría, en términos de la legislación aplicable, como centros de recreación y esparcimiento para la población y la exhibición de flora y fauna silvestres con fines de educación y conservación;\nXLIX. Celebrar actos administrativos con terceros sobre los espacios e infraestructura que confieran su uso, aprovechamiento y administración de las áreas naturales protegidas, áreas de valor ambiental, zoológicos y unidades de manejo de vida silvestre a cargo de la Secretaría, en los términos de lo que establecen: el Programa General de Ordenamiento Ecológico Territorial del Distrito Federal, General de Desarrollo Urbano y Programa de Áreas Naturales Protegidas, así como demás normatividad aplicable, vigilando el cumplimiento de las obligaciones de los usuarios;\nL. Recibir y administrar los ingresos que se perciban por el uso y aprovechamiento de las áreas naturales protegidas, áreas de valor ambiental, zoológicos y unidades de manejo de vida silvestre a cargo de la Secretaría y, de conformidad con los ordenamiento jurídicos correspondientes, recaudarlos, recibirlos, administrarlos y comprobarlos con el carácter de ingresos de aplicación automática de recursos, aplicándolos para proyectos y programas de educación, conservación y mantenimiento;\nLI. Formular y conducir la política del Distrito Federal en materia de uso y aprovechamiento sustentable del agua;\nLII. Solicitar a las Delegaciones el Inventario de áreas verdes de su competencia, así como de las especies de flora y fauna silvestres presentes en las mismas, correspondiente a su demarcación territorial; y\nLIII. Las demás que le confieren esta y otras Leyes, así como las que se deriven de los instrumentos de coordinación celebrados y que se celebren.\nARTÍCULO 10.- Corresponde a cada una de las demarcaciones territoriales de la Ciudad de México:\n\nI. Proponer y opinar, según el caso, respecto del establecimiento de áreas de valor ambiental, áreas verdes en suelo urbano y áreas naturales protegidas dentro de su demarcación territorial, y participar en su vigilancia;\nII. Celebrar convenios con el Gobierno del Distrito Federal para la administración y preservación de las áreas naturales protegidas, los recursos naturales y la biodiversidad;\nIII. Promover la participación ciudadana en materia ambiental individual, colectiva o a través de los órganos de representación ciudadana e instrumentos de participación ciudadana.\nIV. Implementar acciones de conservación, restauración y vigilancia del equilibrio ecológico, así como la protección al ambiente e impulsar acciones orientadas a la construcción de resiliencia desde las demarcaciones territoriales;\nV. Difundir los programas y estrategias relacionadas con el equilibrio ecológico, la protección al ambiente y la contingencia o emergencia ambiental;\nVI. Establecer de forma gradual en el total de mobiliario destinado al servicio de alumbrado público de su demarcación, sistemas de ahorro de energía con tecnologías existentes ó nuevas que permitan el aprovechamiento de energía solar.\nPara tal efecto, las delegaciones deberán destinar, en la medida de sus posibilidades, una parte de su presupuesto para dar exacto cumplimiento a lo anterior. La Secretaría en el ámbito de sus atribuciones, supervisará y verificará que las demarcaciones cumplan dicha disposición.\nVII. Aplicar las sanciones administrativas, medidas correctivas y de seguridad correspondiente por infracciones a esta Ley y sus reglamentos; así como iniciar las acciones correspondientes ante las autoridades competentes, en contra de los funcionarios o personas que inciten o propicien invasiones a áreas verdes de suelo urbano y al suelo de conservación. La cual, ante un inminente daño ambiental podrá aplicar medidas precautorias para garantizar la protección de los derechos.\nVIII.- Las Delegaciones deberán etiquetar un porcentaje de su presupuesto anual que garantice el mantenimiento, la protección, la preservación, la vigilancia de las áreas verdes y barrancas de su demarcación.\n\nLas Delegaciones que tengan un porcentaje mayor de 9 metros cuadrados de área verde por habitante, no deberán permitir por ningún motivo su disminución.\nLas Delegaciones que no cuenten con 9 metros cuadrados de área verde por habitante, deberán incrementarlo buscando alcanzar este objetivo con alternativas para la creación de nuevas áreas verdes como son: azoteas verdes, barrancas, retiro de asfalto innecesario en explanadas, camellones, áreas verdes verticales y jardineras en calles secundarias.\nIX. Elaborar campañas de difusión para informar a los habitantes de su demarcación territorial sobre el tema de cambio climático y la importancia del cuidado al medio ambiente.\nXI. Integrar el Inventario de áreas verdes de su competencia, así como de las especies de flora y fauna silvestres presentes en las mismas, correspondiente a su demarcación territorial;\nXII. Formular, ejecutar y evaluar el programa ambiental delegacional, bajo los objetivos y lineamientos del Programa Sectorial Ambiental;\nXIII. Proponer a la Secretaría las modificaciones en el Programa General de Ordenamiento\nEcológico del Distrito Federal.\nXIV. En coordinación con la Secretaría, crear Jardines Polinizadores dentro de su demarcación territorial administrados en el ámbito de su competencia, así como promover su creación en los ámbitos público, privado y social, a fin de contribuir a la conservación de la biodiversidad y la resiliencia de los ecosistemas.\nPara tal efecto, las demarcaciones territoriales procurarán destinar al menos el uno por ciento del presupuesto total asignado al rubro de medio ambiente, cambio climático y bienestar animal.\nFracción añadida y publicada en la GOCDMX el 04 de mayo de 2023\nXV. Diseñar e implementar programas, acciones, talleres y cursos de educación ambiental dentro de su demarcación territorial, dirigidos a la ciudadanía para concientizar y resignificar a los polinizadores y su importancia para la sostenibilidad de los ecosistemas.\nPara tal efecto, las demarcaciones territoriales procurarán destinar al menos el cero punto cinco por ciento del presupuesto total asignado al rubro de medio ambiente, cambio climático y bienestar animal.\nFracción añadida y publicada en la GOCDMX el 04 de mayo de 2023\n\nARTÍCULO 11.- Se establecerá la Procuraduría Ambiental y del Ordenamiento Territorial de la Ciudad de\nMéxico, para la protección, defensa y restauración del medio ambiente y del desarrollo urbano; así como para instaurar mecanismos, instancias y procedimientos administrativos que procuren el cumplimiento de tales fines, en los términos de las disposiciones de la presente Ley y de la Ley de Desarrollo Urbano del\nDistrito Federal.\nPárrafo modificado y publicado en la GOCDMX el 24 de Marzo de 2023\nLa Ley Orgánica respectiva, dispondrá las atribuciones y estructura de dicha Procuraduría.\nARTÍCULO 12.- La Procuraduría estará a cargo de una o un Procurador, que será nombrado por la persona titular de la Jefatura de Gobierno y ratificado por el Congreso de la Ciudad de México por mayoría calificada de votos. Durará en su encargo cuatro años y podrá ser ratificado por un período adicional.\nReforma publicada en la GOCDMX el 24 de Marzo de 2023\nARTÍCULO 13.- - Las autoridades de la Ciudad de México están obligadas a:\nI. Promover la participación ciudadana en la gestión ambiental;\nII. Fomentar la protección al ambiente y la salud;\nIII. Coordinar acciones que impulsen la construcción de resiliencia en materia de la presente Ley;\nIV. Fomentar y hacer un uso eficiente de los recursos naturales; y\nV. En caso de inducir cualquier actividad que afecte el ambiente y la disponibilidad futura de los recursos naturales, reparar los daños causados.\nARTÍCULO 14.- Las autoridades del Distrito Federal, promoverán y aplicarán acciones correctivas para restaurar el ambiente en forma coordinada, concertada, y corresponsable con la sociedad en general, así como con las dependencias federales competentes, en el ámbito de sus respectivas atribuciones.\nARTÍCULO 15.- El Distrito Federal participará en los términos establecidos por la Constitución Política de los\nEstados Unidos Mexicanos y el Estatuto de Gobierno del Distrito Federal, en la planeación y ejecución de acciones coordinadas con la Federación, entidades federativas y municipios conurbados, en materias de\n\nprotección al ambiente, conservación y restauración del equilibrio ecológico, mejoramiento y desarrollo sustentable, para lo cual se podrán suscribir convenios para la integración de una Comisión en la que concurran y participen con apego a sus leyes\nARTÍCULO 16.- La Comisión será constituida por acuerdo conjunto de las entidades participantes. En el instrumento de creación se determinará la forma de integración, estructura y funciones.\nARTÍCULO 17.- Los acuerdos y convenios de coordinación y colaboración administrativa que se celebren por el Jefe de Gobierno del Distrito Federal deberán ajustarse, además de las bases a que se refiere la Ley\nGeneral, a lo siguiente:\nI. Deberán ser congruentes con las disposiciones de la política ambiental del Distrito Federal;\nII. Procurar que en los mismos se establezcan condiciones que faciliten el proceso de descentralización de funciones y recursos financieros a las dependencias y entidades de la\nAdministración Pública del Distrito Federal, involucradas en las acciones de prevención y control del ambiente; y\nIII. Las demás que tenga por objeto dar cumplimiento a lo dispuesto por la presente Ley.\nTÍTULO TERCERO\nDE LA POLÍTICA DE DESARROLLO SUSTENTABLE\nCAPÍTULO I\nDE LOS PRINCIPIOS E INSTRUMENTOS DE LA POLÍTICA DE\nDESARROLLO SUSTENTABLE\nARTÍCULO 18.- Para la formulación y conducción de la política ambiental y aplicación de los instrumentos previstos en esta Ley, las dependencias y entidades de la Administración Pública Local, así como, los particulares observarán los principios y lineamientos siguientes:\nI. La conservación y el manejo sustentable de los recursos naturales del Distrito Federal prevalecerán sobre cualquier otro tipo de uso y destino que se pretenda asignar;\n\nII. Las autoridades así como la sociedad, deben asumir en corresponsabilidad la protección del ambiente, así como la conservación, restauración y manejo de los ecosistemas y el mejoramiento de la calidad del aire, del agua y del suelo del Distrito Federal, con el fin de proteger la salud humana y elevar el nivel de vida de su población;\nIII. En el territorio del Distrito Federal, toda persona tiene derecho a gozar de un ambiente adecuado para su desarrollo, salud y bienestar. Esta Ley definirá los mecanismos tendientes para hacer efectivo tal derecho;\nIV. Es deber de las autoridades ambientales del Distrito Federal garantizar el acceso de los ciudadanos a la información sobre el medio ambiente y la participación corresponsable de la sociedad en general, en las materias que regula la presente Ley;\nV. Los ecosistemas y sus elementos deben ser aprovechados de manera que se asegure una productividad óptima y sostenida, compatible con su equilibrio e integridad;\nVI. Quien realice obras o actividades que afecten o puedan afectar el ambiente, está obligado a prevenir, minimizar o restaurar, y en su caso, reparar los daños que cause, de conformidad con las reglas que establece esta Ley;\nVII. Los recursos naturales no renovables deben utilizarse de modo que se evite el peligro de su agotamiento y la generación de efectos ecológicos adversos;\nVIII. Cualquier programa, proyecto o acción que se desarrolle en el Distrito Federal deberá garantizar el mantenimiento y conservación de la biodiversidad, así como de la continuidad e integridad de los ecosistemas;\nIX. Se deberá propiciar la continuidad de los procesos ecológicos en el Distrito Federal; y\nX. Es responsabilidad de la Secretaría fomentar e incentivar el mantenimiento y mejoramiento de la calidad de los recursos naturales y servicios ambientales que proporcionan a la población.\nXI. Es responsabilidad de toda persona en la Ciudad de México respetar, mantener y cuidar de los Jardines Polinizadores, para contribuir a la conservación de la biodiversidad y la resiliencia de los ecosistemas.\nFracción añadida y publicada en la GOCDMX el 04 de mayo de 2023\n\nARTÍCULO 19.- La política de desarrollo sustentable de la Ciudad de México será elaborada y ejecutada conforme a los siguientes instrumentos:\nI. La participación ciudadana;\nII. La planeación;\nIII. El ordenamiento ecológico;\nIV. Las normas ambientales para el Distrito Federal;\nV. La evaluación del impacto ambiental;\nVI. La Manifestación Ambiental Única;\nReforma publicada en la GOCDMX el 27 de febrero de 2023\nVII. Los permisos y autorizaciones a que se refiere esta ley;\nVIII. La auditoría ambiental;\nIX. El sistema de certificación y el certificado de reducción de emisiones contaminantes;\nX. Los convenios de concertación;\nXI. Los estímulos establecidos por esta u otras leyes;\nXI Bis. Todos aquellos instrumentos de planeación que hacen referencia a la construcción de resiliencia para la Ciudad de México, que promuevan la prevención y reducción de riesgos de cualquier tipo;\nXII. La educación y la investigación ambiental;\nXIII. La información sobre medio ambiente; y\nXIV. El fondo ambiental público.\n\nCAPÍTULO II\nPARTICIPACIÓN CIUDADANA\nARTÍCULO 20.- Los habitantes del Distrito Federal tienen derecho a disfrutar de un ambiente sano.\nTodo habitante del Distrito Federal tiene la potestad de exigir el respeto a su derecho y a los recursos naturales de la Tierra.\nLa participación ciudadana podrá ser individual, colectiva o a través del órgano de representación ciudadana electo en cada colonia o pueblo, así como de las organizaciones sociales, civiles y empresariales e instituciones académicas, en los términos del artículo 171 fracción IV de la Ley de Participación\nCiudadana, y serán los medios para promover y fomentar los derechos en materia ambiental y la utilización de los instrumentos de participación ciudadana, que garantizarán la participación corresponsable de la ciudadanía a fin de que se conozca e informe de la elaboración en los programas de protección ambiental, desarrollo sustentable y educación en materia ambiental a la sociedad.\nARTÍCULO 21.- La Secretaría deberá promover y garantizar la participación corresponsable de la ciudadanía, para la toma de decisiones mediante los mecanismos establecidos por la ley de participación ciudadana, en los programas de desarrollo sustentable.\nLa política ambiental deberá garantizar los mecanismos de participación social más efectivos en la toma de decisiones y en la elaboración de los programas de protección ambiental y de educación en la materia.\nARTÍCULO 22.- Para los efectos del artículo anterior, el Jefe de Gobierno de la Ciudad de México y la\nSecretaría:\nI. Convocarán, en el ámbito del sistema local de planeación democrática, a todos los sectores interesados en la materia ambiental, para que manifiesten su opinión y propuestas;\nII. Celebrarán convenios con personas interesadas, ejidos y comunidades agrarias, organizaciones sociales e instituciones, para el establecimiento, administración y manejo de áreas naturales protegidas de jurisdicción de la Ciudad de México, el aprovechamiento sustentable de los recursos naturales; las acciones de protección al ambiente; la realización de\n\nestudios e investigación en la materia; el impulso a la construcción de resiliencia; y la retribución por la conservación de servicios ambientales;\nIII. Celebrarán convenios con los medios de comunicación masiva para la difusión, divulgación,\nInformación y promoción de acciones de conservación del equilibrio ecológico, de protección al ambiente y de educación;\nIV. Promoverán el establecimiento de reconocimientos a los esfuerzos más destacados de la sociedad para conservar y restaurar el equilibrio ecológico y proteger el ambiente;\nV. Impulsarán el desarrollo y fortalecimiento de la cultura ambiental, a través de la realización de acciones conjuntas con la comunidad para la conservación y restauración del ambiente, el aprovechamiento racional de los recursos naturales y el correcto manejo de los residuos;\nVI. Fomentar, desarrollar y difundir las experiencias y prácticas de ciudadanos, para la conservación y aprovechamiento sustentable de los recursos naturales y del ambiente; y\nVII. Coordinarán y promoverán acciones e inversiones con los sectores sociales y privados, con instituciones académicas, grupos, organizaciones sociales, y demás personas interesadas, para la conservación y restauración del equilibrio ecológico y la protección al ambiente.\nARTÍCULO 23.- Son obligaciones de las personas que se encuentran en la Ciudad de México:\nI. Defender y respetar los recursos naturales que componen a la Tierra;\nI.Bis. Utilizar los recursos naturales de modo racional y sustentable;\nFracción añadida y publicada en la GOCDMX el 28 de noviembre de 2023\nII. Prevenir y evitar daños al ambiente y, en su caso, reparar los daños que hubieran causado;\nIII. Promover la armonía en la Tierra en todos los ámbitos de su relación con las personas y el resto de la naturaleza en los sistemas de vida;\nIV. Participar de forma activa, personal o colectivamente, en la generación de propuestas orientadas al respeto y la defensa de los recursos naturales de la Tierra;\n\nV. Asumir prácticas de producción y hábitos de consumo sustentables y en armonía con los recursos naturales de la Tierra;\nFracción modificada y publicada en la GOCDMX el 28 de noviembre de 2023\nVI. Minimizar los daños al ambiente que no puedan prevenir o evitar, en cuyo caso estarán obligadas a reparar los daños causados;\nVII. Ayudar en la medida de lo posible a establecer las condiciones que permitan garantizar la subsistencia y regeneración del ambiente y los recursos naturales;\nVIII. Realizar todas sus actividades cotidianas bajo los criterios de ahorro y reuso de agua, conservación del ambiente rural y urbano, prevención y control de la contaminación de aire, agua y suelo, y protección de la flora y fauna en el Distrito Federal;\nVIII Bis. Coadyuvar con las autoridades ambientales en las acciones de construcción de resiliencia que implementen;\nVIII Ter. Respetar la vida e integridad de los animales como seres sintientes, lo cual no excluye implementar las medidas de manejo y prevención emitidas por la Secretaría en el caso de especies exóticas y ferales.\nFracción añadida y publicada en la GOCDMX el 28 de noviembre de 2023\nIX. Asegurar el uso y aprovechamiento sustentable de los componentes de la Tierra;\nFracción modificada y publicada en la GOCDMX el 28 de noviembre de 2023\nX. Denunciar todo acto que atente contra los recursos naturales de la Tierra, sus sistemas de vida y/o sus componentes; y\nFracción modificada y publicada en la GOCDMX el 28 de noviembre de 2023\nXI. Fomentar el respeto por las especies animales y vegetales locales, endémicas, en riesgo y aquellas cuya presencia sea relevante para el equilibrio del ecosistema, como los polinizadores, carnívoros, entre otros.\nFracción añadida y publicada en la GOCDMX el 28 de noviembre de 2023\n\nCAPÍTULO III\nPLANEACIÓN DEL DESARROLLO SUSTENTABLE\nARTÍCULO 24.- En la planeación del desarrollo del Distrito Federal se deberá incluir la política de desarrollo sustentable, desarrollo rural y el ordenamiento ecológico. En la planeación y ejecución de acciones a cargo de las dependencias y entidades de la Administración Pública del Distrito Federal, se observarán los lineamientos, criterios e instrumentos de política ambiental, el Programa General de Desarrollo del Distrito\nFederal, el Programa Sectorial Ambiental y los programas correspondientes.\nEn concordancia con lo que dispone el artículo 16 de la Ley de Desarrollo Urbano del Distrito Federal, la planeación del Desarrollo sustentable y el ordenamiento ecológico del territorio, serán junto con el\nPrograma General de Desarrollo Urbano, y demás programas de Desarrollo Urbano, el sustento territorial para la planeación económica y social para el Distrito Federal, de conformidad con lo señalado en la Ley de\nPlaneación del Desarrollo del Distrito Federal.\nARTÍCULO 25.- La planeación ambiental se basará en la expedición de programas que favorezcan el conocimiento y la modificación de los ciclos y sistemas ambientales en beneficio de la salud y calidad de vida de la población, compatibilizando el desarrollo económico y la protección de sus recursos naturales fundamentales.\nARTÍCULO 26.- El Jefe de Gobierno del Distrito Federal formulará y evaluará, en coordinación con las diferentes instancias involucradas en las acciones de protección ambiental, el Programa Sectorial\nAmbiental, el cual contendrá las estrategias y acciones prioritarias para la ejecución de la política ambiental del Distrito Federal e integrará las acciones de los diferentes sectores, de conformidad con la Ley de\nPlaneación.\nARTÍCULO 27.- El programa sectorial ambiental se evaluará anualmente por la Secretaría y presentará un informe ante la Asamblea, de los avances del mismo.\nARTÍCULO 27 Bis. En la Ciudad de México los Programas de Desarrollo Urbano se elaborarán atendiendo, además de las disposiciones jurídicas aplicables, los siguientes criterios:\nPárrafo modificado y publicado en la GOCDMX el 28 de noviembre de 2023\nI. El cumplimiento y observancia del Programa General de Ordenamiento Ecológico del Distrito\nFederal;\n\nII. El cuidado de la proporción que debe existir entre las áreas verdes y las edificaciones destinadas a habitación, los servicios y en general otras actividades, siendo responsabilidad de las autoridades y de los habitantes del Distrito Federal la forestación y reforestación;\nIII. La preservación de las áreas rurales, de uso agropecuario y forestal, y en general de áreas existentes en suelo de conservación, evitando su fraccionamiento para fines de desarrollo urbano;\nIV. La integración de inmuebles de alto valor histórico, arquitectónico y cultural con áreas verdes y áreas de valor ambiental;\nV. La compatibilidad para crear zonas habitacionales entorno a centros industriales; y\nVI. La preservación de las áreas verdes existentes, evitando ocuparlas con obras o instalaciones que se contrapongan a su función, y\nFracción modificada y publicada en la GOCDMX el 28 de noviembre de 2023\nVII. Las determinaciones que establece el artículo 88 Bis 6 de la presente Ley.\nFracción añadida y publicada en la GOCDMX el 28 de noviembre de 2023\nCAPÍTULO IV\nORDENAMIENTO ECOLÓGICO\nArtículo 28. El ordenamiento ecológico es un instrumento de política ambiental que tiene por objeto definir y regular los usos del suelo en el Suelo de Conservación, así como establecer los lineamientos, estrategias y criterios ambientales con los que deberán llevarse a cabo las actividades productivas y de conservación, para hacer compatible el mantenimiento de los recursos naturales, servicios ambientales y la conservación de la biodiversidad con el desarrollo regional. La observancia de este instrumento es obligatoria en el\nDistrito Federal y servirá de base para la elaboración de programas, proyectos, obras y actividades de desarrollo que se pretendan ejecutar.\nARTÍCULO 29.- En la formulación de los programas de ordenamiento ecológico se deberá n considerar los siguientes criterios:\nI. La naturaleza y características de los ecosistemas existentes en el territorio del Distrito Federal;\n\nII. La vocación de cada zona, en función de sus elementos naturales, la distribución de la población y las actividades económicas predominantes;\nIII. La aptitud del suelo sobre la base de una regionalización ecológica;\nIV. Los desequilibrios existentes en los ecosistemas por efecto de los asentamientos humanos, de las actividades económicas o de otras actividades humanas o fenómenos naturales;\nV. El equilibrio que debe existir entre los asentamientos humanos y sus condiciones ambientales;\nVI. El impacto ambiental de nuevos asentamientos humanos, vías de comunicación y demás obras y actividades;\nVII. La evaluación de las actividades productivas predominantes en relación con su impacto ambiental, la distribución de la población humana y los recursos naturales en una zona o región;\ny\nVIII. La obligatoriedad de la regulación ambiental derivada del ordenamiento ecológico tendrá prioridad sobre otros aprovechamientos que no sean compatibles con los principios del desarrollo sustentable, integrándose a los Programas de Desarrollo Urbano expedidos de conformidad con la Ley de Desarrollo Urbano del Distrito Federal.\nEl ordenamiento ecológico incluido en los programas de desarrollo urbano será obligatorio en materia de usos y destinos en suelo de conservación, de criterios ambientales aplicables a los usos y destinos del suelo de los Programas de Desarrollo Urbano en los asentamientos humanos en suelo de conservación, en el manejo de los recursos naturales y realización de actividades que afecten al ambiente; los cuales deberán contener los lineamientos y estrategias ecológicas para la conservación, protección, restauración y aprovechamiento sustentable de los recursos naturales, así como para la localización de actividades productivas y cuando se pretenda la ampliación de los poblados rurales y del suelo urbano o nuevos asentamientos humanos.\nARTÍCULO 30.- Los programas de ordenamiento ecológico del territorio en el Distrito Federal señalarán los mecanismos que proporcionen solución a problemas ambientales específicos y a la reducción de conflictos\n\na través del establecimiento de políticas ambientales, lineamientos, criterios ecológicos y construcción de consensos, con la participación de la sociedad en general.\nARTÍCULO 31.- La elaboración, aprobación e inscripción de los programas de ordenamiento ecológico así como sus modificaciones, se sujetará al siguiente procedimiento:\nI. La Secretaría publicará el aviso del inicio del proceso de elaboración del proyecto de programas o de sus modificaciones en la Gaceta Oficial y en un diario de mayor circulación en el Distrito\nFederal, por una vez;\nII. La Secretaría elaborará los proyectos de programas o sus modificaciones y en coordinación con la Secretaría de Desarrollo Urbano y Vivienda y de Desarrollo Rural y Equidad para las\nComunidades, definirán los elementos de articulación de dichos programas con los de desarrollo urbano para asentamientos humanos en suelo de conservación;\nIII. Una vez que haya sido integrado el proyecto, la Secretaría publicará, por una vez, el aviso de que se inicia la consulta pública, en la Gaceta Oficial y en un diario de mayor circulación, de acuerdo con las siguientes bases:\na) En las publicaciones se indicará los plazos y mecanismos para garantizar la participación ciudadana, así como los lugares y las fechas de las audiencias públicas que se llevarán a cabo en ese periodo;\nb) En la audiencia o audiencias los interesados pueden presentar por escrito los planteamientos que consideren respecto del proyecto del programa o de sus modificaciones;\nc) Los planteamientos que hayan sido formulados por escrito deberán dictaminarse fundada y motivadamente por escrito; y d) El dictamen a que se refiere el inciso anterior estará disponible para la consulta de los interesados en las oficinas de la Secretaría;\nIV. Una vez que termine el plazo de consulta pública la Secretaría incorporará al proyecto las observaciones que considere procedentes;\nV. La Secretaría, una vez concluida la etapa anterior, remitirá el proyecto al Jefe de Gobierno del\nDistrito Federal;\n\nVI. El Jefe de Gobierno del Distrito Federal, incorporará, en su caso, las observaciones que considere pertinentes y remitirá el proyecto con carácter de iniciativa a la Asamblea Legislativa para su análisis y dictamen;\nVII. Una vez que la Asamblea apruebe el programa lo enviará al Jefe de Gobierno del Distrito\nFederal, para su promulgación en los términos del inciso b) fracción II, base segunda del artículo\n122 constitucional.\nARTÍCULO 32.- Una vez publicado el programa se inscribirá en el Registro de los Planes y Programas de\nDesarrollo Urbano y en el Registro Público de la Propiedad.\nEl programa de ordenamiento ecológico surtirá sus efectos a partir del día siguiente a su publicación en la\nGaceta Oficial.\nARTÍCULO 33.- Los programas de ordenamiento ecológico deberá ser revisado en forma permanente, y en su caso, actualizado cada tres años.\nARTÍCULO 34.- Los Programas de ordenamiento ecológico del territorio del Distrito Federal se harán del conocimiento de las autoridades federales y se promoverá su observancia en el otorgamiento de permisos y autorizaciones de proyectos de obras y actividades así como en el aprovechamiento de recursos naturales de competencia federal.\nARTÍCULO 35.- Los Programas de ordenamiento ecológico del territorio serán de observancia obligatoria en:\nI. Las autorizaciones en materia de impacto ambiental, y en general en los proyectos y ejecución de obras, así como en el establecimiento de actividades productivas;\nII. El aprovechamiento de los recursos naturales en el Distrito Federal;\nIII. La creación de áreas naturales protegidas de competencia del Distrito Federal;\nIV. Los programas de desarrollo urbano; y\nV. La elaboración de políticas y programas en materia de promoción y fomento agrícola, agropecuario, turismo alternativo y programas del sector rural.\n\nCAPÍTULO V\nNORMAS AMBIENTALES PARA EL DISTRITO FEDERAL\nARTÍCULO 36.- La Secretaría, en el ámbito de su competencia emitirá normas ambientales las cuales tendrán por objeto establecer:\nI. Los requisitos o especificaciones, condiciones, parámetros y límites permisibles en el desarrollo de una actividad humana que pudiera afectar la salud, la conservación del medio ambiente, la protección ecológica o provocar daños al ambiente y los recursos naturales;\nII. Los requisitos, condiciones o límites permisibles en la operación, recolección, transporte, almacenamiento, reciclaje, tratamiento, industrialización o disposición final de residuos sólidos;\nIII. Los requisitos, condiciones, parámetros y límites permisibles para el tratamiento y aprovechamiento de aguas residuales provenientes de actividades domésticas, industriales, comerciales, agrícolas, acuícolas, pecuarias o de cualquier otra actividad humana y que, por el uso recibido, se les hayan incorporado contaminantes;\nIV. Las condiciones de seguridad, requisitos y limitaciones en el manejo de residuos sólidos que presenten riesgo para el ser humano, para el equilibrio ecológico o para el ambiente:\nV. Los requisitos, condiciones, parámetros y límites permisibles para la protección, el manejo, el aprovechamiento y la restauración de los recursos naturales en suelo de conservación;\nVI. Los requisitos, condiciones, parámetros y límites permisibles para la protección, el manejo, el aprovechamiento y la restauración de los recursos naturales en las Áreas Naturales Protegidas de competencia del Distrito Federal; y\nVII. Los requisitos y condiciones para la incorporación voluntaria de personas físicas y morales a los programas de prácticas de producción sustentable, así como los procesos para su certificación.\nARTÍCULO 37.- Las normas ambientales para el Distrito Federal podrán determinar requisitos, condiciones, parámetros y límites más estrictos que los previstos en las Normas Oficiales Mexicanas y deberán referirse a materias que sean de competencia local.\n\nARTÍCULO 38.- En la formulación de las normas ambientales para el Distrito Federal deberá considerarse que el cumplimiento de sus previsiones se realice de conformidad con las características de cada proceso productivo o actividad sujeta a regulación.\nARTÍCULO 39.- La sociedad, las instituciones de investigación y educación superior, las organizaciones empresariales, así como las entidades y dependencias de la Administración Pública, podrán proponer la creación de las normas ambientales para el Distrito Federal, en los términos señalados en el reglamento que al efecto se expida.\nARTÍCULO 40. La elaboración, aprobación y expedición de las normas ambientales para el Distrito Federal, así como sus modificaciones, se sujetarán al siguiente procedimiento:\nI. La Secretaría creará un Comité de Normalización Ambiental para coordinar el proceso de emisión de normas ambientales;\nII. El Comité antes mencionado convocará a la conformación de grupos de trabajo que elaboren y opinen sobre los proyectos, a través de medios masivos de difusión por lo menos con quince días naturales de antelación;\nIII. La Secretaría publicará el proyecto de norma o de su modificación en la Gaceta Oficial, a efecto de que los interesados presenten sus comentarios dentro de los treinta días naturales siguientes;\nIV. Al término del plazo a que se refiere la fracción anterior, la Secretaría estudiará los comentarios recibidos y, en su caso, procederá a modificar el proyecto de norma ambiental y emitir la norma definitiva;\nV. Se ordenará la publicación en la Gaceta Oficial de las respuestas a los comentarios recibidos así como de las modificaciones al proyecto, cuando menos 15 días naturales antes de la publicación de la norma ambiental para el Distrito Federal.\nLa Secretaría deberá responder por escrito a los interesados las razones fundadas por las cuales los comentarios a que se refiere la fracción III de este artículo no fueron tomados en consideración dentro del proyecto de norma ambiental, pudiendo los afectados interponer el recurso de inconformidad a que se refiere esta Ley en contra de la respuesta que emita la\nSecretaria a los comentarios recibidos; y\n\nVI. Transcurridos los plazos anteriores, la Secretaría publicará las normas ambientales para el\nDistrito Federal o sus modificaciones en la Gaceta Oficial.\nARTÍCULO 41.- Una vez publicada una norma ambiental para el Distrito Federal en la Gaceta Oficial, será obligatoria. Las normas ambientales para el Distrito Federal señalarán su ámbito de validez, vigencia y gradualidad en su aplicación.\nARTÍCULO 42.- En casos de emergencia que pongan en riesgo la integridad de las personas o del ambiente, la Secretaría podrá publicar en la Gaceta Oficial normas ambientales del Distrito Federal sin sujetarse al procedimiento establecido en el artículo anterior. Estas normas tendrán una vigencia máxima de seis meses. En ningún caso se podrá expedir más de dos veces consecutivas la misma norma en los términos de este artículo.\nARTÍCULO 43.- La Secretaría promoverá la creación de un sistema de certificación para el Distrito Federal, con el propósito de establecer parámetros de calidad ambiental en:\nI. Capacitación y formación de especialistas e instructores;\nII. La elaboración de bienes y productos;\nIII. Desarrollo tecnológico y de ecotecnias; y\nIV. Procesos productivos y de consumo\nCAPÍTULO VI\nEVALUACIÓN DE IMPACTO AMBIENTAL\nARTÍCULO 44.- La evaluación de impacto ambiental es el procedimiento a través del cual la autoridad evalúa los efectos que sobre el ambiente y los recursos naturales pueden generar la realización de programas, obras y actividades de desarrollo dentro del territorio del Distrito Federal, a fin de evitar o reducir al mínimo efectos negativos sobre el ambiente, prevenir futuros daños al ambiente y propiciar el aprovechamiento sustentable de los recursos naturales.\n\nEl procedimiento de evaluación de impacto ambiental se inicia mediante la presentación del estudio de impacto ambiental en sus diferentes modalidades ante la Secretaría y concluye con la resolución ó dictamen que esta emita. La elaboración del estudio de impacto ambiental se sujetará a lo que establecen la presente Ley y su reglamento correspondiente a la materia.\nLas modalidades de los estudios de impacto ambiental son:\nI. Evaluación ambiental estratégica.\nII. Manifestación de impacto ambiental específica;\nIII. Manifestación de impacto ambiental general;\nIV. Informe preventivo;\nV. Estudio de riesgo ambiental; y\nVI. Declaratoria de cumplimiento ambiental.\nARTÍCULO 45.- En los casos de aquellas obras y actividades donde además de la autorización de impacto ambiental requiera la de impacto urbano, se estará a lo dispuesto en la presente Ley, en la Ley de Desarrollo\nUrbano del Distrito Federal y a l reglamento que sobre estas materias al efecto se emita.\nLa Secretaría y las Secretarías de Desarrollo Urbano y Vivienda y Desarrollo Rural y Equidad para las\nComunidades podrán interpretar y aplicar para efectos administrativos en la esfera de sus respectivas competencias, las disposiciones de esta Ley y de los programas de ordenamiento ecológico territorial, así como, de la Ley de Desarrollo Urbano del Distrito Federal, y de los Programas de Desarrollo Urbano, respectivamente, y del Reglamento al que se refiere el párrafo anterior, emitiendo para tal efecto, de manera conjunta los dictámenes, circulares y recomendaciones en materia de impacto urbano y ambiental.\nARTÍCULO 46.- Las personas físicas o morales interesadas en la realización de obras o actividades que impliquen o puedan implicar afectación del medio ambiente o generación de riesgos requieren evaluación de impacto ambiental y, en su caso, de riesgo previo a la realización de las mismas. Las obras y actividades que requieren autorización por encontrarse en el supuesto anterior, son las siguientes:\n\nI. Los programas que en general promuevan cambios de uso en el suelo de conservación o actividades económicas o prevean el aprovechamiento de los recursos naturales del Distrito\nFederal;\nII. Obras y actividades, o las solicitudes de cambio de uso del suelo que en los casos procedentes, pretendan realizarse en suelos de conservación;\nIII. Obras y actividades que pretendan realizarse en áreas de valor ambiental y áreas naturales protegidas de competencia del Distrito Federal;\nIV. Obras y actividades dentro de suelo urbano en los siguientes casos:\na) Las que colinden con áreas de valor ambiental, áreas naturales protegidas, suelo de conservación o con vegetación acuática;\nb) Nuevas actividades u obras de infraestructura, servicios o comerciales o sus ampliaciones, cuyos procesos requieran de medidas, sistemas o equipos especiales para no afectar los recursos naturales o para cumplir con las normas ambientales para el\nDistrito Federal; y c) Obras, actividades o cambios de uso de suelo que se pretendan realizar en predios con cobertura arbórea significativa o cuerpos de agua competencia del Distrito Federal.\nV. Obras y actividades para la extracción de materiales pétreos, cantera, tepetate, arcilla, y en general cualquier yacimiento; así como su regeneración ambiental;\nVI. Obras y actividades que afecten la vegetación y los suelos de escurrimientos superficiales, barrancas, cauces, canales y cuerpos de agua del Distrito Federal, y en general cualquier obra o actividad para la explotación de la capa vegetal; con excepción de los que sean de competencia federal.\nLos casos y modalidades para la presentación de los estudios de impacto ambiental señalados en el párrafo anterior se establecerán en el Reglamento correspondiente a la materia y, en su caso, se precisarán en los manuales de trámites y servicios, guías técnicas, formatos y acuerdos administrativos correspondientes;\nVII. Las obras y actividades que se establezcan en el programa de ordenamiento ecológico del territorio;\n\nVIII. Las obras y actividades de carácter público o privado, destinadas a la prestación de un servicio público;\nIX. Vías de comunicación de competencia del Distrito Federal;\nX. Zonas y parques industriales y centrales de abasto y comerciales;\nXI. Conjuntos habitacionales;\nXII. Actividades consideradas riesgosas en los términos de esta Ley;\nXIII. Las instalaciones para el manejo de residuos sólidos e industriales no peligrosos, en los términos del Titulo Quinto, Capitulo V de esta Ley;\nXIV. Aquellas obras y actividades que estando reservadas a la Federación, se descentralicen a favor del Distrito Federal;\nXV. Aquellas obras y actividades que no estando expresamente reservadas a la Federación en los términos de la Ley General, causen o puedan causar desequilibrios ecológicos, rebasen los límites y condiciones establecidos en las disposiciones jurídicas referidas a la conservación del equilibrio ecológico y la protección al ambiente;\nXVI. Obras de más de 10 mil metros cuadrados de construcción u obras nuevas en predios de más de cinco mil metros cuadrados para uso distinto al habitacional, para obras distintas a las mencionadas anteriormente, para la relotificación de predios y ampliaciones de construcciones que en su conjunto rebasen los parámetros señalados; y\nXVII. Construcción de estaciones de gas y gasolina.\nEl reglamento de la presente Ley y, en su caso, los acuerdos administrativos correspondientes precisarán, respecto del listado anterior, los casos y modalidades para la presentación de las manifestaciones de impacto ambiental y riesgo, así como la determinación de las obras o actividades que, no obstante estar previstas en los supuestos a que se refiere este artículo, por su ubicación, dimensiones, características o alcances no produzcan impactos ambientales significativos o no causen o puedan causar riesgos, y que por\n\nlo tanto no deban sujetarse al procedimiento de evaluación del impacto ambiental previsto en este ordenamiento.\nARTÍCULO 47.- Para obtener autorización en materia de impacto ambiental, los interesados, previamente al inicio de cualquier obra o actividad, deberán presentar ante la Secretaría, el estudio de impacto ambiental en la modalidad que corresponda, conforme a lo señalado en el artículo 44 de la presente Ley, el cual deberá contener, según corresponda por lo menos:\nI. Nombre, denominación o razón social, nacionalidad, domicilio para oír y recibir notificaciones, personas señaladas para tal efecto, teléfono y correo electrónico de quien pretenda llevar a cabo la obra o actividad objeto de la manifestación y nombre, denominación o razón social, nacionalidad, domicilio, teléfono y correo electrónico de la persona física o moral responsable de elaborar la manifestación de impacto ambiental, así como copia cotejada de la cédula profesional o certificación o acreditación en la materia ambiental y/o riesgo;\nII. Descripción de la obra o actividad proyectada, desde la etapa de selección del sitio para la ejecución de la obra o el desarrollo de la actividad, la superficie de terreno requerido, incluyendo la manifestación de las actividades previas realizadas en el predio,; el programa de construcción, montaje de instalaciones y operación correspondiente; el tipo de actividad, volúmenes de producción previstos, e inversiones necesarias para la ejecución del proyecto y monto destinado a la instrumentación de medidas de prevención, mitigación y compensación de impactos ambientales; la clase y cantidad de recursos naturales que habrán de aprovecharse, tanto en la etapa de construcción como en la operación de la obra o el desarrollo de la actividad, el programa para el manejo de residuos, tanto en la construcción y montaje como durante la operación o desarrollo de la actividad; y, en su caso el programa para el abandono de las obras o el cese de las actividades;\nIII. Aspectos generales del medio natural y socioeconómico del área donde pretenda desarrollarse la obra o actividad;\nIII bis.- Delimitación y justificación del área de influencia del proyecto;\nIV. Vinculación con las normas y regulaciones sobre uso del suelo en el área correspondiente;\n\nV. Identificación, descripción y evaluación de los impactos ambientales que ocasionaría la ejecución del proyecto o actividad, en sus distintas etapas determinando los indicadores ambientales del proyecto; y\nVI. Medidas de prevención y mitigación para los impactos ambientales identificados en cada una de las etapas, así como el escenario ambiental modificado.\nCuando se trate de actividades consideradas riesgosas en los términos de esta Ley, la manifestación deberá incluir el estudio de riesgo correspondiente, el cual será considerado al evaluarse el impacto ambiental. La evaluación de riesgo deberá incluir la identificación, jerarquización, análisis y evaluación de los riesgos ambientales y las medidas pertinentes.\nSi después de la presentación de un estudio de impacto ambiental se realizan modificaciones al proyecto de los programas, obras o actividades respectivas, los interesados deberán hacerlas del conocimiento de la\nSecretaría, a fin de que ésta, les notifique si es necesaria la presentación de información adicional para evaluar los efectos al ambiente que pudiesen ocasionar tales modificaciones, en los términos de lo dispuesto en esta Ley.\nArtículo 48. En las áreas naturales protegidas, áreas de valor ambiental y suelo de conservación, se requerirá de una manifestación de impacto ambiental en su modalidad específica, o general según corresponda para toda actividad, obra y operación pública o privada que se pretenda desarrollar, en términos de lo dispuesto en el Reglamento de Impacto Ambiental y Riesgo.\nARTÍCULO 49.- Una vez ingresada la solicitud de autorización de impacto y riesgo ambiental, así como sus anexos se considerará integrado el expediente y estará dispuesto para consulta del público.\nCon el objeto de agilizar y simplificar el procedimiento de evaluación y comprobar que la información sea la mínima suficiente, la Secretaría implementará un proceso de revisión previa, el cual consistirá en la aplicación de una lista de chequeo por parte del área encargada de la evaluación, del cual se determinará lo siguiente:\nI. El ingreso del trámite para su evaluación correspondiente, cuando no se detecte algún faltante de la lista de chequeo.\nII. Informar al promovente las omisiones o inconsistencias detectadas que debe subsanar, haciendo entrega de una copia de la lista de chequeo donde se indican los faltantes.\n\nEl interesado de la obra o actividad, al momento de ingresar la solicitud de impacto ambiental en sus diferentes modalidades, determinará en la carpeta de consulta para el público, la información que debe mantenerse en reserva de conformidad con la Ley de Transparencia y Acceso a la Información Pública del\nDistrito Federal; en caso de no hacerlo, se entenderá que toda la información puede ser consultada por cualquier persona.\nARTÍCULO 50.- La autoridad competente, deberá llevar a cabo una consulta pública, conforme a las bases de la Ley de Participación Ciudadana y al Reglamento de la presente Ley.\nDicha consulta tendrá que realizarse a costa del interesado que haya presentado la manifestación a la que se refiere el artículo 47 de esta Ley, con independencia del pago de la publicación a la que se refiere el siguiente artículo.\nEn estos casos, la Secretaría dictará las medidas y los mecanismos de operación que considere pertinentes para el desarrollo de la consulta pública.\nARTÍCULO 51.- Los promoventes de obras o actividades que requieran una manifestación de impacto ambiental en modalidad específica, o que deban someterse a consulta pública por determinación de la\nSecretaría, deberán publicar, a su costa, en un diario de circulación nacional, un resumen del proyecto. Las personas que participen en la consulta pública, podrán presentar a la Secretaría por escrito sus observaciones o comentarios, dentro de los cinco días hábiles siguientes a que ésta haya sido convocada.\nUna vez presentados las observaciones y comentarios, la Secretaría los ponderará y los considerará al momento de resolver sobre la autorización en materia de impacto ambiental.\nLa Secretaría al momento de emitir la resolución correspondiente de manera fundada y motivada, indicará a los interesados las razones por las cuales los comentarios a que se refiere el párrafo primero de este artículo fueron o no tomados en consideración, pudiendo los afectados interponer el recurso de inconformidad a que se refiere esta Ley, en contra de la resolución por la cual la Secretaría ponga fin al procedimiento de evaluación de impacto ambiental.\nARTÍCULO 52.- Al realizar la evaluación del impacto ambiental, la autoridad se ajustará, entre otros aspectos, a los programas de ordenamiento ecológico del territorio; a los programas de desarrollo urbano;\na las declaratorias de áreas de valor ambiental y de áreas naturales protegidas y sus programas de manejo, programas de rescate y recuperación; a las normas y demás disposiciones jurídicas que resulten aplicables.\n\nARTÍCULO 52 Bis.- Para contar con mayores elementos de evaluación y, en su caso, comprobar y constar el contenido de los estudios de impacto ambiental en sus diferentes modalidades, o de evaluación de daño ambiental, la Secretaria a través de su personal autorizado podrá realizar reconocimientos técnicos al sitio donde se pretenda o desarrolla el programa, obra o actividad.\nLa Secretaría establecerá de común acuerdo con los promoventes del programa, obra o actividad que se pretenda desarrollar, la fecha y hora para la realización del reconocimiento técnico. El procedimiento para la realización de los reconocimientos técnicos se establecerá en el Reglamento correspondiente a la materia.\nARTÍCULO 53.- Una vez evaluada la manifestación de impacto ambiental, la autoridad competente emitirá, debidamente fundada y motivada, la resolución correspondiente, en la que podrá:\nI. Autorizar la instrumentación de los programas, así como la realización de la obra o actividad de que se trate, en los términos solicitados;\nII. Autorizar la instrumentación de los programas, así como la realización de la obra o actividad de que se trate, sujetándose a la modificación del proyecto o al establecimiento de medidas adicionales de prevención y mitigación, a fin de que se eviten, atenúen o compensen los impactos ambientales adversos susceptibles de ser producidos en la ejecución del proyecto, así como en caso de accidentes;\nIII. Negar la autorización solicitada, cuando:\na) Se contraponga con lo establecido en esta Ley, su reglamento, las normas oficiales mexicanas, las normas ambientales del Distrito Federal, los planes y programas de ordenamiento ecológico y de desarrollo urbano y demás disposiciones legales aplicables;\nb) La obra o actividad afecte a la población en su salud o una o más especies amenazadas, o en peligro de extinción o a las zonas intermedias de salvaguarda y elementos que contribuyen al ciclo hidrológico o algún o algunos ecosistemas en particular; y c) Exista falsedad en la información proporcionada por los promoventes, respecto de los impactos ambientales de la obra o actividad de que se trate.\nd) Cuando la evaluación de los impactos y riesgos ambientales no garanticen la integridad del ambiente y de las personas.\n\nLa Secretaría podrá exigir el otorgamiento de garantías respecto del cumplimiento de las condicionantes establecidas en la autorización, en aquellos casos expresamente señalados en el reglamento de la Ley, cuando durante la realización de las obras puedan producirse daños graves a los ecosistemas o al ambiente.\nLa Secretaría podrá por una sola ocasión, en un plazo no mayor a cinco días hábiles a partir del ingreso de la solicitud, requerir información adicional para complementar o precisar el contenido técnico de la manifestación de impacto ambiental en sus diferentes modalidades y estudios de riesgo, para lo cual el interesado deberá dar respuesta en un plazo no mayor a cinco días hábiles.\nEn todos los casos de autorizaciones de impacto ambiental, la autoridad deberá establecer un sistema de seguimiento del cumplimiento de las disposiciones y medidas de prevención, mitigación y compensación de impactos ambientales que hubiere establecido en las resoluciones correspondientes.\nLa Secretaría deberá emitir la resolución correspondiente en un plazo de quince días hábiles, a partir de que se integre la información necesaria. Transcurrido este plazo sin que la autoridad emita la resolución se entenderá que la realización de la obra o actividad ha sido negada.\nLa Secretaría establecerá los procedimientos para el reporte del cumplimiento de condicionantes, que podrán presentar los interesados a través de los prestadores de servicios profesionales acreditados.\nEn todos los casos de autorizaciones de impacto ambiental, la autoridad deberá establecer un sistema de seguimiento del cumplimiento de las disposiciones y medidas de prevención, mitigación y compensación de impactos ambientales que hubiere establecido en las resoluciones correspondientes.\nARTÍCULO 54.- Las personas que presten servicios de evaluación de impacto ambiental, serán responsables ante la autoridad competente, de los informes preventivos, declaratorias de cumplimiento ambiental, estudios de daño ambiental y manifestaciones de impacto ambiental en sus diferentes modalidades, que elaboren.\nLos prestadores de servicios declararán bajo protesta de decir verdad que en dichos documentos se incorporan las mejores técnicas y metodologías existentes y que serán aplicadas en la identificación y evaluación de los impactos y riesgos, así como la determinación de medidas de prevención y mitigación más efectivas. En caso de incumplimiento o falsedad en la información proporcionada, el prestador de servicios será corresponsable con el interesado y se hará acreedor a las sanciones previstas en la presente ley y en el Reglamento correspondiente a la materia, y la Secretaría procederá a negar la autorización solicitada o a la cancelación del trámite de evaluación correspondiente.\n\nAsimismo, los informes preventivos, declaratorias de cumplimiento ambiental, estudios de daño ambiental, manifestaciones de impacto ambiental en sus diferentes modalidades podrán ser presentados por los interesados, instituciones de investigación, colegios o asociaciones profesionales; en este caso, existirá una corresponsabilidad con el interesado respecto del contenido del documento.\nARTÍCULO 55.- Las obras o actividades a que se refiere el artículo 46 que por su ubicación, dimensiones, características o alcances no produzcan impactos ambientales significativos, o no causen desequilibrio ecológicos, ni rebasen los límites y condiciones establecidos en las disposiciones jurídicas referidas a la preservación del equilibrio ecológico y la protección al ambiente, estarán sujetas a la evaluación de impacto ambiental, a través de la presentación de un informe preventivo ante la Secretaría, o bien, podrá consultar a la Secretaría si las obras o actividades de que se trate requieran la presentación de una manifestación de impacto ambiental, antes de iniciar la obra o actividad.\nTanto la presentación del informe preventivo como la consulta, a elección de los interesados, podrán realizarse a través de los medios de comunicación electrónica, produciendo los mismos efectos que los presentados en papel cuando aparezca en los mismos la firma electrónica registrada y reconocida por la\nAdministración Pública del Distrito Federal.\nEn los términos que establezca el Reglamento correspondiente a la materia o las disposiciones administrativas aplicables, la Secretaría podrá hacer uso de medios de comunicación electrónica para realizar notificaciones, citatorios y requerimientos de información o documentación a los interesados.\nArtículo 56.- Las obras y actividades en suelo urbano que estarán sujetas a la evaluación de impacto ambiental a través de la presentación de un informe preventivo ante la Secretaría, además de las que se señalen en el Reglamento correspondiente a la materia, son las siguientes:\na) Conjuntos habitacionales;\nb) Conjuntos habitacionales mixtos;\nc) Centros comerciales;\nd) Oficinas, y e) Estacionamientos mayores a diez mil metros cuadrados.\n\nARTÍCULO 57.- El informe preventivo deberá contener:\nI. Nombre, denominación o razón social, nacionalidad, domicilio para oír y recibir notificaciones, personas señaladas para tal efecto, teléfono y correo electrónico del interesado de la obra o actividad proyectada y del responsable de la elaboración del informe preventivo; este último, además deberá presentar copia cotejada de la cédula profesional o certificación o acreditación en la materia;\nII. Documentos que determinen el uso de suelo autorizado o permitido para el predio;\nIII. Descripción de la obra o actividad proyectada;\nIV. Descripción de los materiales o productos que vayan a emplearse en la ejecución de la obra o actividad proyectada, y los que en su caso vayan a obtenerse como resultado de dicha obra o actividad, incluyendo emisiones a la atmósfera, descargas de aguas residuales, tipo de residuos y procedimientos para su disposición final;\nV. Monto de la inversión requerida para ejecutar la obra o actividad, así como porcentaje de ésta que se destinará a la instrumentación de medidas de prevención, mitigación y compensación de impactos ambientales;\nVI. Programa calendarizado de ejecución de la obra o actividad;\nVII. Medidas contempladas para la prevención o mitigación de impactos ambientales que pudieran ocasionarse con la realización de la obra o actividad; y\nVIII. En su caso, el estudio de riesgo si se tratase de acciones que lo ameriten sin requerir una manifestación de impacto ambiental.\nARTÍCULO 58.- Una vez recibido el informe preventivo, la autoridad competente, en un plazo no mayor a cinco días hábiles, comunicará, preferentemente por medio de correo electrónico a los interesados si procede o no la presentación de una manifestación de impacto ambiental, así como la modalidad y plazo para hacerlo. Transcurrido el plazo señalado, sin que la autoridad emita la comunicación correspondiente, se entenderá que no es necesaria la presentación de una manifestación de impacto ambiental.\n\nEn aquellos casos que por negligencia, dolo o mala fe se ingrese el informe preventivo, pretendiendo se aplique la afirmativa ficta, se entenderá que el ingreso del procedimiento para la autorización del informe preventivo es inexistente, independientemente de las sanciones previstas en esta Ley.\nLa Secretaría en un plazo no mayor a quince días hábiles, a partir de ingresado el informe preventivo o recibida la información adicional solicitada en su caso, emitirá la resolución correspondiente.\nARTÍCULO 58 Bis.- Las obras o actividades a que se refiere el artículo 46 que por su ubicación, dimensiones, características o alcances produzcan impactos ambientales tipificados en la normatividad ambiental vigente quedarán sujetos a la presentación ante la Secretaría de una Declaratoria de Cumplimiento\nAmbiental.\nLa Declaratoria de Cumplimiento Ambiental es el documento firmado por el interesado bajo protesta de decir verdad, a través del cual se comunica a la Secretaría sobre la realización de las siguientes obras o actividades:\nI. De demolición;\nII. Rehabilitación;\nIII. Emergencia;\nIV. Modificación, ampliación, sustitución de infraestructura, conservación y mantenimiento;\nV. Desazolve;\nVI. Conjuntos habitacionales, conjuntos habitacionales mixtos y oficinas de hasta diez mil metros cuadrados totales de construcción;\nVII. Centros comerciales de hasta diez mil metros cuadrados totales de construcción; y\nVIII. Estacionamientos.\nLas obras o actividades antes mencionadas, quedan sujetas al cumplimiento de las disposiciones ambientales señaladas en el Reglamento correspondiente a la materia y a las disposiciones ambientales contenidas en la legislación ambiental vigente.\n\nEl Jefe de Gobierno, mediante acuerdos o en el Reglamento correspondiente a la materia podrá establecer la posibilidad de que la Declaratoria de Cumplimiento Ambiental se presente a través de los medios de comunicación electrónica, otorgando a la firma electrónica que se autorice al mismo valor probatorio que a los presentados con firma autógrafa.\nARTÍCULO 58 Ter.- Las personas físicas o morales que realicen obras de construcción de conjuntos habitacionales u oficinas, deberán realizar el pago de aprovechamientos establecido en el Código\nFinanciero del Distrito Federal, para la realización de acciones necesarias para prevenir, minimizar, mitigar, compensar y/o resarcir las afectaciones o alteraciones a los recursos naturales y el ambiente.\nTambién deberán cubrir el pago de aprovechamientos las obras de construcción, operación y mantenimiento de conjuntos habitacionales o de oficinas en predios que colinden con barrancas, suelo de conservación, áreas naturales protegidas, áreas de valor ambiental o cuerpo de agua, los que además deberán cumplir con las condicionantes establecidas en la autorización de impacto ambiental correspondiente.\nPara el caso de conjuntos mixtos, el pago de aprovechamientos se calculará conforme a la superficie de construcción que corresponda a los usos habitacional y/u oficinas. Se excluirá del cálculo la superficie de estacionamiento y/o de uso comercial.\nARTÍCULO 58 Quater.- La Declaratoria de Cumplimiento Ambiental podrá presentarse por medio electrónico en los términos de las disposiciones aplicables, en cuyo caso el acuse de recibo oficial correspondiente será válido únicamente cuando el interesado hubiere presentado la documentación probatoria indicada.\nARTÍCULO 58 Quinquies.- La Declaratoria Ambiental de Cumplimiento deberá presentarse ante la\nSecretaría, en original y copia, previamente a la ejecución de las actividades pretendidas y ajustarse al siguiente contenido:\nI. Formato de registro que para el efecto publique la Secretaría;\nII. Declaración firmada por el interesado, en la que bajo protesta de decir verdad, manifiesta las consideraciones bajo las cuales se ubica su proyecto que lo eximen de obtener la autorización en materia de impacto ambiental, incluyendo la documentación legal que respalde tales consideraciones.\n\nIII. Datos generales de quien pretenda realizar la obra o actividad proyectada, o en su caso, de quien hubiere ejecutado los proyectos o estudios previos correspondientes;\nIV. Documentos que determinen el uso de suelo autorizado o permitido para el predio;\nV. Descripción de la obra o actividad proyectada;\nVI. Descripción de los materiales o productos que vayan a emplearse en la ejecución de la obra o actividad proyectada, y los que en su caso vayan a obtenerse como resultado de dicha obra o actividad, incluyendo emisiones a la atmósfera, descargas de aguas residuales, tipo de residuos y procedimientos para su disposición final;\nVII. Monto de la inversión requerida para ejecutar la obra o actividad, así como porcentaje de ésta que se destinará a la instrumentación de medidas de prevención, mitigación y compensación de impactos ambientales;\nVIII. Programa calendarizado de ejecución de la obra o actividad indicando fechas de inicio y conclusión de las actividades; y\nIX. Medidas contempladas para la prevención o mitigación de impactos ambientales que pudieran ocasionarse con la realización de la obra o actividad.\nX. El comprobante del pago de los aprovechamientos establecidos en el Código Financiero del\nDistrito Federal.\nEl Jefe de Gobierno en el Reglamento correspondiente a la materia o mediante acuerdos generales, podrá eximir a los interesados la presentación de los datos y documentos cuando la Secretaría pueda obtener por otra vía la información correspondiente.\nARTÍCULO 58 Sexies.- Una vez recibida la declaratoria de cumplimiento ambiental el interesado podrá iniciar la obra o actividad, dando cumplimiento a las disposiciones ambientales que al efecto dicte la autoridad competente a través de informes semestrales o al término del proyecto.\nEn aquellos casos que por negligencia, dolo, mala fe o pretendiendo inducir a error a la autoridad, se ingrese una declaratoria de cumplimiento ambiental, a sabiendas que lo procedente es la presentación de\n\nuna Manifestación de Impacto Ambiental en cualquiera de las modalidades, Informe Preventivo o Estudio de Riesgo, dicha declaratoria se tendrá por no presentada independientemente de las medidas de seguridad y sanciones previstas en esta Ley y en el Reglamento correspondiente a la materia.\nARTÍCULO 59.- Las autorizaciones, licencias o permisos otorgados en contravención a lo dispuesto en esta\nLey, serán nulos de pleno derecho y los servidores públicos que los hayan otorgado serán sancionados de conformidad con la Ley de Responsabilidades de los Servidores Públicos correspondiente, para cuyo efecto la Secretaría informará el hecho de inmediato a la autoridad competente, lo anterior sin perjuicio de otras sanciones que pudieran aplicarse.\nARTÍCULO 60.- La persona que construya una obra nueva, amplíe una existente, o explote recursos naturales sin contar previamente con la autorización de impacto ambiental respectiva o que contando con ésta incumpla los requisitos y condiciones establecidos en la misma o en esta Ley, estará obligada a reparar los daños ambientales que con tal motivo hubiere causado a los recursos naturales o al ambiente, sin perjuicio de la aplicación de las medidas de seguridad y sanciones respectivas.\nARTÍCULO 61.- Las autorizaciones que se otorguen en materia de impacto ambiental estarán referidas a la obra o actividad de que se trate.\nLas autoridades competentes deberán acudir al lugar especificado en el informe de impacto ambiental para inspeccionar, verificar y, llegado el caso, sancionar las irregularidades que existieran de acuerdo a lo previsto en el Título VII, Capítulo II de esta Ley.\nCAPÍTULO VI BIS\nMANIFESTACIÓN AMBIENTAL ÚNICA PARA LA CIUDAD DE MÉXICO\nARTÍCULO 61 Bis. La Manifestación Ambiental Única para la Ciudad de México es el instrumento de política ambiental por medio del cual los responsables de fuentes fijas que están sujetos a las disposiciones de esta\nLey, informan sobre el cumplimiento de sus obligaciones ambientales relativas a:\nI. Emisiones a la atmósfera;\nII. Descarga de aguas residuales;\nIII. Generación y manejo de residuos sólidos;\n\nIV. Generación de ruido y vibraciones mecánicas y;\nV. Registro de emisiones y transferencia de contaminantes.\nReforma publicada en la GOCDMX el 27 de febrero de 2023\nARTÍCULO 61 bis 1.- Para presentar la Manifestación Ambiental Única para la Ciudad de México a que se refiere el Artículo anterior, los responsables de las fuentes fijas deberán registrar y adjuntar en la Plataforma\nDigital, en un plazo no mayor a 60 días hábiles a partir del inicio de operaciones del establecimiento, la siguiente información y documentación:\nI. Datos generales del solicitante;\nII. Ubicación de la fuente fija;\nIII. Descripción del proceso y/o los servicios brindados;\nIV. Horario de operación;\nV. Cantidad y tipo de materias primas o combustibles que se utilicen en su proceso y forma de almacenamiento;\nVI. Transporte de materias primas o combustibles al área de proceso;\nVII. Transformación de materias primas o combustibles;\nVIII. Productos, subproductos y residuos que se generen;\nIX. Los estudios y análisis realizados por laboratorios autorizados por la Secretaría, conforme al\nArtículo 200 de la presente Ley, y los anexos, planes o programas que de acuerdo con la actividad del establecimiento se deban presentar;\nReforma publicada en la GOCDMX el 27 de febrero de 2023\nX. Almacenamiento, transporte y distribución de productos y subproductos;\nXI. Cantidad y naturaleza de los contaminantes a la atmósfera esperados;\n\nXII. Equipos para el control de la contaminación a la atmósfera que vayan a utilizarse; y\nXIII. Programas de acciones para el caso de contigencias atmosféricas, que contenga las medidas y acciones que se llevarán a cabo cuando las condiciones meteorológicas de la región sean desfavorables, o cuando se presenten emisiones de contaminantes extraordinarias no controladas;\nXIV. Programa de aprovechamiento, regulación, mitigación y control de la luz artificial y luz intrusa, conforme a la Norma Ambiental en la materia.\nFracción añadida y publicada en la GOCDMX el 04 de mayo de 2023\nEl Jefe de Gobierno, mediante acuerdos o en el Reglamento correspondiente a la materia, podrá establecer la posibilidad de que la Solicitud se presente a través de los medios de comunicación electrónica, otorgando a la firma electrónica que se autorice al mismo valor probatorio que a los presentados con firma autógrafa.\nEl Jefe de Gobierno en el Reglamento correspondiente a la materia o mediante acuerdos generales, podrá eximir a los interesados la presentación de los datos y documentos cuando la Secretaría pueda obtener por otra vía la información correspondiente.\nARTÍCULO 61 Bis 2.- La información a que se refiere el Artículo anterior deberá presentarse mediante la\nPlataforma Digital; la Secretaría podrá verificar en cualquier momento la veracidad de la misma.\nReforma publicada en la GOCDMX el 27 de febrero de 2023\nUna vez presentada la manifestación con los requisitos aplicables, la fuente fija obtendrá de la plataforma el documento digital que acredita el cumplimiento de la obligación de presentar dicha manifestación.\nReforma publicada en la GOCDMX el 27 de febrero de 2023\nPor su parte, la Secretaría realizará el análisis del expediente digital y emitirá en un plazo de veinte días hábiles, debidamente fundada y motivada, la Resolución en la cual se establecerán las obligaciones ambientales a las que queda sujeto el establecimiento de acuerdo con su actividad y capacidad, y dispondrá si procede presentar la información del desempeño ambiental de la fuente fija de manera anual.\nReforma publicada en la GOCDMX el 27 de febrero de 2023\n\nEn tanto la Secretaría no haya emitido la Resolución a que hace referencia el párrafo que antecede, el responsable de la fuente fija no podrá ser objeto de sanción por parte de cualquier autoridad por incumplimiento a las obligaciones ambientales derivadas de la manifestación presentada\nReforma publicada en la GOCDMX el 27 de febrero de 2023\nEn caso de que la información o documentación presentada no esté correcta o completa, la Secretaría prevendrá por una sola ocasión al responsable de la fuente fija para que, en los términos que establezca el\nReglamento de la presente Ley que al efecto se emita, subsane o aclare lo correspondiente y una vez subsanado, la Secretaría tendrá 5 días hábiles para emitir la Resolución.\nReforma publicada en la GOCDMX el 27 de febrero de 2023\nEn el supuesto de que el responsable de la fuente fija no subsane la prevención en el término establecido en la prevención, se procederá en términos de lo dispuesto en el Reglamento señalado en el párrafo que antecede.\nReforma publicada en la GOCDMX el 27 de febrero de 2023\nTranscurrido el plazo establecido en el párrafo tercero del presente artículo sin que la autoridad haya emitido la resolución, este se renovará automáticamente por una sola ocasión, por un plazo de veinte días hábiles.\nReforma publicada en la GOCDMX el 27 de febrero de 2023\nARTÍCULO 61 Bis 3.- La Resolución relativa a la Manifestación Ambiental Única para la Ciudad de México que emita la Secretaría, deberá establecer:\nI. El número de registro ambiental;\nII. Las condiciones de operación;\nIII. Los límites máximos permisibles de emisión por tipo de contaminante a que deberá sujetarse la fuente emisora;\nIV. Las obligaciones ambientales a las que queda sujeto el establecimiento, de acuerdo con sus características y actividad;\nV. La periodicidad con la que deberá llevarse a cabo la medición, monitoreo y reporte de emisiones; y\n\nVI. Las medidas y acciones que deberán llevarse a cabo en caso de una contingencia.\nSe deroga.\nReforma publicada en la GOCDMX el 27 de febrero de 2023\nARTÍCULO 61 Bis 4.- Los responsables de las fuentes fijas que, de acuerdo con la Resolución emitida por la\nSecretaría estén sujetos a presentar la información de su desempeño ambiental anualmente, deben cumplir con dicha disposición cabalmente de forma anual e ininterrumpida, durante el primer cuatrimestre de cada año calendario, a través de la Plataforma Digital, registrando y adjuntando el o los anexos correspondientes, acompañados de los estudios, análisis, planes o programas que se establecen en la fracción IX del Artículo 61 bis l, de la presente Ley. El período a que se refiere este Artículo será improrrogable.\nReforma publicada en la GOCDMX el 27 de febrero de 2023\nARTÍCULO 61 Bis 5.- El listado que agrupa a los establecimientos que por su capacidad y actividad no se encuentran sujetos a registrar la Manifestación Ambiental Única para la Ciudad de México, será publicado y actualizado anualmente, en el primer bimestre de cada año calendario, en la Gaceta Oficial de la Ciudad de México.\nReforma publicada en la GOCDMX el 27 de febrero de 2023\nArtículo 61 Bis 6. Las fuentes fijas que operen sin haber presentado su Manifestación Ambiental Única u omitan el cumplimiento con alguna o algunas de sus obligaciones ambientales, establecidas en el presente capítulo, serán acreedores a las sanciones previstas en la presente Ley y demás ordenamientos jurídicos que se establezcan.\nReforma publicada en la GOCDMX el 27 de febrero de 2023\nCAPÍTULO VII\nAUTORREGULACIÓN Y AUDITORÍAS\nARTÍCULO 62.- La Secretaría fomentará programas de autorregulación y auditoría ambiental y promoverá la aplicación de incentivos fiscales, a quienes participen en dichos programas.\nEl desarrollo de la auditoría ambiental es de carácter voluntario y no limita las facultades que esta Ley confiere a la autoridad en materia de inspección y vigilancia.\n\nARTÍCULO 63.- Los responsables de los establecimientos industriales, mercantiles, de servicios y de espectáculos, que pretendan una auditoría ambiental deberán solicitar por escrito su incorporación al programa de auditorías ambientales y establecer su compromiso de cumplir con la normatividad correspondiente y con las recomendaciones derivadas de la propia auditoría.\nARTÍCULO 64. Los productores, empresas u organizaciones empresariales que cumplan con la normatividad vigente en materia ambiental, podrán convenir con la Secretaría el establecimiento de procesos voluntarios de autorregulación a través de los cuales mejoren su desempeño ambiental, y se comprometan a superar o cumplir mayores niveles, metas o beneficios en materia de protección ambiental.\nLa Secretaría inducirá o concertará:\nI. El desarrollo de procesos productivos adecuados y compatibles con el ambiente, así como sistemas de protección y restauración en la materia, convenidos con cámaras de industria, comercio y otras actividades productivas, organizaciones de productores, organizaciones representativas de una zona o región, instituciones de investigación científica y tecnológica y otras organizaciones interesadas;\nII. El cumplimiento de normas voluntarias o especificaciones técnicas en materia ambiental que sean más estrictas que las normas oficiales mexicanas o que se refieran a aspectos no previstos por éstas. Para tal efecto, la Secretaría podrá promover el establecimiento de normas ambientales de Distrito Federal o normas mexicanas;\nIII. El establecimiento de sistemas de certificación de procesos, productos o desarrollo de infraestructura y equipamiento, y de edificaciones sustentables para inducir patrones de consumo, producción o de desarrollo urbano que sean compatibles o que preserven, mejoren o restauren el medio ambiente; y\nIV. Las demás acciones que induzcan a las personas físicas o morales a alcanzar los objetivos de la política ambiental superiores a las previstas en la normatividad ambiental establecida.\nARTÍCULO 64 Bis.- Los responsables de vehículos o flotillas podrán suscribir convenios de autorregulación en los que se comprometan a actualizar la tecnología de dichos vehículos o hacer conversiones a combustibles alternos en los términos que la Secretaría establezca.\n\nARTÍCULO 64 Bis 1.- Los convenios de autorregulación que se suscriban serán obligatorios y su incumplimiento será motivo para la cancelación de los estímulos, certificaciones y de las exenciones otorgados, independientemente de las sanciones aplicables conforme la presente Ley.\nARTÍCULO 65.- Una vez firmado o firmados los convenios de autorregulación y siempre que lo solicite el interesado, mediante el llenado de un cuestionario y la presentación de los documentos requeridos al efecto, podrá solicitar la realización de una visita de inspección voluntaria a la empresa.\nIntegrado el expediente, la Secretaría revisará la información y documentación aportadas, así como el resultado de la inspección realizada y emitirá un certificado de reducción de emisiones contaminantes siempre y cuando se hayan logrado reducir por debajo de los límites establecidos por las normas oficiales mexicanas y las normas ambientales para el Distrito Federal.\nARTÍCULO 66.- La Secretaría elaborará y aplicará un programa de auditorías ambientales voluntarias, para lo cual deberá:\nI. Instrumentar un sistema de aprobación, acreditamiento y registro de peritos y auditores ambientales, ya sean personas físicas o morales, en los términos de las reglas de carácter general que en materia de autorregulación y auditoría ambiental publique en la Gaceta Oficial del\nDistrito Federal la Secretaría;\nII. Desarrollar programas de capacitación en materia de peritajes y auditorías ambientales;\nIII. Instrumentar un sistema de reconocimientos, estímulos y certificación de las empresas, que permita identificar a aquellas que cumplan oportunamente los compromisos adquiridos como resultado de las auditorías ambientales;\nIV. Promover y concertar, en apoyo a la pequeña y mediana industria, los mecanismos que faciliten la realización de auditorías en varias unidades productivas de un mismo ramo o sector económico.\nARTÍCULO 67.- La Secretaría podrá eximir de la obligación de realizar verificaciones en determinados periodos, a las empresas que realicen auditorías ambientales voluntarias, en los casos en que así lo considere conveniente. En todo caso esa circunstancia deberá constar en resolución por escrito, debidamente fundada y motivada.\n\nARTÍCULO 68.- Sin perjuicio de lo dispuesto en los artículos precedentes, la Secretaría podrá en todo momento, de oficio o a petición fundada y motivada de cualquier interesado, ordenar la realización de auditorías ambientales en forma obligatoria para cerciorarse del cumplimiento de las disposiciones de la presente Ley.\nCAPÍTULO VIII\nDEL FONDO AMBIENTAL PÚBLICO\nARTÍCULO 69.- Se crea el fondo ambiental público cuyos recursos se destinarán a:\nI. La realización de acciones de conservación del medio ambiente, la protección ecológica y la restauración del equilibrio ecológico;\nII. La vigilancia y conservación de los recursos naturales en Áreas Comunitarias de Conservación\nEcológica;\nII Bis. La vigilancia y conservación, restauración, preservación, conservación de la biodiversidad, ecosistemas y aprovechamiento sustentable de los recursos naturales en suelo de conservación;\nIII. El manejo y la administración de las áreas naturales protegidas;\nIV. La restauración y conservación, así como la elaboración de los programas de manejo de las áreas de valor ambiental;\nV. El desarrollo de programas vinculados con inspección y vigilancia en las materias a que se refiere esta Ley;\nVI. La retribución por proteger, restaurar o ampliar los servicios ambientales;\nVII. La retribución por la conservación de los servicios ambientales en Áreas Comunitarias de\nConservación Ecológica;\nVII Bis. La retribución por la protección, conservación o ampliación de servicios ambientales y por la realización de actividades vinculadas al desarrollo rural, equitativo y sustentable en suelo de conservación;\n\nVIII. El desarrollo de programas de educación e investigación en materia ambiental y para el fomento y difusión de experiencias y prácticas para la protección, conservación y aprovechamiento de los recursos naturales y el ambiente;\nIX. El cuidado y protección de los animales del Distrito Federal;\nX. La supervisión del cumplimiento de los convenios con los sectores productivo y académico;\nXI. La reparación de daños ambientales; y\nXII. Proyectos de participación ciudadana previamente analizados y que cuenten con la autorización de la Procuraduría con relación a los recursos naturales de la Tierra.\nARTÍCULO 70.- Los recursos del fondo se integrarán con:\nI. Las herencias, legados y donaciones que reciba;\nII. Los recursos destinados para ese efecto en el Presupuesto de Egresos del Distrito Federal;\nIII. Los productos de sus operaciones y de la inversión de fondos;\nIV. Los relativos al pago de contribuciones o cualquier tipo de ingresos por servicios ambientales y por la realización acciones de compensación de los efectos negativos sobre el ambiente y los recursos naturales que se establezcan en la normatividad aplicable;\nV. El monto de las multas que se impongan por fracciones a las disposiciones ambientales;\nVI. Los recursos derivados de los instrumentos económicos y de mercado correspondientes a programas y proyectos de reducción de emisiones de gases de efecto invernadero; y\nVII. Los demás recursos que se generen por cualquier otro concepto.\nARTÍCULO 70 Bis. El Presupuesto de Egresos del Distrito Federal establecerá los recursos del fondo ambiental y, entre otros, aquellos destinados específicamente para la vigilancia y conservación de los recursos naturales, la retribución por la conservación de los servicios ambientales en Áreas Comunitarias\n\nde Conservación Ecológica, así como las acciones de vigilancia de los recursos inherentes a Tierra y su monto no podrá ser menor al que se hubiera establecido en el ejercicio fiscal anterior.\nARTÍCULO 71.- El Jefe de Gobierno emitirá un acuerdo que establezca la integración del consejo técnico del fondo ambiental, su organización y sus reglas de funcionamiento.\nCAPÍTULO IX\nINSTRUMENTOS ECONÓMICOS\nARTÍCULO 71 Bis.- La Secretaría diseñará, desarrollará y aplicará instrumentos económicos que incentiven el cumplimiento de los objetivos de la política ambiental, y mediante los cuales se buscará:\nI. Promover un camb io en la conducta de las personas que realicen actividades industriales, comerciales y de servicios, de tal manera que sus intereses sean compatibles con los intereses colectivos de protección ambiental y de desarrollo sustentable;\nII. Fomentar la incorporación de información confiable y suficiente sobre las consecuencias, beneficios y costos ambientales al sistema de precios de la economía;\nIII. Otorgar incentivos a quien realice acciones para la protección, preservación o restauración del equilibrio ecológico. Asimismo, deberán procurar que quienes dañen el ambiente, hagan un uso indebido de recursos naturales o alteren los ecosistemas, asuman los costos respectivos;\nIV. Promover una mayor equidad social en la distribución de costos y beneficios asociados a los objetivos de la política ambiental; y\nV. Procurar su utilización conjunta con otros instrumentos de política ambiental, en especial cuando se trate de observar umbrales o límites en la utilización de ecosistemas, de tal manera que se garantice su integridad y equilibrio, la salud y el bienestar de la población.\nARTÍCULO 71 Bis 1.- Se consideran instrumentos económicos los mecanismos normativos y administrativos de carácter fiscal, financiero o de mercado, mediante los cuales las personas asumen los beneficios y costos ambientales que generen sus actividades económicas, incentivándolas a realizar acciones que favorezcan el ambiente.\n\nSe consideran instrumentos económicos de carácter fiscal, los estímulos fiscales que incentiven el cumplimiento de los objetivos de la política ambiental. En ningún caso, estos instrumentos se establecerán con fines exclusivamente recaudatorios.\nSon instrumentos financieros los créditos, las fianzas, los seguros de responsabilidad civil, los fondos y los fideicomisos, cuando sus objetivos estén dirigidos a la preservación, protección, restauración o aprovechamiento sustentable de los recursos naturales y el ambiente, así como al financiamiento de programas, proyectos, estudios e investigación científica y tecnológica para la preservación del equilibrio ecológico y protección al ambiente.\nSon instrumentos de mercado las concesiones, autorizaciones, licencias y permisos que corresponden a volúmenes preestablecidos de emisiones de contaminantes en el aire, agua o suelo, o bien, que establecen los límites de aprovechamiento de recursos naturales, o de construcción en áreas naturales protegidas o en zonas cuya preservación y protección se considere relevante desde el punto de vista ambiental.\nLas prerrogativas derivadas de los instrumentos económicos de mercado serán transferibles, no gravables y quedarán sujetos al interés público y al aprovechamiento sustentable de los recursos naturales.\nARTÍCULO 72.- La Secretaría promoverá el otorgamiento de estímulos fiscales, financieros y administrativos a quienes:\nI. Adquieran, instalen y opere n las tecnologías, sistemas, equipos y materiales o realicen las acciones que acrediten prevenir o reducir las emisiones contaminantes establecidos por las normas oficiales mexicanas y las ambientales para el Distrito Federal, o prevenir y reducir el consumo de agua o de energía, o que incorporen sistemas de recuperación y reciclamiento de las aguas de desecho o que utilicen aguas tratadas o de reuso para sus funciones productivas, de conformidad con los programas que al efecto se establezcan;\nII. Realicen desarrollo tecnológicos y de ecotecnias viables cuya aplicación demuestre prevenir o reducir las emisiones contaminantes, la producción de grandes cantidades de residuos sólidos urbanos, el consumo de agua o el consumo de energía, en los términos de los programas que al efecto se expidan;\nIII. Integren organizaciones civiles con fines de desarrollo sustentable, que acrediten su personalidad jurídica ante la Secretaría;\n\nIV. Lleven a cabo actividades que garanticen la conservación sustentable de los recursos naturales, y\nV. Desarrollen infraestructura y equipamiento, así como de edificaciones que en su diseño de concepto incorporen criterios de sustentabilidad;\nARTÍCULO 72 Bis.- Se consideran prioritarias, para efectos del otorgamiento de los estímulos fiscales que se establezcan conforme al Código Fiscal del Distrito Federal, las actividades relacionadas con:\nI. La investigación, incorporación o utilización de mecanismos, equipos y tecnologías que tengan por objeto evitar, reducir o controlar la contaminación o deterioro ambiental, así como el uso eficiente de recursos naturales y de energía;\nII. La investigación e incorporación de sistemas de ahorro de energía y de utilización de fuentes de energía menos contaminantes;\nIII. El ahorro y aprovechamiento sustentable y la prevención de la contaminación del agua;\nIV. La ubicación y reubicación de instalaciones industriales, comerciales y de servicios en áreas ambientalmente adecuadas;\nV. El establecimiento, manejo y vigilancia de áreas naturales protegidas y áreas de valor ambiental; y\nVI. En general, aquellas actividades relacionadas con la preservación y restauración del equilibrio ecológico y la protección al ambiente.\nCAPÍTULO X\nINVESTIGACIÓN Y EDUCACIÓN AMBIENTALES\nARTÍCULO 73.- Las autoridades ambientales del Distrito Federal, en el ámbito de su competencia promoverán:\nI. Que las instituciones de educación en todos sus niveles incorporen en sus programas de enseñanza temas de contenido ambiental;\n\nII. El fortalecimiento de una cultura ambiental de participación corresponsable;\nIII. La difusión de los contenidos de los recursos inherentes a la Tierra;\nIV. El adiestramiento en y para el trabajo en materia de conservación del ambiente, la protección ecológica y la restauración del equilibrio ecológico, con arreglo a lo que establece esta ley;\nV. La incorporación de contenidos ambientales en los programas de las comisiones mixtas de seguridad e higiene, en coordinación con las autoridades competentes; y\nVI. La formación de especialistas así como la coordinación para la investigación y el desarrollo tecnológico en materia ambiental, que permitan prevenir, controlar y abatir la contaminación, propiciar el aprovechamiento sustentable de los recursos y proteger los ecosistemas.\nArtículo 73 Bis. La Secretaría de Ciencia, Tecnología e Innovación del Distrito Federal en el ámbito de su competencia promoverá:\nI. La investigación básica, tecnológica y aplicada que se necesiten para la solución de los problemas ambientales del Distrito Federal, promoviendo la cooperación entre el sector privado y el sector público, universidades y centros de investigación;\nII. El financiamiento adicional a las instituciones académicas y centros de investigación para el fomento y realización de investigaciones ambientales conforme a programas y proyectos específicos;\nIII. La celebración de convenios de ciencia y tecnología que coadyuven al mejoramiento del medio ambiente del Distrito Federal; y,\nIV. La amplia relación, vinculación y coordinación entre los centros de investigación y de enseñanza superior radicados en el Distrito Federal para fomentar la investigación científica en el cuidado del medio ambiente.\nARTÍCULO 74.- Para efectos de lo dispuesto por el artículo anterior, dentro del año de la promulgación de la presente Ley, la Secretaría establecerá un conjunto de recomendaciones y directrices tendientes a que las autoridades e instituciones educativas y culturales, públicas y privadas, introduzcan en los procesos\n\neducativos formales y no formales, así como en los sistemas de capacitación de la administración pública y empresariales y en los medios de comunicación, contenidos y metodologías para el desarrollo en la población de conocimientos, hábitos de conducta y actitudes orientadas a favorecer las transformaciones necesarias para alcanzar el desarrollo sustentable, así como la conservación y restauración de los recursos naturales.\nCAPÍTULO XI\nINFORMACIÓN AMBIENTAL\nARTÍCULO 75.- Toda persona tendrá derecho a que las autoridades ambientales pongan a su disposición la información ambiental que les soliciten, en los términos previstos por esta Ley y sus reglamentos.\nEn su caso, los gastos que se generen correrán por cuenta del solicitante y de requerir copias certificadas deberá cubrir los derechos correspondientes de conformidad con el Código Financiero del Distrito Federal.\nPara los efectos de lo dispuesto en esta Ley, se considera información ambiental, cualquier información escrita, visual o en forma de base de datos, de que dispongan las autoridades ambientales del Distrito\nFederal.\nToda petición de información ambiental deberá presentarse por escrito, especificando claramente la información que se solicita y los motivos de la petición. Los solicitantes deberán identificarse indicando su nombre o razón social y domicilio.\nARTÍCULO 76.- La Secretaría desarrollará un Sistema de Información Ambiental del Distrito Federal, en coordinación con el Sistema Nacional de Información Ambiental y de Recursos Naturales, que tendrá por objeto registrar, organizar, actualizar y difundir la información ambiental del Distrito Federal.\nEn dicho Sistema se integrarán, entre otros aspectos, información de los mecanismos y resultados obtenidos del monitoreo de la calidad del aire, del agua y del suelo; de las áreas verdes, áreas de valor ambiental y áreas naturales protegidas; del ordenamiento ecológico del territorio, así como la información relativa a emisiones atmosféricas, descargas de aguas residuales y residuos no peligrosos, y la correspondiente a los registros, programas y acciones que se realicen para la preservación del ambiente, protección ecológica y restauración del equilibrio ecológico.\n\nLa Secretaría y las Delegaciones, emitirán un informe público anual sobre el estado que guardan el ambiente y los recursos naturales de su jurisdicción.\nARTÍCULO 77.- Las autoridades ambientales deberán responder por escrito a los solicitantes de información ambiental en un plazo no mayor de veinte días hábiles a partir de la fecha de recepción de la petición respectiva. En caso de que la autoridad conteste negativamente la solicitud, deberá señalar las razones que motivaron tal determinación.\nLos afectados por actos de la Secretaría regulados en este capítulo, podrán interponer el recurso de inconformidad, de acuerdo con lo dispuesto en la Ley de Procedimiento Administrativo del Distrito Federal.\nARTÍCULO 78.- Quien reciba información ambiental de las autoridades competentes, en los términos del presente capítulo, será responsable de su adecuada utilización y deberá responder por los daños y perjuicios que se ocasionen por su indebido manejo.\nARTÍCULO 79.- La Secretaría negará la información solicitada cuando:\nI. Se considere por disposición legal que la información es confidencial o que por su propia naturaleza su difusión afecta o puede afectar la seguridad pública en el Distrito Federal;\nII. Se trate de información relativa a asuntos que son materia de procedimientos judiciales o de inspección y vigilancia, pendientes de resolución;\nIII. Se trate de información aportada por terceros cuando los mismos no estén obligados por disposición legal a proporcionarla; o\nIV. Se trate de información sobre inventarios e insumos y tecnología de proceso, incluyendo la descripción del mismo.\nCAPÍTULO XII\nDENUNCIA CIUDADANA\nARTÍCULO 80. Toda persona física o moral, podrá denunciar ante la Procuraduría, todo hecho, acto u omisión que produzca o pueda producir desequilibrios ecológicos o daños al ambiente o a los recursos naturales, en suelo urbano o suelo de conservación, o contravenga las disposiciones de la presente Ley y\n\ndemás ordenamientos que regulen materias relacionadas con la conservación del ambiente, protección ecológica y restauración del equilibrio ecológico.\nSi por la naturaleza de los hechos denunciados se tratare de asuntos de competencia del orden federal o sujetos a la jurisdicción de otra autoridad federativa, la misma autoridad que la recibió deberá turnarla a la autoridad competente.\nSin perjuicio de lo anterior, los interesados podrán presentar su denuncia directamente ante la\nProcuraduría General de Justicia del Distrito Federal si consideran que los hechos u omisiones de que se trate pueden ser constitutivos de algún delito, en cuyo caso deberá sujetarse a lo dispuesto por el Código de Procedimientos Penales para el Distrito Federal..\nARTÍCULO 81.- La autoridad ambiental y las autoridades delegacionales en el ámbito de sus atribuciones, están facultadas para iniciar las acciones que procedan, ante las autoridades judiciales competentes, cuando conozca de actos, hechos u omisiones que constituyan violaciones a la legislación administrativa o penal.\nARTÍCULO 82.- Si del resultado de las investigaciones realizadas por la autoridad ambiental, se desprende que se trata de actos, hechos u omisiones en que hubieren incurrido autoridades federales, estatales o municipales, emitirá las recomendaciones necesarias para promover ante estas u otras, la ejecución de las acciones procedentes.\nARTÍCULO 83.- La denuncia deberá presentarse por escrito y contener al menos:\nI. El nombre o razón social, domicilio, y teléfono en su caso;\nII. Los actos, hechos u omisiones denunciados;\nIII. Los datos que permitan identificar al presunto infractor o localizar la fuente de contaminación;\ny\nIV. Las pruebas que en su caso ofrezca el denunciante.\nUna vez ratificada la denuncia y en su caso, desahogadas las pruebas, la Procuraduría podrá, en los términos de su Ley Orgánica, realizar la visita de inspección correspondiente en los términos de esta Ley, a efecto de determinar la existencia o no de la infracción motivo de la denuncia.\n\nUna vez calificada el acta levantada con motivo de la visita de inspección referida en el artículo anterior, la\nProcuraduría procederá a dictar la resolución que corresponda conforme a derecho.\nSin perjuicio de la resolución señalada en el Artículo precedente, la Procuraduría dará contestación, debidamente fundada y motivada, a la denuncia en un plazo de treinta días hábiles a partir de su ratificación, la que deberá notificar personalmente al denunciante y en la cual se informará del resultado de la inspección, de las medidas que se hayan tomado y, en su caso, de la imposición de la sanción respectiva.\nARTÍCULO 84.- La autoridad estará obligada a informar al denunciante sobre el trámite que recaiga a su denuncia.\nTÍTULO CUARTO\nDE LA PROTECCIÓN, RESTAURACIÓN Y APROVECHAMIENTO\nSUSTENTABLE DE LOS RECURSOS NATURALES\nCAPÍTULO I\nDISPOSICIONES GENERALES\nARTÍCULO 85. Para la protección, restauración, preservación y aprovechamiento sustentable de la biodiversidad, los recursos naturales y el suelo de conservación, así como el establecimiento, rehabilitación, protección y preservación de las áreas naturales protegidas se considerarán, por lo menos, los siguientes criterios:\nI. En los programas y actividades de restauración, reforestación o forestación, en su caso, así como de aprovechamiento de la vida silvestre, se protegerán especialmente las especies nativas y aquellas que se encuentren en riesgo de acuerdo a la normatividad aplicable;\nII. Para evitar el deterioro de la biodiversidad, no se permitirá el uso de especies que no sean nativas del lugar;\nIII. En la restauración o rehabilitación de las áreas naturales protegidas, o en la protección de barrancas, no podrán ser alteradas en forma definitiva los cauces naturales y escurrimientos temporales o permanentes;\n\nIV. Durante el desarrollo de obras o actividades de cualquier tipo, se evitará la pérdida o erosión del suelo y el deterioro de la calidad del agua;\nV. En los sitios a proteger, se procurará el rescate del conocimiento tradicional, con relación al uso y manejo de los recursos naturales, y\nVI. Se promoverá la participación de vecinos, comunidades, pueblos indígenas y población en general, en los programas y acciones para el establecimiento, cuidado y vigilancia de las áreas naturales protegidas.\nLos programas y actividades de forestación, reforestación, restauración o aprovechamiento de la flora y fauna, procurarán la preservación y el desarrollo de las especies nativas del Distrito Federal. El uso o aprovechamiento de los elementos naturales se sujetarán a los criterios de sustentabilidad que permitan garantizar la subsistencia de las especies sin ponerlas en riesgo de extinción y permitiendo su regeneración en la cantidad y calidad necesarias para no alterar el equilibrio ecológico.\nARTÍCULO 86. Para la preservación, manejo, aprovechamiento sustentable y restauración de los recursos naturales, la Secretaría tendrá las siguientes facultades:\nI. El cuidado, administración y vigilancia de las áreas naturales protegidas, áreas de valor ambiental y áreas verdes de su competencia;\nII. La emisión de normas ambientales para el Distrito Federal;\nIII. El desarrollo de programas de inspección y vigilancia y en su caso, la imposición de las sanciones que correspondan de conformidad con esta Ley;\nIV. El ejercicio de las acciones administrativas que correspondan en los casos de invasión de áreas verdes, áreas de valor ambiental y áreas naturales protegidas de su competencia y, en general, de suelo de conservación;\nV. Elaborar los programas de reforestación y restauración con especies nativas apropiadas a cada ecosistema; y\n\nVI. La formulación e instrumentación del Programa de Retribución por la Conservación de\nServicios Ambientales en Áreas Comunitarias de Conservación Ecológica.\nCompete a las delegaciones conforme a lo previsto en esta Ley y demás disposiciones legales aplicables, el ejercicio de las acciones administrativas que procedan en los casos de invasión de áre as verdes de su competencia, así como de las que corresponden a la Secretaría previa la celebración del convenio respectivo\nEl reglamento determinará los lineamientos para la ejecución de las acciones administrativas derivadas de la invasión de áreas verdes, áreas de valor ambiental y áreas naturales protegidas, así como en predios del dominio público y de particulares en suelo de conservación.\nARTÍCULO 86 Bis.- En caso de que el titular de la delegación no proceda conforme las atribuciones que le brinda esta ley y como lo establece el artículo 86, para desalojar a quienes invadan suelo de conservación con el fin de asentarse irregularmente, o no finque acción penal en contra de quien destruya el mismo, será considerado coparticipe en esa acción y se le impondrá lo establecido en el articulo 343 BIS del Código\nPenal del Distrito Federal.\nCAPÍTULO I BIS\nDE LA TIERRA Y SUS RECURSOS NATURALES\nArtículo 86 bis 1. La Tierra es un sistema viviente dinámico conformado por la comunidad indivisible de todos los sistemas de vida y los seres vivos, interrelacionados, interdependientes y complementarios, que comparten un destino común.\nArtículo 86 Bis 2. Los sistemas de vida son comunidades complejas y dinámicas de plantas, animales, micro organismos, otros seres y su entorno, donde interactúan comunidades humanas junto al resto de la naturaleza como una unidad funcional, bajo la influencia de factores climáticos, fisiográficos y geológicos, así como de las prácticas productivas, la diversidad cultural, y las cosmovisiones de los grupos indígenas.\nArtículo 86 Bis 3. Para efectos de la protección y tutela de sus recursos naturales, la Tierra adopta el carácter de ente colectivo sujeto de la protección del interés público. En su aplicación se tomarán en cuenta las especificidades y particularidades de sus diversos componentes.\n\nArtículo 86 Bis 4. Todas las personas, al formar parte de la comunidad de seres que componen la Tierra, ejercen los derechos establecidos en la presente ley, de forma armónica con sus derechos individuales y colectivos.\nArtículo 86 Bis 5. Los habitantes del Distrito Federal tienen las siguientes responsabilidades para con la\nTierra y sus recursos naturales.\nI. Al mantenimiento de la vida. A la preservación de la integridad de los sistemas de vida y los procesos naturales que los sustentan, así como las capacidades y condiciones para su regeneración;\nII. Al mantenimiento a la diversidad de la vida. A la preservación de la diferenciación y la variedad de los seres que componen la Tierra, sin ser alterados genéticamente ni modificados en su estructura de manera artificial, de tal forma que amenace su existencia, funcionamiento y potencial futuro;\nIII. A la conservación del agua. A la preservación de la funcionalidad de los ciclos del agua, de su existencia en la cantidad y calidad necesarias para el sostenimiento de los sistemas de vida, y su protección frente a la contaminación para la reproducción de la vida de la Tierra y todos sus componentes;\nIV. A mantener el aire limpio. A la preservación de la calidad y composición del aire para el sostenimiento de los sistemas de vida y su protección frente a la contaminación, para la reproducción de la vida de la Tierra y todos sus componentes;\nV. Al equilibrio ecológico. Al mantenimiento de la interrelación, interdependencia, complementariedad y funcionalidad de los componentes de la Tierra, de forma equilibrada para la continuación de sus ciclos y la reproducción de sus procesos vitales;\nVI. A la restauración del ecosistema. A la restitución oportuna y efectiva de los sistemas de vida afectados por las actividades humanas directa o indirectamente; y\nVII. A vivir libre de contaminación. A la preservación de la Tierra de contaminación de cualquiera de sus componentes, así como de residuos tóxicos y radiactivos generados por las actividades humanas.\n\nArtículo 86 Bis 6. El Gobierno del Distrito Federal tiene las siguientes obligaciones:\nI. Desarrollar políticas públicas y acciones sistemáticas de prevención, alerta temprana, protección, para evitar que las actividades humanas conduzcan a la extinción de poblaciones de seres, la alteración de los ciclos y procesos que garantizan la vida o la destrucción de sistemas de vida, que incluyen los sistemas culturales que son parte de la Tierra;\nII. Desarrollar en el ámbito de sus atribuciones, formas de producción y patrones de consumo equilibrados en la búsqueda del bien común, salvaguardando las capacidades regenerativas y la integridad de los ciclos, procesos y equilibrios vitales de la Tierra;\nIII. Desarrollar políticas para defender la Tierra en el ámbito nacional, de la sobreexplotación de sus componentes, de la mercantilización de los sistemas de vida o los procesos que los sustentan y de las causas estructurales del Cambio Climático y sus efectos;\nIV. Desarrollar políticas y campañas de promoción a fin de asegurar la sustentabilidad energética a largo plazo a partir una cultura del ahorro, el aumento de la eficiencia y la incorporación paulatina de fuentes alternativas limpias y renovables entre los habitantes del Distrito Federal; y\nV. Velar en el ámbito de sus atribuciones, por el reconocimiento de la necesidad de financiamiento y transferencia de tecnologías limpias, efectivas y compatibles con los recursos naturales de la Tierra, además de otros mecanismos.\nCAPÍTULO II\nÁREAS VERDES\nARTÍCULO 87. Para los efectos de esta Ley se consideran áreas verdes:\nI. Parques y jardines;\nII. Plazas jardinadas o arboladas;\nIII. Jardineras;\n\nIV. Zonas con cualquier cubierta vegetal en la vía pública; así como área o estructura con cualquier cubierta vegetal o tecnología ecológica instalada en azoteas de edificaciones.\nV. Alamedas y arboledas;\nVI. Promontorios, cerros, colinas, elevaciones y depresiones orográficas, pastizales naturales y áreas rurales de producción forestal, agroindustrial o que presten servicios ecoturísticos;\nVII. Se deroga;\nVIII. Zonas de recarga de mantos acuíferos;\nVIII Bis. Áreas de Valor Ambiental; y\nIX. Las demás áreas análogas.\nCorresponde a las Delegaciones la construcción, rehabilitación, administración, preservación, protección, restauración, forestación, reforestación, fomento y vigilancia de las áreas verdes establecidas en las fracciones I a la V del párrafo anterior, y a la Secretaría el ejercicio de las acciones antes mencionadas cuando se trate de las áreas previstas en las fracciones VI a la IX siempre y cuando no estén ubicadas dentro de los límites administrativos de la zona urbana de los centros de población y poblados rurales de las delegaciones localizados en suelo de conservación, mismas que se consideren competencia de las delegaciones, así como cuando se trate de los recursos forestales, evitando su erosión y deterioro ecológico con el fin de mejorar el ambiente y la calidad de vida de toda persona en el Distrito Federal, de conformidad con los criterios, lineamientos y normatividad que para tal efecto expida la propia Secretaría.\nLa Secretaría solicitará a la Secretaría de Desarrollo Urbano y Vivienda el establecimiento de áreas verdes de su competencia en los programas de desarrollo urbano.\nLas delegaciones procurarán el incremento de áreas verdes de su competencia, en proporción equilibrada con los usos de suelo distintos a áreas verdes, espacios abiertos y jardinados o en suelo de conservación existentes en su demarcación territorial, e incorporarlos a los programas delegacionales de desarrollo urbano.\nARTÍCULO 88.- El mantenimiento, mejoramiento, restauración, rehabilitación, fomento, forestación, reforestación y conservación de las áreas verdes del Distrito Federal, deberá realizarse con las técnicas y especias apropiadas.\n\nARTÍCULO 88 Bis.- La Secretaría y las Delegaciones podrán celebrar convenios con los ejidatarios, avecinados o comunidades agrarias establecidos en suelo de conservación y con vecinos de las áreas verdes de su competencia, para que participen en su mantenimiento, mejoramiento, restauración, fomento y conservación; así como en la ejecución de acciones de forestación, reforestación, recreativas y culturales, proporcionando mecanismos de apoyo en especie, cuando sea necesario y promoverán su intervención en la vigilancia de tales áreas.\nARTÍCULO 88 Bis 1. En los parques y jardines, plazas jardinadas o arboladas, zonas con cualquier cubierta vegetal en la vía pública, alamedas y arboledas, jardineras, barrancas, áreas de valor ambiental y áreas naturales protegidas, queda prohibido:\nI. La construcción de edificaciones, y de cualesquier obra o actividad que tengan ese fin;\nII. El cambio de uso de suelo;\nIII. La extracción de tierra y cubierta vegetal, así como el alambrado o cercado, siempre que ello no sea realizado por las autoridades competentes o por persona autorizada por las mismas, para el mantenimiento o mejoramiento del área respectiva; y\nIV. El depósito de cascajo y de cualquier otro material proveniente de edificaciones que afecte o pueda producir afectaciones a los recursos naturales de la zona.\nARTÍCULO 88 Bis 2. Las áreas verdes bajo las categorías de parques, jardines, alamedas y arboledas o áreas análogas, establecidas en los programas de desarrollo urbano, deberán conservar su extensión y en caso de modificarse para la realización de alguna obra pública deberán ser compensadas con superficies iguales o mayores a la extensión modificada, en el lugar más cercano.\nEn el Distrito Federal se deberá conservar en su extensión el suelo de conservación.\nARTÍCULO 88 Bis 3. La construcción de edificaciones en las áreas verdes previstas en las fracciones VI a la IX del artículo 87 de la presente Ley, podrá ser autorizada o realizada por la autoridad competente, para su protección, fomento y educación ambiental, para lo cual, se requerirá de la emisión de un dictamen técnico preliminar en el que se determinen las acciones y medidas que habrán de considerarse y en su caso ordenarse en la autorización correspondiente, a efecto de evitar que se generen afectaciones a los recursos naturales de la zona durante el desarrollo de la construcción.\n\nARTÍCULO 88 Bis 4. La Secretaría establecerá el Inventario General de las Áreas Verdes del Distrito Federal, con la finalidad de conocer, proteger y preservar dichas áreas, así como para proponer a la Secretaría de\nDesarrollo Urbano y Vivienda y a las delegaciones, según su competencia, el incremento de dichas áreas en zonas donde se requiera, el cual deberá contener, por lo menos:\nI. La ubicación y superficie;\nII. Los tipos de área verde;\nIII. Las especies de flora y fauna que la conforman;\nIV. Las zonas en las cuales se considera establecer nuevas áreas verdes;\nV. Las demás que establezca el Reglamento.\nLas delegaciones llevarán el inventario de áreas verdes de su competencia en su demarcación territorial, en los términos establecidos en el párrafo anterior y lo harán del conocimiento de la Secretaría para su integración en el inventario general al que se refiere el presente artículo, proporcionando anualmente las actualizaciones correspondientes, en los términos del Reglamento. Dicho inventario formará parte del\nSistema de Información Ambiental del Distrito Federal.\nARTÍCULO 88 BIS 5.- Las autoridades locales del Distrito Federal, instalarán en la medida de sus posibilidades azoteas verdes en las edificaciones de que sean propietarios; para el caso de inmuebles catalogados por el Instituto Nacional de Antropología e Historia, el Instituto Nacional de Bellas Artes y la\nSecretaría de Desarrollo Urbano y Vivienda, deberán contar con la autorización correspondiente.\nLas azoteas verdes se sujetarán a la normatividad que para tal efecto estipule la Secretaría.\nARTÍCULO 88 Bis 6. Las áreas verdes que formen parte del área libre en una construcción, deberán representar por lo menos el 70 por ciento de ésta, y ubicarse a nivel de banqueta, preferentemente con acceso público.\nIndependientemente de las sanciones penales o administrativas, cuando para una obra nueva sea necesario talar, podar, trasplantar, mutilar o cualquier acción que cause muerte o alteración en detrimento\n\nde las condiciones de los sujetos arbóreos, dicha acción tendrá como consecuencia jurídica el aumento en el porcentaje de área libre conforme a lo dispuesto por la Norma Ambiental en la materia.\nEn caso de incumplimiento a lo dispuesto por este artículo se estará a lo que referido en el artículo 214 quinquies de la presente Ley.\nPárrafo añadido y publicado en la GOCDMX el 28 de noviembre de 2023\nARTÍCULO 89.- Todos los trabajos de mantenimiento, mejoramiento, fomento, forestación, reforestación y conservación a desarrollarse en las áreas verdes, deberán sujetarse a la normatividad que establezca la\nSecretaría.\nARTÍCULO 89 Bis. En todo caso, la autorización para el derribo, poda o trasplante del arbolado en suelo de conservación, áreas de valor ambiental y áreas naturales protegidas, se limitará a medidas fitosanitarias o de prevención de incendios.\nARTÍCULO 90. En caso de dañar un área verde, el responsable deberá reparar los daños causados, en los siguientes términos:\nI. Restaurando el área afectada; o\nII. Llevando a cabo las acciones de compensación que se requieran a efecto de que se restituya un área equivalente a la afectada, en el sitio más próximo posible a ésta.\nLas alternativas referidas deberán ser consideradas por las autoridades competentes en el orden en que se enuncian.\nLa reparación de los daños causados a las áreas verdes podrá ordenarse por las autoridades competentes, como medida correctiva o sanción.\nExcepcionalmente, en caso de que el daño realizado sea irreparable en términos de las fracciones I y II del presente artículo, el responsable deberá pagar una compensación económica que deberá destinarse al fondo ambiental público, a efecto de aplicarse a restauración o compensación de áreas afectadas.\nLo anterior, sin perjuicio de la aplicación de las medidas correctivas o sanciones adicionales que sean procedentes por infracciones a lo dispuesto en la presente ley.\n\nCAPÍTULO II BIS\nÁREAS DE VALOR AMBIENTAL\nARTÍCULO 90 Bis. Las categorías de áreas de valor ambiental de competencia del Distrito Federal, son:\nI. Bosques Urbanos, y\nII. Barrancas.\nARTÍCULO 90 Bis 1. - Los bosques urbanos son las áreas de valor ambiental que se localizan en suelo urbano, en las que predominan especies de flora arbórea y arbustiva y se distribuyen otras especies de vida silvestre asociadas y representativas de la biodiversidad, así como especies introducidas para mejorar su valor ambiental, estético, científico, educativo, recreativo, histórico o turístico, o bien, por otras razones análogas de interés general, cuya extensión y características contribuyen a mantener la calid ad del ambiente en el Distrito Federal.\nARTÍCULO 90 Bis 2.- Se deroga.\nARTÍCULO 90 Bis 3.- Las áreas de valor ambiental bajo la categoría de bosques urbanos se establecerán mediante decreto del Jefe de Gobierno, el cual deberá contener, además de los requisitos establecidos en las fracciones II, IV y VI del artículo 94 de esta Ley, las siguientes:\nI.- La categoría de área de valor ambiental que se constituye, así como la finalidad y objetivos de su declaratoria,\nII.- Limitaciones y modalidades al uso del suelo y destinos, así como, en su caso, los lineamientos para el manejo de los recursos naturales del área;\nIII.- Los responsables de su manejo, y\nIV. La determinación y especificación de los elementos naturales y la biodiversidad que pretenda restaurarse, rehabilitarse o conservarse.\nLas barrancas del Distrito Federal son áreas de valor ambiental. La Secretaría elaborará un diagnóstico ambiental para la formulación del programa de manejo observando las disposiciones contendidas en la\n\npresente Ley, el Programa de Ordenamiento Ecológico del Distrito Federal y el Programa de Desarrollo\nUrbano del Distrito Federal y los delegacionales aplicables.\nLa Secretaría solicitará la opinión de las delegaciones correspondientes, previo a la expedición de la declaratoria de un área de valor ambiental.\nARTÍCULO 90 Bis 4.- En el establecimiento, administración, manejo y vigilancia de las áreas de valor ambiental se aplicarán, en lo conducente, las disposiciones establecidas en el Capítulo de la presente Ley relativo a las áreas naturales protegidas.\nARTÍCULO 90 Bis 5.- Los programas de manejo de las áreas de valor ambiental que elabore la Secretaría, con la participación de la o las delegaciones correspondientes y demás participantes que determine el reglamento, deberán de contener, además de los requisitos establecidos e n las fracciones II, V, VI y VII del artículo 95 de esta Ley, los siguientes:\nI. Las características físicas, biológicas, rurales, culturales, sociales, recreativas y económicas del área;\nII.- La regulación del uso del suelo y, en su caso, del manejo de recursos naturales y de la realización de actividades en el área, y\nIII. Las acciones a realizar en el corto, mediano y largo plazos para la restauración, rehabilitación y preservación del área.\nARTÍCULO 90 Bis 6. Las prohibiciones que establece la presente Ley en relación con las áreas naturales protegidas, deberán observarse para las áreas de valor ambiental, además de la prohibición para el aprovechamiento o extracción de recursos naturales, salvo en aquellos casos que se determinen en el reglamento respectivo, observando las disposiciones de la presente Ley.\nARTÍCULO 90 Bis 7. Los bosques urbanos bajo la categoría de áreas de valor ambiental tendrán un Consejo\nRector Ciudadano, cuyo objeto es evaluar, planear, diseñar y sancionar, en coordinación con las autoridades competentes, los programas, proyectos y acciones que se pretendan desarrollar en estás, así como establecer los criterios que normen las decisiones administrativas en dichas Áreas de Valor Ambiental.\n\nEstos criterios serán considerados por las autoridades competentes para la administración de las Áreas de\nValor Ambiental, sin que estos sustituyan los actos de autoridad frente a los gobernados, mismos que invariablemente estarán fundados y motivados.\nEl Consejo Rector Ciudadano estará integrado por 7 ciudadanos reconocidos por sus actividades ambientales, preferentemente vecinos de las áreas, que serán designados por el Jefe de Gobierno y que durarán en su encargo cuatro años posteriores a su designación, pudiendo ratificarse su permanencia por un período de dos años adicionales, y sólo podrán retirarse del encargo por renuncia expresa o por remoción determinada por la mayoría de los miembros del Consejo.\nEl Consejo Rector Ciudadano estará organizado y funcionará en los términos del acuerdo que emita el Jefe de Gobierno para este efecto y tendrá las funciones que le establezca el Reglamento, además de las siguientes:\nI. Ser un órgano de planeación, evaluación y sanción de las acciones, programas y proyectos que se desarrollen en los bosques urbanos, así como de la aplicación de recursos públicos y privados:\nII. Participar en la elaboración de los proyectos de regulación sobre el funcionamiento de los bosques urbanos;\nIII. Emitir opinión, respecto el establecimiento de criterios para la expedición de autorizaciones, permisos, concesiones y demás actos jurídicos para la realización de actividades dentro de los bosques urbanos, que determine la autoridad competente;\nIV. Sancionar los Programas de Manejo de los bosques urbanos y sus modificaciones, antes de la aprobación por la autoridad competente;\nV. Emitir las recomendaciones y presentar proyectos para las tareas de conservación, mantenimiento y, en su caso, aprovechamiento de los bosques urbanos;\nVI. Colaborar con las autoridades en la persecución de fondos y/o financiamiento, para la conservación, aprovechamiento y mantenimiento de los bosques urbanos; y\nVII. Las demás que determine el Acuerdo que expida el Jefe de Gobierno.\n\nArtículo 90 Bis 8. Los cuerpos de agua naturales y artificiales dentro del territorio y bajo las competencias de la Ciudad de México, cuya extensión y características contribuyen a mantener la calidad del ambiente de la entidad, son áreas de valor ambiental.\nReforma publicada en la GOCDMX el 27 de octubre de 2022\nCAPÍTULO III\nÁREAS NATURALES PROTEGIDAS\nARTÍCULO 91.- Corresponde al Jefe de Gobierno del Distrito Federal el establecimiento de las áreas naturales protegidas no reservadas a la Federación, que se requieran para la preservación, cuidado, restauración, forestación, reforestación y mejoramiento ambiental. Su establecimiento y preservación es de utilidad pública y se realizará en forma concertada y corresponsable con la sociedad, así como con los propietarios y poseedores de los predios ubicados en la zona objeto del decreto o declaratoria respectiva.\nARTÍCULO 92. Las categorías de áreas naturales protegidas de competencia del Distrito Federal son:\nI. DEROGADA\nII. Zonas de Conservación Ecológicas;\nIII. Zonas de Protección Hidrológica y Ecológica;\nIV. Zonas Ecológicas y Culturales;\nV. Refugios de vida silvestre;\nVI. Zonas de Protección Especial;\nVII. Reservas Ecológicas Comunitarias; y\nVIII. Las demás establecidas por las disposiciones legales aplicables.\nARTÍCULO 92 Bis. Las zonas de conservación ecológica son aquéllas que contienen muestras representativas de uno o más ecosistemas en buen estado de preservación y que están destinadas a proteger los elementos naturales y procesos ecológicos que favorecen el equilibrio y bienestar social.\n\nARTÍCULO 92 Bis 1. Las zonas de protección hidrológica y ecológica, son aquellas que se establecen para la protección, preservación y restauración de sistemas hídricos naturales, así como su fauna, flora, suelo y subsuelo asociados.\nARTÍCULO 92 Bis 2. Las zonas ecológicas y culturales son aquellas con importantes valores ambientales y ecológicos, donde también se presentan elementos físicos, históricos o arqueológicos o se realizan usos y costumbres de importancia cultural.\nARTÍCULO 92 Bis 3. Los refugios de vida silvestre son aquellos que constituyen el hábitat natural de especies de fauna y flora que se encuentran en alguna categoría de protección especial o presentan una distribución restringida.\nARTÍCULO 92 Bis 4. Las Reservas Ecológicas Comunitarias son aquellas establecidas por pueblos, comunidades y ejidos en terrenos de su propiedad destinadas a la preservación, protección y restauración de la biodiversidad y del equilibrio ecológico, sin que se modifique el régimen de propiedad.\nLa Secretaría promoverá la expedición de la declaratoria correspondiente, mediante la cual se establecerá el programa de manejo del área por parte del promovente, con la participación de la Secretaría conforme a las atribuciones que al respecto se le otorgan en la presente Ley.\nARTÍCULO 92 Bis 5.- La administración y manejo de las áreas naturales protegidas propiedad del Gobierno del Distrito Federal corresponderá a la Secretaría. La Secretaría podrá suscribir convenios administrativos con las delegaciones a fin de que éstas se hagan cargo de la administración y manejo de las áreas naturales protegidas en su demarcación territorial. En el caso de las áreas naturales protegidas de propiedad social, su administración corresponderá a sus propietarios o poseedores o a la Secretaría, en el caso de suscribir convenios administrativos para tal fin con los pueblos, comunidades y ejidos.\nARTÍCULO 92 Bis 6. Las Zonas de Protección Especial son aquellas que se localizan en suelo de conservación y que tienen la característica de presentar escasa vegetación natural, vegetación inducida o vegetación fuertemente modificada y que por su extensión o características no pueden estar dentro de las otras categorías de áreas naturales protegidas, aun cuando mantienen importantes valores ambientales.\nARTÍCULO 93.- El Gobierno del Distrito federal podrá administrar las áreas naturales protegidas de índole federal, conforme a lo estipulado en la Ley General.\n\nARTÍCULO 93 Bis. Para el establecimiento de las áreas naturales protegidas deberán considerarse, al menos la presencia de ecosistemas naturales representativos, la importancia biológica o ecológica del sitio, y la importancia de los servicios ambientales generados.\nARTÍCULO 93 Bis 1.- En las áreas naturales protegidas se podrán realizar actividades de protección, preservación, restauración, forestación, reforestación y aprovechamiento sustentable y controlado de recursos naturales, investigación, educación ambiental, recreación y ecoturismo. El programa de manejo correspondiente establecerá cuáles de estas actividades están permitidas realizar de conformidad con las especificaciones de las categorías de áreas naturales protegidas que esta Ley y demás ordenamientos jurídicos aplicables establecen.\nEn las áreas naturales protegidas queda prohibido:\nI. El establecimiento de cualquier asentamiento humano irregular, y de nuevos asentamientos humanos regulares o su expansión territorial.\nII. La realización de actividades que afecten los ecosistemas del área de acuerdo con la Ley, su\nReglamento, las normas oficiales mexicanas, las normas ambientales para el Distrito Federal, el decreto de declaratoria del área, su programa de manejo o la evaluación de impacto ambiental respectiva;\nIII. La realización de actividades riesgosas;\nIV. Las emisiones contaminantes al aire, agua, suelo y subsuelo, así como el depósito o disposición de residuos de cualquier tipo y el uso de los equipos anticontaminantes sin autorización correspondiente;\nV. La extracción de suelo o materiales del subsuelo con fines distintos a los estrictamente científicos;\nVI. La interrupción o afectación del sistema hidrológico de la zona;\nVII. La realización de actividades cinegéticas o de explotación ilícitas de especies de fauna y flora silvestres, y\n\nVIII. Las demás actividades previstas en el decreto de creación y en las disposiciones jurídicas aplicables.\nARTÍCULO 93 Bis 2. En el otorgamiento o expedición de permisos, licencias, concesiones, o en general de autorizaciones a que se sujetará la realización de actividades culturales, deportivas o recreativas, así como el aprovechamiento no extractivo de los elementos y recursos naturales en áreas naturales protegidas competencia del Distrito Federal, se observarán las disposiciones de la presente Ley y demás disposiciones jurídicas aplicables.\nLa Secretaría y, en su caso, las delegaciones, expedirán las autorizaciones, permisos o licencias respectivos, tomando en cuenta lo dispuesto en el programa de manejo del área correspondiente. Las concesiones o permisos para el uso y aprovechamiento de los inmuebles patrimonio del gobierno del Distrito Federal, se ajustarán a la Ley de la materia.\nARTÍCULO 94.- Las áreas naturales protegidas de la competencia del Distrito Federal se establecerán mediante decreto del titular de la Administración Pública Local. Dicho decreto deberá contener:\nI. La categoría de área natural protegida que se constituye, así como la finalidad u objetivos de su declaratoria;\nII. Delimitación del área con descripción de poligonales, ubicación, superficie, medidas y linderos y, en su caso, zonificación;\nIII. Limitaciones y modalidades al uso del suelo, reservas y destinos, así como lineamientos para el manejo de los recursos naturales del área;\nIV. Descripción de las actividades que podrán llevarse a cabo en el área, sus limitaciones y modalidades;\nV. Responsables de su manejo;\nVI. Las causas de utilidad pública que sirvan de base para la expropiación del área por parte de la autoridad competente, cuando ésta se requiera en los términos de las disposiciones aplicables;\n\nVII. Lineamientos y plazo para que la Secretaría elabore el programa de manejo del área, mismos que deberán publicarse en la Gaceta Oficial del Distrito Federal; y\nVIII. La determinación y especificación de los elementos naturales o reservas de la biodiversidad cuya protección o conservación se pretenda lograr, en su caso.\nARTÍCULO 95.- El programa de manejo de las áreas naturales protegidas es el instrumento de planificación y normatividad que contendrá entre otros aspectos, las líneas de acción, criterios, lineamientos y en su caso, actividades específicas a las cuales se sujetará la administración y manejo de las mismas, deberá contener lo siguiente:\nI. Las características físicas, biológicas, culturales, sociales y económicas del área;\nII. Los objetivos del área;\nIII. La regulación de los usos de suelo, del manejo de recursos naturales y de la realización de actividades en el área y en sus distintas zonas, de acuerdo con sus condiciones ecológicas, las actividades compatibles con las mismas y con los programas de desarrollo urbano respectivos;\nIV. Las acciones a realizar en el corto, mediano y largo plazos para la conservación, restauración e incremento de los recursos naturales, para la investigación y educación ambiental y, en su caso, para el aprovechamiento racional del área y sus recursos;\nV. Las bases para la administración, mantenimiento y vigilancia del área;\nVI. El señalamiento de las disposiciones jurídicas ambientales aplicables; y\nVII. Los mecanismos de financiamiento del área.\nEn tanto se expide el programa de manejo correspondiente, la Secretaría emitirá mediante acuerdo administrativo las normas y criterios que deben observarse para la realización de cualquier actividad dentro de las áreas naturales protegidas, conforme a esta Ley, su reglamento y el decreto respectivo.\nARTÍCULO 96.- Las limitaciones y modalidades establecidas en las áreas naturales protegidas a los usos, reservas, provisiones, destinos y actividades son de utilidad pública y serán obligatorias para los propietarios o poseedores de los bienes localizados en las mismas. El ejercicio del derecho de propiedad,\n\nde posesión y cualquier otro derivado de la tenencia de los predios, se sujetará a dichas limitaciones y modalidades.\nARTÍCULO 97.- Los decretos mediante los cuales se establezcan áreas naturales protegidas, deberán publicarse en la Gaceta Oficial del Distrito Federal y se notificarán personalmente a los propietarios o poseedores de los predios afectados cuando se conocieren sus domicilios, en caso contrario se hará una segunda publicación en la misma Gaceta, que surtirá efectos de notificación personal.\nARTÍCULO 98.- La superficie materia del decreto, así como las limitaciones y modalidades a las que se sujetará, se incorporarán de inmediato al ordenamiento ecológico, a los programas de desarrollo urbano y a los instrumentos que se deriven de éstos, se inscribirán en el Registro Público de la Propiedad, se relacionarán en las constancias y certificados que el mismo expida y se inscribirán en el Registro de los\nPlanes y Programas para el Desarrollo Urbano del Distrito Federal.\nARTÍCULO 99.- La Secretaría, establecerá el Sistema Local de Áreas Naturales Protegidas y llevará el registro e inventario de acuerdo a su clasificación, en los que consignará los datos de inscripción, así como un resumen de la información contenida en los decretos, programas de manejo y demás instrumentos correspondientes, la cual deberá actualizarse anualmente.\nARTÍCULO 100.- Todos los actos, convenios y contratos relativos a la propiedad, posesión o cualquier derecho relacionado con bienes inmuebles ubicados en áreas naturales protegidas de la competencia del\nDistrito Federal, deberán señalar las limitaciones y modalidades del predio respectivo que consten en el decreto correspondiente, así como sus datos de inscripción en el Registro Público de la Propiedad. El incumplimiento de lo dispuesto en este artículo producirá la nulidad absoluta del acto, convenio o contrato respectivo.\nARTÍCULO 101.- Los notarios y los demás fedatarios públicos sólo podrán autorizar las escrituras públicas, actos jurídicos, convenios o contratos en los que intervengan, cuando se cumpla lo dispuesto en el artículo anterior.\nNo se inscribirán en el Registro Público de la Propiedad los actos jurídicos, convenios o contratos que no se ajusten al decreto y a las limitaciones y modalidades establecidas en él.\nARTÍCULO 102.- Cualquier persona podrá solicitar por escrito a la Secretaría, el establecimiento de un área natural protegida, para lo cual dicha dependencia dictaminará su procedencia.\n\nARTÍCULO 103.- La Secretaría integrará el Registro de Áreas Naturales Protegidas del Distrito Federal, en el que se inscribirán los decretos mediante los cuales se declaren las áreas naturales protegidas y los instrumentos que los modifiquen, el cual podrá ser consultado por cualquier persona que así lo solicite y deberá ser integrado al sistema de información ambiental del Distrito Federal.\nCAPÍTULO III Bis\nÁREAS COMUNITARIAS DE CONSERVACIÓN ECOLÓGICA\nARTÍCULO 103 Bis. Las Áreas Comunitarias de Conservación Ecológica se establecen por acuerdo del ejecutivo local con los ejidos y comunidades y se mantendrán como tal, con el consentimiento de éstas, expresado en Asamblea, así como la suscripción de un Convenio de Concertación de Acciones con el\nGobierno del Distrito Federal.\nARTÍCULO 103 Bis 1. Una vez suscrito el convenio respectivo, el titular de la Administración Pública Local emitirá la declaratoria constitutiva del Área Comunitaria de Conservación Ecológica, y ambos instrumentos serán publicados en la Gaceta Oficial del Distrito Federal.\nLa declaratoria de un Área Comunitaria de Conservación Ecológica no modifica el régimen de propiedad y no tendrá como propósito la expropiación.\nARTÍCULO 103 Bis 2. El Convenio de Concertación de Acciones deberá contener, cuando menos:\nI. La finalidad y objetivos de la declaratoria;\nII. La delimitación del área que se destinará a la preservación, protección y restauración de la biodiversidad y los servicios ambientales, con la descripción de poligonales, ubicación, superficie, medidas y linderos y, en su caso, zonificación;\nIII. Las obligaciones de las partes para asegurar la conservación y vigilancia de la Reserva; y\nIV. Los lineamientos y plazo para que se elabore el programa de manejo del Área Comunitaria de Conservación Ecológica.\nARTÍCULO 103 Bis 3. La administración y manejo de las Áreas Comunitarias de Conservación Ecológica corresponde a los ejidos o comunidades que detentan su propiedad.\n\nARTÍCULO 103 Bis 4. El programa de manejo del Área de Conservación Ecológica es el instrumento de planeación y normatividad, contendrá entre otros aspectos, las líneas de acción, criterios, lineamientos y, en su caso, actividades específicas a las cuales se sujetará su administración y manejo. Deberá contener lo siguiente:\nI. Las características físicas, biológicas, culturales, sociales y económicas del área;\nII. Los objetivos del área;\nIII. Las limitaciones y regulación sobre el manejo de recursos naturales y la realización de actividades en el área y en sus distintas zonas, de acuerdo con sus condiciones ecológicas, las actividades compatibles con las mismas y con los objetivos del área;\nIV. Las acciones a realizar en el corto, mediano y largo plazo para la conservación, restauración e incremento de los recursos naturales, para la investigación y educación ambiental y, en su caso, para el aprovechamiento racional del área y sus recursos;\nV. Las bases para la administración, mantenimiento y vigilancia del área;\nVI. El señalamiento de las disposiciones jurídicas ambientales aplicables; y\nVII. Los mecanismos de financiamiento del área, incluido el programa de inversión para la conservación.\nARTÍCULO 103 Bis 5. El programa de manejo del Área Comunitaria de Conservación Ecológica será elaborado por el ejido o comunidad que corresponda, quien podrá ser asistido en el proceso por instituciones u organizaciones con experiencia en la conservación y manejo de recursos naturales. Su contenido deberá tener el consenso y validación de los miembros del pueblo, comunidad o ejido, expresada mediante asamblea.\nEl programa de manejo deberá ser aprobado conjuntamente por la Secretaría y por la Secretaría de\nDesarrollo Rural y Equidad para las Comunidades y publicado en la Gaceta Oficial del Distrito Federal.\nLas disposiciones del programa de manejo se integrarán en los programas de Ordenamiento Ecológico del\nDistrito Federal.\n\nARTÍCULO 103 bis 6. Las limitaciones y regulación sobre el manejo de recursos naturales y la realización de actividades establecidas en las Áreas Comunitarias de Conservación Ecológica son de utilidad pública y serán obligatorias para los propietarios o poseedores de los terrenos y los bienes localizados en las mismas.\nARTÍCULO 103 Bis 7. Para apoyar económicamente a los núcleos agrarios que determinen el establecimiento de Áreas Comunitarias de Conservación Ecológica, la Secretaría formulará y publicará en la Gaceta Oficial del Distrito Federal, el Programa de Retribución por la Conservación de Servicios\nAmbientales en Áreas Comunitarias de Conservación Ecológica.\nEn dicho programa se establecerán los montos máximos y condiciones mínimas de las retribuciones provenientes del Fondo Ambiental Público, para que los pueblos, comunidades y ejidos realicen la administración, manejo, conservación y vigilancia de dichas áreas, e incluirá el pago de estímulos por la conservación de los servicios ambientales.\nCAPÍTULO IV\nCONSERVACIÓN Y APROVECHAMIENTO SUSTENTABLE DEL AGUA\nARTÍCULO 104.- La Secretaría regulará la eliminación gradual del uso de agua potable en los procesos en que se pueda utilizar aguas de reuso o tratadas.\nARTÍCULO 105.- Para el aprovechamiento sustentable de las aguas de competencia del Distrito Federal, así como el uso adecuado del agua que se utiliza en los centros de población, se considerarán los criterios siguientes:\nI. Corresponde al Gobierno del Distrito Federal y a la sociedad la protección de los elementos hidrológicos, ecosistemas acuáticos y del equilibrio de los recursos naturales que intervienen en su ciclo;\nII. El aprovechamiento sustentable de los recursos naturales que comprenden los ecosistemas acuáticos deben realizarse de manera que no se afecte su equilibrio ecológico;\nIII. Para mantener la integridad y el equilibrio de los elementos naturales que intervienen en el ciclo hidrológico, se deberá considerar la protección de suelos y áreas boscosas así como el\n\nmantenimiento de caudales básicos y fuentes naturales de las corrientes de agua, para mantener la capacidad de recarga de los acuíferos;\nIV. La conservación y el aprovechamiento sustentable del agua, es responsabilidad de la autoridad y de los usuarios, así como de quienes realicen obras o actividades que afecten dicho elemento;\nV. El agua debe ser aprovechada y distribuida con equidad, calidad y eficiencia, dando preferencia a la satisfacción de las necesidades humanas y la protección a la salud;\nVI. El agua tratada constituye una forma de prevenir la afectación del amb iente y sus ecosistemas;\nVII. El reuso del agua y el aprovechamiento del agua tratada es una forma eficiente de utilizar y conservar el recurso; y\nVIII. El aprovechamiento del agua de lluvia constituye una alternativa para incrementar la recarga de los acuíferos así como para la utilización de ésta en actividades que no requieran de agua potable, así como también para el consumo humano, en cuyo caso, deberá dársele tratamiento de potabilización, de acuerdo con los criterios técnicos correspondientes.\nARTÍCULO 106.- Los criterios anteriores serán considerados en:\nI. La formulación e integración de programas relacionados con el aprovechamiento del agua;\nII. El otorgamiento y revocación de concesiones, permisos, licencias, las autorizaciones de impacto ambiental y en general toda clase de autorizaciones para el aprovechamiento de los recursos naturales no reservados a la Federación, que afecten o puedan afectar el ciclo hidrológico;\nIII. El otorgamiento de autorizaciones para la desviación, extracción o derivación de aguas de propiedad del Distrito Federal;\nIV. La operación y administración de los sistemas de agua potable y alcantarillado que sirven a los centros de población e industrias;\n\nV. Los programas parciales y delegacionales de desarrollo urbano,\nVI. La construcción de resiliencia para una gestión integrada de los recursos hídricos;\nVII. El diseño y ubicación de proyectos urbanos; y\nVIII. La ejecución de proyectos de estructuras que permitan el almacenamiento, la utilización, la infiltración y el consumo del agua de lluvia.\nARTÍCULO 107.- Con el propósito de asegurar la disponibilidad del agua y abatir los niveles de desperdicio, la Secretaría deberá:\nI. Proteger las zonas de recarga;\nII. Promover acciones para el ahorro y uso eficiente del agua, el tratamiento de aguas residuales y su reuso, así como la captación y aprovechamiento de las aguas pluviales;\nIII. Establecer las zonas críticas y formular programas especiales para éstas;\nIV. Desarrollar programas de información y educación que fomenten una cultura para el aprovechamiento racional del agua; y\nV. Considerar las disponibilidades de agua en la evaluación del impacto ambiental de las obras o proyectos que se sometan a su consideración.\nARTÍCULO 108.- Son obligaciones de los habitantes del Distrito Federal:\nI. Usar racionalmente el agua;\nII. Reparar las fugas de agua dentro de sus predios;\nIII. Denunciar las fugas de agua en otros predios particulares o en la vía pública; y\nIV. La observancia de la normatividad para el uso, reuso y reciclaje del agua y el aprovechamiento del agua pluvial.\n\nARTÍCULO 109.- La Secretaría realizará las acciones necesarias para evitar o, en su caso, controlar procesos de degradación de las aguas.\nARTÍCULO 110.- Queda estrictamente prohibido el relleno, secado o uso diferente al que tienen, los cuerpos de agua superficiales del Distrito Federal.\nCAPÍTULO V\nCONSERVACIÓN Y APROVECHAMIENTO SUSTENTABLE DEL SUELO\nARTÍCULO 111.- Para la conservación, restauración, protección y aprovechamiento sustentable del suelo en el territorio del Distrito Federal, se considerarán los siguientes criterios:\nI. El uso del suelo debe ser compatible con su aptitud natural, preservando en todo momento los recursos naturales de la Tierra y no debe alterar el equilibrio de los ecosistemas;\nII. La realización de las obras públicas o privadas que por sí mismas puedan provocar deterioro de los suelos, deben incluir acciones equivalentes de regeneración, recuperación y restablecimiento de su aptitud natural;\nIII. La necesidad de prevenir o reducir su erosión, deterioro de las propiedades físicas, químicas o biológicas del suelo y la pérdida de la vegetación natural;\nIV. En las zonas afectadas por fenómenos de degradación, salinización o desertificación, deberán llevarse a cabo las acciones de regeneración, recuperación y rehabilitación necesarias para su restauración;\nV. La acumulación o depósito de residuos constituye una fuente de contaminación que altera los procesos biológicos de los suelos; y\nVI. Deben evitarse las prácticas que causen alteraciones en el suelo y perjudiquen su aprovechamiento, uso o explotación, o que provoquen riesgos o problemas de salud.\nARTÍCULO 112.- Los criterios anteriores serán considerados en:\n\nI. Los apoyos a las actividades agropecuarias que otorguen las dependencias de la\nAdministración Pública del Distrito Federal, de manera directa o indirecta, para que promuevan la progresiva incorporación de cultivos compatibles con la conservación del equilibrio ecológico y la restauración de los ecosistemas;\nI Bis. La formulación y desarrollo de programas que establezcan mecanismos de retribución por la protección, conservación o ampliación de servicios ambientales y por la realización de actividades vinculadas al desarrollo rural, equitativo y sustentable en suelo de conservación;\nII. La autorización de fraccionamientos habitacionales y asentamientos humanos en general;\nIII. La modificación y elaboración de los programas de desarrollo urbano;\nIV. El establecimiento de usos, reservas y destinos, en los programas de desarrollo urbano, así como en las acciones de restauración y conservación de los centros de población;\nV. Las disposiciones, programas y lineamientos técnicos para la conservación, protección y restauración de los suelos, en las actividades agropecuarias, mineras, forestales e hidráulicas;\nVI. Las actividades de exploración, explotación, extracción y aprovechamiento de materiales o sustancias, no reservadas a la Federación, así como las excavaciones y todas aquellas acciones que alteren los recursos y la vegetación forestal;\nVII. La formulación del programa de ordenamiento ecológico; y\nVIII. La evaluación del impacto ambiental de las obras o proyectos que en su caso se sometan a consideración de la Secretaría.\nCAPÍTULO VI\nRESTAURACIÓN DE ZONAS AFECTADAS\nARTÍCULO 113.- En aquellas áreas de los suelos de conservación que presenten procesos de degradación o desertificación, o grave deterioro ecológico, el Jefe de Gobierno del Distrito Federal, por causa de interés público y tomando en consideración a la sociedad, podrá expedir declaratorias de zonas de restauración\n\necológica con la finalidad de establecer las modalidades a los derechos de propiedad que procedan para regular usos del suelo y limitar la realización de actividades que estén ocasionando dichos fenómenos.\nARTÍCULO 114.- Están obligados a restaurar el suelo, subsuelo, acuífero y los demás recursos naturales afectados, quienes por cualquier causa los contaminen o deterioren, de acuerdo con la presente Ley y las normas ambientales para el Distrito Federal.\nARTÍCULO 115.- En los suelos de conservación que presenten deterioros ecológicos, la Secretaría formulará programas de restauración de los elementos naturales, con el propósito de que se lleven a cabo las acciones necesarias para la recuperación, forestación y reforestación y restablecimiento de las condiciones que propicien la evolución y continuidad de los procesos naturales que en ellos se desarrollan.\nEn la formulación, ejecución y seguimiento de dichos programas, la Secretaría deberá de promover la participación las instituciones federales a través de un convenio, de las delegaciones, propietarios, poseedores, organizaciones sociales, instituciones públicas o privadas y demás personas interesadas.\nCAPÍTULO VII\nPROTECCIÓN Y APROVECHAMIENTO DE LA FLORA Y FAUNA\nARTÍCULO 116.- Para coadyuvar a la conservación y aprovechamiento sustentable de la flora y fauna, la\nSecretaría, previo los estudios correspondientes, podrá promover ante las autoridades federales competentes:\nI. El establecimiento de vedas o modificación de vedas;\nII. La declaración de especies amenazadas, raras, en peligro de extinción, endémicas o sujetas a protección especial;\nIII. La creación de áreas de refugio para protección de las especies de flora y fauna; y\nIV. La modificación o revocación de concesiones, permisos y, en general, de toda clase de autorizaciones para el aprovechamiento, posesión, administración, conservación, repoblación, propagación y desarrollo de la fora y fauna silvestres.\n\nARTÍCULO 117.- Dentro del territorio del Distrito Federal, la Secretaría coadyuvará con las autoridades federales para la prevención y erradicación del tráfico de especies de flora y fauna silvestre, de conformidad con la legislación aplicable.\nARTÍCULO 118. Las Alcaldías en coordinación con la Secretaría del Medio Ambiente, tendrán a su cargo la conservación, preservación, mantenimiento, protección, restitución y desarrollo, así como la implementación de tratamientos fitosanitarios de los árboles que se encuentren en su territorio, con productos inofensivos para el entorno natural y humano, privilegiando los tratamientos naturales por encima de los industrializados. Toda nueva plantación deberá incorporar sustratos mejorados o compostas en las cepas de plantación, mientras que todo árbol que se someta a tratamiento fitosanitario deberá integrar la descompactación y mejoramiento de suelo como elementos imprescindibles de su tratamiento.\nPárrafo reformado y publicado en la GOCDMX el 04 de agosto de 2023\nPara realizar la poda, derribo, desmoche o trasplante de árboles únicamente en los que casos que se señalan más adelante, se requiere contar con autorización previa de la Alcaldía respectiva, la cual deberá remitirse en un plazo no mayor a 20 días hábiles, contados a partir de que se haga la solicitud.\nReforma publicada en la GOCDMX el 27 de octubre de 2022\nLa Alcaldía podrá autorizar el derribo, poda o trasplante de árboles ubicados en bienes de dominio público o en propiedades particulares, únicamente cuando se requiere para salvaguarda de la integridad de las personas o sus bienes, en los siguientes casos:\nReforma publicada en la GOCDMX el 27 de octubre de 2022\nI. Cuando exista riesgo real y presente para las personas o para sus bienes inmuebles;\nII. Cuando exista riesgo real y presente para el patrimonio urbanístico o arquitectónico del\nDistrito Federal;\nIII. Cuando sean necesarias para el saneamiento del árbol; y\nIV. Cuando deban ejecutarse para evitar afectaciones significativas en la infraestructura del lugar donde se encuentren.\nEn todos los demás casos distintos a los que se señalan en las fracciones anteriores, será la Secretaría quien resuelva en el ámbito de su competencia.\nReforma publicada en la GOCDMX el 27 de octubre de 2022\n\nLa autorización a que se refiere el presente artículo deberá estar sustentada mediante un dictamen técnico emitido por la Alcaldía correspondiente que avale la factibilidad del derribo, poda o trasplante de árboles.\nReforma publicada en la GOCDMX el 27 de octubre de 2022\nLos trabajos que se deriven de la autorización que al efecto concede la Alcaldía de los que se señalan en las fracciones I a IV del presente artículo, deberán ser ejecutados en un plazo no mayor a 20 días hábiles contados a partir de la fecha en que se emita la misma, conforme a los parámetros y especificaciones establecidas en las Normas Ambientales aplicables para la Ciudad de México.\nReforma publicada en la GOCDMX el 27 de octubre de 2022\nAsimismo, la poda será procedente cuando se requiera para mejorar o restaurar la estructura de los árboles.\nEn todo caso, el derribo de árboles sólo será procedente cuando no exista otra alternativa viable.\nLa Secretaría expedirá conforme a las disposiciones previstas en esta ley, las normas ambientales en las que se establecen los requisitos y especificaciones técnicas que deberán cumplir las personas físicas o morales, tanto públicas como privadas, que realicen la poda, derribo y trasplante de árboles en la Ciudad de México.\nReforma publicada en la GOCDMX el 27 de octubre de 2022\nLo dispuesto en este capítulo, así como en el Reglamento de la presente Ley y en las normas ambientales conducentes, serán aplicable a las actividades relacionadas con la poda, derribo o trasplante de árboles, siempre que dichas actividades no se realicen en terrenos forestales o de aptitud preferentemente forestal.\nARTÍCULO 119. Las personas que realicen el derribo de árboles deberán llevar a cabo la restitución correspondiente mediante la compensación física o económica. En todo caso se deberá tener como primera alternativa la restitución física a efecto de conservar la cubierta vegetal necesaria para un equilibrio ecológico en el Distrito Federal, y sólo en los supuestos que ello no sea posible se considerará la compensación económica.\nPara efectos de que se cumpla lo anterior, en la autorización respectiva se citarán las medidas compensatorias procedentes. Así mismo, la Secretaría expedirá las normas ambientales en las que se establezcan los requisitos y especificaciones técnicas que deberán cumplir las personas para la compensación física correspondiente.\n\nPara los efectos de la presente Ley, se equipara al derribo de árboles cualquier acto que provoque su muerte.\nARTÍCULO 120.- En la autorización se determinará el destino de los esquilmos o productos del derribo o poda de los árboles en vía pública o bienes de dominio público.\nARTÍCULO 120 Bis. Las acciones de inspección e imposición de medidas de seguridad, correctivas o de urgente aplicación y sanciones, respecto a las disposiciones previstas en este capítulo sobre poda, derribo y trasplante de árboles, corresponden a las Delegaciones Políticas en su respectiva circunscripción territorial, sin perjuicio de las atribuciones conferidas a otras autoridades por cuestiones diversas.\nARTÍCULO 121.- La Secretaría establecerá en los programas respectivos las medidas necesarias para evitar los incendios forestales.\nCAPÍTULO VIII\nAPROVECHAMIENTO DE LOS RECURSOS ENERGÉTICOS\nARTÍCULO 122.- La Secretaría celebrará acuerdos y convenios para el establecimiento de programas que permitan el ahorro de energía y su utilización eficiente, así como para el desarrollo de diferentes fuentes de energía, incluidas las fuentes renovables, conforme a los principios establecidos en la presente Ley.\nARTICULO 122 BIS.- Las Dependencias, delegaciones, órganos desconcentrados, entidades, órganos autónomos y órganos de gobierno del Distrito Federal, deberán en la medida de sus posibilidades presupuestarias, instalar algún tipo de tecnología solar, a fin de reducir el uso de energía y la emisión de gases de efecto invernadero.\nTITULO QUINTO\nDE LA PREVENCIÓN, CONTROL Y ACCIONES CONTRA LA\nCONTAMINACIÓN AMBIENTAL\nCAPÍTULO I\nDISPOSICIONES GENERALES\n\nARTÍCULO 123.- Todas Las personas están obligadas a cumplir con los requisitos y límites de emisiones contaminantes a la atmósfera, agua, suelo, subsuelo, redes de drenaje y alcantarillado y cuerpos receptores del Distrito Federal establecidos por las normas aplicables o las condiciones particulares de descarga que emita la Secretaría, así como a utilizar los equipos, dispositivos y sistemas de reducción de emisiones que determine dicha dependencia. Quedan comprendidos la generación de residuos sólidos, de contaminantes visuales y de la emisión de contaminantes de ruido, vibraciones, energía térmica, lumínica y olores, de acuerdo con las disposiciones jurídicas aplicables.\nCAPITULO II\nDE LAS ACCIONES CORRECTIVAS DE LA CONTAMINACIÓN AMBIENTAL\nARTÍCULO 124.- La Secretaría vigilará que se lleven a cabo las acciones correctivas de sitios o zonas donde se declare la contaminación ambiental, de los recursos naturales o biodiversidad. Estas acciones deberán garantizar dentro de los avances científicos y tecnológicos que se trata de la metodología o técnica más adecuada para corregir el problema de afectación negativa.\nARTÍCULO 125.- Los estudios para la prevención y control de la contaminación ambiental y la restauración de los recursos considerarán:\nI. Diferentes alternativas de solución en caso de afectación al ambiente y a los recursos naturales, incluyendo tanto los factores beneficio-costo como factores ambientales y sociales, para garantizar la selección óptima de la tecnología aplicable; y\nII. Alternativas del proyecto de restauración y sus diversos efectos tanto positivos como negativos en el ambiente y recursos naturales.\nARTÍCULO 126.- Queda prohibido emitir o descargar contaminantes a la atmósfera, el agua y los suelos que ocasionen o puedan ocasionar desequilibrios ecológicos, daños al ambiente o afecten la salud.\nEn todas las descargas de contaminantes a la atmósfera, al agua y los suelos, deberán ser observadas las previsiones de la Ley General, esta Ley, sus disposiciones reglamentarias, así como las normas oficiales mexicanas y normas ambientales del Distrito Federal que al efecto se expidan.\nARTÍCULO 127.- La Secretaría, en los términos que señalen el reglamento de esta Ley, integrará y mantendrá actualizado, un inventario de emisiones a la atmósfera, descargas de aguas residuales,\n\nmateriales y residuos, el registro de emisiones y transferencia de contaminantes y coordinará la administración de los registros que establece la Ley y creará un sistema consolidado de información basado en las autorizaciones, licencias o permisos que en la materia se otorguen.\nARTÍCULO 128.- La Secretaría en coordinación con las autoridades federales y locales, establecerá un sistema de información relativo a los impactos en la salud provocados por la exposición a la contaminación del aire, agua y suelo.\nARTÍCULO 129.- La Secretaría podrá emitir lineamientos y criterios obligatorios para que la actividad de la administración pública del Distrito Federal en materia de obra pública y de adquisiciones de bienes muebles tome en consideración los aspectos de conservación ambiental, así como de ahorro de energía eléctrica y agua y de mínima generación de todo tipo de residuos sólidos y de aguas residuales.\nCAPÍTULO III\nPREVENCIÓN Y CONTROL DE LA CONTAMINACIÓN DE LA ATMÓSFERA\nSección I\nDisposiciones Generales\nARTÍCULO 130.- Las disposiciones del presente capítulo son aplicables a las fuentes fijas y móviles de jurisdicción local.\nARTÍCULO 131.- Para la protección a la atmósfera se considerarán los siguientes criterios:\nI. Las políticas y programas de las autoridades ambientales deberán estar dirigidas a garantizar que la calidad del aire sea satisfactoria en el Distrito Federal con base en los niveles máximos permisibles de emisión de contaminantes a la atmósfera, establecidos en las normas oficiales mexicanas y demás normativa aplicable; y\nII. Las emisiones de todo tipo de contaminantes a la atmósfera, sean de fuentes fijas o móviles, deben ser prevenidas, reguladas, reducidas y controladas, para asegurar una calidad del aire satisfactoria para la salud y bienestar de la población y el mantenimiento del equilibrio ecológico.\nARTÍCULO 132.- Los criterios anteriores serán considerados en:\n\nI. La expedición de normas ambientales del Distrito Federal para la prevención y control de la contaminación de la atmósfera;\nII. La ordenación, regulación y designación de áreas y zonas industriales, así como en la determinación de los usos de suelo que establezcan los programas de desarrollo urbano respectivos, particularmente en lo relativo a las condiciones topográficas, climatológicas y meteorológicas para asegurar la adecuada dispersión de contaminantes;\nIII. La clasificación de áreas o zonas atmosféricas, de acuerdo a su capacidad de asimilación o dilución, y la carga de contaminantes que estos puedan recibir; y\nIV. El otorgamiento de todo tipo de autorizaciones, licencias, registros o permisos para emitir contaminantes a la atmósfera.\nARTÍCULO 133.- Para regular, prevenir, controlar, reducir o evitar la contaminación de la atmósfera, la\nSecretaría tendrá las siguientes facultades:\nI. Coordinarse con la Federación, entidades federativas y municipios de la zona conurbada para la planeación y ejecución de acciones coordinadas en materia de gestión de la calidad del aire;\nII. Elaborar un programa local de gestión de calidad del aire, sujeto a revisión y ajuste periódico, con base en los niveles máximos permisibles de emisión de contaminantes a la atmósfera, establecidos en las normas oficiales mexicanas y demás normativa aplicable;\nIII. Requerir a los responsables de fuentes emisoras de su competencia, el cumplimiento de los limites máximos permisibles de emisión de contaminantes, las normas oficiales mexicanas y las normas ambientales para el Distrito Federal, de conformidad con esta Ley, la Ley General, en materias de competencia local, y sus reglamentos;\nIV. Promover ante los responsables de la operación de fuentes contaminantes, la aplicación de la mejor tecnología disponible, con el propósito de reducir sus emisiones a la atmósfera;\nV. Integrar y mantener actualizado el inventario de las fuentes emisoras de contaminantes a la atmósfera de su competencia;\n\nVI. Establecer y operar sistemas de monitoreo de la calidad del aire en el Distrito Federal;\nVII. Expedir normas ambientales del Distrito Federal para regular las emisiones provenientes de fuentes fijas y móviles que no sean de jurisdicción federal, y las medidas de tránsito, y en su caso, la suspensión de circulación, en casos graves de contaminación;\nVIII. Elaborar y emitir un Pronóstico de la Calidad del Aire, en forma diaria, en función de los sistemas meteorológicos:\nIX. Expedir normas ambientales del Distrito Federal para regular las emisiones provenientes de fuentes fijas y móviles que no sean de jurisdicción federal, y las medidas de tránsito, y en su caso, la suspensión de circulación, en casos graves de contaminación;\nX. Tomar las medidas necesarias para prevenir, regular y controlar las contingencias ambientales por contaminación atmosférica.\nXI. Establecer y operar sistemas de verificación de emisiones de automotores en circulación, y en su caso, expedir la constancia de verificación de emisiones;\nXII. Aplicar las normas oficiales mexicanas y normas ambientales del Distrito Federal para la protección de la atmósfera en las materias y supuestos de su competencia;\nXIII. Requerir la instalación de equipos o sistemas de control de emisiones a quienes realicen actividades que las generen;\nXIV. Establecer y operar sistemas de verificación de emisiones de automotores en circulación, y en su caso, expedir la constancia de verificación de emisiones;\nXV. Proponer el monto de las tarifas que deberán cubrirse por los servicios de verificación de automotores en circulación;\nXVI. Llevar un registro de los centros de verificación de automotores en circulación, y mantener un informe actualizado de los resultados obtenidos;\n\nXVII. Entregar, cuando proceda, a los propietarios de vehículos automotores, el documento que acredite que dicha fuente no rebasa los límites máximos permisibles de emisión, conforme a las normas oficiales mexicanas y normas ambientales para el Distrito Federal; y\nXVIII. Fomentar la participación de la sociedad en el desarrollo de programas para impulsar alternativas de transporte que reduzcan el uso de vehículos particulares.\nARTÍCULO 134.- Para prevenir y controlar la contaminación de la atmósfera, las Delegaciones, tomarán las medidas necesarias en coordinación con la Secretaría.\nSección II\nControl De Emisiones Contaminantes Provenientes De Fuentes\nFijas\nARTÍCULO 135.- Para la operación y funcionamiento de las fuentes fijas de jurisdicción local que emitan o puedan emitir olores, gases o partículas sólidas o líquidas a la atmósfera, se requerirá la Manifestación\nAmbiental Única de la Ciudad de México que expedirá la Secretaría a los interesados que demuestren cumplir con los requisitos y límites determinados en las normas correspondientes y cumplir además con las siguientes obligaciones:\nReforma publicada en la GOCDMX el 27 de febrero de 2023\nI. Emplear equipos y sistemas que controlen las emisiones a la atmósfera, para que no rebasen los niveles máximos permisibles establecidos en las normas oficiales mexicanas y las normas ambientales locales correspondientes;\nII. Integrar un inventario anual de sus emisiones contaminantes a la atmósfera, en el formato que determine la Secretaría;\nIII. Instalar plataformas y puertos de muestreo en chimeneas para realizar la medición de emisiones en campo, de acuerdo a lo establecido en las normas correspondientes;\nIV. Medir sus emisiones contaminantes a la atmósfera, registrar los resultados en el formato que determine la Secretaría y remitir a ésta la información que se determine en el reglamento, a fin de demostrar que opera dentro de los límites permisibles;\n\nV. Llevar una bitácora de operación y mantenimiento de sus equipos de combustión, de proceso y de control;\nVI. Dar aviso anticipado a la Secretaría del inicio de operación de sus procesos, en el caso de paros programados y de inmediato en el caso de que éstos sean circunstanciales, si ellos pueden provocar contaminación; y\nVII. Dar aviso inmediato a la Secretaría en el caso de falla del equipo o sistema de control.\nLa Secretaría, de conformidad con lo que establezca el reglamento de esta Ley, determinará los casos de fuentes fijas que por los niveles de emisión de contaminantes quedarán exentos del cumplimiento de las obligaciones a que se refiere este artículo.\nARTÍCULO 136.- Derogado\nARTÍCULO 137.- Derogado\nARTÍCULO 138.- En materia de prevención y control de la contaminación atmosférica producida por fuentes fijas, la Secretaría establecerá las medidas preventivas y correctivas para reducir las emisiones contaminantes; y promoverá ante los responsables de operación de las fuentes, la aplicación de nuevas tecnologías con el propósito de reducir sus emisiones a la atmósfera.\nLos responsables de las fuentes fijas podrán solicitar su exención al Programa de Contingencias\nAmbientales Atmosféricas, a través del formato que determine la Secretaría y que además demuestre cumplir con el marco normativo vigente y programas de contingencias correspondientes, así mismo podrán solicitarla todas las fuentes fijas que operen y apliquen tecnologías encaminadas a la reducción de sus emisiones a la atmósfera.\nSección III\nControl De Emisiones Provenientes De Fuentes Móviles\nARTÍCULO 139.- La Secretaría podrá limitar la circulación de vehículos automotores en la Ciudad de México, con base a los niveles máximos permisibles de emisión de contaminantes a la atmosfera, establecidos en las normas oficiales mexicanas, el Programa Hoy No Circula y demás normativa aplicable, incluyendo los que cuenten con placas expedidas por la Secretaría de Infraestructura, Comunicaciones y Transportes, por\n\notras entidades federativas o por el extranjero, para prevenir y reducir las emisiones contaminantes, en los términos de las disposiciones jurídicas aplicables.\nArtículo modificado y publicado en la GOCDMX el 04 de mayo de 2023\nARTÍCULO 139 Bis.- El Programa Hoy No Circula, al que se refiere el artículo 139 de esta Ley, deberá establecer las medidas aplicables a la circulación vehicular de fuentes móviles o vehículos automotores, con el objetivo de prevenir, minimizar y controlar la emisión de contaminantes provenientes de fuentes móviles que circulan en la Ciudad de México.\nLas medidas a la circulación de fuentes de vehículos o móviles, podrán considerar dentro de las exenciones de circulación a aquellos vehículos utilizados por productores agropecuarios, para transportar mercancías y productos de carácter perecedero, para su distribución y comercialización en la Ciudad de México, de conformidad con los criterios que expida la Secretaría en el Programa Hoy No Circula.\nPara efectos de este artículo, se entenderá por productores, a las personas físicas o morales que se dediquen a actividades agropecuarias.\nArtículo añadido y publicado en la GOCDMX el 04 de mayo de 2023\nARTÍCULO 140.- Los propietarios o poseedores de vehículos automotores en circulación matriculados en el\nDistrito Federal, deberán someter sus unidades a la verificación de emisiones contaminantes, en los centros de verificación autorizados por la Secretaría dentro del periodo que le corresponda en los términos del programa de verificación vehicular obligatoria que al efecto se expida y, en su caso, reparar los sistemas de emisión de contaminantes y sustituir los equipos y dispositivos que no funcionen adecuadamente, en los términos que determine el Programa de Verificación correspondiente.\nARTÍCULO 141.- El propietario o poseedor del vehículo deberá pagar al centro de verificación respectivo, la tarifa autorizada por la Secretaría en los términos del programa de verificación vehicular obligatoria para el\nDistrito Federal.\nARTÍCULO 142.- El propietario o poseedor de un vehículo que no haya realizado la verificación dentro del periodo que le corresponda, de acuerdo al calendario establecido en el programa de verificación vehicular obligatoria que al efecto se expida, podrá trasladarse en un término de treinta días únicamente a un taller mecánico o a un Centro de Verificación, previo pago de la multa correspondiente, independientemente de la multa que establezca el Reglamento de Tránsito del Distrito Federal.\nEn caso que no se apruebe la verificación dentro del plazo señalado, o si durante el mismo el vehículo circula hacia un lugar distinto al taller o al Centro de Verificación, se duplicará la multa, una vez pagada,\n\ncontará con un nuevo plazo de treinta días naturales a partir de su imposición para agredir dicho cumplimiento. De no presentarse éste dentro del plazo citado se duplicará la segunda multa señalada.\nARTÍCULO 143.- Si los vehículos en circulación rebasan los límites máximos permisibles de emisiones contaminantes fijados por las normas correspondientes, serán retirados de la misma por la autoridad competente, hasta que acredite su cumplimiento.\nARTÍCULO 144.- El propietario o poseedor del vehículo que incumpla con las normas oficiales mexicanas o las normas ambientales del Distrito Federal de acuerdo con el artículo anterior, tendrá un plazo de treinta días naturales para hacer las reparaciones necesarias y presentarlo a una nueva verificación. El vehículo podrá circular en ese período sólo para ser conducido al taller mecánico o ante el verificador ambiental.\nARTÍCULO 145.- La Secretaría, en coordinación con las Secretarías de Transporte y Vialidad, y de Seguridad\nPública podrán restringir y sujetar a horarios nocturnos el tránsito vehicular y las maniobras respectivas en la vía pública de los vehículos de carga, a fin de agilizar la circulación vehicular diurna y reducir, de esta forma, las emisiones contaminantes generadas por las fuentes móviles. Para estos efectos, el Jefe de\nGobierno del Distrito Federal publicará el Acuerdo correspondiente en la Gaceta Oficial.\nLa Secretaría podrá otorgar permisos, autorizaciones y acreditaciones a fabricantes, distribuidores, importadores y talleres, para el servicio de diagnóstico, reparación, comercialización e instalación de dispositivos y equipos de reducción de emisiones contaminantes y de sistemas de gas, conforme a las convocatorias que al efecto emita, en las que se incluyan las condiciones y características a que deba sujetarse su actividad.\nARTÍCULO 146.- Los vehículos que transporten en el Distrito Federal materiales o residuos peligrosos, deberán cumplir con los requisitos y condiciones establecidos en esta Ley y las demás disposiciones aplicables.\nARTÍCULO 147.- Los vehículos matriculados en el Distrito Federal, así como de servicio público de transporte de pasajeros o carga que requieran de sistemas, dispositivos y equipos para prevenir o minimizar sus emisiones contaminantes, lo harán conforme a las características o especificaciones que determine la\nSecretaría.\nARTÍCULO 148.- La Secretaría, en coordinación con la Secretaría de Transporte y Vialidad, deberá publicar en la Gaceta Oficial las determinaciones referidas en el artículo anterior.\n\nLos conductores y los propietarios de los vehículos serán solidariamente responsables del cumplimiento de lo establecido en el párrafo anterior.\nARTÍCULO 149.- Para prevenir y reducir la emisión de contaminantes a la atmósfera, la Secretaría promoverá ante las autoridades competentes, programas de ordenamiento vial y de agilización del transito vehicular.\nSección IV\nRegulación De Quemas A Cielo Abierto\nARTÍCULO 150.- Queda prohibida la quema de cualquier tipo de material o residuo sólido o líquido a cielo abierto salvo en los siguientes casos y previo aviso a la Secretaría:\nI. Para acciones de adiestramiento y capacitación de personal encargado del combate de incendios;\nII. Cuando con esta medida se evite un riesgo mayor a la comunidad o los elementos naturales, y medie recomendación de alguna autoridad de atención a emergencias; y\nIII. En caso de quemas agrícolas, cuando medie autorización de alguna autoridad forestal o agropecuaria.\nLa Secretaría establecerá las condicionantes y medidas de seguridad que deberán de observarse.\nSección V\nDe La Contaminación Térmica, Visual Y La Generada Por Ruido,\nOlores, Vapores Y Fuentes Luminosas\nARTÍCULO 151.- Quedan prohibidas las emisiones de ruido, vibraciones, energía térmica, lumínica, gases, olores y vapores, así como la contaminación visual que rebasen las normas oficiales mexicanas y las normas ambientales para el Distrito Federal correspondientes. La Secretaría, en coordinación con las demarcaciones territoriales del Distrito Federal, adoptarán las medidas necesarias para cumplir estas disposiciones, e impondrán las sanciones necesarias en caso de incumplimiento.\n\nLos propietarios de fuentes que generen cualquiera de estos contaminantes, están obligados a instalar mecanismos para recuperación y disminución de vapores, olores, ruido, energía y gases o a retirar los elementos que generan contaminación visual.\nCorresponde a la Secretaría, en coordinación con las autoridades competentes, la realización de campañas intensivas de información y orientación en materia de emisiones de ruido, vibraciones, energía térmica, lumínica, gases, olores y vapores, así como la contaminación visual.\nARTÍCULO 151 Bis. Para la prevención y control de la contaminación lumínica, las personas físicas o morales, así como las autoridades de la Ciudad de México deberán considerar los siguientes criterios:\na) El alumbrado público deberá observar criterios de eficiencia energética conforme las disposiciones jurídicas en la materia o demás lineamientos que para ello se emitan;\nb) Mantener las condiciones naturales de las horas nocturnas para propiciar el sano descanso de la población, así como de la fauna nocturna de la Ciudad de México; y c) Reducir la luz intrusa en entornos naturales e interior de edificios.\nArtículo añadido y publicado en la GOCDMX el 04 de mayo de 2023\nARTÍCULO 151 TER.- La norma ambiental establecerá el procedimiento de medición, las especificaciones técnicas y los límites máximos permisibles de la intensidad lumínica en el medio ambiente. Por su parte, en la Manifestación Ambiental Única deberá establecerse, para las fuentes fijas, la obligación del cumplimiento de la norma aplicable en materia de contaminación lumínica.\nArtículo añadido y publicado en la GOCDMX el 04 de mayo de 2023\nCAPÍTULO IV\nPREVENCIÓN Y CONTROL DE LA CONTAMINACIÓN DEL AGUA\nARTÍCULO 152.- Las disposiciones contenidas en el presente capítulo son aplicables a las descargas de aguas residuales que se viertan a los cuerpos de aguas y a los sistemas de drenaje y alcantarillado en e l\nDistrito Federal.\nARTÍCULO 153.- Para la prevención y control de la contaminación del agua se considerarán los siguientes criterios:\n\nI. La prevención y control de la contaminación del agua, es fundamental para evitar que se reduzca su disponibilidad y para proteger los ecosistemas del Distrito Federal;\nII. Corresponde al Gobierno y a la sociedad prevenir la contaminación de los cuerpos de agua, incluyendo las aguas del subsuelo;\nIII. El aprovechamiento del agua conlleva la responsabilidad del tratamiento de las descargas, en condiciones adecuadas para su reutilización;\nIV. Las aguas residuales deben recibir tratamiento previo a su descarga en ríos, cuencas, vasos, y demás depósitos o corrientes de agua, incluyendo las aguas del subsuelo; y\nV. La participación y corresponsabilidad de la sociedad y los medios de comunicación, es condición indispensable para evitar la contaminación del agua.\nARTÍCULO 154.- Los criterios para la prevención y control de la contaminación del agua deberán considerarse en:\nI. La expedición de normas ambientales del Distrito Federal para el uso tratamiento y disposición de aguas residuales, para evitar riesgos y daños a la salud y el ambiente;\nII. El otorgamiento de concesiones, permisos, licencias de construcción y de uso de suelo, y en general toda clase de autorizaciones para el aprovechamiento de agua y las descargas de agua residual;\nIII. El diseño y operación de sistemas de agua potable, alcantarillado y tratamiento de agua residual; y\nIV. La restricción o suspensión de explotaciones y aprovechamientos en casos de contaminación de las fuentes de abastecimiento.\nARTÍCULO 155.- Las atribuciones de la Secretaría en materia de manejo y disposición de aguas residuales son las siguientes:\nI. Prevenir y controlar la contaminación por aguas residuales;\n\nII. Integrar y mantener actualizado el inventario de descargas de aguas residuales domésticas e industriales;\nIII. Vigilar que las descargas cumplan con la normatividad vigente en cantidad y calidad, esto en coordinación con las autoridades vinculadas;\nIV. Determinar y promover el uso de plantas de tratamiento, fuentes de energía, sistemas y equipos para prevenir y reducir al mínimo las emisiones contaminantes en el Distrito Federal, así como fomentar el cambio a tecnologías compatibles con el ambiente;\nV. Verificar el cumplimiento de las normas aplicables, así como establecer condiciones particulares de descarga de aguas residuales; y\nVI. Establecer y aplicar las medidas necesarias para prevenir y reducir al mínimo las emisiones de descargas contaminantes, así como las que le corresponden para prevenir y controlar la contaminación del agua superficial y cuerpos receptores.\nARTÍCULO 156.- Queda prohibido descargar aguas residuales en cualquier cuerpo o corriente de agua.\nARTÍCULO 157.- Las fuentes que descarguen aguas residuales distintas a las domésticas, deberán tramitar la Manifestación Ambiental Única para la Ciudad de México.\nReforma publicada en la GOCDMX el 27 de febrero de 2023\nARTÍCULO 158. Derogado\nARTÍCULO 159. Derogado\nARTÍCULO 160.- Se exceptúa de la obligación de presentar los estudios de aguas residuales a través de la\nManifestación Ambiental Única para la Ciudad de México a las descargas provenientes de los siguientes usos:\nReforma publicada en la GOCDMX el 27 de febrero de 2023\nI. Domésticos, siempre y cuando no se relacionen con otras actividades industriales, de servicios, de espectáculos o comerciales, dentro del predio del establecimiento;\n\nII. Servicios análogos a los de tipo doméstico, que determine la norma correspondiente, siempre y cuando se demuestre cumplir con lo establecido en las normas oficiales mexicanas y normas ambientales para el Distrito Federal, y\nIII. Aquellos que determinen las normas ambientales para el Distrito Federal.\nARTÍCULO 161.- Cuando alguna descarga al sistema de drenaje, a pesar del cumplimiento de los límites establecidos en las normas oficiales, cause efectos negativos en las plantas de tratamiento de aguas residuales del Distrito Federal o en la calidad que éstas deben cumplir antes de su vertido a cuerpos receptores, la Secretaría podrá fijar condiciones particulares de descarga en las que fije límites más estrictos.\nARTÍCULO 162.- La Secretaría establecerá y operará un sistema de monitoreo de las aguas residuales en el\nDistrito Federal.\nCAPÍTULO V\nPREVENCIÓN Y CONTROL DE LA CONTAMINACIÓN DEL SUELO\nARTÍCULO 163.- Para la prevención y control de la contaminación del suelo, se considerarán los siguientes criterios:\nI. Corresponde al Gobierno y a la sociedad prevenir la contaminación del suelo;\nII. Deben ser controlados los residuos que constituyan la principal fuente de contaminación de los suelos;\nIII. Es necesario prevenir y reducir la generación de residuos, incorporando técnicas, ecotecnias y procedimientos para su reuso y reciclaje.\nIV. La regulación ambiental por parte de la Secretaría instrumentará los sistemas de agricultura orgánica, que protejan los suelos, mantos friáticos y la producción agropecuaria, mediante el uso de abonos orgánicos;\n\nV. En el Suelo de Conservación del Distrito Federal, queda prohibido el uso de agroquímicos, fertilizantes nitrogenados, fertilizantes químicos, herbicidas, insecticidas y pesticidas que contaminen el suelo y que afecten la flora, fauna y la salud;\nVI. Promover y fomentar la instrumentación de sistemas de agricultura, que no degraden ni contaminen;\nVII. En los suelos contaminados, deberán llevarse a cabo las acciones necesarias para recuperar o restablecer sus condiciones.\nARTÍCULO 164.- Los criterios para la prevención y control de la contaminación del suelo deberán considerarse en:\nI. La expedición de normas para el funcionamiento de los sistemas de recolección, almacenamiento, transporte, acopio, alojamiento, reuso, tratamiento y disposición final de residuos sólidos, a fin de evitar riesgos y daños a la salud y al ambiente;\nII. La ordenación y regulación del desarrollo urbano, turístico, industrial y agropecuario;\nIII. La generación, manejo, tratamiento y disposición final de residuos, así como en las autorizaciones y permisos que al efecto se otorguen;\nIV. La autorización y operación de los sistemas de recolección, almacenamiento, transporte, acopio, alojamiento, reuso, tratamiento y disposición final de residuos sólidos peligrosos; y\nV. El otorgamiento de todo tipo de autorizaciones para la fabricación, comercialización, utilización y en general la realización de actividades relacionadas con plaguicidas, fertilizantes y sustancias tóxicas.\nARTÍCULO 165.- Las autoridades del Distrito Federal que tengan a su cargo la promoción y el fomento de las actividades agropecuarias vigilarán que en la aplicación y empleo de plaguicidas, fertilizantes o sustancias tóxicas, no se provoque degradación, pérdida o contaminación del suelo y así evitar daños a los seres humanos y al ambiente.\nARTÍCULO 166.- Con el propósito de promover el desarrollo sustentable y prevenir y controlar la contaminación del suelo y de los mantos acuíferos, la Secretaría, con la participación de la sociedad,\n\nfomentará y desarrollará programas y actividades para la minimización, separación, reuso y reciclaje de residuos sólidos, industriales no peligrosos y peligrosos.\nARTÍCULO 167.- Quienes realicen obras o proyectos que contaminen o degraden los suelos o desarrollen actividades relacionadas con la exploración, explotación, extracción y aprovechamiento de materia les o sustancias no reservadas a la Federación, están obligados a:\nI. Instrumentar prácticas y aplicar tecnologías o ecotecnias que eviten los impactos ambientales negativos;\nII. Cumplir con las normas oficiales mexicanas y normas ambientales del Distrito Federa l que al efecto se expidan; y\nIII. Restaurar las áreas utilizadas una vez concluidos los trabajos respectivos.\nARTÍCULO 168.- Quienes realicen obras o actividades en las que se generen residuos de construcción deben presentar un informe a la Secretaría sobre el destino que le darán a dicho material. El cumplimiento de esta obligación debe ser considerado por las autoridades competentes en la expedición de las autorizaciones para el inicio de la obra respectiva.\nSección I\nResiduos No Peligrosos\nARTÍCULO 169.- Durante las diferentes etapas del manejo de residuos sólidos, se prohíbe:\nI. El depósito o confinamiento en sitios no autorizados;\nII. El fomento o creación de basureros clandestinos;\nIII. El depósito o confinamiento de residuos sólidos en suelo de conservación ecológica o áreas naturales protegidas;\nIV. La quema de dichos residuos sin los mecanismos de prevención de generación de contaminantes adecuados, ni de su autorización;\n\nV. La dilución o mezcla de residuos sólidos o peligrosos en cualquier líquido y su vertimiento al sistema de alcantarillado o sobre los suelos con o sin cubierta vegetal;\nVI. La mezcla de residuos peligrosos con residuos sólidos;\nVII. El transporte inadecuado de residuos sólidos; y\nVIII. El confinamiento o depósito final de residuos en estado líquido o con contenidos líquidos que excedan los máximos permitidos por las normas oficiales mexicanas o las normas ambientales para el Distrito Federal.\nLa mezcla de residuos no peligrosos con peligrosos, se considerará como un residuo peligroso.\nARTÍCULO 170.- Es responsabilidad de la Secretaría elaborar programas para reducir la generación de residuos.\nLa generación, la separación, el acopio, el almacenamiento, transporte y disposición final de los residuos sólidos, estarán sujetas al Reglamento de ésta Ley y a la normatividad correspondiente.\nARTÍCULO 171.- En materia de residuos sólidos, corresponde a la Secretaría:\nI. Expedir normas ambientales para el Distrito Federal en materia de generación y manejo;\nII. Derogado\nIII. Inspeccionar y vigilar el cumplimiento de esta ley, su reglamento, las normas oficiales mexicanas y las normas ambientales para el Distrito Federal en materia de generación y manejo, y en su caso imponer las sanciones que correspondan; y\nIV. Tomar las medidas preventivas necesarias para evitar contingencias ambientales por la generación, manejo, tratamiento y disposición final.\nARTÍCULO 172.- Para la obtención de la autorización como generador de residuos sólidos, los interesados deberán presentar la solicitud de la Manifestación Ambiental Única para la Ciudad de México ante la\nSecretaría.\nReforma publicada en la GOCDMX el 27 de febrero de 2023\n\nARTÍCULO 173.- Cuando la generación, manejo y disposición final de residuos sólidos produzca contaminación del suelo, independientemente de las sanciones penales o administrativas que procedan, los responsables estarán obligados a:\nI. Llevar a cabo las acciones necesarias para recuperar y restablecer las condiciones del suelo; y\nII. En caso de que la recuperación y restablecimiento no sean factibles, a indemnizar los daños causados de conformidad con la legislación civil aplicable.\nLa responsabilidad a que se refiere este precepto es de carácter objetivo y para su actualización no requiere que medie culpa o negligencia del demandado.\nSon responsables solidarios por los daños que se produzcan tanto el generador como las empresas que presten los servicios de manejo, transporte y disposición final de los residuos sólidos e industriales no peligrosos.\nARTÍCULO 174.- Los residuos no peligrosos que sean usados, tratados o reciclados, en un proceso distinto al que los generó, dentro del mismo predio, serán sujetos a un control interno por parte del generador, de acuerdo con lo que establezca la normatividad correspondiente.\nSección II\nReglas Complementarias En Materia De Residuos Peligrosos\nARTÍCULO 175.- Para la protección al ambiente, con motivo de la operación de sistemas destinados al manejo de materiales y residuos peligrosos, el reglamento de esta Ley y las normas ambientales del Distrito\nFederal podrán establecer medidas o restricciones complementarias a las que emita la Federación, en los siguientes aspectos:\nI. Generación, manejo y disposición final de residuos de baja peligrosidad;\nII. Características de las edificaciones que alberguen dichas instalaciones;\nIII. Tránsito dentro de las zonas urbanas, rurales y centros de población;\n\nIV. Aquellas necesarias para evitar o prevenir contingencias ambientales; y\nV. Detección de residuos peligrosos en el ejercicio de atribuciones correspondientes a la\nSecretaría.\nLa vigilancia y aplicación de dichas medidas o restricciones corresponderá a la Secretaría, en el ámbito de competencia determinado por la Ley General, y de conformidad con lo previsto en la presente Ley.\nEn caso de que se detecten irregularidades o violaciones en el manejo de los residuos peligrosos competencia de la Federación, la Secretaría levantará el acta respectiva, ordenará las medidas de seguridad y restauración inmediatamente enviará el expediente a la instancia correspondiente, independientemente de atender la situación de contingencia.\nSección III\nActividades Riesgosas\nARTÍCULO 176.- El reglamento de esta Ley y las normas ambientales para la Ciudad de México, establecerán la clasificación de las actividades que deban considerarse riesgosas, en virtud de las características corrosivas, reactivas, explosivas, tóxicas, inflamables o biológico infecciosas, de los materiales que se generen o manejen en los establecimientos industriales, comerciales o de servicios, considerando, además, los volúmenes de manejo y la ubicación del establecimiento, así como los casos en los que por las sustancias que maneje el establecimiento, deba tramitar su Manifestación Ambiental Única para la Ciudad de México.\nReforma publicada en la GOCDMX el 27 de febrero de 2023\nPara el establecimiento de esta clasificación, se deberá considerar la opinión de las autoridades competentes.\nARTÍCULO 177.- Quienes realicen actividades riesgosas, que por sus características no estén sujetas a la obtención de la autorización previa en materia de impacto ambiental deberán presentar para la autorización de la Secretaría, a través de escrito con firma autógrafa o por medios electrónicos autorizados un estudio de riesgo y un programa de prevención de accidentes.\n\nUna vez autorizado el estudio de riesgo, el interesado deberá presentar en la misma forma el programa de prevención de accidentes ante la Secretaría, quien deberá resolver sobre su autorización en los plazos que establezca el Reglamento correspondiente a la materia.\nARTÍCULO 178.- Sin perjuicio de lo dispuesto en la presente Ley en materia de evaluación de impacto ambiental y riesgo, las personas que realicen actividades riesgosas no reservadas a la Federación, deberán observar las medidas preventivas, de control y correctivas establecidas en las normas oficiales o determinadas por las autoridades competentes conforme a la ley de Protección Civil para el Distrito Federal y las demás disposiciones aplicables, para prevenir y controlar accidentes que puedan afectar la integridad de las personas o del ambiente.\nARTÍCULO 179.- La Administración Pública del Distrito Federal publicará en la Gaceta Oficial del Distrito\nFederal las medidas señaladas en el artículo precedente y las difundirá a través de los medios conducentes.\nARTÍCULO 180.- Para evitar o reducir los riesgos ambientales con motivo de la realización de actividades riesgosas, corresponde a la Secretaría:\nI. Evaluar y, en su caso aprobar, los estudios de riesgo ambiental.\nII. Establecer condiciones de operación y requerir la instalación de equipos o sistemas de seguridad;\nIII. Promover ante los responsables de la realización de las actividades riesgosas, la aplicación de la mejor tecnología disponible para evitar y minimizar los riesgos ambientales; y\nIV. Tomar las medidas preventivas necesarias para evitar contingencias ambientales.\nARTÍCULO 181.- Las Delegaciones propondrán que en la determinación de los usos del suelo se especifiquen las zonas en las que se permita el establecimiento de industrias, comercios o servicios que de conformidad con esta Ley o con la Ley General sean considerados riesgosas o altamente riesgosas, por la gravedad de los efectos que puedan generar en los ecosistemas o en el ambiente, tomando en consideración:\nI. Las condiciones topográficas, meteorológicas, climatológicas, geológicas y sísmicas de las zonas;\n\nII. Su ubicación y proximidad a centros de población, previniendo las tendencias de expansión del respectivo asentamiento y la creación de nuevos asentamientos;\nIII. Los impactos que tendría un posible evento extraordinario de la industria, comercio o servicio de que se trate sobre los centros de población y sobre los recursos naturales;\nIV. La compatibilidad con otras actividades de las zonas;\nV. La infraestructura existente y necesaria para la atención de emergencias ecológicas; y\nVI. La infraestructura para la dotación de servicios básicos.\nARTÍCULO 181 BIS.- La Secretaría o las Delegaciones propondrán al Jefe de Gobierno el establecimiento de zonas intermedias de salvaguarda, con el objeto de prevenir y controlar el riesgo ambiental que puedan ocasionar las industrias, comercios y servicios que realicen actividades riesgosas en el territorio del Distrito\nFederal.\nCAPÍTULO VI\nDE LAS CONTINGENCIAS AMBIENTALES\nARTÍCULO 182.- La Secretaría emitirá Programas de Contingencia Ambiental en los que se establecerán las condiciones ante las cuales es procedente la determinación de estado de contingencia, así como las medidas aplicables para hacerles frente.\nARTÍCULO 183.- Las autoridades competentes declararán contingencia ambiental cuando se presente una concentración de contaminantes o un riesgo ambiental, derivado de actividades humanas o fenómenos naturales, que puedan afectar la salud de la población o al ambiente de acuerdo con las normas ambientales y elementos técnicos aplicables.\nARTÍCULO 184.- La declaratoria y las medidas que se aplicarán deberán darse a conocer a través de los medios de comunicación masiva y de los instrumentos que se establezcan para tal efecto. Dichas medidas entrarán en vigor y se instrumentarán en los términos que se precisen en el Reglamento de esta Ley y en los respectivos Programas de Contingencia Ambiental.\n\nARTÍCULO 185.- Los Programas de Contingencia Ambiental establecerán las condiciones bajo las cuales permanecerán vigentes las medidas y los términos en que podrán prorrogarse, así como las condiciones y supuestos de exención.\nARTÍCULO 186.- En situación de contingencia ambiental, los responsables de fuentes de contaminación estarán obligados a cumplir con las medidas de prevención y control establecidas en los programas de contingencia correspondientes.\nCAPÍTULO VII\nDE LA PREVENCIÓN Y CONTROL DE RUIDO\nARTÍCULO 186 Bis.- Sin perjuicio de la distribución de competencias previstas en el presente y otros ordenamientos legales, las atribuciones específicas en materia de ruido se ejercerán de la siguiente manera:\nI. A la Secretaría le corresponde:\na) Elaborar los mapas de ruido de la Ciudad de México;\nb) Formular, ejecutar y evaluar el apartado en materia de prevención y control de la contaminación generada por ruido en el Programa Sectorial Ambiental;\nc) Establecer los límites máximos permisibles de ruido de las fuentes fijas y las móviles que, conforme a lo establecido en la Ley General del Equilibrio Ecológico y la Protección al Ambiente, no sean de competencia Federal;\nd) Establecer los criterios y especificaciones de los equipos, dispositivos y sistemas de reducción de emisiones sonoras que deban adoptar las fuentes fijas y las móviles, que conforme a lo establecido en la Ley General del Equilibrio Ecológico y la Protección al\nAmbiente no sean de competencia Federal;\ne) Realizar acciones de inspección y vigilancia a fin de verificar el cumplimiento de las disposiciones legales aplicables en materia de ruido por parte de las fuentes fijas y móviles que, conforme a lo establecido en la Ley General del Equilibrio Ecológico y la\nProtección al Ambiente, no sean de competencia Federal y, en su caso, iniciar y sustanciar el procedimiento administrativo que corresponda; y f) Determinar las sanciones administrativas que deriven del procedimiento administrativo que, en su caso, se inicie.\n\nII. A las Alcaldías les corresponde, colaborar con la Secretaría en la elaboración de los mapas de ruido especiales, así como en la ejecución del apartado del Programa Sectorial Ambiental en materia de prevención y control de la contaminación generada por ruido;\nIII. A la Secretaría de Seguridad Ciudadana le corresponde, detener y presentar ante el Juez\nCívico a los probables infractores que ocasionen ruidos por cualquier medio que notoriamente atenten contra la tranquilidad o representen un riesgo a la salud y el ambiente de las personas, en los términos de la Ley de Cultura Cívica de la Ciudad de México.\nARTÍCULO 186 Ter.- Para verificar el cumplimiento de los límites máximos permisibles de ruido previstos en las Normas Oficiales Mexicanas o Normas Ambientales para la Ciudad de México que resulten aplicables a las fuentes móviles que se encuentren en estado de encendido o que circulen en la vía pública, la\nSecretaría, en coordinación con la Secretaría de Seguridad Ciudadana, podrá llevar a cabo acciones de inspección y vigilancia, pudiendo detener la marcha o circulación de los vehículos automotores que se presuman contaminantes en virtud del ruido que emitan, a fin de llevar a cabo la verificación y, en su caso, iniciar el procedimiento administrativo que corresponda.\nARTÍCULO 186 Quater.- Los mapas de ruido elaborados por la Secretaría como instrumentos de política de desarrollo sustentable tienen por objeto conocer la situación acústica de la ciudad de México y para ello se desarrollarán a través de las siguientes modalidades:\nI. General, para todo el territorio de la Ciudad de México; y\nII. Especial, para aquellas zonas o regiones donde se presente una mayor incidencia de ruido.\nARTÍCULO 186 Quinquies.- Los mapas de ruido deberán contener, por lo menos:\nI. El territorio, zonas o regiones a monitorear;\nII. La situación acústica existente en el territorio, zonas o regiones a monitorear;\nIII. Las zonas de calidad acústica;\nIV. Las zonas y horarios donde se presenten casos en los que se superen los límites máximos permisibles;\n\nV. La identificación de las fuentes que provocan que se supere los límites máximos permisibles;\ny\nVI. El número de personas afectadas en las zonas donde se superan los límites máximos permisibles.\nARTÍCULO 186 Sexies.- La Secretaría, con base en los mapas de ruido correspondientes, definirá los límites máximos permisibles de ruido en exteriores, en función de las zonas de calidad acústica siguientes:\nI. Hospitalarias y escolares;\nII. Preservación ecológica;\nIII. Habitacional y áreas verdes;\nIV. Comercial, de servicios y de espectáculos;\nV. Rural;\nVI. Transportes y vialidades; y\nVII. Industrial.\nARTÍCULO 186 Septies.- Los mapas de ruido deberán ser revisados y, en su caso actualizados, cuando menos cada 5 años, o antes y se presente información que lo justifique.\nARTÍCULO 186 Octies.- El Programa Sectorial Ambiental deberá incluir un apartado en materia de prevención y control de la contaminación generada por ruido, el cual deberá considerar los mapas de ruido, y contendrá por lo menos:\nI. El diagnóstico de la situación acústica existente;\nII. Las zonas o regiones en las que se superen los límites máximos permisibles, así como las fuentes que generan el exceso de ruido y los horarios correspondientes;\n\nIII. Las metas y objetivos específicos de las zonas de calidad acústica establecidas en función de los casos en los que se superen los límites máximos permisibles, en la zona o zonas identificadas;\nIV. Las acciones necesarias para prevenir, controlar, reducir o minimizar la contaminación generada por ruido en la zonas o regiones identificadas; y\nV. La asignación de:\na) Recursos para la ejecución de las acciones que permitan alcanzar las metas y objetivos específicos, a efecto de prevenir, controlar, reducir o minimizar la contaminación generada por ruido en las zonas o regiones identificadas;\nb) Responsabilidades de la Secretaría, así como las acciones de coordinación con otras dependencias y entidades de la Administración Pública de la Ciudad de México y con las\nAlcaldías; y c) Tiempos de ejecución, revisión y evaluación de resultados.\nARTÍCULO 186 Nonies.- La información y las prescripciones contenidas en el apartado del Programa\nSectorial Ambiental en materia de prevención y control de la contaminación generada por ruido, deberán ser observadas en:\nI. Los programas de desarrollo urbano;\nII. El Programa de Ordenamiento Ecológico;\nIII. Las autorizaciones en materia de impacto ambiental de obras o actividades;\nIV. El otorgamiento de la Manifestación Ambiental Única;\nReforma publicada en la GOCDMX el 27 de febrero de 2023\nV. Los permisos y autorizaciones para la celebración de espectáculos públicos en la vía pública o en lugares que no cuenten con la licencia de funcionamiento correspondiente; y\nVI. Los permisos para operar un giro con impacto vecinal o zonal.\n\nARTÍCULO 186 Decies.- Las sanciones a las conductas previstas en el presente capítulo se resolverán en términos de lo establecido en el artículo 213 de la Ley, atendiendo a las circunstancias específicas del caso y de manera supletoria lo establecido en la Ley de Cultura Cívica de la Ciudad de México.\nTITULO SEXTO\nDE LOS PRESTADORES DE SERVICIOS AMBIENTALES\nCAPÍTULO I\nDE LOS PRESTADORES DE SERVICIOS DE IMPACTO AMBIENTAL\nARTÍCULO 187.- La Secretaría elaborará y publicará el padrón de prestadores de servicios de impacto ambiental, para cuyo efecto podrá consultar a los Colegios de Profesionistas, a las instituciones de investigación y de educación superior.\nARTÍCULO 188.- Los prestadores de servicios de impacto ambiental son responsables de la calidad, contenido y veracidad de la información, así como del nivel profesional de los informes preventivos, manifestaciones de impacto ambiental en cualquiera de sus modalidades, estudios de riesgo, estudios de daño ambiental, evaluaciones ambientales estratégicas, declaratorias de cumplimiento ambiental, informes de cumplimiento de condicionantes y/o de disposiciones ambientales que elaboren, y deberán recomendar a los promoventes sobre la adecuada realización de las medidas de mitigación y compensación derivadas de los estudios y la autorización.\nEn caso de incumplimiento a lo establecido en el presente artículo, se aplicarán las sanciones dispuestas en la presente Ley y en los demás otros ordenamientos aplicables.\nARTÍCULO 189.- La Secretaría instrumentará programas de acreditación y/o certificación de prestadores de servicios ambientales en coordinación con los Colegios, Asociaciones de Profesionales, Instituciones de\nInvestigación y de Educación Superior.\nARTÍCULO 190.- En ningún caso podrá prestar servicios ambientales directamente o a través de terceros, el servidor público que intervenga en cualquier forma en la aplicación de la presente Ley ni las personas con las que tenga interés personal, familiar o de negocios, incluyendo aquéllas de las que pueda resultar un beneficio para él, su cónyuge o parientes consanguíneos hasta el cuarto grado, por afinidad o civiles, terceros con los que tenga relaciones profesionales, laborales o de negocios, socios o personas morales de\n\nlas que el servidor público o las personas antes referidas formen o hayan formado parte. La infracción a esta disposición será sancionada en los términos de la Ley de Responsabilidades de los Servidores Públicos.\nARTICULO 190 Bis.- El Reglamento correspondiente a la materia establecerá los procedimientos de convocatoria, selección, admisión, permanencia, lineamientos de actuación y sanciones de los Prestadores de Servicios Ambientales.\nARTÍCULO 190 Ter.- La falta de calidad técnica, ética, dolo, mala fe o la falsedad en la información presentada por un Prestador de Servicios Ambientales responsable de la elaboración de cualquier modalidad de los estudios de impacto ambiental, será sancionada conforme a lo previsto en la presente ley y en su Reglamento correspondiente a la materia.\nCAPÍTULO II\nDE LOS CENTROS DE VERIFICACIÓN\nARTÍCULO 191.- La Secretaría, atendiendo a las necesidades de los servicios de verificación de fuentes móviles de su competencia, expedirá, previa convocatoria pública, autorizaciones a los interesados que cumplan los requisitos correspondientes. Para tal efecto, la Secretaría publicará las convocatorias en la\nGaceta Oficial, en las cuales se determinarán los elementos materiales y humanos y demás condiciones que deberán reunir los centros de verificación para obtener la autorización, las normas y procedimientos de verificación que se deberán observar, así como el número y ubicación de las instalaciones de los verificadores ambientales.\nARTÍCULO 192.- Quienes realicen verificaciones de vehículos automotores y entreguen los documentos que acrediten su aprobación sin contar con la autorización correspondiente, serán sancionados en los términos de esta Ley y las demás disposiciones jurídicas aplicables.\nSerá revocada la autorización a los centros de verificación vehicular que presten el servicio de verificación a un vehículo, realizando pruebas trampeadas con la finalidad de modificar los resultados para lograr la aprobación de emisiones de algún vehículo, como son:\nI.- Alterar el equipo o la toma de la muestra;\nII.- Verificar un vehículo para aprobar otro;\n\nIII.- Capturar la información de identidad de un vehículo que no corresponda al que realmente efectuó la prueba; y\nIV. - Usar cualquier dispositivo o sistema no autorizado.\nARTÍCULO 193.- Los centros de verificación vehicular deberán obtener y mantener vigentes las siguientes pólizas de:\nI. Fianza para garantizar el cumplimiento de las obligaciones y condiciones establecidas en esta\nLey, su Reglamento, el programa de Verificación Vehicular, la autorización y circulares correspondientes, expedida por compañía autorizada por el equivalente a once mil quinientas veces la Unidad de Cuenta de la Ciudad de México vigente.\nII.- Fianza que garantice el buen uso, posesión, manejo extravío, destrucción, perdida por cualquier motivo o deterioro de la constancia de verificación que se utilice en el Programa de\nVerificación Vehicular vigente; así como la devolución oportuna del remanente de la documentación oficial, al término de cada uno de los periodos de verificación o en el caso de que el Centro de Verificación Vehicular deje de prestar el servicio y cuidado de los documentos referidos, considerando que el valor unitario deberá ser de 3 veces la Unidad de Cuenta de la\nCiudad de México vigente, por un monto total y cantidad que se considere conveniente. La vigencia de esta fianza deberá renovarse durante el tiempo en que permanezca en vigor la autorización.\nIII.- Seguro que ampare la constancia de verificación que se utilice en el Programa de Verificación\nVehicular vigente, contra los riesgos de incendio, inundación, robo con violencia y/o asalto y terremoto, considerando que el valor unitario deberá ser de 3 veces la Unidad de Cuenta de la\nCiudad de México vigente, por un monto total y cantidad que se considere conveniente. La vigencia de este seguro deberá renovarse durante el tiempo en que permanezca en vigor la autorización.\nARTÍCULO 194.- La autorización a que se refiere este capítulo tendrá la vigencia que se indique en la convocatoria, la que solamente podrá darse por terminada cuando:\nI. La Secretaría modifique las condiciones conforme a las que deberá prestarse el servicio;\nII. Concluya el término de la autorización; y\n\nIII. Proceda la revocación de la autorización en los términos de la presente Ley.\nPara efectos de la fracción primera la Secretaría publicará en la Gaceta Oficial y en un diario de circulación nacional, las nuevas condiciones que se deberán cumplir para que las autorizaciones sean revalidadas, con sesenta días naturales de anticipación, como mínimo, a la fecha prevista para que dichas condiciones entren en vigor.\nCuando los incumplimientos que se detecten en los centros de verificación sean atribuibles a los proveedores de maquinaria y servicios, éstos serán responsables en términos de lo dispuesto por ésta Ley.\nARTÍCULO 195.- Los centros de verificación están obligados a:\nI. Operar conforme a los sistemas, procedimientos, instalaciones, equipos, plazos y condiciones establecidos en esta Ley, las normas oficiales mexicanas, normas ambientales para el Distrito\nFederal, el programa de verificación, la convocatoria, autorización y circulares correspondientes;\nII. Que el personal del centro de verificación esté debidamente capacitado y acreditado por la\nSecretaría;\nIII. Mantener sus instalaciones y equipos calibrados en las condiciones requeridas por la\nSecretaría, observando los requisitos que fije la misma para la debida prestación del servicio de verificación vehicular;\nIV. Destinar exclusivamente a la verificación de emisiones contaminantes sus establecimientos respectivos, sin efectuar en éstos reparaciones mecánicas, venta de refacciones automotrices o cualquier otra actividad industrial, o realizar actividades comerciales o de servicios sin autorización de la Secretaría;\nV. Abstenerse de recibir documentación reportada como robada, falsificada o notoriamente alterada como soporte de las verificaciones vehiculares;\nVI. Llevar un registro con la información de las verificaciones efectuadas y remitir a la Secretaría los datos obtenidos en los términos fijados por ésta;\n\nVII. Dar aviso inmediato a la Secretaría cuando dejen de prestar el servicio de verificación vehicular o los equipos e instalaciones no funcionen debidamente, en cuyo caso se abstendrán de realizar verificaciones hasta en tanto los mismos funcionen correctamente;\nVIII. Conservar en depósito y manejar debidamente los documentos que reciban de la Secretaría para acreditar la aprobación de la verificación vehicular, hasta que éstos sean entregados al interesado y, en su caso, adheridos a la fuente emisora de contaminantes;\nIX. Dar aviso inmediato a la Secretaría y presentar las denuncias correspondientes, en caso de robo o uso indebido de los documentos utilizados para acreditar la aprobación de la verificación vehicular;\nX. Enviar a la Secretaría en los términos establecidos por ésta, la documentación e información requerida para la supervisión y control de la verificación;\nXI. Mantener durante las horas de funcionamiento a un representante legal y recibir las verificaciones administrativas que ordene la Secretaría en cualquier momento;\nXII. Que sus establecimientos cuenten con los elementos distintivos determinados por la\nSecretaría;\nXIII. Cobrar las tarifas autorizadas por la Secretaría por la prestación del servicio de verificación vehicular;\nXIV. Mantener en vigor la fianza correspondiente durante la vigencia de la autorización para prestar el servicio de verificación vehicular; y\nXV. Corroborar que el equipo y programa de cómputo que se le instale para proporcionar el servicio de verificación vehicular, sea la versión autorizada por la Secretaría, de lo contrario abstenerse de proporcionar el servicio.\nCuando los centros de verificación vehicular incumplan con alguna de las normas establecidas en la presente Ley, la Secretaría podrá iniciar el procedimiento administrativo con base en la documentación e información que proporcionen o con la que disponga la Secretaría.\n\nARTÍCULO 196.- Por cada verificación vehicular que realicen los prestadores de servicios autorizados, expedirán a los interesados una constancia con los resultados, la cual contendrá la siguiente información:\nI. Fecha de la verificación vehicular y número de folio de la constancia;\nII. Identificación del prestador de servicios autorizado y de quien efectuó la verificación vehicular;\nIII. Indicación de las normas oficiales o técnicas ecológicas locales aplicadas en la verificación vehicular;\nIV. Determinación del resultado de la verificación vehicular;\nV. Marca, tipo, año, modelo, número de placas de circulación, de serie, de motor y de registro del vehículo de que se trate, así como el nombre y domicilio del propietario; y\nVI. Las demás que señalen las normas oficiales, el programa de verificación, la convocatoria, la autorización y circulares respectivas.\nARTÍCULO 197.- El original de la constancia de verificación se entregará al propietario o poseedor de la fuente emisora de contaminantes, adhiriendo inmediatamente, en caso de ser aprobatoria, el documento respectivo en un lugar visible de la propia fuente.\nARTÍCULO 198.- Los proveedores de equipos y servicios para la operación de los Centros de Verificación vehicular deberán contar con la autorización de la Secretaría.\nARTÍCULO 199.- Los proveedores de equipos, programas de cómputo y servicios para la operación de centros de verificación de emisiones generadas por fuentes móviles están obligados a:\nI. Suministrar equipos, programas de cómputo y servicios que cumplan con las normatividad correspondiente, proporcionando los manuales de operación;\nII. Garantizar que el personal que efectúe la instalación, suministro y mantenimiento esté debidamente capacitado y acreditado ante la Secretaría;\n\nIII. En su caso, prestar los servicios de mantenimiento a los equipos instalados cerciorándose de que están calibrados y en óptimas condiciones, y observar que éstos cumplan con los requisitos que fije la Secretaría;\nIV. Llevar un registro con la información de las operaciones de mantenimiento y reparación de equipos y remitir un informe mensual a la Secretaría;\nV. Dar aviso a la Secretaría cuando dejen de prestar el servicio de suministro y mantenimiento de equipos y programas de cómputo;\nVI. Presentar y mantener en vigor una fianza de tres mil veces la Unidad de Cuenta de la Ciudad de México vigente, para garantizar el cumplimiento de las obligaciones y la confidencialidad de los sistemas de seguridad, durante la vigencia de la autorización, misma que se hará efectiva en los casos que la prestación del servicio contravenga las disposiciones aplicables;\nVII. Prestar sus servicios de conformidad con los contratos autorizados por la Secretaría; y\nVIII.- Dar una póliza de fianza a los centros de verificación, para garantizar el cumplimiento por sus servicios que incluya mano de obra y refacciones.\nCAPÍTULO III\nDE LOS LABORATORIOS AMBIENTALES\nARTÍCULO 200.- La Secretaría establecerá los lineamientos y procedimientos para autorizar laboratorios ambientales de análisis de contaminantes en el aire, agua, suelo, subsuelo, materiales o residuos, atendiendo las acreditaciones y reconocimientos que de conformidad con la Ley Federal sobre Metrología y Normalización, hayan obtenido dichos laboratorios.\nTITULO SÉPTIMO\nMEDIDAS DE CONTROL, DE SEGURIDAD Y SANCIONES\nCAPITULO I\nDISPOSICIONES GENERALES\n\nARTÍCULO 201.-Las disposiciones contenidas en el presente título, se aplicarán en los procedimientos que lleven a cabo las autoridades ambientales competentes para comprobar el cumplimiento de las disposiciones contenidas en la presente Ley, y en los reglamentos, decretos, normas ambientales, acuerdos, y demás disposiciones jurídicas que de la misma se deriven. Asimismo, dichas disposiciones serán observadas en la imposición de medidas de seguridad, correctivas, de urgente aplicación y sanciones.\nLos procedimientos en materia de inspección y vigilancia ambiental estarán sujetos a los principios de prevención de daños ambientales, oportunidad en la detección de ilícitos y justa reparación de los daños ocasionados al ambiente y sus elementos.\nSerán de aplicación supletoria al presente Título, en el orden que se indica, las disposiciones de la Ley de\nProcedimiento Administrativo y del Código de Procedimientos Civiles, del Distrito Federal.\nCuando en el procedimiento correspondiente obre información obtenida por la Secretaría de Seguridad\nPública del Distrito Federal con equipos y sistemas tecnológicos a que se refiere la Ley que regula el uso de tecnología para la Seguridad Pública del Distrito Federal serán valorados conforme a la legislación aplicable.\nCAPÍTULO II\nDE LA INSPECCIÓN Y VIGILANCIA\nARTÍCULO 201 Bis.- La Secretaría organizará y coordinará el servicio de inspección y vigilancia ambiental del Distrito Federal, con el propósito de establecer los criterios y lineamientos que se habrán observar por las distintas unidades administrativas del gobierno del Distrito Federal que realicen acciones para verificar el cumplimiento de las disposiciones jurídicas señaladas en el artículo 201 de esta Ley, así como para fortalecer la capacitación y profesionalización de los servidores públicos que participen en dichas tareas.\nEl servicio a que se refiere el párrafo anterior estará integrado orgánicamente con los servidores públicos de la Secretaría que intervengan en los procedimientos de inspección ambiental; de los inspectores ambientales; de vigilantes ecoguardas en funciones de vigilancia ambiental; y del cuerpo de policías ambientales.\nLa Secretaría de Seguridad Pública establecerá el cuerpo de policías ambientales como una unidad de apoyo técnico operativo diario para la ejecución de acciones de prevención de delitos e infracciones\n\nadministrativas en materia ambiental que se realicen en suelo urbano y de conservación en auxilio de la\nSecretaría.\nLa Secretaría establecerá y aplicará los sistemas de capacitación y profesionalización de los policías ambientales.\nARTÍCULO 201 Bis 1. Con independencia de las medidas de seguridad, correctivas y de urgente aplicación, las sanciones y medidas de apremio que en materia administrativa correspondan, los policías ambientales pondrán a disposición de la autoridad competente a quienes realicen actos u omisiones probablemente constitutivos de delito o infracción administrativa en materia ambiental, que sucedan en suelo urbano y suelo de conservación así como en áreas de valor ambiental y áreas naturales protegidas.\nARTÍCULO 202.- Para verificar el cumplimiento de las disposiciones de esta Ley y sus reglamentos, las autoridades ambientales competentes deberán realizar según corresponda, visitas domiciliarias o actos de inspección, a través de personal debidamente autorizado por la Secretaría. Asimismo, dichas autoridades podrán iniciar procedimientos de inspección en los casos a que se refieren los artículos 195, último párrafo, y 202 Bis.\nAl realizar las visitas domiciliarias o los actos de inspección, dicho personal deberá contar con el documento oficial que lo acredite o autorice a practicar la actuación correspondiente, así como con la orden escrita debidamente fundada y motivada expedida por la autoridad competente.\nARTÍCULO 202 Bis.- Las autoridades ambientales competentes podrán requerir a los obligados o a otras autoridades, información relacionada con el cumplimiento de las disposiciones jurídicas a que se refiere el artículo 201.\nCuando de la información recabada por las autoridades ambientales competentes se desprenda la presunción fundada de violación o incumplimiento de la normatividad ambiental que corresponda, dichas autoridades podrán instaurar el respectivo procedimiento administrativo de inspección, debiendo emplazar al mismo al probable infractor, de conformidad con lo dispuesto en el artículo 207 de este ordenamiento.\nARTÍCULO 202 Bis 1.- Para llevar a cabo las visitas domiciliarias la autoridad ambiental competente expedirá una orden escrita, fundada y motivada en la que se señalará la persona a visitar; el domicilio donde se practicará la inspección, el objeto de la diligencia y su alcance.\n\nARTÍCULO 202 Bis 2.- Los actos de inspección a que se refiere el artículo 202 de esta Ley, tendrán por objeto verificar el cumplimiento de las disposiciones jurídicas señaladas en el artículo 201, cuando se trate del transporte por cualquier medio de bienes o recursos naturales, o del aprovechamiento, extracción, posesión y afectación de los bienes o recursos naturales regulados por estas disposiciones jurídicas, siempre que no sea posible identificar a la persona responsable de los hechos a verificar y el lugar exacto donde se realizan los mismos.\nPara llevar a cabo los actos de inspección en los supuestos antes señalados, la autoridad ambiental competente expedirá una orden escrita, fundada y motivada, en la que se indique que está dirigida al propietario, poseedor u ocupante del medio de transporte, bien o recurso natural de que se trate, o al responsable del aprovechamiento, extracción, posesión o afectación de los bienes o recursos naturales respectivos. Asimismo, se señalará el lugar o zona donde se practicará la diligencia lo cual quedará satisfecho al indicarse los puntos físicos de referencia, las coordenadas geográficas o cualquier otro dato que permita la ubicación concreta del lugar o la zona donde se practicará el acto de inspección; así como el objeto de la diligencia y su alcance.\nARTÍCULO 203.- Las visitas domiciliarias o los actos de inspección podrán entenderse con cualquier persona que se encuentre en el lugar o bien a inspeccionar, sin que ello afecte la validez de la diligencia. El personal autorizado deberá exhibirle a la persona con quien se entienda la diligencia, la credencia vigente con fotografía, expedida por la Secretaría que lo acredite para realizar la visita o acto correspondiente. Además, le deberá exhibir y entregar la orden respectiva con firma autógrafa, requiriéndola para que en el acto designe dos testigos.\nEn caso de que la persona con quien se entienda la diligencia se niegue a designar los testigos de asistencia o los que designe no acepten fungir como testigos, el personal autorizado para practicar la verificación podrá designarlos haciendo constar esta situación en el acta administrativa que al efecto se levante sin que esta circunstancia invalide los efectos de la actuación.\nCuando en el domicilio, lugar o zona donde se practique la diligencia de inspección, no existan personas que puedan fungir como testigos de asistencia, se podrá llevar a cabo la visita correspondiente siempre que la persona con la que se entienda la misma manifieste su consentimiento para ello, situación que se hará constar en el acta que se levante al efecto, lo cual no afectará la validez de la actuación.\nARTÍCULO 204.- La persona con quien se entienda una visita domiciliaria o acto de inspección, estará obligada a permitir al personal autorizado el acceso al lugar o lugares donde se deba practicar la diligencia, en los términos previstos en la orden escrita correspondiente, así como a proporcionar al personal que\n\nejecute la visita, toda clase de información que conduzca a cumplir con el objeto de la orden respectiva, con excepción de lo relativo a derechos de propiedad industrial que sean confidenciales conforme a las disposiciones jurídicas aplicables, debiendo la autoridad mantenerlos en absoluta reserva si así lo solicita el interesado, salvo que la información sea pública en los términos de la Ley de Acceso a la Información\nPública del Distrito Federal o de cualquier otro ordenamiento jurídico aplicable.\nARTÍCULO 205. Para efectuar una visita domiciliaria o un acto de inspección, así como cualquier otra actuación que determine con motivo de los procedimientos de inspección y vigilancia ambiental, la autoridad competente podrá asistirse de elementos de la policía ambiental.\nLo anterior, sin perjuicio de las sanciones o medios de apremio que procedan para las personas que obstaculicen o se opongan a la práctica de la diligencia de que se trate.\nARTÍCULO 205 Bis.- Las visitas domiciliarias y actos de inspección que practiquen las autoridades ambientales serán ordinarios o extraordinarias. Serán ordinarias las que se inicien en días y horas hábiles, y extraord inarias las que se inicien en días y horas inhábiles.\nPara la práctica de visitas domiciliarias o actos de inspección extraordinarias, la autoridad ambiental ordenadora deberá habilitar los días y/o las horas inhábiles en que se practicará la diligencia, señalando las razones que se tiene para ello.\nLas visitas domiciliarias o actos de inspección podrán iniciarse en días y horas hábiles, y concluir en días y horas inhábiles; y viceversa, lo cual no afectará la validez de la diligencia.\nARTÍCULO 206.- De toda visita o acto de inspección se levantará acta, en la que se harán constar en forma circunstanciada los hechos u omisiones que se hubiesen presentado durante la diligencia, así como la información referida en el artículo 103 de la Ley de Procedimiento Administrativo del Distrito Federal.\nConcluida la visita domiciliaria o acto de inspección, se dará oportunidad a la persona con la que se entendió la diligencia para que en el mismo acto formule sus observaciones con relación a los hechos u omisiones asentados en el acta respectiva y para que ofrezca las pruebas que considere convenientes;\nademás, se le hará saber al interesado que puede ejercer ese derecho dentro de un plazo de cinco días hábiles contados a partir del día siguiente a la fecha en que concluya la diligencia.\nA continuación, se procederá a firmar el acta por la persona con quien se entendió la actuación, por los testigos y el personal que practicó la diligencia, quien entregará copia del acta al interesado.\n\nSi la persona con la que se entendió la diligencia o los testigos se negaren a firmar el acta, o se negare la persona con la que se entendió la actuación a aceptar copia de la misma, dichas circunstancias se asentarán en ella, sin que esto afecte su validez.\nARTÍCULO 206 Bis.- Una vez iniciada una visita domiciliaria o acto de inspección, será procedente la suspensión de la diligencia, cuando:\nI. Se suscite algún accidente que imposibilite materialmente su continuación;\nII. Las circunstancias de tiempo impidan su continuación; o\nIII. Lo acuerden las personas que intervengan en la actuación, en razón de la complejidad o amplitud de los hechos a verificar.\nEn aquellos casos en los que se suspenda una visita domiciliaria o acto de inspección, se hará constar tal situación en el acta correspondiente, sin que en el momento se tenga por concluida la actuación; además se señalará la fecha y hora en que se continuará con la diligencia, que deberá ser al día siguiente, salvo casos excepcionales debidamente justificados, en los cuales se podrá reanudar en un plazo máximo de cinco días hábiles. El acta respectiva deberá ser firmada por todas las personas que intervengan en la diligencia.\nCuando la persona con la que se entienda la diligencia o los testigos de asistencia no se presentaren en la fecha y hora fijada en el acta para la continuación de la diligencia, el personal de la autoridad ambiental que practique la verificación podrá reanudar la misma con la persona que se encuentre en el lugar y con otros testigos de asistencia, que serán nombrados en la forma que se señala en el artículo 203 de la presente Ley; situación que se hará constar en el acta respectiva y ello no afectará la validez de la diligencia.\nARTÍCULO 207.- Cuando de las actas levantadas en las visitas domiciliarias o actos de inspección se desprendan actos, hechos u omisiones que constituyan presuntas violaciones o incumplimiento de las disposiciones referidas en el artículo 201 de esta Ley, o en los supuestos a que se refieren los artículo 195 y 202 Bis, la autoridad ambiental ordenadora emplazará al probable responsable, mediante acuerdo fundado y motivado, para que dentro del plazo de diez días hábiles manifiesto lo que a su derecho convenga y, en su caso, aporte las pruebas que considere procedentes en relación con las probables infracciones, daños o afectaciones que se le imputen.\n\nAsimismo, la autoridad ambiental podrá ordenar al presunto infractor, en el acuerdo de emplazamiento respectivo, la ejecución de medidas correctivas o de urgente aplicación necesarias para subsanar las irregularidades, daños o afectaciones detectadas en la visita domiciliaria o acto de inspección, en cuyo caso se señalará el plazo y demás especificidades que deberán ser observadas por los responsables.\nEl emplazamiento al procedimiento administrativo deberá hacerse dentro del término de quince días, contados a partir del día en que se hubiere cerrado la visita domiciliaria o acto de inspección.\nARTÍCULO 207 Bis.- Las personas a las que se les hubiesen ordenado las medidas correctivas o de urgente aplicación, deberán informar a la autoridad ambiental ordenadora, dentro de un plazo de diez días hábiles, contados a partir del día siguiente a la fecha en que concluya el plazo que se les hubiere señalado para su cumplimiento, sobre las acciones realizadas al efecto, anexando en su caso las pruebas que sustenten su informe.\nLa autoridad ambiental ordenadora podrá otorgar una sola prórroga para el cumplimiento de las medidas correctivas o de urgente aplicación, en los siguientes supuestos:\nI. Cuando existan elementos de prueba en el expediente respectivo que acrediten la imposibilidad material para cumplir con las mismas en el plazo señalado originalmente; o\nII. Se acredite la existencia de causas ajenas a la voluntad de las personas obligadas, que hubieran impedido o imposibilitado su cumplimiento.\nARTÍCULO 208.- Transcurrido el plazo para que la persona o personas interesadas manifiesten lo que a su derecho convenga y ofrezcan las pruebas que consideren para su defensa, sin que éstas hubiesen hecho uso de su derecho, o cuando se hubiere hecho uso de tal derecho y ya no existan diligencias pendientes de desahogo, la autoridad ambiental correspondiente, emitirá la resolución administrativa dentro de los veinte días hábiles siguientes.\nLa resolución administrativa referida en el párrafo que antecede deberá estar debidamente fundada y motivada, y se notificará a la persona o personas interesadas personalmente o por correo certificado con acuse de recibo.\nEn dicha resolución administrativa se tendrán por cumplidas, o en su caso se ratificarán o adicionarán, las medidas correctivas o de urgente aplicación que correspondan.\n\nARTÍCULO 208 Bis.- Si durante la tramitación de un procedimiento de inspección se allegaran al expediente respectivo, elementos de prueba que acrediten la existencia de hechos diversos a los que dieron origen a tal actuación, que puedan constituir presuntas infracciones o violaciones a la normatividad referida en el artículo 201 de este ordenamiento, la autoridad ambiental que tramita el exp ediente podrá iniciar un nuevo procedimiento e integrar otro expediente por tales hechos, con un desglose de copias certificadas de las constancias que para ello se requieran.\nARTÍCULO 208 Bis.- Durante el procedimiento y antes de que se dicte resolución, las autoridades administrativas y los presuntos infractores podrán convenir la realización de las acciones de restauración o compensación de daños necesarias para la corrección de las irregularidades detectadas por las propias autoridades ambientales, siempre que ello no afecte el cumplimiento de disposiciones jurídicas.\nEn todo caso las autoridades ambientales competentes deberán cuidar que se garantice debidamente la ejecución de los convenios por parte de quienes asuman obligaciones de restauración o compensación.\n(Nota del editor: Existen dos artículos 208 Bis, debido a que en la Gaceta Oficial del Distrito Federal del 10 de febrero de 2004 así se publicó.)\nARTÍCULO 209.- Dentro de los cinco días hábiles siguientes al vencimiento del plazo otorgado al infractor para subsanar las deficiencias e irregularidades observadas, éste deberá comunicar por escrito y en forma detallada a la autoridad ordenadora, haber dado cumplimiento a las medidas ordenadas en los términos del requerimiento o resolución respectiva.\nARTÍCULO 209 Bis.- De conformidad con lo que establezca el reglamento de este ordenamiento, las autoridades ambientales podrán aplicar mecanismos alternativos para la solución de conflictos derivados de infracciones a las disposiciones jurídicas a que se refiere el artículo 201 del mismo. Dentro de dichos mecanismos, se podrán considerar la mediación, el arbitraje y la conciliación.\nEn ningún caso los mecanismos alternativos de solución de conflictos pueden implicar eximir de responsabilidad a los responsables de violaciones o incumplimientos de la normatividad ambiental y tendrán por objeto resarcir daños al ambiente y a los recursos naturales.\nEl reglamento conciliará la aplicación de los mecanismos anotados y los procedimientos de verificación que instauren las autoridades ambientales.\n\nARTÍCULO 210.- Corresponde a la Secretaría y a las delegaciones realizar la vigilancia de las actividades en vía pública, áreas naturales protegidas y suelo de conservación para prevenir y sancionar la comisión de infracciones a la presente Ley. Los vigilantes ecoguardas asignados a esta función deberán estar debidamente acreditados por la Secretaría en los términos del reglamento de esta Ley y en sus actuaciones observarán, en lo aplicable, las disposiciones relativas a las visitas domiciliarias y actos de inspección señaladas en este Título.\nCAPÍTULO III\nMEDIDAS DE SEGURIDAD\nARTÍCULO 211.- De existir riesgo inminente de desequilibrio ecológico, o de daño o deterioro grave a los ecosistemas o a los recursos naturales, casos de contaminación con repercusiones peligrosas para la salud, para los ecosistemas o sus componentes, operación indebida de programas de cómputo y equipos, o se realicen obras o actividades sin contar con la autorización de impacto ambiental o riesgo debiendo sujetarse ala obtención previa de ésta, la autoridad ambiental competente, en forma fundada y motivada, podrá ordenar inmediatamente alguna o algunas de las siguientes medidas de seguridad:\nI. La neutralización o cualquier acción análoga que impida que materiales, sustancias o residuos contaminantes, generen los efectos previstos en el primer párrafo de este artículo;\nII. El aseguramiento precautorio de materiales, sustancias o residuos contaminantes; así como de vehículos, utensilios, instrumentos, equipo, herramientas y cualquier bien directamente relacionado con la conducta que da lugar a la imposición de la medida de seguridad;\nIII. El Aislamiento o retiro temporal, en forma parcial o total, de los bienes, equipos o actividades que generen el riesgo inminente a que se refiere el primer párrafo de este artículo;\nIV. La clausura temporal, parcial o total, de las fuentes contaminantes, de obras y actividades, así como de las instalaciones en que se desarrollen los hechos que den lugar a los supuestos a que se refiere el primer párrafo de este artículo;\nV. La suspensión temporal de obras o actividades;\nVI. La suspensión temporal de permisos, licencias, concesiones o autorizaciones; y\n\nVII. La realización de las demás acciones que sean necesarias para evitar que continúe suscitándose el riesgo inminente o los demás supuestos a que se refiere el primer párrafo del presente artículo.\nLas medidas de seguridad previstas en las fracciones II y IV de este artículo, también serán procedentes cuando se ejecuten obras y actividades sin el permiso, licencia, autorización o concesión correspondientes.\nLa autoridad podrá solicitar el auxilio de la fuerza pública para ejecutar cualquiera de las acciones anteriores.\nEn todo caso, la autoridad deberá hacer constar en el documento en el que ordene las medidas de seguridad, las razones por las cuales considera que se actualiza el supuesto de procedencia de las mismas.\nARTÍCULO 211 Bis.- Las personas responsables de los hechos que dan lugar a la imposición de las medidas de seguridad deberán acatar las mismas, sin perjuicio de que las autoridades ambientales realicen las acciones que se requieran para la debida observancia y ejecución de las referidas medidas de seguridad, supuesto en el cual, las personas responsables de los hechos que dieron lugar a la determinación de tales medidas, deberán cubrir los gastos que hubiesen sufragado las autoridades ambientales, por lo que, dichos gastos tendrán el carácter de un crédito fiscal.\nARTÍCULO 212.- Cuando la autoridad ordene alguna de las medidas de seguridad previstas en el artículo\n211 de esta Ley, indicará al interesado, cuando procedan, las acciones que debe llevar a cabo para subsanar o corregir los hechos que motivaron la imposición de dichas medidas, así como los plazos para su realización, a fin de que una vez cumplidas éstas, se dejen sin efectos o se ordene el retiro de las medidas de seguridad impuestas.\nCAPÍTULO IV\nSANCIONES ADMINISTRATIVAS\nARTÍCULO 213.- Cada una de las infracciones a esta Ley, su reglamento, las normas ambientales del Distrito\nFederal y demás disposiciones que de ella emanen, serán sancionadas administrativamente por la autoridad, con una o más de las siguientes sanciones:\nI. Amonestación con apercibimiento;\n\nII. Multa por el equivalente desde veinte hasta cien mil veces la Unidad de Cuenta de la Ciudad de México vigente;\nIII. Clausura temporal o definitiva, parcial o total de las fuentes contaminantes, de las obras y actividades, así como de las instalaciones en que se desarrollen los hechos que den lugar a la imposición de la sanción;\nIV. Arresto administrativo hasta por treinta y seis horas;\nV. Reparación del daño ambiental;\nVI. Decomiso de los materiales, sustancias o residuos contaminantes; así como de vehículos, utensilios, instrumentos, equipo, herramientas, contenedores, pipas o autotanques de gas y cualquier bien directamente relacionado con la conducta que da lugar a la imposición de la sanción;\nVII. Demolición de las obras e instalaciones relacionadas con la conducta que da lugar a la imposición de la sanción;\nVIII. Suspensión temporal, anulación o revocación de permisos, licencias, certificaciones, registros, concesiones y/o autorizaciones.\nIX. Compensación del daño ambiental en función del dictamen del daño ambiental que la autoridad ambiental emita, y\nX. Realización de programas, obras o actividades ambientales a cargo de la Secretaría contenidos en sus programas de trabajo encaminados al rescate y protección de áreas ambientalmente impactadas.\nEn todo caso, las sanciones se aplicarán en los términos que disponga el Reglamento correspondiente a la materia.\nARTÍCULO 214.- Para la imposición de las sanciones por infracciones a esta Ley, se tomarán en cuenta:\nI. Los daños o afectaciones que se hubiesen propiciado o se puedan generar a los recursos naturales, con motivo de los hechos constitutivos de las infracciones de que se trate;\n\nII. Las condiciones económicas de la persona infractora para determinar que no sea ruinosa o desproporcionada una multa;\nIII. La reincidencia, si la hubiere;\nIV. El cumplimiento o incumplimiento de medidas correctivas o de seguridad.\nV. El monto de la inversión de la obra, proyecto, programa o actividad; así como el importe destinado a la aplicación de medidas de seguridad, prevención, mitigación y/o compensación que no se hubieran cumplido;\nVI. Las ganancias o beneficios obtenidos con la operación de una obra proyecto, programa o actividad de manera clandestina y de aquellas que operan sin contar con la autorización, permiso, licencia o registro correspondiente;\nVII. La veracidad o falsedad, dolo o mala fe con que se conduzca el interesado o prestador de servicios ambientales o el error al que haya inducido o pretenda inducir a la autoridad para obtener un beneficio o ganancia indebida; y\nVIII. El cumplimiento o incumplimiento de las condicionantes, obligaciones, lineamientos y/o disposiciones establecidos en las licencias, autorizaciones, permisos, registros y demás ordenamientos ambientales vigentes, por parte del responsable de una obra, proyecto, programa o actividad en cada una de sus etapas.\nARTÍCULO 214 BIS. Se sancionará con una multa de 100 a 1,000 Unidades de Cuenta de la Ciudad de\nMéxico vigente a quien impida al personal autorizado el acceso al lugar o lugares sujetos a inspección ambiental, en los términos previstos en la orden escrita de acuerdo al artículo 205 de la Ley;\nARTÍCULO 214 TER. Se sancionará con una multa de 5,00 a 80,000 Unidades de Cuenta de la Ciudad de\nMéxico vigente las siguientes conductas:\nI. No se empleen equipos y sistemas que controlen las emisiones a la atmósfera, para que no rebasen los niveles máximos permisibles establecidos en las normas oficiales mexicanas y las normas ambientales locales correspondientes; de conformidad con las obligaciones establecidas en la fracción I del artículo 135 de la Ley;\n\nII. A quien no mida y reporte sus emisiones contaminantes a la atmósfera, de acuerdo a los formatos establecidos por la secretaria, de conformidad con lo establecido en la fracción II del artículo 135 de la Ley;\nIII. A quien omita dar los avisos a que se refieren las fracciones VI y VII del artículo 135 de la Ley;\nIV. Realizar obras y actividades en suelo urbano sin la presentación del informe preventivo ante la Secretaría de conformidad con lo previsto en el artículo 56 de la Ley y el Reglamento de\nImpacto y Riesgo Ambiental;\nV. Realizar obras y actividades a que se refiere el artículo 46 de la Ley que por su ubicación, dimensiones, características o alcances produzcan impactos ambientales y no presenten la\nDeclaratoria de Cumplimiento Ambiental ante la Secretaría de conformidad con lo previsto en el artículo 58 Bis de la Ley;\nARTÍCULO 214 QUATER. A quien se coloque en cualquiera de los siguientes supuestos, será sancionado con multa de 50,000 a 100,000 Unidades de Medida y Actualización vigente:\nReforma publicada en la GOCDMX el 27 de febrero de 2023\nI. Realizar obras o actividades de explotación o aprovechamiento de recursos en áreas naturales protegidas, sin la autorización correspondiente;\nII. Realizar obras o actividades que causen o pudieran causar impacto ambiental negativo, sin la autorización correspondiente, o bien, en contravención de los términos y condiciones establecidos en la autorización derivada de la manifestación de impacto ambiental presentada;\nIII. Realizar obras o actividades que causen o pudieran causar impacto ambiental negativo, sin la autorización correspondiente, o bien, en contravención de los términos y condiciones establecidos en la Manifestación Ambiental Única o su actualización;\nReforma publicada en la GOCDMX el 27 de febrero de 2023\nIV. Descargar aguas residuales de origen industrial que rebasen los límites permitidos en el sistema de drenaje y alcantarillado, así como a los cuerpos de agua o a los sistemas de drenaje y alcantarillado, sin cumplir con los criterios, reglamentos y normas oficiales mexicanas;\n\nV. No instalar plantas o sistemas de tratamiento de aguas residuales de conformidad con los criterios, reglamentos y normas oficiales mexicanas;\nVI. No cumplir con los programas de ordenamiento ecológico del territorio; a las declaratorias de áreas de valor ambiental y de áreas naturales protegidas y sus programas de manejo, programas de rescate y recuperación; a las normas y demás disposiciones jurídicas aplicables;\nVII. Aquel prestador de servicios en materia de impacto ambiental que no actué conforme a las obligaciones señaladas en esta ley, o actué con negligencia comprobada, de tal modo de dicho actuar genere un daño o peligro al ambiente;\nVIII. No contar con la autorización correspondiente para llevar a cabo el manejo y disposición final de residuos en términos del artículo 172 de la Ley;\nARTÍCULO 214 QUINQUIES. La infracción a cualquier otro precepto de la Ley o de las disposiciones que de ella deriven, de las normas oficiales mexicanas o las normas oficiales emitidas por la Secretaría distinta de las señaladas expresamente en algún otro artículo de esta Ley y que no tenga sanción especialmente prevista en este ordenamiento será sancionada con multa de 2,000 a 10,000 Unidades de Cuenta de la\nCiudad de México.\nARTÍCULO 214 SEXIES. Con independencia de la multa que se imponga por la conducta infractora en que se incurra, se podrá determinar adicionalmente, cualquiera de las demás sanciones administrativas establecidas en el artículo 213 de esta Ley.\nARTÍCULO 215.- Cuando se trate de segunda o posterior inspección para constatar el cumplimiento de un requerimiento o requerimientos anteriores, y del acta correspondiente se desprenda que no se ha dado cumplimiento a las medidas previamente ordenadas, la autoridad competente podrá imponer, además de la sanción o sanciones que procedan conforme al presente capítulo, una multa adicional que no exceda de los límites máximos señalados.\nPara el caso de reincidencia, el monto de la multa podrá ser hasta por dos veces del monto inicialmente impuesto, así como la clausura definitiva.\nSe considere reincidente al infractor que incurra más de una vez en conductas que impliquen infracciones a un mismo precepto, en un periodo de dos años, contados a partir de la fecha en que se levante el acta en que se hizo constar la primera infracción, siempre que esta no hubiese sido des virtuada.\n\nARTÍCULO 216.- En el caso en que el infractor realice las medidas correctivas o de urgente aplicación, o subsane las irregularidades en que hubiere incurrido, previamente a la imposición de una sanción y siempre que lo haga del conocimiento de la autoridad competente, ésta considerará tal situación como atenuante al momento de dictar la resolución respectiva.\nARTÍCULO 216 Bis. La autoridad ambiental competente, a solicitud del infractor, podrá otorgar a éste la opción de conmutar hasta la mitad del monto de la multa por la realización de inversiones equivalentes a dicha reducción, en adquisición o instalación de equipos para evitar la contaminación ambiental o en la protección, preservación o restauración del ambiente y los recursos naturales, siempre y cuando se garanticen las obligaciones del infractor y la autoridad justifique plenamente su decisión.\nEl plazo para la interposición de la solicitud de conmutación será de quince días, contados a partir de la notificación de la resolución administrativa correspondiente. La solicitud deberá indicar las acciones propuestas y el plazo para ejecutarlas.\nLa autoridad podrá negar la conmutación cuando ésta no represente un beneficio para el ambiente, proporcional al de la multa conmutada.\nARTÍCULO 217.- Cuando se aplique como sanción la clausura temporal o definitiva, el personal comisionado para ejecutarla, procederá a levantar un acta circunstanciada de la diligencia correspondiente.\nEn los casos en que se imponga como sanción la clausura temporal, la autoridad ambiental deberá indicar al infractor las medidas correctivas y las acciones que en su caso debe llevar a cabo para subsanar las irregularidades que motivaron dicha sanción, así como los plazos para su realización a efecto de que sea susceptible el levantamiento de dicha clausura.\nARTÍCULO 217 Bis.- En el caso de que se imponga como sanción la demolición de obras e instalaciones, sin necesidad de recurrir a ningún otro proceso o procedimiento, las autoridades ambientales correspondientes deberán indicar a los infractores los plazos y condiciones para llevar a cabo las acciones respectivas. Si una vez transcurrido dicho plazo o cumplidas las condiciones no se realiza la demolición respectiva, las propias autoridades ambientales podrán realizarlas a costa del infractor, sin que proceda la indemnización ni compensación alguna. Los gastos derivados de las labores de demolición o retiro de materiales llevados a cabo por las autoridades ambientales, constituirán créditos fiscales a favor de las autoridades del Gobierno del Distrito Federal, a cargo de los propios infractores.\n\nARTÍCULO 218.- Cuando las autoridades ambientales, en los términos de esta Ley tengan conocimiento de constancias que se presuman apócrifas, harán la denuncia correspondiente por los ilícitos que resulten. Los documentos apócrifos serán considerados nulos de pleno derecho. Las autoridades competentes implementarán los mecanismos de información para consulta del público respecto de certificaciones, permisos, licencias y autorizaciones que emitan, en los términos de las disposiciones jurídicas vigentes al respecto.\nEn el caso de aquellas constancias, certificados, certificaciones, permisos, licencias, autorizaciones o documentos oficiales que hayan sido emitidos con error, dolo o mala fe, la Administración Pública del\nDistrito Federal, por conducto de la dependencia competente, revocará el acto de que se trate, independientemente de las responsabilidades administrativas o penales que resulten.\nARTÍCULO 219.- Los funcionarios públicos que contravengan las disposiciones de esta Ley, su reglamento y las demás disposiciones aplicables incurren en responsabilidad y serán sancionados en los términos de la Ley correspondiente.\nCAPÍTULO V\nRECURSO DE INCONFORMIDAD\nARTÍCULO 220.- Las resoluciones dictadas en los procedimientos administrativos con motivo de la aplicación de esta Ley, sus reglamentos, normas ambientales del Distrito Federal y disposiciones que de ella emanen, podrán ser impugnadas sin que se pruebe el interés jurídico, mediante el recurso de inconformidad conforme a las reglas establecidas en la Ley de Procedimiento Administrativo del Distrito\nFederal.\nCAPÍTULO VI\nDE LA RESPONSABILIDAD POR EL DAÑO AMBIENTAL\nARTÍCULO 221.- Sin perjuicio de las sanciones penales o administrativas que procedan, toda persona que contamine o deteriore el ambiente, o afecte los recursos naturales de competencia del Distrito Federal será responsable y estará obligada a reparar los daños causados, de conformidad con lo dispuesto en la legislación civil aplicable al Distrito Federal y esta Ley.\n\nLa acción por daños al ambiente se ejercerá sin perjuicio del ejercicio de la acción indemnizatoria ordinaria promovida por el directamente afectado.\nLa acción para demandar la responsabilidad por daños al ambiente prescribirá cinco años después de que hayan cesado los efectos del daño en cuestión.\nCualquier persona física o moral de las comunidades afectadas tendrá derecho a ejercer la acción de responsabilidad por daño al ambiente, siempre que demuestre en el procedimiento la existencia del daño y el vínculo entre éste y la conducta imputable al demandado. En consecuencia, los tribunales del Distrito\nFederal le reconocerán interés jurídico en los procedimientos de que se trate, sin necesidad de probar que el daño le afecta directamente en sus personas o en sus bienes.\nARTÍCULO 222.-. La reparación del daño consistirá en la restitución de las cosas al estado en que se encontraban antes de producido el daño y sólo si ello no fuere posible, en el pago de una indemnización.\nCuando en un juicio en el que se ejerza la acción de responsabilidad por daño al ambiente el juez determine que ha lugar al pago de una indemnización, el monto de la misma pasará a integrarse a los recursos del fondo ambiental a que se refiere esta Ley.\nARTÍCULO 223.- En materia de daños al ambiente serán competentes todos los jueces del Distrito Federal atendiendo a las disposiciones relativas a la distribución de competencias, por territorio y por cuantía que establecen las disposiciones correspondientes.\nPara el desahogo del procedimiento en el que se ejerza la acción por daños al ambiente se seguirán las reglas establecidas para el procedimiento ordinario civil, establecido en el Código de Procedimientos\nCiviles del Distrito Federal.\nARTÍCULO 224.- Cuando por infracción a las disposiciones de esta Ley y sus disposiciones reglamentarias se ocasionen daños o perjuicios, los interesados podrán solicitar a la autoridad ambiental, la formulación de un dictamen técnico al respecto, el cual tendrá el valor de medio de convicción, en caso de que se presente en juicio.\nArtículo 224 Bis.- Los promoventes de las obras o actividades que se hayan iniciado o realizado sin contar con la autorización en materia de Impacto Ambiental correspondiente, deberán presentar ante la Secretaría el Estudio de Daño Ambiental, con la finalidad de que se dictamine.\n\nEl Estudio de Daño Ambiental deberá presentarse en la Secretaría en original y copia, junto con el pago de derechos correspondiente al dictamen de daño ambiental contemplado en el Código Fiscal del Distrito\nFederal.\nEl Estudio de Daño Ambiental deberá contener al menos lo siguiente:\nI. Datos generales de la persona física o moral en la que recaiga la responsabilidad del daño ambiental;\nII. Ubicación del predio donde se ocasionó el daño ambiental;\nIII. Descripción de las obras o actividades que ocasionaron el daño ambiental;\nIV. La identificación de los factores ambientales dañados;\nV. Estimación de los contaminantes generados;\nVI. El daño ambiental ocasionado, indicando las metodologías utilizadas para su determinación;\nVII. Vinculación con la normatividad ambiental local y/o federal aplicable en sus respectivos ámbitos de competencia;\nVIII. Medidas de prevención, minimización, mitigación y seguridad implementadas durante las etapas realizadas, con sus correspondientes documentos probatorios;\nIX. Servicios ambientales que se afectaron o perdieron por la ocurrencia del daño ambiental;\nX. Propuestas de restauración de los factores ambientales dañados;\nXI. Los costos que serán necesarios para lograr la restauración de los factores ambientales dañados;\nXII. Etapa o etapas de la obra o actividad que falta por concluir, con la finalidad de determinar si se sujetan a la solicitud de autorización en materia de impacto ambiental en su caso, y\n\nXIII. El estudio de daño ambiental deberá presentarse en la secretaría de conformidad con los formatos y guías que al efecto se publiquen.\nCAPÍTULO VII\nDE LOS DELITOS AMBIENTALES\nARTÍCULO 225.- En aquellos casos en que, como resultado del ejercicio de sus atribuciones, la autoridad ambiental tenga conocimiento de actos u omisiones que pudieran constituir delitos conforme a lo previsto en la legislación penal aplicable, formulará ante el Ministerio Público la denuncia correspondiente.\nToda persona podrá presentar directamente las denuncias penales que correspondan a los delitos en contra del ambiente previstos en el Código Penal vigente.\nARTÍCULO 226.- La autoridad ambiental proporcionará, en las materias de su competencia, los dictámenes técnicos o periciales que le soliciten el Ministerio Publico o las autoridades judiciales, con motivo de las denuncias presentadas por delitos en contra del ambiente.\nIgualmente la autoridad ambiental proporcionará los dictámenes técnicos o periciales que le soliciten, con motivo de los juicios contencioso administrativos que se ventilen ante dicho Tribunal.\nT R A N S I T O R I O S\nPRIMERO.- La presente Ley entrará en vigor a los treinta días siguientes de su publicación en la Gaceta\nOficial.\nSEGUNDO.- A la entrada en vigor de la presente Ley se abroga la Ley Ambiental del Distrito Federal, publicada en el Diario Oficial de la Federación el 9 de julio de 1996.\nTERCERO.- La reglamentación de esta Ley deberá ser expedida dentro de los ciento ochenta días hábiles siguientes a la entrada en vigor de este ordenamiento.\nCUARTO.- En tanto se expidan las disposiciones administrativas que deriven de la presente ley seguirán en vigor aquéllas que no la contravengan.\n\nQUINTO.- Todos los procedimientos y recursos administrativos relacionados con las materias de esta Ley iniciadas con anterioridad a la entrada en vigor del presente decreto, se tramitarán y resolverán conforme a las disposiciones vigentes en ese momento.\nSEXTO.- En tanto sea creada la Procuraduría Ambiental y del Ordenamiento Territorial del Distrito Federal, las funciones que en la presente Ley se le atribuyen, serán ejercidas por las áreas competentes de la\nSecretaría del Medio Ambiente.\nSÉPTIMO.- El Jefe de Gobierno formulará la iniciativa de Ley Orgánica de la Procuraduría Ambiental y del\nOrdenamiento Territorial del Distrito Federal que se menciona en el artículo 11 de ésta Ley, y la presentará a la consideración de la Asamblea Legislativa del Distrito Federal, en un plazo no mayor de noventa días, contados a partir de la publicación de éste ordenamiento en la Gaceta Oficial del Distrito Federal.\nOCTAVO.- Los recursos financieros que actualmente integran el fondo CONSERVA pasarán a integrarse al fondo a que se refiere esta Ley.\nNOVENO.- En tanto se expiden las disposiciones reglamentarias de esta Ley, seguirá en vigor el Reglamento de la Ley Ambiental del Distrito Federal, publicado en el Diario Oficial de la Federación el 3 de diciembre de 1997, en lo que no se oponga a la presente Ley.\nSalón de Sesiones de la Asamblea Legislativa del Distrito Federal, a 21 de diciembre de mil novecientos noventa y nueve.- Por la Mesa Directiva, Dip. Rene Baldomero Rodríguez Ruiz, presidente.- Dip. Yolanda\nTello Mondragón, Secretario.- Dip. José Luis Benitez Gil, Secretario. Firmas.\nEn cumplimiento de lo dispuesto por lo dispuesto por los artículos 122, apartado C, base segunda, fracción\nII, inciso b), de la Constitución Política de los Estados Unidos mexicanos; 48, 49 y 67, fracción II del Estatuto de Gobierno del Distrito Federal, y para su debida publicación y observancia, expido el presente decreto promulgatorio, en la Residencia Oficial de la Jefa de Gobierno del Distrito Federal, en la Ciudad de México, a los treinta y un días del mes de diciembre de mil novecientos noventa y nueve.- La Jefa de Gobierno del\nDistrito Federal, Rosario Robles Berlanga.- Firma.- El Secretario de Gobierno, Leonel Godoy Rangel.-Firma.-\nEl Secretario de Desarrollo Urbano y Vivienda, Roberto Eibenschutz Hartman.-Firma.- El Secretario del\nMedio Ambiente, Alejandro Encinas Rodríguez.- Firma.\n\nTRANSITORIOS DEL DECRETO QUE REFORMA, ADICIONA Y DEROGA DIVERSAS DISPOSICIONES DE LA LEY\nAMBIENTAL DEL DISTRITO FEDERAL PÚBLICADO EN LA GACETA OFICIAL DEL DISTRITO FEDERAL EL 31 DE\nENERO DE 2002.\nPRIMERO. El presente decreto entrará en vigor el día siguiente al de su publicación en la Gaceta Oficial del\nDistrito Federal.\nSEGUNDO. En tanto se expidan las disposiciones reglamentarias que se deriven del presente Decreto, seguirán en vigor las actuales en lo que no lo contravengan.\nTERCERO. Se derogan todas aquellas disposiciones que contravengan al presente Decreto.\nCUARTO. El Jefe de Gobierno del Distrito Federal, en cumplimiento a la fracción IX del artículo 8º de la Ley\nAmbiental del Distrito Federal, enviará a la Asamblea Legislativa las propuestas de modificación de la categoría de Área Natural Protegida que conforme a lo dispuesto en el presente Decreto corresponderá a las áreas o zonas que hayan sido establecidas con anterioridad a la entrada en vigor del mismo, cuando así sea procedente, de conformidad a sus características y objetivos.\nQUINTO. Para los efectos de este Decreto, se considerará Zona de Preservación Ecológica el área natural protegida denominada “Bosque de Tlalpan”. El Jefe de Gobierno enviará a la Asamblea Legislativa del\nDistrito Federal la propuesta por el cual se modifica la categoría de esta área natural protegida, en cumplimiento a la fracción IX del artículo 8º de la Ley Ambiental del Distrito Federal, dentro de los siguientes 90 días naturales a partir de la entrada en vigor del presente decreto.\nTRANSITORIOS DEL DECRETO POR EL QUE SE REFORMAN, ADICIONAN Y DEROGAN DIVERSAS\nDISPOSICIONES DE LA LEY DE DESARROLLO URBANO DEL DISTRITO FEDERAL, DE LA LEY AMBIENTAL DEL\nDISTRITO FEDERAL, DE LA LEY DE AGUAS DEL DISTRITO FEDERAL, DE LA LEY DE VIVIENDA DEL DISTRITO\nFEDERAL Y DE LA LEY DEL NOTARIADO PARA EL DISTRITO FEDERAL; PUBLICADO EN LA GACETA OFICIAL DEL\nDISTRITO FEDERAL EL 29 DE ENERO DE 2004.\nPRIMERO.- En tanto se expidan las disposiciones administrativas que deriven de las presentes adiciones y modificaciones seguirán en vigor aquellas que no las contravengan.\n\nTRANSITORIOS DEL DECRETO POR EL QUE SE REFORMAN, ADICIONAN Y DEROGAN DIVERSOS ARTÍCULOS\nDE LA LEY AMBIENTAL DEL DISTRITO FEDERAL; PUBLICADO EN LA GACETA OFICIAL DEL DISTRITO FEDERAL\nEL 10 DE FEBRERO DE 2004.\nÚNICO.- El presente Decreto entrará en vigor al día siguiente al de su publicación en la Gaceta Oficial del\nDistrito Federal.\nTRANSITORIOS DEL DECRETO POR EL QUE SE REFORMAN, ADICIONAN Y DEROGAN DIVERSAS\nDISPOSICIONES DE LA LEY AMBIENTAL DEL DISTRITO FEDERAL PUBLICADO EN LA GACETA OFICIAL DEL\nDISTRITO FEDERAL EL 4 DE JUNIO DE 2004.\nÚNICO.- El presente Decreto entrará en vigor al día siguiente al de su publicación en la Gaceta Oficial del\nDistrito Federal.\nTRANSITORIOS DEL DECRETO POR EL QUE SE REFORMA Y ADICIONA LA LEY AMBIENTAL DEL DISTRITO\nFEDERAL, PUBLICADO EN LA GACETA OFICIAL DEL DISTRITO FEDERAL EL 21 DE JUNIO DE 2006.\nPRIMERO.- El presente decreto entrará en vigor al día siguiente de su publicación en la Gaceta Oficial del\nDistrito Federal.\nSEGUNDO.- La Secretaría y las autoridades competentes del Gobierno del Distrito Federal realizarán las adecuaciones correspondientes en los Programas y Reglamentos derivadas de la presente reforma\nTERCERO.-. Se exceptúan de la aplicación de las disposiciones a que se refieren los artículos 139 y 140 las motocicletas en circulación matriculadas en el Distrito Federal, hasta en tanto se expida la Normatividad\nOficial Mexicana aplicable precisamente a la verificación de emisiones contaminantes de motocicletas y una vez expedidas, la Secretaría deberá establecer una tarifa equitativa por concepto de verificación y un holograma específico por la verificación de motocicletas.\nCUARTO.- La instalación del Consejo Rector Ciudadano a que se refiere el artículo 90 Bis 7, se conformará dentro de los 120 días siguientes a la declaratoria que se emita de Bosque Urbano.\n\nTRANSITORIOS DEL DECRETO POR EL QUE SE REFORMA LA LEY AMBIENTAL DEL DISTRITO FEDERAL, LA LEY\nDE SALUD PARA EL DISTRITO FEDERAL Y LA LEY PARA EL FUNCIONAMIENTO DE ESTABLECIMIENTOS\nMERCANTILES DEL DISTRITO FEDERAL, PUBLICADO EN LA GACETA OFICIAL DEL DISTRITO FEDERAL EL 9 DE\nFEBRERO DE 2007.\nPRIMERO.-Se derogan todas las disposiciones que contravengan la presente iniciativa.\nSEGUNDO.- Las presentes reformas y adiciones entrarán en vigor al día siguiente al de su publicación en la\nGaceta Oficial del Gobierno del Distrito Federal y para su mayor Difusión en el Diario Oficial de la\nFederación.\nTRANSITORIOS DEL DECRETO POR EL QUE SE REFORMA LA LEY DEL HEROICO CUERPO DE BOMBEROS DEL\nDISTRITO FEDERAL, SE REFORMA LA LEY DE DESARROLLO URBANO DEL DISTRITO FEDERAL, SE REFORMA LA\nLEY DE PROTECCIÓN CIVIL PARA EL DISTRITO FEDERAL, SE REFORMA LA LEY AMBIENTAL DEL DISTRITO\nFEDERAL, SE REFORMA LA LEY ORGÁNICA DE LA ADMINISTRACIÓN PÚBLICA DEL DISTRITO FEDERAL, SE\nREFORMA LA LEY DE LA PROCURADURÍA SOCIAL DEL DISTRITO FEDERAL, SE REFORMA LA LEY DE AGUAS\nDEL DISTRITO FEDERAL, SE REFORMA LA LEY DE TURISMO DEL DISTRITO FEDERAL, SE REFORMA LA LEY DE\nLOS DERECHOS DE LAS NIÑAS Y NIÑOS DEL DISTRITO FEDERAL, SE REFORMA LA LEY DEL DEPORTE PARA EL\nDISTRITO FEDERAL Y SE REFORMA LA LEY DEL INSTITUTO DE CIENCIA Y TECNOLOGÍA DEL DISTRITO FEDERAL.\nPUBLICADO EN LA GACETA OFICIAL DEL DISTRITO FEDERAL EL 30 DE ABRIL DE 2007.\nPRIMERO.- Publíquese en la Gaceta Oficial del Distrito Federal, y en el Diario Oficial de la Federación para su mayor difusión.\nSEGUNDO.- Las presentes reformas y adiciones entrarán en vigor al día siguiente de su publicación en la\nGaceta Oficial del Distrito Federal.\nTRANSITORIOS DEL DECRETO POR EL QUE SE REFORMA Y ADICIONA LA LEY ORGÁNICA DE LA SECRETARÍA\nDE SEGURIDAD PÚBLICA DEL DISTRITO FEDERAL; SE REFORMA Y ADICIONA LA LEY DEL HEROICO CUERPO\nDE BOMBEROS DEL DISTRITO FEDERAL Y SE REFORMA Y ADICIONA LA LEY AMBIENTAL DEL DISTRITO\nFEDERAL. PUBLICADO EN LA GACETA OFICIAL DEL DISTRITO FEDERAL EL 31 DE OCTUBRE DE 2008.\nPRIMERO.- Publíquese en la Gaceta Oficial del Distrito Federal y para su mayor difusión en el Diario Oficial de la Federación.\n\nSEGUNDO.- Las presentes modificaciones de ley entrarán en vigor 90 días después de su publicación en la\nGaceta Oficial para el Distrito Federal.\nTERCERO.- De conformidad con el artículo 39 de la Ley Orgánica de la Secretaría de Seguridad Pública del\nDistrito Federal, la Secretaria de Seguridad Pública denominará a los agrupamientos que cumplan con las nuevas especificaciones de esa ley, como “Policía ambiental” y que formarán parte de la Policía\nMetropolitana.\nCUARTO.- A partir de la entrada en vigor de la presente ley, en la aprobación del presupuesto de egresos del 2009, se incluirá un apartida especial para el Heroico cuerpo de Bomberos del Distrito Federal, para la construcción de las Estaciones y subestaciones de Bomberos Forestales, así como para los recursos materiales, humanos y financieros que se requieren para el establecimiento de la policía ambiental.\nQUINTO.- La Secretaría de Seguridad Pública del Gobierno del Distrito Federal, establecerá la estructura administrativa, así como los recursos humanos y materiales necesarios para la creación del cuerpo de policía ambiental con los recursos adicionales que le sean autorizados.\nTRANSITORIOS DEL DECRETO POR EL QUE SE REFORMA LA LEY AMBIENTAL DEL DISTRITO FEDERAL,\nPUBLICADO EN LA GACETA OFICIAL DEL DISTRITO FEDERAL EL 13 DE ENERO DE 2009.\nPRIMERO.- Publíquese en la Gaceta Oficial del Distrito Federal y en el Diario Oficial de la Federación para su mayor difusión.\nSEGUNDO.- El presente decreto entrará en vigor al día siguiente de su publicación.\nTRANSITORIOS DEL DECRETO POR EL QUE SE REFORMA EL ARTÍCULO 201 DE LA LEY AMBIENTAL DEL\nDISTRITO FEDERAL, PUBLICADO EN LA GACETA OFICIAL DEL DISTRITO FEDERAL EL 24 DE FREBRERO DE\n2009.\nPRIMERO.- El presente decreto entrará en vigor al día siguiente de su publicación en la Gaceta Oficial del\nDistrito Federal.\nSEGUNDO.- Se derogan todas las disposiciones legales y administrativas que se opongan a la presente.\n\nTRANSITORIOS DEL DECRETO POR EL QUE SE ADICIONA UN ARTÍCULO 122 BIS A LA LEY AMBIENTAL DEL\nDISTRITO FEDERAL, PUBLICADO EN LA GACETA OFICIAL DEL DISTRITO FEDERAL EL 29 DE NOVIEMBRE DE\n2010.\nPRIMERO.- El presente decreto entrará en vigor en enero del 2012, después de su publicación en la Gaceta\nOficial para el Distrito Federal.\nSEGUNDO.- Publíquese en la Gaceta Oficial del Distrito Federal y para su mayor difusión en el Diario Oficial de la Federación.\nTRANSITORIOS DEL DECRETO POR EL QUE SE REFORMAN DIVERSAS DISPOSICIONES DE LA LEY ORGÁNICA\nDE LA ADMINISTRACIÓN PÚBLICA DEL DISTRITO FEDERAL; DE LA LEY DEL RÉGIMEN PATRIMONIAL Y DEL\nSERVICIO PÚBLICO DEL DISTRITO FEDERAL Y DE LA LEY AMBIENTAL DEL DISTRITO FEDERAL. PUBLICADO EN\nLA GACETA OFICIAL DEL DISTRITO FEDERAL EL 27 DE DICIEMBRE DE 2010.\nPRIMERO. El presente decreto entrará en vigor a partir del día siguiente de su publicación en la Gaceta\nOficial del Distrito Federal.\nSEGUNDO.- Publíquese en la Gaceta Oficial del Distrito Federal y para su mayor difusión en el Diario Oficial de la Federación.\nTERCERO.- Para el cumplimiento de lo dispuesto en la fracción VI del artículo 10 de la Ley Ambiental del\nDistrito Federal, esta Asamblea Legislativa sujeto a disponibilidad presupuestal, deberá incluir en el\nPresupuesto de Egresos del Distrito Federal del Ejercicio Fiscal inmediato a la aprobación de la presente reforma, una partida especial para que las delegaciones políticas cumplan con las disposiciones relativas al establecimiento de sistemas de ahorro de energía ó tecnologías que permitan el aprovechamiento de la energía solar, en mobiliario destinado al servicio de alumbrado público.\nCada año, sujeto a disponibilidad presupuestal se deberá asignar una partida especial en el Presupuesto de Egresos del Distrito Federal, para el establecimiento de sistemas de ahorro de energía ó tecnologías que aprovechen la energía solar, a que se refiere la fracción VI del artículo 10 de la presente reforma en la Ley\nAmbiental del Distrito Federal.\n\nDurante el primer año, cuando haya presupuesto asignado, las demarcaciones procurarán cambiar el 15 por ciento del mobiliario por sistemas de ahorro de energía ó tecnologías que permitan el aprovechamiento de la energía solar; asimismo, tendrán que cambiar anualmente el 10 por ciento de su mobiliario hasta llegar sucesivamente a la totalidad en la demarcación.\nLas Delegaciones presentaran con 6 meses de anticipación en coordinación con la Secretaría de Medio\nAmbiente estos programas a su aprobación.\nTRANSITORIOS DEL DECRETO POR EL QUE SE ADICIONAN LAS FRACCIONES IV Y V DEL ARTÍCULO 163 DE LA\nLEY AMBIENTAL DEL DISTRITO FEDERAL, PUBLICADO EN LA GACETA OFICIAL DEL DISTRITO FEDERAL EL 14\nDE FEBRERO DE 2011.\nPRIMERO. El presente decreto entrará en vigor a partir del día siguiente al de su publicación en la Gaceta\nOficial.\nSEGUNDO.- La Secretaría del Medio Ambiente del Distrito Federal, cuenta con 9 meses para elaborar y publicar en la Gaceta Oficial del Distrito Federal, la norma ambiental a que hace referencia el presente decreto.\nTERCERO.- Publíquese en la Gaceta Oficial del Distrito Federal y para su mayor difusión en el Diario Oficial de la Federación.\nTRANSITORIOS DEL DECRETO POR EL QUE SE REFORMAN DIVERSOS ARTÍCULOS DE LA LEY AMBIENTAL DEL\nDISTRITO FEDERAL, PUBLICADO EN LA GACETA OFICIAL DEL DISTRITO FEDERAL EL 18 DE FEBRERO DE 2011.\nPRIMERO: El presente Decreto entrará en vigor a los 180 días de su publicación en la Gaceta Oficial del\nDistrito Federal.\nSEGUNDO: Publíquese en la Gaceta Oficial del Distrito Federal y en el Diario Oficial de la Federación para su mayor difusión.\nTRANSITORIOS DEL DECRETO QUE REFORMA, ADICIONA Y DEROGA DIVERSAS DISPOSICIONES DE LA LEY\nDE PROCEDIMIENTO ADMINISTRATIVO DEL DISTRITO FEDERAL, DE LA LEY DE ADQUISICIONES DEL DISTRITO\n\nFEDERAL Y DE LA LEY AMBIENTAL DEL DISTRITO FEDERAL; PUBLICADO EN LA GACETA OFICIAL DEL DISTRITO\nFEDERAL EL 7 DE ABRIL DE 2011.\nPRIMERO.- Publíquese en la Gaceta Oficial del Distrito Federal.\nSEGUNDO.- Se derogan aquellas disposiciones que se opongan a lo contenido en el presente Decreto.\nTERCERO.- La Oficialía Mayor implementará el Padrón de Proveedores de la Administración Pública del\nDistrito Federal a que se refiere el artículo 14 Bis de la Ley de Adquisiciones para el Distrito Federal, dentro de los doce meses siguientes a la entrada en vigor de este Decreto.\nCUARTO.- Este Decreto entrará en vigor al día siguiente de su publicación en la Gaceta Oficial del Distrito\nFederal.\nTRANSITORIOS DEL DECRETO POR EL QUE SE REFORMAN Y ADICIONAN DIVERSAS DISPOSICIONES DE LA\nLEY AMBIENTAL DEL DISTRITO FEDERAL, PUBLICADO EN LA GACETA OFICIAL DEL DISTRITO FEDERAL EL 3 DE\nMAYO DE 2011.\nPRIMERO. El presente Decreto entrará en vigor al día siguiente al de su publicación en la Gaceta Oficial del\nDistrito Federal.\nSEGUNDO.- Publíquese en la Gaceta Oficial del Distrito Federal y para su mayor difusión en el Diario Oficial de la Federación.\nTRANSITORIOS DEL DECRETO POR DECRETO POR EL QUE SE ADICIONA LA LEY AMBIENTAL DEL DISTRITO\nFEDERAL, PUBLICADO EN LA GACETA OFICIAL DEL DISTRITO FEDERAL EL 3 DE MAYO DE 2011.\nPRIMERO. El presente Decreto entrará en vigor al siguiente día de su publicación en la Gaceta Oficial del\nDistrito Federal.\nSEGUNDO.- Se derogan todas aquellas disposiciones que contravengan el contenido del presente Decreto.\n\nTRANSITORIOS DEL DECRETO POR EL QUE SE REFORMAN LOS ARTÍCULOS 61 Y 118 DE LA LEY AMBIENTAL\nDEL DISTRITO FEDERAL, PUBLICADO EN LA GACETA OFICIAL DEL DISTRITO FEDERAL EL 24 DE NOVIEMBRE\nDE 2011.\nPRIMERO.- El presente Decreto entrará en vigor al día siguiente de su publicación.\nSEGUNDO.- Publíquese en la Gaceta Oficial del Distrito Federal para su debida observancia y aplicación.\nTRANSITORIOS DEL DECRETO POR EL QUE SE ADICIONA UNA FRACCIÓN IX AL ARTÍCULO 10 DE LA LEY\nAMBIENTAL DEL DISTRITO FEDERAL, PUBLICADO EN LA GACETA OFICIAL DEL DISTRITO FEDERAL EL 15 DE\nMAYO DE 2012.\nPRIMERO.- El presente Decreto, entrará en vigor al día siguiente de su publicación en la Gaceta Oficial del\nDistrito Federal.\nSEGUNDO.- Publíquese en la Gaceta Oficial del Distrito Federal y en el Diario Oficial de la Federación, para su mayor difusión.\nTRANSITORIOS DEL DECRETO POR EL QUE SE REFORMAN Y ADICIONAN DIVERSAS DISPOSICIONES DE LA\nLEY DE CULTURA CÍVICA DEL DISTRITO FEDERAL Y DE LA LEY AMBIENTAL DEL DISTRITO FEDERAL, PUBLICADO\nEN LA GACETA OFICIAL DEL DISTRITO FEDERAL EL 31 DE MAYO DE 2012.\nPRIMERO.- Publíquese en la Gaceta Oficial del Distrito Federal y en el Diario Oficial de la Federación, para su mayor difusión.\nSEGUNDO.- El presente Decreto, entrará en vigor al día siguiente de su publicación en la Gaceta Oficial del\nDistrito Federal.\nTRANSITORIOS DEL DECRETO POR EL QUE SE REFORMAN Y ADICIONAN DIVERSAS DISPOSICIONES DE LA\nLEY AMBIENTAL DEL DISTRITO FEDERAL Y POR EL QUE SE REFORMAN DIVERSAS DISPOSICIONES DE LA LEY\nORGÁNICA DE LA PROCURADURÍA AMBIENTAL Y DEL ORDENAMIENTO TERRITORIAL DEL DISTRITO FEDERAL.\nPUBLICADO EN LA GACETA OFICIAL DEL DISTRITO FEDERAL EL 25 DE JULIO DE 2012.\n\nPRIMERO: Publíquese en la Gaceta Oficial del Distrito Federal y para su mayor difusión en el Diario Oficial de la Federación.\nSEGUNDO: El presente Decreto entrará en vigor a partir del día siguiente de su publicación en la Gaceta\nOficial del Distrito Federal.\nTRANSITORIOS DEL DECRETO POR EL QUE SE REFORMAN DIVERSAS DISPOSICIONES DE LA LEY AMBIENTAL\nDEL\nDISTRITO FEDERAL, PUBLICADO EN LA GACETA OFICIAL DEL DISTRITO FEDERAL EL 27 DE JUNIO DE 2013.\nPRIMERO.- El presente Decreto entrará en vigor al día siguiente de su publicación en la Gaceta Oficial del\nDistrito Federal.\nSEGUNDO.- El Jefe de Gobierno del Distrito Federal deberá hacer las adecuaciones necesarias a la normatividad reglamentaria aplicable dentro de los 180 días naturales siguientes a la entrada en vigor del presente Decreto.\nTRANSITORIOS DEL DECRETO POR EL QUE SE CAMBIA EL NOMBRE DE LA LEY AMBIENTAL DEL DISTRITO\nFEDERAL POR LEY DE PROTECCIÓN A LA TIERRA EN EL DISTRITO FEDERAL Y SE REFORMAN Y ADICIONAN\nDIVERSAS DISPOSICIONES DE LA LEY AMBIENTAL DEL DISTRITO FEDERAL; ASÍ COMO SE REFORMAN\nDIVERSAS DISPOSICIONES DE LA LEY ORGÁNICA DE LA PROCURADURÍA AMBIENTAL Y DEL ORDENAMIENTO\nTERRITORIAL DEL DISTRITO FEDERAL, PUBLICADO EN LA GACETA OFICIAL DEL DISTRITO FEDERAL EL 17 DE\nSEPTIEMBRE DE 2013.\nPRIMERO.- El presente decreto entrará en vigor a los treinta días siguientes de su publicación en la Gaceta\nOficial del Distrito Federal.\nSEGUNDO.- La modificación y adecuación de la reglamentación de estas leyes deberá ser expedida dentro de los ciento ochenta días hábiles siguientes a la entrada en vigor de este ordenamiento.\nTERCERO.- En tanto se expidan las disposiciones administrativas que deriven de la presente reforma seguirán en vigor aquéllas que no la contravengan.\n\nCUARTO.- Todos los procedimientos y recursos administrativos relacionados con las materias de esta ley iniciadas con anterioridad a la entrada en vigor del presente decreto, se tramitarán y resolverán conforme a las disposiciones vigentes en ese momento.\nQUINTO.- Las reformas a la Ley Ambiental del Distrito Federal, turnadas a la Comisión de Preservación del\nMedio Ambiente, Protección Ecológica y Cambio Climático, durante el Primer Periodo Ordinario, el Primer\nReceso y el Segundo Periodo Ordinario, del Primer Año de Ejercicio, y las que se presenten en lo sucesivo, relativo a la Ley Ambiental del Distrito Federal, se entenderán referidas a la Ley Ambiental de Protección a la Tierra en el Distrito Federal.\nTRANSITORIOS DEL DECRETO POR EL QUE SE REFORMAN DIVERSOS ARTÍCULOS DE CÓDIGOS Y LEYES\nLOCALES, QUE DETERMINAN SANCIONES Y MULTAS ADMINISTRATIVAS, CONCEPTOS DE PAGO Y MONTOS\nDE REFERENCIA, PARA SUSTITUIR AL SALARIO MÍNIMO POR LA UNIDAD DE CUENTA DE LA CIUDAD DE\nMÉXICO, DE MANERA INDIVIDUAL O POR MÚLTIPLOS DE ÉSTA, PUBLICADOS EN LA GACETA OFICIAL DEL\nDISTRITO FEDERAL EL 28 DE NOVIEMBRE DE 2014.\nPRIMERO.- Publíquese en la Gaceta Oficial del Distrito Federal.\nSEGUNDO.- El presente Decreto se tomará como referencia para el diseño e integración del paquete económico correspondiente al ejercicio fiscal 2015 y entrará en vigor junto con dicho paquete, a excepción de lo dispuesto en los artículos SEGUNDO y CUADRAGÉSIMO OCTAVO del presente Decreto relacionado con la materia Electoral, que entrarán en vigor al día siguiente a aquél en que concluya el proceso electoral\n2014-2015 del Distrito Federal.\nTERCERO.- Las reformas contenidas en el presente decreto no se aplicarán de manera retroactiva en perjuicio de persona alguna, respecto de las sanciones y multas administrativas, conceptos de pago, montos de referencia y demás supuestos normativos que se hayan generado o impuesto de manera previa a la entrada en vigor del presente decreto.\nCUARTO.- Las referencias que se hagan del salario mínimo en las normas locales vigentes, incluso en aquellas pendientes de publicar o de entrar en vigor, se entenderán hechas a la Unidad de Cuenta de la\nCiudad de México, a partir de la entrada en vigor del presente Decreto.\n\nTRANSITORIOS DEL DECRETO POR EL QUE REFORMAN, ADICIONAN Y DEROGAN, DIVERSOS ARTÍCULOS DEL\nCÓDIGO CIVIL PARA EL DISTRITO FEDERAL; CÓDIGO DE INSTITUCIONES Y PROCEDIMIENTOS ELECTORALES\nDEL DISTRITO FEDERAL; CÓDIGO FISCAL DEL DISTRITO FEDERAL; CÓDIGO PENAL PARA EL DISTRITO\nFEDERAL; LEY AMBIENTAL DE PROTECCIÓN A LA TIERRA EN EL DISTRITO FEDERAL; LEY DE ACCESO DE LAS\nMUJERES A UNA VIDA LIBRE DE VIOLENCIA DEL DISTRITO FEDERAL; LEY DE ASISTENCIA Y PREVENCIÓN DE\nLA VIOLENCIA FAMILIAR; LEY DE CENTROS DE RECLUSIÓN PARA EL DISTRITO FEDERAL; LEY DE CULTURA\nCÍVICA DEL DISTRITO FEDERAL; LEY DE ESTABLECIMIENTOS MERCANTILES DEL DISTRITO FEDERAL; LEY DE\nEXTINCIÓN DE DOMINIO PARA EL DISTRITO FEDERAL; LEY DE FISCALIZACIÓN SUPERIOR DE LA CIUDAD DE\nMÉXICO; LEY DE IGUALDAD SUSTANTIVA ENTRE MUJERES Y HOMBRES EN EL DISTRITO FEDERAL; LEY DE\nJUSTICIA ALTERNATIVA DEL TRIBUNAL SUPERIOR DE JUSTICIA PARA EL DISTRITO FEDERAL; LEY DE JUSTICIA\nALTERNATIVA EN LA PROCURACIÓN DE JUSTICIA PARA EL DISTRITO FEDERAL; LEY DE JUSTICIA PARA\nADOLESCENTES PARA EL DISTRITO FEDERAL; LEY DE PARTICIPACIÓN CIUDADANA DEL DISTRITO FEDERAL;\nLEY DE PROTECCIÓN A LAS VÍCTIMAS DEL DELITO DE SECUESTRO PARA EL DISTRITO FEDERAL; LEY DE\nPRESTACIÓN DE SERVICIOS INMOBILIARIOS DEL DISTRITO FEDERAL; LEY DE PROTECCIÓN A LOS ANIMALES\nDEL DISTRITO FEDERAL; LEY DE PROTECCIÓN DE DATOS PERSONALES PARA EL DISTRITO FEDERAL; LEY DE\nSALUD DEL DISTRITO FEDERAL; LEY DE SALUD MENTAL DEL DISTRITO FEDERAL; LEY DE SEGURIDAD PRIVADA\nPARA EL DISTRITO FEDERAL; LEY DE TRANSPARENCIA Y ACCESO A LA INFORMACIÓN PÚBLICA DEL DISTRITO\nFEDERAL; LEY DEL FONDO DE APOYO A LA ADMINISTRACIÓN DE JUSTICIA EN EL DISTRITO FEDERAL; LEY DEL\nFONDO DE APOYO A LA PROCURACIÓN DE JUSTICIA EN EL DISTRITO FEDERAL; LEY DEL HEROICO CUERPO\nDE BOMBEROS DEL DISTRITO FEDERAL; LEY DEL INSTITUTO DE ESTUDIOS CIENTÍFICOS PARA LA\nPREVENCIÓN DEL DELITO EN EL DISTRITO FEDERAL; LEY DEL INSTITUTO DE VERIFICACIÓN ADMINISTRATIVA\nDEL DISTRITO FEDERAL; LEY DEL NOTARIADO PARA EL DISTRITO FEDERAL; LEY DE LA COMISIÓN DE\nDERECHOS HUMANOS DEL DISTRITO FEDERAL; LEY DE LA DEFENSORÍA PÚBLICA DEL DISTRITO FEDERAL;\nLEY DE LOS DERECHOS DE LAS PERSONAS ADULTAS MAYORES EN EL DISTRITO FEDERAL; LEY ORGÁNICA\nDEL TRIBUNAL SUPERIOR DE JUSTICIA DEL DISTRITO FEDERAL; LEY ORGÁNICA DE LA ADMINISTRACIÓN\nPÚBLICA DEL DISTRITO FEDERAL; LEY ORGÁNICA DE LA PROCURADURÍA AMBIENTAL Y DEL ORDENAMIENTO\nTERRITORIAL DEL DISTRITO FEDERAL; LEY PARA LA ATENCIÓN INTEGRAL DEL CONSUMO DE SUSTANCIAS\nPSICOACTIVAS DEL DISTRITO FEDERAL; LEY PARA LA INTEGRACIÓN AL DESARROLLO DE LAS PERSONAS CON\nDISCAPACIDAD DEL DISTRITO FEDERAL; LEY PARA LA PROMOCIÓN DE LA CONVIVENCIA LIBRE DE\nVIOLENCIA EN EL ENTORNO ESCOLAR DEL DISTRITO FEDERAL; LEY PARA LA PROTECCIÓN, ATENCIÓN Y\nASISTENCIA A LAS VÍCTIMAS DE LOS DELITOS EN MATERIA DE TRATA DE PERSONAS DEL DISTRITO FEDERAL;\nLEY PARA PREVENIR LA VIOLENCIA EN LOS ESPECTÁCULOS DEPORTIVOS EN EL DISTRITO FEDERAL; LEY QUE\nESTABLECE EL PROCEDIMIENTO DE REMOCIÓN DE LOS SERVIDORES PÚBLICOS QUE DESIGNA LA\nASAMBLEA LEGISLATIVA DEL DISTRITO FEDERAL Y DE LOS TITULARES DE LOS ÓRGANOS POLÍTICO\nADMINISTRATIVOS DEL DISTRITO FEDERAL; Y LEY REGISTRAL PARA EL DISTRITO FEDERAL, PUBLICADO EN LA\nGACETA OFICIAL DEL DISTRITO FEDERAL EL 18 DE DICIEMBRE DE 2014.\n\nPRIMERO.- Publíquese en la Gaceta Oficial del Distrito Federal.\nSEGUNDO.- El presente Decreto entrará en vigor en los términos establecidos en la Declaratoria de la\nIncorporación del Sistema Procesal Penal Acusatorio y del Código Nacional de Procedimientos Penales al orden jurídico del Distrito Federal, publicada en la Gaceta Oficial el día 20 de agosto del presente año, así como su Fe de Erratas y Aclaratoria de Fe de Erratas, publicadas en la Gaceta Oficial, los días 21 y 22 de agosto del 2014.\nTERCERO.- Los asuntos iniciados con anterioridad a la entrada en vigor del presente decreto, se tramitarán conforme a las disposiciones anteriores, que le sean aplicables.\nCUARTO.- La reforma al Código de Instituciones y Procedimientos Electorales del Distrito Federal prevista en el presente Decreto, entrará en vigor al día siguiente a aquél en que concluya el proceso electoral local de 2014-2015 en el Distrito Federal.\nTRANSITORIOS DEL DECRETO POR EL QUE SE ADICIONA UN ARTÍCULO 73 BIS A LA LEY AMBIENTAL DE\nPROTECCIÓN A LA TIERRA EN EL DISTRITO FEDERAL, PUBLICADOS EN LA GACETA OFICIAL DEL DISTRITO\nFEDERAL EL 20 DE AGOSTO DE 2015.\nTRANSITORIOS\nPRIMERO. Publíquese el presente decreto en la Gaceta Oficial del Distrito Federal y para su mayor difusión, en el Diario Oficial de la Federación.\nSEGUNDO.- El Presente Decreto entrará en vigor al día siguiente de su publicación en la Gaceta Oficial del\nDistrito Federal.\nRecinto de la Asamblea Legislativa del Distrito Federal, a los diez días del mes de junio del año dos mil catorce.- POR LA MESA DIRECTIVA.- DIP. SANTIAGO TABOADA CORTINA, PRESIDENTE.- DIP. JORGE AGUSTÍN\nZEPEDA CRUZ, SECRETARIO.- DIP. ALBERTO EMILIANO CINTA MARTÍNEZ, SECRETARIO.- FIRMAS.\n\nEn cumplimiento de lo dispuesto por los artículos 122, apartado C, Base Segunda, fracción II, inciso b), de la Constitución Política de los Estados Unidos Mexicanos; 48, 49 y 67, fracción II, del Estatuto de Gobierno del Distrito Federal, para su debida publicación y observancia, expido el presente Decreto Promulgatorio en la Residencia Oficial del Jefe de Gobierno del Distrito Federal, en la Ciudad de México, a los diez días del mes de agosto del año dos mil quince.- EL JEFE DE GOBIERNO DEL DISTRITO FEDERAL, MIGUEL ÁNGEL\nMANCERA ESPINOSA.- FIRMA.- SECRETARÍA DE GOBIERNO.- FIRMA.- SECRETARÍA DEL MEDIO AMBIENTE.-\nFIRMA.-SECRETARÍA DE CIENCIA, TECNOLOGÍA E INNOVACIÓN.- FIRMA.\nTRANSITORIOS DEL DECRETO POR EL QUE SE REFORMAN Y ADICIONAN DIVERSAS DISPOSICIONES DE LA\nLEY AMBIENTAL Y DE PROTECCIÓN A LA TIERRA EN EL DISTRITO FEDERAL, PUBLICADOS EN LA GACETA\nOFICIAL DEL DISTRITO FEDERAL EL 17 DE NOVIEMBRE DE 2015.\nPRIMERO.- El presente Decreto entrará en vigor al día siguiente de su publicación en la Gaceta Oficial del\nDistrito Federal.\nSEGUNDO.- El Jefe de Gobierno del Distrito Federal deberá hacer las adecuaciones necesarias a la normatividad reglamentaria aplicable dentro de los 180 días naturales siguientes a la entrada en vigor del presente Decreto.\nRecinto de la Asamblea Legislativa del Distrito Federal, a los catorce días del mes de abril del año dos mil quince.- POR LA MESA DIRECTIVA.- DIP. MANUEL ALEJANDRO ROBLES GÓMEZ, PRESIDENTE.- DIP.\nORLANDO ANAYA GONZÁLEZ, SECRETARIO.- DIP. ALEJANDRO RAFAEL PIÑA MEDINA, SECRETARIO.- (Firmas)\nEn cumplimiento de lo dispuesto por los artículos 122, apartado C, Base Segunda, fracción II, inciso b), de la Constitución Política de los Estados Unidos Mexicanos; 48, 49 y 67, fracción II, del Estatuto de Gobierno del Distrito Federal, para su debida publicación y observancia, expido el presente Decreto Promulgatorio en la Residencia Oficial del Jefe de Gobierno del Distrito Federal, en la Ciudad de México, a los veintiocho días del mes de agosto del año dos mil quince.- EL JEFE DE GOBIERNO DEL DISTRITO FEDERAL, MIGUEL\nÁNGEL MANCERA ESPINOSA.- FIRMA.- LA SECRETARIA DE GOBIERNO, DORA PATRICIA MERCADO CASTRO.-\nFIRMA.- EL SECRETARIO DE DESARROLLO URBANO Y VIVIENDA, FELIPE DE JESÚS GUTIÉRREZ GUTIÉRREZ.-\nFIRMA.- LA SECRETARIA DEL MEDIO AMBIENTE, TANYA MÜLLER GARCÍA.- FIRMA.- EL SECRETARIO DE\nSEGURIDAD PÚBLICA, HIRAM ALMEIDA ESTRADA.- FIRMA.- LA SECRETARIA DE DESARROLLO RURAL Y\nEQUIDAD PARA LAS COMUNIDADES, ROSA ÍCELA RODRÍGUEZ VELÁZQUEZ.- FIRMA.\n\nTRANSITORIOS DEL DECRETO POR EL QUE SE REFORMAN Y ADICIONAN DIVERSAS DISPOSICIONES A LA LEY\nAMBIENTAL DE PROTECCIÓN A LA TIERRA DEL DISTRITO FEDERAL Y A LA LEY DE RESIDUOS SÓLIDOS DEL\nDISTRITO FEDERAL, PUBLICADOS EN LA GACETA OFICIAL DEL DISTRITO FEDERAL EL 18 DE NOVIEMBRE DE\n2015.\nPRIMERO.- Túrnese el presente Decreto, al Jefe de Gobierno del Distrito Federal para su publicación en la\nGaceta Oficial del Distrito Federal.\nSEGUNDO.- El presente Decreto entrará en vigor el 30 de enero del 2015. La entrada en vigor quedará sujeta a la suficiencia presupuestal que para tal efecto describe el presente Decreto, y que apruebe la\nAsamblea Legislativa del Distrito Federal, en el siguiente Presupuesto de Egresos del Distrito Federal para el Ejercicio Fiscal 2015.\nTERCERO.- El Jefe de Gobierno del Distrito Federal contará con sesenta días posteriores a la entrada en vigor de dicho Decreto, para expedir las modificaciones reglamentarias y administrativas necesarias aplicables.\nCUARTO.- Las Secretarías del Medio Ambiente y de Desarrollo Económico del Gobierno del Distrito Federal así como las Delegaciones, deberán diseñar e implementar una campaña permanente para dar a conocer a la ciudadanía en general, la forma de operación y participación en los sistemas de intercambio de residuos sólidos por productos en especie tratados en el presente Decreto; previéndose las partidas presupuestales pertinentes para llevar a cabo las mencionadas acciones en medios electrónicos e impresos.\nQUINTO.- La Secretaría de Medio Ambiente del Gobierno del Distrito Federal, deberá solicitar la suficiencia presupuestal suficiente con el fin de iniciar y hacer cumplir las modificaciones que indica el presente\nDecreto.\nRecinto de la Asamblea Legislativa del Distrito Federal, a los diez días del mes de junio del año dos mil catorce.- POR LA MESA DIRECTIVA.- DIP. SANTIAGO TABOADA CORTINA, PRESIDENTE.- DIP. JORGE AGUSTÍN\nZEPEDA CRUZ, SECRETARIO.- DIP. ALBERTO EMILIANO CINTA MARTÍNEZ, SECRETARIO.- (Firmas)\nEn cumplimiento de lo dispuesto por los artículos 122, apartado C, Base Segunda, fracción II, inciso b), de la Constitución Política de los Estados Unidos Mexicanos; 48, 49 y 67, fracción II, del Estatuto de Gobierno del Distrito Federal, para su debida publicación y observancia, expido el presente Decreto Promulgatorio en la Residencia Oficial del Jefe de Gobierno del Distrito Federal, en la Ciudad de México, a los veinticuatro días del mes de agosto del año dos mil quince.- EL JEFE DE GOBIERNO DEL DISTRITO FEDERAL, MIGUEL\n\nÁNGEL MANCERA ESPINOSA.- FIRMA.- LA SECRETARIA DE GOBIERNO, DORA PATRICIA MERCADO CASTRO.-\nFIRMA.- LA SECRETARIA DEL MEDIO AMBIENTE, TANYA MÜLLER GARCÍA.- FIRMA.- EL SECRETARIO DE\nDESARROLLO ECONÓMICO, SALOMÓN CHERTORIVSKI WOLDENBERG.- FIRMA.- EL SECRETARIO DE\nFINANZAS, ÉDGAR ABRAHAM AMADOR ZAMORA.- FIRMA.- EL SECRETARIO DE OBRAS Y SERVICIOS, EDGAR\nOSWALDO TUNGÜÍ RODRÍGUEZ.- FIRMA.\nTRANSITORIOS DEL DECRETO POR EL QUE SE ADICIONAN Y REFORMAN DIVERSAS DISPOSICIONES DE LA\nLEY AMBIENTAL DE PROTECCIÓN A LA TIERRA EN EL DISTRITO FEDERAL; DE LA LEY DE MITIGACIÓN Y\nADAPTACIÓN AL CAMBIO CLIMÁTICO Y DESARROLLO SUSTENTABLE PARA EL DISTRITO FEDERAL; DE LA LEY\nDE FOMENTO DE PROCESOS PRODUCTIVOS EFICIENTES PARA EL DISTRITO FEDERAL; DE LA LEY DE\nADQUISICIONES PARA EL DISTRITO FEDERAL Y DE LA LEY DE GOBIERNO ELECTRÓNICO DEL DISTRITO\nFEDERAL, PUBLICADOS EN LA GACETA OFICIAL DE LA CIUDAD DE MÉXICO EL 15 DE SEPTIEMBRE DE 2016.\nPRIMERO. El presente Decreto entrará en vigor al día siguiente de su publicación en la Gaceta Oficial del\nDistrito Federal.\nSEGUNDO. El Jefe de Gobierno del Distrito Federal contará con 180 días después de la publicación de este\nDecreto en la Gaceta Oficial del Distrito Federal para efecto de adecuar las disposiciones reglamentarias correspondientes.\nRecinto de la Asamblea Legislativa del Distrito Federal, a los cinco días del mes de mayo del año dos mil dieciséis.- POR LA MESA DIRECTIVA.- DIP. JOSÉ MANUEL DELGADILLO MORENO, PRESIDENTE.- DIP. EVA\nELOISA LESCAS HERNÁNDEZ, SECRETARIA.- DIP. CARLOS ALFONSO CANDELARIA LÓPEZ, SECRETARIO.-\n(Firmas)\nCon fundamento en lo dispuesto por los artículos 122, Apartado A, Base III, de la Constitución Política de los Estados Unidos Mexicanos; Transitorios Primero y Segundo del Decreto por el que se declaran reformadas y derogadas diversas disposiciones de la Constitución Política de los Estados Unidos Mexicanos, en materia de la Reforma Política de la Ciudad de México; 48, 49 y 67, fracción II, del Estatuto de Gobierno del Distrito Federal, para su debida publicación y observancia, expido el presente Decreto Promulgatorio en la Residencia Oficial del Jefe de Gobierno de la Ciudad de México, a los catorce días del mes de septiembre del año dos mil dieciséis.- EL JEFE DE GOBIERNO DE LA CIUDAD DE MÉXICO, MIGUEL ÁNGEL\nMANCERA ESPINOSA.- FIRMA.- LA SECRETARIA DE GOBIERNO, DORA PATRICIA MERCADO CASTRO.- FIRMA.-\n\nEL SECRETARIO DE DESARROLLO URBANO Y VIVIENDA, FELIPE DE JESÚS GUTIÉRREZ GUTIÉRREZ.- FIRMA.-\nEL SECRETARIO DE DESARROLLO ECONÓMICO, SALOMÓN CHERTORIVSKI WOLDENBERG.- FIRMA.- LA\nSECRETARIA DEL MEDIO AMBIENTE, TANYA MÜLLER GARCÍA.- FIRMA.- EL SECRETARIO DE OBRAS Y\nSERVICIOS, EDGAR OSWALDO TUNGÜI RODRÍGUEZ.- FIRMA.- EL SECRETARIO DE DESARROLLO SOCIAL,\nJOSÉ RAMÓN AMIEVA GÁLVEZ.- FIRMA.- EL SECRETARIO DE MOVILIDAD, HÉCTOR SERRANO CORTES.-\nFIRMA.- EL SECRETARIO DE TURISMO, MIGUEL TORRUCO MÁRQUES.- FIRMA.- EL SECRETARIO DE CULTURA,\nEDUARDO VÁZQUEZ MARTÍN.- FIRMA.- EL SECRETARIO DE SEGURIDAD PÚBLICA, HIRAM ALMEIDA\nESTRADA.- FIRMA.- EL SECRETARIO DE PROTECCIÓN CIVIL, FAUSTO LUGO GARCÍA.- FIRMA.- LA SECRETARIA\nDE TRABAJO Y FOMENTO AL EMPLEO, AMALIA DOLORES GARCÍA MEDINA.- FIRMA.- EL SECRETARIO DE\nEDUCACIÓN, MAURICIO RODRÍGUEZ ALONSO.- FIRMA.- LA SECRETARIA DE DESARROLLO RURAL Y EQUIDAD\nPARA LAS COMUNIDADES, ROSA ÍCELA RODRÍGUEZ VELÁZQUEZ.- FIRMA.- EL SECRETARIO DE FINANZAS,\nÉDGAR ABRAHAM AMADOR ZAMORA.- FIRMA.- EL SECRETARIO DE SALUD, JOSÉ ARMANDO AHUED\nORTEGA.- FIRMA.- EL SECRETARIO DE CIENCIA, TECNOLOGÍA E INNOVACIÓN, RENÉ RAÚL DRUCKER COLÍN.-\nFIRMA.\nTRANSITORIOS DEL DECRETO POR EL QUE SE REFORMAN DIVERSAS DISPOSICIONES DE LA LEY AMBIENTAL\nDE PROTECCIÓN A LA TIERRA EN EL DISTRITO FEDERAL, PUBLICADOS EN LA GACETA OFICIAL DE LA CIUDAD\nDE MÉXICO EL 04 DE NOVIEMBRE DE 2016.\nPRIMERO.- Publíquese el presente Decreto en la Gaceta Oficial del Distrito Federal y para su mayor difusión en el Diario Oficial de la Federación.\nSEGUNDO.- El presente Decreto entrará en vigor a partir del día siguiente al de su publicación en la Gaceta\nOficial para el Distrito Federal.\nTERCERO.- El Jefe de Gobierno del Distrito Federal realizará dentro de los 180 días posteriores a la publicación de este decreto, las modificaciones en la reglamentación correspondiente.\nRecinto de la Asamblea Legislativa del Distrito Federal, a los catorce días del mes de septiembre del año dos mil dieciséis.- POR LA MESA DIRECTIVA, DIP. JOSÉ MANUEL DELGADILLO MORENO, PRESIDENTE.- DIP.\nCARLOS ALFONSO CANDELARIA LÓPEZ.- SECRETARIO.- DIP. MAURICIO ALONSO TOLEDO GUTIÉRREZ,\nSECRETARIO.- (Firmas)\n\nCon fundamento en lo dispuesto por los artículos 122, Apartado A, Base III, de la Constitución Política de los Estados Unidos Mexicanos; Transitorios Primero y Segundo del Decreto por el que se declaran reformadas y derogadas diversas disposiciones de la Constitución Política de los Estados Unidos Mexicanos, en materia de la Reforma Política de la Ciudad de México; 48, 49 y 67, fracción II, del Estatuto de Gobierno del Distrito Federal, para su debida publicación y observancia, expido el presente Decreto Promulgatorio en la Residencia Oficial del Jefe de Gobierno de la Ciudad de México, a los tres días del mes de noviembre del año dos mil dieciséis.- EL JEFE DE GOBIERNO DE LA CIUDAD DE MÉXICO, MIGUEL ÁNGEL MANCERA\nESPINOSA.- FIRMA.- LA SECRETARIA DE GOBIERNO, DORA PATRICIA MERCADO CASTRO.- FIRMA.- LA\nSECRETARIA DEL MEDIO AMBIENTE, TANYA MÜLLER GARCÍA.- FIRMA.\nTRANSITORIOS DEL DECRETO POR EL QUE SE CAMBIA EL NOMBRE DE LEY ORGÁNICA DE LA PROCURADURÍA\nAMBIENTAL Y DEL ORDENAMIENTO TERRITORIAL DEL DISTRITO FEDERAL, POR EL DE LEY ORGÁNICA DE LA\nPROCURADURÍA AMBIENTAL Y DEL ORDENAMIENTO TERRITORIAL DE LA CIUDAD DE MÉXICO; SE\nREFORMAN, ADICIONAN Y DEROGAN DIVERSAS DISPOSICIONES DE LA LEY ORGÁNICA DE LA\nPROCURADURÍA AMBIENTAL Y DEL ORDENAMIENTO TERRITORIAL DE LA CIUDAD DE MÉXICO Y DE LA LEY\nAMBIENTAL DE PROTECCIÓN A LA TIERRA EN EL DISTRITO FEDERAL, PUBLICADOS EN LA GACETA OFICIAL DE\nLA CIUDAD DE MÉXICO EL 20 DE JULIO DE 2017.\nPRIMERO. El presente Decreto entrará en vigor a los treinta días hábiles siguientes a su publicación en la\nGaceta Oficial de la Ciudad de México.\nRecinto de la Asamblea Legislativa del Distrito Federal, a los diecisiete días del mes de noviembre del año dos mil dieciséis.- POR LA MESA DIRECTIVA.- DIP. LUIS ALBERTO MENDOZA ACEVEDO, PRESIDENTE.- DIP.\nEVA ELOISA LESCAS HERNÁNDEZ, SECRETARIA.- DIP. LOURDES VALDEZ CUEVAS, SECRETARIA.- (Firmas)\nCon fundamento en lo dispuesto por los artículos 122, Apartado A, Base III, de la Constitución Política de los Estados Unidos Mexicanos; Transitorios Primero y Segundo del Decreto por el que se declaran reformadas y derogadas diversas disposiciones de la Constitución Política de los Estados Unidos Mexicanos, en materia de la Reforma Política de la Ciudad de México; 48, 49 y 67, fracción II, del Estatuto de Gobierno del Distrito Federal, para su debida publicación y observancia, expido el presente Decreto Promulgatorio en la Residencia Oficial del Jefe de Gobierno de la Ciudad de México, a los dieciocho días del mes de julio del año dos mil diecisiete.- EL JEFE DE GOBIERNO DE LA CIUDAD DE MÉXICO, MIGUEL ÁNGEL MANCERA\nESPINOSA.- FIRMA.- LA SECRETARIA DE GOBIERNO, DORA PATRICIA MERCADO CASTRO.- FIRMA.- EL\nSECRETARIO DE DESARROLLO URBANO Y VIVIENDA, FELIPE DE JESÚS GUTIÉRREZ GUTIÉRREZ.- FIRMA.- LA\n\nSECRETARIA DEL MEDIO AMBIENTE.- TANYA MÜLLER GARCÍA.- FIRMA.- EL SECRETARIO DE SEGURIDAD\nPÚBLICA, HIRAM ALMEIDA ESTRADA.- FIRMA.\nTRANSITORIOS DEL DECRETO POR EL QUE SE REFORMAN Y ADICIONAN DIVERSAS DISPOSICIONES DE LA\nLEY AMBIENTAL DE PROTECCIÓN A LA TIERRA EN EL DISTRITO FEDERAL, PUBLICADOS EN LA GACETA OFICIAL\nDE LA CIUDAD DE MÉXICO EL 08 DE SEPTIEMBRE DE 2017.\nPRIMERO.- El presente Decreto entrará en vigor al día siguiente de su publicación en la Gaceta Oficial de la\nCiudad de México.\nSEGUNDO.- El Jefe de Gobierno de la Ciudad de México deberá hacer las adecuaciones necesarias a la normatividad reglamentaria aplicable dentro de los 180 días naturales siguientes a la entrada en vigor del presente\nDecreto. Recinto de la Asamblea Legislativa del Distrito Federal, a los seis días del mes de abril del año dos mil diecisiete.- POR LA MESA DIRECTIVA.- DIP. ERNESTO SÁNCHEZ RODRÍGUEZ, PRESIDENTE.- DIP. REBECA\nPERALTA LEÓN, SECRETARIA.- DIP. EVA ELOISA LESCAS HERNÁNDEZ, SECRETARIA.- (Firmas)\nCon fundamento en lo dispuesto por los artículos 122, Apartado A, Base III, de la Constitución Política de los Estados Unidos Mexicanos; Transitorios Primero y Segundo del Decreto por el que se declaran reformadas y derogadas diversas disposiciones de la Constitución Política de los Estados Unidos Mexicanos, en materia de la Reforma Política de la Ciudad de México; 48, 49 y 67, fracción II, del Estatuto de Gobierno del Distrito Federal, para su debida publicación y observancia, expido el presente Decreto Promulgatorio en la Residencia Oficial del Jefe de Gobierno de la Ciudad de México, a los seis días del mes de septiembre del año dos mil diecisiete.- EL JEFE DE GOBIERNO DE LA CIUDAD DE MÉXICO, MIGUEL ÁNGEL MANCERA\nESPINOSA.- FIRMA.- LA SECRETARIA DE GOBIERNO, DORA PATRICIA MERCADO CASTRO.- FIRMA.- LA\nSECRETARIA DEL MEDIO AMBIENTE, TANYA MÜLLER GARCÍA.- FIRMA.\nTRANSITORIOS DEL DECRETO POR EL QUE SE ADICIONAN LOS ARTÍCULOS 214 BIS, 214 TER, 214 QUATER,\n214 QUINTIES Y 214 SEXIES A LA LEY AMBIENTAL DE PROTECCIÓN A LA TIERRA EN EL DISTRITO FEDERAL,\nPUBLICADOS EN LA GACETA OFICIAL DE LA CIUDAD DE MÉXICO, EL 25 DE JUNIO DE 2019.\nPrimero- El presente decreto entrará en vigor al día siguiente de su publicación en la Gaceta Oficial del\nGobierno de la Ciudad de México.\n\nSegundo. Dentro de los ciento ochenta días siguientes a la publicación del presente Decreto, el Gobierno de la Ciudad de México a través de la Secretaría de Medio Ambiente, realizará la actualización y armonización de Reglamento de la Ley Ambiental y de Protección a la Tierra en el Distrito Federal.\nTercero. -Se derogan todas aquellas disposiciones que contravengan el contenido del presente decreto.\nPalacio Legislativo del Congreso de la Ciudad de México, a los veinticinco días del mes de abril del año dos mil diecinueve. - POR LA MESA DIRECTIVA. - DIPUTADO JOSÉ DE JESÚS MARTÍN DEL CAMPO CASTAÑEDA,\nPRESIDENTE. - DIPUTADA ISABELA ROSALES HERRERA, SECRETARIA. - DIPUTADA ANA PATRICIA BAEZ\nGUERRERO, SECRETARIA. - (Firmas)\nCon fundamento en lo dispuesto por los artículos 122, Apartado A, fracción III, de la Constitución Política de los Estados Unidos Mexicanos; 32 apartado C, numeral 1, inciso a) de la Constitución Política de la\nCiudad de México; 2, 3, fracciones XVII y XVIII, 7, 10 fracción II, 12 y 21 párrafo primero de la Ley Orgánica del Poder Ejecutivo y de la Administración Pública de la Ciudad de México; para su debida publicación y observancia, expido el presente Decreto Promulgatorio en la Residencia Oficial de la Jefatura de Gobierno de la Ciudad de México, a los diecisiete días del mes de mayo del año dos mil diecinueve.- LA JEFA DE\nGOBIERNO DE LA CIUDAD DE MÉXICO, DRA. CLAUDIA SHEINBAUM PARDO.- FIRMA.- LA SECRETARIA DEL\nMEDIO AMBIENTE, MARINA ROBLES GARCÍA.- FIRMA.\nTRANSITORIO DEL DECRETO POR EL QUE SE REFORMAN Y ADICIONAN DIVERSAS DISPOSICIONES DE LA LEY\nAMBIENTAL DE PROTECCIÓN A LA TIERRA EN EL DISTRITO FEDERAL, PUBLICADO EN LA GACETA OFICIAL DE\nLA CIUDAD DE MÉXICO EL 23 DE ABRIL DE 2021.\nPRIMERO. Remítase a la Jefatura de Gobierno para su promulgación y publicación en la Gaceta Oficial de la Ciudad de México.\nSEGUNDO. El presente Decreto entrará en vigor al día natural siguiente de su publicación en la Gaceta\nOficial de la Ciudad de México.\nTERCERO. Dentro de los 180 días naturales siguientes a la entrada en vigor del presente decreto, el\nGobierno de la Ciudad de México expedirá las disposiciones necesarias para armonizar los instrumentos administrativos de su competencia al contenido del presente decreto, en función de la suficiencia presupuestal.\n\nCUARTO: La Jefatura de Gobierno de la Ciudad de México deberá elaborar las disposiciones reglamentarias a las que se refiere el Título Quinto de la presente Ley de la Prevención, Control y Acciones Contra la\nContaminación Ambiental, dentro de los noventa días siguientes a la publicación del presente Decreto.\nPalacio Legislativo del Congreso de la Ciudad de México, a los veintitrés días del mes de marzo del año dos mil veintiuno. POR LA MESA DIRECTIVA, DIPUTADA MARGARITA SALDAÑA HERNÁNDEZ, PRESIDENTA.-\nDIPUTADA DONAJI OFELIA OLIVERA REYES, SECRETARIA.- DIPUTADO PABLO MONTES DE OCA DEL OLMO,\nSECRETARIO (Firmas)\nCon fundamento en lo dispuesto por los artículos 122, apartado A, fracción III de la Constitución Política de los Estados Unidos Mexicanos; 32, apartado C, numeral 1, inciso a) de la Constitución Política de la Ciudad de México; 2 párrafo segundo, 3 fracciones XVII y XVIII, 7 párrafo primero, 10 fracción II, 12 y 21 párrafo primero de la Ley Orgánica del Poder Ejecutivo y de la Administración Pública de la Ciudad de México; para su debida publicación y observancia, expido el presente Decreto Promulgatorio en la Residencia Oficial de la Jefatura de Gobierno de la Ciudad de México, a los veintidós días del mes de abril del año dos mil veintiuno.- LA JEFA DE GOBIERNO DE LA CIUDAD DE MÉXICO, DRA. CLAUDIA SHEINBAUM PARDO.- FIRMA.-\nEL SECRETARIO DE GOBIERNO, JOSÉ ALFONSO SUÁREZ DEL REAL Y AGUILERA.- FIRMA.- LA SECRETARIA DEL\nMEDIO AMBIENTE, MARINA ROBLES GARCÍA.- FIRMA.- EL SECRETARIO DE SEGURIDAD CIUDADANA, OMAR\nHAMID GARCÍA HARFUCH.- FIRMA.\nTRANSITORIOS DEL DECRETO POR EL QUE SE REFORMAN Y ADICIONAN DIVERSAS DISPOSICIONES DE LA\nLEY AMBIENTAL DE PROTECCIÓN A LA TIERRA EN EL DISTRITO FEDERAL, PUBLICADO EN LA GACETA\nOFICIAL DE LA CIUDAD DE MÉXICO, EL 27 DE OCTUBRE DE 2022.\nPRIMERO. Remítase a la persona titular de la Jefatura de Gobierno para su promulgación y publicación en la Gaceta Oficial de la Ciudad de México.\nSEGUNDO. El presente Decreto entrará en vigor al siguiente día de su publicación en la Gaceta Oficial de la Ciudad de México.\nPalacio Legislativo del Congreso de la Ciudad de México, los cuatro días del mes de octubre del año dos mil veintidós.- POR LA MESA DIRECTIVA.- DIPUTADO FAUSTO MANUEL ZAMORANO ESPARZA,\nPRESIDENTE.- DIPUTADA MARCELA FUENTE CASTILLO, SECRETARIA.- DIPUTADA MARIA GABRIELA SALIDO\nMAGOS, SECRETARIA.- (Firmas)\n\nCon fundamento en lo dispuesto por los artículos 122, apartado A, fracción III de la Constitución Política de los Estados Unidos Mexicanos; 32, apartado C, numeral 1, inciso a) de la Constitución Política de la\nCiudad de México; 2 párrafo segundo, 3 fracciones XVII y XVIII, 7 párrafo primero, 10 fracción II, 12 y 21 párrafo primero de la Ley Orgánica del Poder Ejecutivo y de la Administración Pública de la Ciudad de\nMéxico; para su debida publicación y observancia, expido el presente Decreto Promulgatorio en la\nResidencia Oficial de la Jefatura de Gobierno de la Ciudad de México, a los veintiséis días del mes de octubre del año dos mil veintidós.-LA JEFA DE GOBIERNO DE LA CIUDAD DE MÉXICO, DRA. CLAUDIA\nSHEINBAUM PARDO.- FIRMA.- EL SECRETARIO DE GOBIERNO, MARTÍ BATRES GUADARRAMA.- FIRMA.- LA\nSECRETARIA DEL MEDIO AMBIENTE, MARINA ROBLES GARCÍA.- FIRMA.\nTRANSITORIOS DEL DECRETO POR EL QUE SE ADICIONA UN PÁRRAFO AL ARTÍCULO 5 Y UN ARTÍCULO 61 BIS\n6; SE MODIFICA LA FRACCIÓN VI DEL ARTÍCULO 19; LA DENOMINACIÓN DEL CAPÍTULO VI BIS, EL ARTÍCULO\n61 BIS, EL ARTÍCULO 61 BIS 1, EL ARTÍCULO 61 BIS 2, EL ARTÍCULO 61 BIS 3, EL ARTÍCULO 61 BIS 4 Y EL\nARTÍCULO 61 BIS 5, ARTÍCULO 135, ARTÍCULO 157, ARTÍCULO 160, ARTÍCULO 135, ARTÍCULO 172, ARTÍCULO\n176, FRACCIÓN IV DEL ARTICULO 186 NONIES Y FRACCIÓN II DEL ARTÍCULO 214 QUATER Y; SE DEROGA EL\nÚLTIMO PÁRRAFO DEL ARTÍCULO 61 BIS 3; TODOS DE LA LEY DE AMBIENTAL DE PROTECCIÓN A LA TIERRA\nEN EL DISTRITO FEDERAL, PUBLICADO EN LA GACETA OFICIAL DE LA CIUDAD DE MÉXICO, EL 27 DE FEBRERO\nDE 2022.\nPRIMERO. Remítase a la persona titular de la Jefatura de Gobierno para su promulgación y publicación en la Gaceta Oficial de la Ciudad de México.\nSEGUNDO. El presente Decreto entrará en vigor al día siguiente de su publicación en la Gaceta Oficial de la\nCiudad de México.\nTERCERO. La Agencia Digital de Innovación Pública de la Ciudad de México tendrá un plazo de 180 días hábiles a partir de la entrada en vigor del presente Decreto para desarrollar la Plataforma Digital mediante la cual se realizará el registro de la Manifestación Ambiental Única para la Ciudad de México. Mientras tanto, se continuará con el registro de Manifestación en la misma forma en la que hasta ahora se ha presentado la Licencia Ambiental Única.\nCUARTO. Dentro de los 90 días naturales siguientes a la entrada en vigor del presente Decreto, la Secretaría deberá expedir el Reglamento de la Ley Ambiental de Protección a la Tierra en el Distrito Federal en materia\n\nde Manifestación Ambiental Única, en tanto, se aplicará lo establecido en la Ley de Procedimiento\nAdministrativo de la Ciudad de México.\nQUINTO. A partir de la publicación del presente Decreto, la Secretaría contará con un periodo de 180 días naturales a efecto de ajustar sus procedimientos para transitar de la Licencia Ambiental Única hacia la\nManifestación Ambiental Única.\nSEXTO. Las referencias hechas a la Licencia Ambiental Única en esta Ley, así como, de manera enunciativa más no limitativa en otras leyes, reglamentos, decretos, acuerdos y demás disposiciones normativas, se entenderán como Manifestación Ambiental Única.\nSÉPTIMO. Se derogan todas aquellas disposiciones que contravengan el presente Decreto.\nPalacio Legislativo del Congreso de la Ciudad de México, a los catorce días del mes de febrero del año dos mil veintitrés.- POR LA MESA DIRECTIVA.- DIPUTADO FAUSTO MANUEL ZAMORANO ESPARZA.- PRESIDENTE.-\nDIPUTADA MARCELA FUENTE CASTILLO, SECRETARIA.- DIPUTADA MARIA GABRIELA SALIDO MAGOS,\nSECRETARIA.- (Firmas)\nCon fundamento en lo dispuesto por los artículos 122, apartado A, fracción III de la Constitución Política de los Estados Unidos Mexicanos; 32, apartado C, numeral 1, inciso a) de la Constitución Política de la Ciudad de México; 2 párrafo segundo, 3 fracciones XVII y XVIII, 7 párrafo primero, 10 fracción II, 12 y 21 párrafo primero de la Ley Orgánica del Poder Ejecutivo y de la Administración Pública de la Ciudad de México; para su debida publicación y observancia, expido el presente Decreto Promulgatorio en la Residencia Oficial de la Jefatura de Gobierno de la Ciudad de México, a los veinticuatro días del mes de febrero del año dos mil veintitrés.-LA JEFA DE GOBIERNO DE LA CIUDAD DE MÉXICO, DRA. CLAUDIA SHEINBAUM PARDO.- FIRMA.-\nLA SECRETARIA DEL MEDIO AMBIENTE, MARINA ROBLES GARCÍA.- FIRMA.\nTRANSITORIOS DEL DECRETO POR EL QUE SE MODIFICA LA DENOMINACIÓN DE LA LEY AMBIENTAL DE\nPROTECCIÓN A LA TIERRA EN EL DISTRITO FEDERAL Y CON ELLO SE MODIFICA EL SEPTUAGÉSIMO PÁRRAFO\nDEL ARTÍCULO 5; LOS ARTÍCULOS 6, 11 PRIMER PÁRRAFO Y 12 TODOS DE LA LEY AMBIENTAL DE\nPROTECCIÓN A LA TIERRA EN EL DISTRITO FEDERAL, PUBLICADO EN LA GACETA OFICIAL DE LA CIUDAD DE\nMÉXICO EL 24 DE MARZO DE 2023.\nPRIMERO. Remítase a la persona titular de la Jefatura de Gobierno para su promulgación y publicación en la Gaceta Oficial de la Ciudad de México.\n\nSEGUNDO. El presente Decreto entrará en vigor al día siguiente de su publicación en la Gaceta Oficial de la\nCiudad de México.\nPalacio Legislativo del Congreso de la Ciudad de México, a los dos días del mes de marzo del año dos mil veintitrés.- POR LA MESA DIRECTIVA.- DIPUTADO FAUSTO MANUEL ZAMORANO ESPARZA.- PRESIDENTE.-\nDIPUTADA MARCELA FUENTE CASTILLO, SECRETARIA.- DIPUTADA MARIA GABRIELA SALIDO MAGOS,\nSECRETARIA.- (Firmas)\nCon fundamento en lo dispuesto por los artículos 122, apartado A, fracción III de la Constitución Política de los Estados Unidos Mexicanos; 32, apartado C, numeral 1, inciso a) de la Constitución Política de la Ciudad de México; 2 párrafo segundo, 3 fracciones XVII y XVIII, 7 párrafo primero, 10 fracción II, 12 y 21 párrafo primero de la Ley Orgánica del Poder Ejecutivo y de la Administración Pública de la Ciudad de México; para su debida publicación y observancia, expido el presente Decreto Promulgatorio en la Residencia Oficial de la Jefatura de Gobierno de la Ciudad de México, a los veintitrés días del mes de marzo del año dos mil veintitrés.-LA JEFA DE GOBIERNO DE LA CIUDAD DE MÉXICO, DRA. CLAUDIA SHEINBAUM PARDO.- FIRMA.-\nEL SECRETARIO DE GOBIERNO, MARTÍ BATRES GUADARRAMA.- FIRMA.- LA SECRETARIA DEL MEDIO\nAMBIENTE, MARINA ROBLES GARCÍA.- FIRMA.\nTRANSITORIOS DEL DECRETO POR EL QUE SE REFORMA Y ADICIONAN DIVERSAS DISPOSICIONES DE LA LEY\nAMBIENTAL DE PROTECCIÓN A LA TIERRA EN LA CIUDAD DE MÉXICO, PUBLICADO EN LA GACETA OFICIAL DE\nLA CIUDAD DE MÉXICO EL 04 DE MAYO DE 2023.\nPRIMERO. Remítase a la Jefatura de Gobierno para su promulgación y publicación en la Gaceta Oficial de la Ciudad de México.\nSEGUNDO. El presente decreto entrará en vigor al día siguiente de su publicación en la Gaceta Oficial de la\nCiudad de México.\nTERCERO. La Jefatura del Gobierno de la Ciudad tendrá hasta 120 días naturales para modificar las disposiciones Reglamentarias materia del presente decreto.\nCUARTO. Dentro de los 180 días posteriores a la publicación de este decreto, la Secretaría de Medio\nAmbiente de la Ciudad de México, deberá iniciar con la elaboración de la Norma Ambiental que establezca los límites máximos permisibles de luz artificial que ilumine en el medio ambiente y que regule las\n\nemisiones de la misma, así como el control de la contaminación lumínica, que establezca el procedimiento para su medición, y determine cuáles son los establecimientos regulados.\nPalacio Legislativo del Congreso de la Ciudad de México, a los veinticinco días del mes de abril del año dos mil veintitrés. POR LA MESA DIRECTIVA.- DIPUTADO FAUSTO MANUEL ZAMORANO ESPARZA, PRESIDENTE.-\nDIPUTADA MARCELA FUENTE CASTILLO, SECRETARIA.- DIPUTADA MARIA GABRIELA SALIDO MAGOS,\nSECRETARIA.- (Firmas)\nCon fundamento en lo dispuesto por los artículos 122, apartado A, fracción III de la Constitución Política de los Estados Unidos Mexicanos; 32, apartado C, numeral 1, inciso a) de la Constitución Política de la Ciudad de México; 2 párrafo segundo, 3 fracciones XVII y XVIII, 7 párrafo primero, 10 fracción II, 12 y 21 párrafo primero de la Ley Orgánica del Poder Ejecutivo y de la Administración Pública de la Ciudad de México; para su debida publicación y observancia, expido el presente Decreto Promulgatorio en la Residencia Oficial de la Jefatura de Gobierno de la Ciudad de México, a los tres días del mes de mayo del año dos mil veintitrés.-\nLA JEFA DE GOBIERNO DE LA CIUDAD DE MÉXICO, DRA. CLAUDIA SHEINBAUM PARDO.- FIRMA.- EL\nSECRETARIO DE GOBIERNO, MARTÍ BATRES GUADARRAMA.- FIRMA.- LA SECRETARIA DE ADMINISTRACIÓN Y\nFIANZAS, LUZ ELENA GONZÁLEZ ESCOBAR.- FIRMA.- SECRETARIO DE DESARROLLO URBANO Y VIVIENDA,\nCARLOS ALBERTO ULLOA PÉREZ.- FIRMA.- LA SECRETARIA DEL MEDIO AMBIENTE, MARINA ROBLES GARCÍA.-\nFIRMA.- EL SECRETARIO DE SEGURIDAD CIUDADANA, OMAR HAMID GARCÍA HARFUCH.- FIRMA.\nTRANSITORIOS DEL DECRETO POR EL QUE SE MODIFICA EL ARTÍCULO 118 DE LA LEY AMBIENTAL DE\nPROTECCIÓN A LA TIERRA EN LA CIUDAD DE MÉXICO, PUBLICADO EN LA GACETA OFICIAL DE LA CIUDAD DE\nMÉXICO EL 04 DE AGOSTO DE 2023.\nPRIMERO. Remítase a la Jefatura de Gobierno para su promulgación y publicación en la Gaceta Oficial de la Ciudad de México.\nSEGUNDO. El presente decreto entrará en vigor al día siguiente de su publicación en la Gaceta Oficial de la\nCiudad de México.\nTERCERO. La Jefatura del Gobierno de la Ciudad tendrá hasta 120 días naturales para modificar las disposiciones Reglamentarias materia del presente decreto.\nPalacio Legislativo del Congreso de la Ciudad de México, a los veintiún días del mes de julio del año dos mil veintitrés.- POR LA MESA DIRECTIVA.- DIPUTADO FAUSTO MANUEL ZAMORANO ESPARZA, PRESIDENTE.-\n\nDIPUTADA MARCELA FUENTE CASTILLO, SECRETARIA.- DIPUTADA MARIA GABRIELA SALIDO MAGOS,\nSECRETARIA.- (Firmas)\nCon fundamento en lo dispuesto por los artículos 122, apartado A, base III, de la Constitución Política de los Estados Unidos Mexicanos; 32, apartado C, numeral 1, inciso a), de la Constitución Política de la Ciudad de México; 2, párrafo segundo, 3 fracciones XVII y XVIII, 7, párrafo primero, 10, fracción II, 12 y 21, párrafo primero, de la Ley Orgánica del Poder Ejecutivo y de la Administración Pública de la Ciudad de México;\npara su debida publicación y observancia, expido el presente Decreto Promulgatorio en la Residencia\nOficial de la Jefatura de Gobierno de la Ciudad de México, a los 3 días del mes de agosto del año dos mil veintitrés.- EL JEFE DE GOBIERNO DE LA CIUDAD DE MÉXICO, MTRO. MARTÍ BATRES GUADARRAMA.- FIRMA.-\nEL SECRETARIO DE GOBIERNO, RICARDO RUIZ SUÁREZ.- FIRMA.- LA SECRETARIA DEL MEDIO AMBIENTE,\nMARINA ROBLES GARCÍA.- FIRMA.\nTRANSITORIOS DEL DECRETO POR EL QUE SE MODIFICAN LAS FRACCIONES V, IX Y X DEL ARTÍCULO 23; ASÍ\nCOMO EL PÁRRAFO PRIMERO Y LA FRACCION VI DEL ARTÍCULO 27 BIS; SE ADICIONAN LAS FRACCIONES I\nBIS, VIII TER Y XI, DEL ARTÍCULO 23; Y LA ADICIÓN DE UN ARTÍCULO 88 BIS 6, TODAS ELLAS DE LA LEY\nAMBIENTAL DE PROTECCIÓN A LA TIERRA DEL DISTRITO FEDERAL, PUBLICADO EN LA GACETA OFICIAL DE LA\nCIUDAD DE MÉXICO EL 28 DE NOVIEMBRE DE 2023.\nPRIMERO. Remítase a la Jefatura de Gobierno para su promulgación y publicación en la Gaceta Oficial de la Ciudad de México.\nSEGUNDO. El presente decreto entrará en vigor al día siguiente de su publicación en la Gaceta Oficial de la\nCiudad de México.\nTERCERO. La Secretaría de Medio Ambiente y la Jefatura de Gobierno, ambas de la Ciudad de México, a través del Comité de Normalización Ambiental, tendrán hasta 180 días naturales para realizar las modificaciones pertinentes a las correspondientes Normas Ambientales de la Ciudad de México.\nCUARTO. El Congreso de la Ciudad de México deberá realizar las modificaciones a las Normas Generales de\nOrdenación correspondientes.\nQUINTO. La Jefatura del Gobierno de la Ciudad tendrá hasta 120 días naturales para modificar las disposiciones Reglamentarias materia del presente decreto.\n\nPalacio Legislativo del Congreso de la Ciudad de México, a los veintinueve días del mes de noviembre del año dos mil veintidós.- POR LA MESA DIRECTIVA.- DIPUTADO FAUSTO MANUEL ZAMORANO ESPARZA,\nPRESIDENTE.- DIPUTADA MARCELA FUENTE CASTILLO, SECRETARIA, DIPUTADA MARIA GABRIELA SALIDO\nMAGOS, SECRETARIA.- (Firmas)\nCon fundamento en lo dispuesto por los artículos 122, apartado A, base III, de la Constitución Política de los Estados Unidos Mexicanos; 32, apartado C, numeral 1, inciso a), de la Constitución Política de la Ciudad de México; 2, párrafo segundo, 3, fracciones XVII y XVIII, 7, párrafo primero, 10, fracción II, 12 y 21, párrafo primero, de la Ley Orgánica del Poder Ejecutivo y de la Administración Pública de la Ciudad de México;\npara su debida publicación y observancia, expido el presente Decreto Promulgatorio en la Residencia\nOficial de la Jefatura de Gobierno de la Ciudad de México, a los veintisiete días del mes de noviembre del año dos mil veintitrés.- EL JEFE DE GOBIERNO DE LA CIUDAD DE MÉXICO, MTRO. MARTÍ BATRES\nGUADARRAMA.- FIRMA.- EL SECRETARIO DE GOBIERNO, RICARDO RUIZ SUÁREZ.- FIRMA.- EL SECRETARIO DE\nDESARROLLO URBANO Y VIVIENDA, CARLOS ALBERTO ULLOA PÉREZ.- FIRMA.- LA SECRETARIA DEL MEDIO\nAMBIENTE, MARINA ROBLES GARCÍA.- FIRMA.",
  "ordenamiento": "Marco Jurídico",
  "jurisdiccion": "CIUDAD DE MEXICO",
  "fuente_oficial": "Congreso de la Ciudad de México",
  "status": "Vigente",
  "Fecha de Publicación": "05-12-2023",
  "Fecha de Última Reforma": "28 de noviembre de 2023",
  "numero_paginas": 180,
  "es_escaneado": false,
  "tiene_tablas": false,
  "url": "https://www.congresocdmx.gob.mx/archivo-7b5d6d072257bd2e9f67310ccd2ae280324fed10.pdf",
  "materia": [
    "ambiental"
  ]
}