{
  "titulo": "Ley ORGÁNICA DEL PODER JUDICIAL DE LA CIUDAD DE MÉXICO",
  "Contenido": "PUBLICADO EN LA GACETA OFICIAL DE LA CIUDAD DE MÉXICO\nEL 04 DE MAYO DE 2018\nTEXTO VIGENTE\nÚLTIMA REFORMA PUBLICADA EN LA G.O.C.D.M.X.\nEL 01 DE AGOSTO DE 2024\nDECRETO POR EL QUE SE EXPIDE LA LEY ORGÁNICA DEL PODER JUDICIAL DE LA CIUDAD DE MÉXICO\nJOSÉ RAMÓN AMIEVA GÁLVEZ, Jefe de Gobierno de la Ciudad de México, a sus habitantes sabed:\nQue la H. Asamblea Legislativa del Distrito Federal, VII Legislatura se ha servido dirigirme el siguiente\nD E C R E T O\n(Al margen superior izquierdo el Escudo Nacional que dice: ESTADOS UNIDOS MEXICANOS. - ASAMBLEA\nLEGISLATIVA DEL DISTRITO FEDERAL. - VII LEGISLATURA)\nASAMBLEA LEGISLATIVA DEL DISTRITO FEDERAL\nVII LEGISLATURA\nD E C R E T A\nDECRETO POR EL QUE SE EXPIDE LA LEY ORGÁNICA DEL PODER JUDICIAL DE LA CIUDAD DE MÉXICO.\nARTÍCULO ÚNICO. Se expide la Ley Orgánica del Poder Judicial de la Ciudad de México, para quedar como sigue:\n\nLEY ORGÁNICA DEL PODER JUDICIAL DE LA CIUDAD DE\nMÉXICO\nTÍTULO PRIMERO\nDE LA FUNCIÓN JURISDICCIONAL\nCAPÍTULO ÚNICO\nDISPOSICIONES GENERALES\nArtículo 1. La presente Ley es de orden público e interés general y tiene por objeto regular la organización y funcionamiento del Tribunal Superior de Justicia y del Consejo de la Judicatura ambos de la Ciudad de\nMéxico, así como a los órganos judiciales, con base en lo dispuesto la Constitución Política de los Estados\nUnidos Mexicanos, la Constitución Política de la Ciudad de México y demás ordenamientos que regulan el funcionamiento de los órganos que integran el Poder Judicial.\nEl Tribunal Superior de Justicia es un Órgano de Gobierno y una autoridad local de la Ciudad de México cuyo objeto es la administración e impartición de justicia del fuero común en la Ciudad de México.\nEl Consejo de la Judicatura es el órgano encargado de la administración, vigilancia, evaluación, disciplina y servicio de carrera. Asimismo le corresponde manejar, administrar y ejercer, de manera autónoma, su presupuesto y el del Tribunal Superior de Justicia de la Ciudad de México de conformidad con las disposiciones jurídicas aplicables en materia presupuestal.\nDe conformidad con lo señalado en la Constitución Política de la Ciudad de México, para la integración del\nPoder Judicial se deberá garantizar en todo momento, el principio de paridad de género.\nArtículo 2. La función judicial, se regirá por los principios de legalidad y honradez, accesibilidad, transparencia, máxima publicidad y rendición de cuentas. Por ende, las personas servidoras públicas adscritas al Poder Judicial, en su actuación pública, deberán atender a dichos principios, mismos que implican las siguientes conductas:\nI. Legalidad y honradez. Actuar dentro de las atribuciones que les confieran las normas jurídicas en lo particular, y el marco jurídico en lo general; así como conducirse con rectitud, sin utilizar su cargo para obtener algún beneficio personal ni buscar o aceptar algún tipo de compensación.\n\nII.Accesibilidad. Permitir y facilitar a las personas con alguna discapacidad el uso de los servicios públicos que ofrece el Poder Judicial, de manera progresiva.\nIII. Transparencia. Los órganos públicos que integran al Poder Judicial deben brindar publicidad a las deliberaciones y actos relacionados con sus atribuciones, así como dar acceso a la información que generen, de conformidad con las leyes en la materia.\nIV. Máxima publicidad. Toda la información en posesión de los órganos públicos que integran al\nPoder Judicial será pública, completa, oportuna y accesible, sujeta a un claro régimen de excepciones, que deberán estar definidas y ser además legítimas y estrictamente necesarias en una sociedad democrática.\nV. Rendición de cuentas. Los órganos públicos que integran al Poder Judicial deben reportar detalladamente sus actos y los resultados de los mismos a través de la creación de un sistema que, además permita a la ciudadanía vigilar su desempeño.\nArtículo 3. Las y los Magistrados, así como las y los Jueces gozarán de todas las garantías judiciales previstas en la Constitución Política de los Estados Unidos Mexicanos y en la Constitución Política de la Ciudad de\nMéxico, a fin de ejercer su función con plena autonomía, independencia e imparcialidad; asimismo, percibirán una remuneración adecuada e irrenunciable, la cual no podrá ser disminuida durante su encargo.\nArtículo 4. El Tribunal Superior de Justicia de la Ciudad de México funcionará en Pleno y en Salas, y tendrá las siguientes atribuciones:\nI. Ejercer el control de constitucionalidad, convencionalidad y legalidad en los términos que establece la Constitución Política de los Estados Unidos Mexicanos, y determinar la inaplicación de las leyes o decretos contrarios a la Constitución Política de la Ciudad de México, en las materias de sus respectivas competencias;\nII. Proteger y salvaguardar los derechos humanos y sus garantías reconocidos por la Constitución\nPolítica de la Ciudad de México y los tratados internacionales en materia de derechos humanos de los cuales el Estado mexicano sea parte;\nIII. La administración e impartición de justicia del fuero común en la Ciudad de México; y\n\nIV. Las demás que establezcan la Constitución Política de los Estados Unidos Mexicanos, la\nConstitución Política de la Ciudad de México, esta Ley y demás disposiciones jurídicas aplicables.\nArtículo 5. Para los efectos de esta Ley se entenderá por:\nI. Acción efectiva, a la acción de protección efectiva de derechos;\nII. Archivo Judicial, al Archivo Judicial del Tribunal Superior de Justicia del Poder Judicial de la\nCiudad de México;\nIII. Centro de Justicia Alternativa, al Centro de Justicia Alternativa del Tribunal Superior de\nJusticia del Poder Judicial de la Ciudad de México;\nIV. Comisión de Disciplina Judicial, a la Comisión de Disciplina Judicial del Consejo de la\nJudicatura del Poder Judicial de la Ciudad de México;\nV. Congreso, al Congreso de la Ciudad de México;\nVI. Consejo de la Judicatura, al Consejo de la Judicatura del Poder Judicial de la Ciudad de\nMéxico;\nVII. Constitución, a la Constitución Política de la Ciudad de México;\nVIII. Contraloría, a la Contraloría del Tribunal Superior de Justicia del Poder Judicial de la Ciudad de México;\nIX. Instituto de Estudios Judiciales, al Instituto de Estudios Judiciales del Consejo de la Judicatura del Poder Judicial de la Ciudad de México;\nX. Juzgados, a los órganos jurisdiccionales del Tribunal Superior de Justicia del Poder Judicial de la Ciudad de México;\nXI. Las y los Consejeros de la Judicatura, a las personas integrantes del Consejo de la Judicatura del Poder Judicial de la Ciudad de México;\n\nXII. Las y los Magistrados, a las Magistradas o Magistrados adscritos al Tribunal Superior de\nJusticia del Poder Judicial de la Ciudad de México;\nXIII. Juzgadores y/o las y los Jueces de la Ciudad de México, a las personas titulares de los\nJuzgados del Tribunal Superior de Justicia del Poder Judicial de la Ciudad de México;\nXIV. Ley, a la presente Ley Orgánica del Poder Judicial de la Ciudad de México;\nXV. Pleno, al Pleno del Tribunal Superior de Justicia del Poder Judicial de la Ciudad de México;\nXVI. Pleno del Consejo, al Pleno del Consejo de la Judicatura del Poder Judicial de la Ciudad de\nMéxico;\nXVII. Poder Judicial, al Poder Judicial de la Ciudad de México;\nXVIII. Sala o Salas, a las Salas del Tribunal Superior de Justicia del Poder Judicial de la Ciudad de\nMéxico en cualquiera de las siguientes materias: Civil, Penal, Familiar, Justicia para\nAdolescentes, Especializadas en Ejecución de Sentencias Penales y Laboral;\nXIX. Sala Constitucional, a la Sala Constitucional del Tribunal Superior de Justicia del Poder\nJudicial de la Ciudad de México, y\nXX. Tribunal Superior de Justicia, al Tribunal Superior de Justicia del Poder Judicial de la Ciudad de México.\nArtículo 6. El ejercicio jurisdiccional en todo tipo de asuntos relativos a las materias civil, mercantil, penal, de extinción de dominio, familiares, justicia para adolescentes, de tutela de Derechos Humanos, laboral y los del orden federal en los casos que expresamente las leyes les confieran competencia, corresponde a las personas servidoras públicas y órganos judiciales que se señalan a continuación:\nI. Las y los Magistrados del Tribunal Superior de Justicia; y\nII. Las y los Jueces de la Ciudad de México.\nLas demás personas servidoras públicas y auxiliares de la administración de justicia intervendrán en el ejercicio jurisdiccional, en los términos que establece la Constitución Política de los Estados Unidos\n\nMexicanos, esta Ley, los Códigos de Procedimientos Nacionales o los vigentes en la Ciudad de México y demás disposiciones jurídicas aplicables.\nArtículo 7. Las personas árbitras no ejercerán autoridad pública, pero de acuerdo con las reglas y restricciones que fijen los Códigos de Procedimientos Nacionales o los vigentes en la Ciudad de México, el\nCódigo de Comercio para toda la República y otras leyes que expresamente lo regulen, conocerán, según los términos de los compromisos respectivos, del negocio o negocios civiles y mercantiles que les encomienden las personas interesadas. Para que resulten ejecutables sus fallos, éstos deben ser homologados por las autoridades civiles y jurisdiccionales correspondientes, sólo en relación con los requisitos inherentes a su formalidad.\nArtículo 8. Son personas auxiliares de la administración de justicia y están obligados a cumplir órdenes que, en el ejercicio de sus atribuciones legales, emitan las y los Jueces y las y los Magistrados del Tribunal\nSuperior de Justicia:\nI. El Registro Civil;\nII. El Registro Público de la Propiedad y el Comercio;\nIII. Los peritos médicos legistas;\nIV. Las personas que ejerzan como mediadores, conciliadores y árbitros privados certificados y registrados por el Poder Judicial de la Ciudad de México en términos de la Ley de Justicia\nAlternativa del Poder Judicial de la Ciudad de México;\nV. Las personas que ejerzan como intérpretes oficiales y demás peritos en las ramas que les sean encomendadas;\nVI. Los síndicos e interventores de concursos y quiebras;\nVII. Las personas que ejerzan como albaceas, interventores, depositarios, tutores, curadores y notarios, en las funciones que les encomienden las leyes correspondientes;\nVIII. La Secretaría de Finanzas;\nIX. La Secretaría del Trabajo y Fomento al Empleo;\n\nX. La Secretaría de Salud;\nXI. La Secretaría de Educación;\nXII. La Secretaría de Desarrollo Social;\nXIII. Sistema para el Desarrollo Integral de la Familia;\nXIV. La Secretaría de Seguridad Pública y la Policía adscrita a la Fiscalía General de Justicia de la\nCiudad de México, y\nXV. Todas las demás a quienes las leyes les confieran ese carácter.\nLa persona Titular de la Jefatura de Gobierno de la Ciudad de México facilitará el ejercicio de las funciones a que se refiere este artículo.\nArtículo 9. Para los efectos de esta Ley, habrá un sólo partido judicial con la extensión y límites que para la\nCiudad de México señale la Ley Orgánica de la Administración Pública correspondiente.\nTÍTULO SEGUNDO\nDE LAS CONDICIONES Y PROHIBICIONES PARA EJERCER FUNCIONES\nJUDICIALES\nCAPÍTULO I\nDE LA DESIGNACIÓN\nArtículo 10. Los nombramientos de las y los Magistrados del Tribunal Superior de Justicia se realizarán en los términos previstos por la Constitución Política de los Estados Unidos Mexicanos, la Constitución y la Ley\nOrgánica del Congreso de la Ciudad de México.\nArtículo 11. A propuesta del Consejo de la Judicatura, las y los Magistrados adscritos al Tribunal Superior de Justicia serán designados y, en su caso, ratificados por las dos terceras partes de las y los Diputados del\nCongreso.\n\nLas y los Magistrados durarán seis años en su cargo y podrán ser ratificados, previa evaluación pública en los términos dispuestos en la Constitución y en esta Ley.\nLas personas aspirantes propuestas deberán cumplir con los requisitos establecidos en el artículo 35\nApartado E, numeral 11 de la Constitución.\nArtículo 12. El Congreso deberá designar o ratificar a la persona candidata a ocupar el cargo de Magistrada o Magistrado, o bien, rechazar, dentro del improrrogable plazo de quince días hábiles, contados a partir del día siguiente en que se reciba en el propio Congreso el oficio respectivo del Consejo de la Judicatura.\nPara computar dicho plazo, el oficio que contenga la o las propuestas de las personas candidatas a ocupar el cargo de Magistrada o Magistrado del Tribunal Superior de Justicia, se remitirá al Congreso con una copia, a fin de que en ésta se asiente el sello de recibido y la fecha correspondiente de la instancia que actúe como oficialía de partes de ese órgano legislativo.\nArtículo 13. En caso de que el Congreso rechace por escrito la totalidad de las personas aspirantes de la o las propuestas en el referido plazo, en un tiempo máximo de dos días hábiles contados a partir de que fue notificada la resolución del Congreso, el Consejo someterá una nueva propuesta, en los términos del artículo precedente.\nSi esta segunda propuesta fuere rechazada por escrito del Congreso o el Consejo de la Judicatura no fuese notificado por el Congreso de su resolución en el plazo de quince días hábiles mencionado, ocupará el cargo con carácter provisional la persona que determine el Consejo de la Judicatura, quien deberá haber acreditado los requisitos establecidos en el artículo 21 de esta Ley y demás disposiciones jurídicas aplicables.\nArtículo 14. En caso de que el Congreso no apruebe dos nombramientos sucesivos respecto de la misma vacante, el Consejo de la Judicatura hará un tercero que surtirá sus efectos provisionales y estará sometido a la aprobación del Congreso en un plazo de quince días hábiles improrrogables.\nArtículo 15. Aquellas personas que hayan resultado electas como Magistrados del Tribunal Superior de\nJusticia, deberán rendir la protesta de ley ante el Congreso.\nArtículo 16. Al término de su encargo las y los Magistrados, serán sometidas al procedimiento de ratificación. Para tal efecto, quien presida el Tribunal Superior de Justicia deberá hacer del conocimiento\n\ndel Consejo de la Judicatura, con una antelación de por lo menos cuarenta y cinco días, el nombre de las\nMagistradas y los Magistrados que estén por concluir el ejercicio de su encargo.\nEl Consejo de la Judicatura remitirá al Congreso, con una antelación de treinta días a la fecha de conclusión del encargo del funcionario judicial, sus propuestas, en los términos de la Constitución.\nEn los casos de propuesta de nombramiento, así como en el de ratificación del encargo, el Consejo de la\nJudicatura anexará un expediente en el que se integren un extracto curricular del desarrollo profesional del candidato, así como con la documentación que acredite el cumplimiento de los requisitos establecidos por esta Ley y demás ordenamientos aplicables.\nArtículo 17. El Consejo de la Judicatura designará a las y los Jueces por un período de seis años y podrán ser ratificados, previa evaluación pública, en los términos que para el efecto desarrollen, y tomando en consideración los elementos establecidos en la presente Ley.\nUna vez ratificados, las y los Jueces durarán en el cargo hasta los setenta y cinco años de edad y sólo podrán ser privados de sus puestos en los términos previstos en la Constitución, esta Ley y demás disposiciones jurídicas aplicables.\nPárrafo modificado y publicado en la GOCDMX el 01 de agosto de 2024\nArtículo 18. El Pleno y las Salas del Tribunal Superior de Justicia, así como las y los Jueces y demás órganos judiciales que con cualquier otra denominación se creen, nombrarán y removerán a sus funcionarios y empleados conforme a lo que establezca la Constitución y esta Ley en materia de carrera judicial.\nArtículo 19. Las y los Jueces rendirán protesta ante los respectivos Plenos del Tribunal Superior de Justicia\nCiudad de México y del Consejo de la Judicatura. Las demás personas servidoras públicas judiciales harán lo propio ante el titular del Órgano que los haya nombrado.\nArtículo 20. Toda persona que fuere nombrada para desempeñar algún cargo o empleo judicial, una vez rendida la protesta de ley, comenzará a ejercer las funciones que le correspondan, dentro de los quince días naturales siguientes a la fecha del nombramiento. Si no se presentare sin causa justificada, el nombramiento se tendrá por no hecho y se procederá a hacer una nueva designación.\nTratándose de personas servidoras públicas de la administración de justicia que deban trasladarse para tomar posesión de su puesto a lugares distintos, al plazo señalado deberá aumentarse al que fije la autoridad que hizo la designación.\n\nLas relaciones de trabajo entre el personal y el Tribunal Superior de Justicia se regirán por la Ley Federal de los Trabajadores al Servicio del Estado, reglamentaria del apartado B del artículo 123 de la Constitución\nPolítica de los Estados Unidos Mexicanos, así como por las carreras judicial y administrativa y las condiciones generales de trabajo.\nCAPÍTULO II\nDE LOS REQUISITOS\nArtículo 21. Para ser nombrado Magistrada o Magistrado se requiere:\nI. Tener la ciudadanía mexicana, en pleno goce de sus derechos políticos y civiles;\nII. Tener cuando menos treinta y cinco años de edad cumplidos al día de la designación;\nIII. Poseer al día de la designación, con antigüedad mínima de diez años, título profesional de licenciado en Derecho y cédula profesional expedidos por la autoridad o institución legalmente facultada para ello;\nIV. Gozar de buena reputación, para lo cual se tomará en cuenta no ser deudor alimentario moroso y contar con una trayectoria laboral respetable a través de un estudio minucioso de los antecedentes del postulante en el que se pueda evaluar su conducta ética;\nV. No haber sido condenado por sentencia firme, por delito doloso que amerite pena de prisión de más de un año, pero si se tratare de robo, fraude, falsificación, abuso de confianza u otro que lastime seriamente la buena fama en el concepto público, lo inhabilitará para el cargo, cualquiera que haya sido la pena;\nVI. Haber residido en el país durante los dos años anteriores al día de la designación;\nVII. No haber ocupado el cargo de titular de la Jefatura de Gobierno, la Secretaría General, la\nFiscalía General de Justicia o una Diputación al Congreso de la Ciudad de México, durante el año previo al día de la designación;\nVIII. Presentar su declaración de evolución patrimonial, conforme a la ley de la materia; y\n\nIX. Se Deroga.\nLos nombramientos de las y los Magistrados serán hechos preferentemente de entre aquellas personas que cuentan con el Servicio Civil de Carrera Judicial y que se hayan desempeñado como juez o jueza o que hayan prestado sus servicios con eficiencia y probidad en la impartición o procuración de justicia, o en su caso, que por su honorabilidad, competencia y antecedentes en otras ramas de la profesión jurídica se consideren aptos para impartirla. En igualdad de circunstancias, se preferirá a los originarios o vecinos de la Ciudad de México.\nArtículo 22. Para ser Juez o Jueza de la Ciudad de México, se requiere:\nI. Ser mexicana o mexicano por nacimiento, no haber adquirido otra nacionalidad y estar en pleno goce y ejercicio de sus derechos civiles y políticos;\nII. Tener cuando menos treinta años de edad cumplidos al día de la designación;\nIII. Contar con título de Licenciado en Derecho y Cédula Profesional expedida por la autoridad o\nInstitución legalmente facultada para ello;\nIV. Tener práctica profesional mínima de cinco años, contados a partir de la obtención del título profesional, relacionada con la materia del cargo para el que concursa;\nV. Haber residido en la Ciudad de México o en su área Metropolitana durante los dos años anteriores al día de la designación y presentar su declaración de evolución patrimonial, conforme a la ley de la materia;\nVI. Gozar de buena reputación, para lo cual se tomará en cuenta no ser deudor alimentario moroso y contar con una trayectoria laboral respetable a través de un estudio minucioso de los antecedentes del postulante en el que se pueda evaluar su conducta ética;\nVII. No haber sido condenado por sentencia firme, por delito doloso que amerite pena corporal de más de un año de prisión; pero si se tratare de robo, fraude, falsificación, abuso de confianza u otro que lastime seriamente la buena fama en el concepto público, lo inhabilitará para el cargo, cualquiera que haya sido la pena; y\n\nVIII. Participar y obtener resultado favorable en el concurso de oposición, así como en los exámenes que establece ésta Ley, en los mismos términos de lo que ésta dispone.\nArtículo 23. Se Deroga.\nArtículo 24. Para ejercer la titularidad de la Secretaría tanto de Acuerdos, como de Instrucción, según corresponda, en los Juzgados, Tribunales Laborales y en las Salas del Tribunal Superior de Justicia, así como para la de Proyectista de Segunda Instancia, se requiere:\nI. Tener la ciudadanía mexicana en pleno ejercicio de sus derechos civiles y políticos;\nII. Contar con Título de licenciatura en Derecho con cédula profesional expedida por la autoridad o Institución legalmente facultada para ello;\nIII. Tener dos años de práctica profesional, contados desde la fecha de expedición del título.\nIV. El requisito de la práctica profesional podrá ser dispensado, tratándose de personal que tenga una antigüedad en el Tribunal de cuando menos dos años; y\nV. No haber sido condenado por sentencia definitiva, por delito doloso que amerite pena privativa de libertad de más de un año de prisión, pero si se tratare de robo, fraude, falsificación, abuso de confianza u otro que lastime seriamente la buena fama en el concepto público, quedará inhabilitado para el cargo, cualquiera que haya sido la pena.\nArtículo 25. Para ocupar la Titularidad de la Primera o Segunda Secretaría de Acuerdos de la Presidencia y\nTribunal Pleno, así como Secretaría Auxiliar de la misma, se necesita que los interesados sean mexicanos por nacimiento y no hayan adquirido otra nacionalidad, satisfagan los requisitos indicados en el artículo que antecede, con la salvedad que en el caso de la Secretaría Auxiliar no se requiere tener dos años de práctica profesional. La o el Presidente del Tribunal Superior de Justicia les asignará sus funciones.\nArtículo 26. Para ser Secretaria o Secretario Actuario se requiere:\nI. Tener la ciudadanía mexicana en pleno ejercicio de sus derechos civiles y políticos;\nII. Tener título profesional de Licenciatura en Derecho con cédula profesional expedida por la autoridad o institución legalmente facultada para ello;\n\nIII. No haber sido condenado por sentencia firme, por delito doloso que amerite pena corporal de más de un año de prisión, pero si se tratare de robo, fraude, falsificación, abuso de confianza u otro que lastime seriamente la buena fama en el concepto público, quedará inhabilitado para el cargo, cualquiera que haya sido la pena; y\nIV. Tener una práctica profesional en el campo jurídico de seis meses y haber hecho un curso de preparación no menor de tres meses en el Instituto de Estudios Judiciales.\nPara ser Titular de la Secretaría Auxiliar Actuario de Sala se deben cubrir los requisitos establecidos en esta\nLey, a excepción del relativo a la práctica profesional.\nArtículo 27. Para ser Secretaria o Secretario Proyectista de Juzgado, Conciliador, Auxiliar de Juzgado de\nProceso Oral en materia Familiar u Oficial Notificador, se deberán reunir los mismos requisitos establecidos en esta Ley con excepción a lo relativo a la práctica profesional.\nLas personas servidoras públicas a que se refieren los artículos 24, 25 y 26 de esta Ley, deberán, además, aprobar los exámenes que el Instituto de Estudios Judiciales habrá de aplicar, para cada caso, en los términos de esta Ley.\nCAPÍTULO III\nDE LAS INCOMPATIBILIDADES E INCAPACIDADES\nArtículo 28. Las y los Magistrados, Juezas y Jueces, Consejeras y Consejeros, así como las y los Secretarios adscritos al Poder Judicial, no podrán en ningún caso aceptar ni desempeñar empleo, cargo o comisión de la Federación, de los Estados, de la Ciudad de México o de particulares, salvo los cargos no remunerados en asociaciones o instituciones científicas, docentes, artísticas o de beneficencia que no interfieran en su horario de trabajo ni menoscabe el pleno ejercicio de sus funciones.\nLas incompatibilidades a que se refiere este precepto serán aplicables a las personas servidoras públicas judiciales aun cuando gocen de licencia.\nArtículo 29. Los nombramientos que se hagan para las personas servidoras públicas judiciales, del Consejo de la Judicatura y auxiliares de la administración de justicia, no podrán recaer en ascendientes,\n\ndescendientes, cónyuges o colaterales dentro del cuarto grado por consanguinidad y segundo por afinidad, de la persona servidora pública que haga la designación.\nLas personas servidoras públicas que ocupen los cargos a los que se refiere el párrafo anterior, deberán ser designados por las autoridades u órganos competentes en los plazos y términos previstos por las normas aplicables, sin que puedan dejarse vacantes por más de treinta días hábiles.\nArtículo 30. Las personas servidoras públicas de la administración de justicia, no podrán desempeñarse corredores, comisionistas, apoderados judiciales, tutores, curadores, albaceas, depositarios, síndicos, administradores, interventores, árbitros, peritos, asesores jurídicos ni ejercer la abogacía, salvo en asuntos de carácter personal.\nLas y los Jueces, Magistrados y Consejeros no podrán actuar como patronos, abogados o representantes en cualquier proceso ante los órganos judiciales de la Ciudad de México mientras estén en el cargo, cuando hayan sido separados del mismo por sanción disciplinaria o dentro de los dos años siguientes a su retiro.\nArtículo 31. El retiro de las y los Jueces y las y los Magistrados se producira,́́ por sobrevenir incapacidad física o mental que imposibilite el adecuado desempeño del cargo, o al cumplir setenta y cinco años de edad.\nPárrafo modificado y publicado en la GOCDMX el 01 de agosto de 2024\nLas y los Magistrados ratificados, tendrán derecho al haber por retiro de carácter vitalicio, equivalente al cien por ciento de sus percepciones mensuales netas, durante los dos primeros años y al setenta por ciento de éstas durante el resto de su vida, cuando se encuentren bajo los siguientes supuestos:\na) Tener quince años o más como Magistrados; o b) Tener treinta años o más al servicio del Tribunal Superior de Justicia.\nA las y los Magistrados que hayan sido ratificados que opten por el retiro, se les deberá elaborar el cálculo actuarial correspondiente para conocer la cantidad que deberá aportar el Tribunal al Fondo de Retiro.\nLas cantidades resultantes de dicho estudio actuarial, se entregarán inmediatamente al Consejo de la\nJudicatura quien decidirá la forma de administrarlas.\n\nLas y los Magistrados que no fueren ratificados, al concluir su encargo si cumplen con el supuesto a que se refiere el inciso b) del párrafo anterior, tendrán derecho a un haber especial por retiro durante dos años, en el primer año será el equivalente al setenta por ciento de la percepción mensual neta del último año de ejercicio y el segundo será por el equivalente al cincuenta por ciento de dichas percepciones.\nEl ingreso mensual a que se refiere este artículo, se tomará como base para su tabulación las percepciones de las Magistraturas en activo.\nLas y los Magistrados ratificados, al cumplir sesenta y cinco años de edad podrán retirarse voluntariamente del cargo, en este caso cuando se retiren sin tener quince años de ejercicio y cuenten con veinticinco años o más al servicio del Tribunal, disfrutarán del haber por retiro, el que será proporcional al tiempo en que se hayan desempeñado como tales.\nDel monto total al que tenga derecho deberá deducirse, en su caso, aquél que reciba por parte del Instituto de Seguridad y Servicios Sociales de los Trabajadores del Estado.\nNo podrán recibir ninguna otra prestación que establezca la Ley del Fondo de Apoyo a la\nAdministración de Justicia en la Ciudad de México.\nEl haber por retiro se entregará por medio de ministraciones mensuales, las cuales se incrementarán en la misma proporción en que se aumenten las percepciones de los Magistrados en activo.\nLas y los Jueces ratificados, al retirarse del cargo, disfrutarán de un haber por retiro de carácter vitalicio en los términos del que corresponde a las y los Magistrados, de conformidad con lo establecido por los párrafos aplicables de este artículo; para lo cual se deberá cumplir con lo siguiente: haber sido ratificado, haberse desempeñado en ese cargo por quince años o más y contar, por lo menos, con veinte años de servicio en el Tribunal Superior de Justicia.\nPara dar cumplimiento a lo anterior, el Consejo de la Judicatura, establecerá un fondo para el retiro que será administrado por un fideicomiso. Para la constitución del Fondo para el Retiro se observará lo siguiente:\nLas y los Magistrados aportarán el equivalente al 8% de su percepción mensual neta, durante los seis primeros años y el 4% los subsecuentes, hasta el retiro.\n\nEl Consejo de la Judicatura a propuesta del Pleno del Tribunal, establecerá por medio de acuerdos conducentes, las reglas para la administración del Fondo, sin afectar las economías y funciones jurisdiccionales propias del Tribunal Superior de Justicia.\nTÍTULO TERCERO\nDE LA ORGANIZACIÓN DEL TRIBUNAL\nCAPÍTULO I\nDEL TRIBUNAL SUPERIOR DE JUSTICIA DE LA CIUDAD DE MÉXICO\nArtículo 32. El Poder Judicial se deposita en un Tribunal Superior de Justicia que contará con una Sala\nConstitucional; un Consejo de la Judicatura y Juzgados.\nEl Tribunal Superior de Justicia funcionará en Pleno y en Salas.\nEl Pleno del Tribunal de Justicia, es el órgano supremo del Poder Judicial, éste se integra por las y los\nMagistrados adscritos al Tribunal Superior de Justicia, una o uno de los cuales presidirá sin formar parte de alguna Sala.\nArtículo 33. El Tribunal Superior de Justicia contará con una Sala Constitucional de carácter permanente, misma que será la máxima autoridad local en materia de interpretación de la Constitución, la cual se regirá de conformidad con la ley en la materia.\nEl número de Salas del Tribunal Superior de Justicia, será determinado por el Consejo de la Judicatura, conforme a las necesidades y el presupuesto.\nArtículo 34. Para que funcione el Tribunal en Pleno se necesita la concurrencia de cuando menos las dos terceras partes de las y los Magistrados que lo integran sus resoluciones se tomarán por unanimidad o mayoría de votos de los presentes, salvo los asuntos que expresamente requieran votación por mayoría calificada. En caso de empate, se confiere voto de calidad quien presida del Tribunal.\nSe requerirá de la mayoría de votos de las Magistradas y Magistrados presentes del Pleno, para aprobar un proyecto de iniciativa y/o decreto que se presente ante el Congreso, en los ordenamientos relacionados con la organización y funcionamiento de la administración de justicia.\n\nArtículo 35. Las sesiones del Tribunal en Pleno serán ordinarias o extraordinarias y, en ambos casos, públicas o privadas. Las sesiones ordinarias deberán celebrarse cuando menos una vez al mes y las extraordinarias cuando sea necesario para tratar y resolver asuntos urgentes, previa convocatoria de quien lo presida, en la que determinará si son públicas o privadas, a iniciativa propia o a solicitud de tres integrantes del Tribunal cuando menos.\nArtículo 36. Para la Presidencia y el Tribunal en Pleno se designarán un Primer Secretario de Acuerdos, un\nSegundo Secretario de Acuerdos y el número de Secretarios Auxiliares de la Presidencia, así como los servidores públicos de la administración de justicia que fije el presupuesto de egresos respectivo, los cuales deben cumplir con los requisitos señalados en la presenta Ley para puestos similares.\nArtículo 37. Son facultades del Tribunal Superior de Justicia de la Ciudad de México en Pleno:\nI. Elegir, de entre las y los Magistrados con una antigüedad no menor de tres años a quien presida el Tribunal Superior de Justicia;\nII. Conocer de la calificación de la recusación de dos o tres Magistrados integrantes de una Sala;\nIII. Resolver sobre las contradicciones de criterios generales sustentados por las y los Magistrados y entre las Salas del Tribunal, sin perjuicio de observarse la jurisprudencia de los Tribunales\nFederales. Lo anterior podrá hacerse a petición de parte o de los órganos en conflicto ante el\nPleno del Tribunal Superior de Justicia.\nLa resolución que se dicte no afectará las situaciones jurídicas concretas derivadas de los juicios en los cuales se hubiesen dictado las sentencias que sustentaron las tesis contradictorias.\nEl Pleno deberá dictar la resolución correspondiente dentro del término de tres meses y deberá ordenar su publicación en el Boletín Judicial y en los Anales de Jurisprudencia y la remitirá a todos los órganos jurisdiccionales en la materia, que forman parte del Tribunal Superior de\nJusticia;\nIV. Solicitar al Consejo de la Judicatura, el cambio de adscripción de las o los Jueces y, en su caso, su remoción del cargo por causa justificada;\nV. Emitir precedentes jurisdiccionales sobre criterios sostenidos en asuntos competencia del\nPleno, a petición de cualquier persona Magistrada, los cuales serán del conocimiento público;\n\nVI. Se Deroga.\nVII. Solicitar al Instituto de Estudios Judiciales la implementación permanente de cursos de capacitación y actualización de carácter jurisdiccional, en los que participen las personas servidoras públicos del Poder Judicial de la Ciudad de México;\nVIII. Recibir y en su caso aceptar o rechazar la renuncia de quien presida el Tribunal;\nXI. Determinar la materia de las Salas del Tribunal Superior de Justicia;\nX. Calificar en cada caso las excusas o impedimentos que sus miembros presenten para conocer de determinados asuntos, así como de las recusaciones que se promuevan en contra de las\nMagistradas y los Magistrados, en negocios de la competencia del Pleno;\nXI. Proponer al Consejo de la Judicatura, sin perjuicio de las facultades administrativas y de gestión de este último para emitirlas, a través de su Presidente, las adecuaciones administrativas tendientes a simplificar y eficientar los procedimientos de registro, control y seguimiento de los asuntos que sean tramitados ante los Tribunales del Fuero Común y del Tribunal Superior de\nJusticia procurando en todo caso, y en la medida de lo posible, la incorporación de los métodos más modernos de sistematización y computarización para la más expedita, eficaz y transparente administración de justicia;\nXII. Conocer de las quejas que se presenten en contra de quien lo presida;\nXIII. Conocer de los asuntos cuya resolución no esté expresamente atribuida a otro órgano judicial;\nXIV. Resolver las revisiones administrativas a que se refiere el párrafo octavo del artículo 100 de la Constitución Política de los Estados Unidos Mexicanos, en los términos que esta Ley dispone;\nXV. Solicitar al Consejo de la Judicatura, sin perjuicio de la facultad administrativa directa de este último, la expedición de aquellos acuerdos generales que considere necesarios para asegurar un adecuado ejercicio de la función de los órganos judiciales;\n\nXVI. Revisar, modificar y, en su caso, revocar los acuerdos que el Consejo de la Judicatura apruebe, siempre y cuando se refieran a la designación, adscripción, remoción de las y los\nMagistrados o Jueces, requiriéndose para ello el voto de cuando menos dos terceras partes de sus integrantes, de conformidad con los artículos 108 y109 de la Constitución Política de los\nEstados Unidos Mexicanos;\nXVII. Acordar la realización de visitas periódicas a las instituciones del sistema penitenciario de la Ciudad de México, para entrevistarse con los individuos sujetos a proceso y conocer las condiciones bajo las cuales se están llevando los procesos penales;\nXVIII. Designar a las y los Magistrados que integren comisiones substanciadoras de aquellos procesos judiciales que corresponda resolver al Pleno, mismas que podrán dictar los acuerdos de trámite necesarios;\nXIX. Revisar el cumplimiento de los requisitos que exige el artículo 16 de la Constitución Política de los Estados Unidos Mexicanos, en la resolución que dicte el Juzgador de la causa, mediante la cual determine la procedencia de la orden de aprehensión o comparecencia, cuando se hubiere ejercitado acción penal en contra de una Magistrada o un Magistrado, Consejera o\nConsejero, así como un Jueza o Juez en el desempeño de su cargo o con motivo de éste. De resultar procedente se asentará mediante acuerdo y éste se comunicará al Consejo de la\nJudicatura, por conducto de quien presida, para que proceda en términos de la fracción VII, del artículo 258 de esta Ley;\nXX. Conocer de los recursos de apelación que se interponga en las causas que se instauren en contra de un integrante del Tribunal Superior de Justicia, del Consejo de la Judicatura o Titular de un Juzgado;\nXXI. Discutir, aprobar o rechazar los proyectos de iniciativas y decretos propuestos por las y los\nJueces y las y los Magistraturas del Tribunal, respecto de los ordenamientos relacionados con la organización y funcionamiento de la administración de justicia, mismos que serán presentados ante el Congreso;\nXXII. Designar en sesiones abiertas y transparentes las Magistradas y Magistrados de la Sala\nConstitucional; y\nXXIII. Las demás que expresamente le confieran esta Ley y otras disposiciones aplicables.\n\nCAPÍTULO II\nDE LA PRESIDENCIA DEL TRIBUNAL SUPERIOR DE JUSTICIA DE LA\nCIUDAD DE MÉXICO\nArtículo 38.- La o el Magistrado que presida el Tribunal Superior de Justicia de la Ciudad de México, será electo por las y los magistrados integrantes del Pleno del Tribunal Superior de Justicia, por mayoría de votos en sesión pública y mediante sufragio secreto; durará en su encargo cuatro años. La persona que haya ocupado la presidencia bajo los supuestos del presente numeral, no podrá volver a ocuparla posteriormente bajo ningún concepto, ni sucesiva, ni alternadamente, independientemente de la calidad con que pueda ostentarla.\nEl periodo de ejercicio del Presidente iniciará en el mes de enero y rendirá la protesta de ley ante el Pleno del Tribunal Superior de Justicia, en la primera sesión del año en curso.\nArtículo 39. La o el Magistrado que presida el Tribunal Superior de Justicia, tendrá las atribuciones que le confiere la presente Ley, siendo sus funciones principales las de: impulsar el desarrollo del Sistema de\nImpartición y Administración de Justicia en la Ciudad de México; procurar la correcta aplicación de la ley y velar para que la administración de justicia sea eficaz y expedita, dictando al efecto las providencias que fueren necesarias, promoviendo la modernización y adecuado funcionamiento de los diversos órganos jurisdiccionales y administrativos, por sí o por conducto de las personas servidoras públicas judiciales facultados al efecto.\nArtículo 40. Las providencias y acuerdos de la Presidencia pueden reclamarse ante el Tribunal en Pleno, por la parte interesada, dentro del plazo de tres días hábiles, siempre que dicha reclamación se presente por escrito, con motivo fundado.\nArtículo 41. Corresponde a la Presidencia del Tribunal Superior de Justicia de la Ciudad de México:\nI. Representar al Tribunal Superior de Justicia:\na) En los actos oficiales, teniendo la facultad de delegar en otros Magistrados o Jueces dicha representación; y\n\nb) Ante las autoridades en cualquier procedimiento en que el Tribunal Superior de Justicia sea parte, teniendo la facultad de delegar por causas de fuerza mayor en aquellos casos que las leyes lo permitan, la representación en el Titular de la Dirección Jurídica.\nII. Nombrar a las personas secretarias de la Presidencia y del Pleno del Tribunal, así como a la persona titular de la Oficialía Mayor, de la Dirección General del Centro de Justicia Alternativa, de la Dirección General del Instituto de Estudios Judiciales y de la Dirección del Instituto de\nServicios Pericial y Ciencias Forenses;\nIII. Designar a los Titulares de las Secretarías Auxiliares o Técnicas, y demás personal de la\nPresidencia. De igual forma a los funcionarios, técnicos y personal que señale la presente ley;\nIV. Llevar el turno de las Magistradas y los Magistrados que se excusen de conocer de alguno de los asuntos de su competencia o que sean recusados, para suplirlos con otros integrantes del\nTribunal;\nV. Llevar una lista de las excusas, recusaciones, incompetencias y sustituciones que estará a disposición de los interesados en la Secretaría de Acuerdos correspondiente;\nVI. Remitir al juez correspondiente los exhortos, rogatorias, suplicatorias, requisitorias y despachos, de acuerdo con el turno que al efecto se lleve;\nVII. Llevar la correspondencia del Tribunal Superior de Justicia de la Ciudad de México;\nVIII. Recibir quejas sobre demoras, excusas o faltas en el despacho de los negocios, turnándolas, en su caso, a quien corresponda;\nIX. Regular, instrumentar, sistematizar, dirigir y supervisar en el Tribunal Superior de Justicia, las funciones de desarrollo institucional, programación, política financiera, información, evaluación y de coordinación con otros sectores e instituciones; asimismo le corresponde instrumentar y supervisar el Programa General de Trabajo de la Institución, con la colaboración y participación de todas las áreas integrantes de la misma. Para la realización de esas funciones dispondrá de las correspondientes unidades de apoyo, de conformidad con las disponibilidades presupuestales del Tribunal y con las facultades que se les confieran en el Reglamento Interior del mismo;\n\nX. Hacer del conocimiento del Consejo de la Judicatura:\na) En un plazo no mayor de cinco días, sobre la vacante de una o un Magistrado que, por muerte, haya cesado en el ejercicio del encargo;\nb) En un plazo no mayor de cinco días, sobre la vacante de una o un Magistrado que, por incapacidad física o mental, esté imposibilitado para el desempeño del cargo; y c) Con una antelación no menor a cuarenta y cinco días, el nombre de aquellos titulares de Magistraturas que estén por concluir el ejercicio de su encargo.\nXI. Elaborar y difundir la información estadística relevante desglosada por rubros y categorías, ya sea para fines meramente informativos, o bien para el seguimiento, control y evaluación de los asuntos. El Consejo de la Judicatura establecerá los niveles de divulgación y privilegios de acceso a la misma, según la naturaleza y fines de la información;\nXII. Remitir al Congreso, las propuestas de iniciativa o decretos aprobadas por el Pleno del\nTribunal Superior de Justicia, de los ordenamientos relacionados con la organización y funcionamiento de la administración de justicia;\nXIII. Formar parte del Comité Coordinador del Sistema Integral de Derechos Humanos; y\nXIV. Las demás que expresamente le confiera esta Ley y otras disposiciones aplicables.\nArtículo 42. El Presidente del Tribunal Superior de Justicia también lo es del Tribunal en Pleno y sus obligaciones son las siguientes:\nI. Presidir las sesiones que celebre dicho Tribunal;\nII. Convocar a sesiones ordinarias o extraordinarias;\nIII. Dirigir los debates y conservar el orden durante las sesiones;\nIV. Proponer al Tribunal en Pleno los acuerdos que juzgue conducentes para el mejor desempeño de la función judicial;\n\nV. Tramitar todos los asuntos de la competencia del Tribunal en Pleno hasta ponerlos en estado de resolución;\nVI. Autorizar en unión con la Secretaría de Acuerdos que corresponda, las actas de las sesiones, haciendo constar en ellas las deliberaciones del Tribunal en Pleno y los acuerdos que éste dicte en los negocios de su competencia;\nVII. Dar cuenta al Tribunal en Pleno con las demandas de responsabilidad civil presentadas en contra de las y los Magistrados;\nVIII. Turnar a la Sala que competa, los expedientes que de conformidad con sus atribuciones les corresponda conocer para los efectos a que hubiere lugar;\nIX. Dar cuenta al Tribunal en Pleno, en el informe anual correspondiente, de los actos que lleve a cabo en el ejercicio de sus funciones, así como del desempeño general de los servicios que le sean adscritos;\nX. Aprobar la formalización de acuerdos y convenios de colaboración teórico–académica, con instituciones públicas o privadas tendientes a una mayor profesionalización y capacitación en el campo de la impartición de justicia; y\nXI. Las demás que expresamente le confiera esta Ley y otras disposiciones aplicables.\nCAPÍTULO III\nDE LAS SALAS DEL TRIBUNAL\nArtículo 43. La Sala Constitucional es de carácter permanente, y es la máxima autoridad local en materia de interpretación de la Constitución, cuyas facultades y atribuciones se establecen en la Ley de la materia.\nEstará encargada de garantizar la defensa, integridad y supremacía de la Constitución y la integridad del sistema jurídico local sin perjuicio de lo previsto en la Constitución Política de los Estados Unidos\nMexicanos.\n\nArtículo 44. La Sala Constitucional se integra por siete Magistradas y Magistrados designados por el Pleno del Tribunal Superior de Justicia, el proceso de selección se llevará al cabo en sesiones abiertas y transparentes. El número de integrantes de un mismo género no podrá ser mayor a cuatro.\nLas y los Magistrados de la Sala Constitucional durarán en el cargo ocho años.\nArtículo 45. Para ser electa Magistrada o Magistrado de la Sala Constitucional se requiere:\nI. Cubrir los requisitos previstos en las fracciones I a V del artículo 95 de la Constitución Política de los Estados Unidos Mexicanos y del artículo 21 de la presente Ley; y\nII. Adicional a los requisitos señalados en el inciso anterior, los magistrados deben tener al menos 5 años de experiencia en temas constitucionales y/o de defensa de derechos humanos.\nÚnicamente para el caso de los Magistrados de la Sala Constitucional, los diez años de experiencia puede ser acreditada mediante la práctica profesional docente en universidades de reconocido prestigio.\nArtículo 46. Con excepción de la Constitucional, las Salas del Tribunal Superior de Justicia, se integrarán cada una por tres magistrados, y serán designadas cada una por un número ordinal, en Salas Civiles,\nPenales, Familiares, Justicia para Adolescentes y Especializadas en Ejecución de Sentencias Penales.\nLos integrantes de las mismas actuarán en forma unitaria o colegiada en los términos establecidos por esta\nLey. El Pleno del Tribunal determinará las materias de las Salas, de acuerdo con los requerimientos de una buena administración de justicia.\nLa Salas Especializadas en Ejecución de Sanciones Penales del Tribunal Superior de Justicia, resolverán en forma colegiada sobre la negativa o el otorgamiento de los beneficios en materia penitenciaria y en todos los demás casos resolverán de manera unitaria.\nArtículo 47. Las y los Magistrados que integren la Sala, elegirán anualmente de entre ellos a quien los presida que durará en su cargo un año y no podrá ser reelecto para el período siguiente.\nArtículo 48. Las y los Magistrados de las Salas desahogarán semanariamente por orden progresivo y en forma equitativa todo trámite de Segunda Instancia.\n\nLas Salas penales establecerán un sistema de guardia y control, para substanciar el trámite de Segunda\nInstancia, en tratándose de asuntos urgentes de conformidad con el Código Nacional de Procedimientos\nPenales.\nArtículo 49. Las resoluciones colegiadas de las Salas se tomarán por unanimidad o mayoría de votos.\nAsimismo, a petición de cualquiera de sus integrantes, podrán integrar precedentes los criterios emitidos por unanimidad en asuntos de su competencia.\nArtículo 50. Corresponde a la Presidenta o Presidente de la Sala:\nI. Llevar la correspondencia de la Sala, autorizándola con su firma;\nII. Distribuir por riguroso turno los negocios, entre él y los demás miembros de la Sala, para su estudio y presentación oportuna, en su caso, del proyecto de resolución que en cada uno deba dictarse;\nIII. Presidir las audiencias de la Sala, cuidar el orden de la misma y dirigir los debates;\nIV. Dirigir la discusión de los negocios sometidos al conocimiento de la Sala y ponerlos a votación cuando la Sala declare terminado el debate;\nV. Dar a la Secretaría de Acuerdos los puntos que comprendan las disposiciones resolutivas votadas y aprobadas;\nVI. Llevar la administración de la oficina de la Sala;\nVII. Ordenar la publicación y difusión de los precedentes respecto de criterios definidos por asuntos competencia de la Sala, aprobados por unanimidad por sus integrantes, y\nVIII. Vigilar que las Secretarías y demás personas servidoras públicas de la Sala cumplan con sus respectivos deberes.\nArtículo 51. Las Salas en materia Civil, conocerán:\n\nI. De los casos de responsabilidad civil de los Titulares de Juzgados Civiles, de lo Civil de Cuantía\nMenor, de Proceso Oral y de Extinción de Dominio del Tribunal Superior de Justicia.\nAsimismo, de los recursos de apelación y queja que se interpongan contra las resoluciones dictadas en asuntos civiles y de extinción de dominio y en los juicios de pago de daños culposos causados con motivo del tránsito de vehículos, por los titulares de los juzgados de lo civil, extinción de dominio y de lo Civil de Cuantía Menor. De igual manera de los recursos de queja que se interpongan contra las resoluciones dictadas en los Juzgados de lo Civil de Cuantía\nMenor.\nII. De las excusas y recusaciones de los Titulares de los Juzgados Civiles, de los de lo Civil de\nCuantía Menor, de lo Civil de Proceso Oral y de Extinción de Dominio, del Tribunal Superior de\nJusticia;\nIII. De los conflictos competenciales que se susciten en materia civil entre las autoridades judiciales del Tribunal Superior de Justicia; y\nIV. De las cuestiones de competencia por declinatoria que se susciten en materia civil, y\nV. De los demás asuntos que determinen las leyes.\nLas sentencias definitivas o resoluciones que pongan fin a la instancia que recaigan a los asuntos a que se refieren las fracciones anteriores, se pronunciarán de manera colegiada. En todos los demás casos se dictarán unitariamente por los Magistrados que integren la Sala conforme al turno correspondiente.\nCualquiera de las y los Magistrados podrá determinar que el fallo se realice en forma colegiada en razón del criterio que se va a establecer o por otra circunstancia.\nArtículo 52. Las Salas en materia Penal, conocerán:\nI. De los recursos de apelación y denegada apelación que les correspondan y que se interpongan en contra de las resoluciones dictadas por las y los Jueces del orden Penal de la\nCiudad de México, incluyéndose las resoluciones relativas a incidentes civiles que surjan en los procesos;\nII. De las excusas y recusaciones de las y los Jueces Penales del Tribunal Superior de Justicia;\n\nIII. Del conflicto competencial que se susciten en materia penal entre las autoridades judiciales del Tribunal Superior de Justicia;\nIV. De las contiendas de acumulación que se susciten en materia penal, entre las autoridades que expresa la fracción anterior;\nV. De las notificaciones que deberán realizar de manera inmediata a los Agentes del\nMinisterio Público adscritos, al momento en que se dicten y previo a su ejecución, respecto de los autos de libertad por falta de elementos para procesar y las sentencias absolutorias;\nVI. De los casos de responsabilidad civil de las y los jueces penales del Tribunal Superior de\nJusticia; y\nVII. De los demás asuntos que determinen las leyes.\nEstas Salas resolverán de manera colegiada, cuando se trate de apelaciones contra sentencias definitivas derivadas de procedimientos ordinarios dictadas en procesos instruidos por delitos graves en los que se imponga pena de prisión mayor a cinco años. En todos los demás casos, las resoluciones se dictarán en forma unitaria conforme al turno correspondiente.\nTratándose de procedimientos en materia oral la Sala resolverá conforme a lo establecido en el párrafo anterior, cuando se trate de apelaciones contra sentencias definitivas en las que se haya impuesto pena de prisión mayor de cinco años.\nCualquiera de las y los Magistrados podrá determinar que el fallo se realice en forma colegiada en razón del criterio que se va a establecer o por otra circunstancia.\nArtículo 53. Las Salas en materia de Justicia para Adolescentes conocerán:\nI. De los recursos de apelación y denegada apelación que les correspondan y que se interpongan en contra de las resoluciones dictadas por las y los Jueces de Justicia para\nAdolescentes de la Ciudad de México, incluyéndose las resoluciones relativas a incidentes civiles que surjan en los procesos;\n\nII. De las excusas y recusaciones de las y los Jueces en materia de Justicia para Adolescentes de la Ciudad de México;\nIII. De los conflictos competenciales que se susciten en materia de Justicia para\nAdolescentes, entre las autoridades judiciales del Tribunal Superior de Justicia;\nIV. De las contiendas de acumulación que se susciten en materia de Justicia para Adolescentes, entre las autoridades que expresa la fracción anterior;\nV. De los casos de responsabilidad civil de las y los jueces de Justicia para Adolescentes del\nTribunal Superior de Justicia; y\nVI. De los demás asuntos que determinen las leyes.\nEstas Salas resolverán de manera colegiada, cuando se trate de apelaciones contra sentencias definitivas dictadas en procesos instruidos por conductas típicas calificadas como graves, o en los casos en que se imponga la medida de internamiento, resoluciones que versen sobre hechos que en el correspondiente pliego sean calificados de antisociales, al amparo la acción penal por alguna conducta típica calificada como grave, con independencia de que se determine la comprobación o no de la conducta típica calificada como grave, la reclasificación de las conductas o hechos, o la no acreditación de alguna agravante o modalidad que provisionalmente determine que la conducta típica calificada como grave; o en contra de cualquier resolución en la que se haya determinado la libertad por conclusión del internamiento por rehabilitación social. En todos los demás casos las resoluciones se dictarán en forma unitaria conforme al turno correspondiente.\nCualquiera de las y los Magistrados podrá determinar que el fallo se realice en forma colegiada en razón del criterio que se va a establecer o por otra circunstancia.\nArtículo 54. A las y los Magistrados de las Salas Especializadas en Ejecución de Sanciones Penales del\nTribunal Superior de Justicia, les corresponde conocer:\nI. De los recursos de apelación y denegada apelación interpuestos en contra de las resoluciones de los jueces de ejecución de sanciones penales que dicten en sus funciones de vigilancia de ejecución de la pena, reparación del daño y negación de beneficios penitenciarios;\n\nII. De las excusas y recusaciones de las Juezas y Jueces de Ejecución de Sanciones Penales;\nIII. De los conflictos competenciales que se susciten entre las y los Jueces de Ejecución de\nSanciones Penales;\nIV. De los casos de responsabilidad Civil de las y los Jueces de Ejecución de Sanciones Penales del Tribunal Superior de Justicia; y\nV. De los demás asuntos que determinen las leyes.\nArtículo 55. Las Salas en materia Familiar, conocerán:\nI. De los casos de responsabilidad civil y de los recursos de apelación y queja que se interpongan en asuntos de materia Familiar, contra las resoluciones dictadas por los jueces del mismo ramo;\nII. De las excusas y recusaciones de las Juezas y Jueces del Tribunal Superior de Justicia, en asuntos del orden familiar;\nIII. De las competencias que se susciten en materia Familiar entre las autoridades judiciales del\nTribunal Superior de Justicia, y\nIV. De los demás asuntos que determinen las leyes.\nLas sentencias en los asuntos a que se refieren las fracciones anteriores, se pronunciarán de manera colegiada tratándose de definitivas o de resoluciones que pongan fin a la instancia y las que versen sobre custodia de menores. En todos los demás casos se dictarán unitariamente por aquellos que integren la\nSala conforme al turno correspondiente.\nCualquiera de las Magistradas o Magistrados podrá determinar que el fallo se realice en forma colegiada en razón del criterio que se va a establecer o por otra circunstancia.\nArtículo 56. Las Salas que integran el Poder Judicial de la Ciudad de México, que al efecto determine el\nConsejo de la Judicatura, conocerán de las excusas y recusaciones, que se planteen en los conflictos laborales.\n\nArtículo 57. Las Salas al resolver sobre las excusas de las y los Jueces, en caso de que éstas sean infundadas, remitirán la resolución al Consejo de la Judicatura para que imponga la sanción correspondiente.\nPara el desempeño de los asuntos encomendados, cada Sala tendrá cuando menos una persona responsable de la Secretaría Acuerdos, y dos de la Secretarías o Secretarios Auxiliares, doce Secretarias o\nSecretarios Proyectistas y dos Secretarios Actuarios, que serán designadas y removidas por las Magistradas y Magistrados integrantes de la Sala y la planta de servidores públicos de la administración de justicia que fije el presupuesto de egresos.\nLas y los Secretarios de Acuerdos y las y los Secretarios Auxiliares de Salas, tendrán en lo conducente, las mismas atribuciones que las Secretarías de Acuerdos de los Juzgados de Primera Instancia.\nTÍTULO CUARTO\nDE LOS JUZGADOS DEL TRIBUNAL SUPERIOR DE JUSTICIA DE LA\nCIUDAD DE MÉXICO\nCAPÍTULO I\nDE SU INTEGRACIÓN Y FUNCIONAMIENTO\nArtículo 58. Los Juzgados son órganos jurisdiccionales, cuyos titulares son las y los Jueces.\nEn la Ciudad de México habrá el número de Juzgados que el Consejo de la Judicatura considere necesarios para que la administración de justicia sea expedita. Dichos Juzgados estarán numerados progresivamente.\nAsimismo, podrá definir el número y especialización de los mismos, de conformidad con las necesidades y el presupuesto con el que se cuente.\nArtículo 59.. Los Juzgados de lo Civil de Proceso Escrito conocerán de procedimientos escritos:\nI. De los asuntos de jurisdicción voluntaria, cuyo conocimiento no corresponda a la materia familiar;\nII. De los juicios contenciosos que versen sobre la propiedad o demás derechos reales, cuyo conocimiento no corresponda a los Jueces Civiles de Proceso Oral;\n\nIII. De los asuntos que versen sobre derechos personales, en materia civil, cuyo conocimiento no corresponda a los Juzgados Civiles de Proceso Oral;\nIV. De los asuntos de jurisdicción contenciosa, concurrente cuya competencia no esté expresivamente prevista a favor de los juzgados de lo civil de proceso oral.\nV. De los asuntos de jurisdicción contenciosa concurrente de tramitación especial que versen sobre derechos personales, cuyo conocimiento no corresponda a los Juzgados Civiles de Proceso\nOral;\nVI. De los interdictos, juicios hipotecarios, vía de apremio y ejecutivos civiles, con excepción de lo previsto en artículo 98, fracción V, de esta Ley;\nVII. De la diligenciación de los exhortos, rogatorias, suplicatorias, requisitorias y despachos, en el ámbito de su competencia;\nVIII. De todas las controversias que se susciten en materia de arrendamiento de inmuebles destinados a habitación, comercio, industria o cualquier otro uso, giro o destino permitido por la ley;\nIX. De los asuntos relativos a la inmatriculación judicial de inmuebles y demás asuntos referentes a la materia que establezcan las leyes;\nX. Siempre serán competentes de los asuntos de cuantía indeterminada, es decir, aquellos que no sean cuantificables en dinero, en materia común o concurrente;\nXI. Siempre serán competentes de los asuntos de cuantía indeterminada, es decir, aquellos que no sean cuantificables en dinero, en materia común o concurrente;\nXII. De las diligencias preliminares de consignación;\nXIII. Del Juicio de Pago de Daños Culposos causados con motivo del Tránsito de Vehículos, establecido en el Código de Procedimientos Civiles vigente en la Ciudad de México, independientemente del monto que se demande como pago y en los términos y plazos que se señalan en dicho capítulo;\n\nXIV. De juicios contenciosos que versen sobre adeudos de cuotas de mantenimiento, intereses o sanciones por incumplimiento a la Ley de Propiedad en Condominio de Inmuebles para el\nDistrito Federal, y de las resoluciones y convenios celebrados ante la Procuraduría Social de la\nCiudad de México, y\nXV. De los demás asuntos que les encomienden las leyes.\nLos procedimientos de su competencia podrán tramitarse en línea o a través del uso de tecnologías de la información aprovechando el principio de equivalencia funcional del documento electrónico, conforme a los Lineamientos que al efecto emita el Consejo de la Judicatura.\nArtículo 60. Los Juzgados Penales y de Justicia para Adolescentes ejercerán las competencias y atribuciones que les confieran las leyes, a partir de la recepción del turno de trámite que se establecerá por orden numérico en los términos del control que lleve a cabo la Dirección de Turno de Consignaciones Penales y de Justicia para Adolescentes del Tribunal y de conformidad con las reglas que para el efecto expida el\nConsejo de la Judicatura.\nEstas reglas deberán garantizar objetividad e imparcialidad en los turnos así como equilibrio en las cargas de trabajo entre los distintos juzgados.\nLas personas servidoras públicas del Tribunal y del Consejo de la Judicatura que, con motivo de sus funciones posean información sobre el turno y las reglas, deberán dar trato estrictamente confidencial a dicha información, haciéndose acreedoras, en caso de incumplimiento, a la respectiva sanción penal o administrativa, de acuerdo con el carácter de la infracción.\nLos Juzgados Penales y de Justicia para Adolescentes conocerán de los delitos en materia de narcomenudeo previstos en el Título Décimo Octavo Capítulo VII de la Ley General de Salud. En los procedimientos penales que se substancien con motivo de los mismos, se observarán las disposiciones previstas en el artículo 480 de dicho ordenamiento.\nLas y los Jueces en el ámbito penal deberán ordenar de manera inmediata la práctica de la notificación a los Agentes del Ministerio Público adscrito, al momento en que se dicten y previo a su ejecución, de los autos de libertad por falta de elementos para procesar y las sentencias absolutorias.\nArtículo 61. Los órganos jurisdiccionales del Sistema Penal Acusatorio que actúen de manera unitaria o colegiada, ejercerán las competencias y atribuciones que les confieran las leyes, a partir de la recepción del\n\nturno de trámite que se establecerá por orden numérico en los términos del control que lleve a cabo la\nUnidad de Gestión Judicial y de conformidad con las reglas que para el efecto expida el Consejo de la\nJudicatura.\nEstas reglas deberán garantizar objetividad e imparcialidad en los turnos así como equilibrio en las cargas de trabajo entre los distintos Juezas y Jueces.\nLas personas servidoras públicas del Tribunal de Justicia y del Consejo de la Judicatura que con motivo de sus funciones posean información sobre el turno y las reglas deberán dar trato estrictamente confidencial a dicha información, haciéndose acreedores, en caso de incumplimiento, a la respectiva sanción penal o administrativa, de acuerdo con el carácter de la infracción.\nLas y los Jueces del Sistema Penal Acusatorio que actúen de manera unitaria o colegiada, conocerán de los delitos en materia de narcomenudeo previstos en la Ley General de Salud. En los procedimientos penales que se substancien con motivo de los mismos, se observarán las disposiciones previstas en el artículo 480 de dicho ordenamiento.\nDe igual manera, y tomando en consideración las características del hecho investigado, por razones de seguridad en las prisiones o por otras que impidan garantizar el desarrollo adecuado del proceso, serán competentes los jueces del sistema penal acusatorio de la Ciudad de México, en asuntos donde la comisión del delito es distinta al de su jurisdicción.\nLas y los Jueces de Control, conocerá desde el inicio de la etapa de investigación hasta el dictado del auto de apertura de juicio; así como resolverán de manera unitaria.\nLos Tribunales de Enjuiciamiento que actúen de manera unitaria o colegiada, conocerán del asunto desde que se reciba el auto de apertura a juicio, hasta la sentencia firme. En todos los casos la actuación del\nTribunal será de manera unitaria, salvo que determine lo contrario la persona juzgadora a quien se le designe el asunto por razón del criterio que se va a establecer o por otra circunstancia. El Tribunal de\nEnjuiciamiento actuando de manera colegiada se integrará por tres personas juzgadoras.\nEn materia penal tendrán la validez y eficacia de un documento físico original de registro, los archivos de documentos, mensajes, imágenes, bancos de datos y toda aplicación almacenada o transmitida por medios electrónicos, informáticos, magnéticos, ópticos, telemáticos o producidos por nuevas tecnologías, destinados a la tramitación judicial, ya sea que registren actos o resoluciones judiciales. Lo anterior siempre que cumplan con los procedimientos establecidos para garantizar su autenticidad, integridad y seguridad.\n\nLas alteraciones que afecten la autenticidad o integridad de dichos soportes los harán perder el valor jurídico que se les otorga en el párrafo anterior.\nCuando un Juzgador de la materia penal utilice los medios indicados en el párrafo anterior de este artículo, para hacer constar sus actos o resoluciones, los medios de protección del sistema resultan suficientes para acreditar la autenticidad, aunque no se impriman en papel ni sean firmados.\nLas autoridades judiciales de la materia penal podrán utilizar los medios referidos para comunicarse oficialmente entre sí, remitiéndose informes, comisiones y cualquier otra documentación.\nEl Pleno del Consejo de la Judicatura dictará los reglamentos necesarios para normar el envío, recepción, trámite y almacenamiento de los citados medios; para garantizar su seguridad y conservación; así como para determinar el acceso del público a la información contenida en las bases de datos, conforme a la ley.\nArtículo 62. Los Juzgados de lo Familiar conocerán:\nI. De los procedimientos de jurisdicción voluntaria, relacionados con el derecho familiar;\nII. De los juicios contenciosos relativos al matrimonio a su ilicitud o nulidad; de divorcio; que se refieren al régimen de bienes en el matrimonio; que tengan por objeto modificaciones o rectificaciones de las actas del Registro Civil; que afecten al parentesco, a los alimentos, a la paternidad y a la filiación; que tengan por objeto cuestiones derivadas de la patria potestad, estado de interdicción y tutela y las cuestiones de ausencia y de presunción de muerte, y que se refieran a cualquier cuestión relacionada con el patrimonio de familia, con su constitución, disminución, extinción o afectación en cualquier forma;\nIII. De los juicios sucesorios;\nIV. De los asuntos judiciales concernientes a otras acciones relativas al estado civil, a la capacidad de las personas y a las derivadas del parentesco;\nV. De las diligencias de consignación en todo lo relativo a la materia familiar;\nVI. De la diligenciación de los exhortos, suplicatorias, requisitorias y despachos, relacionados con el orden familiar;\n\nVII. De las cuestiones relativas a los asuntos que afecten en sus derechos de persona a los menores e incapacitados; y\nVIII. En general, todas las cuestiones familiares que reclamen la intervención judicial.\nArtículo 63. A las y los Jueces de Ejecución de Sanciones Penales en la Ciudad de México les corresponde:\nI. Resolver en audiencia oral, todos los incidentes relativos a la revocación de cualquier beneficio concedido a los sentenciados por cualquier autoridad jurisdiccional, y en aquellos casos en que deba resolverse sobre libertad anticipada de los sentenciados;\nII. Resolver todas las cuestiones relacionadas con la ejecución de las consecuencias jurídicas del delito;\nIII. Realizar todas las acciones necesarias para la vigilancia de la ejecución de las consecuencias jurídicas del delito;\nIV. Responder a las consultas formuladas por las autoridades penitenciarias; y\nV. Todas las demás que establezcan las leyes correspondientes.\nArtículo 64. A los Juzgados para Adolescentes les corresponde:\nI. Conocer las causas instauradas en contra de las personas a quienes se imputen la realización de un acto tipificado como delito en las leyes locales, cuando tengan entre doce años cumplidos y dieciocho no cumplidos;\nII. Promover la conciliación entre quien ejerza la patria potestad o en su caso represente al adolescente y la víctima u ofendido como formas de rehabilitación social, a fin de cumplir con los principios de mínima intervención y subsidiaridad y en su caso, decretar la suspensión del proceso por arreglo conciliatorio;\nIII. Resolver los asuntos sometidos a su conocimiento, conforme a la Ley Nacional del Sistema\nIntegral de Justicia Penal para Adolescentes.\n\nIV. Resolver sobre las medidas a imponer, atendiendo al estudio de los hechos y estudio de su personalidad, que lleven a establecer los principios de culpabilidad, proporcionalidad y racionalidad, por el acto antisocial, así como a las circunstancias, gravedad de la conducta, características y necesidades de los Adolescentes, que represente el menor daño al adolescente para su reincorporación social.\nArtículo 65. Los Juzgados de Extinción de Dominio conocerán:\nI. De los procedimientos de Extinción de Dominio establecidos en la Ley de la materia;\nII. De las medidas cautelares en materia de Extinción de Dominio;\nIII. De la diligenciación de los exhortos, rogatorias, suplicatorias, requisitorias y despachos, en la materia; y\nIV. De las demás diligencias, acuerdos y actividades que les encomiende la Ley de Extinción de\nDominio para la Ciudad de México y demás legislación vigente.\nArtículo 66. Los Juzgados de Tutela de Derechos Humanos conocerán de la acción de protección efectivas de derechos de conformidad con lo que establece el artículo 36, apartado B, numeral 3 de la Constitución.\nLa acción de protección efectiva es el mecanismo por medio del cual los jueces tutelares conocen de manera directa las posibles violaciones a los derechos humanos reconocidos en la Constitución, contra los que se inconformen el titular de un derecho o de un interés legítimo individual o colectivo al inicio y/o durante la sustanciación del algún procedimiento competencia de la Administración Pública.\nArtículo 67. Las reclamaciones de tutela son procedentes en los siguientes casos:\nI. En contra de la acción de alguna autoridad u Órgano Autónomo de la Ciudad de México que constituya una probable violación, que viole o que haya violado los derechos contemplados en la Constitución; y\nII. En contra de la omisión de alguna autoridad de la Ciudad de México u Órgano Autónomo de la Ciudad de México que constituya una probable violación, que viole o que haya violado los derechos contemplados en la Constitución.\n\nArtículo 68. Son improcedentes las reclamaciones de tutela en los siguientes casos:\nI. Contra las resoluciones judiciales emitidas por otros órganos jurisdiccionales.\nII. Cuando se trate de un hecho consumado, salvo cuando continúe la acción u omisión que haya violado los derechos contemplados en la Constitución.\nIII. Los temas que fueron expresamente excluidos en la Constitución.\nArtículo 69. La acción de protección efectiva de derechos se interpondrá en cualquier momento sin mayores formalidades y a través de solicitud oral o escrita y en todos los casos se aplicará la suplencia en la deficiencia de la queja.\nPara la promoción de la acción de protección efectiva, el quejoso deberá expresar como mínimo lo siguiente:\nI. Nombre del sujeto legitimado, debiendo señalar domicilio para recibir notificaciones dentro de la Ciudad de México;\nII. Indicar una relación sucinta de los hechos que describan la posible violación de un derecho reconocido por la Constitución;\nIII. Señalar a la autoridad o autoridades que intervinieron, y\nIV. En su caso las pruebas con que se cuenten;\nArtículo 70. Posterior a la presentación de la acción efectiva, salvo lo dispuesto en el artículo anterior, no se admitirán al quejoso otros documentos, salvo los que se hallen en alguno de los casos siguientes:\nI. Ser de fecha posterior a dichos escritos;\nII. Los de fecha anterior, respecto de los cuales, manifieste bajo protesta decir verdad, no haber tenido conocimiento de su existencia; y\n\nIII. Los que no haya sido posible obtener con anterioridad por causas que no sean imputables a la parte interesada, y siempre que acredite que los haya solicitado dentro del término señalado en el artículo anterior.\nArtículo 71. Recibida la acción efectiva, el Juez de Tutela en un plazo no mayor a tres días hábiles requerirá a la autoridad o autoridades que intervinieron rindan un informe sobre los hechos controvertidos, mismo que deberá rendirse dentro de los dos días hábiles siguientes a su notificación.\nEn caso de que la autoridad o autoridades no rindan el informe correspondiente dentro del plazo señalado, se tendrá por ciertos los hechos descritos por el quejoso.\nArtículo 72. La autoridad o autoridades, al rendir su informe deberán expresar cuando menos:\nI. Las consideraciones de hecho y de derecho que permitan entender al quejoso de una manera clara y precisa la legalidad del acto, debiendo señalar el ámbito de su competencia en el asunto y su intervención en el procedimiento;\nII. Se referirá concretamente a cada uno de los hechos que el quejoso le impute de manera expresa o por escrito, afirmándolos o negándolos, expresando que los ignora por no ser propios o exponiendo cómo ocurrieron, según sea el caso;\nIII. Las pruebas que ofrezca en su caso;\nIV. A manera de conclusión expondrá brevemente si el acto que motivo la acción efectiva es improcedente y las razones que lo motiven.\nArtículo 73. Rendido el informe el Juez de Tutela deberá acordar dentro de los dos días hábiles siguientes el desahogo de las pruebas ofrecidas.\nLa valoración de las pruebas se hará de acuerdo con las siguientes disposiciones:\nI. Harán prueba plena, la inspección ocular, las presunciones legales que no admitan prueba en contrario, así como los hechos legalmente afirmados por autoridades en documentos públicos;\nII. Tratándose de actos de comprobación de las autoridades administrativas, se entenderán como legalmente afirmados los hechos que consten en las actas respectivas, y\n\nIII. El valor de las pruebas pericial y testimonial, así como las demás pruebas quedará a la prudente apreciación del Juez de Tutela;\nDesahogadas las diligencias anteriores, la autoridad emitirá la resolución dentro del término de diez días naturales.\nArtículo 74. Una vez recibido el informe, el Juez de Tutela cuando no existiere ninguna prueba que amerite necesariamente el desahogo de pruebas y/o diligencias, ni cuestión pendiente que impida su resolución, notificará a las partes que tienen un término de dos días hábiles para formular alegatos. El quejoso podrá presentarlos de manera oral o escrita. La autoridad deberá presentarlos por escrito. Los alegatos presentados en tiempo deberán ser considerados al dictar resolución.\nAl vencer el plazo a que se refiere el párrafo anterior, con alegatos o sin ellos, sin necesidad de una declaratoria expresa, y a partir del día siguiente empezará a computarse el plazo para la emisión de la resolución que no excederá de diez días naturales.\nArtículo 75. Para hacer cumplir sus determinaciones, los jueces de tutela, bajo su criterio y responsabilidad, podrán hacer uso, indistintamente, de las siguientes medidas de apremio:\nI. Multa;\nII. Auxilio de la fuerza pública que deberán prestar las autoridades policíacas de la Ciudad de\nMéxico; y\nIII. Ordenar que se ponga al infractor a disposición de la autoridad ministerial por la probable comisión de delito en el supuesto de flagrancia; en caso contrario, redactar el acta respectiva y hacer la denuncia ante la representación social.\nArtículo 76. La resolución que declare fundada la acción efectiva tendrá por objeto restituir al quejoso en el pleno goce de sus derechos reconocidos por la Constitución, restableciendo las cosas al estado que guardaban antes de la violación, cuando el acto sea de carácter positivo; y cuando sea de carácter negativo, el efecto de la acción efectiva será obligar a la autoridad a que obre en el sentido de respetar el derecho de que se trate y a cumplir, por su parte, lo que el mismo derecho exige.\nLas sentencias dictadas por los jueces de tutela podrán ser impugnadas ante la Sala Constitucional.\n\nA falta de disposición expresa en lo establecido por esta Ley se estará a lo dispuesto por el Código de\nProcedimientos Civiles vigente en la Ciudad de México y demás disposiciones relativas aplicables.\nArtículo 77. El Consejo de la Judicatura a través de acuerdos generales y considerando la carga de trabajo de estos juzgados y las necesidades de presupuesto, establecerá cuando menos un juzgado de tutela en cada una de las demarcaciones territoriales.\nArtículo 78. El sistema de justicia laboral se integra por Tribunales Laborales para Conflictos Individuales, y para Conflictos Colectivos, los cuales tendrán la competencia para conocer de las controversias de acuerdo a su naturaleza.\nI. Los Tribunales Laborales para Conflictos Individuales conocerán: De los conflictos que el artículo 123 apartado A fracción XXXI de la Constitución Política de los Estados Unidos Mexicanos no tenga reservados como competencia del Poder Judicial de la Federación, que sea la competencia local en la Ciudad de México y que constituya un conflicto individual, y\nII. Los Tribunales Laborales para Conflictos Colectivos conocerán de todos aquellos conflictos que el artículo 123, apartado A, fracción XXXI, de la Constitución Política de los Estados Unidos\nMexicanos no tenga reservados como competencia del Poder Judicial de la Federación, que sea la competencia local en la Ciudad de México y que constituya un conflicto colectivo.\nCAPÍTULO II\nDE LA ORGANIZACIÓN INTERNA DE LOS JUZGADOS Y ÓRGANOS\nJURISDICCIONALES ORALES\nArtículo 79. Cada uno de los Juzgados o Tribunales Laborales a que se refiere este capítulo, contará con el siguiente personal:\nI. Un Titular, Jueza o Juez, que atenderá proporcional y equitativamente las cargas de trabajo con el objeto de lograr que el conocimiento de los asuntos a su cargo, se realice de manera inmediata y expedita;\n\nII. Las y los Secretarios de Acuerdos o Instructores, Conciliadores, Proyectistas y Actuarios que requiera el servicio, y tratándose de Juzgados de Proceso Oral en materia Familiar, las Secretarías\nJudiciales y Auxiliares que requiera el servicio; y\nIII. Las personas servidoras públicas de la administración de justicia que autorice el presupuesto.\nArtículo 80. La persona Titular de la Secretaría de Acuerdos o de instrucción que determine el Juzgador, será el jefe inmediato de la oficina en el orden administrativo, dirigirá las labores de ella conforme a las instrucciones de su superior jerárquico y lo suplirá en sus ausencias, cuando no excedan de un mes.\nArtículo 81. Son obligaciones de las personas titulares de las Secretarías de Acuerdos o de Instrucción, así como de las y los Secretarios Auxiliares.\nI. Formular los proyectos de acuerdo, realizar emplazamientos y notificaciones cuando lo ordene el órgano jurisdiccional;\nII. Dar cuenta diariamente al órgano jurisdiccional bajo su responsabilidad y dentro de las veinticuatro horas siguientes a su presentación ante la oficialía de partes del Tribunal Superior de Justicia, con todos los escritos y promociones, en los negocios de la competencia de aquellos, así como de los oficios y demás documentos que se reciban en él;\nIII. Autorizar y dar fe de los despachos, exhortos, actas, diligencias, autos y toda clase de resoluciones que se expidan, asienten, practiquen o dicten por el órgano jurisdiccional;\nIV. Asentar en los expedientes las certificaciones que procedan conforme a la ley o que el órgano jurisdiccional ordene;\nV. Asistir a las diligencias de pruebas que debe recibir el órgano jurisdiccional de acuerdo con las leyes aplicables;\nVI. Expedir las copias autorizadas que la ley determine o deban darse a las partes en virtud de decreto judicial;\nVII. Cuidar que los expedientes sean debidamente foliados, utilizando, para el efecto el equipo que permita imprimir de forma permanente dicho folio y el material aprobado por el Consejo de la Judicatura para la integración de los expedientes. Al agregar o sustraer alguna o algunas de\n\nlas hojas de éstos, asentar razón con motivo de la causa, sellando las actuaciones, oficios y demás documentos que lo requieran, rubricando aquéllas en el centro del escrito;\nVIII. Guardar en el secreto del órgano jurisdiccional los pliegos, escritos o documentos y valores cuando así lo disponga la ley;\nIX. Inventariar y conservar en su poder los expedientes mientras se encuentren en trámite en el órgano jurisdiccional y entregarlos con las formalidades legales, cuando deba tener lugar la remisión;\nX. Notificar en el local del órgano jurisdiccional, personalmente a las partes, en los juicios o asuntos que se ventilen ante él, en los términos del Código de Procedimientos Civiles vigente en la Ciudad de México;\nXI. Cuidar y vigilar que el archivo se arregle por orden alfabético, de apellidos del actor o del promovente en asuntos de jurisdicción voluntaria;\nXII. Remitir los expedientes al Archivo Judicial, a la superioridad o al substituto legal, previo registro en sus respectivos casos, conforme a los lineamientos marcados en esta ley.\nEn el caso de la remisión de expedientes, tocas, testimonios y constancias al Archivo Judicial, en aquellos casos en que se ordene su depuración, deberá certificar y entregar al Titular del órgano jurisdiccional, las copias de las constancias necesarias para que quede registro de la orden judicial.\nXIII. Ordenar y vigilar que se despachen sin demora los asuntos y correspondencia del órgano jurisdiccional, ya sea que se refiera a negocios judiciales del mismo o al desahogo de los oficios que se manden librar en las determinaciones respectivas, dictadas en los expedientes;\nXIV. Tener a su cargo, bajo su responsabilidad y debidamente autorizados para su uso, los libros de control del órgano jurisdiccional, designando, de entre los empleados subalternos del mismo, al que debe llevarlos;\nXV. Conservar en su poder el sello del órgano jurisdiccional;\n\nXVI. Ejercer bajo su responsabilidad, por sí mismo o por conducto de los servidores públicos de la administración de justicia subalterna, la vigilancia que sea necesaria en la oficina, para evitar la pérdida o extravío de expedientes. En cada Juzgado existirá una mesa que controlará su ubicación y distribución, que sólo se mostrarán mediante el vale de resguardo respectivo previa identificación oficial vigente, el cual será sellado a la devolución del expediente y entregado en la mesa de salida del Juzgado; y\nXVII. Las demás que les confieran las leyes y los reglamentos.\nArtículo 82. Las y los Secretarios de Acuerdos adscritos a los juzgados de justicia oral civil tendrán las obligaciones y atribuciones que establece esta Ley en los artículos 80 y 81, y además deberán formular los proyectos de resoluciones que se dicten en los juicios orales.\nArtículo 83. Las y los Secretarios adscritos a los Juzgados Penales y de Justicia para Adolescentes, tienen las obligaciones y atribuciones que establece esta ley en los artículos 80 y 81 en lo que sean compatibles, y además deberán:\nI. Practicar aseguramientos o cualquier otra diligencia que deba llevarse a cabo con arreglo a la\nLey o determinación judicial y ejecutar, en su caso, las decisiones del Juzgador en cuanto a la entrega de los bienes materia del delito que no competa hacerlo a autoridad diversa, y\nII. Revisar, en el caso de las personas Titulares de las Secretarías de Juzgados Penales, que se lleve a cabo la notificación de manera inmediata a los Agentes del Ministerio Público adscritos, al momento en que se dicten y previo a su ejecución, de los autos de libertad por falta de elementos para procesar y las sentencias absolutorias; y\nIII. Las demás que la Ley o las y los Jueces les encomienden, relativas a asuntos de la oficina.\nArtículo 84. Quienes ejerzan como conciliadores tendrán las atribuciones y obligaciones siguientes:\nI. Estar presentes en la audiencia de conciliación, escuchar las pretensiones de las partes y procurar de manera eficiente su avenencia;\nII. Dar cuenta de inmediato al titular del Juzgado del convenio al que hubieren llegado los interesados para efectos de su aprobación, en caso de que proceda, y diariamente informar al\nJuzgador de los resultados logrados en las audiencias de conciliación que se les encomienden;\n\nIII. Autorizar las diligencias en que intervengan y dar fe de las resoluciones pronunciadas en ellas por quien ostente la titularidad del órgano jurisdiccional;\nIV. Sustituir al Titular de la Secretaría de Acuerdos en sus ausencias temporales,\nV. Notificar en el Juzgado, personalmente a las partes, en los juicios o asuntos que se ventilen ante él, en los términos del Código de Procedimientos Civiles vigente en la Ciudad de México y para el caso de los Tribunales Laborales, conforme a lo establecido en la Ley Federal del Trabajo;\nVI. Auxiliar a la o al Secretario de Acuerdos a realizar aquellas certificaciones inherentes a la función de dichas personas servidoras públicas; las personas auxiliares de los Secretarios\nInstructores, actuarán de conformidad con la Ley Federal del Trabajo;\nVII. Preparar adecuada y eficientemente todo lo concerniente a la audiencia de conciliación y dar cuenta al Juzgador por lo menos con tres días de anticipación a la celebración de la misma; y\nVIII. Las demás que su superior jerárquico y esta Ley les encomienden, incluyendo emplazamientos y notificaciones.\nArtículo 85. Las personas Secretarias Actuarias estarán adscritas a cada Juzgado o Tribunal Laboral y tendrán las obligaciones siguientes:\nI. Concurrir diariamente al Juzgado de adscripción en el horario previsto;\nII. Recibir de la Secretaría de Acuerdos o de Instrucción, según sea el caso, los expedientes de notificaciones o diligencias que deban llevarse a cabo fuera de la oficina del propio Juzgado, firmando en el libro respectivo;\nIII. Hacer las notificaciones y practicar las diligencias decretadas por las y los Jueces, bajo la responsabilidad de la fe pública que les corresponda y dentro de las horas hábiles del día, entendiéndose por éstas las que median desde las siete hasta las diecinueve horas, devolviendo los expedientes dentro de las veinticuatro horas siguientes, previas las anotaciones en el libro respectivo. Durante las notificaciones y diligencias podrán llevar a cabo el procedimiento de mediación y, en su caso, redactar los acuerdos respectivos que hayan convenido las partes, en los términos de la Ley de la materia; y\n\nIV. En caso de existir imposibilidad para practicar las diligencias ordenadas, deberá asentar razón de ello y devolver las actuaciones dentro de las veinticuatro horas siguientes.\nLa o el Secretario Auxiliar Actuario de Sala tendrá las mismas obligaciones referidas en las fracciones anteriores.\nArtículo 86. Las y los Secretarios de Actuarios deberán llevar un libro debidamente autorizado para su uso, donde asienten diariamente las actuaciones y notificaciones que lleven a cabo con expresión de:\nI. La fecha en que reciben el expediente respectivo;\nII. La fecha del auto que deben diligenciar;\nIII. El lugar en que deben llevarse a cabo las diligencias, indicando la calle y número de la casa de que se trate;\nIV. La fecha en que haya practicado la diligencia, notificación o acto que deban ejecutar, o los motivos por los cuales no lo hayan hecho, y\nV. La fecha de devolución del expediente.\nArtículo 87. Son obligaciones de las y los Secretarios Proyectistas, de cuantía menor, primera instancia y segunda instancia, así como de las personas Secretarias de Acuerdos de Justicia Oral Civil:\nI. Elaborar proyectos de sentencia o resolución en el término señalado por su Titular que permita a este último su oportuna revisión, así como acatar de manera inmediata las instrucciones y observaciones hechas a sus proyectos.\nAl aprobarse éstos, éste asentará su firma en cada una de las fojas que integren la sentencia. De carecer la sentencia de dicha firma, se entenderá que la resolución se emitió sin la colaboración del proyectista.\nII. Guardar el debido secreto respecto de los asuntos que le son turnados para la elaboración del proyecto de sentencia o resolución;\n\nIII. En la elaboración de proyectos de sentencias o resoluciones, considerar las leyes y disposiciones vigentes aplicables según lo requiera el caso en estudio, atendiendo a las constancias de autos; y\nIV. Las demás que deriven de la ley.\nArtículo 88. Para los efectos de esta Ley, el Consejo de la Judicatura, con base en los estudios correspondientes determinará el número de Juzgados por las materias señaladas, en función de las cargas de trabajo que cada uno tenga que desahogar.\nLas y los Jueces podrán facultar a las y los pasantes de derecho que laboren en el juzgado respectivo, para practicar notificaciones personales a excepción del emplazamiento.\nCAPÍTULO III\nEL PROCESO ORAL EN MATERIA FAMILIAR\nArtículo 89. Las y los Jueces de Proceso Oral en materia Familiar, además, tendrán a su cargo, la etapa de conciliación durante la celebración de la audiencia preliminar, en los términos dispuestos en el Código de\nProcedimientos respectivo, Nacional o vigente en la Ciudad de México.\nArtículo 90. Las y los Jueces de Proceso Oral en materia Familiar podrán habilitar a las personas servidoras públicas adscritos a sus juzgados para que, cuando las necesidades del servicio así lo requieran, auxilien a la Central de Comunicaciones Procesales, dando constancia del cumplimiento de las órdenes de visitas para convivencia y entregas y regreso de menores.\nArtículo 91. Además de las aplicables para las y los Secretarios de Acuerdos y de las y los Secretarios\nAuxiliares, son obligaciones de las y los Secretarios Judiciales de Proceso Oral en materia Familiar:\nI. Dirigir la junta anticipada, en los términos dispuestos en el Código de Procedimientos Civiles vigente en la Ciudad de México;\nII. Asistir al Juzgador en la celebración de las audiencias orales, emitiendo las constancias y las actas respectivas, en términos del Código de Procedimientos Civiles vigente en la Ciudad de\nMéxico;\n\nIII. Hacer constar por escrito el medio en donde se encuentre registradas las audiencias identificando dicho medio con el número de expediente que corresponda;\nIV. Tramitar, previo pago de los derechos correspondientes, la expedición de copias, simples o certificadas, de las actas o medio electrónico de los registros que obren en el procedimiento, en los términos dispuestos en el Código de Procedimientos Civiles vigente en la Ciudad de México;\nV. Formular los proyectos de resolución que se dicten en los procesos orales en materia familiar;\nVI. Auxiliar al Juzgador en el control de la agenda de audiencias orales, y supervisar su oportuna preparación;\nVII. Dar aviso a la Central de Comunicaciones de las notificaciones practicadas por el personal del juzgado tanto en la sede jurisdiccional, como aquellas llevadas a cabo fuera de ésta por instrucción y habilitación expresa de la o el Juez, e n términos de lo dispuesto por la Ley;\nVIII. Certificar y dar constancia del cumplimiento de las partes en las órdenes de visitas para convivencia y entregas y regresos de menores, en los casos en que la o el Juez así lo ordene; y\nIX. Las demás que determine la normatividad aplicable y el Juzgador.\nArtículo 92. Las y los Secretarios Auxiliares de Juzgado de Proceso Oral en materia Familiar, asistirán a las o los Secretarios Judiciales en el desempeño de sus funciones y de las obligaciones consignadas en las fracciones II, V, VI, VII y XI del artículo 81, teniendo además, las siguientes obligaciones:\nI. Preparar los proyectos de acuerdo que recaigan en los asuntos de nuevo ingreso que sean turnados a la atención y trámite del Juzgado;\nII. Asistir al Secretario Judicial en la atención y trámite inmediato a los juicios de amparo interpuestos, elaborando los proyectos de informe que ordene la autoridad federal, así como en la integración y despacho de las constancias correspondientes;\nIII. Preparar los proyectos de acuerdo que recaigan a las promociones y solicitudes presentadas por los justiciables fuera de las audiencias orales;\n\nIV. Dar aviso a la o el Juez Secretario Secretaria Judicial de las notificaciones practicadas en la sede del juzgado tanto, como de aquellas llevadas a cabo fuera de ésta por instrucción y habilitación expresa del Juzgador, en términos del artículo 87 de esta Ley;\nV. Dar fe y constancia del cumplimiento de las partes en las órdenes de visitas para convivencia y entregas y regresos de menores, en los casos en que la o el Juez así lo ordene;\nVI. Cuidar y vigilar que el archivo se arregle por orden alfabético, de apellidos del actor o del promovente en asuntos de jurisdicción voluntaria; y\nVII. Las demás que determinen la o el Juez o la persona Secretaria y la normatividad aplicable.\nArtículo 93. Las comunicaciones procesales ordenadas por las Juezas o los Jueces de Proceso Oral en materia Familiar, y que en términos de ley deban realizarse de manera personal, serán practicadas por la\nCentral de Comunicaciones Procesales, por conducto de su plantilla de Oficiales Notificadores.\nLas personas que ostenten la función de Oficiales Notificadores estarán obligados a asistir diariamente a la\nCentral de Comunicaciones Procesales en el horario previsto, y tendrán bajo su responsabilidad:\nI. Recibir diariamente la asignación del turno de notificación que le corresponda, haciendo constar fecha y hora exacta de su recepción en el registro respectivo;\nII. Practicar las notificaciones personales que le sean asignadas, en los términos de las fracciones\nIII y IV del artículo 84 de esta Ley y de la demás normatividad aplicable;\nIII. Presentar las constancias de las diligencias de notificación realizadas a la Central de\nComunicaciones Procesales, haciendo constar la fecha y hora exacta de entrega recepción en la\nCentral, mediante el asiento del reloj checador;\nIV. Llevar el registro de las diligencias practicadas, cubriendo como mínimo los datos señalados en el artículo 85 de esta Ley;\nV. Realizar la entrega de oficios, exhortos, informes y demás documentos cuya tramitación sea ordenada por los jueces de proceso oral en materia familiar;\n\nVI. Rendir a la Central de Comunicaciones Procesales los informes que ésta le requiera, relativos a su gestión;\nVII. Certificar y dar constancia del cumplimiento de las partes en las órdenes de visitas para convivencia y entregas y regresos de menores, en los casos ordenados por la autoridad jurisdiccional, para lo cual todos los días y las horas se tendrán por hábiles; y\nVIII. La demás que determinen la Ley, el Consejo, el Titular de la Central de Comunicaciones, y la normatividad aplicable.\nQuedará inhabilitado para asumir el cargo de Oficial Notificador quien haya sido condenado por delito que amerite pena corporal de más de un año de prisión, y cualquiera que haya sido la pena en caso de que se trate de robo, fraude, falsificación, abuso de confianza u cualquier otro que lastime seriamente la buena fama en el concepto público. De igual forma quedará impedido en el caso de haber sido sancionado con inhabilitación administrativa por incurrir en responsabilidad durante el ejercicio del servicio público, sin importar la gravedad de la falta.\nArtículo 94. Para su mejor desempeño, la operación de los Juzgados de Proceso Oral en materia Familiar, estará asistida por las Unidades de Gestión Judicial, quienes tendrán una dependencia funcional de la\nPresidencia del Tribunal, cuya persona titular tendrá fe pública sobre asuntos de su competencia y tendrá las siguientes atribuciones:\nI. Las Unidades de Gestión Administrativa que, conforme a las cargas de trabajo y las necesidades del servicio, determine el Consejo, tendrán a su cargo:\na) El control, administración y supervisión de las Unidades de Apoyo Tecnológico y de la\nCentral de Comunicaciones Procesales;\nb) Elaborar los despachos, exhortos, actas, diligencias y toda clase de documento cuya emisión sea ordenada por los Jueces de Proceso Oral en materia Familiar, dentro de los asuntos a su cargo;\nc) Auxiliar a los Juzgados de Proceso Oral en materia Familiar en la digitalización de aquellos documentos, que por su volumen no puedan ser procesados en estos sin afectar su carga de trabajo;\n\nd) Auxiliar a los Juzgados de Proceso Oral en materia Familiar en el trámite y remisión de expedientes al Archivo Judicial, a la superioridad o al substituto legal, previo registro en sus respectivos casos, conforme a los lineamientos marcados en esta ley;\ne) Supervisar la adecuada, oportuna y eficientemente preparación de las salas de audiencia oral para llevar a cabo las audiencias programadas por los Juzgados de Proceso\nOral en materia Familiar;\nf) El control de agenda y asignación de las salas de audiencia oral;\ng) El trámite, administración y distribución de los insumos necesarios para la operación y el mantenimiento de los Juzgados de Proceso Oral en materia Familiar, y de las salas de audiencia oral; y h) Las demás que determinen la normatividad aplicable, el Consejo y/o el Titular de la\nOficialía Mayor.\nII. Una Central de Comunicaciones Procesales, bajo cuya responsabilidad estarán las siguientes actividades:\na) El control, evaluación y supervisión de los oficiales notificadores a su cargo;\nb) Coordinar y organizar equitativamente el turno de las notificaciones ordenadas por los\nJueces de Proceso Oral en materia Familiar, y que deban ser practicadas por los oficiales notificadores a su cargo;\nc) Recibir y registrar, verificando que se cumpla con los términos legales, las constancias de las notificaciones practicadas por los oficiales notificadores, turnándolas al Juzgado de\nProceso Oral en materia Familiar que corresponda;\nd) Diseñar y proponer al Consejo los mecanismos que hagan más eficiente el desarrollo de sus funciones; y e) Las demás que determine la normatividad aplicable, el Consejo y/o el Oficial Mayor;\n\nIII. Las Unidades de Apoyo Tecnológico que, conforme a las cargas de trabajo y las necesidades del servicio, determine el Consejo, estarán encargadas de:\na) La administración, control, operación y mantenimiento técnico de las Salas de\nAudiencia Oral;\nb) Preparar adecuada, oportuna y eficientemente las salas de audiencia oral para que se lleven a cabo las audiencias programadas por los Juzgados de Proceso Oral en materia\nFamiliar;\nc) El auxilio técnico inmediato de los Jueces de Proceso Oral en materia Familiar durante la celebración de las audiencias orales;\nd) El auxilio de los Jueces de Proceso Oral en materia Familiar en la obtención de los soportes electrónicos de las audiencias que se celebren, identificándolos plenamente con el asunto al que pertenecen;\ne) Emitir los respaldos y las copias de seguridad de los soportes electrónicos de las audiencias que se celebren, y entregarlos al Juzgador correspondiente para su debido resguardo;\nf) Emitir las copias de los soportes electrónicos de las audiencias que se celebren, y que le sean solicitadas por el Juzgado de Proceso Oral en materia Familiar que corresponda;\ng) Llevar el registro de los soportes electrónicos que se generen de las audiencias orales celebradas, identificados por juzgado, número de expediente, número consecutivo, fecha de emisión, y en su caso número de copias emitidas;\nh) Rendir a la Unidad de Gestión Judicial los informes que ésta le requiera;\ni) Diseñar y proponer al Director General de Gestión Judicial los mecanismos que hagan más eficiente el desarrollo de sus funciones; y j) La demás que determinen el Presidente del Tribunal y al Director General de Gestión\nJudicial.\n\nArtículo 95. Para ser titular de la Unidad de Supervisión de Medidas Cautelares y de la Suspensión\nCondicional del Proceso se requiere:\nI. Tener cuando menos treinta años cumplidos al día de la asignación.\nII. Contar con título y cédula legalmente expedidos por autoridad o institución legalmente facultada para ello, afín a las tareas de su encomienda, y\nIII. No haber sido condenado en sentencia ejecutoriada por delito doloso.\nArtículo 96. Para ser supervisor de medidas cautelares y de la suspensión condicional del proceso se requiere:\nI. Tener cuando menos veinticinco años cumplidos al día de la asignación.\nII. Contar con título y cédula universitarios legalmente expedidos por autoridad o institución legalmente facultada para ello afín a las tareas de su encomienda.\nIII. No haber sido condenado en sentencia ejecutoriada por delito doloso, y\nIV. Haber acreditado el examen de aptitud que elabore el Instituto de Estudios Judiciales.\nArtículo 97. La Unidad de Supervisión de Medidas Cautelares y de la Suspensión Condicional del Proceso ejercerá las atribuciones que confiere el Código Nacional de Procedimientos Penales, y tendrá, además, las siguientes:\nI. Entrevistar al imputado previamente a la realización de cualquier audiencia sobre medidas cautelares, para obtener información relevante para decidir sobre las medidas cautelares.\nAntes de empezar la entrevista, el funcionario encargado debe hacerle saber el objetivo de la entrevista, que tiene derecho a que su defensor esté presente durante la misma, que puede abstenerse de suministrar información y que aquélla que proporcione no podrá ser usada para demostrar su culpabilidad.\nLa entrevista se llevará a cabo con la presencia de la o del defensor público o privado; que deberá estar acreditado ante el órgano judicial respectivo.\n\nII. Verificar la información proporcionada por el imputado y recolectar aquella otra que sea relevante para decidir o modificar las medidas, de modo tal que éstas resulten adecuadas para que el imputado cumpla con sus obligaciones procesales.\nLa información deberá incluir datos sobre la historia personal del imputado, sus lazos con la comunidad, relaciones familiares, amistades, empleos, lugares de residencia, estudios, antecedentes penales, y cualquier otra información pertinente.\nIII. Elaborar reportes para las partes, denominadas opiniones técnicas, así como evaluaciones previas para el órgano jurisdiccional que contengan la información recabada en sus indagaciones, así como sus observaciones y recomendaciones sobre la necesidad y el tipo de medidas cautelares que sería necesario imponer al imputado para asegurar la protección e integridad de la víctima, de los testigos o de terceros; el desarrollo de la investigación o la comparecencia del imputado al proceso.\nEn caso de urgencia las evaluaciones previas podrán hacerse de manera verbal en una audiencia ante la o el Juez con la presencia de las partes. Cuando la publicidad afecte innecesariamente los derechos de la o el imputado, a solicitud de éste, la audiencia podrá celebrarse en privado, siempre que sea grabada y preservada en el registro, bajo reserva, hasta que no exista justificación para levantarla.\nIV. Entregar a las partes, al inicio de la audiencia en la que se discutan medidas cautelares, copias de los reportes relacionados con las mismas y recogerlos al término de la audiencia, y\nV. Las demás que determine la Ley o demás disposiciones aplicables.\nCAPÍTULO IV\nDE LA ORGANIZACIÓN INTERNA DE LOS ÓRGANOS JURISDICCIONALES\nDEL SISTEMA PENAL ACUSATORIO\nArtículo 98. Cada uno de los órganos jurisdiccionales del Sistema Penal Acusatorio a que se refiere este capítulo contará con el siguiente personal:\n\nI. Una o un Juez coordinador que será elegido por las y los Jueces que integren el Sistema Penal\nAcusatorio cada seis meses; que atenderán proporcional y equitativamente las cargas de trabajo con el objeto de lograr que se cumplan con los principios de publicidad, contradicción, concentración, continuidad e inmediación y aquellos previstos en la Constitución de los Estados\nUnidos Mexicanos, Tratados Internacionales y demás leyes, que son rectores del procedimiento penal acusatorio, que son necesarios para el conocimiento de los asuntos a su cargo.\nII. Las y los Auxiliares Judiciales que autorice el presupuesto y le proporcione la Dirección General de Unidad de Gestión Judicial; previa autorización de quien presida el Tribunal Superior de\nJusticia.\nIII. Las personas servidoras públicas de la Administración de Justicia que autorice el presupuesto y le proporcione la Dirección General de Unidad de Gestión Judicial; previa autorización de quien presida el Tribunal Superior de Justicia.\nArtículo 99. Son obligaciones de las y los Auxiliares Judiciales de los Jueces del Sistema Penal Acusatorio:\nI. Al legar de los instrumentos de conocimiento jurídico que sean necesarios para el razonamiento jurídico que deba realizar la o el Juez al momento de deliberar previo y dentro de la audiencia;\nII. Realizar la transcripción de las audiencias que se celebren y de las que hace mención el Código\nNacional de Procedimientos Penales, asentando su participación mediante firma en cada foja.\nAdemás de integrar las leyes y disposiciones vigentes aplicables según lo requiera el caso en estudio, atendiendo los términos señalados por su Titular;\nIII. Guardar el debido secreto en su colaboración en los escritos que se hacen mención en la fracción anterior; y\nIV. Las demás que deriven de la ley y los acuerdos para el efecto emita el Consejo de la Judicatura de la Ciudad de México.\n\nCAPÍTULO V\nDEL SISTEMA PENAL ACUSATORIO ORAL\nArtículo 100. La función jurisdiccional en materia penal, estará a cargo de:\nI. Jueces de Control;\nII. Tribunal de Enjuiciamiento;\nIII. Jueces de Ejecución; y\nIV. Tribunal de Alzada.\nLas y los Jueces del Sistema Penal Acusatorio elegirán de entre ellos, una Jueza o Juez coordinador, quien durará seis meses en su encargo.\nEl apoyo judicial para las y los Jueces del Sistema Penal Acusatorio se ejercerá a través de la Dirección\nGeneral de Gestión Judicial, por conducto de las Unidades de Gestión Judicial que la integran.\nArtículo 101. Las Unidades de Gestión Judicial tendrán la estructura que les autorice el Consejo de la\nJudicatura, de conformidad con su especialidad y funciones específicas. Contarán tanto con personal de carrera judicial como administrativo.\nArtículo 102. Los Juzgados de Control, Tribunal de Enjuiciamiento, Jueces de Ejecución y Tribunal de\nAlzada, conocerán de los asuntos respecto de los cuales el Código Nacional de Procedimientos Penales, esta Ley Orgánica y demás aplicables, les confieran competencias y atribuciones.\nLos asuntos les serán asignados en riguroso turno por parte del Órgano De Gestión Judicial y conforme a las reglas que al efecto emita el Consejo de la Judicatura, mismas que deberán garantizar objetividad, imparcialidad y equidad en los turnos, así como equilibrio en las cargas de trabajo entre los distintos juzgados.\nEl Tribunal de Enjuiciamiento se integrará y conocerá del juicio oral, de manera unitaria o colegiada. En este último supuesto, será en razón del criterio que se va a establecer o por otra circunstancia, según lo determine el juez a quien se le designe el asunto; y resolverán de manera unitaria en los demás casos.\n\nArtículo 103. El Tribunal de Alzada en el Sistema Procesal Acusatorio Oral conocerá:\nI. De los recursos de apelación que les correspondan y que se interpongan en contra de las resoluciones dictadas por las y los Jueces de Control, Tribunal de Enjuiciamiento y Juzgadores de Ejecución de la Ciudad de México;\nII. De las excusas y recusaciones de las y los Jueces de Control, Tribunal de Enjuiciamiento y\nJueces de Ejecución de la Ciudad de México;\nIII. Del conflicto competencial que eleven las y los Jueces de Control, Tribunal de Enjuiciamiento y Jueces de Ejecución de la Ciudad de México; y\nIV. De los demás asuntos que determinen las leyes.\nEl Tribunal de Alzada resolverá de manera colegiada, respecto a las sentencias dictadas por el Tribunal de\nEnjuiciamiento, en las que se haya impuesto pena de prisión mayor de cinco años o cuando alguna de las\nMagistradas o Magistrados lo determine en razón del precedente u otra circunstancia. En todos los demás casos, las resoluciones se dictarán en forma unitaria conforme al turno correspondiente.\nCAPÍTULO VI\nDE LA JUSTICIA CIVIL DE CUANTÍA MENOR, DEL PROCESO ORAL\nCIVIL Y PENAL\nArtículo 104. Se Deroga.\nArtículo 105. Las y los Jueces de lo Civil de Proceso Oral conocerán:\nI. De los juicios contenciosos que versen sobre la propiedad o demás derechos reales cuyo valor de la cosa sea inferior a la cantidad que el Código de Procedimientos Civiles vigente en la Ciudad de México establezca para que un juicio sea apelable, cantidad que se actualizará en términos de lo dispuesto por el artículo 691 del Código de Procedimientos Civiles vigente en la Ciudad de\nMéxico;\nII. De los juicios que versen sobre derechos personales de naturaleza civil, cuya suerte principal sea inferior a la cantidad que el Código de Procedimientos Civiles vigente en la Ciudad de México\n\nestablezca para que un juicio se apelable, cantidad que se actualizará en los términos en esta\nLey;\nIII. De los negocios de jurisdicción concurrente sin limitación de cuantía, previstos en el artículo\n1390 Bis del Código de Comercio;\nIV. De los medios preparatorios a juicio y de las providencias precautorias relacionados con los juicios que son de su competencia, en términos de las fracciones anteriores;\nV. De los asuntos de jurisdicción voluntaria, así como de la diligenciación de exhortos, rogatorias, suplicatorias, requisitorias y despachos, relacionados con los juicios orales en materia civil y mercantil;\nVI. De los juicios ejecutivos mercantiles orales cuya suerte principal sea igual o superior a las cantidades que establecen los artículos 1339 y 1340 del Código de Comercio establece para que un juicio sea apelable, y hasta cuatro millones de pesos 00/100 moneda nacional, sin tomar en cuenta los intereses y demás accesorios reclamados a la fecha de la interposición de la demanda, cantidad sujeta a la actualización a que se refiere el artículo 1253 fracción VI del citado Código, y\nVII. Los demás que establezcan las leyes.\nLos procedimientos de su competencia podrán tramitarse en línea o a través del uso de tecnologías de la información aprovechando el principio de equivalencia funcional del documento electrónico, conforme a los Lineamientos que al efecto emita el Consejo de la Judicatura.\nArtículo 106. Los Juzgados Penales de Delitos No Graves conocerán:\nI. De los delitos no graves así definidos por la ley penal;\nII. De la notificación que deberán realizar de manera inmediata a los Agentes del Ministerio\nPúblico adscritos, al momento en que se dicten y previo a su ejecución, de los autos de libertad por falta de elementos para procesar y las sentencias absolutorias; y\nIII. De la diligenciación de los exhortos y despacho de los demás asuntos que les encomienden las leyes.\n\nArtículo 107. Los Juzgados a que se refieren este Capítulo, para el despacho de los negocios, contarán con las personas servidoras públicas de la administración de justicia que fije el presupuesto.\nAsimismo, conforme a las disposiciones que emita el Consejo de la Judicatura y atendiendo a la disponibilidad presupuestal, para el apoyo de las funciones jurisdiccionales los Juzgados Civiles de Proceso\nOral, podrán contar con una Unidad de Gestión Judicial para Juzgados Orales Civiles, dependiente de la\nDirección General de Gestión Judicial, cuya persona titular contará con fe pública en la emisión de actos de su competencia.\nTÍTULO QUINTO\nDEL PROCEDIMIENTO PARA SUPLIR AUSENCIAS DE LAS PERSONAS\nSERVIDORAS PÚBLICAS DE LA ADMINISTRACIÓN DE JUSTICIA\nCAPÍTULO I\nDE LAS AUSENCIAS DE LAS MAGISTRADAS Y LOS MAGISTRADOS\nArtículo 108. Las ausencias temporales de las y los Magistrados del Tribunal Superior de Justicia, en las diversas funciones que las leyes les encomienden, se suplirán en los términos siguientes:\nI. Las de quien preside el Tribunal Superior de Justicia que no excedan de un mes, por la o el\nMagistrado que corresponda en orden de antigüedad de acuerdo a su designación; las que excedan de este tiempo, mediante designación especial que deberá hacerse por el Tribunal en Pleno;\nII. Las de quienes presidan las Salas que no excedan de un mes por el Magistrado de la misma\nSala que designen sus integrantes; y\nIII. Las ausencias de las y los Magistrados, cuando no excedan de un mes, por la o el Secretario de Acuerdos o en su caso por cualquiera de los Secretarios Proyectista de la Ponencia del Titular ausente. Cuando exceda de este tiempo y hasta por tres meses, por los Jueces de Primera\nInstancia de la materia, que serán nombrados por el Consejo de la Judicatura, prefiriendo en su caso al de mayor antigüedad en el cargo.\n\nArtículo 109. Las ausencias de los Titulares de las Magistraturas por más de tres meses, serán cubiertas mediante nombramiento previsto por la Constitución Política de los Estados Unidos Mexicanos y la\nConstitución, con la aprobación del Congreso.\nEntre tanto se hace la designación, la ausencia será suplida en términos de lo dispuesto en la fracción III del artículo anterior.\nArtículo 110. Si por defunción, renuncia o incapacidad faltare alguna Magistrada o Magistrado, el Consejo de la Judicatura en los términos de las disposiciones respectivas anteriores, someterá nuevo nombramiento a la aprobación del Congreso.\nEn todo caso y mientras se hace la designación, la ausencia será suplida en los términos ya previstos.\nCAPÍTULO II\nDE LAS Y LOS JUECES Y PERSONAS SERVIDORAS PÚBLICAS DE LA\nADMINISTRACIÓN DE JUSTICIA\nArtículo 111. Las y los Jueces serán suplidos en sus ausencias que no excedan de un mes, por la persona\nSecretaria de Acuerdos o de Instrucción, según corresponda, en los términos del artículo 80 de esta Ley.\nTratándose de las ausencias de Las y los Jueces de Proceso Oral en materia Familiar, éstas serán suplidas por la persona Secretaria Judicial que estos determinen.\nSi la ausencia excede de un mes, pero no de tres meses, el Consejo de la Judicatura nombrará una Jueza o\nJuez interino. Si estos tuviera que seguir desempeñando el cargo después de transcurridos los tres meses, deberá sujetarse a examen en términos del artículo 281 de esta Ley, y se tendrá en cuenta también su actitud durante el desempeño del servicio público.\nLos Titulares de las Secretarías, a su vez, serán suplidos por los Conciliadores o por testigos de asistencia;\nel superior jerárquico deberá nombrar de inmediato y de manera provisional a una persona que ocupe la Secretaría de Acuerdos que lo sustituya.\nLas personas titulares de las Secretarías, a su vez, serán suplidas por las y los Conciliadores o por testigos de asistencia; el superior jerárquico deberá nombrar de inmediato y de manera provisional a una persona que ocupe la Secretaría de Acuerdos o de Instrucción que le sustituya.\n\nLas ausencias temporales de los Titulares de las Secretarías de Acuerdos de Salas serán suplidas por cualquiera de las personas Secretarias Auxiliares que designe quien preside la Sala de que se trate.\nArtículo 112. En caso de ausencia definitiva de Juzgadores, el Consejo de la Judicatura deberá convocar, dentro de los siguientes cinco días hábiles, al concurso de oposición respectivo.\nArtículo 113. Los Titulares de las Secretarías del Tribunal en Pleno serán suplidos en sus ausencias temporales, el primero por el segundo y a falta de éste, por el que designe quien preside el Tribunal\nSuperior de Justicia. Si la ausencia fuere definitiva, se procederá a hacer nueva designación, de acuerdo con esta Ley.\nArtículo 114. Las ausencias de las demás personas servidoras públicas de la administración de justicia, se suplirán en la forma que determine el superior jerárquico, dentro de las prescripciones que señala esta Ley para la carrera judicial.\nArtículo 115. En todo caso y cuando las ausencias no excedan de quince días las personas servidoras públicas suplentes seguirán percibiendo los sueldos correspondientes a sus puestos de planta; cuando excedan de este término percibirán el sueldo correspondiente al puesto que desempeñen como substitutos.\nTÍTULO SEXTO\nDE LAS PERSONAS AUXILIARES DE LA ADMINISTRACIÓN DE JUSTICIA\nCAPÍTULO I\nDE LOS SÍNDICOS\nArtículo 116. Las personas que ejerzan el cargo de Síndicos desempeñan funciones públicas en la administración de justicia del fuero común, de la que debe considerárseles auxiliares. Quedan por lo tanto sujetos a las determinaciones de esta Ley, sin perjuicio de las demás disposiciones legales relativas.\nArtículo 117. Las personas nombradas Síndicos provisionales, como auxiliares de la administración de justicia, serán designadas por los Titulares de los Juzgados de Primera Instancia en los términos establecidos por la ley de la materia, entre las personas comprendidas en la lista que para tal efecto les sea enviada por el Consejo de la Judicatura. Los Síndicos definitivos nombrados con arreglo a la ley, quedarán\n\nsujetos a las disposiciones de ésta y de las demás leyes al igual que los síndicos provisionales, por lo que se refiere a sus facultades y obligaciones.\nArtículo 118. La lista a que se refiere el artículo anterior, será el resultado de una escrupulosa selección que el Consejo de la Judicatura llevará a cabo entre todos los aspirantes a las sindicaturas de que se trate. Al efecto, se formará una lista en la que figuren tanto candidatos propuestos por todas las asociaciones profesionales debidamente constituidas y reconocidas por el Consejo de la Judicatura, como los profesionistas que, sin estar asociados, reúnan los requisitos exigidos por esta Ley para ejercer las sindicaturas y cuya reputación y antecedentes de competencia y moralidad sean notorios.\nArtículo 119. Corresponde al Consejo de la Judicatura la selección de profesionales que deban formar la lista de personas acreditadas para ser Síndicos, pero en ningún caso ni por ningún motivo formarán parte de ella personas que no llenen estrictamente los requisitos exigidos por esta Ley.\nArtículo 120. El Consejo de la Judicatura dividirá la lista a que se refiere el artículo anterior, en proporción al número de Juzgados que deban hacer nombramientos de Síndicos. Las listas así formadas tendrán numeradas progresivamente a las personas en ellas comprendidas, deberán ser comunicadas a los Jueces oportunamente y publicadas en el Boletín Judicial.\nArtículo 121. Los Juzgados harán las designaciones de síndicos de la lista correspondiente, siguiendo precisamente el orden numérico establecido en ella, bajo el concepto de que no podrán nombrar a una misma persona para el desempeño de varias sindicaturas, sino después de haber agotado la lista en que aquélla figure y de que, por razón del orden en que deben hacerse las designaciones, le corresponda nuevamente el nombramiento de que se trate, salvo lo dispuesto en el artículo 123.\nArtículo 122. Para ocupar el cargo de Síndico se requiere:\nI. Tener la ciudadanía mexicana, en pleno goce de sus derechos políticos y civiles;\nII. Poseer el Titulo de Licenciatura en Derecho con cédula profesional expedida por la autoridad o institución legalmente facultada para ello y acreditar una práctica profesional, no menor de cinco años;\nIII. Gozar de buena reputación;\nIV. No encontrarse comprendido en el supuesto previsto por el artículo siguiente de esta Ley;\n\nV. No haber sido condenado por sentencia definitiva, por delito doloso que amerite pena privativa de libertad de más de un año de prisión, pero si se tratare de robo, fraude, falsificación, abuso de confianza u otro que lastime seriamente la buena fama en el concepto público, inhabilitará para el cargo cualquiera que haya sido la pena;\nVI. No haber sido removido de otra sindicatura, por falta o delitos cometidos en el ejercicio de sus funciones;\nVII. No tener interés personal de ningún tipo que pudiera afectar su función; y\nVIII. Tener domicilio en la Ciudad de México.\nArtículo 123. El Juzgador deberá cerciorarse de que la persona en cuyo favor pretenda hacer la designación no se encuentre desempeñando otra sindicatura, pero si por circunstancias especiales, consistentes en que en negocio distinto ya estuviere funcionando como Síndico y, no obstante, por el turno llevado en el Juzgado le correspondiere la designación, ésta podrá hacerse siempre y cuando en el primer negocio se hubiere llegado ya hasta la presentación y aprobación de los créditos de concurso.\nArtículo 124. La fianza que debe otorgar el Síndico para caucionar su manejo, deberá ser por cantidad determinada y bajo la responsabilidad del Juzgador; si no la otorgare, se tendrá por perdido su turno en la lista; dicha fianza deberá entregarse en un plazo máximo de quince días.\nArtículo 125. El Síndico tendrá derecho a ser relevado de la sindicatura por causa debidamente justificada que calificará el Juzgador, oyendo previamente, si fuera posible, a los acreedores.\nArtículo 126. El Síndico que no hubiere aceptado alguna sindicatura, perderá el turno en la lista respectiva.\nArtículo 127. Los Síndicos en ejercicio de sus funciones podrán, bajo su más estricta responsabilidad, asesorarse o consultar con profesionales de la Correduría, contaduría o cualquier otro profesionista afín a la función y que cuente con título legalmente expedido, a quienes se pagarán los honorarios que determine la ley de la materia.\nArtículo 128. El Síndico que faltare al cumplimiento de las obligaciones que le impone esta Ley, perderá la retribución que le corresponde por el ejercicio de su cargo, independientemente de quedar sujeto a las responsabilidades que procedan en su contra.\n\nArtículo 129. Los daños y perjuicios que se ocasionaren al concurso por culpa o negligencia del Síndico en el ejercicio de sus funciones, serán a cargo de éste en beneficio de los acreedores, procediéndose a retener la garantía que haya dado sin perjuicio de que se ejercite, por quienes corresponda, la acción o acciones procedentes a fin de asegurar debidamente los intereses del concurso, independientemente de la acción penal en que hubiere incurrido en fraude de acreedores. A este efecto, la garantía respectiva no será cancelada sino cuando hubiere concluido totalmente el procedimiento, aun cuando el Síndico hubiere renunciado o sido removido. Cuando hubiere habido dos o más síndicos, la garantía que cada uno hubiere otorgado responderá en su respectivo ejercicio.\nCAPÍTULO II\nDE LOS INTERVENTORES, ALBACEAS, TUTORES, CURADORES Y\nDEPOSITARIOS\nArtículo 130. Las personas nombradas como Interventores de concurso, al igual que los Síndicos, desempeñan una función pública en la administración de justicia del fuero común, en la que debe considerárseles también como auxiliares, quedando por lo tanto sujetos a las determinaciones de esta Ley, sin perjuicio de las demás disposiciones legales respectivas.\nArtículo 131. Los Interventores serán nombrados por los acreedores, en cualquier tiempo, por mayoría de votos y en los términos del Código de Procedimientos Civiles vigente para la Ciudad de México.\nArtículo 132. Las atribuciones del Interventor serán:\nI. Exigir mensualmente la presentación de las cuentas de administración del Síndico al Juzgador, dentro de los diez primeros días de cada mes, y\nII. Vigilar la conducta del Síndico, especialmente que se cumplan oportunamente todas las obligaciones y desempeñe todas las funciones que las leyes le imponen, dando cuenta inmediatamente de las irregularidades que notare y de todos los actos que pudieren afectar a los intereses o derechos de la masa.\nArtículo 133. Será causa de remoción del Interventor, el no ejercer la vigilancia necesaria en todos los casos que sean encomendados al Síndico, pudiendo cualquiera de los acreedores hacerlo del conocimiento del\nMinisterio Público para que, previa audiencia, se proceda como corresponda.\n\nArtículo 134. Asimismo, será causa de remoción del Interventor, no dar aviso oportuno al Juzgador dentro del plazo de cinco días, a partir de aquel en que haya tenido conocimiento de las faltas u omisiones en que hubiere incurrido el Síndico, sin perjuicio de las penas y responsabilidades a que se hubiere hecho acreedor.\nArtículo 135. Los que se desempeñen como Albaceas, Tutores, Curadores, Depositarios, así como\nInterventores diversos a los de concurso, ya sean provisionales o definitivos, designados por los\nJuzgadores, deberán llenar todos los requisitos establecidos en este título para los Síndicos, en aquello que sea compatible con su carácter y función.\nCAPÍTULO III\nDE LOS PERITOS\nArtículo 136. El peritaje de los asuntos judiciales que se presenten ante las autoridades comunes de la\nCiudad de México, es una función pública y en esa virtud los profesionales, los técnicos o prácticos en cualquier materia científica, arte u oficio que presten sus servicios a la administración pública, están obligados a cooperar con dichas autoridades, dictaminando en los asuntos relacionados con su encomienda.\nArtículo 137. Para ser Perito se requiere poseer la ciudadanía mexicana, gozar de buena reputación, tener domicilio en la Ciudad de México, así como conocer la ciencia, arte u oficio sobre el que vaya a versar el peritaje y acreditar su pericia mediante examen que presentará ante un jurado que designe el Consejo de la Judicatura, con la cooperación de instituciones públicas o privadas que a juicio del propio Consejo cuenten con la capacidad para ello. La decisión del jurado será irrecurrible.\nArtículo 138. Los peritajes que deban versar sobre materias relativas a profesiones, deberán encomendarse a personas autorizadas con título, que deberán satisfacer los requisitos señalados en el artículo anterior.\nLos peritos profesionales a que se refiere esta Ley, deberán provenir de la lista de peritos, que, en cada materia profesional, elaboran anualmente los colegios de profesionistas y estar colegiados de acuerdo con la Ley reglamentaria de la materia. Asimismo se considerarán las propuestas de Institutos de Investigación que reúnan tales requisitos.\n\nArtículo 139. Sólo en casos precisos, cuando no hubiere en la localidad de que se trate ciudadanos mexicanos suficientemente idóneos para el peritaje respectivo, podrá dispensarse el requisito de nacionalidad; pero las personas designadas, al protestar cumplir su cargo, deberán someterse expresamente a las leyes mexicanas para todos los efectos legales del peritaje que vayan a emitir.\nArtículo 140. Sólo en el caso de que no existiere lista de peritos en el arte o ciencia de que se trate, o que los enlistados estuvieren impedidos para ejercer el cargo, las autoridades podrán nombrarlos libremente, y se ocurrirá de preferencia a las instituciones públicas, poniendo el hecho en conocimiento del Consejo de la Judicatura para los efectos a que haya lugar.\nArtículo 141. Los honorarios de las y los Peritos designados por el Juzgador, la o el Magistrado serán cubiertos de acuerdo con el arancel que al efecto fije esta Ley, sin perjuicio de lo que disponga la sentencia definitiva respecto a la condenación en costas.\nTÍTULO SÉPTIMO\nDE LAS COSTAS Y DE LOS ARANCELES\nCAPÍTULO I\nDE LAS COSTAS\nArtículo 142. Las costas son la sanción impuesta en los términos de la ley a los litigantes que hayan actuado de mala fe, con falsedad o sin derecho, cuyo objeto es el pago de los gastos legales que el juicio implicó a la contraparte.\nArtículo 143. Las y los Jueces y las y los Magistrados al momento de dictar la sentencia que condene a costas determinarán el monto líquido de las mismas si ello fuese posible, de no serlo se determinará por vía incidental. En su caso, las partes deberán aportar los elementos necesarios para efectuar la liquidación correspondiente y en su defecto, el Juzgador la determinará con los elementos que se desprendan del propio expediente.\nLas partes siempre tendrán derecho al cobro de las costas establecidas en esta ley, cuando acrediten haber sido asesorados, durante el juicio, por persona titulada en Licenciatura en Derecho con cédula profesional expedida por la autoridad o institución legalmente facultada para ello.\n\nPara el efecto de la acreditación, estos registrarán su cédula profesional ante la Primera Secretaría de\nAcuerdos de la Presidencia y del Pleno del Tribunal Superior de Justicia, de conformidad con el acuerdo, que para tal efecto expida, el Consejo de la Judicatura. Debiendola Primera Secretaría de Acuerdos de la\nPresidencia y del Pleno del Tribunal Superior de Justicia proporcionar el número correspondiente para la acreditación ante cualquiera de los órganos jurisdiccionales del fuero común en la Ciudad de México.\nEn caso de que la parte favorecida con el resultado del juicio haya sido asesorada por terceros, podrá solicitar al Juzgador que las costas sean determinadas en la sentencia a favor del abogado o la institución que lo haya patrocinado.\nArtículo 144. Las costas en Primera Instancia se causarán conforme a las siguientes bases:\na) Cuando el monto del negocio no exceda del equivalente a tres mil veces la Unidad de Cuenta de la Ciudad de México vigente, se causará el 10%;\nb) Cuando el monto del negocio exceda del equivalente a tres mil veces la Unidad de Cuenta de la Ciudad de México vigente y sea hasta de seis mil veces la Unidad de Cuenta de la Ciudad de\nMéxico vigente, se causará el 8%; y c) Cuando el monto del negocio exceda del equivalente a seis mil veces la Unidad de Cuenta de la Ciudad de México vigente, se causará el 6%.\nSi el asunto tuviere que resolverse a través de una segunda instancia, las cuotas anteriores se aumentarán en 2%.\nArtículo 145. En los negocios de cuantía indeterminada se causarán las costas siguientes:\nI. Por el estudio del negocio para plantear la demanda, el equivalente a cien veces la Unidad de\nMedida y Actualización;\nII. Por el escrito de demanda, el equivalente a sesenta veces la Unidad de Medida y Actualización y por el estudio del negocio para su contestación el equivalente a cien veces la Unidad de Medida y Actualización;\nIII. Por el escrito de contestación a la demanda, el equivalente a sesenta veces la Unidad de\nMedida y Actualización;\n\nIV. Por la lectura de escritos o promociones presentados por el contrario, por foja, el equivalente a cinco veces la Unidad de Medida y Actualización;\nV. Por el escrito en que se promueva un incidente o recurso del que deba conocer el mismo\nJuzgador de los autos, o se evacue el traslado o vistas de promociones de la contraria, el equivalente a diez veces la Unidad de Medida y Actualización;\nVI. Por cada escrito proponiendo pruebas, el equivalente a veinte veces la Unidad de Medida y\nActualización;\nVII. Por cada interrogatorio de posiciones a la contraria, de preguntas o repreguntas a las o los testigos, o cuestionarios a los peritos, el equivalente a diez veces la Unidad de Medida y\nActualización por pliego, cuestionario o interrogatorio;\nVIII. Por la asistencia a juntas, audiencias o diligencias en el local del Juzgado o Sala, por cada hora o fracción, el equivalente a ocho veces la Unidad de Medida y Actualización;\nIX. Por la asistencia a cualquier diligencia fuera del juzgado o de la Sala, por cada hora o fracción, contada a partir de la salida del Juzgado, el equivalente a diez veces la Unidad de Medida y\nActualización;\nX. Por la notificación o vista de proveídos, el equivalente a cinco veces la Unidad de Medida y\nActualización;\nXI. Por notificación o vista de sentencia, el equivalente a ocho veces la Unidad de Medida y\nActualización;\nLas costas a que se refiere esta fracción y la anterior, se cobrarán sólo cuando conste en autos que el abogado fue notificado directamente por el actuario. En cualquier otro caso, por cada notificación se cobrará el equivalente a dos veces la Unidad de Medida y Actualización, siempre que la promoción posterior revele que el abogado tuvo conocimiento del proveído o sentencia relativos;\nXII. Por los alegatos en lo principal, según la importancia o dificultad del caso a juicio del\nJuzgador, el equivalente a seis y hasta doce veces la Unidad de Medida y Actualización, y\n\nXIII. Por el escrito de agravios o contestación de los mismos, el equivalente a cien veces la Unidad de Medida y Actualización.\nArtículo 146. Si en un juicio civil o mercantil hubiere condenación en costas y los escritos relativos no estuvieren firmados por abogado alguno, pero pudiere comprobarse plenamente la intervención de éste y sus gestiones en el negocio, la regulación de costas se hará de acuerdo con este arancel.\nArtículo 147. Las y los abogados que intervengan en juicios civiles o mercantiles por derecho propio, cobrarán las costas que fija el presente arancel, aun cuando no sean patrocinados por otro abogado.\nCAPÍTULO II\nDE LOS ARANCELES\nSección Primera\nDe quienes Ejerzan Como Interventores Y Albaceas Judiciales\nArtículo 148. En los juicios sucesorios, las y los interventores y albaceas judiciales cobrarán el 4% del importe de los bienes, si no exceden de ocho mil veces la Unidad de Cuenta de la Ciudad de México vigente, si exceden de esta suma, pero no del equivalente a veinticuatro mil veces la Unidad de Cuenta de la Ciudad de México vigente, cobrará además el 2% sobre el exceso; si excediere del equivalente a veinticuatro mil veces la Unidad de Medida y Actualización cobrará además el 1% sobre la cantidad excedente.\nSección Segunda\nDe las Personas Depositarias\nArtículo 149. Las personas depositarias de bienes muebles, además de los gastos de arrendamiento del local en donde se constituya el depósito, así como de la conservación que autoriza el Juzgador, cobrarán como honorarios hasta un 2% sobre el valor de los muebles depositados.\nArtículo 150. Las personas depositarias de semovientes cobrarán sus honorarios con arreglo al artículo anterior, además de los gastos de manutención y costo de arrendamiento del local necesario para el depósito.\n\nArtículo 151. En el caso de los dos artículos que anteceden, si se hiciere necesaria la venta de los bienes, los depositarios cobrarán además de dichos honorarios, del 2% al 5% sobre el producto líquido de ésta, si en ella hubieren intervenido.\nArtículo 152. Las personas depositarias de fincas urbanas cobrarán el 10% del importe bruto de los productos o rentas que se recauden. En caso de que la finca nada produzca, los honorarios se regularán conforme a lo dispuesto en el artículo 156 de esta Ley.\nArtículo 153. Las personas depositarias de fincas rústicas percibirán como honorarios los que señale el artículo 169 de la presente Ley más un 10% sobre las utilidades líquidas de la finca.\nArtículo 154. Cuando el secuestro recaiga sobre créditos, el depositario, además de los honorarios a que se refiere el artículo 149, cobrará el 5% sobre el importe de los réditos o pensiones que recaude.\nSección Tercera\nDe Las Personas Intérpretes Y Traductores\nArtículo 155. De las personas intérpretes y traductores podrán cobrar por honorarios, hasta un máximo de lo señalado en los casos siguientes:\nI. Por asistencia ante las autoridades judiciales para traducir declaraciones en lenguas indígenas o en idioma extranjero, el equivalente a cinco veces la Unidad de Medida y Actualización;\nII. Por traducción de cualquier documento, por hoja, el equivalente a dos veces la Unidad de\nMedida y Actualización; y\nIII. A los intérpretes de Lengua de Señas Mexicanas por cada hora o fracción, el equivalente a cinco veces la Unidad de Medida y Actualización.\n\nSección Cuarta\nDe Los Peritos\nArtículo 156. Las personas que lleven a cabo peritajes de las diferentes especialidades que prestan sus servicios como auxiliares de la administración de justicia, cobrarán conforme al arancel siguiente:\nI. En asuntos relacionados con valuación, el 2.5 al millar del valor de los bienes por valuar;\nII. En exámenes de grafoscopía, dactiloscopía y de cualquier otra técnica, veinte veces la Unidad de Medida y Actualización; y\nIII. En los negocios de cuantía indeterminada, los peritos cobrarán hasta doscientos cuarenta veces la Unidad de Medida y Actualización, cantidad que se determinará por el Juzgador, tomando en cuenta la naturaleza del negocio y la complejidad de la materia sobre la que verse el peritaje. Dicha cantidad se actualizará en términos de lo dispuesto por el último párrafo del artículo anterior.\nSección Quinta\nDel Arbitraje\nArtículo 157. Los árbitros necesarios o voluntarios, salvo convenio de las partes, cobrarán como únicos honorarios por conocer y decidir el juicio en que intervengan, hasta el 4% del valor del negocio.\nArtículo 158. Cuando quien lleve a cabo el arbitraje no llegue a pronunciar el laudo, por haberse avenido las partes, por recusación o por cualquier otro motivo, cobrará el 25% del porcentaje que se establece en el artículo que antecede y el 50% del mismo porcentaje, si hubiere recibido pruebas y el negocio estuviere en estado de resolución.\nArtículo 159. Cuando no pronuncien el laudo dentro del plazo obligado, no devengarán honorarios.\nArtículo 160. La persona que ejerza como Secretaria que sin ser árbitro, intervenga con este carácter en el juicio respectivo, devengará el 50% de los honorarios que le corresponderían si fuere árbitro.\nArtículo 161. Cuando no exista acuerdo respecto de las tarifas, devengarán hasta el 25% de la cuota señalada en el artículo 157 de esta Ley.\n\nArtículo 162. Las cuotas de la tarifa anterior rigen para el caso de que el árbitro sea único. Cuando sean dos o más, cada uno de ellos percibirá como honorarios el 50% del importe de las cuotas respectivas que señala la tarifa mencionada.\nArtículo 163. Los árbitros terceros, para el caso de discordia, devengarán el 75% del porcentaje señalado en el artículo 156 de la presente Ley.\nArtículo 164. En los negocios cuya cuantía sea indeterminada, el árbitro cobrará doscientos a quinientos veces la Unidad de Medida y Actualización.\nPara regular la cuota anterior, se atenderá a la importancia del negocio, a las dificultades técnicas que presente y a las posibilidades pecuniarias de las partes.\nTÍTULO OCTAVO\nDE LAS DEPENDENCIAS DEL TRIBUNAL SUPERIOR DE JUSTICIA DE LA\nCIUDAD DE MÉXICO\nCAPÍTULO I\nDEL ARCHIVO JUDICIAL DE LA CIUDAD DE MÉXICO Y DEL REGISTRO\nPÚBLICO DE AVISOS JUDICIALES\nArtículo 165. El Consejo de la Judicatura organizará y vigilará el correcto funcionamiento del Archivo\nJudicial, para que éste desarrolle cabalmente sus labores de auxiliar de los órganos judiciales de la Ciudad de México.\nArtículo 166. Se depositarán en el Archivo Judicial:\nI. Todos los expedientes, tocas y testimonios concluidos del orden civil y penal;\nII. Los expedientes del orden civil que, aun cuando no estén concluidos, hayan dejado de tramitarse por cualquier motivo durante seis meses;\n\nIII. Cualesquiera otros expedientes concluidos que conforme a la ley se integren por los órganos judiciales de la Ciudad de México y cuya remisión o entrega no haya de hacerse a oficina determinada o a los particulares interesados, respectivamente;\nIV. Los expedientes y documentos que remita el Consejo de la Judicatura, y\nV. Los demás documentos que las leyes determinen.\nEn todos los casos a que se refieren las fracciones anteriores, deberá atenderse al Reglamento de Archivos del Tribunal y del Consejo de la Judicatura, siendo facultad exclusiva del órgano jurisdiccional o de éste\nConsejo, según corresponda, determinar qué expedientes son susceptibles de depuración, en términos del\nReglamento respectivo, debiendo determinarlo así en aquél acuerdo que ordene su remisión al Archivo\nJudicial para tales efectos.\nEn aquellos casos en que el expediente haya de remitirse únicamente para su debido resguardo, no será necesario acuerdo alguno al respecto.\nAl devolver el Archivo Judicial un expediente para su radicación en el juzgado, el Titular del órgano jurisdiccional al dictar el primer auto que recaiga a esa remisión deberá hacer del conocimiento de las partes sobre la posibilidad de que una vez concluido en su totalidad el expediente, será destruido, previa digitalización del mismo.\nArtículo 167. Habrá en el archivo ocho secciones: civil, familiar, penal, administrativa, laboral y constitucional y del Consejo de la Judicatura, mismas que se dividirán de acuerdo con el reglamento respectivo.\nArtículo 168. Los órganos judiciales remitirán al Archivo los expedientes respectivos. Para su resguardo llevarán un registro computarizado en el cual harán constar, en forma de inventario, los expedientes que contenga cada remisión y al pie de este inventario pondrá quien ejerza la Jefatura de archivo, su recibo correspondiente.\nArtículo 169. Los expedientes y documentos entregados al Archivo serán anotados en un libro general de entradas y en otro que se llevará por orden alfabético y se le marcará con un sello especial de la oficina y arreglados convenientemente para que no sufran deterioros, y se clasificarán tomando en cuenta el departamento a que correspondan así como si se trata de expedientes para su posterior destrucción una vez fenecido el plazo de reserva señalado por la autoridad remitente, y se depositarán en la sección\n\nrespectiva, de lo cual se tomará razón en los libros que el reglamento determine, asentándose en ellos los datos necesarios para facilitar la busca de cualquier expediente o documento archivado.\nArtículo 170. Por ningún motivo se extraerá expediente alguno del Archivo Judicial, a no ser por orden escrita de la autoridad que lo haya remitido a la oficina, o de quien legalmente la substituya, insertando en el oficio relativo la determinación que motive el pedimento. La orden se colocará en el lugar que ocupa el expediente solicitado, y el conocimiento respectivo de salida de éste será suscrito por persona legalmente autorizada que la reciba.\nArtículo 171. La vista o examen de libros, documentos o expedientes del Archivo podrá permitirse en presencia del Titular de la Dirección o de las personas servidoras públicas de la oficina, y dentro de ella, a los interesados, a sus procuradores, o a cualquier abogado autorizado. Será motivo de responsabilidad para el Titular de la Dirección del Archivo, impedir el examen a que se refiere este artículo y la sanción respectiva será impuesta por el Consejo de la Judicatura.\nArtículo 172. No se permitirá por ningún motivo a las personas servidoras públicas del Archivo, extraer documentos o expedientes.\nArtículo 173. Cualquier irregularidad que advierta el Titular de la Dirección del Archivo en los expedientes o documentos que se le remitan para su depósito, lo comunicará de inmediato a la autoridad u órgano depositante, para que aclare o corrija la irregularidad, y en caso de presentarse nuevamente con dicha irregularidad, lo hará del conocimiento del Consejo de la Judicatura.\nArtículo 174. El Archivo Judicial estará a cargo de un Titular de la Dirección, que preferentemente deberá contar con Licenciatura en Derecho, que cuente además con conocimientos en archivonomía y del personal necesario para el desempeño de sus funciones de acuerdo al presupuesto.\nArtículo 175. El reglamento respectivo fijará las atribuciones de los servidores públicos del Archivo y determinará la división de las secciones, la forma de los asientos, índices y libros que en la misma oficina deban llevarse.\nPara el mejor funcionamiento del Archivo se implementará un sistema de digitalización de expedientes.\nEl Consejo de la Judicatura, en atención a la normatividad aplicable en materia de transparencia y acceso a la información pública; protección de datos personales, y archivos públicos, elaborará las disposiciones\n\nnecesarias para reglamentar los procedimientos para la conservación y destrucción de los acervos documentales con que cuente.\nNo podrán ser destruidos aquellos expedientes que no hubieren causado ejecutoria, o bien aquellos que derivados de alguna circunstancia que se advierta de las constancias que los integran, haga imposible su destrucción, a criterio del órgano jurisdiccional o del Consejo de la Judicatura, debiendo fundar y motivar esa determinación al remitir dicho expediente al Archivo Judicial.\nEl Titular de la Dirección del Archivo Judicial, bajo su más estricta responsabilidad, tendrá facultad para certificar las reproducciones electrónicas o impresas de aquellos archivos que se encuentren bajo su guarda y custodia, mismas que tendrán pleno valor probatorio.\nLa negativa injustificada por parte del órgano remitente para la destrucción de un expediente, será causa de responsabilidad administrativa, para lo cual el Titular de la Dirección del Archivo Judicial, dará el correspondiente aviso por escrito al Consejo de la Judicatura, a efecto de que en el ámbito de su competencia resuelva lo conducente.\nArtículo 176. El Archivo Judicial organizará y operará un servicio de bases de datos electrónicos que se denominará Registro Público de Avisos Judiciales, el cual se publicará y difundirá a través del sistema informático denominado Internet.\nEste servicio tendrá por objeto la inscripción de los avisos judiciales para efectos de publicidad. Cualquier interesado, previo pago de los derechos correspondientes, podrá inscribir o consultar la información del\nRegistro.\nLos avisos que se publiquen en el Registro Público de Avisos Judiciales, mientras permanezcan accesibles a cualquier usuario en la página de Internet correspondiente, por los mismos términos señalados en la leyes para la publicación de que se trate, surtirán los mismos efectos que los avisos publicados en los diarios de mayor circulación de la Ciudad de México, ello cuando el Juzgador lo considere pertinente y en adición a éstos.\nCualquier interesado, previo pago de los derechos correspondientes, podrá publicar los avisos judiciales que considere convenientes y consultar la base de datos correspondiente.\nSe llevará un registro histórico de los avisos publicados, para facilitar la investigación y consulta de los mismos.\n\nCAPÍTULO II\nDE LA DIRECCIÓN GENERAL DE LOS ANALES DE JURISPRUDENCIA Y\nBOLETÍN JUDICIAL\nArtículo 177. El Boletín Judicial se publicará por la Dirección General de los Anales de Jurisprudencia diariamente, con excepción de los sábados, domingos y días inhábiles.\nArtículo 178. La Dirección General de Anales de Jurisprudencia y Boletín Judicial, contará con un Titular de la Dirección General que deberá reunir los requisitos señalados en las fracciones I a V del artículo 22 de esta Ley.\nArtículo 179. En la Ciudad de México se publicará una revista que se denominará “Anales de\nJurisprudencia”, la que tendrá por objeto dar a conocer tanto estudios jurídicos, como los fallos más notables y precedentes que sobre cualquier materia pronuncie el Tribunal Superior de Justicia, en Pleno o\nSalas, misma que deberá publicarse de manera bimestral.\nEl Boletín Judicial contendrá los acuerdos, sentencias y avisos de todos los Juzgados y Salas, así como los avisos y acuerdos del Pleno y del Consejo, su publicación se hará todos los días laborables del Tribunal\nSuperior de Justicia.\nArtículo 180. En todo lo relativo a las publicaciones, el Consejo de la Judicatura administrará los ingresos que por ventas se recaben, haciendo las aplicaciones que estime pertinentes y cuyo producto se destinará exclusivamente para la ampliación y el mejoramiento de dichas publicaciones.\nArtículo 181. Los edictos, convocatorias y demás avisos judiciales que deban insertarse en el Boletín\nJudicial, se publicarán gratuitamente en negocios cuya cuantía no exceda de treinta veces la Unidad de\nCuenta de la Ciudad de México vigente.\nArtículo 182. Queda a cargo de la propia Dirección la publicación de las resoluciones que se dicten por el\nPleno del Tribunal en los casos a que se refiere la fracción III del artículo 37 de esta Ley, la Jurisprudencia y tesis sobresalientes de los Tribunales Federales entre Jueces y Magistrados, mediante la consulta respectiva que se haga del Semanario Judicial de la Federación.\n\nCAPÍTULO III\nDE LA UNIDAD DE TRABAJO SOCIAL, DEL SERVICIO DE INFORMÁTICA\nY BIBLIOTECA Y DEL CENTRO DE CONVIVENCIA FAMILIAR\nSUPERVISADA\nArtículo 183. El Tribunal Superior de Justicia, contará con una Unidad de Trabajo Social, cuyo principal objetivo será auxiliar a las Magistradas, Magistrados, Juezas, Jueces, al Centro de Convivencia Familiar\nSupervisada y al Instituto de Servicios Periciales y Ciencias Forenses, en los casos en que la Ley lo prevé.\nContará con una persona Jefa de Unidad y con el número de trabajadores sociales y el personal de apoyo administrativo necesario.\nArtículo 184. El Tribunal Superior de Justicia contará con un sistema de cómputo y red interna para las Salas y Juzgados, al que sólo tendrán acceso las y los Jueces y las y los Magistrados.\nDe igual forma, el Tribunal Superior de Justicia contará con un sistema de Internet de servicio al público, en los términos que establezca el Consejo de la Judicatura.\nAsimismo, contará con un servicio de Biblioteca, en los términos que establezca el Consejo de la Judicatura.\nAmbos servicios contarán con el personal especializado y administrativo que designe el Consejo de la\nJudicatura.\nArtículo 185. El Centro de Convivencia Familiar Supervisada es un órgano del Tribunal Superior de Justicia con autonomía técnica y operativa, que tiene por objeto facilitar la convivencia paterno–filial en aquellos casos que, a juicio de los Titulares de los Juzgados y Salas de lo Familiar, ésta no puede realizarse de manera libre o se ponga en riesgo el interés superior del menor.\nLos servicios del Centro de Convivencia Familiar Supervisada, se otorgarán de forma gratuita en sus instalaciones.\nEl Centro de Convivencia Familiar Supervisada será administrado y vigilado por el Consejo de la Judicatura, el cual expedirá las bases para su organización y funcionamiento.\nEl Centro de Convivencia Familiar Supervisada estará integrado por una estructura conformada por una\nDirección, dos Subdirecciones y el cuerpo de trabajadores sociales y psicólogos necesarios para el cumplimiento de sus funciones. Deberá igualmente, contar con los Secretarios Auxiliares que sean necesarios para dar fe.\n\nPara ser Titular de la Dirección del Centro de Convivencia Familiar deberá reunir los requisitos señalados por las fracciones I, II, IV y V del artículo 22 de esta Ley, además deberá poseer título con antigüedad de cinco años a nivel licenciatura en: Pedagogía, Psicología, Sociología, Trabajo Social o su equivalente, y acreditar la experiencia y capacidad indispensables para el desempeño del cargo.\nCAPÍTULO IV\nDE LA DIRECCIÓN GENERAL DE PROCEDIMIENTOS JUDICIALES\nArtículo 186.La Dirección General de Procedimientos Judiciales se compondrá por las siguientes áreas:\nI. Oficialía de Partes Común para Juzgados y Salas;\nII. Dirección de Consignaciones Civiles;\nIII. Dirección de Turno de Consignaciones Penales; y\nIV. Oficialía de Partes Común para los Juzgados.\nPara ser Titular de la Dirección General de Procedimientos Judiciales, se deberán satisfacer los requisitos que señala el artículo 22 de esta Ley, con excepción de lo establecido en las fracciones VI y VII.\nArtículo 187. Corresponde a la Oficialía de Partes Común para Juzgados y Salas que integran el Tribunal\nSuperior de Justicia:\nI. Asignar la Sala que corresponda para su conocimiento, en términos de estricto control, el turno para la resolución de recursos y de incompetencias, así como de los demás asuntos que deban conocer, el cual se realizará de manera equitativa a través del programa respectivo, mediante el sistema de cómputo aprobado por el Consejo de la Judicatura. Si con anterioridad una Sala ha conocido de un recurso o excepción de incompetencia, será la misma que deberá conocer de los recursos subsecuentes deducidos de los mismos autos;\nII. Recibir los escritos de término en materia constitucional, civil, familiar, laboral y de extinción de dominio que se presenten fuera del horario de labores de las Salas o Juzgados;\n\nIII. Turnar las demandas nuevas a los diversos juzgados en las ramas civil, familiar, laboral y de extinción de dominio, así como de los demás asuntos que deban conocer, cuya tramitación no este reservada por esta Ley a diversa área administrativa para turnarlo, el cual se realizará de manera equitativa a través del programa respectivo, mediante el sistema de cómputo aprobado por el Consejo de la Judicatura;\nIV. Realizar los cambios correspondientes en su base de datos, cuando le sea indicada alguna corrección en el nombre de los interesados o de las partes, por los órganos jurisdiccionales competentes para ello e informar lo realizado, oportunamente a la autoridad correspondiente que haya indicado el cambio;\nV. Las demás que deriven de esta Ley y las que resultan aplicables.\nLa Oficialía de Partes estará a cargo de una Directora o Director, que deberá satisfacer los requisitos establecidos por las fracciones I a V del artículo 22 de esta Ley; salvo en la antigüedad del Título, que será de cinco años.\nLa Oficialía permanecerá abierta durante las horas hábiles que establezca el Código de Procedimientos\nCiviles vigente en la Ciudad de México.\nCAPÍTULO V\nDE LA DIRECCIÓN DE CONSIGNACIONES CIVILES Y DE LA OFICIALÍA\nDE PARTES COMÚN PARA LOS JUZGADOS\nArtículo 188.La Dirección de Consignaciones Civiles tendrá competencia para conocer de las diligencias preliminares de consignación.\nLa Consignación de dinero deberá hacerse exhibiendo billete de depósito, expedido por institución legalmente facultada para ello.\nLa Dirección de Consignaciones Civiles notificará personalmente de manera fehaciente a la consignataria o consignatario la existencia del billete de depósito a su favor, para que éste, dentro del término de un año, acuda ante la misma, la que previa identificación y recibo hará la entrega correspondiente.\n\nEn caso de oposición o de no presentarse la consignataria o consignatario, a petición del interesado se expedirá la constancia resultante.\nEsta Dirección estará a cargo de una persona Directora, que deberá satisfacer los requisitos que se establecen en las fracciones I a IV y VI del artículo 22 de esta Ley.\nArtículo 189. Para los Juzgados del Ramo Civil, de Extinción de Dominio y Familiares, se contará con una\nOficialía de Partes Común, que estará a cargo de un Titular de la Dirección, el que deberá reunir los requisitos que se señalan en las fracciones I a IV y VI del artículo 22 de esta Ley.\nCAPÍTULO VI\nDE LA DIRECCIÓN DE TURNO DE CONSIGNACIONES PENALES Y DE\nJUSTICIA PARA ADOLESCENTES\nArtículo 190. Corresponde a la Dirección de Turno de Consignaciones Penales y de Justicia para\nAdolescentes, recibir diariamente las consignaciones que remita la Procuraduría General de Justicia de la\nCiudad de México para su distribución a los Jueces Penales y los pliegos de actos antisociales para su distribución a los de Justicia para Adolescentes, según su competencia que se llevará a cabo conforme a las reglas que para el efecto expida el Consejo de la Judicatura.\nArtículo 191.La Dirección de Turno de Consignaciones Penales estará integrada por un titular director y el personal administrativo suficiente para su buen funcionamiento.\nArtículo 192. Quien ejerza la Titularidad de la Dirección deberá reunir los requisitos señalados en el artículo\n22 de esta Ley.\nArtículo 193.La Dirección estará en servicio en los días y horarios que señalen las reglas de turno de los jueces penales.\nCAPÍTULO VII\nDE LA DIRECCIÓN JURÍDICA\nArtículo 194. Corresponde a la Dirección Jurídica asesorar y desahogar consultas a los órganos, dependencias y unidades administrativas del Tribunal Superior de Justicia y del Consejo de la Judicatura.\n\nAdemás, serán de su competencia los asuntos contenciosos laborales en donde el Tribunal Superior de\nJusticia o el Consejo de la Judicatura, o alguno de sus integrantes, por razón de su encargo sean parte.\nLa Dirección Jurídica contará con una persona Titular de la Dirección y las demás personas servidoras públicas que requiera para el desarrollo de sus funciones, el cual deberá cumplir con los requisitos establecidos en el artículo 22 de esta Ley, con la salvedad de lo indicado en las fracciones VI y VII.\nCAPÍTULO VIII\nLA COORDINACIÓN DE RELACIONES INSTITUCIONALES\nArtículo 195. Corresponde a la Coordinación de Relaciones Institucionales, establecer vínculos de colaboración con los Poderes Ejecutivo y Legislativo y demás Instituciones de la Ciudad de México, que por sus características hagan necesaria la interacción con éstos y el Tribunal Superior de Justicia.\nLa Coordinación de Relaciones Institucionales contará con un Coordinador y los demás servidores públicos indispensables que se requieran para el desarrollo de sus funciones.\nLa persona Titular de la Coordinación de Relaciones Institucionales deberá cumplir con los requisitos del artículo 22 de esta Ley, con excepción de lo establecido por las fracciones VI y VII, además deberá contar con los conocimientos necesarios en las áreas administrativa y legislativa.\nCAPÍTULO IX\nDE LA DIRECCIÓN DE ORIENTACIÓN CIUDADANA Y DERECHOS\nHUMANOS\nArtículo 196. Corresponde a la Dirección de Orientación Ciudadana y Derechos Humanos informar y atender a quienes solicitan los servicios que presta el Tribunal Superior de Justicia.\nAsimismo, le corresponde coordinar las acciones de seguimiento, gestión, concertación y conciliación necesarias para dar una atención eficaz, pronta y expedita a las quejas presentadas contra personas servidoras públicas del Tribunal Superior de Justicia y del Consejo de la Judicatura.\n\nTambién le corresponde promover, difundir y fomentar los Programas referentes a la impartición de la justicia y de protección de los Derechos Humanos, así como servir de enlace con la Comisión de Derechos\nHumanos de la Ciudad de México y la Comisión Nacional de Derechos Humanos, para verificar el cumplimiento de los requerimientos y recomendaciones que emitan dichas instituciones.\nLa Dirección de Orientación Ciudadana y Derechos Humanos contará con un Director y los servidores públicos indispensables que se requieran para el desarrollo de sus funciones.\nLa o el Director deberá cumplir con los requisitos del artículo 22 de esta Ley, salvo lo establecido en la fracción V.\nCAPÍTULO X\nDE LA COORDINACIÓN DE COMUNICACIÓN SOCIAL\nArtículo 197. Corresponde a la Coordinación de Comunicación Social recabar y difundir la información generada por las diversas áreas del Tribunal Superior de Justicia y el Consejo de la Judicatura, así como llevar un seguimiento de las noticias que se divulguen tanto en medios impresos como electrónicos, contará con el personal indispensable para el desarrollo de sus actividades.\nPara ser Coordinadora o Coordinador de Comunicación Social del Tribunal Superior de Justicia, se requiere:\nI. Poseer la nacionalidad mexicana;\nII. Tener cuando menos treinta años de edad cumplidos el día de la designación;\nIII. Contar con experiencia mínima de cinco años y la capacidad indispensables para el desempeño del cargo; y\nIV. Gozar de buena reputación y no haber sido condenado por delito que amerite pena privativa de libertad de más de un año de prisión, pero si se tratare de robo, fraude, falsificación, abuso de confianza u otro que lastime seriamente la buena fama en el concepto público, inhabilitará para el cargo cualquiera que haya sido la pena.\n\nCAPÍTULO XI\nDEL CENTRO DE JUSTICIA ALTERNATIVA\nArtículo 198. El Centro de Justicia Alternativa formará parte del Poder Judicial de la Ciudad de México, mismo que se instituye para administrar y substanciar los medios alternos de solución de controversias, como la mediación, la conciliación, el arbitraje y aquellos señalados en la Ley de Justicia Alternativa del\nPoder Judicial de la Ciudad de México, para la atención de los conflictos de naturaleza civil, mercantil, familiar o penal, entre particulares, así como para su desarrollo.\nEstos medios alternativos de solución de controversias son parte fundamental y privilegiada del sistema integral de justicia de la Ciudad de México.\nArtículo 199. El Centro de Justicia Alternativa tendrá las siguientes atribuciones y facultades:\nI. El desarrollo y la administración eficaz y eficiente de los medios alternos de solución de controversias, principalmente de la mediación;\nII. Actuar como órgano especializado en la aplicación de los mecanismos alternativos de solución de controversias en materia penal;\nIII. Facilitar el desarrollo y la administración eficaz y eficiente de la Justicia Alternativa a través de los medios alternos de solución de controversias en controversias civiles, mercantiles, familiares, penales cuando se trate de delitos no graves y de justicia para adolescentes y las demás reconocidas por la ley;\nIV. Mediar en controversias vinculadas con el régimen de condominios;\nV. Coordinar con las instancias de acción comunitaria establecidas por la ley para la mediación y resolución de conflictos vecinales, comunitarios, de barrios y pueblos;\nVI. La prestación de los servicios de información al público, sobre los medios alternativos de solución de controversias así como de orientación jurídica, psicológica y social a los mediados, durante su substanciación;\nVII. La capacitación, certificación, selección, registro y monitoreo de los facilitadores y de los mediadores para el servicio público y privado; a efecto de garantizar altos índices de competencia\n\nprofesional; así como la capacitación de mediadores y desarrollo de proyectos de mediación en apoyo a instituciones públicas y privadas, para la solución de controversias en todos los ámbitos de interacción social, tales como mediación escolar y comunitaria, entre otras;\nVIII. La difusión y divulgación permanente de los servicios que presta;\nIX. El fortalecimiento de sus funciones y la ampliación de sus metas, a partir de su experiencia y del intercambio permanente con instituciones públicas, privadas, nacionales y extranjeras;\nX. La supervisión constante de los servicios a cargo de las o los Mediadores y Facilitadores y del funcionamiento de los módulos de mediación, su retroalimentación oportuna, para mantenerlos dentro de niveles superiores de calidad, así como el registro de los convenios de mediación y de la base de datos de asuntos atendidos en materia penal;\nXI. El apoyo al trabajo jurisdiccional del Tribunal;\nXII. El diseño y actualización de su normatividad interna, que será aprobada por el Presidente del\nTribunal Superior de Justicia;\nXIII. La optimización de sus servicios a través de la aplicación de programas estratégicos de investigación, planeación y modernización científica y tecnológica;\nXIV. Operar como órgano especializado de la justicia para adolescentes; y\nXV. Cumplir con las disposiciones legales aplicables, así como con las que le atribuya expresamente esta Ley, sus disposiciones reglamentarias y los acuerdos que emita Presidente del Tribunal Superior de Justicia.\nArtículo 200. El Centro contará con una Dirección General, del cual partirá la estructura necesaria del mismo, para el desarrollo eficaz y eficiente de sus funciones, así como con una planta de mediadores especializados y el personal técnico y administrativo que para ello requiera.\nEl Consejo de la Judicatura, a propuesta de la o el Presidente designará a la persona titular del Centro de\nJusticia Alternativa.\n\nArtículo 201. La o el Titular de la Dirección General será designado por el Consejo, para un periodo de seis años, sin posibilidad de reelección. En su persona se reunirán una formación y experiencia multidisciplinarias en Derecho, Psicología, Sociología, Mediación u otras áreas del conocimiento aplicables a los mecanismos alternativos de solución de controversias.\nDurante el ejercicio de su encargo, el Titular de la Dirección General sólo podrá ser removido por la comisión de delitos dolosos o por actualizarse en su persona alguna de los supuestos siguientes:\nI. El incumplimiento de sus atribuciones o negligencia en el desempeño de las mismas;\nII. Padecer alguna incapacidad durante más de seis meses, que impida el correcto ejercicio de sus funciones;\nIII. El desempeño de algún empleo, cargo o comisión distinto a los no remunerados de carácter docente o en instituciones de asistencia social, públicas o privadas;\nIV. Dejar de ser ciudadano mexicano o dejar de cumplir alguno de los requisitos para ejercer el cargo;\nV. No cumplir los acuerdos de la Presidencia del Tribunal Superior de Justicia o actuar deliberadamente de manera grave en exceso o defecto de sus atribuciones;\nVI. Divulgar o utilizar en beneficio propio o de terceros la información confidencial de que disponga en razón de su cargo;\nVII. Someter a la consideración del Consejo información falsa teniendo conocimiento de ello; y\nVIII. Ausentarse de sus labores por más de tres días hábiles consecutivos sin la autorización de quien presida la Presidencia del Tribunal Superior de Justicia, o sin mediar causa de fuerza mayor o motivo justificado.\nArtículo 202. Para ser Directora o Director del Centro de Justicia Alternativa se deberán reunir los requisitos siguientes:\nI. Tener la ciudadanía mexicana en pleno goce y ejercicio de sus derechos civiles y políticos;\n\nII. Tener por lo menos treinta años de edad, cumplidos al día de la designación;\nIII. Tener título y cédula profesionales de estudios de licenciatura en Derecho, Psicología,\nSociología, Mediación u otras áreas del conocimiento aplicables a la función sustantiva del\nCentro;\nIV. Tener práctica profesional mínima de cinco años, contados a partir de la fecha de expedición del título profesional;\nV. Haber residido en la Ciudad de México durante el último año anterior al día de la designación;\nVI. Gozar de buena reputación;\nVII. No haber sido sentenciado, mediante sentencia condenatoria ejecutoriada, por un delito doloso o inhabilitado; y\nVIII. Acreditar con al menos 75%, las evaluaciones que para el efecto prepare y aplique el Instituto de Estudios Judiciales.\nArtículo 203. El Titular de la Dirección General, los que ejerzan en las Direcciones y Subdirecciones de\nMediación del Centro de Justicia Alternativa del Tribunal Superior de Justicia, estarán facultados para expedir copias certificadas de los documentos que obren en los archivos del mismo, y para efectuar los registros e inscripciones que previene la legislación correspondiente.\nCAPÍTULO XII\nDE LOS SERVICIOS DE MEDIACIÓN, CONCILIACIÓN Y ARBITRAJES\nPRIVADOS\nArtículo 204. Los servicios de mediación, conciliación y arbitraje a cargo de personas que ejerzan como privados certificados y registrados por el Poder Judicial de la Ciudad de México en los términos de la Ley de Justicia Alternativa del Poder Judicial de la Ciudad de México, representan una función pública complementaria a la administración de justicia que corresponden a la figura de descentralización por colaboración, por lo que sus actividades son supervisadas y monitoreadas por el Centro de Justicia\nAlternativa a efecto de garantizar altos índices de competencia profesional.\n\nArtículo 205. Para ocupar el cargo de mediador, conciliador o árbitro privado se requiere:\nI. Tener la ciudadanía mexicana en pleno ejercicio de sus derechos civiles y políticos y tener cuando menos veinticinco años de edad al día de su certificación y registro;\nII. Poseer grado de licenciatura, así como dos años de experiencia profesional mínima demostrable;\nIII. Gozar de buena reputación profesional y reconocida honorabilidad;\nIV. No haber sido sentenciado, mediante sentencia condenatoria ejecutoriada, por delito doloso que merezca pena privativa de libertad;\nV. Presentar y aprobar el examen de conocimientos de competencias laborales;\nVI. Aprobar los cursos de capacitación para la certificación y registro; y\nVII. Realizar las horas de práctica en el Centro que fijen las Reglas.\nLa persona que haya obtenido la certificación y el registro para ejercer como mediador, conciliador y árbitro privado, previamente al inicio de sus funciones y dentro de los noventa días siguientes a la expedición de su constancia de certificación deberá cumplir con los requisitos previstos en la Ley de Justicia Alternativa del Poder Judicial de la Ciudad de México.\nArtículo 206. Sin perjuicio de las responsabilidades legales en que pudiera incurrir el mediador, conciliador y árbitro privado en el ejercicio de su función, queda sometido al régimen disciplinario y procedimiento previsto en la Ley de Justicia de Alternativa del Poder Judicial de la Ciudad de México y las demás disposiciones aplicables.\nArtículo 207. Los honorarios de los mediadores, conciliadores y árbitros privados que atiendan los casos que les remita algún Juzgador, en los términos de la Ley de Justicia Alternativa del Poder Judicial de la\nCiudad de México, serán cubiertos por las partes, conforme lo establezcan las disposiciones aplicables.\n\nTÍTULO NOVENO\nDEL CONSEJO DE LA JUDICATURA DE LA CIUDAD DE MÉXICO\nCAPÍTULO I\nDENOMINACIÓN, OBJETO, INTEGRACIÓN Y FUNCIONAMIENTO\nArtículo 208. El Consejo de la Judicatura de la Ciudad de México, es un órgano del Poder Judicial de la\nCiudad de México dotado de autonomía, independencia técnica y de gestión para realizar sus funciones;\nestará encargado de la administración, vigilancia, evaluación, disciplina y servicio de carrera del Tribunal\nSuperior de Justicia, de los Juzgados, demás órganos judiciales y desconcentrados, en los términos que esta Ley establece. Sus resoluciones serán definitivas e inatacables.\nArtículo 209.- El Consejo de la Judicatura se integra por quien preside el Tribunal y seis personas\nConsejeras, que serán una persona Magistrada y dos Juezas o Jueces elegidos por al menos, las dos terceras partes del Pleno del Tribunal en votación; asimismo, dos Consejeras o Consejeros electos por el\nCongreso de la Ciudad de México, y una designada por la persona titular de la Jefatura de Gobierno de la\nCiudad de México. La designación de las tres últimas personas Consejeras que refiere el párrafo anterior, deberá recaer en personas que se hayan distinguido por su capacidad, honestidad y honorabilidad en el ejercicio de las actividades jurídicas y administrativas.\nI. Será competente en la adscripción y remoción de las y los Jueces y de las y los Magistrados, sin perjuicio de la facultad del Pleno del Tribunal Superior de Justicia de revocar o modificar los acuerdos que al efecto emita el Consejo de la Judicatura, en los términos que señala esta Ley;\nII. Velará por los derechos humanos laborales de las personas servidoras públicas para nombrar y remover al personal administrativo;\nIII. Nombrará y removerá al personal administrativo del Poder Judicial respetando el servicio civil de carrera, a propuesta de las y los titulares de los órganos; y en la aplicación de las normas que regulan las relaciones de trabajo de las personas servidoras públicas y los poderes de la Ciudad, así como las demás facultades que la ley señale; y\nIV. Tendrá las demás facultades que la Constitución Local y la presente Ley establezcan.\n\nArtículo 210. Salvo quien presida el Consejo de la Judicatura, el resto de sus integrantes durarán seis años en el cargo y no podrán ser nombrados para un nuevo período, ni sucesiva ni alternadamente, con independencia de la forma en que hayan sido electos.\nEn caso de ausencia definitiva de algún integrante, según corresponda, el Pleno del Tribunal Superior de\nJusticia o el Congreso de la Ciudad de México, deberán iniciar el proceso de elección de la persona que ocupará dicho encargo por el periodo restante, en un plazo no mayor a treinta días naturales desde que se produjo la vacante, y en su caso, la o el Jefe de Gobierno de la Ciudad de México deberá hacer la designación correspondiente. Las y los Consejeros serán sustituidos conforme se produzcan las vacantes una vez concluido el periodo para el cual fueron designados.\nQuien presida el Tribunal Superior de Justicia también presidirá el Consejo de la Judicatura por el tiempo que dure su encargo, y será sustituido de este conforme lo sea en la Presidencia del Tribunal.\nArtículo 211. Las y los Consejeros de la Judicatura ejercerán su función con independencia e imparcialidad.\nLas sesiones del Consejo de la Judicatura serán públicas, salvo lo dispuesto en la normatividad aplicable.\nLos actos y decisiones del Consejo de la Judicatura, en ningún caso, podrán modificar las resoluciones o invadir la función jurisdiccional depositada en los órganos del Tribunal Superior de Justicia, ni podrán afectar las resoluciones de las y los Jueces ni de las y los Magistrados.\nArtículo 212. El Consejo de la Judicatura seguirá los principios de legalidad y honradez, accesibilidad, transparencia, máxima publicidad y rendición de cuentas, previstos en la Constitución y en la presente Ley.\nContará por lo menos con dos Comisiones que serán:\na) Comisión de Disciplina Judicial; y b) Comisión de Administración y Presupuesto.\nArtículo 213. Las y los integrantes del Consejo estarán sujetos a las mismas responsabilidades en el ejercicio de su función que los del Tribunal Superior de Justicia y la Sala Constitucional; y salvo quien lo presida, serán sustituidos escalonadamente, conforme se produzcan las vacantes una vez concluido el periodo para el cual se les hubiere designado; la persona que presida el Consejo será sustituida conforme lo sea en la Presidencia del Tribunal. Recibirán los mismos emolumentos que las y los Magistrados.\n\nLos integrantes del Consejo sólo podrán ser removidos en los términos del Título Cuarto de la Constitución\nPolítica de los Estados Unidos Mexicanos y la Constitución.\nArtículo 214. Las Consejeras y Consejeros no podrán mientras estén en el cargo, cuando hayan sido separados del mismo por sanción disciplinaria o dentro de los dos años siguientes a la fecha de su retiro, actuar como patronos, abogados o representantes en cualquier proceso ante los órganos judiciales de la\nCiudad de México. No podrán ser Consejeras o Consejeros las personas que hayan ocupado la Jefatura de\nGobierno de la Ciudad de México, la Secretaría General, la Titularidad de la Fiscalía General de Justicia, o cargo de elección popular local, durante el año previo al día de la designación.\nArtículo 215. Las y los Consejeros de la Judicatura se abstendrán de intervenir de cualquier manera en los asuntos a cargo del Tribunal Superior de Justicia, de la Sala Constitucional, del Tribunal Electoral y de los\nJuzgados.\nArtículo 216. Para el cumplimiento de sus funciones, el Consejo de la Judicatura expedirá su propio reglamento interior, tomando en consideración las bases siguientes:\nI. Sesionar en Pleno cuando menos una vez cada quince días, y cuantas veces sea convocado por quien lo presida. Las sesiones las presidirá la o el Presidente del Consejo de la Judicatura y podrán ser públicas o privadas, según lo ameriten los asuntos a tratar;\nII. Para que el Pleno del Consejo de la Judicatura sesione válidamente, se requiere la asistencia de al menos cinco integrantes del Consejo;\nIII. Para la validez de los acuerdos del Pleno será necesario el voto de la mayoría de sus integrantes siempre y cuando esté presente la totalidad de sus miembros. En caso contrario se requerirá mayoría absoluta;\nIV. Las o los Consejeros no podrán negarse de votar sino cuando tengan impedimento legal o cuando no hayan estado presentes durante la discusión del asunto de que se trate. El Pleno del\nConsejo de la Judicatura calificará los impedimentos de sus integrantes, siempre que fueren planteados en asuntos de su competencia;\nV. Las o los Consejeros de la Judicatura, a excepción de quien ostente la Presidencia, desahogarán semanariamente por orden progresivo el trámite de las quejas que se reciban hasta\n\nponerlas en estado de resolución, turnándolas, en su caso, a la Consejera o al Consejero Ponente o al Unitario;\nVI. Las quejas serán turnadas por orden alfabético equitativamente y por el número de expediente en forma progresiva y diariamente a cada consejera o consejero para su resolución o para la elaboración del proyecto respectivo según el caso;\nVII. Las ausencias de la o el Presidente del Consejo de la Judicatura que no requieran licencia, serán suplidas por la o el Consejero que designe el mismo Presidente. Las demás serán suplidas conforme a su reglamento interior;\nVIII. Las resoluciones del Pleno del Consejo de la Judicatura, y en su caso de sus Comisiones, constarán en acta y deberán firmarse por las o los Consejeros intervinientes, ante la presencia de la o del Secretario del Consejo de la Judicatura, quien dará fe;\nIX. Las y los Consejeros que disintieran de la mayoría podrá formular por escrito voto particular, el cual se engrosará en el acta respectiva y será presentado dentro de los tres días hábiles siguientes a la fecha del acuerdo y versará sobre los puntos de disidencia que hayan sido discutidos en la sesión correspondiente;\nX. Las resoluciones del Consejo de la Judicatura deberán notificarse dentro del plazo de cinco días hábiles a la fecha del acuerdo, a las partes interesadas, mediante su publicación en el Boletín\nJudicial, salvo los casos en que la resolución finque responsabilidad administrativa; cuando se haya dejado de actuar por más de seis meses sin causa justificada, o tratándose de asuntos de importancia y trascendencia a juicio del propio Consejo de la Judicatura, la notificación deberá ser personal; y\nXI. La ejecución de las resoluciones deberá realizarse por los órganos del propio Consejo.\nArtículo 217. El Consejo de la Judicatura, está facultado para expedir acuerdos generales para el adecuado ejercicio de sus funciones y para el desarrollo de programas de soluciones alternativas de controversias.\nSiempre que el Consejo de la Judicatura considere que los acuerdos son de interés general ordenara su publicación en el Boletín Judicial y en su caso, en la Gaceta Oficial de la Ciudad de México.\n\nEl Pleno del Tribunal Superior de Justicia, podrá solicitar al Consejo la expedición de aquellos acuerdos generales que considere necesarios para apoyar el adecuado ejercicio de la función jurisdiccional, mismos que deberán ser realizados en un término no mayor a treinta días hábiles, y comunicados al Pleno del\nTribunal Superior de Justicia por conducto de quien lo presida, para los efectos que correspondan.\nLos actos y decisiones del Consejo de la Judicatura, en ningún caso, podrán modificar las resoluciones o invadir la función jurisdiccional depositada en los órganos del Poder Judicial de la Ciudad de México, ni podrán afectas las resoluciones de las y los Jueces y Magistradas o Magistrados.\nLas decisiones del Consejo de la Judicatura serán definitivas e inatacables y, por lo tanto, no procederá juicio ni recurso alguno en contra de las mismas, salvo las que se refieran a la designación, adscripción o de ratificación a que se contrae el artículo 284 de esta Ley, así como la remoción de Magistradas,\nMagistrados y Juzgadores, las cuales podrán ser revisadas por el Pleno del Tribunal Superior de Justicia, únicamente para verificar que hayan sido adoptadas conforme a las reglas que establece esta Ley.\nCAPÍTULO II\nFACULTADES Y OBLIGACIONES DEL CONSEJO DE LA JUDICATURA DE\nLA CIUDAD DE MÉXICO\nArtículo 218. Son facultades del Consejo de la Judicatura, las siguientes:\nI. Expedir los acuerdos generales y demás disposiciones reglamentarias para el adecuado ejercicio de sus funciones;\nII. Emitir propuesta al Congreso, de designación o ratificación de Magistradas y Magistrados del\nTribunal Superior de Justicia;\nIII. Designar a las y los Jueces de la Ciudad de México en los términos que señala esta Ley, así como adscribir a estos y a las Magistradas y Magistrados;\nAsimismo, resolver todas las cuestiones que con dicho nombramiento se relacionen, cambiar con causa justificada a las y los Jueces de una adscripción a otra, así como variar la materia de los\nJuzgados;\n\nIV. Resolver, por causa justificada, sobre la remoción de Juzgadores y Titulares de Magistraturas, por sí, o a solicitud del Pleno del Tribunal, de conformidad con el artículo 108 y 109 de la\nConstitución Política de los Estados Unidos Mexicanos;\nV. Vigilar que se cumplan las disposiciones que sobre la carrera judicial señale esta Ley, y aprobar los planes y programas del Instituto de Estudios Judiciales;\nVI. Conocer y resolver las quejas que no sean de carácter jurisdiccional y en su caso dar vista a la\nContraloría, así como los procedimientos oficiosos contra actos u omisiones de los miembros del\nConsejo de la Judicatura, Magistraturas Juzgados y demás personas servidoras públicas de la administración de Justicia, así como integrantes de las Unidades de Gestión Judicial del Sistema\nProcesal Penal Acusatorio, haciendo la sustanciación correspondiente y, en su caso, imponer la medida disciplinaria procedente;\nVII. Ordenar, previa comunicación del Pleno del Tribunal Superior de Justicia, la suspensión de su cargo del Titular de la Magistratura, del Consejo o Juzgado de quien se haya dictado acuerdo respecto a la procedencia de la orden de aprehensión o comparecencia en su contra durante el tiempo que dure el proceso que se le instaure, así como su puesta a disposición del Juzgador que conozca del asunto.\nEl Consejo podrá adoptar las medidas cautelares que correspondan para evitar que la o el inculpado se sustraiga a la acción de la justicia, en caso de ser estrictamente necesario, fundada y motivada su decisión, y en su caso, ejecutará la destitución e inhabilitación que se imponga.\nLa detención que se practique en contravención a este precepto y sus correlativos, será sancionada en los términos que prevenga el Código Penal aplicable;\nVIII. Pedir a quien ostente la Presidencia del Consejo y a sus integrantes el fiel cumplimiento de sus obligaciones y en su caso fincar la responsabilidad en que incurran de acuerdo con esta Ley y leyes en la materia;\nIX. Elaborar y someter a la aceptación del Pleno del Tribunal Superior de Justicia, el presupuesto del Tribunal Superior de Justicia, de los Juzgados y demás Órganos Judiciales, incluido el\nConsejo de la Judicatura, el cual deberá priorizar el mejoramiento de la impartición de justicia y su vinculación con las metas y objetivos del plan institucional y programas que de él deriven.\n\nEl presupuesto deberá remitirse a la persona titular de la Jefatura de Gobierno para el sólo efecto de que se incorpore, en capítulo por separado y en los mismos términos formulados por el\nConsejo, al proyecto de Presupuesto de Egresos de la Ciudad de México, que será sometido a la aprobación del Congreso.\nX. Determinar el número de Salas, Magistraturas, Juzgados, y demás personal con el que contará el Tribunal Superior de Justicia.\nXI. Vigilar que se cumplan las disposiciones legales y administrativas relacionadas con sistemas de registro y contabilidad, contratación y pago de personal, contratación de servicios, obra pública, adquisiciones, arrendamientos, conservación, uso, destino, afectación, enajenación y baja de bienes muebles e inmuebles, almacenes y demás activos y recursos materiales;\nXII. Realizar visitas administrativas ordinarias cada tres meses a las Salas y Juzgados, por conducto de la Visitaduría Judicial, sin perjuicio de las que pueda realizar de manera extraordinaria, ya sea individual o conjuntamente en casos especiales cualesquiera de los\nConsejeros, pudiendo ser apoyados por las y los Magistrados de las Salas que conozcan de la misma materia.\nTambién podrá el Consejo o la Visitaduría realizar visitas administrativas, cuando se trate de un medio de prueba dentro del trámite de una queja administrativa o de un procedimiento oficioso, o para verificar objetiva y oportunamente el eficaz funcionamiento de la instancia judicial de que trate, o en su caso, a petición de una Magistrada o Magistrado, cuando se trate de Juzgados.\nXIII. Designar a una persona Titular de la Secretaría General del Consejo, la cual asistirá a las sesiones y dará fe de los acuerdos, así como al personal técnico y de apoyo. Las ausencias temporales de éste serán suplidas por el funcionario designado por quien presida el Consejo de la Judicatura, dentro del personal técnico;\nXIV. Designar al Jurado que con la cooperación de instituciones públicas o privadas se integrará para el examen que presentarán las personas que deban ejercer los cargos de peritos, en los asuntos que se tramiten ante el Tribunal y dentro de los requisitos que esta Ley señale;\nXV. Nombrar a las personas Titulares de la Visitaduría General y de las Visitadurías Judiciales.\n\nXVI. Proponer al Congreso la o el Titular de la Contraloría General;\nXVII. Nombrar a las personas servidoras públicas administrativas de base y de confianza, del propio Consejo de la Judicatura, así como aquellos cuya designación no esté reservada a la autoridad judicial, a las y los titulares de los Órganos de apoyo judicial, áreas administrativas y las y los Consejeros;\nXVIII. Vigilar que se cumpla con las publicaciones de los extractos de las declaraciones de no responsabilidad pronunciadas en las quejas interpuestas en contra de las personas servidoras públicas de la administración de justicia y miembros del Consejo, que deberán efectuarse en el\nBoletín Judicial y en un periódico de circulación en la Ciudad de México, y notificar personalmente al interesado el contenido de la publicación que se hizo.\nEn caso de no cumplir con la presente disposición, el interesado podrá solicitar al Consejo que dé cumplimiento a la misma, debiendo éste notificarle personalmente en un término no mayor a cinco días el cumplimiento dado a esta fracción;\nXIX. Autorizar licencias cuando procedan por causa justificada, sin goce de sueldo, que excedan de quince días y hasta de tres meses, en un año;\nXX. Establecer los montos que por razón de la cuantía deberán conocer los Juzgados de lo Civil de Cuantía Menor y los de Proceso Oral Civil en los términos de esta Ley, y darlos a conocer a los\nÓrganos Jurisdiccionales, mediante su publicación oportuna en el Boletín Judicial;\nXXI. Desempeñar las funciones administrativas mediante la Comisión que al efecto se forme por quien presida y dos Consejeros en forma rotativa, bimestral y en orden alfabético, relacionadas con el manejo de los recursos humanos, financieros, materiales y de toda índole que correspondan al Consejo de la Judicatura, así como las del Tribunal, Juzgados y demás órganos judiciales;\nXXII. Vigilar el cumplimiento por parte de las y los Jueces y Titulares de Magistraturas respecto de las instrucciones y lineamientos que en materia de estadística se dicten para el control administrativo y seguimiento de los expedientes que se tramiten ante ellos, tomando las medidas necesarias para su debida observancia;\n\nXXIII. Dictar las medidas necesarias para la organización y funcionamiento de la Dirección\nGeneral de Procedimientos Judiciales y expedir las reglas de turno ordinario y extraordinario de los Juzgados Penales, las cuales deberá hacer del conocimiento de la Oficina\nCentral de Consignaciones de la Procuraduría General de Justicia de la Ciudad de México cuando menos con treinta días de anticipación;\nXXIV. Autorizar cada dos años, en forma potestativa y con vista a sus antecedentes, a las personas que deben ejercer los cargos de Síndicos e Interventores en los Juicios de Concurso, Albaceas,\nDepositarios Judiciales, Árbitros, Peritos y demás auxiliares de la administración de justicia que hayan de designarse en los asuntos que se tramiten ante las Salas y Juzgados del Tribunal, previa la satisfacción de los requisitos a que se refiere el Título Sexto de esta Ley.\nLa decisión que al respecto adopte el Consejo de la Judicatura será irrecurrible;\nXXV. Fijar las bases de la política informática y de información estadística que permitan conocer y planear el desarrollo del Tribunal Superior de Justicia y del propio Consejo, así como regular, recopilar, documentar, seleccionar y difundir para conocimiento público, con apego a las normas en materia de transparencia y acceso a la información pública;\nXXVI. Emitir, en términos de la legislación relativa a transparencia y acceso a la información pública; protección de datos personales y las relativas al manejo de archivos públicos, las disposiciones reglamentarias conducentes;\nXXVII. Establecer a través de acuerdos generales, juzgados de tutela en las Demarcaciones territoriales;\nXXVIII. Formar parte del Comité Coordinador del Sistema Anticorrupción de la Ciudad de México.\nXXIX. Conocer de las excitativas que tengan por objeto conminar a Juzgadores y titulares de\nMagistraturas para que administren pronta y cumplida justicia cuando sin causa justificada transcurran los términos legales sin dictar las resoluciones que correspondan.\nLas excitativas serán remitidas al Pleno del Tribunal Superior de Justicia, previa determinación de su procedencia y sólo podrán ser presentadas por las partes con interés legítimo;\n\nXXX. Emitir disposiciones y programas que coadyuven para la prevención, atención e indemnización de enfermedades o riesgos de trabajo psicosociales, derivados de la fatiga y estrés laboral para las personas trabajadoras del Poder Judicial de la Ciudad de México; mismas que deberán contemplar mecanismos que garanticen un entorno laboral favorable;\nXXXI. Expedir los acuerdos generales y demás disposiciones reglamentarias para el adecuado ejercicio de sus funciones y de las relativas a la función jurisdiccional del Tribunal Superior de\nJusticia, del Instituto de Servicios Periciales y Ciencias Forenses y de los órganos judiciales;\nXXXII. Expedir acuerdos, lineamientos y demás disposiciones administrativas que coadyuven a la función jurisdiccional, especialmente aquellas que garanticen el acceso a la justicia, a las tecnologías de la información, justicia digital y la tutela jurisdiccional efectiva, sin perjuicio de la autonomía de los órganos jurisdiccionales;\nXXXIII. Nombrar a la persona titular del Centro de Justicia Alternativa, y\nXXXIV. Las demás que determinen las Leyes y el Reglamento Interior del Consejo de la\nJudicatura.\nArtículo 219. Son atribuciones de quien Presida el Consejo de la Judicatura las siguientes:\nI. Representar legalmente al Consejo y atender los asuntos de la competencia del Pleno de dicho\nConsejo;\nII. Asegurar la congruencia e interrelación de las funciones conferidas al Consejo de la Judicatura y a la Contraloría del Tribunal Superior de Justicia, con respecto a la investigación del comportamiento en el servicio del personal del Tribunal y de dicho Consejo. Igualmente sobre la imposición de medidas disciplinarias o de responsabilidades a esas personas servidoras públicas;\nIII. Recibir quejas sobre demoras y faltas en el despacho de los asuntos, turnándolos en su caso a la comisión correspondiente del propio Consejo, así como practicar por sí mismo visitas a Salas y Juzgados;\nIV. Presidir el Pleno del Consejo, sus comisiones, con excepción de la de Disciplina Judicial, y dirigir los debates, conservar el orden en las sesiones y llevar la correspondencia del Consejo;\n\nV. Convocar a sesión extraordinaria cada vez que lo estime necesario, o si así lo piden más de dos\nConsejeras o Consejeros;\nVI. Proponer al Consejo de la Judicatura el nombramiento y remoción de las o los titulares de la\nOficialía Mayor; de la Dirección General del Instituto de Estudios Judiciales; de la Visitaduría\nGeneral y Visitadurías Judiciales, y del titular del Centro de Justicia Alternativa;\nVII. Resolver los asuntos cuya atención no admita demora, debido a su importancia, dando cuenta dentro de las veinticuatro horas siguientes al Consejo;\nVIII. Conceder licencias a las personas servidoras públicas del Tribunal Superior de Justicia y del\nConsejo, cuando procedan por causa justificada, con o sin goce de sueldo, cuando no excedan de quince días;\nIX. Vigilar la publicación de los Anales de Jurisprudencia y del Boletín Judicial;\nXI. Dirigir, con la colaboración de la Oficialía Mayor, la policía de los edificios que ocupa el\nTribunal Superior de Justicia y los Juzgados, dictando las medidas adecuadas a su conservación e higiene, y a la distribución de las oficinas judiciales en sus diversas dependencias. Esta facultad se entiende sin perjuicio de las que confieren las leyes a las y los Magistrados y Juzgadores, para conservar el orden de sus respectivos locales dando aviso a quien presida;\nXI. Proponer al Pleno del Consejo de la Judicatura la expedición de acuerdos generales y demás disposiciones reglamentarias para el adecuado ejercicio de sus funciones; y\nXII. Presentar propuestas de acuerdos Generales, lineamientos y demás disposiciones administrativas competencia del Consejo de la Judicatura, y\nXIII. Las demás que determinen las leyes y el Reglamento Interior del Consejo.\n\nTÍTULO DÉCIMO\nDE LA VISITADURÍA JUDICIAL\nCAPÍTULO ÚNICO\nArtículo 220. La Visitaduría Judicial es el órgano auxiliar del Consejo de la Judicatura de la Ciudad de\nMéxico, el cual estará bajo la responsabilidad de la Comisión de Disciplina Judicial, es competente para verificar el funcionamiento de las Salas y de los Juzgados, y para supervisar las conductas de los integrantes de estos órganos, de conformidad con los lineamientos emitidos por el Consejo.\nContará con una persona Titular que se denomina Visitador General, así como con visitadores judiciales que dependerán de él.\nEl Titular de la Visitaduría, así como los Visitadores deberán satisfacer los requisitos del artículo 21, con excepción de lo señalado por las fracciones VI y VII primer párrafo de la presente ley.\nArtículo 221. Las personas nombradas Visitadoras tendrán el carácter de representantes del Consejo de la\nJudicatura, debiendo ser nombrados por éste en el número que acuerde, en los términos de esta Ley.\nEl Consejo de la Judicatura establecerá, en su propio reglamento interior y mediante acuerdos generales, el funcionamiento de la Visitaduría, así como los sistemas que permitan evaluar de manera periódica el desempeño y la honorabilidad del Visitador General y de los Visitadores, para efecto de lo dispuesto en esta Ley en materia de responsabilidades.\nArtículo 222. Las personas con nombramiento de Visitadores deberán realizar visitas administrativas ordinarias cada tres meses a las Salas y Juzgados, o extraordinarias cuando así lo acuerde la Comisión de\nDisciplina Judicial, con la finalidad de supervisar su funcionamiento de conformidad con las disposiciones generales que emita el Consejo de la Judicatura en esta materia.\nNinguna de estas personas Visitadoras podrá visitar los mismos órganos por más de dos ocasiones en un año.\nArtículo 223. En las visitas ordinarias las personas Visitadoras, tomando en cuenta las particularidades de cada órgano, realizarán además de lo que específicamente determine el Consejo de la Judicatura, lo siguiente:\n\nI. Pedirán la lista del personal para comprobar su asistencia;\nII. Verificarán que los valores estén debidamente guardados, ya sea en la caja de seguridad del órgano, o en la institución autorizada al efecto por la ley o en el Monte de Piedad;\nIII. En los juzgados penales corroborarán si los procesados que disfrutan de libertad caucional han cumplido con la obligación de presentarse en los plazos fijados, y si en algún proceso en suspenso transcurrió el término de prescripción de la acción penal;\nIV. Revisarán el libro de gobierno y los demás libros de control a fin de determinar si se encuentran en orden y contienen los datos requeridos;\nV. Harán constar el número de asuntos que hayan ingresado al órgano visitado durante el tiempo que comprenda la visita; y\nVI. Examinarán los expedientes formados a fin de verificar que se llevan con arreglo a la ley, y cuando el Visitador advierta que en un proceso se venció el término para dictar cualquier resolución, recomendará que ésta se pronuncie a la brevedad.\nDe toda visita de inspección deberá levantarse acta circunstanciada, en la cual se hará constar el desarrollo de la misma, las quejas o denuncias presentadas en contra de los titulares y demás servidores del órgano de que se trate, las manifestaciones que respecto de la visita o del contenido del acta quisieran realizar los propios titulares o servidores del órgano, la firma del Titular del Juzgado o de la Magistratura que corresponda y la de la persona Visitadora.\nEn caso de negarse a firmar el Titular del Juzgado o de la Magistratura, se hará constar esta situación y la causa de la misma, recabando la firma de dos testigos de asistencia.\nEl acta levantada por la persona visitadora será entregada al Titular del órgano visitado y a la Comisión de\nDisciplina Judicial, por conducto de la persona Visitadora General, a fin de que determine lo que corresponda y, en caso de responsabilidad, para que proceda en los términos previstos por esta Ley. La persona Visitadora General, con base a las actuaciones realizadas por los Visitadores, propondrá a la\nComisión de Disciplina Judicial, por medio de proyectos, las sanciones o medidas correctivas conducentes.\nArtículo 224. El Consejo de la Judicatura, podrá ordenar la realización de visitas extraordinarias de inspección o acordar la integración de Comisiones Especiales de Investigación, siempre que a su juicio\n\nexistan elementos que hagan presumir irregularidades cometidas por un Titular del Juzgado o de la\nMagistratura. En dichas Comisiones intervendrá además el Visitador General.\nArtículo 225. La Unidad de Supervisión de Medidas Cautelares y de la suspensión condicional del proceso tiene como objeto dotar al Juzgador de los elementos suficientes para emitir una medida cautelar y su seguimiento.\nEsta Unidad, a solicitud de las partes, deberá proporcionarles la información sobre la evaluación de riesgo, previo a la audiencia para preparar el debate de la solicitud de las medidas cautelares.\nI. La Unidad de Supervisión de Medidas Cautelares y de la suspensión condicional del proceso estará integrada por:\na) Un Titular de la Dirección designado por el Pleno del Consejo de la Judicatura;\nb) La Jefatura de Departamento de evaluación del nivel de riesgo del imputado y, en consecuencia, la medida cautelar más apropiada para su caso;\nc) Evaluadores de riesgo, que se encuentren ubicados en las unidades de control de detención ya que constituyen un lugar en donde serán trasladados los detenidos, se considera para facilitar las entrevistas a los detenidos y que sean suficientes como el\nConsejo de la Judicatura determine;\nd) Áreas de supervisión de medidas cautelares, encargados de verificar su cumplimiento adecuado a través de las redes institucionales que para tal efecto se hayan articulado y mediante la verificación presencial por parte de los responsables de ésta área;\ne) Oficina de control de gestión, área responsable de concentrar las relacionadas con el control de reportes e indicadores; y f) Oficina de relaciones interinstitucionales, a esta área le corresponde mantener las buenas relaciones interinstitucionales.\nII. Para ser Titular de la Dirección de la Unidad de Supervisión de Medidas Cautelares y de la suspensión condicional del proceso se requiere:\n\na) Tener cuando menos veinticinco años cumplidos;\nb) Contar con título universitario afín a las tareas de su encomienda;\nc) No haber sido condenado en sentencia ejecutoriada por delito doloso; y d) Acreditar el proceso de selección que elabore el Consejo de la Judicatura.\nArtículo 226. Para ser evaluador de riesgo se requiere:\nI. Tener cuando menos veinticinco años cumplidos al día de la asignación;\nII. Contar con título y cédula universitarios legalmente expedidos por autoridad o institución legalmente facultada para ello afín a las tareas de su encomienda;\nIII. No haber sido condenado en sentencia ejecutoriada por delito doloso;\nIV. Haber acreditado el examen de aptitud que elabore el Instituto de Estudios Judiciales.\nV. Para ser Titular de la Jefatura de departamento, entrevistador o supervisor de la Autoridad de\nSupervisión de Medidas Cautelares y de la suspensión condicional del proceso se deberá:\na) Tener cuando menos veinticinco años cumplidos;\nb) Contar con título universitario y cédula expedidos por autoridad o institución legalmente facultada para ello afín a las tareas de su encomienda;\nc) No haber sido condenado en sentencia ejecutoriada por delito doloso; y d) Acreditar el examen de aptitud que elabore el Consejo de la Judicatura.\nArtículo 227. La Unidad de Supervisión de Medidas Cautelares y de la Suspensión Condicional del\nProceso, ejercerá las obligaciones que confiere el Código Nacional de Procedimientos Penales a la\nAutoridad de Supervisión de Medidas Cautelares y de la suspensión condicional del proceso; y tendrá, además, las facultades de:\n\nI. Entrevistar al imputado previamente a la realización de cualquier audiencia sobre medidas cautelares, para obtener información relevante para decidir sobre las medidas cautelares. Antes de empezar la entrevista, la persona servidora pública encargada debe hacerle saber el objetivo de la entrevista, que tiene derecho a que su defensor esté presente durante la misma, que puede abstenerse de suministrar información y que aquélla que proporcione no podrá ser usada para demostrar su culpabilidad. La entrevista se llevará a cabo con la presencia del defensor, en caso de que no esté presente su defensor, se llevará a cabo con un defensor de oficio;\nII. Verificar la información proporcionada por el imputado y recolectar aquella otra que sea relevante para decidir o modificar las medidas, de modo tal que éstas resulten adecuadas para que el imputado cumpla con sus obligaciones procesales. La información deberá incluir datos sobre la historia personal del imputado, sus lazos con la comunidad, relaciones familiares, amistades, empleos, lugares de residencia, estudios, antecedentes penales, y cualquier otra información pertinente;\nIII. Elaborar reportes para el Juzgador que contengan la información recabada en sus indagaciones, así como sus observaciones y recomendaciones sobre la necesidad y el tipo de medidas cautelares que sería necesario imponer al imputado para asegurar la protección e integridad de la víctima, de los testigos o de terceros; el desarrollo de la investigación o la comparecencia del imputado al proceso. En caso de urgencia el reporte podrá hacerse de manera verbal en una audiencia ante el Juzgador con la presencia de las partes. Cuando la publicidad afecte innecesariamente los derechos del imputado, a solicitud de éste, la audiencia podrá celebrarse en privado, siempre que sea grabada y preservada en el registro, bajo reserva, hasta que no exista justificación para levantarla;\nIV. Entregar a las partes, al inicio de la audiencia en la que se discutan medidas cautelares, copias de los reportes relacionados con las mismas y recogerlos al término de la audiencia;\nV. Supervisar y dar seguimiento a las medidas cautelares impuestas, distintas a la prisión preventiva, vigilar el estricto cumplimiento por parte del imputado de las obligaciones impuestas, y hacer recomendaciones sobre cualquier cambio que amerite alguna modificación de las medidas; y\nVI. Las demás que determine la Ley o demás disposiciones aplicables.\n\nArtículo 228. Para cumplir con sus facultades de supervisión y vigilancia de la Unidad de Supervisión de\nMedidas Cautelares y de la suspensión condicional del proceso podrán además de las obligaciones que confiere el Código Nacional de Procedimientos Penales, además de las siguientes:\nI. Establecer las condiciones y la periodicidad en que los imputados deben reportarse, canalizar a los imputados a servicios sociales de asistencia, públicos o privados, en materia de salud, empleo, educación, vivienda y apoyo jurídico;\nII. Realizar visitas no anunciadas en los domicilios o lugares de trabajo de los imputados;\nIII. Requerir que los imputados proporcionen muestras para detectar el posible uso de alcohol, en su caso, o de drogas prohibidas;\nIV. Supervisar que las personas e instituciones a las que el Juzgador encargue el cuidado del imputado, cumplan las obligaciones contraídas; y solicitar a los imputados informes y reportes que sean necesarios para verificar el cumplimiento de las condiciones impuestas;\nV. Revisar y recomendar el cambio de las condiciones de las medidas impuestas al imputado, de oficio o a solicitud de parte, cuando cambien las circunstancias originales que sirvieron de base para imponer la medida;\nVI. Informar al Juzgador de cualquier violación a las medidas y condiciones impuestas y recomendar las modificaciones que estime pertinentes;\nVII. Realizar estudios estadísticos sobre el nivel del cumplimiento y efectividad de las medidas cautelares impuestas por las y los Jueces;\nVIII. Solicitar y proporcionar información a las oficinas con funciones similares de la Federación o de los Estados, y\nIX. Las demás que determine la Ley o demás disposiciones aplicables.\nArtículo 229. La Dirección de la Unidad de Gestión Judicial en materia Familiar tiene como objeto coordinar a las Unidades de Gestión Judicial en materia Familiar que apoyan a los Juzgados Familiares.\n\nArtículo 230. Para ser persona Directora de la Unidad de Gestión Judicial en materia Familiar se deberán satisfacer los requisitos establecidos en el artículo 24 de esta Ley; además, se deberá acreditar tener conocimientos en la materia. Será designada por quien presida el Tribunal Superior de Justicia a propuesta de la Dirección General de Gestión Judicial, con apego a la normativa vigente.\nArtículo 231. La o el Director de la Unidad de Gestión Judicial en materia Familiar, tendrá las siguientes facultades:\nI. El control, administración y supervisión de las Unidades de Gestión Judicial en Materia\nFamiliar;\nII. Supervisar la elaboración de los despachos, exhortos, actas, diligencias y toda clase de documentos cuya emisión sea ordenada por las y los Jueces de Proceso Oral en materia Familiar, dentro de los asuntos a su cargo;\nIII. Coordinar el auxilio que se le brinde a los Juzgados de Proceso Oral en materia Familiar en la digitalización de aquellos documentos, que por su volumen no puedan ser procesados en estos sin afectar su carga de trabajo;\nIV. Coordinar el auxilio que se le brinde a los Juzgados de Proceso Oral en materia Familiar en el trámite y remisión de expedientes al Archivo Judicial, a la superioridad o al substituto legal, previo registro en sus respectivos casos, conforme a los lineamientos establecidos en esta Ley;\nV. Supervisar la adecuada, oportuna y eficientemente preparación de las salas de audiencia oral para llevar a cabo las audiencias programadas por los Juzgados de Proceso Oral en materia\nFamiliar;\nVI. Supervisar el control de agenda y asignación de las Salas de Audiencia Oral;\nVII. Supervisar y garantizar el trámite, administración y distribución de los insumos necesarios para la operación y el mantenimiento de los Juzgados de Proceso Oral en materia Familiar, y de las Salas de Audiencia Oral;\nVIII. Diseñar y proponer al Director General de Gestión Judicial los mecanismos más eficientes para el desarrollo de sus funciones;\n\nIX. Rendir a la Dirección General de Gestión Judicial los informes que esta requiera;\nX. Supervisar el control, evaluación y supervisión del personal que la conforma;\nXI. Supervisar la organización de las notificaciones que se realizan;\nXII. Garantizar que se cumplan los términos legales en la entrega de las notificaciones;\nXIII. Coordinar la administración del uso que se dé a las Salas de Audiencia;\nXIV. Aportar a la Oficialía Mayor la información que esta requiera con el fin de generar la planeación, programación, ejercicio del presupuesto y evaluación del desempeño de las áreas y al área del Poder Judicial responsable de la Estadística, la información que requiera para desarrollar su función;\nXV. Proveer la información relativa a su área y que las diversas del Tribunal Superior de Justicia y del Consejo de la Judicatura le requieran, con motivo del cumplimiento de sus funciones; y\nXVI. Las demás que determinen la Dirección General de Gestión Judicial y la normatividad aplicable.\nArtículo 232.La Dirección de la Unidad de Gestión Judicial en materia Familiar estará integrada por:\nI. Una Central de Comunicaciones Procesales, responsable de las siguientes actividades:\na) El control, evaluación y supervisión de los oficiales notificadores a su cargo;\nb) La coordinación y organización equitativa del turno de las notificaciones ordenadas por las y los Jueces de Proceso Oral en materia Familiar, y que deban ser practicadas por los oficiales notificadores a su cargo;\nc) La recepción y registro, verificando que se cumpla con los términos legales, de las constancias de las notificaciones practicadas por los oficiales notificadores, turnándolas al\nJuzgado de Proceso Oral en Materia Familiar que corresponda; y\n\nd) Las demás que determine la normatividad aplicable, y la o el Director de Gestión\nJudicial en materia Familiar;\nII. Las Unidades de Apoyo Tecnológico estarán encargadas de:\na) La administración, control, operación y mantenimiento técnico de las Salas de\nAudiencia Oral;\nb) La preparación adecuada, oportuna y eficiente de las salas de audiencia oral, para que se lleven a cabo las audiencias programadas por los Juzgados de Proceso Oral en Materia\nFamiliar;\nc) El auxilio técnico inmediato de las y los Jueces de Proceso Oral en materia Familiar durante la celebración de las audiencias orales;\nd) El auxilio de las y los Jueces de Proceso Oral en Materia Familiar en la obtención de los soportes electrónicos de las audiencias que se celebren, identificándolos plenamente con el asunto al que pertenecen;\ne) La emisión de los respaldos y de las copias de seguridad de los soportes electrónicos de las audiencias que se celebren, y de entregarlos a la o al Juez correspondiente para su debido resguardo;\nf) La emisión de las copias de los soportes electrónicos de las audiencias que se celebren, y que le sean solicitadas por el Juzgado de Proceso Oral en materia Familiar que corresponda;\ng) El control del registro de los soportes electrónicos que se generen de las audiencias orales celebradas, identificados por juzgado, número de expediente, número consecutivo, fecha de emisión, y en su caso número de copias emitidas;\nh) La elaboración de los informes requeridos por la Dirección de Gestión Judicial en materia Familiar;\ni) El diseño y propuesta, a la Dirección de Gestión Judicial en materia Familiar, de los mecanismos que hagan más eficiente el desarrollo de sus funciones; y\n\nj) Las demás que determinen la legislación aplicable y la Dirección de Gestión Judicial en materia Familiar.\nEstas áreas serán autónomas con relación a los Juzgados de Proceso Oral en materia Familiar y dependerán de la Dirección General de Gestión Judicial.\nArtículo 233. La o el Titular de la Central de Comunicaciones Procesales deberá satisfacer los requisitos del artículo 24 de esta Ley.\nArtículo 234. La o el titular de la Unidad de Apoyo Tecnológico deberá:\nI. Ser mayor de veintiocho años;\nII. Ser ingeniera o ingeniero en computación, o ingeniera o ingeniero en sistemas computacionales o ingenierías o licenciaturas afines, con cédula profesional expedida por la autoridad o institución legalmente facultada para ello;\nIII. Tener dos años de práctica profesional contados desde la fecha de expedición del título; y\nIV. No haber sido condenado por delito doloso.\nTÍTULO DÉCIMO PRIMERO\nCAPÍTULO I\nDE LA OFICIALÍA MAYOR\nArtículo 235. La Oficialía Mayor dependerá de la o el Presidente del Poder Judicial de la Ciudad de México y podrá ser asistida por la Comisión de Administración y Presupuesto del Consejo; asimismo, contará con las Direcciones Ejecutivas y de Área que correspondan a los apartados de este artículo. Además, ejercerá directamente o por conducto de aquellas, las facultades y obligaciones siguientes:\nI. En materia de programación, presupuesto, planeación administrativa y organización:\n\na) Instrumentar las normas generales aprobadas, así como las directrices, normas y criterios técnicos para el proceso interno de programación, presupuestación, evaluación presupuestal e informática del Tribunal Superior de Justicia, así como vigilar su aplicación e informar de su cabal cumplimiento al Pleno del Consejo de la Judicatura;\nb) Someter a la consideración del Pleno del Consejo de la Judicatura, las adecuaciones requeridas a la organización interna de la Oficialía y las diversas Coordinaciones y\nDirecciones de la Institución, así como la actualización de los manuales de organización, de procedimientos y de servicios al público del Tribunal Superior de Justicia; y c) Proponer con aprobación del Pleno del Consejo de la Judicatura, las normas, sistemas y procedimientos aplicables en materia de programación, presupuestación, planeación administrativa y organización de la Institución, de acuerdo con sus programas y objetivos;\ny con la supervisión del Pleno del Consejo de la Judicatura, su instrumentación, seguimiento y estricta observancia.\nII. En materia de Tecnologías de la Información:\na) Proponer e instrumentar las normas generales aprobadas, así como las directrices, normas y criterios técnicos para la administración de los servicios de tecnologías de la información del Tribunal, así como vigilar su aplicación e informar de su cabal cumplimiento al Pleno del Consejo de la Judicatura;\nb) Proporcionar a las áreas del Tribunal Superior de Justicia, los servicios de apoyo requeridos en materia de diseño de sistemas y equipamiento tecnológico, que serán por lo menos los necesarios para que las Salas y Juzgados dispongan de los equipos de cómputo y sistemas de red interna, comunicaciones y archivo, así como los demás que sean necesarios para el mejor desempeño de las funciones del Tribunal Superior de\nJusticia; y c) Proponer al Pleno del Consejo de la Judicatura, los sistemas y procedimientos para la administración de los servicios de tecnologías de la información de la Institución, de acuerdo con sus programas y objetivos, y con la supervisión del Pleno del Consejo de la\nJudicatura instrumentarlos, así como darles seguimiento y verificar su estricta observancia.\n\nIII. En materia de recursos materiales y servicios generales:\na) Planear, formular y ejecutar el programa anual de obra pública, adquisiciones, arrendamientos, servicios, conservación y mantenimiento de bienes muebles e inmuebles del Tribunal Superior de Justicia, previa autorización y supervisión del Pleno del Consejo de la Judicatura; y b) Proponer al Pleno del Consejo de la Judicatura, las normas, sistemas y procedimientos aplicables en materia de obra pública, adquisiciones, arrendamientos, servicios, conservación y mantenimiento de bienes muebles e inmuebles de la Institución, de acuerdo con sus programas y objetivos; y con la supervisión del Pleno del Consejo la instrumentación, seguimiento y estricta observancia.\nIV. En materia de Administración y Desarrollo de Personal:\na) Planear y formular, previa autorización del Pleno del Consejo de la Judicatura, el programa del Tribunal Superior de Justicia, destinado a la administración y desarrollo de su personal, y con la supervisión del Pleno del Consejo, la ejecución y control de dicho programa;\nb) Supervisar que las relaciones laborales se desarrollen de acuerdo con las políticas que señale el Pleno del Consejo de la Judicatura, en apego a las leyes laborales y a las condiciones generales de trabajo vigentes, así como su cumplimiento;\nc) Proponer al Pleno del Consejo de la Judicatura, los acuerdos relativos a la suscripción de contratos, convenios y acuerdos relativos al ejercicio de sus atribuciones, así como demás documentos que impliquen actos de administración, de acuerdo con las disposiciones legales aplicables y previo dictamen de la Dirección Jurídica;\nd) Formular, concertar e instrumentar, de conformidad con las directrices del Pleno del\nConsejo de la Judicatura, las condiciones generales de trabajo de los servidores públicos judiciales de base; y e) Regular, sistematizar, dirigir, coordinar y supervisar el Servicio de Profesionalización y\nDesarrollo de las Personas Servidoras Públicas Administrativos del Tribunal Superior de\nJusticia y del Consejo de la Judicatura.\n\nV. En materia general:\na) Las demás que le confiera el Pleno del Consejo de la Judicatura México y las que le señalen las disposiciones legales y reglamentarias relativas;\nb) La instrumentación de esas Direcciones Generales de la Oficialía Mayor será congruente con las disponibilidades presupuestales del Tribunal y con las atribuciones y responsabilidades que se les confieran en el Reglamento Interior del mismo;\nc) Asimismo, y en apoyo de la función jurisdiccional, la Oficialía Mayor tendrá a su cargo la administración, supervisión y control de las Unidades de Apoyo Tecnológico, propondrá al Consejo las políticas, lineamientos y criterios a los que dichas áreas deberán de sujetarse;\nd) La Oficialía Mayor estará a cargo de una persona servidora pública que se denominará\nOficial Mayor. Para desempeñar dicho cargo, se deben cumplir los requisitos establecidos por las fracciones I, II, IV, y V del artículo 16 de esta Ley. Además, contar con título profesional a nivel de licenciatura y acreditar una experiencia mínima de diez años en áreas o actividades afines al desempeño del cargo; y e) Se Deroga.\nArtículo 236.La Dirección General de Gestión Judicial se integrará con las siguientes áreas:\nI. Direcciones de Gestión Judicial,\nII. Unidades de Gestión Judicial en materia Penal y Familiar, y\nIII. Unidad de Supervisión de Medidas Cautelares y de la Suspensión Condicional del Proceso.\nArtículo 237. Para ser persona Titular de la Dirección de Gestión Judicial se deberán satisfacer los requisitos dispuestos en el artículo 24 de esta Ley, salvo pronunciamiento expreso del Consejo de la Judicatura; y será designada por la o el Presidente del Tribunal Superior de Justicia a propuesta de la Dirección General de Gestión Judicial, con apego a la normatividad vigente.\n\nArtículo 238. La persona Titular de la Dirección General de Gestión Judicial, dependerá de quien presida el\nTribunal Superior de Justicia y tendrá las siguientes obligaciones y facultades:\nI. Cumplir con aquellas determinaciones que le confiere la o el Presidente del Tribunal Superior de Justicia, así como aquellas disposiciones que determine el Consejo de la Judicatura y las que le señalen las demás disposiciones jurídicas;\nII. En apoyo de las funciones jurisdiccionales tendrá a su cargo la coordinación y supervisión de las Unidades de Gestión Judicial en Materia Penal, la Unidad de Supervisión de Medidas\nCautelares y de la Suspensión Condicional del Proceso, así como de la Unidad de Gestión Judicial en Materia Familiar;\nIII. Coordinar que las Unidades de Gestión Judicial en materia Penal y en materia Familiar, provean la programación de las diligencias a desarrollarse en las salas de audiencia a su cargo;\nIV. Proponer al Presidente del Tribunal Superior de Justicia las directrices que deberán seguir las\nUnidades de Gestión Judicial en materia Penal y materia Familiar para la administración de las agendas de las o los Jueces;\nV. Proponer al Presidente del Tribunal Superior de Justicia, las directrices que deberán seguir las\nUnidades de Gestión Judicial en materia Penal, respecto al archivo y control de las Carpetas\nJudiciales;\nVI. Proponer al Presidente del Tribunal Superior de Justicia, los mecanismos que se instrumentarán para la gestión de entrega de notificaciones en las Unidades que la componen;\nVII. Proponer al Presidente del Tribunal Superior de Justicia, la política y estándares de las áreas de atención ciudadano.\nVIII. Participar en conversatorios y llegar a acuerdos con los operadores del Sistema Procesal\nPenal Acusatorio, a fin de proponer al Presidente del Tribunal Superior de Justicia directrices y lineamientos que deberán seguir las Unidades de Gestión Judicial en materia Penal;\nIX. Coordinar la estrategia de vigilancia y acciones necesarias, a fin de garantizar que las\nUnidades de Gestión Judicial en materia Penal y en materia Familiar lleven a cabo la grabación sistemática de todas las audiencias y la administración del archivo de las mismas;\n\nX. Coordinar mecanismos de vigilancia y acciones necesarias a efecto de que las Unidades que la componen cumplan los lineamientos y normatividad que al efecto se emitan.\nProponer al Pleno del Tribunal Superior de Justicia las modificaciones y actualizaciones de los lineamientos y normatividad que considere necesarios para el correcto funcionamiento de las\nUnidades que la componen.\nXI. Promover y participar en conversatorios con las y los Magistrados, y con las y los Jueces, que permitan proponer a la o al Presidente de Tribunal Superior de Justicia, directrices que permitan la coordinación de las Unidades que componen esta Dirección General de Gestión Judicial con los órganos jurisdiccionales;\nXII. Establecer las normas, políticas y procedimientos para la adecuada operación de todas las unidades administrativas bajo su responsabilidad con apego a la normativa vigente;\nXIII. Establecer los objetivos, metas y programas de trabajo de las áreas bajo su cargo;\nXIV. Coordinarse con las o los titulares de otras unidades administrativas cuando el caso lo requiera para el buen funcionamiento del área;\nXV. Formular los reportes de cumplimiento de metas que se requieran por las áreas administrativas competentes;\nXVI. Promover la capacitación y adiestramiento, así como el desarrollo de su personal, en coordinación con el área responsable de ello;\nXVII. Emitir opinión sobre las propuestas que la o el Presidente del Tribunal Superior de Justicia realice al Consejo de la Judicatura respecto de los nombramientos de las o los titulares de las\nDirecciones de Gestión Judicial, instancias que conforman la Dirección General de Gestión\nJudicial, así de los nombramientos de las o los titulares de Unidad de Gestión Judicial;\nXVIII. Revisar los reportes de las áreas de Control de Gestión que pertenecen a sus unidades y actuar en consecuencia;\n\nXIX. Aportar la información que las diversas áreas del Tribunal Superior de Justicia y del Consejo de la Judicatura le requieran, con motivo del cumplimiento de sus funciones;\nXX. Aportar a la Oficialía Mayor la información que esta requiera con el fin de generar la planeación, programación, ejercicio del presupuesto, y evaluación del desempeño de las áreas;\ny al área del Poder Judicial responsable de la Estadística, brindarle la información que requiera para el puntual desarrollo de su función;\nXXI. Proveer la información de la Dirección General de Gestión Judicial que las diversas áreas del\nTribunal Superior de Justicia y del Consejo de la Judicatura le requieran, con motivo del cumplimiento de sus funciones;\nXXII. Coordinar la estrategia de vigilancia, así como acciones requeridas a efecto de que las y los\nJueces reciban los elementos suficientes para que dicte las medidas cautelares y se dé el seguimiento que corresponda;\nXXIII. Previa propuesta a la o al Presidente de Tribunal Superior de Justicia, se promoverá conversatorios con las autoridades del ámbito de seguridad pública o ciudadana, para establecer mecanismos de coordinación interinstitucional que permita generar estrategias para la adecuada supervisión de las medidas cautelares;\nXXIV. Previa propuesta a la o al Presidente de Tribunal Superior de Justicia, se promoverá conversatorios con las autoridades de la administración pública de la Ciudad de México y\nOrganizaciones Civiles que puedan aportar en el seguimiento de aquellas suspensiones condicionales del proceso así lo requieran; y\nXXV. Proponer a la o al Presidente del Tribunal Superior de Justicia proyectos de lineamientos y protocolos para la entrevista de los imputados, la verificación de información que estos proporcionan, así como la elaboración de reportes para la o el Juez, y aquellas funciones que le confiere el Código Nacional de Procedimientos Penales en la materia.\nArtículo 239. La Unidad de Gestión Judicial, por el número que se necesiten dependerá de quien sea nombrado Titular de la Dirección General de Gestión.\nArtículo 240. La Unidad de Gestión Judicial es el área de apoyo judicial encargada de dar trámite a la substanciación de los asuntos turnados para conocimiento de las Magistradas y los Magistrados Penales,\n\nasí como las y los Jueces, todos del Sistema Penal Acusatorio, respecto al seguimiento de las carpetas judiciales, tanto en lo legal, como en lo administrativo.\nArtículo 241. La Unidad de Gestión Judicial contará con una persona Titular que estará a cargo de la estructura que autorice el Consejo de la Judicatura para la misma.\nArtículo 242. Para ser persona Titular de las Unidades de Gestión Judicial se deberán satisfacer los requisitos dispuestos en el artículo 24 de esta Ley salvo pronunciamiento expreso del Consejo de la\nJudicatura.\nArtículo 243. La persona Administradora de las Unidades de Gestión será responsable de:\nI. El resguardo de las salas de audiencias donde se despachen los Jueces de Control y el Tribunal de Enjuiciamiento;\nII. Ejecutar las acciones necesarias para el desarrollo de sistema de gestión en apoyo al servicio de las y los Jueces, bajo los lineamientos autorizados por el Consejo de la Judicatura;\nIII. Dirigir los trabajos y supervisar el desempeño del personal a su cargo;\nIV. Vigilar la correcta y eficiente aplicación de los recursos asignados a su unidad;\nV. Vigilar el rol de turnos de los Jueces y demás personal del Tribunal Superior de Justicia, se realice en tiempo y forma;\nVI. Guardar el debido secreto respecto de los asuntos que por su oficio o puesto tenga conocimientos;\nVII. Vigilar que el personal a su cargo guarde el debido secreto respecto de los asuntos que por su oficio o puesto tengan conocimiento;\nVIII. Determinar las medidas disciplinarias a su personal;\nIX. Mantener en continua capacitación al personal bajo su dirección;\n\nX. Coordinar y controlar la ubicación y distribución adecuación del personal, acorde con sus perfiles, competencias y naturaleza profesional;\nXI. Aportar a la Oficialía Mayor la información que esta requiera con el fin de generar la planeación, programación, ejercicio del presupuesto y evaluación del desempeño de las áreas;\nXII. Proveer la información relativa a su área y que las demás del Tribunal Superior de Justicia y\nConsejo de la Judicatura le requieran con motivo del cumplimiento de sus funciones;\nXIII. Proponer el nombramiento de la persona titular de la Dirección de Gestión Judicial de la lista de aspirantes que integraran las Unidades de Gestión Judicial; y\nXIV. Las demás que le confieran las leyes, reglamentos y acuerdos que emita el Consejo de la\nJudicatura.\nArtículo 244. La Dirección de Gestión Judicial en materia Penal es la autoridad que tiene a su cargo los equipos multidisciplinarios de gestión que desarrollan el Sistema Procesal Penal Acusatorio en el Tribunal\nSuperior de Justicia.\nLa Dirección de Gestión Judicial en materia Penal es responsable de coordinar las funciones de las diversas\nUnidades de Gestión Judicial en materia Penal, Justicia para Adolescentes, Ejecución de Medidas\nSancionadoras y Ejecución de Sanciones Penales que conforman el Sistema Procesal Penal Acusatorio y supervisa el apoyo que se brinda a las o los Magistrados y a las y los Jueces que integran el Sistema Procesal\nPenal Acusatorio.\nArtículo 245. La Directora o Director de Gestión Judicial en materia Penal dependerá de la o del Director\nGeneral de Gestión Judicial y tendrá las siguientes atribuciones:\nI. Cumplir con aquellas determinaciones que le confiere la o el Director General de Gestión\nJudicial, así como aquellas disposiciones legales y reglamentarias relativas;\nII. En apoyo de las funciones jurisdiccionales tendrá a su cargo la coordinación, supervisión de las Unidades de Gestión Judicial en Materia Penal, Ejecución Penal, Adolescentes y Ejecución de\nMedidas Sancionadoras;\n\nIII. Proponer a la o al Director General de Gestión Judicial, la conformación de las Unidades de\nGestión Judicial que se requieran; así como justificar su creación y especialización;\nIV. Proponer a la o al Director General de Gestión Judicial la designación de las o los titulares de cada Unidad de Gestión Judicial;\nV. Vigilar que las Unidades de Gestión Judicial proporcionen el soporte logístico-administrativo a las Juezas o Jueces para la adecuada celebración de las audiencias;\nVI. Supervisar a las Unidades de Gestión Judicial existentes, la programación de las diligencias a desarrollarse en las salas de audiencia a su cargo;\nVII. Garantizar que las Unidades de Gestión Judicial administren de forma equitativa las agendas de las o los Jueces con base en los lineamientos y directrices establecidas, asegurando que se informe a las o los Jueces el detalle de la ejecución de las audiencias;\nVIII. Vigilar y generar controles a fin de que se realice el archivo de las Carpetas Judiciales conforme a los acuerdos, lineamientos y directrices existentes;\nIX. Vigilar que la entrega de las notificaciones se realice conforme a los lineamientos y directrices establecidas;\nX. Garantizar que el servicio que brinden las Unidades de Gestión Judicial se realice conforme a los estándares establecidos;\nXI. Vigilar que el traslado de las y los imputados y las solicitudes de apoyo de seguridad durante las audiencias se realicen de conformidad a los lineamientos y directrices establecidas;\nXII. Garantizar que las Unidades de Gestión graben de forma sistemática todas las audiencias y que administren los archivos de conformidad a las directrices y lineamientos establecidos;\nXIII. Difundir y vigilar el cumplimiento de los lineamientos y normatividad en las Unidades de\nGestión Judicial a su cargo;\n\nXIV. Garantizar que las o los titulares de cada Unidad de Gestión Judicial a su cargo acuerden con las y los Jueces coordinadores la resolución de los asuntos cuya tramitación se encuentre dentro de su área de su competencia;\nXV. Proponer a la Dirección General de Gestión Judicial las normas, políticas y procedimientos para la adecuada operación de todas las unidades administrativas bajo su responsabilidad;\nXVI. Proponer a la Dirección General los objetivos, metas y programas de trabajo de las áreas bajo su cargo;\nXVII. Previa autorización de la o del Director General de Gestión Judicial se coordinará con las o los titulares de otras unidades del Tribunal Superior de Justicia cuando el caso lo requiera para el buen funcionamiento del área;\nXVIII. Formular los reportes de metas que las áreas competentes lo requieran;\nXIX. Detectar las necesidades de capacitación y adiestramiento del personal de las Unidades de\nGestión, a fin de proponer a la Dirección General de Gestión Judicial lo conducente.\nXX. Revisar los reportes de las áreas de Control de Gestión que pertenecen a sus unidades y actuar en consecuencia;\nXXI. Elaborar el proyecto de informe anual de su área para someterlo a su superior inmediato;\nXXII. Garantizará que las Unidades de Gestión a su cargo resguarden las salas de audiencia donde despachan las o los Jueces;\nXXIII. Proponer a la Directora o Director General el personal que conformará las Unidades de\nGestión Judicial que se encuentran a su cargo;\nXXIV. Garantizar que las Unidades de Gestión Judicial supervisen el desempeño del personal a su cargo;\nXXV. Coordinar y vigilar la correcta aplicación de los recursos asignados a cada Unidad;\n\nXXVI. Vigilar que las Unidades de Gestión Judicial lleven a cabo los roles de turno conforme a los lineamientos aprobados, a fin de que estos se realicen en tiempo y forma;\nXXVII. Guardar el debido secreto de los asuntos que tenga conocimiento;\nXXVIII. Vigilar que el personal a su cargo guarde el debido secreto respecto de los asuntos que por su oficio o puesto tengan conocimiento;\nXXIX. Aplicar las medidas disciplinarias que se encuentren establecidas en la normatividad aplicable;\nXXX. Garantizar la correcta coordinación, ubicación, distribución del personal que se encuentra en las Unidades de Gestión a su cargo, a fin de que las mismas se encuentren acordes a sus perfiles y naturaleza profesional; y\nXXXI. Las demás que le confieran las leyes, reglamentos y acuerdos que emita el Pleno del\nTribunal Superior de Justicia.\nArtículo 246. Las Unidades de Gestión Judicial en materia Penal apoyarán a las Magistradas y los\nMagistrados, a las y los Jueces del Control, al Tribunal de Enjuiciamiento, de Ejecución, de Justicia para\nAdolescentes y Ejecución de Medidas Sancionadoras, conforme a la estructura que defina por el Consejo de la Judicatura.\nArtículo 247. Las Unidades de Gestión Judicial en materia Penal tendrán la estructura autorizada por el\nConsejo de la Judicatura, de conformidad con su especialidad y funciones específicas. Contarán tanto con personal de carrera judicial como administrativo.\nArtículo 248. Las Unidades de Gestión Judicial en materia Penal tendrán el apoyo técnico administrativo de las siguientes áreas del Poder Judicial:\nI. Unidad de Servicios Generales; y\nII. Unidad de Informática y Videograbación.\n\nEstas Unidades técnico administrativas estarán compuestas por el personal que se determine para garantizar el adecuado desempeño de las funciones de las instalaciones que albergan las Unidades de\nGestión Judicial.\nLa Unidad de Recursos Materiales y Servicios Generales dependerán de la Dirección Ejecutiva de Obras,\nMantenimiento y Servicios y la Unidad de Informática y Videograbación dependerá de la Dirección\nEjecutiva de Gestión Tecnológica y serán estas Direcciones las responsables de proponer al Oficial Mayor su conformación de acuerdo a la normatividad aplicable.\nArtículo 249. La o el Administrador de las Unidades de Gestión Judicial será responsable de las siguientes funciones:\nI. Resguardar las salas de audiencias donde despachen las o los Jueces de Control y el Tribunal de Enjuiciamiento;\nII. Ejecutar las acciones necesarias para el desarrollo del sistema de gestión en apoyo al servicio de las y los jueces, bajo los lineamientos autorizados por el Consejo de la Judicatura;\nIII. Dirigir los trabajos y supervisar el desempeño del personal a su cargo;\nIV. Vigilar la correcta y eficiente aplicación de los recursos asignados a su unidad;\nV. Vigilar que el rol de turnos de las y los Jueces y demás personal del Tribunal Superior de\nJusticia, se realice en tiempo y forma;\nVI. Guardar el debido secreto respecto de los asuntos que por su oficio o puesto tenga conocimiento;\nVII. Vigilar que el personal a su cargo guarde el debido secreto respecto de los asuntos que por su oficio o puesto tengan conocimiento;\nVIII. Determinar las medidas disciplinarias a su personal;\nIX. Mantener en continua capacitación al personal bajo su dirección;\n\nX. Coordinar y controlar la ubicación, distribución y adecuación del personal, acorde con sus perfiles, competencias y naturaleza profesional;\nXI. Aportar a la Oficialía Mayor la información que esta requiera con el fin de generar la planeación, programación, ejercicio del presupuesto y evaluación del desempeño de las áreas;\nXII. Proveer la información relativa a su área y que las demás del Tribunal Superior de Justicia y\nConsejo de la Judicatura le requieran con motivo del cumplimiento de sus funciones;\nXIII. Proponer el nombramiento a la o al director de Gestión Judicial de la lista aspirantes que integrarán las Unidades de Gestión Judicial; y\nXIV. Las demás que le confieran leyes, reglamentos, acuerdos y demás disposiciones jurídicas.\nCAPÍTULO II\nDEL INSTITUTO DE SERVICIOS PERICIALES Y CIENCIAS FORENSES\nArtículo 250. El Instituto de Servicios Periciales y Ciencias Forenses es un órgano del Tribunal Superior de\nJusticia, especializado en la prestación de servicios periciales y forenses. El Instituto deberá garantizar en los dictámenes que emita la objetividad e imparcialidad de conformidad con lo dispuesto por leyes y los estándares nacionales e internacionales en la materia, en atención a lo dispuesto por el artículo 35 de la\nConstitución, Apartado F.\nContará con un Consejo Técnico que coadyuvará en el debido funcionamiento y el ejercicio de las atribuciones del propio Instituto de Servicios Periciales y Ciencias Forenses, el cual será presidido por la persona titular de la Dirección General del Instituto de Servicios Periciales y Ciencias Forenses e integrado de la forma siguiente:\nI. Una persona titular de la Dirección General del Instituto de Servicios Periciales y Ciencias\nForenses;\nII. Una persona titular de la Subdirección del Instituto de Servicios Periciales y Ciencias Forenses;\nIII. Una persona titular de la Jefatura de Unidad Departamental del Instituto de Servicios\nPericiales y Ciencias Forenses; y\n\nIV. Tres peritos forenses, de los cuales uno será médico forense y dos especialistas en disciplinas forenses distintas.\nLa designación de los integrantes del Consejo Técnico estará a cargo del Consejo de la Judicatura, sujetándose a lo dispuesto en las siguientes fracciones:\nI. El Consejo Técnico se reunirá semestralmente, debiéndose renovar en su totalidad cada dos años con excepción del Director General, quien será miembro permanente y deberá presidir las reuniones mientras dure en su cargo;\nII. El Consejo Técnico será una instancia normativa de operación, control, supervisión y evaluación de las actividades técnicas periciales, así como de las de enseñanza e investigación.\nLos peritos asignados al Instituto de Servicios Periciales y Ciencias Forenses desempeñarán, en auxilio de la administración de justicia, las funciones establecidas por esta Ley y en el Reglamento Interno del\nInstituto.\nArtículo 251. El Consejo Técnico tendrá las siguientes atribuciones relacionadas con la actividad pericial del personal adscrito al Instituto de Servicios Periciales y Ciencias Forenses:\nI. Verificar y evaluar que los procesos técnicos periciales se ajusten a la normatividad nacional e internacional aplicable en la materia;\nII. Crear mecanismos que permitan vigilar y detectar errores y/u omisiones del orden técnico que influyan negativamente en el desarrollo de la investigación forense;\nIII. Instruir al personal pericial que se conduzca con apego a las normas institucionales, así como actuar de manera ética y con respeto a los derechos humanos durante el desarrollo de sus actividades profesionales;\nIV. Tratándose de sujetos vivos, vigilar que el personal pericial efectúe la entrevista con apego a las normas institucionales nacionales e internacionales de cada especialidad, obteniendo en su caso por escrito el consentimiento informado;\n\nV. Tratándose de cadáveres, vigilar que el personal pericial efectúe su actividad profesional apegado a las normas y técnicas de cada especialidad vigilando en todo momento el respeto y la dignidad del cadáver; y\nVI. En casos detectados de mala práctica pericial, el Comité se reunirá para analizar y evaluar cada caso en particular, que de ser confirmada aquella, se informará lo conducente al Comité de\nVigilancia del Consejo de la Judicatura.\nArtículo 252. El Instituto de Servicios Periciales y Ciencias Forenses, estará integrado por personas que ejerzan la Dirección General, de Servicios Periciales, de Tanatología, de Clínica y Laboratorios,\nAdministrativo, de Investigación y Enseñanza; subdirecciones de área, jefaturas de departamento y las demás personas servidoras públicas que se requieran para su correcto y adecuado funcionamiento.\nArtículo 253. Para desempeñar como Titular de la Dirección General del Instituto de Servicios Periciales y\nCiencias Forenses, se requiere:\nI. Tener la ciudadanía mexicana;\nII. Tener cuando menos treinta y cinco años de edad cumplidos el día de la designación;\nIII. Poseer título de Médico Cirujano registrado ante las autoridades competentes;\nIV. Acreditar estudios de posgrado (especialidad, maestría o doctorado) en la disciplina, exhibiendo en su caso la documentación correspondiente;\nV. Tener cuando menos siete años ininterrumpidos de práctica profesional en el Instituto de\nServicios Periciales y Ciencias Forenses;\nVI. Gozar de buena reputación; y\nVII. No haber sido condenado por sentencia definitiva por delito doloso alguno o estar inhabilitado.\nArtículo 254. Para desempeñar la Titularidad de la Dirección de Servicios Periciales, Tanatología, de Clínica y Laboratorios, Administrativo, y de Investigación y Enseñanza, se requiere:\n\nI. Tener la ciudadanía mexicana;\nII. Contar con treinta años de edad cumplidos al día de la designación;\nIII. Contar con estudios de licenciatura con título y cédula registrados ante autoridad competente sobre la materia a ejercer;\nIV. El ejercicio sobre la materia deberá ser de cinco años como mínimo, preferentemente en el\nInstituto de Ciencias Forenses;\nV. Haber cursado un posgrado (especialidad, maestría o doctorado) sobre la materia a ejercer acreditándolo con los documentos correspondientes;\nVI. Gozar de buena reputación; y\nVII. No haber sido condenado por sentencia definitiva por delito doloso alguno o estar inhabilitado.\nArtículo 255. Para desempeñar la Titularidad de cualquier Subdirección de área se requiere:\nI. Tener la ciudadanía mexicana;\nII. Contar con treinta años de edad cumplidos al día de la designación;\nIII. El ejercicio sobre la materia deberá ser de cuatro años como mínimo;\nIV. Contar como mínimo con estudios de licenciatura con título y cédula registrado ante autoridad competente sobre la materia a ejercer;\nV. Haber cursado una especialidad sobre la materia a ejercer acreditándolo con los documentos correspondientes;\nVI. Gozar de buena reputación; y\nVII. No haber sido condenado por sentencia definitiva por delito doloso alguno o estar inhabilitado.\n\nArtículo 256. Para desempeñar la Titularidad de una Jefatura de Departamento se requiere:\nI. Tener mínimo 30 años cumplidos al día de la designación;\nII. Deberá contar con 3 años de ejercicio en el Instituto de Ciencias Forenses;\nIII. Haber cursado una especialidad sobre la materia y contar con diploma y cédula profesional;\nIV. Gozar de buena reputación; y\nV. No haber sido condenado por sentencia definitiva por delito doloso alguno o estar inhabilitado.\nArtículo 257. Para desempeñar el cargo de Perito Médico Forense se requiere:\nI. Tener cuando menos 25 años de edad cumplidos el día de la designación;\nII. Poseer título y cédula de médico cirujano registrado ante las autoridades competentes;\nIII. Tener estudios de especialidad en la materia acreditándolo con diploma y cédula profesional;\nIV. No haber sido condenado por sentencia definitiva por delito doloso alguno o estar inhabilitado como perito; y\nV. Gozar de buena reputación.\nArtículo 258. Para ser perito auxiliar del Instituto de Servicios Periciales y Ciencias Forenses en las ramas de patología, antropología, química, odontología, entomología, psiquiatría, sicología, criminología, criminalística, fotografía, dactiloscopia y demás especialidades se requiere:\nI. Tener cuando menos veinticinco años de edad cumplidos el día de la designación;\n\nII. Poseer título y cédula profesional sobre la materia registrado ante autoridades competentes;\nIII. Haber cursado estudios de especialidad sobre la materia a ejercer acreditándolo con el diploma y cédula profesional correspondientes;\nIV. Gozar de buena reputación; y\nV. No haber sido condenado por sentencia definitiva por delito doloso alguno o estar inhabilitado como perito.\nArtículo 259. En relación al requisito para ocupar los cargos anteriormente señalados, relativo al no haber sido condenado por delito que amerite pena privativa de libertad de más de un año de prisión, cuando se tratare de robo, fraude, falsificación, abuso de confianza u otro que lastime seriamente la buena fama en el concepto público, lo inhabilitará para el cargo cualquiera que haya sido la pena.\nArtículo 260. La designación de las personas Titulares de la Dirección General, de las Direcciones y\nSubdirecciones será efectuada por la o el Presidente del Tribunal Superior de Justicia.\nArtículo 261. Son facultades y obligaciones del Director General del Instituto de Servicios Periciales y\nCiencias Forenses\nI. Cuidar que el Instituto se desempeñe eficazmente dictando al efecto los acuerdos complementarios que fueren convenientes;\nII. Formular anualmente el programa de trabajo y someterlo a la aprobación del Consejo de la\nJudicatura;\nIII. Convocar y presidir la junta de peritos médicos con el objeto de:\na) Estudiar los casos de singular importancia que se presenten;\nb) Examinar, por orden de la autoridad judicial, y decidir sobre dictámenes objetados;\nc) Formular planes para el desarrollo de actividades docentes, con la finalidad de mejorar la preparación teórica y práctica del personal con responsabilidades médico forenses;\n\nd) Implementar los acuerdos emitidos por el Pleno del Tribunal Superior de Justicia, así como adoptar los acuerdos para procurar la unidad de criterio en cuestiones relativas a la materia;\ne) Formular recomendaciones para el mejoramiento del servicio, y f) Llevar a cabo las actividades académicas y de investigación, con la finalidad de dotar de mayor capacidad técnica y profesional a las personas servidoras públicas y personal del\nInstituto.\nIV. Representar a este Instituto en los actos oficiales, así como designar a quien lo represente en congresos y otros eventos científicos relacionados con las ciencias forenses;\nV. Atender personalmente o por conducto del Titular de la Dirección de Tanatología, cuando lo considere necesario o conveniente, los casos urgentes que se presenten y, en su caso, determinar en estos casos quien debe suplir a los Peritos en sus faltas por enfermedad, licencia o vacaciones;\nVI. Remitir al Consejo de la Judicatura las solicitudes de licencia de los Titulares de las\nDirecciones, Subdirecciones, Jefaturas de Unidad Departamental, de los Peritos Médico\nForenses, de los Auxiliares en el Instituto de Ciencias Forenses y de los demás miembros del personal técnico y administrativo quien acordará lo procedente;\nVII. Informar al Consejo de la Judicatura de las faltas cometidas en el servicio por el personal técnico y administrativo;\nVIII. Rendir el último día hábil del mes de noviembre de cada año, al Consejo de la Judicatura el informe anual de las labores desarrolladas por el Instituto;\nIX. Solicitar al Consejo de la Judicatura el material y equipo necesarios para su adecuado funcionamiento;\nXI. Formular el proyecto del Reglamento Interno del Instituto de Ciencias Forenses y someterlo a la aprobación del Consejo de la Judicatura, el cual se encargará de la tramitación subsiguiente;\n\nXI. Formular planes de investigación científica, dándolos a conocer al Consejo de la Judicatura y previa autorización del mismo, fomentar su desarrollo; y\nXII. Las demás que señalen las leyes y reglamentos.\nArtículo 262. En casos de ausencia del Director General del Instituto de Servicios Periciales y Ciencias\nForenses, ya sea por enfermedad, vacaciones o por el desempeño de comisiones, informará oportunamente a quien presida el Consejo de la Judicatura quien, al autorizarla, aprobará en su caso al sustituto que el mismo Titular de la Dirección proponga.\nArtículo 263. Con excepción de los casos en que deben intervenir los médicos asignados a las Agencias\nInvestigadoras del Ministerio Público, a los hospitales públicos, a los reclusorios preventivos, de ejecución de sentencias y lugares de reclusión, los reconocimientos, análisis y demás trabajos médico forenses relacionados con los procedimientos judiciales serán desempeñados por los peritos médico forenses, quienes están obligados a concurrir a las juntas, audiencias y diligencias a las que fueren legalmente citados y a extender los dictámenes respectivos.\nArtículo 264. Las necropsias deberán practicarse, por regla general, en las instalaciones del Instituto de\nServicios Periciales y Ciencias Forenses, salvo los casos en que circunstancias especiales justifiquen lo contrario, a juicio del Titular de la Dirección General y de lo previsto en la legislación de procedimientos penales aplicable a la Ciudad de México. En estos últimos casos, éste podrá disponer que dos peritos médico forenses se constituyan fuera del Instituto para presenciar o practicar la necropsia o para verificar su resultado.\nArtículo 265. Cuando las partes objetaren el dictamen de los peritos médico forenses, la autoridad judicial dispondrá, cuando estime fundado el motivo que se alegue, que el Titular de la Dirección General del Instituto convoque a junta de peritos, con el objeto de que se discuta y decida si se ratifica o rectifica el dictamen de que se trate.\nArtículo 266. El Consejo de la Judicatura organizará y vigilará el correcto funcionamiento del Instituto de\nServicios Periciales y Ciencias Forenses para que éste desarrolle cabalmente sus labores de auxiliar de la administración de justicia.\nArtículo 267. Los médicos dependientes de la Dirección de Servicios de Salud de la Ciudad de México, asignados a las Agencias Investigadoras del Ministerio Público, serán auxiliares de las autoridades judiciales y de los agentes del Ministerio Público, en sus funciones médico forenses y tendrán la obligación\n\nde rendir los informes que les soliciten los órganos judiciales respecto de los casos en que oficialmente hubieren intervenido. En los mismos términos quedarán obligados los médicos adscritos a los hospitales públicos y a los reclusorios preventivos, de ejecución de sentencias y demás lugares de reclusión.\nArtículo 268. Son obligaciones de los médicos asignados a las Agencias Investigadoras del Ministerio\nPúblico:\nI. Proceder de inmediato, al reconocimiento y curación de los heridos que se reciban en la sección médica que esté a su cargo;\nII. Asistir a las diligencias de fe de cadáver y a todas las demás que sean necesarias o convenientes para la eficacia de la investigación;\nIII. Redactar el informe médico forense relacionado con la investigación y expedir las certificaciones que sean necesarias para la comprobación de los elementos del tipo penal;\nIV. Recoger y entregar los objetos y las substancias que puedan servir para el esclarecimiento del hecho que se investigue e indicar las precauciones con que deben ser guardados o remitidos a quien corresponda;\nV. Hacer en el certificado de lesiones, la descripción y la clasificación legal provisional o definitiva de las mismas;\nVI. Describir exactamente en los certificados de lesiones, las modificaciones que hubiere sido necesario hacer en ellas con motivo de su tratamiento, y\nVII. Las demás que les corresponden conforme a las leyes y reglamentos.\nArtículo 269. Son obligaciones de los médicos de hospitales públicos:\nI. Reconocer a los lesionados o enfermos que se reciban en el establecimiento y encargarse de su curación, expidiendo sin demora, cuando proceda, los certificados médico forenses correspondientes;\nII. Hacer en el certificado de lesiones, la descripción y clasificación legal provisional o definitiva de las mismas;\n\nIII. Practicar la necropsia de los lesionados que fallezcan en el hospital y se encuentren a disposición del Ministerio Público o de autoridades judiciales y extender el dictamen respectivo expresando con exactitud la causa de la muerte y los demás datos que sean útiles para la investigación;\nIV. Prestar los primeros auxilios y expedir los certificados correspondientes, en todos los casos de lesiones o de otros delitos que ocurrieren en el hospital y que requieran la intervención médico forense, y\nV. Las demás que señalen las leyes y reglamentos.\nArtículo 270. Las y los médicos adscritos a los reclusorios preventivos, de ejecución de sentencias y demás lugares de reclusión, deberán asistir a los internos enfermos y expedir los certificados que correspondan.\nIgualmente, prestarán los primeros auxilios en los casos de lesiones y de otros delitos que ocurrieren dentro de la prisión y que requieran la intervención médico forense, e intervendrán en cualquier diligencia judicial que ahí se practique, cuando para ello fueren requeridos por el Ministerio Público o la autoridad competente.\nArtículo 271. A los auxiliares de la administración de justicia a que se refiere este título, les serán aplicables las reglas establecidas en la presente Ley, en lo que fuere compatible, para los efectos de su designación, remoción y atribuciones.\nCAPÍTULO III\nDEL INSTITUTO DE ESTUDIOS JUDICIALES\nArtículo 272. El Instituto de Estudios Judiciales es un órgano dependiente de la o el Presidente del Tribunal\nSuperior de Justicia y tiene como objetivo coadyuvar en el fortalecimiento del servicio de impartición de justicia del propio Tribunal, mediante la formación y capacitación de las personas servidoras públicas jurisdiccionales y de apoyo judicial, desarrollando las competencias necesarias para llevar a cabo el buen desarrollo de sus atribuciones, así como a través de la implementación de procesos de selección, ratificación y evaluación de los cargos de la carrera judicial.\nEl Instituto tendrá una persona Titular de la Dirección General que deberá reunir los requisitos establecidos en el artículo 22 de esta Ley, a excepción de su fracción VI; además, contará con el personal necesario\n\npara el cumplimiento de sus objetivos. Las y los Jueces y Las y los Magistrados que así lo soliciten, se podrán incorporar al cuerpo docente del Instituto.\nEl funcionamiento y atribuciones del Instituto de Estudios Judiciales se regirán por el acuerdo respectivo, que expedirá el Consejo de la Judicatura.\nArtículo 273. El Instituto contará con un Consejo Académico integrado por cinco miembros: tres que se hayan desempeñado como Juzgadores o Titulares de una Magistratura y los dos restantes serán académicos con experiencia docente universitaria de cuando menos cinco años en las materias de las cuales conoce el Tribunal Superior de Justicia.\nEl Consejo tendrá a su cargo elaborar los programas de investigación, preparación y capacitación para los alumnos del Instituto, mecanismos de evaluación y rendimiento, que deberá someter a la aprobación del\nConsejo de la Judicatura.\nArtículo 274. Las Magistradas, Magistrados, Juzgadores y personas servidoras públicas de la administración de justicia del Tribunal, deberán acudir y participar en los programas de especialización y capacitación aprobados por el Consejo de la Judicatura. Los programas que imparta el Instituto de Estudios\nJudiciales tendrán como objeto lograr que los integrantes del Tribunal Superior de Justicia, o quienes aspiren a ingresar a éste, fortalezcan los conocimientos y habilidades necesarios para el adecuado desempeño de la función judicial. Para ello, el Instituto de Estudios Judiciales establecerá los programas y cursos tendientes a:\nI. Desarrollar el conocimiento práctico de los trámites, diligencias y actuaciones que forman parte de los procedimientos y asuntos de la competencia del Tribunal Superior de Justicia;\nII. Perfeccionar las habilidades y técnicas en materia de preparación y ejecución de actuaciones judiciales;\nIII. Reforzar, actualizar y profundizar los conocimientos respecto del ordenamiento jurídico positivo, doctrina y jurisprudencia;\nIV. Proporcionar y desarrollar técnicas y análisis, argumentación e interpretación que permitan valorar correctamente las pruebas y evidencias aportadas en los procedimientos, así como formular adecuadamente las actuaciones y resoluciones judiciales;\n\nV. Difundir las técnicas de organización en la función judicial;\nVI. Contribuir al desarrollo de la vocación de servicio, así como al ejercicio de los valores y principios éticos inherentes a la función judicial; y\nVII. Promover intercambios académicos con instituciones de educación superior.\nArtículo 275. El Instituto de Estudios Judiciales llevará a cabo cursos de preparación para los exámenes correspondientes a las distintas categorías que componen la Carrera Judicial.\nTÍTULO DÉCIMO SEGUNDO\nDEL SERVICIO CIVIL DE LA CARRERA JUDICIAL\nCAPÍTULO ÚNICO\nArtículo 276. La carrera judicial es el sistema que organiza los estudios e investigaciones de las diversas disciplinas jurídicas, dirigido al mejor desempeño de la función judicial y para hacer accesible la preparación básica para la presentación de exámenes de aptitud para cubrir las vacantes, por medio de los concursos de oposición correspondientes.\nLa carrera judicial se regirá por los principios de excelencia, objetividad, imparcialidad, profesionalismo e independencia, que deberán reunir los integrantes del Tribunal Superior de Justicia y las personas servidoras públicas a que se refiere este Título.\nEl ingreso se hará mediante concursos públicos de oposición a cargo del Instituto de Estudios Judiciales.\nLa permanencia estará sujeta al cumplimiento de los requisitos para el cargo, así como a la evaluación y vigilancia sobre el desempeño en los términos previstos en esta Ley y en los Acuerdos Generales que con arreglo a la misma, emita el Consejo Académico.\nArtículo 277. Los cargos judiciales son los siguientes:\nI. Pasante de Derecho;\nII. Secretaria o Secretario Actuario;\n\nIII. Oficial Notificadora o Notificador;\nIV. Secretaria o Secretario Proyectista de Juzgado;\nV. Secretaria o Secretario Conciliador;\nVI. Secretaria o Secretario Auxiliar de Juzgado de Proceso Oral en materia Familiar;\nVII. Secretaria o Secretaria de Acuerdos de Juzgado;\nVIII. Secretaria o Secretario Judicial de Juzgado de Proceso Oral en materia Familiar;\nIX. Secretaria o Secretario Auxiliar de Sala;\nX. Secretaria o Secretario de Acuerdos de Sala;\nXI. Secretaria o Secretario Proyectista de Sala;\nXI Bis. Secretaria o Secretario Instructor de Tribunales Laborales;\nXII. Jueza o Juez; y\nXIII. Magistrada o Magistrado\nArtículo 278. Salvo los nombramientos de Magistradas, Magistrados y Juzgadores, la designación de los cargos judiciales se llevará a cabo por el órgano judicial en donde se origine la vacante, previo examen de aptitud, en los términos de esta Ley.\nArtículo 279. Las designaciones que deban hacerse en las plazas vacantes de Juzgadores, ya sea definitivas o con carácter de interino, deberán ser cubiertas mediante concurso interno de oposición o de oposición libre en la proporción que fije el Pleno del Consejo de la Judicatura. En ambos casos el concurso será público.\nAdemás de los exámenes de conocimiento a que se refiere este artículo, a los candidatos se les aplicara examen psicométrico.\n\nLos concursos internos de oposición y los de oposición libre se sujetarán al procedimiento establecido en el reglamento que para tales efectos expida el Consejo de la Judicatura.\nArtículo 280. La organización y aplicación de los exámenes de aptitud para las personas servidoras públicas judiciales, estará a cargo del Instituto de Estudios Judiciales en términos de las bases que determine el\nConsejo de la Judicatura y de conformidad con lo que disponen esta Ley y el reglamento respectivo.\nLos exámenes de aptitud se realizarán a petición del Titular del órgano que deba llevar a cabo la correspondiente designación, debiendo preferir a quienes se encuentren en las categorías inmediatas inferiores.\nArtículo 281. Los exámenes para determinar la aptitud de los servidores públicos señalados en el artículo anterior serán elaborados por un Comité integrado por un miembro del Consejo de la Judicatura, quien lo presidirá, por una Magistrada o Magistrado, un Juzgador de primera instancia y un miembro del Comité\nAcadémico apoyado por el personal del propio Instituto de Estudios Judiciales.\nTratándose de conocimientos que se aplicarán en la impartición de justicia, el Comité será presidido por una Magistrada o Magistrado. La designación de los miembros del Comité se hará en los términos que establezca el reglamento respectivo.\nArtículo 282. El jurado encargado de aplicar los instrumentos de evaluación en los concursos de oposición se integrará por:\nI. Un miembro del Consejo de la Judicatura, quien lo presidirá;\nII. Una Magistrada o Magistrado que haya sido ratificado y sea integrante de una sala afín a la materia que se va a examinar;\nIII. Un Juzgador ratificado que ejerza funciones en la materia que se va a examinar y;\nIV. Una persona designada por el Instituto de Estudios Judiciales de entre los integrantes de su\nComité Académico.\n\nLos miembros del jurado estarán impedidos de participar en los concursos a que se refiere este artículo en caso de tener algún vínculo de tipo moral, laboral o económico con cualquiera de los interesados. Estos impedimentos serán calificados por el propio jurado.\nArtículo 283. Para la ratificación de Juzgadores y, en lo que resulte aplicable en la opinión sobre la propuesta de designación o ratificación de Magistradas y Magistrados, el Consejo de la Judicatura tomará en consideración los elementos siguientes:\nI. El desempeño que se haya tenido en el ejercicio de su función;\nII. Los resultados de las visitas de inspección;\nIII. Los diversos cursos de actualización y especialización acreditados de manera fehaciente, y tratándose de jueces, también la aprobación del examen de actualización;\nIV. No haber sido sancionado por falta grave, con motivo de una queja de carácter administrativo;\nV. Los demás que estime pertinentes, siempre que consten en acuerdos generales publicados con seis meses de anticipación a la fecha de la ratificación, y\nVI. Aquellos elementos que presente el evaluado por escrito.\nTÍTULO DÉCIMO TERCERO\nDE LA SUSTITUCIÓN EN CASO DE IMPEDIMENTOS, RECUSACIONES Y\nEXCUSAS CAPÍTULO ÚNICO\nArtículo 284. Si un Juzgador deja de conocer un caso por impedimento, recusación o excusa, remitirá el expediente a la Dirección General de Procedimientos Judiciales, para que lo envíe al Juzgado que corresponda, de acuerdo con el turno respectivo.\nArtículo 285. Si el Juzgador deja de conocer un caso por impedimento, recusación o excusa, remitirá el expediente a la Unidad de Gestión Judicial, para que ésta lo envíe al Tribunal de Alzada que corresponda conocer y resolver de las excusas y recusaciones de los Jueces de Control, Tribunal de Enjuiciamiento y\nJueces de Ejecución de la Ciudad de México, de acuerdo con el turno respectivo.\n\nArtículo 286. Si una Magistrada o Magistrado dejare de conocer de algún asunto por impedimento o recusación, conocerá de éste su igual mediante el turno que lleve la Presidencia del Tribunal Superior de\nJusticia.\nCuando los tres Magistrados que integran una Sala estuvieren impedidos de conocer un negocio, pasará éste al conocimiento de la Sala que en la misma materia le sigue en número.\nSi todas las Salas o Magistrados del ramo estuvieren impedidos de conocer, pasará el asunto al conocimiento de las Salas de otro ramo, por el orden indicado y si también éstas se agotaren, se integrará una Sala que conozca del asunto con Juzgadores penales, civiles, familiares, de justicia para adolescentes, de extinción de dominio, según corresponda, designados por el Tribunal Superior de Justicia en Pleno que al efecto se reunirá inmediatamente y sin perjuicio de sus demás labores y funciones.\nTÍTULO DÉCIMO CUARTO\nDE LAS RESPONSABILIDADES OFICIALES\nCAPÍTULO I\nDE LAS RESPONSABILIDADES DE LAS PERSONAS SERVIDORAS\nPÚBLICAS DE LA ADMINISTRACIÓN DE JUSTICIA\nArtículo 287. Las o los Magistrados del Tribunal Superior de Justicia, las o los Consejeros de la Judicatura, las o los Jueces, la o el Visitador General, las o los Visitadores Judiciales, así como todas o todos los servidores públicos de la administración de justicia, son responsables de las faltas que cometan en el ejercicio de sus cargos y quedan por ello sujetos a las sanciones que determinen la presente Ley, la ley en materia de responsabilidades administrativas y demás disposiciones jurídicas aplicables.\nEl órgano encargado de sustanciar los procedimientos e imponer las sanciones por faltas de las personas servidoras públicas de la administración de justicia del fuero común en la Ciudad de México, es el Consejo de la Judicatura, por conducto de la Comisión de Disciplina Judicial en primera instancia y en términos del reglamento que establezca su funcionamiento.\nEl Consejo de la Judicatura resolverá, en definitiva, en los términos de esta Ley y de la Ley de\nResponsabilidades de los Servidores Públicos de la Ciudad de México, mediante la substanciación del recurso de inconformidad previsto en esta ley.\n\nLos Magistrados del Tribunal Superior de Justicia y los Consejeros de la Judicatura, solo podrán ser removidos de sus puestos en la forma y términos que determina el Título Cuarto de la Constitución Política de los Estados Unidos Mexicanos.\nArtículo 288. Las Magistradas y Magistrados, así como las y los Jueces del Poder Judicial de la Ciudad de\nMéxico, serán responsables de la interpretación o inaplicación de disposiciones jurídicas por virtud del control difuso y del control de convencionalidad, cuando se compruebe que hubo cohecho o mala fe.\nArtículo 289. Serán causas de responsabilidad para las personas servidoras públicas del Poder Judicial de la Ciudad de México:\nI. Realizar conductas que atenten contra la independencia de la función judicial, tales como aceptar o ejercer consignas, presiones, encargos o comisiones, o cualquier acción que genere o implique subordinación respecto de alguna persona, del mismo u otro poder;\nII. Inmiscuirse indebidamente en cuestiones de orden jurisdiccional que competan a otros órganos de poder del Distrito Federal, de otros Estados de la República o de la Federación;\nIII. Tener una notoria ineptitud o descuido en el desempeño de las funciones o labores que deban realizar;\nIV. Impedir en los procedimientos judiciales que las partes ejerzan los derechos que legalmente les corresponden;\nV. Conocer de algún asunto o participar en algún acto para el cual se encuentren impedidos;\nVI. Realizar nombramientos promociones o ratificaciones infringiendo las disposiciones generales correspondientes;\nVII. No hacer del conocimiento del Consejo de la Judicatura, cualquier acto tendiente a vulnerar la independencia de la función judicial o que implique infracción a las obligaciones que tienen los servidores públicos del poder judicial;\nVIII. No preservar la dignidad, imparcialidad y profesionalismos propios de la función judicial en el desempeño de sus labores;\n\nIX. Emitir opinión pública que implique prejuzgar sobre un asunto de su conocimiento;\nX. Abandonar el local del juzgado, sala, ponencia u oficina al que se encuentre adscrito o dejar de desempeñar las funciones y labores que tenga a su cargo;\nXI. Abandonar sin causa justificada los estudios respecto de los cuales se le hubiere otorgado una beca por parte del Tribunal, del Consejo, o de cualquier otra de o las instituciones con los que éstos tengan convenio;\nXII. Dejar de asistir sin causa justificada a sus labores o incumplir el horario de trabajo establecido para el Poder Judicial de la Ciudad de México;\nXIII. Incumplir las disposiciones establecidas en la Constitución Política de los Estados Unidos\nMexicanos, de la Constitución, así como otras de índole legal y reglamentarias en materia de propaganda y de informes de labores o de gestión; y\nXIV. Las demás que determine esta Ley, la Ley de Responsabilidades Administrativas de la Ciudad de México y demás reglamentos, acuerdos generales, circulares, manuales de procedimiento y normatividad que le resulte aplicable, de acuerdo con sus funciones.\nArtículo 290. Las personas que hayan laborado como personas servidoras públicas del Poder Judicial de la\nCiudad de México, ya sea con carácter de provisional, interino o definitivo, no podrán, dentro de los dos años siguientes a la fecha de su retiro, actuar como patronos, abogados o representantes en cualquier proceso ante los órganos del mismo.\nLos impedimentos de este artículo serán aplicables a los funcionarios judiciales que gocen de licencia.\nLa infracción a este último párrafo, será sancionada con la destitución del cargo dentro del Poder Judicial de la Ciudad de México, así como de las prestaciones y beneficios que en lo sucesivo correspondan pro el mismo, independientemente de las demás sanciones que las leyes prevean.\nArtículo 291. El procedimiento para determinar las responsabilidades de las personas servidoras públicas de la administración de justicia de la Ciudad de México, se iniciará de oficio; por denuncia presentada por cualquier persona; por queja presentada en términos del artículo 288 de esta Ley; por petición de la Fiscalía de Investigación de los Delitos cometidos por Servidores Públicos de la Procuraduría General de Justicia\n\nde la Ciudad de México o bien derivadas de las visitas judiciales practicadas a los órganos jurisdiccionales en los términos de éste artículo.\nLas denuncias a que se refiere el párrafo anterior podrán efectuarse de forma anónima, escrita, vía telefónica o por cualquier medio electrónico cuyo único requisito para su trámite es que se establezcan de forma clara circunstancias de modo, tiempo y lugar, y permitan identificar o hacer identificables a las personas servidoras públicas involucradas. Las denuncias que se formulen se podrán acompañar de las pruebas documentales o elementos probatorios suficientes que permitan a la sección de la Comisión de\nDisciplina Judicial, para determinar la existencia de la irregularidad que se atribuye a la persona servidora pública denunciada.\nEn caso de no contar con documentos fehacientes relacionados con los hechos denunciados, por encontrarse en poder de las instancias de la administración de justicia de la Ciudad de México, bastará con que el denunciante manifieste su imposibilidad para presentarlas, para que la Comisión de Disciplina\nJudicial, pueda requerirlos en el momento que resulte oportuno.\nArtículo 292. El recurso de inconformidad tiene por objeto que el Pleno del Consejo de la Judicatura confirme, revoque o modifique la resolución dictada por la Comisión de Disciplina Judicial.\nEl término para interponer el recurso de inconformidad será de cinco días hábiles, contados a partir del día siguiente en que le sea hecha la notificación de la resolución que se recurre.\nDicho recurso deberá presentarse por escrito ante la propia Comisión de Disciplina Judicial, debiendo contener los siguientes requisitos:\nI. El nombre y firma del recurrente, así como el domicilio para oír y recibir notificaciones y documentos;\nII. Señalar la resolución administrativa que se impugna, precisando los datos de identificación del procedimiento del que deriva la resolución, y\nIII. Los motivos de inconformidad que considere en contra de la resolución que se recurre.\nLa interposición de dicho recurso tendrá como efecto la suspensión de la ejecución de la resolución recurrida hasta en tanto se resuelva éste por el Pleno del Consejo de la Judicatura.\n\nArtículo 293. La persona servidora pública dispondrá de un término de tres días hábiles, contados a partir del día siguiente a la notificación de la resolución recurrida, para interponer el recurso.\nEl recurso de inconformidad deberá presentarse por escrito ante la propia Comisión de Disciplina, conteniendo los siguientes requisitos:\nI. El nombre y firma de la o del recurrente, así como el domicilio para oír y recibir notificaciones;\nII. Precisar la resolución administrativa que se impugna, así como la fecha en que fue notificado de la misma; y\nIII. Los motivos de inconformidad que considere le cause la resolución impugnada y los argumentos de derecho en contra de la resolución que se recurre.\nArtículo 294. En caso de que sea admitido a trámite dicho recurso, la interposición de éste tendrá como efecto el que la resolución recurrida no sea ejecutada hasta en tanto no sea resuelto en definitiva por el\nPleno del Consejo de la Judicatura.\nLa suspensión de la ejecución de la resolución de primera instancia que se decrete al resolver el recurso de inconformidad, tendrá el efecto de impedir que se realicen aquellos actos que afecten o causen agravio en la esfera jurídica de la o del servidor público declarado responsable. Asimismo, no podrá inhibirse del conocimiento del asunto del que devenga la queja, hasta en tanto el fallo que resuelva el recurso de inconformidad cause ejecutoria.\nArtículo 295. Siempre que se presente una denuncia o queja en contra de alguna o algún servidor público de la administración de justicia, la Comisión de Disciplina Judicial, formará inmediatamente el expediente respectivo con expresión del día y hora en que se reciba la queja, a efecto de que concluya inexcusablemente por resolución dentro de un término no mayor de veintidós días hábiles, para la primera instancia, y de treinta días hábiles para la segunda y definitiva, en su caso.\nEl término de veintidós días hábiles que refiere este artículo, comenzará a correr una vez que se cierre la etapa de instrucción y sea materialmente entregado el expediente a la o al Consejero Ponente para su análisis y resolución correspondiente.\n\nLas o los Consejeros que no emitan la resolución en los términos que para ese efecto se fijan en este artículo, estarán sujetos a las mismas responsabilidades a que están sujetos las y los Magistrados y\nJuzgadores.\nLa Contraloría Interna será la encargada de sustanciar el procedimiento respectivo e imponer las sanciones que en su caso correspondan.\nArtículo 296. La o el Presidente turnará el recurso de inconformidad a la o al Consejero que corresponda, que en ningún caso podrá ser aquél que haya resuelto el asunto en primera instancia; a fin de elaborar el proyecto respectivo y presentarlo ante el Pleno del Consejo de la Judicatura en la sesión correspondiente para su discusión y de ser procedente su aprobación.\nEl Pleno del Consejo de la Judicatura confirmará, revocará o modificará la resolución dictada por la\nComisión de Disciplina Judicial y resolverá en forma definitiva e inatacable.\nArtículo 297. El Consejo de la Judicatura, por medio de la Comisión de Disciplina Judicial, deberá substanciar el expediente relativo, solicitando un informe a la o al servidor público denunciado, quien deberá rendirlo por escrito en un plazo no mayor de tres días hábiles, contados a partir del día siguiente a la notificación, en el que podrá ofrecer las pruebas que estime necesarias.\nEn cualquier etapa del proceso disciplinario, se podrá acordar la suspensión temporal de la o del servidor público involucrado en su cargo, empleo o comisión, si a juicio del Pleno del Consejo de la Judicatura, existiera causa grave que así lo amerite, fundando y motivando la decisión; determinar de manera fundada y motivada el criterio razonado, el porcentaje de salario que le deba corresponder durante dicha suspensión.\nLa suspensión temporal no prejuzga sobre la determinación final que se tome. Si la o el servidor público temporalmente suspendido no resultare responsable de la falta que se le haya imputado, será restituido en el goce de sus derechos, debiéndosele cubrir en lo inmediato las percepciones que debió recibir durante la suspensión, más una indemnización equivalente a las dos terceras partes del periodo que haya durado la suspensión.\nLa suspensión temporal no prejuzga sobre la determinación final que se tome. Si la persona servidora pública temporalmente suspendida, no resultare responsable de la falta que se le haya imputado, será restituido en el goce de sus derechos, y se le cubrirá las percepciones que debió recibir durante la\n\nsuspensión. La suspensión temporal cesará cuando así lo determine el Pleno del Consejo de la Judicatura o hasta que se emita en el mismo procedimiento, la resolución de primera instancia.\nEntre tanto, se substancia el procedimiento disciplinario y una vez suspendido temporalmente al presunto infractor, el Pleno del Consejo deberá proveer respecto de la persona servidora pública que en forma interina deberá suplirlo.\nArtículo 298. Tienen acción para denunciar la comisión de faltas de las personas servidoras públicas de la administración de justicia de la Ciudad de México:\nI. Las partes en el juicio en que se cometieren;\nII. Las personas físicas o morales a quienes se les haya desconocido indebidamente la calidad de parte, en los casos de la fracción V del artículo 347 de esta Ley;\nIII. Las y los abogados de las partes en los casos de responsabilidades provenientes de hechos u omisiones cometidas en el juicio en que intervengan, siempre que tengan título legalmente expedido y registro en la Dirección General de Profesiones;\nIV. El Ministerio Público en los negocios en que intervenga;\nV. Las y los Jueces y Titulares de Magistraturas de la Ciudad de México en materia Familiar en los negocios de su competencia o en aquellos relacionados directamente con los mismos o que afecten los intereses de menores e incapaces, así como respecto de aquellas conductas de sus subalternos, que sean contrarias a lo que esta Ley y demás disposiciones aplicables establecen;\nVI. Las y los Jueces y los titulares de Magistraturas, en las demás materias, en los asuntos de su competencia, y de todas aquellas conductas de sus subalternos, que sean contrarias a lo que esta\nLey y demás disposiciones aplicables establecen; y\nVII. Las organizaciones de profesionales en Derecho constituidas legalmente, por conducto de sus representantes legítimos, quienes lo harán a nombre de la organización de que se trate.\nArtículo 299. Cualquier integrante del Consejo de la Judicatura de la Ciudad de México, tomando en cuenta la gravedad de la irregularidad observada en las visitas practicadas a los Juzgados o Salas, solicitará a la\nComisión de Disciplina Judicial lleve a cabo de oficio el procedimiento señalado en esta ley.\n\nLa Comisión de Disciplina Judicial deberá informar al Pleno del Consejo la resolución correspondiente.\nEl Pleno del Tribunal Superior de Justicia está facultado para supervisar en todo tiempo la secuela procesal.\nArtículo 300. La Comisión de Disciplina Judicial tiene como función primordial, conocer las conductas de los servidores públicos y resolver, en su caso, la responsabilidad administrativa de los mismos, a fin de lograr un ejercicio responsable, profesional e independiente en la función jurisdiccional, así como evitar actos que la demeriten.\nArtículo 301. La Comisión de Disciplina Judicial tiene las siguientes atribuciones:\nI. Conocer en primera instancia de todos los procedimientos administrativos de responsabilidad en contra de los servidores públicos de la administración de justicia, en términos de esta Ley;\nII. Conocer de los asuntos en materia de responsabilidad que someta a su consideración la\nContraloría; y\nIII. Las demás que establezcan esta Ley y el Pleno del Consejo de la Judicatura.\nArtículo 302.La Comisión de Disciplina Judicial para su mejor funcionamiento estará integrada por tantas secciones como Consejeras y Consejeros que se encuentren en activo y funcionarán de forma simultánea.\nArtículo 303. El Pleno del Consejo de la Judicatura determinará mediante un acuerdo plenario los siguientes aspectos:\n1. El número y la forma en que se organizarán las Secciones, cuyo orden se asignará por el número consecutivo de ponencia que corresponda, mismas que deberán estar integradas por tres Consejeras o Consejeros cada una, con excepción de la o del presidente del Consejo, en los términos del artículo 219 fracción IV de esta Ley;\n2. El procedimiento, plazos y términos para que las Secciones emitan la resolución correspondiente en los términos de esta Ley.\n\nArtículo 304. Las resoluciones que se presenten a través del trabajo colegiado en las secciones de la\nComisión de Disciplina Judicial se tomarán por el sistema de votación que, según el caso, deberá quedar asentado en el acuerdo contenido en el acta respectiva que al efecto se emita, siendo el siguiente:\nI. Por unanimidad;\nII. Por mayoría de votos, en cuyo caso la o el Consejero disidente, presentará en un término de tres días hábiles su voto particular por escrito ante la Secretaría Técnica de la Comisión de\nDisciplina Judicial, debiendo versar sobre los puntos que generan el disenso y que deberá engrosarse al cuerpo del acta de la sesión que corresponda.\nEn caso de que el proyecto presentado por una o un Consejero sea desechado por la mayoría, será returnado a otro para que formule un nuevo proyecto, mismo que se presentará a la Sección de la Comisión de Disciplina Judicial correspondiente, dentro de los cinco días hábiles siguientes.\nEl Pleno del Consejo de la Judicatura calificará de plano las excusas o impedimentos de los miembros integrantes de la Comisión de Disciplina Judicial.\nArtículo 305. La interposición de recursos de revisión en materia de amparo y cumplimiento de ejecutorias de juicios de garantías le corresponderán a la o el Consejero que hubiere dictado la resolución en el procedimiento administrativo de origen.\nArtículo 306. Las y los Consejeros, a excepción de quien ocupe la Presidencia, desahogaran semanalmente y por orden alfabético el trámite de las quejas y procedimientos de oficio hasta ponerlos en estado de resolución, turnándolas a la o el Consejero de la Sección que corresponda.\nCorrespondiendo a la o el Consejero semanero acordar todos los escritos, oficios y documentos que se hubieren recibido en la Oficialía de Partes de la Comisión de Disciplina Judicial durante la semana que le corresponde.\nArtículo 307. Para realizar las actividades que le compete, la Comisión de Disciplina Judicial contará con una persona Secretaria Técnica que asistirá y dará fe de las actuaciones de las y los Consejeros, ya sea por semanería o por sección, según sea el caso.\nArtículo 308. A quien ocupe la Secretaría Técnica de la Comisión de Disciplina Judicial le corresponde:\n\nI. Autorizar con su firma en los asuntos en materia de responsabilidad que se tramiten ante la\nComisión de Disciplina Judicial;\nII. Someter a la consideración del Pleno, las disposiciones, reglas, bases de carácter general, normas, lineamientos y políticas, en el ejercicio de las atribuciones que competan a la Comisión de Disciplina Judicial;\nIII. Auxiliar en la substanciación de las quejas administrativas y procedimientos de responsabilidad oficiosos que competa conocer y resolver a la Comisión de Disciplina Judicial, a través de sus secciones y a la o al Consejero semanero;\nIV. Dar cuenta, dentro del término de veinticuatro horas, a la o al Consejero semanero, con las promociones que se hicieren en los procedimientos respectivos. Para tal efecto, hará constar en los expedientes el día y hora en que se presenten los escritos relativos;\nV. Vigilar que los expedientes sean foliados al agregarse cada una de las hojas, rubricadas todas éstas en el centro del escrito o promoción, y asentado el sello de la secretaría en el centro del cuaderno, de manera que abarque las dos caras, y en su caso con el sello del Boletín correspondiente;\nVI. Asistir a la o al Consejero semanero en el desahogo de las audiencias señaladas en los procedimientos disciplinarios;\nVII. Enviar diariamente la lista de los acuerdos emitidos en los procedimientos disciplinarios que deban ser publicados en el Boletín Judicial;\nVIII. Suscribir y autorizar los documentos relativos al ejercicio de sus atribuciones, cotejar las copias o testimonios de constancias que se manden expedir, previo acuerdo, y autorizar con su firma y el sello correspondiente;\nIX. Ordenar y vigilar que se despachen sin demora los asuntos y correspondencia de cada una de las Secciones de la Comisión de Disciplina Judicial, desahogando las notificaciones ordenadas por éstas en los expedientes de que conozcan o de lo que determine la o el Consejero semanero en turno;\n\nX. Enviar los oficios mediante los cuales se requiera informe justificado a las personas servidoras públicas del Tribunal y del Consejo, así como las demás comunicaciones necesarias para el desahogo de las pruebas y notificaciones respectivas;\nXI. Firmar las actas que en la primera semana de cada mes, las o los Titulares de las secciones levanten en relación con los asuntos sujetos a su resolución; el sentido de las resoluciones, y de los acuerdos emitidos durante el mes inmediato anterior;\nXII. Vigilar que los expedientes que se turnen para resolución, se encuentren debidamente acompañados de sus antecedentes, así como verificar que los expedientes para audiencia, se encuentren debidamente integrados;\nXIII. Realizar los trámites necesarios ante la Secretaría General del Consejo, a fin de que se ejecuten las sanciones acordadas por la Comisión de Disciplina Judicial; y\nXIV. Las demás que determine el Pleno del Consejo de la Judicatura, la Comisión de Disciplina\nJudicial y las disposiciones legales aplicables.\nArtículo 309.La Comisión de Disciplina Judicial conocerá de los procedimientos disciplinarios cuyo propósito es determinar, en su caso, la responsabilidad administrativa de las y los servidores públicos de la administración de justicia, la que resolverá en primera instancia.\nEn los procedimientos administrativos disciplinarios derivados de faltas y de la inobservancia a las obligaciones previstas en las leyes sustantivas y adjetivas y reglamentos de la materia, así como las fijadas en esta Ley, se observará el trámite conducente en la misma.\nArtículo 310. El procedimiento de oficio derivará de irregularidades observadas en las visitas de inspección practicadas a los órganos jurisdiccionales que integran al Tribunal Superior de Justicia, o de las que se tenga conocimiento por otro medio, así como las que se desprendan del ejercicio de la función de las o los servidores públicos de la administración de justicia.\nArtículo 311. La Comisión de Disciplina Judicial, a través de la o del Consejero semanero en turno substanciará, semanalmente y por orden progresivo, el trámite de las quejas y los procedimientos de oficio hasta ponerlos en estado de resolución, en términos de esta Ley.\n\nArtículo 312. La Comisión de Disciplina Judicial a través de la o del Consejero semanero o de la o del\nConsejero de la sección que corresponda, podrá decretar la práctica de diligencias para mejor proveer y, en su caso, ordenar que se subsane toda omisión que notare en la sustanciación para el efecto de regularizar el procedimiento.\nArtículo 313. Las quejas que se presenten por las faltas en que presuntamente hayan incurrido las o los\nMagistrados, las y los Consejeros, las y los Jueces, así como las y los demás servidores públicos de la administración de justicia, se harán constar por escrito, para su debida tramitación, las cuales en todo caso deberán contener nombre, firma y domicilio de la o del denunciante, y se harán bajo protesta de decir verdad.\nLas quejas que se formulen deberán estar apoyadas en pruebas documentales o elementos probatorios suficientes para establecer la existencia de la falta y presumir la responsabilidad de la o del servidor público denunciado.\nArtículo 314. Los escritos que se presenten para denunciar las presuntas faltas administrativas cometidas por las personas servidoras públicas del Tribunal Superior de Justicia, deberán contener los requisitos previstos en el artículo 313 de ésta Ley Orgánica. En caso de que no reúnan algunos de ellos, se prevendrá a la o al promovente para que dentro del término de tres días, lo subsane, sino lo hiciere, se tendrá por no interpuesto el escrito de queja, dejando a salvo sus derechos para que los haga valer en la vía y forma que estime pertinente.\nTambién podrá prevenirse a la o al promovente, en los mismos términos del párrafo anterior, cuando de la atenta lectura de su escrito, no sea posible ubicar con precisión cuales son los hechos que motivan su inconformidad, así como a la persona servidora pública a quien los imputa. El único efecto que tendrá dicha prevención será que se precisen concretamente las conductas que se pretenden denunciar y a qué persona servidora pública se le atribuyen, apercibiéndosele que de no hacerlo en el término de tres días se tendrá por no interpuesta. La Comisión de Disciplina Judicial de ninguna manera queda limitada, ni ligada, por la calificación jurídica que a la o al promovente haga de los hechos.\nLas quejas o denuncias que sean notoriamente jurisdiccionales se desecharán de plano.\nArtículo 315. Los escritos que presenten las personas no comprendidas dentro de la enumeración del artículo 298 de esta Ley, se tramitarán de la siguiente forma:\n\nI. El escrito deberá reunir los requisitos mencionados en el primer párrafo del artículo anterior.\nSi adolece de alguno de ellos se prevendrá a la o al promovente en los términos expuestos, apercibiéndosele que de no hacerlo en el término de tres días se tendrá por no interpuesta;\nII. Admitido a trámite, la o el Consejero semanero requerirá a la persona servidora pública denunciada, para que, en un término de tres días, contados a partir del día siguiente al de la notificación, rinda un informe al respecto, al que deberán, en su caso, adjuntar las constancias que estimen pertinentes para sustentarlo;\nIII. Si cualquiera de las o los Titulares de las secciones que integran la Comisión de Disciplina\nJudicial, estima que son necesarios mayores elementos de convicción, podrá ordenar las diligencias que considere pertinentes para allegárselos;\nIV. Una vez que se rinda el informe precitado, la Comisión de Disciplina Judicial, después de valorar las constancias del expediente respectivo, si estima que existen elementos que hagan probable la realización de una falta administrativa, iniciará de oficio el procedimiento administrativo correspondiente; y\nV. En caso de que la Comisión de Disciplina Judicial estime que no se desprende ninguna falta, se archivará el asunto como concluido. Esta determinación deberá notificarse por Boletín\nJudicial.\nArtículo 316. Cuando alguna o alguno de los interesados a que se refiere la fracción III del artículo 298 de esta Ley, que promuevan la queja en nombre y representación de una persona física o moral, su personalidad será reconocida en el procedimiento de queja para todos los efectos legales, siempre que compruebe tal circunstancia con las constancias respectivas.\nArtículo 317. La o el Consejero semanero, así como los integrantes de la Comisión de Disciplina Judicial, para hacer cumplir sus determinaciones podrán hacer uso de los medios de apremio previstos en el Código\nNacional de Procedimientos Penales, de aplicación supletoria.\nAsimismo, las o los Consejeros para preservar el orden, así como el respeto y consideración que les corresponde, durante las audiencias o la realización de cualquier tipo de diligencia, podrán aplicar las correcciones disciplinarias previstas en el Código Nacional de Procedimientos Penales, de aplicación supletoria\n\nArtículo 318. Procede la acumulación en los casos en que se estén substanciando varias quejas contra un mismo servidor o servidora pública del Consejo de la Judicatura o del Tribunal Superior de Justicia, por los mismos hechos o cuando exista identidad de las partes y los hechos guarden estrecha relación. Se acumularán aquellas en que no se hubiera pronunciado resolución y se resolverán en un mismo fallo, debiendo conocer de ellas la o el Consejero que primero hubiere conocido de alguna, mediante turno.\nArtículo 319. Si la Comisión de Disciplina no encontrare motivos de improcedencia, o se hubiesen llenado los requisitos omitidos, se admitirá el escrito de queja, y en mismo auto, pedirá a las o a los servidores públicos, que dentro del término de tres días rindan el informe con justificación en el que expondrán las razones y fundamentos legales que estimen pertinentes, para sostener la legalidad del acto o conducta que se denuncia y acompañarán, en su caso, copia certificada de las constancias que sean necesarias para apoyar dicho informe; señalará día y hora para la celebración de la audiencia, dentro del término de diez días, y dictará las demás providencias que procedan con arreglo a esta ley.\nArtículo 320. El término de veintidós días hábiles que refiere el artículo 295 de la Ley, comenzará a correr, a partir del día siguiente en que hubiera surtido sus efectos el emplazamiento o notificación del acuerdo en el que se hace del conocimiento del quejoso y servidores públicos involucrados, la apertura o inicio del procedimiento y el término para que dichos servidores públicos rindan informe con justificación.\nUna vez iniciado dicho término sólo podrá interrumpirse por acuerdo de la o el Consejero semanero dictado con una antelación de por lo menos diez días hábiles a su conclusión, siempre y cuando así lo requiera la preparación y desahogo de las pruebas admitidas. Concluido el trámite por el que se decretó la interrupción del término, continuará éste.\nArtículo 321. Las o los secretarios actuarios, adscritos a la Comisión de Disciplina Judicial, deberán practicar las notificaciones dentro de las setenta y dos horas siguiente al en que reciban las constancias, devolviendo los expedientes dentro de las veinticuatro horas siguientes, previas las anotaciones en el libro respectivo.\nArtículo 322. Las notificaciones en los procedimientos de responsabilidad ya sea por denuncia, queja o de oficio, se harán:\nI. Personalmente a las o los quejosos, cuando se trate de requerimientos o prevenciones que se le formulen;\n\nII. A las o los quejosos, apoderados, procuradores, defensores, representantes, personas para oír y recibir notificaciones por medio de Boletín Judicial, cuando se trate de determinaciones de mero trámite;\nIII. A las personas servidoras públicas, sujetas a procedimiento, por medio de cédula, que será ejecutado en el domicilio de su oficina o, en su caso, en el domicilio particular, y sólo en caso de imposibilidad permanente para ello, se les notificará en el domicilio particular, tratándose del requerimiento del informe con justificación, y de la resolución que finque responsabilidad administrativa y tratándose del requerimiento del informe con justificación, y de la resolución que finque responsabilidad administrativa; y\nIV. Personalmente a las partes, cuando se haya dejado de actuar por más de seis meses sin causa justificada; tratándose de asuntos de importancia y trascendencia a juicio del Consejo de la\nJudicatura.\nArtículo 323. Las notificaciones personales se harán conforme a las siguientes reglas:\nI. Cuando deban hacerse a la o al quejoso, a las o los servidores públicos, personas extrañas al procedimientos, con domicilio señalado para oír y recibir notificaciones, la o el secretario actuario deberá buscar a la persona a quien deba hacerse, para que la diligencia se entienda directamente con ella, dejándole copia íntegra y autorizada de la determinación que se notifica, levantando la razón respectiva;\nII. Para hacer una notificación personal, se cerciorará la o el secretario actuario, por cualquier medio, de que la persona que deba ser notificada vive en la casa designada, y después de ello, practicará la diligencia, de todo lo cual asentará razón en autos;\nIII. Si no encontrare a la persona a la que deba hacerse la notificación, procederá a notificar por cédula, se entregará a los parientes, empleados del interesado o cualquier otra persona que viva o que se encuentre en el domicilio señalado y en la que se hará constar la fecha y la hora en que se entregue, la naturaleza del procedimiento, el nombre y apellidos de las partes, la autoridad que manda practicar la diligencia; transcripción de la determinación que se manda notificar, el nombre y apellido de la persona a quien se entrega, levantando el acta correspondiente, en la que se deberá recabar la firma de aquél con quien se hubiere entendido la actuación, y en caso de que el notificado o la persona con quien se entienda la diligencia se niegue a firmar, deberá asentarlo el actuario; y\n\nIV. Sólo si el que deba ser notificado se niega a recibir a la o al Secretario Actuario encargado de hacer la notificación, o las personas que residen en el domicilio se rehúsan a recibir la cédula, se fijará la cédula en la puerta de entrada, previo acuerdo emitido por la o el Consejero semanero.\nArtículo 324. Las notificaciones surtirán efectos:\nI. Tratándose de las personales, el término empezará a correr desde el día siguiente a aquél en que se hubiere hecho la notificación;\nII. La notificación por medio de Boletín Judicial, desde el día siguiente de aquél en que haya surtido efectos la publicación; y\nIII. Las notificaciones hechas por cédula, a partir del día siguiente a aquel en que se hubiere hecho.\nArtículo 325. Las notificaciones que no fueren hechas en la forma que establecen las disposiciones precedentes, serán nulas.\nArtículo 326. En el procedimiento de responsabilidad, ya sea por queja, denuncia en los casos previstos que contempla a las y los Jueces y Titulares de Magistraturas dentro de los negocios de su competencia o en aquellos relacionados directamente con los mismos o que afecten los intereses de menores e incapaces, así como respecto de aquellas conductas de sus subalternos, que sean contrarias a lo que esta Ley y demás disposiciones aplicables establecen, o incluso de oficio, es admisible toda clase de pruebas, excepto la confesional y las que fueren contra la moral o el derecho; además deberán tener relación directa con los hechos y deberán ofrecerse en el escrito inicial respectivo o informe con justificación.\nLa preparación de las pruebas quedará a cargo de la o del oferente; las que se desahogarán el día y hora en que tenga verificativo la audiencia que se señale para tal efecto. Para el caso de que las mismas no se exhiban o presenten oportunamente, se declararán desiertas en la citada audiencia, por falta de interés de su oferente. Si la falta de preparación o de exhibición de las pruebas que hayan de rendirse en audiencia no es imputable al oferente, se diferirá la audiencia y se señalará nueva fecha para ella.\nArtículo 327. El Consejo de la Judicatura podrá decretar en todo tiempo y hasta antes de la audiencia de ley, la práctica o ampliación de cualquier diligencia probatoria siempre que sea conducente para el conocimiento de la verdad sobre los hechos materia de los procedimientos administrativos.\n\nSolo procede la inspección judicial como medio de prueba cuando los hechos no puedan ser acreditados por otro medio idóneo, el que tendrá como finalidad la observación por la o el secretario actuario a través de sus sentidos de determinados objetos y lugares a fin de hacer constar lo que hubiera captado. Prueba que será valorada al prudente arbitrio de las o los Consejeros.\nArtículo 328. Las pruebas documentales deberán ser acompañadas con el escrito inicial, o el informe justificado solicitado; las que no se hayan exhibido, pero hayan sido anunciadas oportunamente en el escrito o informe respectivo, podrán ser presentadas a más tardar al inicio de la audiencia de ley, con el apercibimiento que de no hacerlo se declarará desierta la prueba por falta de interés de su oferente.\nAl interesado que acredite que solicitó oportunamente a las autoridades o funcionarios, copias o documentos para ofrecerlas como pruebas en el procedimiento y aquellas no cumplan con esa obligación o se denegaran, a petición de parte, se requerirán para que las envíen en un término no mayor de tres días, que podrá ser ampliado por tres días más, si las circunstancias lo ameritan, con el apercibimiento que de no hacerlo se hará uso de los medios de apremio correspondientes.\nArtículo 329. Cuando las partes tengan que rendir la prueba pericial para acreditar algún hecho, deberán anunciarla en el escrito inicial o al rendir el informe justificado, exhibiendo el cuestionario para los peritos, señalando con toda precisión la ciencia, arte, técnica, oficio o industria sobre la cual deba practicarse, los puntos sobre los que versará y las cuestiones que se deben resolver, así como copia certificada de la cédula profesional, o de los documentos que acrediten la calidad técnica, artística o industrial de la o el perito propuesto, nombre, apellido, y domicilio de esta o este.\nLa prueba pericial no será admitida, si no se encuentra relacionada con los hechos controvertidos, y si no reúne los requisitos señalados.\nAl admitirse la prueba pericial, la o el Consejero semanero podrá hacer la designación de un perito oficial para la práctica de la diligencia correspondiente, sin perjuicio de que cada parte pueda designar un perito para que rinda su dictamen pericial. Las o los peritos designados, deberán rendir su dictamen en el término que para tal efecto se señale en el Auto donde se admita dicha prueba. La prueba pericial será calificada por las o los Consejeros, según prudente estimación, y en concordancia con las demás pruebas rendidas, al dictarse la sentencia respectiva.\nLas o los peritos emitirán su dictamen por escrito y lo ratificarán ante la propia Comisión de Disciplina al momento de su presentación.\n\nArtículo 330. La prueba testimonial deberá ser ofrecida en el escrito inicial o al rendir el informe justificado, siempre y cuando se encuentre relacionada directamente con los hechos controvertidos, señalando el nombre y apellidos de las o los testigos, así como su domicilio, si se pide la citación por conducto del\nConsejo de la Judicatura. No se admitirán más de dos testigos por cada hecho.\nLas o los testigos serán citados a declarar únicamente cuando la parte que ofrezca su testimonio manifieste bajo protesta de decir verdad no poder presentarlos. La citación se hará con apercibimiento de apremio si faltaren sin justa causa.\nArtículo 331. Para acreditar hechos o circunstancias en relación con los hechos controvertidos, pueden las partes presentar fotografías, video grabaciones y en general, toda clase de elementos aportados por los descubrimientos de la ciencia, prueba que deberá ofrecerse en el escrito inicial o al rendir el informe con justificación y estará a cargo de la o del oferente la presentación de los instrumentos necesarios para su reproducción el día y hora en que se verificará la audiencia de ley, con el apercibimiento que de no hacerlo se declarará desierta la prueba por falta de interés, así como en caso de que en el desahogo de dicha probanza los instrumentos que presenten para su reproducción no funcionen.\nArtículo 332. La audiencia será pública, hecha excepción de la que, a juicio de las y los Consejeros, de oficio o a petición de parte, se determine que sea privada. Abierta la audiencia se procederá a recibir y desahogar, en primer término, las pruebas; a continuación las justificaciones y explicaciones del caso, otorgando el uso de la palabra a la o al denunciante y al denunciado, si hubiera asistido y, acto continuo, se asignará el asunto a la o al consejero que por turno le corresponda, para la elaboración de la resolución correspondiente.\nArtículo 333. La o el Consejero semanero cuidará que los procedimientos de responsabilidad no queden paralizados, proveyendo lo que corresponda hasta poner el asunto en estado de resolución.\nArtículo 334. En todas las cuestiones relativas al procedimiento administrativo de queja, por denuncia hecha por las y los Jueces y Titulares de Magistraturas de la Ciudad de México en los negocios de su competencia o en aquellos relacionados directamente con los mismos o que afecten los intereses de menores e incapaces, así como respecto de aquellas conductas de sus subalternos, que sean contrarias a lo que esta Ley y demás disposiciones aplicables establecen, o incluso de oficio, no previstas en esta Ley, así como en la apreciación de las pruebas, se observarán las disposiciones del Código Nacional de\nProcedimientos Penales.\n\nArtículo 335. Cada Consejera o Consejero titular de sección de la Comisión de Disciplina Judicial elaborará la resolución de los asuntos que le sean turnados, de conformidad con lo establecido en esta Ley.\nArtículo 336. Las resoluciones del Pleno del Consejo de la Judicatura, así como las de las Secciones que integran a la Comisión de Disciplina Judicial constarán en actas y deberán firmarse por las o los consejeros intervinientes, ante la presencia de la o del secretario técnico de la Comisión de Disciplina Judicial.\nArtículo 337. Las sentencias causarán ejecutoria:\nI. Por previo acuerdo, las pronunciadas en primera instancia, cuando se hayan consentido expresamente o cuando, concluido el término que esta Ley señala para interponer el recurso de inconformidad, no se haya hecho valer; y\nII. Por ministerio de ley, las pronunciadas en segunda instancia.\nArtículo 338. Únicamente se remitirán a la Oficialía Mayor, para su integración en los expedientes personales de las o los servidores públicos, las resoluciones emitidas por las Secciones de la Comisión de\nDisciplina Judicial que declaren fundadas las quejas presentadas en su contra, así como las declaratorias de responsabilidad que recaigan en los procedimientos disciplinarios que se les inicien.\nArtículo 339. Contra las resoluciones dictadas por las Secciones que integran a la Comisión de Disciplina\nJudicial, que declaren la responsabilidad de la persona servidora pública, procede el recurso de inconformidad, en los términos del artículo 392 de esta Ley.\nArtículo 340. Las personas servidoras públicas del Tribunal Superior de Justicia y del Consejo de la\nJudicatura que incurran en la comisión de alguna o algunas de las faltas previstas por esta ley, serán sancionados con:\nI. Amonestación;\nII. Multa de cinco a cien días de salario que el servidor de que se trate perciba;\nIII. Suspensión temporal de cinco días a cinco meses, sin goce de sueldo; y\nIV. Separación del cargo.\n\nArtículo 341. Si el órgano encargado de resolver sobre una queja no lo hiciera dentro del plazo a que se refiere el artículo 295, serán multados sus integrantes, con el importe de cinco días de salario que perciban, por el órgano encargado de la imposición de sanciones. Si el Pleno del Consejo lo fuere, se impondrá a los integrantes del mismo, igualmente multa de cinco días del salario que perciban, hayan concurrido o no al\nPleno respectivo. El órgano encargado de sancionar estas faltas será el Pleno del Tribunal Superior de\nJusticia.\nArtículo 342. La declaración de no responsabilidad por faltas deberá ser publicada por dos veces en extracto en el Boletín Judicial y en un periódico de circulación en la Ciudad de México, según lo disponga quien hiciere aquélla. Ambas publicaciones serán a costa de la quejosa o del quejoso; a quien, si no cumpliere, se le impondrá, además, una multa como medio de apremio por el mismo órgano que resuelva, por una cantidad que no será inferior a seis mil pesos ni superior a sesenta mil. Dichos montos se actualizarán conforme a la actualización prevista en la fracción II del artículo 59 de esta Ley. Estas multas se duplicarán en caso de reincidencia injustificada.\nEl órgano que hizo la declaración de no responsabilidad, estará encargado de vigilar que se dé cumplimiento a lo dispuesto por este artículo, y en caso de incumplimiento será sancionado en términos de lo dispuesto por el artículo anterior.\nEs facultad del Pleno del Tribunal Superior de Justicia supervisar cuando así lo estime conveniente o a petición de parte, a través de la solicitud del informe correspondiente, tanto a la Comisión de Disciplina como al Consejo de la Judicatura, por conducto de sus respectivas secretarías, del cumplimiento de esta obligación.\nArtículo 343. La declaración de responsabilidad por faltas producirá el efecto de impedir a la persona servidora pública de que se trate, tenga conocimiento del negocio en el que se hubieren cometido.\nCAPÍTULO II\nDE LAS FALTAS\nArtículo 344. Son faltas de las y los Jueces:\nI. No dictar, sin causa justificada, dentro del término señalado por la ley, los acuerdos que procedan a los escritos y promociones de las partes;\n\nII. No dar a la Secretaría los puntos resolutivos ni dictar, sin causa justificada, dentro del término que señala la ley, las sentencias interlocutorias o definitivas de los negocios de su conocimiento;\nIII. No concluir, sin causa justificada, dentro del término de la ley, la instrucción de los procesos de su conocimiento;\nIV. Dictar resoluciones o trámites notoriamente innecesarios, que sólo tiendan a dilatar el procedimiento;\nV. Admitir demandas o promociones de parte de quien no acredite su personalidad conforme a la ley, o desechar por esa deficiencia, unas y otras, de quien la hubiere acreditado suficientemente;\nVI. Admitir fianzas o contrafianzas en los casos que prescriben las leyes, de personas que no acrediten suficientemente su solvencia y la libertad de gravámenes de los bienes que sirvan para ello;\nVII. Actuar en los negocios en que estuvieren impedidos por las causas previstas por la ley;\nVIII. Hacer declaración de rebeldía en perjuicio de alguna de las partes, sin que las notificaciones o citaciones anteriores hayan sido hechas en forma legal o antes del término previsto por la ley;\nIX. No recibir las pruebas ofrecidas por las partes en el juicio, cuando reúnan los requisitos establecidos en la ley;\nX. Hacer uso, en perjuicio de las partes, de los medios de apremio sin causa justificada;\nXI. No presidir las audiencias de recepción de pruebas, las juntas y demás diligencias para las que la ley determine su intervención;\nXII. Señalar, para la celebración de las vistas o audiencias, injustificadamente, una fecha lejana;\nXIII. Decretar un embargo o ampliación de él, sin que se reúnan los requisitos de ley, o negar la reducción o levantamiento del mismo, cuando se prueben en autos, de manera fehaciente, que procede una u otra;\n\nXIV. No concurrir, sin causa justificada, al desempeño de sus labores oficiales, durante todas las horas reglamentarias;\nXV. Alterar el orden de las listas al hacer el nombramiento de auxiliares de la administración de justicia;\nXVI. Dedicar a las personas servidoras públicas de la administración de justicia de su dependencia, al desempeño de labores extrañas o ajenas a las funciones oficiales;\nXVII. Desobedecer injustificadamente las circulares, acuerdos y órdenes expedidas por el\nTribunal Superior de Justicia y el Consejo de la Judicatura;\nXVIII. Mostrar notoria ineptitud, negligencia o descuido en el desempeño de las funciones o labores que deba realizar;\nXIX. Dejar de aplicar una ley, desacatando una disposición que establece expresamente su aplicación;\nXX. No practicar las diligencias encomendadas por el Poder Judicial Federal, sin causa justificada.\nLo anterior, sin perjuicio de las sanciones que pudieran imponer tales autoridades en términos de los ordenamientos legales aplicables;\nXXI. No ordenar la práctica de la notificación de manera inmediata a los Agentes del Ministerio\nPúblico adscritos, al momento en que se dicten y previo a su ejecución, de los autos de libertad por falta de elementos para procesar y las sentencias absolutorias; y\nXXII. No iniciar y dar el trámite correspondiente a los procedimientos administrativos a aquellas personas servidoras públicas que estén a su cargo y que incurra en alguna de las faltas previstas por esta ley, así como no remitir la correspondiente acta al Consejo de la Judicatura o a la autoridad competente.\nEn el caso de las fracciones IV, V, VI, VIII, IX y XIII será requisito de procedibilidad que la resolución de que se trate haya sido revocada.\nArtículo 345. Son faltas de las y los Jueces del Sistema Penal Acusatorio.\n\nI. No presidir la audiencia en el horario establecido;\nII. No excusarse del asunto inmediatamente tenga conocimiento de la actualización de una de las hipótesis del artículo 37 del Código Nacional de Procedimientos Penales;\nIII. Permitir se violen los principios rectores del sistema penal acusatorio;\nIV. Declararse incompetente por declinatoria o inhibitoria en razón de seguridad;\nV. Dictar resolución o sentencias por escrito contrarias o en exceso de lo que emitió en sala de audiencias;\nVI. Dictar resolución o sentencias por escrito fuera de los términos establecidos por la ley de la materia;\nVII. No llevar un orden en las audiencias que presida;\nVIII. No realizar de manera justificada las diligencias urgentes antes de que se dicte auto de apertura a juicio oral;\nIX. No emitir su voto particular por escrito dentro de los 3 días a que se refiere el artículo 67 último párrafo del Código Nacional de Procedimientos Penales;\nX. No firmar las resoluciones en las que participó a pesar de que sea suplida dicha falta con posterioridad;\nXI. No resolver de inmediato el sobreseimiento cuando proceda;\nXII. No recibir la garantía en efectivo cuando por razones de la hora o por tratarse de día inhábil no pueda constituirse el depósito o no realice el registro correspondiente; y\nXIII. Celebrar audiencia sin estar presentes todas las partes que en ella debe intervenir.\nXIV. Las demás que le confieran las leyes, reglamentos y acuerdos del Consejo de la Judicatura.\n\nArtículo 346. Son faltas de las y los Jueces del Sistema Oral:\nI. No presidir la audiencia en el horario establecido;\nII. No excusarse del asunto inmediatamente tenga conocimiento de la actualización de una de las hipótesis del artículo 37 del Código Nacional de Procedimientos Penales;\nIII. Permitir se violen los principios rectores del sistema penal acusatorio;\nIV. Declararse incompetente por declinatoria o inhibitoria en razón de seguridad;\nV. Dictar resolución o sentencias por escrito contrarias o en exceso de lo que emitió en sala de audiencias;\nVI. Dictar resolución o sentencias por escrito fuera de los términos establecidos por la ley de la materia;\nVII. No llevar un orden en las audiencias que presida;\nVIII. No realizar de manera justificada las diligencias urgentes antes de que se dicte auto de apertura a juicio oral;\nIX. No emitir su voto particular por escrito dentro de los 3 días a que se refiere el artículo 67 último párrafo del Código Nacional de Procedimientos Penales;\nX. No firmar las resoluciones en las que participó a pesar de que sea suplida dicha falta con posterioridad;\nXI. No resolver de inmediato el sobreseimiento cuando proceda;\nXII. No recibir la garantía en efectivo cuando por razones de la hora o por tratarse de día inhábil no pueda constituirse el depósito o no realice el registro correspondiente;\nXIII. Celebrar audiencia sin estar presentes todas las partes que en ella debe intervenir; y\nXIV. Las demás que le confiera las leyes, reglamentos y acuerdos del Consejo de la Judicatura.\n\nArtículo 347. Se considerarán como faltas de las personas que presiden las Salas, Semaneros, así como\nMagistradas y Magistrados integrantes de aquéllas, en sus respectivos casos, las que tienen ese carácter, conforme a las fracciones I, II, IV, V, VI, VII, VIII, IX, XII, XIV y XV del artículo anterior y además, las siguientes:\nI. Faltar a las sesiones del Pleno sin causa justificada;\nII. Desintegrar sin motivo justificado el quórum en los plenos, vistas o audiencias, una vez comenzadas, o\nIII. Intervenir de cualquier forma en el nombramiento del personal de los Juzgados.\nArtículo 348. Si la falta se cometiere por alguna Sala del Tribunal Superior de Justicia, por no dictar resoluciones dentro del término legal, sólo será responsable la Magistrada o Magistrado ponente cuando no presentare oportunamente el proyecto respectivo a la consideración de los demás Magistrados; y estos últimos serán responsables si, habiéndose presentado la ponencia correspondiente, no concurrieren a la discusión del negocio o no lo votan dentro del mismo plazo legal, o cuando, según el caso, no emita voto particular razonado.\nArtículo 349. Son faltas de los Titulares de las Secretarías en el Ramo Penal, y de Justicia para Adolescentes:\nI. No dar cuenta, dentro del término de la ley, con los oficios y documentos oficiales dirigidos al juzgado y con los escritos y promociones de las partes;\nII. No asentar en autos, dentro del término, las certificaciones que procedan de oficio o por mandato judicial;\nIII. No diligenciar, dentro de las veinticuatro horas siguientes a aquéllas en las que surtan efectos las resoluciones judiciales, a menos que exista causa justificada;\nIV. No dar cuenta, al Juzgador o a quien presida la Sala, de las faltas u omisiones que personalmente hubieren notado en las personas servidoras públicas de la administración de justicia subalternos de la oficina, o que se le denuncien por el público verbalmente o por escrito;\nV. No engrosar, dentro de ocho días siguientes a la decisión del negocio, la sentencia que corresponda, en los casos que fuere su obligación hacerlo;\n\nVI. En el caso de los Titulares de las Secretarías en el ramo penal, no revisar que se realice de manera inmediata la notificación a los Agentes del Ministerio Público adscritos, al momento en que se dicten y previo a su ejecución, de los autos de libertad por falta de elementos para procesar y las sentencias absolutorias; y\nVII. Las señaladas en las fracciones VII, XIV y XVI al XX del artículo 344.\nArtículo 350. Son faltas de las personas titulares de las Secretarías del ramo civil, familiar, de extinción de dominio y laboral, las fijadas en el artículo anterior y, además las siguientes:\nI. No turnar a la persona Secretaria Actuaria adscrita los expedientes que requieran notificación personal o la práctica de alguna diligencia;\nII. No hacer a las partes las notificaciones personales en términos de ley, que procedan cuando concurran al Juzgado o Tribunal;\nIII. No mostrar a las partes los expedientes sin causa justificada, cuando lo soliciten, mediante el vale de resguardo respectivo y previa identificación oficial vigente, o exigir requisitos no contemplados en la ley para tal efecto;\nIV. No mostrar a las partes, inmediatamente que lo soliciten mediante el vale de resguardo respectivo y previa identificación oficial vigente, los negocios que se hayan publicado en el\nBoletín del día;\nV. No remitir al archivo oportunamente los expedientes cuya remisión sea forzosa, conforme a los lineamientos establecidos en esta ley;\nVI. No observar lo establecido en la fracción VII del artículo 81 de esta Ley;\nVII. No entregar a las partes las copias simples de resoluciones o constancias de autos que les soliciten, previo pago realizado en los términos correspondientes, cuando para ello no se requiera acuerdo para la expedición;\nVIII. No entregar las copias certificadas ordenadas por decreto judicial, dentro del término de cinco días hábiles contados a partir del día siguiente en que surta efectos la notificación del\n\nproveído que lo ordene, cuando haya sido exhibido el pago correspondiente y no exista impedimento legal para ello; y\nIX. No elaborar los proyectos de acuerdo que deban recaer a los asuntos en trámite a su cargo, de manera adecuada tanto en fondo como en forma conforme a las constancias de los expedientes y la ley que resulte aplicable.\nArtículo 351. Son faltas de los Titulares de las Secretarías Proyectistas, así como de las de Acuerdos de\nJusticia Oral Civil:\nI. Elaborar proyectos de sentencia o resolución fuera del término señalado por su Titular que permita a este último su oportuna revisión; no acatar de manera inmediata las instrucciones y observaciones hechas a sus proyectos;\nII. No guardar el debido secreto respecto de los asuntos que le son turnados para la elaboración del proyecto de sentencia o resolución;\nIII. Mostrar negligencia, descuido, ignorancia o ineptitud en el desempeño de su labor;\nIV. En la elaboración de proyectos de sentencias o resoluciones, dejar de aplicar leyes desacatando disposiciones que establecen expresamente su aplicación o bien, aplicando disposiciones que se encuentren derogadas;\nV. Elaborar proyectos de sentencia o resoluciones en contravención a las constancias de autos; y\nVI. Las demás que deriven de la ley.\nArtículo 352. Son faltas de las personas Secretarias Actuarias:\nI. No practicar legalmente o con la debida oportunidad y sin causa justificada, las notificaciones personales, ni llevar a cabo las diligencias de sus atribuciones, cuando deban efectuarse fuera del Juzgado o Tribunal;\nEn materia penal, no practicar la notificación de manera inmediata a los Agentes del Ministerio\nPúblico adscritos, al momento en que se dicten y previo a su ejecución, de los autos de libertad por falta de elementos para procesar y las sentencias absolutorias;\n\nSolicitar a cualesquiera de las partes, retribuciones económicas o materiales, por sí o por interpósita persona, para efectuar las diligencias o notificaciones, así como solicitar a las partes proporcionen los medios e traslado para realizar las mismas;\nII. Retardar indebida o injustificadamente las notificaciones, emplazamientos, embargos o diligencias de cualquier clase que les fueren encomendadas;\nIII. Dar preferencia a alguno o algunos de los litigantes, y con perjuicio de otros, por cualquier causa que sea, en la diligencia de sus asuntos en general, y, especialmente, para llevar a cabo las que se determinan en la fracción que antecede;\nIV. Hacer notificaciones, citaciones o emplazamientos a las partes, por cédula o instructivo, fuera del lugar designado en autos, o sin cerciorarse, cuando proceda, de que el interesado tiene su domicilio en donde se lleva a cabo la diligencia; y\nV. Practicar embargos, aseguramientos o retención de bienes o lanzamientos, de persona física o moral que no sea la designada en el auto respectivo, o cuando en el momento de la diligencia o antes de retirarse el personal del Juzgado, se le demuestre que esos bienes son ajenos, para comprobar lo cual, en todo caso, deberá agregar a los autos la documentación que se les presente, a efecto de dar cuenta a quien hubiere ordenado la diligencia.\nArtículo 353. Son faltas de las personas Secretarias Conciliadoras:\nI. Dejar de cumplir con las obligaciones inherentes a su cargo, reguladas por el artículo 84 de esta Ley; y\nII. Las demás que deriven de la ley.\nArtículo 354. Son faltas de las personas servidoras públicas de los juzgados, salas, direcciones, unidad de gestión judicial, presidencia y demás dependencias del Tribunal Superior de Justicia:\nI. Solicitar a cualquiera de las partes, retribuciones económicas o materiales por sí o por interpósita persona, como condición para el desempeño de sus obligaciones o rehusarse a recibir los escritos y promociones de cualquiera de las partes, así como aceptar o recibir dádivas o retribuciones de cualquier índole por el desempeño de sus funciones;\n\nII. No concurrir a las horas reglamentarias al desempeño de sus labores;\nIII. No atender oportunamente y de forma correcta a los litigantes y público en general;\nIV. No mostrar a las partes, inmediatamente que lo soliciten, y una vez que hayan presentado su vale de resguardo e identificación oficial vigente, los expedientes que se hayan publicado en el Boletín del día o se encuentren en los archivos, o exigir a las partes requisitos no contemplados en la ley;\nV. No elaborar y despachar adecuada y oportunamente, los oficios, notificaciones, y correspondencia en general ordenados en los procedimientos judiciales y trámites administrativos inherentes al despacho del juzgado, o no llevar a cabo las diligencias que se les encomienden, por su superior jerárquico inmediato o por el Titular del órgano jurisdiccional;\nVI. No hacer del conocimiento del Titular del órgano al que pertenezcan, las faltas cometidas por otros servidores públicos de su área; y,\nVII. No remitir al archivo oportunamente los expedientes cuya remisión sea forzosa, conforme a la ley.\nArtículo 355. Las personas Secretarias Judiciales, así como las Auxiliares de Juzgado de Proceso Oral en materia Familiar incurrirán en faltas, si cometen alguna acción que pueda encuadrarse en cualquiera de los supuestos señalados en las fracciones II, III, IV, V, VI, y IX del artículo 350 y 351 de esta Ley.\nPor su parte, las faltas de las personas Oficiales Notificadores se sujetarán a lo dispuesto en el artículo 352 de esta Ley.\nLas personas servidoras públicas adscritas a la Unidad de Gestión Administrativa, a la Unidad de Apoyo\nTecnológico y a la Central de Comunicaciones Procesales, cometerán falta si incurren en alguno de los supuestos previstos en las fracciones I, VI, VII y VIII del artículo 350; de la fracción III del artículo 351, de las fracciones II y III del artículo 352; así como los supuestos establecidos en el artículo 354 de la presente Ley.\n\nCAPÍTULO III\nDE LAS SANCIONES\nArtículo 356. Las faltas en que incurran las personas servidoras públicas, previstas en los artículos 344 fracciones I a IV, XII, XIV y XVI a XXI; 345 fracciones I a XIV y XVI; 347, fracciones I y II; 349, con excepción de la fracción III; 350, salvo la fracción IX; 352 fracciones II a V y 354 fracciones II a VII, serán sancionadas, la primera vez con amonestación por escrito, y la segunda, con multa.\nSi la falta es de las que se refieren en la fracción IX del Artículo 350, 351, 352 la fracción I del Artículo 353 o en la fracción I del Artículo 354, se le sancionará con multa si es la primera vez que se comete, y la segunda vez se le sancionará con suspensión temporal.\nEn el caso de reincidencia en una tercera ocasión tratándose del Artículo 351, el proyectista será separado del cargo.\nTodo lo anterior, sin perjuicio de la facultad del Consejo de la Judicatura, a que se refiere el artículo 357 de esta Ley.\nArtículo 357. Las faltas en que incurran las personas servidoras públicas, previstas en los artículos 344 fracciones V, VI, VII, VIII, IX, X, XI, XIII y XV; 349 fracción III, así como reincidir en las establecidas por el artículo 350, serán sancionadas la primera vez con multa en los términos de la fracción II del artículo 340, y la segunda con suspensión temporal, en los términos de la fracción III, de dicho artículo. Se impondrá suspensión a la persona servidora pública que incurra en la falta prevista por la fracción I del artículo 352 o la prevista en la fracción I del artículo 354, cuando se trate de la segunda vez.\nArtículo 358. Para la imposición de las sanciones con motivo de las faltas señaladas en la presente ley, la\nComisión de Disciplina Judicial deberá tomar en cuenta los siguientes elementos:\nI. La gravedad de la responsabilidad en que se incurra;\nII. Los antecedentes del infractor;\nIII. La reincidencia en la comisión de faltas;\nPara los efectos de la fracción I, se considerarán como faltas graves el incumplimiento de las obligaciones previstas en:\n\na) El Artículo 81, fracciones I a VIII y XII a XVI de esta Ley;\nb) El Artículo 83 fracción I del presente ordenamiento;\nc) El Artículo 84 fracciones I a III, VI y VII de esta Ley;\nd) El Artículo 85 fracciones III y IV;\ne) El Artículo 87 de la presente ley, con excepción de la fracción IV.\nIgualmente serán consideradas como faltas graves:\nf) Las que se refieren las fracciones I a XIII y XVI a XX del Artículo 321 de esta Ley;\ng) El Artículo 347 del presente ordenamiento;\nh) El Artículo 349, fracciones I a VI de la presente Ley;\ni) El Artículo 350, fracciones I, III, IV y VII a IX de esta Ley;\nj) El Artículo 351, con excepción de la fracción VI de este ordenamiento;\nk) El Artículo 352 y 353 de la presente Ley;\nl) El Artículo 354, con excepción de la fracción VII, de este ordenamiento legal.\nArtículo 359. Cuando un Juzgador del sistema penal acusatorio, haya incurrido, en la falta a que se refiere el artículo 345 fracción XV de esta Ley, se le impondrá como sanción:\nI. Cuando se trate de la primera vez, multa a que se refiere la fracción II del artículo 340 de esta\nLey, debiéndose tomar nota en el expediente de dicha persona servidora pública;\nII. Cuando se trate de segunda ocasión en dicha hipótesis, suspensión temporal de cinco días a cinco meses, sin goce de sueldo; y\n\nIII. Cuando se trate de la tercera ocasión en dicha hipótesis, será separado de su cargo, conforme al artículo 340 fracción IV.\nArtículo 360. Todas las disposiciones contenidas en este Capítulo serán aplicables, sin perjuicio de lo que previenen las demás disposiciones legales aplicables a los Servidores del Tribunal Superior de Justicia.\nCuando una persona servidora pública de la administración de justicia sea sancionada por cometer tres faltas en el desempeño de un mismo cargo, dentro de un período de hasta tres años, será separado del cargo conforme a la fracción IV del artículo 340.\nArtículo 361. La separación del cargo a que hace referencia la fracción IV del artículo 356 de esta Ley, se impondrá al resolver el procedimiento oficioso o de queja instaurado en contra de la o del servidor público que se encuentre en alguno de los siguientes supuestos:\nI. Al que sea declarado responsable por la comisión de cuatro faltas administrativas, de las previstas en el artículo 356 de esta Ley, en uno o varios procedimientos.\nII. Al que sea declarado responsable por la comisión de tres faltas administrativas de las previstas en el artículo 357 de esta Ley, en uno o varios procedimientos.\nIII. Al que haya sido declarado administrativamente responsable por la comisión de cuatro faltas, de las previstas por los artículos 356 y 357 de la presente Ley, en forma indistinta, en uno o varios procedimientos.\nLo anterior, sin perjuicio de la facultad de la Comisión de Disciplina Judicial para imponer la separación del cargo, al sancionar a la o al servidor público que cometa falta de tal magnitud grave que pudiera ser constitutiva de delito, incluso si se tratara de la primera vez que incurre en falta.\nArtículo 362. También se sancionará como falta, según el caso, a juicio de la Comisión de Disciplina\nJudicial, y en los términos que prescriben, los artículos 356 y 357 de esta Ley, las infracciones y omisiones en que incurran los servidores públicos de la administración de justicia de la Ciudad de México, con relación a los deberes que les imponen las disposiciones de esta Ley y las demás sustantivas y adjetivas de la Ciudad de México y los reglamentos respectivos.\nArtículo 363. Cuando se actualicen las hipótesis a que se refieren el artículo 360 fracción III o 358 de esta\nLey Orgánica, según se trate, se ordenará que se instrumente procedimiento en los siguientes términos:\n\na) Una vez que cause ejecutoria la última resolución sancionatoria, la Secretaría Técnica de la\nComisión de Disciplina Judicial de manera oficiosa, ordenará al archivo la remisión de los expedientes relativos a los procedimientos en que se haya declarado previamente la responsabilidad de la persona servidora pública implicada y requerirá su expediente personal;\nhecho lo cual, elaborará una certificación en la que asiente las fechas en que se declararon firmes dichas resoluciones y dará cuenta al Consejero semanero sobre el estatus del asunto.\nb) Con los elementos anteriores, el Consejero semanero pronunciará el acuerdo correspondiente, con el que se dará cuenta al Pleno del Consejo de la Judicatura.\nc) De estimar procedente el inicio del procedimiento relativo a la separación del cargo, el Pleno del Consejo remitirá el expediente a la Comisión de Disciplina Judicial para su sustanciación, quien por conducto del Consejero semanero ordenará la notificación a la persona servidora pública de que se trate, para que en un plazo que no exceda de tres días hábiles contados a partir de la notificación, manifieste lo que a su derecho corresponda y ofrezca las pruebas que estime necesarias.\nd) Con la certificación y expedientes recabados por la Secretaría Técnica de la Comisión de\nDisciplina Judicial, más los elementos que, en su caso, proponga la persona servidora pública y que deberán tener relación únicamente con la materia del procedimiento de separación del cargo, se celebrará la audiencia. Encontrándose el expediente en estado de resolución se turnará al Consejero ponente para la elaboración del proyecto de resolución en un plazo que no exceda de diez días hábiles, contados a partir de que se turne el expediente para dicho fin.\ne) Dicha resolución deberá versar exclusivamente sobre la comprobación de los extremos a que se refiere el Artículo 335 fracción III o 337 de esta Ley Orgánica según se trate.\nf) Una vez hecho lo anterior, se presentará el proyecto a la aprobación del Pleno del Consejo de la Judicatura de la Ciudad de México, el que resolverá en definitiva.\ng) Una vez dictada la resolución de separación del cargo, se turnará a la Secretaría Técnica de la\nComisión de Disciplina Judicial para su ejecución inmediata.\n\nCAPÍTULO IV\nDE LOS ÓRGANOS Y SISTEMAS PARA LA IMPOSICIÓN DE LAS\nSANCIONES ADMINISTRATIVAS\nArtículo 364. Las sanciones previstas en esta ley serán impuestas por la Comisión de Disciplina Judicial, en primera instancia, ante la presencia del Secretario de la Comisión que dará fe tanto de las sanciones como de las actuaciones de la Comisión.\nLa Comisión de Disciplina Judicial actuará de manera unitaria, a través de la o del Consejero Semanero en turno, para imponer las sanciones previstas en esta Ley; resoluciones que son resueltas de manera definitiva e inatacable.\nEl Pleno del Consejo de la Judicatura conocerá de la imposición de sanciones en segunda instancia, pudiendo, en su caso, revisar, revocar o modificar la resolución dictada por la Comisión de Disciplina.\nEn todo caso el Pleno del Consejo de la Judicatura resolverá de forma definitiva e inatacable.\nArtículo 365. Causarán ejecutoria:\nI. Las resoluciones o sentencias pronunciadas por la Comisión de Disciplina Judicial, en primera instancia, cuando se hayan consentido expresamente o cuando no se haga valer recurso alguno dentro del término de ley; y\nII. Las resoluciones o sentencias dictadas por el Pleno del Consejo de la Judicatura, en segunda instancia con motivo del recurso inconformidad, mismas que serán irrevocables.\nArtículo 366. Para los efectos de la imposición de las sanciones que señala esta Ley, se estará al procedimiento previsto en el artículo 395 de la misma y a lo siguiente: la Comisión de Disciplina Judicial, hará la declaración previa de que la persona servidora pública incurrió en la falta de que se trate, sin más requisitos que oír a éste y al denunciante, si quisiera concurrir a la diligencia.\nArtículo 367. El asunto se discutirá y votará en una sola sesión del órgano que corresponda, en caso de empate en la votación, sin aplazar la resolución del asunto, se discutirá de nueva cuenta procediendo a la votación y si aun así no fuere posible el desempate, quien presida tendrá voto de calidad para ese asunto específico. Los acuerdos tomados serán asentados en las actas respectivas.\n\nSiendo facultad del órgano que corresponda imponer las sanciones administrativas el resolver y calificar de plano, las excusas o impedimentos de sus miembros; si una u otra se presentare para el caso de la primera instancia por más de un integrante de la Comisión de Disciplina Judicial, ésta será calificada por el Pleno del Consejo de la Judicatura, y de resultar fundada, el o los Consejeros en que proceda, serán sustituidos en cuanto a la integración de dicho órgano y exclusivamente para los efectos del asunto en particular, por las Consejeras o Consejeros que se designen mediante el turno que para tal efecto lleve la\nPresidencia del Consejo de la Judicatura.\nCAPÍTULO V\nDEL RECURSO DE REVISIÓN ADMINISTRATIVA\nArtículo 368. Las decisiones dictadas por el Consejo de la Judicatura serán definitivas e inatacables, salvo las que se refieren a la designación, propuestas de designación o de ratificación y remoción de Magistrados y Jueces, las cuales podrán impugnarse ante el Pleno del Tribunal Superior de Justicia, mediante el recurso de revisión administrativa, que tendrá alcances de anulación del acto combatido.\nEl recurso de revisión administrativa tendrá como único objeto que el Pleno del Tribunal Superior de\nJusticia determine si el Consejo de la Judicatura designó, adscribió, emitió la propuesta de designación o de ratificación, o removió a una Magistrada o Magistrado o al Juzgador, con estricto apego a los requisitos formales previstos en esta Ley, o en los reglamentos interiores y acuerdos generales expedidos por el propio Consejo de la Judicatura.\nArtículo 369. El recurso de revisión administrativa podrá interponerse en contra de:\nI. Resoluciones de designación con motivo de un examen de oposición, por cualquiera de las personas que hubieren participado en él;\nII. Resoluciones en las que se emita opinión negativa sobre la propuesta de designación o de ratificación, se interpondrá por el Titular de la Magistratura o el Juzgador en el caso de negativa a la ratificación; y\nIII. Resoluciones de remoción.\nArtículo 370. El recurso de revisión administrativa deberá presentarse por escrito ante quien presida el\nConsejo de la Judicatura, dentro de los cinco días hábiles siguientes a la fecha en que hubiere surtido sus\n\nefectos la notificación de la resolución que haya de combatirse. Quien presida el Consejo instruirá a un integrante de éste, para que realice y presente el informe circunstanciado, en el que se sostenga la legalidad del acto combatido, acompañado de aquellos elementos probatorios en que se haya fundado el mismo. El recurso de revisión y el informe correspondiente serán turnados, dentro de los tres días hábiles siguientes, a un Magistrado ponente según el turno, para que elabore el proyecto de resolución que corresponda.\nArtículo 371. En los casos en que el recurso de revisión administrativa se interponga contra las resoluciones de designación o adscripción, deberá notificarse también al tercero interesado, teniendo este carácter la o las personas que se hubieren visto favorecidas con la resolución que se combate, a fin de que en el término de cinco días hábiles pueda alegar lo que a su derecho convenga.\nArtículo 372. Tratándose de los recursos de revisión administrativa interpuestos contra las resoluciones de designación, no se admitirán más pruebas que las documentales públicas, las cuales deberán ser ofrecidas por el promovente o el tercero interesado en el escrito de interposición de recurso o en el de contestación a éste.\nArtículo 373. En caso de que el recurso de revisión administrativa se presente en contra de resoluciones de remoción o propuestas de designación o de ratificación, el Magistrado ponente podrá ordenar la apertura de un período probatorio hasta por diez días. En este caso, únicamente serán admisibles las pruebas documental y testimonial. Cuando alguna de las partes ofrezca una prueba documental que no obre en su poder, solicitará al Magistrado ponente que requiera a la autoridad que cuente con ella, a fin de que la proporcione a la brevedad.\nArtículo 374. Las resoluciones del Pleno del Tribunal Superior de Justicia que declaren fundado el recurso de revisión administrativa planteado, se limitarán a declarar la nulidad del acto impugnado, para el efecto de que el Consejo de la Judicatura dicte una nueva resolución en un plazo no mayor a treinta días naturales.\nDichas resoluciones serán válidas cuando sean adoptadas por el voto de las dos terceras partes de los integrantes del Pleno del Tribunal Superior de Justicia.\nLa nulidad del acto que se reclame no producirá la invalidez de las actuaciones del Magistrado o Juzgador nombrado o adscrito.\nLa interposición del recurso de revisión administrativa no interrumpirá en ningún caso, los efectos de la resolución impugnada.\n\nTÍTULO DÉCIMO QUINTO\nDEL SERVICIO CIVIL DE CARRERA ADMINISTRATIVA\nCAPÍTULO I\nDE LA CARRERA ADMINISTRATIVA\nArtículo 375. En el Tribunal Superior de Justicia y el Consejo de la Judicatura se establecerá el Servicio Civil de Carrera Administrativa para las y los servidores públicos, de conformidad con el reglamento que el efecto emita el propio Consejo, el cual comprenderá, entre otros aspectos, la selección, ingreso, promoción, capacitación, profesionalización, evaluación, estímulos y separación.\nLos acuerdos que el consejo apruebe para su implementación determinarán las bases, lineamientos y modalidades a observar, según la naturaleza del área administrativa de que se trate.\nLa implementación del Servicio Civil de Carrera Administrativa será gradual y progresiva.\nArtículo 376. El Servicio Civil de Carrera Administrativa se regirá por los principios de excelencia, profesionalismo, objetividad, imparcialidad, independencia, perspectiva de género, igualdad de oportunidades y antigüedad.\nAdemás, en el funcionamiento de dicho servicio se deberán observar los principios y criterios de legalidad, honestidad, eficiencia, eficacia, economía, racionalidad, austeridad, transparencia, control y rendición de cuentas.\nArtículo 377. En la interpretación y aplicación de estos conceptos prevalecerá la prohibición de toda forma de discriminación por origen étnico, nacionalidad, género, edad, discapacidad, condiciones sociales o de salud, religión, orientación sexual, opiniones, estado civil o cualquier otra que atente contra la dignidad humana, y tenga por objeto y/o resultado anular o menoscabar los derechos y libertades de la persona, con el propósito específico de transitar hacia un esquema de ingreso, promoción y desarrollo del Servicio Civil de Carrera Administrativa.\nEn la interpretación y aplicación de estos principios, servirá de guía lo dispuesto en el Código de Ética del\nTribunal Superior de Justicia.\n\nArtículo 378. El Servicio Civil de Carrera Administrativa se regirá por los principios de excelencia, profesionalismo, objetividad, imparcialidad, independencia, perspectiva de género, igualdad de oportunidades y antigüedad.\nAdemás, en el funcionamiento de dicho Servicio se deberán observar los principios y criterios de legalidad, honestidad, eficiencia, eficacia, economía, racionalidad, austeridad, transparencia, control y rendición de cuentas.\nArtículo 379. En la interpretación y aplicación de estos conceptos prevalecerá la prohibición de toda forma de discriminación por origen étnico, nacionalidad, género, edad, discapacidad, condiciones sociales o de salud, religión, orientación sexual, opiniones, estado civil o cualquier otra que atente contra la dignidad humana, y tenga por objeto y/o resultado anular o menoscabar los derechos y libertades de la persona, con el propósito específico de transitar hacia un esquema de ingreso, promoción y desarrollo del Servicio Civil de Carrera Administrativa.\nEn la interpretación y aplicación de estos principios, servirá de guía lo dispuesto en el Código de Ética del\nTribunal Superior de Justicia.\nArtículo 380. El propósito que persigue la implementación del Servicio Civil de Carrera Administrativa es establecer un modelo de ingreso, capacitación y evaluación del desempeño para la profesionalización de la actividad administrativa del Tribunal Superior de Justicia y del Consejo de la Judicatura.\nEn el desarrollo de los esquemas del Servicio Civil de Carrera Administrativa se reconocerá la necesidad de generar condiciones de igualdad entre mujeres y hombres.\nArtículo 381. El Servicio Civil de Carrera Administrativa comprenderá al personal del Tribunal Superior de\nJusticia y del Consejo de la Judicatura, de conformidad con lo establecido en el reglamento que al efecto emita el consejo.\nLa profesionalización de dicho personal se llevará a cabo mediante capacitación y evaluación de acuerdo con los programas académicos y/o técnicos que para tal efecto se implementen.\nArtículo 382. Para el óptimo desarrollo del Servicio Civil de Carrera Administrativa en el Tribunal Superior de Justicia y el Consejo de la Judicatura deberán:\n\nI. Seleccionar al personal del Servicio Civil de Carrera Administrativa de conformidad con lo establecido en el Reglamento que se aprueben por el Tribunal Superior de Justicia y por el\nConsejo de la Judicatura.\nII. Promover el desarrollo del personal del Servicio Civil de Carrera Administrativa a través de su capacitación y actualización.\nIII. Implementar la evaluación del desempeño conforme a lo establecido en el Reglamento que se apruebe.\nCAPÍTULO II\nDEL COMITÉ DEL SERVICIO CIVIL DE CARRERA\nArtículo 383. Se establecerá un Comité del Servicio Civil de Carrera Administrativa para el Tribunal Superior de Justicia y otro para el Consejo de la Judicatura, los cuales estarán conformados, bajo el principio de paridad, en una proporción que no exceda de tres integrantes de un mismo género, conforme a lo siguiente:\nA. El Comité del Servicio Civil de Carrera Administrativa del Tribunal Superior de Justicia:\nI. Será presidido por la persona titular del Tribunal Superior de Justicia;\nII. Una persona titular de la Magistratura de las Salas del Tribunal Superior de Justicia;\nIII. Un Juzgador;\nIV. La persona titular de la Primera Secretaría de la Presidencia y del Pleno del Tribunal\nSuperior de Justicia, que realizará las funciones de Secretariado Técnico del Servicio Civil de Carrera Administrativa.;\nV. La persona titular de la Dirección Ejecutiva de Orientación Ciudadana y Derechos\nHumanos y la Dirección Ejecutiva de Recursos Humanos, que realizarán funciones de asesoría permanente; y\n\nVI. Las personas titulares de la Contraloría Interna y la Dirección Ejecutiva Jurídica, que realizarán funciones de observación permanente.\nLas y los titulares de las áreas que se mencionan en las fracciones I, II, III y IV participarán en las sesiones del Comité del Servicio Civil de Carrera Administrativa con voz y voto.\nLas y los titulares de las áreas que refieren las fracciones V y VI, participarán en las sesiones del\nComité del Servicio Civil de Carrera Administrativa sólo con voz. En caso de empate, quien ocupe la Presidencia del Comité tendrá el voto de calidad.\nLas atribuciones de la Dirección Ejecutiva de Orientación Ciudadana y Derechos Humanos y la\nDirección Ejecutiva de Recursos Humanos, se determinarán en el Reglamento.\nB. El Comité del Servicio Civil de Carrera Administrativa del Consejo de la Judicatura:\nI. Será presidido por quien ocupe la Presidencia del Consejo de la Judicatura;\nII. La persona titular de la Oficialía Mayor;\nIII. Una Magistrada o Magistrado integrante de las salas del Tribunal Superior de Justicia que desempeñe el cargo de Consejera o Consejero en el Consejo de la Judicatura;\nIV. Una Jueza o un Juez, que desempeñe el cargo de Consejera o Consejero en el Consejo de la Judicatura;\nV. La persona Titular de la Secretaría General del Consejo de la Judicatura, que realizará las funciones de Secretariado Técnico del Comité del Servicio Civil de Carrera\nAdministrativa;\nVI. La persona Titular de la Comisión de Disciplina Judicial y la Comisión de\nAdministración y Presupuesto, que realizarán funciones de asesoría permanente; y\nVII. La persona Titular de la Contraloría Interna y la Dirección Ejecutiva Jurídica, que realizarán funciones de observación permanente.\n\nLas y los Titulares de las áreas que se mencionan en las fracciones I, II, III y IV participarán en las sesiones del Comité con voz y voto.\nLas y los Titulares de las áreas que refieren las fracciones VI y VII, participarán en las sesiones del\nComité solo con voz. En caso de empate, la Presidencia del Comité tendrá el voto de calidad.\nLas atribuciones de la Dirección Ejecutiva de Orientación Ciudadana y Derechos Humanos y la\nDirección Ejecutiva de Recursos Humanos, se determinarán en el Reglamento.\nArtículo 384. Los Comités del Servicio Civil de Carrera Administrativa del Tribunal Superior de Justicia y del\nConsejo de la Judicatura tendrá las siguientes atribuciones:\nI. Proponer según corresponda a quien presida al Tribunal Superior de Justicia o al Consejo de la Judicatura las directrices para el óptimo funcionamiento del sistema;\nII. Aprobar las convocatorias para los concursos de ingreso;\nIII. Resolver los recursos de revisión presentados por las y los participantes en los concursos de ingreso;\nIV. Resolver los casos no previstos en las convocatorias;\nV. Aprobar las designaciones provisionales;\nVI. Resolver los recursos de revisión presentados por las y los integrantes del Servicio Civil de\nCarrera en los procesos de evaluación del desempeño; y\nVII. Las demás que determine quien presida al Tribunal Superior de Justicia o al Consejo de la\nJudicatura, o la normatividad aplicable.\nArtículo 385. Los Reglamentos que al efecto aprueben quienes presidan al Tribunal Superior de Justicia o al Consejo de la Judicatura, según correspondan, regularán los aspectos relacionados con las atribuciones de los Comités, designación de sus integrantes, funciones del secretariado técnico, de asesoría y de observación permanente; así como el quórum, votación, sesiones y trámite de asuntos.\n\nCAPÍTULO III\nDE LA SELECCIÓN, INGRESO PARITARIO Y PROMOCIÓN\nArtículo 386. Las personas interesadas en ingresar al Servicio Civil de Carrera deberán cumplir con los requisitos establecidos en los Catálogos de Puestos.\nArtículo 387. El ingreso al Servicio Civil de Carrera comprende el reclutamiento y selección de aspirantes para la ocupación de puestos vacantes.\nArtículo 388. El procedimiento de ingreso se realizará conforme a lo siguiente:\nI. Por concurso abierto, que es la vía de ingreso dirigida a personal interno y aspirantes externos al Tribunal Superior de Justicia y al Consejo de la Judicatura.\nII. Por concurso cerrado, que es la vía de selección dirigida a personal interno del Tribunal\nSuperior de Justicia y al Consejo de la Judicatura.\nLos concursos se realizarán conforme a las necesidades del servicio que considere el comité. En ambos supuestos se privilegiará el mecanismo abierto.\nEn caso de una vacante de urgente ocupación, la o el Titular del área administrativa podrá hacer la designación sin concurso, en cuyo caso, quien ocupe la vacante deberá participar en el inmediato posterior a su designación.\nArtículo 389. El proceso de reclutamiento y selección se realizará de conformidad con el reglamento que al efecto apruebe el Consejo de la Judicatura.\nLos términos, requisitos y forma de difusión de las convocatorias se establecerán en el reglamento.\nCAPÍTULO IV\nDE LA CAPACITACIÓN Y PROFESIONALIZACIÓN DEL PERSONAL\nArtículo 390. El Tribunal Superior de Justicia y el Consejo de la Judicatura, establecerán y organizarán programas de capacitación para proveer la formación necesaria a efecto de generar igualdad de\n\ncondiciones a las y los servidores públicos que permitan la profesionalización en el Servicio Civil de Carrera\nAdministrativa.\nArtículo 391. El proceso de capacitación y profesionalización del personal del Servicio Civil de Carrera\nAdministrativa será anual y se realizará en los términos que señale el reglamento que al efecto expida el\nConsejo de la Judicatura. Será determinado en su contenido por el comité, aprobado por el acuerdo del\nConsejo de la Judicatura y coordinado en su ejecución por el Instituto de Estudios Judiciales.\nArtículo 392. El Instituto, en colaboración con la Dirección Ejecutiva de Recursos Humanos, llevará el registro de los resultados obtenidos por el personal del Servicio Civil de Carrera Administrativa, a efecto de desarrollar las acciones necesarias para su profesionalización.\nArtículo 393. Con base en los lineamientos que apruebe el Consejo de la Judicatura, el Instituto de Estudios\nJudiciales con la colaboración de la Dirección Ejecutiva de Recursos Humanos llevará a cabo una detección de necesidades de capacitación, para conocer la situación actual de conocimientos, habilidades y nivel de profesionalización del personal que pertenece al Servicio Civil de Carrera Administrativa, que permita identificar las necesidades específicas para alcanzar las exigencias del puesto conforme a los catálogos de puestos.\nArtículo 394. El programa de capacitación será integrado y desarrollado por el Instituto de Estudios\nJudiciales en coordinación con las áreas administrativas y se basará en la detección de necesidades, de acuerdo con los perfiles de puestos establecidos en los catálogos de puestos, así como en los resultados de la evaluación de desempeño y el proceso de gestión de recursos humanos, a efecto de:\nI. Elevar las competencias del personal del Servicio Civil de Carrera Administrativa para cumplir los requisitos del puesto que desempeña.\nII. Fomentar la actualización o adquisición de conocimientos y habilidades acordes al desarrollo e innovación de los procesos administrativos del Tribunal Superior de Justicia y el Consejo de la\nJudicatura.\nEn los programas de capacitación deberán incluirse los relacionados con la integridad, ética y servicio público, la igualdad de género, así como aquellos relacionados con los derechos de los integrantes de grupos en situación de vulnerabilidad.\n\nArtículo 395. El programa de capacitación será obligatorio para el personal del Servicio Civil de Carrera\nAdministrativa, por lo que las y los Titulares otorgarán todas las facilidades para que asistan a las capacitaciones que les correspondan.\nCAPÍTULO V\nDE LA EVALUACIÓN DEL DESEMPEÑO Y CERTIFICACIÓN DE\nCOMPETENCIAS\nArtículo 396. La Dirección Ejecutiva de Recursos Humanos llevará a cabo, de forma anual, la evaluación al desempeño de las y los integrantes del Servicio Civil de Carrera Administrativa, conforme a la metodología, instrumentos y parámetros establecidos para tal efecto, conforme a la normatividad aplicable y a los catálogos de puestos.\nArtículo 397. En caso de desacuerdo con los resultados de la evaluación, el personal del Servicio Civil de\nCarrera Administrativa podrá solicitar la revisión de los resultados ante la Dirección Ejecutiva de Recursos\nHumanos dentro de los cuatro días hábiles siguientes a la notificación de los mismos.\nLa Dirección Ejecutiva de Recursos Humanos presentará el recurso de revisión al Comité para que este resuelva lo conducente dentro del plazo de veinte días hábiles posteriores a la recepción de la solicitud. La resolución emitida será definitiva e inatacable y deberá ser notificada de manera personal a la o el solicitante, en su área de trabajo.\nArtículo 398. El Comité podrá establecer programas, exámenes y mecanismos combinados a nivel institucional para la certificación de competencias del personal que forma parte del Servicio Civil de Carrera\nAdministrativa, con el apoyo del Instituto de Estudios Judiciales y la Dirección Ejecutiva de Recursos\nHumanos.\nArtículo 399. Con el apoyo de la Dirección Ejecutiva de Recursos Humanos, el Comité determinará el personal del Servicio Civil de Carrera Administrativa susceptible de certificación.\nEl expediente formado por la Dirección Ejecutiva de Recursos Humanos y los documentos entregados por las y los aspirantes, serán medios idóneos de comprobación de los requisitos contemplados en el catálogo y planes de carrera que al efecto se emitan.\n\nArtículo 400. La certificación de competencias deberá ser periódica, por lo que en ningún caso podrá tener una duración mayor a cinco años.\nAntes de que expire la vigencia de la certificación, la persona servidora pública interesada la deberá obtener de nueva cuenta, de conformidad con las políticas que al efecto expida el comité.\nArtículo 401. El comité podrá incorporar las mejores prácticas nacionales e internacionales en materia de certificación de competencias, para lo cual podrá proponer al Consejo de la Judicatura celebrar convenios con instancias certificadoras externas, tanto de índole pública como privada.\nArtículo 402. Los reconocimientos se podrán otorgar con motivo del resultado sobresaliente tanto en la capacitación como en la evaluación del desempeño y dependerá de la información obtenida durante el procedimiento de evaluación global. El Consejo de la Judicatura, a propuesta del Comité, definirá los criterios.\nCAPÍTULO VI\nDE LA SEPARACIÓN DEL PERSONAL DEL SERVICIO CIVIL DE CARRERA\nADMINISTRATIVA\nArtículo 403. El Servicio Civil de Carrera Administrativa contará con los mecanismos y procedimientos a seguir para que el nombramiento de una persona servidora pública de carrera administrativa deje de surtir efectos, sin responsabilidad para la dependencia, así como si procede autorizar a una persona servidora pública de carrera para que deje de desempeñar las funciones de su puesto de manera temporal, y lo relativo a la suspensión de los efectos del nombramiento respectivo.\nArtículo 404. La separación del personal del Servicio Civil de Carrera podrá darse por las siguientes causas:\nI. Por renuncia, que deberá hacer por escrito;\nII. Retiro por edad o tiempo de servicio;\nIII. Por no aprobar las evaluaciones comprendidas en el Servicio Civil de Carrera Administrativa;\nIV. Por no cumplir con las obligaciones establecidas en el Servicio Civil de Carrera Administrativa;\ny\n\nV. Destitución o inhabilitación por resolución firme que así lo determine.\nArtículo 405. El proceso de substanciación para la separación del personal del Servicio Civil de Carrera\nAdministrativa será definido por el Comité del Servicio Civil de Carrera Administrativa, con la aprobación del Consejo de la Judicatura, respetando en todo momento los Derechos Humanos y sus garantías.\nTÍTULO DÉCIMO SEXTO\nDE LA CONTRALORÍA\nCAPÍTULO ÚNICO\nArtículo 406.La Contraloría del Poder Judicial de la Ciudad de México, tendrá autonomía técnica y de gestión.\nLa Contraloría tendrá a su cargo las facultades de control, supervisión, evaluación, inspección y vigilancia del cumplimiento de las normas de funcionamiento administrativo que fijan las leyes aplicables a los\nÓrganos, personas servidoras públicas y empleados del propio Tribunal Superior de Justicia y del Consejo de la Judicatura, por lo que será competente para realizar las auditorías, revisiones e inspecciones con el propósito de verificar el cumplimiento a la normativa aplicable; promover, evaluar y fortalecer el buen funcionamiento del control interno, así como para iniciar y sustanciar los procedimientos de responsabilidad administrativa de las personas servidoras públicas y resolverlos en los términos establecidos en las disposiciones jurídicas aplicables.\nArtículo 407. La Contraloría contará con el personal necesario para el correcto ejercicio de sus facultades.\nContará con una persona Titular que se denomina Contralor General del Tribunal Superior de Justicia, nombrado por el Consejo de la Judicatura y ratificado por el Congreso Local, durará en el cargo seis años sin posibilidad de reelección, deberá satisfacer los requisitos que señala el artículo 21, con excepción de lo establecido por el último párrafo de la fracción VII, de esta Ley, deberá además acreditar los conocimientos suficientes para el ejercicio del cargo.\nArtículo 408. Corresponde a la o al titular de la Contraloría originalmente la representación y trámite de los asuntos de la competencia de aquella, y quien podrá, para la mejor distribución y desarrollo del trabajo, conferir sus facultades a las y los servidores públicos subalternos, sin perjuicio de su ejercicio directo.\n\nArtículo 409. Para el ejercicio de sus funciones la Contraloría tiene a su cargo las atribuciones que corresponden a su propio ámbito de competencia y se regirá por lo previsto en esta Ley y su Reglamento, así como en los acuerdos que para tal efecto apruebe quien sea competente.\nArtículo 410. La competencia de la Contraloría estará determinada por la naturaleza de la conducta o faltas de las y los servidores públicos del Poder Judicial por lo que deberá ajustarse a lo estrictamente establecido en el artículo siguiente de esta Ley, sujetando su actuación al conocimiento de las disposiciones en materia de planeación, presupuesto, ingresos, egresos, financiamiento, inversión, patrimonio, fondos y valores, así como las relativas a los sistemas de registro y contabilidad, contratación y pago de personal, contratación de servicios y recursos materiales, planeación, situación patrimonial y auditorías, transparencia y datos personales, vigilando su cumplimiento y las demás, conforme a la normatividad aplicable, así como a las leyes en materia de responsabilidades administrativas.\nArtículo 411.La Contraloría del Tribunal Superior de Justicia contará con las siguientes atribuciones:\nI. Someter a la consideración y aprobación de quien presida al Tribunal Superior de Justicia, el programa anual de auditoría, de la declaración de modificación patrimonial de cada anualidad, participación en inventarios y los demás inherentes a las funciones a cargo de la Contraloría;\nII. Someter a quien presida el Tribunal Superior de Justicia los asuntos encomendados a la\nContraloría, que así lo amerite, desempeñar las comisiones y funciones que éste le confiera y mantenerlo informado sobre el desarrollo de las mismas;\nIII. Establecer e instrumentar las políticas, procedimientos y estrategias de operación de la\nContraloría, conforme a la normatividad en materia de auditoría; control y evaluación;\nresponsabilidades, quejas, denuncias e inconformidades;\nIV. Llevar a cabo las visitas administrativas a las áreas no jurisdiccionales en materia de planeación, presupuesto, ingresos, egresos, financieras, administrativas, operacionales, fondos y valores, obra pública, recursos humanos, contabilidad y de cualquier otro tipo, a las áreas que conforman el Tribunal Superior de Justicia y el Consejo de la Judicatura, emitiendo el informe correspondiente a que haya lugar, pudiendo ampliar el objeto de dicha visita, con el propósito de transparentar la gestión del manejo de sus recursos;\n\nV. Verificar el cabal cumplimiento a los dictámenes de estructura, manuales de organización y procedimientos que se emitan por su Titular;\nVI. Formular y presentar los anteproyectos de programas y presupuestos de la Contraloría, y proponer las adecuaciones que requiera su correcto ejercicio;\nVII. Vigilar el cumplimiento, por parte de las personas servidoras públicas del poder judicial de las disposiciones en materia de planeación, presupuesto, ingresos, egresos, financiamiento, inversión, patrimonio, fondos y valores;\nVIII. Formular y presentar los anteproyectos de programas y presupuestos de la contraloría, y proponer las adecuaciones que requiera su correcto ejercicio;\nIX. Verificar el cabal cumplimiento a los dictámenes de estructura, manuales de organización y procedimientos que se emitan por su titular;\nX. Formular y presentar los anteproyectos de programas y presupuestos de la contraloría, y proponer las adecuaciones que requiera su correcto ejercicio;\nXI. Vigilar el cumplimiento, por parte de las y los servidores públicos del Poder Judicial, de las disposiciones en materia de planeación, presupuesto, ingresos, egresos, financiamiento, inversión, patrimonio, fondos y valores;\nXII. Vigilar el debido cumplimiento de las normas establecidas por la legislación en materia de responsabilidades administrativas;\nXIII. Asimismo, inspeccionar y vigilar la debida observancia del cumplimiento de las normas y disposiciones relativas a los sistemas de registro y adquisiciones, contabilidad, contratación de personal, contratación de servicios y ejecución de obra pública, conservación, uso, destino, afectación y baja de bienes muebles e inmuebles, almacén y recursos materiales del Poder\nJudicial;\nXIV. Planear, programar, dirigir, controlar y evaluar las auditorías en materia de planeación, presupuesto, ingresos, egresos, financieras, administrativas, operacionales, integrales, de desempeño y de seguimiento, patrimonio, fondos, obra pública, recursos humanos y contabilidad, de cualquier otro tipo, de las áreas que conforman el Poder Judicial, emitiendo los\n\ndictámenes técnicos o informes de auditoría a que haya lugar, pudiendo autorizar la ampliación del período sujeto a revisión, así como el objeto de dichas auditorías, con el propósito de transparentar la gestión y manejo de los recursos del Poder Judicial;\nXV. Dentro del ámbito de su competencia, ordenar de oficio, por queja o denuncia debidamente fundada, o en virtud de irregularidades derivadas de auditorías, la práctica de investigaciones respecto de la conducta de las o los servidores públicos del Tribunal Superior de Justicia y del\nConsejo de la Judicatura, que pudiera implicar inobservancia de las obligaciones previstas por la legislación en materia de responsabilidades administrativas y demás disposiciones aplicables, y tratándose de conductas atribuibles a las y los servidores públicos del ámbito judicial, cuando estas se relacionen con su actuación en asuntos jurisdiccionales, remitirlos a la Comisión de\nDisciplina Judicial;\nXVI. Colaborar con la Auditoría Superior en el desarrollo de las auditorías y la revisión de la cuenta pública;\nXVII. Aprobar la contratación de profesionistas independientes, personas físicas o morales, para la realización de auditorías, de la gestión pública en las Unidades Administrativas y de Apoyo\nJudicial, del Poder Judicial;\nXVIII. Determinar mecanismos para auditar la prestación de los servicios públicos, a fin de mejorar su calidad, corregir las irregularidades detectadas y promover la comparación sistemática con los estándares de calidad de otros centros de servicio;\nXIX. Verificar el cumplimiento de las obligaciones contenidas en las disposiciones, normas y lineamientos en materia de planeación, programación y presupuesto, información, estadística, contabilidad, organización y procedimientos, ingresos, egresos, financiamiento, inversión, deuda, administración de recursos humanos, informáticos, materiales y financieros, patrimonio, obra pública, fondos, valores y fideicomisos, por parte de los órganos y las o los servidores públicos del Poder Judicial;\nXX. Intervenir en la revisión de los programas anuales de adquisiciones, arrendamientos y prestación de servicios, de obra pública, enajenación de bienes muebles e inmuebles y los demás que refieran manejo de los recursos, así como de las bases conforme a las cuales se sujetarán los procedimientos de licitación pública, invitación restringida y adjudicación directa;\n\nXXI. Inspeccionar y vigilar la contratación de adquisiciones, arrendamientos, prestación de servicios y obra pública y enajenación y baja de bienes muebles e inmuebles;\nXXII. Participar en los procedimientos de adquisición, contratación, servicios y arrendamientos, de obra pública, conservación, uso, destino, afectación y baja de bienes muebles e inmuebles, almacén y recursos materiales; así como en los procedimientos de enajenación y destrucción de bienes muebles e inmuebles, así como en los procedimientos de destrucción y enajenación de bienes decomisados y abandonados;\nXXIII. Intervenir en los procesos de entrega-recepción de los diversos cargos de las o los servidores públicos del Poder Judicial;\nXXIV. Colaborar en los procedimientos regulados en los acuerdos generales mediante los cuales se establecen lineamientos en materia de adquisiciones, arrendamiento de bienes muebles y prestación de servicios de cualquier naturaleza; normas para el registro, control, destino final y baja de bienes muebles, así como para el registro y control de bienes inmuebles, que integran el activo del Tribunal Superior de Justicia y del Consejo de la Judicatura; en materia de obra pública y servicios relacionados con ésta. Y en materia de entrega recepción de los recursos del\nTribunal Superior de Justicia y del Consejo de la Judicatura;\nXXV. Coordinar la recepción y registro de las declaraciones de situación patrimonial, conflicto de intereses y entrega de la copia del acuse de la declaración fiscal que deben presentar los servidores públicos del Poder Judicial y, en su caso, instruir las acciones correspondientes por incumplimiento, en su presentación;\nXXVI. Ordenar el registro, seguimiento y resguardo de las declaraciones de situación patrimonial, de conflicto de intereses y declaración fiscal, presentadas por las o los servidores públicos que integran el Poder Judicial, regulada por el acuerdo general que establece los lineamientos mediante los cuales se determina como obligatoria la presentación de las declaraciones de modificación de situación patrimonial anual, de situación patrimonial de inicio y conclusión, así como de declaración de conflicto de intereses;\nXXVII. Ordenar dentro del ámbito de su competencia, el inicio de los procedimientos administrativos de responsabilidad, por presuntas violaciones a las leyes en materia de responsabilidades administrativas y demás normatividad que con motivo de su empleo, cargo o\n\ncomisión deban observar los servidores públicos adscritos al Poder Judicial, dando cuenta al\nPresidente del Tribunal Superior de Justicia o al Consejo de la Judicatura según corresponda;\nXXVIII. Llevar a cabo las diligencias que marca la normatividad en materia de responsabilidades, emitiendo los acuerdos correspondientes dentro de dicho procedimiento, relativo al desahogo de pruebas así como emitir la resolución que resuelva el mismo o le ponga fin, y determinar, en su caso, las sanciones que correspondan en los términos de la legislación de la materia, informando al Presidente del Tribunal Superior de Justicia y al Presidente del Consejo de la\nJudicatura, así como a la Oficialía Mayor para su correspondiente aplicación;\nXXIX. Conocer y resolver los recursos de inconformidad que interpongan los licitantes por los actos de procedimiento que se consideren realizados en contravención con la normatividad en materia de adquisiciones, arrendamientos y prestación de servicios, enajenación de bienes y obra pública;\nXXX. Proporcionar a cualquier interesada o interesado las facilidades necesarias para presentar las quejas y denuncias en contra de las o los servidores públicos del Poder Judicial, con motivo del incumplimiento de sus obligaciones y/o irregularidades en la prestación de un servicio;\nXXXI. Establecer las sanciones correspondientes informando al Pleno del Consejo de la\nJudicatura, así como a la Oficialía Mayor para su correspondiente aplicación;\nXXXII. Llevar el registro y control de las quejas y denuncias, comunicándolas a las áreas donde se originaron y solicitándoles su desahogo a la brevedad posible;\nXXXIII. Analizar las causas y los mecanismos utilizados en los casos de comisión de probables ilícitos, así como comprobar la forma en que funcionan los controles establecidos, con el fin de evitar y prevenir su recurrencia;\nXXXIV. Emitir opiniones y observaciones tratándose de asuntos de la competencia de la\nContraloría;\nXXXV. Delegar o conferir las atribuciones que fueren necesarias al personal adscrito a la\nContraloría para el debido cumplimiento de los asuntos de su competencia, con el objeto de cumplir con la máxima diligencia las funciones y atribuciones de la Contraloría, así como en los casos de ausencia del Contralor General.\n\nXXXVI. Expedir las autorizaciones que se requieran de cualquier documentación que obre en los archivos de la Contraloría, excepto las que por su especial naturaleza sea considerada información y/o documentación clasificada como confidencial o reservada, con respecto a los procedimientos administrativos de responsabilidad, auditorías y situación patrimonial de las y los servidores públicos del Poder Judicial, en términos de la Ley de Transparencia, Acceso a la\nInformación Pública y Rendición de Cuentas de la Ciudad de México;\nXXXVII. Denunciar ante las autoridades competentes los hechos de que se tengan conocimiento y puedan ser constitutivos de probables delitos, y solicitar la intervención del área jurídica respectiva a formular, cuando así se requiera, las querellas a que hubiere lugar;\nXXXVIII. Recibir, tramitar y dictaminar, en su caso, con sujeción a lo dispuesto por la Ley General de Responsabilidades Administrativas y la Ley de Responsabilidad Patrimonial de la Ciudad de\nMéxico, las solicitudes de los particulares relacionadas con las y los servidores públicos del Poder\nJudicial, a quienes se les comunicará el dictamen para que reconozcan, si así lo determinan, la responsabilidad de indemnizar la reparación del daño;\nXXXIX. Requerir a las áreas del Poder Judicial, la información necesaria para cumplir con sus atribuciones administrativas;\nXL. Proponer la designación y remoción del personal que conforma la Contraloría;\nXLI. Informar trimestralmente al Pleno del Consejo de la Judicatura sobre el resultado de la evaluación de las áreas que hayan sido objeto de fiscalización, así como sobre la ejecución y avances de su programa anual de trabajo;\nXLII. Planear, programar, establecer, organizar y coordinar el sistema de control interno y evaluación de la gestión gubernamental del Poder Judicial de la Ciudad de México, manteniendo permanentemente su actualización, así como establecer indicadores para la evaluación de la gestión, en los términos de las disposiciones aplicables;\nXLIII.Someter para autorización del Pleno del Consejo de la Judicatura las normas, instrumentos y procedimientos de control interno en el Poder Judicial;\n\nXLIV. Aportar toda la información en el ámbito de su competencia para la debida integración y operación de la Plataforma Digital del Sistema Anticorrupción de la Ciudad de México, en términos de la Ley de la Materia;\nXLV. Celebrar convenios de coordinación, con la Auditoría Superior de la Ciudad de México, y con la Secretaría de la Función Pública, para el establecimiento de los procedimientos necesarios que permitan a ambos órganos el cumplimiento de sus respectivas funciones y fortalecer los trabajos del Sistema de Fiscalización de la Ciudad de México; y\nXLVI. Las demás que con tal carácter le atribuyan expresamente las disposiciones legales y reglamentarias.\nARTÍCULOS TRANSITORIOS\nPRIMERO. - Remítase al Jefe de Gobierno del Distrito Federal para efectos de su promulgación y publicación.\nSEGUNDO. - Publíquese en la Gaceta Oficial de la Ciudad de México y en el Diario Oficial de la Federación para su mayor difusión.\nTERCERO. - De conformidad con el artículo Décimo Primero Transitorio de la Constitución Política de la\nCiudad de México, la presente Ley entrará en vigor al día siguiente de su publicación en la Gaceta de la\nCiudad de México, con excepción de las disposiciones que establezcan una entrada en vigor diferente en la Constitución y la presente ley.\nDe conformidad con el artículo Vigésimo Tercero Transitorio de la Constitución Política de la Ciudad de\nMéxico, con el propósito de sustituir de forma escalonada a las y a los integrantes del Consejo de la\nJudicatura, quienes, a la fecha de entrada en vigor del presente, ocupen dicho encargo, concluirán el periodo para el que fueron electos. La persona, que actualmente ocupa la presidencia del Pleno del\nTribunal y del Consejo de la Judicatura, concluirá el periodo para el cual haya sido electo y, en su caso, podrá participar en el proceso de elección siguiente.\nCUARTO. -Las normas relativas a la Sala Constitucional empezarán su vigencia el 1 de julio del año 2019.\n\nQUINTO. - Al momento de la entrada en vigor de la Ley Orgánica del Poder Judicial de la Ciudad de México, quedarán abrogadas la Ley Orgánica del Tribunal Superior de Justicia del Distrito Federal, y los ordenamientos legales contrarios al presente Decreto.\nSEXTO.- El Tribunal Superior de Justicia de la Ciudad de México, contará con 180 días naturales a partir de la entrada en vigor de este Decreto, para adecuar su estructura a lo establecido en la presente Ley.\nSÉPTIMO.- Los transitorios contenidos en los decretos publicados en la Gaceta Oficial del Distrito Federal el veinticuatro de abril de dos mil tres y nueve de junio de dos mil catorce, permanecerán vigentes para regular al correspondiente fondo de retiro, por tratarse de derechos adquiridos.\nOCTAVO.- En tanto no entre en vigencia la Unidad de Medida y Actualización se entenderá que se tendrá por válida la Unidad de Cuenta de la Ciudad de México.\nNOVENO.- En lo referente al sistema jurídico de los pueblos y barrios originarios de la Ciudad de México, se estará a lo que disponga la Ley reglamentaria que emita el primer Congreso de la Ciudad de México.\nDÉCIMO.- Las personas trabajadoras del Poder Judicial de la Ciudad de México conservaran los derechos adquiridos que deriven de la aplicación del orden jurídico que los rija al momento de entrar en vigor las disposiciones en la materia de la Constitución.\nLas personas trabajadoras de los órganos públicos de la Ciudad de México que hasta el 31 de diciembre de\n2019 se encuentren incorporados al Instituto de Seguridad y Servicios Sociales de los Trabajadores del\nEstado, continuarán sujetos al mismo régimen de seguridad social.\nCorresponde al Tribunal Laboral del Poder Judicial la impartición de la Justicia Laboral de acuerdo con lo establecido en el Apartado A del artículo 123 de la Constitución Política de los Estados Unidos Mexicanos y la Ley Federal del Trabajo.\nDÉCIMO PRIMERO.- El Poder Judicial de la Ciudad de México conservará su denominación, atribuciones y estructura hasta en tanto no entre en vigor la presente Ley.\nDÉCIMO SEGUNDO.- El Poder Judicial de la Ciudad de México recibirá los bienes y los recursos humanos y materiales que estén a cargo del mismo.\n\nDÉCIMO TERCERO.- En tanto no entre en vigor disposición normativa que supla lo relativo a la materia de cuantía, se estará a lo dispuesto a lo que establece el Código de Procedimientos Civiles para el Distrito\nFederal.\nDÉCIMO CUARTO. -El Poder Legislativo de la Ciudad de México expedirá las leyes de la función judicial sobre las disposiciones que entraran en vigor a partir del 1 de Octubre de 2019, y aquellas necesarias para adecuar lo relativo a la Justicia Alternativa.\nRecinto de la Asamblea Legislativa del Distrito Federal, a los veinte días del mes de diciembre del año dos mil diecisiete.- POR LA MESA DIRECTIVA.- DIP. ADRIÁN RUBALCAVA SUÁREZ, PRESIDENTE.- DIP. REBECA\nPERALTA LEÓN, SECRETARIA.- DIP. EVA ELOISA LESCAS HERNÁNDEZ, SECRETARIA. (Firmas)\nCon fundamento en lo dispuesto por los artículos 122, Apartado A, Base III, de la Constitución Política de los Estados Unidos Mexicanos; Transitorios Primero y Segundo del Decreto por el que se declaran reformadas y derogadas diversas disposiciones de la Constitución Política de los Estados Unidos Mexicanos, en materia de la Reforma Política de la Ciudad de México; 48, 49 y 67, fracción II, del Estatuto de Gobierno del Distrito Federal, para su debida publicación y observancia, expido el presente Decreto Promulgatorio en la Residencia Oficial del Jefe de Gobierno de la Ciudad de México, a los tres días del mes de mayo del año dos mil dieciocho. EL JEFE DE GOBIERNO DE LA CIUDAD DE MÉXICO, JOSÉ RAMÓN AMIEVA GÁLVEZ. -\nFIRMA. - EL SECRETARIO DE GOBIERNO, GUILLERMO OROZCO LORETO. - FIRMA.\nTRANSITORIOS DEL DECRETO POR EL QUE SE REFORMA EL SEGUNDO PÁRRAFO DEL ARTÍCULO 66 DE LA LEY\nORGÁNICA DEL PODER JUDICIAL DE LA CIUDAD DE MÉXICO, PUBLICADO EN LA GACETA OFICIAL DE LA\nCIUDAD DE MÉXICO EL 08 DE FEBRERO 2019.\nPRIMERO. - El presente decreto entrará en vigor de conformidad con lo dispuesto en el Artículo Décimo\nPrimero Transitorio de la Constitución Política de la Ciudad de México.\nSEGUNDO. - Remítase al Jefe de Gobierno del Distrito Federal para su publicación en la Gaceta Oficial de la Ciudad de México.\nPalacio Legislativo del Congreso de la Ciudad de México, a los veinte días del mes de diciembre del año dos mil dieciocho. - POR LA MESA DIRECTIVA. - DIPUTADO JOSÉ DE JESÚS MARTÍN DEL CAMPO CASTAÑEDA,\nPRESIDENTE. - DIPUTADA ISABELA ROSALES HERRERA, SECRETARIA. - DIPUTADA ANA PATRICIA BAEZ\nGUERRERO. - SECRETARIA. - (Firmas)\n\nCon fundamento en lo dispuesto por los artículos 122, Apartado A, fracción III, de la Constitución Política de los Estados Unidos Mexicanos; 32 apartado C, numeral 1, inciso a) de la Constitución Política de la\nCiudad de México; 2, 3, fracciones XVII y XVIII, 7, 10 fracción II, 12 y 21 párrafo primero de la Ley Orgánica del Poder Ejecutivo y de la Administración Pública de la Ciudad de México; para su debida publicación y observancia, expido el presente Decreto Promulgatorio en la Residencia Oficial de la Jefatura de Gobierno de la Ciudad de México, a los veintinueve días del mes de enero del año dos mil diecinueve. LA JEFA DE\nGOBIERNO DE LA CIUDAD DE MÉXICO, DRA. CLAUDIA SHEINBAUM PARDO. - FIRMA. - LA SECRETARIA DE\nGOBIERNO, ROSA ICELA RODRÍGUEZ VELÁZQUEZ. - FIRMA.\nTRANSITORIOS DEL DECRETO POR EL QUESE REFORMAN LOS ARTÍCULOS TRANSITORIOS TERCERO Y\nCUARTO DE LA LEY ORGÁNICA DEL PODER JUDICIAL DE LA CIUDAD DE MÉXICO, PUBLICADO EN LA GACETA\nOFICIAL DE LA CIUDAD DE MÉXICO, EL 26 DE ABRIL DE 2019\nPRIMERO. Publíquese en la Gaceta Oficial de la Ciudad de México.\nSEGUNDO. La presente reforma entrará en vigor inmediatamente después de que entre entren en vigor las reformas correspondientes al articulado transitorio de la Constitución de la Ciudad de México aludido en este decreto.\nPalacio Legislativo del Congreso de la Ciudad de México, a los catorce días del mes de marzo del año dos mil diecinueve.- POR LA MESA DIRECTIVA.- DIPUTADO JOSÉ DE JESÚS MARTÍN DEL CAMPO CASTAÑEDA,\nPRESIDENTE.- DIPUTADA ISABELA ROSALES HERRERA, SECRETARIA.- DIPUTADA ANA PATRICIA BAEZ\nGUERRERO, SECRETARIA.- (Firmas)\nCon fundamento en lo dispuesto por los artículos 122, Apartado A, fracción III, de la Constitución Política de los Estados Unidos Mexicanos; 32 apartado C, numeral 1, inciso a) de la Constitución Política de la\nCiudad de México; 3 fracciones XVII y XVIII, 7, 10 fracción II, 16 y 21, párrafo primero, de la Ley Orgánica del Poder Ejecutivo y de la Administración Pública de la Ciudad de México; para su debida publicación y observancia, expido el presente Decreto Promulgatorio en la Residencia Oficial de la Jefatura de Gobierno de la Ciudad de México, a los veintiséis días del mes de marzo del año dos mil diecinueve.- LA JEFA DE\nGOBIERNO DE LA CIUDAD DE MÉXICO, DRA. CLAUDIA SHEINBAUM PARDO.- FIRMA.- LA SECRETARIA DE\nGOBIERNO, ROSA ICELA RODRÍGUEZ VELÁZQUEZ.- FIRMA.\n\nTRANSITORIOS DEL DECRETO POR EL QUE SE REFORMAN LOS ARTÍCULOS 38, 209, 210, 213, LA FRACCIÓN\nIX DEL ARTÍCULO 218 Y EL ARTÍCULO TERCERO TRANSITORIO DE LA LEY ORGÁNICA DEL PODER JUDICIAL DE\nLA CIUDAD DE MÉXICO, PUBLICADO EN LA GACETA OFICIAL DE LA CIUDAD DE MÉXICO, EL 10 DE DICIEMBRE\nDE 2019\nPRIMERO. - El presente Decreto entrará en vigor el día siguiente de su publicación en la Gaceta Oficial de la Ciudad de México.\nSEGUNDO. - Se derogan todas las disposiciones que se opongan al presente Decreto. TERCERO. -\nPublíquese en la Gaceta Oficial de la Ciudad de México, y para su mayor difusión en el Diario Oficial de la\nFederación.\nPalacio Legislativo del Congreso de la Ciudad de México, a los cinco días del mes de diciembre del año dos mil diecinueve.- POR LA MESA DIRECTIVA.- DIPUTADA ISABELA ROSALES HERRERA, PRESIDENTA.-\nDIPUTADA MARTHA SOLEDAD VENTURA ÁVILA, SECRETARIA.- DIPUTADA MARGARITA SALDAÑA\nHERNÁNDEZ, SECRETARIA.- (Firmas)\nCon fundamento en lo dispuesto por los artículos 122, apartado A, fracción III, de la Constitución Política de los Estados Unidos Mexicanos; 32 apartado C, numeral 1, inciso a) de la Constitución Política de la\nCiudad de México; 3, fracciones XVII y XVIII, 7 párrafo primero, 10 fracción II, 12 y 21 párrafo primero de la\nLey Orgánica del Poder Ejecutivo y de la Administración Pública de la Ciudad de México; para su debida publicación y observancia, expido el presente Decreto Promulgatorio en la Residencia Oficial de la Jefatura de Gobierno de la Ciudad de México, a los nueve días del mes de diciembre del año dos mil diecinueve.-\nLA JEFA DE GOBIERNO DE LA CIUDAD DE MÉXICO, DRA. CLAUDIA SHEINBAUM PARDO.- FIRMA.- LA\nSECRETARIA DE GOBIERNO, ROSA ICELA RODRÍGUEZ VELÁZQUEZ.- FIRMA\nTRANSITORIOS DEL DECRETO POR EL QUE SE REFORMAN LOS ARTÍCULOS 52 PÁRRAFO SEGUNDO Y\nTERCERO, 61 PÁRRAFO SEPTIMO, 102 PÁRRAFO TERCERO Y 103 ÚLTIMO PÁRRAFO DE LA LEY ORGÁNICA\nDEL PODER JUDICIAL DE LA CIUDAD DE MÉXICO, PUBLICADO EN LA GACETA OFICIAL DE LA CIUDAD DE\nMÉXICO, EL 24 DE DICIEMBRE DE 2019\nPRIMERO. – El presente decreto entrará en vigor al día siguiente de su publicación en la Gaceta Oficial de la Ciudad de México.\nSEGUNDO. - Remítase a la Jefa de Gobierno de la Ciudad de México para efectos de su publicación.\n\nTERCERO.- Publíquese en la Gaceta Oficial de la Ciudad de México y en el Diario Oficial de la Federación para su mayor difusión.\nPalacio Legislativo del Congreso de la Ciudad de México, a los trece días del mes de diciembre del año dos mil diecinueve.- POR LA MESA DIRECTIVA.- DIPUTADA ISABELA ROSALES HERRERA, PRESIDENTA.-\nDIPUTADA MARTHA SOLEDAD VENTURA ÁVILA, SECRETARIA.- DIPUTADA MARGARITA SALDAÑA\nHERNÁNDEZ, SECRETARIA.- (Firmas)\nCon fundamento en lo dispuesto por los artículos 122, apartado A, fracción III, de la Constitución Política de los Estados Unidos Mexicanos; 32 apartado C, numeral 1, inciso a) de la Constitución Política de la\nCiudad de México; 3 fracciones XVII y XVIII, 7 párrafo primero, 10 fracción II, 12 y 21, párrafo primero, de la Ley Orgánica del Poder Ejecutivo y de la Administración Pública de la Ciudad de México; para su debida publicación y observancia, expido el presente Decreto Promulgatorio en la Residencia Oficial de la Jefatura de Gobierno de la Ciudad de México, a los veintitrés días del mes diciembre del año dos mil diecinueve.-\nLA JEFA DE GOBIERNO DE LA CIUDAD DE MÉXICO, DRA. CLAUDIA SHEINBAUM PARDO.- FIRMA.- LA\nSECRETARIA DE GOBIERNO, ROSA ICELA RODRÍGUEZ VELÁZQUEZ.- FIRMA.\nTRANSITORIOS DEL DECRETO POR EL QUE SE REFORMA EL ARTÍCULO 218 DE LA LEY ORGÁNICA DEL PODER\nJUDICIAL DE LA CIUDAD DE MÉXICO, ADICIONANDO UNA NUEVA FRACCIÓN XXXI. EL ACTUAL CONTENIDO\nDE LA FRACCIÓN XXX, SE TRASLADA DE FORMA ÍNTEGRA Y PASA A FORMAR PARTE DE LA NUEVA FRACCIÓN\nXXXI\nPrimero: El presente decreto entrará en vigor, al día siguiente de su publicación en la Gaceta Oficial de la\nCiudad de México.\nSegundo. Remítase a la Jefa de Gobierno para efectos los efectos procedimentales correspondientes.\nPalacio Legislativo del Congreso de la Ciudad de México, a los siete días del mes de julio del año dos mil veintiuno. POR LA MESA DIRECTIVA, DIPUTADA ANA PATRICIA BAEZ GUERRERO, PRESIDENTA, DIPUTADA\nDONAJI OFELIA OLIVERA REYES, SECRETARIA, DIPUTADO PABLO MONTES DE OCA DEL OLMO (Firmas)\nCon fundamento en lo dispuesto por los artículos 122, apartado A, fracción III de la Constitución Política de los Estados Unidos Mexicanos; 32, apartado C, numeral 1, inciso a) de la Constitución Política de la Ciudad de México; 2 párrafo segundo, 3 fracciones XVII y XVIII, 7 párrafo primero, 10 fracción II, 12 y 21 párrafo\n\nprimero de la Ley Orgánica del Poder Ejecutivo y de la Administración Pública de la Ciudad de México; para su debida publicación y observancia, expido el presente Decreto Promulgatorio en la Residencia Oficial de la Jefatura de Gobierno de la Ciudad de México, a los veintiún días del mes de julio del año dos mil veintiuno.- LA JEFA DE GOBIERNO DE LA CIUDAD DE MÉXICO, DRA. CLAUDIA SHEINBAUM PARDO.- FIRMA.-\nEL SECRETARIO DE GOBIERNO, MARTÍ BATRES GUADARRAMA.- FIRMA.\nTRANSITORIO DEL DECRETO POR EL QUE SE MODIFICA LA DENOMINACIÓN DEL CAPÍTULO VI DEL TÍTULO\nCUARTO; SE REFORMAN Y MODIFICAN LAS FRACCIONES II, III, IV, VI, VIII, IX, X, XI, XII, XIII, XV, XVI, XVIII,\nXIX, Y XX DEL ARTÍCULO 5; SE MODIFICA EL ÚLTIMO PÁRRAFO DEL ARTÍCULO 6, ASÍ COMO LOS ARTÍCULOS\n7, 11, 12, 13 Y 14; SE DEROGAN LA FRACCIÓN IX DEL ARTÍCULO 21, ASÍ COMO EL ARTÍCULO 23; SE\nMODIFICAN LOS ARTÍCULOS 32, ASÍ COMO LAS FRACCIONES V, VI, VII, XI, Y XV DEL ARTÍCULO 37; SE\nREFORMAN LOS ARTÍCULOS 39, LA FRACCIÓN II DEL ARTÍCULO 41 Y 49; SE MODIFICAN LAS FRACCIONES\nVI, VII; Y VIII DEL ARTÍCULO 50 Y 58; SE REFORMAN EL PRIMER PÁRRAFO, ASÍ COMO LAS FRACCIONES II,\nIII, V, VI, X, XI, XII, XIII, XIV Y XV, Y SE AGREGA UN ÚLTIMO PÁRRAFO, AL ARTÍCULO 59; SE REFORMAN EL\nPÁRRAFO TERCERO DEL ARTÍCULO 60 Y EL PÁRRAFO SÉPTIMO DEL ARTÍCULO 61; SE REFORMAN LOS\nARTÍCULOS 89, 94, 100, 101; SE DEROGA EL ARTÍCULO 104; SE MODIFICAN LAS FRACCIONES I, V, VI Y VII,\nY SE AGREGA UN ÚLTIMO PÁRRAFO AL ARTÍCULO 105; SE REFORMAN EL SEGUNDO PÁRRAFO DEL ARTÍCULO\n107 Y EL PRIMER PÁRRAFO DEL ARTÍCULO 179; SE MODIFICA EL PRIMER PÁRRAFO DEL ARTÍCULO 198; SE\nMODIFICA EL SEGUNDO PÁRRAFO DEL ARTÍCULO 200; SE REFORMAN LOS ARTÍCULO 217, 218, ASÍ COMO\nLAS FRACCIONES XV, XXX, XXXI, XXXII Y XXXIII DEL ARTÍCULO 219; SE MODIFICAN EL ARTÍCULO 230, ASÍ\nCOMO EL PRIMER PÁRRAFO, Y LOS INCISOS C) Y E) DE LA FRACCIÓN V DEL ARTÍCULO 235; SE REFORMAN\nLAS FRACCIONES I, II Y III DEL ARTÍCULO 236, ASÍ COMO LOS ARTÍCULOS 237, 240, 241, 242, 246, 247,\nPRIMER PÁRRAFO DEL ARTÍCULO 250, 260 Y 272 DE LA LEY ORGÁNICA DEL PODER JUDICIAL DE LA CIUDAD\nDE MÉXICO, PUBLICADO EN LA GACETA OFICIAL DE LA CIUDAD DE MÉXICO EL DÍA 02 DE SEPTIEMBRE DE\n2021.\nPRIMERO. - Remítase a la Jefa de Gobierno de la Ciudad de México para efectos de su promulgación y publicación.\nSEGUNDO. - El presente Decreto entrará en vigor al día siguiente de su publicación en la Gaceta Oficial de la Ciudad de México.\nTERCERO. - Las personas servidoras públicas adscritas al Poder Judicial que formaron parte de los órganos jurisdiccionales del Sistema Penal Tradicional, transitarán al Sistema Penal Acusatorio bajo la homologación y adscripción que proponga la Dirección General de Gestión Judicial, y autorice el Consejo\n\nde la Judicatura dentro de los treinta días hábiles siguientes contados a partir de la publicación del acuerdo respectivo.\nCUARTO. - El proceso de transformación y/o, en su caso, transformación de Juzgados Civiles de Cuantía\nMenor a Juzgados Civiles de Proceso Oral o Civiles de Proceso Escrito, será determinado por el Consejo de la Judicatura en acuerdos que se harán públicos.\nQUINTO. - La nueva competencia de los Juzgados Civiles de Proceso Escrito y los Juzgados Civiles de\nProceso Oral entrará en vigor a partir del 1 enero de 2022.\nLos asuntos recibidos antes de la entrada en vigor del presente Decreto continuarán conociéndolos, hasta su conclusión, los Juzgados Civiles competentes en ese momento, independientemente de que sea transformado el órgano jurisdiccional respectivo.\nPalacio Legislativo del Congreso de la Ciudad de México, a los treinta días del mes de agosto del año dos mil veintiuno.- POR LA MESA DIRECTIVA, DIPUTADA ANA PATRICIA BAEZ GUERRERO, PRESIDENTA,\nDIPUTADA DONAJI OFELIA OLIVERA REYES, SECRETARIA, DIPUTADO PABLO MONTES DE OCA DEL OLMO\n(Firmas)\nCon fundamento en lo dispuesto por los artículos 122, apartado A, fracción III de la Constitución Política de los Estados Unidos Mexicanos; 32, apartado C, numeral 1, inciso a) de la Constitución Política de la Ciudad de México; 2 párrafo segundo, 3 fracciones XVII y XVIII, 7 párrafo primero, 10 fracción II, 12 y 21 párrafo primero de la Ley Orgánica del Poder Ejecutivo y de la Administración Pública de la Ciudad de México; para su debida publicación y observancia, expido el presente Decreto Promulgatorio en la Residencia Oficial de la Jefatura de Gobierno de la Ciudad de México, a los treinta y un días del mes de agosto del año dos mil veintiuno.-LA JEFA DE GOBIERNO DE LA CIUDAD DE MÉXICO, DRA. CLAUDIA SHEINBAUM PARDO.- FIRMA.-\nEL SECRETARIO DE GOBIERNO, MARTÍ BATRES GUADARRAMA.- FIRMA.\nTRANSITORIOS DEL DECRETO POR EL QUE SE ADICIONA UNA FRACCIÓN XXX Y SE RECORREN LAS\nFRACCIONES SUBSECUENTES DEL ARTÍCULO 218 DE LA LEY ORGÁNICA DEL PODER JUDICIAL DE LA CIUDAD\nDE MÉXICO, PUBLICADO EN LA GACETA OFICIAL DE LA CIUDAD DE MÉXICO EL DÍA 29 DE NOVIEMBRE DE\n2021.\nPrimero. Remítase a la persona titular de la Jefatura de Gobierno, para su promulgación y publicación en la Gaceta Oficial de la Ciudad de México.\n\nSegundo. El presente Decreto entrará en vigor al día siguiente de su publicación en la Gaceta Oficial de la\nCiudad de México.\nPalacio Legislativo del Congreso de la Ciudad de México, a los veinticinco días del mes de noviembre del año dos mil veintiuno. POR LA MESA DIRECTIVA, DIPUTADO HÉCTOR DIAZ POLANCO, PRESIDENTE,\nDIPUTADA MARCELA FUENTE CASTILLO, SECRETARIA, DIPUTADA FRIDA JIMENEZ GUILLÉN ORTIZ (Firmas)\nCon fundamento en lo dispuesto por los artículos 122, apartado A, fracción III de la Constitución Política de los Estados Unidos Mexicanos; 32, apartado C, numeral 1, inciso a) de la Constitución Política de la Ciudad de México; 2 párrafo segundo, 3 fracciones XVII y XVIII, 7 párrafo primero, 10 fracción II, 12 y 21 párrafo primero de la Ley Orgánica del Poder Ejecutivo y de la Administración Pública de la Ciudad de México; para su debida publicación y observancia, expido el presente Decreto Promulgatorio en la Residencia Oficial de la Jefatura de Gobierno de la Ciudad de México, a los veintiséis días del mes de noviembre del año dos mil veintiuno.- LA JEFA DE GOBIERNO DE LA CIUDAD DE MÉXICO, DRA. CLAUDIA SHEINBAUM PARDO.- FIRMA.-\nEL SECRETARIO DE GOBIERNO, MARTÍ BATRES GUADARRAMA.- FIRMA.\nTRANSITORIOS DEL DECRETO POR EL QUE SE REFORMAN LOS ARTÍCULOS 24, PRIMER PÁRRAFO Y SU\nFRACCIÓN II, 56, 78, 79 PÁRRAFO PRIMERO Y SU FRACCIÓN II, 80, 81 PÁRRAFO PRIMERO; SE REFORMAN\nLAS FRACCIONES V Y VI DEL ARTÍCULO 84; SE REFORMAN LOS ARTÍCULOS, 85 PÁRRAFO PRIMERO Y SU\nFRACCIÓN II, 111 PÁRRAFOS PRIMERO Y CUARTO, 167; SE ADICIONA LA FRACCIÓN XI BIS DEL ARTÍCULO\n277; Y SE REFORMA EL PRIMER PÁRRAFO Y LA FRACCIÓN II DEL ARTÍCULO 350, TODOS DE LA LEY ORGÁNICA\nDEL PODER JUDICIAL DE LA CIUDAD DE MÉXICO, PUBLICADO EN LA GACETA OFICIAL DE LA CIUDAD DE\nMÉXICO EL DÍA 29 DE ABRIL DE 2022\nPRIMERO. Remítase a la persona titular de la Jefatura de Gobierno para su promulgación y publicación en la Gaceta Oficial de la Ciudad de México.\nSEGUNDO. El presente Decreto entrará en vigor al momento de su publicación en la Gaceta Oficial de la\nCiudad de México. Los Tribunales Laborales de la Ciudad de México, iniciarán sus funciones a más tardar el 3 de octubre de 2022.\nTERCERO. Se derogan todas las disposiciones que contravengan el presente Decreto.\n\nPalacio Legislativo del Congreso de la Ciudad de México, a los veintiocho días del mes de abril del año dos mil veintidós. POR LA MESA DIRECTIVA, DIPUTADO JÓSE GONZALO ESPINA MIRANDA, PRESIDENTE. -\nDIPUTADA MARCELA FUENTE CASTILLO, SECRETARIA. - DIPUTADA FRIDA JIMENA GUILLÉN ORTIZ,\nSECRETARIA. - (Firmas)\nCon fundamento en lo dispuesto por los artículos 122, apartado A, fracción III de la Constitución Política de los Estados Unidos Mexicanos; 32, apartado C, numeral 1, inciso a) de la Constitución Política de la Ciudad de México; 2 párrafo segundo, 3 fracciones XVII y XVIII, 7 párrafo primero, 10 fracción II, 12 y 21 párrafo primero de la Ley Orgánica del Poder Ejecutivo y de la Administración Pública de la Ciudad de México; para su debida publicación y observancia, expido el presente Decreto Promulgatorio en la Residencia Oficial de la Jefatura de Gobierno de la Ciudad de México, a los veintiocho días del mes de abril del año dos mil veintidós.- LA JEFA DE GOBIERNO DE LA CIUDAD DE MÉXICO, DRA. CLAUDIA SHEINBAUM PARDO.- FIRMA.-\nEL SECRETARIO DE GOBIERNO, MARTI BATRES GUADARRAMA.- FIRMA.- EL SECRETARIO DE TRABAJO Y\nFOMENTO AL EMPLEO, JOSÉ LUIS RODRÍGUEZ DÍAZ DE LEÓN.- FIRMA.\nTRANSITORIOS DEL DECRETO POR EL QUE SE REFORMAN LOS ARTÍCULOS 13, FRACCIÓN XL Y 133,\nPÁRRAFOS PRIMERO, SEGUNDO Y CUARTO, DE LA LEY ORGÁNICA DEL CONGRESO DE LA CIUDAD DE\nMÉXICO; ASI COMO LOS ARTÍCULOS 218, FRACCIÓN II, 283, PÁRRAFO PRIMERO Y 368 PÁRRAFO PRIMERO\nDE LA LEY ORGÁNICA DEL PODER JUDICIAL DE LA CIUDAD DE MÉXICO EL DÍA 15 DE JUNIO DE 2022\nPRIMERO. - El presente Decreto entrará en vigor al día siguiente de su publicación.\nSEGUNDO. - Publíquese en la Gaceta Oficial de la Ciudad de México para su difusión.\nPalacio Legislativo del Congreso de la Ciudad de México, a los nueve días del mes de junio del año dos mil veintidós. POR LA MESA DIRECTIVA, DIPUTADO HÉCTOR DIAZ POLANCO, PRESIDENTE.- DIPUTADA MARCELA\nFUENTE CASTILLO, SECRETARIA.- DIPUTADA FRIDA JIMENA GUILLÉN ORTIZ, SECRETARIA.- (Firmas)\nCon fundamento en lo dispuesto por los artículos 122, apartado A, fracción III de la Constitución Política de los Estados Unidos Mexicanos; 32, apartado C, numeral 1, inciso a) de la Constitución Política de la Ciudad de México; 2 párrafo segundo, 3 fracciones XVII y XVIII, 7 párrafo primero, 10 fracción II, 12 y 21 párrafo primero de la Ley Orgánica del Poder Ejecutivo y de la Administración Pública de la Ciudad de México; para su debida publicación y observancia, expido el presente Decreto Promulgatorio en la Residencia Oficial de la Jefatura de Gobierno de la Ciudad de México, a los catorce días del mes de junio del año dos mil\n\nveintidós.- LA JEFA DE GOBIERNO DE LA CIUDAD DE MÉXICO, DRA. CLAUDIA SHEINBAUM PARDO.- FIRMA.-\nEL SECRETARIO DE GOBIERNO, MARTÍ BATRES GUADARRAMA.- FIRMA\nARTÍCULOS TRANSITORIOS\nPRIMERO. Remítase a la persona titular de la Jefatura de Gobierno para su promulgación y publicación en la Gaceta Oficial de la Ciudad de México.\nSEGUNDO. El presente Decreto entrará en vigor a partir del siguiente Ejercicio Fiscal al de su publicación.\nTERCERO. Las personas titulares de las dependencias, órganos, entidades y las alcaldías contarán con un plazo de 120 días naturales contados a partir de la entrada en vigor de la presente Ley, para llevar a cabo el levantamiento de la información sobre su infraestructura e informar a la ADIP sobre aquella infraestructura que se encuentre en desuso.\nCUARTO. La ADIP contará con un plazo de 60 días naturales contados a partir de la entrada en vigor de la presente Ley para emitir la normativa para la implementación de la presente ley.\nPalacio Legislativo del Congreso de la Ciudad de México, a los dieciséis días del mes de febrero del año dos mil veintitrés.- POR LA MESA DIRECTIVA.- DIPUTADO FAUSTO MANUEL ZAMORANO ESPARZA.- PRESIDENTE.-\nDIPUTADA MARCELA FUENTE CASTILLO, SECRETARIA.- DIPUTADA MARIA GABRIELA SALIDO MAGOS,\nSECRETARIA.- (Firmas)\nCon fundamento en lo dispuesto por los artículos 122, apartado A, fracción III de la Constitución Política de los Estados Unidos Mexicanos; 32, apartado C, numeral 1, inciso a) de la Constitución Política de la Ciudad de México; 2 párrafo segundo, 3 fracciones XVII y XVIII, 7 párrafo primero, 10 fracción II, 12 y 21 párrafo primero de la Ley Orgánica del Poder Ejecutivo y de la Administración Pública de la Ciudad de México; para su debida publicación y observancia, expido el presente Decreto Promulgatorio en la Residencia Oficial de la Jefatura de Gobierno de la Ciudad de México, a los veinticuatro días del mes de febrero del año dos mil veintitrés.- LA JEFA DE GOBIERNO DE LA CIUDAD DE MÉXICO, DRA. CLAUDIA SHEINBAUM PARDO.- FIRMA.-\nEL SECRETARIO DE GOBIERNO, MARTÍ BATRES GUADARRAMA.- FIRMA.- LA SECRETARIA DE ADMINISTRACIÓN\nY FINANZAS, LUZ ELENA GONZÁLEZ ESCOBAR.- FIRMA.- EL SECRETARIO DE LA CONTRALORÍA GENERAL, JUAN\nJOSÉ SERRANO MENDOZA.- FIRMA.- LA SECRETARIA DE CULTURA, CLAUDIA STELLA CURIEL DE ICAZA.-\nFIRMA.- EL SECRETARIO DE DESARROLLO ECONÓMICO, FADLALA AKABANI HNEIDE.- FIRMA.- EL SECRETARIO\nDE DESARROLLO URBANO Y VIVIENDA, CARLOS ALBERTO ULLOA PÉREZ.- FIRMA.- LA SECRETARIA DE\n\nEDUCACIÓN, CIENCIA, TECNOLOGÍA E INNOVACIÓN, JESÚS OFELIA ANGULO GUERRERO.- FIRMA.- LA\nSECRETARIA DE GESTIÓN INTEGRAL DE RIESGOS Y PROTECCIÓN CIVIL, MYRIAM VILMA URZÚA VENEGAS.-\nFIRMA.- EL SECRETARIO DE INCLUSIÓN Y BIENESTAR SOCIAL, RIGOBERTO SALGADO VÁZQUEZ.- FIRMA.- LA\nSECRETARIA DEL MEDIO AMBIENTE, MARINA ROBLES GARCÍA.- FIRMA.- EL SECRETARIO DE MOVILIDAD,\nANDRÉS LAJOUS LOAEZA.- FIRMA.- LA SECRETARIA DE LAS MUJERES, INGRID GÓMEZ SARACÍBAR.- FIRMA.-\nEL SECRETARIO DE OBRAS Y SERVICIOS, JESÚS ANTONIO ESTEVA MEDINA.- FIRMA.- LA SECRETARIA DE\nPUEBLOS Y BARRIOS ORIGINARIOS Y COMUNIDADES INDÍGENAS RESIDENTES, LAURA ITA ANDEHUI RUIZ\nMONDRAGÓN.- FIRMA.- LA SECRETARIA DE SALUD, OLIVA LÓPEZ ARELLANO.- FIRMA.- EL SECRETARIO DE\nSEGURIDAD CIUDADANA, OMAR HAMID GARCÍA HARFUCH.- FIRMA.- EL SECRETARIO DE TRABAJO Y\nFOMENTO AL EMPLEO, JOSÉ LUIS RODRÍGUEZ DÍAZ DE LEÓN.- FIRMA.- LA SECRETARÍA DE TURISMO,\nNATHALIE VERONIQUE DESPLAS PUEL.- FIRMA.- EL CONSEJERO JURÍDICO Y DE SERVICIOS LEGALES, NÉSTOR\nVARGAS SOLANO.- FIRMA.\nTRANSITORIOS DEL DECRETO POR EL QUE SE REFORMA EL ARTÍCULO 35 APARTADO B, NUMERALES 3,\nPÁRRAFO TERCERO Y 4, PÁRRAFO TERCERO DE LA CONSTITUCIÓN POLÍTICA DE LA CIUDAD DE MÉXICO; Y SE\nREFORMAN LOS ARTÍCULOS 17, PÁRRAFO SEGUNDO, Y 31, PÁRRAFO PRIMERO; AMBOS DE LA LEY\nORGÁNICA DEL PODER JUDICIAL DE LA CIUDAD DE MÉXICO, PUBLICADO EN LA GACETA OFICIAL DE LA\nCIUDAD DE MÉXICO EL 01 DE AGOSTO DE 2024.\nPRIMERO. Remítase a la persona titular de la Jefatura de Gobierno para su promulgación y publicación en la Gaceta Oficial de la Ciudad de México.\nSEGUNDO. El presente Decreto entrará en vigor al día siguiente de su publicación en la Gaceta Oficial de la\nCiudad de México.\nPalacio Legislativo del Congreso de la Ciudad de México, a los tres días del mes de julio del año dos mil veinticuatro.- POR LA MESA DIRECTIVA.- DIPUTADA MARÍA GABRIELA SALIDO MAGOS, PRESIDENTA.-\nDIPUTADA MARCELA FUENTE CASTILLO, SECRETARIA.- DIPUTADA FRIDA FERNANDA ALCÁNTARA CABRERA,\nSECRETARIA.- (Firmas)\nCon fundamento en lo dispuesto por los artículos 122, apartado A, base III, de la Constitución Política de los Estados Unidos Mexicanos; 32, apartado C, numeral 1, inciso a), de la Constitución Política de la Ciudad de México; 2, párrafo segundo, 3, fracciones XVII y XVIII, 7, párrafo primero, 10, fracción II, 12 y 21, párrafo primero, de la Ley Orgánica del Poder Ejecutivo y de la Administración Pública de la Ciudad de México;\npara su debida publicación y observancia, expido el presente Decreto Promulgatorio en la Residencia\n\nOficial de la Jefatura de Gobierno de la Ciudad de México, a los treinta y un días del mes de julio del año dos mil veinticuatro.- EL JEFE DE GOBIERNO DE LA CIUDAD DE MÉXICO, DR. MARTÍ BATRES GUADARRAMA.-\nFIRMA.- EL SECRETARIO DE GOBIERNO, RICARDO RUIZ SUÁREZ.- FIRMA.",
  "ordenamiento": "Marco Jurídico",
  "jurisdiccion": "CIUDAD DE MEXICO",
  "fuente_oficial": "Congreso de la Ciudad de México",
  "status": "Vigente",
  "Fecha de Publicación": "22-10-2024",
  "Fecha de Última Reforma": "01 de agosto de 2024",
  "numero_paginas": 199,
  "es_escaneado": false,
  "tiene_tablas": false,
  "url": "https://www.congresocdmx.gob.mx/archivo-af5ff0143894fd95b49b9ad9df27172f94d872bc.pdf",
  "materia": [
    "administrativo",
    "justicia"
  ]
}