{
  "titulo": "Ley DE EDUCACIÓN FÍSICA y DEPORTE DE LA CIUDAD DE MÉXICO",
  "Contenido": "PUBLICADO EN LA GACETA OFICIAL DE LA CIUDAD DE MÉXICO\nEL 04 DE ENERO DE 2008\nTEXTO VIGENTE\nÚLTIMA REFORMA PUBLICADA EN LA G.O.CDMX\nEL 15 DE MAYO DE 2023\nLEY DE EDUCACIÓN FÍSICA Y DEPORTE DE LA CIUDAD DE MÉXICO\n(Al margen superior un escudo que dice: Ciudad de México.- Capital en Movimiento)\nLEY DE EDUCACIÓN FÍSICA Y DEPORTE DE LA CIUDAD DE MÉXICO\nMARCELO LUIS EBRARD CASAUBON, Jefe de Gobierno del Distrito Federal, a sus habitantes sabed:\nQue la H. Asamblea Legislativa del Distrito Federal, IV Legislatura se ha servido dirigirme el siguiente:\nDECRETO\n(Al margen superior izquierdo el Escudo Nacional que dice: ESTADOS UNIDOS MEXICANOS.- ASAMBLEA\nLEGISLATIVA DEL DISTRITO FEDERAL.- IV LEGISLATURA)\nASAMBLEA LEGISLATIVA DEL DISTRITO FEDERAL\nIV LEGISLATURA.\nD E C R E T A\nDECRETO POR EL QUE SE EXPIDE LA LEY DE EDUCACIÓN FÍSICA Y DEPORTE DE LA CIUDAD DE MÉXICO.\nArtículo Único.- Se expide la Ley de Educación Física y Deporte de la Ciudad de México para quedar como sigue:\n\nLEY DE EDUCACIÓN FÍSICA Y DEPORTE DE LA CIUDAD\nDE MÉXICO\nCAPÍTULO PRIMERO\nDISPOSICIONES GENERALES\nArtículo 1.- Las disposiciones de la presente Ley son de orden público e interés social y tienen por objeto normar las actividades tendientes a fomentar, organizar, coordinar, promocionar y desarrollar la educación física y el deporte en la Ciudad de México.\nArtículo 2.- Para efectos del presente ordenamiento y sin perjuicio de otros ordenamientos legales, se entiende por:\nI. Deporte.- La práctica de actividades físicas e intelectuales que las personas, de manera individual o en conjunto, realicen con propósitos competitivos o de esparcimiento en apego a su reglamentación. Dicha práctica propiciará el desarrollo de las aptitudes del individuo, el cuidado de su salud y promoverá su integración y desarrollo en la sociedad;\nII. Educación física.- La preparación física del ser humano por medio de procesos pedagógicos.\nIII. Alcaldías.- Los órganos político-administrativos de cada una de las demarcaciones territoriales de la Ciudad de México;\nIV. Instituto: El Instituto del Deporte de la Ciudad de México;\nV. Fondo: El Fondo de Apoyo para Deportistas de Alto Rendimiento de la Ciudad de México;\nVI. Programa: Programa del Deporte de la Ciudad de México;\nVII. Registro: El Registro del Deporte de la Ciudad de México;\nVIII. Sistema: El Sistema de Cultura Física y Deporte de la Ciudad de México;\nIX. Consejo: Consejo del Deporte de la Ciudad de México;\n\nX. Cultura física: Sistema de categorías desprendidas de la actividad motriz de las personas y manifestada en diferentes connotaciones determinadas en la práctica diaria vital, de donde se desprenden como categorías el entrenamiento deportivo, la educación física y la recreación física; y\nFracción modificada y publicada en la GOCDMX el 15 de mayo de 2023\nXI. Liga: Organismo deportivo que tiene como finalidad agrupar, coordinar y estimular la formación de equipos para la práctica de una disciplina, independientemente de la denominación que adopte.\nArtículo 3.- La función social del deporte y la educación física es la de fortalecer la interacción de la sociedad, para desarrollar de manera armónica las aptitudes físicas e intelectuales de las personas que contribuyan a fomentar la solidaridad como valor social; además de promover y estimular la actividad y recreación física como medios importantes para la preservación de la salud física y mental, así como la prevención de enfermedades.\nLos titulares de las oficinas de dependencias de la Administración Pública local, tendrán la obligación de fomentar la práctica de actividades físicas o deportivas entre sus trabajadores; se promoverán, de acuerdo a las características de cada área y oficina, programas de activación física en donde se dediquen al menos\n20 minutos de la jornada laboral para estas actividades.\nArtículo 4.- La Función Educativa del Deporte debe implicar además de la enseñanza de técnicas y el desarrollo de las cualidades físicas de los alumnos, la transmisión de hábitos, valores y actitudes.\nArtículo 5.- Son sujetos de la presente Ley los deportistas, educadores físicos, entrenadores deportivos, técnicos, los organismos deportivos de los sectores público, social y privado, equipos, clubes, asociaciones y ligas deportivas, jueces, árbitros y demás personas que por su naturaleza, condición o funciones sean susceptibles de integrarse al Sistema de Cultura Física y Deporte en esta Ciudad.\nArtículo 6.- Se reconoce el derecho de todas las personas al conocimiento, difusión y práctica del deporte, donde se prohíbe toda forma de discriminación, formal o de facto, que atente contra la dignidad humana o tenga por objeto o resultado la negación, exclusión, distinción, menoscabo, impedimento o restricción de los derechos de las personas, grupos y comunidades, motivada por origen étnico o nacional, apariencia física, color de piel, lengua, género, edad, discapacidades, condición social, situación migratoria, condiciones de salud, embarazo, religión, opiniones, preferencia sexual, orientación sexual, identidad de género, expresión de género, características sexuales, estado civil o cualquier otra. También se considerará\n\ndiscriminación la misoginia, cualquier manifestación de xenofobia, segregación racial, antisemitismo, islamofobia, así como la discriminación racial y otras formas conexas de intolerancia.\nArtículo 7.- Corresponde al Instituto del Deporte de la Ciudad de México ser el órgano rector de la política deportiva en esta ciudad. Para ello contará con las facultades que le otorga esta Ley, así como las que le otorguen otras disposiciones legales para el mejor desarrollo, fomento y promoción de la educación física y el deporte en la Ciudad de México.\nCAPÍTULO SEGUNDO\nDEL SISTEMA DE CULTURA FÍSICA Y DEPORTE DE LA CIUDAD DE\nMÉXICO\nArtículo 8.- El Sistema de Cultura Física y Deporte de la Ciudad de México estará constituido por el conjunto de instrumentos, métodos, acciones, recursos y procedimientos que las personas, agrupaciones sociales y organismos deportivos de los sectores público, social y privado de la Ciudad de México establezcan y lleven a cabo entre sí y con los diversos organismos que conforman el Sistema Nacional del Deporte.\nArtículo modificado y publicado en la GOCDMX el 15 de mayo de 2023\nArtículo 9.- Las funciones que conforme a esta Ley corresponden al Sistema estarán a cargo del Instituto del\nDeporte de la Ciudad de México.\nArtículo 10.- Las instituciones educativas públicas y privadas promoverán el deporte en sus planteles, de conformidad a los programas educativos diseñados por la autoridad competente, por lo que cuidarán que se imparta la clase de educación física cuando menos tres veces por semana; en caso de no contar con el espacio suficiente podrán utilizar las instalaciones deportivas públicas más cercanas previa autorización de la autoridad delegacional correspondiente.\nLas instituciones educativas privadas podrán permitir el acceso y uso de sus instalaciones a sus educandos y a las madres y padres de familia de éstos; y en su caso los deportistas y/o habitantes de la Ciudad de\nMéxico, ajenos a los Planteles; dentro de los horarios y condiciones que establezca su Reglamento respectivo; por lo que hace a los deportistas y/o habitantes de la Ciudad de México se les podrá cobrar una cuota de recuperación para el mantenimiento de sus instalaciones, la cual será de una vez la Unidad de\nCuenta de la Ciudad de México vigente, al momento de realizarse la actividad o deporte.\n\nArtículo 11.- El Sistema y el Programa de Educación Física y el Deporte de la Ciudad de México, se apegarán a los lineamientos establecidos en el Sistema y el Programa Nacional del Deporte, estableciendo los mecanismos de coordinación para integrar en ellos las actividades que realicen otras instituciones públicas o privadas relacionadas con el deporte e informarán públicamente el desarrollo de los mismos.\nArtículo 12.- Se consideran integrantes del Sistema de Cultura Física y Deporte:\na) Deportista: Las personas que realicen actividades deportivas de orden competitivo o recreativo bajo reglamentación establecida;\nb) Órganos deportivos: La agrupación formada libremente por individuos, personas morales u organizaciones deportivas como:\nI. Equipos y Clubes;\nII. Ligas;\nIII. Asociaciones Deportivas;\nIV. Unión Deportiva;\nV. Comités Delegacionales del Deporte;\nVI. Consejo del Deporte; y\nVII. Comité del Deporte Adaptado de la Ciudad de México.\nc) Órganos de representación ciudadana que establezca la Ley de Participación Ciudadana;\nd) Entrenadores deportivos, Educadores Físicos y demás profesionales de la materia;\ne) Especialistas en medicina deportiva; y f) Personas que por su naturaleza y funciones sean susceptibles de integrarse al Sistema de\nCultura Física y Deporte de la Ciudad de México.\n\nArtículo 13.- Los organismos deportivos previamente incorporados al Sistema deberán estar registrados obligatoriamente para tener acceso a los servicios ante el Instituto presentando su programa anual de actividades, para su inclusión y seguimiento en el Programa del Deporte de la Ciudad de México.\nAl efectuar dicho registro de programas anuales serán considerados para la utilización de instalaciones deportivas dentro de la Ciudad de México.\nArtículo 14.- Son también integrantes del Sistema los deportistas profesionales de la Ciudad de México, que conforme a la reglamentación deportiva internacional sean susceptibles de ostentar la representación de la Ciudad de México o la nacional. Artículo\nArtículo 15.- En el Registro del Deporte de la Ciudad de México, como instrumento del Sistema, deberá constar la inscripción actualizada de los deportistas, jueces, árbitros, técnicos, entrenadores, educadores físicos, especialistas en medicina deportiva, las organizaciones deportivas, y demás profesionales en la materia; así como las instalaciones y espacios para la práctica del deporte y, las competencias y actividades deportivas que determina el reglamento de esta ley.\nArtículo 16.- Los derechos de los integrantes del Sistema son:\nI. Participar en el o los deportes de su elección;\nII. Asociarse para la práctica del deporte y, en su caso, para la defensa de sus derechos;\nIII. Utilizar las instalaciones deportivas de acuerdo con la normatividad establecida;\nIV. Recibir asistencia y entrenamiento deportivos, así como los servicios médicos adecuados en competencias oficiales; así como durante sus prácticas y entrenamientos.\nV. Participar en eventos deportivos reglamentarios u oficiales, emanados del Sistema;\nVI. Elegir y, en su caso, ser electos para cargos directivos en los organismos deportivos a los que pertenezcan;\nVII. Recibir los premios, estímulos y becas, en dinero o en especie, ofrecidos en las competencias o eventos deportivos de que se trate, o los que determine esta ley;\n\nVIII. Recibir apoyo logístico en aquellas competencias que organicen, previo informe al Instituto del Deporte de la Ciudad de México y al Órgano Político-Administrativo de la Demarcación\nTerritorial de la Ciudad de México. El apoyo logístico se otorgará de acuerdo a la suficiencia presupuestal con que se cuente;\nIX. Representar a su Club, Asociación, Demarcación Territorial de la Ciudad de México, a la Ciudad de México o al país, en competencias deportivas oficiales;\nX. Participar en la elaboración del programa del deporte, así como de programas y reglamentos deportivos a convocatoria de la autoridad rectora;\nXI. Obtener de las autoridades correspondientes el registro que lo acredite como deportista; y\nXII. Los demás que le otorguen esta ley u otros ordenamientos legales.\nArtículo 17.- Son obligaciones de los integrantes del Sistema:\nI. Cumplir con los Estatutos y Reglamentos de su deporte, especialidad o actividad;\nII. Respetar los lineamientos del Sistema y del Programa del Deporte de la Ciudad de México;\nIII. Cuidar y vigilar que la infraestructura deportiva utilizada en sus prácticas, se ocupe para el fin adecuado, procurando se conserve en buen estado, conforme a lo establecido en los\nReglamentos aplicables;\nIV. Informar a la Institución competente sobre el uso de los apoyos materiales o financieros recibidos, considerándose éstos como etiquetados quedando prohibido su utilización para fines distintos a los que fueron destinados de conformidad con el Reglamento y las disposiciones del\nSistema de Cultura Física y Deporte de la Ciudad de México.\nV. Fomentar la participación organizada de la sociedad a través del deporte, sin discriminación.\nVI. Participar en el desarrollo de la cultura del deporte, conforme a lo dispuesto en esta Ley;\n\nVII. Mantener en óptimas condiciones de uso y mantenimiento las instalaciones deportivas;\nequipándolas con todos y cada uno de los elementos materiales necesarios para la práctica de cada especialidad, contando con infraestructura de punta y avances tecnológicos;\nVIII. Proporcionar la vigilancia y resguardo de las instalaciones; así como la seguridad para los deportistas que entrenen o compitan en ellas;\nIX. Promover medidas necesarias para erradicar la violencia y la discriminación en todos los espacios deportivos y de recreación, además de fomentar los principios encaminados a la prevención de las adicciones y farmacodependencia; y\nX. Las contenidas en el texto de esta Ley y demás disposiciones aplicables.\nArtículo 18.- La participación en el Sistema de Cultura Física y Deporte de la Ciudad de México, es obligatoria para la Administración Pública de la Ciudad de México.\nArtículo 19.- Las personas físicas que realicen actividades deportivas podrán participar en el Sistema de\nCultura Física y Deporte de la Ciudad de México en lo individual o mediante organismos deportivos en los términos que señalen esta ley y su reglamento.\nArtículo 20.- Los integrantes del Sistema deberán contar con la constancia actualizada de inscripción en el\nRegistro del Deporte de la Ciudad de México como requisito indispensable para obtener cualquier clase de apoyo y estímulos previstos en la ley.\nLa constancia de inscripción se obtendrá, actualizará y revocará en los términos que establezca el\nReglamento de esta Ley.\nArtículo 21.- Los deportistas, agrupaciones, organismos deportivos y demás personas que tengan por objeto el desarrollo de actividades vinculadas con el deporte y que su fin no implique necesariamente la competencia deportiva, podrán inscribirse en el Registro del Deporte, siempre y cuando no tengan fines lucrativos.\nCAPÍTULO TERCERO\nDEL INSTITUTO DEL DEPORTE DE LA CIUDAD DE MÉXICO\n\nArtículo 22.- El Instituto del Deporte de la Ciudad de México es un órgano descentralizado de la\nAdministración Pública de la Ciudad de México, con personalidad jurídica, patrimonio propio, autonomía técnica y de gestión para el cumplimiento de sus objetivos y atribuciones, teniendo a su cargo el cumplimiento de la presente Ley.\nEl Instituto del Deporte de la Ciudad de México contará con una Junta de Gobierno y un Órgano de Control\nInterno.\nArtículo 22 Bis.- La persona titular del Instituto del Deporte, será nombrada y removida libremente por la\nJefa o Jefe de Gobierno, debiendo cumplir con los siguientes requisitos:\nI. Ser ciudadana o ciudadano mexicano en pleno goce de sus derechos;\nII. Tener 25 años cumplidos, o más, al día de su designación;\nIII. Tener reconocimiento y experiencia en materia deportiva; y\nIV. Gozar de probada honorabilidad.\nArtículo 23.- Las atribuciones del Instituto del Deporte de la Ciudad de México son:\nI. Proponer, formular y ejecutar coordinadamente políticas que fomenten y desarrollen la práctica del deporte y la recreación, enfatizando la atención en los sectores de la educación básica e instituciones de educación especial;\nII. Establecer el procedimiento de coordinación en materia deportiva con los Órganos Político-\nAdministrativos de cada una de las Demarcaciones Territoriales de la Ciudad de México;\nIII. En lo referente al deporte adaptado, así como en el deporte para las personas mayores dará opinión, para que se efectúen las adecuaciones necesarias a la infraestructura deportiva, las cuales serán tomadas en cuenta en toda instalación deportiva que se construya y/o se remodele;\nFracción modificada y publicada en la GOCDMX el 15 de mayo de 2023\nIV. Promover la participación y conjunción de esfuerzos en materia deportiva entre los sectores público, social y privado;\n\nV. Efectuar el Programa de Becas para los Deportistas sobresalientes, activos o retirados, así como, un Programa de Becas para los deportistas considerados como nuevos valores, otorgados por acuerdo del Consejo del Deporte de la Ciudad de México;\nVI. Gestionará ante las autoridades fiscales federales la deducibilidad de los donativos de las personas físicas o morales de los sectores social y privado destinados en favor del fomento del deporte en la Ciudad de México;\nVII. Formular y entregar el Programa del Deporte de la Ciudad de México en el mes de octubre del año anterior a las y los Titulares de los Órganos Político-Administrativos de cada una de las\nDemarcaciones Territoriales de la Ciudad de México, para su aplicación, debiendo llevar el seguimiento puntual del mismo;\nVIII. Propiciar la participación de los organismos deportivos y de los deportistas en la determinación y ejecución de las políticas;\nIX. Formular programas tendientes a apoyar, promover y fomentar el deporte realizado por personas con discapacidad.\nIX Bis. Promover programas que desarrollen actividades deportivas que busquen la inclusión de las niñas, niños y adolescentes, primordialmente aquellos que se encuentran en situación de vulnerabilidad y/o zonas de marginación.\nIX Ter. Fomentar e impulsar programas que desarrollen actividades deportivas que busquen la inclusión de las personas mayores de 60 años, primordialmente aquellas que se encuentran en situación de vulnerabilidad.\nFracción añadida y publicada en la GOCDMX el 15 de mayo de 2023\nX. Coadyuvar en el fortalecimiento de los patrones culturales que determinen hábitos, costumbres y actitudes relacionados con el deporte, que redunden en el bienestar físico, intelectual y social de las y los habitantes de la Ciudad de México;\nXI. Determinar, conforme al Registro del Deporte de la Ciudad de México, a las y los legítimos representantes del deporte en la Ciudad de México para las competencias nacionales e internacionales;\n\nXII. Emitir opiniones en materia sanitaria y educativa, relacionada con la práctica del deporte en la Ciudad de México;\nXIII. Efectuar la difusión del deporte, a través de la Dirección de Comunicación Social del propio\nInstituto, en diversos medios de comunicación destacando los beneficios y valores del deporte, con la finalidad de propiciar la cultura del deporte en la sociedad;\nXIV. Establecer mecanismos de vinculación con organismos y entidades públicas y privadas para la difusión, promoción, capacitación, fomento e investigación en materia deportiva que promueva el desarrollo deportivo;\nXV. Emitir recomendaciones y opiniones en materia de espectáculos deportivos;\nXVI. Promover entre la sociedad, alternativas de financiamiento que permitan incrementar los recursos destinados al sector deportivo;\nXVII. Otorgar reconocimientos y estímulos a deportistas, incluidos los deportistas con discapacidad, en las entidades u organismos públicos sociales y privados de los Órganos Político-\nAdministrativos de las Demarcaciones Territoriales de la Ciudad de México que se hayan distinguido en el deporte o en la difusión, promoción, fomento o investigación en materia deportiva;\nXVIII. Efectuar verificaciones anuales a las instalaciones deportivas de la Ciudad de México, en coordinación con la unidad administrativa de Gestión Integral de Riesgos y Protección Civil de las alcaldías, a efecto de que se encuentren en óptimas condiciones de uso y mantenimiento; así como equipadas con todos y cada uno de los elementos materiales necesarios para la práctica de cada especialidad; y en su caso podrán vetar el uso de cualquier instalación que no cumpla con los requisitos de seguridad; dicha verificación se reportará en un informe anual que detallará las condiciones de la infraestructura deportiva y que estará públicamente disponible en el portal de\nInternet del Instituto.\nXIX. Deberá coordinar a las y los promotores deportivos quienes promoverán la participación activa, sistemática y planeada de las y los habitantes de la Ciudad de México a la práctica, apoyo, estímulo y fomento del deporte, la actividad física y la recreación;\n\nXX. Emitirá los certificados que acredite la condición de deportista de alto rendimiento, motivado de que dicha condición suponga para el deportista la obtención de beneficios inmediatos;\nXXI. Realizar campañas para prevenir, combatir y erradicar el uso de estimulantes, sustancias psicoactivas o farmacológicas, así como métodos prohibidos y restringidos destinados a aumentar artificialmente las capacidades físicas de los deportistas o a modificar el resultado de las competiciones y que tengan relación con lo señalado en el Capítulo décimo cuarto de la presente ley.\nFracción añadida y publicada en la GOCDMX el 15 de mayo de 2023\nXXII. Contará en cada una de las demarcaciones territoriales con Unidades de Iniciación y\nDesarrollo del Deporte para niñas y niños desde los 5 años de edad, con especialistas para el desarrollo de habilidades deportivas, y posteriormente ingresen a Escuelas Técnicas de\nDesarrollo de Talentos Deportivos, para finalmente se incorporen a los Centros de Alto\nRendimiento;\nXXIII. Otorgar el aval para la realización de eventos deportivos selectivos y recreativos que se lleven a cabo en la Ciudad de México;\nXXIV. Fomentar programas y proponer políticas públicas para el desarrollo de la actividad física y el deporte en zonas con población en situación de pobreza, marginación y rezago social para dar atención y eliminar la discriminación en el deporte y la actividad física;\nXXIV Bis. Promover estrategias, metodologías, programas de investigación, contenidos, materiales, programas y planes institucionales en materia de cultura física y deporte;\nXXV. Promover la participación de las mujeres en el deporte y la actividad física, así como crear e implementar protocolos para eliminar y erradicar la violencia hacia las mujeres en el deporte; y\nXXVI. Todas las demás que deriven del Sistema y Programas Nacionales del Deporte y de la operación y funcionamiento del Sistema; y en particular, las tendientes a dar seguimiento constante y puntual a los nuevos valores deportivos, estimulando su continuidad en la práctica de su deporte o actividad.\nCAPÍTULO CUARTO\n\nDEL CONSEJO DEL DEPORTE\nArtículo 24.- El Instituto contará con el Consejo del Deporte de la Ciudad de México como órgano consultivo y de propuesta que tiene por objeto opinar y coordinar acciones específicas de colaboración, difusión, promoción, desarrollo y estímulo en las tareas necesarias para crear y consolidar condiciones que favorezcan el derecho de las y los habitantes de la Ciudad de México al conocimiento de la cultura física y la práctica del deporte.\nArtículo 25.- El Consejo estará conformado de la manera siguiente:\nI. La persona titular de la Jefatura de Gobierno de la Ciudad de México, quien lo presidirá;\nII. La persona titular de la Dirección del Instituto del Deporte de la Ciudad de México, quien fungirá como Secretaria o Secretario;\nIII. La Presidencia, o en su caso, un integrante de la Comisión de Deporte del Congreso de la\nCiudad de México.\nIV. El presidente del Comité Deportivo Estudiantil;\nV. Un representante de organismos que presidan deportes de conjunto;\nVI. Un representante de organismos que manejen deportes individuales;\nVII. Una persona representante de organismos para personas con discapacidad y en situación de vulnerabilidad.\nVIII. Dos representantes de la iniciativa privada que se hayan distinguido por el apoyo brindado económica o técnicamente al fomento del deporte y la cultura física;\nIX. Las dieciséis personas titulares de la Dirección del Área Deportiva de cada una de las\nDemarcaciones Territoriales de la Ciudad de México;\nX.Una persona representante de la Secretaría de Educación, Ciencia, Tecnología e Innovación de la Ciudad de México;\n\nLas personas representantes señaladas en las fracciones V, VI, VII y VIII serán nombradas por la persona titular de la Dirección General del Instituto del Deporte de la Ciudad de México, tomando como base su dinamismo en el fomento y desarrollo del deporte, la perspectiva de género y por su destacada labor deportiva o representatividad que se encuentren previamente inscritos en el Registro del Deporte de la\nCiudad de México.\nLos integrantes del Consejo desempeñarán sus funciones de manera honorífica de acuerdo a las disposiciones previstas en el reglamento correspondiente.\nEl Consejo se reunirá de forma ordinaria un día cada mes, pudiendo en todo caso reunirse de forma extraordinaria cuando sea necesario. En ausencia de la persona titular de la Jefatura de Gobierno, la persona titular de la Dirección presidirá y desahogará las sesiones del Consejo.\nArtículo 26.- El Consejo tendrá las funciones siguientes:\nI. Asesorar y proponer a la persona titular de la Jefatura de Gobierno de la Ciudad de México los mecanismos de consulta con los sectores sociales, en las materias relacionadas con las funciones del Consejo, con el fin de expandir la cultura física y deportiva al mayor número de habitantes de la Ciudad de México;\nII. Proponer criterios para fomentar el apoyo y estímulos para la activación física, el deporte y la recreación en la Ciudad de México;\nIII. Servir de enlace entre las dependencias y entidades del Gobierno Federal y Local; entre personas o agrupaciones sociales y privadas, con posibilidades de otorgar apoyo, material o financiero, a los destinatarios de servicios deportivos y de cultura física;\nIV. Proponer la adopción de medidas idóneas para aprovechar de manera íntegra los espacios públicos para la práctica del deporte, la activación física y la recreación;\nV. Apoyar en la difusión sobre la importancia del deporte, la activación física y la recreación como elementos de desarrollo individual y colectivo de la población;\nVI. Proponer a los Comités Delegacionales acciones requeridas para eficientar el desarrollo de la actividad deportiva, física y recreativa en las instalaciones;\n\nVII. Coadyuvar en la elaboración de programas que contribuyan a la promoción, desarrollo, fomento y estímulo de la cultura física y el deporte;\nVIII. Verificar el otorgamiento de Becas para los Deportistas sobresalientes, activos o retirados, así como para los deportistas considerados como nuevos valores;\nIX. Dar seguimiento puntual al Fondo de Apoyo para Deportistas de Alto Rendimiento que se constituya para tal efecto mediante fideicomiso, con la participación de los sectores público, social y privado, así mismo determinarán, conforme a lo establecido en el reglamento, los deportistas que en la Ciudad de México han alcanzado ese nivel y por lo cual son susceptibles de ser beneficiados;\nX. Conformar grupos de trabajo a efecto de investigar y proponer al Instituto acciones acerca de los asuntos relacionados con la cultura física y el deporte, así como plantear las propuestas surgidas de los resultados recabados en las consultas por los Comités Delegacionales;\nXI. Analizarán las propuestas recibidas de los deportistas candidatos para determinar el deportista que será distinguido con el Premio al Mérito Deportivo que anualmente entregará la persona titular de la Jefatura de Gobierno de la Ciudad de México de conformidad con las bases y lineamientos que se establezcan en el reglamento;\nXII. Crear el Comité de Arbitraje Deportivo; y proponer a la persona titular de la Jefatura de\nGobierno de la Ciudad de México, por conducto de la persona titular de la Dirección del Instituto del Deporte, la expedición del Reglamento correspondiente.\nEl Comité de Arbitraje Deportivo deberá estar integrado por un Representante del Instituto, un\nRepresentante de los Deportistas, y otro de las diferentes ligas o agrupaciones deportivas que tengan registro ante el Instituto. Dicho Comité será integrado de forma impar, es decir, podrán ser sus integrantes 3, 5, 7 y así respectivamente, según lo determine el Reglamento correspondiente; y\nXIII. Expedir sus lineamientos de organización y funcionamiento.\nCAPÍTULO QUINTO\nDEL PROGRAMA DEL DEPORTE DE LA CIUDAD DE MÉXICO\n\nArtículo 27.- El Instituto formulará y coordinará el Programa, que tendrá el carácter de instrumento rector de las actividades deportivas del Sistema.\nArtículo 28.- El programa establecerá los objetivos, lineamientos y acciones, así como la participación de los Órganos Político Administrativos de cada una de las Demarcaciones Territoriales de la Ciudad de\nMéxico, de los sectores públicos, sociales y privados, con el fin de ordenar la planificación, organización, desarrollo del deporte y la recreación a través de su práctica en la Ciudad de México, de manera específica contendrá:\nI. La política del deporte;\nII. Los objetivos, prioridades, estrategias y metas para el desarrollo del deporte en la Ciudad de\nMéxico, acordes con el Plan Nacional de Desarrollo y los Programas Sectoriales correspondientes;\nIII. Los objetivos, prioridades, estrategias y metas para el desarrollo del deporte en la Ciudad de\nMéxico, acordes con el Plan Nacional de Desarrollo y los Programas Sectoriales correspondientes;\nIV. Las acciones que cada uno de los integrantes del Sistema deberá realizar de acuerdo a su ámbito de competencia y naturaleza.\nArtículo 29.- El programa del Deporte de la Ciudad de México deberá formularse de acuerdo a los siguientes rubros:\nI. Deporte Infantil.- Para facilitar un adecuado crecimiento y aprendizaje, el deporte practicado por los menores constituye la base para la formación motriz, aportando elementos fundamentales para el desarrollo, estabilización intelectual y psíquica destinada a permanecer y ser aplicada toda la vida;\nII. Deporte Popular:- Se considera como el conjunto de actividades físicas que practican los grandes núcleos de población, normada convencionalmente y sin que se requiera para su práctica equipos o instalaciones especializados, cuyo objeto es el aprendizaje, mantenimiento de la salud y el de esparcimiento, para favorecer el desarrollo integral de la comunidad;\nIII. Deporte Estudiantil:- Se consideran como las actividades competitivas que se organizan en el sector educativo como complemento a la educación física;\n\nIV. Deporte Adaptado:- Entendiéndose por éste, la práctica del deporte de personas con cualquier restricción o impedimento del funcionamiento de una actividad ocasionado por una deficiencia dentro del ámbito considerado normal del ser humano;\nV. Deporte de Alto Rendimiento- Es el practicado con el propósito de obtener una clasificación de calidad dentro de los organismos deportivos;\nVI. Deporte Autóctono y Tradicional.- Se refiere a la practica de deportes propios de la comunidad desde tiempos remotos que son memorizadas que pasan a través de generaciones;\nVII. Deporte Asociado:- Es la actividad competitiva que realiza un sector de la comunidad debidamente organizado, cuya estructura puede ser de dos maneras:\na) Organizaciones deportivas afiliadas a una Asociación del Deporte; y b) Grupo de ciudadanos que se reúnen con un motivo deportivo sin encontrarse afiliado a una Asociación del Deporte;\nVIII. Deporte para las personas mayores: práctica metódica de ejercicios físicos que realizan las personas mayores de sesenta años;\nIX. Preparación y profesionalización de:\na) Administrador Deportivo b) Entrenador Deportivo c) Educador Físico d) Recreador Físico e) Instructor Deportivo f) Guardavidas\n\ng) Monitor Deportivo h) Promotor Deportivo\nX. Instalaciones deportivas; y\nXI. Difusión de las culturas, investigaciones y desarrollo del deporte.\nArtículo 30.- El Premio al Mérito Deportivo que se entregará anualmente por la persona titular de la Jefatura de Gobierno de la Ciudad de México o la persona que éste designe, de conformidad con las bases y lineamientos que se expidan para tal efecto por el Consejo del Deporte.\nCAPÍTULO SEXTO\nDE LA PARTICIPACIÓN DE LAS ALCADÍAS ÉN EL SISTEMA DE\nCULTURA FÍSICA Y DEPORTE DE LA CIUDAD DE MÉXICO\nArtículo 31.-Los Órganos Político- Administrativos de cada una de las Alcaldías de la Ciudad de México, tendrán las facultades siguientes:\nI. Promover y organizar en sus respectivas circunscripciones actividades y prácticas físicodeportivas, como medio importante en la preservación de la salud, prevención de enfermedades, así como la prevención de las adicciones y el consumo de sustancias psicoactivas;\nII. Constituir un Comité Delegacional del Deporte que estará conformado por los integrantes del\nSistema de Cultura Física y Deporte, el cual contará con varias comisiones, entre ellas la de\nVigilancia. El procedimiento de constitución y el número de Comisiones del Comité Delegacional quedará establecido en el Reglamento de esta Ley;\nIII. Coordinarse con los Comités y Ligas Delegacionales deportivas, en todas sus promociones de carácter no profesional en el área del deporte;\nIV. Facilitar la plena utilización de las instalaciones deportivas en su circunscripción a todas las personas, incluyendo los espacios sujetos a concesión o renta a particulares, a través de la programación de su uso, de conformidad con la reglamentación establecida;\n\nV. Apegarse a los lineamientos establecidos en el Programa del Deporte;\nVI. Prever anualmente, dentro de su presupuesto autorizado, los recursos necesarios para el desarrollo de las metas de sus programas deportivos, becas, así como para la correcta y oportuna difusión de los mismos;\nVII. Llevar, mantener y actualizar un censo de sus usuarios e instalaciones deportivas; y expedir periódicamente, según la disciplina y modalidad deportiva de que se trate, las guías técnicas que contengan las características de las instalaciones y las normas de seguridad;\nVIII. Contemplar las adecuaciones necesarias en sus instalaciones deportivas de acuerdo a la normatividad respectiva, para la práctica y desarrollo del deporte adaptado y del deporte para las personas mayores, así como el equipamiento, medidas de seguridad e implementos que requiere la práctica de estos deportes, mismos que deberán ser previstos anualmente como parte de los programas que establece la fracción VI que antecede;\nFracción modificada y publicada en la GOCDMX el 15 de mayo de 2023\nIX. Fijar las bases a que se sujetará la participación de deportistas del Órgano Político-\nAdministrativo de la Demarcación Territorial respectiva, en congruencia con las disposiciones federales y locales vigentes;\nX. Destinar, conforme lo establezcan sus presupuestos de egresos, recursos para la construcción, mejoramiento, mantenimiento, equipamiento y rehabilitación de instalaciones deportivas, atendiendo a las características de accesibilidad\nFracción modificada y publicada en la GOCDMX el 15 de mayo de 2023\nXI. Vigilarán que la entrada a las instalaciones y la expedición de credenciales de los deportivos que correspondan a su competencia sean totalmente gratuitos; bajo la supervisión y vigilancia de la contraloría correspondiente;\nXII. Promover la realización de programas y campañas de difusión con perspectiva de género sobre la no violencia en el deporte, la erradicación de actos racistas, intolerantes y violentos y de una cultura de sana convivencia y esparcimiento al interior de las instalaciones y espacios deportivos de su jurisdicción.\n\nXIII. Ofrecer servicios en materia de medicina del deporte y prevenir el uso de sustancias y métodos que pongan en riesgo la salud de los deportistas; y\nXIV. Los demás que le atribuyan otras disposiciones legales y reglamentarias aplicables.\nArtículo 32.- Los Comités Deportivos de los Órganos Político-Administrativos de cada una de las\nDemarcaciones Territoriales de la Ciudad de México tendrán las siguientes atribuciones:\nI. Ejecutar los planes y programas en materia deportiva y recreativa que apruebe el Instituto del\nDeporte;\nII. Difundir, promover y fomentar el deporte entre todos los sectores y habitantes de la\nDemarcación Territorial;\nIII. Promover la creación, mantenimiento y preservación de instalaciones y espacios deportivos;\nIV. Promover la realización de eventos deportivos y recreativos;\nV. Proponer al Instituto del Deporte a quienes se hayan distinguido en el deporte o en la difusión, promoción, fomento o investigación en materia deportiva dentro de la Demarcación Territorial, para la entrega de reconocimientos y estímulos;\nVI. Promover la realización de convenios de coordinación o colaboración en materia deportiva;\nVII. Realizar competencias semestrales las cuales tendrán como finalidad, difundir la importancia y trascendencia del deporte para todos los habitantes;\nVIII. Promover, en coordinación con el Instituto y la dependencia local de salud, programas de difusión e información con perspectiva de género entre equipos, clubes, ligas, uniones y asociaciones deportivas para erradicar la violencia deportiva así como para prevenir la atención de las adicciones relacionadas con el tabaquismo, alcoholismo y fármacodependencia; y\nIX. Las demás que le otorgue esta Ley u otros ordenamientos.\nCAPÍTULO SÉPTIMO\n\nDE LOS DEPORTISTAS DE ALTO RENDIMIENTO, BENEFICIOS Y OBLIGACIONES.\nArtículo 33.- Se considera deporte de alto rendimiento la práctica sistemática y planificada, que busca el desarrollo de las máximas capacidades competitivas en los diversos rangos de edad y en el marco competitivo de una disciplina deportiva para alcanzar un nivel superior en los equipos representativos en justas deportivas de carácter local, nacional o internacional.\nArtículo 34.- Para que los deportistas de alto rendimiento accedan a los beneficios que esta Ley otorga deberán ser propuestos por el Consejo del Deporte cumpliendo con los siguientes requisitos:\na) Ser mexicano residente en la Ciudad de México.\nb) Estar previamente inscrito en el Registro del Deporte de la Ciudad de México.\nc) No encontrarse sancionado con carácter firme por dopaje o por algunas de las infracciones previstas en esta Ley.\nd) Haber obtenido triunfos trascendentales en competiciones organizadas por las Federaciones nacionales, internacionales o por el Comité Olímpico/Paralímpico Internacional, en alguna de las modalidades deportivas oficialmente reconocidas.\nArtículo 35.- Los deportistas con discapacidad física, intelectual o sensorial o enfermedad mental se considerarán de alto rendimiento cumpliendo los requisitos citados, en atención a su trayectoria deportiva y relevancia social, la obtención de esta condición.\nArtículo 36.- El procedimiento para la declaración de deportistas de alto rendimiento se iniciará a instancia de los interesados presentando su solicitud directamente, o en su caso, a través de los integrantes del\nSistema de Cultura Física y Deporte, quienes durante los dos primeros meses de cada año, enviarán al\nConsejo del Deporte las propuestas de inclusión en la relación anual de deportistas de alto rendimiento, de aquellos deportistas que durante el año anterior hayan cumplido con los requisitos exigidos en el\nArtículo anterior.\nArtículo 37.- El Consejo del Deporte publicará los nombres de los deportistas seleccionados en la Gaceta\nOficial de la Ciudad de México lo que implicará el reconocimiento automático de la condición de deportista de alto rendimiento.\n\nArtículo 38.- Los deportistas al adquirir la calidad de alto rendimiento podrán ser beneficiarios de las becas y ayudas económicas específicas que, anualmente, sean convocadas por el Instituto.\nArtículo 39.- Los deportistas de alto rendimiento podrán ser valorados para la obtención de puestos de trabajo en los diferentes órganos administrativos de la Ciudad de México, en virtud de que se considerará como mérito evaluable en las convocatorias de plazas y en la provisión de puestos de trabajo, relacionados con la actividad deportiva.\nEl Instituto podrá suscribir convenios con empresas y otros entes e instituciones, con el fin de facilitar a los deportistas de alto rendimiento las condiciones para compatibilizar su preparación técnico-deportiva con el disfrute de un puesto de trabajo.\nArtículo 40.- Los deportistas de alto rendimiento que cursen nivel básico, primaria y secundaria, estarán exentos de la realización de pruebas en esta materia, en virtud de que la Secretaría de Educación de la\nCiudad de México deberá desarrollar programas de atención y ayuda a los deportistas de alto rendimiento para facilitar la realización de sus estudios compatibilizándolos con el entrenamiento y la práctica deportiva para conseguir su plena integración social y académica.\nEn relación con los ciclos de grado medio y grado superior, las universidades públicas o privadas podrán establecer un porcentaje de plazas reservadas a deportistas de alto rendimiento; valorando los expedientes de estos alumnos conforme a lo dispuesto en la normativa aplicable, que cumplan los requisitos académicos correspondientes.\nEn lo referente al acceso a las enseñanzas conducentes a los títulos de formación profesional en Actividades\nFísicas y Deportivas, los deportistas que acrediten la condición de deportista de alto rendimiento quedarán exentos de la realización de la parte específica de la prueba de acceso que sustituye a los requisitos académicos; así mismo podrán reservar un cupo adicional equivalente como mínimo al cinco por ciento de las plazas ofertadas para los deportistas de alto rendimiento.\nArtículo 41.- Los deportistas de alto rendimiento gozarán, además de los beneficios señalados en los\nArtículos anteriores, de las siguientes medidas de apoyo:\na) En el supuesto de existir relación de servicio con la administración pública local, previa petición del interesado y siempre que las necesidades del servicio lo permitan, podrá adaptársele su horario en función de sus necesidades para la realización de los entrenamientos. Asimismo, se\n\nles podrá conceder permiso retribuido, para asistir a las convocatorias de las selecciones de las\nFederaciones deportivas, como deber inexcusable de carácter público.\nb) Uso preferente de las instalaciones deportivas públicas, siempre que exista disponibilidad para ello.\nc) Reserva de un cupo adicional de plazas, por parte de la Secretaría de Educación de la Ciudad de México, para aquellos deportistas de alto rendimiento que reúnan los requisitos académicos necesarios.\nArtículo 42.- Los deportistas de alto rendimiento deberán colaborar con el Instituto en los proyectos de difusión del deporte base y de la práctica deportiva en general, así como en aquellas actividades que promocionen la educación para la salud, la prevención de fármaco dependencia y especialmente aquellas actividades destinadas a fomentar la práctica deportiva por parte de la mujer para promover la igualdad de genero, y a los grupos vulnerables en su caso.\nArtículo 43.- Los beneficios del reconocimiento de la condición de deportista de alto rendimiento, tendrán una vigencia de dos años desde la fecha del reconocimiento, pudiéndose en todo caso ratificar siempre que el deportista mantenga en vigor su registro ante el Instituto.\nArtículo 44.- La condición de deportista de alto rendimiento se perderá por algunas de las causas siguientes:\na) Desaparición de alguno de los requisitos establecidos, para alcanzar dicha condición.\nb) Negativa injustificada a cumplir las obligaciones establecidas en esta Ley.\nc) Por haber sido incluido en el registro de la Comisión Nacional del Deporte.\nArtículo 45.- La pérdida de la condición de deportista de alto rendimiento requerirá ser evaluado el expediente administrativo por el Consejo del Deporte, quien en todo caso dará audiencia al interesado con anterioridad a emitir una terminación motivada.\nArtículo 46.- Desaparecidas las causas que motivaron la pérdida de la condición de deportista de alto rendimiento, podrá solicitarse nuevamente su reconocimiento sin perjuicio de que, en caso de sanción impuesta al deportista, haya de estarse al cumplimiento de la misma para volver a instar la solicitud.\n\nArtículo 47.- La pérdida de la condición de deportista de alto rendimiento implicará también la de sus beneficios.\nCAPÍTULO OCTAVO\nDE LA PARTICIPACIÓN DE LOS SECTORES PÚBLICO, PRIVADO Y\nSOCIAL.\nArtículo 48.- Los convenios que el Instituto del Deporte de la Ciudad de México promueva para la participación de los sectores social y privado, entidades de la Administración Pública Federal, así como de los organismos deportivos, con el fin de integrarlos al Sistema de Cultura Física y Deporte deberán tener como objetivo fundamental el fomento y desarrollo del deporte previendo:\nI. La forma en que se desarrollarán las actividades deportivas que se realicen dentro del Sistema de Cultura Física y Deporte de la Ciudad de México;\nII. Los apoyos que, en su caso, les sean destinados para el desarrollo y fomento del deporte, comprendiendo las actividades científicas y técnicas que se relacionen con el mismo; y\nIII. Las acciones y recursos que aporten para la promoción y fomento del deporte, así como el uso de su infraestructura.\nArtículo 49.- El Instituto del Deporte podrá suscribir convenios con las universidades e instituciones educativas privadas, con el fin de que los deportistas de alto rendimiento puedan gozar de condiciones especiales en relación al acceso y permanencia en las mismas, respetando, en todo caso, los requisitos académicos generales previstos para el acceso.\nAsí como con el fin de hacer compatibles los estudios con los entrenamientos y la asistencia a competiciones del colectivo de deportistas de alto rendimiento, para la puesta en marcha de tutorías académicas que presten apoyo a quienes tengan dificultades para mantener el ritmo normal de asistencia.\nArtículo 49 Bis.- El Instituto del Deporte promoverá ante las diversas instancias del Gobierno, el rescate y acondicionamiento de parques, plazas y demás espacios públicos en donde sea factible la instalación de equipos y accesorios especiales destinados a la práctica de la cultura física, procurando que sean accesibles bajo el principio de diseño universal.\n\nPara ello, el Instituto promoverá entre la administración pública local y los sectores social y privado, convenios de colaboración que permitan la adecuación, equipamiento y uso de dichos espacios públicos con la finalidad de propiciar su rescate e incentivar el desarrollo de la cultura física de la comunidad.\nCAPÍTULO NOVENO\nDEL FONDO DE APOYO PARA DEPORTISTAS DE ALTO RENDIMIENTO\nArtículo 50.- El Instituto del Deporte de la Ciudad de México promoverá la constitución del Fondo de Apoyo\npara Deportistas de Alto Rendimiento mediante un fideicomiso que se constituya para tal efecto, con la participación de los sectores público, social y privado.\nDicho fondo tendrá como finalidad captar recursos financieros y materiales para apoyar la preparación de los deportistas que han alcanzado ese nivel, para lo cual se contará con Centros de Alto Rendimiento donde podrán entrenar en forma adecuada con servicios de apoyo nutricional, médicos y psicólogos; así como programas para prevenir el consumo de sustancias prohibidas.\nArtículo 51.- El Titular del Instituto deberá enviar trimestralmente a la Comisión de Deporte del Congreso de la Ciudad de México, un informe detallado del estado financiero que guarda el Fondo de Apoyo para\nDeportistas de Alto Rendimiento.\nCAPÍTULO DÉCIMO\nDEL SERVICIO SOCIAL\nArtículo 52.- Se instituye el servicio social, para los egresados de las facultades de organización deportiva de las instituciones educativas de nivel superior ó con similares profesiones, consistente en prestar sus servicios profesionales por el tiempo establecido por cada institución educativa, en el desarrollo de los programas deportivos de la Ciudad de México.\nArtículo 53.- Para dar cabal cumplimiento a dicha función se establecerán mecanismos de coordinación entre el Instituto y las autoridades educativas con la finalidad de llevar a cabo la eficaz prestación del servicio social de los egresados de las facultades de organización deportiva.\n\nArtículo 54.- El servicio social en materia del deporte se llevará a cabo prioritariamente en áreas de menor desarrollo económico y social, contando para ello con un incentivo mensual en dinero o en especie para la manutención y transportación del prestador del servicio.\nCAPÍTULO UNDÉCIMO\nDE LA CULTURA DEL DEPORTE\nArtículo 55.- Se entiende por cultura del deporte la manifestación social producto de valores, conocimientos y recursos generados en su desarrollo, orientada a realizar acciones permanentes fundadas en la investigación, en los requerimientos y en las posibilidades sociales, para extender sus beneficios a todos los sectores de la población.\nArtículo 56.- En el Programa del Deporte de la Ciudad de México, se establecerán acciones que promuevan su cultura, impulsen la investigación, capacitación de las disciplinas, ciencias aplicadas y que fomenten el deporte popular.\nSe establecerán, igualmente acciones que permitan generar y difundir la cultura del deporte adaptado, así como promover e impulsar la investigación de los diferentes implementos que se requieren para la práctica de las diferentes disciplinas y modalidades que practican las personas con discapacidad.\nSe promoverán programas de fomento deportivo y recreativo, para la participación incluyente de grupos de atención prioritaria y sus intersecciones, en especial para las personas mayores, personas con discapacidad y personas que se encuentran en zonas de alta marginación.\nArtículo 57.- La cultura del deporte en la Ciudad de México se asociará a la participación social, a la libre y respetuosa manifestación de las ideas y a la conveniencia del compromiso colectivo.\nCAPÍTULO DUODÉCIMO\nDE LAS SANCIONES ADMINISTRATIVAS Y RECURSOS EN EL DEPORTE\nArtículo 58.- La aplicación de sanciones por infracciones a esta Ley, a su reglamento y disposiciones legales aplicables corresponde al Instituto del Deporte y a las Direcciones de los Órganos Político-Administrativos de cada una de las Demarcaciones Territoriales de la Ciudad de México relacionadas con la materia deportiva de acuerdo a su ámbito de competencia.\n\nArtículo 59.- Las sanciones que se aplicarán a los integrantes del Sistema de Cultura Física y Deporte de la\nCiudad de México por infracciones a esta Ley, consistirán en:\nI. Amonestación privada o pública;\nII. Suspensión de su registro;\nIII. Suspensión hasta por tres meses en el uso de las instalaciones deportivas propiedad del\nGobierno de la Ciudad de México\nIV. Reducción o cancelación de apoyos económicos;\nV. Suspensión hasta por cinco años en la participación de competencias y actividades deportivas organizadas por las autoridades deportivas del Gobierno de la Ciudad de México;\nVI. Cancelación del registro;\nVII. Anulación de reconocimientos, premios o incentivos derivados de las competencias deportivas organizadas por las autoridades deportivas del Gobierno de la Ciudad de México;\nVIII. Anulación del carácter de representante deportivo estatal, hasta por un periodo de tres años;\nIX. Suspensión de la cédula profesional o cartilla del Sistema de Capacitación y Certificación de\nEntrenadores Deportivos hasta por cinco años; y\nX. Suspensión hasta por cinco años en la representación de la Ciudad de México en competencias y actividades deportivas organizadas por las autoridades deportivas federales.\nArtículo 60.- En caso de diferencias entre los deportistas o, entre éstos y las autoridades e instituciones del deporte, así como al interior de las asociaciones deportivas, podrán éstos acudir ante el Comité de Arbitraje\nDeportivo. Éste en su carácter de árbitro resolverá en amigable composición sus diferencias. El procedimiento se establecerá en el reglamento respectivo.\n\nArtículo 61.- En caso de que los Deportistas no deseen promover o sujetarse al arbitraje, podrán promover los recursos o juicios establecidos en la Ley de Procedimiento Administrativo de la Ciudad de México, con los efectos correspondientes.\nCAPÍTULO DECIMOTERCERO\nDE LAS INSTALACIONES DEPORTIVAS, RESPONSABILIDADES Y\nCLAUSURA\nArtículo 62.- Para los efectos de esta ley se entiende por instalación deportiva, los deportivos, complejos deportivos o unidades deportivas independientemente de la denominación que adopten y en general todo inmueble construido o adecuado para la práctica de actividades físicas e intelectuales, que realicen las personas con propósitos competitivos o de esparcimiento.\nArtículo 63.- Se declara de utilidad social e interés público la construcción, remodelación, ampliación, conservación y mantenimiento de las instalaciones deportivas, con el objeto de atender adecuadamente las demandas que requiera la práctica del deporte, el Congreso de la Ciudad de México promoverá la asignación de recursos suficientes para la construcción y rehabilitación de instalaciones deportivas adscritas a cada una de las Alcaldías.\nLos recursos obtenidos mediante autogenerados, obligatoriamente se deberán destinar para estos fines en las instalaciones deportivas en que fueron recaudados.\nArtículo 64.- En la construcción de nuevas instalaciones deportivas, así como en el mejoramiento, equipamiento y rehabilitación de los actuales espacios se fomentará el uso de energías, tecnologías y combustibles alternativos y renovables.\nArtículo 65.- Los Titulares de los Órganos Político-Administrativos que corresponda mantendrán en óptimas condiciones de uso y mantenimiento las instalaciones deportivas deberán conservarse y mantenerse adecuadamente a fin de que puedan ser utilizados por todos los sectores de la población, equipándolas con infraestructura de punta y avances tecnológicos todos y cada uno de los elementos materiales necesarios para la práctica de cada especialidad.\nArtículo 66.- El uso de las instalaciones deportivas debe ser exclusivamente para eventos deportivos, en caso contrario procederá su clausura en términos de la legislación administrativa aplicable a cada caso.\n\nArtículo 67.- Los administradores de instalaciones deportivas y las asociaciones son corresponsables de que sus instructores, entrenadores y técnicos que impartan clases y seminarios cuenten con el reconocimiento oficial que acredite su capacidad para ejercer como tales, en caso de no contar con dicho reconocimiento oficial procederá la clausura de las instalaciones por parte del Instituto del Deporte.\nArtículo 68.- Los responsables administrativos de las instalaciones deportivas realizadas con recursos de la\nFederación, Ciudad de México o los Órganos Político-Administrativos de cada una de las Demarcaciones\nTerritoriales de la Ciudad de México e inscritas en el Registro del Deporte de la Ciudad de México deberán registrar su calendario anual de actividades ante el Instituto del Deporte durante los primeros treinta días de cada año.\nArtículo 69.- Los responsables o administradores de toda instalación deportiva deberán tramitar su registro ante el Instituto del Deporte de la Ciudad de México, quien verificará que cuente con las condiciones adecuadas para la práctica del deporte, calidad y seguridad que se requiere.\nDebiendo realizarse verificaciones anuales o con anterioridad a petición de los interesados. El Instituto del\nDeporte de la Ciudad de México podrá vetar el uso de cualquier instalación deportiva que no cumpla con los requisitos señalados.\nArtículo 70.- - Las instalaciones deportivas de los Órganos Político-Administrativos de cada una de las\nDemarcaciones Territoriales de la Ciudad de México deberán contar con las adecuaciones arquitectónicas para la práctica del deporte adaptado que realizan las personas con discapacidad, debiendo contemplarse por los Órganos Político-Administrativos de cada una de las Demarcaciones Territoriales de la Ciudad de\nMéxico en los presupuestos que se ejercerán cada año para dar cumplimiento a las adecuaciones que resulten necesarias.\nSe procederá en las nuevas construcciones de instalaciones deportivas y en la rehabilitación de los actuales espacios, al acondicionamiento arquitectónico, de acceso y servicios, para la realización del deporte adaptado.\nCAPÍTULO DECIMOCUARTO\nDEL ANTIDOPAJE, PREVENCIÓN DE USO DE SUSTANCIAS PROHIBIDAS\nY SANCIONES\n\nArtículo 71.- Para los efectos de esta Ley, se entiende por dopaje el uso de sustancias y métodos utilizados para modificar, alterar o incrementar de manera artificial o no fisiológica la capacidad de rendimiento mental o físico del deportista.\nArtículo 72.- Para garantizar el principio de igualdad de oportunidades de los participantes en las competencias deportivas oficiales, así como la salud física y psíquica de los deportistas se prohíbe el dopaje.\nArtículo 73.- Toda persona que participe en las competencias deportivas oficiales organizadas por las autoridades deportivas del Gobierno de la Ciudad de México, está obligada a sujetarse a la práctica de pruebas para determinar la existencia de dopaje\nArtículo 74.- El Instituto del Deporte de la Ciudad de México en coordinación con la autoridad a cargo de la\nSalud en la Ciudad de México, se encargará de:\nI. Emitir y difundir periódicamente el listado oficial y actualizado de las sustancias y métodos cuyo uso o empleo en las competencias deportivas oficiales se prohíba, por ser considerados generadores de modificación, alteración o incremento artificial o no fisiológico de la capacidad de rendimiento mental o físico del deportista;\nII. Estipular el tipo de exámenes que han de aplicarse para determinar si existió dopaje, así como su procedimiento de aplicación; y\nIII. Practicar directamente u ordenar la aplicación de los exámenes para determinar si sé incurrió en dopaje.\nArtículo 75.- - Los deportistas a quienes se les haya comprobado que incurrieron en dopaje en competencias deportivas organizadas por el Gobierno de la Ciudad de México, así como los instructores, entrenadores y médicos integrantes del Sistema de Cultura Física y Deporte de la Ciudad de México que hayan inducido o administrado las sustancias o métodos prohibidos que dieron lugar a la determinación del dopaje, serán sancionados de conformidad con esta Ley.\nCAPÍTULO DECIMOQUINTO\nPROTECCIÓN A LA SALUD DE LOS DEPORTISTAS\n\nArtículo 76.- Con el propósito de proteger la salud e integridad de los usuarios de las instalaciones deportivas propiedad del Gobierno de la Ciudad de México, el Instituto del Deporte de la Ciudad de México, garantizará que el personal que a su servicio imparta clases teórico-prácticas de actividades deportivas y físicas, cuente con la capacitación y certificación de conocimientos, para desempeñar tales actividades.\nArtículo 77.- Los organismos deportivos integrantes del Sistema de Cultura Física y Deporte de la Ciudad de México que ofrezcan servicios de capacitación, entretenimiento deportivo o atención médica, están obligadas a garantizar que sus instructores, entrenadores, técnicos y personal especializado en medicina deportiva, cuenten con la certificación de conocimientos avalados por las autoridades competentes y que acredite su capacidad para ejercer como tales, además de su incorporación al registro.\nArtículo 78.- En el caso de existir contingencia ambiental declarada por las autoridades competentes deberán suspenderse las actividades deportivas al aire libre en las instalaciones deportivas propiedad del\nGobierno de la Ciudad de México.\nArtículo 79.- Las instalaciones deportivas integrantes del Sistema de Cultura Física y Deporte de la Ciudad de México deberán ofrecer un servicio de atención médica deportiva profesional, tanto para los usuarios como para aquellos deportistas que entrenen en sus instalaciones. Este servicio deberá estar disponible de manera permanente en todos los horarios mientras se realicen en dichas instalaciones actividades deportivas.\nCAPÍTULO DECIMOSEXTO\nDE LAS LIGAS DEPORTIVAS\nArtículo 80.- El presente título tiene por objeto establecer el marco jurídico normativo para el control, regulación y manejo de las ligas que desarrollen sus actividades en las instalaciones deportivas que se encuentran administradas por los Órganos Político Administrativos de cada una de las Demarcaciones\nTerritoriales de la Ciudad de México.\nArtículo 81.- La creación de ligas en las instalaciones deportivas tendrán los siguientes objetivos:\nI. Desarrollar la práctica ordenada de los deportes de conjunto;\nII.Fomentar la sana competencia;\n\nIII. Responder a la demanda social como un satisfactor para la práctica deportiva; y\nIV. Difundir la cultura y conocimiento de sus disciplinas deportivas.\nArtículo 82.- Las ligas deportivas estarán obligadas a presentar su calendario anual, incluyendo horarios, de las actividades ante el Instituto del Deporte de la Ciudad de México para ser autorizado y éste a su vez lo remita a las autoridades encargadas de administrar la instalación deportiva correspondiente.\nArtículo 83.- Corresponde a la administración de las instalaciones deportivas supervisar el cumplimiento de la normatividad para el mejor funcionamiento de las ligas deportivas. Así como evitar que se violen las disposiciones que se estipulen en el presente ordenamiento. Las personas administradoras deberán presentar a las personas titulares de las Alcaldías de la Ciudad de México y al Instituto del Deporte, un informe anual pormenorizado sobre la situación de las ligas deportivas.\nArtículo 84.- El funcionamiento de las ligas deportivas será de conformidad con esta Ley, los lineamientos para el uso de las instalaciones deportivas, su Reglamento y a su normatividad interna.\nArtículo 85.- Las ligas deportivas deberán responsabilizarse del uso de las instalaciones durante los horarios que les son concedidos. Junto con la administración del deportivo asumirán las tareas de mantenimiento y conservación de las mismas.\nArtículo 86.- La administración de las instalaciones deportivas será responsable de que las ligas deportivas que utilicen las instalaciones y los servicios que ofrece el deportivo lo hagan de acuerdo a las disposiciones de esta ley y acorde con la cultura deportiva.\nCAPÍTULO DECIMOSÉPTIMO\nDEL DEPORTE ADAPTADO\nArtículo 87.- Las personas a que se refiere este título recibirán sin discriminación alguna, los estímulos y demás beneficios que se establecen en esta ley y su reglamento.\nArtículo 88.- El Instituto del Deporte de la Ciudad de México, así como las personas titulares de los Órganos\nPolíticoAdministrativos cada una de las Demarcaciones Territoriales de la Ciudad de México, deberán alentar la práctica de nuevas disciplinas y modalidades del deporte adaptado en las instalaciones deportivas donde se cuente con la infraestructura necesaria contando para ello, con la colaboración de las\n\ndiferentes organizaciones del deporte adaptado, con el objeto de apoyar su integración a la sociedad y propiciar su bienestar\nArtículo 89.- El desarrollo de las actividades del deporte adaptado se dará siempre en un marco de respeto e igualdad, vigilándose la salud física y mental del individuo.\nArtículo 90.- Los aspirantes a ingresar a cualquiera de las disciplinas del deporte adaptado, requerirán un certificado médico que los acredite aptos para su práctica. Cuando las personas a que se refiere el presente título deseen realizar actividades deportivas, que no impliquen un riesgo para la salud, no será necesaria la presentación del diagnóstico médico citado.\nArtículo 91.- El Instituto del Deporte de la Ciudad de México, deberá contar dentro de la Dirección de\nPromoción y Desarrollo Deportivo con un área específica que se encargue de la elaboración, programación, ejecución, difusión y en su caso de la supervisión de los programas que con relación al deporte adaptado sean elaborados para su aplicación en la Ciudad de México.\nArtículo 92.- Los Órganos Políticos-Administrativos de cada una de las Demarcaciones Territoriales de la\nCiudad de México deberán contar dentro de la Dirección de la Área Deportiva con un departamento específico cuya función sea la de elaborar, complementar y en su caso supervisar los programas para el deporte adaptado.\nArtículo 93.- Los Órganos Político-Administrativos de cada una de las Demarcaciones Territoriales de la\nCiudad de México, en el ámbito de sus respectivas circunscripciones deberán observar el debido cumplimiento del presente Título, así como de los demás ordenamientos establecidos en la presente Ley y su reglamento.\nTRANSITORIOS\nPRIMERO.- Remítase a la Jefatura de Gobierno para su Promulgación y Publicación en la Gaceta Oficial de la Ciudad de México.\nSEGUNDO.- El presente Decreto entrará en vigor al día siguiente de su publicación en la Gaceta Oficial de la Ciudad de México.\n\nTERCERO.- El Reglamento de la presente Ley, deberá expedirse dentro de los veinte días siguientes a la fecha en que entre en vigor esta Ley.\nCUARTO.- De acuerdo al presupuesto anual todos los recursos destinados al Deporte deberán ir etiquetados para tal fin.\nRecinto de la Asamblea Legislativa del Distrito Federal, a los veintisiete días del mes de noviembre del año dos mil siete.- POR LA MESA DIRECTIVA.- DIP. RAÚL ALEJANDRO RAMÍREZ RODRÍGUEZ, PRESIDENTE.- DIP.\nSERGIO MIGUEL CEDILLO FERNÁNDEZ, SECRETARIO.- DIP. MIGUEL ÁNGEL ERRASTI ARANGO, SECRETARIO.-\n(Firmas)\nEn cumplimiento de lo dispuesto por el artículo 122, Apartado C, Base Segunda, fracción II, inciso b), de la\nConstitución Política de los Estados Unidos Mexicanos; 48, 49 y 67, fracción II del Estatuto de Gobierno del\nDistrito Federal, y para su debida publicación y observancia expido el presente Decreto Promulgatorio, en la Residencia Oficial del Jefe de Gobierno del Distrito Federal, en la Ciudad de México, a los doce días del mes de diciembre de dos mil siete.- EL JEFE DE GOBIERNO DEL DISTRITO FEDERAL, MARCELO LUIS EBRARD\nCASAUBON.- FIRMA.- EL SECRETARIO DE GOBIERNO, JOSÉ ÁNGEL ÁVILA PÉREZ.- FIRMA.- EL SECRETARIO DE\nEDUCACIÓN, AXEL DIDRIKSSON TAKAYANAGÜI.- FIRMA.\nTRANSITORIOS DEL DECRETO POR EL QUE SE ADICIONA UNA FRACCIÓN AL ARTÍCULO 25 DE LA LEY DE\nEDUCACIÓN FÍSICA Y DEPORTE DEL DISTRITO FEDERAL, PUBLICADO EN LA GACETA OFICIAL DEL DISTRITO\nFEDERAL EL 3 DE FEBRERO DE 2011.\nPRIMERO. Publíquese en la Gaceta Oficial del Distrito Federal y para su mayor conocimiento en el Diario\nOficial de la Federación.\nSEGUNDO. La presente reforma entrará en vigor al día siguiente de su publicación.\nTRANSITORIOS DEL DECRETO POR EL QUE SE REFORMA EL ARTÍCULO 31 DE LA LEY DE EDUCACIÓN FÍSICA\nY DEPORTE DEL DISTRITO FEDERAL, PUBLICADO EN LA GACETA OFICIAL DEL DISTRITO FEDERAL EL 2 DE\nNOVIEMBRE DE 2012.\nPRIMERO.- El presente Decreto, entrará en vigor al día siguiente de su publicación en la Gaceta Oficial del\nDistrito Federal.\n\nSEGUNDO.- Publíquese en la Gaceta Oficial del Distrito Federal y en el Diario Oficial de la Federación, para su mayor difusión.\nTRANSITORIOS DEL DECRETO POR EL QUE SE REFORMAN Y ADICIONAN DIVERSAS DISPOSICIONES DE LA\nLEY DE EDUCACIÓN FÍSICA Y DEPORTE DEL DISTRITO FEDERAL, PUBLICADO EN LA GACETA OFICIAL DEL\nDISTRITO FEDERAL EL 8 DE AGOSTO DE 2013.\nPRIMERO.- Publíquese en la Gaceta Oficial del Distrito Federal, y en el Diario Oficial de la Federación para su mayor difusión.\nSEGUNDO.- Las presentes reformas y adiciones entrarán en vigor al día siguiente de su publicación en la\nGaceta Oficial del Distrito Federal.\nTRANSITORIOS DEL DECRETO POR EL QUE SE REFORMAN DIVERSOS ARTÍCULOS DE CÓDIGOS Y LEYES\nLOCALES, QUE DETERMINAN SANCIONES Y MULTAS ADMINISTRATIVAS, CONCEPTOS DE PAGO Y MONTOS\nDE REFERENCIA, PARA SUSTITUIR AL SALARIO MÍNIMO POR LA UNIDAD DE CUENTA DE LA CIUDAD DE\nMÉXICO, DE MANERA INDIVIDUAL O POR MÚLTIPLOS DE ÉSTA, PUBLICADOS EN LA GACETA OFICIAL DEL\nDISTRITO FEDERAL EL 28 DE NOVIEMBRE DE 2014.\nPRIMERO.- Publíquese en la Gaceta Oficial del Distrito Federal.\nSEGUNDO.- El presente Decreto se tomará como referencia para el diseño e integración del paquete económico correspondiente al ejercicio fiscal 2015 y entrará en vigor junto con dicho paquete, a excepción de lo dispuesto en los artículos SEGUNDO y CUADRAGÉSIMO OCTAVO del presente Decreto relacionado con la materia Electoral, que entrarán en vigor al día siguiente a aquél en que concluya el proceso electoral\n2014-2015 del Distrito Federal.\nTERCERO.- Las reformas contenidas en el presente decreto no se aplicarán de manera retroactiva en perjuicio de persona alguna, respecto de las sanciones y multas administrativas, conceptos de pago, montos de referencia y demás supuestos normativos que se hayan generado o impuesto de manera previa a la entrada en vigor del presente decreto.\n\nCUARTO.- Las referencias que se hagan del salario mínimo en las normas locales vigentes, incluso en aquellas pendientes de publicar o de entrar en vigor, se entenderán hechas a la Unidad de Cuenta de la\nCiudad de México, a partir de la entrada en vigor del presente Decreto.\n_________________________________________________________________________\n______\nTRANSITORIOS DEL DECRETO POR EL QUE SE REFORMAN LA FRACCIÓN IV DEL ARTÍCULO 31 Y SE MODIFICA\nY ADICIONA UN PÁRRAFO AL ARTÍCULO 63 DE LA LEY DE EDUCACIÓN FÍSICA Y DEL DEPORTE DEL DISTRITO\nFEDERAL, PUBLICADOS EN LA GACETA OFICIAL DE LA CIUDAD DE MÉXICO EL 09 DE DICIEMBRE DE 2019.\nPRIMERO.- Publíquese en la Gaceta Oficial de la Ciudad de México.\nSEGUNDO.- El presente Decreto entrará en vigor al día siguiente de su publicación en la Gaceta Oficial de la Ciudad de México.\nTERCERO. Se derogan todas las disposiciones que se opongan al presente Decreto.\nPalacio Legislativo del Congreso de la Ciudad de México, a los tres días del mes de septiembre del año dos mil diecinueve.- POR LA MESA DIRECTIVA.- DIPUTADA ISABELA ROSALES HERRERA, PRESIDENTA.-\nDIPUTADA MARTHA SOLEDAD VENTURA AVILA, SECRETARIA.- DIPUTADA MARGARITA SALDAÑA\nHERNÁNDEZ, SECRETARIA.- (Firmas)\nCon fundamento en lo dispuesto por los artículos 122, apartado A, fracción III, de la Constitución Política de los Estados Unidos Mexicanos; 32 apartado C, numeral 1, inciso a) de la Constitución Política de la\nCiudad de México; 3, fracciones XVII y XVIII, 7 párrafo primero, 10 fracción 11, 12 y 21 párrafo primero de la Ley Orgánica del Poder Ejecutivo y de la Administración Pública de la Ciudad de México; para su debida publicación y observancia, expido el presente Decreto Promulgatorio en la Residencia Oficial de la Jefatura de Gobierno de la Ciudad de México, a los veinticinco días del mes de septiembre del año dos mil diecinueve.- LA JEFA DE GOBIERNO DE LA CIUDAD DE MÉXICO, DRA. CLAUDIA SHEINBAUM PARDO.-\nFIRMA.- LA SECRETARIA DE GOBIERNO, ROSA ICELA RODRÍGUEZ VELÁZQUEZ.- FIRMA.\nTRANSITORIO DEL DECRETO POR EL QUE SE REFORMA LA FRACCIÓN I, DEL ARTÍCULO 31 DE LA LEY DE\nEDUCACIÓN FÍSICA Y DEPORTE DEL DISTRITO FEDERAL, PUBLICADO EN LA GACETA OFICIAL DE LA CIUDAD\nDE MÉXICO EL DÍA 02 DE MARZO DE 2021.\n\nPRIMERO: Remítase el presente decreto a la persona Titular de la Jefatura de Gobierno de la Ciudad de\nMéxico para su promulgación y publicación en la Gaceta Oficial de la Ciudad de México.\nSEGUNDO: El presente Decreto entrará en vigor al día siguiente de su publicación.\nTERCERO: Todas las disposiciones legales que contravengan esta reforma, se entienden como derogadas.\nPalacio Legislativo del Congreso de la Ciudad de México, a los once días del mes de febrero del año dos mil veintiuno. POR LA MESA DIRECTIVA.-DIPUTADA MARGARITA SALDAÑA HERNÁNDEZ, PRESIDENTA.-\nDIPUTADA DONAJI OFELIA OLIVERA REYES, SECRETARIA.- DIPUTADO PABLO MONTES DE OCA DEL OLMO,\nSECRETARIO.- (Firmas)\nCon fundamento en lo dispuesto por los artículos 122, apartado A, fracción III de la Constitución Política de los Estados Unidos Mexicanos; 32, apartado C, numeral 1, inciso a) de la Constitución Política de la Ciudad de México; 2 párrafo segundo, 3 fracciones XVII y XVIII, 7 párrafo primero, 10 fracción II, 12 y 21 párrafo primero de la Ley Orgánica del Poder Ejecutivo y de la Administración Pública de la Ciudad de México; para su debida publicación y observancia, expido el presente Decreto Promulgatorio en la Residencia Oficial de la Jefatura de Gobierno de la Ciudad de México, al primer día del mes de marzo del año dos mil veintiuno.-\nLA JEFA DE GOBIERNO DE LA CIUDAD DE MÉXICO, DRA. CLAUDIA SHEINBAUM PARDO.- FIRMA.- EL\nSECRETARIO DE GOBIERNO, JOSÉ ALFONSO SUÁREZ DEL REAL Y AGUILERA.-FIRMA.\nTRANSITORIO DEL DECRETO POR EL QUE SE REFORMAN LOS ARTÍCULOS 6; 22; LA DENOMINACIÓN DEL\nCAPITULO TERCERO; LAS FRACCIONES I Y II DEL ARTÍCULO 22 BIS; SE ADICIONAN DOS FRACCIONES Y SE\nREFORMAN LAS FRACCIONES II, VI, VII, X, XI, XII, XVII, XIX, XXII, XXIII Y XXIV, QUE PASA A SER LA XXVI DEL\nARTÍCULO 23, DE LA LEY DE EDUCACIÓN FÍSICA Y DEPORTE DEL DISTRITO FEDERAL, PUBLICADO EN LA\nGACETA OFICIAL EL DÍA 02 DE MARZO DE 2021.\nPRIMERO. – Remítase el presente Decreto a la persona Titular de la Jefatura de Gobierno de la Ciudad de\nMéxico para su promulgación y publicación en la Gaceta Oficial de la Ciudad de México.\nSEGUNDO. - El presente decreto entrará en vigor al día siguiente de su publicación.\nTERCERO. – El Instituto del Deporte de la Ciudad tendrá 120 días hábiles para emitir los protocolos y hacer las adecuaciones correspondientes de la presente reforma.\n\nPalacio Legislativo del Congreso de la Ciudad de México, a los once días del mes de febrero del año dos mil veintiuno. POR LA MESA DIRECTIVA.-DIPUTADA MARGARITA SALDAÑA HERNÁNDEZ, PRESIDENTA.-\nDIPUTADA DONAJI OFELIA OLIVERA REYES, SECRETARIA.- DIPUTADO PABLO MONTES DE OCA DEL OLMO,\nSECRETARIO.- (Firmas)\nCon fundamento en lo dispuesto por los artículos 122, apartado A, fracción III de la Constitución Política de los Estados Unidos Mexicanos; 32, apartado C, numeral 1, inciso a) de la Constitución Política de la Ciudad de México; 2 párrafo segundo, 3 fracciones XVII y XVIII, 7 párrafo primero, 10 fracción II, 12 y 21 párrafo primero de la Ley Orgánica del Poder Ejecutivo y de la Administración Pública de la Ciudad de México; para su debida publicación y observancia, expido el presente Decreto Promulgatorio en la Residencia Oficial de la Jefatura de Gobierno de la Ciudad de México, al primer día del mes de marzo del año dos mil veintiuno.-\nLA JEFA DE GOBIERNO DE LA CIUDAD DE MÉXICO, DRA. CLAUDIA SHEINBAUM PARDO.- FIRMA.- LA\nSECRETARIA DE EDUCACIÓN, CIENCIA, TECNOLOGÍA E INNOVACIÓN, ROSAURA RUIZ GUTIÉRREZ.- FIRMA.\nTRANSITORIO DEL DECRETO POR EL QUE SE REFORMA EL TÍTULO DE LA LEY, EL ARTÍCULO 1, LAS\nFRACCIONES III, IV, V, VI, VII, VIII Y IX DEL ARTÍCULO 2; EL ARTÍCULO 7, EL TÍTULO DEL CAPÍTULO SEGUNDO,\nEL ARTÍCULO 8, EL ARTÍCULO 9, PÁRRAFO SEGUNDO DEL ARTÍCULO 10, EL ARTÍCULO 11; LA FRACCIÓN VII\nDEL INCISO B Y EL INCISO F DEL ARTÍCULO 12; PÁRRAFOS PRIMERO Y SEGUNDO DEL ARTÍCULO 13, EL\nARTÍCULO 14, EL ARTÍCULO 15, FRACCIONES VIII Y IX DEL ARTÍCULO 16; FRACCIONES II Y IV DEL ARTÍCULO\n17, ARTÍCULO 18, ARTÍCULO 19, PÁRRAFO PRIMERO DEL ARTÍCULO 20; FRACCIONES V, IX Y XVIII DEL\nARTÍCULO 23, ARTÍCULO 24; FRACCIONES I, II, III, VII, IX, X Y PÁRRAFOS SEGUNDO Y CUARTO DEL ARTÍCULO\n25; FRACCIONES I, II, IX, XI Y PÁRRAFO PRIMERO DE LA FRACCIÓN XII DEL ARTÍCULO 26, TÍTULO DEL\nCAPÍTULO QUINTO, EL PÁRRAFO PRIMERO Y FRACCIÓN II DEL ARTÍCULO 28, EL PÁRRAFO PRIMERO Y LA\nFRACCIÓN VIII DEL ARTÍCULO 29, EL ARTÍCULO 30, EL PÁRRAFO PRIMERO Y LAS FRACCIONES II Y V DEL\nARTÍCULO 32; INCISOS A Y B DEL ARTÍCULO 34, ARTÍCULO 37, PÁRRAFO PRIMERO DEL ARTÍCULO 39,\nPÁRRAFO PRIMERO DEL ARTÍCULO 40; INCISO C DEL ARTÍCULO 41; PÁRRAFO PRIMERO Y FRACCIÓN I DEL\nARTÍCULO 48, PÁRRAFO PRIMERO DEL ARTÍCULO 50, ARTÍCULO 51, ARTÍCULO 52; PÁRRAFO PRIMERO DEL\nARTÍCULO 56, EL ARTÍCULO 57, EL ARTÍCULO 58; EL PÁRRAFO PRIMERO Y FRACCIONES III, V, VII Y X DEL\nARTÍCULO 59, ARTÍCULO 61, ARTÍCULO 68; ARTÍCULO 69, PÁRRAFO PRIMERO DEL ARTÍCULO 70, ARTÍCULO\n73; PÁRRAFO PRIMERO DEL ARTÍCULO 74, ARTÍCULO 75, ARTÍCULO 76, ARTÍCULO 77, ARTÍCULO 78,\nARTÍCULO 79, ARTÍCULO 80, ARTÍCULO 82, ARTÍCULO 83, ARTÍCULO 88, ARTÍCULO 91, ARTÍCULO 92 Y EL\nARTÍCULO 93; SE ADICIONA UNA FRACCIÓN IX BIS AL ARTÍCULO 23, UN PÁRRAFO TERCERO AL ARTÍCULO\n56; TODOS DE LA LEY DE EDUCACIÓN FÍSICA Y DEPORTE DEL DISTRITO FEDERAL, PUBLICADO EN LA GACETA\nOFICIAL DE LA CIUDAD DE MÉXICO EL DÍA 03 DE DICIEMBRE DE 2021.\n\nPRIMERO. Remítase a la Jefatura de Gobierno para su Promulgación y Publicación en la Gaceta Oficial de la Ciudad de México.\nSEGUNDO. El presente Decreto entrará en vigor al día siguiente de su publicación en la Gaceta Oficial de la\nCiudad de México.\nPalacio Legislativo del Congreso de la Ciudad de México, a los treinta días del mes de noviembre del año dos mil veintiuno.- POR LA MESA DIRECTIVA, DIPUTADO HÉCTOR DIAZ POLANCO, PRESIDENTE, DIPUTADA\nMARCELA FUENTE CASTILLO, SECRETARIA, DIPUTADA FRIDA JIMENEZ GUILLÉN ORTIZ (Firmas)\nCon fundamento en lo dispuesto por los artículos 122, apartado A, fracción III de la Constitución Política de los Estados Unidos Mexicanos; 32, apartado C, numeral 1, inciso a) de la Constitución Política de la Ciudad de México; 2 párrafo segundo, 3 fracciones XVII y XVIII, 7 párrafo primero, 10 fracción II, 12 y 21 párrafo primero de la Ley Orgánica del Poder Ejecutivo y de la Administración Pública de la Ciudad de México; para su debida publicación y observancia, expido el presente Decreto Promulgatorio en la Residencia Oficial de la Jefatura de Gobierno de la Ciudad de México, a los dos días del mes de diciembre del año dos mil veintiuno.- LA JEFA DE GOBIERNO DE LA CIUDAD DE MÉXICO, DRA. CLAUDIA SHEINBAUM PARDO.- FIRMA.-\nEL SECRETARIO DE GOBIERNO, MARTÍ BATRES GUADARRAMA.- FIRMA.- SECRETARIA DE EDUCACIÓN,\nCIENCIA, TECNOLOGÍA E INNOVACIÓN, DRA. ROSAURA RUIZ GUTIÉRREZ.- SECRETARIO DE INCLUSIÓN Y\nBIENESTAR SOCIAL, CARLOS ALBERTO ULLOA PEREZ.- FIRMA\nTRANSITORIOS DEL SE REFORMAN LOS ARTÍCULOS 3, PÁRRAFO PRIMERO; 17, FRACCIONES V Y IX; 23,\nFRACCIONES XVIII Y XXIV; 25, SEGUNDO PÁRRAFO; 49 BIS, PÁRRAFO PRIMERO Y 64; Y SE ADICIONA LA\nFRACCIÓN XXIV BIS AL ARTÍCULO 23, TODOS DE LA LEY DE EDUCACIÓN FÍSICA Y DEPORTE DE LA CIUDAD\nDE MÉXICO; Y SE MODIFICA LA FRACCIÓN XIV Y SE ADICIONA LA FRACCIÓN XV AL ARTÍCULO 71 DE LA LEY\nORGÁNICA DE ALCALDÍAS DE LA CIUDAD DE MÉXICO, PUBLICADO EN LA GACETA OFICIAL EL 13 DE ABRIL\nDE 2022.\nPRIMERO. – Remítase el presente Decreto a la persona Titular de la Jefatura de Gobierno de la Ciudad de\nMéxico para su promulgación y publicación en la Gaceta Oficial de la Ciudad de México.\nSEGUNDO. - El presente decreto entrará en vigor al día siguiente de su publicación.\nTERCERO. – Se derogan todas aquellas disposiciones que se opongan al presente Decreto.\n\nPalacio Legislativo del Congreso de la Ciudad de México, a los quince días del mes de marzo del año dos mil veintidós. POR LA MESA DIRECTIVA, DIPUTADO HÉCTOR DIAZ POLANCO, PRESIDENTE.- DIPUTADA\nMARCELA FUENTE CASTILLO, SECRETARIA.- DIPUTADA FRIDA JIMENA GUILLÉN ORTIZ, SECRETARIA.- (Firmas)\nCon fundamento en lo dispuesto por los artículos 122, apartado A, fracción III de la Constitución Política de los Estados Unidos Mexicanos; 32, apartado C, numeral 1, inciso a) de la Constitución Política de la Ciudad de México; 2 párrafo segundo, 3 fracciones XVII y XVIII, 7 párrafo primero, 10 fracción II, 12 y 21 párrafo primero de la Ley Orgánica del Poder Ejecutivo y de la Administración Pública de la Ciudad de México; para su debida publicación y observancia, expido el presente Decreto Promulgatorio en la Residencia Oficial de la Jefatura de Gobierno de la Ciudad de México, a los doce días del mes de abril del año dos mil veintidós.-\nLA JEFA DE GOBIERNO DE LA CIUDAD DE MÉXICO, DRA. CLAUDIA SHEINBAUM PARDO.- FIRMA.- EL\nSECRETARIO DE GOBIERNO, MARTÍ BATRES GUADARRAMA.- FIRMA.- LA SECRETARIA DE EDUCACIÓN,\nCIENCIA, TECNOLOGÍA E INNOVACIÓN, ROSAURA RUIZ GUTIÉRREZ.- FIRMA.\nTRANSITORIOS DEL DECRETO POR EL QUE SE MODIFICAN LOS ARTÍCULOS 2 FRACCIÓN X; 8; 23, FRACCIÓN\nIII; 31 FRACCIONES VIII Y X; Y SE MODIFICA UNA FRACCIÓN IX TER AL ARTÍCULO 23, TODOS DE LA LEY DE\nEDUCACIÓN FÍSICA Y DEPORTE DE LA CIUDAD DE MÉXICO, PUBLICADO EN LA GACETA OFICIAL DE LA CIUDAD\nDE MÉXICO EL 15 DE MAYO DE 2023.\nPRIMERO. Remítase a la Jefatura de Gobierno de la Ciudad de México para su promulgación y publicación en la Gaceta Oficial de la Ciudad de México.\nSEGUNDO. El presente Decreto entrará en vigor al día siguiente de su publicación en la Gaceta Oficial de la\nCiudad de México.\nPalacio Legislativo del Congreso de la Ciudad de México, a los veintisiete días del mes de abril del año dos mil veintitrés.- POR LA MESA DIRECTIVA.- DIPUTADO FAUSTO MANUEL ZAMORANO ESPARZA, PRESIDENTE.-\nDIPUTADA MARCELA FUENTE CASTILLO, SECRETARIA.- DIPUTADA MARIA GABRIELA SALIDO MAGOS,\nSECRETARIA.- (Firmas)\nCon fundamento en lo dispuesto por los artículos 122, apartado A, fracción III de la Constitución Política de los Estados Unidos Mexicanos; 32, apartado C, numeral 1, inciso a) de la Constitución Política de la Ciudad de México; 2 párrafo segundo, 3 fracciones XVII y XVIII, 7 párrafo primero, 10 fracción II, 12 y 21 párrafo primero de la Ley Orgánica del Poder Ejecutivo y de la Administración Pública de la Ciudad de México; para su debida publicación y observancia, expido el presente Decreto Promulgatorio en la Residencia Oficial de\n\nla Jefatura de Gobierno de la Ciudad de México, a los doce días del mes de mayo del año dos mil veintitrés.-\nLA JEFA DE GOBIERNO DE LA CIUDAD DE MÉXICO, DRA. CLAUDIA SHEINBAUM PARDO.- FIRMA.- EL\nSECRETARIO DE GOBIERNO, MARTÍ BATRES GUADARRAMA.- FIRMA.- LA SECRETARIA DE EDUCACIÓN,\nCIENCIA, TECNOLOGÍA E INNOVACIÓN, JESÚS OFELIA ANGULO GUERRERO.- FIRMA.- EL SECRETARIO DE\nINCLUSIÓN Y BIENESTAR SOCIAL, RIGOBERTO SALGADO VÁZQUEZ.- FIRMA.\nTRANSITORIOS DEL DECRETO POR EL QUE SE ESPECIFICA LA DENOMINACIÓN DE LA LEY Y SE MODIFICA LA\nFRACCIÓN XXI DEL ARTÍCULO 23 DE LA LEY DE EDUCACIÓN FÍSICA Y DEPORTE DE LA CIUDAD DE MÉXICO,\nPUBLICADO EN LA GACETA OFICIAL DE LA CIUDAD DE MÉXICO EL 15 DE MAYO DE 2023.\nPRIMERO. Remítase a la Jefatura de Gobierno de la Ciudad de México para su promulgación y publicación en la Gaceta Oficial de la Ciudad de México.\nSEGUNDO. El presente Decreto entrará en vigor al día siguiente de su publicación en la Gaceta Oficial de la\nCiudad de México.\nPalacio Legislativo del Congreso de la Ciudad de México, a los veintisiete días del mes de abril del año dos mil veintitrés.- POR LA MESA DIRECTIVA.- DIPUTADO FAUSTO MANUEL ZAMORANO ESPARZA, PRESIDENTE.-\nDIPUTADA MARCELA FUENTE CASTILLO, SECRETARIA.- DIPUTADA MARIA GABRIELA SALIDO MAGOS,\nSECRETARIA.- (Firmas)\nCon fundamento en lo dispuesto por los artículos 122, apartado A, fracción III de la Constitución Política de los Estados Unidos Mexicanos; 32, apartado C, numeral 1, inciso a) de la Constitución Política de la Ciudad de México; 2 párrafo segundo, 3 fracciones XVII y XVIII, 7 párrafo primero, 10 fracción II, 12 y 21 párrafo primero de la Ley Orgánica del Poder Ejecutivo y de la Administración Pública de la Ciudad de México; para su debida publicación y observancia, expido el presente Decreto Promulgatorio en la Residencia Oficial de la Jefatura de Gobierno de la Ciudad de México, a los doce días del mes de mayo del año dos mil veintitrés.-\nLA JEFA DE GOBIERNO DE LA CIUDAD DE MÉXICO, DRA. CLAUDIA SHEINBAUM PARDO.- FIRMA.- EL\nSECRETARIO DE GOBIERNO, MARTÍ BATRES GUADARRAMA.- FIRMA.- LA SECRETARIA DE EDUCACIÓN,\nCIENCIA, TECNOLOGÍA E INNOVACIÓN, JESÚS OFELIA ANGULO GUERRERO.- FIRMA.",
  "ordenamiento": "Marco Jurídico",
  "jurisdiccion": "CIUDAD DE MEXICO",
  "fuente_oficial": "Congreso de la Ciudad de México",
  "status": "Vigente",
  "Fecha de Publicación": "01-06-2023",
  "Fecha de Última Reforma": "15 de mayo de 2023",
  "numero_paginas": 41,
  "es_escaneado": false,
  "tiene_tablas": false,
  "url": "https://www.congresocdmx.gob.mx/archivo-3fc3ce103074da800388fc41c9dbff8b80a119a0.pdf",
  "materia": [
    "deporte",
    "educación"
  ]
}