{
  "titulo": "Ley ORGÁNICA DE LA FISCALÍA GENERAL DE JUSTICIA DE LA CIUDAD DE MÉXICO",
  "Contenido": "PUBLICADA EN LA GACETA OFICIAL DE LA CIUDAD DE MÉXICO\nEL 24 DE DICIEMBRE DE 2019\nTEXTO VIGENTE\nÚLTIMA REFORMA PUBLICADA EN LA G.O.C.D.M.X.\nEL 23 DE AGOSTO DE 2024\nDECRETO POR EL QUE SE EXPIDE LA LEY ORGÁNICA DE LA FISCALÍA GENERAL DE JUSTICIA DE LA CIUDAD\nDE MÉXICO\nDRA. CLAUDIA SHEINBAUM PARDO, Jefa de Gobierno de la Ciudad de México, a sus habitantes sabed.\nQue el H. Congreso de la Ciudad de México I Legislatura, se ha servido dirigirme el siguiente:\nD E C R E T O\nCONGRESO DE LA CIUDAD DE MÉXICO\nI LEGISLATURA\nEL CONGRESO DE LA CIUDAD DE MÉXICO, DECRETA:\nSE EXPIDE LA LEY ORGÁNICA DE LA FISCALÍA GENERAL DE JUSTICIA DE LA CIUDAD DE MÉXICO.\nDECRETO\nDECRETO POR EL QUE SE EXPIDE LA LEY ORGÁNICA DE LA FISCALÍA GENERAL DE JUSTICIA DE LA CIUDAD\nDE MÉXICO\nArtículo único. Se expide la Ley Orgánica de la Fiscalía General de Justicia de la Ciudad de México.\nPara quedar como sigue:\n\nDE LA CIUDAD DE MÉXICO\nTÍTULO PRIMERO\nDISPOSICIONES GENERALES\nCAPÍTULO PRIMERO\nOBJETO, NATURALEZA Y PRINCIPIOS\nArtículo 1. Objeto de la Ley\nLa presente Ley es de orden público, observancia general y tiene por objeto:\nI. La organización de la Fiscalía General de Justicia de la Ciudad de México, encargada de la investigación y persecución de los delitos de su competencia a través del Ministerio Público, de conformidad con lo establecido en la Constitución Política de los Estados Unidos Mexicanos, la\nConstitución Política de la Ciudad de México, el Código Nacional de Procedimientos Penales, el\nCódigo Penal para el Distrito Federal, así como los Tratados Internacionales en que México, sea parte y las demás normas aplicables;\nII. Establecer los lineamientos y principios de la conducción de la investigación de los delitos que se cometan en la Ciudad de México, y resolver consecuentemente sobre el ejercicio de la acción penal, o sobre la facultad de abstenerse de investigar, en términos del artículo 253 y demás relativos aplicables del Código Nacional, entre otras que le han sido conferidas legalmente;\nIII. Indicar la Actuación y permanencia de los servidores públicos, de dicha Fiscalía, incluyendo su capacitación permanente;\nIV. Regular la estructura orgánica, facultades y funcionamiento de la Fiscalía General de Justicia de la Ciudad de México.\nArtículo 2. Naturaleza Jurídica.\nLa Fiscalía General de la Ciudad de México, es un organismo público constitucional autónomo, de carácter especializado e imparcial, con personalidad jurídica y patrimonio propio, con autonomía técnica,\n\npresupuestal, y de gestión plena. Estará encabezada por una persona designada como Fiscal General, sobre quien recae la rectoría y conducción de la Institución del Ministerio Público.\nLa Fiscalía General contará para la debida conducción de la investigación y ejercicio de la acción penal, con fiscales de investigación y acusación, coordinará a la policía de investigación, técnica y científica, a los servicios periciales para los efectos de determinar la existencia del delito y la responsabilidad de quien lo ha cometido.\nArtículo 3. Independencia Técnica\nLa persona Fiscal General así como el personal competente de la Fiscalía General, que dirigirá la investigación, perseguirá el delito y ejercitará acción penal con legalidad, independencia, imparcialidad y autonomía, libres de cualquier tipo de coacción o de interferencia ajena a su actuar y con apego a las leyes.\nEn el ejercicio de sus funciones, se conducirán conforme al criterio de objetividad, con base en el cual dirigirán la investigación de los hechos y circunstancias que prueben, eximan o atenúen la responsabilidad de las personas imputadas, bajo los principios que rigen el sistema acusatorio en la Ciudad de México.\nArtículo 4. Competencia\nLa Fiscalía General tiene como competencia investigar los delitos del orden común cometidos en la Ciudad de México, de acuerdo a lo establecido en la Constitución Local, Código Penal, la presente ley y demás leyes que resulten aplicables. Así como todo lo relativo al ejercicio de la acción penal o a la abstención de investigación de dichos delitos.\nSe mantendrá una coordinación permanente con la Fiscalía General de la República, para aquellos casos en que se requiera ejercer la facultad de atracción en los términos establecidos por las leyes aplicables.\nArtículo 5. Glosario\nPara efectos de la presente ley se entenderá por:\nI. Centro: al Centro de Evaluación y Control de Confianza de la Fiscalía General del Ciudad de\nMéxico;\nII. Código Nacional: al Código Nacional de Procedimientos Penales;\n\nIII. Código Penal: al Código Penal para el Distrito Federal;\nIV. Constitución Federal: a la Constitución Política de los Estados Unidos Mexicanos;\nV. Constitución Local: a la Constitución Política del Ciudad de México;\nVI. Consejo de Asuntos Internos: al Órgano Colegiado denominado Consejo de Asuntos Internos de la Fiscalía General de Justicia de la Ciudad de México;\nVII. Consejo Ciudadano: al Consejo Ciudadano de la Fiscalía General de Justicia de la Ciudad de\nMéxico;\nVIII. Consejo Judicial: al Consejo Judicial Ciudadano;\nIX. Criterios de Oportunidad: a los señalados en el artículo 256 del Código Nacional, a excepción de la violencia familiar, delitos fiscales, sexuales y aquellos que afecten gravemente el interés público.\nX. Estado de riesgo: a la probabilidad de un ataque social, sexual, delictivo individual o colectivo, a partir de la construcción social de desigualdad y discriminación;\nXI. Fiscal General: a la persona Titular de la Fiscalía General de Justicia de la Ciudad de México;\nXII. Fiscalía General: al organismo constitucional autónomo denominado Fiscalía General de\nJusticia de la Ciudad de México;\nXIII. Igualdad Sustantiva: a la igualdad distributiva, que analiza las desigualdades para construir la igualdad, bajo la premisa de que no se trata igual a desiguales;\nXIV. Ley: a Ley Orgánica de la Fiscalía General de Justicia de la Ciudad de México;\nXV. Ley General del Sistema: a la Ley General del Sistema Nacional de Seguridad Pública;\nXVI. Modelo: al modelo de Procuración de Justicia para la conducción de la investigación y acusación de los delitos, así como de operación de la Fiscalía;\n\nXVII. Plan: al Plan de Política Criminal;\nXVIII. Perspectiva de género: a la visión científica y analítica sobre las construcciones políticas, jurídicas, sociales, psicológicas y culturales que se articulan entre mujeres y hombres. Se propone eliminar las causas de opresión respecto al género, como la desigualdad, la injusticia y la jerarquización de las personas basada en el género. Promueve la igualdad entre los géneros, la igualdad de derechos y oportunidades;\nXIX. Personal Sustantivo: a los Fiscales, Peritos y Policías de Investigación, Técnica y Científica que se encuentran sujetos al Servicio Profesional de Carrera de la Fiscalía General de Justicia;\nXX. Protocolo: al procedimiento por medio del cual se estandariza la acción del Personal\nSustantivo, pudiendo existir según sea el caso protocolos de coordinación, investigación, facultativos, atención y actuación;\nXXI. Policía de Investigación: a las personas integrantes del cuerpo de Policía de Investigación del Delito de la Fiscalía General:\nXXII. Policía Técnica y Científica: a la policía especializada;\nXXIII. Perito: a las personas integrantes de los Cuerpos de Investigación Técnica y Científica de la\nFiscalía General;\nXXIV. Reglamento: al El Reglamento de la Ley Orgánica de la Fiscalía General de Justicia de la\nCiudad de México;\nXXV. Servicio Profesional: al Servicio Profesional de Carrera de la Fiscalía General.\nArtículo 6. Principios Rectores de Actuación\nLa Fiscalía regirá su actuación por los principios de autonomía, legalidad, objetividad, eficiencia, profesionalismo, transparencia, inmediatez, honradez, respeto a los Derechos Humanos, accesibilidad, debida diligencia, imparcialidad, interculturalidad, perspectiva de género, igualdad sustantiva, inclusión, accesibilidad, interés superior de niñas, niños y adolescentes, diseño universal, etaria, no discriminación, el debido proceso y sustentabilidad.\n\nArtículo 7. Rectoría de Derechos Humanos, No Discriminación e Igualdad Sustantiva.\nEn el ejercicio de sus atribuciones, todas las personas servidoras públicas de la Fiscalía General, deberán conforme al artículo 1o. de la Constitución Federal, promover, respetar, proteger y garantizar los Derechos\nHumanos, de conformidad con los siguientes lineamientos y demás que se dispongan en la normatividad aplicable, por lo que:\nI. Otorgará la protección más amplia y efectiva de los Derechos Humanos a las personas, para lo cual implementará, durante la investigación de los delitos y las etapas del proceso penal, los enfoques diferenciados, especializados e interseccionales.\nII. Operará bajo el Principio de Igualdad y Derecho a la No Discriminación, el cual será considerado en razón de la condición étnica, migratoria, de género, edad, discapacidad, condición social, salud, religión, opiniones, preferencia, orientación o identidad sexual, estado civil o cualquier otra condición o motivo que atente contra la dignidad humana, o bien, tenga por objeto anular o menoscabar los derechos y libertades de las personas.\nIII. Garantizará la atención prioritaria para el pleno ejercicio de los derechos de las personas, que debido a la desigualdad estructural enfrentan algún tipo de discriminación, exclusión, maltrato, abuso, violencia y mayores obstáculos para el pleno ejercicio de sus derechos y libertades fundamentales. En consecuencia, se reconoce que ciertos grupos requieren de una atención especializada que responda a las particularidades de su situación.\nIV. Se removerán progresivamente los obstáculos que impidan el acceso real y efectivo de las víctimas a las medidas reguladas por la presente Ley, para realizar prioritariamente acciones encaminadas al fortalecimiento de sus derechos, contribuir a su recuperación como sujetos en ejercicio pleno de sus derechos y deberes, así como evaluar permanentemente el impacto de las acciones que se implementen a su favor.\nArtículo 8. Criterios de Interpretación\nLas disposiciones de esta Ley se interpretarán, bajo el principio pro persona, conforme a los principios de la Constitución Federal, Constitución Local, Tratados e instrumentos Internacionales, celebrados en materia de Derechos Humanos y ratificados por el Estado Mexicano, las sentencias de la Corte Interamericana de\nDerechos Humanos, así como por el Código Nacional.\n\nCAPÍTULO SEGUNDO\nFINES, PUBLICIDAD Y TRANSPARENCIA\nArtículo 9. Fines Institucionales\nEl Ministerio Público de la Ciudad de México se organizará en una Fiscalía General y tiene como fines:\nI. Conducir y coordinar la investigación, así como, resolver sobre el ejercicio de la acción penal sobre los delitos materia de su competencia;\nII. Otorgar una procuración de justicia eficaz, efectiva, apegada a derecho, que contribuya a combatir la inseguridad y disminuirla;\nIII. Fortalecer el Estado de Derecho de la Ciudad de México;\nIV. Colaborar con las autoridades Federales y Locales en materia de seguridad y procuración de justicia, así como para la prevención del delito;\nV. Salvaguardar al inocente, procurando que el culpable no quede impune;\nVI. Promover, proteger, respetar y garantizar los derechos de verificación de los hechos, revelación pública y completa de la verdad, justicia, reparación integral del daño, de asistencia en todas las etapas y de garantía de no repetición a favor de las víctimas así como de la sociedad;\nVII. Proteger los derechos de las víctimas, a efecto de que cuenten con una justicia real que garantice el derecho a la verdad, mediante los protocolos necesarios;\nVIII. Facilitar la participación ciudadana en el diseño de las políticas públicas en materia de procuración de justicia; y\nIX. Proponer la política criminal y el plan correspondiente en el ámbito local.\n\nArtículo 10. Publicidad y Transparencia.\nLa Fiscalía General garantizará el acceso a la información pública generada en el marco de sus atribuciones, conforme a lo establecido en la Ley de la materia, y demás normatividad aplicable, estableciendo la Unidad de Estadística y Trasparencia.\nRespecto a las investigaciones relacionadas con las violaciones a los Derechos Humanos, se estará a lo dispuesto por el artículo 5 de la Ley General de Transparencia y Acceso a la Información Púbica.\nArtículo 11. Mandato o Solicitud de Colaboración.\nLos órganos a cargo de la función de procuración de justicia y de investigación, podrán solicitar la colaboración de cualquier autoridad, para la práctica de un acto de investigación o procedimental, siempre que dicha solicitud sea realizada de manera fundada y motivada.\nLos actos de colaboración entre la Fiscalía General con autoridades federales, estatales y municipales, se realizará de conformidad, con lo previsto en los artículos 21 y 102 A de la Constitución, en el Capítulo IV del Título III del Código Nacional, la presente Ley, así como en las disposiciones contenidas en otras normas y convenios de colaboración que se hayan emitido o suscrito.\nLa Fiscalía General para el cumplimiento de su objeto, no podrá ser impedida ni coartada en el ejercicio de sus facultades por ninguna autoridad; la población en general y entidades públicas y privadas, deberán prestarle la colaboración que le solicite cuando sean requeridos para ello.\nTÍTULO SEGUNDO\nMODELO DE PROCURACIÓN DE JUSTICIA\nCAPÍTULO PRIMERO\nDISPOSICIONES GENERALES\nArtículo 12. Modelo de Procuración de Justicia\nLa Fiscalía General establecerá un Modelo de Procuración de Justicia, cuyos componentes atenderán el combate a la corrupción institucional; atención centrada en los Derechos Humanos de las personas;\ndiversificación de canales de recepción de denuncias, querellas y reducción significativa de tiempos de\n\natención; despliegue territorial estratégico; segmentación de casos; impulso de la justicia restaurativa para atender delitos de bajo impacto; resultados en delitos complejos; mejora de infraestructura y capacidades del personal; profesionalización de la gestión institucional y control interno.\nArtículo 13. Lineamientos para la Operación de la Investigación\nPara los efectos de fortalecer las capacidades de investigación del delito, y la debida persecución de estos se establecen los siguientes lineamientos operativos:\nI. Contar con un sistema de diversificación en la recepción de denuncias, empleando tecnologías y plataformas electrónicas para los delitos de bajo y alto impacto según corresponda;\nII. Establecer un manejo de flujo de casos eficiente;\nIII. Contar con Protocolos de investigación para cada delito de alto impacto o de necesidad de investigación estratégica, así como de los que afecten a la sociedad como son los de violencia familiar y sexual;\nIV. Contar con sistema de carpetas de investigación digital, que registre y asigne a cada carpeta al Ministerio público y Policía de Investigación que tenga conocimiento, y que no se descargará del mismo hasta en tanto no concluya la investigación;\nV. Establecer las unidades operativas para la recepción de las denuncias, la conducción de la investigación, acusación, protección y asistencia a víctimas, entre otras;\nVI. Señalar los mecanismos alternativos de solución de controversias, en términos de lo que establece el Código Nacional en su artículo 187 y demás relativos, aplicables a excepción de los delitos de violencia familiar y los delitos de carácter sexual;\nVII. Determinar el despliegue estratégico que sea necesario;\nVIII. Instituir una profesionalización de la gestión institucional, así como de Ministerios Públicos,\nPeritos y Policía de Investigación, Técnica y Científica, entre otros.\nArtículo 14. Unidades Operativas\n\nPara la debida operación del modelo La Fiscalía General establecerá diversas Unidades Operativas, con el número de las personas servidoras que se consideren necesarios de acuerdo con su misión.\nI. Unidades de Atención Temprana;\nII. Unidades de Investigación con Detenido;\nIII. Unidad de Investigación de delitos de personas servidoras públicas;\nIV. Unidades de Análisis Criminal;\nV. Unidades de Análisis Estratégico y de Contexto;\nVI. Unidad de Análisis y Contexto de los Delitos de Género\nVII. Unidades de Análisis Criminalístico, Criminógeno y Criminológico;\nVIII. Unidades de Protección y Asistencia a Víctimas;\nIX. Unidades de Investigación de Violencia Familiar;\nX. Unidades de Investigación y Litigación;\nXI. Unidades de Acusación y Judicialización;\nXII. Unidades de Gestión Administrativa; para casos de Orientación Jurídica que no constituyan delito;\nXIII. Unidades Criminalísticas de Proximidad (UCP);\nXIV. Unidades de Responsabilidad Penal de las Empresas.\nXV. Unidades\nXVI. Mecanismos Alternativos de Solución de Controversias (MASC)\n\nLas funciones, atribuciones y adscripción de las Unidades antes señaladas estarán en el reglamento de la\nLey.\nArtículo 15. Recepción Inicial de Denuncia o Querella.\nPara los efectos del artículo anterior y con independencia de lo que señale el reglamento de la Ley, el\nMinisterio Público recibirá la denuncia o querella pudiendo ser auxiliado por las o los oficiales secretarios con que cuente para su sistematización, procediendo sin dilación a conocer el hecho denunciado, explicar a la víctima los alcances y procedimiento respecto a su denuncia o querella, y en su caso proceder a la derivación de conformidad con la segmentación de casos; en ningún supuesto se solicitará la ratificación de la misma.\nLas denuncias o querellas podrán ser presentadas de manera oral, escrita o a través de medios digitales, electrónicos o de cualquier otra tecnología; sin necesidad de ratificación por parte del denunciante o querellante.\nDurante todo el procedimiento penal podrán utilizarse medios digitales, electrónicos o de cualquier otra tecnología para facilitar su operación, de acuerdo con las reglas particulares que al efecto establezca la ley,\nCódigo Penal, Código Nacional, y demás leyes aplicables en la materia.\nArtículo 16. Sistema de Recepción de Denuncias: Derivaciones y Segmentación de Casos\nLa recepción de denuncias y segmentación de casos se sujetará a lo siguiente:\nI. Recibir y canalizar los casos a los órganos competentes de la Fiscalía General para su conocimiento, investigación o tramitación con base en el Programa de Persecución Penal;\nII. Canalizar los casos y asuntos que no son competencia de la Fiscalía General a las autoridades competentes;\nIII. Orientar y canalizar a todas las víctimas a los órganos y autoridades competentes para su protección y asistencia.\nPara dar cumplimiento a lo dispuesto en el sistema de recepción de denuncias, se crearán unidades o equipos de investigación y litigación de acuerdo a lo que señale el Reglamento.\n\nArtículo 17. Unidades de Investigación y Litigio\nLas Unidades de Investigación y Litigio serán órganos compuestos por equipos, que tienen como función organizar y gestionar la estrategia político criminal y procesal de la Fiscalía General establecida en el\nPrograma de Persecución Penal, para concretar los fines generales del proceso que son la búsqueda de la verdad y el acceso a la justicia, mediante la libre obtención de prueba racional. Estarán dirigidas por fiscales y se integrarán por los equipos de investigación necesarios para su adecuado funcionamiento.\nArtículo 18. Equipos de Investigación y Litigio\nLos Equipos de Investigación serán los grupos encargados del desarrollo de las investigaciones a cargo de la Policía y los Peritos, que harán entrega de los resultados de la investigación criminal a los Fiscales, para la preparación del ejercicio de la acción penal y, en su caso, la determinación que corresponda.\nArtículo 19. Equipos Multidisciplinarios de Investigación y Litigación\nEl Titular de la Fiscalía General podrá conformar equipos mixtos de investigación con integrantes de distintas unidades y coordinaciones, así como, dentro de los esquemas de colaboración institucional, con personal de otras Fiscalías o Procuradurías de las Entidades Federativas, para el desarrollo de investigaciones y el ejercicio de la acción penal en el ámbito de sus competencias, cuando exista concurrencia de delitos, de fenómenos delictivos o para fines orientados al cumplimiento del Plan de\nPolítica Criminal. En todos los casos se cuidará la integridad y no fragmentación de las investigaciones.\nArtículo 20. Unidades de Análisis Estratégico y de Contexto\nLas Fiscalías Especializadas contarán con las Unidades de Análisis Estratégico y de Contexto para el cumplimiento de sus funciones y del Programa de Persecución Penal, las cuales tendrán, entre otros, los siguientes objetivos:\nI. La identificación de patrones de actuación reiterada, seriales, sistemática o generalizada sobre ciertas estructuras o fenómenos criminales;\nII. La identificación de niveles y tipos de responsabilidad o de los partícipes de los hechos delictivos, incluyendo servidores públicos;\n\nIII. La identificación de niveles de responsabilidad de estructuras delincuenciales o paralelas al\nEstado;\nIV. La identificación de aspectos multifactoriales y multidelictivos de los fenómenos criminales.\nEstas Unidades actuarán coordinadamente con el Ministerio Público y serán integradas por analistas, técnicos y expertos en las materias de su competencia.\nArtículo 21. Operación Territorial Estratégica\nEl despliegue territorial de la operación sustantiva del Ministerio Público se llevará a cabo a través de\nUnidades o Equipos de Investigación y Litigación, cuya distribución, tamaño, recursos y temporalidad se establecerán en el Plan de Política Criminal de la Fiscalía General.\nLas unidades o equipos deberán estar integrados por el personal necesario para ejercer la función de investigación dentro del ámbito territorial y por el tiempo que hubieren sido establecidos por las Fiscalías o Coordinaciones conforme al Programa de Persecución Penal.\nLas unidades o equipos desplegados se desintegrarán al cumplirse el objetivo establecido, debiendo reubicar al personal en otras Unidades o Equipos de Investigación y Litigación.\nArtículo 22. Criterios para el Despliegue Territorial\nLa distribución territorial de las unidades o equipos de investigación y litigación se definirán conforme a cualquiera de los siguientes criterios:\nI. La atención específica de fenómenos criminales para una o varias alcaldías;\nII. El despliegue territorial de la policía de investigación y peritos, atendiendo a la priorización de delitos que marque el programa de persecución penal;\nIII. La regionalización y coordinación en materia de procuración de justicia con las Instituciones\nPoliciales y otras Fiscalías;\nIV. El enfoque diferenciado, incluyendo el de género en la respuesta al fenómeno delictivo; y\n\nV. El acceso a la justicia para grupos de atención prioritaria.\nArtículo 23. Delitos Complejos\nSe consideran delitos complejos aquellos en los que, de acuerdo a las características del hecho o hechos con apariencia de delito, sea determinante para el esclarecimiento de la verdad, considerar la incidencia de las siguientes circunstancias:\nI. Gravedad de la lesión a los bienes jurídicamente tutelados;\nII. Aplicación de Protocolos de Investigación;\nIII. Concurso o conexidad de delitos;\nIV. Realizar una investigación compleja;\nV. Aplicación de técnicas de investigación especiales o con control judicial;\nVI. Que el hecho con apariencia de delito provenga necesariamente de diverso ilícito penal;\nVII. La participación de personas servidoras públicas en el hecho, excepto si se trata de actos de corrupción;\nVIII. La puesta en riesgo del ejercicio de una función pública o de un ente público;\nIX. Prevenir violaciones graves a Derechos Humanos;\nX. Situación de riesgo o vulnerabilidad estructural de las víctimas;\nXI. Generen situaciones de alto impacto.\nLa persona Titular de la Fiscalía General, establecerá en el Plan de Política Criminal los lineamientos bajo los cuales las investigaciones deberán ser conocidas por la Fiscalía de Delitos Complejos.\n\nArtículo 24. Nuevas Tecnologías\nLa Fiscalía General, promoverá el uso estandarizado de las tecnologías de la información y comunicaciones, compatibles con cualquier medio o dispositivo electrónico, para satisfacer el cumplimiento de los componentes, establecidos en el artículo que antecede.\nCAPÍTULO SEGUNDO\nDE LA PROTECCIÓN\nArtículo 25. Responsabilidad de los Órganos de la Fiscalía General respecto a las Víctimas.\nEn toda investigación y proceso penal los Órganos de la Fiscalía General deberán garantizar los derechos de las víctimas establecidos en la Constitución Federal y en la Constitución Local, así como en Tratados e\nInstrumentos Internacionales ratificados por el Estado Mexicano, llevando a cabo las siguientes funciones:\nI. Coordinar con las víctimas, sus representantes y organizaciones de la sociedad civil que las asesoran, los planes de investigación y la práctica de actos de investigación específicos que las involucren, en los términos de las normas aplicables;\nII. Desarrollar investigaciones completas, exhaustivas con perspectiva de género e igualdad sustantiva. Respetando el enfoque, diferencial y especializado en las investigaciones y determinaciones de acuerdo a las condiciones específicas de las víctimas, además de garantizar y proteger los derechos de estas y de las imputadas de un delito;\nIII. Proporcionar de forma clara y permanente a las víctimas, a sus representantes y asesores, información sobre sus derechos, sobre el estado que guardan las investigaciones y sobre los actos de investigación previstos y programados, garantizando su participación en las diligencias que correspondan;\nIV. Proporcionar los registros de investigación y copias solicitadas por las víctimas y sus representantes, con relación a las investigaciones;\nV. Proteger, garantizar y respetar el derecho de las víctimas y sus representantes, a presentar peritajes independientes;\n\nVI. Garantizar que en las audiencias de vinculación la victima acuda, para los efectos de los acuerdos reparatorios y planes de reparación, con el dictamen que acredite el daño material y moral, así como su debida cuantificación;\nVII. Proteger y asistir de inmediato a las víctimas en situaciones de crisis con el apoyo y auxilio de otras entidades Públicas o Privadas con las que tenga convenios de colaboración o coordinación, de conformidad con la presente Ley y demás aplicables;\nVIII. Las demás que señalen otras disposiciones aplicables.\nConsiderando de manera indicativa las disposiciones que establece el Protocolo para Juzgar con\nPerspectiva de Género de la Suprema Corte de Justicia de la Nación.\nArtículo 26. Medidas de Protección\nLos Órganos de Procuración de Justicia, en el ámbito de sus respectivas competencias, establecerán garantías especiales y medidas de protección a los grupos expuestos a un mayor riesgo de violación de sus derechos, motivada por origen étnico o nacional, apariencia física, color de piel, lengua, género, edad, discapacidades, condición social, situación migratoria, condiciones de salud, embarazo, religión, opiniones, preferencia sexual, orientación sexual, identidad de género, expresión de género, características sexuales, estado civil o cualquier otra.\nLa Fiscalía General, adoptará medidas que respondan a la atención de dichas particularidades, grado y cruces de condición de riesgo que las pongan en situación de vulnerabilidad, reconociendo los daños sufridos por su gravedad que requieran de un tratamiento especializado para dar respuesta a su rehabilitación y reintegración a la sociedad.\nPor lo que en casos de delitos relacionados con violencia de género, se deberá de considerar las medidas de protección que establece el artículo 137 del Código Nacional de Procedimientos Penales, en concordancia con la Ley General de Acceso de las Mujeres a una Vida Libre de Violencia, La Ley de Acceso de las Mujeres a una vida Libre de Violencia de la Ciudad de México, así como el Protocolo conducente.\n\nCAPÍTULO TERCERO\nDEL PLAN DE POLÍTICA CRIMINAL\nArtículo 27. Plan de Política Criminal\nLa Fiscalía General, contará para el desarrollo de sus funciones y dar respuesta a las conductas consideradas como delitos con un Plan de Política Criminal anual.\nPara los efectos anteriores, la persona Fiscal General al inicio de su gestión definirá el Plan de Política\nCriminal en materia de procuración de justicia, y de este desglosará el Programa de Persecución Penal, que presentará ante el Congreso de la Ciudad de México, en los plazos establecidos en la Constitución Local y deberá ser producto de un amplio consenso social.\nEste deberá presentarse cada año, públicamente, junto con los avances en la ejecución de los programas del Plan de Política Criminal que contenga y, en su caso, las modificaciones al mismo.\nLa Fiscalía General, a través del Órgano de Política Criminal, en colaboración con la Coordinación General\nJurídica, elaborará dicho Plan de Política Criminal que orientará las atribuciones de la Institución del\nMinisterio Público.\nEl plan de Política Criminal definirá los fines generales y específicos de la procuración de justicia en la\nCiudad de México, junto con los programas y estrategias político criminales dirigidas a instalar las capacidades institucionales necesarias para el adecuado funcionamiento del procedimiento.\nArtículo 28. Determinación del Plan de Política Criminal\nSu elaboración se realizará, desde una visión metropolitana, con un diagnóstico de la criminalidad, la calidad del trabajo del Ministerio Público y criterios sobre los delitos que se atenderán de manera prioritaria, estableciendo una exposición sistemática, ordenada de fines generales y específicos, programas y estrategias político criminales dirigidas a instaurar las capacidades institucionales necesarias, para el adecuado funcionamiento del procedimiento penal acusatorio, desde la perspectiva de la procuración de justicia y medios multidisciplinarios.\nPara el cumplimiento de los fines institucionales, dicho plan además contemplará entre otros programas, el que desarrolle el modelo de procuración de justicia, la normatividad complementaria que requiera la operatividad de la procuración de justicia en el nuevo contexto del Sistema Penal Acusatorio, el programa\n\nrelativo al presupuesto, infraestructura, recursos financieros, materiales y humanos; el que contemple la capacitación, especialización y servicio profesional de carrera, los programas de coordinación interinstitucional y estadística criminal, los referentes a las metas e indicadores de gestión de la institución del Ministerio Público y, un programa de seguimiento, monitoreo y evaluación interna que se instale en la\nFiscalía.\nArtículo 29. Contenido del Plan de Política Criminal\nI. Un diagnóstico de la criminalidad, mapeo, análisis y estrategia de priorización de los fenómenos criminales que perseguirá, divididos en criminalidad común y criminalidad compleja y emergente, desde el enfoque que considere las siguientes características: el alto impacto social, el riesgo de vulnerabilidad de las víctimas, las violaciones graves de Derechos Humanos y los delitos por hechos de corrupción, entre otros;\nII. La calidad del trabajo del Ministerio Público y su capacidad de judicialización;\nIII. Criterios de atención a los delitos de manera prioritaria con el modelo de procuración de justicia que comprenda una gestión profesional y trato diferenciado a las denuncias, su segmentación y derivación para el esclarecimiento de los hechos o la solución del conflicto penal, la continuación de los casos en el litigio oral y su terminación por el uso prioritario de salidas alternas o la terminación anticipada del proceso penal;\nIV. Una metodología para la evaluación de resultados por áreas del servicio de procuración de justicia, que abarque un año y se confronte con el presupuesto otorgado para el funcionamiento de las áreas;\nV. La aplicación de los criterios de oportunidad en los supuestos delictivos más recurrentes en la\nCiudad de México;\nVI. Metas de desempeño;\nVII. Un Programa de Persecución Penal, el cual se emitirá en los términos que determine el\nReglamento de la Ley, dicha persecución penal con los modelos de investigación científica del delito en casos específicos de micro y macro-criminalidad; a partir del trabajo interdisciplinario de Policías y Peritos;\n\nVIII. Una Estrategia específica para la selección de personal con un perfil óptimo, que integre los grupos de fiscales especializados de litigio oral y de ejecución penal de sanciones, con el acompañamiento de expertos en algunas disciplinas que respalden el trabajo procesal de los fiscales durante las diversas etapas del procedimiento penal;\nIX. Análisis de presupuestos por programas que incluya la persecución penal inteligente; la aplicación de mecanismos alternativos de solución de conflictos, la resolución de casos por las unidades de análisis criminalístico, criminógeno y criminológico, los asuntos sometidos a los tribunales, priorizando salidas alternas y terminación anticipada del proceso penal, así como, las sentencias condenatorias donde las víctimas lleguen a obtener la reparación integral del daño causado;\nX. Los programas que anualmente se determinen como prioritarios.\nLos programas buscarán el desarrollo sostenido del diseño institucional, la definición de los procesos, su incorporación a plataformas tecnológicas, mediante la utilización de protocolos de actuación mínima y, el uso de registros para la integración de la carpeta de investigación electrónica.\nArtículo 30. Programa de Persecución Penal\nLa persona Titular de la Fiscalía General, al definir el Plan de Política Criminal en materia de procuración de justicia, establecerá el Programa de Persecución Penal que presentará ante el Congreso de la Ciudad de\nMéxico.\nArtículo 31. Objetivos del Programa de Persecución Penal\nEl programa de persecución penal, tendrá como objetivos.\nI. Elevar los controles actuación Ministerial;\nII. El tratamiento que recibirá cada denuncia según el delito;\nIII. La factibilidad de las investigaciones delictivas y la calidad de los datos, medios y las pruebas aportadas al proceso penal;\nIV. La trazabilidad de la investigación;\n\nV. La revisión del índice delictivo y la actuación en consecuencia.\nArtículo 32. Integración del Programa de Persecución Penal\nEl programa deberá establecer los siguientes aspectos desglosados con metas a corto, mediano y largo plazo, así como definición de objetivos, estrategias, acciones, metas e indicadores de resultados:\nI. La priorización de casos en la persecución de los delitos;\nII. El despliegue de mecanismos alternativos y los programas o políticas de asistencia a víctimas;\nIII. El análisis de la situación de la incidencia delictiva relacionada con los fenómenos criminales para generar planes de investigación policial y pericial eficaces;\nIV. La orientación de los recursos humanos, materiales y financieros;\nV. La estrategia de despliegue territorial y la emisión de lineamientos operativos para la función de procuración de justicia, entre otros;\nVI. El despliegue territorial de los Policías, Peritos y Fiscales, para lograr la desconcentración operativa estratégica atendiendo a la incidencia delictiva regional de contexto y de las particularidades del fenómeno criminal.\nEl Programa de Persecución Penal, además de los elementos del modelo de procuración de justicia, desarrollará una estrategia diferenciada de recepción de denuncias, con un programa especial para la atención a las víctimas de delitos de alto impacto, desde la recepción de la denuncia hasta la terminación del proceso.\nTIÍTULO TERCERO\nDE LAS FACULTADES Y ATRIBUCIONES\nCAPÍTULO PRIMERO\nCOMPETENCIA Y FACULTADES DE LA FISCALÍA GENERAL Y DEL\nMINISTERIO PÚBLICO\n\nArtículo 33. De conformidad con el principio de indivisibilidad del Ministerio Público las facultades, las ejercerá la persona Titular de la Fiscalía por sí, o a través de las Coordinaciones Generales, Fiscalías\nEspecializadas, Órganos, Supervisiones Generales, Fiscalías, Fiscales o Agentes del Ministerio Público y\nUnidades Operativas y Administrativas competentes, salvo aquéllas que por su naturaleza, sean de ejercicio exclusivo.\nEl Reglamento de esta Ley, señalará la distribución de competencias de las Autoridades Ministeriales y de las Unidades Administrativas y Órganos de la Fiscalía, así como, las facultades delegables e indelegables de la persona titular.\nArtículo 34. Órganos a cargo de la Procuración de Justicia.\nLa Institución del Ministerio Público en la Ciudad de México a cargo de la Fiscalía General, buscará en todas sus actuaciones el beneficio del interés general, teniendo en el centro de sus fines a las personas.\nLa representación de la Fiscalía General de la Ciudad de México, en la conducción legal de la investigación y en el ejercicio de la acción penal, corresponde a los siguientes Órganos:\nI. La Fiscalía General;\nII. La Fiscalía Especializada en Atención de Delitos Electorales;\nIII. La Fiscalía Especializada en Combate a la Corrupción;\nIV. Las Coordinaciones Generales;\nV. La Policía de Investigación, Técnica y Científica;\nVI. Las Fiscalías especializadas para la investigación de delitos complejos que determine la persona titular de la Fiscalía General y\nVII. Los y Las Fiscales nombrados de acuerdo con la presente Ley y su Reglamento, conforme a las necesidades que determine el Plan de Política Criminal.\nEl Reglamento de esta Ley, definirá los grados de la carrera policial, de la Policía de investigación, Técnica y Científica.\n\nArtículo 35. Facultades y Atribuciones de la Persona Titular de la Fiscalía General\nLa persona Titular de la Fiscalía General, para el debido cumplimiento de su encargo tendrá las siguientes facultades y atribuciones en forma exclusiva:\nI. Dirigir la investigación de los hechos constitutivos de delito, los que determinen la participación punible y los que acrediten la inocencia de persona imputada;\nII. Implementar la adopción de medidas para proteger a las víctimas y a los testigos, en términos del artículo 137 del Código Nacional de Procedimientos Penales;\nIII. Establecer un Plan de Política Criminal con un Programa de Persecución Penal, que le permitan gestionar, de manera estratégica los delitos del fuero común; aquellos en los que, por disposición de las leyes generales, exista competencia concurrente, así como federales cuando lo determine la ley;\nIV. Interponer las Acciones de Inconstitucionalidad en términos el artículo 36 Apartado C de la\nConstitución Local;\nV. Crear mecanismos institucionales de coordinación para ordenar las diligencias pertinentes y útiles para esclarecer los hechos que pudieran ser constitutivos de un delito;\nVI. Emitir el Reglamento de esta Ley;\nVII. Establecer mediante Reglamento o acuerdo, los órganos colegiados, grupos técnicos, grupos especializados, comités de análisis y evaluación, comités de trabajo, unidades administrativas, unidades operativas, especiales, fiscalías, centros, y dictar las medidas, registros, protocolos y controles para gestionar y normar las facultades conferidas al Ministerio Público de la Ciudad de\nMéxico;\nVIII. Crear una Unidad Interna de Estadística y Transparencia, que garantice la publicación oportuna de información, de conformidad con esta ley;\nIX. Expedir reglas para la administración eficiente de los recursos materiales y humanos de la institución y ejercer las facultades administrativas, fiscales y hacendarias que señalen las leyes;\n\nX. Instituir mecanismos de asistencia con las instituciones de seguridad ciudadana, en las formas y modalidades que establezca la ley para la colaboración y autorización de sus actuaciones;\nXI. Establecer un servicio profesional de carrera, con reglas para la selección, ingreso, formación, promoción y permanencia de las personas servidoras públicas, con arreglo a la Ley;\nXII. Emitir las reglas conforme a las cuales sistematizará la información bajo su resguardo, acorde a los lineamientos establecidos en la ley respectiva;\nXIII. Participar en las instancias relacionadas con los sistemas local, regional y nacional de seguridad, así como con las alcaldías y demás entes públicos;\nXIV. Nombrar y remover libremente a Las o Los titulares de las unidades operativas y administrativas de la Fiscalía General, salvo los casos establecidos en la Constitución local y otras disposiciones aplicables;\nXV. Participar en el Consejo de Asuntos Internos de la Fiscalía, con voto de calidad;\nXVI. Ostentar la representación legal de la Fiscalía, en los términos que señale esta Ley y el\nReglamento; y realizar todos los actos de dominio, administración, de pleitos y cobranzas en favor de la institución, conforme a las normas aplicables;\nXVII. Fomentar e incentivar el uso de las herramientas y mecanismos digitales; para la presentación de denuncias o querellas, así como, para todas y cada una de las diligencias durante el procedimiento penal, de acuerdo a sus competencias;\nXVIII. Adoptar instrumentos en materia de tecnología digital, con el fin de garantizar los principios de legalidad, objetividad, eficiencia, profesionalismo, honradez y respeto a los\nDerechos Humanos reconocidos en la Constitución Federal y Local;\nXIX. Proponer, formular y ejecutar los mecanismos en materia de tecnología, a fin de atender de manera efectiva la recepción de denuncias o querellas; y\n\nXX. Asignar competencia y autorizar a las áreas de investigación de la Fiscalía, para conocer o llevar a cabo los registros y actos de investigación correspondientes en determinada carpeta de investigación, y\nXXI. Las demás que señale la normatividad aplicable.\nArtículo 36. Facultades del Ministerio Público.\nSon facultades del Ministerio Público de la Ciudad de México, las siguientes:\nI. Recibir las denuncias o querellas que le presenten en forma oral, por escrito, o a través de medios electrónicos, incluso mediante denuncias anónimas en términos de las disposiciones legales aplicables, sobre hechos con apariencia de delito;\nII. Investigar y perseguir los delitos en el ámbito de su competencia, interviniendo en todas las etapas del procedimiento penal y realizando todas las actuaciones procesales aplicables;\nIII. Dirigir la investigación de los hechos constitutivos de delito, con el deber de objetividad y debida diligencia, los que determinen la participación punible y los que acrediten la inocencia de la persona imputada, garantizando el respeto de los derechos de las partes y el debido proceso;\nIV. Aplicar los protocolos de investigación que le competan;\nV. Ordenar a la Policía y a sus auxiliares, en el ámbito de su competencia, la práctica de actos de investigación conducentes para el esclarecimiento del hecho con apariencia de delito, así como analizar las que dichas autoridades hubieren practicado;\nVI. Instruir a las Policías sobre la legalidad, pertinencia, suficiencia y contundencia de los indicios recolectados o por recolectar, así como las demás actividades y diligencias que deben ser llevadas a cabo dentro de la investigación;\nVII. Solicitar y efectuar actos de investigación conforme al principio de libertad probatoria, desarrollar investigaciones completas y exhaustivas, con perspectiva de género, interés superior de la niñez, enfoque especializado y diferenciado;\n\nVIII. Aplicar los principios y estándares nacionales e internacionales de Derechos Humanos, con enfoque diferencial y especializado, en las investigaciones y procesos penales;\nIX. Adoptar y garantizar las providencias precautorias y medidas de protección a las víctimas y a los testigos u otros sujetos procesales; Instalando mecanismos para proteger, garantizar y respetar los Derechos Humanos, con perspectiva de género, interés superior de la niñez, enfoque especializado y diferenciado;\nX. Garantizar la reparación integral del daño de las víctimas;\nXI. Proporcionar información veraz sobre los hechos, hallazgos en la investigación y no ocultar a los intervinientes elemento alguno que pudiera resultar favorable para la posición que ellos asumen, sobre todo cuando resuelva no incorporar alguno de esos elementos al procedimiento, salvo la reserva que en determinados casos la ley autorice en las investigaciones;\nXII. Vigilar que los registros de la investigación, así como todos los documentos, independientemente de su contenido o naturaleza, los objetos, los registros de voz e imágenes o cosas que le estén relacionados, que son estrictamente reservados, únicamente las partes tendrán acceso a los mismos, con las limitaciones establecidas en el Código Nacional y demás disposiciones aplicables;\nXIII. Gestionar la asistencia de un intérprete o traductor de su lengua, en caso de que las víctimas no comprendan el idioma español o tenga discapacidad auditiva, verbal o visual;\nXIV. Realizar las funciones respecto de las personas menores de dieciocho años a quienes se atribuya la comisión o participación en un hecho que la ley señale como delito;\nXV. Poner a disposición de la autoridad competente a personas inimputables mayores de edad, a quien se deba aplicar medidas de seguridad ejercitando las acciones correspondientes y realizando los ajustes razonables al tratarse de la persona inimputable, con respeto absoluto a sus Derechos Humanos;\nXVI. Citar a personas servidoras públicas para la realización de entrevistas, obtención de información, acceso a lugares, archivos, documentos y, en general, para la realización de los actos de investigación necesarios por motivo de sus funciones;\n\nXVII. Solicitar, cuando fuere procedente, la orden de aprehensión, reaprehensión, comparecencia o de cita;\nXVIII. Solicitar y en su caso habilitar la intervención de personas expertas independientes o personal técnico especializado de otros entes públicos, de otras entidades federativas, de otros países y de instituciones nacionales e internacionales a fin de que colaboren con las autoridades competentes en la investigación de los hechos y la realización de peritajes, en los casos que correspondan en el ámbito de su competencia;\nXIX. Realizar el aseguramiento de bienes, indicios, evidencias físicas, objetos, instrumentos, productos, sustancias, huellas y objetos relacionados con el hecho delictuoso, dispositivos, medios de almacenamiento electrónico y sistemas de información en general que puedan constituir dato de prueba y en términos de las disposiciones aplicables declarar su abandono, en términos de las disposiciones aplicables y participar en la disposición final de los mismos;\nXX. Ejercer la acción penal, cuando proceda;\nXXI. Determinar el archivo temporal y el no ejercicio de la acción penal, así como ejercer la facultad de no investigar y la aplicación de criterios de oportunidad, en los casos autorizados por el Código Nacional y demás normatividad aplicable;\nXXII. Dar respuestas diferenciadas por tipo de delito, en función de lo que establezca la política criminal de persecución penal;\nXXIII. Promover la resolución de conflictos a través de la aplicación de mecanismos alternativos de solución de controversias, sólo cuando sea procedente;\nXXIV. Declinar competencia al Ministerio Público de la Federación o al de otras Entidades\nFederativas de conformidad con las normas aplicables;\nXXV. Pedir al Órgano Jurisdiccional la libertad del imputado en los casos que proceda;\nXXVI. Solicitar las medidas cautelares correspondientes contra las personas imputadas;\nXXVII. Solicitar a la autoridad judicial la imposición de las penas o medidas de seguridad que correspondan;\n\nXXVIII. Procurar que los juicios en materia penal se sigan con regularidad para que la impartición de justicia sea completa, pronta y expedita;\nXXIX. Presentar y desahogar pruebas que acrediten la responsabilidad de las personas acusadas en la comisión de los hechos que las leyes señalen como delito;\nXXX. Promover los recursos procedentes;\nXXXI. Preparar, ejercer la acción y ser parte en el procedimiento de extinción de dominio, en términos de las disposiciones aplicables;\nXXXII. Actuar en materia de sobreseimiento en los procesos penales, en los casos en que proceda;\nXXXIII. Intervenir y participar en el proceso de ejecución penal;\nXXXIV. Informar y facilitar a las personas detenidas de nacionalidad extranjera el ejercicio del derecho a recibir asistencia consular por las embajadas o consulados, comunicando a la representación diplomática la situación jurídica de la persona detenida;\nXXXV. Ejercer todas aquellas funciones que establezcan las leyes procesales o especiales, así como las que disponga la normativa interna;\nXXXVI.Acceder a la información, documentos, registros físicos y electrónicos en poder de las instituciones públicas;\nXXXVII. Crear y conservar bancos de datos biométricos, en los términos que establezcan las leyes;\nXXXVIII. Poner en conocimiento de la autoridad administrativa correspondiente, las quejas o denuncias formuladas por particulares, respecto de irregularidades o hechos que no constituyan delito;\nXXXIX. Atender las visitas, quejas, propuestas de conciliación y recomendaciones tanto de la\nComisión Nacional de los Derechos Humanos como de la Comisión de Derechos Humanos de la\nCiudad de México, conforme a las normas aplicables;\n\nXL.Compartir información con instituciones policiales, de procuración y administración de justicia y de atención victimal, locales y federales, conforme lo determinen las leyes;\nXLI. Solicitar la colaboración de otras autoridades, así como auxiliar a las que lo soliciten, en la persecución de los probables autores o partícipes del hecho delictivo, en los términos que dispongan las leyes, acuerdos, convenios, bases y demás instrumentos de colaboración celebrados para tales efectos;\nXLII. Cumplir las disposiciones en materia de transparencia y protección de datos personales;\nXLIII. Las demás que le confieran las disposiciones legales aplicables.\nArtículo 37. Obligaciones Ministeriales de Igualdad Sustantiva:\nEl Ministerio Público conducirá su actuación, considerando la perspectiva de género, y la igualdad sustantiva. Esta obligación comprenderá como mínimo, lo siguiente:\nI. En cuanto reciba una denuncia o querella por hechos que impliquen riesgo a la integridad física y psicoemocional hacia una mujer por violencia, dictar sucesivamente las medidas u órdenes de protección de emergencia y preventivas necesarias, confirmando su vigencia en tanto permanezcan las condiciones que las originaron;\nII. Prevenir y evitar la revictimización en el desarrollo del procedimiento penal;\nIII. Allegarse de los dictámenes para el acceso efectivo a la reparación del daño, con la acreditación del daño y su cuantificación; y\nIV. Evitar en todo momento los prejuicios y estereotipos de género o de sumisión, así como de roles tradicionales asociados a factores sociales, culturales o laborales, como la forma de vestir, la expresión verbal o corporal, la condición socioeconómica o étnica, las preferencias sexuales, identidad o expresión de género o las actividades a que se dedique la mujer, sea víctima o inculpada;\nFracción modificada y publicada en la GOCDMX el 23 de agosto de 2024\n\nV. Aplicar estrictamente en la acreditación de los delitos que sean en contra de la comunidad\nLGBTTTI, con especial atención en el delito de transfeminicidio, el Protocolo de Actuación para la\nAtención a las personas de la Comunidad LGBTTTI;\nFracción adicionada y publicada en la GOCDMX el 23 de agosto de 2024\nVI. En el caso de la entrega del cádaver de alguna persona transgénero, si este no es reclamado por sus familares consanguíneos o en caso de que sí sea reclamado, estos pudieren vulnerar la identidad de género, expresión de género de la víctima o su dignidad humana, el cuerpo de esta deberá ser entregado a su familia social, en términos de lo que establece la Ley de Víctimas de la Ciudad de México; y\nFracción adicionada y publicada en la GOCDMX el 23 de agosto de 2024\nVII. Generar datos estadísticos e informes trimestrales sobre los delitos que sean en contra de la comunidad LGBTTTI, respetando en la generación de dichos datos la identidad o expresión de género real o percibida de la víctima.\nFracción adicionada y publicada en la GOCDMX el 23 de agosto de 2024\nArtículo 38. Obligaciones respecto al interés superior de las niñas o niños.\nEn todos los procedimientos en que intervenga, el Ministerio Público deberá atender prioritariamente el interés superior del niño. Esta atención comprenderá como mínimo las acciones siguientes:\nI. Ordenar las medidas administrativas tendientes a la protección física, psicológica y para el sano desarrollo del niño, la niña o el adolescente, y solicitarlas en el procedimiento respectivo, velando por su efectiva ejecución;\nII. Asumir y ejercer la representación legal del niño, la niña o el adolescente que carezcan de ella, o si se desconoce que la tienen, en tanto se constituye la autoridad conducente para ello;\nIII. Representar legalmente al niño, la niña o el adolescente afectados o impedidos en sus derechos, por quien legalmente los represente o tenga obligación de protegerlos en tanto se constituye la autoridad conducente para ello;\nIV. Si su edad lo permite, procurar que los niños, las niñas o los adolescentes tengan oportunidad procesal para expresar su opinión por sí mismos de manera libre; y\n\nV. Verificar a través de los dictámenes periciales correspondientes, se acredite el sano desarrollo físico, mental y social de la persona menor relacionado con algún procedimiento, incluidos los que se encuentren bajo la patria potestad, tutela o custodia de persona inculpada.\nCAPÍTULO SEGUNDO\nDE LA PERSONA TITULAR DE LA FISCALÍA GENERAL\nArtículo 39. Designación de la Persona Titular de la Fiscalía\nPara ser Titular de la Fiscalía de la Ciudad de México se requiere que al momento de su designación cumpla con los siguientes requisitos:\na) Tener ciudadanía mexicana;\nb) Tener cuando menos treinta y cinco años de edad;\nc) Contar con título y cédula de licenciatura en derecho, con experiencia mínima de 5 años;\nd) No haber sido condenada por delito doloso;\ne) Someterse y acreditar en los términos de la ley, las evaluaciones y certificación de confianza;\nf) Presentar y hacer pública, en los términos de la ley su declaración patrimonial, fiscal y de intereses;\ng) No haber desempeñado un cargo de elección popular, o cargo de dirección de un Partido\nPolítico, un año previo.\nLa persona Fiscal General será de reputación honorable, con conocimientos y experiencia en el ámbito jurídico y de procuración de justicia, capacidad de administración y dirección institucional, diseño y ejecución de políticas públicas, independiente en su actuación, con una visión de respeto y protección a los Derechos Humanos, a las víctimas y perspectiva de género.\nArtículo 39.BIS\n\nLa persona titular de la Fiscalía Especializada para la Atención de Delitos Electorales deberá cumplir los mismos requisitos que para ser Fiscal General.\nLa persona titular de la Fiscalía Especializada en Combate a la Corrupción, deberá cumplir los requisitos señalados en la Ley Orgánica del Congreso de la Ciudad de México.\nLa persona titular de la Fiscalía Especializada para la Atención de Delitos Electorales, deberá contar con el siguiente perfil: Será de reputación honorable, con conocimientos y experiencia en el ámbito jurídico, especialmente en derecho constitucional, derecho electoral, sistemas políticos y participación ciudadana, con capacidad de administración y dirección institucional e independiente en su actuación. Deberá contar además con una visión de respeto y protección a los derechos humanos y perspectiva de género.\nLa persona titular de la Fiscalía Especializada en Combate a la Corrupción, deberá contar con el siguiente perfil: Será de reputación honorable con conocimientos y experiencia en el ámbito jurídico de la administración pública, sistemas de fiscalización de recursos públicos, auditorías, prevención, detección y combate a la corrupción y delitos cometidos por personas servidoras públicas, con capacidad de administración y dirección institucional, diseño y ejecución de políticas públicas e independiente en su actuación.\nLa persona titular de la Fiscalía en investigación de Delitos Complejos, deberá tener el mismo perfil que de la persona Titular de la Fiscalía General.\nArtículo 40. Nombramiento\nEl o la Fiscal General, será nombrada (o) y designada (o) dentro de una terna que, para tales efectos formule el Consejo Judicial Ciudadano, establecido en la Constitución Local, a la persona Titular de la Jefatura de\nGobierno, para que seleccione y remita una persona al Congreso o bien teniendo ésta o este la potestad de remitir para su selección la terna al Congreso Local, y este elija.\nArtículo 41. Causales y Procedimiento de Remoción\nSólo podrá iniciarse un procedimiento de remoción de quien encabeza la Fiscalía General por la persona titular de la Jefatura de Gobierno de la Ciudad de México, por incurrir en alguna de las siguientes causas graves, determinadas por resolución firme de autoridad competente:\n\nI. Incumplir de forma grave sistemática, generalizada e injustificada, los objetivos del Plan de\nPolítica Criminal;\nII. Participar en actos que impliquen violaciones graves a los Derechos Humanos;\nIII. Por violaciones graves a la Constitución Local y las leyes que de ella emanen, así como por el manejo indebido de fondos y recursos públicos de la Ciudad de México;\nIV. Las causas graves contempladas en la Ley de Responsabilidades Administrativas de la Ciudad de México.\nLa persona Titular de la Jefatura de Gobierno deberá expresar las razones, justificar y acreditar la causa grave que motivó el inicio del proceso de remoción, e informará al Congreso de la Ciudad de México para que realice lo conducente, de conformidad con lo dispuesto en el artículo 65 de la Constitución Política de la Ciudad de México.\nArtículo 42. Ratificación\nArtículo reformado y publicado en la GOCDMX el 17 de mayo de 2023\nLas personas titulares de la Fiscalía General y de las Fiscalías Especializadas para la Atención de Delitos\nElectorales y de Combate a la Corrupción, podrán ser ratificadas hasta por un periodo igual al de su nombramiento, debiéndose seguir el procedimiento que establece la Constitución Local y esta ley.\nEl proceso para la ratificación será el siguiente:\nI. El Consejo Judicial requerirá por escrito a la persona titular de la Fiscalía en funciones que corresponda para que manifieste si tiene interés en someterse al proceso de ratificación en el cargo;\nII. En caso negativo, se procederá en términos del artículo 120 de la Ley Orgánica del Congreso de la Ciudad de México;\nIII. En caso de que la persona titular manifieste interés en someterse a proceso de ratificación, el\nConsejo Judicial deberá iniciar un proceso público y abierto de evaluación de su desempeño;\nEste proceso tiene por objeto recibir recomendaciones y opiniones sobre el desempeño de las\n\npersonas titulares de cuya ratificación se trata. Asimismo, considerará las recomendaciones y opiniones sobre el desempeño, que emita el Consejo Ciudadano;\nIV. El Consejo Judicial entrevistará a la persona titular de la Fiscalía General, de la Fiscalía\nEspecializada para la Atención de Delitos Electorales o de Combate a la Corrupción, según sea el caso, como elemento de la evaluación de su desempeño;\nV. Asimismo, el Consejo Judicial considerará lo siguiente:\na) Los conocimientos y experiencia en el ámbito jurídico y de procuración de justicia;\nb) La información que la persona titular de la Fiscalía General haya presentado ante el\nCongreso, respecto del Plan de Política Criminal y del Programa de Persecución Penal durante su gestión, y c) La aplicación de estrategias y capacidad de administración y dirección institucional, diseño y ejecución de políticas de procuración de justicia y criminales, independencia en su actuación, con una visión de respeto y protección a los Derechos Humanos, a las víctimas y perspectiva de género.\nVI. Con base en el resultado de la evaluación, el Consejo Judicial emitirá opinión sobre la ratificación de la persona titular, con el voto de las dos terceras partes de las personas Consejeras, misma que será remitida a la persona Titular de Jefatura de Gobierno de la Ciudad de México, a más tardar en treinta días naturales a partir de que se haya constituido dicho Consejo Judicial;\nVII. La persona Titular de la Jefatura de Gobierno de la Ciudad de México, dentro de los siguientes quince días naturales a la recepción de la propuesta, la enviará al Congreso de la Ciudad de\nMéxico, emitiendo su razonamiento sobre la idoneidad de la propuesta de ratificación;\nVIII. La Mesa Directiva del Congreso de la Ciudad de México, al recibir las recomendaciones y opiniones sobre la ratificación, dará trámite en lo conducente, conforme a lo dispuesto en el\nTítulo Décimo Primero de su Ley Orgánica, relativo a las designaciones, nombramientos y ratificaciones que establece, y\nIX. De no obtenerse la mayoría calificada en el Pleno del Congreso de la Ciudad de México para la aprobación de la ratificación, la Mesa Directiva notificará al Consejo Judicial, a efecto de que emita la convocatoria para el proceso de selección de la persona titular de la Fiscalía General, de\n\nlas Fiscalías Especializadas para la Atención de Delitos Electorales o de Combate a la Corrupción, cuando corresponda.\nArtículo 42 bis.- El Consejo Judicial Ciudadano se instalará en los términos previstos en la Constitución\nPolítica de la Ciudad de México y la Ley Orgánica del Congreso de la Ciudad de México, a más tardar noventa días naturales antes de que concluya la gestión de la persona titular de la Fiscalía General o dentro de los treinta días hábiles que se requiera realizar un nombramiento ante la ausencia, falta temporal o absoluta de cualquiera de las personas titulares de la Fiscalía General o de las Fiscalías Especializadas para la Atención de Delitos Electorales y de Combate a la Corrupción.\nArtículo adicionado y publicado en la GOCDMX el 17 de mayo de 2023\nEl Consejo Judicial para su organización y funcionamiento se sujetará a las siguientes bases:\nI. Para sesionar y adoptar acuerdos, de conformidad en el calendario de sesiones ordinarias o extraordinarias, o a solicitud de los consejeros, bastará la mayoría simple de las personas consejeras presentes en la sesión, salvo que se trate de aprobar la opinión de ratificación de la persona titular de la Fiscalía General, en cuyo caso se estará a lo dispuesto en la fracción VI del artículo 42 de esta Ley, o para aprobar la conformación de terna de la o el Fiscal General, caso en el cual se requerirá del voto de al menos las dos terceras partes de las personas consejeras, y\nII. Elegirá de entre sus integrantes a una persona encargada de la Presidencia y otra de la\nSecretaría Técnica del Consejo. El resto de las personas Consejeras serán vocales.\nSon facultades de la persona Consejera Presidente:\na) Representar al Consejo Judicial ante toda clase de autoridades;\nb) Presidir las sesiones;\nc) Emitir convocatoria a sesionar;\nd) Declarar el inicio y el cierre de las sesiones, o la falta de quorum para sesionar;\ne) Decretar recesos en las sesiones cuando así fuere necesario;\n\nf) Adoptar las medidas conducentes para el desarrollo de las sesiones;\ng) Vigilar la aplicación del Reglamento de Operación y Funcionamiento del Consejo\nJudicial;\nh) Asistir a las sesiones con voz y voto; en caso de empate, la Presidencia tendrá voto de calidad;\ni) Declarar, en caso de fuerza mayor, la suspensión de la sesión, y j) Firmar los acuerdos que emita el Consejo Judicial.\nSon facultades de la persona Consejera Secretaria Técnica:\na) Asistir a las sesiones con voz y voto;\nb) Registrar la asistencia de las personas consejeras a las sesiones;\nc) Declarar la existencia de quórum para sesionar;\nd) Elaborar el proyecto de Orden del Día;\ne) Remitir a las personas consejeras los documentos necesarios para el desarrollo de las sesiones;\nf) Elaborar el acta de las sesiones y recabar la firma de las personas consejeras;\ng) Tomar las votaciones de los acuerdos y dar a conocer el resultado de las mismas;\nh) Registrar e informar en las sesiones el avance en el cumplimiento de los acuerdos del Consejo Judicial;\ni) Certificar documentos que obren en poder del Consejo Judicial, y j) Compilar las actas de las sesiones y archivarlas.\n\nSon facultades de las personas Consejeras vocales:\na) Asistir a las sesiones con voz y voto;\nb) Analizar los asuntos de la Orden del Día de las sesiones;\nc) Solicitar la inclusión de temas para el desarrollo de las sesiones y aportar la documentación necesaria para ello, con anticipación a la fecha programada para cada sesión;\nd) Hacer uso de la voz para expresar su posición respecto de los temas tratados en las sesiones, y e) Emitir su voto de manera libre, pudiendo razonar su voto y emitir voto particular o concurrente.\nIII. El Consejo Judicial podrá sesionar de forma presencial o por vía remota, al menos una vez por semana;\nIV. La persona Consejera Presidente emitirá la convocatoria para la celebración de sesiones, cuando lo estime necesario, o, a solicitud de la mayoría simple de los integrantes del Consejo.\nLa convocatoria será escrita y podrá ser notificada físicamente o por medios electrónicos;\nV. Las sesiones serán públicas y podrán transmitirse en los medios electrónicos que para tal efecto establezca el Consejo, serán videograbadas y entregadas al área competente del Congreso de la Ciudad de México y de la Fiscalía General para la difusión de las mismas en las plataformas de ambos entes.\nEl Congreso de la Ciudad de México otorgará todos los elementos materiales, humanos, técnicos y financieros al Consejo Judicial para el desempeño de sus funciones;\nVI. Las personas consejeras no podrán designar suplentes para el desarrollo de las sesiones ni para la emisión de votos. En caso de falta absoluta de una o más personas consejeras, el Consejo\n\nJudicial podrá sesionar válidamente con al menos ocho integrantes, en cuyo caso se computarán las votaciones con base en el número de integrantes vigentes, y\nVII. El Consejo Judicial podrá celebrar sesiones ordinarias y extraordinarias; éstas últimas serán para casos urgentes y sólo se tratarán los asuntos sobre los cuales versó la convocatoria respectiva.\nCAPÍTULO TERCERO\nDESIGNACIONES Y SUPLENCIA\nArtículo 43. Designación de Titulares de Fiscalías Especializadas.\nLa persona Titular de la Fiscalía General, remitirá una propuesta compuesta por una terna para ocupar el cargo del titular de a Fiscalía Especializada para la investigación de los Delitos Complejos, procurando siempre el principio de la paridad de género, y esta será ratificada por mayoría calificada del Congreso\nLocal, conforme al procedimiento que marca la Constitución Local y la Ley Orgánica del Congreso de la\nCiudad de México.\nLa persona titular de la Fiscalía Especializada en Delitos Complejos deberá cumplir con los mismos requisitos que para ser titular de la Fiscalía General. Será designada por un período de 4 años y podrá ser ratificada por un mismo período.\nArtículo 44. Facultad de Designación.\nLa persona Titular de la Fiscalía General nombrará y removerá libremente a las o los titulares de las\nCoordinaciones Generales, Supervisiones Generales, Órganos, Jefaturas, Fiscalías y demás unidades administrativas, cuya designación no esté prevista de otra forma en la Constitución Local o en esta ley, procurando siempre el principio de paridad de género.\nArtículo 45. Representación.\nLa persona Titular de la Fiscalía General, será representada ante las autoridades judiciales, administrativas y del trabajo por las personas servidoras públicas que señale esta Ley y su Reglamento, por las personas titulares de unidades administrativas y o Las o Los Agentes del Ministerio Público que se designen para el caso concreto.\n\nArtículo 46. Suplencia.\nLa persona Titular de la Fiscalía será suplida en ausencias o faltas temporales por la persona titular de la\nCoordinación General de Investigación Territorial, y a falta de ésta, por las personas servidoras públicas en los términos que disponga el Reglamento de esta Ley. En caso de ausencia definitiva la persona que funja como suplente notificará al Congreso de la Ciudad de México para que proceda conforme a lo dispuesto en el texto constitucional.\nTÍTULO CUARTO\nESTRUCTURA ORGÁNICA\nCAPÍTULO PRIMERO\nDISPOSICIONES GENERALES\nArtículo 47. Estructura Orgánica\nLa persona Titular de la Fiscalía General, ejercerá autoridad jerárquica sobre todo el personal de la\nInstitución.\nPara el despacho de los asuntos que competen a la institución, y en ejercicio de su autonomía, la Fiscalía contará con Coordinaciones Generales, Fiscalías Especializadas, Órganos, Fiscales, Agentes del Ministerio\nPúblico, Policía de Investigación, analistas, auxiliares, técnicos y científicos forenses, peritos, personal especializado en asistencia a víctimas y en mecanismos alternativos de solución de controversias, así como con el personal profesional, técnico y administrativo necesario para la realización de sus funciones, en términos de las disposiciones jurídicas aplicables.\nArtículo 48. La Fiscalía General tendrá la siguiente estructura orgánica:\nI. Oficina de la Fiscalía General;\nII. Unidad de Implementación;\nIII. Unidad interna de combate a la corrupción y la infiltración de la delincuencia organizada;\n\nIV. Consejo de Asuntos Internos;\nV. Órgano de Política Criminal;\nVI. Fiscalía Especializada en Combate a la Corrupción;\nVII. Fiscalía Especializada para la Atención de Delitos Electorales;\nVIII. Fiscalía Especializada en Investigación de Delitos Complejos;\nIX. Coordinación General de Investigación Forense y Servicios Periciales;\nX. Coordinación General de Investigación Territorial;\nXI. Coordinación General de Investigación de Delitos de Género y Atención a Víctimas;\nXII. Coordinación General Jurídica y de Derechos Humanos;\nXIII. Coordinación General de Investigación Estratégica;\nXIV. Coordinación General de Investigación de Delitos de Alto Impacto;\nXV. Coordinación General de Administración;\nXVI. Jefatura General de la Policía de Investigación;\nXVII. Supervisión General de Liquidación de Casos;\nXVIII. Supervisión General de Justicia Alternativa;\nXIX. Órgano de Gestión Administrativa de casos no penales;\nXX. Instituto de Formación Profesional y Estudios Superiores;\nXXI. Consejo de Honor y Justicia;\n\nXXII. Órgano Interno de Control;\nXXIII. Unidad de Investigación de delitos de personas servidoras públicas; y\nXXIV. Coordinación General de Acusación, Procedimiento y Enjuiciamiento;\nFracción adicionada y publicada en la GOCDMX el 25 de mayo de 2023\nXXV. Unidad de Asuntos Internos, y\nFracción adicionada y publicada en la GOCDMX el 25 de mayo de 2023\nXXVI. Los demás órganos o unidades administrativas de investigación, de acusación, de protección a víctimas o administrativas que determinen otras disposiciones aplicables y las que la persona titular de la Fiscalía General establezca en el ejercicio de la autonomía constitucional en el Reglamento de esta Ley o mediante Acuerdo.\nFracción modificada y publicada en la GOCDMX el 25 de mayo de 2023\nArtículo 49. Disposiciones Comunes de los Órganos de Procuración de Justicia\nLos Órganos que ejercen la función de Procuración de Justicia tendrán las siguientes facultades:\nI. Ejecutar los lineamientos del Plan de Política Criminal y las acciones concretas del Programa de Persecución Penal, dictados por la persona titular de la Fiscal General;\nII. Dirigir la investigación de los hechos constitutivos de delito, los que determinen la participación punible y los que acrediten la inocencia de la persona imputada, sujetos procesales, en el marco de la legislación vigente, por sí o en coordinación con otras entidades públicas o privadas;\nIII. Requerir y coordinar la cooperación y coadyuvancia necesaria de instituciones públicas y privadas, en la conducción legal de la investigación y la persecución de los delitos;\nIV. Suministrar información al Órgano de Política Criminal, relativa a los patrones, estructuras y organizaciones criminales para el diseño de las políticas institucionales y toma de decisiones\n\nV. Aplicar los estándares nacionales e internacionales de Derechos Humanos, con enfoque diferencial y especializado, y la igualdad sustantiva en las investigaciones y procesos penales;\nVI. Aplicar los protocolos de investigación que les competan;\nVII. Ejercer todas aquellas funciones que establezcan las leyes procesales o especiales, así como las que disponga la persona Titular de la Fiscalía General a través de la normativa interna, en el ámbito de su competencia;\nVIII. Las demás que señalen otras disposiciones aplicables.\nArtículo 50. Distribución y Asignación Reglamentaria de Atribuciones y Facultades\nEl Reglamento de esta Ley establecerá el capital humano, recursos materiales, financieros y tecnológicos de la Fiscalía General y sus unidades administrativas, así como las atribuciones o funciones de las personas servidoras públicas, garantizando la adecuada operación, eficacia, eficiencia en su desempeño, a fin de cumplir en todo momento con la legislación en la materia que tiene competencia, y las tareas encomendadas.\nLos acuerdos, circulares, lineamientos, instructivos, guías, protocolos, manuales, bases y demás normas jurídico administrativas emitidas en el ámbito de sus atribuciones por parte de las Coordinaciones\nGenerales y demás unidades administrativas, que sean necesarios para regular la actuación a su cargo, en ningún caso podrán contradecir las normas emitidas por la persona Titular de la Fiscalía General.\nLas Fiscalías Especializadas se sujetarán a lo que expresamente establecen las Leyes de la materia de su competencia, al Código Nacional, en materia de investigación y persecución de los delitos que deban realizar conforme a las mismas, y demás disposiciones aplicables.\nArtículo 51. Organización Interna de cada Unidad Administrativa de la Fiscalía General\nCada Unidad Administrativa de la Fiscalía contará con una persona titular que ejercerá autoridad jerárquica sobre todo el personal que la conforme, y será responsable del cabal cumplimiento de las atribuciones que le confiera esta Ley, su Reglamento, protocolo y demás disposiciones aplicables.\nLa persona titular de cada unidad o área, con la aprobación del o la Fiscal General, se auxiliará para el desempeño de sus atribuciones, facultades y funciones por el personal de confianza, técnico y\n\nadministrativo que se determine conforme a la presente Ley y su Reglamento. Las atribuciones y funciones de dicho personal auxiliar se establecerán en el Reglamento y demás disposiciones.\nArtículo 52. Oficina de la Fiscalía General\nLa persona Titular de la Fiscalía General para el despacho de los asuntos que competen contará con las unidades administrativas, que se establezcan en el Reglamento.\nArtículo 53. Órgano de Política Criminal.\nEl Órgano de Política Criminal será el área responsable de formular ante la persona Titular de la Fiscalía\nGeneral, el Plan de Política Criminal, el diseño institucional, la planeación de las capacidades institucionales y la vinculación con otras organizaciones.\nSon facultades del Órgano de Política Criminal:\nI. Coordinar la operación de la Unidad de Estadística y Transparencia;\nII. Definir, en colaboración con las Coordinaciones Generales, la Política Criminal y elaborar el\nPrograma de Persecución Penal que seguirá la institución, de acuerdo con los estudios y análisis de su competencia;\nIII. Proponer y dar seguimiento a las políticas de vinculación y coordinación interinstitucional, en el ámbito de su competencia;\nIV. Apoyar las labores necesarias para el seguimiento y evaluación de las estrategias político criminales, así como, elaborar los reportes respectivos, de acuerdo con el Programa de\nPersecución Penal definidos por la Fiscalía General;\nV. Definir indicadores y metas institucionales, de acuerdo con la Política Criminal y el Programa de Persecución Penal y dar seguimiento puntual a los mismos;\nVI. Elaborar la estadística criminal y difundir la misma, considerando los datos desagregados por sexo cuando sea procedente;\n\nVII. Coordinar a las unidades y órganos de la Fiscalía General, en el suministro de información y asegurar su consolidación, consistencia, oportunidad y confiabilidad;\nVIII. Organizar, dirigir e implementar mecanismos de sistematización y análisis de la información del Sistema de Gestión de Información;\nIX. Desarrollar la política del Sistema de Gestión Documental y Administración de archivos de la entidad, las directrices y los procesos de generación;\nX. Garantizar el acceso a la información pública generada en el marco de sus atribuciones y conforme a lo establecido en la normativa de la materia y demás normativa aplicable;\nXI. Administrar el desarrollo de la arquitectura institucional que comprende los procesos, sistemas, la identificación de competencias profesionales, las propuestas de normativa que faciliten la coordinación interna;\nXII. Proponer un gobierno por procesos, en donde participen todas las áreas que incidan en éstos. El gobierno en los procesos debe procurar la mejora continua de los mismos a partir de la evaluación de su funcionamiento, costos y resultados;\nXIII. Fijar los lineamientos generales para el desarrollo de las capacidades institucionales, que deberán ser reflejadas en los programas de capacitación del Instituto de Formación Profesional y Estudios Superiores;\nXIV. Las demás que se señalen en el Reglamento de la Ley.\nArtículo 53. Bis. Unidad de Implementación.\nLa Unidad de Implementación es la encargada de coordinar, implementar, ejecutar y llevar a cabo la evolución del Plan de Transición de la Fiscalía General.\nArtículo adicionado y publicado en la GOCDMX el 25 de mayo de 2023\nArtículo 54. Supervisión General de Liquidación de Casos\nLa supervisión General de Liquidación de Casos tendrá las siguientes facultades:\n\nI. Proponer e implementar dos esquemas de trabajo: uno que aborde los asuntos del sistema tradicional y otro, de los asuntos relativos al sistema acusatorio. Para ambos esquemas se señalará un plazo para concluir los casos, mediante las distintas opciones legales existentes;\nII. Instalar una oficina de seguimiento, monitoreo y evaluación de los casos para evitar impunidad, que será considerada en el presupuesto para el Plan de Transición;\nIII. Integrar un programa de actuación que contemple las necesidades presupuestales, tecnológicas, de infraestructura y equipamiento o de cualquier índole, que sean indispensables para el cumplimiento de los objetivos y metas trazados, con el fin de dar continuidad a las investigaciones y procesos, para el cierre definitivo de los asuntos que así lo ameriten, de acuerdo a las disposiciones legales aplicables;\nIV. Formar un grupo especializado de las personas Agentes del Ministerio Público del más alto perfil y personal especializado indispensable, con la finalidad de elaborar un inventario de los asuntos con el estatus jurídico y la clasificación por delitos, sus posibilidades de éxito y, en su caso, de alguna salida alterna o aplicación de un criterio de oportunidad. El inventario final será entregado a la persona Titular de la Fiscalía General, los expedientes de averiguación previa y carpetas de investigación a grupos especializados de trabajo que asumirán la responsabilidad de cierre de los asuntos;\nLos casos pendientes de resolución relacionados con violaciones graves de Derechos Humanos o corrupción no podrán ser liquidados. La persona Titular de la Fiscalía General, determinará la forma de atención y trámite a estos casos hasta su conclusión en una unidad especializada distinta de la Supervisión\nGeneral de Liquidación de Casos.\nArtículo 55. Nombramiento y disposiciones comunes de las Fiscalías Especializadas.\nEl nombramiento de las Personas Titulares de las Fiscalías Especializadas en Atención de Delitos Electorales, de Combate a la Corrupción, y de Delitos Complejos, se realizará conforme a los procedimientos correspondientes establecidos en la Constitución de la Ciudad de México y en esta ley, respectivamente.\nSu designación, será por mayoría calificada del Congreso de la Ciudad de México.\nLas Fiscalías Especializadas en Atención de Delitos Electorales y de Combate a la Corrupción, estarán adscritas a la Fiscalía General y trabajarán en coordinación para la investigación de los delitos de las que son competentes. Su estructura orgánica se establecerá en el Reglamento de la Ley.\n\nCon independencia de las facultades que en materia de investigación y procuración de justicia se dispongan en la presente Ley, deberán coordinarse con las autoridades en materia anticorrupción y electoral, respectivamente, según las leyes de la materia.\nLas Fiscalías Especializadas en Atención de Delitos Electorales, y de Combate a la Corrupción, gozarán de autonomía técnica y de gestión, en el ámbito de su competencia.\nTendrán también, las atribuciones comunes siguientes:\nI. Proponer a la persona Titular de la Fiscalía General la celebración de convenios y acuerdos de colaboración con las instancias públicas o privadas que se requieran para el ejercicio de sus funciones;\nII. En ejercicio de su especialización, participar en estrategias de coordinación con las instancias federales y estatales, homólogas o que resulten pertinentes para el ejercicio de sus funciones;\nIII. Emitir dentro del ámbito de su competencia, la normativa necesaria para el desempeño de sus funciones;\nIV. Participar en la integración del Plan de Política Criminal; y\nV. Las demás que establezcan la Constitución Local y las leyes para el cumplimiento de sus funciones, y\nVI. Rendir informes necesarios a la persona titular de la Fiscalía General de Justicia sobre las investigaciones de delitos en sus correspondientes áreas.\nArtículo 56. Fiscalía Especializada en Combate a la Corrupción.\nLa persona Titular de la Fiscalía Especializada en Combate a la Corrupción, será nombrada por un periodo de cuatro años y podrá ser ratificada hasta por un periodo igual, debiéndose seguir el procedimiento que establece la Constitución Local.\nLa Fiscalía Especializada en Combate a la Corrupción, tendrá las facultades siguientes:\n\nI. Recibir denuncias y querellas que se presenten en las Agencias del Ministerio Público, por hechos que la ley considera como delitos en materia de corrupción;\nII. Investigar de manera oficiosa cualquier conducta presumiblemente ilícita en materia de corrupción.\nIII. Investigar los hechos que la ley considera como delitos en materia de corrupción con la Policía de Investigación que estará bajo su conducción y mando, los Servicios Periciales y las demás instancias competentes, en los términos de las disposiciones legales aplicables;\nIV. Disponer de los medios e instrumentos tecnológicos necesarios para la debida y pronta investigación de los hechos que la ley considera como delitos en materia de corrupción;\nV. En ejercicio de su especialización, participar en estrategias de coordinación con las instancias federales y estatales, homólogas o que resulten necesarias para el ejercicio de sus funciones;\nVI. Asegurar los bienes muebles e inmuebles, instrumentos, huellas, objetos, vestigios o productos relacionados con los hechos delictivos, en los casos que corresponda;\nVII. Remitir a las autoridades correspondientes las investigaciones de hechos que la ley considera como delitos en materia de corrupción que no sean competencia del Ministerio Público del fuero común de la Ciudad de México;\nVIII. Ejercer la acción penal ante la autoridad judicial correspondiente de los asuntos de su competencia;\nIX. Abstenerse de conocer de carpetas de investigación en las que se encuentren relacionados el personal adscrito a dicha Fiscalía Especializada, en los términos que determine la normatividad aplicable;\nX. Poner a disposición de la ciudadanía mecanismos para llevar a cabo la denuncia pública y elaborar campañas preventivas sobre las acciones que tipifican delitos en materia de corrupción;\nXI. Dar vista inmediatamente a la Fiscalía Especializada en Atención de Delitos Electorales en caso de existir alguna correlación entre los delitos electorales y posibles actos de corrupción;\n\nXII. Dar vista al Órgano Interno de Control, cuando con motivo de su investigación se pudiera actualizar alguna responsabilidad en materia de su competencia;\nXIII. Participar en el Sistema Anticorrupción de la Ciudad de México en los términos que dispongan las leyes aplicables, y\nXIV. Las demás que en su caso le confieran otras disposiciones legales aplicables.\nArtículo 57. Fiscalía Especializada en Atención a Delitos Electorales.\nLa persona titular de la Fiscalía Especializada en Atención a Delitos Electorales, será nombrada por un periodo de cuatro años y podrá ser ratificada hasta por un periodo igual, debiéndose seguir el procedimiento que establece la Constitución Local.\nLa Fiscalía Especializada para la Atención de Delitos Electorales tendrá bajo su cargo la investigación, prevención y persecución de los delitos establecidos en el Título Vigésimo Sexto del Código Penal, así como los previstos en la Ley General en Materia de Delitos Electorales, en lo que corresponda a su competencia.\nLa Fiscalía Especializada en Atención de Delitos Electorales, tendrá las facultades siguientes:\nI. Recibir denuncias y querellas que se presenten en las Agencias del Ministerio Público por hechos que la ley considera como delitos en materia de delitos electorales;\nII. Investigar de manera oficiosa cualquier conducta presumiblemente ilícita en materia electoral;\nIII. Investigar los hechos que la ley considera como delitos en materia electoral con la Policía de\nInvestigación que estará bajo su conducción y mando, los Servicios Periciales y las demás instancias competentes, en los términos de las disposiciones legales aplicables;\nIV. Disponer de los medios e instrumentos tecnológicos necesarios para la debida y pronta investigación de los hechos que la ley considera como delitos en materia electoral;\nV. En ejercicio de su especialización, participar en estrategias de coordinación con las instancias federales y estatales, homólogas o que resulten necesarias para el ejercicio de sus funciones;\n\nVI. Asegurar los bienes muebles e inmuebles, instrumentos, huellas, objetos, vestigios o productos relacionados con los hechos delictivos, en los casos que corresponda;\nVII. Remitir a las autoridades correspondientes las investigaciones de hechos que la ley considera como delitos en materia electoral que no sean competencia del Ministerio Público del fuero común de la Ciudad de México;\nVIII. Ejercer la acción penal ante la autoridad judicial correspondiente de los asuntos de su competencia;\nIX. Abstenerse de conocer de carpetas de investigación en las que se encuentren relacionados el personal adscrito a dicha Fiscalía Especializada, en los términos que determine la normatividad aplicable;\nX. Poner a disposición de la ciudadanía mecanismos para llevar a cabo la denuncia pública y elaborar campañas preventivas sobre las acciones que tipifican delitos electorales;\nXI. Dar vista inmediatamente a la Fiscalía Especializada en Combate a la Corrupción en caso de existir alguna correlación entre los delitos electorales y posibles actos de corrupción;\nXII. Dar vista inmediatamente a las áreas de investigación correspondientes de la Fiscalía cuando exista un tema de su competencia;\nXIII. Realizar operativos de observación y supervisión en procesos electorales en cada una de las\nAlcaldías, cuando se lleven a cabo elecciones o consultas populares;\nXIV. Dar vista al Instituto Electoral de la Ciudad de México, cuando con motivo de su investigación se pudiera actualizar alguna responsabilidad en materia de su competencia;\nXV. Establecer esquemas de colaboración con el Instituto Electoral de la Ciudad de México para la creación de programas, estrategias y demás medidas aplicables, en materia de prevención de delitos en materia electoral, y\nXVI. Las demás que en su caso le confieran otras disposiciones legales aplicables.\nArtículo 58. Fiscalía Especializada en Investigación de Delitos Complejos\n\nLa Fiscalía Especializada en Investigación de Delitos Complejos contará con las siguientes facultades:\nI. Investigar los delitos que debido a la naturaleza, gravedad y complejidad de los hechos, de los derechos tutelados vulnerados o personas involucradas se requiera de un tratamiento especializado;\nII. Planear, programar, organizar y dirigir el funcionamiento de la Fiscalía;\nIII. Atender y proteger, considerando la naturaleza específica de la Fiscalía, y en los términos de esta Ley, a las víctimas, testigos y demás terceros involucrados, en el proceso penal;\nIV. Participar en las instancias de coordinación que le instruya la persona Titular de la Fiscalía\nGeneral, en los términos de esta Ley;\nV. Ejercer en el ámbito de su competencia, las atribuciones que esta Ley y demás disposiciones jurídicas confieren al Ministerio Público;\nVI. Elaborar el análisis de incidencia delictiva de los delitos de su competencia; y\nVII. Las demás que le otorguen la persona Titular de la Fiscalía General, esta Ley, su Reglamento y diversas disposiciones aplicables.\nArtículo 59. Coordinación General de Investigación Forense y Servicios Periciales\nLa Coordinación General de Investigación Forense y Servicios Periciales tendrá las siguientes obligaciones y facultades:\nI. Preservar y levantar los indicios o evidencias en los lugares de investigación, probablemente relacionados con un hecho delictivo, elaborando las respectivas cadenas de custodia;\nII. Formar los equipos inter y multidisciplinarios e interinstitucionales en las distintas especialidades forenses con la colaboración de la Policía de Investigación, cuando se requiera;\n\nIII. Procesar y analizar en los laboratorios de ciencias forenses los indicios o evidencias de interés criminalístico, con la finalidad de aportar datos o elementos para auxiliar a la autoridad con los resultados obtenidos durante el proceso de investigación;\nIV. Realizar los peritajes con autonomía técnica e independencia de criterio, que le sean solicitados por la autoridad competente;\nV. Llevar a cabo los estudios criminalísticos, criminógenos y criminológicos necesarios en colaboración con la Policía de Investigación, Técnica y Científica a efecto de identificar patrones de comportamiento delictivo que sean determinantes en el aumento de la criminalidad;\nVI. Resguardar los indicios y evidencias que pudieran constituirse en elementos materiales probatorios para garantizar su conservación, preservación y almacenamiento;\nVII. Las demás facultades y atribuciones que determinen las leyes aplicables.\nArtículo 60. Coordinación General de Investigación Territorial.\nLa Coordinación General de Investigación Territorial establecerá un sistema central de recepción y canalización de los asuntos que sean competencia de la Fiscalía General.\nTendrá las siguientes facultades:\nI. Coordinar la gestión, movilidad e integración de las Unidades de investigación y litigio, garantizando la independencia y condiciones de dichas unidades, designando a los fiscales encargados de los casos, salvo que aquellos sean nombrados por la persona Titular de la Fiscalía\nGeneral quienes realizarán investigaciones de hechos probablemente delictivos;\nII. Dirigir y ejercer la acción penal en los casos que determine la ley de la materia;\nIII. Analizar de forma estratégica los datos agregados del fenómeno criminal, la realización de estudios criminalísticos, criminógenos, criminológicos y geodelictivos, así como la información de contexto que se considere relevante para coadyuvar en la investigación;\n\nIV. Efectuar reportes estratégicos sobre criminalidad por alcaldía, identificación de patrones, estructuras y organizaciones, así como cualquier otro que se considere necesario para la investigación de los casos;\nV. Servir de apoyo para el análisis técnico científico de los actos de investigación y datos de prueba, a solicitud de los fiscales para el desarrollo de sus investigaciones;\nVI. Apoyar la verificación y control de las pruebas periciales y exámenes forenses practicados a solicitud de las autoridades competentes;\nVII. Evaluar riesgos y proteger a las personas ofendidas, víctimas, testigos y demás sujetos procesales en los casos que existan amenazas a su integridad física o psicoemocional y a su vida;\nVIII. Coordinar los esquemas de colaboración con entidades gubernamentales y otras autoridades en la materia de sus competencias para la implementación de los esquemas de seguridad de víctimas, testigos y demás sujetos procesales;\nIX. Dirigir las Unidades de Atención Temprana;\nX. Las demás que señalen otras disposiciones legales aplicables.\nArtículos 61. Coordinación General de Investigación de Delitos de Género y Atención a Víctimas.\nLa Coordinación General de Investigación de Delitos de Género y Atención a Víctimas, en el ámbito de su competencia tendrá las atribuciones siguientes:\nI. Realizar investigaciones de los delitos de violencia de género contra las mujeres y niñas, violencia familiar, delitos sexuales, delitos contra niñas, niños y adolescentes, delitos cometidos contra la población de la diversidad sexual, trata de personas, delitos contra personas adultas mayores, personas integrantes de comunidades indígenas y feminicidio, así como ejercer las funciones en materia de justicia penal para adolescentes y de cualquier otro grupo de atención prioritaria;\nFracción modificada y publicada en la GOCDMX el 25 de mayo de 2023\n\nII. Coordinar las funciones de la unidad de análisis y contexto de los delitos materia de su competencia y prestar la atención multidisciplinaria de urgencia con personal especializado y certificado a través de sus Centros;\nIII. Proponer criterios de actuación y normatividad para el personal policial, ministerial y pericial para la adecuada intervención en la atención e investigación de delitos de violencia de género, dentro del ámbito de su competencia así como para la reparación integral del daño;\nIV. Colaborar en la integración y establecimiento de las unidades de atención temprana, a través del funcionamiento de las Unidades de Protección y Asistencia a víctimas;\nV. Brindar los servicios reconocidos en los instrumentos internacionales, nacionales y locales sobre los derechos de las víctimas de delitos, en especial el derecho a la asistencia, protección, atención, verdad, justicia, reparación integral, y debida diligencia;\nVI. Proporcionar asistencia, atención psicológica, médica, de trabajo social y las demás especializadas de urgencia, pudiendo gestionar la atención médica de urgencia, cuando no esté en condiciones de proporcionarla directamente, según el tipo de delito de violencia de género;\nVII. Garantizar la incorporación de la perspectiva de género e igualdad sustantiva, en la adopción de las medidas de protección a favor de las víctimas y testigos de estos delitos según el marco internacional, nacional y local de los Derechos Humanos de las mujeres y niñas y demás normatividad aplicable;\nVIII. Proponer lineamientos de detección, prevención, canalización, atención, de política criminal de género, y programas de investigación e intervenciones especializadas para la investigación y atención de los delitos de violencia de género;\nIX. Proveer según la competencia de los delitos de violencia de género, la debida protección y asistencia en lugares propios destinados a la seguridad, alojamiento y empoderamiento a las víctimas de estos delitos;\nX. Garantizar que las personas que solicitan el ingreso en el Registro Nacional de Víctimas sean atendidas de manera preferencial y orientadas de forma digna y respetuosa; se orientará a la persona que solicite el ingreso sobre el trámite y efectos de la diligencia;\n\nXI. Solicitar la intervención de expertos independientes locales, nacionales e internacionales, a fin de que colaboren con las autoridades competentes en investigación de los hechos y la realización de peritajes, en los casos que impliquen graves violaciones a los Derechos Humanos y violencia de género con la realización de peritajes, dictámenes o impresiones diagnosticas especializadas, para estos últimos;\nXII. Establecer coordinación inmediata con la Comisión Ejecutiva de Atención a Víctimas, con la\nComisión Ejecutiva de Atención a Víctimas de la Ciudad de México, así como los órganos públicos necesarios para el desempeño y ejecución de acciones e investigaciones de los delitos que sean de su competencia;\nFracción modificada y publicada en la GOCDMX el 25 de mayo de 2023\nXIII. Establecer y Promover mecanismos de coordinación, colaboración, y concertación con instituciones públicas y privadas, locales, nacionales e internacionales, para la efectiva protección, ayuda, asistencia, atención y reparación integral a las víctimas de los delitos previstos en normatividad nacional e internacional de acuerdo con los estándares internacionales en la materia, en especial de derechos humanos de mujeres y niñas;\nXIV. Coordinar acciones en materia de asesoría jurídica penal y asistencia victimal con la\nComisión Ejecutiva de Atención a Víctimas local, conforme a la Ley de Víctimas para la Ciudad de\nMéxico y las disposiciones transitorias de la presente Ley;\nXV. Las demás que señalen otras disposiciones legales aplicables en la materia.\nArtículo 62. Coordinación General Jurídica y de Derechos Humanos\nLa Coordinación General Jurídica y de Derechos Humanos tendrá las atribuciones siguientes:\nI. Representar a la Fiscalía General en los procedimientos administrativos o jurisdiccionales de los que forme parte;\nII. Formular los informes previos y justificados en los juicios de amparo promovidos contra actos del Fiscal General y las personas Coordinadoras Generales y representarlos en los juicios de garantías respectivos, incluso ofrecer pruebas y recursos correspondientes;\n\nIII. Representar al Fiscal General, en las acciones de inconstitucionalidad y controversias constitucionales a que se refiere el artículo 105, fracciones I y II de la Constitución Federal y su\nLey reglamentaria;\nIV. Brindar asesoría jurídica a las áreas de la Fiscalía General, emitiendo para tal efecto las observaciones y comentarios a los proyectos y documentos que le sean sometidos a su consideración;\nV. Revisar y someter a consideración la persona Titular Fiscal General los anteproyectos de leyes, reformas, reglamentos, decretos, acuerdos, circulares y demás normativa, que formulen las áreas en el ámbito de sus competencias;\nVI. Elaborar, compilar y difundir los acuerdos, Protocolos, circulares y normativa expedida por la persona Titular de la Fiscalía General;\nVII. Revisar el contenido jurídico de convenios, contratos y demás actos que formulen las áreas en el ámbito de sus competencias, en los que intervenga la Fiscalía General, observando el cumplimiento de los requisitos legales correspondientes;\nVIII. Coadyuvar con la Unidad de Estadística y Transparencia de la Fiscalía General y gestionar el cumplimiento de las obligaciones que impone la normativa general y local aplicable;\nIX. Dar seguimiento a la atención de las quejas, recomendaciones, propuestas de conciliación, medidas cautelares y requerimientos formulados por las Comisiones Nacional y Estatal de\nDerechos Humanos, así como Organismos Internacionales de la materia;\nX. Promover, gestionar y vigilar el trámite y procedimiento de extradición y asistencia jurídica internacional, de conformidad a lo establecido por la Ley de la materia y Tratados Internacionales de los que el Estado Mexicano sea parte, así como en los convenios de colaboración celebrados entre los Estados;\nXI. Gestionar las solicitudes de colaboración entre Fiscalías u órganos de procuración de justicia, que sean solicitadas por los Agentes del Ministerio Público de esta dependencia y las que sean requeridas por otras entidades federativas; y\n\nXII. Coordinar y supervisar al Órgano de Gestión Administrativa de Casos No Penales y a la\nSupervisión General de Justicia Alternativa, y\nFracción modificada y publicada en la GOCDMX el 25 de mayo de 2023\nXIII. Las demás que le señalen las leyes, reglamentos y otras disposiciones jurídicas, así como las que le encomiende y delegue la persona Titular de la Fiscalía General.\nArtículo 63. Coordinación General de Investigación Estratégica.\nLa Coordinación General de Investigación Estratégica tendrá a su cargo la investigación y persecución de los siguientes delitos: homicidio, robo de vehículos, fraude, abuso de confianza, fraude procesal, encubrimiento por receptación, financieros y los demás que señalen las disposiciones normativas aplicables.\nLa persona Titular de la Fiscalía General podrá establecer en el Reglamento de esta ley o mediante acuerdo, la creación de Fiscalías para investigar y perseguir dichos delitos, para lo cual nombrará y removerá libremente a sus titulares, quienes ejercerán las atribuciones del Ministerio Público señaladas en la presente Ley y demás normativa.\nLas citadas fiscalías estarán jerárquicamente subordinadas a la Coordinación General de Investigación\nEstratégica, la cual coordinará, vigilará, supervisará y orientará las actuaciones de dichas fiscalías.\nTendrá las siguientes facultades:\nI. Dirigir la investigación y ejercer la acción penal en los casos que determine la ley de la materia;\nII. Coordinar los esquemas de colaboración con otras autoridades en la materia de sus competencias;\nIII. Garantizar la independencia y condiciones de trabajo de las unidades de investigación y litigio;\nIV. Analizar de forma estratégica los datos agregados del fenómeno criminal, la realización de estudios criminalísticos, criminógenos criminológicos y geodelictivos, así como la información de contexto que se considere relevante para coadyuvar en la investigación;\n\nV. Efectuar reportes estratégicos sobre criminalidad por tipos de delitos, identificación de patrones, estructuras y organizaciones criminales, así como cualquier otro que se considere necesario para la investigación de los casos y suministrar dicha información al Órgano de Política\nCriminal;\nVI. Comunicar la información de utilidad relativa a la seguridad ciudadana que obtenga en el ejercicio de sus funciones para que la remita a la autoridad competente en su caso;\nVII. Evaluar riesgos y proteger a las personas ofendidas, víctimas, testigos y demás sujetos procesales en los casos que existan amenazas a su integridad o vida;\nVIII. Coordinar y colaborar con otras entidades gubernamentales para la implementación de los esquemas de seguridad de víctimas, testigos y demás sujetos procesales;\nIX. Las demás que señalen otras disposiciones jurídicas aplicables.\nArtículo 63 Bis. Coordinación General de Investigación de Delitos de Alto impacto.\nLa Coordinación General de Investigación de Delitos de Alto Impacto tiene a su cargo la investigación de los siguientes delitos: secuestro, extorsión, narcomenudeo, desaparición forzada de personas y desaparición cometidas por particulares, así como cualquier otro que, por su relevancia social, peligrosidad o reiteración, deba ser retraído a su competencia, previa autorización de la persona Titular de la Fiscalía\nGeneral, y tiene las siguientes facultades:\nPárrafo modificado y publicado en la GOCDMX el 25 de mayo de 2023\nTendrá las siguientes facultades:\nI. Dirigir la investigación y ejercer la acción penal en los casos que determine la ley de la materia;\nII. Coordinar los esquemas de colaboración con otras autoridades en la materia de sus competencias;\nIII. Garantizar la independencia y condiciones de trabajo de las unidades de investigación y litigio;\n\nIV. Analizar de forma estratégica los datos agregados del fenómeno criminal, la realización de estudios criminalísticos, criminógenos criminológicos y geodelictivos, así como la información de contexto que se considere relevante para coadyuvar en la investigación;\nV. Efectuar reportes estratégicos sobre criminalidad por tipos de delitos, identificación de patrones, estructuras y organizaciones, así como cualquier otro que se considere necesario para la investigación de los casos;\nVI. Suministrar información al Órgano de Política Criminal, relativa a los patrones, estructuras y organizaciones criminales para el diseño de las políticas institucionales y toma de decisiones;\nVII. Comunicar la información de utilidad relativa a la seguridad ciudadana que obtenga en el ejercicio de sus funciones para que la remita a la autoridad competente en su caso;\nVIII. Evaluar riesgos y proteger a las o los ofendidos, víctimas, testigos y demás sujetos procesales en los casos que existan amenazas a su integridad o vida;\nIX. Coordinar y colaborar con otras entidades gubernamentales para la implementación de los esquemas de seguridad de víctimas, testigos y demás sujetos procesales;\nX. Sistematizar la información obtenida a través de las distintas investigaciones realizadas;\nXI. Solicitar información a las compañías proveedoras de telefonía móvil y fija, con los requisitos que señale la ley;\nXII. Establecer coordinación inmediata con la Comisión Nacional de Búsqueda de personas, con la Comisión de Búsqueda de Personas de la Ciudad de México u homólogas de las Entidades\nFederativas, así como con órganos públicos necesarios para el desempeño y ejecución de las acciones de búsqueda y localización de personas desaparecidas y demás que sean de su competencia, y\nFracción modificada y publicada en la GOCDMX el 25 de mayo de 2023\nXIII. Las demás que señalen otras disposiciones jurídicas aplicables.\nArtículo 64. Coordinación General de Administración\n\nLa Coordinación General de Administración será la entidad encargada de administrar y gestionar los recursos humanos, materiales y financieros de la Fiscalía General. Son facultades de la Coordinación\nGeneral de Administración:\nI. Consolidar la información administrativa y financiera para elaborar estudios e informes;\nII. Elaborar y orientar el programa de inversiones en infraestructura física;\nIII. Tener a su cargo la administración de los recursos humanos, materiales, tecnológicos, financieros, patrimoniales, presupuestales y cualquier otro asignado a la Fiscalía General de conformidad con las políticas aprobadas por el Fiscal General en esta materia y con los criterios acordados con el Órgano de Política Criminal, así como los bienes asegurados, en los términos de la normatividad aplicable;\nIV. Representar a la Fiscalía General en materia de administración de los recursos humanos, materiales, tecnológicos, financieros, patrimoniales, presupuestales y cualquier otro de conformidad con las políticas aprobadas por la persona titular Fiscal General;\nV. Ejercer los actos de administración, de mandatario judicial y de dominio que requiera la\nFiscalía General para su debido funcionamiento de conformidad con las políticas aprobadas por la persona titular de la Fiscalía General y de conformidad con lo que prevea el reglamento;\nVI. Proponer, para su aprobación, los criterios generales en materia administrativa para proporcionar los servicios administrativos generales que requieran las áreas de la Fiscalía\nGeneral;\nVII. Establecer y controlar las políticas y procedimientos de adquisición, aprovechamiento y administración de bienes y servicios;\nVIII. Aprobar el uso de los recursos financieros de la Fiscalía General en materia de contrataciones, ejercicio del gasto, adquisiciones, arrendamientos y contratación de bienes, servicios y obras públicas, así como de asociaciones público-privadas de conformidad con la normativa aplicable;\nIX. Administrar y ejercer los fondos federales y locales destinados a la procuración de justicia de conformidad con los ordenamientos jurídicos aplicables, transparentando su aplicación;\n\nX. Establecer El Comité de Adquisiciones de conformidad con el Reglamento que emita la persona titular de la Fiscalía General;\nXI. Suscribir convenios o cualquier otro acto o instrumento jurídico en el ámbito administrativo que tenga relación con los fines que a la Fiscalía General le encomienda la Constitución Local, la presente ley y demás ordenamientos jurídicos aplicables;\nXII. Colaborar con el titular de Instituto de Formación Profesional y Estudios Superiores para asegurar la suficiencia presupuestal para el cumplimiento y desarrollo de los rubros que contempla el Servicio Profesional de Carrera;\nXIII. Vigilar el cumplimiento, de las disposiciones en materia de planeación, presupuesto, ingresos y patrimonio;\nXIV. Emitir las normas para que los recursos patrimoniales y financieros sean aprovechados y aplicados, respectivamente, con criterios de eficacia, legalidad, eficiencia y simplificación administrativa; así como, realizar o encomendar las investigaciones, estudios y análisis necesarios sobre estas materias, todo lo anterior, en acuerdo con la persona Fiscal General;\nXV. Realizar auditorías, revisiones y evaluaciones a las áreas de la Fiscalía General, con el objeto de examinar, fiscalizar y promover la eficiencia, eficacia y legalidad en su gestión y encargo;\nXVI. Llevar y normar el registro de las personas servidoras públicas de la Fiscalía General;\nXVII. Elaborar y someter a la aprobación de la persona titular de la Fiscalía General el proyecto de presupuesto anual de egresos del organismo;\nXVIII. Diseñar, la política del sistema de gestión documental así como los sistemas y mecanismos de sistematización y análisis de la información a fin de apoyar el desarrollo de las funciones sustantivas de la Fiscalía General;\nXIX. Realizar toda clase de actos jurídicos y administrativos con relación a los bienes asegurados;\nXX. Las demás atribuciones que le sean aplicables por la naturaleza de sus funciones.\n\nArtículo 65. Jefatura General de la Policía de Investigación\nLa Jefatura General de la Policía de Investigación, tendrá las atribuciones y obligaciones siguientes:\nI. Desplegar metodologías científicas y técnicas para desarrollar una investigación exhaustiva, completa e imparcial de los delitos cometidos, bajo la conducción y mando del Ministerio\nPúblico;\nII. Realizar los actos de investigación que les instruyan las personas fiscales y cumplimentar las actuaciones procesales que ordene la autoridad jurisdiccional;\nIII. Verificar la información que reciba sobre hechos probablemente delictivos y, en su caso, hacerla del conocimiento inmediato de la persona Ministerio Público;\nIV. Recibir las denuncias sobre hechos con apariencia de delito, de acuerdo a las obligaciones que establece el Código Nacional;\nV. Proporcionar protección y atención a personas víctimas, ofendidas o testigos del delito, en los términos que determine el Reglamento de esta Ley;\nVI. Efectuar las detenciones, realizando el registro inmediato conforme lo señale la normativa aplicable;\nVII. Integrar grupos de tarea y grupos especializados, para operaciones que requieran especialidades científicas o técnicas, conforme a lo dispuesto en esta Ley, conforme a lo establecido en el Reglamento de esta Ley;\nVIII. Preservar y procesar el lugar de los hechos o del hallazgo, conservando la integridad de objetos, instrumentos o productos y cualquier evidencia física relacionada con los hechos investigados, conforme a las normas y protocolos aplicables;\nIX. Recolectar y resguardar los objetos, instrumentos y productos vinculados a la investigación criminal, realizando la cadena de custodia y utilizando protocolos de actuación mínima;\n\nX. Solicitar a las autoridades competentes y a las personas físicas o morales los informes, documentos y material audio o videográfico que sea indispensable para la investigación de los delitos cometidos;\nXI. Elaborar los registros de los actos de investigación que se realicen para incorporarlos a la carpeta de investigación y remitirlos a la persona Ministerio Público;\nXII. Efectuar análisis técnico, táctico o estratégico de la información obtenida para la generación de líneas de investigación que conduzca al esclarecimiento de los hechos delictivos;\nXIII. Llevar a cabo operaciones encubiertas en la investigación de delitos, previo control judicial y en los términos y con los requisitos que determine la normativa;\nXIV. Desarrollar, mantener y supervisar fuentes de información en la sociedad, que permitan obtener datos sobre actividades relacionadas con fenómenos delictivos;\nXV. Dar cumplimiento a las órdenes de aprehensión, cateo, intervenciones de comunicaciones que sean autorizadas por la persona juez de control, aportando de inmediato los datos de prueba que se obtengan al Ministerio Público;\nXVI. Realizar las entrevistas a las personas que puedan proporcionar datos o elementos de prueba;\nXVII. Desarrollar todos los actos de investigación sin afectar el derecho de las personas a la protección de sus datos;\nXVIII. Cuando las necesidades de la investigación criminal lo requieran, pedir de inmediato a la persona Ministerio Público, que solicite autorización judicial, para que los concesionarios, permisionarios; operadoras telefónicas y comercializadoras de servicios en materia de telecomunicaciones o de sistemas de comunicación vía satélite, la información en tiempo real vinculada a los hechos delictivos que se investigan, así como la georreferenciación de los equipos de comunicación móvil;\nXIX. Realizar acciones de vigilancia, identificación, monitoreo y rastreo en la red pública de internet con el fin de investigar actos delictivos;\n\nXX. Operar sistemas, bases de datos y plataformas tecnológicas para el adecuado control y desarrollo de las investigaciones realizadas;\nXXI. Registrar en el Informe Policial Homologado los datos de las actividades e investigaciones que realice, conforme a la normativa;\nXXII. Proponer convenios de coordinación con otras instituciones policiales de los tres órdenes de gobierno, así como con organizaciones no gubernamentales para el apoyo y colaboración en la investigación de los delitos;\nXXIII. Las demás que le asigne de manera directa la persona Fiscal General.\nXXIV. En todos los actos de investigación que realicen deberán evitar cometer actos de revictimización;\nFracción adicionada y publicada en la GOCDMX el 23 de agosto de 2024\nXXV. Aplicar estrictamente en la acreditación de los delitos que sean en contra de la comunidad\nLGBTTTI, con especial atención en el delito de transfeminicidio, el Protocolo de Actuación para la\nAtención a las personas de la Comunidad LGBTTTI; y\nFracción adicionada y publicada en la GOCDMX el 23 de agosto de 2024\nXXVI. Evitar en todo momento los prejuicios y estereotipos de género o de sumisión, así como de roles tradicionales asociados a factores sociales, culturales o laborales, como la forma de vestir, la expresión verbal o corporal, la condición socioeconómica o étnica, las preferencias sexuales, identidad género y expresión de género o las actividades a que se dedique la persona, sea víctima o inculpada.\nFracción adicionada y publicada en la GOCDMX el 23 de agosto de 2024\nCAPÍTULO SEGUNDO\nÓRGANOS AUXILIARES\nArtículo 66. Se Deroga.\nArtículo derogado y publicado en la GOCDMX el 25 de mayo de 2023\n\nArtículo 66 Bis. Coordinación General de Acusación, Procedimiento y Enjuiciamiento.\nArtículo adicionado y publicado en la GOCDMX el 25 de mayo de 2023\nLa Coordinación General de Acusación, Procedimiento y Enjuiciamiento tiene las facultades siguientes:\nI. Establecer un control de los registros de las audiencias celebradas por el Ministerio Público antes las autoridades jurisdiccionales;\nII. Coordinar a las Fiscalías y Unidades Operativas a su cargo, para intervenir en los procesos que se lleven ante los Jueces de Control, Tribunal de Enjuiciamiento, Jueces de Ejecución Penal y\nTribunal de Alzada, presentando oportunamente las acusaciones correspondientes, aportando las pruebas tendientes a comprobar la responsabilidad penal de las personas imputadas y acreditar la reparación del daño, conforme a la normatividad aplicable; requerir la imposición de penas o medidas de seguridad que correspondan al ejercer la acción penal;\nIII. Supervisar que las personas Titulares de Fiscalías a su cargo, instruyan al personal ministerial que corresponda, para que éste acuda a las diligencias o audiencias que se practiquen ante las autoridades jurisdiccionales y desahoguen las vistas correspondientes;\nIV. Proponer criterios de actuación para el personal ministerial de las Fiscalías y Unidades\nOperativas a su cargo, para actos que tengan por resultado el sobreseimiento del proceso o la libertad absoluta de la persona imputada;\nV. Autorizar, previa propuesta y aprobación de las personas Titulares de las Fiscalías de su adscripción, la reducción de pena en los procedimientos abreviados;\nVI. Supervisar que las personas Titulares de Fiscalías a su cargo, instruyan a su personal ministerial para que los procesos se sigan con regularidad y, en su caso se interpongan los recursos o acciones legales procedentes;\nVII. Coordinar la elaboración y presentación, ante los órganos jurisdiccionales competentes, de agravios, contestaciones, apelaciones adhesivas y la intervención que corresponda como tercero interesado en los juicios de amparo y demás asuntos de su competencia;\nVIII. Supervisar que la Fiscalía de Procesos en Juzgados Civiles, presten los servicios correspondientes a la representación social en juicios del orden civil;\n\nIX. Solicitar ante los órganos jurisdiccionales competentes y a través de la Fiscalía Especializada en la materia, la acción de extinción de dominio y en su caso aprobar la propuesta del Ministerio\nPúblico sobre la improcedencia o desistimiento de la acción;\nX. Coordinar a través del área de gestión y análisis procesal, el registro correspondiente de las carpetas de investigación recibidas; coordinar, en tanto subsista el Sistema Mixto, la recepción de las averiguaciones previas, en las que se proponga el ejercicio de la acción penal, y se turnen a la Dirección de consignaciones del Poder Judicial de la Ciudad de México; así como la recepción de Carpetas de Investigación remitidas por el personal ministerial investigador, previo acuerdo de cierre de investigación complementaria, para su remisión a la Fiscalía de Acusación y\nEnjuiciamiento correspondiente;\nXI. Supervisar que el área de Gestión y Análisis Procesal, reciba y notifique al Poder Judicial de la Ciudad de México, las audiencias solicitadas por el personal ministerial;\nXII. Coordinar a las Fiscalías y Unidades Operativas del Sistema Mixto a su cargo, para que intervengan conforme a derecho en los procesos ante las autoridades jurisdiccionales, aportando las pruebas tendientes a comprobar la responsabilidad penal de los indiciados y exigir la reparación integral del daño, conforme a la normatividad aplicable;\nXIII. Supervisar la gestión de requerimientos que realice la autoridad judicial por demoras, excesos o faltas del personal ministerial a las audiencias;\nXIV. Coordinar el enlace entre la Unidad de Supervisión de Medidas Cautelares (USMECA) del\nPoder Judicial de la Ciudad de México y las Unidades Administrativas de la Fiscalía General;\nXV. Supervisar que en las carpetas de investigación en las que haya concluido el plazo de investigación complementaria, se solicite la terminación anticipada del proceso;\nXVI. Supervisar la remisión de Carpetas Judiciales en las que el órgano jurisdiccional determine la declinación competencia, para la continuación de la secuela procesal en la Unidad de Gestión\nJudicial que corresponda;\nXVII. Proponer criterios orientadores relacionados con las resoluciones que se recurran ante el\nPoder Judicial de la Ciudad de México;\n\nXVIII. Supervisar el registro de altas, control y seguimiento de las Órdenes Judiciales hasta su cumplimiento o cancelación;\nXIX. Desarrollar con la Jefatura General de la Policía de Investigación, programas para la ejecución de órdenes judiciales, de conformidad con los términos de prescripción, cancelación o suspensión que las vuelvan inejecutables, y\nXX. Las demás que la persona Titular de la Fiscalía General y la normatividad aplicable determinen.\nArtículo 67. La Supervisión General de Justicia Alternativa\nDicha Supervisión tendrá las siguientes facultades:\nI. Coordinar la aplicación de los métodos alternativos de solución de controversias en materia penal, a través de los mecanismos alternativos de solución de controversias con que cuenta La\nFiscalía General;\nII. Recibir y analizar las derivaciones realizadas por la persona Ministerio Público o el Juez de\nControl en términos de la Ley Nacional de Mecanismos Alternativos de Solución de Controversias en Materia Penal, e informar a la autoridad que hubiere realizado la derivación, sobre los acuerdos alcanzados para su aprobación;\nIII. Determinar la procedencia de resolver una controversia mediante la aplicación de un mecanismo alternativo y, en consecuencia, de una solución alterna, de conformidad con el\nCódigo Nacional de Procedimientos Penales, la Ley Nacional de Mecanismos Alternativos de\nSolución de Controversias en Materia Penal y en la Ley Nacional del Sistema Integral de Justicia\nPenal para Adolescentes, salvo las que se refieren a violencia familiar y delitos sexuales;\nIV. Informar durante el seguimiento de los acuerdos reparatorios alcanzados por los intervinientes a la persona Ministerio Público, Juez de Control y los intervinientes sobre el cumplimiento o incumplimiento de estos, con el monitoreó respectivo;\n\nV. Emitir las directrices para promover la solución alternativa de los conflictos en el ámbito de\nProcuración de Justicia, entre las personas denunciantes, querellantes, víctimas, ofendidas, imputadas y en programas de capacitación estandarizados para el capital humano;\nVI. Registrar y actualizar el Sistema Integral del Seguimiento de Expedientes del Registro\nNacional de Mecanismos Alternativos de Solución de Controversias en Materia Penal;\nVII. Establecer estudios estadísticos en torno al funcionamiento del servicio proporcionado, el porcentaje de cumplimiento e incumplimiento de los acuerdos y los casos de reiteración de las controversias entre los intervinientes, desagregadas por sexo;\nVIII. Elaborar en coordinación con las unidades administrativas competentes de la Fiscalía\nGeneral, los proyectos de lineamientos generales de operación y funcionamiento, así como la estrategia de difusión para promover la utilización de los mecanismos alternativos;\nIX. Promover la certificación del capital humano que tenga adscrito;\nX. Las demás que señale la normativa aplicable.\nArtículo 68. Órgano de Gestión Administrativa de Casos No Penales\nEl Órgano de Gestión Administrativa de casos no penales tendrá las siguientes facultades:\nI. Realizar criterios estratégicos de vinculación con los entes públicos locales y federales, para agilizar los trámites de conflictos no penales denunciados en las oficinas del Ministerio Público;\nII. Coordinar las Unidades de Gestión Administrativa de casos no penales;\nIII. Atender aquellos casos que no representan lesión grave a los bienes jurídicos tutelados por las leyes penales;\nIV. Canalizar los conflictos de naturaleza distinta a la penal a las oficinas competentes para su resolución;\nV. Expedir constancia de extravíos de bienes y documentos;\n\nVI. Las demás que le confiera la persona titular de la Fiscalía General de Justicia de la Ciudad de\nMéxico.\nTÍTULO QUINTO\nDEL INSTITUTO DE FORMACIÓN PROFESIONAL Y ESTUDIOS\nSUPERIORES\nCAPÍTULO PRIMERO\nGENERALIDADES\nArtículo 69. Naturaleza del Instituto\nEl Instituto de Formación Profesional y Estudios Superiores es un órgano desconcentrado de la Fiscalía con autonomía técnica y de gestión, facultado para diseñar e implementar el Servicio Profesional de Carrera del personal sustantivo; desarrollar actividades académicas, de posgrado, de investigación, y de extensión académica en las materias relacionadas con el sistema de justicia penal; coadyuvar en la elaboración del\nPrograma de Gestión y Desarrollo Humano, con el objetivo de alcanzar la especialización técnica y científica y contribuir en el proyecto de vida profesional de las personas servidoras públicas de la Fiscalía.\nDel cual dependerá el Centro de Evaluación y Control de Confianza, cuya operación estará en el\nReglamento.\nArtículo 70. Facultades\nPara el cumplimiento de sus fines y objetivos, el Instituto tendrá las siguientes atribuciones:\nI. Elaborar y someter a la aprobación de la persona Titular de la Fiscalía, los planes y programas, relacionados con el Servicio Profesional de Carrera del personal Sustantivo de la Fiscalía y demás operadores del Sistema de Justicia Penal, así como, el Reglamento Interior del Instituto y sus modificaciones;\nII. Normar, dirigir y ejecutar los procedimientos relativos al Servicio Profesional de Carrera del personal, definir el perfil profesional y competencial sustantivo de la Fiscalía General y demás operadores del Sistema de Justicia Penal, contenidos en los Programas respectivos, considerando en todo momento el principio de paridad de género;\n\nIII. Participar en coordinación con las áreas competentes, en el sistema integral de evaluación de la Fiscalía General, con el objeto de obtener información necesaria para elaboración de diagnósticos, la formulación de los planes y programas relacionados con el Servicio Profesional de Carrera;\nIV. Formular, ejecutar planes, programas académicos y de posgrado, atendiendo las exigencias de profesionalización, capacitación permanente y especialización técnica y científica, de la personal de la Fiscalía y demás operadores del Sistema de Justicia Penal, con o sin vinculación directa con el Servicio Profesional de Carrera, con perspectiva de género;\nV. Expedir títulos, grados, diplomas, constancias, certificados y demás documentación, que acredite los estudios correspondientes a los programas académicos, posgrado, extensión académica que implemente y ejecute el Instituto;\nVI. Diseñar y desarrollar proyectos de investigación sobre temas relacionados con las ciencias penales, política y criminal;\nVII. Integrar la plantilla del personal docente y de investigación del Instituto, así como, regular sus funciones y actividades;\nVIII. Proponer al titular de la Fiscalía, la celebración de convenios, bases y otros instrumentos de coordinación, con instituciones similares del país o del extranjero, para el desarrollo profesional, de las ciencias penales y de la política criminal;\nIX. Aplicar las evaluaciones de Conocimientos Generales y de Competencias Profesionales del personal sustantivo de la Fiscalía;\nX. Coordinar la aplicación de las evaluaciones de Control de Confianza del personal sustantivo de la Fiscalía General, a través de su Centro de Evaluación y Control de Confianza;\nXI. Suscribir convenios, bases y demás instrumentos con Instituciones del sector público y privado, para la prestación de servicios académicos y de capacitación, relacionados con las ciencias penales;\n\nXII. Establecer y administrar las cuotas de recuperación por la prestación de servicios educativos, posgrado, capacitación y demás actividades académicas a su cargo y que no se encuentren vinculados con el Servicio Profesional de Carrera, de conformidad con las disposiciones aplicables;\nXIII. Gestionar y administrar los recursos asignados al Instituto;\nXIV. Elaborar y expedir el Manual Operativo Escolar y sus modificaciones;\nXV. Coordinar la elaboración y modificaciones al Reglamento del Servicio Profesional de Carrera y del Programa de Gestión de Desempeño y Desarrollo Humano, con las áreas competentes de la Fiscalía,\nXVI. Favorecer la capacitación y certificación de las personas Ministerios Públicos, peritos y todo el personal de la Fiscalía General que se estime necesario en materias de prevención y atención de mujeres, víctimas de violencia; y\nXVII. Las demás que le confieran las normas contenidas en el reglamento de esta ley y demás disposiciones aplicables.\nArtículo 71. Del Titular\nEl Instituto de Formación Profesional y Estudios Superiores de la Fiscalía, estará a cargo de una\nCoordinación General, cuyo titular será designado directamente por el Fiscal General.\nLa estructura, organización y funcionamiento del Instituto, se regirá por la presente Ley, su Reglamento, el\nReglamento Interior del Instituto y demás disposiciones legales aplicables.\nCAPÍTULO II\nDEL SERVICIO PROFESIONAL DE CARRERA\nArtículo 72. Servicio Profesional.\n\nEl Servicio Profesional de Carrera, será el sistema integral de regulación del empleo público del personal sustantivo que preste sus servicios en la Fiscalía General, el cual comprenderá: ingreso, permanencia, promoción, estímulos y separación.\nPara el ingreso y promoción del personal sustantivo, se tomará en consideración además de los méritos y perfil, el principio de paridad de género, en especial en lo que se refiere a la policía de investigación, técnica y científica.\nEl personal sustantivo, deberá aprobar las evaluaciones de Conocimientos Generales, de Competencias\nProfesionales y de control de confianza, así como, los cursos de actualización que imparta el instituto y se determinen en el Reglamento.\nLos requisitos y perfiles para el ingreso, capacitación, evaluación, control de confianza y promoción del personal sustantivo, se determinaran en el Reglamento.\nArtículo 73. Regulación del Servicio Profesional\nEl Servicio Profesional de Carrera, estará regulado en el Reglamento correspondiente y se ejecutará de conformidad con los Planes y Programas respectivos, contará para su implementación con los recursos financieros, técnicos y humanos suficientes, para su operación.\nEl Servicio Profesional de Carrera, será organizado con la finalidad de estimular el profesionalismo, la igualdad de oportunidades laborales entre mujeres y hombres, remuneración adecuada, garantías de seguridad social, el crecimiento institucional, el comportamiento ético, la independencia técnica y las prácticas para erradicar conflictos de interés; la iniciativa, innovación y la eficiencia institucional, la capacitación continua todo ello para erradicar violaciones a derechos humanos y los actos de corrupción, mediante una estructura organizada de prevención, seguimiento y mejora continua. Considerando las compensaciones e incentivos debidos para el personal sustantivo.\nArtículo 74. Consejo de Profesionalización del Servicio de Carrera.\nLa Fiscalía, contará con un Consejo de Profesionalización del Servicio de Carrera, quien fungirá como órgano rector en la materia. La integración y atribuciones de este Consejo se establecerán en el Reglamento correspondiente.\n\nTÍTULO SEXTO\nRELACIONES LABORALES Y RÉGIMEN DE RESPONSABILIDADES\nCAPÍTULO PRIMERO\nGENERALIDADES\nArtículo 75. Relaciones con las personas servidoras públicas.\nLas relaciones administrativas entre la Fiscalía General y el personal sustantivo se regirán por lo dispuesto en el artículo 123, Apartado B, fracción XIII de la Constitución Federal, la presente Ley y demás disposiciones aplicables.\nLa Fiscalía General brindará a todas las personas servidoras públicas de su adscripción, las condiciones para que desarrolle sus actividades profesionales en un ambiente libre de discriminación y violencia, buscando la conciliación de la vida laboral con la familiar\nArtículo modificado y publicado en la GOCDMX el 25 de mayo de 2023\nArtículo 76. Régimen de Responsabilidades de las personas servidoras públicas.\nArtículo modificado y publicado en la GOCDMX el 25 de mayo de 2023\nLas personas servidoras públicas de la Fiscalía General, estarán sujetas a lo previsto en la Ley General del\nSistema Nacional de Seguridad Pública, Ley del Sistema de Seguridad Ciudadana de la Ciudad de México,\nLey de Responsabilidades Administrativas de la Ciudad de México, así como a las disposiciones establecidas en esta Ley, su Reglamento y demás normatividad aplicable.\nSon obligaciones de las personas servidoras públicas de la Fiscalía General:\nI. Combatir la impunidad;\nII. Evitar la infiltración de conductas delictivas o de corrupción en las Unidades administrativas;\nIII. Promover la eficiencia y eficacia de la gestión pública;\nIV. Abstenerse de prácticas de Acoso y Hostigamiento Sexual de cualquier índole al interior de la\nFiscalía General, de conformidad con la normatividad aplicable;\n\nV. Favorecer un clima laboral sin violencia de ningún tipo entre las personas servidoras públicas;\nVI. Garantizar la debida aplicación de los Protocolos de investigación y atención que se emitan para el buen desempeño de la Fiscalía General;\nVII. Favorecer que las víctimas del delito sean atendidas y se garantice la reparación integral del daño; VIII. Garantizar el sigilo de las investigaciones, y evitar filtraciones a personas no autorizadas;\nIX. Promover el uso eficiente y responsable y la gestión competente de los recursos de la Fiscalía\nGeneral;\nX. Denunciar ante las autoridades competentes hechos de corrupción con apariencia de delito;\nXI. Cumplir con el Código de Ética de la Fiscalía General, y\nXII. Las que señale el Reglamento de esta Ley y demás disposiciones aplicables.\nArtículo 77. Incompatibilidades con el Servicio Público\nEn el desempeño de sus funciones, las personas servidoras públicas de la Fiscalía General no podrán:\nI. Desempeñar empleo, cargo o comisión de cualquier naturaleza en otro ente público federal, local, estatal, organismo autónomo o descentralizado, municipal, de las Alcaldías, poder legislativo o poder judicial, así como trabajos o servicios en instituciones privadas, salvo los de carácter docente y aquellos que autorice la Fiscalía General, siempre y cuando no sean incompatibles con sus funciones en la misma;\nII. Ejercer la abogacía por sí o por interpósita persona;\nIII. Conocer de asuntos cuando pudieran incurrir en conflictos de interés;\nIV. Ejercer las funciones de tutor, curador o albacea judicial, a no ser que tenga el carácter de heredero o legatario o se trate de sus ascendientes, descendientes, hermanos, adoptante o adoptado;\n\nV. Desempeñar las funciones de depositario o apoderado judicial, síndico, administrador, interventor en quiebra o concurso, notario, corredor, comisionista, árbitro o arbitrador; y\nVI. Las demás explícitamente señaladas en otras disposiciones legales.\nCAPÍTULO SEGUNDO\nDE LA UNIDAD INTERNA DE COMBATE A LA CORRUPCIÓN Y LA\nINFILTRACIÓN DE LA DELINCUENCIA ORGANIZADA\nArtículo 78. Unidad interna de combate a la corrupción y la infiltración de la delincuencia organizada.\nTendrá como función llevar a cabo las investigaciones de los casos que sean de su conocimiento en los que estén involucrados servidores públicos adscritos a la Fiscalía General, relacionados con corrupción y delincuencia organizada. Para tal efecto llevará a cabo todas las acciones que sean necesarias.\nSi derivado de sus investigaciones obtiene elementos que acrediten la posible comisión de algún delito, dará parte a las instancias competentes.\nLa persona Titular de la Fiscalía General deberá dotar a esta Unidad interna de todos los instrumentos jurídicos, así como de los recursos técnicos, informáticos, materiales y financieros para el cumplimiento de sus atribuciones.\nEl reglamento de la presente ley establecerá el funcionamiento de esta unidad interna.\nTITULO SEXTO\nCAPÍTULO TERCERO\nDE LA UNIDAD DE ASUNTOS INTERNOS Y DEL CONSEJO DE\nASUNTOS INTERNOS\nModificado y publicado en la GOCDMX el 25 de mayo de 2023\nArtículo 79. Unidad de Asuntos Internos.\nArtículo modificado y publicado en la GOCDMX el 25 de mayo de 2023\n\nLa Unidad de Asuntos Internos cuenta con las siguientes facultades:\nLa Unidad de Asuntos Internos tendrá el carácter de Secretaría Ejecutiva del Consejo y estará adscrita a la\nOficina de la persona titular de la Fiscalía General.\nLa Unidad de Asuntos Internos cuenta con las siguientes facultades:\nI. Investigar el incumplimiento de las obligaciones del personal ministerial, pericial de estructura y administrativo, previstas en la normatividad aplicable;\nII. Instrumentar, de conformidad con la normatividad aplicable, el procedimiento de investigación de oficio o por queja, en contra del personal ministerial y pericial de la Fiscalía\nGeneral, por incumplimiento de las disposiciones jurídicas aplicables al ejercicio de sus funciones; así como substanciar el procedimiento disciplinario correspondiente y dar vista al\nÓrgano Interno de la Fiscalía General; al Consejo de Honor de la Policía de Investigación; a la\nFiscalía Especializada en Combate a la Corrupción de la Ciudad de México y demás autoridades competentes;\nIII. Emitir y aplicar, en cualquier momento de la investigación o procedimiento, medidas cautelares o precautorias cuando se incumpla cualquiera de las obligaciones previstas en el\nReglamento del Régimen Disciplinario del Personal Sustantivo de la Fiscalía General de Justicia de la Ciudad de México;\nIV. Conocer de las quejas que presenten las personas usuarias por probables irregularidades del personal ministerial y pericial de la Fiscalía General y, en su caso, iniciar el procedimiento correspondiente;\nV. Establecer mecanismos de vigilancia de la función del personal ministerial y pericial, conforme a la normatividad que emita la persona titular de la Fiscalía General;\nVI. Hacer del conocimiento a la autoridad competente, aquellos hechos que no sean materia de la Unidad de Asuntos Internos, advertidos en el ejercicio de sus funciones o con motivo de ellas;\n\nVII. Emitir recomendaciones relacionadas con el desempeño del personal adscrito a las Unidades\nAdministrativas de la Fiscalía General y con mecanismos para prevenir el incumplimiento de las obligaciones del personal ministerial y pericial que establezca la normatividad aplicable;\nVIII. Llevar a cabo, en el ámbito de su competencia, las recomendaciones y acuerdos que emita el Consejo Ciudadano de la Fiscalía General;\nIX. Definir lineamientos de supervisión y vigilancia de las Unidades Administrativas y Órganos\nOperativos de la Fiscalía de Justicia;\nX. Supervisar y vigilar a través de visitas, estudios monitoreo y medios electrónicos, el cumplimiento de la normatividad aplicable;\nXI. Elaborar Actas necesarias en las que se haga constar hechos, circunstancias, situaciones o probables conductas irregulares de las personas servidoras públicas de la Fiscalía General, en términos de las disposiciones que para tal efecto se admitan, y\nXII. Las demás que señale el Reglamento de esta Ley y demás disposiciones aplicables.\nEl procedimiento disciplinario que sustancie la Unidad de Asuntos Internos deberá respetar en todo momento, la garantía de audiencia y legalidad respectiva y sólo preverá el Recurso de Reconsideración.\nArtículo 80. Consejo de Asuntos Internos.\nArtículo modificado y publicado en la GOCDMX el 25 de mayo de 2023\nEl Consejo de Asuntos Internos es el órgano colegiado de la Fiscalía General encargado de resolver si la actuación del personal ministerial y pericial se ajustó a lo establecido en la normatividad aplicable, y al respeto irrestricto a los Derechos Humanos.\nEl procedimiento disciplinario que sustancie el Consejo de Asuntos Internos deberá respetar en todo momento, la garantía de audiencia y de legalidad respectiva.\nEl Consejo de Asuntos Internos cuenta con las facultades siguientes:\n\nI. Emitir las resoluciones del Procedimiento Disciplinario por incumplimiento de las obligaciones del personal ministerial y pericial, de conformidad con la normatividad aplicable. Sus resoluciones serán inatacables y definitivas.\nEn términos del artículo 123, Apartado B, Fracción XIII de la Constitución Federal será improcedente la reinstalación del personal ministerial y pericial destituido, cualquiera que sea el resultado del juicio o medio de defensa que hubiere promovido, y en su caso, sólo procederá su indemnización. Cuando los órganos jurisdiccionales condenen al pago de haberes dejados de percibir o remuneración ordinaria, éstos se cubrirán hasta por un máximo de doce meses, con base en el tabulador vigente de la fecha en que para tal efecto se exhiba.\nII. Coordinar con las Unidades Administrativas competentes, la implementación de estrategias de prevención de actos de corrupción y el fomento de buenas prácticas en materia de rendición de cuentas;\nIII. Promover el cumplimiento del Código de Ética de la Fiscalía General, y\nIV. Generar políticas y programas con enfoque preventivo para evitar la infiltración de conductas delictivas o de corrupción en las Unidades Administrativas.\nArtículo 81. Intervención.\nEl Consejo de Asuntos Internos intervendrá en los casos del personal ministerial y pericial, sometidos a su consideración por parte de la Unidad de Asuntos Internos, con independencia de cualquier tipo de responsabilidad en que pudiera incurrir dicho personal, de conformidad con la normatividad aplicable.\nArtículo modificado y publicado en la GOCDMX el 25 de mayo de 2023\nArtículo 82. Integración\nEl Consejo de Asuntos Internos se integrará por las personas titulares que se señalan a continuación, no pudiendo existir al respecto suplencias, salvo en el caso de la Fiscal General.\nI. La persona titular de la Fiscalía General, en su calidad de persona titular de la Presidencia;\nII. La persona titular de la Unidad de Asuntos Internos, en su calidad de persona titular de la\nSecretaría Ejecutiva;\n\nIII. Las personas titulares de la Fiscalía Especializada en Combate a la Corrupción y de la Fiscalía\nEspecializada para la Atención de Delitos Electorales;\nIV. Las personas titulares de las Coordinaciones Generales previstas en esta Ley y su Reglamento, y\nV. Las demás personas servidoras públicas de la Fiscalía General que apruebe el Consejo de\nAsuntos Internos.\nTodo lo referente a la operación y funcionamiento del Consejo de Asuntos Internos se establecerán en la normatividad aplicable. En caso de empate en las votaciones, la persona titular de la Fiscalía General tendrá voto de calidad.\nArtículo 83. Sanciones.\nEl Consejo de Asuntos Internos podrá imponer las siguientes sanciones:\nI. Suspensión Temporal;\nII. Amonestación;\nIII. Suspensión definitiva, y\nIV. Remoción del cargo.\nCAPÍTULO CUARTO\nCONSEJO DE HONOR Y JUSTICIA\nArtículo 84.\nA. Naturaleza.\nEl Consejo de Honor y Justicia, será el Órgano Colegiado encargado de determinar las políticas de estímulos y recompensas de la Policía de Investigación, así como de emitir las resoluciones que previo\n\nprocedimiento, determinen la separación temporal o definitiva de los miembros de la Policía de\nInvestigación que incurran en conductas que transgredan los principios y normas disciplinarias que rijan su actuación. El Reglamento establecerá su organización y funcionamiento.\nB. Procedimiento y Sanciones ante el Consejo de Honor y Justicia.\n1. El Consejo de Honor y Justica, podrá imponer las siguientes sanciones:\nI. Suspensión temporal;\nII. Amonestación;\nIII. Suspensión definitiva, y\nIV. Remoción del cargo.\n2. El procedimiento ante el Consejo de Honor y Justicia se sujetará a lo siguiente:\nI. Se radicará el asunto formando expediente y se notificará al elemento policial corriéndole traslado para que en un plazo de diez días formule contestación por escrito y ofrezca pruebas; podrá nombrar defensor y en su defecto se le nombrará uno de oficio;\nII. Transcurrido el plazo señalado, se dictará auto en el cual se resuelva sobre la admisión de pruebas y se citará a audiencia de desahogo de las mismas y alegatos. Son admisibles toda clase de pruebas excepto la confesional de autoridades;\nIII. Celebrada la audiencia de desahogo de pruebas y alegatos, se cerrará la instrucción y se turnarán el asunto para resolución, la cual deberá ser emitida en un plazo de veinte días hábiles;\nIV. La resolución definitiva será notificada al Elemento de manera personal y se agregará al expediente personal del elemento policial.\nLas resoluciones que emita el Consejo de Honor y Justicia serán inatacables y definitivas.\nPárrafo modificado y publicado en la GOCDMX el 25 de mayo de 2023\n\nEn términos del artículo 123, Apartado B, fracción XIII de la Constitución Federal, será improcedente la reinstalación del personal policial destituido, cualquiera que sea el resultado del juicio o medio de defensa que hubiere promovido, y en su caso, sólo procederá la indemnización. Cuando los órganos jurisdiccionales condenen al pago de haberes dejados de percibir o remuneración ordinaria, éstos serán cubiertos hasta por un periodo máximo de doce meses, con base en el tabulador vigente de la fecha en la que para tal efecto se exhiba.\nPárrafo modificado y publicado en la GOCDMX el 25 de mayo de 2023\nTÍTULO SEPTIMO\nDE LA EVALUACION Y SEGUIMIENTO\nCAPÍTULO ÚNICO\nArtículo 85. Seguimiento y Evaluación.\nLa Fiscalía General, a fin de dar seguimiento al Modelo diseñará metodologías, políticas y criterios, para su implementación, seguimiento y evaluación, a través de un Programa de Evaluación, que articule la Unidad de Implementación.\nArtículo 86. Evaluación.\nLa Fiscalía, establecerá un esquema de proyecto de vida para el personal de la institución, que comprenda al menos la evaluación del desempeño, la evaluación de competencias profesionales, así como regímenes de prestaciones y de atención a riesgos laborales y psicosociales, considerando el enfoque de género y el clima laboral.\nTÍTULO OCTAVO\nPRESUPUESTO, ADMINISTRACIÓN Y PATRIMONIO\nCAPÍTULO ÚNICO\nArtículo 87. Presupuesto\n\nLa Fiscalía General, ejercerá su presupuesto con autonomía y garantizará la suficiencia para el oportuno y eficaz cumplimiento de las obligaciones conferidas por la Constitución, sujetos a las previsiones de ingreso de la hacienda pública local. El presupuesto que apruebe el Congreso para la Fiscalía General, no podrá ser menor, en términos reales, al asignado para el año fiscal inmediato anterior y deberá garantizarse la autonomía e independencia funcional y financiera.\nLa Fiscalía General, elaborará su proyecto de presupuesto anual de egresos, el cual será remitido, en ejercicio de su autonomía, directamente a la Secretaría de Administración y Finanzas, para su debida incorporación en sus términos en el proyecto de Presupuesto de Egresos de la Ciudad de México, el cual será enviado al Congreso de la Ciudad de México para su aprobación.\nEl proyecto de presupuesto que se presente por parte de la Fiscalía General observará las medidas y disposiciones de austeridad gubernamental en la materia y conforme a las disposiciones que para tal efecto emita la persona Titular de la Fiscalía, con un anexo transversal para el enfoque de género al interior de la\nFiscalía, así como en la articulación de sus políticas públicas de servicio.\nEl presupuesto de la Fiscalía General, se ejercerá en términos de las disposiciones en materia de planeación y presupuesto, conforme a las disposiciones que para tal efecto emita la persona Titular de la Fiscalía\nGeneral.\nArtículo 88. Patrimonio\nPara la realización de sus funciones el patrimonio de la Fiscalía General, estará constituido por los bienes y recursos siguientes:\nI. Los bienes muebles o inmuebles que la Fiscalía General adquiera;\nII. Los bienes muebles o inmuebles que la Federación y el Gobierno de la Ciudad de México transfieran para el cumplimiento de las funciones de la Fiscalía General;\nIII. Los bienes muebles o inmuebles que el Gobierno de la Ciudad de México determine que son de uso exclusivo de la Fiscalía General;\nIV. Los recursos que anualmente determine el Congreso de la Ciudad de México en el\nPresupuesto de Egresos de la Ciudad de México;\n\nV. Los derechos de los fideicomisos o fondos destinados al cumplimiento de las funciones de la\nFiscalía General;\nVI. Las utilidades, intereses, dividendos, rentas y aprovechamientos de sus bienes muebles e inmuebles;\nVII. Los recursos que reciba por concepto de los bienes o productos que enajene;\nVIII. Los bienes que le correspondan de conformidad con la legislación aplicable, que causen abandono por estar vinculados con la comisión de delitos, los bienes decomisados por autoridad judicial o su producto en la parte que le corresponda, así como los sujetos de extinción de dominio, de conformidad con la legislación; y\nIX. Los demás que establezcan otras disposiciones legales o reglamentarias.\nArtículo 89. Contrataciones y Adquisiciones.\nPara el caso de las contrataciones públicas que lleve a cabo la Fiscalía General, se sujetarán en lo que resulte conducente y conforme a su autonomía constitucional, a la Ley de Adquisiciones para el Distrito Federal y la Ley de Obras Públicas del Distrito Federal, así como cualquier otra disposición normativa aplicable, sin perjuicio de la facultad de persona Titular de la Fiscalía General de emitir normas particulares, conforme las leyes.\nArtículo 90. Fondo Especial para Emergencias\nLa Fiscalía General contará con un fondo especial para emergencias para garantizar el desarrollo de sus actividades. La responsabilidad, gestión y administración de éste será facultad de la Coordinación General de Administración.\nTÍTULO NOVENO\nCOORDINACIÓN CON ENTIDADES DE SEGURIDAD CIUDADANA,\nPROCURACIÓN Y ADMINISTRACIÓN DE JUSTICIA\nCAPÍTULO ÚNICO\n\nArtículo 91. Coordinación en Materia de Seguridad.\nLa Fiscalía General aplicará en lo que corresponda a su competencia, las disposiciones contempladas en la\nLey General del Sistema Nacional de Seguridad Pública y la Ley del Sistema de Seguridad Ciudadana de la\nCiudad de México, con el fin de colaborar con las instituciones de Seguridad Ciudadana en garantizar la paz y la seguridad ciudadana de las personas que habitan y transitan en la Ciudad de México, con pleno respeto a los derechos humanos.\nArtículo 92. La persona Titular de la Fiscalía General, deberá participar por si o a través de la Unidad\nAdministrativa que designe, en el Sistema Nacional de Seguridad Pública, el Sistema de Seguridad\nCiudadana de la Ciudad de México, la Conferencia Nacional de Seguridad Pública y la Conferencia Nacional de Procuración de Justicia, y en los mecanismos, protocolos y registros previstos en otras leyes, para dar cumplimiento a los compromisos institucionales e instrumentos legales Nacionales e Internacionales y administrativos.\nArtículo 93. Como parte de la coordinación en materia de seguridad ciudadana, procuración y administración de justicia, la Fiscalía General, en el ámbito de sus competencias, y previo convenio de colaboración, intercambiará, suministrará y sistematizará, según sea el caso, los datos que se generen para coadyuvar a los Sistemas de Seguridad Ciudadana. Asimismo, podrá utilizar la información vertida por los\nSistemas en el ámbito de la investigación y persecución de delitos, observando los requerimientos de las leyes de transparencia, acceso a la información y protección de datos personales.\nArtículo 94. La Fiscalía General, promoverá acciones con otras instituciones de procuración y administración de justicia, comisiones de derechos humanos, búsqueda de personas y atención a víctimas, en general con todas las instituciones que permitan generar colaboraciones, investigaciones y estudios que permitan mejorar la procuración de justicia.\nTÍTULO DÉCIMO\nPARTICIPACIÓN CIUDADANA\nCAPÍTULO PRIMERO\nGENERALIDADES\nArtículo 95. La Fiscalía General, establecerá mecanismos y procedimientos para la participación directa y permanente de la ciudadanía respecto al desarrollo de actividades que comprendan la política criminal y\n\nla procuración de justicia, observando los principios de confianza, colaboración, inclusión, transparencia y corresponsabilidad.\nLa Fiscalía General incentivará la participación ciudadana para:\nI. La consulta, análisis y opinión en materia de política criminal y procuración de justicia;\nII. Proponer a La Fiscalía el mecanismo para mejorar la cobertura y calidad de los servicios;\nIII. Proponer adecuaciones a los procedimientos que permitan mejorar la atención ciudadana;\nIV. Cooperar con la Fiscalía para promover la cultura de la denuncia y rendición de cuentas;\nV. Las demás que dispongan las leyes aplicables y el Reglamento.\nArtículo 96. La persona Titular de la Fiscalía General, podrá convenir con las Organizaciones de la Sociedad\nCivil e instituciones educativas su participación en la creación e implementación de programas orientados a la capacitación, profesionalización, diagnóstico y evaluación del modelo de procuración de justicia, rendición de cuentas y proximidad gubernamental, a fin de garantizar el derecho a la buena administración.\nCAPÍTULO SEGUNDO\nDEL CONSEJO CIUDADANO\nArtículo 97. El Consejo Ciudadano de la Fiscalía General, será un Órgano Colegiado de consulta y de carácter honorífico.\nEstará integrado por siete personas de probidad y prestigio que se hayan destacado por su contribución en materia de procuración e impartición de justicia, investigación criminal y derechos humanos, en especial de grupos de atención prioritaria. En su integración se garantizará el principio de la paridad de género.\nSerá presidido por una de las personas integrantes elegida por mayoría simple de entre ellas y sesionará de acuerdo con lo dispuesto en el Reglamento del Consejo. Las y Los integrantes del Consejo Ciudadano durarán en su encargo dos años improrrogables y serán renovados de manera escalonada, conforme lo determine el Reglamento.\n\nLas personas fiscales de la Fiscalía General y de las demás unidades administrativas, podrán asistir a las reuniones con voz, pero sin voto.\nArtículo 98. Integración.\nLa Comisión de Administración y Procuración de Justicia del Congreso de la Ciudad de México, seleccionará a personas integrantes del Consejo Ciudadano de la Fiscalía General, previa convocatoria pública abierta y transparente. La convocatoria preverá un plazo de 5 días para que la ciudadanía y organizaciones de la sociedad civil presenten opiniones, adhesiones y objeciones sobre las personas inscritas.\nArtículo 99. Facultades.\nEl Consejo Ciudadano tendrá las siguientes facultades:\nI. Opinar, dar seguimiento y emitir recomendaciones públicas sobre el contenido e implementación del Plan de Política Criminal y del Programa de Persecución Penal, así como los programas anuales de trabajo y su implementación;\nInciso reformado y publicado en la GOCDMX el 17 de mayo de 2023\nII. Opinar sobre la creación de nuevas estructuras administrativas propuestas por La o El titular de la Fiscalía General;\nIII. Hacer del conocimiento del Órgano Interno de Control cuando advierta una probable responsabilidad administrativa;\nIV. Dar opiniones para fortalecer el presupuesto de la institución;\nV. Opinar sobre la normativa interna de la Fiscalía General;\nVI. Opinar sobre las propuestas y planes del Servicio Profesional de Carrera;\nVII. Establecer las reglas operativas del propio Consejo;\nVIII. Realizar monitoreos sobre el tratamiento que a los temas de procuración de justicia dan los medios de comunicación y redes sociales y darlos a conocer a la opinión pública.\n\nIX. En general, emitir opiniones y recomendaciones sobre el desempeño de la Fiscalía y sus áreas;\nX. Establecer relaciones con la Organizaciones de la Sociedad Civil y Ciudadanas que realicen investigaciones sobre la temática de procuración de justicia y establecer mecanismos de colaboración y difusión de sus estudios y actividades;\nXI. Las demás que establezcan esta Ley y su Reglamento.\nLas opiniones y recomendaciones emitidas por el Consejo no son vinculantes. La Fiscalía y las unidades administrativas a las que vayan dirigidas las recomendaciones deberán fundar y motivar las razones por las cuales se acepta o rechaza la recomendación. Dicho procedimiento será de carácter público.\nArtículo 100. El Consejo Ciudadano se auxiliará con una Secretaría Técnica, así como con el personal que se requiera para el desempeño de sus funciones, de conformidad con lo dispuesto por el Reglamento de esta Ley.\nTITULO DÉCIMO PRIMERO\nDEL CONTROL INTERNO\nCAPÍTULO ÚNICO\nArtículo 101. El Órgano de Control Interno, es un órgano dotado de autonomía técnica y de gestión para decidir sobre su funcionamiento y resoluciones. Tendrá a su cargo prevenir, corregir, investigar y calificar actos u omisiones que pudieran constituir responsabilidades administrativas de servidores públicos de la\nFiscalía y de particulares vinculados con faltas graves; para sancionar aquellas distintas a las que son competencia del Tribunal de Justicia Administrativa; revisar el ingreso, egreso, manejo, custodia, aplicación de recursos públicos; así como presentar las denuncias por hechos u omisiones que pudieran ser constitutivos de delito ante las autoridades competentes.\nSerán facultades del Órgano de Control Interno las siguientes:\nI. Las que contempla la Ley de Responsabilidades Administrativas y la Ley del Sistema Nacional\nAnticorrupción, ambas de la Ciudad de México;\n\nII. Verificar que el ejercicio de gasto de la Fiscalía General se realice conforme a la normativa aplicable, los programas aprobados y montos autorizados;\nIII. Realizar auditorías, revisiones y evaluaciones y presentar a La o al titular de la Fiscalía General, los informes correspondientes con el objeto de examinar, fiscalizar y promover la eficiencia, eficacia y legalidad en su gestión y encargo, así como emitir recomendaciones;\nIV. Revisar que las operaciones presupuestales que realice La Fiscalía General, se hagan con apego a las disposiciones legales y administrativas aplicables y, en su caso, determinar las desviaciones de las mismas y las causas que les dieron origen;\nV. Promover ante las instancias correspondientes, las acciones administrativas y legales que se deriven de los resultados de las auditorías;\nVI. Investigar, en el ámbito de su competencia, los actos u omisiones que impliquen alguna irregularidad o conducta ilícita en el ingreso, egreso, manejo, custodia y aplicación de fondos y recursos de La Fiscalía General;\nVII. Evaluar el cumplimiento de los objetivos y metas fijadas en los programas de naturaleza administrativa contenidos en el presupuesto de egresos de la Fiscalía General, empleando la metodología que determine;\nVIII. Recibir quejas y denuncias conforme a las leyes aplicables;\nIX. Solicitar la información y efectuar visitas a las áreas y órganos de la Fiscalía General para el cumplimento de sus funciones;\nX. Ejercer en el ámbito de la Fiscalía General, en lo que resulte conducente, las facultades que se deriven de otros ordenamientos legales;\nXI. Intervenir en los actos de entrega-recepción de las o los servidores públicos de la Fiscalía\nGeneral, en los términos de la normativa aplicable;\nXII. Participar, conforme a las disposiciones vigentes, en los comités y subcomités que prevea la normativa e intervenir en los actos que se deriven de los mismos;\n\nXIII. Formular el anteproyecto de presupuesto del Órgano de Control Interno;\nXIV. Presentar al Fiscal General los informes, previo y anual, de resultados de su gestión;\nXV. Presentar al Fiscal General los informes respecto de los expedientes relativos a las faltas administrativas y, en su caso, sobre la imposición de sanciones en materia de responsabilidades administrativas;\nXVI. Emitir el Código de Ética de las o los servidores públicos de la Fiscalía General, el cual debe incluir la perspectiva de género y el clima laboral libre de violencia de género;\nXVII. Establecer mecanismos que prevengan actos u omisiones que pudieran constituir responsabilidades administrativas;\nXVIII. Vigilar, en colaboración con las autoridades competentes el cumplimiento de las normas de control interno, fiscalización, integridad, transparencia, rendición de cuentas, acceso a la información y combate a la corrupción en la Fiscalía General y\nXIX. Las demás que señalen las leyes y reglamentos.\nArtículo 102. Designación de la Persona Titular del Órgano Interno de Control.\nLa designación de la persona Titular del Órgano Interno de Control de la Fiscalía General de Justicia de la\nCiudad de México, se realizará conforme los términos de los artículos 46 de la Constitución Local, 143 de la Ley Orgánica del Congreso de la Ciudad de México y 74 de la Ley del Sistema Anticorrupción de la Ciudad de México.\nTRANSITORIOS\nPRIMERO. Publíquese el presente Decreto en la Gaceta Oficial de la Ciudad de México para su mayor difusión.\nSEGUNDO. El presente Decreto entrará en vigor el día 10 de enero de 2020.\n\nTERCERO. A partir de la entrada en vigor de la Ley Orgánica de la Fiscalía General de Justicia de la Ciudad de México, la Ley de Transición de la Procuraduría General de Justicia a la Fiscalía General de Justicia de la\nCiudad de México, publicada en la Gaceta Oficial de la Ciudad de México, el 14 de Febrero de 2019, quedará abrogada.\nLas normas aplicables de la Ley Orgánica de la Procuraduría General de Justicia del Distrito Federal, el\nReglamento de la misma, así como los acuerdos, protocolos, lineamientos, manuales y demás instrumentos normativos continuarán en vigor, hasta en tanto se expidan, publiquen y adquieran vigencia las disposiciones jurídicas que los sustituyan.\nLas autoridades y unidades administrativas de la Procuraduría General de Justicia de la Ciudad de México conservarán sus denominaciones, atribuciones y estructura hasta en tanto no entren en vigor las normas jurídicas y estructuras administrativas que los supriman o sustituyan.\nConforme avance el Plan de Transición, la persona titular de la Fiscalía General de Justicia de la Ciudad de\nMéxico, mediante avisos publicados en la Gaceta Oficial, declarará la cesación de funciones de las unidades administrativas que conforman la Procuraduría General de Justicia del Distrito Federal y el inicio de funciones de las unidades administrativas creadas por esta Ley y el reglamento.\nCUARTO. La Procuraduría General de Justicia de la Ciudad de México continuará encargándose de la función ministerial hasta que inicie sus funciones la Fiscalía General de Justicia de la Ciudad de México.\nQUINTO. El Congreso de la Ciudad de México declarará concluido el mandato de la Comisión de Transición, una vez que haya concluido la ejecución del Plan de Transición.\nLa Comisión opinará y supervisará las actividades de la Unidad de Implementación hasta la conclusión del\nPlan de Transición.\nEl Plan de Transición comprenderá como mínimo los aspectos siguientes:\nI. Diagnóstico, mapeo y análisis de los fenómenos criminales que perseguirá; la definición del plan de política criminal y la operación y despliegue del modelo de investigación criminal;\nII. Definición de objetivos, estrategias, acciones, metas e indicadores de resultados del proceso de transición, con base en criterios de gradualidad que consideren los tipos y fenómenos delictivos, unidades operativas centrales y territoriales, regiones geográficas u otros;\n\nIII. Estrategia específica respecto al personal en activo y al reclutamiento de nuevos talentos, que contemple a su vez esquemas de formación inicial, certificación, capacitación, desarrollo y gestión del cambio;\nIV. Estrategia para el diseño de la nueva estructura organizativa; así como del proceso de cierre de las estructuras y procesos previos;\nV. Proponer la estrategia de liquidación de casos, con el inventario de casos en trámite que proporcione la persona titular de la Procuraduría; así como su situación jurídica, tanto del sistema inquisitivo mixto como del acusatorio, para garantizar su adecuada atención; así como la identificación de casos de alto impacto social o de violaciones graves a los derechos humanos.\nLos casos pendientes de resolución relacionados con violaciones graves de derechos humanos o corrupción no podrán ser liquidados, así como la forma de atención y trámite a estos casos hasta su conclusión;\nVI. Estrategia de transparencia, participación ciudadana y rendición de cuentas del proceso de transición que asegure la publicidad y mecanismos necesarios para el seguimiento, colaboración y vigilancia;\nVII. Estrategia de colaboración y articulación con otras instituciones con las que requiera coordinarse para llevar a cabo la función fiscal;\nVIII. Las propuestas normativas necesarias para el funcionamiento de la Fiscalía.\nIX. Establecerá un mecanismo expeditivo para establecer el sistema central de recepción y canalización de los asuntos nuevos que tenga que conocer la Fiscalía General; y\nX. La Comisión definirá el plazo o plazos para la instrumentación del Plan de Transición, el cual podrá ser gradual.\nSEXTO. Una vez publicado este Decreto y habiendo sido designada La o El titular de la Fiscalía General\nJusticia de la Ciudad de México, el Congreso de la Ciudad de México deberá emitir la declaratoria expresa de la entrada en vigor de la autonomía constitucional de la misma.\n\nSÉPTIMO. Todos los convenios y actos jurídicos celebrados por la Procuraduría General de la Ciudad de\nMéxico se entenderán como vigentes y obligarán en sus términos a la Fiscalía General, sin perjuicio del derecho de las partes a ratificarlos, modificarlos o cancelarlos posteriormente.\nOCTAVO. Todas las referencias normativas a la Procuraduría General de la Ciudad de México, así como todas las participaciones institucionales de ésta o de la persona titular de la Procuraduría General de la Ciudad de México, se entenderán referidas a la Fiscalía General de la Ciudad de México, o a la persona titular de la misma.\nLa persona titular de la Procuraduría General de Justicia de la Ciudad de México que se encuentre en funciones al momento de expedirse la declaratoria a que se refiere el artículo transitorio segundo, continuará en su encargo hasta en tanto el Congreso de la Ciudad de México designe a La o El titular de la\nFiscalía General de Justicia de la Ciudad de México.\nNOVENO. El Reglamento de la Ley Orgánica de la Fiscalía General de Justicia de la Ciudad de México deberá publicarse en la Gaceta Oficial de la Ciudad de México en un plazo que no exceda de ciento veinte días naturales, contados a partir del nombramiento de la persona titular de la Fiscalía.\nDÉCIMO. Las averiguaciones previas, carpetas de investigación y demás casos que se encuentren en trámite a la entrada en vigor del presente Decreto serán resueltos por las áreas o unidades administrativas a las que están asignadas, conforme a los ordenamientos vigentes al momento de su inicio o apertura. Lo anterior sin perjuicio de que se adscriban a nuevas unidades conforme a los avances del proceso de la transición orgánica de la Fiscalía General de Justicia de la Ciudad de México.\nA partir del inicio de funciones de la persona titular de la Fiscalía General de Justicia de la Ciudad de México contará con 120 días para presentar una estrategia de liquidación de casos, así como su situación jurídica, tanto del sistema inquisitivo mixto como del acusatorio, para garantizar su adecuada atención; así como la identificación de casos de alto impacto social o de violaciones graves a los derechos humanos. Los casos pendientes de resolución relacionados con violaciones graves de derechos humanos o corrupción no podrán ser liquidados, así como la forma de atención y trámite a estos casos hasta su conclusión.\nDECIMO PRIMERO. El Congreso de la Ciudad de México, tomando en cuenta el principio de austeridad, contemplará en el Decreto por el que se expide el Presupuesto de Egresos de la Ciudad de México para el\nEjercicio Fiscal 2020 y subsecuentes, la asignación y garantía de la suficiencia presupuestal para la instalación de la Fiscalía General de Justicia de la Ciudad de México y la ejecución de la planeación estratégica del proceso de transición, conforme a lo establecido en la Ley de Transición de la Procuraduría\n\nGeneral de Justicia a la Fiscalía General de Justicia de la Ciudad de México y el artículo 72 de la Ley del\nSistema Anticorrupción de la Ciudad de México.\nDÉCIMO SEGUNDO. La persona Titular de la Fiscalía General de Justicia, deberá elaborar el Plan de Política\nCriminal para presentarlo ante el Congreso de la Ciudad de México, de conformidad con el artículo 44, apartado B, numeral 2, de la Constitución Política de la Ciudad de México.\nEl Plan se elaborará a partir de la realización de un inventario integral y un diagnóstico de los recursos financieros, humanos y materiales, casos pendientes, procesos de colaboración e inteligencia y cualquier otro insumo que considere necesario para la integración del mismo.\nEn el Plan se deberá priorizar en orden de importancia el establecimiento del Servicio Profesional de\nCarrera, la consolidación de los sistemas informáticos, las unidades de análisis criminalístico y criminológico que investigarán el volumen de casos con imputado desconocido, los grupos especializados de litigio oral y ejecución penal, los órganos administrativos y los sustantivos necesarios para la función de procuración de justicia.\nDÉCIMO TERCERO. Las o Los Fiscales, Agentes del Ministerio Público, oficiales Secretarios, policías de investigación, analistas, auxiliares y peritos, así como el o El personal profesional, técnico y administrativo que a la entrada en vigor del presente ordenamiento se encuentren laborando en la Procuraduría General de Justicia de la Ciudad de México se sujetarán a las disposiciones de relaciones laborales que dispone el artículo Transitorio Vigésimo Quinto de la Constitución Política de la Ciudad de México.\nEn la transición del personal de la Procuraduría General de Justicia, tratándose de personal sindicalizado, la representación gremial participará en los términos que señalen las leyes e instrumentos aplicables.\nLa Fiscalía contará con médicos legistas en su plantilla de personal. El personal que actualmente funge con tal carácter podrá ser readscrito a la Fiscalía, previo consentimiento, en los términos de la normatividad aplicable e intervención de la representación sindical, en su caso.\nDÉCIMO CUARTO. Una vez instaladas las Fiscalías Especializadas y demás unidades administrativas, las personas titulares de inmediato solicitarán a La o El titular de la Fiscalía General de la Ciudad de México, la asignación del personal que integrará dichas áreas, de acuerdo a la Ley y Reglamento. En el proceso de asignación, se observarán, entre otros, los principios de igualdad, paridad y no discriminación entre mujeres y hombres.\n\nDÉCIMO QUINTO. La Fiscalía Especializada en Combate a la Corrupción, respondiendo a la satisfacción del interés público y del bien común, podrá atraer por conducto de su titular, asuntos cuyo trámite se hubiese iniciado con anterioridad a la asignación de su gestión.\nDÉCIMO SEXTO. Los Órganos Colegiados de la Procuraduría General de Justicia de la Ciudad de México que se encuentren integrados y en operación a la entrada en vigor del presente Decreto, seguirán actuando conforme a los ordenamientos vigentes aplicables; lo anterior; sin perjuicio de que se modifique su integración y funcionamiento conforme a los avances del proceso de la transición orgánica de la Fiscalía\nGeneral de Justicia de la Ciudad de México.\nDÉCIMO SÉPTIMO. A la entrada en vigor del presente Decreto, los bienes muebles, inmuebles y demás recursos materiales, financieros y presupuestales, asignados a la Procuraduría General de Justicia de la\nCiudad de México, pasarán a formar parte del patrimonio de la Fiscalía General de la Ciudad de México. En lo relativo a bienes en posesión o servicios contratados para los fines de la Procuraduría General, obtenidos por arrendamiento, comodato o cualquier otro contrato mediante el cual se haya transmitido la posesión o propalado dichos servicios, continuarán siendo utilizados por la Fiscalía General de la Ciudad de México.\nLa Secretaría de Finanzas y Administración de la Ciudad de México, deberá efectuar las gestiones y trámites correspondientes, para dar cumplimiento cabal al presente artículo, conforme a las disposiciones legales aplicables.\nDÉCIMO OCTAVO. La persona Titular de la Fiscalía General, deberá designar dentro de los treinta días siguientes al inicio su gestión, a la persona que encabezará la unidad de implementación del proceso de\nTransición.\nDÉCIMO NOVENO. El proceso de transición de la Procuraduría General de Justicia de la Ciudad de México a Fiscalía General de Justicia de la Ciudad de México, será gradual hasta un plazo de cuatro años, a partir de la asunción del cargo de La o El titular de la Fiscalía, de acuerdo con el Plan de Transición.\nVIGÉSIMO. El proceso de transición de la Procuraduría General a la Fiscalía General de la Ciudad de México, se llevará a cabo de acuerdo con el Plan de Transición y será coordinado por la Unidad de Implementación.\nEste proceso deberá ejecutarse conforme a los lineamientos que expida la persona titular de la Fiscalía\nGeneral, en un plazo de 120 días contados desde la fecha de su designación, asignándose para tales efectos el fondo especial para el financiamiento de dicho proceso.\n\nVIGÉSIMO PRIMERO. Las personas agentes del ministerio público adscritos a juzgados civiles y familiares dejaran de estar adscritos a dichos juzgados, debiendo ser sustituidos por el personal que salvaguarda los derechos de las niñas, niños y adolescentes de conformidad con la ley de la materia.\nNo obstante, en tanto no se establezca la sustitución de la función de representación social que llevan a cabo los agentes del ministerio público, en los juzgados civiles y familiares del Tribunal Superior de\nJusticia, continuaran adscritos a dichos juzgados efectuando dicha función en beneficio de las niñas y niños de la ciudad de México.\nVIGÉSIMO SEGUNDO. La Fiscalía General y la Comisión de Atención a Víctimas de la Ciudad de México convendrán un periodo de transición en lo concerniente a la asesoría jurídica y la atención a víctimas, conforme al cual, en forma escalonada y paulatina, ejecuten las siguientes acciones:\n1. En materia de asesoría jurídica penal, la Comisión de Víctimas, absorberá exclusivamente la asesoría jurídica en los siguientes delitos de alto impacto y que se enuncian a continuación:\nhomicidio doloso, feminicidio, secuestro, trata de personas, delitos en materia de tortura, desaparición forzada de personas y desaparición cometida por particulares, así como abordar en forma exclusiva la representación victimal en materia de la ejecución de sentencias penales.\nLa asesoría jurídica victimal en su totalidad será transferida a partir del 1º de enero de 2024, en cuyo caso, la Comisión de Víctimas conocerá en forma exclusiva de la asesoría jurídica de las víctimas, en observancia y para efectos del artículo 20, apartado C de la Constitución Federal y de conformidad con la Ley General de Víctimas. Asimismo, conocerá adicionalmente para efectos de la asesoría jurídica victimal de los delitos de abuso o violencia sexual contra menores, como delitos sexuales en general.\n2. En materia de atención a víctimas, la Comisión de Atención a Víctimas de la Ciudad de México a partir del 1º de enero de 2022, conocerá exclusivamente de la atención a víctimas y primer contacto, conforme a la Ley General de Víctimas y la Ley de Víctimas de la ciudad de México.\nAmbas instancias se coordinarán estrechamente en forma previa para permitir la implementación y transmisión ordenada de la atención a víctimas a la Comisión de Víctimas.\nVIGÉSIMO TERCERO. Los requisitos de ingreso, promoción y permanencia para el personal sustantivo se establecerán en el Reglamento y no podrán ser menores a los señalados a la Ley Orgánica de la\nProcuraduría General de Justicia de la Ciudad de México.\n\nPalacio Legislativo del Congreso de la Ciudad de México, a los trece días del mes de diciembre del año dos mil diecinueve.- POR LA MESA DIRECTIVA.- DIPUTADA ISABELA ROSALES HERRERA, PRESIDENTA.-\nDIPUTADA MARTHA SOLEDAD VENTURA ÁVILA, SECRETARIA.- DIPUTADA MARGARITA SALDAÑA\nHERNÁNDEZ, SECRETARIA.- (Firmas)\nCon fundamento en lo dispuesto por los artículos 122, apartado A, fracción III, de la Constitución Política de los Estados Unidos Mexicanos; 32 apartado C, numeral 1, inciso a) de la Constitución Política de la\nCiudad de México; 3 fracciones XVII y XVIII, 7 párrafo primero, 10 fracción II, 12 y 21, párrafo primero, de la Ley Orgánica del Poder Ejecutivo y de la Administración Pública de la Ciudad de México; para su debida publicación y observancia, expido el presente Decreto Promulgatorio en la Residencia Oficial de la Jefatura de Gobierno de la Ciudad de México, a los veintitrés días del mes diciembre del año dos mil diecinueve.-\nLA JEFA DE GOBIERNO DE LA CIUDAD DE MÉXICO, DRA. CLAUDIA SHEINBAUM PARDO.- FIRMA.- LA\nSECRETARIA DE GOBIERNO, ROSA ICELA RODRÍGUEZ VELÁZQUEZ.- FIRMA.- LA SECRETARIA DE\nADMINISTRACIÓN Y FINANZAS, LUZ ELENA GONZÁLEZ ESCOBAR.- FIRMA.\nTRANSITORIOS DEL DECRETO POR EL QUE SE REFORMAN LOS ARTÍCULOS 43, 48, 55, 56, 57, 61, 63, 66 Y\n81. SE ADICIONAN: UNA FRACCIÓN XX AL ARTÍCULO 35, RECORRIÉNDOSE LA FRACCIÓN SUBSECUENTE EN\nSU ORDEN, RESPETANDO DE MANERA ÍNTEGRA SU CONTENIDO; UN ARTÍCULO 39 BIS Y UN NUEVO\nARTÍCULO 63 BIS, TODOS DE LA LEY ORGÁNICA DE LA FISCALÍA GENERAL DE JUSTICIA DE LA CIUDAD DE\nMÉXICO, PUBLICADO EL 28 DE JULIO DE 2020 EN LA GACETA OFICIAL DE LA CIUDAD DE MÉXICO.\nPrimero. El presente decreto entrará en vigor, el día siguiente al de su publicación en la Gaceta Oficial de la Ciudad de México.\nSegundo. Publíquese en la Gaceta Oficial de la Ciudad de México.\nTercero. Remítase el presente decreto a la Jefa de Gobierno para sus efectos legales.\nPalacio Legislativo del Congreso de la Ciudad de México, a los veintiocho días del mes de julio del año dos mil veinte.- POR LA MESA DIRECTIVA.- DIPUTADA ISABELA ROSALES HERRERA, PRESIDENTA.- DIPUTADA\nDONAJI OFELIA OLIVERA REYES, SECRETARIA.- DIPUTADA MARGARITA SALDAÑA HERNÁNDEZ, SECRETARIA.-\n(Firmas)\nCon fundamento en lo dispuesto por los artículos 122, apartado A, fracción III de la Constitución Política de los Estados Unidos Mexicanos; 32, apartado C, numeral 1, inciso a) de la Constitución Política de la Ciudad\n\nde México; 2 párrafo segundo, 3 fracciones XVII y XVIII, 7 párrafo primero, 10 fracción II, 12 y 21 párrafo primero de la Ley Orgánica del Poder Ejecutivo y de la Administración Pública de la Ciudad de México; para su debida publicación y observancia, expido el presente Decreto Promulgatorio en la Residencia Oficial de la Jefatura de Gobierno de la Ciudad de México, a los veintiocho días del mes de julio del año dos mil veinte.- LA JEFA DE GOBIERNO DE LA CIUDAD DE MÉXICO, DRA. CLAUDIA SHEINBAUM PARDO.- FIRMA.- EL\nSECRETARIO DE GOBIERNO, JOSÉ ALFONSO SUÁREZ DEL REAL Y AGUILERA.- FIRMA.\nTRANSITORIOS DEL DECRETO POR EL QUE SE ADICIONA EL ARTÍCULO 42 BIS; Y SE REFORMAN LOS\nARTÍCULOS 42 Y 99, TODOS DE LA LEY ORGÁNICA DE LA FISCALÍA GENERAL DE JUSTICIA DE LA CIUDAD DE\nMÉXICO, PUBLICADO EN LA GACETA OFICIAL DE LA CIUDAD DE MÉXICO EL 17 DE MAYO DE 2023.\nPRIMERO. - Remítase a la persona titular de la Jefatura de Gobierno, para su promulgación y publicación en la Gaceta Oficial de la Ciudad de México.\nSEGUNDO. - El presente Decreto entrará en vigor al día siguiente de su publicación en la Gaceta Oficial de la Ciudad de México.\nTERCERO. – La emisión y modificación de las Reglas Operativas y de funcionamiento, se llevarán a cabo por los Presidentes del Consejo Ciudadano y Judicial respectivamente, con la aprobación de la mayoría de sus integrantes.\nPalacio Legislativo del Congreso de la Ciudad de México, a los nueve días del mes de mayo del año dos mil veintitrés.- POR LA MESA DIRECTIVA.- DIPUTADO FAUSTO MANUEL ZAMORANO ESPARZA, PRESIDENTE.-\nDIPUTADA MARCELA FUENTE CASTILLO, SECRETARIA.- DIPUTADA MARIA GABRIELA SALIDO MAGOS,\nSECRETARIA.- (Firmas)\nCon fundamento en lo dispuesto por los artículos 122, apartado A, fracción III de la Constitución Política de los Estados Unidos Mexicanos; 32, apartado C, numeral 1, inciso a) de la Constitución Política de la Ciudad de México; 2 párrafo segundo, 3 fracciones XVII y XVIII, 7 párrafo primero, 10 fracción II, 12 y 21 párrafo primero de la Ley Orgánica del Poder Ejecutivo y de la Administración Pública de la Ciudad de México; para su debida publicación y observancia, expido el presente Decreto Promulgatorio en la Residencia Oficial de la Jefatura de Gobierno de la Ciudad de México, a los doce días del mes de mayo del año dos mil veintitrés.-\nLA JEFA DE GOBIERNO DE LA CIUDAD DE MÉXICO, DRA. CLAUDIA SHEINBAUM PARDO.- FIRMA.- EL\nSECRETARIO DE GOBIERNO, MARTÍ BATRES GUADARRAMA.- FIRMA.\n\nTRANSITORIOS DEL DECRETO POR EL QUE SE DEROGAN EL ARTÍCULO 66; ÚLTIMO PÁRRAFO DEL ARTÍCULO\n82; SE REFORMAN LOS ARTÍCULOS 75; 76; 79; 80 Y 81; SE ADICIONAN LAS FRACCIONES XXIV Y XXV DEL\nARTÍCULO 48 Y SE RECORRE LA SUBSECUENTE; ARTÍCULO 53 BIS; 66 BIS, LOS ÚLTIMOS DOS PÁRRAFOS DEL\nARTÍCULO 82; SE MODIFICAN LA FRACCIÓN XXIV DEL ARTÍCULO 48; FRACCIONES I Y XII DEL ARTÍCULO 61;\nFRACCIÓN XII DEL ARTÍCULO 62; PRIMER PÁRRAFO Y FRACCIÓN XII DEL ARTÍCULO 63 BIS; ÚLTIMO PÁRRAFO\nDEL ARTÍCULO 84, TODOS DE LA LEY ORGÁNICA DE LA FISCALÍA GENERAL DE JUSTICIA DE LA CIUDAD DE\nMÉXICO, PUBLICADO EN LA GACETA OFICIAL DE LA CIUDAD DE MÉXICO EL 25 DE MAYO DE 2023.\nPRIMERO. El presente Decreto entrará en vigor al día siguiente de su publicación en la Gaceta Oficial de la\nCiudad de México.\nSEGUNDO. Los asuntos que se encontraban en trámite en la Subprocuraduría de Procesos, hasta antes de la entrada en vigor del presente Decreto, serán atendidos y resueltos por la Coordinación General de\nAcusación, Procedimiento y Enjuiciamiento.\nLos recursos humanos, financieros, materiales y tecnológicos con los que contaban las Subprocuraduría de\nProcesos serán transferidos a la Coordinación General de Acusación, Procedimiento y Enjuiciamiento.\nLas menciones y referencias normativas hechas a la Subprocuraduría de Procesos, así como las facultades y participaciones institucionales de esta o de su persona Titular, se entenderán hechas a la Coordinación\nGeneral de Acusación, Procedimiento y Enjuiciamiento, cuando sean asuntos de su competencia.\nEn su caso, la Coordinación General Jurídica y de Derechos Humanos emitirá opinión jurídica respecto a la\nUnidad Administrativa que deba de continuar con la atención de los asuntos de la entonces\nSubprocuraduría de Procesos.\nTERCERO. Las facultades de la Unidad de Implementación previstas en la presente Ley y en el Reglamento serán transferidas al Órgano de Política Criminal, una vez concluido el Proceso de Transición de la Fiscalía\nGeneral.\nCUARTO. Se derogan todas aquellas disposiciones que se opongan al presente Decreto.\nPalacio Legislativo del Congreso de la Ciudad de México, a los nueve días del mes de mayo del año dos mil veintitrés.- POR LA MESA DIRECTIVA.- DIPUTADO FAUSTO MANUEL ZAMORANO ESPARZA, PRESIDENTE.-\nDIPUTADA MARCELA FUENTE CASTILLO, SECRETARIA.- DIPUTADA MARIA GABRIELA SALIDO MAGOS,\nSECRETARIA.- (Firmas)\n\nCon fundamento en lo dispuesto por los artículos 122, apartado A, fracción III de la Constitución Política de los Estados Unidos Mexicanos; 32, apartado C, numeral 1, inciso a) de la Constitución Política de la Ciudad de México; 2 párrafo segundo, 3 fracciones XVII y XVIII, 7 párrafo primero, 10 fracción II, 12 y 21 párrafo primero de la Ley Orgánica del Poder Ejecutivo y de la Administración Pública de la Ciudad de México; para su debida publicación y observancia, expido el presente Decreto Promulgatorio en la Residencia Oficial de la Jefatura de Gobierno de la Ciudad de México, a los diecinueve días del mes de mayo del año dos mil veintitrés.-LA JEFA DE GOBIERNO DE LA CIUDAD DE MÉXICO, DRA. CLAUDIA SHEINBAUM PARDO.- FIRMA.-\nEL SECRETARIO DE GOBIERNO, MARTÍ BATRES GUADARRAMA.- FIRMA.\nTRANSITORIOS DEL DECRETO POR EL QUE SE MODIFICA EL PÁRRAFO PRIMERO DEL ARTÍCULO 69 TER, LA\nFRACCIÓN VIII DEL ARTÍCULO 138, EL SEGUNDO PÁRRAFO, LA FRACCIÓN IX Y EL INCISO A) DEL PÁRRAFO\nQUINTO, DEL ARTÍCULO 148 BIS; SE ADICIONA UN CAPÍTULO VII, AL TÍTULO PRIMERO DEL LIBRO SEGUNDO\nPARTE ESPECIAL, Y UN ARTÍCULO 148 TER, AL CÓDIGO PENAL PARA EL DISTRITO FEDERAL; SE ADICIONA UN\nPÁRRAFO SEGUNDO AL ARTÍCULO 118 DEL CÓDIGO CIVIL PARA EL DISTRITO FEDERAL; SE MODIFICA LA\nFRACCIÓN IV DEL ARTÍCULO 37; SE ADICIONAN LAS FRACCIONES V, VI, VII AL ARTÍCULO 37, Y LAS\nFRACCIONES XXIV, XXV, XXVI, AL ARTÍCULO 65, DE LA LEY ORGÁNICA DE LA FISCALÍA GENERAL DE JUSTICIA\nDE LA CIUDAD DE MÉXICO Y SE ADICIONA UNA FRACCIÓN XIV BIS AL ARTÍCULO 3 DE LA LEY DE VÍCTIMAS\nPARA LA CIUDAD DE MÉXICO, PÚBLICADO EN LA GACETA OFICIAL DE LA CIUDAD DE MÉXICO EL 23 DE\nAGOSTO DE 2024.\nPRIMERO. Remítase a la persona titular de la Jefatura de Gobierno, para su promulgación y publicación en la Gaceta Oficial de la Ciudad de México.\nSEGUNDO. El presente Decreto entrará en vigor el día siguiente al de su publicación en la Gaceta Oficial de la Ciudad de México.\nPalacio Legislativo del Congreso de la Ciudad de México, a los dieciocho días del mes de julio del año dos mil veinticuatro.- POR LA MESA DIRECTIVA.- DIPUTADA MARÍA GABRIELA SALIDO MAGOS, PRESIDENTA.-\nDIPUTADA MARCELA FUENTE CASTILLO, SECRETARIA.- DIPUTADA FRIDA FERNANDA ALCÁNTARA CABRERA,\nSECRETARIA.- (Firmas)\nCon fundamento en lo dispuesto por los artículos 122, apartado A, base III, de la Constitución Política de los Estados Unidos Mexicanos; 32, apartado C, numeral 1, inciso a), de la Constitución Política de la Ciudad de México; 2, párrafo segundo, 3, fracciones XVII y XVIII, 7, párrafo primero, 10, fracción II, 12 y 21, párrafo primero, de la Ley Orgánica del Poder Ejecutivo y de la Administración Pública de la Ciudad de México;\n\npara su debida publicación y observancia, expido el presente Decreto Promulgatorio en la Residencia\nOficial de la Jefatura de Gobierno de la Ciudad de México, a los veintidós días del mes de agosto del año dos mil veinticuatro.- EL JEFE DE GOBIERNO DE LA CIUDAD DE MÉXICO, DR. MARTÍ BATRES GUADARRAMA.-\nFIRMA.- EL SECRETARIO DE GOBIERNO, RICARDO RUIZ SUÁREZ.- FIRMA.- EL SECRETARIO DE BIENESTAR E\nIGUALDAD SOCIAL, JUAN GERARDO LÓPEZ HERNÁNDEZ.-FIRMA.- LA SECRETARIA DE LAS MUJERES, INGRID\nAURORA GÓMEZ SARACÍBAR.- FIRMA.- EL SECRETARIO DE SEGURIDAD CIUDADANA, LICENCIADO PABLO\nVÁZQUEZ CAMACHO.- FIRMA.- EL CONSEJERO JURÍDICO Y DE SERVICIOS LEGALES, NÉSTOR VARGAS\nSOLANO.- FIRMA.",
  "ordenamiento": "Marco Jurídico",
  "jurisdiccion": "CIUDAD DE MEXICO",
  "fuente_oficial": "Congreso de la Ciudad de México",
  "status": "Vigente",
  "Fecha de Publicación": "22-10-2024",
  "Fecha de Última Reforma": "23 de agosto de 2024",
  "numero_paginas": 98,
  "es_escaneado": false,
  "tiene_tablas": true,
  "url": "https://www.congresocdmx.gob.mx/archivo-9f74acb7161683c662d59b2affce2de003e62615.pdf",
  "materia": [
    "justicia",
    "administrativo"
  ]
}