{
  "titulo": "Ley DE ACCESO DE LAS MUJERES A UNA VIDA LIBRE DE VIOLENCIA DE LA CIUDAD DE MÉXICO",
  "Contenido": "PUBLICADO EN LA GACETA OFICIAL DE LA CIUDAD DE MÉXICO\nEL 29 DE ENERO DE 2008\nTEXTO VIGENTE\nÚLTIMA REFORMA PUBLICADA EN LA G.O.C.D.M.X.\nEL 27 DE MARZO DE 2024\nADMINISTRACIÓN PÚBLICA DEL DISTRITO FEDERAL\nJEFATURA DE GOBIERNO\nLEY DE ACCESO DE LAS MUJERES A UNA VIDA LIBRE DE VIOLENCIA DEL DISTRITO FEDERAL\n(Al margen superior un escudo que dice: Ciudad de México. - Capital en Movimiento)\nDECRETO POR EL QUE SE EXPIDE LA LEY DE ACCESO DE LAS MUJERES A UNA VIDA LIBRE DE VIOLENCIA DEL\nDISTRITO FEDERAL.\nMARCELO LUIS EBRARD CASAUBON, Jefe de Gobierno del Distrito Federal, a sus habitantes sabed: Que la\nH. Asamblea Legislativa del Distrito Federal, IV Legislatura se ha servido dirigirme el siguiente:\nDECRETO\n(Al margen superior izquierdo el Escudo Nacional que dice: ESTADOS UNIDOS MEXICANOS. - ASAMBLEA\nLEGISLATIVA DEL DISTRITO FEDERAL. - IV LEGISLATURA) ASAMBLEA LEGISLATIVA DEL DISTRITO FEDERAL IV\nLEGISLATURA DECRETA\nDECRETO POR EL QUE SE EXPIDE LA LEY DE ACCESO DE LAS MUJERES A UNA VIDA LIBRE DE VIOLENCIA DEL\nDISTRITO FEDERAL.\nARTÍCULO PRIMERO. - Se expide la Ley de Acceso de las Mujeres a una Vida Libre de Violencia del Distrito\nFederal, para quedar como sigue:\n\nL E Y D E A C C E S O D E L A S M U J E R E S A U N A V I D A\nL I B R E D E V I O L E N C I A D E L A C I U D A D D E\nM É X I C O\nT Í T U L O P R I M E R O\nC A P Í T U L O Ú N I C O\nD I S P O S I C I O N E S G E N E R A L E S\nArtículo 1. Las disposiciones de la presente Ley son de orden público, interés social y observancia general en la Ciudad de México.\nArtículo 2. El objeto de la presente ley es establecer los principios y criterios que, desde la perspectiva de género, orienten las políticas públicas para reconocer, promover, proteger y garantizar el derecho de las mujeres a una vida libre de violencia; así como establecer la coordinación interinstitucional para prevenir, atender, sancionar y erradicar la violencia contra las mujeres en el marco de los ordenamientos jurídicos aplicables en la Ciudad de México y lo previsto en el primero, segundo y tercer párrafos del artículo 1º de la Constitución Política de los Estados Unidos Mexicanos, respetándose los derechos humanos de las mujeres de conformidad con los principios de universalidad, interdependencia, indivisibilidad, pro persona y progresividad establecidos en los Tratados Internacionales en materia de Derechos Humanos de las Mujeres.\nArtículo 3. Para efectos de la presente ley se entenderá:\nI. Acciones afirmativas: Las medidas especiales de carácter temporal, correctivo, compensatorio y de promoción, encaminadas a acelerar la igualdad sustantiva entre mujeres y hombres, aplicables en tanto subsista la discriminación, desigualdad de trato y oportunidades de las mujeres respecto a los hombres;\nI Bis. Cosificación. Tratar, considerar, reducir o pensar a las mujeres, adolescentes y niñas, o su cuerpo o partes de éste, como bien u objeto y no como la persona misma con identidad, ideas, sentimientos, voluntad, derechos y necesidades propias.\nFracción adicionada y publicada en la GOCDMX el 06 de octubre de 2023\nLa cosificación se puede encontrar en cualquier tipo o modalidad de violencia contra las mujeres.\n\nII. Debida diligencia: La obligación de las personas que tienen la calidad de servidores públicos, las dependencias y entidades de la Ciudad de México, de dar respuesta eficiente, eficaz, oportuna y responsable para garantizar los derechos de las mujeres;\nIII. Declaratoria de Alerta de Violencia contra las mujeres: conjunto de acciones gubernamentales de emergencia para enfrentar y erradicar la violencia feminicida en un territorio determinado, ya sea ejercida por individuos o por la propia comunidad;\nIV. Discriminación contra las mujeres: Toda distinción, exclusión o restricción que sufren las mujeres por razón de género, edad, salud, características físicas, posición social, económica, condición étnica, nacional, religiosa, opinión, identidad u orientación sexual, estado civil, o cualquier otra que atente contra su dignidad humana, que tiene por objeto menoscabar o anular el goce o ejercicio de sus derechos;\nV. Empoderamiento de las mujeres: El proceso que permite el tránsito de las mujeres de cualquier situación de opresión, desigualdad, discriminación, explotación o exclusión hacia un estadio de conciencia, autodeterminación y autonomía, que se manifiesta en el ejercicio pleno de sus derechos y garantías;\nVI. Fiscalía: La Fiscalía General de la Ciudad de México;\nVII. SEMUJERES: Secretaría de las Mujeres de la Ciudad de México;\nVIII. Ley: Ley de Acceso de las Mujeres a una Vida Libre de Violencia de la Ciudad de México;\nIX. LUNAS: Unidades de Atención a mujeres víctimas de violencia que brindan asesoría psicológica y legal, formación para el liderazgo y servicios comunitarios, para promover la autonomía y la exigibilidad de derechos de las mujeres y niñas;\nX. Misoginia: Las conductas de odio contra las mujeres por el hecho de serlo;\nXI. Mujeres en condición de vulnerabilidad: Aquellas en mayor situación de riesgo de ser víctimas de violencia en atención a su raza, origen étnico, edad, discapacidad, condición social, económica, de salud, embarazo, lengua, idioma, religión, opiniones, orientación sexual, estado civil; cuando tengan la calidad de migrante, refugiada, desplazada o privadas de la libertad por mandato judicial; sea víctima de trata de personas, turismo sexual, prostitución, pornografía,\n\nprivación de la libertad o cualquier otra condición que anule o menoscabe su derecho a una vida libre de violencia;\nXII. Modalidades de violencia: Los ámbitos donde ocurre, públicos o privados, y se ejerce la violencia contra las mujeres;\nXIII. Parto Humanizado: Modelo de atención a las mujeres durante el parto y el puerperio, basado en el respeto a sus derechos humanos, su dignidad, Integridad, libertad y toma de decisiones relativas a cómo, dónde y con quién parir. La atención Médica otorgada debe estar basada en fundamentos científicos y en las recomendaciones de la Organización Mundial de la\nSalud, proporcionando condiciones de comodidad y privacidad durante el parto, con lo mejor de la atención desmedicalizada, y garantizando en su caso, la coordinación y los acuerdos interinstitucionales para identificar, atender y resolver de manera oportuna y segura las complicaciones y emergencias obstétricas.\nEl modelo incluye de manera explícita y directa, las opiniones, necesidades y valoraciones emocionales de las mujeres y sus familias en los procesos de atención del parto y puerperio, incorporando medidas para erradicar las barreras culturales y de género que dificultan el acceso de las mujeres a los servicios de salud, reconociendo la diversidad cultural existente, y los aportes de la partería tradicional y otros aportes clínico terapéuticos de salud no convencionales;\nXIV. Persona agresora: Quien o quienes infligen algún tipo de violencia contra las mujeres en cualquiera de sus tipos y modalidades;\nXV. Perspectiva de género: Visión crítica, explicativa, analítica y alternativa que aborda las relaciones entre los géneros y que permite enfocar y comprender las desigualdades construidas socialmente entre mujeres y hombres y establece acciones gubernamentales para disminuir las brechas de desigualdad entre mujeres y hombres;\nXV Bis. Perspectiva Intercultural: enfoque que toma como punto de partida la realidad social y la pluralidad cultural de determinados grupos sociales que pertenecen a una cultura históricamente marginada;\nXVI. Red de información de violencia contra las mujeres: El sistema de recolección, procesamiento y clasificación de la información producida por las dependencias y entidades señaladas en esta Ley;\n\nXVII. Refugios Especializados. Las estancias del Gobierno de la Ciudad de México, específicamente creadas para la atención de víctimas de trata de personas;\nXVIII. Registro: El Registro Público de Personas Agresores Sexuales;\nXIX. Relación afectiva o de hecho: Aquella en la que se comparte una relación íntima sin convivencia ni vínculo matrimonial o concubinato;\nXX. Tipos de violencia: Los distintos daños que puede ocasionar la violencia contra las mujeres;\nXXI. Tribunal: El Tribunal Superior de Justicia de la Ciudad de México;\nXXII. Víctima: La mujer de cualquier edad que sufra algún tipo de violencia;\nXX Bis. Servicios reeducativos: Procesos mediante los cuales se trabaja con las personas agresoras de manera individual o colectiva, con el objetivo de erradicar las creencias de supremacía masculina, las prácticas machistas y aquellas conductas que posibilitan, justifican y sostienen el ejercicio de las violencias contra las mujeres en cualquiera de sus tipos y modalidades;\nFracción adicionada y publicada en la GOCDMX el 10 de octubre de 2023\nXXIII. Víctima indirecta: familiares de la víctima y/o personas que tengan o hayan tenido relación o convivencia con la misma y que sufran, hayan sufrido o se encuentren en situación de riesgo por motivo de la violencia ejercida contra las mujeres;\nXXIV. Violencia contra las mujeres: Toda acción u omisión que, basada en su género y derivada del uso y/o abuso del poder, tenga por objeto o resultado un daño o sufrimiento físico, psicológico, patrimonial, económico, sexual o la muerte a las mujeres, tanto en el ámbito público como privado, que limite su acceso a una vida libre de violencia.\nArtículo 4. Los principios rectores de esta Ley son:\nI. El respeto a la dignidad humana de las mujeres;\nII. La libertad y autonomía de las mujeres;\nIII. La no discriminación;\n\nIV. La igualdad de género;\nV. La transversalidad de la perspectiva de género, y la coordinación institucional en términos del artículo 11 de esta ley;\nVI. Seguridad Jurídica, en términos del artículo 54 de la propia ley;\nVII. La protección y seguridad; y\nVIII. El apoyo y desarrollo integral de la víctima.\nArtículo 5. Las mujeres víctimas de cualquier tipo de violencia tendrán los derechos siguientes:\nI. Ser tratadas con respeto a su integridad y el ejercicio pleno de sus derechos;\nII. Contar con protección inmediata y efectiva por parte de las autoridades cuando se encuentre en riesgo su integridad física o psicológica, la libertad o seguridad de la víctima o de las víctimas indirectas.\nIncluyendo para efectos de prevención de riesgo de sufrir algún acto de violencia sexual, el que exista un Registro Público de Personas Agresoras Sexuales, en los términos y bajo las características que señale la normatividad aplicable;\nIII. Recibir información veraz y suficiente que les permita decidir sobre las opciones de atención, así como la orientación, atención y de ser necesario, la canalización oportuna por parte de las autoridades;\nFracción modificada y publicada en la GOCDMX el 10 de octubre de 202\nIV. Contar con asesoría y representación jurídica gratuita y expedita;\nV. Recibir información, atención y acompañamiento médico y psicológico;\nVI. Acudir y ser recibidas con sus hijas e hijos, en los casos de violencia familiar, delitos sexuales, contra la libertad personal, tentativa de feminicidio y lesiones, en las Casas de Emergencia y los\nCentros de Refugio destinados para tal fin. Cuando se trate de víctimas de trata de personas, las mujeres recibirán atención integral con sus hijas e hijos en Refugios Especializados;\n\nVII. Ser valoradas y educadas libres de estereotipos de comportamiento y prácticas sociales y culturales basadas en conceptos de inferioridad o subordinación;\nReforma publicada en la GOCDMX el 30 de noviembre de 2022\nVIII. Acceder a procedimientos expeditos y accesibles de procuración y administración de justicia.\nIX. Recibir información en su idioma o lengua materna sobre sus derechos y el progreso de los trámites judiciales y administrativos;\nX. A la protección de su identidad y la de su familia.\nT Í T U L O S E G U N D O\nT I P O S Y M O D A L I D A D E S D E V I O L E N C I A C O N T R A L A S\nM U J E R E S\nC A P Í T U L O I\nD E L O S T I P O S D E V I O L E N C I A C O N T R A L A S M U J E R E S\nArtículo 6. Los tipos de violencia contra las mujeres son:\nI. Violencia Familiar: Es aquella que puede ocurrir dentro o fuera del domicilio de la víctima, cometido por parte de la persona agresora con la que tenga o haya tenido parentesco por consanguinidad o por afinidad, derivada de concubinato, matrimonio, sociedad de convivencia o relaciones de hecho;\nLa violencia psicoemocional se sanciona de acuerdo con lo establecido en los artículos 138 y 200 del Código Penal para el Distrito Federal.\nII. Violencia Física: Es cualquier acción u omisión que cause o busque causar daño en la integridad física de la mujer, provocando lesiones temporales o permanentes, internas, externas o ambas, algún tipo de discapacidad o pongan en peligro la vida.\nFracción modificada y publicada en la GOCDMX el 19 de febrero de 2024\nLa violencia física se sanciona de acuerdo con lo establecido en los artículos 130, 131 y 132 del\nCódigo Penal para el Distrito Federal\n\nIII. Violencia Patrimonial: Toda acción u omisión que ocasiona daño o menoscabo en los bienes muebles o inmuebles de la mujer y su patrimonio; también puede consistir en la sustracción, destrucción, desaparición, ocultamiento o retención de objetos, documentos personales, bienes o valores o recursos económicos;\nLa violencia patrimonial se sanciona de acuerdo con lo establecido en los artículos 200 y 236 del\nCódigo Penal para el Distrito Federa\nIV. Violencia Económica: Toda acción u omisión que afecta la economía de la mujer, a través de limitaciones encaminadas a controlar el ingreso de sus percepciones económicas, en la restricción, limitación y/o negación injustificada para obtener recursos económicos, percepción de un salario menor por igual trabajo, explotación laboral, exigencia de exámenes de no gravidez, así como la discriminación para la promoción laboral;\nLa violencia económica se sanciona de acuerdo con lo establecido en el artículo 193 del Código\nPenal para el Distrito Federal.\nV. Violencia Sexual: Toda acción u omisión que amenaza, pone en riesgo o lesiona la libertad, seguridad, integridad y desarrollo psicosexual de la mujer, como miradas o palabras lascivas, hostigamiento, prácticas sexuales no voluntarias, acoso, violación, explotación sexual comercial, trata de personas para la explotación sexual o el uso denigrante de la imagen de la mujer;\nLa violencia sexual se sanciona de acuerdo con lo establecido en los artículos 152, 174, 175, 176,\n177, 178, 179, 180, 181, 181 Bis, 181 Ter, 181 Quáter, 186, 187, 188, 188 Bis, 189 y 189 Bis del Código Penal para el Distrito Federal.\nVI. Violencia contra los Derechos Reproductivos: Toda acción u omisión que limite o vulnere el derecho de las mujeres a decidir libre y voluntariamente sobre su función reproductiva, en relación con el número y espaciamiento de los hijos; el acceso a métodos anticonceptivos de su elección; a una maternidad elegida y segura; a servicios de aborto seguro en el marco previsto por la ley para la interrupción legal del embarazo; a servicios de atención prenatal; a servicios obstétricos de emergencia; así como la libertad de elección en cuanto a los productos e insumos para la gestión menstrual.\nPárrafo modificado y publicado en la GOCDMX el 27 de marzo de 2024\n\nLa violencia contra los derechos reproductivos se concreta al no cumplir con lo establecido en el artículo 144 del Código Penal para el Distrito Federal.\nVII. Violencia Obstétrica: Es toda acción u omisión que provenga de una o varias personas, que proporcionen atención médica o administrativa, en un establecimiento privado o institución de salud pública del gobierno de la Ciudad de México que dañe, lastime, o denigre a las mujeres de cualquier edad, cultura, grupo étnico u origen durante el embarazo, parto o puerperio, así como la negligencia, juzgamiento, maltrato, discriminación y vejación en su atención médica; se expresa por el trato deshumanizado, abuso de medicación y patologización de los procesos naturales, vulnerando la libertad e información completa, así como la capacidad de las mujeres para decidir libremente sobre su cuerpo, salud, sexualidad o sobre el número y espaciamiento de sus hijos. Se caracteriza por:\nReforma publicada en la GOCDMX el 22 de diciembre de 2022\nSe caracteriza por:\na) Omitir o retardar la atención oportuna y eficaz de las emergencias y servicios obstétricos; especialmente cuando se trate de mujeres indígenas y/o afrodescendientes;\nb) Obligar a la mujer a parir en condiciones ajenas a su voluntad o contra sus prácticas culturales, cuando existan los medios necesarios para la realización del parto humanizado y parto natural;\nc) Obstaculizar el apego precoz de la niña o niño con su madre sin causa médica justificada, negándole la posibilidad de cargarle y amamantarle inmediatamente después de nacer;\nd) Alterar el proceso natural del parto de bajo riesgo, mediante el uso de medicamentos o técnicas de aceleración, sin obtener el consentimiento voluntario, culturalmente adecuado, expreso e informado de la mujer;\ne) Practicar el parto por vía de cesárea, existiendo condiciones para el parto natural, o;\nImponer bajo cualquier medio el uso de métodos anticonceptivos o de esterilización sin que medie el consentimiento voluntario, culturalmente adecuado, expreso e informado de la mujer; y\nReforma publicada en la GOCDMX el 22 de diciembre de 2022\n\nVIII. Violencia Feminicida: Toda acción u omisión que constituye la forma extrema de violencia contra las mujeres producto de la violación de sus derechos humanos y que puede culminar en homicidio u otras formas de muerte violenta de mujeres.\nIX. Simbólica: La que, a través de patrones estereotipados, mensajes, valores, íconos o signos, transmita y reproduzca dominación, cosificación, desigualdad y discriminación en las relaciones sociales, naturalizando la subordinación de las mujeres en la sociedad.\nFracción modificada y publicada en la GOCDMX el 06 de octubre de 2023\nX. Violencia Vicaria: es la acción u omisión cometida por quien tenga o haya tenido una relación de matrimonio, concubinato o haya mantenido una relación de hecho o de cualquier otro tipo, por sí o por interpósita persona, que provoque la separación de la madre con sus hijas e hijos o persona vinculada significativamente a la mujer, a través de la retención, sustracción, ocultamiento, maltrato, amenaza, puesta en peligro o promoviendo mecanismos jurídicos y no jurídicos que retrasen, obstaculicen, limiten e impidan la convivencia, para manipular, controlar a la mujer o dañar el vínculo afectivo, que ocasionen o puedan ocasionar un daño psicoemocional, físico, patrimonial o de cualquier otro tipo a ella y a sus hijas e hijos o persona vinculada significativamente a la mujer, e incluso el suicidio a las madres y a sus hijas e hijos o persona vinculada significativamente a la mujer, así como desencadenar en el feminicidio u homicidio de las hijas e hijos perpetrados por su progenitor\nEste tipo de violencia puede cometerse también a través de familiares o personas con relación afectiva de quien comete este tipo de violencia.\nEs particularmente grave cuando las instituciones destinadas a la atención y acceso a la justicia, al no reconocerla, emiten determinaciones, resoluciones y sentencias sin perspectiva de género vulnerando derechos humanos de las mujeres y el interés superior de la niñez.\nReforma publicada en la GOCDMX el 12 de diciembre de 2022\nXI. Violencia por ataques con ácido, sustancias químicas o corrosivas: Es cualquier acción u omisión que cause o busque causar daño no accidental arrojando, derramando o poniendo en contacto con algún tipo de gas, compuesto químicos, ácido, álcalis, sustancias químicas, corrosivas, cáusticas, irritantes, tóxicas, inflamables, explosivas, reactivas, líquidos a altas temperaturas o cualquier otra sustancia que por sí misma o en determinadas condiciones pueda provocar lesiones temporales o permanentes, internas, externas o ambas, algún tipo de discapacidad o pongan en peligro la vida.\n\nFracción adicionada y publicada en la GOCDMX el 19 de febrero de 2024\nC A P Í T U L O I I\nD E L A S M O D A L I D A D E S D E L A V I O L E N C I A\nArtículo 7. Las modalidades de violencia contra las mujeres son:\nI. Violencia Familiar: Es aquella que puede ocurrir dentro o fuera del domicilio de la víctima, cometido por parte de la persona agresora con la que tenga o haya tenido parentesco por consanguinidad o por afinidad, derivada de concubinato, matrimonio, o sociedad de convivencia;\nReforma publicada en la GOCDMX el 30 de noviembre de 2022\nLa violencia familiar se sanciona de acuerdo con lo establecido en los artículos 181 Ter, fracción\nII, 193 y 200, del Código Penal para el Distrito Federal;\nII. Violencia en el noviazgo: Es el acto abusivo de poder u omisión intencional, dirigido a dominar, someter, controlar o agredir a las mujeres de cualquier edad, mediante la relación de uno o varios tipos de violencia, durante o después de una relación de noviazgo, una relación afectiva o de hecho o una relación sexual.\nLa violencia en el noviazgo se sanciona de acuerdo con lo establecido en los artículos 131 y 148\nBis del Código Penal para el Distrito Federal;\nIII. Violencia Laboral: Es aquella que ocurre cuando se presenta la negativa a contratar a la víctima o a respetar su permanencia o condiciones generales de trabajo; la descalificación del trabajo realizado, las amenazas, la intimidación, las humillaciones, la explotación y todo tipo de discriminación por condición de género;\nLa violencia laboral se sanciona de acuerdo con lo establecido en los artículos 131, 148 Bis, 179 y 181 Ter del Código Penal para el Distrito Federal. Así como, lo establecido en el artículo 994 de la Ley Federal del Trabajo;\n\nIV. Violencia Escolar: Son todas aquellas conductas, acciones u omisiones, infligidas por el personal docente o administrativo o cualquier integrante de la comunidad educativa que daña la dignidad, salud, integridad, libertad y seguridad de las víctimas. La violencia escolar se manifiesta en todas aquellas conductas cometidas individual o colectivamente, en un proceso de interacción que se realiza y prolonga tanto al interior como al exterior de los planteles educativos o del horario escolar, y se expresa mediante la realización de uno o varios tipos de violencia contra las mujeres en cualquier etapa de su vida.\nLa violencia escolar se sanciona de acuerdo con lo establecido en los artículos 131, 148 Bis y 178 del Código Penal para el Distrito Federal;\nV. Violencia Docente: Es aquella que puede ocurrir cuando se daña la autoestima de las alumnas o maestras con actos de discriminación por su sexo, edad, condición social, académica, limitaciones y/o características físicas, que les inflingen maestras o maestros;\nLa violencia docente se sanciona de acuerdo con lo establecido en los artículos 131, 148 Bis, 179 y 181 Ter del Código Penal para el Distrito Federal;\nVI. Violencia en la Comunidad: Es aquella cometida de forma individual o colectiva, que atenta contra su seguridad e integridad personal y que puede ocurrir en el barrio, en los espacios públicos o de uso común, de libre tránsito, en inmuebles públicos o medios de transporte público, propiciando su discriminación, marginación o exclusión social;\nPárrafo modificado y publicado en la GOCDMX el 10 de octubre de 2023\nLa violencia en la comunidad se sanciona de acuerdo con lo establecido en los artículos 174 y\n179 del Código Penal para el Distrito Federal. Así como, lo establecido en el artículo 161, fracción\nXVIII del reglamento de la Ley de Movilidad del Distrito Federal;\nVII. Violencia Institucional: Son los actos u omisiones de las personas con calidad de servidor público que discriminen o tengan como fin dilatar, obstaculizar o impedir el goce y ejercicio de los derechos humanos de las mujeres así como su acceso al disfrute de políticas públicas destinadas a prevenir, atender, investigar, sancionar y erradicar los diferentes tipos de violencia.\nEl Gobierno de la Ciudad de México, se encuentra obligado a actuar con la debida diligencia para evitar que se inflija violencia contra las mujeres.\n\nLa violencia institucional se sanciona de acuerdo con lo establecido en los artículos 153, 178 fracción II, 179, 181 Quintus fracción IV, 206 fracción II y 206 Bis del Código Penal para el Distrito\nFederal;\nVIII. Violencia mediática contra las mujeres: Aquella publicación o difusión de mensajes e imágenes estereotipados a través de cualquier medio de comunicación público o privado, que de manera directa o indirecta produzca contenidos o promueva la explotación de niñas y mujeres adolescentes o adultas, o sus imágenes, cosifique, injurie, difame, discrimine, deshonre, humille o atente contra la dignidad de las mujeres, fomente o exhiba mujeres violentadas, como así también la utilización de mujeres, adolescentes y niñas en mensajes e imágenes pornográficas, legitimando la desigualdad de trato o construya patrones socioculturales reproductores de la desigualdad o generadores de violencia contra las mujeres.\nPárrafo modificado y publicado en la GOCDMX el 06 de octubre de 2023\nSe considera dentro de esta modalidad de la violencia la influencia de las personas físicas y morales que tienen el poder, control, dominio de los medios de comunicación y que utilizan, difunden o exhiben a figuras públicas o su imagen para promover e incitar a la violencia contra las mujeres, adolescentes y niñas en las personas usuarias o en quienes consumen el contenido.\nPárrafo adicionado y publicado en la GOCDMX el 06 de octubre de 2023\nIX. Violencia Política en Razón de Género: Es toda acción u omisión ejercida en contra de una mujer, en el ámbito político o público, que tenga por objeto o resultado sesgar, condicionar, impedir, restringir, suspender, menoscabar, anular, obstaculizar, excluir o afectar el reconocimiento, acceso, goce o ejercicio de los derechos político electorales de una mujer, así como el acceso al pleno ejercicio de las atribuciones inherentes a su cargo o función en el poder público.\nLa violencia política en razón de género se sanciona de acuerdo con lo establecido en el Código de Instituciones y Procedimientos Electorales de la Ciudad de México y lo que se establece en el artículo 264 Bis del mismo en el Protocolo de Atención, Sanción y Erradicación de la Violencia\nPolítica en Razón de Género;\nX. Violencia digital.- Es cualquier acto realizado mediante el uso de materiales impresos, correo electrónico, mensajes telefónicos, redes sociales, plataformas de internet, correo electrónico, o cualquier medio tecnológico, por el que se obtenga, exponga, distribuya, difunda, exhiba, reproduzca, transmita, comercialice, oferte, intercambie y comparta imágenes, audios o videos\n\nreales o simulados de contenido sexual íntimo de una persona, sin su consentimiento; que atente contra la integridad, la dignidad, la intimidad, la libertad, la vida privada de las mujeres o cause daño psicológico, económico o sexual tanto en el ámbito privado como en el público, además de daño moral, tanto a ellas como a sus familias.\nSe manifiesta en presión, persecución, hostigamiento, acoso, coacción, vejación, discriminación, amenazas o privación de la libertad o de la vida en razón del género.\nSe consideran actos de violencia política en contra de las mujeres, entre otros, los siguientes:\na) Obligar, instruir o coaccionar a realizar u omitir actos diferentes a las funciones y obligaciones de su cargo, establecidas en los ordenamientos jurídicos, incluyendo aquellos motivados por los roles o estereotipos de género;\nb) Ejercer cualquier tipo de violencia señalada en la presente Ley, en contra de las mujeres, de sus familiares o personas cercanas, con el fin de sesgar, condicionar, impedir, acotar o restringir la participación y representación política y pública, así como la toma de decisiones en contra de su voluntad o contrarias al interés público;\nc) Coartar o impedir el ejercicio de la participación, representación y facultades inherentes a los cargos públicos y políticos de las mujeres, o bien coartar e impedir aquellas medidas establecidas en Ia Constitución y los ordenamientos jurídicos dirigidas a proteger sus derechos frente a los actos que violenten o eviten el ejercicio de su participación y representación política y pública, incluyendo la violencia institucional;\nd) Proporcionar información falsa, errónea o imprecisa que induzca al inadecuado ejercicio de sus funciones político-públicas;\ne) Impedir o excluir de la toma de decisiones o del derecho a voz y voto, a través del engaño o la omisión de notificación de actividades inherentes a sus facultades o a la participación y representación política y pública;\nf) Proporcionar información o documentación incompleta o errónea con el objeto de impedir el ejercicio pleno de los derechos político electorales o inducir al ejercicio indebido de sus atribuciones o facultades;\n\ng) Ocultar información o documentación con el objeto de limitar o impedir el ejercicio de sus derechos político-electorales o inducir al ejercicio indebido de sus atribuciones;\nh) Proporcionar o difundir información con la finalidad de impedir o limitar el ejercicio de los derechos político-electorales o impedir el ejercicio de sus atribuciones o facultades;\ni) Obstaculizar o impedir el ejercicio de licencias o permisos justificados a los cargos públicos a los cuales fueron nombradas o electas, así como Ia reincorporación posterior;\nj) Restringir total o parcialmente, por cualquier medio o mecanismo, el ejercicio de los derechos de voz y voto de las mujeres, que limiten o impidan las condiciones de igualdad respecto de los hombres para el ejercicio de la función y representación política y pública;\nk) Acosar u hostigar mediante la acusación o Ia aplicación de sanciones sin motivación o fundamentación, que contravengan las formalidades, el debido proceso y Ia presunción de inocencia, con el objetivo o resultado de impedir o restringir el ejercicio de los derechos político-electorales;\nl) Realizar cualquier acto de discriminación que tenga como resultado impedir, negar, anular o menoscabar el ejercicio de sus derechos político-electorales;\nm) Publicar o revelar información personal, privada o falsa, o bien difundir imágenes, información u opiniones con sesgos basados en los roles y estereotipos de género a través de cualquier medio, con o sin su consentimiento, que impliquen difamar, desprestigiar o menoscabar la credibilidad, capacidad y dignidad humana de las mujeres, con el objetivo o resultado de obtener su remoción, renuncia o licencia al cargo electo o en ejercicio;\nn) Espiar o desprestigiar a las mujeres a través de los medios de comunicación con el objetivo o resultado de impedir o restringir el ejercicio de los derechos políticoelectorales;\no) Obligar, intimidar, o amenazar a las mujeres para que suscriban documentos, colaboren en proyectos o adopten decisiones en contra de su voluntad o del interés público, en función de su representación política;\np) Proporcionar información incompleta, falsa o errónea de los datos personales de las mujeres candidatas a cargos de elección popular, ante el lnstituto Nacional Electoral o los\n\nOrganismos Públicos Locales Electorales, con Ia finalidad de impedir, obstaculizar o anular sus registros a las candidaturas;\nq) Impedir o restringir su incorporación, de toma de protesta o acceso al cargo o función para el cual ha sido nombrada, electa o designada.\nr) Impedir u obstaculizar los derechos de asociación y afiliación en los partidos políticos en razón de género; y s) Cualquier otro que tenga por objeto o resultado coartar los derechos políticoelectorales, incluyendo los motivados en razón de sexo o género.\nLa violencia digital se sanciona de acuerdo con lo establecido en el artículo 181 Quintus del\nCódigo Penal para el Distrito Federal.\nLos conceptos, y sanciones anteriores se deben entender en términos del Código Penal, el\nCódigo de Instituciones y Procedimientos Electorales, la Ley de Movilidad, el Protocolo de\nAtención, Sanción y Erradicación de la Violencia Política en Razón de Género y demás Leyes aplicables y vigentes en la Ciudad de México.\nT Í T U L O T E R C E R O\nD E L A D E C L A R A T O R I A D E A L E R T A Y M E D I D A S P O R\nV I O L E N C I A C O N T R A L A S M U J E R E S\nC A P Í T U L O I\nD E L A D E C L A R A T O R I A D E A L E R T A P O R V I O L E N C I A\nC O N T R A L A S M U J E R E S\nArtículo 8. La Secretaría de Gobierno, a petición la Secretaría de las Mujeres y/o de las personas titulares de las Alcaldías, así como de organismos públicos autónomos de derechos humanos u organismos internacionales de protección de derechos humanos, o de las organizaciones de la sociedad civil legalmente constituidas, emitirá en un periodo máximo de diez días naturales la Declaratoria de Alerta de\nViolencia de Género contra las Mujeres para enfrentar la violencia feminicida que se ejerce en su contra cuando:\n\nI. Existan hechos documentados que presuman la comisión de delitos graves y sistemáticos contra las mujeres\nII. Existan elementos que presuman una inadecuada investigación y sanción de esos delitos; o\nIII. Exista un agravio comparado que impida el ejercicio pleno de los derechos humanos de las mujeres.\nArtículo 9. La Declaratoria de Alerta de Violencia de Género contra las Mujeres tendrá como objetivo garantizar el cese de la violencia contra las mujeres, así como su seguridad e integridad física, emocional y patrimonial. Para ello, la Alerta de Violencia contra las Mujeres deberá:\nI. Conformar un grupo interinstitucional, multidisciplinario y con perspectiva de género que dé seguimiento a las acciones de la Declaratoria de Alerta de Violencia de Género contra las Mujeres;\nII. Acordar e implementar las acciones preventivas, de seguridad y justicia, necesarias para garantizar el cese de violencia contra las mujeres;\nIII. Asignar recursos presupuestales necesarios para hacer frente a la alerta de violencia contra las mujeres, y\nIV. Hacer del conocimiento público el motivo de la Declaratoria de Alerta de Violencia de Género contra las Mujeres y la zona territorial que abarcan las medidas a implementar.\nC A P Í T U L O I I\nD E L A S M E D I D A S E N L O S C A S O S D E V I O L E N C I A\nF E M I N I C I D A\nArtículo 10. Ante la Declaratoria de Alerta de Violencia de Género contra las Mujeres, el Gobierno de la\nCiudad de México deberá tomar las siguientes medidas:\nI. Apoyar de forma inmediata a las mujeres víctimas de violencia y sus hijas e hijos a través de servicios especializados y con perspectiva de género tanto médicos, como psicológicos, y legales.\nEstos servicios serán gratuitos;\n\nII. Reparación integral del daño a las mujeres víctimas de violencia, sus hijas e hijos o víctimas indirectas, garantizar su seguridad a través de medidas de protección y el seguimiento del cumplimiento de estas; y, la investigación y sanción de los actos de autoridades omisas o negligentes, que pudieron haber propiciado casos de impunidad o violaciones a los derechos humanos de las mujeres víctimas de violencia;\nII Bis. Diseñar e instrumentar políticas públicas específicas e integrales para prevenir la comisión de nuevos delitos contra las mujeres, así como para la verificación de los hechos y la publicidad de la verdad; y\nIII. Todas aquellas que se consideren necesarias para atender, erradicar y sancionar la violencia contra las mujeres, atendiendo las observaciones y recomendaciones del grupo interinstitucional multidisciplinario que se conforme para atender la declaratoria de la Alerta de Violencia de\nGénero contra Mujeres.\nT Í T U L O C U A R T O\nD E L G A B I N E T E D E I G U A L D A D S U S T A N T I V A Y\nV I O L E N C I A C O N T R A L A S M U J E R E S Y L A S M E D I D A S D E\nP R E V E N C I Ó N Y A T E N C I Ó N\nC A P Í T U L O I\nD E L G A B I N E T E D E I G U A L D A D S U S T A N T I V A Y\nV I O L E N C I A C O N T R A L A S M U J E R E S\nArtículo 11. Para la efectiva aplicación de la presente Ley, las dependencias, órganos y entidades de la\nCiudad de México establecerán el Gabinete de Igualdad Sustantiva y Violencia contra las Mujeres para la\nCiudad de México, entre las Secretarías de Gobierno, Inclusión y Bienestar Social, Seguridad Ciudadana,\nTrabajo y Fomento al Empleo, Salud, Educación, Ciencia, Tecnología e Innovación, Cultura, Desarrollo\nUrbano y Vivienda, Fiscalía General de Justicia, Consejería Jurídica y de Servicios Legales, Secretaría de las\nMujeres, Procuraduría Social, Sistema de Transporte Público, Sistema para el Desarrollo Integral de la\nFamilia de la Ciudad de México y las dieciséis Alcaldías. El Gabinete de Igualdad Sustantiva y Violencia contra las Mujeres para la Ciudad de México establecido en esta Ley se coordinará con el Sistema Nacional\npara Prevenir, Atender, Sancionar y Erradicar la Violencia contra las Mujeres.\nArtículo 12. El Gabinete de Igualdad Sustantiva y Violencia contra las Mujeres para la Ciudad de México implementará las acciones de prevención, atención y de acceso a la justicia, así como las acciones\n\nafirmativas que considere necesarias, desde la debida diligencia para erradicar la violencia contra las mujeres.\nAsimismo, diseñará un Plan Anual de Trabajo que contenga las acciones en materia de prevención, atención, sanción y erradicación de la violencia contra las mujeres.\nC A P Í T U L O I I\nD E L A P R E V E N C I Ó N\nArtículo 13. La prevención es el conjunto de acciones que deberán llevar a cabo las dependencias, entidades de la Ciudad de México y las Alcaldías, conjuntamente con la población, la iniciativa privada, la sociedad civil organizada y los medios de comunicación, para evitar la comisión de delitos y otros actos de violencia contra las mujeres, atendiendo a los posibles factores de riesgo tanto en los ámbitos público y privado.\nLa prevención también comprenderá medidas en materia de educación para toda la población, encaminadas a eliminar la cultura y prácticas machistas, roles de género, cualquier tipo de violencia y prejuicios de toda índole.\nReforma publicada en la GOCDMX el 30 de noviembre de 2022\nLas dependencias, entidades de la Ciudad de México y las Alcaldías difundirán, promoverán y fomentarán la participación de la población, la iniciativa privada, la sociedad civil organizada y los medios de comunicación, en el conjunto de acciones que se lleve a cabo en materia de prevención.\nAsí como las medidas de seguridad que determine el órgano jurisdiccional en materia de registro de personas sentenciadas por delitos relacionados con violencia sexual.\nArtículo 14. Las medidas de prevención general, son aquellas que, desde los distintos ámbitos de acción de las dependencias, entidades de la Ciudad de México y las Alcaldías, están destinadas a toda la colectividad y tienen como propósito evitar la comisión de conductas delictivas y otros actos de violencia contra las mujeres, así como propiciar su empoderamiento.\nArtículo 14 Bis.- Serán consideradas como medidas especiales de prevención aquellas que permitan a las mujeres embarazadas, con discapacidad, de la tercera edad, de identidad indígena, pertenecientes a un pueblo y barrio originario o comunidad indígena residente, afrodescendiente o afectadas por cualquiera\n\notra condición de vulnerabilidad, el establecimiento de acciones concretas y obligatorias para que gocen de las siguientes facilidades:\nReforma publicada en la GOCDMX el 22 de diciembre de 2022\nI. Contar con una atención preferente, ágil, pronta, expedita y culturalmente adecuada, cuando se encuentren realizando algún trámite, solicitando algún servicio o participando de algún procedimiento ante cualquier Autoridad Local;\nII. Ser atendidas con prontitud y diligencia por los particulares que brinden algún servicio público.\nArticulo 14 Ter. Se crea el Registro Público de Personas Agresoras Sexuales de la Ciudad de México, como mecanismo efectivo de prevención y protección para los efectos de atender al factor de riesgo de reincidencia y repetición de conductas de violencia sexual, a favor de víctimas o potenciales víctimas de esta violencia.\nArtículo 15. Corresponde a las dependencias, órganos, entidades de la Ciudad de México y a las Alcaldías:\nI. Capacitar y especializar a las personas servidoras públicas en materia de derechos humanos de las mujeres, igualdad y perspectiva de género, con apego a los lineamientos establecidos por la\nSecretaría de las Mujeres;\nFracción modificada y publicada en la GOCDMX el 10 de octubre de 2023\nII. Difundir las campañas informativas sobre los tipos y modalidades de la violencia contra las mujeres, así como de las instituciones que atienden a las víctimas;\nToda campaña publicitaria deberá ser incluyente, estar libre de estereotipos y de lenguaje sexista o misógino.\nToda campaña publicitaria deberá estar libre de estereotipos y de lenguaje sexista o misógino.\nIII. Promover y ejecutar acciones para que las condiciones laborales se desarrollen con igualdad de oportunidades, de trato y no discriminación en el acceso al empleo, la capacitación, el ascenso y la permanencia de las mujeres;\n\nIV. Fomentar un ambiente laboral libre de discriminación, riesgos y violencia laboral, así como establecer condiciones, mecanismos e instancias para detectar, atender y erradicar el hostigamiento sexual en el lugar de trabajo;\nV. Remitir la información y estadísticas a la red de información de violencia contra las mujeres conforme a la periodicidad y especificidad que solicite la Secretaría de las Mujeres; y\nVI. Establecer mecanismos internos para la denuncia del personal que incurra en violencia institucional; y\nVII. Las demás que señalen las disposiciones legales.\nArtículo 15 Bis. Son obligaciones de la Secretaría de Gobierno las siguientes:\nI. Se deroga.\nII. Participar en la Coordinación Interinstitucional y en las acciones de prevención y erradicación de la violencia que prevé esta Ley;\nIII. Se deroga.\nIV. Se deroga.\nV. Suscribir los convenios con instituciones públicas, privadas y académicas necesarios para el cumplimiento de su objeto.\nArtículo 16. La Secretaría de las Mujeres, deberá:\nI. Diseñar lineamientos, mecanismos, instrumentos e indicadores para el seguimiento y vigilancia de los objetivos de la presente Ley; así como para la capacitación y especialización de las y los servidores públicos del gobierno de la Ciudad de México en perspectiva de género y derechos humanos de las mujeres;\nII. Coordinar y operar la Red de Información de Violencia contra las Mujeres;\nIII. Realizar diagnósticos, investigaciones, estudios e informes sobre el cumplimiento de los objetivos de esta Ley;\n\nIV. Realizar acciones de prevención territorial y comunitaria para la promoción de los derechos de las mujeres y prevención de la violencia de género, a partir de las Unidades Territoriales de\nAtención, LUNAS;\nV. Realizar acciones y proyectos destinados a prevenir el embarazo en adolescentes y por violencia de género;\nVI. Brindar información y orientación requerida para cada caso sobre los programas con los que cuenta la SEMUJERES para víctimas de violencia de género, en alto riesgo y/o riesgo feminicida;\nVII. Promover una imagen de las mujeres libre de prejuicios y estereotipos, así como la eliminación del lenguaje sexista y/o misógino;\nVIII. Celebrar convenios de cooperación, coordinación y concertación con empresas, organizaciones patronales y sindicatos, para promover los derechos de las mujeres en los ámbitos público y privado;\nIX. Promover y vigilar la integración de la perspectiva de género y enfoque de derechos humanos, en los programas, servicios y acciones que ejecuten las instituciones del Gobierno de la Ciudad de México;\nX. Fomentar la coordinación local y nacional con los Centros de Refugio y Casas de Emergencia para mujeres víctimas de violencia de género;\nXI. Garantizar que la atención telefónica de primer contacto gratuita y especializada las 24 horas del día, los 365 días del año a través de Línea Mujeres, en donde se brindará orientación, intervención y respuesta inmediata para la prevención y atención de todo tipo de violencias para las mujeres de la Ciudad de México;\nXII. Brindar orientación y asesoría jurídica a mujeres víctimas de violencia de género a través de las Abogadas de las Mujeres, para el trámite de medidas de protección en términos de la presente Ley, con el objetivo de prevenir la comisión de un delito así como la violencia feminicida;\nXIII. Establecer mecanismos de coordinación interinstitucional con las Alcaldías para implementar acciones de prevención de la violencia contra las mujeres y niñas;\n\nXIII Bis. Diseñar y ejecutar acciones y programas enfocados en la gestión menstrual, con el objeto de garantizar el derecho humano a una menstruación digna y eliminar estereotipos y prejuicios en la materia, y\nFracción adicionada y publicada en la GOCDMX el 27 de marzo de 2024\nXIV. Las demás que señalen las disposiciones legales.\nArtículo 17. La Secretaría de Inclusión y Bienestar Social de la Ciudad de México deberá:\nI. Definir sus programas de prevención de la violencia familiar de conformidad con los principios de esta Ley;\nII. Realizar programas dirigidos a las mujeres en mayores condiciones de vulnerabilidad, que tiendan a fortalecer el ejercicio de su ciudadanía, su desarrollo integral y su empoderamiento;\nII Bis. Implementar las acciones afirmativas y políticas públicas pertinentes para garantizar el derecho humano a una menstruación digna de las mujeres y personas menstruantes que pertenezcan a un grupo de atención prioritaria;\nFracción adicionada y publicada en la GOCDMX el 27 de marzo de 2024\nIII. Asegurar que el servicio de localización telefónica LOCATEL oriente a las mujeres en aspectos relacionados con la presente Ley, con la finalidad de que puedan acceder a la atención integral que brinda;\nIV. A través de la Dirección de Igualdad:\na) Diseñar y promover campañas de información de prevención de la violencia contra las mujeres;\nb) Desarrollar campañas de difusión sobre los servicios que brindan las Unidades de\nAtención;\nc) Fomentar la coordinación local y nacional con los Centros de Refugio y Casas de\nEmergencia para mujeres víctimas de violencia;\n\nd) Supervisar y verificar las condiciones en las que operan las instituciones públicas y privadas que presten el servicio de Centro de Refugio o Casas de Emergencia.\ne) Elaborar e instrumentar mecanismos, programas y acciones para identificar la violencia contra las mujeres.\nf) Realizar estudios estadísticos e investigaciones que permitan la elaboración de políticas públicas que prevengan la violencia contra las mujeres;\nV. Las demás que le señalen las disposiciones legales aplicables y el Reglamento de esta Ley.\nArtículo 18. La Secretaría de Salud de la Ciudad de México deberá:\nI. Realizar estudios estadísticos e investigaciones en materia de salud pública con perspectiva de género e interseccionalidad cuyos resultados contribuyan en la elaboración de políticas públicas para la prevención.\nII. Elaborar e instrumentar mecanismos, programas y acciones tendientes a identificar y disminuir los factores de riesgo que afectan la salud de las mujeres;\nIII. Generar y difundir información sobre los derechos sexuales y reproductivos; menstruación digna libre de prejuicios y discriminación; prevención de las enfermedades de transmisión sexual; adicciones; accidentes; interrupción legal del embarazo; salud mental, así como todos aquellos tendientes a prevenir la violencia contra las mujeres;\nFracción modificada y publicada en la GOCDMX el 27 de marzo de 2024\nIV. Ejecutar programas especializados para prevenir las afectaciones en la salud mental de las mujeres;\nV. Elaborar informes semestrales de las acciones realizadas en el cumplimiento de la NOM-046-\nSSA2-2005 Oficiales Mexicanas en materia de salud para las mujeres,\nReforma publicada en la GOCDMX el 22 de diciembre de 2022\nVI. Garantizar servicios de interpretación u otros medios adecuados, así como procurar realizar programas de sensibilización a su personal sobre la atención a mujeres pertenecientes a los\nPueblos y Barrios Originarios y Comunidades Indígenas, así como a mujeres afrodescendientes y;\n\nReforma publicada en la GOCDMX el 22 de diciembre de 2022\nVII. Las demás que le señalen las disposiciones legales.\nArtículo 19. La Secretaría de Educación, Ciencia, Tecnología e Innovación, deberá:\nI. Formular, coordinar y ejecutar políticas, programas y acciones de promoción de los derechos humanos de las mujeres, y de prevención de todas las formas de violencia contra las mujeres, adolescentes y niñas.\nFracción modificada y publicada en la GOCDMX el 10 de octubre de 2023\nII. Generar acciones y mecanismos que favorezcan el desarrollo de las potencialidades de las mujeres en todas las etapas del proceso educativo;\nIII. Identificar las causas de deserción que afectan la vida escolar de las mujeres a efecto de crear programas que fomenten la igualdad de oportunidades en su acceso y permanencia;\nIV. Elaborar mecanismos de detección, denuncia y canalización de la violencia contra las mujeres fuera o dentro de los Centros educativos, así como prácticas discriminatorias y violentas en la comunidad escolar,;\nV. Elaborar y difundir materiales educativos para la prevención y atención de la violencia contra las mujeres;\nVI. Establecer mecanismos de denuncia y de protección para las alumnas que sean discriminadas y violentadas en sus derechos;\nVII. Diseñar y difundir materiales educativos con información sobre los derechos sexuales y reproductivos, así como del derecho a la gestión menstrual digna, con la finalidad de prevenir el abuso sexual infantil y la violencia contra los derechos reproductivos;\nFracción modificada y publicada en la GOCDMX el 27 de marzo de 2024\nVIII. Promover talleres de prevención de la violencia contra las mujeres dirigidos a sus familiares;\nIX. Diseñar e instrumentar programas no formales de educación comunitaria para prevenir la violencia contra las mujeres;\n\nX. Realizar estudios estadísticos e investigaciones para conocer y analizar el impacto de la violencia contra las mujeres en la deserción escolar, su desempeño, así como en el desarrollo integral de todas sus potencialidades;\nXI. Coordinar acciones con las asociaciones de madres y padres de familia y vecinales con el objeto de fomentar su participación en los programas de prevención que establece esta ley;\nXI Bis. Coordinar acciones con personas titulares de direcciones y rectorías de escuelas públicas y privadas de nivel básico, medio superior y superior, para establecer mecanismos de aplicación y seguimiento de las disposiciones anteriores para garantizar su cumplimiento; y\nXII. Las demás que le señalen las disposiciones legales.\nArtículo 20. La Secretaría de Trabajo y Fomento al Empleo deberá:\nI. Formular, coordinar y ejecutar políticas, programas y acciones de promoción de los derechos humanos de las mujeres y el desarrollo integral de sus capacidades y habilidades en su desempeño laboral;\nII. Incorporar en la supervisión de las condiciones laborales de los centros de trabajo la vigilancia en el cumplimiento de las normas en materia de igualdad de oportunidades, de trato y no discriminación en el acceso al empleo, la capacitación, el ascenso y la permanencia de las mujeres;\nIII. Promover campañas de información en los centros de trabajo sobre los tipos y modalidades de la violencia contra las mujeres, así como de las instituciones que atienden a las víctimas;\nIV. Proponer y coordinar campañas de difusión de los derechos de las mujeres trabajadoras, así como las obligaciones de las y los empleadores;\nV. Difundir, promover y garantizar el derecho de las mujeres a la igualdad de oportunidades y de trato, remuneración y seguridad social, poniendo énfasis en la información sobre las conductas que atentan contra su libertad sexual y/o reproductiva o su integridad física y psicológica.\nEn ese sentido, se diseñarán y ejecutarán campañas de concientización para evitar la discriminación en los centros laborales motivada por el proceso de menstruación.\nFracción modificada y publicada en la GOCDMX el 27 de marzo de 2024\n\nVI. Realizar estudios estadísticos e investigaciones sobre la situación de las mujeres en el trabajo que permitan la formulación de políticas públicas para el ejercicio pleno de sus derechos laborales;\nVII. Gestionar beneficios fiscales para las empresas que otorguen empleo a las mujeres en prisión y a las liberadas, preliberadas o externadas;\nVIII. Reconocer e incentivar a las empresas que se abstengan de solicitar a las mujeres certificados de no gravidez y de no antecedentes penales para su contratación o permanencia en el empleo, salvo las excepciones expresamente previstas en otras disposiciones legales; y\nIX. Las demás que le señalen las disposiciones legales.\nArtículo 21. La Secretaría de Desarrollo Urbano y Vivienda deberá:\nI. Elaborar programas y acciones de desarrollo urbano y vivienda, que beneficien con créditos accesibles, otorgamiento y mejoramiento de vivienda, entre otros, a las mujeres víctimas de violencia, en forma prioritaria a aquellas que se encuentren en mayor condición de vulnerabilidad; y\nII. Las demás que le señalen las disposiciones legales.\nArtículo 22. La Secretaría de Cultura deberá:\nI. Promover a través de los programas y actividades culturales, los derechos humanos de las mujeres;\nII. Promover que las mujeres dispongan de espacios para el esparcimiento, juegos y actividades recreativas, y participen en la vida cultural y artística;\nIII. Desarrollar con otras dependencias y entidades, encargadas de promover la cultura, campañas para prevenir la violencia contra las mujeres;\nIV. Elaborar programas artísticos y culturales, que difundan y promuevan una cultura de la igualdad entre mujeres y hombres;\n\nV. Formular, coordinar y ejecutar políticas, programas y acciones de promoción de los derechos humanos de las mujeres para su empoderamiento y desarrollo integral a través de las diferentes manifestaciones culturales y artísticas;\nVI. Generar mecanismos de prevención, detección y canalización de las mujeres víctimas de violencia en los centros de promoción de la cultura o en los espacios donde se desarrollen las actividades culturales y artísticas;\nVII. Diseñar y promover campañas de información sobre los tipos y modalidades de la violencia contra las mujeres así como de las dependencias y entidades que las atienden, en coordinación con las organizaciones beneficiarias del financiamiento de los proyectos de vivienda; y\nVIII. Las demás que le señalen las disposiciones legales aplicables y el Reglamento de esta Ley.\nArtículo 23. El Sistema de Transporte Público de la Ciudad de México deberá:\nI. Generar mecanismos de prevención, detección y canalización de las mujeres víctimas de violencia;\nII. Realizar estudios estadísticos e investigaciones que permitan la elaboración de políticas públicas que prevengan la violencia contra las mujeres en el transporte público;\nIII. Realizar con otras dependencias campañas de prevención de la violencia contra las mujeres en el transporte público; y\nIV. Las demás que le señalen las disposiciones legales aplicables y el Reglamento de esta Ley.\nArtículo 24. El Sistema para el Desarrollo Integral de la Familia de la Ciudad de México deberá:\nI.Diseñar y promover campañas de información de prevención de la violencia contra las niñas, adolescentes y mujeres\nFracción modificada y publicada en la GOCDMX el 10 de octubre de 2023\nI Bis. Diseñar y promover campañas de información sobre las nuevas masculinidades con perspectiva de género y protección de los derechos humanos para la prevención de la violencia a través de los procesos educativos y socioculturales;\nFracción adicionada y publicada en la GOCDMX el 10 de octubre de 2023\n\nII Desarrollar campañas de difusión sobre los servicios que brinda;\nIII. Realizar estudios estadísticos e investigaciones que permitan la elaboración de políticas públicas que prevengan la violencia contra las mujeres;\nIV. Establecer las acciones y medidas que se deberán tomar para la reeducación y reinserción social de la persona agresora de violencia sexual o cualquier otro tipo de violencia; siempre y cuando exista un modelo de abordaje psicoterapéutico debidamente probado en sus beneficios y alcances y supervisado por la Secretaría de las Mujeres;\nFracción modificada y publicada en la GOCDMX el 10 de octubre de 2023\nV. Sensibilizar y concientizar a las personas usuarias de sus servicios sobre las consecuencias y efectos de la violencia contra las mujeres y las niñas dentro del entorno familiar;\nVI. Desarrollar programas de intervención temprana para prevenir casos de violencia contra las mujeres en el ámbito familiar en coordinación con la Secretaría de las Mujeres y demás dependencias e instituciones competentes; y\nVI Bis. Diseñar y ejecutar campañas permanentes de información y concientización sobre educación sexual, reproductiva, así como de gestión y salud menstrual, y\nFracción adicionada y publicada en la GOCDMX el 27 de marzo de 2024\nVII. Las demás que le confieran esta y otras leyes o disposiciones legales aplicables y el\nReglamento de esta Ley.\nArtículo 25. La Secretaría de Seguridad Ciudadana deberá:\nI. Elaborar e implementar en coordinación con la Fiscalía, acciones de política criminal que incidan en la prevención de la violencia contra las mujeres, dando prioridad a las zonas de mayor incidencia delictiva, así como a aquellas donde residan un mayor número de personas inscritas en el Registro;\nII. Generar y participar en la creación de mecanismos y protocolos de prevención, atención, detección y canalización de las mujeres víctimas de violencia en cualquier ambiente, en coordinación aquellas instancias y/o dependencias que sean competentes en la materia y en apego a la normativa aplicable en la materia;\n\nFracción modificada y publicada en la GOCDMX el 10 de octubre de 2023\nIII. Realizar estudios estadísticos e investigaciones que permitan la elaboración de políticas públicas que prevengan la violencia contra las mujeres en los ámbitos público y privado.\nDebiendo en todo momento estar actualizadas las consultas al Registro;\nIV. Diseñar la política integral para la prevención de delitos violentos contra las mujeres;\nIV Bis. Publicar en su portal web oficial, el Registro Público de Personas Agresoras Sexuales, registrando a la persona sentenciada una vez que cause ejecutoria la sentencia;\nIV Ter. Establecer los lineamientos para crear, organizar, implementar, gestionar, actualizar, monitorear y evaluar el funcionamiento del Registro Público de Agresores Sexuales;\nIV Quáter. Expedir los mecanismos que permitan inscribir, acceder, rectificar, cancelar y oponerse cuando resulte procedente, la información contenida en el Registro;\nV. Realizar, en coordinación con la Secretaría de las Mujeres campañas de prevención del delito, en función de los factores de riesgo que atañen a las mujeres, incluyendo los de carácter sexual, y las consultas al Registro;\nV Bis. Implementar en los Centros Penitenciarios, Centro de Sanciones Administrativas y de\nIntegración Social, Centros Especializados y acción cívica, Centros de Reinserción Social, servicios reeducativos especializados en masculinidades no violentas, con perspectiva de género y de protección de los derechos humanos, con el objetivo de erradicar las creencias de supremacía masculina, las prácticas machistas y aquellas conductas que posibilitan, justifican y sostienen el ejercicio de las violencias contra las mujeres en cualquiera de sus tipos y modalidades;\nFracción adicionada y publicada en la GOCDMX el 10 de octubre de 2023\nVI. Formular acciones y programas orientados a fomentar la cultura del respeto a los derechos humanos de las mujeres;\nVI Bis. Participar en la Coordinación Interinstitucional y en las acciones de prevención y erradicación de la violencia que prevé esta Ley;\nVI Ter. Suscribir los convenios con instituciones públicas, privadas y académicas necesarios para el cumplimiento de su objeto;\n\nVI Quater. Formular acciones y programas con el objetivo de garantizar el derecho a una menstruación digna a las mujeres privadas de su libertad en los Centros Femeniles de\nReadaptación Social, y\nFracción adicionada y publicada en la GOCDMX el 27 de marzo de 2024\nVII. Las demás que le señalen las disposiciones legales aplicables y el Reglamento de esta Ley.\nArtículo 26. La Fiscalía deberá:\nI. Elaborar e instrumentar en coordinación con la Secretaria de Seguridad Ciudadana, acciones de política criminal que incidan en la prevención de la violencia contra las mujeres, dando prioridad a las zonas de mayor incidencia delictiva y en donde residen mayor número personas inscritas en el Registro;\nII. Realizar investigaciones para detectar y desarticular redes de prostitución, corrupción, trata de personas y otros delitos de los que son víctimas las mujeres;\nIII. Fomentar la coordinación interinstitucional local y nacional para detectar las redes señaladas en fracciones anteriores e informar a la sociedad sobre las acciones en materia de detección y consignación de estas redes;\nIV. Desarrollar campañas de difusión de los servicios que prestan los centros que integran el\nSistema de Auxilio a Víctimas del Delito;\nV. Desarrollar campañas de difusión sobre los derechos que tienen las víctimas de delitos que atentan contra la libertad, la salud, la seguridad sexuales y el normal desarrollo psicosexual, así como de violencia familiar, y las agencias especializadas o Fiscalías que las atienden.\nVI. Crear bases de datos que contengan información de carácter público a efecto que pueda registrarse el seguimiento de los casos donde la mujer es víctima de algún delito que atente contra su integridad personal, desde la etapa de averiguación previa o investigación hasta la ejecución de la sentencia, incluyendo el procedimiento respectivo para la reparación del daño.\n\nVII. Realizar estudios estadísticos e investigaciones referentes al acceso a la justicia de las mujeres víctimas de violencia, así como de los procedimientos penales y sentencias que se dictan en contra de las mujeres responsables de delitos;\nVIII. Crear un sistema de registro público de los delitos cometidos en contra de mujeres, que integre la estadística criminal y victimal para definir políticas en materia de prevención del delito, procuración y administración de justicia, que incluya la clasificación de los hechos de los que tenga conocimiento, lugar en que ocurrieron, especificando su tipología, características de la víctima, pero nunca datos personales que permita su localización o identificación y del sujeto activo, móviles, diligencias básicas a realizar, así como las dificultades para la práctica de diligencias y determinaciones; los índices de incidencia y reincidencia, las personas sentenciadas y que la autoridad jurisdiccional ordena se inscriban en el Registro, los vinculados a proceso, aquellos en que se haya dictado el auto de apertura a juicio oral, los sancionados y aquellos en los que procedió la reparación del daño;\nIX. Elaborar una página de Internet en la cual se encuentren los datos generales de las mujeres y niñas que sean reportadas como desaparecidas. Dicha página deberá actualizarse constantemente. La información deberá ser pública y permitir que la población en general pueda aportar información sobre el paradero de las mujeres y niñas desaparecidas; atendiendo en los términos de que establece la Ley de Protección de Datos Personales en Posesión de Sujetos\nObligados de la Ciudad de México.\nX. Especializar a las y los agentes del Ministerio Público, peritos, personal que atiende a víctimas a través de programas y cursos permanentes, instaurados por el Instituto de Formación\nProfesional, en: derechos humanos y género; perspectiva de género para la debida diligencia en la conducción de averiguaciones previas, la investigación de hechos que la ley señale como delitos y procesos judiciales relacionados con discriminación, violencia y feminicidios;\nincorporación de la perspectiva de género en los servicios periciales; eliminación de estereotipos sobre el rol social de las mujeres, entre otros;\nXI. Elaborar, aplicar y actualizar Protocolos especializados con perspectiva de género en: la búsqueda inmediata de mujeres y niñas desaparecidas, para la investigación de los feminicidios y la violencia sexual;\nXII. Crear una Base de Información Genética que contenga la información personal disponible de mujeres y niñas desaparecidas; la información genética y muestras celulares de los familiares\n\nde las personas desaparecidas que lo consientan; la información genética y muestras celulares proveniente de los cuerpos de cualquier mujer o niña no identificada;\nLa información integrada en esta base deberá ser resguardada y podrá ser utilizada para la confrontación de información genética entre cuerpos no identificados y personas desaparecidas y en los términos de la legislación de procedimientos penales aplicable a la Ciudad de México; y\nXIII. Las demás que le señalen las disposiciones legales aplicables y el Reglamento de esta Ley.\nArtículo 27. El Tribunal deberá:\nI. Capacitar y especializar a su personal en materia de derechos humanos de las mujeres;\nII. Promover a través de la capacitación del personal, la construcción de una cultura libre de conductas misóginas, de roles y lenguaje sexista que atentan contra la dignidad de las mujeres;\nIII. Fomentar un ambiente laboral libre de discriminación, riesgos y violencia laboral, así como establecer condiciones, mecanismos e instancias para detectar, atender y erradicar el hostigamiento sexual en el lugar de trabajo\nIV. Diseñar y promover campañas de información sobre los tipos y modalidades de la violencia contra las mujeres.\nV. Generar mecanismos y promover su implementación para la detección de violencia contra las mujeres;\nVI. Las demás que le atribuyan otros ordenamientos legales.\nC A P Í T U L O I I I\nD E L A A T E N C I Ó N\nArtículo 28. Las medidas de atención en materia de violencia contra las mujeres consisten en brindar servicios médicos, psicológicos, jurídicos y sociales con calidad y calidez para su empoderamiento y desarrollo integral de sus potencialidades.\n\nArtículo 29. Las dependencias, órganos y entidades de la Ciudad de México, las Alcaldías, así como las instituciones privadas que presten servicio de atención en materia de violencia contra las mujeres, deberán contar con personal profesional y especializado, quienes deberán recibir continuamente capacitación en materia de derechos humanos de las mujeres.\nArtículo 30. La intervención especializada, desde la perspectiva de género, para las mujeres víctimas de violencia se regirá por los siguientes lineamientos:\nI. Atención integral: Se realizará considerando el conjunto de necesidades derivadas de la situación de violencia, tales como la sanitaria, psicosocial, laboral, orientación y representación jurídica, albergue y seguridad, patrimonial y económica;\nII. Efectividad: se adoptarán las medidas necesarias para que las víctimas, sobre todo aquellas que se encuentran en mayor condición de vulnerabilidad, accedan a los servicios integrales que les garantice el ejercicio efectivo de sus derechos;\nIII. Legalidad: Apego al orden jurídico y respeto a los derechos humanos de las mujeres víctimas de violencia;\nIV. Auxilio oportuno: Brindar apoyo inmediato y eficaz a las mujeres en situación de riesgo o que hayan sido víctimas de algún delito, así como brindar protección a sus bienes y derechos; y\nV. Respeto a los Derechos Humanos de las Mujeres: Abstenerse en todo momento y bajo cualquier circunstancia de hacer uso indebido de la fuerza, de infligir, tolerar o permitir actos de tortura u otros tratos o sanciones crueles, inhumanos o degradantes en contra de las mujeres.\nArtículo 31. Con el fin de proporcionar una efectiva atención a la violencia contra las mujeres, se actuará a partir de un Modelo Único de Atención, para garantizar que las intervenciones en cada ámbito de la violencia correspondan a una base conceptual y un conjunto de lineamientos de coordinación que impidan la fragmentación de la acción de las dependencias y entidades.\nArtículo 32. El Modelo Único de Atención establecerá que los servicios de atención social, psicológica, jurídica y médica de las distintas dependencias y entidades se coordinen para operar a través de la red de información de violencia contra las mujeres, mediante una cédula de registro único, de tal manera que con independencia de la institución a la que acudan por primera vez las mujeres víctimas de violencia, se garantice el seguimiento del caso hasta su conclusión.\n\nLas dependencias, entidades de la Ciudad de México y las Alcaldías deberán registrar el ingreso de las mujeres víctimas de violencia en la Red de Información de violencia contra las mujeres mediante la cédula de registro único. Esta cédula deberá transmitirse a las dependencias y entidades de la Ciudad de México a donde se canalicen las víctimas o se preste el servicio subsecuente, a efecto de que se tenga un registro de la atención que se brinda desde el inicio hasta la conclusión de cada caso. El Reglamento de la presente\nLey, contemplará las características y el mecanismo para instrumentar la Cédula de Registro Único.\nArtículo 33. El Modelo Único de Atención tendrá las siguientes etapas:\nI Identificación de la problemática. Consiste en determinar las características del problema, el tipo, modalidad de violencia o hecho delictivo, los efectos y posibles riesgos para las víctimas directas e indirectas, en su esfera social, económica, laboral, educativa y cultural;\nII. Determinación de prioridades. Consiste en identificar las necesidades inmediatas y mediatas, así como las medidas de protección que en su caso requiera la víctima;\nIII. Orientación y canalización. La autoridad o entidad a la que acuda la víctima por primera vez brindará de manera precisa, con lenguaje sencillo y accesible, la orientación social y jurídica necesaria y suficiente con respecto al caso de violencia que presente, realizando la canalización ante la instancia correspondiente.\nIV. Brindar acompañamiento. Cuando la condición física y/o psicológica de la víctima lo requiera deberá realizar el traslado con personal especializado a la institución que corresponda;\nV. Seguimiento. Son las acciones para vigilar el cumplimiento de los procedimientos de canalización contenidos en esta Ley para atender los casos de violencia contra las mujeres.\nArtículo 34. Las dependencias, entidades de la Ciudad de México y las Alcaldías que atienden a mujeres víctimas de violencia en la Ciudad de México deberán:\nI. Canalizar de manera inmediata a las mujeres víctimas de violencia a las Unidades de Atención;\ncuando se trate de violencia sexual, serán trasladadas a la agencia del Ministerio Público que corresponda;\nII. Realizar en coordinación con las otras dependencias, para asegurar la uniformidad y la calidad de la atención de las mujeres víctimas de violencia, protocolos de atención médica, psicológica y jurídica;\n\nIII. Las dependencias, entidades de la Ciudad de México y las Alcaldías que atiendan a mujeres víctimas de violencia deberán expedir documentos que hagan constar la atención de las mujeres víctimas de violencia, con la finalidad de que los hagan valer en sus centros de trabajo.\nArtículo 35. La Secretaría de las Mujeres de la Ciudad de México deberá:\nI. Realizar acciones de atención multidisciplinaria y especializada, detección de riesgo de violencia feminicida y, en su caso, acompañamiento a mujeres y niñas en situación de violencia de género, que acudan las Unidades Territoriales de Atención, LUNAS, ubicadas en cada alcaldía.\nLa atención se brindará con enfoque de género y derechos humanos;\nII. Garantizar la aplicación de los instrumentos para la atención inicial, orientación jurídica y psicológica, y asistencia social en las Unidades Territoriales de Atención, LUNAS, quienes realizarán:\na) Entrevista inicial a la víctima, elaboración de la Cédula de Registro único, detección de riesgo y en el caso de delitos sexuales, se deberá canalizar y acompañarla sin dilación alguna a la Procuraduría;\nb) La orientación y asesoría jurídica a las víctimas de violencia de género;\nc) La atención psicológica urgente y terapéutica, según se requiera y que puede ser:\ni. De intervención en crisis;\nii. Individual; o iii. Grupal.\nd) Canalizar a la víctima para seguimiento y atención a la instancia correspondiente;\ne) La gestión de su ingreso a los Centros de Refugio, en caso de resultar necesario.\nIII. Coordinar y administrar el Programa de Reinserción Social para las mujeres egresadas de los\nCentros de Refugio, con la finalidad de generar las condiciones necesarias que les permitan superar su situación de exclusión social;\nIV. Generar programas específicos en conjunto con la Secretaría de Salud de la Ciudad de México para atención de las mujeres en reclusión, internas en hospitales psiquiátricos y mujeres con capacidades especiales o diferentes;\nV. Gestionar:\n\na) Ante la Secretaría de Desarrollo Económico, impulsar y facilitar el acceso de las víctimas a sus programas de crédito, así como, generar una bolsa de trabajo;\nb) Ante la Secretaría del Trabajo y Fomento al Empleo, incentivar en las empresas la capacitación y generación de empleo con horarios favorables y remuneración justa y vigilar que las contratadas gocen de todos sus derechos laborales;\nc) Ante el Sistema de Transporte Público, la obtención de credenciales que permitan la gratuidad del transporte para las mujeres que se encuentren en un albergue, por el espacio en que dure su estancia en el mismo;\nd) Ante la Secretaría de Desarrollo Urbano y Vivienda, facilitar los trámites para que las mujeres víctimas de violencia de género obtengan vivienda y/o créditos accesibles para la adquisición o mejoramiento de la vivienda;\ne) Ante el Sistema para el Desarrollo Integral de la Familia de la Ciudad de México, el acceso preferencial y gratuito o a bajo costo, a estancias o guarderías para las y los hijos de las mujeres víctimas de violencia y, en conjunción con la Secretaría de Educación,\nCiencia, Tecnología e Innovación, gestionar un programa de becas exclusivo para este tipo de población en riesgo y privilegiar su ingreso a escuelas cercanas al albergue o domicilio de las víctimas; y f) Con la Secretaría de Administración y Finanzas, la exención del pago en la emisión de documentos que requieran las víctimas de violencia de género para la substanciación de procedimientos en materia penal y civil instaurados con motivo de la violencia que viven.\nVI. Dar seguimiento a los casos integrando el expediente con la cédula de registro único, documentos de referencia y soporte;\nVII. A través de las Abogadas de las Mujeres:\na) Atender a las mujeres víctimas de violencia de género b) Realizar entrevista inicial para la identificación de la problemática y detección de riesgo de violencia;\nc) Brindar orientación y asesoría jurídica a las mujeres víctimas de violencia de género, en las Agencias Desconcentradas y algunas Fiscalías Especializadas del Ministerio Público;\nd) Coadyuvar en el proceso de denuncia de las mujeres víctimas de violencia de género en las Agencias del Ministerio Público;\nVIII. Las demás que le atribuyan otras leyes y el Reglamento de la presente Ley.\nArtículo 36. La Secretaría de Salud deberá:\n\nI. Brindar a las mujeres víctimas de violencia el acceso gratuito a los servicios de atención médica y psicológica para su tratamiento correspondiente;\nII. Canalizar a las Unidades de Atención, previa notificación, a las mujeres que presenten lesiones u otros signos que sean presumiblemente consecuencia de la violencia sufrida, excepto los casos de violencia sexual.\nIII. Llevar a cabo registros de información desagregada por sexo, considerando todas las variables necesarias que permitan analizar el impacto de la violencia en la salud de las mujeres; Crear programas especializados para atender a mujeres víctimas de violencia con necesidades de atención psicológica y/o psiquiátrica.\nIV. Proporcionar atención en salud reproductiva de las mujeres, en especial de aquellas que se encuentran en mayores condiciones de vulnerabilidad y/o privadas de su libertad;\nV. Diseñar y ejecutar programas especializados para atender a mujeres víctimas de violencia con necesidades de salud mental, en los Casas de Emergencia y Centros de Refugio;\nV Bis. Capacitar al personal al interior de sus instancias de atención sobre las dinámicas de la violencia vicaria a efecto de concientizarles sobre la importancia de brindar a las madres la información sobre el estado de salud de sus hijas e hijos, así como personas con discapacidad o en situación de dependencia, sin necesidad de orden judicial, sujetándose a las disposiciones y la normatividad interna en materia de Salud, y\nFracción adicionada y publicada en la GOCDMX el 10 de octubre de 2023\nV Ter. Las autoridades y/o el personal de los servicios de salud correspondientes deberán llevar un registro y remitir la información y estadísticas sobre las personas atendidas en caso de violencia por ataques con ácido, sustancias químicas o corrosivas a las autoridades competentes.\nLo anterior en términos de lo dispuesto por los artículos 15 fracción V, 32, de esta Ley, las Normas\nOficiales Mexicanas y demás disposiciones aplicables de las leyes vigentes en la Ciudad de\nMéxico.\nLas personas prestadoras de servicios de salud deberán implementar los criterios, protocolos y/o lineamientos con los que cuente la Secretaría de Salud, para coordinarse interinstitucionalmente con las autoridades correspondientes ante los casos de violencia contra las mujeres; y\nFracción adicionada y publicada en la GOCDMX el 9 de febrero de 2024\n\nVI. Las demás que le atribuyan otras leyes y el Reglamento de la presente Ley.\nArtículo 37. La Secretaría de Trabajo y Fomento al Empleo deberá:\nI. Promover en coordinación con la Dirección de Igualdad, la creación o generación de bolsas de trabajo específicas para mujeres víctimas de violencia y apoyar la capacitación para el auto empleo;\nII. Brindar acompañamiento jurídico a las mujeres víctimas de violencia en el ámbito laboral; y\nIII. Las demás que le atribuyan otras leyes y el Reglamento de la presente Ley.\nArtículo 38. La Consejería Jurídica y de Servicios Legales gestionará las facilidades y exenciones para el pago de derechos y expedición de copias certificadas de las actas del estado civil de las Personas, para mujeres víctimas de violencia.\nArtículo 39. El Sistema de Transporte Público deberá:\nI. Gestionar para que a las mujeres víctimas de violencia se les brinden facilidades y exenciones de pago por el uso del servicio de transporte público, en tanto que permanezcan en los mismos;\ny\nII. Las demás que le atribuyan otras leyes y el Reglamento de la presente Ley.\nArtículo 40. La Secretaría de Desarrollo Urbano y Vivienda, en coordinación con la Secretaría de las Mujeres de la Ciudad de México y la Fiscalía, deberá facilitar los trámites para que las mujeres víctimas de violencia obtengan vivienda y/o créditos accesibles para la adquisición o mejoramiento de la vivienda. Este programa deberá considerar las condiciones de vulnerabilidad en las que se encuentren las mujeres víctimas.\nArtículo 41. La Secretaría de Educación, Ciencia, Tecnología e Innovación de la Ciudad de México, en colaboración con el Sistema para el Desarrollo Integral de la Familia de la Ciudad de México y la Secretaria de Inclusión y Bienestar Social; deberá formular programas de otorgamiento de becas dirigido a mujeres víctimas de violencia y en situación de riesgo, así como a sus dependientes.\nArtículo 42. El Sistema para el Desarrollo Integral de la Familia de la Ciudad de México deberá:\n\nI. Dar acceso preferencial y gratuito o a bajo costo, a estancias o guarderías, a las hijas y los hijos de las mujeres víctimas de violencia;\nII. Brindar asesoría, orientación y asistencia social a las personas víctimas de violencia familiar y violencia de género, en todos los centros que se encuentren a su cargo, así como servicios reeducativos integrales a las personas agresoras, con la finalidad de erradicar la violencia de su vida;\nIII. Capacitar y sensibilizar al personal a su cargo a fin de que otorguen atención con perspectiva de género a las personas víctimas de violencia familiar;\nIV. Canalizar oportunamente a las instancias competentes los casos de violencia contra las mujeres y las niñas, así como, brindar a las víctimas la orientación necesaria sobre el proceso y tramites respectivos; y\nVI. Las demás que le atribuyan otras leyes y el Reglamento de la presente Ley\nC A P Í T U L O I V\nD E L S E G U I M I E N T O Y E V A L U A C I Ó N\nArtículo 43. Las personas titulares de las dependencias, órganos, entidades de la Ciudad de México y las\nAlcaldías que integran el Gabinete de Igualdad Sustantiva y Violencia Contra las Mujeres, se reunirán de manera periódica con la finalidad de evaluar el cumplimiento de los objetivos esta Ley.\nArtículo 44. Las reuniones de la Coordinación Interinstitucional serán presididas por la persona Titular de la Jefatura de Gobierno y funcionará como Secretaría Ejecutiva, la persona Titular de la Secretaría de las\nMujeres.\nArtículo 45. Serán invitadas permanentes las personas titulares de las dependencias del Gobierno de la\nCiudad de México, que no sean parte de la Comisión Interinstitucional; la persona titular de la Comisión de Derechos Humanos de la Ciudad de México, tres representantes del Congreso de la Ciudad de México, tres representantes de la sociedad civil y tres investigadoras especialistas, así como representantes de organismos internacionales especializados en la materia.\n\nArtículo 46. Quienes participen en las reuniones de la Comisión Interinstitucional tendrán derecho a voz y a voto, y podrán designar a una persona suplente previa acreditación, la cual deberá tener capacidad decisoria.\nArtículo 47. Con la finalidad de avanzar en el desarrollo de políticas públicas coordinadas, las dependencias de la Comisión Interinstitucional podrán conformarse en Comités de trabajo, por materia, que serán los siguientes:\nI. De prevención, que será coordinado por la Secretaría de las Mujeres;\nII. De atención, que será coordinado por la Dirección de Igualdad; y\nIII. De acceso a la justicia, el cual será coordinado por la Fiscalía.\nIV. De Protección y Registro de Agresores\nArtículo 48. El Reglamento de la presente Ley establecerá el funcionamiento de la Comisión\nInterinstitucional en cuanto al seguimiento y evaluación de la presente Ley.\nC A P Í T U L O V\nD E L A S C A S A S D E E M E R G E N C I A, C E N T R O S D E R E F U G I O\nY R E F U G I O S E S P E C I A L I Z A D O S P A R A M U J E R E S\nV Í C T I M A S D E V I O L E N C I A\nArtículo 49. Las Casas de Emergencia son estancias especialmente acondicionadas para recibir a las mujeres víctimas de violencia y a las víctimas indirectas, que operan las 24 horas del día y los 365 días del año.\nCada una de las 16 Alcaldías de la Ciudad de México deberá contar, por lo menos, con una Casa de\nEmergencia, que opere bajo los protocolos y modelos de atención aprobados por la Secretaría de las\nMujeres.\nPodrá ingresar a las Casas de Emergencia, cualquier mujer, sin importar su condición, origen étnico o pertenencia a la diversidad sexual; así como sus hijas e hijos de cualquier edad, o cualquier persona que dependa de ella. El periodo de estancia no será mayor de tres días, previa canalización a un albergue, de ser necesario.\n\nReforma publicada en la GOCDMX el 30 de noviembre de 2022\nEn caso de que la mujer víctima de violencia, sus hijas e hijos de cualquier edad, o cualquier persona que dependa de ella, sean de origen indígena, extranjeras, de la tercera edad, con alguna discapacidad o alguna condición económica, cultural o social que les afecte de manera directa y cause un daño grave en su dignidad humana, las Casas de Emergencia podrán solicitar a través de la Secretaría de las Mujeres, la colaboración de otras dependencias e Instituciones, así como a la Fiscalía General de Justicia de la Ciudad de México y a las 16 Alcaldías, que en el ámbito de su competencia, se tomen medidas integrales y de urgencia para reparar el ejercicio de derechos y libertades, primordialmente para asegurar su integridad personal.\nArtículo 50. Los Centros de Refugio son lugares temporales de seguridad para la víctima y víctimas indirectas que funcionarán las 24 horas del día, los 365 días del año.\nLa permanencia en los Centros de Refugio se dará en tanto subsista la inestabilidad física y/o psicológica, o bien subsista el riesgo para la víctima directa y las víctimas indirectas.\nArtículo 50 Bis. Los Refugios Especializados son estancias del Gobierno de la Ciudad de México específicamente creadas para víctimas de trata de personas, en las que se brindarán las condiciones para garantizar el respeto a los derechos humanos de las víctimas, su alojamiento por el tiempo necesario, asistencia médica especializada, jurídica, psiquiátrica y psicológica, capacitación para su integración social y laboral, alimentación y los cuidados mínimos que cubran las necesidades particulares de las víctimas y las víctimas indirectas, los cuales funcionarán de forma permanente.\nLa internación en Refugios Especializados se hará como medida de protección temporal cuando la restitución o reinserción de la víctima a su núcleo familiar no sea posible, o se considere desfavorable.\nArtículo 50 Ter. Los Refugios Especializados estarán a cargo de la Fiscalía General de Justicia de la Ciudad de México, la cual deberá incluir en su anteproyecto de presupuesto de egresos de la Ciudad de México de cada ejercicio fiscal los recursos necesarios para su operación.\nArtículo 50 Quater. Para brindar los servicios y atención a las víctimas de trata de personas, los Refugios\nEspecializados estarán a lo dispuesto en los artículos 51 y 52 de esta Ley, así como a las medidas de protección de las víctimas y al Programa que refiere la Ley para Prevenir y Erradicar la Trata de Personas, el abuso sexual y la explotación sexual comercial infantil vigente en la Ciudad de México\nArtículo 51. Las Casas de Emergencia y los Centros de Refugio brindarán los siguientes servicios:\n\nI. Atención psicológica, médica, jurídica y social;\nII. Acceso a servicios de atención especializada para contención de personas en estado de crisis o enlaces permanentes para canalización a dependencias especializadas de servicios médicos y de psicología que pueden ser otorgados por instituciones públicas o privadas;\nIII. Capacitación para que las mujeres desarrollen habilidades para el empleo, a fin de que logren estar en condiciones de participar plenamente en la vida pública, social y privada; y\nIV. Bolsa de trabajo, con la finalidad de que puedan tener una actividad laboral remunerada en caso de que lo soliciten.\nArtículo 52. Las Casas de Emergencia y Centros de Refugio, para estar en condiciones óptimas y así garantizar la atención con calidad y calidez, tendrán:\nI. Instalaciones higiénicas;\nII. Áreas suficientes, iluminadas y ventiladas;\nIII. Áreas especiales para la atención de las niñas y los niños que acompañen a las víctimas;\nIV. Áreas especiales para la atención de las personas mayores que acompañen a las víctimas;\nV. Agua potable, luz eléctrica, lavabos y regaderas suficientes, red de agua caliente para baños;\nVI. Personal femenino en las áreas de trabajo social, psicología y medicina;\nVII. Dormitorios con camas individuales o espacios para una familia integrada por una mujer y sus dependientes;\nVIII. Seguridad en el acceso a las instalaciones; y\nVIII Bis. Espacios adecuados, insumos y productos necesarios para gestionar dignamente el proceso menstrual, y\nFracción adicionada y publicada en la GOCDMX el 27 de marzo de 2024\n\nIX. Personal capacitado que apliquen las Normas Oficiales Mexicanas relativas y vigentes a este tipo de centros de atención.\nArtículo 52 Bis. En todos los casos se garantizará que la estancia en las Casas de Emergencia, Centros de\nRefugio o Refugios Especializados sea voluntaria y se procurará que en la canalización a estos espacios la familia no sea separada.\nArtículo 53. La Secretaría de las Mujeres y las 16 Alcaldías, deberán actuar de forma coordinada, con el fin de establecer estándares de gestión y atención que garanticen a todas las mujeres de la Ciudad de México que requieran acceder a una Casa de Emergencia o Centros de Refugio los servicios con calidad, oportunidad y pertinencia con apoyo de agentes clave de gobierno y sociedad civil.\nCon este propósito podrán celebrar convenios o proyectos de coinversión con las organizaciones de la sociedad civil especializadas en los temas de competencia, para el diseño, concertación de acciones y programas de financiamiento y apoyo a las Casas de Emergencia o Centros de Refugio.\nLas Alcaldías podrán celebrar convenios de colaboración y coordinación con diversas dependencias e instituciones del gobierno de la Ciudad de México, para garantizar que, en el proceso de instalación de las\nCasas de emergencia, se cuente con el personal suficiente y debidamente capacitado para atender a las mujeres víctimas de violencia, sus hijas e hijos, de acuerdo con lo establecido en la presente Ley y el Modelo\nÚnico de Atención.\nPárrafo adicionado y publicado en la GOCDMX el 10 de octubre de 2023\nLas Alcaldías deberán contemplar en su Plan de Egresos de cada año lo establecido en la presente ley para la instalación progresiva, operatividad y/o el mantenimiento de la o las respectivas Casas de Emergencia.\nEl recurso público designado deberá considerar la capacitación y especialización en temas de género, derechos humanos y prevención de la violencia contra las mujeres del personal que laborará en las Casas de Emergencia.\nPárrafo modificado y publicado en la GOCDMX el 10 de octubre de 2023\nEl Congreso de la Ciudad de México deberá considerar lo establecido por la presente ley para la asignación de recursos a las Alcaldías en cada ejercicio fiscal.\nC A P Í T U L O V I\nD E L A C C E S O A L A J U S T I C I A\n\nArtículo 54. El acceso a la justicia de las mujeres, es el conjunto de acciones jurídicas que deben realizar las dependencias, entidades de la Ciudad de México y las Alcaldías para hacer efectiva la exigibilidad de sus derechos en los ámbitos civil, familiar, penal, entre otros. Implica la instrumentación de medidas de protección, así como el acompañamiento, la representación jurídica y, en su caso, la reparación del daño.\nArtículo 55. Las acciones de acceso a la justicia consisten en:\nI. Implementar de manera pronta y eficaz medidas de protección para las mujeres víctimas de violencia o en riesgo de serlo, para salvaguardar su integridad física y psíquica, así como su patrimonio, tomando en cuenta las condiciones de vulnerabilidad en las que se encuentren.\nConsiderando para los casos de riesgo de violencia sexual el Registro puntual de los agresores;\nII. Actuar con la debida diligencia para orientar, acompañar y representar a las mujeres víctimas de violencia en los procedimientos en que participen, con el fin de que sean sancionados los actos de violencia cometidos en su contra, así como para hacer efectiva la reparación del daño; y\nIII. Instrumentar acciones integrales que tiendan a disminuir los efectos de la violencia contra las mujeres y evitar la violencia institucional;\nArtículo 56. En la esfera de la procuración y administración de justicia, se contará con abogadas victimales y asesoras o asesores jurídicos que coadyuven con las mujeres víctimas de violencia, quienes podrán tener la representación legal de aquellas mujeres que no cuenten con los medios económicos suficientes para contratar una o un defensor particular.\nArtículo 57. La representación legal que se proporcione a las víctimas, consistirá en el patrocinio y asesoría legal especializada, en asuntos del fuero común, en materia penal, civil, familiar, arrendamiento y laboral de la siguiente manera:\nI. En materia penal a cargo de la Fiscalía a través de una asesora o un asesor jurídico;\nII. En materia civil y arrendamiento, a cargo de la Consejería Jurídica y de Servicios Legales a través de una defensora o un defensor público;\nIII. En materia familiar a cargo del Sistema para el Desarrollo Integral de la Familia de la Ciudad de México, a través de sus abogadas y abogados adscritos;\n\nIV. En materia laboral a cargo de la Procuraduría de la Defensa del Trabajo, a través de personal jurídico adscrito a la Subprocuraduría de Atención a Mujeres.\nArtículo 58. La Fiscalía, desde la perspectiva de género, deberá:\nI. Verificar que exista la representación legal en materia penal a las mujeres víctimas de violencia, a través de asesoras o asesores jurídicos;\nII. Elaborar los dictámenes psicológicos victimales en los términos de la legislación de procedimientos penales aplicable a la Ciudad de México.\nLa exploración y atención médica psiquiátrica, ginecológica o cualquiera otra que se practique a la mujer víctima de un delito que atente contra su libertad y el normal desarrollo psicosexual, estará a cargo de persona facultativa de su mismo sexo, salvo cuando la víctima del delito sexual o su representante legal solicite lo contrario. Cuando la mujer víctima sea menor de edad, dicha atención será proporcionada por personal especializado en el tratamiento de menores.\nIII. Fortalecer el Fondo de Apoyo a Víctimas del Delito para apoyar económicamente a todas las mujeres víctimas de violencia que se encuentren en mayores condiciones de vulnerabilidad y propiciar su autonomía;\nIV. Gestionar convenios con la Secretaría de Administración y Finanzas para exención del pago de derechos a las mujeres víctimas de violencia en la emisión de copias certificadas, videograbaciones o cualquier otro medio digital, electrónico, óptico o de cualquier otra tecnología o copia de las versiones escritas que correspondan a los procedimientos en materia penal;\nV. Habilitar una línea única de atención telefónica para recibir denuncias de violencia contra las mujeres, por parte de la propia víctima o cualquier otra persona, y dar inicio a la investigación respectiva; y\nVI. Realizar las investigaciones relacionadas con feminicidios, a través de la Fiscalía que para tal efecto prevea su Ley Orgánica, y además a).- Dos peritos practicarán la necropsia del cadáver, expresando con minuciosidad el estado que guarda y las causas que originaron la muerte. Solo podrá dejarse de hacer la necropsia, cuando el Juez lo acuerde previo informe o dictamen de los peritos médicos;\n\nb).- La investigación pericial, ministerial y policial deberá realizarse de conformidad con los parámetros establecidos en los protocolos especializados con perspectiva de género.\nLa aplicación de dicho protocolo será obligatoria y su inobservancia será motivo de responsabilidad;\nc).- La Fiscalía deberá conservar un registro fotográfico de la víctima, de la descripción de sus lesiones, objetos y vestimenta con que haya sido encontrada que servirán para resolver cada caso, así como para investigaciones de la misma naturaleza.\nCuando se trate de cadáveres no identificados o que no puedan ser reconocidos, deberá realizarse un estudio para determinar su ADN que se integrará al Banco de Datos de Información\nGenética, a cargo de la Fiscalía, al que se incorporará la información genética de familiares de mujeres desaparecidas o presuntas víctimas de feminicidio, cuando así lo soliciten o en cumplimiento a una orden de la autoridad judicial.\nVII.- Implementar los mecanismos necesarios que permitan, en los casos de violencia contra las mujeres, aplicar con prontitud y eficacia las medidas u órdenes de protección señaladas en esta\nLey y en la legislación de procedimientos penales aplicable a la Ciudad de México; y\nVIII.-Las demás que le atribuyen otros ordenamientos legales.\nArtículo 59. La Secretaría de Seguridad Ciudadana, desde la perspectiva de género, deberá:\nI. Conformar un cuerpo policíaco especializado en atender y proteger a las víctimas de violencia, y brindar las medidas de protección y de monitoreo del Registro que establece esta Ley;\nII. Crear mecanismos de coordinación y colaboración con las dependencias encargadas de la seguridad pública en las distintas entidades federativas que coadyuven en la ejecución de las medidas que garanticen la seguridad de las víctimas; y\nIII. Las demás que le atribuyan otros ordenamientos legales.\nArtículo 60. La Consejería Jurídica y de Servicios Legales de la Ciudad de México a través de la Defensoría\nPública, desde la perspectiva de género, deberá:\nI. Representar y asesorar a las mujeres víctimas de violencia canalizadas por las dependencias que integran el Gabinete de Igualdad Sustantiva y Violencia Contra las Mujeres, en materias penal, civil y familiar;\n\nII. Promover ante el Tribunal las medidas u órdenes de protección establecidas en la presente\nLey, de conformidad con las normas sustantivas y adjetivas aplicables a la Ciudad de México;\nIII. Canalizar a la Secretaría de las Mujeres a las víctimas que tengan necesidad de ingresar a las\nCasas de Emergencia o Centros de Refugio a fin de que reciban los beneficios de los programas sociales establecidos;\nIV. Promover las denuncias correspondientes por hechos que la ley señale como delitos cometidos en agravio de sus defendidas, que se encuentren internas en los centros de reinserción social y penitenciarías; y\nV. Las demás que le atribuyan otros ordenamientos legales.\nArtículo 60 Bis. Son funciones de la Subsecretaría del Sistema Penitenciario:\nI. Organizar, administrar, actualizar y resguardar la información contenida en el Registro en términos de las leyes aplicables, lineamientos y protocolos para la recepción, procesamiento, consulta y resguardo de la información que se expidan para tal efecto;\nII. Realizar y elaborar estudios, investigaciones y estadísticas con los datos contenidos en el\nRegistro, respetando la información de datos personales conforme a la normatividad aplicable para la elaboración de políticas públicas;\nIII. Recibir de los órganos jurisdiccionales, la entrega de los datos de las personas sentenciadas con ejecutoria para registro de los mismos.\nIV. Adoptar las medidas necesarias para asegurar la veracidad, integridad y accesibilidad de la información, así como la protección de los datos personales contenidos, en el Registro de conformidad con la normativa aplicable, aplicando los lineamientos y protocolos respectivos;\nV. Proporcionar información sobre los agresores sexuales a las autoridades locales competentes de conformidad con la normatividad aplicable;\nVI. Vigilar el uso correcto de la información contenida en el Registro y, en su caso, sancionar o dar vista a la autoridad competente respecto del uso indebido de la información,\n\nVII. Las demás que prevean otras disposiciones legales.\nArtículo 61. El Tribunal, desde la perspectiva de género, deberá:\nI. Contar con jueces de lo civil, familiar y penal las veinticuatro horas del día, y los trescientos sesenta y cinco días del año, que puedan ordenar en cualquier momento las medidas u órdenes de protección que requieran las mujeres víctimas de violencia, así como las víctimas indirectas;\nII. Dictar las medidas u órdenes de protección necesarias para salvaguardar la integridad física y psíquica, la libertad, la seguridad y el patrimonio de las mujeres víctimas de violencia o en riesgo de serlo, así como de sus dependientes; y\nIII. Las demás que le atribuyan otros ordenamientos legales.\nArtículo 61 bis. La Secretaría de Salud, desde la perspectiva de género, la interseccionalidad y la perspectiva intercultural deberá:\nReforma publicada en la GOCDMX el 22 de diciembre de 2022\nI.- A petición de la mujer interesada, practicar el examen que compruebe la existencia de su embarazo, así como su interrupción, en los casos relacionados con una solicitud de interrupción del mismo;\nII. Proporcionar a la mujer información imparcial, objetiva, veraz, suficiente y en su caso culturalmente adecuada sobre los procedimientos, riesgos, consecuencias y efectos; así como los apoyos y alternativas existentes, para que la mujer embarazada pueda tomar la decisión de manera libre, informada y responsable. Esta información deberá ser proporcionada de manera inmediata y no deberá tener como objetivo, inducir o retrasar la decisión de la mujer.\nDe igual manera, en el período posterior a la interrupción del embarazo, ofrecerá la orientación y apoyos necesarios para propiciar la rehabilitación personal y familiar de la mujer.\nLa Secretaría de Salud coordinará acciones con la Fiscalía con el fin de implementar los mecanismos necesarios para el debido cumplimiento a lo establecido en esta fracción; y\nIII. Las demás que le atribuyan otros ordenamientos legales.\nArtículo 61 Ter. Las Alcaldías, desde la perspectiva de género, deberán:\n\nI. Proporcionar asesoría legal a las mujeres víctimas de violencia;\nII. Establecer un mecanismo de vinculación interinstitucional, para atender las denuncias de violencia contra las mujeres, recibidas a través de línea mujeres de LOCATEL, por parte de la propia víctima o cualquier otra persona;\nIII. Disponer elementos de la policía de proximidad para atender y proteger a las víctimas de violencia;\nIV. Crear mecanismos de coordinación y colaboración con las dependencias encargadas de la seguridad pública que coadyuven en la ejecución de las medidas que garanticen la seguridad de las víctimas;\nV. Contar, por lo menos, con una Casa de Emergencia con el objetivo de establecerse como el primer vínculo de proximidad con las mujeres víctimas de violencia o con las víctimas indirectas, así como canalizar ante la unidad administrativa correspondiente a las víctimas que tengan necesidad de ingresar a las Casas de Emergencia o Centros de Refugio;\nVI. Generar en el ámbito de su competencia, las acciones para el registro, procesamiento, clasificación y seguimiento de las atenciones brindadas a las mujeres y niñas víctimas de violencia, de acuerdo a lo establecido en los Lineamientos para la operación y funcionamiento de la Red de Información de Violencia contra las Mujeres y el Sistema para la Identificación y\nAtención del Riesgo de Violencia Feminicida para las dependencias, entidades y órganos político-administrativos de la Ciudad de México\nVII. Las demás que le atribuyan otros ordenamientos legales.\nC A P Í T U L O V I I\nM E D I D A S U Ó R D E N E S D E P R O T E C C I Ó N\nArtículo 62. Las medidas u órdenes de protección son un derecho de todas las mujeres y niñas, son urgentes y de carácter temporal implementadas por autoridad competente en favor de las mujeres o niñas en situación de violencia, así ́como de las víctimas indirectas en situación de riesgo.\n\nLas medidas u órdenes de protección vinculadas a casos de violencia contra la mujer se aplicarán en los términos y condiciones que se establecen en la Ley General de Acceso de las Mujeres a una Vida Libre de\nViolencia, esta Ley, y las legislaciones sustantivas y adjetivas aplicables a la Ciudad de México.\nLas medidas de protección tienen como propósito prevenir, interrumpir o impedir la comisión de un delito o que se actualice un supuesto en materia civil o familiar que implique violencia contra las mujeres, a través de la emisión de una medida u orden de protección.\nLas medidas u órdenes de protección prohíben u ordenan la realización de determinadas conductas y son precautorias, cautelares y de urgente aplicación en función del interés superior de la víctima. Deberán otorgarse por el Ministerio Público y los órganos jurisdiccionales penales, o los jueces civil y familiar, según corresponda, inmediatamente que conozcan los hechos probablemente constitutivos delitos o supuestos del orden civil o familiar, que impliquen violencia contra la víctima o víctimas indirectas.\nLas medidas de protección deberán otorgarse de oficio por la autoridad competente desde el momento en que tenga conocimiento del hecho de violencia.\nEn el caso en que el Ministerio Público o el Órgano Jurisdiccional competente considere la existencia de extrema violencia y urgencia, podrán implementar de manera directa e inmediata las medidas de protección necesarias para salvaguardar la vida, integridad, libertad y seguridad de las víctimas, sin condicionarlas a la iniciación de una denuncia.\nLas autoridades competentes deberán de establecer los lineamientos básicos para la implementación de las medidas de protección en coordinación con las instancias responsables de atender a las mujeres y niñas en situación de violencia.\nArtículo 62 Bis. Las autoridades emisoras y ejecutoras de las medidas de protección deberán observar los siguientes principios:\nI. Principio de protección: considerar de manera primordial la obligación de salvaguardar la vida, integridad, libertad y seguridad de las personas;\nI Bis. Principio de Buena fe: las autoridades, en todo momento, presumirán la buena fe de las víctimas en situación de riesgo o violencia y deberán creer en su narración de los hechos. Las personas servidoras públicas que intervengan con motivo del ejercicio de los derechos de las víctimas, no deberán revictimizarlas o hacerlas responsables de su situación. En todo momento deberán permitir el ejercicio efectivo de sus derechos.\n\nII. Principio de necesidad y proporcionalidad: las medidas de protección deben responder a las necesidades inmediatas y específicas de las víctimas, atendiendo a la situación de riesgo, peligro existente o a las consecuencias de los actos de violencia.\nIII. Principio de confidencialidad: toda la información y actividad administrativa o jurisdiccional relacionada con el ámbito de protección de las personas, debe ser reservada para los fines de la investigación o del proceso respectivo.\nIV. Principio de oportunidad y eficacia: Las medidas deben ser otorgadas e implementadas de manera inmediata y durante el tiempo que garanticen su objetivo.\nV. Principio de accesibilidad: se deberá ́ articular un procedimiento sencillo para garantizar la materialización de la protección inmediata a las víctimas de acuerdo con sus condiciones específicas, tomando en consideración el contexto de la violencia.\nTratándose de mujeres y niñas indígenas, la información proporcionada deberá ́ser en su lengua, mediante un formato pertinente y culturalmente adecuado. En el caso de mujeres o niñas con discapacidad, este principio debe incluir la accesibilidad al entorno físico y también a las comunicaciones, considerando los diferentes tipos de necesidades para los diversos tipos de discapacidades reconocidas.\nVI. Principio de integralidad: El otorgamiento de la medida a favor de la víctima deberá garantizar la salvaguarda de todos los derechos de las víctimas, considerando los distintos aspectos que se presentan en cada caso.\nVII. Principio de concentración: No se necesita una orden para cada medida, una sola orden de protección podrá concentrar el número de medidas necesarias para garantizar la seguridad y bienestar de la mujer en situación de violencia y en su caso de las víctimas indirectas.\nVIII. Principio pro persona: Para interpretar lo referente al otorgamiento de las medidas de protección, en caso de duda, con relación a la situación de violencia, se estará a lo más favorable para la víctima.\nIX. Principio de interés superior de la niñez: Cuando las decisiones que se adopten relacionadas con el trámite de medidas de protección, afecte de manera directa o indirecta a una niña, niño o\n\nadolescente se deberán evaluar y ponderar las posibles repercusiones para evitar efectos negativos en su esfera de derechos\nArtículo 62 Ter. Además de los principios establecidos en el artículo anterior, las autoridades administrativas, ministeriales o el órgano jurisdiccional competente, al emitir órdenes de protección, deberán incorporar la perspectiva intercultural tomando en cuenta, cuando menos, los siguientes elementos:\nI. El criterio de autoadscripción que es la base sobre la cual se define la pertenencia a un pueblo o comunidad indígena, por lo que no se deberán solicitar pruebas para acreditar dicha pertenencia;\nII. El nivel de castellanización o la lengua indígena de la mujer o niña, y\nIII. Deberán identificarse condiciones de exclusión que obstaculicen el acceso a la justicia y pudieran requerir adecuaciones procesales para garantizar el acceso a una orden de protección.\nArtículo 63. Las medidas u órdenes de protección en materia penal, se consideran personalísimas e intransferibles y podrán ser:\nI. Prohibición de acercarse o comunicarse con la víctima u ofendido;\nII.- Prohibición para asistir o acercarse al domicilio de la víctima directa o indirecta, así como acercarse al lugar de trabajo, estudio o cualquiera lugar que frecuente.\nIII. La desocupación inmediata por parte del agresor, del domicilio de la víctima, independientemente de la acreditación de propiedad o posesión del inmueble, aún en los casos de arrendamiento del mismo, del matrimonio en sociedad conyugal o de separación de bienes, y en su caso, el reingreso de la mujer en situación de violencia una vez que se resguarde su seguridad. Se debe garantizar el cumplimiento de las obligaciones contractuales del agresor con respecto a la propiedad o posesión que previamente existían o los apoyos que brindaba para ello.\nIV. La prohibición de realizar conductas de intimidación o molestia a la víctima u ofendido o a personas relacionados con ellos.\n\nV. La entrega inmediata de objetos de uso personal y documentos de identidad de la víctima que tuviera en posesión el agresor, y en su caso, los de sus hijas e hijos. En este caso deberá contar con el acompañamiento, del Ministerio Público y del personal de la policía de investigación.\nVI. Vigilancia en el domicilio de la víctima u ofendido;\nVII. Custodia personal y/ o domiciliaria a las víctimas, que estará a cargo de los cuerpos policiales adscritos a la Fiscalía y de la Secretaría de Seguridad Ciudadana, ambas de la Ciudad de México, según corresponda, con base a la disponibilidad de personal con el que estas instancias cuenten;\nVIII. Auxilio inmediato por integrantes de instituciones policiales, al domicilio en donde se localice o se encuentre la víctima u ofendido en el momento de solicitarlo;\nIX. Canalizar a las víctimas directas e indirectas para alojamiento temporal en espacios seguros tales como casas de emergencia, refugios y albergues que garanticen su seguridad y dignidad, en términos de las disposiciones aplicables de esta ley.\nX. Reingreso de la mujer y en su caso víctimas indirectas al domicilio, una vez que se salvaguarde su seguridad, en caso de que así lo desee.\nPara el cumplimiento de esta medida se garantizará el acompañamiento, del Ministerio Público y del personal de la policía de investigación, a la víctima de violencia para acceder al domicilio, lugar de trabajo u otro, en cualquier caso, podrá ser acompañada de una persona de su confianza. En caso de que no haya personal de policía de investigación disponible, el acompañamiento será a cargo de personal de cualquier institución de seguridad pública que garantice la seguridad de las víctimas.\nXI. Ordenar al agresor que entregue el pasaporte si existiere de sus hijas e hijos menores de 18 años, para el resguardo del mismo, hasta en tanto el juez de lo familiar no determine la custodia o el régimen de visitas según sea el caso;\nXII. Prohibición a la persona agresora de intimidar o molestar por si, por cualquier medio o interpósita persona, a la mujer en situación de violencia y en su caso sus hijas e hijos u otras víctimas indirectas o testigos de los hechos o cualquier otra persona con quien la mujer tenga una relación familiar, afectiva, de confianza o de hecho.\n\nXIII. La reserva del domicilio, lugar de trabajo, profesión o cualquier otro dato que permita que la persona agresora o su familia puedan ubicar a la víctima.\nXIV. Implementar medidas para evitar que se capten y/o se transmitan por cualquier medio o tecnologías de la información y la comunicación, imágenes de la mujer en situación de violencia que permitan su identificación o la de sus familiares. Tratándose de niñas hay una prohibición absoluta de transmitir datos e imágenes que permitan su identificación.\nXV. La interrupción, bloqueo, destrucción o eliminación de imágenes, audios, videos de contenido sexual íntimo de una persona, sin su consentimiento; de medios impresos, redes sociales, plataforma digital o cualquier dispositivo o medio tecnológico.\nXVI. Además de los anteriores, aquellas y cuantas sean necesarias para salvaguardar la integridad, vida, libertad y seguridad de la mujer y las víctimas indirectas en situación de violencia\nC A P Í T U L O V I I\nM E D I D A S U Ó R D E N E S D E P R O T E C C I Ó N\nArtículo 64. La autoridad competente que reciba la solicitud bajo su más estricta responsabilidad, ordenará fundada y motivadamente, de manera inmediata y a más tardar en un plazo que no exceda de 4 horas, a partir del conocimiento de los hechos, cualquiera de las medidas u órdenes de protección mencionadas en esta Ley, debiendo tomar en cuenta, en su caso, el interés superior de la niñez.\nArtículo 65.- Dentro de los cinco días siguientes a la imposición de las medidas de protección previstas en las fracciones I, II y III del artículo 63 de esta Ley, deberá celebrarse una audiencia en la que el órgano jurisdiccional correspondiente podrá ratificarlas, ampliarlas o cancelarlas, en este último caso siempre y cuando se encuentre documentado que el riesgo ha cesado.\nEn caso de que la persona agresora incumpla cualquier medida de protección, con independencia de la responsabilidad penal del sujeto activo, se reforzarán las acciones que se contemplaron en un primer momento con la finalidad de salvaguardar la vida y seguridad de las víctimas directas o indirectas.\nArtículo 66. Las medidas de protección serán permanentes en tanto el riesgo persista, se mantendrán vigentes con una revisión trimestral que justifique su permanencia, para salvaguardar la vida, integridad,\n\nlibertad y seguridad de las mujeres y niñas en situación de violencia, así como de las víctimas indirectas en situación de riesgo.\nArtículo 67. La Jueza o el Juez de Control podrá emitir como orden de protección preventiva la retención y guarda de armas en posesión de la persona agresora, y dar aviso a la autoridad federal competente.\nArtículo 68. En materia penal, el órgano jurisdiccional o el Ministerio Público, para el cumplimiento de las medidas u órdenes de protección, autorizará a la autoridad ejecutora, lo siguiente:\nI. Ingresar al domicilio o al lugar en dónde ocurra o haya ocurrido el acto de violencia;\nII. Proporcionar protección policíaca en tanto persista la situación de emergencia y se conduzca a la víctima y, en su caso, a las víctimas indirectas a un lugar donde se encuentren fuera de peligro;\nIII. Acompañar a la víctima a su domicilio para recoger sus pertenencias personales y, en su caso, de las víctimas indirectas;\nIV. Trasladar a la víctima y víctimas indirectas, si así lo requieren, a las Casas de Emergencia o\nCentros de Refugio;\nEn todos los casos, al finalizar la diligencia de ejecución de las medidas u órdenes de protección, la autoridad ejecutora deberá proporcionar toda la información necesaria para que la víctima acceda a protección policíaca inmediata, en cualquier momento que esté en riesgo su seguridad e integridad.\nArtículo 69. Las medidas u órdenes de protección podrán ser solicitadas por la víctima o cualquier persona, que tenga conocimiento del riesgo en que se encuentra la integridad física o psicológica, la libertad o seguridad de la víctima y víctimas indirectas.\nArtículo 69 Bis. Las medidas u órdenes de protección, cuando se trate de casos urgentes, se atenderán de acuerdo con lo previsto en los artículos 23 y 24 del Código Nacional de Procedimientos Penales.\nLas autoridades competentes podrán realizar los actos administrativos y jurídicos necesarios para garantizar la efectiva protección de las mujeres y las niñas conforme a los principios establecidos en el artículo 62 Bis de esta Ley.\n\nDurante los primeros tres días posteriores a la implementación de las medidas u órdenes, la autoridad que la emitió mantendrá contacto directo con la víctima cada 24 horas. A partir del sexto día, se establecerá el plan de seguimiento personalizado; de acuerdo con las circunstancias, la valoración del riesgo y el avance en la carpeta de investigación.\nArtículo 70. Las órdenes de protección de naturaleza civil tienen como propósito salvaguardar el patrimonio de la víctima o víctimas indirectas y podrán ser dictadas por la jueza o el juez de lo familiar o de lo civil, según corresponda dentro del término previsto en el artículo 64 de esta ley y serán permanentes en tanto el riesgo persista, con efecto inmediato y sin vincularse a la notificación correspondiente a la persona agresora, debiendo implementar todas las medidas que garanticen la integridad y seguridad de las mujeres y sus hijas e hijos.\nArtículo 71. Son órdenes de protección de naturaleza civil las siguientes:\nI. Suspensión temporal al agresor del régimen de visitas y convivencia con sus descendientes;\nII. Elaboración del inventario de los bienes propiedad del agresor o que formen parte de su patrimonio, incluyendo los implementos de trabajo de la víctima;\nIII. Prohibición al agresor de enajenar o gravar de cualquier forma bienes de la sociedad conyugal o las que se encuentren en el domicilio común en caso de concubinato o sociedad de convivencia, siendo nulas de pleno derecho aquellas que se realicen por el agresor en contravención;\nIV. Obligación alimentaría provisional e inmediata.\nV. Recuperación y entrega inmediata de las hijas, hijos, personas menores de 18 años y/o personas que requieran cuidados especiales, a las mujeres víctimas de cualquier tipo violencia.\nFracción modificada y publicada en la GOCDMX el 10 de octubre de 2023\nVI. Restablecimiento inmediato de las convivencias de las hijas o hijos con su progenitora.\nFracción adicionada y publicada en la GOCDMX el 10 de octubre de 2023\nLas personas juzgadoras deberán recibir por cualquier medio las solicitudes de medidas en materia civil y familiar, incluidas las que se presentan por escrito, decretando a favor de las mujeres la medida por la situación de violencia que están viviendo.\nPárrafo adicionado y publicado en la GOCDMX el 10 de octubre de 2023\n\nArtículo 72. La orden de protección surtirá sus efectos al momento de ser notificada y en la misma se citará a la persona agresora para comparecer ante el juez que emite la orden al día siguiente en que la reciba para que celebrar audiencia de pruebas y alegatos.\nEn la audiencia se recibirán, admitirán y desahogarán las pruebas que procedan y se recibirán los alegatos.\nSerán supletorios a la audiencia que se celebre los códigos procesales de la materia en que se dicten las medidas.\nEl juez tendrá veinticuatro horas para dictar resolución donde confirme, modifique o revoque.\nArtículo 72 Bis. Las medidas de protección deberán ser registradas en el banco nacional de datos e información sobre casos y delitos de violencia cometida en contra de mujeres.\nArtículo 72 Ter.- Tratándose de violencia digital, la o el Ministerio Público, la Jueza o Juez, procederá de acuerdo al siguiente procedimiento:\nI.-La querella podrá presentarse vía electrónica o mediante escrito de manera personal; y\nII- El Ministerio Público ordenará de manera inmediata, las medidas de protección necesarias, ordenando vía electrónica o mediante escrito a las empresas de plataformas digitales, redes sociales o páginas electrónicas, personas físicas o morales, la interrupción, bloqueo, destrucción, o eliminación de imágenes, audios, o videos relacionados con la querella.\nC A P Í T U L O V I I I\nD E L A R E P A R A C I Ó N D E L D A Ñ O A L A S M U J E R E S\nV Í C T I M A S D E V I O L E N C I A E N L A C I U D A D D E M É X I C O\nArtículo 73. Las mujeres víctimas de violencia, tendrán derecho a obtener la reparación del daño de conformidad con el artículo 20, apartado C, fracción IV, de la Constitución Política de los Estados Unidos\nMexicanos. Con el objetivo de garantizar el goce de este derecho, el Gobierno la Ciudad de México, brindará servicios jurídicos especializados.\nArtículo 74. Para procurar la reparación del daño a las mujeres víctimas de violencia, el Ministerio Público deberá:\n\nI. Informar a la ofendida o víctima del delito, así como a sus derechohabientes, sobre el derecho que tiene a que se le repare el daño material y moral derivado de la comisión de ilícito, así como el procedimiento y alcance de la reparación del daño;\nII. Solicitar al juez el embargo precautorio de los bienes del probable responsable, cuando se tenga el temor fundado de que el obligado a la reparación del daño oculte o enajene los bienes para hacer efectiva dicha reparación.\nIII. Informar a la víctima sobre el derecho que tiene de acudir a la Comisión de Derechos\nHumanos del Distrito Federal cuando de los hechos que constituyen delito también se desprende la violación a sus derechos humanos y orientarla para que considere la opción de presentar su denuncia o queja ante la Fiscalía de Servidores Públicos u órgano de control interno de la dependencia que corresponda.\nT Í T U L O Q U I N T O\nD E L P R E S U P U E S T O P A R A L A I N S T R U M E N T A C I Ó N D E\nE S T A L E Y\nArtículo 75. Las dependencias, entidades de la Ciudad de México y las Alcaldías, encargadas del cumplimiento del objeto de la presente Ley, deberán requerir como prioritarios, en su Presupuesto\nOperativo Anual, las partidas y recursos necesarios para su cumplimiento.\nArtículo 76. El Proyecto de Presupuesto de Egresos Anual deberá incluir como prioritarios, con base en los presupuestos operativos anuales enviados por las dependencias, entidades de la Ciudad de México y las\nAlcaldías, las partidas y recursos necesarios para la aplicación y cumplimiento de la presente Ley.\nAsimismo, el Tribunal deberá integrar en su presupuesto los recursos necesarios para el cumplimiento de las atribuciones que le otorga esta Ley.\nT Í T U L O S E X T O\nD E L A R E S P O N S A B I L I D A D D E L A S P E R S O N A S\nS E R V I D O R A S P Ú B L I C A S\nArtículo 77. Las personas servidoras públicas de la Ciudad de México serán responsables por todo acto u omisión que viole, infrinja, incumpla o contraríe las disposiciones de esta Ley.\n\nArtículo 78. La responsabilidad de los servidores públicos será sancionada por los órganos de control competentes de conformidad con la legislación aplicable, sin menoscabo de las acciones penales, civiles o cualquier otra que se derive de su incumplimiento.\nT Í T U L O S E P T I M O\nC A P Í T U L O U N I C O\nR E G I S T R O P Ú B L I C O D E P E R S O N A S A G R E S O R A S\nS E X U A L E S\nArtículo 79. El Registro Público de Personas Agresoras Sexuales de la Ciudad de México constituye un sistema de información de carácter público que contendrá los registros de personas sentenciadas con ejecutoria por un juez penal, en términos de los establecidos en los artículos 69 Ter y 69 Quarter del Código\nPenal del Distrito Federal vigente.\nEn ningún caso y bajo ninguna circunstancia, se incluirán datos personales de las víctimas o datos que hagan posible su localización e identificación y ocasionen una revictimización.\nArtículo 80. El registro sólo se verificará cuando exista la instrucción de la autoridad jurisdiccional, y la sentencia ejecutoriada respectiva, considerando su inscripción y a partir de qué momento es efectivo el término de diez años como mínimo y máximo de 30 que señala la legislación penal aplicable.\nLa inscripción contenida en el Registro Público de Personas Agresoras Sexuales se cancelará, cuando concluya el término respectivo o cuando sea ordenado por la autoridad jurisdiccional que corresponda, señalando el motivo.\nLa autoridad responsable del Registro, bajo su más estricta responsabilidad, deberá garantizar los derechos humanos de la persona registrada.\nArtículo 81. El Registro Público de Personas Agresoras Sexuales tendrá las siguientes características y mecanismos de protección y auditoría de la información con la finalidad de garantizar que los datos resguardados en el mismo, gocen de la calidad de la información que impida cualquier daño, pérdida, alteración, destrucción o para impedir el uso, acceso o tratamiento no autorizado de la información:\nI. Confiabilidad;\n\nII. Encriptación;\nIII. Gratuidad en su uso y acceso, y\nIV. Público a través de los portales de internet respectivos.\nLas autoridades y personas servidoras públicas que intervengan en la captura, ingreso, envío, recepción, manejo, consulta o actualización de la información que integra el Registro, deberán adoptar las medidas necesarias para mantener exactos, completos, correctos y actualizados, los datos personales en su posesión.\nLa Agencia Digital de Innovación Pública, brindará el apoyo técnico y asesoría en materia de infraestructura tecnológica, seguridad informática e interoperabilidad para la operación y funcionamiento del Registro.\nArtículo 82. El Registro contendrá información general de personas sentenciadas con ejecutoria en materia penal de acceso público, pero su consulta será por petición escrita, organizada por delito, y los datos que se indican a continuación:\na) Fotografía actual;\nb) Nombre;\nc) Edad;\nd) Alias;\ne) Nacionalidad\nArtículo 83. El Registro contendrá también la información clasificada a la cual sólo tendrán acceso las personas titulares del Ministerio Público, debidamente motivada y fundada y en su caso con la autorización del juez de control respectivo así como aquellas personas autorizadas exclusivamente por las autoridades judiciales.\na) Señas particulares;\nb) zona criminológica de los delitos;\n\nc) Modus operandi;\nd) Ficha signaléctica;\ne) Perfil Genético.\nT R A N S I T O R I O S\nARTÍCULO PRIMERO.-Publíquese en la Gaceta Oficial del Distrito Federal para su conocimiento y en el Diario\nOficial de la Federación para su mayor difusión.\nARTÍCULO SEGUNDO.-El presente decreto entrará en vigor el ocho de marzo del año dos mil ocho.\nARTÍCULO TERCERO.-El Jefe de Gobierno del Distrito Federal deberá emitir, en un plazo no mayor a sesenta días naturales a partir de la entrada en vigor del presente Decreto, el Reglamento de la Ley que se crea.\nARTÍCULO CUARTO.-La Comisión Interinstitucional a que se refiere la Ley que se crea, comenzará sus trabajos dentro de los sesenta días naturales siguientes a la entrada en vigor del presente.\nARTÍCULO QUINTO.-En un plazo no mayor a sesenta días hábiles a partir de la entrada en vigor del presente\nDecreto, se armonizará la legislación del Distrito Federal, entre otros el Código Penal y de Procedimientos\nPenales, Código Civil y de Procedimientos Civiles, así como todas las demás disposiciones que sean necesarias para la debida aplicación de la Ley.\nRecinto de la Asamblea Legislativa del Distrito Federal, a los trece días del mes de diciembre del año dos mil siete.- POR LA MESA DIRECTIVA.- DIP. KENIA LÓPEZ RABADÁN, PRESIDENTA.- DIP. MARÍA ELBA GÁRFIAS\nMALDONADO, SECRETARIA.- DIP. ALFREDO VINALAY MORA, SECRETARIO.- (Firmas)\nEn cumplimiento de lo dispuesto por los artículos 122, apartado C, base segunda, fracción II, inciso b), de la Constitución Política de los Estados Unidos Mexicanos; 48, 49 y 67, fracción II, del Estatuto de Gobierno del Distrito Federal, para su debida publicación y observancia, expido el presente Decreto Promulgatorio en la Residencia Oficial del Jefe de Gobierno del Distrito Federal, en la Ciudad de México, a los veinte días del mes de diciembre del año dos mil siete.- EL JEFE DE GOBIERNO DEL DISTRITO FEDERAL, MARCELO LUIS\nEBRARD CASAUBON.- FIRMA.- EL SECRETARIO DE GOBIERNO, JOSÉ ÁNGEL ÁVILA PÉREZ.- FIRMA.- EL\nSECRETARIO DE DESARROLLO URBANO Y VIVIENDA, JESÚS ARTURO AISPURO CORONEL.- FIRMA.- EL\nSECRETARIO DE DESARROLLO SOCIAL, MARTÍ BATRES GUADARRAMA.- FIRMA.- EL SECRETARIO DE SALUD,\n\nMANUEL MONDRAGÓN Y KALB.- FIRMA.- EL SECRETARIO DE SEGURIDAD PÚBLICA, A. JOEL ORTEGA\nCUEVAS.- FIRMA.- LA SECRETARIA DE CULTURA, ELENA CEPEDA DE LEÓN.- FIRMA.- EL SECRETARIO DE\nTRABAJO Y FOMENTO AL EMPLEO, BENITO MIRÓN LINCE.- FIRMA.- EL SECRETARIO DE EDUCACIÓN, AXEL\nDIDRIKSSON TAKAYANAGUI.- FIRMA.\nTRANSITORIO DEL DECRETO POR EL QUE SE REFORMA EL ARTÍCULO 18 DE LA LEY DE ACCESO DE LAS\nMUJERES A UNA VIDA LIBRE DE VIOLENCIA DEL DISTRITO FEDERAL, PUBLICADO EN LA GACETA OFICIAL DEL\nDISTRITO FEDERAL EL 29 DE JULIO DE 2010.\nÚNICO.-El Presente Decreto entrará en vigor al día siguiente de su publicación en la Gaceta Oficial del\nDistrito Federal.\nRecinto de la Asamblea Legislativa del Distrito Federal, a los veintinueve días del mes de junio del año dos mil diez.- POR LA MESA DIRECTIVA.- DIP. AXEL VÁZQUEZ BURGETTE, PRESIDENTA.- DIP. MA. NATIVIDAD\nPATRICIA RAZO VÁZQUEZ, SECRETARIA.- DIP. JOSÉ MANUEL RENDÓN OBERHAUSER, SECRETARIO.- (Firmas)\nEn cumplimiento de lo dispuesto por los artículos 122, apartado C, Base Segunda, fracción II, inciso b), de la Constitución Política de los Estados Unidos Mexicanos; 48, 49 y 67, fracción II, del Estatuto de Gobierno del Distrito Federal, para su debida publicación y observancia, expido el presente Decreto Promulgatorio en la Residencia Oficial del Jefe de Gobierno del Distrito Federal, en la Ciudad de México, a los 28 días del mes de julio del año dos mil diez. EL JEFE DE GOBIERNO DEL DISTRITO FEDERAL, MARCELO LUIS EBRARD\nCASAUBON.- FIRMA.- EL SECRETARIO DE GOBIERNO, JOSÉ ÁNGEL ÁVILA PÉREZ.- FIRMA.- EL SECRETARIO DE\nSALUD, DR. ARMANDO AHUED ORTEGA.- FIRMA.\nTRANSITORIOS DEL DECRETO POR EL QUE SE REFORMAN Y ADICIONAN DIVERSAS DISPOSICIONES A LA LEY\nDE ACCESO DE LAS MUJERES A UNA VIDA LIBRE DE VIOLENCIA DEL DISTRITO FEDERAL, PUBLICADO EN LA\nGACETA OFICIAL DEL DISTRITO FEDERAL EL 14 DE ENERO DE 2011.\nPRIMERO.-Túrnese el presente Decreto al Jefe de Gobierno del Distrito Federal, para su promulgación y debido cumplimiento.\nSEGUNDO.-El presente Decreto entrará en vigor al día siguiente de su publicación.\nTERCERO.-El Jefe de Gobierno del Distrito Federal incluirá en el proyecto de presupuesto de egresos que envíe a este órgano legislativo en cada ejercicio fiscal, las previsiones necesarias que permitan contar con\n\nun Centro de Refugio para la atención de violencia familiar en las zonas de mayor incidencia del Distrito\nFederal, en un plazo que no excederá de ocho años, a partir de la aprobación de la presente reforma.\nCUARTO.-Publíquese en la Gaceta Oficial del Distrito Federal para su debida observancia y publicación y para su mayor difusión publíquese en el Diario Oficial de la Federación.\nRecinto de la Asamblea Legislativa del Distrito Federal, a los veinticinco días del mes de noviembre del año dos mil diez.- POR LA MESA DIRECTIVA.- DIP. EMILIANO AGUILAR ESQUIVEL, PRESIDENTE.- DIP. JOSÉ\nVALENTÍN MALDONADO SALGADO, SECRETARIO.- DIP. GUILLERMO OCTAVIO HUERTA LING, SECRETARIO.-\nFIRMAS.\nEn cumplimiento de lo dispuesto por los artículos 122, apartado C, Base Segunda, fracción II, inciso b), de la Constitución Política de los Estados Unidos Mexicanos; 48, 49 y 67, fracción II, del Estatuto de Gobierno del Distrito Federal, para su debida publicación y observancia, expido el presente Decreto Promulgatorio en la Residencia Oficial del Jefe de Gobierno del Distrito Federal, en la Ciudad de México, a los trece días del mes de enero del año dos mil once.- EL JEFE DE GOBIERNO DEL DISTRITO FEDERAL, MARCELO LUIS\nEBRARD CASAUBON.- FIRMA.- EL SECRETARIO DE GOBIERNO, JOSÉ ÁNGEL ÁVILA PÉREZ.- FIRMA.- EL\nSECRETARIO DE SALUD, JOSÉ ARMANDO AHUED ORTEGA.- FIRMA.- EL SECRETARIO DE SEGURIDAD\nPÚBLICA, MANUEL MONDRAGÓN Y KALB.- FIRMA.- EL SECRETARIO DE DESARROLLO SOCIAL, MARTÍ BATRES\nGUADARRAMA.- FIRMA.- EL SECRETARIO DE EDUCACIÓN, MARIO M. DELGADO CARRILLO.- FIRMA.- EL\nSECRETARIO DE TRABAJO Y FOMENTO AL EMPLEO, BENITO MIRÓN LINCE.- FIRMA.- EL SECRETARIO DE\nTURISMO, ALEJANDRO ROJAS DÍAZ DURÁN.- FIRMA.\nTRANSITORIOS DEL DECRETO POR EL QUE SE REFORMAN Y ADICIONAN DIVERSAS DISPOSICIONES DE LA\nLEY DE ACCESO DE LAS MUJERES A UNA VIDA LIBRE DE VIOLENCIA PARA EL DISTRITO FEDERAL; PUBLICADO\nEN LA GACETA OFICIAL DEL DISTRITO FEDERAL EL 25 DE JULIO DE 2012.\nPRIMERO.-Publíquese en la Gaceta Oficial del Distrito Federal.\nSEGUNDO.-El presente decreto entrará en vigor al siguiente día de su publicación.\nTERCERO.-Las autoridades del presente Decreto, conforme a la suficiencia presupuestal asignada por la\nAsamblea Legislativa, instrumentarán las acciones establecidas para dar cumplimiento a la misma.\nRecinto de la Asamblea Legislativa del Distrito Federal, a los veinticinco días del mes de noviembre del año dos mil diez.- POR LA MESA DIRECTIVA.- DIP. EMILIANO AGUILAR ESQUIVEL, PRESIDENTE.- DIP. JOSÉ\n\nVALENTÍN MALDONADO SALGADO, SECRETARIO.- DIP. GUILLERMO OCTAVIO HUERTA LING, SECRETARIO.-\nFIRMAS.\nEn cumplimiento de lo dispuesto por los artículos 122, apartado C, Base Segunda, fracción II, inciso b), de la Constitución Política de los Estados Unidos Mexicanos; 48, 49 y 67, fracción II, del Estatuto de Gobierno del Distrito Federal, para su debida publicación y observancia, expido el presente Decreto Promulgatorio en la Residencia Oficial del Jefe de Gobierno del Distrito Federal, en la Ciudad de México, a los trece días del mes de enero del año dos mil once.- EL JEFE DE GOBIERNO DEL DISTRITO FEDERAL, MARCELO LUIS\nEBRARD CASAUBON.- FIRMA.- EL SECRETARIO DE GOBIERNO, JOSÉ ÁNGEL ÁVILA PÉREZ.- FIRMA.- EL\nSECRETARIO DE SALUD, JOSÉ ARMANDO AHUED ORTEGA.- FIRMA.- EL SECRETARIO DE SEGURIDAD\nPÚBLICA, MANUEL MONDRAGÓN Y KALB.- FIRMA.- EL SECRETARIO DE DESARROLLO SOCIAL, MARTÍ BATRES\nGUADARRAMA.- FIRMA.- EL SECRETARIO DE EDUCACIÓN, MARIO M. DELGADO CARRILLO.- FIRMA.- EL\nSECRETARIO DE TRABAJO Y FOMENTO AL EMPLEO, BENITO MIRÓN LINCE.- FIRMA.- EL SECRETARIO DE\nTURISMO, ALEJANDRO ROJAS DÍAZ DURÁN.- FIRMA.\nTRANSITORIOS DEL DECRETO POR EL QUE SE REFORMAN DIVERSAS DISPOSICIONES DE LA LEY DE ACCESO\nDE LAS MUJERES A UNA VIDA LIBRE DE VIOLENCIA DEL DISTRITO FEDERAL, PUBLICADO EN LA GACETA\nOFICIAL DEL DISTRITO FEDERAL EL 9 DE AGOSTO DE 2013.\nARTÍCULO PRIMERO.-Remítase al Jefe de Gobierno del Distrito Federal para su publicación en la Gaceta\nOficial del Distrito Federal y para su mayor difusión en el Diario Oficial de la Federación.\nARTÍCULO SEGUNDO.-El presente Decreto entrará en vigor al día siguiente de su publicación en la Gaceta\nOficial del Distrito Federal.\nRecinto de la Asamblea Legislativa del Distrito Federal, a los treinta días del mes de abril del año dos mil trece.- POR LA MESA DIRECTIVA.- DIP. EFRAÍN MORALES LÓPEZ, PRESIDENTE.- DIP. ROSALÍO ALFREDO\nPINEDA SILVA, SECRETARIO.- DIP. RUBÉN ERIK ALEJANDRO JIMÉNEZ HERNÁNDEZ, SECRETARIO.- (Firmas)\nEn cumplimiento de lo dispuesto por los artículos 122, apartado C, Base Segunda, fracción II, inciso b), de la Constitución Política de los Estados Unidos Mexicanos; 48, 49 y 67, fracción II, del Estatuto de Gobierno del Distrito Federal, para su debida publicación y observancia, expido el presente Decreto Promulgatorio en la Residencia Oficial del Jefe de Gobierno del Distrito Federal, en la Ciudad de México, a los nueve días del mes de julio del año dos mil trece.- EL JEFE DE GOBIERNO DEL DISTRITO FEDERAL, MIGUEL ÁNGEL\nMANCERA ESPINOSA.- FIRMA.-ELSECRETARIO DE GOBIERNO, HÉCTOR SERRANO CORTÉS.- FIRMA.- EL\nSECRETARIO DE DESARROLLO URBANO Y VIVIENDA DEL DISTRITO FEDERAL, SIMÓN NEUMANN LADENZON.-\n\nFIRMA.- EL SECRETARIO DE DESARROLLO ECONÓMICO DEL DISTRITO FEDERAL, SALOMÓN CHERTORIVSKI\nWOLDENBERG.- FIRMA.- LA SECRETARIA DE MEDIO AMBIENTE DEL DISTRITO FEDERAL, TANYA MÜLLER\nGARCÍA.- FIRMA.- EL SECRETARIO DE OBRAS Y SERVICIOS DEL DISTRITO FEDERAL, LUIS ALBERTO RÁBAGO\nMARTÍNEZ.- FIRMA.- LA SECRETARIA DE DESARROLLO SOCIAL DEL DISTRITO FEDERAL, ROSA ÍCELA\nRODRÍGUEZ VELÁZQUEZ.- FIRMA.- EL SECRETARIO DE TRANSPORTES Y VIALIDAD DEL DISTRITO FEDERAL,\nRUFINO H. LEÓN TOVAR.- FIRMA.- EL SECRETARIO DE TURISMO DEL DISTRITO FEDERAL, MIGUEL TORRUCO\nMÁRQUES.- FIRMA.- LA SECRETARIA DE CULTURA DEL DISTRITO FEDERAL, LUCÍA GARCÍA NORIEGA Y NIETO.-\nFIRMA.- EL SECRETARIO DE SEGURIDAD PÚBLICA DEL DISTRITO FEDERAL, JESÚS RODRÍGUEZ ALMEIDA.-\nFIRMA.- EL SECRETARIO DE PROTECCIÓN CIVIL DEL DISTRITO FEDERAL, FAUSTO LUGO GARCÍA.- FIRMA.- EL\nSECRETARIO DE TRABAJO Y FOMENTO AL EMPLEO DEL DISTRITO FEDERAL, CARLOS NAVARRETE RUÍZ.-\nFIRMA.- LA SECRETARIA DE EDUCACIÓN DEL DISTRITO FEDERAL, MARA ROBLES VILLASEÑOR.- FIRMA.- EL\nSECRETARIO DE DESARROLLO RURAL Y EQUIDAD PARA LAS COMUNIDADES DEL DISTRITO FEDERAL, HEGEL\nCORTÉS MIRANDA.- FIRMA.- EL SECRETARIO DE FINANZAS DEL DISTRITO FEDERAL, EDGAR ABRAHAM\nAMADOR ZAMORA.- FIRMA.- EL SECRETARIO DE SALUD DEL DISTRITO FEDERAL, JOSÉ ARMANDO AHUED\nORTEGA.- FIRMA.- EL SECRETARIO DE CIENCIA, TECNOLOGÍA E INNOVACIÓN DEL DISTRITO FEDERAL, RENÉ\nRAÚL DRUCKER COLÍN.- FIRMA.\nTRANSITORIOS DEL DECRETO POR EL QUE REFORMAN, ADICIONAN Y DEROGAN, DIVERSOS ARTÍCULOS DEL\nCÓDIGO CIVIL PARA EL DISTRITO FEDERAL; CÓDIGO DE INSTITUCIONES Y PROCEDIMIENTOS ELECTORALES\nDEL DISTRITO FEDERAL; CÓDIGO FISCAL DEL DISTRITO FEDERAL; CÓDIGO PENAL PARA EL DISTRITO\nFEDERAL; LEY AMBIENTAL DE PROTECCIÓN A LA TIERRA EN EL DISTRITO FEDERAL; LEY DE ACCESO DE LAS\nMUJERES A UNA VIDA LIBRE DE VIOLENCIA DEL DISTRITO FEDERAL; LEY DE ASISTENCIA Y PREVENCIÓN DE\nLA VIOLENCIA FAMILIAR; LEY DE CENTROS DE RECLUSIÓN PARA EL DISTRITO FEDERAL; LEY DE CULTURA\nCÍVICA DEL DISTRITO FEDERAL; LEY DE ESTABLECIMIENTOS MERCANTILES DEL DISTRITO FEDERAL; LEY DE\nEXTINCIÓN DE DOMINIO PARA EL DISTRITO FEDERAL; LEY DE FISCALIZACIÓN SUPERIOR DE LA CIUDAD DE\nMÉXICO; LEY DE IGUALDAD SUSTANTIVA ENTRE MUJERES Y HOMBRES EN EL DISTRITO FEDERAL; LEY DE\nJUSTICIA ALTERNATIVA DEL TRIBUNAL SUPERIOR DE JUSTICIA PARA EL DISTRITO FEDERAL; LEY DE JUSTICIA\nALTERNATIVA EN LA PROCURACIÓN DE JUSTICIA PARA EL DISTRITO FEDERAL; LEY DE JUSTICIA PARA\nADOLESCENTES PARA EL DISTRITO FEDERAL; LEY DE PARTICIPACIÓN CIUDADANA DEL DISTRITO FEDERAL;\nLEY DE PROTECCIÓN A LAS VÍCTIMAS DEL DELITO DE SECUESTRO PARA EL DISTRITO FEDERAL; LEY DE\nPRESTACIÓN DE SERVICIOS INMOBILIARIOS DEL DISTRITO FEDERAL; LEY DE PROTECCIÓN A LOS ANIMALES\nDEL DISTRITO FEDERAL; LEY DE PROTECCIÓN DE DATOS PERSONALES PARA EL DISTRITO FEDERAL; LEY DE\nSALUD DEL DISTRITO FEDERAL; LEY DE SALUD MENTAL DEL DISTRITO FEDERAL; LEY DE SEGURIDAD PRIVADA\nPARA EL DISTRITO FEDERAL; LEY DE TRANSPARENCIA Y ACCESO A LA INFORMACIÓN PÚBLICA DEL DISTRITO\nFEDERAL; LEY DEL FONDO DE APOYO A LA ADMINISTRACIÓN DE JUSTICIA EN EL DISTRITO FEDERAL; LEY DEL\nFONDO DE APOYO A LA PROCURACIÓN DE JUSTICIA EN EL DISTRITO FEDERAL; LEY DEL HEROICO CUERPO\n\nDE BOMBEROS DEL DISTRITO FEDERAL; LEY DEL INSTITUTO DE ESTUDIOS CIENTÍFICOS PARA LA\nPREVENCIÓN DEL DELITO EN EL DISTRITO FEDERAL; LEY DEL INSTITUTO DE VERIFICACIÓN ADMINISTRATIVA\nDEL DISTRITO FEDERAL; LEY DEL NOTARIADO PARA EL DISTRITO FEDERAL; LEY DE LA COMISIÓN DE\nDERECHOS HUMANOS DEL DISTRITO FEDERAL; LEY DE LA DEFENSORÍA PÚBLICA DEL DISTRITO FEDERAL;\nLEY DE LOS DERECHOS DE LAS PERSONAS ADULTAS MAYORES EN EL DISTRITO FEDERAL; LEY ORGÁNICA\nDEL TRIBUNAL SUPERIOR DE JUSTICIA DEL DISTRITO FEDERAL; LEY ORGÁNICA DE LA ADMINISTRACIÓN\nPÚBLICA DEL DISTRITO FEDERAL; LEY ORGÁNICA DE LA PROCURADURÍA AMBIENTAL Y DEL ORDENAMIENTO\nTERRITORIAL DEL DISTRITO FEDERAL; LEY PARA LA ATENCIÓN INTEGRAL DEL CONSUMO DE SUSTANCIAS\nPSICOACTIVAS DEL DISTRITO FEDERAL; LEY PARA LA INTEGRACIÓN AL DESARROLLO DE LAS PERSONAS CON\nDISCAPACIDAD DEL DISTRITO FEDERAL; LEY PARA LA PROMOCIÓN DE LA CONVIVENCIA LIBRE DE\nVIOLENCIA EN EL ENTORNO ESCOLAR DEL DISTRITO FEDERAL; LEY PARA LA PROTECCIÓN, ATENCIÓN Y\nASISTENCIA A LAS VÍCTIMAS DE LOS DELITOS EN MATERIA DE TRATA DE PERSONAS DEL DISTRITO FEDERAL;\nLEY PARA PREVENIR LA VIOLENCIA EN LOS ESPECTÁCULOS DEPORTIVOS EN EL DISTRITO FEDERAL; LEY QUE\nESTABLECE EL PROCEDIMIENTO DE REMOCIÓN DE LOS SERVIDORES PÚBLICOS QUE DESIGNA LA\nASAMBLEA LEGISLATIVA DEL DISTRITO FEDERAL Y DE LOS TITULARES DE LOS ÓRGANOS POLÍTICO\nADMINISTRATIVOS DEL DISTRITO FEDERAL; Y LEY REGISTRAL PARA EL DISTRITO FEDERAL, PUBLICADO EN LA\nGACETA OFICIAL DEL DISTRITO FEDERAL EL 18 DE DICIEMBRE DE 2014.\nPRIMERO. - Publíquese en la Gaceta Oficial del Distrito Federal.\nSEGUNDO. - El presente Decreto entrará en vigor en los términos establecidos en la Declaratoria de la\nIncorporación del Sistema Procesal Penal Acusatorio y del Código Nacional de Procedimientos Penales al orden jurídico del Distrito Federal, publicada en la Gaceta Oficial el día 20 de agosto del presente año, así como su Fe de Erratas y Aclaratoria de Fe de Erratas, publicadas en la Gaceta Oficial, los días 21 y 22 de agosto del 2014.\nTERCERO. - Los asuntos iniciados con anterioridad a la entrada en vigor del presente decreto, se tramitarán conforme a las disposiciones anteriores, que le sean aplicables.\nCUARTO. - La reforma al Código de Instituciones y Procedimientos Electorales del Distrito Federal prevista en el presente Decreto, entrará en vigor al día siguiente a aquél en que concluya el proceso electoral local de 2014-2015 en el Distrito Federal.\nRecinto de la Asamblea Legislativa del Distrito Federal, a los veinticinco días del mes de noviembre del año dos mil catorce.- POR LA MESA DIRECTIVA.- DIP. JAIME ALBERTO OCHOA AMORÓS, PRESIDENTE.- DIP.\nOSCAR OCTAVIO MOGUEL BALLADO, PROSECRETARIO.- DIP. KARLA VALERIA GÓMEZ BLANCAS,\nSECRETARIA.- FIRMAS.\n\nEn cumplimiento de lo dispuesto por los artículos 122, apartado C, Base Segunda, fracción II, inciso b), de la Constitución Política de los Estados Unidos Mexicanos; 48, 49 y 67, fracción II, del Estatuto de Gobierno del Distrito Federal, para su debida publicación y observancia, expido el presente Decreto Promulgatorio en la Residencia Oficial del Jefe de Gobierno del Distrito Federal, en la Ciudad de México, a los veintiocho días del mes de noviembre del año dos mil catorce.- EL JEFE DE GOBIERNO DEL DISTRITO FEDERAL, DR.\nMIGUEL ÁNGEL MANCERA ESPINOSA.- FIRMA.- EL SECRETARIO DE GOBIERNO, HÉCTOR SERRANO CORTÉS.-\nFIRMA.- EL SECRETARIO DE SALUD, JOSÉ ARMANDO AHUED ORTEGA.- FIRMA.- LA SECRETARIA DE\nDESARROLLO SOCIAL, ROSA ÍCELA RODRÍGUEZ VELÁZQUEZ.- FIRMA.- EL SECRETARIO DE DESARROLLO\nECONÓMICO, SALOMÓN CHERTORIVSKI WOLDENBERG.- LA SECRETARIA DE EDUCACIÓN, MARA\nNADIEZHDA ROBLES VILLASEÑOR.- FIRMA.- EL SECRETARIO DE DESARROLLO URBANO Y VIVIENDA, FELIPE\nDE JESÚS GUTIÉRREZ GUTIÉRREZ.- FIRMA.- EL SECRETARIO DE SEGURIDAD PÚBLICA, JESÚS RODRÍGUEZ\nALMEIDA.- FIRMA.- EL SECRETARIO DE FINANZAS, EDGAR ABRAHAM AMADOR ZAMORA.- FIRMA.- LA\nSECRETARIA DE MEDIO AMBIENTE, TANYA MÜLLER GARCÍA.- FIRMA.\nTRANSITORIOS DELDECRETO POR EL QUE SE ADICIONAN Y REFORMAN DIVERSAS DISPOSICIONES DE LA\nLEY DE ACCESO DE LAS MUJERES A UNA VIDA LIBRE DE VIOLENCIA PARA EL DISTRITO FEDERAL, PUBLICADO\nEN LA GACETA OFICIAL DEL DISTRITO FEDERAL EL 26 DE NOVIEMBRE DEL 2015.\nPRIMERO. -El presente decreto entrará en vigor al día siguiente de su publicación en la Gaceta Oficial del\nDistrito Federal.\nRecinto de la Asamblea Legislativa del Distrito Federal, a los treinta días del mes de abril del año dos mil quince. - POR LA MESA DIRECTIVA. - DIP. MANUEL ALEJANDRO ROBLES GÓMEZ, PRESIDENTE. - DIP.\nORLANDO ANAYA GONZÁLEZ, SECRETARIO. - DIP. ALEJANDRO RAFAEL PIÑA MEDINA, SECRETARIO. - FIRMA.\nEn cumplimiento de lo dispuesto por los artículos 122, apartado C, Base Segunda, fracción II, inciso b), de la Constitución Política de los Estados Unidos Mexicanos; 48, 49 y 67, fracción II, del Estatuto de Gobierno del Distrito Federal, para su debida publicación y observancia, expido el presente Decreto Promulgatorio en la Residencia Oficial del Jefe de Gobierno del Distrito Federal, en la Ciudad de México, a los doce días del mes de noviembre del año dos mil quince.- EL JEFE DE GOBIERNO DEL DISTRITO FEDERAL, MIGUEL\nÁNGEL MANCERA ESPINOSA.- FIRMA.- LA SECRETARIA DE GOBIERNO, DORA PATRICIA MERCADO CASTRO.-\nFIRMA.- EL SECRETARIO DE DESARROLLO SOCIAL, JOSÉ RAMÓN AMIEVA GÁLVEZ.- FIRMA.- EL SECRETARIO\nDE SEGURIDAD PÚBLICA, HIRAM ALMEIDA ESTRADA.- FIRMA.- LA SECRETARIA DE EDUCACIÓN, MARÍA\nALEJANDRA BARRALES MAGDALENO.\n\nTRANSITORIOS DEL DECRETO POR EL QUE SE REFORMAN Y ADICIONAN DIVERSAS DISPOSICIONES DE LA\nLEY DE ACCESO DE LAS MUJERES A UNA VIDA LIBRE DE VIOLENCIA DEL DISTRITO FEDERAL, PUBLICADO EN\nLA GACETA OFICIAL DE LA CIUDAD DE MÉXICO EL 10 DE NOVIEMBRE DE 2016.\nPRIMERO.- El presente Decreto entrará en vigor el día siguiente de su publicación en la Gaceta Oficial del\nDistrito Federal.\nSEGUNDO.- Publíquese en la Gaceta Oficial del Gobierno del Distrito Federal para su conocimiento y en el\nDiario Oficial de la Federación para su mayor difusión.\nRecinto de la Asamblea Legislativa del Distrito Federal, a los trece días del mes de octubre del año dos mil dieciséis.- POR LA MESA DIRECTIVA.- DIP. A. XAVIER LÓPEZ ADAME, PRESIDENTE.- DIP. SOCORRO MEZA\nMARTÍNEZ, SECRETARIA.- DIP. CARLOS ALFONSO CANDELARIA LÓPEZ, SECRETARIO.- (Firmas)\nCon fundamento en lo dispuesto por los artículos 122, Apartado A, Base III, de la Constitución Política de los Estados Unidos Mexicanos; Transitorios Primero y Segundo del Decreto por el que se declaran reformadas y derogadas diversas disposiciones de la Constitución Política de los Estados Unidos Mexicanos, en materia de la Reforma Política de la Ciudad de México; 48, 49 y 67, fracción II, del Estatuto de Gobierno del Distrito Federal, para su debida publicación y observancia, expido el presente Decreto Promulgatorio en la Residencia Oficial del Jefe de Gobierno de la Ciudad de México, a los siete días del mes de noviembre del año dos mil dieciséis.- EL JEFE DE GOBIERNO DE LA CIUDAD DE MÉXICO, MIGUEL ÁNGEL MANCERA\nESPINOSA.- FIRMA.- LA SECRETARIA DE GOBIERNO, DORA PATRICIA MERCADO CASTRO.- FIRMA.- EL\nSECRETARIO DE DESARROLLO SOCIAL, JOSÉ RAMÓN AMIEVA GÁLVEZ.- FIRMA.\nTRANSITORIOS DEL DECRETO POR EL QUE SE ADICIONAN DIVERSAS DISPOSICIONES DE LA LEY DE ACCESO\nDE LAS MUJERES A UNA VIDA LIBRE DE VIOLENCIA DEL DISTRITO FEDERAL, PUBLICADO EN LA GACETA\nOFICIAL DE LA CIUDAD DE MÉXICO EL 11 DE JULIO DE 2017.\nPRIMERO.- El presente Decreto entrará en vigor el día siguiente al de su publicación en la Gaceta Oficial de la Ciudad de México.\nSEGUNDO.-Publíquese en la Gaceta Oficial de la Ciudad de México para su conocimiento y en el Diario\nOficial de la Federación para su mayor difusión.\n\nRecinto de la Asamblea Legislativa del Distrito Federal, a los cinco días del mes de abril del año dos mil diecisiete.- POR LA MESA DIRECTIVA.- DIP. ERNESTO SÁNCHEZ RODRÍGUEZ, PRESIDENTE.- DIP. REBECA\nPERALTA LEÓN, SECRETARIA.- DIP. EVA ELOISA LESCAS HERNÁNDEZ, SECRETARIA.- (Firmas)\nCon fundamento en lo dispuesto por los artículos 122, Apartado A, Base III, de la Constitución Política de los Estados Unidos Mexicanos; Transitorios Primero y Segundo del Decreto por el que se declaran reformadas y derogadas diversas disposiciones de la Constitución Política de los Estados Unidos Mexicanos, en materia de la Reforma Política de la Ciudad de México; 48, 49 y 67, fracción II, del Estatuto de Gobierno del Distrito Federal, para su debida publicación y observancia, expido el presente Decreto Promulgatorio en la Residencia Oficial del Jefe de Gobierno de la Ciudad de México, a los treinta y un días del mes de mayo del año dos mil diecisiete.- EL JEFE DE GOBIERNO DE LA CIUDAD DE MÉXICO, MIGUEL ÁNGEL\nMANCERA ESPINOSA.- FIRMA.- LA SECRETARIA DE GOBIERNO, DORA PATRICIA MERCADO CASTRO.- FIRMA.-\nEL SECRETARIO DE DESARROLLO SOCIAL, JOSÉ RAMÓN AMIEVA GÁLVEZ.- FIRMA.\nTRANSITORIOS DEL DECRETO POR EL QUE SE ADICIONAN DIVERSAS DISPOSICIONES DE LA LEY DE ACCESO\nDE LAS MUJERES A UNA VIDA LIBRE DE VIOLENCIA DEL DISTRITO FEDERAL, PUBLICADO EN LA GACETA\nOFICIAL DE LA CIUDAD DE MÉXICO EL 13 DE JULIO DE 2017.\nPRIMERO.- El presente Decreto entrará en vigor el día siguiente al de su publicación en la Gaceta Oficial de la Ciudad de México.\nSEGUNDO.- Publíquese en la Gaceta Oficial de la Ciudad de México para su conocimiento y en el Diario\nOficial de la Federación para su mayor difusión.\nRecinto de la Asamblea Legislativa del Distrito Federal, a los veintitrés días del mes de mayo del año dos mil diecisiete.- POR LA MESA DIRECTIVA.- DIP. MAURICIO ALONSO TOLEDO GUTIÉRREZ, PRESIDENTE.- DIP.\nREBECA PERALTA LEÓN, SECRETARIA.- DIP. LUCIANO JIMENO HUANOSTA, SECRETARIO.- (Firmas)\nCon fundamento en lo dispuesto por los artículos 122, Apartado A, Base III, de la Constitución Política de los Estados Unidos Mexicanos; Transitorios Primero y Segundo del Decreto por el que se declaran reformadas y derogadas diversas disposiciones de la Constitución Política de los Estados Unidos Mexicanos, en materia de la Reforma Política de la Ciudad de México; 48, 49 y 67, fracción II, del Estatuto de Gobierno del Distrito Federal, para su debida publicación y observancia, expido el presente Decreto Promulgatorio en la Residencia Oficial del Jefe de Gobierno de la Ciudad de México, a los treinta y un días del mes de mayo del año dos mil diecisiete.- EL JEFE DE GOBIERNO DE LA CIUDAD DE MÉXICO, MIGUEL ÁNGEL\n\nMANCERA ESPINOSA.- FIRMA.- LA SECRETARIA DE GOBIERNO, DORA PATRICIA MERCADO CASTRO.- FIRMA.-\nEL SECRETARIO DE DESARROLLO SOCIAL, JOSÉ RAMÓN AMIEVA GÁLVEZ.- FIRMA.\nTRANSITORIOS DEL DECRETO POR EL QUE SE ADICIONAN DIVERSAS DISPOSICIONES DE LA LEY DE ACCESO\nDE LAS MUJERES A UNA VIDA LIBRE DE VIOLENCIA DEL DISTRITO FEDERAL, PUBLICADO EN LA GACETA\nOFICIAL DE LA CIUDAD DE MÉXICO EL 17 DE JULIO DE 2017.\nPRIMERO.- El presente Decreto entrará en vigor el día siguiente al de su publicación en la Gaceta Oficial de la Ciudad de México.\nSEGUNDO.- Publíquese en la Gaceta Oficial de la Ciudad de México para su conocimiento y en el Diario\nOficial de la Federación para su mayor difusión.\nRecinto de la Asamblea Legislativa del Distrito Federal, a los veintitrés días del mes de mayo del año dos mil diecisiete.- POR LA MESA DIRECTIVA.- DIP. MAURICIO ALONSO TOLEDO GUTIÉRREZ, PRESIDENTE.- DIP.\nREBECA PERALTA LEÓN, SECRETARIA.- DIP. LUCIANO JIMENO HUANOSTA, SECRETARIO.- (Firmas)\nCon fundamento en lo dispuesto por los artículos 122, Apartado A, Base III, de la Constitución Política de los Estados Unidos Mexicanos; Transitorios Primero y Segundo del Decreto por el que se declaran reformadas y derogadas diversas disposiciones de la Constitución Política de los Estados Unidos Mexicanos, en materia de la Reforma Política de la Ciudad de México; 48, 49 y 67, fracción II, del Estatuto de Gobierno del Distrito Federal, para su debida publicación y observancia, expido el presente Decreto Promulgatorio en la Residencia Oficial del Jefe de Gobierno de la Ciudad de México, a los treinta y un días del mes de mayo del año dos mil diecisiete.- EL JEFE DE GOBIERNO DE LA CIUDAD DE MÉXICO, MIGUEL ÁNGEL\nMANCERA ESPINOSA.- FIRMA.- LA SECRETARIA DE GOBIERNO, DORA PATRICIA MERCADO CASTRO.- FIRMA.-\nEL SECRETARIO DE DESARROLLO SOCIAL, JOSÉ RAMÓN AMIEVA GÁLVEZ.- FIRMA.\nTRANSITORIOS DEL DECRETO POR EL QUE SE ADICIONAN DIVERSAS DISPOSICIONES DE LA LEY DE ACCESO\nDE LAS MUJERES A UNA VIDA LIBRE DE VIOLENCIA DEL DISTRITO FEDERAL, PUBLICADO EN LA GACETA\nOFICIAL DE LA CIUDAD DE MÉXICO EL 19 DE JULIO DE 2017.\nPRIMERO.- El presente Decreto entrará en vigor el día siguiente al de su publicación en la Gaceta Oficial de la Ciudad de México.\n\nSEGUNDO.- Publíquese en la Gaceta Oficial de la Ciudad de México para su conocimiento y en el Diario\nOficial de la Federación para su mayor difusión.\nRecinto de la Asamblea Legislativa del Distrito Federal, a los seis días del mes de junio del año dos mil diecisiete.- POR LA MESA DIRECTIVA.- DIP. MAURICIO ALONSO TOLEDO GUTIÉRREZ, PRESIDENTE.- DIP.\nREBECA PERALTA LEÓN, SECRETARIA.- DIP. LUCIANO JIMENO HUANOSTA, SECRETARIO.- (Firma)\nCon fundamento en lo dispuesto por los artículos 122, Apartado A, Base III, de la Constitución Política de los Estados Unidos Mexicanos; Transitorios Primero y Segundo del Decreto por el que se declaran reformadas y derogadas diversas disposiciones de la Constitución Política de los Estados Unidos Mexicanos, en materia de la Reforma Política de la Ciudad de México; 48, 49 y 67, fracción II, del Estatuto de Gobierno del Distrito Federal, para su debida publicación y observancia, expido el presente Decreto Promulgatorio en la Residencia Oficial del Jefe de Gobierno de la Ciudad de México, a los treinta y un días del mes de mayo del año dos mil diecisiete.- EL JEFE DE GOBIERNO DE LA CIUDAD DE MÉXICO, MIGUEL ÁNGEL\nMANCERA ESPINOSA.- FIRMA.- LA SECRETARIA DE GOBIERNO, DORA PATRICIA MERCADO CASTRO.- FIRMA.-\nEL SECRETARIO DE DESARROLLO SOCIAL, JOSÉ RAMÓN AMIEVA GÁLVEZ.- FIRMA.\nTRANSITORIOS DEL DECRETO POR EL QUE SE REFORMAN Y ADICIONAN DIVERSAS DISPOSICIONES DE LA\nLEY DE ACCESO DE LAS MUJERES A UNA VIDA LIBRE DE VIOLENCIA DEL DISTRITO FEDERAL, PUBLICADO EN\nLA GACETA OFICIAL DE LA CIUDAD DE MÉXICO EL 08 DE MARZO DE 2019.\nPRIMERO. -A efecto de dar cumplimiento a lo dispuesto en el presente decreto, la persona Titular de la\nJefatura de Gobierno de la Ciudad de México, contará con un plazo que no excederá de 30 días hábiles, para armonizar el contenido del Reglamento de la presente Ley.\nSEGUNDO. – Con motivo de la entrada en vigor de la Ley Orgánica del Poder Ejecutivo y de la\nAdministración Pública de la Ciudad de México, las referencias hechas al Instituto de las Mujeres en el\nDistrito Federal, deberán entenderse hechas a la Secretaría de las Mujeres.\nTERCERO. - El presente decreto entrará en vigor el día siguiente al de su publicación en la Gaceta Oficial de la Ciudad de México.\nPalacio Legislativo del Congreso de la Ciudad de México, a los veintiocho días del mes de diciembre del año dos mil dieciocho. - POR LA MESA DIRECTIVA. - DIPUTADO JOSÉ DE JESÚS MARTÍN DEL CAMPO\nCASTAÑEDA, PRESIDENTE. - DIPUTADA ISABELA ROSALES HERRERA, SECRETARIA. - DIPUTADA ANA PATRICIA\nBAEZ GUERRERO, SECRETARIA. - (Firmas)\n\nCon fundamento en lo dispuesto por los artículos 122, Apartado A, fracción III, de la Constitución Política de los Estados Unidos Mexicanos; 32 apartado C, numeral 1, inciso a) de la Constitución Política de la\nCiudad de México; 3 fracciones XVII y XVIII, 7, 10 fracción II, 16 y 21, párrafo primero, de la Ley Orgánica del Poder Ejecutivo y de la Administración Pública de la Ciudad de México; para su debida publicación y observancia, expido el presente Decreto Promulgatorio en la Residencia Oficial de la Jefatura de Gobierno de la Ciudad de México, a los seis días del mes de marzo del año dos mil diecinueve.- LA JEFA DE GOBIERNO\nDE LA CIUDAD DE MÉXICO, DRA. CLAUDIA SHEINBAUM PARDO.- FIRMA.- LA SECRETARIA DE GOBIERNO,\nROSA ICELA RODRÍGUEZ VELÁZQUEZ.- FIRMA.- LA SECRETARIA DE ADMINISTRACIÓN Y FINANZAS, LUZ\nELENA GONZÁLEZ ESCOBAR.- FIRMA.- LA SECRETARIA DE LAS MUJERES, GABRIELA RODRÍGUEZ RAMÍREZ.\nTRANSITORIOS DEL DECRETO POR EL QUE SE ADICIONA UNA FRACCIÓN X AL ARTÍCULO 7, UNA FRACCIÓN\nXV AL ARTÍCULO 63 Y UN ARTÍCULO 72 TER DE LA LEY DE ACCESO DE LAS MUJERES A UNA VIDA LIBRE DE\nVIOLENCIA DE LA CIUDAD DE MÉXICO, PUBLICADO EN LA GACETA OFICIAL DE LA CIUDAD DE MÉXICO EL 22\nDE ENERO DE 2020.\nPRIMERO.- El presente decreto entrará en vigor, al día siguiente de su publicación en la Gaceta Oficial de la Ciudad de México.\nSEGUNDO.- Remítase a la Jefatura de Gobierno para su publicación en la Gaceta Oficial de la Ciudad de\nMéxico para los efectos legales a que haya lugar.\nPalacio Legislativo del Congreso de la Ciudad de México, a los tres días del mes de diciembre del año dos mil diecinueve.- POR LA MESA DIRECTIVA.- DIPUTADA ISABELA ROSALES HERRERA, PRESIDENTA.-\nDIPUTADA MARTHA SOLEDAD ÁVILA VENTURA, SECRETARIA.- DIPUTADA MARGARITA SALDAÑA\nHERNÁNDEZ, SECRETARIA.- (Firmas)\nCon fundamento en lo dispuesto por los artículos 122, apartado A, fracción III de la Constitución Política de los Estados Unidos Mexicanos; 32, apartado C, numeral 1, inciso a) de la Constitución Política de la Ciudad de México; 2 párrafo segundo, 3 fracciones XVII y XVIII, 7 párrafo primero, 10 fracción II, 12 y 21 párrafo primero de la Ley Orgánica del Poder Ejecutivo y de la Administración Pública de la Ciudad de México; para su debida publicación y observancia, expido el presente Decreto Promulgatorio en la Residencia Oficial de la Jefatura de Gobierno de la Ciudad de México, a los veintiún días del mes enero del año dos mil veinte.-\nLA JEFA DE GOBIERNO DE LA CIUDAD DE MÉXICO, DRA. CLAUDIA SHEINBAUM PARDO.- FIRMA.- LA\nSECRETARIA DE GOBIERNO, ROSA ICELA RODRÍGUEZ VELÁZQUEZ.- FIRMA.- LA SECRETARIA DE LAS\nMUJERES, GABRIELA RODRÍGUEZ RAMÍREZ.- FIRMA\n\nTRANSITORIOS DEL DECRETO POR EL QUE SE REFORMA Y ADICIONA, DIVERSAS DISPOSICIONES DEL\nCÓDIGO PENAL DEL DISTRITO FEDERAL, DE LA LEY DE ACCESO DE LAS MUJERES A UNA VIDA LIBRE DE\nVIOLENCIA DE LA CIUDAD DE MEXICO Y DE LA LEY DE LOS DERECHOS DE NIÑAS, NIÑOS Y ADOLESCENTES\nDE LA CIUDAD DE MÉXICO, PUBLICADO EN LA GACETA OFICIAL DE LA CIUDAD DE MÉXICO EL 20 DE MARZO\nDE 2020.\nPRIMERO.- Publíquese en la Gaceta Oficial de la Ciudad de México.\nSEGUNDO.- El presente Decreto entrará en vigor al día siguiente de su publicación en la Gaceta Oficial de la Ciudad de México.\nTERCERO.- A efecto de dar cumplimiento a lo dispuesto en el presente decreto, la persona Titular de la\nJefatura de Gobierno de la Ciudad de México, contará con un plazo que no excederá de 30 días hábiles, para armonizar el contenido del Reglamento de la Ley de Acceso de las Mujeres una Vida libre de Violencia de la Ciudad de México con el presente decreto.\nCUARTO.- La Secretaria de Gobierno de la Ciudad de México, contará con un término máximo de 90 días naturales para crear el Registro Público de Personas Agresoras Sexuales de la Ciudad de México, mismo que entrara en vigor al día siguiente de su publicación en la Gaceta Oficial de la Ciudad de México.\nQUINTO.- A partir de la entrada en vigor del presente decreto, la Secretaria de Gobierno, deberá incluir en la base de datos del Registro, todas aquellas personas sentenciadas que hayan adquirido ese carácter con fecha posterior a la entrada del presente decreto.\nSEXTO.- Envíese el presente decreto a la Jefa de Gobierno de la Ciudad de México para sus efectos legales.\nPalacio Legislativo del Congreso de la Ciudad de México, a los diez días del mes de marzo del año dos mil veinte.- POR LA MESA DIRECTIVA.- DIPUTADA ISABELA ROSALES HERRERA, PRESIDENTA.- DIPUTADA DONAJI\nOFELIA OLIVERA REYES, SECRETARIA.- DIPUTADA MARGARITA SALDAÑA HERNÁNDEZ, SECRETARIA.-\n(Firmas)\nCon fundamento en lo dispuesto por los artículos 122, apartado A, fracción III de la Constitución Política de los Estados Unidos Mexicanos; 32, apartado C, numeral 1, inciso a) de la Constitución Política de la Ciudad de México; 2 párrafo segundo, 3 fracciones XVII y XVIII, 7 párrafo primero, 10 fracción II, 12 y 21 párrafo primero de la Ley Orgánica del Poder Ejecutivo y de la Administración Pública de la Ciudad de México; para\n\nsu debida publicación y observancia, expido el presente Decreto Promulgatorio en la Residencia Oficial de la Jefatura de Gobierno de la Ciudad de México, a los diecinueve días del mes marzo del año dos mil veinte.- LA JEFA DE GOBIERNO DE LA CIUDAD DE MÉXICO, DRA. CLAUDIA SHEINBAUM PARDO.- FIRMA.- LA\nSECRETARIA DE GOBIERNO, ROSA ICELA RODRÍGUEZ VELÁZQUEZ.- FIRMA.- LA SECRETARIA DE INCLUSIÓN\nY BIENESTAR SOCIAL, ALMUDENA OCEJO ROJO.- FIRMA.\nTRANSITORIOS DEL DECRETO POR EL QUE SE REFORMA LA FRACCIÓN IV Y SE ADICIONAN LAS FRACCIONES\nV Y VI, RECORRIENDOSE EN SU ORDEN LA SUBSECUENTE, DEL ARTÍCULO 24; Y SE REFORMA EL PRIMER\nPÁRRAFO, SE ADICIONAN LAS FRACCIONES III Y IV DEL ARTÍCULO 42, RECORRIÉNDOSE EN SU ORDEN LA\nSUBSECUENTE; AMBOS DE LA LEY DE ACCESO DE LAS MUJERES A UNA VIDA LIBRE DE VIOLENCIA DE LA\nCIUDAD DE MÉXICO, PUBLICADO EN LA GACETA OFICIAL DE LA CIUDAD DE MÉXICO EL 14 DE OCTUBRE DE\n\nPRIMERO.- Túrnese al Ejecutivo Local para su publicación en la Gaceta Oficial de la Ciudad de México.\nSEGUNDO.- El presente decreto entrará en vigor el día siguiente al de su publicación en la Gaceta Oficial de la Ciudad de México.\nTERCERO.- La Jefatura de Gobierno contará con un plazo que no excederá de 30 días hábiles para realizar las adecuaciones reglamentarias que sean necesarias.\nPalacio Legislativo del Congreso de la Ciudad de México, a los diez días del mes de septiembre del año dos mil veinte. POR LA MESA DIRECTIVA.- DIPUTADA MARGARITA SALDAÑA HERNÁNDEZ, PRESIDENTA.-\nDIPUTADA DONAJI OFELIA OLIVERA REYES, SECRETARIA.- DIPUTADO HÉCTOR BARRERA MARMOLEJO,\nSECRETARIO.- (Firmas)\nCon fundamento en lo dispuesto por los artículos 122, apartado A, fracción III, de la Constitución Política de los Estados Unidos Mexicanos; 32 apartado C, numeral 1, inciso a) de la Constitución Política de la\nCiudad de México; 3 fracciones XVII y XVIII, 7 párrafo primero, 10 fracción II, 12 y 21, párrafo primero de la\nLey Orgánica del Poder Ejecutivo y de la Administración Pública de la Ciudad de México, para su debida publicación y observancia, expido el presente Decreto Promulgatorio en la Residencia Oficial de la Jefatura de Gobierno de la Ciudad de México, a los doce días del mes de octubre del año dos mil veinte.- LA JEFA\nDE GOBIERNO DE LA CIUDAD DE MÉXICO, DRA. CLAUDIA SHEINBAUM PARDO.- FIRMA.- LA SECRETARIA DE\nINCLUSIÓN Y BIENESTAR SOCIAL, ALMUDENA OCEJO ROJO.- FIRMA\nTRANSITORIO DEL DECRETO POR EL QUE SE DEROGA LA LEY DE ASISTENCIA Y PREVENCIÓN DE LA VIOLENCIA\nFAMILIAR PARA EL DISTRITO FEDERAL. Y SE MODIFICAN LOS ARTÍCULOS 2, 3, 8 FRACCIÓN III, 11, 12, 16,\n\n35, 57, FRACCIONES I Y III, 64, 65 PRIMER PÁRRAFO, 67 Y 70, LA DENOMINACIÓN DEL TÍTULO CUARTO,\nASÍ COMO EL NOMBRE DEL CAPÍTULO I DEL MISMO TÍTULO; Y SE AGREGA UNA FRACCIÓN V AL ARTÍCULO\n71; TODOS ELLOS DE LA LEY DE ACCESO DE LAS MUJERES A UNA VIDA LIBRE DE VIOLENCIA DE LA CIUDAD\nDE MÉXICO, PUBLICADO EN LA GACETA OFICIAL DE LA CIUDAD DE MÉXICO EL 19 DE OCTUBRE DE 2020.\nPRIMERO.- Remítase a la Jefatura de Gobierno para su conocimiento y efectos legales conducentes.\nSEGUNDO.- El presente decreto entrará en vigor al día siguiente al de su publicación en la Gaceta Oficial de la Ciudad de México.\nPalacio Legislativo del Congreso de la Ciudad de México, a los veintidós días del mes de septiembre del año dos mil veinte. POR LA MESA DIRECTIVA.- DIPUTADA MARGARITA SALDAÑA HERNÁNDEZ, PRESIDENTA.-\nDIPUTADA DONAJI OFELIA OLIVERA REYES, SECRETARIA.- DIPUTADO HÉCTOR BARRERA MARMOLEJO,\nSECRETARIO.- (Firmas)\nCon fundamento en lo dispuesto por los artículos 122, apartado A, fracción III, de la Constitución Política de los Estados Unidos Mexicanos; 32 apartado C, numeral 1, inciso a) de la Constitución Política de la\nCiudad de México; 3 fracciones XVII y XVIII, 7 párrafo primero, 10 fracción II, 12 y 21, párrafo primero de la\nLey Orgánica del Poder Ejecutivo y de la Administración Pública de la Ciudad de México, para su debida publicación y observancia, expido el presente Decreto Promulgatorio en la Residencia Oficial de la Jefatura de Gobierno de la Ciudad de México, a los dieciséis días del mes de octubre del año dos mil veinte.- LA\nJEFA DE GOBIERNO DE LA CIUDAD DE MÉXICO, DRA. CLAUDIA SHEINBAUM PARDO.- FIRMA.- - EL\nSECRETARIO DE GOBIERNO, JOSÉ ALFONSO SUÁREZ DEL REAL Y AGUILERA.- FIRMA.- LA ENCARGADA DEL\nDESPACHO DE LA SECRETARÍA DE CULTURA, MARÍA GUADALUPE LOZADA LEÓN.- FIRMA.- LA SECRETARIA\nDE DESARROLLO URBANO Y VIVIENDA, ILEANA AUGUSTA VILLALOBOS ESTRADA.- FIRMA.- LA SECRETARIA\nDE EDUCACIÓN, CIENCIA, TECNOLOGÍA E INNOVACIÓN, ROSAURA RUIZ GUTIÉRREZ.- FIRMA.- LA\nSECRETARIA DE INCLUSIÓN Y BIENESTAR SOCIAL, ALMUDENA OCEJO ROJO.- FIRMA.- LA SECRETARIA DE\nLAS MUJERES, INGRID AURORA GÓMEZ SARACÍBAR.- FIRMA.- EL SECRETARIO DE MOVILIDAD, ANDRÉS\nLAJOUS LOAEZA.- FIRMA.- LA SECRETARIA DE SALUD, OLIVA LÓPEZ ARELLANO.- FIRMA.- EL SECRETARIO DE\nSEGURIDAD CIUDADANA, OMAR HAMID GARCÍA HARFUCH.- FIRMA.- LA SECRETARIA DE TRABAJO Y\nFOMENTO AL EMPLEO, HAYDEÉ SOLEDAD ARAGÓN MARTÍNEZ.- FIRMA.- EL CONSEJERO JURÍDICO Y DE\nSERVICIOS LEGALES, NÉSTOR VARGAS SOLANO.- FIRMA.\nTRANSITORIOS DEL DECRETO POR EL QUE SE REFORMAN, EL ARTÍCULO 3; LA FRACCIÓN VII DEL ARTÍCULO\n7; LA FRACCIÓN III DEL ARTÍCULO 8; EL ARTÍCULO 11; EL PRIMER PÁRRAFO DEL ARTÍCULO 15; EL PRIMER\nPÁRRAFO DEL ARTÍCULO 17; EL PRIMER PÁRRAFO DEL ARTÍCULO 18; EL PRIMER PÁRRAFO DEL ARTÍCULO\n\n19; EL PRIMER PÁRRAFO DEL ARTÍCULO 23; LA FRACCIÓN IV DEL ARTÍCULO 24; LA FRACCIÓN IX Y EL\nSEGUNDO PÁRRAFO DE LA FRACCIÓN XII DEL ARTÍCULO 26; LOS ARTÍCULOS 29, 35, 40, 41; EL PRIMER\nPÁRRAFO DEL ARTÍCULO 42; LOS ARTÍCULOS 43, 45; PRIMER PÁRRAFO DEL ARTÍCULO 50 BIS; EL ARTÍCULO\n50 TER; EL ARTÍCULO 50 QUATER, LA FRACCIÓN III DEL ARTÍCULO 57; LOS ARTÍCULOS 58, 60, 61 BIS; EL\nSEGUNDO PÁRRAFO DEL ARTÍCULO 62; LAS FRACCIONES III Y VII DEL ARTÍCULO 63; LAS FRACCIONES II Y\nIII DEL ARTÍCULO 71; SE REFORMA LA DENOMINACIÓN DEL CAPÍTULO VIII CORRESPONDIENTE AL TÍTULO\nCUARTO; SE REFORMA EL ARTÍCULO 73; SE REFORMA LA DENOMINACIÓN DEL TÍTULO SEXTO; Y SE\nREFORMA EL ARTÍCULO 77; TODOS DE LA LEY DE ACCESO DE LAS MUJERES A UNA VIDA LIBRE DE VIOLENCIA\nDE LA CIUDAD DE MÉXICO, PUBLICADO EN LA GACETA OFICIAL DE LA CIUDAD DE MÉXICO EL 23 DE\nNOVIEMBRE DE 2020\nPRIMERO.- Remítase a la Jefatura de Gobierno para su publicación en la Gaceta Oficial de la Ciudad de\nMéxico.\nSEGUNDO.- El presente Decreto entrará en vigor al día siguiente de su publicación en la Gaceta Oficial de la Ciudad de México.\nTERCERO.- La Jefatura de Gobierno contará con un plazo máximo de 120 días hábiles para realizar las reformas reglamentarias necesarias para la aplicación del presente decreto.\nPalacio Legislativo del Congreso de la Ciudad de México, a los diez días del mes de noviembre del año dos mil veinte. POR LA MESA DIRECTIVA.- DIPUTADA MARGARITA SALDAÑA HERNÁNDEZ, PRESIDENTA.-\nDIPUTADA DONAJI OFELIA OLIVERA REYES, SECRETARIA.- DIPUTADO HÉCTOR BARRERA MARMOLEJO,\nSECRETARIO.- (Firmas)\nCon fundamento en lo dispuesto por los artículos 122, apartado A, fracción III, de la Constitución Política de los Estados Unidos Mexicanos; 32 apartado C, numeral 1, inciso a) de la Constitución Política de la\nCiudad de México; 3 fracciones XVII y XVIII, 7 párrafo primero, 10 fracción II, 12 y 21, párrafo primero de la\nLey Orgánica del Poder Ejecutivo y de la Administración Pública de la Ciudad de México, para su debida publicación y observancia, expido el presente Decreto Promulgatorio en la Residencia Oficial de la Jefatura de Gobierno de la Ciudad de México, a los veinte días del mes de noviembre del año dos mil veinte.- LA\nJEFA DE GOBIERNO DE LA CIUDAD DE MÉXICO, DRA. CLAUDIA SHEINBAUM PARDO.- FIRMA.- LA\nSECRETARIA DE INCLUSIÓN Y BIENESTAR SOCIAL, ALMUDENA OCEJO ROJO.- FIRMA.- LA SECRETARIA DE\nLAS MUJERES, INGRID AURORA GÓMEZ SARACÍBAR.- FIRMA.\nTRANSITORIO DEL DECRETO POR EL QUE SE ADICIONA UN ÚLTIMO PÁRRAFO AL ARTÍCULO 49, SE REFORMA\nEL ARTÍCULO 53 Y LA FRACCIÓN V DEL ARTÍCULO 61 TER, TODOS DE LA LEY DE ACCESO DE LAS MUJERES A\n\nUNA VIDA LIBRE DE VIOLENCIA DE LA CIUDAD DE MÉXICO, PUBLICADO EN LA GACETA OFICIAL DE LA\nCIUDAD DE MÉXICO EL DÍA 26 DE FEBRERO DE 2021.\nPRIMERO.- Remítase a la Jefatura de Gobierno para su promulgación y publicación en la Gaceta Oficial de la Ciudad de México.\nSEGUNDO.- El presente decreto entrará en vigor el día siguiente al de su publicación.\nTERCERO.- El Congreso de la Ciudad de México deberá otorgar en el Presupuesto de Egresos de la Ciudad, correspondiente al ejercicio fiscal del año 2022, la suficiencia presupuestal para dar cumplimiento a lo establecido en el tercer párrafo del artículo 53 del presente decreto.\nCUARTO.- A efecto de dar cumplimiento a lo dispuesto en el presente decreto, las personas Titulares de las\n16 Alcaldías de la Ciudad de México, contarán con un plazo que no excederá de 90 días hábiles posteriores a la aprobación del Presupuesto de Egresos de la Ciudad correspondiente al ejercicio fiscal del año 2022, para la instalación progresiva y el debido funcionamiento de sus respectivas casas de emergencia.\nPalacio Legislativo del Congreso de la Ciudad de México, a los once días del mes de febrero del año dos mil veintiuno. POR LA MESA DIRECTIVA.-DIPUTADA MARGARITA SALDAÑA HERNÁNDEZ, PRESIDENTA.-\nDIPUTADA DONAJI OFELIA OLIVERA REYES, SECRETARIA.- DIPUTADO PABLO MONTES DE OCA DEL OLMO,\nSECRETARIO.- (Firmas)\nCon fundamento en lo dispuesto por los artículos 122, apartado A, fracción III de la Constitución Política de los Estados Unidos Mexicanos; 32, apartado C, numeral 1, inciso a) de la Constitución Política de la Ciudad de México; 2 párrafo segundo, 3 fracciones XVII y XVIII, 7 párrafo primero, 10 fracción II, 12 y 21 párrafo primero de la Ley Orgánica del Poder Ejecutivo y de la Administración Pública de la Ciudad de México; para su debida publicación y observancia, expido el presente Decreto Promulgatorio en la Residencia Oficial de la Jefatura de Gobierno de la Ciudad de México, a los veinticinco días del mes de febrero del año dos mil veintiuno.- LA JEFA DE GOBIERNO DE LA CIUDAD DE MÉXICO, DRA. CLAUDIA SHEINBAUM PARDO.- FIRMA.-\n- EL SECRETARIO DE GOBIERNO, JOSÉ ALFONSO SUÁREZ DEL REAL Y AGUILERA.-FIRMA.- LA SECRETARIA DE\nINCLUSIÓN Y BIENESTAR SOCIAL, ALMUDENA OCEJO ROJO.- FIRMA.- LA SECRETARIA DE LAS MUJERES,\nINGRID AURORA GÓMEZ SARACÍBAR.- FIRMA.\nTRANSITORIOS DEL DECRETO POR EL QUE SE MODIFICA EL PRIMER PÁRRAFO DEL ARTÍCULO 26 Y SE\nDEROGAN LAS FRACCIONES XII, XIII Y XIV DE DICHO NUMERAL DE LA LEY ORGÁNICA DEL PODER EJECUTIVO\nY DE LA ADMINISTRACIÓN PÚBLICA DE LA CIUDAD DE MÉXICO. SE MODIFICA LA FRACCIÓN XXVII DEL\nARTÍCULO 3º Y SE ADICIONAN LAS FRACCIONES XXVII BIS, XXVII TER, XXVII QUÁTER Y XXVII QUINQUIES A\n\nDICHO NUMERAL, DE LA LEY ORGÁNICA DE LA SECRETARÍA DE SEGURIDAD CIUDADANA DE LA CIUDAD DE\nMÉXICO. SE MODIFICA LA FRACCIÓN XIV DEL ARTÍCULO 18 Y SE ADICIONAN LAS FRACCIONES XIV BIS Y XIV\nTER A DICHO NUMERAL; SE ADICIONA UN PÁRRAFO AL ARTÍCULO 55, SE DEROGAN LOS ARTÍCULOS 20 Y\n54, Y SE MODIFICA EL ARTÍCULO 119, DE LA LEY DEL SISTEMA DE SEGURIDAD CIUDADANA DE LA CIUDAD\nDE MÉXICO. SE DEROGAN LAS FRACCIONES I, III Y IV DEL ARTÍCULO 15 BIS Y SE ADICIONAN AL ARTÍCULO\n25 LAS FRACCIONES IV BIS, IV TER IV QUÁTER, VI BIS Y VI TER DE LA LEY DE ACCESO DE LAS MUJERES A UNA\nVIDA LIBRE DE VIOLENCIA DE LA CIUDAD DE MÉXICO. SE ABROGA LA LEY DE CENTROS DE RECLUSIÓN PARA\nEL DISTRITO FEDERAL Y SE EXPIDE LA LEY DE CENTROS PENITENCIARIOS DE LA CIUDAD DE MÉXICO,\nPUBLICADO EN LA GACETA OFICIAL DE LA CIUDAD DE MÉXICO EL DÍA 02 DE SEPTIEMBRE DE 2021.\nPRIMERO. Remítase el presente Decreto a la Jefatura de Gobierno para su promulgación y publicación en la Gaceta Oficial de la Ciudad de México.\nSEGUNDO. El presente decreto entrará en vigor el día siguiente al de su publicación en la Gaceta Oficial de la Ciudad de México.\nTERCERO. Se abroga la Ley de Centros de Reclusión para el Distrito Federal, publicado en la Gaceta Oficial de la Ciudad de México el 04 de abril de 2014 y demás disposiciones que contravengan el presente decreto.\nCUARTO. A partir de la entrada en vigor del presente Decreto, las referencias hechas a la Subsecretaría del\nSistema Penitenciario de la Secretaría de Gobierno o a las Unidades Administrativas y/o Unidades\nAdministrativas de Apoyo Técnico-Operativo de su adscripción en otras leyes, reglamentos, decretos, acuerdos y demás disposiciones administrativas, así como en contratos o convenios, respecto de las atribuciones que se transfieren por virtud del presente Decreto, se entenderán realizadas a la Secretaría de\nSeguridad Ciudadana de la Ciudad de México. Misma situación ocurrirá para los órganos colegiados a los que asista la persona titular de la Secretaría de Gobierno de la Ciudad de México en materia de sistema penitenciario, la Secretaría de Seguridad Ciudadana de Ciudad de México designará a su representante.\nQUINTO. El Gobierno de la Ciudad de México contará con 120 días hábiles, contados a partir de la entrada en vigor del presente Decreto, para realizar las adecuaciones a los reglamentos y emitir las disposiciones correspondientes; hasta en tanto, las disposiciones actuales continúan vigentes y podrán ser aplicadas por la Secretaría de Seguridad Ciudadana de la Ciudad de México.\nSEXTO. Los recursos humanos, materiales, técnicos y tecnológicos, así como los bienes muebles e inmuebles asignados a la Secretaría de Gobierno de la Ciudad de México para la Subsecretaría del Sistema\n\nPenitenciario pasarán a formar parte del patrimonio de la Secretaría de Seguridad Ciudadana de la Ciudad de México.\nEn lo relativo a bienes en posesión o servicios contratados por la Secretaría de Gobierno de la Ciudad de\nMéxico para la Subsecretaría del Sistema Penitenciario o por esta última, obtenidos por arrendamiento, comodato o cualquier otro contrato mediante el cual se haya transmitido la posesión o propalado dichos servicios, su utilización corresponderá a la Subsecretaría, en tanto no se determine lo contrario.\nLa Secretaría de Administración y Finanzas de la Ciudad de México coadyuvará con la Secretaría de\nGobierno y la Subsecretaría de Sistema Penitenciario, a efecto de realizar las gestiones y trámites correspondientes para dar cumplimiento cabal al presente artículo, conforme a las disposiciones legales aplicables.\nSÉPTIMO. El personal que en ejecución del presente Decreto deba ser transferido a la Secretaría de\nSeguridad Ciudadana de la Ciudad de México podrá participar en las evaluaciones de control de confianza para su permanencia, sujetándose al régimen administrativo que esta Ley y demás normativa aplicable establecen. La Secretaría de Administración y Finanzas y la Secretaría de Seguridad Ciudadana, ambas de la Ciudad de México, determinarán los procedimientos para la reubicación del personal de base que sea necesario, respetando los derechos laborales adquiridos.\nOCTAVO. La Secretaría de Seguridad Ciudadana de la Ciudad de México deberá adecuar su estructura orgánica y actualizar sus Manuales Administrativos en los plazos y condiciones que establezca la Dirección\nEjecutiva de Dictaminación y Procedimientos Organizacionales de la Secretaría de Administración y\nFinanzas de la Ciudad de México.\nNOVENO. Los asuntos o procedimientos que a la entrada en vigor del presente Decreto se encuentren en trámite y deban ser atendidos por las Unidades Administrativas y/o Unidades Administrativas de Apoyo\nTécnico-Operativo objeto de transferencia, serán resueltos por la dependencia que los recibe, dentro de los plazos establecidos al efecto, a excepción de los trámites urgentes o sujetos a plazo improrrogable.\nDÉCIMO. En tanto se formaliza material, financiera y administrativamente la transferencia a la Secretaría de Seguridad Ciudadana de la Ciudad de México, de los recursos humanos, materiales, técnicos, tecnológicos, financieros y presupuestales de la Subsecretaría de Sistema Penitenciario, la Secretaría de\nGobierno continuará ejerciendo los recursos presupuestales correspondientes a esta área administrativa de conformidad con los techos presupuestales aprobados en el Presupuesto de Egresos de la Ciudad de\nMéxico para el ejercicio fiscal 2021.\n\nDÉCIMO PRIMERO. La Subsecretaría de Sistema Penitenciario deberá actualizar las reglas de operación para potenciar el funcionamiento del patronato al que se refiere el artículo 70 de la Ley de Centros\nPenitenciarios de la Ciudad de México, en un lapso de noventa días naturales contados a partir de la entrada en vigor del presente Decreto.\nDÉCIMO SEGUNDO. La Secretaría de Seguridad Ciudadana deberá establecer las bases para la organización y operación del Servicio Profesional de Carrera de las y los integrantes del Sistema Penitenciario, a que se refiere la Ley de Centros Penitenciarios de la Ciudad de México.\nLos procesos de formación, actualización y especialización de las personas integrantes del Sistema\nPenitenciario se alinearán al Programa de Profesionalización y al Programa Rector de Profesionalización de la Universidad de la Policía de la Ciudad de México.\nEl Instituto de Capacitación Penitenciaria continuará en funciones hasta en tanto se implemente el Servicio\nProfesional de Carrera de las personas integrantes del Sistema Penitenciario.\nPalacio Legislativo del Congreso de la Ciudad de México, a los treinta días del mes de agosto del año dos mil veintiuno.- POR LA MESA DIRECTIVA, DIPUTADA ANA PATRICIA BAEZ GUERRERO, PRESIDENTA,\nDIPUTADA DONAJI OFELIA OLIVERA REYES, SECRETARIA, DIPUTADO PABLO MONTES DE OCA DEL OLMO\n(Firmas)\nCon fundamento en lo dispuesto por los artículos 122, apartado A, fracción III de la Constitución Política de los Estados Unidos Mexicanos; 32, apartado C, numeral 1, inciso a) de la Constitución Política de la Ciudad de México; 2 párrafo segundo, 3 fracciones XVII y XVIII, 7 párrafo primero, 10 fracción II, 12 y 21 párrafo primero de la Ley Orgánica del Poder Ejecutivo y de la Administración Pública de la Ciudad de México; para su debida publicación y observancia, expido el presente Decreto Promulgatorio en la Residencia Oficial de la Jefatura de Gobierno de la Ciudad de México, a los treinta y un días del mes de agosto del año dos mil veintiuno.-LA JEFA DE GOBIERNO DE LA CIUDAD DE MÉXICO, DRA. CLAUDIA SHEINBAUM PARDO.- FIRMA.-\nEL SECRETARIO DE GOBIERNO, MARTÍ BATRES GUADARRAMA.- FIRMA.- LA SECRETARIA DE\nADMINISTRACIÓN Y FINANZAS, LUZ ELENA GONZÁLEZ ESCOBAR.- FIRMA.- LA SECRETARIA DE GESTIÓN\nINTEGRAL DE RIESGOS Y PROTECCIÓN CIVIL, MYRIAM VILMA URZÚA VENEGAS. - FIRMA.- LA SECRETARIA DE\nINCLUSIÓN Y BIENESTAR SOCIAL, ALMUDENA OCEJO ROJO.- FIRMA.- LA SECRETARIA DE LAS MUJERES,\nINGRID GÓMEZ SARACÍBAR.- FIRMA.- LA SECRETARIA DE SALUD, OLIVA LÓPEZ ARELLANO.- FIRMA.- EL\nSECRETARIO DE SEGURIDAD CIUDADANA, OMAR HAMID GARCÍA HARFUCH.- FIRMA\nTRANSITORIOS DEL DECRETO POR EL QUE SE MODIFICAN LOS ARTÍCULOS 62, PÁRRAFO PRIMERO, Y 62 BIS,\nFRACCIÓN V, Y SE ADICIONA UNA FRACCIÓN XV BIS AL ARTÍCULO 3; UNA FRACCIÓN I BIS Y UN PÁRRAFO\n\nSEGUNDO A LA FRACCIÓN V AL ARTÍCULO 62 BIS, ASÍ́ COMO UN ARTÍCULO 62 TER; TODOS DE LA LEY DE\nACCESO DE LAS MUJERES A UNA VIDA LIBRE DE VIOLENCIA DE LA CIUDAD DE MÉXICO, PUBLICADO EN LA\nGACETA OFICIAL DE LA CIUDAD DE MÉXICO EL DÍA 23 DE MARZO DE 2022.\nPRIMERO. Remítase a la persona titular de la Jefatura de Gobierno, para su promulgación y publicación en la Gaceta Oficial de la Ciudad de México.\nSEGUNDO. El presente Decreto entrará en vigor el día siguiente al de su publicación en la Gaceta Oficial de la Ciudad de México.\nPalacio Legislativo del Congreso de la Ciudad de México, a los quince días del mes de marzo del año dos mil veintidós. POR LA MESA DIRECTIVA, DIPUTADO HÉCTOR DIAZ POLANCO, PRESIDENTE.- DIPUTADA\nMARCELA FUENTE CASTILLO, SECRETARIA.- DIPUTADA FRIDA JIMENA GUILLÉN ORTIZ, SECRETARIA.- (Firmas)\nCon fundamento en lo dispuesto por los artículos 122, apartado A, fracción III de la Constitución Política de los Estados Unidos Mexicanos; 32, apartado C, numeral 1, inciso a) de la Constitución Política de la Ciudad de México; 2 párrafo segundo, 3 fracciones XVII y XVIII, 7 párrafo primero, 10 fracción II, 12 y 21 párrafo primero de la Ley Orgánica del Poder Ejecutivo y de la Administración Pública de la Ciudad de México; para su debida publicación y observancia, expido el presente Decreto Promulgatorio en la Residencia Oficial de la Jefatura de Gobierno de la Ciudad de México, a los veintidós días del mes de marzo del año dos mil veintidós.- LA JEFA DE GOBIERNO DE LA CIUDAD DE MÉXICO, DRA. CLAUDIA SHEINBAUM PARDO.- FIRMA.-\nEL SECRETARIO DE GOBIERNO, MARTÍ BATRES GUADARRAMA.- FIRMA.- LA SECRETARIA DE LAS MUJERES,\nINGRID GÓMEZ SARACÍBAR.- FIRMA.\nTRANSITORIOS DEL DECRETO POR EL QUE SE REFORMAN FRACCIONES I, II, III, IV, V, VI, VII Y VIII DEL\nARTÍCULO 6, LAS FRACCIONES I, II, III, IV, V, VI, VII, VIII, IX Y X DEL ARTÍCULO 7, EL PRIMER PÁRRAFO Y LAS\nFRACCIONES I Y III DEL ARTÍCULO 8, EL PRIMER PÁRRAFO Y LAS FRACCIONES I, II Y IV DEL ARTÍCULO 9, EL\nPRIMER PÁRRAFO Y LAS FRACCIONES I, II Y III DEL ARTÍCULO 10, EL PRIMER PÁRRAFO DEL ARTÍCULO 13, EL\nSEGUNDO PÁRRAFO DE LA FRACCIÓN II DEL ARTÍCULO 15, LA FRACCIÓN XII DEL ARTÍCULO 19, EL PRIMER\nPÁRRAFO DEL ARTÍCULO 64, EL ARTÍCULO 65, 66 Y 70; Y SE ADICIONA UN PARRAFO SEGUNDO AL ARTICULO\n7; UNA FRACCIÓN II BIS AL ARTÍCULO 10, UN SEGUNDO PÁRRAFO AL ARTÍCULO 13 RECORRIÉNDOSE LOS\nSUBSECUENTES, UNA FRACCIÓN XI BIS AL ARTÍCULO 19, UN SEGUNDO PÁRRAFO AL ARTÍCULO 49\nRECORRIÉNDOSE LOS SUBSECUENTES Y SE ADICIONA UN ARTÍCULO 69 BIS, TODOS DE LA DE LA LEY DE\nACCESO DE LAS MUJERES A UNA VIDA LIBRE DE VIOLENCIA DE LA CIUDAD DE MÉXICO, PUBLICADO EN LA\nGACETA OFICIAL DE LA CIUDAD DE MÉXICO, EL 10 DE JUNIO DE 2022.\n\nPRIMERO. Remítase a la persona titular de la Jefatura de Gobierno, para su promulgación y publicación en la Gaceta Oficial de la Ciudad de México.\nSEGUNDO. El presente Decreto entrará en vigor el día siguiente al de su publicación en la Gaceta Oficial de la Ciudad de México.\nTERCERO. A efecto de dar cumplimiento a lo dispuesto en el presente decreto, la persona titular de la\nJefatura de Gobierno contará con un plazo de 60 días hábiles a partir de su entrada en vigor, para armonizar el contenido del Reglamento de la presente Ley.\nPalacio Legislativo del Congreso de la Ciudad de México, a los treinta días del mes de mayo del año dos mil veintidós. POR LA MESA DIRECTIVA, DIPUTADO HÉCTOR DIAZ POLANCO, PRESIDENTE. - DIPUTADA\nMARCELA FUENTE CASTILLO, SECRETARIA. - DIPUTADA FRIDA JIMENA GUILLÉN ORTIZ, SECRETARIA. -\n(Firmas)\nCon fundamento en lo dispuesto por los artículos 122, apartado A, fracción III de la Constitución Política de los Estados Unidos Mexicanos; 32, apartado C, numeral 1, inciso a) de la Constitución Política de la Ciudad de México; 2 párrafo segundo, 3 fracciones XVII y XVIII, 7 párrafo primero, 10 fracción II, 12 y 21 párrafo primero de la Ley Orgánica del Poder Ejecutivo y de la Administración Pública de la Ciudad de México; para su debida publicación y observancia, expido el presente Decreto Promulgatorio en la Residencia Oficial de la Jefatura de Gobierno de la Ciudad de México, a los nueve días del mes de junio del año dos mil veintidós.- LA JEFA DE GOBIERNO DE LA CIUDAD DE MÉXICO, DRA. CLAUDIA SHEINBAUM PARDO.- FIRMA.-\nEL SECRETARIO DE GOBIERNO, MARTÍ BATRES GUADARRAMA.- FIRMA.- LA SECRETARIA DE LAS MUJERES,\nINGRID GÓMEZ SARACÍBAR.- FIRMA.\nTRANSITORIOS DEL DECRETO POR EL QUE SE MODIFICA EL TERCER PÁRRAFO DEL ARTÍCULO 49, Y EL TERCER\nPÁRRAFO DEL ARTÍCULO 53, DE LA LEY DE ACCESO DE LAS MUJERES A UNA VIDA LIBRE DE VIOLENCIA DE\nLA CIUDAD DE MÉXICO, PUBLICADO EN LA GACETA OFICIAL DE LA CIUDAD DE MÉXICO, EL 30 DE\nNOVIEMBRE DE 2022.\nPRIMERO. Remítase a la persona titular de la Jefatura de Gobierno, para su promulgación y publicación en la Gaceta Oficial de la Ciudad de México.\nSEGUNDO. El presente Decreto entrará en vigor el día siguiente al de su publicación en la Gaceta Oficial de la Ciudad de México.\n\nPalacio Legislativo del Congreso de la Ciudad de México, a los diez días del mes de noviembre del año dos mil veintidós.- POR LA MESA DIRECTIVA.- DIPUTADO GERARDO VILLANUEVA ALBARRÁN, PRESIDENTE.-\nDIPUTADA MARCELA FUENTE CASTILLO, SECRETARIA.- DIPUTADA MARIA GABRIELA SALIDO MAGOS,\nSECRETARIA.- (Firmas)\nCon fundamento en lo dispuesto por los artículos 122, apartado A, fracción III de la Constitución Política de los Estados Unidos Mexicanos; 32, apartado C, numeral 1, inciso a) de la Constitución Política de la Ciudad de México; 2 párrafo segundo, 3 fracciones XVII y XVIII, 7 párrafo primero, 10 fracción II, 12 y 21 párrafo primero de la Ley Orgánica del Poder Ejecutivo y de la Administración Pública de la Ciudad de México; para su debida publicación y observancia, expido el presente Decreto Promulgatorio en la Residencia Oficial de la Jefatura de Gobierno de la Ciudad de México, a los veintinueve días del mes de noviembre del año dos mil veintidós.- LA JEFA DE GOBIERNO DE LA CIUDAD DE MÉXICO, DRA. CLAUDIA SHEINBAUM PARDO.-\nFIRMA.- EL SECRETARIO DE GOBIERNO, MARTÍ BATRES GUADARRAMA.- FIRMA.- LA SECRETARIA DE LAS\nMUJERES, INGRID GÓMEZ SARACÍBAR.- FIRMA.\nTRANSITORIOS DEL DECRETO POR EL QUE SE MODIFICA LA FRACCIÓN VI DEL ARTÍCULO 5, LA FRACCIÓN I\nDEL ARTÍCULO 7, SE ADICIONA UN SEGUNDO PÁRRAFO RECORRIÉNDOSE LOS SUBSECUENTES AL ARTÍCULO\n13 TODOS DE LA LEY DE ACCESO DE LAS MUJERES A UNA VIDA LIBRE DE VIOLENCIA DE LA CIUDAD DE\nMÉXICO, PUBLICADO EN LA GACETA OFICIAL DE LA CIUDAD DE MÉXICO, EL 30 DE NOVIEMBRE DE 2022.\nPRIMERO. Remítase a la persona titular de la Jefatura de Gobierno, para su promulgación y publicación en la Gaceta Oficial de la Ciudad de México.\nSEGUNDO. El presente Decreto entrará en vigor el día siguiente al de su publicación en la Gaceta Oficial de la Ciudad de México.\nTERCERO. A partir de la entrada en vigor del presente decreto las autoridades competentes tendrán 120 días naturales para realizar las adecuaciones reglamentarias correspondientes\nPalacio Legislativo del Congreso de la Ciudad de México, a los diez días del mes de noviembre del año dos mil veintidós.- POR LA MESA DIRECTIVA.- DIPUTADO GERARDO VILLANUEVA ALBARRÁN, PRESIDENTE.-\nDIPUTADA MARCELA FUENTE CASTILLO, SECRETARIA.- DIPUTADA MARIA GABRIELA SALIDO MAGOS,\nSECRETARIA.- (Firmas)\nCon fundamento en lo dispuesto por los artículos 122, apartado A, fracción III de la Constitución Política de los Estados Unidos Mexicanos; 32, apartado C, numeral 1, inciso a) de la Constitución Política de la Ciudad\n\nde México; 2 párrafo segundo, 3 fracciones XVII y XVIII, 7 párrafo primero, 10 fracción II, 12 y 21 párrafo primero de la Ley Orgánica del Poder Ejecutivo y de la Administración Pública de la Ciudad de México; para su debida publicación y observancia, expido el presente Decreto Promulgatorio en la Residencia Oficial de la Jefatura de Gobierno de la Ciudad de México, a los veintinueve días del mes de noviembre del año dos mil veintidós.- LA JEFA DE GOBIERNO DE LA CIUDAD DE MÉXICO, DRA. CLAUDIA SHEINBAUM PARDO.-\nFIRMA.- EL SECRETARIO DE GOBIERNO, MARTÍ BATRES GUADARRAMA.- FIRMA.-- LA SECRETARIA DE\nEDUCACIÓN, CIENCIA, TECNOLOGÍA E INNOVACIÓN, ROSAURA RUIZ GUTIÉRREZ.- FIRMA.- EL ENCARGADO\nDE DESPACHO DE LA SECRETARÍA DE INCLUSIÓN Y BIENESTAR SOCIAL, RIGOBERTO SALGADO VÁZQUEZ.-\nFIRMA.- LA SECRETARIA DE LAS MUJERES, INGRID GÓMEZ SARACÍBAR.- FIRMA.\nTRANSITORIOS DEL DECRETO POR EL QUE SE ADICIONA LA FRACCIÓN X AL ARTÍCULO 6 DE LA LEY DE\nACCESO DE LAS MUJERES A UNA VIDA LIBRE DE VIOLENCIA DE LA CIUDAD DE MÉXICO, PUBLICADO EN LA\nGACETA OFICIAL DE LA CIUDAD DE MÉXICO, EL 12 DE DICIEMBRE DE 2022.\nPRIMERO. Remítase a la persona titular de la Jefatura de Gobierno, para su promulgación y publicación en la Gaceta Oficial de la Ciudad de México.\nSEGUNDO. El presente Decreto entrará en vigor el día siguiente al de su publicación en la Gaceta Oficial de la Ciudad de México.\nPalacio Legislativo del Congreso de la Ciudad de México, a los veintinueve días del mes de noviembre del año dos mil veintidós.- POR LA MESA DIRECTIVA.- DIPUTADO FAUSTO MANUEL ZAMORANO ESPARZA,\nPRESIDENTE.- DIPUTADA MARCELA FUENTE CASTILLO, SECRETARIA.- DIPUTADA MARIA GABRIELA SALIDO\nMAGOS, SECRETARIA.- (Firmas)\nCon fundamento en lo dispuesto por los artículos 122, apartado A, fracción III de la Constitución Política de los Estados Unidos Mexicanos; 32, apartado C, numeral 1, inciso a) de la Constitución Política de la Ciudad de México; 2 párrafo segundo, 3 fracciones XVII y XVIII, 7 párrafo primero, 10 fracción II, 12 y 21 párrafo primero de la Ley Orgánica del Poder Ejecutivo y de la Administración Pública de la Ciudad de México; para su debida publicación y observancia, expido el presente Decreto Promulgatorio en la Residencia Oficial de la Jefatura de Gobierno de la Ciudad de México, a los nueve días del mes de diciembre del año dos mil veintidós.- LA JEFA DE GOBIERNO DE LA CIUDAD DE MÉXICO, DRA. CLAUDIA SHEINBAUM PARDO.- FIRMA.-\nEL SECRETARIO DE GOBIERNO, MARTÍ BATRES GUADARRAMA.- FIRMA.- EL SECRETARIO DE INCLUSIÓN Y\nBIENESTAR SOCIAL, RIGOBERTO SALGADO VÁZQUEZ.- FIRMA.- LA SECRETARIA DE LAS MUJERES, INGRID\nGÓMEZ SARACÍBAR.- FIRMA\n\nTRANSITORIOS DEL DECRETO POR EL QUE SE REFORMAN, MODIFICAN Y ADICIONAN DIVERSAS\nDISPOSICIONES A LA LEY DE SALUD DE LA CIUDAD DE MÉXICO, LA LEY DE DERECHOS DE LOS PUEBLOS Y\nBARRIOS ORIGINARIOS Y COMUNIDADES INDÍGENAS RESIDENTES EN LA CIUDAD DE MÉXICO Y LEY DE\nACCESO DE LAS MUJERES A UNA VIDA LIBRE DE VIOLENCIA DE LA CIUDAD DE MÉXICO PARA PREVENIR LA\nVIOLENCIA OBSTÉTRICA A LAS MUJERES INDÍGENAS, PUBLICADO EN LA GACETA OFICIAL DE LA CIUDAD DE\nMÉXICO, EL 22 DE DICIEMBRE DE 2022.\nPRIMERO. - Remítase a la Jefatura de Gobierno de la Ciudad de México y en consecuencia sea publicado en la Gaceta Oficial de la Ciudad de México.\nSEGUNDO. - El presente Decreto entrará en vigor a partir del siguiente día de su publicación en la Gaceta\nOficial del Gobierno de la Ciudad de México.\nPalacio Legislativo del Congreso de la Ciudad de México, a los catorce días del mes de diciembre del año dos mil veintidós. POR LA MESA DIRECTIVA.- DIPUTADO FAUSTO MANUEL ZAMORANO ESPARZA,\nPRESIDENTE.- DIPUTADA MARCELA FUENTE CASTILLO, SECRETARIA.- DIPUTADA MARIA GABRIELA SALIDO\nMAGOS, SECRETARIA.- (Firmas)\nCon fundamento en lo dispuesto por los artículos 122, apartado A, fracción III de la Constitución Política de los Estados Unidos Mexicanos; 32, apartado C, numeral 1, inciso a) de la Constitución Política de la Ciudad de México; 2 párrafo segundo, 3 fracciones XVII y XVIII, 7 párrafo primero, 10 fracción II, 12 y 21 párrafo primero de la Ley Orgánica del Poder Ejecutivo y de la Administración Pública de la Ciudad de México; para su debida publicación y observancia, expido el presente Decreto Promulgatorio en la Residencia Oficial de la Jefatura de Gobierno de la Ciudad de México, a los veintidós días del mes de diciembre del año dos mil veintidós.- LA JEFA DE GOBIERNO DE LA CIUDAD DE MÉXICO, DRA. CLAUDIA SHEINBAUM PARDO.- FIRMA.-\nEL SECRETARIO DE GOBIERNO, MARTÍ BATRES GUADARRAMA.- FIRMA.- LA SECRETARIA DE ADMINISTRACIÓN\nY FINANZAS, LUZ ELENA GONZÁLEZ ESCOBAR.- FIRMA.- EL SECRETARIO DE LA CONTRALORÍA GENERAL, JUAN\nJOSÉ SERRANO MENDOZA.- FIRMA.- LA SECRETARIA DE CULTURA, CLAUDIA STELLA CURIEL DE ICAZA.-\nFIRMA.- EL SECRETARIO DE DESARROLLO ECONÓMICO, FADLALA AKABANI HNEIDE.- FIRMA.- EL SECRETARIO\nDE DESARROLLO URBANO Y VIVIENDA, CARLOS ALBERTO ULLOA PÉREZ.- FIRMA.- LA SECRETARIA DE\nEDUCACIÓN, CIENCIA, TECNOLOGÍA E INNOVACIÓN, ROSAURA RUIZ GUTIÉRREZ.- FIRMA.- LA SECRETARIA DE\nGESTIÓN INTEGRAL DE RIESGOS Y PROTECCIÓN CIVIL, MYRIAM VILMA URZÚA VENEGAS.- FIRMA.- EL\nSECRETARIO DE INCLUSIÓN Y BIENESTAR SOCIAL, RIGOBERTO SALGADO VÁZQUEZ.- FIRMA.- LA SECRETARIA\nDEL MEDIO AMBIENTE, MARINA ROBLES GARCÍA.- FIRMA.- EL SECRETARIO DE MOVILIDAD, ANDRÉS LAJOUS\nLOAEZA.- FIRMA.- LA SECRETARIA DE LAS MUJERES, INGRID GÓMEZ SARACÍBAR.- FIRMA.- EL SECRETARIO DE\nOBRAS Y SERVICIOS, JESÚS ANTONIO ESTEVA MEDINA.- FIRMA.- LA SECRETARIA DE PUEBLOS Y BARRIOS\n\nORIGINARIOS Y COMUNIDADES INDÍGENAS RESIDENTES, LAURA ITA ANDEHUI RUIZ MONDRAGÓN.- FIRMA.-\nLA SECRETARIA DE SALUD, OLIVA LÓPEZ ARELLANO.- FIRMA.- EL SECRETARIO DE SEGURIDAD CIUDADANA,\nOMAR HAMID GARCÍA HARFUCH.- FIRMA.- EL SECRETARIO DE TRABAJO Y FOMENTO AL EMPLEO, JOSÉ LUIS\nRODRÍGUEZ DÍAZ DE LEÓN.- FIRMA.- LA SECRETARÍA DE TURISMO, NATHALIE VERONIQUE DESPLAS PUEL.-\nFIRMA.- EL CONSEJERO JURÍDICO Y DE SERVICIOS LEGALES, NÉSTOR VARGAS SOLANO.- FIRMA.\nTRANSITORIOS DEL DECRETO POR EL QUE SE MODIFICA LA FRACCIÓN IX DEL ARTÍCULO 6, EL PRIMER\nPÁRRAFO DE LA FRACCIÓN VIII DEL ARTÍCULO 7; SE ADICIONA UNA FRACCIÓN I BIS AL ARTÍCULO 3 Y UN\nPÁRRAFO SEGUNDO A LA FRACCIÓN VIII DEL ARTÍCULO 7, DE LA LEY DE ACCESO DE LAS MUJERES A UNA\nVIDA LIBRE DE VIOLENCIA DE LA CIUDAD DE MÉXICO, PUBLICADO EN LA GACETA OFICIAL DE LA CIUDAD DE\nMÉXICO, EL 06 DE OCTUBRE DE 2023.\nPRIMERO. Remítase el presente decreto a la persona titular de la Jefatura de Gobierno para su promulgación y publicación en la Gaceta Oficial de la Ciudad de México.\nSEGUNDO. El presente decreto entrará en vigor el día siguiente al de su publicación en la Gaceta Oficial de la Ciudad de México.\nPalacio Legislativo del Congreso de la Ciudad de México, a los cinco días del mes de septiembre del año dos mil veintitrés.- POR LA MESA DIRECTIVA.- DIPUTADA MARIA GABRIELA SALIDO MAGOS, PRESIDENTA.-\nDIPUTADA MARCELA FUENTE CASTILLO, SECRETARIA.- DIPUTADA ANA JOCELYN VILLAGRÁN VILLASANA,\nSECRETARIA.- (Firmas)\nCon fundamento en lo dispuesto por los artículos 122, apartado A, base III, de la Constitución Política de los Estados Unidos Mexicanos; 32, apartado C, numeral 1, inciso a), de la Constitución Política de la Ciudad de México; 2, párrafo segundo, 3, fracciones XVII y XVIII, 7, párrafo primero, 10, fracción II, 12 y 21, párrafo primero, de la Ley Orgánica del Poder Ejecutivo y de la Administración Pública de la Ciudad de México;\npara su debida publicación y observancia, expido el presente Decreto Promulgatorio en la Residencia\nOficial de la Jefatura de Gobierno de la Ciudad de México, a los 5 días del mes de octubre del año dos mil veintitrés. EL JEFE DE GOBIERNO DE LA CIUDAD DE MÉXICO, MTRO. MARTÍ BATRES GUADARRAMA.- FIRMA.-\nEL SECRETARIO DE GOBIERNO, RICARDO RUIZ SUÁREZ.- FIRMA.- EL SECRETARIO DE INCLUSIÓN Y BIENESTAR\nSOCIAL, RIGOBERTO SALGADO VÁZQUEZ.- FIRMA.- LA SECRETARIA DE LAS MUJERES, INGRID AURORA\nGÓMEZ SARACÍBAR.- FIRMA.\nTRANSITORIOS DEL DECRETO POR EL QUE SE ADICIONA UNA FRACCIÓN XX BIS AL ARTÍCULO 3, UNA\n\nFRACCIÓN I BIS AL ARTÍCULO 24, UNA FRACCIÓN V BIS AL ARTÍCULO 25, UN PÁRRAFO TERCERO AL ARTÍCULO\n53 RECORRIÉNDOSE EN SU ORDEN LOS SUBSECUENTES; Y SE MODIFICA LA FRACCIÓN III DEL ARTÍCULO 5,\nLA FRACCIÓN VI DEL ARTÍCULO 7, LAS FRACCIONES I Y IV DEL ARTÍCULO 24, LA FRACCIÓN II DEL ARTÍCULO\n25, Y EL PÁRRAFO TERCERO DEL ARTÍCULO 53, TODOS DE LA LEY DE ACCESO DE LAS MUJERES A UNA VIDA\nLIBRE DE VIOLENCIA DE LA CIUDAD DE MÉXICO, PUBLICADO EN LA GACETA OFICIAL DE LA CIUDAD DE\nMÉXICO, EL 10 DE OCTUBRE DE 2023.\nPRIMERO. Remítase a la persona titular de la Jefatura de Gobierno, para su promulgación y publicación en la Gaceta Oficial de la Ciudad de México.\nSEGUNDO. El presente Decreto entrará en vigor el día siguiente al de su publicación en la Gaceta Oficial de la Ciudad de México.\nPalacio Legislativo del Congreso de la Ciudad de México, a los cinco días del mes de septiembre del año dos mil veintitrés.- POR LA MESA DIRECTIVA.- DIPUTADA MARÍA GABRIELA SALIDO MAGOS, PRESIDENTA.-\nDIPUTADA MARCELA FUENTE CASTILLO, SECRETARIA.- DIPUTADA ANA JOCELYN VILLAGRÁN VILLASANA,\nSECRETARIA.- (Firmas)\nCon fundamento en lo dispuesto por los artículos 122, apartado A, base III, de la Constitución Política de los Estados Unidos Mexicanos; 32, apartado C, numeral 1, inciso a), de la Constitución Política de la Ciudad de México; 2, párrafo segundo, 3, fracciones XVII y XVIII, 7, párrafo primero, 10, fracción II, 12 y 21, párrafo primero, de la Ley Orgánica del Poder Ejecutivo y de la Administración Pública de la Ciudad de México;\npara su debida publicación y observancia, expido el presente Decreto Promulgatorio en la Residencia\nOficial de la Jefatura de Gobierno de la Ciudad de México, a los nueve días del mes de octubre del año dos mil veintitrés.- EL JEFE DE GOBIERNO DE LA CIUDAD DE MÉXICO, MTRO. MARTÍ BATRES GUADARRAMA.-\nFIRMA.- EL SECRETARIO DE GOBIERNO, RICARDO RUIZ SUÁREZ.- FIRMA.- EL SECRETARIO DE INCLUSIÓN Y\nBIENESTAR SOCIAL, RIGOBERTO SALGADO VÁZQUEZ.- FIRMA.- LA SECRETARIA DE LAS MUJERES, INGRID\nAURORA GÓMEZ SARACÍBAR.- EL SECRETARIO DE SEGURIDAD CIUDADANA, PABLO VÁZQUEZ CAMACHO.-\nFIRMA.\nTRANSITORIOS DEL DECRETO POR EL QUE SE ADICIONA LA FRACCIÓN V BIS AL ARTÍCULO 36, LA FRACCIÓN\nVI Y UN SEGUNDO PÁRRAFO AL ARTÍCULO 71; SE MODIFICA LA FRACCIÓN I DEL ARTÍCULO 15, LA FRACCIÓN\nI DEL ARTÍCULO 19, Y LA FRACCIÓN V DEL ARTÍCULO 71, TODAS DE LA LEY DE ACCESO DE LAS MUJERES A\nUNA VIDA LIBRE DE VIOLENCIA DE LA CIUDAD DE MÉXICO, PUBLICADO EN LA GACETA OFICIAL DE LA CIUDAD\nDE MÉXICO, EL 10 DE OCTUBRE DE 2023.\n\nPRIMERO. Remítase a la persona titular de la Jefatura de Gobierno de la Ciudad de México para su promulgación y publicación en la Gaceta Oficial de la Ciudad de México, y\nSEGUNDO. El presente Decreto entrará en vigor el día siguiente al de su publicación en la Gaceta Oficial de la Ciudad de México.\nPalacio Legislativo del Congreso de la Ciudad de México, a los cinco días del mes de septiembre del año dos mil veintitrés.- POR LA MESA DIRECTIVA.- DIPUTADA MARÍA GABRIELA SALIDO MAGOS, PRESIDENTA.-\nDIPUTADA MARCELA FUENTE CASTILLO, SECRETARIA.- DIPUTADA ANA JOCELYN VILLAGRÁN VILLASANA,\nSECRETARIA.- (Firmas)\nCon fundamento en lo dispuesto por los artículos 122, apartado A, base III, de la Constitución Política de los Estados Unidos Mexicanos; 32, apartado C, numeral 1, inciso a), de la Constitución Política de la Ciudad de México; 2, párrafo segundo, 3, fracciones XVII y XVIII, 7, párrafo primero, 10, fracción II, 12 y 21, párrafo primero, de la Ley Orgánica del Poder Ejecutivo y de la Administración Pública de la Ciudad de México;\npara su debida publicación y observancia, expido el presente Decreto Promulgatorio en la Residencia\nOficial de la Jefatura de Gobierno de la Ciudad de México, a los nueve días del mes de octubre del año dos mil veintitrés.- EL JEFE DE GOBIERNO DE LA CIUDAD DE MÉXICO, MTRO. MARTÍ BATRES GUADARRAMA.-\nFIRMA.- EL SECRETARIO DE GOBIERNO, RICARDO RUIZ SUÁREZ.- FIRMA LA SECRETARIA DE ADMINISTRACIÓN\nY FIANZAS, LUZ ELENA GONZÁLEZ ESCOBAR.- FIRMA.- LA SECRETARIA DE EDUCACIÓN, CIENCIA, TECNOLOGÍA\nE INNOVACIÓN, JESÚS OFELIA ANGULO GUERRERO.- FIRMA.- EL SECRETARIO DE INCLUSIÓN Y BIENESTAR\nSOCIAL, RIGOBERTO SALGADO VÁZQUEZ.- FIRMA.- LA SECRETARIA DE LAS MUJERES, INGRID AURORA\nGÓMEZ SARACÍBAR.- FIRMA.- LA SECRETARIA DE SALUD, OLIVA LÓPEZ ARELLANO.- FIRMA.\nTRANSITORIOS DEL DECRETO POR EL QUE SE REFORMA LA FRACCIÓN II DEL ARTÍCULO 6 Y LA FRACCIÓN V\nDEL ARTÍCULO 36, Y SE ADICIONA LA FRACCIÓN XI AL ARTÍCULO 6 Y LA FRACCIÓN V TER AL ARTÍCULO 36, DE\nLA LEY DE ACCESO DE LAS MUJERES A UNA VIDA LIBRE DE VIOLENCIA DE LA CIUDAD DE MÉXICO Y SE\nDEROGA LA FRACCIÓN V DEL ARTÍCULO 131; SE REFORMA LA FRACCIÓN II DEL 148 BIS; SE ADICIONA UN\nCAPÍTULO II BIS, LESIONES POR ATAQUES CON ÁCIDO, SUSTANCIAS QUÍMICAS O CORROSIVAS, AL TÍTULO\nPRIMERO, DELITOS CONTRA LA VIDA, LA INTEGRIDAD CORPORAL, LA DIGNIDAD Y EL ACCESO A UNA VIDA\nLIBRE DE VIOLENCIA, DEL LIBRO SEGUNDO PARTE ESPECIAL, Y LOS ARTÍCULOS 135 BIS, 135 TER, 135\nQUÁTER Y 135 QUINQUIES, DEL CÓDIGO PENAL PARA EL DISTRITO FEDERAL, PÚBLICADO EN LA GACETA\nOFICIAL DE LA CIUDAD DE MÉXICO EL 9 DE FEBRERO DE 2024.\nPRIMERO. Remítase a la persona titular de la Jefatura de Gobierno, para su promulgación y publicación en la Gaceta Oficial de la Ciudad de México.\n\nSEGUNDO. El presente Decreto entrará en vigor el día siguiente al de su publicación en la Gaceta Oficial de la Ciudad de México.\nTERCERO. La Secretaría de Salud contará con un lapso no mayor a 90 días naturales a la entrada en vigor del presente Decreto para coordinarse con las autoridades correspondientes a efecto de llevar un registro y remitir información y estadísticas sobre las personas atendidas en caso de violencia por ataques con ácido, sustancias químicas o corrosivas.\nCUARTO. La Secretaría de las Mujeres en coordinación con la Secretaría de Seguridad Ciudadana, la Fiscalía\nGeneral de Justicia de la Ciudad de México, la Secretaría de Inclusión y Bienestar Social de la Ciudad de\nMéxico, la Comisión Ejecutiva de Atención a Víctimas de la Ciudad de México, la Comisión de Derechos\nHumanos de la Ciudad de México, el Consejo para Prevenir y Erradicar la Discriminación de la Ciudad de\nMéxico, el Sistema Integral para el Desarrollo de la Familia de la Ciudad de México y la Secretaría de Salud de la Ciudad de México, formulará en un lapso de seis meses a la entrada en vigor del presente Decreto, una política pública de atención integral a las víctimas de violencia por ataques con ácido, sustancias químicas o corrosivas.\nPalacio Legislativo del Congreso de la Ciudad de México, a los ocho días del mes de febrero del año dos mil veinticuatro.- POR LA MESA DIRECTIVA.- DIPUTADA MARÍA GABRIELA SALIDO MAGOS, PRESIDENTA.-\nDIPUTADA MARCELA FUENTE CASTILLO, SECRETARIA.- DIPUTADA ANA JOCELYN VILLAGRÁN VILLASANA,\nSECRETARIA.- (Firmas)\nCon fundamento en lo dispuesto por los artículos 122, apartado A, base III, de la Constitución Política de los Estados Unidos Mexicanos; 32, apartado C, numeral 1, inciso a), de la Constitución Política de la Ciudad de México; 2, párrafo segundo, 3, fracciones XVII y XVIII, 7, párrafo primero, 10, fracción II, 12 y 21, párrafo primero, de la Ley Orgánica del Poder Ejecutivo y de la Administración Pública de la Ciudad de México;\npara su debida publicación y observancia, expido el presente Decreto Promulgatorio en la Residencia\nOficial de la Jefatura de Gobierno de la Ciudad de México, a los quince días del mes de febrero del año dos mil veinticuatro.- EL JEFE DE GOBIERNO DE LA CIUDAD DE MÉXICO, DR. MARTÍ BATRES GUADARRAMA.-\nFIRMA.- EL SECRETARIO DE GOBIERNO, RICARDO RUIZ SUÁREZ.- FIRMA.-EL SECRETARIO DE INCLUSIÓN Y\nBIENESTAR SOCIAL, RIGOBERTO SALGADO VÁZQUEZ.- FIRMA.- LA SECRETARIA DE LAS MUJERES, INGRID\nAURORA GÓMEZ SARACÍBAR.- FIRMA.- LA SECRETARIA DE SALUD, OLIVA LÓPEZ ARELLANO.- FIRMA.- EL\nSECRETARIO DE SEGURIDAD CIUDADANA, PABLO VÁZQUEZ CAMACHO.- FIRMA.\n\nTRANSITORIOS DEL DECRETO POR EL QUE SE REFORMA LA FRACCIÓN VI DEL ARTÍCULO 6, LA FRACCIÓN III\nDEL ARTÍCULO 18, LA FRACCIÓN VII DEL ARTÍCULO 19, LA FRACCIÓN V DEL ARTÍCULO 20, LA FRACCIÓN VI\nDEL ARTÍCULO 24, LA FRACCIÓN VI TER DEL ARTÍCULO 25, LA FRACCIÓN VIII DEL ARTÍCULO 52; SE ADICIONA\nUNA FRACCIÓN XIII BIS AL ARTÍCULO 16, UNA FRACCIÓN II BIS DEL ARTÍCULO 17, UN PÁRRAFO SEGUNDO\nA LA FRACCIÓN V DEL ARTÍCULO 20, LA FRACCIÓN VI BIS DEL ARTÍCULO 24, LA FRACCIÓN VI QUÁTER AL\nARTÍCULO 25, LA FRACCIÓN VIII BIS AL ARTÍCULO 52, DE LA LEY DE ACCESO DE LAS MUJERES A UNA VIDA\nLIBRE DE VIOLENCIA DE LA CIUDAD DE MÉXICO, PÚBLICADO EN LA GACETA OFICIAL DE LA CIUDAD DE\nMÉXICO EL 27 DE MARZO DE 2024.\nPRIMERO. Remítase a la persona titular de la Jefatura de Gobierno de la Ciudad de México para su promulgación y publicación en la Gaceta Oficial de la Ciudad de México.\nSEGUNDO. El presente Decreto entrará en vigor el día siguiente al de su publicación en la Gaceta Oficial de la Ciudad de México.\nPalacio Legislativo del Congreso de la Ciudad de México, a los cinco días del mes de marzo del año dos mil veinticuatro.- POR LA MESA DIRECTIVA.- DIPUTADA MARÍA GABRIELA SALIDO MAGOS, PRESIDENTA.-\nDIPUTADA MARCELA FUENTE CASTILLO, SECRETARIA.- DIPUTADA ANA JOCELYN VILLAGRÁN VILLASANA,\nSECRETARIA.- (Firmas)\nCon fundamento en lo dispuesto por los artículos 122, apartado A, base III, de la Constitución Política de los Estados Unidos Mexicanos; 32, apartado C, numeral 1, inciso a), de la Constitución Política de la Ciudad de México; 2, párrafo segundo, 3, fracciones XVII y XVIII, 7, párrafo primero, 10, fracción II, 12 y 21, párrafo primero, de la Ley Orgánica del Poder Ejecutivo y de la Administración Pública de la Ciudad de México;\npara su debida publicación y observancia, expido el presente Decreto Promulgatorio en la Residencia\nOficial de la Jefatura de Gobierno de la Ciudad de México, a los veintiséis días del mes de marzo del año dos mil veinticuatro.- EL JEFE DE GOBIERNO DE LA CIUDAD DE MÉXICO, DR. MARTÍ BATRES GUADARRAMA.-\nFIRMA.- EL SECRETARIO DE GOBIERNO, RICARDO RUIZ SUÁREZ.- FIRMA.- LA SECRETARIA DE EDUCACIÓN,\nCIENCIA, TECNOLOGÍA E INNOVACIÓN, JESÚS OFELIA ANGULO GUERRERO.- FIRMA.- EL SECRETARIO DE\nINCLUSIÓN Y BIENESTAR SOCIAL, JUAN GERARDO LÓPEZ HERNÁNDEZ.- FIRMA.- LA SECRETARIA DE LAS\nMUJERES, INGRID AURORA GÓMEZ SARACÍBAR.- FIRMA.- LA SECRETARIA DE SALUD, OLIVA LÓPEZ\nARELLANO.- FIRMA.- EL SECRETARIO DE SEGURIDAD CIUDADANA, PABLO VÁZQUEZ CAMACHO.- FIRMA.- EL\nSECRETARIO DE TRABAJO Y FOMENTO AL EMPLEO, JOSÉ LUIS RODRÍGUEZ DÍAZ DE LEÓN.- FIRMA.",
  "ordenamiento": "Marco Jurídico",
  "jurisdiccion": "CIUDAD DE MEXICO",
  "fuente_oficial": "Congreso de la Ciudad de México",
  "status": "Vigente",
  "Fecha de Publicación": "26-06-2024",
  "Fecha de Última Reforma": "27 de marzo de 2024",
  "numero_paginas": 91,
  "es_escaneado": false,
  "tiene_tablas": true,
  "url": "https://www.congresocdmx.gob.mx/archivo-d9a88d2cc7a2b0f3d5cf61bd5db2e563584e6c14.pdf",
  "materia": [
    "derechos humanos",
    "género"
  ]
}