{
  "titulo": "Ley DE FOMENTO A LAS ACTIVIDADES DE DESARROLLO SOCIAL DE LAS ORGANIZACIONES CIVILES PARA EL DISTRITO FEDERAL",
  "Contenido": "PARA EL DISTRITO FEDERAL\nPUBLICADA EN LA GACETA OFICIAL DEL DISTRITO FEDERAL\nEL 23 DE MAYO DE 2000\nTEXTO VIGENTE\nÚLTIMA REFORMA PUBLICADA EN LA G.O.C.D.M.X.\nEL 11 DE NOVIEMBRE DE 2022\nLEY DE FOMENTO A LAS ACTIVIDADES DE DESARROLLO SOCIAL DE LAS ORGANIZACIONES CIVILES\nPARA EL DISTRITO FEDERAL\n(Al margen superior izquierdo un escudo que dice: CIUDAD DE MÉXICO.- JEFE DE GOBIERNO DEL\nDISTRITO FEDERAL)\nROSARIO ROBLES BERLANGA, Jefa de Gobierno del Distrito Federal, a sus habitantes sabed:\nQue la honorable Asamblea Legislativa del Distrito Federal, I Legislatura, se ha servido dirigirme la siguiente\nLEY\n(Al margen superior izquierdo el escudo nacional que dice: ESTADOS UNIDOS MEXICANOS.-\nASAMBLEA LEGISLATIVA DEL DISTRITO FEDERAL.- I LEGISLATURA)\nLA ASAMBLEA LEGISLATIVA DEL DISTRITO FEDERAL\nI LEGISLATURA\nDECRETA\n\nPARA EL DISTRITO FEDERAL\nLEY DE FOMENTO A LAS ACTIVIDADES DE DESARROLLO\nSOCIAL DE LAS ORGANIZACIONES CIVILES PARA EL\nDISTRITO FEDERAL\nCAPÍTULO PRIMERO\nDisposiciones Generales\nArtículo 1.- La presente Ley es de orden público, de interés social y de aplicación en la Ciudad de\nMéxico y tiene por objeto fomentar las actividades de Desarrollo Social que realicen las organizaciones civiles en beneficio de la población en esta entidad.\nReforma publicada en la GOCDMX el 11 de Noviembre de 2022\nArtículo 2.- Para los efectos de esta ley, se consideran actividades de Desarrollo Social las que realicen en el distrito federal, sin ánimo de lucro, en beneficio de terceros, con sentido de corresponsabilidad y transparencia, sin fines confesionales o político partidistas, y bajo los principios de solidaridad, filantropía y asistencia social, las organizaciones constituidas conforme a las leyes mexicanas, cualquiera que sea la forma jurídica que adopten, para:\nI. Fortalecer y fomentar el goce y ejercicio de los derechos humanos;\nII. Fomentar condiciones sociales que favorezcan integralmente el desarrollo humano;\nIII. Promover la realización de obras y la prestación de servicios públicos para beneficio de la población;\nIV. Fomentar el desarrollo regional y comunitario, de manera sustentable y el aprovechamiento de los recursos naturales, la protección del medio ambiente y la conservación y restauración del equilibrio ecológico;\nV. Realizar acciones de prevención y protección civil;\nVI. Apoyar a los grupos vulnerables y en desventaja social en la realización de sus objetivos;\nVII. Prestar asistencia social en los términos de las leyes en la materia;\nVIII. Promover la educación cívica y la participación ciudadana para beneficio de la población;\nIX. Desarrollar servicios educativos en los términos de la Ley General de Educación;\nX. Aportar recursos humanos, materiales o de servicios para la salud integral de la población,\n\nPARA EL DISTRITO FEDERAL en el marco de la Ley General de Salud y de la Ley de la Salud para la Ciudad de México;\nReforma publicada en la GOCDMX el 11 de Noviembre de 2022\nXI. Apoyar las actividades a favor del desarrollo urbano y el ordenamiento territorial;\nXII. Impulsar el avance del conocimiento y el desarrollo cultural;\nXIII. Desarrollar y promover la investigación científica y tecnológica;\nXIV. Promover las bellas artes, las tradiciones populares y la restauración y mantenimiento de monumentos y sitios arqueológicos, artísticos e históricos, así como la preservación del patrimonio cultural, conforme a la legislación aplicable.\nXV. Proporcionar servicios de apoyo a la creación y el fortalecimiento de las organizaciones civiles mediante:\na) El uso de los medios de comunicación;\nb) La prestación de asesoría y asistencia técnica;\nc) El fomento a la capacitación, y\nXVI. Favorecer el incremento de las capacidades productivas de las personas para alcanzar su autosuficiencia y desarrollo integral;\nXVII. Promoción y fomento del cuidado y protección de los animales que contribuyan a la asistencia social.\nXVIII. Las demás actividades que, basadas en los principios que animan esta ley, contribuyan al desarrollo social de la población.\nArtículo 3.- Para favorecer las actividades de desarrollo social enunciadas en el artículo 2, las organizaciones civiles podrán:\nI. Estimular la capacidad productiva de los grupos sociales beneficiarios a fin de procurar su autosuficiencia;\nII. Procurar, obtener y canalizar recursos económicos, humanos y materiales;\nIII. Promover actividades económicas con el propósito de aportar en forma íntegra sus rendimientos para las acciones de bienestar y Desarrollo Social.\n\nPARA EL DISTRITO FEDERAL\nArtículo 4.- No se aplicará la presente ley, por estar reguladas en otros ordenamientos legales, a actividades que realicen:\nI. Los partidos y asociaciones políticas;\nII. Las asociaciones religiosas;\nIII. Las personas morales que tienen como objeto principal trabajar exclusivamente en beneficio de sus miembros;\nIV. Las personas morales que tienen como objetivo principal la realización de actividades con fines mercantiles y que no cumplen los requisitos estipulados en las fracciones II y III del artículo 9 de esta Ley.\nArtículo 5.- Las actividades a que se refiere el artículo 2 de esta Ley son de interés social, por lo que las dependencias, órganos desconcentrados y entidades de la Administración Pública de la Ciudad de\nMéxico, en el ámbito de sus respectivas competencias, deberán fomentarlas, tanto administrativa como fiscalmente, así como mediante\nReforma publicada en la GOCDMX el 11 de Noviembre de 2022\nI. La promoción de la participación ciudadana en las políticas de Desarrollo Social;\nII. La creación de condiciones que estimulen a las organizaciones civiles que realizan actividades a las que se refiere esta ley;\nIII. La regulación de mecanismos transparentes de información, coordinación, concertación, participación y consulta de las organizaciones civiles;\nIV. El establecimiento de mecanismos que permitan la proyección pública de la relación de corresponsabilidad gobierno-sociedad civil en el ámbito de Desarrollo Social;\nV. El establecimiento de mecanismos para que las organizaciones civiles cumplan con las obligaciones que les señala esta Ley y se les garantice el goce y ejercicio de sus derechos; y\nVI. La promoción de estudios e investigaciones que permitan apoyar a las organizaciones civiles en el desarrollo de sus actividades.\nLas dependencias, órganos desconcentrados y entidades de la Administración Pública de la Ciudad de\nMéxico, en el ámbito de sus respectivas competencias, propiciaran la actuación coordinada para el\n\nPARA EL DISTRITO FEDERAL fomento de las actividades de Desarrollo Social.\nReforma publicada en la GOCDMX el 11 de Noviembre de 2022\nArtículo 6.- La Administración Pública de la Ciudad de México promoverá la celebración de convenios de coordinación con la Federación, Gobiernos de los Estados y de los Municipios, para fomentar las actividades a que se refiere esta Ley.\nReforma publicada en la GOCDMX el 11 de Noviembre de 2022\nCAPÍTULO SEGUNDO\nDel Registro de las Organizaciones Civiles\nArtículo 7.- La Secretaría de Inclusión y Bienestar Social de la Ciudad de México deberá integrar, con la participación de las organizaciones el Registro de Organizaciones Civiles de la Ciudad de México en el que se inscribirán, cuando así lo soliciten, las Organizaciones Civiles que realicen las actividades de\nDesarrollo Social a que se refiere esta Ley. Dicho Registro será público y tendrá las siguientes funciones:\nReforma publicada en la GOCDMX el 11 de Noviembre de 2022\nI. Organizar y administrar un sistema de registro y de información de las organizaciones civiles;\nII. Inscribir a las organizaciones civiles que cumplan con los requisitos que establece esta Ley y otorgarles su respectiva constancia de inscripción;\nIII. Verificar, conforme a lo previsto en el Reglamento de esta Ley, el cumplimiento de las obligaciones estipuladas en esta ley, por parte de las organizaciones civiles.\nIV. Reconocer públicamente las acciones que lleven a cabo las organizaciones civiles que se distingan en la realización de actividades de Desarrollo Social, y\nV. Las demás que le establezcan el Reglamento de esta Ley y demás disposiciones jurídicas aplicables.\nArtículo 8.- Para su inscripción en el Registro de Organizaciones Civiles de la Ciudad de México, las organizaciones presentarán solicitud ante la Secretaría de Inclusión y Bienestar Social de la Ciudad de\nMéxico, en el formato autorizado por ésta, con los requisitos siguientes:\nReforma publicada en la GOCDMX el 11 de Noviembre de 2022\nI. Presentar copia certificada de su acta constitutiva y de sus estatutos;\n\nPARA EL DISTRITO FEDERAL\nII. Que el objeto social y las actividades de la organización civil sean alguna o algunas de las señaladas en esta Ley, así como que no designen individualmente a sus beneficiarios;\nIII. Prever en su acta constitutiva o estatutos que no distribuirán remanentes entre sus asociados y en caso de disolución, transmitirán sus bienes a otra organización inscrita en el\nRegistro;\nIV. Señalar su domicilio social, y\nV. Designar un representante legal.\nArtículo 9.- Recibida la solicitud a que se refiere el artículo anterior, la Secretaría de Inclusión y\nBienestar Social de la Ciudad de México, en un plazo no mayor de treinta días hábiles, resolverá sobre la procedencia de la inscripción.\nReforma publicada en la GOCDMX el 11 de Noviembre de 2022\nLa Secretaría negará la inscripción cuando no se cumpla alguno de los requisitos a que se refiere el artículo anterior, la documentación exhibida presente alguna irregularidad, exista constancia de haber cometido en el desarrollo de sus actividades infracciones graves o reiteradas a esta Ley y a otras disposiciones jurídicas, o cuando haya evidencia de que la organización no cumpla con su objeto.\nCAPÍTULO TERCERO\nDe los Derechos y Obligaciones de las Organizaciones Civiles\nArtículo 10.- Las organizaciones civiles inscritas en el Registro de Organizaciones Civiles de la Ciudad de México adquirirán los derechos siguientes:\nReforma publicada en la GOCDMX el 11 de Noviembre de 2022\nI. Ser instancias de consulta para proponer objetivos, prioridades y estrategias de política de\nDesarrollo Social de la Ciudad de México;\nReforma publicada en la GOCDMX el 11 de Noviembre de 2022\nII. Ser representadas en los órganos de participación y consulta ciudadana que en materia de\nDesarrollo Social establezca la Administración Pública de la Ciudad de México, de conformidad con las disposiciones jurídicas aplicables;\nReforma publicada en la GOCDMX el 11 de Noviembre de 2022\nIII. Participar en la formulación, seguimiento y evaluación de los programas de Desarrollo\n\nPARA EL DISTRITO FEDERAL\nSocial y en la promoción de mecanismo de contraloría social, dentro del Programa General de Desarrollo de la Ciudad de México\nReforma publicada en la GOCDMX el 11 de Noviembre de 2022\nIV. Recibir los bienes de otras organizaciones civiles que se extingan, de conformidad con sus estatutos y sin perjuicio de lo que dispongan otras disposiciones jurídicas;\nV. Acceder, en los términos estipulados por el reglamento, a los recursos y fondos públicos que, para las actividades previstas en esta Ley, y conforme a las disposiciones jurídicas de la materia, destina la Administración Pública de la Ciudad de México;\nReforma publicada en la GOCDMX el 11 de Noviembre de 2022\nVI. Gozar de las prerrogativas fiscales y demás beneficios económicos y administrativos que otorgue la Administración Pública de la Ciudad de México, de conformidad con las disposiciones jurídicas de la materia\nReforma publicada en la GOCDMX el 11 de Noviembre de 2022\nVII. Coadyuvar con las autoridades competentes, en los términos de los convenios de concertación que al efecto se celebren, en la prestación de servicios públicos; y\nVIII. Recibir, en el marco de los programas que al efecto formulen dependencias, órganos desconcentrados y entidades de la Administración Pública de la Ciudad de México, asesoría, capacitación y colaboración, cuando así lo soliciten.\nReforma publicada en la GOCDMX el 11 de Noviembre de 2022\nArtículo 11.- Las organizaciones civiles inscritas en el Registro de Organizaciones Civiles de la Ciudad de México tendrán, además de las obligaciones previstas en otras disposiciones jurídicas que atañen a su objeto social, las siguientes:\nReforma publicada en la GOCDMX el 11 de Noviembre de 2022\nI. Informar al Registro cualquier modificación a su objeto social, domicilio o representación legal, en un plazo no mayor de cuarenta y cinco días hábiles contados a partir de la protocolización respectiva, a efecto de mantener actualizado el sistema de registro a que se refiere esta Ley;\nII. Mantener a disposición de las autoridades competentes para actualizar el sistema de información, así como del público en general, la información de las actividades que realicen y de su contabilidad o, en su caso, de sus estados financieros;\nIII. Destinar la totalidad de sus recursos al cumplimiento de su objeto;\n\nPARA EL DISTRITO FEDERAL\nIV. Carecer de ligas de dependencia o subordinación con partidos políticos y abstenerse de efectuar actividades político-partidistas, así como de realizar proselitismo o propaganda con fines religiosos; y\nV. Proporcionar a la autoridad que otorgue los recursos y fondos públicos a que se refiere la\nLey, la información, así como las facilidades para la verificación, inspección y fiscalización en todo momento, sobre el uso y destino de los apoyos otorgados.\nReforma publicada en la GOCDMX el 11 de Noviembre de 2022\nCAPÍTULO CUARTO\nDe las Sanciones\nArtículo 12.- La Secretaría de Inclusión y Bienestar Social de la Ciudad de México impondrá a las organizaciones civiles registradas las sanciones siguientes:\nReforma publicada en la GOCDMX el 11 de Noviembre de 2022\nI. Apercibimiento, en el caso de que incurran por primera vez en incumplimiento de las obligaciones que establecen las fracciones I y II del artículo 11 de esta Ley, para que, en un plazo no menor de treinta días hábiles contados a partir de la notificación respectiva, subsane la irregularidad;\nII. Suspensión por un año de los derechos estipulados en esta Ley si en un período de cinco años incumplen, por segunda vez, las obligaciones que les establecen las fracciones I y II del artículo 11 de esta Ley; y\nIII. Cancelación definitiva de la inscripción en el Registro, en caso de:\na) El incumplimiento de las obligaciones a que se refieren las fracciones III, IV y V del artículo 11 de esta ley;\nb) Incumplimiento de las demás obligaciones a que se refieren las fracciones I y II del artículo 11 de esta ley por más de dos ocasiones en un periodo de cinco años.\nLas sanciones a que se refiere este artículo, se aplicarán conforme a lo dispuesto por el Reglamento de la presente Ley y sin perjuicio de las de carácter civil o penal que procedan en su caso.\n\nPARA EL DISTRITO FEDERAL\nCAPÍTULO QUINTO\nDel Recurso Administrativo\nArtículo 13.- En contra de los actos y resoluciones de la Administración Pública de la Ciudad de México ordenados o dictados con motivo de la aplicación de la presente Ley y normas jurídicas que de ella emanen, se podrá interponer el recurso de inconformidad, en términos de lo dispuesto por la Ley de\nProcedimiento Administrativo de la Ciudad de México.\nReforma publicada en la GOCDMX el 11 de Noviembre de 2022\nTRANSITORIOS\nARTÍCULO PRIMERO.- La presente Ley entrará en vigor al día siguiente de su publicación en la Gaceta\nOficial del Distrito Federal.\nARTÍCULO SEGUNDO.- Publíquese en la Gaceta Oficial del Distrito Federal para su entrada en vigor y en el Diario Oficial de la Federación para su mayor difusión.\nSalón de Sesiones de la Asamblea Legislativa del Distrito Federal, a 13 de abril del dos mil.- POR LA\nMESA DIRECTIVA.- DIP. MARÍA DE LOS ÁNGELES CORREA DE LUCIO, PRESIDENTA.- DIP. ELVIRA\nALBARRAN RODRÍGUEZ, SECRETARIA.- DIP. JESÚS EDUARDO TOLEDANO LANDERO, SECRETARIO,-\nFIRMAS.\nEn cumplimiento de lo dispuesto por los artículos 122, apartado C, base segunda, fracción II, inciso b), de la Constitución Política de los Estados Unidos Mexicanos; 48, 49 y 67, fracción II del Estatuto de\nGobierno del Distrito Federal, y para su debida publicación y observancia, expido el presente Decreto\nPromulgatorio, en la Residencia de la Jefa de Gobierno del Distrito Federal, en la Ciudad de México, a los veinticuatro días del mes de abril de dos mil.- LA JEFA DE GOBIERNO DEL DISTRITO FEDERAL,\nROSARIO ROBLES BERLANGA.- FIRMA.- LA SECRETARÍA DE DESARROLLO SOCIAL, CLARA JUSIDMAN\nRAPOPORT.- FIRMA.\nTRANSITORIO DEL DECRETO POR EL QUE SE REFORMA LA LEY DE FOMENTO A LAS ACTIVIDADES DE\nDESARROLLO SOCIAL DE LAS ORGANIZACIONES CIVILES PARA EL DISTRITO FEDERAL, PUBLICADO\nEN LA GACETA OFICIAL DEL DISTRITO FEDERAL EL 6 DE ENERO DE 2006.\nÚNICO.- El presente decreto entrará en vigor al día siguiente de su publicación en la Gaceta Oficial del\nDistrito Federal.\n\nPARA EL DISTRITO FEDERAL\nTRANSITORIO DEL DECRETO POR EL QUE SE REFORMAN DIVERSAS DISPOSICIONES DE LA LEY DE\nFOMENTO A LAS ACTIVIDADES DE DESARROLLO SOCIAL DE LAS ORGANIZACIONES CIVILES PARA EL\nDISTRITO FEDERAL, PUBLICADO EN LA GACETA OFICIAL DE LA CIUDAD DE MÉXICO EL 05 DE OCTUBRE\nDE 2017.\nPRIMERO. - El presente Decreto entrará en vigor el día siguiente al de su publicación.\nSEGUNDO. - Publíquese en la Gaceta Oficial de la Ciudad de México.\nTERCERO. - El Jefe de Gobierno de la Ciudad de México deberá adecuar el reglamento de la presente ley, dentro de los 90 días naturales siguientes al día de entrada en vigor del presente Decreto.\nRecinto de la Asamblea Legislativa del Distrito Federal, a los cinco días del mes de abril del año dos mil diecisiete.- POR LA MESA DIRECTIVA.- DIP. ERNESTO SÁNCHEZ RODRÍGUEZ, PRESIDENTE. - DIP.\nREBECA PERALTA LEÓN, SECRETARIA. - DIP. EVA ELOISA LESCAS HERNÁNDEZ, SECRETARIA. -\n(Firmas)\nCon fundamento en lo dispuesto por los artículos 122, Apartado A, Base III, de la Constitución Política de los Estados Unidos Mexicanos; Transitorios Primero y Segundo del Decreto por el que se declaran reformadas y derogadas diversas disposiciones de la Constitución Política de los Estados Unidos\nMexicanos, en materia de la Reforma Política de la Ciudad de México; 48, 49 y 67, fracción II, del\nEstatuto de Gobierno del Distrito Federal, para su debida publicación y observancia, expido el presente\nDecreto Promulgatorio en la Residencia Oficial del Jefe de Gobierno de la Ciudad de México, a los tres días del mes de octubre del año dos mil diecisiete.- EL JEFE DE GOBIERNO DE LA CIUDAD DE MÉXICO,\nMIGUEL ÁNGEL MANCERA ESPINOSA.- FIRMA.- LA SECRETARIA DE GOBIERNO, DORA PATRICIA\nMERCADO CASTRO.- FIRMA.- EL SECRETARIO DE DESARROLLO SOCIAL, JOSÉ RAMÓN AMIEVA\nGÁLVEZ.- FIRMA.\nTRANSITORIO DEL DECRETO POR EL QUE SE REFORMA LOS ARTÍCULOS 1, 2, FRACCIONES I, V, X Y\nXVIII, 5, FRACCIÓN VI, PÁRRAFO SEGUNDO, 6, 7, 8, 9, 10, FRACCIONES I, II, III, V, VI Y VIII, 11,\nFRACCIÓN V, 12 Y 13, ASÍ COMO LA DENOMINACIÓN, DE LA LEY DE FOMENTO A LAS ACTIVIDADES\nDE DESARROLLO SOCIAL DE LAS ORGANIZACIONES CIVILES PARA EL DISTRITO FEDERAL, PUBLICADO\nEN LA GACETA OFICIAL DE LA CIUDAD DE MÉXICO EL 11 DE NOVIEMBRE DE 2022.\nPRIMERO. - Remítase a la persona titular de la Jefatura de Gobierno, para su promulgación y publicación en la Gaceta Oficial de la Ciudad de México.\n\nPARA EL DISTRITO FEDERAL\nSEGUNDO. - El presente Decreto entrará en vigor al día siguiente de su publicación en la Gaceta Oficial de la Ciudad de México.\nPalacio Legislativo del Congreso de la Ciudad de México, a los tres días del mes de noviembre del año dos mil veintidós.- POR LA MESA DIRECTIVA.- DIPUTADO FAUSTO MANUEL ZAMORANO ESPARZA,\nPRESIDENTE.- DIPUTADA MARCELA FUENTE CASTILLO, SECRETARIA.- DIPUTADA MARIA GABRIELA\nSALIDO MAGOS, SECRETARIA.- (Firmas)\nCon fundamento en lo dispuesto por los artículos 122, apartado A, fracción III de la Constitución Política de los Estados Unidos Mexicanos; 32, apartado C, numeral 1, inciso a) de la Constitución Política de la\nCiudad de México; 2 párrafo segundo, 3 fracciones XVII y XVIII, 7 párrafo primero, 10 fracción II, 12 y\n21 párrafo primero de la Ley Orgánica del Poder Ejecutivo y de la Administración Pública de la Ciudad de México; para su debida publicación y observancia, expido el presente Decreto Promulgatorio en la\nResidencia Oficial de la Jefatura de Gobierno de la Ciudad de México, a los diez días del mes de noviembre del año dos mil veintidós.- LA JEFA DE GOBIERNO DE LA CIUDAD DE MÉXICO, DRA.\nCLAUDIA SHEINBAUM PARDO.- FIRMA.- EL SECRETARIO DE GOBIERNO, MARTÍ BATRES\nGUADARRAMA.- FIRMA.- LA SECRETARIA DE ADMINISTRACIÓN Y FINANZAS, LUZ ELENA GONZÁLEZ\nESCOBAR.- FIRMA.- EL SECRETARIO DE LA CONTRALORÍA GENERAL, JUAN JOSÉ SERRANO\nMENDOZA.- FIRMA.- LA SECRETARIA DE CULTURA, CLAUDIA STELLA CURIEL DE ICAZA.- FIRMA.- EL\nSECRETARIO DE DESARROLLO ECONÓMICO, FADLALA AKABANI HNEIDE.- FIRMA.- EL SECRETARIO\nDE DESARROLLO URBANO Y VIVIENDA, CARLOS ALBERTO ULLOA PÉREZ.- FIRMA.- LA SECRETARIA\nDE EDUCACIÓN, CIENCIA, TECNOLOGÍA E INNOVACIÓN, ROSAURA RUIZ GUTIÉRREZ.- FIRMA.- LA\nSECRETARIA DE GESTIÓN INTEGRAL DE RIESGOS Y PROTECCIÓN CIVIL, MYRIAM VILMA URZÚA\nVENEGAS.- FIRMA.- EL ENCARGADO DE DESPACHO DE LA SECRETARÍA EL SECRETARIO DE\nINCLUSIÓN Y BIENESTAR SOCIAL, RIGOBERTO SALGADO VÁZQUEZ.- FIRMA.- LA SECRETARIA DEL\nMEDIO AMBIENTE, MARINA ROBLES GARCÍA.- FIRMA.- EL SECRETARIO DE MOVILIDAD, ANDRÉS\nLAJOUS LOAEZA.- FIRMA.- LA SECRETARIA DE LAS MUJERES, INGRID GÓMEZ SARACÍBAR.- FIRMA.-\nEL SECRETARIO DE OBRAS Y SERVICIOS, JESÚS ANTONIO ESTEVA MEDINA.- FIRMA.- LA\nSECRETARIA DE PUEBLOS Y BARRIOS ORIGINARIOS Y COMUNIDADES INDÍGENAS RESIDENTES,\nLAURA ITA ANDEHUI RUIZ MONDRAGÓN.- FIRMA.- LA SECRETARIA DE SALUD, OLIVA LÓPEZ\nARELLANO.- FIRMA.- EL SECRETARIO DE SEGURIDAD CIUDADANA, OMAR HAMID GARCÍA\nHARFUCH.- FIRMA.- EL SECRETARIO DE TRABAJO Y FOMENTO AL EMPLEO, JOSÉ LUIS RODRÍGUEZ\nDÍAZ DE LEÓN.- FIRMA.- EL ENCARGADO DE DESPACHO DE LA SECRETARÍA DE TURISMO, NATHALIE\nVERONIQUE DESPLAS PUEL.- FIRMA.- EL CONSEJERO JURÍDICO Y DE SERVICIOS LEGALES, NÉSTOR\nVARGAS SOLANO.- FIRMA.",
  "ordenamiento": "Marco Jurídico",
  "jurisdiccion": "CIUDAD DE MEXICO",
  "fuente_oficial": "Congreso de la Ciudad de México",
  "status": "Vigente",
  "Fecha de Publicación": "15-11-2022",
  "Fecha de Última Reforma": "11 de Noviembre de 2022",
  "numero_paginas": 11,
  "es_escaneado": false,
  "tiene_tablas": false,
  "url": "https://www.congresocdmx.gob.mx/archivo-c3d68f00f1c32beaf8434dd4ed709cba45d4b256.pdf",
  "materia": [
    "desarrollo social",
    "organizaciones civiles"
  ]
}