{
  "titulo": "Ley DE BÚSQUEDA DE PERSONAS DE LA CIUDAD DE MÉXICO",
  "Contenido": "PUBLICADA EN LA GACETA OFICIAL DE LA CIUDAD DE MÉXICO\nEL 31 DE DICIEMBRE DE 2019\nTEXTO VIGENTE\nÚLTIMA REFORMA PUBLICADA EN LA G.O.C.D.M.X.\nEL 09 DE ABRIL DE 2021\nADMINISTRACIÓN PÚBLICA DE LA CIUDAD DE MÉXICO\nJEFATURA DE GOBIERNO\nDECRETO POR EL QUE SE ABROGA LA LEY PARA PREVENIR, ELIMINAR Y SANCIONAR LA\nDESAPARICIÓN FORZADA DE PERSONAS Y LA DESAPARICIÓN POR PARTICULARES EN LA CIUDAD DE\nMÉXICO. SE EXPIDE LA LEY DE BÚSQUEDA DE PERSONAS DE LA CIUDAD DE MÉXICO\nDRA. CLAUDIA SHEINBAUM PARDO, Jefa de Gobierno de la Ciudad de México, a sus habitantes sabed.\nQue el H. Congreso de la Ciudad de México I Legislatura, se ha servido dirigirme el siguiente:\nD E C R E T O\nCONGRESO DE LA CIUDAD DE MÉXICO\nI LEGISLATURA\nEL CONGRESO DE LA CIUDAD DE MÉXICO, DECRETA:\nSE ABROGA LA LEY PARA PREVENIR, ELIMINAR Y SANCIONAR LA DESAPARICIÓN FORZADA DE\nPERSONAS Y LA DESAPARICIÓN POR PARTICULARES EN LA CIUDAD DE MÉXICO. SE EXPIDE LA LEY\nDE BÚSQUEDA DE PERSONAS DE LA CIUDAD DE MÉXICO.\nDECRETO\nARTÍCULO PRIMERO.- Se abroga la Ley para Prevenir, Eliminar y Sancionar la Desaparición Forzada de\nPersonas y la Desaparición por Particulares en la Ciudad de México.\nARTÍCULO SEGUNDO.- Se expide la Ley de Búsqueda de Personas de la Ciudad de México, para quedar como sigue:\n\nLEY DE BÚSQUEDA DE PERSONAS DE LA CIUDAD DE\nMÉXICO\nTÍTULO PRIMERO\nDISPOSICIONES GENERALES\nCAPÍTULO PRIMERO\nArtículo 1°. La presente ley es de orden público, interés social y observancia general, para las personas que habitan y/o transitan en la Ciudad de México de conformidad con el mandato establecido en el artículo 29, apartado D, de la Constitución Política de la Ciudad de México, así como los tratados internacionales en materia de derechos humanos suscritos por el Estado Mexicano, y en armonía con la Ley General en Materia de Desaparición Forzada de Personas, Desaparición cometida por\nParticulares y del Sistema Nacional de Búsqueda de Personas.\nArtículo 2°. La presente Ley tiene por objeto:\nI. Establecer la distribución de competencias y la forma de coordinación entre las autoridades de la Ciudad de México y sus Alcaldías, así como la forma de coordinación con las autoridades de las entidades federativas y los Municipios para buscar a las personas desaparecidas, y esclarecer los hechos; así como para prevenir, investigar y erradicar los delitos en materia de desaparición forzada de personas y desaparición cometida por particulares, así como los delitos vinculados que establece la Ley General en Materia de\nDesaparición Forzada de Personas, Desaparición Cometida por Particulares y del Sistema\nNacional de Búsqueda de Personas.\nII. Establecer el Sistema de Búsqueda de Personas de la Ciudad de México;\nIII. Regular a la Comisión de Búsqueda de Personas de la Ciudad de México.\nIV. Garantizar la protección integral de los derechos de las Personas Desaparecidas hasta que se conozca su suerte o paradero; así como la atención, la asistencia, la protección y, en su caso, la reparación integral y las garantías de no repetición, en términos de Ley General en Materia de Desaparición Forzada de Personas, Desaparición Cometida por Particulares y del Sistema Nacional de Búsqueda de Personas, esta Ley y la legislación aplicable;\nV. Crear el Registro de Personas Desaparecidas de la Ciudad de México como entidad que forma parte del Registro Nacional; y\n\nVI. Establecer la forma de participación de los Familiares, sus asesores jurídicos, las instancias de la sociedad civil organizada y del sector privado y demás víctimas indirectas en el diseño, implementación, monitoreo y evaluación de las acciones de búsqueda e identificación de Personas Desaparecidas; así como garantizar la coadyuvancia en las etapas de la investigación, de manera que puedan verter sus opiniones, recibir información, aportar indicios o evidencias.\nArtículo 3°. La aplicación de la presente Ley corresponde a las autoridades de la Ciudad de México y sus Alcaldías, en el ámbito de sus respectivas competencias, y se interpretará de conformidad con los principios de promoción, respeto, protección y garantía de los derechos humanos establecidos en la\nConstitución Política de los Estados Unidos Mexicanos, la Constitución Política de la Ciudad de México, favoreciendo en todo tiempo el principio pro persona.\nArtículo 4°. Para efectos de esta Ley se entiende por:\nI. Banco Nacional de Datos Forenses: a la herramienta del Sistema Nacional que concentra las bases de datos de las entidades federativas y de la Federación; así como, otras bases de datos que tengan información forense relevante para la búsqueda e identificación de\nPersonas Desaparecidas;\nII. Búsqueda inmediata: El inicio de las acciones de búsqueda de oficio, sin dilación y con celeridad de la persona desaparecida por parte de las autoridades de la Ciudad de México luego de que han tomado conciencia de los hechos, mediante la denuncia, el reporte o la noticia.\nIII. Comisión de Víctimas: a la Comisión Ejecutiva de Atención a Víctimas de la Ciudad de\nMéxico;\nIV. Comisión Nacional: a la Comisión Nacional de Búsqueda de Personas;\nV. Comisión de Búsqueda: a la Comisión de Búsqueda de Personas de la Ciudad de México;\nVI. Consejo Ciudadano: al Consejo Ciudadano de la Ciudad de México, órgano del Sistema de\nBúsqueda de Personas de la Ciudad de México;\nVII. Declaración Especial de Ausencia: a la Declaración Especial de Ausencia para Personas\nDesaparecidas;\nVIII. Familiares: a las personas que, en términos de la legislación aplicable, tengan parentesco con la Persona Desaparecida por consanguinidad o afinidad, en línea recta\n\nascendente y descendente sin limitación de grado; en línea transversal hasta el cuarto grado;\nél o la cónyuge, la concubina o concubinario o, en su caso, quienes estén sujetos al régimen de sociedad en convivencia u otras figuras jurídicas análogas. Asimismo, las personas que dependan económicamente de la Persona Desaparecida, que así lo acrediten ante las autoridades competentes;\nIX. Fiscalía Especializada: a la Fiscalía Especializada para la Investigación, Persecución de los\nDelitos en Materia de Desaparición Forzada de Personas y la Desaparición Cometida por\nParticulares y Búsqueda de Personas Desaparecidas de la Fiscalía General de Justicia de la\nCiudad de México, cuyo objeto es la investigación y persecución de los delitos de\nDesaparición Forzada de Personas y la cometida por particulares, así como la búsqueda de personas desaparecidas;\nX. Fiscalía General: a la Fiscalía General de Justicia de la Ciudad de México;\nXI. Grupo de Búsqueda: al grupo de personas especializadas en materia de búsqueda de personas de la Comisión de Búsqueda, que realizarán la búsqueda de campo, entre otras;\nXII. Instituto de Ciencias Forenses: al Instituto de Ciencias Forenses del Tribunal Superior de\nJusticia de la Ciudad de México.\nXIII. Ley de Víctimas: a la Ley de Víctimas para la Ciudad de México;\nXIV. Ley General: Ley General En Materia De Desaparición Forzada De Personas, Desaparición\nCometida Por Particulares Y Del Sistema Nacional De Búsqueda De Personas;\nXV. Noticia: a la comunicación hecha por cualquier medio, distinto al reporte o la denuncia, mediante la cual, la autoridad competente conoce de la desaparición de una persona;\nXVI. Persona Desaparecida: a la persona cuyo paradero y/o ubicación se desconoce;\nXVII. Principios Rectores para la Búsqueda de Personas Desaparecidas: a los Principios\nRectores para la Búsqueda de Personas Desaparecidas aprobados por el Comité Contra la\nDesaparición Forzada, de la Organización de las Naciones Unidas.\nXVIII. Protocolo Homologado de Búsqueda: al Protocolo Homologado para la Búsqueda de\nPersonas Desaparecidas;\nXIX. Protocolo Homologado de Investigación: al Protocolo Homologado para la investigación de los delitos materia de la Ley General;\n\nXX. Registro Nacional: al Registro Nacional de Personas Desaparecidas, que concentra la información de los registros de Personas Desaparecidas, tanto de la Federación como de las\nEntidades Federativas, señalado en la Ley General;\nXXI. Registro Nacional de Personas Fallecidas y No Identificadas: al Registro Nacional de\nPersonas Fallecidas No Identificadas y No Reclamadas que concentra la información forense procesada de la localización, recuperación, identificación y destino final de los restos tanto de la Federación como de las entidades federativas, cualquiera que sea su origen;\nXXII. Registro de Personas Fallecidas: al Registro de Personas Fallecidas No Identificadas y\nNo Reclamadas en la Ciudad de México.\nXXIII. Registro de Personas Desaparecidas: al Registro de Personas Desaparecidas en la\nCiudad de México.\nXXIV. Registro Nacional de Fosas: al Registro Nacional de Fosas Comunes y de Fosas\nClandestinas, que concentra la información respecto de las fosas comunes que existen en los cementerios y panteones de todos los municipios del país, así como de las fosas clandestinas que la Fiscalía General y las Fiscalías Locales localicen;\nXXV. Registro de Fosas: al Registro de Fosas Comunes y de Fosas Clandestinas en la Ciudad de México, que concentra la información respecto de las fosas comunes que existen en los cementerios y panteones de las dieciséis demarcaciones territoriales, así como de las fosas clandestinas que la Fiscalía Especializada localice;\nXXVI. Reporte: a la comunicación mediante la cual la autoridad competente conoce de la desaparición de una persona;\nXXVII. Secretaría de Seguridad Ciudadana: a la Secretaría de Seguridad Ciudadana de la\nCiudad de México;\nXXVIII. Sistema de Búsqueda: al Sistema de Búsqueda de Personas de la Ciudad de México;\nXXIX. Sistema Nacional: al Sistema Nacional de Búsqueda de Personas;\nXXX. Tratados: a los tratados internacionales de los que el Estado Mexicano sea parte; y\nXXXI. Víctimas: aquellas a las que hace referencia la Ley General de Víctimas y la Ley de\nVíctimas para la Ciudad de México y demás disposiciones aplicables.\n\nArtículo 5°. Las acciones, medidas y procedimientos establecidos en esta Ley y su reglamento serán diseñados, implementados y evaluados aplicando los principios de debida diligencia, efectividad y exhaustividad, enfoque diferencial y especializado, enfoque humanitario, gratuidad, igualdad y no discriminación, interés superior de la niñez, máxima protección, no revictimización, participación conjunta, perspectiva de género, presunción de vida, verdad y búsqueda permanente conforme al artículo 5 de la Ley General y de los Principios Rectores para la Búsqueda de Personas Desaparecidas.\nArtículo 6°. En todo lo no previsto en la presente Ley, son aplicables supletoriamente las disposiciones establecidas en la Ley de Víctimas, la Ley de Declaración Especial de Ausencia de la Ciudad de México y la legislación civil aplicable en la Ciudad de México.\nCAPÍTULO SEGUNDO\nDisposiciones Generales para Personas Desaparecidas Menores de 18 Años\nArtículo 7°. Las niñas, niños y adolescentes respecto de los cuales haya Noticia, Reporte o Denuncia que han desaparecido en cualquier circunstancia, se iniciará carpeta de investigación y ficha de búsqueda en todos los casos, y se emprenderá la búsqueda especializada de manera inmediata y diferenciada, de conformidad con el protocolo especializado en búsqueda de personas menores de 18 años de edad que emita el Sistema de Búsqueda.\nLa Fiscalía Especializada y la Comisión de Búsqueda, realizarán el análisis del contexto sobre la desaparición de personas menores de 18 años en la Ciudad de México e intercambiarán con las autoridades competentes, la información sobre el contexto de desaparición, principalmente en la Zona\nMetropolitana del Valle de México y la Región Centro del país, así como de otros delitos que guarden relación directa con los fenómenos de desaparición de personas menores de 18 años y, en su caso coordinarse con otras fiscalías competentes.\nArtículo 8°. La Comisión de Búsqueda y las autoridades que integran el Sistema de Búsqueda deben tomar en cuenta el interés superior de la niñez, y deben establecer la información segmentada por género, edad, situación de vulnerabilidad, riesgo o discriminación.\nLa divulgación que hagan o soliciten las autoridades responsables en medios de telecomunicación sobre la información de una persona menor de 18 años de edad desaparecida, se hará de conformidad con las disposiciones aplicables.\nLa difusión de la ficha de búsqueda de las personas desaparecidas deberá realizarse ampliamente y por todos los medios de difusión posibles, incluidos los medios de comunicación masiva.\n\nArtículo 9°. Todas las acciones que se emprendan para la investigación y búsqueda de personas menores de 18 años de edad desaparecidas, garantizarán un enfoque integral, transversal y con perspectiva de derechos humanos de la niñez, que tome en cuenta las características particulares, incluyendo su identidad y nacionalidad.\nEn aquellos casos en que la niña, niño o adolescentes se localice y se determine que existe un riesgo en contra su vida, integridad o libertad, el Ministerio Público competente dictará las medidas urgentes de protección especial idónea, dando aviso de inmediato a la autoridad jurisdiccional competente, en términos del Código Nacional de Procedimientos Penales, Ley General de los Derechos de Niñas, Niños y Adolescentes y la Ley de los Derechos de Niñas, Niños y Adolescentes de la Ciudad de México.\nArtículo 10°. Las autoridades de búsqueda e investigación en el ámbito de sus competencias se coordinarán con la Procuraduría de Protección de Derechos de Niñas, Niños y Adolescentes de la\nCiudad de México para efectos de salvaguardar sus derechos, de conformidad con la Ley de los\nDerechos de Niñas, Niños y Adolescentes de la Ciudad de México y otras disposiciones aplicables.\nLa Procuraduría de Protección de Derechos de Niñas, Niños y Adolescentes de la Ciudad de México prestará servicios de asesoría a los familiares de personas menores de 18 años de edad desaparecidas, sin perjuicio de los servicios que preste la Comisión de Búsqueda y Comisión de Víctimas.\nAsimismo, podrá llevar la representación en suplencia de niñas, niños y adolescentes desaparecidos, sin perjuicio de las atribuciones que le correspondan al Ministerio Público. Así como intervenir oficiosamente, con representación coadyuvante, en las acciones de búsqueda y localización que realice la Comisión de Búsqueda o en las investigaciones que conduzca la Fiscalía Especializada.\nArtículo 11. En los casos de niñas, niños o adolescentes, las medidas de reparación integral, así como de atención terapéutica y acompañamiento, deberán realizarse por personal especializado en derechos de la niñez y adolescencia, de conformidad con la Ley de Víctimas.\nLa Comisión de Víctimas, sin detrimento de la reparación integral del daño, adoptará de forma prioritaria y preferente todas las medidas idóneas de ayuda, asistencia y atención que permitan la pronta recuperación física, mental o emocional de las víctimas menores de 18 años; así como, aquellas que permitan la realización de su proyecto de vida, garantizando en todo momento su participación.\nLa Comisión de Víctimas deberá tomar en cuenta y considerar las causas, efectos y consecuencias del hecho victimizante, los aspectos culturales, éticos, afectivos, educativos y de salud de personas menores de 18 años, de acuerdo con su edad, desarrollo evolutivo, cognoscitivo y madurez.\nArtículo 12. Para el diseño y la aplicación de las acciones, herramientas y el Protocolo Especializado para la Búsqueda e Investigación de Niñas, Niños y Adolescentes, el Sistema de Búsqueda tomará en\n\ncuenta la opinión de las autoridades del Sistema de Protección Integral de los Derechos de las Niñas,\nNiños y Adolescentes de la Ciudad de México.\nTÍTULO SEGUNDO\nDE LOS DELITOS Y DE LAS RESPONSABILIDADES\nADMINISTRATIVAS\nCAPÍTULO PRIMERO\nDe los Delitos\nArtículo 13. Los tipos penales en materia de desaparición forzada de personas, desaparición cometida por particulares y de los delitos vinculados con la desaparición de personas, serán investigados, perseguidos y sancionados de acuerdo con las disposiciones generales, los criterios de competencia y las sanciones, previstas por la Ley General, en el ámbito de la competencia concurrente que dicha Ley establece.\nCAPÍTULO SEGUNDO\nDe las Responsabilidades Administrativas\nArtículo 14. Los servidores públicos que incumplan injustificadamente con alguna de las obligaciones previstas en esta Ley y que no constituyan un delito, serán sancionados en términos de lo establecido en la Ley de Responsabilidades Administrativas de la Ciudad de México y las demás disposiciones jurídicas aplicables.\nArtículo 15. Para efectos de lo previsto en esta Ley, se considerará grave el incumplimiento injustificado o la actuación negligente ante cualquier obligación relacionada con la búsqueda inmediata de personas, en la investigación ministerial, pericial y policial, así como en los procedimientos establecidos en los protocolos correspondientes.\nTÍTULO TERCERO\nDEL SISTEMA DE BÚSQUEDA DE PERSONAS DE LA CIUDAD DE\nMÉXICO\nCAPÍTULO PRIMERO\nDEL SISTEMA DE BÚSQUEDA DE PERSONAS DE LA CIUDAD DE\nMÉXICO\n\nArtículo 16. El Sistema de Búsqueda tiene como objetivo diseñar y evaluar de manera eficiente y armónica los recursos de la Ciudad de México para establecer las bases generales, políticas públicas y procedimientos entre las autoridades de del Gobierno local para la búsqueda, localización e identificación de Personas Desaparecidas, así como para la prevención e investigación de los delitos en materia de la Ley General; establecer los lineamientos de coordinación con los sistemas o mecanismos homólogos de las entidades federativas y los Municipios.\nAsí mismo mantener comunicación permanente y continua con el Mecanismo de Apoyo Exterior en términos de la Ley General.\nArtículo 17. El Sistema de Búsqueda se integra por:\nI. La persona titular de la Secretaría de Gobierno, quien lo presidirá;\nII. La persona titular de la Fiscalía General de Justicia de la Ciudad de México;\nIII. La persona titular de la Comisión de Búsqueda quien fungirá como Secretaria Ejecutiva;\nIV. La persona titular de la Secretaría de Seguridad Ciudadana de la Ciudad de México;\nV. La persona titular de la Secretaría de las Mujeres de la Ciudad de México;\nVI. La persona Titular de la Secretaría de Gestión Integral de Riesgos y Protección Civil de la\nCiudad de México;\nVII. La persona titular de la Secretaría de Salud de la Ciudad de México;\nVIII. Tres personas del Consejo Ciudadano que representen a cada uno de los sectores que lo integran;\nIX. La persona titular de la Procuraduría de Protección de Derechos de Niñas, Niños y\nAdolescentes de la Ciudad de México;\nX. La persona titular de la Comisión de Víctimas;\nXI. La persona titular del Instituto de Ciencias Forenses del Tribunal Superior de Justicia de la Ciudad de México;\nXII. La persona titular de la Consejería Jurídica y de Servicios Legales de la Ciudad de México;\n\nXIII. La persona titular de la Agencia Digital de Innovación Pública de la Ciudad de México;\ny\nXIV. La persona titular del Centro de Comando, Control, Cómputo, Comunicaciones y\nContacto Ciudadano de la Ciudad de México.\nAsí como, un representante del Tribunal Superior de Justicia de la Ciudad de México; la persona que presida la Comisión de Atención Especial a Víctimas del Congreso de la Ciudad de México, que deberán ser convocadas a cada reunión del Sistema de Búsqueda, donde tendrán solo derecho a voz y no a voto.\nLas personas titulares de las Alcaldías serán integrantes con carácter no permanente del Sistema de\nBúsqueda, deberán ser convocadas para las reuniones del Sistema de Búsqueda en las que se traten asuntos de su competencia; en dichas reuniones tendrán solo derecho a voz.\nLas personas integrantes del Sistema de Búsqueda deben nombrar a sus respectivos suplentes, los cuales deben contar con el nivel jerárquico inmediato inferior.\nTratándose de la persona titular de la Fiscalía General, será suplente la persona titular de la Fiscalía\nEspecializada.\nLas personas integrantes e invitadas del Sistema de Búsqueda no recibirán pago alguno por su participación en el mismo.\nLa persona que preside el Sistema de Búsqueda podrá invitar a las sesiones respectivas a representantes de los organismos constitucionalmente autónomos quienes tendrán solo derecho a voz.\nLas instancias y las personas que integran el Sistema de Búsqueda están obligadas, en el marco de sus competencias, a cumplir con las acciones que deriven del ejercicio de las atribuciones de dicho órgano.\nArtículo 18. El Sistema de Búsqueda sesionará válidamente con la presencia de la mayoría de sus integrantes y sus resoluciones deben ser tomadas por mayoría de votos. La persona que presida tiene voto dirimente en caso de empate.\nArtículo 19. Las sesiones del Sistema de Búsqueda deben celebrarse de manera ordinaria, cada tres meses por convocatoria de la Secretaría Ejecutiva del Sistema de Búsqueda, por instrucción de la persona que lo presida, y de manera extraordinaria cuantas veces sea necesario a propuesta de un tercio de sus integrantes.\n\nLas convocatorias deben realizarse por oficio o por cualquier medio electrónico que asegure y deje constancia de su recepción, con al menos cinco días hábiles a la fecha de celebración de la sesión correspondiente, y dos días hábiles de anticipación para las sesiones extraordinarias. En ambos casos debe acompañarse el orden del día correspondiente.\nArtículo 20. El Sistema de Búsqueda para el ejercicio de sus facultades contará con las siguientes herramientas:\nI. El Registro Nacional, a través de la Comisión Nacional de Búsqueda;\nII. El Registro de Personas Desaparecidas;\nIII. El Banco Nacional de Datos Forenses, a través de la Fiscalía General de la República;\nIV. El Registro Nacional de Personas Fallecidas No Identificadas y No Reclamadas, a través de la Fiscalía General de la República;\nV. El Registro de Personas Fallecidas;\nVI. El Registro Nacional de Fosas, a través de la Fiscalía General de la República;\nVII. El Registro de Fosas;\nVIII. El Registro Nacional de Detenciones, a través de la Secretaría de Seguridad y Protección\nCiudadana;\nIX. La Alerta Amber;\nX. El Protocolo Alba;\nXI. La Alerta Plateada;\nXII. El Protocolo Homologado de Búsqueda y los protocolos previstos en el artículo 73 de la\nLey General; y\nXIII. Otros registros necesarios para su operación, en términos de lo que prevé esta Ley y su reglamento.\n\nArtículo 21. El Sistema de Búsqueda tiene las siguientes atribuciones:\nI. Expedir modelos de lineamientos que permitan la coordinación entre autoridades en materia de búsqueda de personas, así como de investigación de los delitos previstos en la\nLey General;\nII. Establecer la vinculación entre las autoridades federales y las autoridades locales competentes, para la integración y funcionamiento de un sistema de información tecnológica e informática que permita el acceso, tratamiento y uso de toda la información relevante para la búsqueda, localización e Identificación de Personas Desaparecidas; así como para la investigación y persecución de los delitos materia de la Ley General;\nIII. Proponer acuerdos de colaboración entre sus integrantes, la Secretaría de Seguridad\nCiudadana, la Fiscalía General de Justicia, el Centro de Comando, Control, Cómputo,\nComunicaciones y Contacto Ciudadano de la Ciudad de México (C5); la Agencia Digital de\nInnovación Pública de la Ciudad de México y otras instancias que coadyuven para el intercambio, sistematización y actualización de la información de seguridad ciudadana que contribuya a la búsqueda y localización de Personas Desaparecidas;\nIV. Dar seguimiento y evaluar la aplicación del Protocolo Homologado de Búsqueda y el\nProtocolo Homologado de Investigación;\nV. Aprobar los lineamientos y directrices de la Comisión de Búsqueda que sea propuestas por su titular;\nVI. Evaluar permanentemente las políticas públicas que se implementen para la búsqueda y localización de Personas Desaparecidas;\nVII. Generar mecanismos para favorecer que las capacidades presupuestarias, materiales, tecnológicas y humanas permitan la búsqueda eficiente y localización de Personas\nDesaparecidas;\nVIII. Generar los mecanismos y acuerdos necesarios para dar cumplimiento a las recomendaciones y requerimientos que hagan los integrantes del Sistema de Búsqueda para el mejoramiento de políticas públicas que se implementen para la búsqueda y localización de\nPersonas Desaparecidas;\nIX. Evaluar el cumplimiento del Programa de Búsqueda;\n\nX. Evaluar el cumplimiento de los lineamientos que regulen el funcionamiento del Registro de Fosas;\nXI. Proporcionar la información que sea solicitada por el Consejo Ciudadano para el ejercicio de sus funciones;\nXII. Atender y dar seguimiento a las recomendaciones del Consejo Ciudadano en los temas materia de esta Ley;\nXIII. Ampliar los lineamientos que regulen la participación de los Familiares en las acciones de búsqueda;\nXIV. Aplicar el Protocolo Homologado de Búsqueda; y\nXV. Las demás que se requieran para el cumplimiento de los objetivos de la Ley General y esta Ley.\nEl Sistema de Búsqueda deberá conducir todas sus decisiones, actividades y políticas de conformidad con los principios establecidos en el artículo 5° de esta Ley.\nCAPÍTULO SEGUNDO\nDe la Comisión de Búsqueda\nArtículo 22. La Comisión de Búsqueda de personas de la Ciudad de México es un órgano administrativo desconcentrado de la Secretaría de Gobierno, que determina, ejecuta y da seguimiento a las acciones de búsqueda de Personas Desaparecidas, en la Ciudad de México, de conformidad con lo dispuesto en la Ley General, esta Ley y las demás disposiciones jurídicas aplicables, para impulsar los esfuerzos de vinculación, operación, gestión, evaluación y seguimiento de las acciones entre autoridades que participan en la búsqueda, localización e identificación de personas.\nTodas las autoridades de la Ciudad de México, en el ámbito de su competencia están obligadas a colaborar de forma eficaz con la Comisión de Búsqueda para el cumplimiento de esta Ley.\nArtículo 23. La Comisión de Búsqueda está a cargo de una persona titular nombrada y removida por la persona titular de la Jefatura de Gobierno a propuesta de la persona titular de la Secretaría de\nGobierno.\n\nPara el nombramiento a que se refiere el párrafo anterior, la Secretaría de Gobierno realizará una consulta pública previa a los colectivos de Víctimas, personas expertas y organizaciones de la sociedad civil especializadas en la materia.\nPara ser titular se requiere:\nI. Ser ciudadana o ciudadano mexicano;\nII. Derogada\nIII. Contar con título profesional;\nIV. No haber desempeñado cargo de dirigente nacional o estatal en algún partido político, dentro de los dos años previos a su nombramiento;\nV. Haberse desempeñado destacadamente en actividades profesionales, de servicio público, en la sociedad civil o académicas relacionadas con la materia de la ley General y esta Ley, por lo menos en los dos años previos a su nombramiento, y\nVI. Contar con conocimientos y experiencia en derechos humanos, atención a víctimas y búsqueda de personas, y preferentemente con conocimientos en ciencias forenses o investigación criminal.\nEn el nombramiento de la persona titular de la Comisión de Búsqueda, debe garantizar el respeto a los principios que prevé esta Ley, especialmente los de enfoque transversal de género, diferencial y de no discriminación.\nLa persona titular de la Comisión de Búsqueda no podrá tener ningún otro empleo, cargo o comisión, salvo en instituciones docentes, científicas o de beneficencia.\nArtículo 24. Para la consulta pública a la que se hace referencia en el artículo anterior, la Secretaría de\nGobierno deberá observar, como mínimo, las siguientes bases:\nI. Generar un mecanismo a través del cual la ciudadanía presente candidaturas;\nII. Realizar entrevistas públicas a las y los candidatos en las cuales presenten su plan de trabajo;\nIII. Publicar toda la información disponible sobre el perfil de las y los candidatos registrados, y\n\nIV. Hacer público el nombramiento sobre la persona titular de la Comisión de Búsqueda, acompañada de una exposición fundada y motivada sobre la idoneidad del perfil elegido.\nArtículo 25. La Comisión de Búsqueda tiene las siguientes atribuciones:\nI. Emitir y ejecutar el Programa de Búsqueda de la Ciudad de México, el cual deberá ser análogo en lo conducente al Programa Nacional de Búsqueda, rector en la materia;\nII. Ejecutar en la Ciudad de México el Programa Nacional de Búsqueda, de conformidad con la Ley General y esta Ley y ejecutar los lineamientos que regulan el funcionamiento del\nRegistro Nacional, producir y depurar información para satisfacer dicho registro y coordinarse con las autoridades correspondientes, en términos de la Ley General, esta Ley y demás ordenamientos jurídicos aplicables en la materia;\nIII. Atender y formular solicitudes a la Secretaría de Seguridad Ciudadana previstas en la legislación en materia de Seguridad Ciudadana de la Ciudad de México, a efecto de cumplir con su objeto;\nIV. Solicitar el acompañamiento, en términos de lo establecido por la Ley General, de las instancias policiales de los tres órdenes de gobierno cuando sea necesario que el personal de la Comisión de Búsqueda realice trabajos de campo;\nV. Integrar, cada tres meses, un informe sobre los avances y resultados de la aplicación del\nPrograma Nacional de Búsqueda y la verificación y supervisión del Programa de Búsqueda de la Ciudad de México; los informes respectivos, se harán del conocimiento del Sistema de\nBúsqueda;\nVI. Presentar al Consejo de Seguridad Ciudadana de la Ciudad de México, los informes sobre los avances y resultados de la aplicación del Programa Nacional de Búsqueda y de la verificación y supervisión del Programa de Búsqueda de la Ciudad de México, en coordinación con las autoridades competentes;\nVII. Atender los protocolos rectores establecidos por el Sistema Nacional y la Comisión\nNacional;\nVIII. Promover la revisión y actualización del Protocolo Homologado de Búsqueda;\nIX. Emitir opinión respecto del Protocolo Homologado de Investigación, ante las autoridades competentes;\n\nX. Coordinar las acciones de búsqueda de niñas y mujeres que deriven de la Alerta de\nViolencia de Género;\nXI. Diseñar, proponer y aplicar los mecanismos de coordinación y colaboración con las demás dependencias de la Ciudad de México y de los diferentes órdenes de gobierno, a efecto de llevar a cabo las acciones en la búsqueda de Personas Desaparecidas;\nXII. Asesorar y canalizar a los Familiares ante la Fiscalía Especializada para que, de ser el caso, realicen la denuncia correspondiente;\nXIII. Determinar y, en el ámbito de su competencia, ejecutar, las acciones de búsqueda que correspondan, a partir de los elementos con que cuente, de conformidad con el protocolo aplicable. Así como, de manera coordinada con la Comisión Nacional y las demás comisiones locales de búsqueda, realizar y dar seguimiento a las acciones de búsqueda, atendiendo a las características propias del caso, así como a las circunstancias de ejecución o la relevancia social del mismo;\nXIV. Promover la actualización de los protocolos especializados;\nXV. Aplicar los lineamientos emitidos por la Comisión Nacional para acceder, sin restricciones, a la información contenida en plataformas, bases de datos y registros de todas las autoridades para realizar la búsqueda de la Persona Desaparecida, de conformidad con las disposiciones aplicables;\nXVI. Solicitar a los integrantes de la Policía de la Ciudad de México que se realicen acciones específicas de búsqueda de Personas Desaparecidas;\nXVII. Solicitar la colaboración de los tres órdenes de gobierno y otras instancias, para la búsqueda y localización de Personas Desaparecidas;\nXVIII. Mantener comunicación con autoridades federales, locales, municipales o de las\nAlcaldías, y establecer enlaces cuando lo estime pertinente o por recomendación del Consejo\nCiudadano;\nXIX. Integrar grupos de trabajo particulares con objetivos específicos que podrán:\na. Analizar casos individuales y proponer acciones específicas de búsqueda.\n\nb. Analizar el fenómeno de la desaparición a nivel regional, local, por demarcación territorial o colaborar con la Comisión Nacional en el análisis del fenómeno a nivel nacional brindando información sobre el problema en la Ciudad de México.\nXX. Mantener reuniones periódicas y comunicación continua con las personas titulares de las\nComisiones Locales de Búsqueda y la Comisión Nacional a fin de intercambiar experiencias y buscar las mejores prácticas para la localización de personas;\nXXI. Dar aviso de manera inmediata a la Fiscalía Especializada que corresponda sobre la existencia de información relevante y elementos que sean útiles para la investigación de los delitos materia de la Ley General y otras leyes, de conformidad con el Protocolo Homologado de Búsqueda;\nXXII. Colaborar con las instituciones de procuración de justicia en la investigación y persecución de otros delitos;\nXXIII. Solicitar la colaboración de medios de comunicación, organizaciones de la sociedad civil y de la sociedad en general para la búsqueda y localización de Personas Desaparecidas, de conformidad con la normativa aplicable;\nXXIV. Mantener comunicación continua con las Fiscalías Especializadas para la coordinación de acciones de búsqueda y localización, a partir de la información obtenida en la investigación de los delitos materia de la Ley General, esta ley y demás disposiciones aplicables de conformidad con el protocolo homologado de búsqueda;\nXXV. Evaluar y vigilar el cumplimiento de las políticas y estrategias para la búsqueda y localización de Personas Desaparecidas por parte de las instituciones locales;\nXXVI. Conocer y opinar sobre las políticas y estrategias para la identificación de personas localizadas con vida y personas fallecidas localizadas en fosas comunes y clandestinas, notificación y entrega digna de restos humanos, así como vigilar su cumplimiento por parte de las instituciones locales;\nXXVII. Celebrar, de conformidad con las disposiciones aplicables, convenios de coordinación, colaboración y concertación, o cualquier otro instrumento jurídico necesarios para el cumplimiento de los objetivos del Sistema de Búsqueda, así como de sus atribuciones;\nXXVIII. Disponer de un número telefónico, así como de cualquier otro medio de comunicación de acceso gratuito para proporcionar información, sin necesidad de cumplir con formalidad alguna, para contribuir en la búsqueda de Personas Desaparecidas;\n\nXXIX. Solicitar a los concesionarios de radiodifusión y telecomunicaciones, de conformidad con la legislación en la materia, dentro de las transmisiones correspondientes a los tiempos del Estado, y por conducto de la autoridad competente, y previa autorización de los\nFamiliares, la difusión de boletines relacionados con la Búsqueda de Personas\nDesaparecidas;\nXXX. Establecer acciones de búsqueda específicas para las desapariciones de personas vinculadas con movimientos políticos;\nEn caso de que durante las acciones de búsqueda se encuentre algún indicio de la probable comisión de un delito, se dará aviso inmediato a la fiscalía correspondiente;\nXXXI. Diseñar, en colaboración con las comisiones locales de búsqueda que correspondan, programas regionales de búsqueda de personas;\nXXXII Dar seguimiento y, en su caso, atender las recomendaciones de la Comisión Nacional de los Derechos Humanos y la Comisión de Derechos Humanos de la Ciudad de México en los temas relacionados con la búsqueda de personas;\nXXXIII Dar seguimiento y atender a las recomendaciones del Consejo Ciudadano en los temas relacionados con las funciones y atribuciones de la Comisión de Búsqueda;\nXXXIV. Recibir la información que aporten los particulares en los casos de desaparición forzada de personas y desaparición cometida por particulares y remitir a la comisión de búsqueda correspondiente y, en su caso, a la Fiscalía Especializada competente;\nXXXV. Dar vista al Ministerio Público y a las autoridades competentes en materia de responsabilidades administrativas de los servidores públicos, sobre las acciones u omisiones que puedan constituir una violación a esta Ley y demás ordenamientos jurídicos aplicables;\nXXXVI. Establecer mecanismos de comunicación, participación y evaluación con la sociedad civil y los Familiares para que coadyuven con los objetivos, fines y trabajos de la Comisión de\nBúsqueda, en los términos que prevé la Ley General, esta Ley y su reglamento;\nXXXVII. Solicitar a la Comisión de Víctimas que implementen los mecanismos necesarios para que a través del Fondo de Ayuda, Asistencia y Reparación Integral se cubran los Gastos de\nAyuda cuando lo requieran los Familiares de las Personas Desaparecidas, de conformidad con la ley en la materia;\n\nXXXVIII. Recomendar a las autoridades que integran el Sistema de Búsqueda el empleo de técnicas y tecnologías para mejorar las acciones de búsqueda, emitidas por el Sistema\nNacional;\nXXXIX. Elaborar diagnósticos periódicos, por sí o en coordinación con la Fiscalía\nEspecializada, que permitan conocer e identificar modos de operación, prácticas, patrones de criminalidad, estructuras delictivas y asociación de casos que permitan el diseño de acciones estratégicas de búsqueda;\nXL. Elaborar diagnósticos periódicos, por sí o en coordinación con la Fiscalía Especializada, que permitan conocer la existencia de características y patrones de desaparición, de conformidad con el principio de enfoque diferenciado;\nXLI. Suministrar, sistematizar, analizar y actualizar la información de hechos y datos sobre la desaparición de personas, así como de los delitos en materia de la Ley General;\nXLII. Elaborar informes de análisis de contexto que incorporen a los procesos de búsqueda elementos sociológicos, antropológicos y victimológicos, a fin de fortalecer las acciones de búsqueda;\nXLIII. Realizar las acciones necesarias para recabar y cruzar la información contenida en las bases de datos y registros que establece la Ley General y esta Ley, así como con la información contenida en otros sistemas que puedan contribuir en la búsqueda, localización e identificación de una Persona Desaparecida;\nXLIV. Tomar las acciones necesarias a efecto de garantizar la búsqueda de personas en toda la Ciudad de México;\nXLV. Promover, ante las autoridades competentes, las medidas necesarias para lograr la protección de aquellas personas desaparecidas cuya vida, integridad o libertad se encuentre en peligro;\nXLVI. Proponer políticas públicas en materia de búsqueda de personas;\nXLVII. Apoyarse de los sistemas tecnológicos que se implementen en la Ciudad de México, que puedan contribuir para la búsqueda y localización personas;\nXLVIII. Comparecer al menos una vez al año ante la Comisión de Atención Especial a Víctimas del Congreso de la Ciudad de México y cada que este último se lo requiera; y\nXLIX. Las demás que prevea la Ley General, esta Ley, y demás disposiciones aplicables.\n\nArtículo 26. En la integración y operación de los grupos de trabajo para proponer acciones específicas de búsqueda, así como analizar el fenómeno de desaparición, la Comisión de Búsqueda tiene las siguientes atribuciones:\nI. Determinar las personas servidoras públicas que deben integrar los grupos, en cuyo caso podrá solicitar, cuando lo estime pertinente, la participación de autoridades de los tres órdenes de gobierno;\nII. Coordinar el funcionamiento de los grupos de trabajo;\nIII. Solicitar al área de análisis de contexto informes para el cumplimiento de sus facultades, y\nIV. Disolver los grupos de trabajo cuando hayan cumplido su finalidad.\nArtículo 27. La Comisión de Búsqueda para el ejercicio de sus facultades contará con las siguientes herramientas:\nI. El Registro Nacional, a través de la Comisión Nacional de Búsqueda;\nII. El Registro de Personas Desaparecidas;\nIII. El Banco Nacional de Datos Forenses, a través de la Fiscalía General de la República;\nIV. El Registro Nacional de Personas Fallecidas No Identificadas y No Reclamadas, a través de la Fiscalía General de la República;\nV. El Registro de Personas Fallecidas;\nVI. El Registro Nacional de Fosas, a través de la Fiscalía General de la República;\nVII. El Registro de Fosas;\nVIII. El Registro Nacional de Detenciones, a través de la Secretaría de Seguridad y Protección\nCiudadana;\nIX. La Alerta Amber;\nX. El Protocolo Alba;\n\nXI. La Alerta Plateada;\nXII. El Protocolo Homologado de Búsqueda y los protocolos previstos en el artículo 73 de la\nLey General; y\nXIII. Otros registros necesarios para su operación, en términos de lo que prevé esta Ley.\nArtículo 28. Las personas servidoras públicas integrantes de la Comisión de Búsqueda deben estar certificadas y especializadas en materia de búsqueda, de conformidad con los criterios que establezca el Sistema Nacional a que hace referencia la Ley General.\nArtículo 29. Los informes sobre los avances y resultados de la aplicación del Programa Nacional de\nBúsqueda y la verificación y supervisión del Programa de Búsqueda, deben contener, al menos, lo siguiente:\nI. Avance en el cumplimiento de los objetivos del Programa de Búsqueda de la Ciudad de\nMéxico con información del número de personas reportadas como desaparecidas, víctimas de los delitos materia de la Ley General; número de personas localizadas, con vida y sin vida;\ncadáveres o restos humanos que se han localizado e identificado; circunstancias de modo, tiempo y lugar de la localización;\nII. Resultados de la gestión de la Comisión de Búsqueda;\nIII. Avance en la implementación y adecuado cumplimiento del Protocolo Homologado de\nBúsqueda a que se refiere el artículo 99 de la Ley General;\nIV. Resultado de la evaluación del funcionamiento en la Ciudad de México del sistema al que se refiere el artículo 49, fracción II, de la Ley General; y\nV. Las demás que señalen los Reglamentos aplicables.\nArtículo 30. El Consejo de Seguridad Ciudadana de la Ciudad de México, de conformidad con la legislación en materia de Seguridad Ciudadana aplicable, analizará los informes sobre los avances y resultados de la verificación y supervisión en la ejecución de los programas previstos en esta Ley, a fin de adoptar en coordinación con el Sistema de Búsqueda todas aquellas medidas y acciones que se requieran para su cumplimiento.\nArtículo 31. La Comisión de Búsqueda para realizar sus actividades, debe contar como mínimo con:\n\nI. Área de búsqueda, cuyas funciones están previstas en el artículo 66 de la Ley General.\nDicha área estará integrada por personas servidoras públicas especializadas en búsqueda de personas;\nII. Área de Análisis de Contexto y Procesamiento de Información, la cual desempeñará, además de las funciones que la Ley General y otras disposiciones jurídicas prevean;\nIII. Área de Gestión, Vinculación y Atención a Familiares, la cual desempeñará, además de las funciones que la Ley General y otras disposiciones jurídicas le asignen; y\nIV. La estructura sustantiva y administrativa necesaria para el cumplimiento de sus funciones.\nArtículo 32. A efecto de determinar la ubicación de la Persona Desaparecida, las autoridades o instituciones, públicas o privadas, tienen la obligación de informar en tiempo real a través del mecanismo que para ello defina la Comisión de Búsqueda, el ingreso y egreso de las personas, así como de las personas no identificadas o de las cuales no se tenga la certeza de su identidad del ingreso y egreso a sus establecimientos o instituciones. Dicho mecanismo estará conformado con la información que se proporcione a través de las bases de datos o registros de Hospitales, clínicas, centros de atención psiquiátrica, centros de Desarrollo Integral para la Familia, centros de salud, centros de atención de adicciones y rehabilitación, todos ellos públicos o privados, además de los\nCentros de detención y reclusorios a cargo del sistema penitenciario de la Ciudad de México, los registros de los centros de detención administrativos de la Ciudad de México, los Servicios Médicos\nForenses y banco de datos forenses, el Registro de Personas Fallecidas, Albergues públicos y privados, e instituciones de asistencia social, en términos de la Ley de Asistencia e Integración Social del Distrito\nFederal, Panteones o lugares en los que se depositan restos mortales o cadáveres, públicos y privados, identidad de personas y los demás registros y bases de datos que contengan información que pueda contribuir a la localización e identificación de las personas, en términos de las disposiciones jurídicas aplicables.\nLa Comisión de Búsqueda proporcionará asistencia a las autoridades o instituciones, públicas o privadas, para la implementación y operación de dicho mecanismo.\nArtículo 33.- Los establecimientos que presten servicios de salud, los profesionales, técnicos y auxiliares de la salud, que realicen las actividades a que se refieren los Títulos décimo segundo y décimo cuarto de la Ley General de Salud, llevarán las estadísticas que les señalen la Secretaría de\nSalud Federal y Local, proporcionarán a éstas, a la Comisión de Búsqueda y a la Fiscalía Especializada, la información a la que hace referencia el artículo anterior, sin perjuicio de las obligaciones de suministrar la información que les señalen otras disposiciones legales.\n\nCAPÍTULO TERCERO\nDel Consejo Ciudadano\nArtículo 34. El Consejo Ciudadano es un órgano de consulta de la Comisión de Búsqueda, en materia de búsqueda de personas.\nArtículo 35. El Consejo Ciudadano está integrado por:\n1. Cinco Familiares;\n2. Cuatro especialistas de reconocido prestigio y con experiencia comprobable en la protección y defensa de los derechos humanos, la búsqueda de Personas Desaparecidas o en la investigación y persecución de los delitos previstos en la Ley General. Se garantizará que una de las personas especialistas siempre sea en materia forense, y\n3. Cuatro representantes de organizaciones de la sociedad civil de defensa de víctimas y de derechos humanos materia de esta Ley.\nLos integrantes a que se refieren las fracciones anteriores deben ser nombrados por el Congreso de la\nCiudad de México a través de la Comisión de Atención Especial a Víctimas, previa consulta pública con las organizaciones de Familiares, de las organizaciones defensoras de víctimas y de los derechos humanos, de los grupos organizados de Víctimas y expertos en las materias de la Ley General.\nLa duración de su función será de tres años, sin posibilidad de reelección, y no deberán desempeñar ningún cargo en el servicio público.\nArtículo 36. Las personas integrantes del Consejo Ciudadano ejercerán su función en forma honorífica, y no deben recibir emolumento o contraprestación económica alguna por su desempeño.\nLas personas integrantes del Consejo Ciudadano deben elegir a quien coordine los trabajos de sus sesiones, por mayoría de votos, quien durará en su encargo un año.\nEl Consejo Ciudadano emitirá sus reglas de funcionamiento en las que determinará los requisitos y procedimientos para nombrar a su Secretario Técnico, la convocatoria a sus sesiones bimestrales y contenidos del orden del día de cada sesión.\nLas recomendaciones, propuestas y opiniones del Consejo Ciudadano deberán ser comunicadas a la\nComisión de Búsqueda y a las autoridades del Sistema de Búsqueda y podrán ser consideradas para la toma de decisiones.\n\nLa Secretaría de Gobierno de la Ciudad de México proveerá al Consejo Ciudadano de los recursos financieros, técnicos, de infraestructura y humanos necesarios para el desempeño de sus funciones.\nArtículo 37. El Consejo Ciudadano tiene las funciones siguientes:\nI. Proponer a la Comisión Búsqueda y a las autoridades del Sistema de Búsqueda acciones para acelerar o profundizar sus acciones, en el ámbito de sus competencias;\nII. Proponer acciones a las instituciones que forman el Sistema de Búsqueda para ampliar sus capacidades, incluidos servicios periciales y forenses;\nIII. Proponer acciones para mejorar el funcionamiento de los programas, registros, bancos y herramientas materia de la Ley General y de esta Ley;\nIV. Proponer y, en su caso, acompañar las medidas de asistencia técnica para la búsqueda de personas;\nV. Solicitar información a cualquier integrante de la Comisión de Búsqueda y del Sistema de\nBúsqueda, para el ejercicio de sus atribuciones, y hacer las recomendaciones pertinentes;\nVI. Acceder a la información estadística generada a través de las diversas herramientas con las que cuenta la Comisión de Búsqueda y las autoridades que integran el Sistema de\nBúsqueda para el ejercicio de sus atribuciones;\nVII. Contribuir en la promoción de las acciones, políticas públicas, programas y proyectos relacionados con el objeto de la Ley General y de esta Ley;\nVIII. Dar vista a las autoridades competentes y órganos internos de control sobre las irregularidades en las actuaciones de las personas servidoras públicas relacionadas con la búsqueda e investigación de Personas Desaparecidas. Se le reconocerá interés legítimo dentro de las investigaciones para la determinación de responsabilidades de las personas servidoras públicas relacionadas con la búsqueda e investigación de Personas Desaparecidas en términos de las disposiciones jurídicas aplicables;\nIX. Emitir recomendaciones sobre la integración y operación de la Comisión de Búsqueda y el\nSistema de Búsqueda;\nX. Elaborar, aprobar y modificar la Guía de procedimientos del Comité, y\n\nXI. Las demás que señale el Reglamento.\nArtículo 38. Las decisiones que el Consejo Ciudadano adopte son públicas, en apego a la legislación de transparencia y protección de datos personales.\nArtículo 39. El Consejo Ciudadano integrará de entre sus miembros un Comité para la evaluación y seguimiento de las acciones emprendidas por la Comisión de Búsqueda, que tendrá las siguientes atribuciones:\nI. Solicitar información relacionada a los procedimientos de búsqueda y localización a la\nComisión de Búsqueda;\nII. Conocer y emitir recomendaciones sobre los criterios de idoneidad, convenios, lineamientos, programas y reglamentos que emita la Comisión de Búsqueda;\nIII. Dar seguimiento a la implementación en la Ciudad de México del Programa Nacional y del\nPrograma de Búsqueda de la Ciudad de México y del Programa Nacional de Exhumaciones e\nIdentificación Forense;\nIV. Contribuir, de acuerdo a lo establecido en la Ley General, la presente Ley, y disposiciones aplicables, a la participación directa de los Familiares en el ejercicio de sus atribuciones, y\nV. Las demás que determine el Consejo Ciudadano, en el marco de sus atribuciones.\nCAPÍTULO CUARTO\nDe los Grupos de Búsqueda\nArtículo 40. La Comisión de Búsqueda contará con, al menos, un Grupo de Búsqueda en cada demarcación territorial, integrado por personas servidoras públicas especializadas en la búsqueda, tanto del Gobierno de la Ciudad de México como de la Alcaldía respectiva, los cuales deberán quedar instalados en un plazo no mayor a 30 días hábiles siguientes a la toma de protesta de la Alcaldesa o el Alcalde de cada una de las demarcaciones territoriales.\nLas personas servidoras públicas que integren los Grupos de Búsqueda deberán ser capacitadas en un periodo no mayor a 60 días hábiles siguientes a la toma de protesta de la Alcaldesa o Alcalde de cada una de las demarcaciones territoriales.\nLos mecanismos, principios y materia de capacitación para las personas Servidoras Públicas que integren los Grupos de Búsqueda en cada Alcaldía serán determinados por la Comisión de Búsqueda.\n\nCon independencia de lo anterior, la Comisión de Búsqueda podrá auxiliarse por personas especializadas en búsqueda de personas, familiares, colectivos y organizaciones de la sociedad civil especializadas, así como por cuerpos policiales especializados que colaboren con las autoridades competentes, en términos de las disposiciones aplicables.\nLos cuerpos especializados, así como toda persona servidora pública que sea requerida, deberá colaborar con la Comisión de Búsqueda, en términos de las disposiciones legales aplicables\nArtículo 41. Los Grupos de Búsqueda, para el adecuado cumplimiento de sus acciones, tienen las siguientes atribuciones:\nI. Generar la metodología para la búsqueda inmediata considerando el Protocolo Homologado de Búsqueda y otros existentes;\nII. Solicitar a la fiscalía competente que realice actos de investigación específicos sobre la probable comisión de un delito que puedan llevar a la búsqueda, localización o identificación de una persona, así como al esclarecimiento de los hechos en términos de lo dispuesto en el\nCódigo Nacional de Procedimientos Penales. Lo anterior, sin perjuicio del ejercicio directo de las facultades con que cuentan la Comisión de Búsqueda para realizar acciones relacionadas con la búsqueda de personas previstas en esta ley;\nIII. Implementar un mecanismo ágil y eficiente que coadyuve a la pronta localización de personas reportadas como desaparecidas y salvaguarde sus derechos humanos, y\nIV. Garantizar, en el ámbito de sus competencias, que se mantenga la cadena de custodia en el lugar de los hechos o hallazgo, así como en los que se encuentren o se tengan razones fundadas para creer que se encuentran cadáveres o restos humanos de Personas\nDesaparecidas.\nArtículo 42. La Secretaria de Seguridad Ciudadana, en el ámbito de sus respectivas competencias, debe contar y garantizar la disponibilidad inmediata de personal especializado y capacitado en materia de búsqueda de personas. Dicho personal debe atender, de forma inmediata, las solicitudes de la Comisión de Búsqueda según corresponda.\nEl personal al que se refiere el párrafo anterior, además de cumplir con la certificación respectiva, debe acreditar los criterios de idoneidad que emita la Comisión Nacional.\n\nCAPÍTULO QUINTO\nDe la Fiscalía Especializada\nArtículo 43. La Fiscalía General de Justicia de la Ciudad de México deberá contar con la Fiscalía\nEspecializada para la investigación y persecución de los delitos de desaparición forzada de personas y desaparición cometida por particulares, la que deberá coordinarse interinstitucionalmente y dar impulso permanente a la búsqueda de Personas Desaparecidas.\nLa Fiscalía Especializada a que se refiere el primer párrafo de este artículo debe contar con los recursos humanos, financieros, materiales y técnicos especializados y multidisciplinarios y una unidad de análisis de contexto que se requieran para su efectiva operación, entre los que deberá contar con personal sustantivo ministerial, policial, pericial y de apoyo psicosocial.\nTodas las autoridades, en el ámbito de sus competencias, están obligadas a colaborar de forma eficaz con la Fiscalía Especializada para el cumplimiento de la Ley.\nArtículo 44. Las personas servidoras públicas que integren la Fiscalía Especializada deberán cumplir, como mínimo, los siguientes requisitos:\nI. Tener acreditados los requisitos de ingreso y permanencia de la institución respectiva, de conformidad con la legislación en materia de Seguridad Ciudadana y de Procuración de\nJusticia para la Ciudad de México;\nII. Tener el perfil que establezca la Fiscalía General de Justicia, y\nIII. Acreditar los cursos de especialización, capacitación y de actualización que establezca la\nFiscalía General de Justicia, según corresponda.\nLa Fiscalía General de Justicia de la Ciudad de México debe capacitar, conforme a los más altos estándares internacionales, a las personas servidoras públicas adscritas a la Fiscalía General en materia de atención a víctimas, de derechos humanos, perspectiva de género, interés superior de la niñez, sensibilización y relevancia específica de la Desaparición de Personas, aplicación del Protocolo\nHomologado para la investigación, identificación forense, cadena de custodia, entre otros. De igual forma, podrán participar con las autoridades competentes, en la capacitación de las personas servidoras públicas conforme a los lineamientos que sobre la materia emita el Sistema de Búsqueda, en términos de la Ley General y de esta ley.\nArtículo 45. La Fiscalía Especializada tiene, en el ámbito de su competencia, las atribuciones siguientes:\n\nI. Recibir las denuncias relacionadas con la probable comisión de hechos constitutivos de los delitos materia de la Ley General y de esta Ley e iniciar la carpeta de investigación correspondiente;\nII. Mantener coordinación con la Comisión de Búsqueda para realizar todas las acciones relativas a la investigación y persecución de los delitos materia de la Ley General, conforme al Protocolo Homologado de Investigación y demás disposiciones aplicables;\nIII Dar aviso de manera inmediata, a través del Registro correspondiente, a la Comisión de\nBúsqueda sobre el inicio de una investigación de los delitos materia de la Ley General, a fin de que se inicien las acciones correspondientes a la búsqueda; así como compartir la información relevante, de conformidad con el Protocolo Homologado de Investigación y demás disposiciones aplicables;\nIV. Mantener comunicación continua y permanente con la Comisión de Búsqueda, a fin de compartir información que pudiera contribuir en las acciones para la búsqueda y localización de personas, en términos de las disposiciones aplicables;\nV. Informar de manera inmediata a la Comisión de Búsqueda, la localización o identificación de una Persona;\nVI. Solicitar directamente la localización geográfica en tiempo real o la entrega de los datos conservados, en los términos establecidos en el Código Nacional de Procedimientos Penales;\nVII. Requerir a la persona titular de la Fiscalía General, solicite la autorización para ordenar la intervención de comunicaciones, en términos de las disposiciones aplicables;\nVIII. Realizar y comunicar sin dilación todos aquellos actos que requieran de autorización judicial que previamente hayan sido solicitados por la Comisión que corresponda para la búsqueda y localización de una Persona Desaparecida;\nIX. Solicitar el apoyo policial a las autoridades competentes, para realizar las tareas de investigación en campo;\nX. Recabar la información necesaria para la persecución e investigación de los delitos previstos en la Ley General;\nXI. Remitir la investigación y las actuaciones realizadas a las autoridades competentes cuando advierta la comisión de uno o varios delitos diferentes a los previstos en la Ley\nGeneral;\n\nXII. Solicitar al Juez de Control competente las medidas cautelares que sean necesarias, de conformidad con el Código Nacional de Procedimientos Penales;\nXIII. Solicitar la participación de la Comisión de Víctimas; así como a las instituciones y organizaciones de derechos humanos y de protección civil, en los términos de las disposiciones jurídicas aplicables;\nXIV. Establecer mecanismos de cooperación destinados al intercambio de información y adiestramiento continuo de los servidores públicos especializados en la materia;\nXV. Localizar a las familias de las personas fallecidas identificadas no reclamadas, en coordinación con las instituciones correspondientes, para poder hacer la entrega digna y humana, de cadáveres o restos humanos, conforme a lo señalado por el Protocolo\nHomologado de Investigación y demás protocolos en la materia aplicables;\nXVI. Solicitar a las autoridades jurisdiccionales competentes la autorización para la realización de las exhumaciones en cementerios, fosas o de otros sitios en los que se encuentren o se tengan razones fundadas para creer que se encuentran cadáveres o restos humanos de Personas Desaparecidas;\nXVII. Solicitar a las autoridades jurisdiccionales competentes el traslado de las personas internas a otros centros de reclusión salvaguardando sus derechos humanos, siempre que esta medida favorezca la búsqueda o localización de las Personas Desaparecidas o a la investigación de los delitos materia de la Ley General, en términos de la Ley Nacional de\nEjecución Penal;\nXVIII. Facilitar la participación de los Familiares en la investigación de los delitos previstos en la Ley General, incluido brindar información periódicamente a los Familiares sobre los avances en el proceso de la investigación y persecución de los delitos previstos en la Ley\nGeneral en términos del Código Nacional de Procedimientos Penales;\nXIX. Celebrar convenios de colaboración o cooperación, para el óptimo cumplimiento de las atribuciones que le corresponden de conformidad con la presente Ley;\nXX. Brindar la información que la Comisión de Búsqueda le solicite para mejorar la búsqueda de personas, en términos de lo que establezcan las disposiciones aplicables;\nXXI. Brindar la información que la Comisión de Víctimas le solicite para mejorar la atención a las víctimas, en términos de lo que establezcan las disposiciones aplicables;\n\nXXII. Brindar la información que el Consejo Ciudadano le solicite para el ejercicio de sus funciones, en términos de lo que establezcan las disposiciones aplicables; y\nXXIII. Las demás que establezcan otras disposiciones jurídicas aplicables.\nArtículo 46. La Fiscalía Especializada de la Fiscalía General de Justicia la Ciudad de México remitirá inmediatamente a la Fiscalía Especializada en Investigación de los Delitos de Desaparición Forzada de la Fiscalía General de la República los expedientes de los que conozcan cuando se actualicen los supuestos previstos en el artículo 24 de la Ley General, o iniciar inmediatamente la carpeta de investigación, cuando el asunto no esté contemplado expresamente como competencia de la\nFederación.\nArtículo 47. La persona servidora pública que sea señalada como imputada por el delito de desaparición forzada de personas, y que por razón de su encargo o influencia pueda interferir u obstaculizar las acciones de búsqueda o las investigaciones, podrá ser sujeto de medidas cautelares como la suspensión temporal de su encargo, entre otras, por la autoridad jurisdiccional competente, de conformidad con lo establecido en el Código Nacional de Procedimientos Penales.\nAdicionalmente a lo previsto en el párrafo anterior, el superior jerárquico adoptará las medidas administrativas y adicionales necesarias para impedir que la persona servidora pública interfiera con las investigaciones.\nArtículo 48. La Fiscalía Especializada deberá generar criterios y metodología específica para la investigación y persecución de los delitos de desaparición forzada de personas. En el caso de las desapariciones forzadas por motivos políticos de décadas pasadas, de conformidad con el Protocolo\nHomologado de Investigación, la Ley General y esta Ley, las Fiscalías Especializadas deberán emitir criterios y metodología específicos que deberán permitir realizar, al menos, lo siguiente:\nA) Los procedimientos de búsqueda permanente que se lleven a cabo para buscar personas en cualquier lugar donde se presuma pudieran estar privadas de libertad como son centros penitenciarios, centros clandestinos de detención, estaciones migratorias, centros de salud y cualquier otro lugar en donde se pueda presumir pueda estar la persona desaparecida;\nB) Cuando se sospeche que la víctima ha sido privada de la vida, realizar las diligencias pertinentes para la exhumación de los restos en los lugares que se presume pudieran estar, de acuerdo a los estándares internacionales, siendo derecho de los Familiares y demás víctimas indirectas solicitar la participación de peritos especializados independientes, en términos de las disposiciones legales aplicables. En la generación de los criterios y metodología específicos, se tomarán en cuenta las sentencias y resoluciones nacionales e internacionales en materia de búsqueda e investigación de los casos de desaparición forzada.\n\nArtículo 49. La Fiscalía Especializada debe continuar sin interrupción la investigación de los delitos previstos en la Ley General, en términos de lo que establezca el Protocolo Homologado de Investigación y el Código Nacional de Procedimientos Penales.\nArtículo 50. Las autoridades de todos los órdenes de gobierno están obligadas a proporcionar, en el ámbito de su competencia, el auxilio e información que la Fiscalía Especializada les solicite para la investigación y persecución de los delitos previstos en la Ley General.\nArtículo 51. Las personas físicas o jurídicas que cuenten con información que pueda contribuir a la investigación y persecución de los delitos previstos en la Ley General, están obligadas a proporcionarla a la Fiscalía Especializada directamente o a través de cualquier otro medio.\nArtículo 52. La Fiscalía Especializada no puede condicionar la recepción de la información a que se refiere el párrafo anterior al cumplimiento de formalidad alguna.\nCAPÍTULO SEXTO\nDe la Búsqueda de Personas\nArtículo 53. La búsqueda tendrá por objeto realizar todas las acciones y diligencias tendientes para dar con la suerte o el paradero de la persona hasta su localización, incluidas aquellas para identificar plenamente sus restos en caso de que estos hayan sido localizados.\nLa búsqueda a que se refieren la Ley General y la presente Ley se realizará de forma conjunta, coordinada y simultánea entre la Comisión de Búsqueda y la Comisión Nacional.\nLos mecanismos de búsqueda deberán agotarse totalmente hasta que se determine la suerte o paradero de la persona. En coordinación con la Comisión Nacional, la Comisión de Búsqueda garantizará que los mecanismos se apliquen conforme a las circunstancias propias de cada caso, de conformidad con la Ley General, el Protocolo Homologado de Búsqueda y los lineamientos correspondientes.\nCualquier fiscalía o Ministerios Público tiene la obligación sin dilación de recibir las denuncias relacionadas con la probable comisión de hechos constitutivos de los delitos materia de la Ley General y de esta Ley y remitir de manera inmediata a la Fiscalía Especializada.\nArtículo 54. Las acciones y procedimientos de búsqueda, localización e identificación de Personas\nDesaparecidas, deberán realizarse de conformidad con los Capítulos Sexto y Séptimo del Título Tercero\n\nde la Ley General, los Protocolos Homologados de Búsqueda e Investigación y los Lineamientos correspondientes.\nLa investigación y persecución de los delitos previstos por la Ley General se hará conforme a ésta y a los Protocolos a los que hace referencia el artículo 99 de la misma.\nCAPÍTULO SÉPTIMO\nDe los Registros de la Ciudad de México\nApartado Primero\nDel Registro de Personas Desaparecidas en la Ciudad de México\nArtículo 55. El Registro es una herramienta de búsqueda e identificación que organiza y concentra la información sobre Personas Desaparecidas, con el objeto de proporcionar apoyo en las investigaciones para su búsqueda, localización e identificación; el Registro de Personas Desaparecidas se conforma con la información que recaban las autoridades de la Administración Pública Local y la Fiscalía General.\nEl Registro contendrá un apartado de consulta accesible al público en general y dispondrá de espacios de buzón para recibir información que se proporcione por el público en general, respecto de Personas\nDesaparecidas.\nArtículo 56. Corresponde a la Comisión de Búsqueda administrar, y coordinar la operación del Registro de Personas Desaparecidas.\nEs obligación de las autoridades de la Ciudad de México recabar la información para el Registro de\nPersonas Desaparecidas y proporcionar dicha información a la Comisión de Búsqueda de manera inmediata, en términos de lo que establece esta Ley y su reglamento.\nArtículo 57. El Registro de Personas Desaparecidas debe estar interconectado con las herramientas de búsqueda e identificación previstas en la Ley General y esta Ley y ser actualizado en tiempo real, mediante personal designado y capacitado para ello. La información deberá ser recabada de conformidad con el Protocolo Homologado de Búsqueda.\nLa Fiscalía Especializada competente debe actualizar el Registro de Personas Desaparecidas, indicando si la carpeta corresponde al delito de desaparición forzada de personas o desaparición cometida por particulares. Si de las investigaciones se desprende que se trata de un delito diferente a los previstos en la Ley General, así se hará constar en el Registro de Personas Desaparecidas actualizando el estado del folio, sin perjuicio de que continúe la investigación correspondiente.\n\nSi la Persona Desaparecida ha sido encontrada viva o si fueron encontrados sus restos, se dará de baja del Registro de Personas Desaparecidas y se dejará constancia de ello, sin perjuicio del seguimiento de la investigación correspondiente.\nArtículo 58. El Registro de Personas Desaparecidas debe contener como mínimo los campos establecidos en el artículo 106 de la Ley General. Cuando la autoridad competente genere un registro debe de asignar un folio único que deberá proporcionar a la persona que realizó el Reporte, Denuncia o Noticia. Asimismo, se debe incorporar toda la información novedosa que resulte de las diligencias de búsqueda o investigación.\nArtículo 59. Los datos obtenidos inicialmente a través de la Denuncia, Reporte o Noticia deberán asentarse en el Registro de Personas Desaparecidas de manera inmediata. Los datos e información que no puedan ser asentados de forma inmediata o que por su naturaleza requieran de un procedimiento para su obtención previsto en los protocolos a que se refiere esta Ley, deberán ser recabados por personal debidamente capacitado. Asimismo, se deberán llevar a cabo una o más entrevistas con Familiares de la Persona Desaparecida, o con las víctimas indirectas, de conformidad con el protocolo homologado que corresponda, con el fin de obtener la información detallada sobre la persona. Una vez que se recabe la información deberá incorporarse inmediatamente al Registro de\nPersonas Desaparecidas.\nEl personal que lleve a cabo las entrevistas para la obtención de datos forenses deberá ser capacitado en atención psicosocial. En caso de que la persona que denuncie o reporte la desaparición de una persona, desconozca información para su incorporación en el registro, se asentará en el reporte y no podrá negarse el levantamiento de su Reporte o Denuncia.\nArtículo 60. Los datos personales contenidos en el Registro de Personas Desaparecidas deben ser utilizados con el fin de determinar la suerte o paradero de la Persona Desaparecida y esclarecer los hechos. Los Familiares que aporten información para el Registro de Personas Desaparecidas tendrán el derecho a manifestar que dicha información sea utilizada exclusivamente para la búsqueda e identificación de la Persona Desaparecida. Los Familiares deberán ser informados sobre este derecho antes de proporcionar la información. De igual forma, podrán solicitar que no se haga pública la información de la Persona Desaparecida a que se refieren los incisos a) al g) de la fracción II del artículo\n106 de la Ley General por motivos de seguridad.\nLas muestras biológicas y perfiles genéticos únicamente podrán ser utilizados para la búsqueda e identificación de Personas Desaparecidas.\nArtículo 61. El Registro de Personas Desaparecidas puede ser consultado en su versión pública, a través de la página electrónica que para tal efecto establezca la Comisión de Búsqueda, de conformidad con\n\nlo que determine el protocolo respectivo y las disposiciones jurídicas aplicables en materia de transparencia y protección de datos personales.\nArtículo 62. El Registro de Personas Desaparecidas deberá contener como mínimo los siguientes criterios de clasificación de Personas Localizadas:\nI. Persona localizada que no fue víctima de ningún delito;\nII. Persona localizada víctima de un delito materia de la Ley General, y\nIII. Persona localizada víctima de un delito diverso.\nApartado Segundo\nDel Registro de Personas Fallecidas No Identificadas y No\nReclamadas en la Ciudad de México\nArtículo 63. El Registro de Personas Fallecidas y No Identificadas es una herramienta de búsqueda e identificación. La información contenida se actualiza en tiempo real por parte de los servicios periciales o los servicios médicos forenses de la Ciudad de México, en cuanto se recabe la información, de conformidad con los lineamientos aplicables o el protocolo que corresponda. Para cumplir con sus\nObligaciones de búsqueda, la Comisión de Búsqueda puede consultar en cualquier momento este registro.\nArtículo 64. El Registro de Personas Fallecidas No Identificadas y No Reclamadas se encuentra a cargo de la Fiscalía General, formará parte de los datos que se enviarán al Registro Nacional Personas\nFallecidas No Identificadas y No Reclamadas, que contiene información sobre los datos forenses de los cadáveres o restos de personas no identificadas y no reclamadas, del lugar del hallazgo, el lugar de inhumación o destino final y demás información relevante para su posterior identificación.\nEl Registro de Personas Fallecidas y No Identificadas se integra con la información proporcionada por el Instituto de Ciencias Forenses y demás autoridades competentes. El objetivo de este Registro de\nPersonas Fallecidas y No Identificadas es el de concentrar la información que permita la identificación de las personas fallecidas no identificadas y apoyar en la localización de los Familiares de personas fallecidas no reclamadas.\nArtículo 65. El Registro de Personas Fallecidas deberá contener como mínimo los campos establecidos en el artículo 112 de la Ley General; una vez que se logra la identificación del cadáver o de los restos de la persona, la Fiscalía Especializada deberá notificar a los Familiares de la persona fallecida de acuerdo con el Protocolo Homologado de Investigación y los demás protocolos aplicables.\n\nLas autoridades tendrán la obligación de identificar y localizar a los Familiares de la persona fallecida.\nEn caso de que no se pueda identificar o localizar a algún familiar, la información contenida en este registro deberá enviarse al subregistro de personas identificadas no reclamadas, a fin de iniciar el proceso de localización de Familiares conforme al protocolo correspondiente. Una vez realizada la identificación positiva, la notificación a las familias y la aceptación de las familias del resultado o que se haya realizado el peritaje independiente solicitado, se podrán hacer las modificaciones respectivas al Registro de Personas Desaparecidas y cesar las acciones de búsqueda, sin perjuicio del derecho de los Familiares de interponer los recursos legales correspondientes para impugnar la identificación.\nArtículo 66. El personal de servicios periciales y servicios médicos forenses deberá estar permanentemente capacitado y actualizado de conformidad con el protocolo que corresponda.\nArtículo 67. La Comisión de Búsqueda, la Fiscalía Especializada y de los servicios periciales y servicios médicos forenses se encuentran obligados a realizar las acciones pertinentes para la verificación de una probable hipótesis de identificación a partir de la información contenida en los registros previstos en la Ley general y esta Ley, dejando constancia del resultado.\nArtículo 68. La información contenida en el Registro de Personas Fallecidas y No Identificadas estará sujeta a las disposiciones en materia de protección de datos personales y se utilizará únicamente para lograr la identificación de las personas fallecidas.\nLos Familiares tendrán siempre el derecho de solicitar la información contenida en este registro a través de la Comisión de Búsqueda o la Fiscalía Especializada, de conformidad con las disposiciones legales aplicables.\nArtículo 69. El Registro de Personas Fallecidas y No Identificadas deberá contar con las herramientas tecnológicas necesarias para permitir la interrelación con otros registros, el resguardo y la confiabilidad de la información.\nArtículo 70. Ninguna autoridad podrá ordenar la inhumación, en fosas comunes, de cadáveres o restos humanos sin identificar, antes de cumplir obligatoriamente con lo que establece el protocolo homologado aplicable.\nCAPÍTULO OCTAVO\nDe la Disposición de Cadáveres de Personas\n\nArtículo 71. La Fiscalía Especializada deberá contar con un Registro de Fosas Comunes y de Fosas\nClandestinas en la Ciudad de México que concentrará la información de las que existen en los cementerios y panteones de las dieciséis demarcaciones territoriales de la capital, así como de las\nFosas Clandestinas que localicen en la entidad la Fiscalía General o la Fiscalía Especializada; que estará interconectado en tiempo real con el Registro Nacional de Fosas.\nArtículo 72. Los servicios periciales y los servicios médicos forenses de la Fiscalía General deben capturar en el Registro de Personas Fallecidas, la información que recaben, de conformidad con la Ley\nGeneral y el protocolo homologado.\nLos cadáveres o restos de personas cuya identidad se desconozca o no hayan sido reclamados no pueden ser incinerados, destruidos o desintegrados, ni disponerse de sus pertenencias. La Fiscalía\nGeneral debe tener el registro del lugar donde sean colocados los cadáveres o restos de personas cuya identidad se desconozca o no hayan sido reclamados.\nCuando las investigaciones revelen la identidad del cadáver o los restos de la persona, el agente del\nMinisterio Público competente autorizará que los Familiares dispongan de él y de sus pertenencias de manera inmediata, salvo que sean necesarios para continuar con las investigaciones o para el correcto desarrollo del proceso penal, en cuyo caso dictará las medidas correspondientes debidamente fundas y motivadas.\nEn caso de emergencia sanitaria o desastres naturales, se adoptarán las medidas que establezcan la\nSecretaría de Salud Federal, la Secretaría de Salud y la Secretaría de Gestión Integral de Riesgos y\nProtección Civil, ambas de la Ciudad de México.\nArtículo 73. Una vez recabadas las muestras necesarias para el ingreso en los Registros correspondientes de acuerdo a lo señalado por la Ley General, Ley General de Salud y esta Ley, la\nFiscalía General, podrá autorizar la inhumación de un cadáver o resto humano no identificado. En caso de inhumación, se tomarán las medidas necesarias para asegurar que ésta sea digna, en una fosa individualizada, con las medidas que garanticen toda la información requerida para el adecuado registro y en un lugar claramente identificado que permita su posterior localización.\nArtículo 74. La Fiscalía General deberá mantener comunicación permanente con el Instituto de Ciencias\nForenses para organizar la trazabilidad y la localización de las personas fallecidas sin identificar en los términos señalados por la Ley General, La Ley General de Salud, esta Ley, la Ley de Víctimas, los protocolos y los lineamientos correspondientes.\nArtículo 75. Todo propietario, encargado o titular de un hospital, clínica, centro o institución de salud, albergue, centro de atención psiquiátrica e institución de salud mental, sean públicos o privados, así como de los sistemas para el desarrollo integral para la familia, los juzgados cívicos territoriales,\n\nCentros de Sanciones Administrativas y de Integración Social y Centros de Atención a Víctimas tiene la obligación de informar en tiempo real a través del mecanismo que para ello defina la Fiscalía\nEspecializada, el ingreso y egreso a dichos establecimientos o instituciones, de cadáveres, restos humanos de personas no identificadas o de las cuales no se tenga la certeza de su identidad.\nArtículo 76. El Ministerio Público de la Ciudad de México, deberá informar de inmediato a la Comisión de Búsqueda de la inhumación de los restos o el cadáver de una persona no identificada, de la cual no se tenga certeza de su identidad o no haya sido reclamada, en alguna de las fosas comunes de la\nCiudad de México, remitiendo para tal efecto todos los antecedentes con los que cuente, así como todos los datos relacionados con el destino final del cadáver o de los restos humanos, incluyendo aquellos que permitan su inmediata localización y disposición.\nCAPÍTULO NOVENO\nDel Programa de Búsqueda y Localización de la Ciudad de\nMéxico\nArtículo 77. El Programa de Búsqueda y Localización de la Ciudad de México, a cargo de la Comisión de Búsqueda, deberá ajustarse a los lineamientos del Programa Nacional de Búsqueda y Localización y contener, como mínimo:\nI. Diagnóstico, línea de base e información metodológica sobre la elaboración del Programa;\nII. El proceso y metodologías multidisciplinarias para la revisión sistemática y exhaustiva, por parte de las autoridades competentes, de averiguaciones previas, carpetas de investigación y otros documentos oficiales que contengan información sobre la desaparición y los posibles paraderos de personas;\nIII. Las metodologías y procesos para recopilar y sistematizar información de las diferentes fuentes disponibles y para su incorporación y procesamiento bases de datos o sistemas particulares para facilitar las labores de búsqueda y localización;\nIV. La identificación de tiempo y lugar de episodios críticos de desaparición de personas en cada una de las demarcaciones territoriales, la definición de los contextos de las desapariciones y las metodologías a emplearse para la búsqueda y localización en cada uno de esos contextos;\nV. Las estrategias específicas a seguir con base en la información y el análisis de contexto, para la búsqueda de niñas, niños y adolescentes, mujeres, personas con discapacidad,\n\npersonas mayores, personas extranjeras, personas migrantes, o cualquier otra persona en estado de vulnerabilidad;\nVI. Las instituciones que participarán en la implementación del Programa, estableciendo sus responsabilidades e indicadores específicos de gestión, proceso y resultado;\nVII. El método específico de análisis de contexto que contribuya en la búsqueda y localización de personas desaparecidas en episodios de violencia política del pasado, en términos de las disposiciones aplicables;\nVIII. El proceso para la depuración y organización de la información contenida en el Registro de Personas Desaparecidas;\nIX. Los procesos, sistemas y mecanismos para la coordinación con el Programa Nacional de\nBúsqueda y Localización y el Programa Nacional de Exhumaciones e Identificación Forense;\nX. Los mecanismos y modalidades que amplíen la participación familiares de manera individual o colectiva y organizaciones de la sociedad civil o personas acompañantes en los procesos de diseño, implementación, seguimiento y evaluación del Programa;\nXI. La evaluación de los recursos humanos y técnicos necesarios para su implementación;\nXII. El presupuesto asignado para la implementación y seguimiento del Programa;\nXIII. Los objetivos del Programa y sus indicadores de gestión, proceso y resultados, determinando tiempos para su medición, y\nXIV. El cronograma de implementación del Programa, estableciendo acciones a corto, mediano y largo plazo\nCAPÍTULO DÉCIMO\nDel Programa Nacional de Exhumaciones e Identificación\nForense\nArtículo 78. Las autoridades encargadas de la búsqueda y la investigación, en los términos señalados por la Ley General y esta Ley, deberán implementar y ejecutar las acciones contempladas para la Ciudad de México por el Programa Nacional de Búsqueda y el Programa Nacional de Exhumaciones e\nIdentificación Forense.\n\nDichas autoridades estarán obligadas a procesar y proporcionar la información solicitada por la\nComisión Nacional de Búsqueda y la Fiscalía Especializada de la Fiscalía General de República para la elaboración de los programas nacionales. Asimismo, están obligadas a colaborar con dichas autoridades para realizar las acciones que resulten necesarias en la elaboración de los programas.\nTÍTULO CUARTO\nDE LOS DERECHOS DE LAS VÍCTIMAS\nCAPÍTULO PRIMERO\nDisposiciones Generales\nArtículo 79. La Comisión de Víctimas debe proporcionar, en el ámbito de sus atribuciones, medidas de ayuda, asistencia y atención, por sí mismas o en coordinación con otras instituciones competentes, en los términos del presente Título, y de la Ley de Víctimas.\nArtículo 80. Las Víctimas directas de los delitos de desaparición forzada de personas y desaparición cometida por particulares tendrán, además de los derechos a la verdad, el acceso a la justicia, la reparación del daño y las garantías de no repetición y aquellos contenidos en otros ordenamientos legales, los siguientes:\nI. A la protección de sus derechos, personalidad e intereses jurídicos;\nII. A que las autoridades inicien las acciones de búsqueda y localización, bajo los principios de esta Ley, desde el momento en que se tenga noticia de su desaparición;\nIII. A ser restablecido en sus bienes y derechos en caso de ser encontrado con vida;\nIV. A proceder en contra de quienes de mala fe hagan uso de los mecanismos previstos en esta Ley para despojarlo de sus bienes o derechos;\nV. A recibir tratamiento especializado desde el momento de su localización para la superación del daño sufrido producto de los delitos previstos en la Ley General, y\nVI. A que su nombre y honra sean restablecidos en casos donde su defensa haya sido imposible debido a su condición de Persona Desaparecida.\nEl ejercicio de los derechos contenidos en las fracciones I, II, IV y VI de este artículo, será ejercido por los Familiares y personas autorizadas de acuerdo a lo establecido en la presente Ley y en la legislación aplicable.\n\nArtículo 81. Los Familiares de las Víctimas de los delitos de desaparición forzada de personas y desaparición por particulares tendrán, además de los derechos contenidos en otros ordenamientos legales, los siguientes derechos:\nI. Participar dando acompañamiento y ser informados de manera oportuna de aquellas acciones de búsqueda que las autoridades competentes realicen tendientes a la localización de la Persona Desaparecida;\nII. Proponer diligencias que deban ser llevadas a cabo por la autoridad competente en los programas y acciones de búsqueda, así como brindar opiniones sobre aquellas que las autoridades competentes sugieran o planeen. Las opiniones de los Familiares podrán ser consideradas por las autoridades competentes en la toma de decisiones. La negativa de la autoridad a atender las diligencias sugeridas por los Familiares deberá ser fundada y motivada por escrito;\nIII. Acceder, directamente o mediante sus representantes, a los expedientes que sean abiertos en materia de búsqueda o investigación;\nIV. Obtener copia simple gratuita de las diligencias que integren los expedientes de búsqueda;\nV. Acceder a las medidas de ayuda, asistencia y atención, particularmente aquellas que faciliten su participación en acciones de búsqueda, incluidas medidas de apoyo psicosocial;\nVI. Acceder a asesoría jurídica gratuita en términos de lo que determine la Comisión de\nVíctimas;\nVII. Beneficiarse de los programas o acciones de protección que para salvaguarda de su integridad física y emocional emita la Comisión de Búsqueda o promueva ante autoridad competente;\nVIII. Solicitar la intervención de expertos o peritos independientes, nacionales o internacionales en las acciones de búsqueda, en términos de lo dispuesto en la normativa aplicable;\nIX. Ser informados de forma diligente, sobre los resultados de identificación o localización de restos, en atención a los protocolos en la materia;\n\nX. Acceder de forma informada y hacer uso de los derechos, procedimientos y mecanismos que emanen de la presente Ley, además de los relativos a la Ley General y los emitidos por el Sistema Nacional de Búsqueda;\nXI. Ser informados de los mecanismos de participación derivados de la presente Ley, además de los emitidos por el Sistema Nacional de Búsqueda;\nXII. Participar en los diversos espacios y mecanismos de participación de Familiares, de acuerdo a los protocolos en la materia;\nXIII. Acceder a los programas y servicios especializados que las autoridades competentes diseñen e implementen para la atención y superación del daño producto de los delitos contemplados en la Ley General; y\nXIV. Participar en las investigaciones, sin que esto les represente una carga procesal de algún tipo.\nCAPÍTULO SEGUNDO\nDe las Medidas de Ayuda, Asistencia y Atención\nArtículo 82. Los Familiares, a partir del momento en que tengan conocimiento de la desaparición, y lo hagan del conocimiento de la autoridad competente, pueden solicitar y tienen derecho a recibir de inmediato y sin restricción alguna, las medidas de ayuda, asistencia y atención previstas en la Ley de\nVíctimas y demás disposiciones aplicables.\nArtículo 83. Las medidas a que se refiere el artículo anterior deben ser proporcionadas por la Comisión de Víctimas en tanto se realizan las gestiones para que otras instituciones públicas brinden la atención respectiva.\nLa Comisión de Víctimas debe proporcionar las medidas de ayuda, asistencia y atención a que se refiere el presente Título y la Ley de Víctimas, en forma individual, grupal o familiar, según corresponda.\nArtículo 84. Cuando durante la búsqueda o investigación, exista un cambio de fuero, las Víctimas deben seguir recibiendo las medidas de ayuda, asistencia y atención por la Comisión de Víctimas que le atienda al momento del cambio, en tanto se establece el mecanismo de atención a Víctimas del fuero que corresponda.\nCAPÍTULO TERCERO\n\nDe la Declaración Especial de Ausencia\nArtículo 85. Los Familiares, otras personas legitimadas por la ley y el Ministerio Público podrán solicitar a la Jueza o Juez de lo Familiar que emita la Declaración Especial de Ausencia para Personas\nDesaparecidas, en términos de lo dispuesto en la Ley General, la Ley Federal de Declaración Especial de Ausencia para Personas Desaparecidas y la Ley de Declaración Especial de Ausencia para Personas\nDesaparecidas en la Ciudad de México.\nCAPÍTULO CUARTO\nDe las Medidas de Reparación Integral a las Víctimas\nArtículo 86. Las Víctimas de los delitos establecidos en la Ley General tienen derecho a ser reparadas integralmente conforme a las medidas de restitución, rehabilitación, compensación, satisfacción y medidas de no repetición, en sus dimensiones individual, colectiva, material, moral y simbólica, en términos de la Ley de Víctimas.\nEl derecho para que la víctima solicite la reparación integral es imprescriptible.\nArtículo 87. La reparación integral a las Víctimas de los delitos establecidos en la Ley General comprenderá, además de lo establecido en la Ley General de Víctimas, Ley de Víctimas y en la jurisprudencia de la Corte Interamericana de Derechos Humanos y en normas del derecho internacional, los elementos siguientes:\nI. Medidas de satisfacción:\na) Construcción de lugares o monumentos de memoria;\nb) Una disculpa pública de parte del Estado, los autores y otras personas involucradas;\nc) Recuperación de escenarios de encuentro comunitario;\nd) Recuperación de la honra y memoria de la persona o personas desaparecidas, o e) Recuperación de prácticas y tradiciones socioculturales que, en su caso, se perdieron por causa de un hecho victimizante, y\nII. Medidas de no repetición que, entre otras acciones, deben incluir la suspensión temporal o inhabilitación definitiva de los servidores públicos investigados o sancionados por la comisión del delito de desaparición forzada de personas, según sea el caso y previo desahogo de los procedimientos administrativos y/o judiciales que correspondan.\n\nArtículo 88. El Gobierno de la Ciudad de México, es responsable de asegurar la reparación integral a las Víctimas por Desaparición Forzada de Personas cuando sean responsables sus servidores públicos o particulares bajo la autorización, consentimiento, apoyo, aquiescencia o respaldo de éstos.\nEl Gobierno de la Ciudad de México, compensará de forma subsidiaria el daño causado a las Víctimas de desaparición cometida por particulares en los términos establecidos en la Ley de Víctimas para la\nCiudad de México.\nCAPÍTULO QUINTO\nDe la Protección de Personas\nArtículo 89. La Fiscalía Especializada, en el ámbito de su respectiva competencia, debe establecer programas para la protección de las Víctimas, los Familiares y toda persona involucrada en el proceso de búsqueda de Personas Desaparecidas, investigación o proceso penal de los delitos materia de la\nLey General, cuando su vida o integridad corporal pueda estar en peligro, o puedan ser sometidas a actos de maltrato o intimidación por su intervención en dichos procesos.\nSe tomarán medidas urgentes y adecuadas que sean necesarias, para asegurar la protección del denunciante, los testigos, los allegados de la persona desaparecida y sus defensores, así como de quienes participen en la investigación, contra todo maltrato o intimidación en razón de la denuncia presentada o de cualquier declaración efectuada.\nTambién deberán otorgar el apoyo ministerial, pericial, policial y de otras fuerzas de seguridad a las organizaciones de Familiares y a Familiares en las tareas de búsqueda de personas desaparecidas en campo, garantizando todas las medidas de protección a su integridad física.\nArtículo 90. La Fiscalía Especializada puede otorgar, con apoyo de la Comisión de Víctimas, como medida urgente de protección la reubicación temporal, la protección de inmuebles, la escolta de cuerpos especializados y las demás que se requieran para salvaguardar la vida, integridad y libertad de las personas protegidas a que se refiere el artículo anterior, conforme a los procedimientos y con las autorizaciones aplicables.\nArtículo 91. La Fiscalía Especializada puede otorgar, con apoyo de la Comisión de Víctimas, como medida de protección para enfrentar el riesgo, la entrega de equipo celular, radio o telefonía satelital, instalación de sistemas de seguridad en inmuebles, vigilancia a través de patrullajes, entrega de chalecos antibalas, detector de metales, autos blindados, y demás medios de protección que se requieran para salvaguardar la vida, integridad y libertad de las personas protegidas por esta Ley.\n\nCuando se trate de personas defensoras de los derechos humanos o periodistas se estará también a lo dispuesto en la legislación aplicable para la Protección de Personas Defensoras de Derechos Humanos y Periodistas.\nArtículo 92. La incorporación a los programas de protección de personas a que se refiere el artículo 89 de esta Ley debe ser autorizada por el agente del Ministerio Público encargado de la investigación o por el titular de la Fiscalía Especializada.\nArtículo 93. La información y documentación relacionada con las personas protegidas debe ser tratada con estricta reserva o confidencialidad, según corresponda.\nTÍTULO QUINTO\nDE LA PREVENCIÓN DE LOS DELITOS\nCAPÍTULO PRIMERO\nDisposiciones Generales\nArtículo 94. La Secretaría de Gobierno, la Fiscalía General, la Secretaría de Seguridad Ciudadana y demás autoridades necesarias y competentes deberán coordinarse para implementar las medidas de prevención previstas en esta Ley.\nLo anterior con independencia de las establecidas en la Ley General para la Prevención Social de la\nViolencia y la Delincuencia, la Ley General del Sistema Nacional de Seguridad Pública, así como la legislación aplicable en materia de Seguridad Ciudadana de la Ciudad de México.\nArtículo 95. Todo establecimiento, instalación o cualquier sitio en control de las autoridades de la\nCiudad de México y sus Alcaldías en donde pudieran encontrarse personas en privación de la libertad, deberá contar con cámaras de video que permitan registrar los accesos y salidas del lugar. Las grabaciones deberán almacenarse de forma segura por dos años.\nArtículo 96. La Fiscalía General debe administrar bases de datos estadísticas relativas a la incidencia de los delitos previstos en la Ley General, garantizando que los datos estén desagregados, al menos, por género, edad, nacionalidad, demarcación territorial, sujeto activo, rango y dependencia de adscripción, así como si se trata de desaparición forzada o desaparición cometida por particulares.\nLas bases de datos a que se refiere el párrafo que antecede deben permitir la identificación de circunstancias, grupos en condición de vulnerabilidad, modus operandi, delimitación territorial, rutas y zonas de alto riesgo en los que aumente la probabilidad de comisión de alguno de los delitos previstos en la Ley General para garantizar su prevención.\n\nArtículo 97. El Sistema de Búsqueda, a través de la Comisión de Búsqueda, la Secretaría de Gobierno, la Fiscalía General, y la Secretaría de Seguridad Ciudadana, deberán respecto de los delitos previstos en la Ley General:\nI. Llevar a cabo campañas informativas dirigidas a fomentar la Denuncia de los delitos y sobre instituciones de atención y servicios que brindan;\nII. Proponer acciones de capacitación a las Instituciones de Seguridad Ciudadana, a las áreas ministeriales, policiales y periciales y otras que tengan como objeto la búsqueda de personas desaparecidas, la investigación y sanción de los delitos previstos en la Ley General, así como la atención y protección a Víctimas con una perspectiva psicosocial;\nIII. Proponer e implementar programas que incentiven a la ciudadanía, incluyendo a aquellas personas que se encuentran privadas de su libertad, a proporcionar la información con que cuenten para la investigación de los delitos previstos en la Ley General, así como para la ubicación y rescate de las Personas Desaparecidas;\nIV. Promover mecanismos de coordinación con asociaciones, fundaciones y demás organismos no gubernamentales para fortalecer la prevención de las conductas delictivas;\nV. Recabar y generar información respecto a los delitos que permitan definir e implementar políticas públicas en materia de búsqueda de personas, prevención e investigación;\nVI. Identificar circunstancias, grupos vulnerables y zonas de alto riesgo en las que aumente la probabilidad de que una o más personas sean Víctimas de los delitos, así como hacer pública dicha información de manera anual;\nVII. Proporcionar información y asesoría a las personas que así lo soliciten, de manera presencial, por escrito o por cualquier otro medio, relacionada con el objeto de esta Ley, con la finalidad de prevenir la comisión de los delitos;\nVIII. Reunirse, por lo menos dos veces al año, para intercambiar experiencias que permitan implementar políticas públicas en materia de prevención de los delitos;\nIX. Emitir un informe anual respecto de las acciones realizadas para el cumplimiento de las disposiciones de esta Ley;\n\nX. Diseñar instrumentos de evaluación e indicadores para el seguimiento y vigilancia del cumplimiento de la presente Ley, en donde se contemple la participación voluntaria de\nFamiliares;\nXI. Realizar diagnósticos, investigaciones, estudios e informes sobre la problemática de desaparición de personas y otras conductas delictivas conexas o de violencia vinculadas a este delito, que permitan la elaboración de políticas públicas que lo prevengan, y\nXII. Las demás que establezcan otras disposiciones jurídicas aplicables.\nArtículo 98. La Fiscalía Especializada debe intercambiar con las fiscalías especializadas de otras entidades y la Fiscalía General de la Republica la información que favorezca la investigación de los delitos previstos en la Ley General y que permita la identificación y sanción de los responsables.\nArtículo 99. La Fiscalía General debe diseñar los mecanismos de colaboración que correspondan con la finalidad de dar cumplimiento a lo previsto en la Ley General y en esta Ley.\nArtículo 100. El Sistema Búsqueda, a través de la Secretaría de Gobierno y con la participación de la\nComisión de Búsqueda, debe coordinar el diseño y aplicación de programas que permitan combatir las causas que generan condiciones de mayor riesgo y vulnerabilidad frente a los delitos previstos en la\nLey General, con especial referencia a la marginación, las condiciones de pobreza, la violencia comunitaria, la presencia de grupos delictivos, la operación de redes de trata, los antecedentes de otros delitos conexos y la desigualdad social.\nCAPÍTULO SEGUNDO\nDe la Programación\nArtículo 101. Los programas de prevención a que se refiere el presente Título deben incluir metas e indicadores a efecto de evaluar las capacitaciones y procesos de sensibilización impartidos a las personas servidoras públicas.\nArtículo 102. El Gobierno de la Ciudad de México y las Alcaldías están obligados a remitir anualmente al Centro Nacional de Prevención del Delito y Participación Ciudadana, conforme a los acuerdos generados en el marco del Sistema Nacional de Seguridad Pública, estudios sobre las causas, distribución geográfica de la frecuencia delictiva, estadísticas, tendencias históricas y patrones de comportamiento que permitan perfeccionar la investigación para la prevención de los delitos previstos en la Ley General, así como su programa de prevención sobre los mismos. Estos estudios deberán ser públicos y podrán consultarse en la página de Internet del Sistema Nacional de Seguridad Pública, de\n\nconformidad con la legislación aplicable en materia de transparencia, acceso a la información pública y protección de datos personales.\nCAPÍTULO TERCERO\nDe la Capacitación\nArtículo 103. La Comisión de Búsqueda, la Fiscalía Especializada y el titular de cada una de las Alcaldías deben establecer programas obligatorios de capacitación en materia de Atención a Víctimas y de\nDerechos humanos, enfocados a los principios referidos en el artículo 5° de esta Ley, para las personas servidoras públicas de las Instituciones y áreas de Seguridad Ciudadana involucradas en la búsqueda y acciones previstas en este ordenamiento, con la finalidad de prevenir la comisión de los delitos.\nArtículo 104. La Fiscalía General, la Secretaría de Seguridad Ciudadana y el Tribunal Superior de\nJusticia de la Ciudad de México, con el apoyo de la Comisión de Búsqueda deben capacitar, en el ámbito de sus competencias, al personal ministerial, policial y pericial conforme a los más altos estándares internacionales, respecto de las técnicas de búsqueda, investigación y análisis de pruebas para los delitos a que se refiere la Ley General, con pleno respeto a los derechos humanos y con enfoque psicosocial.\nArtículo 105. La Secretaría de Seguridad Ciudadana seleccionará, de conformidad con los procedimientos de evaluación y controles de confianza aplicables, al personal policial que conformará los Grupos de Búsqueda.\nArtículo 106. La Comisión de Búsqueda emitirá los lineamientos que permita a la Secretaría de\nSeguridad Ciudadana determinar el número de integrantes que conformarán los Grupos de Búsqueda de conformidad con las cifras de los índices del delito de desaparición forzada de personas y la cometida por particulares, así como de Desaparecidas que existan en cada Demacración Territorial.\nArtículo 107. La Fiscalía General y la Secretaría de Seguridad Ciudadana deben capacitar y certificar, a su personal conforme a los criterios de capacitación y certificación que al efecto establezca la\nConferencia Nacional de Procuración de Justicia.\nArtículo 108. Sin perjuicio de lo dispuesto en los artículos 106 y 107, la Fiscalía General y la Secretaría de Seguridad Ciudadana deben capacitar a todo el personal policial respecto de los protocolos de actuación inmediata y las acciones específicas que deben realizar cuando tengan conocimiento, por cualquier medio, de la desaparición de una persona.\nArtículo 109. La Comisión de Víctimas debe capacitar a las personas servidoras públicas de la dependencia, conforme a los más altos estándares internacionales, para brindar medidas de ayuda,\n\nasistencia y atención con un enfoque psicosocial y técnicas especializadas para el acompañamiento de las Víctimas de los delitos a que se refiere la Ley General.\nTRANSITORIOS\nPRIMERO.- El presente decreto entrara en vigor al día siguiente de su publicación en el Gaceta Oficial de la Ciudad de México.\nSEGUNDO.- Publíquese el presente decreto en la Gaceta Oficial de la Ciudad de México y para mayor difusión en el Diario Oficial de la Federación.\nTERCERO.- Las facultades conferidas en esta Ley a la Fiscalía General de Justicia de la Ciudad de\nMéxico, serán asumidas por la Procuraduría General de Justicia del Distrito Federal, en tanto no se cree dicha dependencia.\nCUARTO.- El Consejo Ciudadano deberá estar conformado dentro de los noventa días posteriores a la entrada en vigor del presente Decreto.\nEn un plazo de treinta días posteriores a su conformación el Consejo Ciudadano deberá emitir sus reglas de funcionamiento.\nQUINTO.- El Sistema de Búsqueda deberá quedar instalado dentro de los noventa días posteriores a la publicación del presente Decreto.\nEn la primera sesión ordinaria del Sistema de Búsqueda, se deberán emitir los lineamientos y modelos a que se refiere el artículo 21, fracciones I y XII de esta Ley.\nSEXTO.- El Sistema de Búsqueda tiene un plazo de ciento ochenta días naturales a partir del 30 de enero de 2020 para emitir el Protocolo a que hace referencia el artículo 7° del presente Decreto.\nSÉPTIMO.- Dentro de los treinta días siguientes a la emisión de los lineamientos previstos en el artículo transitorio anterior, la Comisión de Búsqueda deberá contar con la infraestructura tecnológica necesaria y comenzar a operar el Registro de Personas Desaparecidas.\nOCTAVO.- Dentro de los ciento ochenta días posteriores a la Publicación del Programa Nacional de\nBúsqueda de Personas, la Comisión de Búsqueda deberá emitir el Programa de Búsqueda.\nNOVENO.-Las personas servidoras públicas que integren la Fiscalía Especializada y la Comisión de\nBúsqueda deberán estar certificadas dentro del año posterior a la entrada en vigor del presente\nDecreto.\n\nDÉCIMO.- La persona titular de la Jefatura de Gobierno, en un plazo de ciento veinte días a partir de la entrada en vigor del presente Decreto, deberá expedir y armonizar las disposiciones reglamentarias que correspondan conforme a lo dispuesto en el presente Decreto.\nDÉCIMO PRIMERO.- La Secretaría de Gobierno y la Secretaría de Administración y Finanzas de la\nCiudad de México, realizarán las gestiones necesarias, ante las instancias locales y federales correspondientes, para el inicio de operaciones de la Comisión de Búsqueda durante el ejercicio fiscal de 2019, en tanto que se emiten las erogaciones correspondientes en los presupuestos de egresos de los próximos ejercicios fiscales.\nDÉCIMO SEGUNDO.- El Congreso de la Ciudad de México realizará las adecuaciones presupuestarias necesarias en los subsecuentes ejercicios fiscales.\nDÉCIMO TERCERO.- Las facultades conferidas al Sistema de Protección Integral de los Derechos de las\nNiñas, Niños y Adolescentes de la Ciudad de México, serán asumidas por el Sistema de Protección\nIntegral de los Derechos de las Niñas, Niños y Adolescentes del Distrito Federal, en tanto no se den las adecuaciones a la legislación en materia.\nDÉCIMO CUARTO.- Los programas de capacitación a que hace referencia el Capítulo Tercero del Título\nQuinto deben incluir herramientas metodológicas de medición que incluyan metas e indicadores a efecto de evaluar las capacitaciones de los servidores públicos.\nDÉCIMO QUINTO.- Se sancionará en los términos de la Ley General de Salud a los establecimientos que presten servicios de salud, los profesionales, técnicos y auxiliares de la salud, que no proporcionen a la Comisión de Búsqueda y a la Fiscalía Especializada, la información a la que hacen referencia los artículos 32 y 75 del presente decreto.\nDÉCIMO SEXTO.- En tanto no se efectúe la completa integración del Registro Nacional de Detenciones y se lleve a cabo la implementación del mismo de conformidad con lo estipulado por la Ley Nacional del Registro de Detenciones, serán aplicables las disposiciones previstas para tal efecto por la misma ley.\nDÉCIMO SÉPTIMO.- Las autoridades que integran el Sistema de Búsqueda, así como toda dependencia de la Ciudad de México que cuente con información relevante relacionada con la materia de Ley\nGeneral y esta Ley, deberán presentar su diagnóstico al que hace referencia la fracción XI del artículo\n97, a más tardar en la Tercera Sesión Ordinaria del mismo.\nPalacio Legislativo del Congreso de la Ciudad de México, a los tres días del mes de diciembre del año dos mil diecinueve.- POR LA MESA DIRECTIVA.- DIPUTADA ISABELA ROSALES HERRERA,\n\nPRESIDENTA.- DIPUTADA MARTHA SOLEDAD ÁVILA VENTURA, SECRETARIA.- DIPUTADA\nMARGARITA SALDAÑA HERNÁNDEZ, SECRETARIA.- (Firmas)\nCon fundamento en lo dispuesto por los artículos 122, apartado A, fracción III, de la Constitución Política de los Estados Unidos Mexicanos; 32 apartado C, numeral 1, inciso a) de la Constitución Política de la\nCiudad de México; 2, párrafo segundo, 3, fracciones XVII y XVIII, 7 párrafo primero, 10 fracción II, 12 y\n21 párrafo primero de la Ley Orgánica del Poder Ejecutivo y de la Administración Pública de la Ciudad de México; para su debida publicación y observancia, expido el presente Decreto Promulgatorio en la\nResidencia Oficial de la Jefatura de Gobierno de la Ciudad de México, a los treinta días del mes de noviembre del año dos mil diecinueve.- LA JEFA DE GOBIERNO DE LA CIUDAD DE MÉXICO, DRA.\nCLAUDIA SHEINBAUM PARDO.- FIRMA.- LA SECRETARIA DE GOBIERNO, ROSA ICELA RODRÍGUEZ\nVELÁZQUEZ.- FIRMA.- LA SECRETARIA DE ADMINISTRACIÓN Y FINANZAS, LUZ ELENA GONZÁLEZ\nESCOBAR.- FIRMA.- LA SECRETARIA DE GESTIÓN INTEGRAL DE RIESGOS Y PROTECCIÓN CIVIL.-\nMYRIAM VILMA URZÚA VENEGAS.- FIRMA.- LA SECRETARIA DE INCLUSIÓN Y BIENESTAR SOCIAL,\nALMUDENA OCEJO ROJO.- FIRMA.- LA SECRETARIA DE LAS MUJERES, GABRIELA RODRÍGUEZ\nRAMÍREZ.- FIRMA.- LA SECRETARIA DE SALUD, OLIVA LÓPEZ ARELLANO.- FIRMA.- EL SECRETARIO\nDE SEGURIDAD CIUDADANA.- OMAR HAMID GARCÍA HARFUCH.- FIRMA.- EL CONSEJERO JURÍDICO\nY DE SERVICOS LEGALES, NÉSTOR VARGAS SOLANO.- FIRMA.\nTRANSITORIOS DEL DECRETO POR EL QUE SE REFORMA EL ARTÍCULO 45, FRACCIÓN VII, DE LA LEY\nDE BÚSQUEDA DE PERSONAS DE LA CIUDAD DE MÉXICO PUBLICADO EN LA GACETA OFICIAL DE LA\nCIUDAD DE MÈXICO, EL DÌA 13 DE OCTUBRE DE 2020.\nPRIMERO.- Publíquese en la Gaceta Oficial de la Ciudad de México y en el Diario Oficial de la\nFederación para su mayor difusión.\nSEGUNDO.- El presente Decreto entrará en vigor al siguiente día de su publicación en la Gaceta Oficial de la Ciudad de México.\nPalacio Legislativo del Congreso de la Ciudad de México, a los ocho días del mes de septiembre del año dos mil veinte.- POR LA MESA DIRECTIVA.- DIPUTADA MARGARITA SALDAÑA HERNÁNDEZ,\nPRESIDENTA.- DIPUTADA DONAJI OFELIA OLIVERA REYES, SECRETARIA.- DIPUTADO HÉCTOR\nBARRERA MARMOLEJO, SECRETARIO.- (Firmas)\nCon fundamento en lo dispuesto por los artículos 122, apartado A, fracción III, de la Constitución Política de los Estados Unidos Mexicanos; 32 apartado C, numeral 1, inciso a) de la Constitución Política de la\nCiudad de México; 3 fracciones XVII y XVIII, 7 párrafo primero, 10 fracción II, 12 y 21, párrafo primero de la Ley Orgánica del Poder Ejecutivo y de la Administración Pública de la Ciudad de México, para su debida publicación y observancia, expido el presente Decreto Promulgatorio en la Residencia Oficial de\n\nla Jefatura de Gobierno de la Ciudad de México, a los nueve días del mes de octubre del año dos mil veinte.- LA JEFA DE GOBIERNO DE LA CIUDAD DE MÉXICO, DRA. CLAUDIA SHEINBAUM PARDO.-\nFIRMA.- EL SECRETARIO DE GOBIERNO, JOSÉ ALFONSO SUÁREZ DEL REAL Y AGUILERA.- FIRMA.\nTRANSITORIO DEL DECRETO POR EL QUE SE REFORMAN LA FRACCIÓN VI DEL ARTÍCULO 2°, 6º, 7º, EL\nPRIMER PÁRRAFO Y SE ADICIONAN LOS PÁRRAFOS SEGUNDO Y TERCERO RECORRIENDO LOS\nSUBSECUENTES DEL ARTÍCULO 40 Y SE DEROGA LA FRACCIÓN II DEL ARTÍCULO 23 DE LA LEY DE\nBÚSQUEDA DE PERSONAS DE LA CIUDAD DE MÉXICO, PUBLICADO EN LA GACETA OFICIAL EL DÌA 19\nDE MARZO DE 2021.\nPRIMERO. – Remítase a la Jefatura de Gobierno para su promulgación y publicación en la Gaceta Oficial de la Ciudad de México y publíquese en el Diario Oficial de la Federación para su mayor difusión.\nSEGUNDO.- El presente Decreto entrara en vigor al día siguiente día de su publicación en la Gaceta\nOficial de la Ciudad de México.\nPalacio Legislativo del Congreso de la Ciudad de México, a los cuatro días del mes de febrero del año dos mil veintiuno. POR LA MESA DIRECTIVA.-DIPUTADA MARGARITA SALDAÑA HERNÁNDEZ,\nPRESIDENTA.- DIPUTADA DONAJI OFELIA OLIVERA REYES, SECRETARIA.- DIPUTADO PABLO MONTES\nDE OCA DEL OLMO, SECRETARIO.- (FIRMAS)\nCon fundamento en lo dispuesto por los artículos 122, apartado A, fracción III de la Constitución Política de los Estados Unidos Mexicanos; 32, apartado C, numeral 1, inciso a) de la Constitución Política de la\nCiudad de México; 2 párrafo segundo, 3 fracciones XVII y XVIII, 7 párrafo primero, 10 fracción II, 12 y\n21 párrafo primero de la Ley Orgánica del Poder Ejecutivo y de la Administración Pública de la Ciudad de México; para su debida publicación y observancia, expido el presente Decreto Promulgatorio en la\nResidencia Oficial de la Jefatura de Gobierno de la Ciudad de México, a los dieciocho días del mes de marzo del año dos mil veintiuno. LA JEFA DE GOBIERNO DE LA CIUDAD DE MÉXICO, DRA. CLAUDIA\nSHEINBAUM PARDO.- FIRMA.- EL SECRETARIO DE GOBIERNO, JOSÉ ALFONSO SUÁREZ DEL REAL Y\nAGUILERA.- FIRMA.\nTRANSITORIO DEL DECRETO POR EL QUE SE REFORMA LA FRACCIÓN VII DEL ARTÍCULO 4° Y SE\nREFORMA EL ARTÍCULO 85, AMBOS DE LA LEY DE BÚSQUEDA DE PERSONAS DE LA CIUDAD DE\nMÉXICO, PUBLICADO EN LA GACETA OFICIAL EL DÍA 09 DE ABRIL DE 2021.\nPRIMERO. Remítase a la Jefatura de Gobierno para su promulgación y publicación en la Gaceta Oficial de la Ciudad de México.\n\nSEGUNDO. El Presente Decreto entrará en vigor al día siguiente de su publicación en la Gaceta Oficial de la Ciudad de México.\nPalacio Legislativo del Congreso de la Ciudad de México, a los dos días del mes de marzo del año dos mil veintiuno. POR LA MESA DIRECTIVA, DIPUTADA MARGARITA SALDAÑA HERNÁNDEZ,\nPRESIDENTA, DIPUTADA DONAJI OFELIA OLIVERA REYES, SECRETARIA, DIPUTADO PABLO MONTES\nDE OCA DEL OLMO, SECRETARIO (Firmas)\nCon fundamento en lo dispuesto por los artículos 122, apartado A, fracción III de la Constitución Política de los Estados Unidos Mexicanos; 32, apartado C, numeral 1, inciso a) de la Constitución Política de la\nCiudad de México; 2 párrafo segundo, 3 fracciones XVII y XVIII, 7 párrafo primero, 10 fracción II, 12 y\n21 párrafo primero de la Ley Orgánica del Poder Ejecutivo y de la Administración Pública de la Ciudad de México; para su debida publicación y observancia, expido el presente Decreto Promulgatorio en la\nResidencia Oficial de la Jefatura de Gobierno de la Ciudad de México, a los ocho días del mes de abril del año dos mil veintiuno.- LA JEFA DE GOBIERNO DE LA CIUDAD DE MÉXICO, DRA. CLAUDIA\nSHEINBAUM PARDO.- FIRMA.- EL SECRETARIO DE GOBIERNO, JOSÉ ALFONSO SUÁREZ DEL REAL Y\nAGUILERA.-FIRMA.",
  "ordenamiento": "Marco Jurídico",
  "jurisdiccion": "CIUDAD DE MEXICO",
  "fuente_oficial": "Congreso de la Ciudad de México",
  "status": "Vigente",
  "Fecha de Publicación": "22-06-2022",
  "Fecha de Última Reforma": "09 de abril de 2021",
  "numero_paginas": 52,
  "es_escaneado": false,
  "tiene_tablas": false,
  "url": "https://www.congresocdmx.gob.mx/archivo-5e3a8d47e66c14ccaadfb897f3ad958de193a1df.pdf",
  "materia": [
    "derechos humanos",
    "víctimas"
  ]
}