{
  "titulo": "Ley DE MEJORAMIENTO BARRIAL y COMUNITARIO DEL DISTRITO FEDERAL",
  "Contenido": "PUBLICADA EN LA GACETA OFICIAL DEL DISTRITO FEDERAL\nEL 29 DE SEPTIEMBRE DE 2015\nTEXTO VIGENTE\nÚLTIMA REFORMA PUBLICADA EN LA G.O.C.D.X.\nEL 27 DE OCTUBRE DE 2022\nADMINISTRACIÓN PÚBLICA DEL DISTRITO FEDERAL\nJEFATURA DE GOBIERNO\nLEY DE MEJORAMIENTO BARRIAL Y COMUNITARIO DEL DISTRITO FEDERAL.\nDECRETO POR EL QUE SE EXPIDE LA LEY DE MEJORAMIENTO BARRIAL Y COMUNITARIO DEL\nDISTRITO FEDERAL\n(Al margen superior un escudo que dice: CIUDAD DE MÉXICO.- Decidiendo Juntos)\nMIGUEL ÁNGEL MANCERA ESPINOSA, Jefe de Gobierno del Distrito Federal, a sus habitantes sabed:\nQue la H. Asamblea Legislativa del Distrito Federal, VI Legislatura se ha servido dirigirme el siguiente\nD E C R E T O\n(Al margen superior izquierdo el Escudo Nacional que dice: ESTADOS UNIDOS MEXICANOS.-\nASAMBLEA LEGISLATIVA DEL DISTRITO FEDERAL.- VI LEGISLATURA)\nASAMBLEA LEGISLATIVA DEL DISTRITO FEDERAL\nVI LEGISLATURA\nD E C R E T A\nDECRETO POR EL QUE SE EXPIDE LA LEY DE MEJORAMIENTO BARRIAL Y COMUNITARIO DEL\nDISTRITO FEDERAL.\nARTÍCULO ÚNICO. - Se expide la Ley de Mejoramiento Barrial y Comunitario del Distrito Federal para quedar como sigue:\n\nLEY DE MEJORAMIENTO BARRIAL Y COMUNITARIO DEL\nDISTRITO FEDERAL\nCAPÍTULO I\nDisposiciones Generales\nArtículo 1º.- La presente ley es de orden público y de observancia general en la Ciudad de México y tiene por objeto, establecer los lineamientos para que las y los habitantes de los barrios, colonias, pueblos y unidades habitacionales, tengan el derecho de presentar y ejecutar proyectos de mejoramiento barrial y comunitario que fomenten el uso, rehabiliten y recuperen los espacios públicos y/o la imagen urbana de sus territorios, así como los espacios de uso común de las unidades habitacionales.\nReforma publicada en la GOCDMX el 27 de Octubre de 2022\nArtículo 2º.- Para los efectos de esta Ley, se entenderá por:\nI.- Administración Pública: El conjunto de dependencias, órganos y entidades que componen la Administración Pública Centralizada y Paraestatal de la Ciudad de México;\nReforma publicada en la GOCDMX el 27 de Octubre de 2022\nII.- Congreso: Congreso de la Ciudad de México;\nReforma publicada en la GOCDMX el 27 de Octubre de 2022\nIII.- Barrios, colonias, pueblos y unidades habitacionales: Las divisiones territoriales que para efectos de nomenclatura se ubican dentro de la Ciudad de México;\nReforma publicada en la GOCDMX el 27 de Octubre de 2022\nIV.- Comisión Interinstitucional: Espacio de Gobierno de la Ciudad de México donde confluyen diversos órganos de la Administración Pública cuyo objeto es generar acciones y políticas convergentes en los territorios donde existan proyectos de mejoramiento barrial y comunitario, que contará con representación de dos personas Diputadas del Congreso de la\nCiudad de México;\nReforma publicada en la GOCDMX el 27 de Octubre de 2022\nV.- Comité Técnico Mixto: Instancia que aprueba los proyectos de mejoramiento barrial y comunitario;\nVI.- Comités: Son órganos operativos del Programa de Mejoramiento Barrial y Comunitario para la administración del recurso autorizado, estos Comités son de Administración, de\nSupervisión y de Desarrollo Comunitario.\n\nVII.- Jefe de Gobierno: el Jefe de Gobierno de la Ciudad de México;\nReforma publicada en la GOCDMX el 27 de Octubre de 2022\nVIII.- Ley: Ley de Mejoramiento Barrial y Comunitario de la Ciudad de México;\nReforma publicada en la GOCDMX el 27 de Octubre de 2022\nIX.- Proyecto de mejoramiento barrial y comunitario: Es la propuesta específica de la zona que se presenta desde los habitantes de los barrios, colonias, pueblos y unidades habitacionales a la convocatoria pública de la Secretaría;\nX.- Proyecto de continuidad: Es el proyecto que define varias etapas en su ejecución y que puede ser autorizado hasta por cinco ejercicios fiscales;\nXI.- Secretaría: La Secretaría de Inclusión y Bienestar de la Ciudad de México;\nReforma publicada en la GOCDMX el 27 de Octubre de 2022\nXII.- Subsecretaría: La Subsecretaría de Participación Ciudadana dependiente de la\nSecretaría.\nArtículo 3º.- La aplicación de la presente Ley estará a cargo de la Secretaría a través de la\nSubsecretaría, sin perjuicio de las atribuciones que correspondan a los demás órganos de la\nAdministración Pública.\nCAPÍTULO II\nDel Mejoramiento Barrial y Comunitario\nArtículo 4º.- Los proyectos de mejoramiento barrial y comunitario deben ser congruentes con el programa de Ordenamiento Territorial de cada demarcación\nReforma publicada en la GOCDMX el 27 de Octubre de 2022\nArtículo 5°.- Los proyectos de mejoramiento barrial y comunitario estarán dirigidos principalmente a aquellas zonas cuya marginalidad esté catalogada como media, alta, y muy alta; así como aquellas que tengan altos niveles de conflictividad e inseguridad social y/o degradación urbana.\nArtículo 6º.- Los proyectos de mejoramiento barrial y comunitario serán presentados ante la\nSubsecretaría por las y los habitantes de los barrios, colonias, pueblos y unidades habitacionales. Para tal efecto, no se considerará en los proyectos delimitación alguna que derive de la nomenclatura de los barrios, colonias, pueblos y unidades habitacionales.\n\nArtículo 7º.- Para la presentación de los proyectos de mejoramiento barrial y comunitario la Secretaría emitirá anualmente una convocatoria pública, la cual se dará a conocer en la Gaceta Oficial de la Ciudad de México, en un diario de amplia circulación de esta entidad federativa y en el portal de internet de la Secretaría. En la convocatoria se establecerán los requisitos, plazos y procedimientos para que los habitantes de los barrios, colonias, pueblos y unidades habitacionales de la Ciudad de México presenten sus proyectos.\nReforma publicada en la GOCDMX el 27 de Octubre de 2022\nArtículo 8º.- Para la aprobación de los proyectos de mejoramiento barrial y comunitario, se establecerá un Comité Técnico Mixto, el cual estará integrado por personas servidoras públicas del Gobierno de la\nCiudad de México y especialistas de la sociedad civil, siendo en ambos casos su participación honorífica\nReforma publicada en la GOCDMX el 27 de Octubre de 2022\nArtículo 9°.- Aprobado el proyecto de mejoramiento barrial y comunitario por el Comité Técnico Mixto, la Secretaría convocará a una asamblea vecinal, en la que podrán participar con derecho a voz y voto las y los ciudadanos residentes en el área de impacto del proyecto, quienes acreditarán su residencia mediante credencial para votar con fotografía. Dicha asamblea avalará o rechazará por mayoría simple de los asistentes el proyecto.\nSi el proyecto fuera avalado, se procederá a elegir de entre las y los asistentes a la asamblea, a los integrantes de los Comités de Administración, de Supervisión y de Desarrollo Comunitario.\nCAPÍTULO III\nDe los Comités\nArtículo 10.- Los Comités de Administración, de Supervisión y de Desarrollo Comunitario; están obligados a dar seguimiento al proyecto de mejoramiento barrial y comunitario, debiendo proporcionar a la Secretaría la información requerida durante el ejercicio previsto en el proyecto aprobado o en el de continuidad y hasta su debida conclusión.\nEl Comité de Administración, será el responsable de recibir los recursos económicos y de su correcta administración, así como de la comprobación completa, correcta y oportuna de los mismos y la rendición periódica de cuentas; además deberá proporcionar tanto a los Comités de Supervisión y de\nDesarrollo Comunitario como a la Secretaria, la información que le sea solicitada.\n\nEl Comité de Supervisión, vigila la correcta aplicación del recurso autorizado, el avance y la calidad de la obra, mediante la solicitud al Comité de Administración de los informes financieros y bitácora de obra.\nEl Comité de Desarrollo Comunitario es el encargado de promover, potenciar y consolidar el proceso de participación vecinal que el proyecto de mejoramiento barrial y comunitario impulse.\nCAPÍTULO IV\nDel Financiamiento\nArtículo 11.- La persona titular de la Jefatura de Gobierno deberá incluir en el Proyecto de Presupuesto de Egresos de la Ciudad de México la asignación que garantice, efectivamente, el derecho de los habitantes de barrios, colonias, pueblos y unidades habitacionales a acceder al mejoramiento barrial y comunitario, el cual no deberá de ser menor al del año inmediato anterior y tendrá una perspectiva de progresividad\nReforma publicada en la GOCDMX el 27 de Octubre de 2022\nArtículo 12.- El Congreso de la Ciudad de México deberá destinar, en forma anual y de manera obligatoria, en el Presupuesto de Egresos de la Ciudad de México los recursos públicos para la operación y ejecución de los proyectos de mejoramiento barrial y comunitario, sin que éste sea menor al del año inmediato anterior\nReforma publicada en la GOCDMX el 27 de Octubre de 2022\nArtículo 13.- La Secretaría promoverá la instalación de una Comisión Interinstitucional donde confluyan órganos de la Administración Pública y cuyo objeto sea generar acciones y políticas convergentes en los territorios donde existan proyectos de mejoramiento barrial y comunitario.\nLa Secretaría apoyará con asesoría técnica, administrativa y legal en el diseño, presentación, gestión, financiamiento, ejecución y desarrollo de los proyectos de mejoramiento barrial y comunitario.\nCAPÍTULO V\nDe las Sanciones\nArtículo 14.- El incumplimiento de la presente Ley por parte de las personas servidoras públicas de la\nCiudad de México será sancionado conforme a la Ley de Responsabilidades Administrativas de la\nCiudad de México, sin perjuicio de la responsabilidad civil, penal o de cualquier otro tipo de carácter legal que llegara a causarse\nReforma publicada en la GOCDMX el 27 de Octubre de 2022\n\nArtículo 15.- En caso de incumplimiento, irregularidad o mal uso de los recursos en la ejecución de los proyectos de mejoramiento barrial y comunitario, la Secretaría requerirá a los integrantes de los\nComités en los términos de la Ley de Procedimiento Administrativo de la Ciudad de México.\nReforma publicada en la GOCDMX el 27 de Octubre de 2022\nEn caso de que se presuma la posible responsabilidad civil, penal o de cualquier otro tipo de índole jurídico, la Secretaría promoverá ante las instancias correspondientes los procedimientos jurídicos aplicables.\nPara efectos del presente artículo se considera que hay incumplimiento, irregularidad o mal uso de los recursos, cuando éstos no se destinen exclusivamente a las actividades necesarias para la ejecución de los proyectos de mejoramiento barrial y comunitario.\nCAPÍTULO VI\nDe la Transparencia y la Rendición de Cuentas\nArtículo 16.- Los proyectos de mejoramiento barrial y comunitario presentados ante la Subsecretaría y aprobados, deberán ser publicados en la Gaceta Oficial de la Ciudad de México y en el portal de internet de la Secretaría a más tardar el 30 de noviembre de cada año\nReforma publicada en la GOCDMX el 27 de Octubre de 2022\nArtículo 17.- La Secretaría publicará en su portal de internet la información relativa a la realización de los proyectos de mejoramiento barrial y comunitario aprobados, a efecto de que los ciudadanos accedan a ella.\nTRANSITORIOS\nPRIMERO.- Publíquese en la Gaceta Oficial del Distrito Federal.\nSEGUNDO. - El presente decreto entrará en vigor al día siguiente de su publicación en la Gaceta Oficial del Distrito Federal.\nTERCERO. - En un periodo no mayor de 90 días hábiles contados a partir de la entrada en vigor de la presente ley, el Jefe de Gobierno del Distrito Federal deberá publicar el Reglamento de esta ley.\n\nCUARTO. - Los proyectos de mejoramiento barrial iniciados con anterioridad a la entrada en vigor de la presente ley, continuarán tramitándose hasta su conclusión, conforme a las disposiciones aplicables vigentes a su inicio.\nRecinto de la Asamblea Legislativa del Distrito Federal, a los diecinueve días del mes de febrero del año dos mil quince. - POR LA MESA DIRECTIVA. - DIP. GABRIEL ANTONIO GODÍNEZ JIMÉNEZ,\nPRESIDENTE. - DIP. ROSALÍO ALFREDO PINEDA SILVA, SECRETARIO. - DIP. ERNESTINA GODOY\nRAMOS, SECRETARIA. - FIRMAS.\nEn cumplimiento de lo dispuesto por los artículos 122, apartado C, Base Segunda, fracción II, inciso b), de la Constitución Política de los Estados Unidos Mexicanos; 48, 49 y 67, fracción II, del Estatuto de\nGobierno del Distrito Federal, para su debida publicación y observancia, expido el presente Decreto\nPromulgatorio en la Residencia Oficial del Jefe de Gobierno del Distrito Federal, en la Ciudad de\nMéxico, a los veintiocho días del mes de agosto del año dos mil quince.- EL JEFE DE GOBIERNO DEL\nDISTRITO FEDERAL, MIGUEL ÁNGEL MANCERA ESPINOSA.- FIRMA.- LA SECRETARIA DE GOBIERNO,\nDORA PATRICIA MERCADO CASTRO.- FIRMA.- EL SECRETARIO DE DESARROLLO SOCIAL, JOSÉ\nRAMÓN AMIEVA GÁLVEZ.- FIRMA.- EL SECRETARIO DE DESARROLLO URBANO Y VIVIENDA, FELIPE\nDE JESÚS GUTIÉRREZ GUTIÉRREZ.- FIRMA.- EL SECRETARIO DE FINANZAS, ÉDGAR ABRAHAM\nAMADOR ZAMORA.- FIRMA.\nTRANSITORIOS DEL DECRETO POR EL QUE SE REFORMAN LOS ARTÍCULOS 1o; LAS FRACCIONES I, II,\nIII, IV, VII, VIII Y XI, DEL ARTÍCULO 2o, 4o, 7o; 8o, 11, 12, 14, 15, PÁRRAFO PRIMERO, Y 16, ASÍ COMO\nLA DENOMINACIÓN, DE LA LEY DE MEJORAMIENTO BARRIAL Y COMUNITARIO DEL DISTRITO\nFEDERAL, PUBLICADO EN LA GACETA OFICIAL DE LA CIUDAD DE MÉXICO EL 27 DE OCTUBRE DE 2022.\nPRIMERO.- Remítase a la persona titular de la Jefatura de Gobierno, para su promulgación y publicación en la Gaceta Oficial de la Ciudad de México.\nSEGUNDO.- El presente Decreto entrará en vigor al día siguiente de su publicación en la Gaceta Oficial de la Ciudad de México.\nPalacio Legislativo del Congreso de la Ciudad de México, a los trece días del mes de septiembre del año dos mil veintidós.- POR LA MESA DIRECTIVA.- DIPUTADO FAUSTO MANUEL ZAMORANO\nESPARZA, PRESIDENTE.- DIPUTADA MARCELA FUENTE CASTILLO, SECRETARIA.- DIPUTADA MARIA\nGABRIELA SALIDO MAGOS, SECRETARIA.- (Firmas)\nCon fundamento en lo dispuesto por los artículos 122, apartado A, fracción III de la Constitución Política de los Estados Unidos Mexicanos; 32, apartado C, numeral 1, inciso a) de la Constitución Política de la\nCiudad de México; 2 párrafo segundo, 3 fracciones XVII y XVIII, 7 párrafo primero, 10 fracción II, 12 y\n\n21 párrafo primero de la Ley Orgánica del Poder Ejecutivo y de la Administración Pública de la Ciudad de México; para su debida publicación y observancia, expido el presente Decreto Promulgatorio en la\nResidencia Oficial de la Jefatura de Gobierno de la Ciudad de México, a los veintiséis días del mes de octubre del año dos mil veintidós.- LA JEFA DE GOBIERNO DE LA CIUDAD DE MÉXICO, DRA. CLAUDIA\nSHEINBAUM PARDO.- FIRMA.- EL SECRETARIO DE GOBIERNO, MARTÍ BATRES GUADARRAMA.-\nFIRMA.- LA SECRETARIA DE ADMINISTRACIÓN Y FINANZAS, LUZ ELENA GONZÁLEZ ESCOBAR.-\nFIRMA.- EL ENCARGADO DE DESPACHO DE LA SECRETARÍA DE INCLUSIÓN Y BIENESTAR SOCIAL,\nRIGOBERTO SALGADO VÁZQUEZ.- FIRMA.",
  "ordenamiento": "Marco Jurídico",
  "jurisdiccion": "CIUDAD DE MEXICO",
  "fuente_oficial": "Congreso de la Ciudad de México",
  "status": "Vigente",
  "Fecha de Publicación": "04-11-2022",
  "Fecha de Última Reforma": "27 de Octubre de 2022",
  "numero_paginas": 8,
  "es_escaneado": false,
  "tiene_tablas": false,
  "url": "https://www.congresocdmx.gob.mx/archivo-f5d50fbcde8ba8aeebb370d7bfb8aaf363c04747.pdf",
  "materia": [
    "desarrollo urbano",
    "participación ciudadana"
  ]
}