{
  "titulo": "Ley DE PUBLICIDAD EXTERIOR DE LA CIUDAD DE MÉXICO",
  "Contenido": "PUBLICADO EN LA GACETA OFICIAL DE LA CIUDAD DE MÉXICO\nEL 06 DE JUNIO DE 2022\nTEXTO VIGENTE\nÚLTIMA REFORMA PUBLICADA EN LA G.O.C.D.M.X.\nEL 28 DE MARZO DE 2023\nLEY DE PUBLICIDAD EXTERIOR DE LA CIUDAD DE MÉXICO\nDRA. CLAUDIA SHEINBAUM PARDO, Jefa de Gobierno de la Ciudad de México, a sus habitantes sabed.\nQue el H. Congreso de la Ciudad de México II Legislatura, se ha servido dirigirme el siguiente:\nD E C R E T O\nEL CONGRESO DE LA CIUDAD DE MÉXICO\nII LEGISLATURA\nEL CONGRESO DE LA CIUDAD DE MÉXICO, DECRETA:\nSE ABROGA LA LEY DE PUBLICIDAD EXTERIOR DEL DISTRITO FEDERAL Y SE EXPIDE LA LEY DE PUBLICIDAD\nEXTERIOR DE LA CIUDAD DE MÉXICO.\nPRIMERO. - Se abroga la Ley de Publicidad Exterior del Distrito Federal.\nSEGUNDO. - Se expide la Ley de Publicidad Exterior de la Ciudad de México, para quedar de la siguiente manera:\n\nLEY DE PUBLICIDAD EXTERIOR DE LA CIUDAD DE\nMÉXICO\nTÍTULO PRIMERO\nDISPOSICIONES GENERALES\nCAPÍTULO PRIMERO\nOBJETO, PRINCIPIOS Y FINES\nArtículo 1. La presente Ley es de orden público e interés general en la Ciudad de México y tiene por objeto regular la instalación, distribución, mantenimiento, permanencia y retiro de los medios publicitarios en el espacio público o en cualquier otro bien visible desde el exterior.\nArtículo 2. Los actos emitidos y ejecutados en términos de la presente Ley, se regirán bajo los principios de innovación, atención ciudadana, gobierno abierto y plena accesibilidad; con base en el diseño universal, simplificación, agilidad, economía, información, precisión, legalidad, transparencia, proporcionalidad, buena fe, integridad, imparcialidad, honradez, lealtad, eficiencia, profesionalización y eficacia; respetando los valores de dignidad, ética, justicia, libertad y seguridad, así como los principios establecidos en la Ley de Procedimiento Administrativo de la Ciudad de México.\nArtículo 3. Son fines de la presente Ley:\nI. Proteger, respetar, procurar, recuperar y regenerar el espacio público y el paisaje urbano de la\nCiudad de México, promoviendo su creación, conservación, mantenimiento y defensa en condiciones de calidad, igualdad, inclusión, accesibilidad y diseño universal, con las medidas de seguridad, gestión integral de riesgos y protección civil, sanidad y funcionalidad para su pleno disfrute; asimismo, evitar la saturación publicitaria en el espacio público o en cualquier otro bien visible desde el exterior en la vía pública;\nII. Garantizar el derecho de las personas en la Ciudad de México a un entorno natural y urbano sostenible que propicie una mejor calidad de vida y libre desarrollo de la ciudadanía, garantizando su seguridad, la percepción armónica de la imagen urbana y el disfrute pleno del paisaje urbano, en su carácter colectivo, comunitario y participativo;\n\nIII. Preservar el paisaje urbano, las edificaciones y los elementos culturales y étnicos que hacen posible la vida en común de las personas y que conforman los rasgos característicos de la Ciudad de México;\nIV. Evitar el abuso de elementos no arquitectónicos que alteran el espacio público o que generen sobreestimulación visual agresiva y/o invasiva;\nV. Salvaguardar la integridad física y patrimonial de las personas, así como la infraestructura vial y de servicios de aquellos riesgos que pueden representar los medios publicitarios en exteriores, de conformidad con las normas en materia de gestión integral de riesgos y protección civil;\nVI. Garantizar la perspectiva de género, así como contribuir a la erradicación de la discriminación y toda forma de violencia contra las mujeres, y\nVII. Garantizar que la comunicación visual publicitaria esté libre de mensajes de discriminación motivada por origen étnico o nacional, de género, edad, discapacidad, condición social y de salud, religión, preferencia sexual, estado civil o cualquier otra que atente contra la dignidad humana.\nArtículo 4. Para los efectos de esta Ley se entiende por:\nI. Anunciante: persona física o moral, marca u organización, que difunda o publicite productos, bienes, servicios o actividades;\nII. Anuncio: medio publicitario a través del cual se difunden mensajes de información de compra, venta, renta, traspaso de inmuebles, oferta de empleo o similares, así como los de tipo denominativo, tapiales y carteleras de muro ciegos en planta baja, ubicados en vialidades secundarias, siempre y cuando no se encuentren en corredores publicitarios, en Áreas de\nConservación Patrimonial, en Áreas de Valor Ambiental, Áreas Naturales Protegidas o en Suelo de Conservación;\nIII. Áreas de Conservación Patrimonial: las que por sus características forman parte del patrimonio cultural urbano según las leyes de la Ciudad, así como las que cuenten con declaratoria federal de Zona de Monumentos Arqueológicos, Históricos o Artísticos, y aquellas que tengan características que requieren atención especial para mantener y potenciar sus valores patrimoniales y que serán definidas en los instrumentos del ordenamiento territorial;\n\nIV. Áreas Naturales Protegidas: espacios físicos naturales en donde los ambientes originales no han sido significativamente alterados por actividades antropogénicas, o que requieren ser preservados y restaurados, por su estructura y función para la recarga del acuífero y la preservación de la biodiversidad. Son áreas que por sus características ecogeográficas, contenido de especies, bienes y servicios ambientales y culturales que proporcionan a la población, hacen imprescindible su preservación;\nV. Áreas de Valor Ambiental: áreas verdes en donde los ambientes naturales originales han sido modificados por las actividades antropogénicas y que requieren ser restauradas y/o preservadas, en función de que siguen manteniendo ciertas características biofísicas y escénicas, las cuales les permiten contribuir a mantener la calidad ambiental de la Ciudad de México;\nVI. Autorización: documento que representa el derecho subjetivo de los particulares, que le confiere facultades o potestades específicas expresadas en actos administrativos competencia de la presente Ley y su Reglamento;\nVII. Autosoportado: el sostenido por una o mas columnas apoyadas a su vez en una cimentación o en una estela desplantada desde el suelo;\nVIII. Beneficio de espacios públicos: acciones que satisfacen necesidades de la población en el espacio público, buscan mejorar la imagen urbana, el equilibrio ambiental y la movilidad de la ciudadanía;\nIX. Bienes de uso común: aquellos que en la Ciudad de México pueden ser aprovechados por todas las personas, con las restricciones y limitaciones establecidas en la Ley del Régimen\nPatrimonial y del Servicio Público y demás normativa que resulte aplicable;\nX. Consejo: Consejo Consultivo para Medios Publicitarios;\nXI. Corredor Publicitario: vía primaria determinada por la Secretaría de Desarrollo Urbano y\nVivienda, de conformidad con lo dispuesto por esta Ley, en la que pueden instalarse medios publicitarios en vallas, tapiales, carteleras en muros ciegos en planta baja, bajo puentes, pasos a desnivel, túneles, conexiones elevadas interurbanas, así como aquellos que autorice la\nSecretaría de acuerdo con las disposiciones de esta Ley y su Reglamento;\n\nXII. DGPI: Dirección General de Patrimonio Inmobiliario de la Secretaría de Administración y\nFinanzas de la Ciudad de México;\nXIII. Equipamiento auxiliar de transporte: accesorios directos e indirectos que resulten complementarios a la prestación del servicio de transporte público de pasajeros y de carga;\nXIV. Equipamiento urbano: conjunto de inmuebles, instalaciones, construcciones y mobiliario urbano, destinados a prestar a la población servicios públicos, de administración pública, de educación y cultura; de comercio, de salud y asistencia; de deporte y de recreación, de traslado, de transporte y otros;\nXV. Espacio público: conjunto de bienes de uso común destinados a la generación y fomento de la interaccion social, o bien, que permitan el desarrollo de las personas.;\nXVI. Espectáculo tradicional: manifestaciones populares de contenido cultural que tengan connotación simbólica y/o arraigo en la sociedad y que contribuyan a preservar y difundir el patrimonio intangible que da identidad a los barrios, pueblos y colonias que conforman la\nCiudad de México;\nXVII. Estereotipos sexistas: prejuicios o estigmas que atribuyen o asocian características denigrantes, de exclusión, de sumisión, de racismo, de burla, de animadversión, o que presenten a las mujeres de forma humillante o discriminatoria, utilizando su cuerpo o parte de este como mero objeto y que atente contra su dignidad o vulnere sus derechos reconocidos en la Constitución Política de la Ciudad de México;\nXVIII. Funcionalidad de la vía pública: uso adecuado y eficiente de la vía pública, generado a través de la interacción de los elementos que la conforman y de la dinámica propia que en ella se desarrolla para la óptima prestación de los servicios públicos urbanos, la movilidad y la imagen urbana, procurando la seguridad, comodidad y disfrute de todas las personas usuarias;\nXIX. Información cívica o cultural: aquella que se difunde a través de medios publicitarios con o sin patrocinio y que alude a la responsabilidad social, derechos humanos, equidad, diversidad cultural, ciencia, salud, respeto al medio ambiente, memoria histórica y la difusión de las artes, entre otros que se consideren indispensables para fomentar la sana convivencia, el respeto, la cultura de la legalidad, la difusión del conocimiento de los derechos y obligaciones de la ciudadanía. Asimismo, los mensajes educativos sobre diversidad sexual, etaria, familiar,\n\nlingüística y funcional, que pueden incluir información sobre biodiversidad, pueblos originarios, etnias, lenguas y dialectos;\nXX. Infraestructura para la movilidad: infraestructura especial que permite el desplazamiento de personas y bienes, así como el funcionamiento de los sistemas de transporte público;\nXXI. Inmuebles afectos al patrimonio cultural de la Ciudad: aquellos considerados como tales por la legislación local debido a su valor histórico y/o arquitectónico. asimismo, aquellos catalogados por el Instituto Nacional de Bellas Artes y Literatura, o por la Secretaría de Desarrollo Urbano y\nVivienda, por su valor artístico y aquellos considerados monumentos históricos o artísticos de acuerdo con la legislación federal aplicable;\nXXII. Instituto: Instituto de Verificación Administrativa de la Ciudad de México;\nXXIII. Ley: Ley de Publicidad Exterior en la Ciudad de México;\nXXIV. Licencia: documento que representa el derecho subjetivo de los particulares, que le confiere facultades o potestades específicas expresadas en actos administrativos, mediante el cual la Secretaría de Desarrollo Urbano y Vivienda de la Ciudad de México permite la instalación de medios publicitarios;\nXXV. Materiales abandonados: lonas, estructuras, soportes, mantas, pantallas electrónicas, equipos de proyección y materiales similares adosados a los inmuebles, así como los objetos publicitarios colocados en la vía pública o cualquier vialidad, que no hayan tenido el mantenimiento que determine la autoridad competente, que no cuenten con Licencia, Permiso o Autorización vigente y cuyo dueño no los haya reclamado o retirado;\nXXVI. Medidas cautelares y de seguridad: disposiciones que dicte la autoridad competente para proteger la salud, seguridad pública y evitar el incumplimiento de la normativa referente a las actividades reguladas que requieran de licencia, permiso o autorización. Las medidas cautelares y de seguridad se establecerán en cada caso por las normas administrativas que no deberán contravenir las disposiciones legales aplicables;\nXXVII. Medio publicitario: cualquier elemento material, con o sin estructura de soporte, por el cual se difunde física, electrónica o digitalmente un mensaje explícito o implícito o bien que, sin contener un mensaje, sea una unidad integral en términos de la presente Ley;\n\nXXVIII. Medio publicitario en vehículo de transporte: el instalado en vehículos de transporte de conformidad con lo establecido en la presente Ley;\nXXIX. Mobiliario urbano: elementos complementarios al equipamiento urbano, ya sean fijos, móviles, permanentes o temporales, ubicados en la vía pública o en espacios públicos formando parte de la imagen de la Ciudad, los que, según su función, se aplican para el descanso, comunicación, información, necesidades fisiológicas, comercio, seguridad, higiene, servicio, jardinería, así como aquellos otros muebles que determinen la Secretaría de Desarrollo Urbano y Vivienda de la Ciudad de México y la Comisión Mixta de Mobiliario Urbano. El mobiliario urbano con publicidad integrada será objeto de la regulación establecida en esta Ley;\nXXX. Muros ciegos: muros que carecen de vanos;\nXXXI.Paisaje urbano: contexto que conforman las edificaciones y demás elementos culturales y naturales que hacen posible la vida en común de la ciudadanía, así como el entorno ambiental en el que se insertan, los cuales conforman los rasgos característicos de la Ciudad y crean un sentido de identidad colectiva;\nXXXII. Permiso: documento que representa el derecho subjetivo de los particulares, que le confiere facultades o potestades específicas expresadas en actos administrativos, por el cual las autoridades competentes permiten la instalación de medios publicitarios de conformidad con lo dispuesto por la Ley de Movilidad de la Ciudad de México, esta Ley y los Reglamentos aplicables;\nXXXIII. PATR: Permiso Administrativo Temporal Revocable, acto administrativo en virtud del cual la Secretaría de Administración y Finanzas, a través de la Dirección General de Patrimonio\nInmobiliario otorga a una persona física o moral el uso de bienes inmuebles propiedad de la\nCiudad, ya sean del dominio público o privado, con el objeto de utilizarlos para la instalación y comercialización de medios publicitarios, de conformidad con la Ley del Régimen Patrimonial y del Servicio Público;\nXXXIV. Plataforma: Plataforma Digital de Publicidad Exterior de la Ciudad de México;\nXXXV. Publicista: persona física o moral dedicada a la instalación, gestión, operación y comercialización de medios publicitarios;\n\nXXXVI.Publicidad institucional: mensajes relativos a las acciones que realizan las distintas autoridades del Gobierno, tanto local, como federal, con fines de comunicación con la población en general;\nXXXVII. Publicidad de carácter sexista: todo contenido publicitario visible desde la vía pública, que directa o indirectamente induzca, fomente o difunda hechos, acciones y símbolos, degradantes o peyorativos hacia las mujeres, así como expresiones basadas en una imagen asociada a estereotipos que perpetúan prejuicios o estigmas que atribuyen o asocian características denigrantes, de exclusión, sumisión, racismo, burla, animadversión o que presenten a las mujeres de forma humillante o discriminatoria, así como utilizar su cuerpo, o parte de éste, como objeto y atente contra su dignidad o vulnere sus derechos reconocidos en la\nConstitución Política de la Ciudad de México;\nXXXVIII. Registro de Publicistas: Listado o padrón de personas físicas o morales que se dedican prioritariamente a la instalación, gestión, operación y comercialización de medios publicitarios en la Ciudad, inscritos debidamente ante la Secretaría de Desarrollo Urbano y Vivienda de la\nCiudad de México, en el que se podrá incorporar el Padrón de Publicidad Exterior publicado el\n10 de diciembre de 2015 en la Gaceta Oficial de la Ciudad de México, y los demás que reconozca la Secretaría, de Desarrollo Urbano y Vivienda.\nXXXIX. Reglamento: Reglamento de la Ley de Publicidad Exterior en la Ciudad de México;\nXL. Responsable de un inmueble: persona física o moral que tenga la propiedad, posesión o administración de un bien inmueble y permita la instalación de un medio publicitario en el mismo;\nXLI. Responsable solidario: publicista, anunciante y responsable de un inmueble, vehículo o bien que permiten o intervienen en la instalación de medios publicitarios;\nXLII. Riesgo inminente: riesgo que, de acuerdo con la opinión técnica emitida por la Secretaría de Gestión Integral de Riesgos y Protección Civil de la Ciudad de México, considera la realización de acciones inmediatas en virtud de existir altas probabilidades de que se produzcan daños o pérdidas;\nXLIII. SAF: Secretaría de Administración y Finanzas de la Ciudad de México;\n\nXLIV. Secretaría: Secretaría de Desarrollo Urbano y Vivienda de la Ciudad de México;\nXLV. Señalización Vial: conjunto de elementos y objetos visuales de contenido informativo, indicativo, restrictivo, preventivo, prohibitivo o de cualquier otro carácter, que se colocan en la infraestructura urbana con el fin de procurar un adecuado funcionamiento vial;\nXLVI. SGIRPC: Secretaría de Gestión Integral de Riesgos y Protección Civil de la Ciudad de México;\nXLVII.SEMOVI: Secretaría de Movilidad de la Ciudad de México;\nXLVIII. Solicitante: persona física o moral que solicite un Permiso, Licencia o Autorización en los términos de esta Ley;\nXLIX. Suelo de Conservación: zonas que, por sus características ecológicas, proveen servicios ambientales, de conformidad con lo establecido en la normativa en materia ambiental. Se consideran necesarios para el mantenimiento de calidad de vida de las personas habitantes y vecinas de la Ciudad de México;\nL. Vanos: puertas, ventanas e intercolumnios de una edificación, así como los elementos arquitectónicos de las edificaciones. Están destinados a permitir el paso de las personas, iluminación y ventilación natural al interior;\nLI. Vía primaria: espacio físico, cuya función es facilitar el flujo del tránsito vehicular continuo o controlado por semáforo, entre distintas zonas de la Ciudad, con la posibilidad de reserva para carriles exclusivos, las cuales pueden contar con carriles exclusivos para la circulación de bicicletas y/o transporte público, y\nLII. Vía secundaria: espacio físico cuya función es permitir el acceso a los predios y facilitar el flujo del tránsito vehicular no continuo. Sus intersecciones pueden estar controladas por semáforos;\nArtículo 5. La publicidad exterior es todo medio publicitario que se instala en el espacio público u otros bienes y que es visible desde el exterior a la vía pública. Su finalidad es difundir propaganda, publicidad comercial o información diversa de interés general.\n\nLa instalación, modificación o retiro de esta clase de publicidad exterior comprenderá el de todos sus elementos y deberá apegarse a lo establecido por la presente Ley, su Reglamento y demás disposiciones aplicables en la materia.\nArtículo 6. La instalación de la propaganda electoral se regirá por las disposiciones de las Leyes Electorales.\nCAPÍTULO SEGUNDO\nATRIBUCIONES\nArtículo 7. Son atribuciones de la Secretaría:\nI. Establecer, coordinar, ejecutar y evaluar las políticas, estrategias y acciones para la instalación, mantenimiento, distribución, permanencia y retiro de los medios publicitarios de su competencia;\nII. Proponer a la persona titular de la Jefatura de Gobierno proyectos de disposiciones legales y reglamentarias en materia de publicidad exterior, así como sus reformas;\nIII. Conservar en forma ordenada y sistemática toda la documentación que genere con motivo del ejercicio de las atribuciones que le confiere esta Ley y su Reglamento;\nIV. Generar un expediente electrónico de los publicistas asociados con lo relativo a los medios publicitarios de su competencia; lo anterior, en términos de lo establecido en la Ley de\nCiudadanía Digital de la Ciudad de México;\nV. Otorgar las Licencias para la instalación de medios publicitarios previstos en el artículo 28 fracción III de esta Ley, conforme a lo dispuesto en la misma y su Reglamento;\nVI. Revocar las Licencias otorgadas para la instalación de medios publicitarios conforme a lo dispuesto en esta Ley y su Reglamento;\nVII. Requerir a los publicistas el retiro de publicidad, en caso de que contravengan lo dispuesto por la presente Ley, su Reglamento y los demás ordenamientos aplicables. Dicho retiro será a costa de las personas responsables solidarias de la instalación;\n\nVIII. Informar, a través de la Plataforma, al Instituto y a la SGIRPC de la emisión y revocación de las Licencias, así como de las resoluciones judiciales o administrativas que establezcan derechos respecto de medios publicitarios o las dejen sin efectos;\nIX. Solicitar al Instituto y a las Alcaldías las visitas de verificación administrativa y, en su caso, la imposición de medidas cautelares y de seguridad, en el ámbito de sus respectivas competencias;\nX. Mantener actualizada la Plataforma con el registro de las Licencias que emita, incluyendo los datos de ubicación de los medios publicitarios, así como la información respectiva al Registro de\nPublicistas;\nXI. Ordenar al publicista la ejecución de los trabajos de conservación y mantenimiento de los medios publicitarios instalados que sean necesarios para garantizar la seguridad de las personas y sus bienes, de conformidad con lo dispuesto en esta Ley, su Reglamento y la normativa en materia de construcciones;\nXII. Solicitar a las dependencias y autoridades correspondientes el retiro de los materiales relacionados con los medios publicitarios abandonados;\nXIII. Solicitar el apoyo de otras dependencias, órganos o entidades de la Administración Pública de la Ciudad y Alcaldías para el ejercicio de sus atribuciones;\nXIV. Determinar los corredores publicitarios. Para tal efecto, solicitará opinión al Congreso, a través de la Comisión de Desarrollo e Infraestructura Urbana, la cual tendrá un plazo de veinte días hábiles para emitirla.\nXV. Determinar la distribución de los espacios respectivos para la instalación de los medios publicitarios en los corredores publicitarios;\nXVI. Emitir opinión técnica respecto a la colocación de medios publicitarios ubicados en Áreas de\nConservación Patrimonial catalogadas por la Secretaría;\nXVII. Presentar las denuncias correspondientes cuando tenga conocimiento de hechos que puedan constituir algún delito en materia de publicidad exterior, así como ejercer las acciones civiles por posibles daños al erario o bienes públicos en contra de las personas responsables de\n\nla instalación de medios publicitarios sin contar con la Licencia, Permiso o Autorización que corresponda;\nXVIII. Autorizar la inscripción de los interesados en el Registro de Publicistas, previa solicitud de éstos y en cumplimiento con lo dispuesto en esta Ley, su Reglamento y demás disposiciones aplicables;\nXIX. Suspender o revocar el registro de publicistas en los casos que se acrediten irregularidades graves, se generen daños o se cometa alguna infracción en esta materia, y\nXX. Las demás que se le atribuyan en esta Ley, su Reglamento y demás ordenamientos aplicables.\nArtículo 8. Son atribuciones de las Alcaldías:\nI. Establecer, coordinar, ejecutar y evaluar las políticas, estrategias y acciones para la instalación, permanencia y retiro de los medios publicitarios colocados en vías secundarias dentro de su territorio;\nII. Conservar en forma ordenada y sistematizada toda la documentación que genere con motivo del ejercicio de las atribuciones que le confiere esta Ley y su Reglamento, de conformidad con lo establecido en la ley de la materia;\nIII. Generar un expediente electrónico de los publicistas asociados con lo relativo a los medios publicitarios de su competencia, en los términos de la Ley de Ciudadanía Digital de la Ciudad de\nMéxico;\nIV. Otorgar las Autorizaciones para la instalación de anuncios, a través de los cuales se difunden mensajes de compra, venta, renta, traspaso de inmuebles, oferta de empleo o similares, así como los de tipo denominativo, tapiales y carteleras de muro ciegos en planta baja, ubicados en vialidades secundarias, siempre y cuando no se encuentren en corredores publicitarios, en Áreas de Conservación Patrimonial, en Áreas de Valor Ambiental, Áreas Naturales Protegidas o en\nSuelo de Conservación, conforme a lo dispuesto en esta Ley, su Reglamento y demás normativa aplicable;\nV. Revocar las Autorizaciones para la instalación de anuncios materia de su competencia;\n\nVI. Requerir al publicista el retiro de anuncios por contravenir lo dispuesto en la presente Ley, su\nReglamento y demás ordenamientos aplicables. Dicho retiro será a costa de las personas responsables solidarias;\nVII. Informar al Instituto y a la SGIRPC de la emisión y revocación de las Autorizaciones de su competencia, así como de las resoluciones judiciales o administrativas que establezcan derechos respecto de anuncios o las dejen sin efectos;\nVIII. Ordenar a la persona titular de una Autorización emitida en el ámbito de su competencia la ejecución de los trabajos de conservación y mantenimiento de los anuncios instalados que sean necesarios para garantizar la seguridad de las personas y sus bienes, de conformidad con lo dispuesto en esta Ley, su Reglamento y la normativa en materia de construcciones;\nIX. Mantener actualizada la Plataforma con el registro de las Autorizaciones que emitan, incluyendo los datos de ubicación de los anuncios;\nX. Solicitar a las dependencias y autoridades competentes el retiro de los materiales relacionados con anuncios abandonados;\nXI. Retirar directamente todos los anuncios considerados abandonados que se encuentren en vías secundarias;\nXII. Ordenar visitas de verificación administrativa a fin de vigilar el cumplimiento de lo dispuesto en esta Ley respecto anuncios e imponer las medidas cautelares y de seguridad, así como las sanciones procedentes en el ámbito de su competencia y ejecutarlas a través del personal especializado en funciones de verificación debidamente acreditado. Lo anterior, conforme al procedimiento establecido en la Ley de Procedimiento Administrativo, la Ley del Instituto de\nVerificación Administrativa, el Reglamento de Verificación Administrativa, todos vigentes en la\nCiudad de México y demás disposiciones jurídicas aplicables;\nXIII. Emitir, a través de su Unidad de Gestión Integral de Riesgos y Protección Civil, las opiniones técnicas de indicadores de riesgo en esta materia, que le soliciten las autoridades competentes en la materia, las personas titulares de las autorizaciones de anuncios, así como en aquellos casos en los que se detecte una situación de riesgo, a fin de que se realicen las acciones correspondientes conforme a sus competencias, y\n\nXIV. Las personas titulares de las Alcaldías responderán por las autorizaciones emitidas y serán responsables de todas aquellas que hayan sido emitidas en contravención a esta Ley.\nArtículo 9. Corresponde al Instituto ordenar y practicar visitas de verificación administrativa a fin de vigilar el cumplimiento de lo dispuesto en esta Ley y su Reglamento, conforme a la Ley de Procedimiento\nAdministrativo, la Ley del Instituto de Verificación Administrativa y el Reglamento de Verificación\nAdministrativa, todos vigentes en la Ciudad de México, así como las demás disposiciones jurídicas aplicables.\nEl instituto cuenta con la facultad de imponer las medidas cautelares y de seguridad y, en su caso, las sanciones procedentes, respecto de los siguientes medios publicitarios:\nI. Prohibidos de conformidad con la presente Ley;\nII. Que requieran Licencia, permiso o autorización; e\nIII. Instalados en vehículos de transporte y en el equipamiento auxiliar del transporte.\nEn los casos en que sea factible, el Instituto dará vista a la Secretaría respecto de los datos de identificación del anunciante y del medio publicitario objeto del retiro, lo anterior, a efecto que ésta, de ser procedente, realice las acciones establecidas en las fracciones XVI y XVIII del artículo 7 de esta Ley.\nArtículo 10. Son atribuciones de la SAF:\nI. Otorgar, asignar o revocar, de acuerdo con la Ley del Régimen Patrimonial y del Servicio\nPúblico, los permisos relacionados con la colocación de publicidad exterior en los bienes inmuebles que integran el patrimonio de la Ciudad, y\nII. Recibir, a través de la Tesorería de la Ciudad de México, los pagos por concepto de derechos que se generen por la expedición de Licencias, Autorizaciones y Permisos, así como aquellos que provengan del pago de multas y sanciones.\nArtículo 11. Son atribuciones de la SGIRPC:\n\nI. Emitir opiniones técnicas de indicadores de riesgo en materia de protección civil que le soliciten las autoridades competentes en la materia, las personas titulares de las licencias, permisos y autorizaciones, así como en aquellos casos en los que se detecte una situación de riesgo, de conformidad con la normativa en la materia. Lo cual deberá hacerlo del conocimiento de la persona solicitante o, en su caso, de las autoridades competentes, a fin de que éstas realicen las acciones correspondientes conforme a sus competencias;\nII. Emitir y registrar las opiniones técnicas a los proyectos de instalación de medios publicitarios, conforme a lo establecido en la normativa aplicable en la materia, así como publicarlas en la\nPlataforma, y\nIII. Las demás que se establezcan en esta Ley, su Reglamento y demás ordenamientos aplicables.\nArtículo 12. Son atribuciones de la SEMOVI:\nI. Autorizar, regular y, en su caso, revocar los permisos relativos a la instalación de medios publicitarios en vehículos de transporte público, privado y mercantil, de pasajeros y de carga y demás modalidades, de conformidad con lo establecido en la Ley de Movilidad de la Ciudad de\nMéxico y su Reglamento, así como en toda aquella normativa aplicable en la materia;\nII. Otorgar, regular y, en su caso, revocar las autorizaciones relativas a la instalación de medios publicitarios en equipamiento auxiliar de transporte, de conformidad con lo establecido en la\nLey de Movilidad de la Ciudad de México y su Reglamento, así como en toda aquella normativa aplicable en la materia;\nIII. Emitir, a solicitud de la Secretaría, visto bueno relativo a la ubicación y características de medios publicitarios en equipamiento auxiliar de transporte;\nIV. Emitir los Lineamientos en materia de medios publicitarios instalados en la infraestructura para la movilidad de los organismos que forman parte del Sistema Integrado de Transporte\nPúblico y sus componentes complementarios, los cuales deberán ser observados en las disposiciones que establezcan sus respectivos órganos de Gobierno y en concordancia con lo establecido en la Ley de Movilidad, la Ley del Régimen Patrimonial y del Servicio Público, así como demás disposiciones aplicables;\n\nV. Emitir normativa complementaria en materia de regulación de medios publicitarios en vehículos de transporte de pasajeros y de carga en todas sus modalidades, y en medios publicitarios en equipamiento auxiliar de transporte, de conformidad con lo establecido en la\nLey de Movilidad de la Ciudad de México y su Reglamento, así como en toda aquella normativa aplicable en la materia;\nVI. Requerir a los responsables de los vehículos de transporte o del equipamiento auxiliar de transporte el retiro de los medios publicitarios instalados en los mismos, por contravenir las disposiciones legales en la materia, dentro del ámbito de sus atribuciones;\nVII. Dar vista a la SAF de hechos relacionados con medios publicitarios instalados en equipamiento auxiliar de transporte que contravengan las disposiciones legales establecidas o los términos bajo los cuales fueron autorizados y que puedan constituir una causal de revocación del Permiso Administrativo Temporal Revocable;\nVIII. Solicitar al Instituto las visitas de verificación administrativa y, en su caso, la imposición de medidas cautelares y de seguridad procedentes, respecto de medios publicitarios de su competencia;\nIX. Coadyuvar con el Instituto para la realización de las acciones dirigidas a la verificación administrativa y, en su caso, la imposición de medidas cautelares y de seguridad de medios publicitarios de su competencia;\nX. Mantener actualizada la Plataforma con el registro de las Autorizaciones y Permisos que emita, incluyendo los datos de los vehículos o el bien en el que se instale, y\nXI. Las demás que le atribuyen otros ordenamientos aplicables.\nArtículo 13. En el ejercicio de sus atribuciones la Secretaría, las Alcaldías, el Instituto, la SAF, la SGIRPC y la\nSEMOVI podrán auxiliarse de otras instancias públicas.\nArtículo 14. Previa obtención de la Licencia, Autorización, PATR o Permiso, según corresponda, únicamente estará permitida la instalación de los siguientes medios publicitarios:\n\nI. Medio publicitario de espectáculos tradicionales: aquellos relacionados con tradiciones y costumbres de un lugar, tales como; ferias, bailes, exposiciones de tipo cultural y artístico, los cuales se sujetarán a los criterios previstos en el Reglamento de esta Ley;\nII. Medio publicitario denominativo: contiene el nombre o denominación comercial, logotipo o emblema con el que se identifica una persona física o moral, una edificación y una actividad, podrán ser colocados en fachadas de los inmuebles o en toldos sobre los vanos de éstas, puede ser integrado, adosado, letras separadas en bajo y alto relieve, pintado o adherido.\nReforma publicada en la GOCDMX el 28 de Marzo de 2023\nLa denominación podrá acompañarse de un eslogan.\nReforma publicada en la GOCDMX el 28 de Marzo de 2023\nEn el Centro Histórico de la Ciudad de México y otras Zonas de Monumentos Históricos, así como en las Áreas de Conservación Patrimonial, se deberán respetar tamaños, ubicación, dimensiones, colores y materiales permitidos, en estricto apego a la normativa establecidas por la Secretaría, en concurrencia con lo establecido por la Ley Federal sobre Monumentos y Zonas Arqueológicos,\nArtísticos e Históricos, con el Instituto Nacional de Antropología e Historia y el Instituto Nacional de Bellas Artes y Literatura;\nIII. Medio publicitario denominativo masivo: medio publicitario denominativo que requiere instalarse en más de cinco ocasiones con características idénticas;\nIV. Medio publicitario denominativo adosado: medio publicitario que se sujeta a una fachada, muro, baranda o barandilla a través de medios y técnicas definidas en el Reglamento;\nV. Medio publicitario denominativo instalado en saliente: aquellos instalados en salientes, tratándose únicamente de denominativos, con las dimensiones y características previstas en el\nReglamento;\nVI. Medio publicitario denominativo mixto: contiene elementos de un medio publicitario denominativo en combinación con medios publicitarios en vallas, banderines y gallardetes u otro elemento determinado en el Reglamento;\nVII. Medio publicitario de gallardetes: medio publicitario de carácter temporal de forma geométrica, sujeto a un asta, astil o poste, en el cual, únicamente se puede colocar información\n\ncívica o cultural y de espectáculos tradicionales. Las dimensiones de éste serán de hasta 0.80 metros por 2.00 metros y deberán ser armónicas con el paisaje urbano, se sujetarán a los criterios antropométricos de esta Ley y su Reglamento;\nVIII. Medio publicitario digital o electrónico: aquellos a través de los cuales se transmiten mensajes mediante un sistema luminoso;\nIX. Medio publicitario de tótem: anuncio denominativo o informativo en una cimentación rectangular o cilíndrica;\nX. Mobiliario urbano con publicidad integrada: aquel que estará determinado por las necesidades de la Ciudad con el objetivo de mejorar la calidad del espacio público, las condiciones de seguridad ciudadana y accesibilidad.\nLa Comisión Mixta de Mobiliario Urbano aprobará y ratificará las dimensiones máximas para el mobiliario, de acuerdo con las necesidades del espacio público y criterios de funcionalidad e integración armónica con el paisaje urbano, atendiendo lo que disponga el Reglamento. Todos los proyectos de colocación y diseño de mobiliario con fines publicitarios, deberán sujetarse a lo anterior.\nNingún nuevo mobiliario urbano con publicidad integrada podrá instalarse en zonas y ubicaciones donde ya existan otras modalidades de mobiliario con publicidad, de acuerdo con las definiciones de proporcionalidad espacial definidas en esta Ley y su Reglamento.\nEl mobiliario urbano con publicidad integrada sólo podrá instalarse en ubicaciones y corredores publicitarios autorizados por la Secretaría.\nLas unidades de mobiliario urbano con publicidad integrada deberán colocarse observándose un radio de, al menos, 150 metros entre sí, distribuidos alternadamente a razón de no más de uno por cuadra y dejando una cuadra libre como mínimo, sin traslaparse con otros medios de publicidad.\nAdicionalmente, la colocación de mobiliario urbano con publicidad integrada debe cumplir estrictamente con los siguientes requisitos:\na) No obstruir el tránsito peatonal ni la accesibilidad universal del espacio público;\n\nb) No afectar la seguridad del tránsito vehicular;\nc) No emplazarse sobre Áreas de Valor Ambiental y no implicar la tala o poda de árboles o follaje para su instalación o visibilidad;\nd) No generar saturación física ni visual, y e) Cumplir con lo previsto en esta Ley y su Reglamento.\nEn el Centro Histórico de la Ciudad de México y otras Zonas de Monumentos Históricos, así como en Áreas de Conservación Patrimonial se deberán respetar tamaños, ubicación, dimensiones, colores y materiales, en apego a la normativa establecida por la Secretaría, en concurrencia con la Ley Federal sobre Monumentos y Zonas Arqueológicas, Artísticas e Históricas, así como con el\nInstituto Nacional de Antropología e Historia y el Instituto Nacional de Bellas Artes y Literatura.\nLa colocación de todo mobiliario urbano con publicidad integrada en los espacios, vías, infraestructuras, equipamientos o bienes inmuebles propiedad de la Ciudad, ya sean del dominio público o privado y que esta Ley contempla, deberá contar con el Permiso\nAdministrativo Temporal Revocable emitido por la SAF, en términos de la Ley del Régimen\nPatrimonial y del Servicio Público, así como con la aprobación de la Comisión Mixta de Mobiliario\nUrbano respecto a su diseño y volumetría. La Secretaría aprobará mediante oficio el emplazamiento de cada unidad de mobiliario urbano en observancia de los criterios de espacialidad y beneficio del espacio público definidos en esta Ley y su Reglamento;\nXI. Medio publicitario en vehículos de transporte: el instalado en vehículos de transporte, previsto en la Ley de Movilidad de la Ciudad de México y su Reglamento, la presente Ley y los lineamientos que para tal efecto emita la SEMOVI;\nXII. Medio publicitario en equipamiento auxiliar de transporte: anuncio instalado en los accesorios directos e indirectos que resulten complementarios a la prestación del servicio de transporte de pasajeros y de carga, que sean susceptibles de autorización para su ubicación y características por parte de la SEMOVI;\nXIII. Medio publicitario en tapiales: el instalado en un tablero de madera, lámina u otros materiales, ubicado en vía pública, destinado a cubrir el perímetro de una obra en proceso de construcción;\n\nXIV. Medio publicitario en valla: cartelera situada en lotes baldíos, estacionamientos públicos y obra en proceso, con fines publicitarios, de conformidad con lo dispuesto por esta Ley y su\nReglamento;\nXV. Medio publicitario en túneles, pasos a desnivel y bajo puentes en corredores publicitarios:\ndichos medios publicitarios deberán cumplir con las características, términos y condiciones que se establezcan en el Reglamento;\nXVI. Medio publicitario temporal en mallas de protección para arreglo y mantenimiento de fachadas, con o sin valor patrimonial: el instalado en una estructura temporal tipo andamio, sobre el que se coloca una malla hasta el 50 % con publicidad. La colocación del andamio deberá permitir el libre y seguro tránsito peatonal sin obstruir la circulación y se instalará bajo las especificaciones determinadas por esta Ley y su Reglamento. Dicho medio publicitario deberá permitir la visibilidad de los trabajos de mantenimiento de las fachadas en que se instalen.\nLos proyectos de arreglo y mantenimiento de fachadas serán autorizados por la Secretaría, sin detrimento de las determinaciones que emitan el Instituto Nacional de Antropología e Historia y/o el Instituto Nacional de Bellas Artes y Literatura, en el ámbito de sus respectivas competencias, conforme a la legislación federal aplicable. El incumplimiento de los términos autorizados en los proyectos de intervención será motivo para suspender o revocar las Licencias respectivas, así como la suspensión o eliminación a del Registro de Publicistas, sin perjuicio de las sanciones que impongan las autoridades competentes;\nXVII. Medios publicitarios de proyección óptica, virtual y nuevas tecnologías: aquellos emitidos por proyección sobre un elemento macizo, los cuales no podrán tener un carácter permanente ni afectar la imagen arquitectónica y sólo se permitirán en condiciones específicas y de manera temporal. Únicamente se permitirá la instalación de estos medios publicitarios para difundir información cívico o cultural con patrocinio y deberán cumplir con las demás especificaciones determinadas en el Reglamento. El tiempo de proyección deberá ser autorizado por la Secretaría, de acuerdo con la propuesta que presente el publicista.\nEste tipo de medios publicitarios sólo podrá utilizarse de acuerdo con criterios de densidad y equilibrio territorial de su ubicación que serán definidos por la Secretaría, establecidos en el\nReglamento y no se podrán instalar sobre fachadas de cristal o que contengan vanos.\n\nEn el caso de los inmuebles y monumentos protegidos o catalogados por el Instituto Nacional de\nAntropología e Historia y/o el Instituto Nacional de Bellas Artes y Literatura, las proyecciones sólo podrán autorizarse previa aprobación de dichos Institutos;\nXVIII. Medios publicitarios de cartelera publicitaria en muro ciego de planta baja: aquellos instalados en muros carentes de vanos y accesos sobre el que se colocará un bastidor ligero de madera o metal sobre el que se colocan carteles publicitarios de materiales reciclables y no permanentes, los cuales deberán estar distribuidos y colocados conforme a las disposiciones del\nReglamento de esta Ley;\nXIX. Anuncios con información de compra, venta, renta, traspaso de inmuebles, oferta de empleo o similares: todo aquel que no se coloque en pendones sobre bienes del dominio público, como en postes de señalización vial, dispositivos de tránsito, telefonía, transmisión de datos y árboles;\nXX. Medios publicitarios con valor patrimonial cultural: aquellos que, dado su valor histórico, artístico o visual en la memoria colectiva de la Ciudad de México, sean declarados de forma individual como bienes materiales afectos al Patrimonio Cultural en los términos de las leyes local y/o federal de la materia;\nXXI. Medio publicitario en conexión elevada interurbana: infraestructura pública con diseño universal que facilita la funcionalidad de la vía pública y permite la interconexión y movilidad tanto de ciclistas como de peatones, dotados de estacionamiento y servicios para bicicletas particulares;\nXXII. Medio publicitario de información cívico cultural: aquellos que difunden información cívica o cultural con o sin patrocinio. Dicho patrocinio deberá cumplir con:\na) Medios impresos, con imágenes fijas o no digitales: la imagen publicitaria comercial no deberá exceder el 20% de la superficie que se expone, y b) Medios digitales o de proyección: la imagen publicitaria comercial no deberá exceder el 15% del tiempo en pantalla.\nEste tipo de medios podrá contar con una licencia de temporalidad acotada a solicitud del publicista y de acuerdo a lo que la Secretaría apruebe en función de criterios de respeto al espacio público, y\n\nXXIII. Medio publicitario denominativo institucional: el que contiene el nombre y el logo de una institución pública local o federal.\nTratándose de medios publicitarios que, de acuerdo con sus características, no se encuentren previstos en este artículo y sean sometidos a consideración de la Secretaría, ésta valorará si es viable o no otorgar una licencia conforme a lo dispuesto en esta Ley, siempre y cuando no se encuentren expresamente prohibidos.\nArtículo 15. En la Ciudad queda prohibida la instalación de los siguientes medios publicitarios:\nI. Instalados en las azoteas;\nII. Autosoportados;\nIII. Con sonido;\nIV. Instalados o pintados en cerros, rocas, árboles, bordes de ríos, lomas, laderas, bosques, lagos o en cualquier otra formación natural;\nV. Colocados en lonas, mantas o mallas que se encuentren fijados, clavados, amarrados o pegados directamente a algún elemento arquitectónico de la fachada del inmueble;\nVI. Pintados o adheridos a una fachada, muro, barda o barandilla, sin ser denominativo;\nVII. Envolventes, instalados, adheridos o pintados en elementos arquitectónicos de las edificaciones, tales como, ventanas, ventanales, muros ciegos no colindantes, fachadas y puertas, que afecten la imagen arquitectónica o impidan, parcial o totalmente, el libre paso de las personas, la iluminación, visibilidad o la ventilación natural al interior.\nSolo se permitirán para la colocación de medios publicitarios de renta, venta o denominativos bajo características que no intervengan en cuestiones de accesibilidad, visibilidad, iluminación, ventilación y seguridad, de conformidad con lo previsto en el Reglamento;\nVIII. En unidades habitacionales, de conformidad con lo establecido en la ley de la materia;\nIX. En postes de señalización vial y dispositivos de tránsito;\n\nX. Pendones de promociones, compra, venta, renta o cualquier otro tipo de servicio instalados en postes de señalización vial, electricidad, telefonía, transmisión de datos, dispositivos de tránsito y en árboles;\nXI. Con drones;\nXII. Cuando se trate de medios publicitarios inflables, cualquiera que sea el lugar de su instalación o estén suspendidos en el aire;\nXIII. Modelados, figurativos o abstractos, con volumen o en tres dimensiones, cualquiera que sea el lugar de su instalación;\nXIV. Adheridos a vidrios, escaparates o ventanales de los establecimientos mercantiles, cuando éstos obstruyan la accesibilidad, visibilidad, iluminación, ventilación y/o seguridad, de conformidad con lo previsto en el Reglamento, excepto aquellos a que se hace alusión en el segundo párrafo del artículo 38 de esta Ley;\nXV. Medios publicitarios en muros ciegos de colindancia;\nXVI. Medios publicitarios que contengan cualquier imagen estática o en movimiento, que atente contra la dignidad de las personas o vulnere los valores o derechos humanos;\nXVII. Proyectados sobre las edificaciones públicas o privadas desde un vehículo en movimiento;\nXVIII. En zonas de conservación ecológica, áreas de valor ambiental, áreas naturales protegidas, bosques y zonas arboladas.\nSolo se permitirá publicidad exterior en parques y jardines tratándose de medios publicitarios que tengan fines de beneficio al espacio público o contengan mensajes informativos, cívicos o culturales, en los términos y ubicaciones que se determinen en el Reglamento;\nXIX. En estructuras instaladas en vehículos motorizados y no motorizados de propiedad pública o privada, que no formen parte del diseño original del vehículo y que tengan fines publicitarios, tales como carteleras en un tablero de madera, lámina, pantallas, anuncios volumétricos, vallas móviles o cualquier otro tipo de estructura;\n\nXX. Pintados, adheridos o indicados sobre el piso del espacio público, directamente o en una placa o soporte;\nXXI. En puentes peatonales.\nXXII. Proyecciones con cualquier tipo de publicidad, cuando éstas se lleven a cabo sobre viniles, pantallas, lonas o cualquier elemento adherido o montado de forma temporal o permanente en fachadas, muros ciegos, cristales o elementos arquitectónicos, y\nXXIII. Los demás que se ubiquen en lugares no permitidos expresamente en esta Ley.\nArtículo 16. Los publicistas procurarán que los materiales para la fabricación y soporte de los medios publicitarios sean biodegradables y deberán evitar que contengan sustancias tóxicas o nocivas para la salud o el medio ambiente; lo anterior, en términos de las disposiciones jurídicas aplicables en materia ambiental y de residuos sólidos.\nArtículo 17. El contenido de los medios publicitarios será acorde al marco legal de la libertad de expresión, por lo que se prohíbe la instalación de aquellos medios publicitarios cuyos contenidos atenten contra la dignidad de las personas, vulneren los derechos humanos y aquellos que difundan mensajes sexistas, lenguaje misógino o inciten a cualquier tipo de violencia.\nArtículo 18. Estará permitida la instalación de medios publicitarios con iluminación, los cuales, preferentemente, deberán ser fabricados con materiales reciclables y sistemas ahorradores de energía, sin contener sustancias tóxicas o nocivas para la salud de las personas o el medio ambiente de conformidad con las Normas Oficiales Mexicanas y demás normativa aplicable.\nAsimismo, dichos medios publicitarios deberán cumplir con las siguientes características:\nI. Funcionarán mediante el uso de leds;\nII. El nivel directo al medio publicitario será hasta 600 luxes, siempre que su reflejo no exceda de 50 luxes;\nIII. Las pantallas electrónicas no podrán exceder de 3 nits sobre la luminosidad ambiental y los\n325 nits durante su proyección en el horario de las 18:00 a 6:00 horas del día siguiente;\n\nIV. En caso de que su contenido consista en imágenes fijas, no podrán tener una duración menor de 18 segundos, ni mayor de 30;\nV. Deberán contar con sensor de intensidad y sistema automático de ajuste que reduzca la misma al nivel permitido;\nVI. No deben tener cambios en la intensidad de la luminosidad durante el periodo en que los mensajes están fijos, ni contener luces en movimiento;\nVII. No deberán contener videos, ni imágenes con fondos blancos, y\nVIII. Las pantallas electrónicas no podrán emitir sonido o proyectar rayos de luz.\nEl cumplimiento de las disposiciones anteriores, se acreditarán al momento de solicitar la Licencia respectiva. La autoridad competente podrá realizar visitas de verificación en cualquier momento.\nDurante la vigencia de la Licencia de los medios publicitarios instalados con iluminación, los publicistas otorgarán a favor del Gobierno de la Ciudad, sin costo, el quince por ciento del tiempo de exhibición al día para emitir mensajes institucionales, culturales, o cívicos. En casos de emergencia o desastre, el Gobierno de la Ciudad podrá disponer de los porcentajes necesarios para dicho efecto.\nLas pantallas electrónicas que sean utilizadas como medios publicitarios solo podrán instalarse en mobiliario urbano, tapiales, vallas y autosoportados que comprueben su legalidad, fuera de las Zonas de\nMonumentos Históricos e Inmuebles afectos al patrimonio cultural, en los términos que señale el\nReglamento.\nArtículo 19. La instalación de medios publicitarios con iluminación, específicamente pantallas, está prohibida en fachadas, muros ciegos, túneles y bajo puentes.\nArtículo 20. Los medios publicitarios que anuncien espectáculos tradicionales de manera temporal, quedan exceptuados de la obtención de Licencias, Autorizaciones o Permisos, siempre que se trate de gallardetes y no pongan en riesgo la integridad física de las personas o sus bienes, no se coloquen en árboles y no afecten la infraestructura de seguridad vial.\n\nLa información cultural podrá difundirse en medios publicitarios mediante gallardetes, cuyas dimensiones y términos específicos serán señaladas en los términos del Reglamento.\nArtículo 21. En las Áreas de Conservación Patrimonial y demás elementos del patrimonio cultural urbano en vialidades primarias sólo se podrán instalar medios publicitarios denominativos y de información cultural, tapiales, mallas para el arreglo y mantenimiento de fachadas, vallas y mobiliario urbano con publicidad integrada, de conformidad con lo previsto en esta Ley y su Reglamento.\nEn el Suelo de Conservación, excepto poblados rurales, solo se podrán instalar medios publicitarios denominativos y de información cultural, de conformidad con lo previsto en esta Ley y su Reglamento.\nArtículo 22. Los medios publicitarios de tótem solamente podrán ser instalados sobre propiedad privada de teatros, bancos, auditorios e inmuebles donde se lleven a cabo exposiciones o espectáculos, estaciones de servicio o de carburación, cines y centros comerciales, siempre y cuando cumplan con las medidas y especificaciones que establece el Reglamento y no se trate de Áreas de Conservación Patrimonial. En las estaciones de servicio o de carburación podrá instalarse un solo medio publicitario en tótem de contenido denominativo e información que la normativa federal aplicable, expresamente establezca.\nEl medio publicitario denominativo de un centro comercial y el de los locales comerciales que lo integran deberán contenerse en un mismo tótem. Cuando los locales comerciales tengan acceso directo al exterior, podrán instalar un medio publicitario denominativo en la fachada por cada local.\nArtículo 23. En los teatros, cines y espacios culturales podrá instalarse o adosarse a la fachada, una cartelera con las medidas y especificaciones que señala el Reglamento.\nArtículo 24. La instalación de medios publicitarios en vallas se permitirá en Áreas de Conservación\nPatrimonial, únicamente cuando se trate de estacionamientos y predios baldíos que no se encuentren dentro de Zonas Federales de Monumentos, bajo las especificaciones que establece la presente Ley y su\nReglamento.\nArtículo 25. No podrán instalarse medios publicitarios en presas, canales, muros de contención, taludes, antenas de telecomunicación y sus soportes, postes de señalización vial, incluidos todos los dispositivos de control de tránsito.\n\nArtículo 26. Los medios publicitarios denominativos solo podrán instalarse en donde se desarrolle la actividad de la persona física o moral que corresponda al medio publicitario y deberán ser adosados, integrados o pintados, con o sin iluminación interna o externa.\nArtículo 27. La distribución de espacios para los medios publicitarios se determinará por la autoridad que emita la Licencia o Autorización, según corresponda, considerando las dimensiones y características de estos, en relación con el entorno urbano y la funcionalidad de las vialidades, garantizando el uso adecuado de las áreas de tránsito peatonal y vehicular, así como los criterios que señala la presente Ley, su\nReglamento y demás ordenamientos aplicables.\nUna vez determinada la distribución de espacios para los medios publicitarios solo podrá modificarse para su redistribución, a efecto de reducir las dimensiones de éstos o el número de los ya existentes; para ello la Secretaría expedirá los lineamientos correspondientes.\nLa instalación de los medios publicitarios deberá considerar lo establecido en el Atlas de Riesgos señalado en la Ley de Gestión Integral de Riesgos y Protección Civil de la Ciudad de México.\nTÍTULO TERCERO\nLICENCIAS, PERMISOS Y AUTORIZACIONES\nCAPÍTULO PRIMERO\nDISPOSICIONES COMUNES\nArtículo 28. Para la instalación de los medios publicitarios que se encuentran permitidos por esta Ley, se requerirá de una Licencia, Permiso, Permiso Administrativo Temporal Revocable o Autorización, según corresponda, en los siguientes términos:\nI. Autorización: emitida por las Alcaldías para la instalación de los siguientes medios publicitarios ubicados en vialidades secundarias, siempre que no se encuentren en corredores publicitarios, en Áreas de Conservación Patrimonial, en Áreas de Valor Ambiental, Áreas Naturales Protegidas o en Suelo de Conservación:\na) Anuncios con información de compra, venta, renta, traspaso de inmuebles, oferta de empleo o similares, cuyas dimensiones sean superiores a 2 metros cuadrados;\nb) De tipo denominativo;\n\nc) Tapiales; y d) Carteleras de muro ciegos en planta baja.\nII. Permiso: emitido por la SEMOVI para la instalación de medios publicitarios en vehículos de transporte, de pasajeros y de carga en todas sus modalidades, así como medios publicitarios en equipamiento auxiliar de transporte.\nIII. Licencia: emitida por la Secretaría, tratándose de los demás medios publicitarios permitidos y que no se encuentren en las facultades de las Alcaldías y la SEMOVI.\nLos medios publicitarios denominativos institucionales quedan exentos de la obtención de\nLicencias y Autorizaciones, siempre y cuando cumplan con las dimensiones y características previstas en esta Ley y su Reglamento, y\nIV. Permiso Administrativo Temporal Revocable (PATR): el que es emitido por la SAF y que deberán tramitar las personas que requieran instalar medios publicitarios o anuncios en la vía pública o en bienes inmuebles que integran el patrimonio de la Ciudad. Lo anterior, de conformidad con lo establecido en la Ley del Régimen Patrimonial y del Servicio Público, así como demás normativa aplicable.\nArtículo 29. Será responsabilidad de la persona titular de una Licencia, Autorización, PATR o Permiso, realizar las actividades de mantenimiento de los medios publicitarios respectivos, a fin de evitar condiciones de alto riesgo, así como informar dichas actividades a la Secretaría, la Alcaldía, la SAF o la\nSEMOVI, según sea el caso.\nEl cumplimiento de esta obligación se revisará mediante un procedimiento aleatorio y, en caso de no verificarse el debido cumplimiento, se iniciará el procedimiento administrativo de verificación correspondiente, de conformidad con lo que establece la Ley del Instituto de Verificación Administrativa de la Ciudad de México.\nArtículo 30. Las personas que requieran instalar más de cinco medios publicitarios denominativos con las mismas características, por tratarse de franquicias o similares deberán solicitar una Licencia de medio publicitario denominativo masivo, en los términos que señale el Reglamento.\n\nArtículo 31. Para poder tramitar Licencias, Autorizaciones, PATR y Permisos, los publicistas deberán estar inscritos en el Registro de Publicistas, el cual contendrá el nombre o denominación social del publicista así como su domicilio fiscal.\nPara solicitar su inclusión en el Registro de Publicistas, las personas interesadas deberán presentar ante la\nSecretaría los documentos con los que se acredite su interés y, en su caso, la personalidad de quien promueva, su domicilio legal para oír y recibir notificaciones así como demás requisitos que al efecto establezca la Secretaría.\nEl procedimiento para su inscripción se establecerá en el Reglamento. Asimismo, la Secretaría contará con\n45 días hábiles siguientes a la presentación de la solicitud para emitir la respuesta correspondiente.\nArtículo 32. Las autoridades competentes para la emisión, verificación y, en su caso, sanción de lo relacionado con esta Ley, proporcionarán a la Secretaría la información necesaria para alimentar el Registro de Publicistas; lo anterior, con la finalidad de que exista una coordinación interinstitucional y una administración pública eficaz y eficiente.\nArtículo 33. En el supuesto de que el publicista sea sancionado por infracciones a esta Ley se dará de baja del Registro de Publicistas, hasta en tanto no cumpla con las sanciones que le hayan sido impuestas.\nArtículo 34. Las personas titulares de las Alcaldías, en el ámbito de sus competencias, expedirán las\nAutorizaciones de anuncios previstas en esta Ley.\nArtículo 35. Los permisos que emita la SEMOVI se realizarán de conformidad con lo establecido en la Ley de Movilidad de la Ciudad de México.\nArtículo 36. Además de lo establecido en el artículo 29, las personas titulares de las Licencias están obligadas a:\nI. Cumplir con las obligaciones establecidas en la Licencia respectiva;\nII. Pagar, de manera puntual e íntegra, los derechos que establece la Ley de la materia;\nIII. Sujetarse a las disposiciones en materia urbana, ambiental, gestión integral de riesgos, protección civil, a las Normas Oficiales Mexicanas y demás que resulten aplicables;\n\nIV. Permitir al personal comisionado por la Secretaría y al de la SGIRPC la revisión de los medios publicitarios, así como al Instituto y las Alcaldías la práctica de visitas de verificación administrativas y demás acciones que deriven de las mismas, en el ámbito de sus respectivas competencias, conforme con las disposiciones jurídicas aplicables;\nV. Contratar un seguro de responsabilidad civil;\nVI. Retirar, al vencimiento del plazo de la Licencia, los bienes que se hayan instalado con motivo de éstas, siempre que no se haya solicitado su revalidación. Dicho trámite deberá realizarse con\n10 días hábiles de anticipación al vencimiento del plazo;\nVII. Observar las normas y disposiciones que resulten aplicables para el cumplimiento del objeto y actividades reguladas por la presente Ley;\nVIII. Estar inscritas en el Registro de Publicistas de la Secretaría, y\nIX. Las demás que señale la presente Ley, su Reglamento y demás disposiciones aplicables.\nSe exceptúan de lo previsto en la fracción II de este artículo los medios publicitarios temporales definidos en el Reglamento que coadyuven a financiar el mejoramiento o rehabilitación del espacio público, a través del mantenimiento y conservación de parques, jardines, camellones y áreas verdes.\nEn este supuesto, la Licencia respectiva será vigente únicamente durante el tiempo que duren los trabajos de mantenimiento. En ningún caso el costo del mantenimiento sería inferior al pago de los derechos de la licencia correspondiente.\nTodo medio publicitario sujeto a lo establecido en el presente artículo deberá exhibir de manera visible los datos de la Licencia y la vigencia de ésta, de conformidad con lo que se establezca en el Reglamento.\nArtículo 37. Tratándose de medios publicitarios instalados en el espacio público o en cualquier otro bien visible desde el exterior, siempre que se trate de proyectos de infraestructura para la movilidad en los organismos que forman parte del Sistema Integrado de Transporte Público y sus componentes complementarios, siempre y cuando estén comprendidos y cumplan con lo dispuesto en el artículo 14 de la presente Ley, se regirán de acuerdo con lo requisitos de la Ley de Movilidad de la Ciudad de México, la\nLey de Régimen Patrimonial y del Servicio Público, sus respectivos reglamentos y demás ordenamientos que resulten aplicables.\n\nArtículo 38. Para la instalación de medios publicitarios denominativos de una superficie mayor a los 5 metros cuadrados se deberá obtener Licencia ante la Secretaría, o en su caso, autorización ante la Alcaldía.\nCuando se trate de medios publicitarios denominativos de superficie menor a 5 metros cuadrados no se requerirá ningún tipo de licencia, permiso o autorización, por lo que las personas físicas o morales titulares de establecimientos mercantiles de bajo impacto que los instalen, no serán consideradas como publicistas.\nAsimismo, dichas personas podrán utilizar para fines de información gráfica sobre la oferta de sus establecimientos las vitrinas, aparadores, ventanales, puertas, bardas y vanos del inmueble en el que se encuentren los establecimientos mercantiles; sin que sea necesario acreditar algún pago o contribución, ni mayor trámite que el Aviso de Apertura del Establecimiento mercantil del que se trata. Sin embargo, deberán observarse las medidas de armonía arquitectónica que se establezcan en el Reglamento.\nLo previsto en el párrafo anterior no será aplicable para establecimientos mercantiles de impacto vecinal e impacto zonal; por lo que en este supuesto estarán obligadas a solicitar la Licencia o autorización correspondiente.\nArtículo 39. Las licencias de medios publicitarios deberán solicitarse por escrito ante la Secretaría, en el formato impreso o electrónico que se encuentre disponible en el Portal de Registro de Trámites y Servicios de la Ciudad de México. Dicha solicitud se resolverá en un plazo no mayor de 30 días hábiles.\nA la solicitud de Licencia se deberá adjuntar la siguiente documentación, según corresponda:\na) Responsiva de un Director Responsable de Obra, así como los planos estructurales, memoria de cálculo y de cimentación en su caso, firmados por éste;\nb) Copia certificada del poder del representante legal;\nc) Recibo de pago de los derechos correspondientes previstos en el Código Fiscal de la Ciudad de México;\nd) Planos acotados a escala (plantas y alzados) deberán incluir el diseño, materiales, acabados, colores, texturas, dimensiones, iluminación y detalles estructurales o de fijación y demás especificaciones técnicas, así como incluir la imagen objetivo de la instalación que se pretenda.\nTratándose de medios publicitarios de proyección se deberá presentar la propuesta que incluya el horario y contenido de ésta;\ne) Aprobación de la Comisión Mixta de Mobiliario Urbano en su caso;\n\nf) Opinión Técnica Favorable otorgada por la SGIRPC, respecto del medio publicitario que se pretende instalar, en los términos y para los casos que señale el Reglamento;\ng) Póliza de seguro de responsabilidad civil;\nh) Cronogramas de los trabajos de mantenimiento a realizarse durante la vigencia de la Licencia;\ni) En caso de requerirse, opinión positiva del Instituto Nacional de Antropología e Historia, en el ámbito de su competencia;\nj) En caso de requerirse, opinión positiva del Instituto Nacional de Bellas Artes y Literatura en el ámbito de su competencia;\nk) Fecha, nombre y firma del solicitante, y l) Los demás requisitos que establezca el Reglamento.\nPara la solicitud de prórroga, se deberá cumplir con los requisitos previstos en los incisos a), c), f), y g) de esta fracción.\nNo podrán instalarse medios publicitarios no autorizados o que obtengan previamente la Licencia, Permiso o Autorización correspondiente.\nArtículo 40. Los publicistas, previo a la solicitud de una licencia, deberán obtener su inscripción en el\nRegistro de Publicistas, en los términos que señale el Reglamento.\nArtículo 41. No podrán otorgarse Licencias a aquellas personas físicas o morales que:\nI. Sean sancionados en tres ocasiones por infracciones a esta Ley;\nII. Se les haya sido revocada la Licencia en los nueve meses anteriores a la presentación de la solicitud, y\nIII. No se encuentren inscritas en el Registro de Publicistas o su registro haya sido suspendido, revocado o dado de baja.\n\nArtículo 42. La Licencia de medios publicitarios que expida la Secretaría, permitirá al publicista beneficiado la instalación de los medios publicitarios aprobados por un plazo de tres años prorrogables una vez por el mismo periodo; salvo los siguientes medios publicitarios, que tendrán la siguiente vigencia:\na) La Licencia que permita la instalación de medios publicitarios en tapiales tendrá la misma vigencia que la manifestación de construcción respectiva;\nb) La Licencia que permita la instalación de medios publicitarios en mallas para el arreglo de fachadas, tendrá la misma vigencia que el Aviso de realización de obras que no requieren manifestación de construcción o licencia de construcción especial, de conformidad con el artículo\n62 del Reglamento de Construcciones vigente en la Ciudad de México correspondiente;\nc) Tratándose de las Licencias para medios publicitarios en vallas o carteleras su vigencia será de uno a tres años. El pago de derechos por dicha Licencia se realizará de forma anual y podrá solicitarse su refrendo con 30 días de anticipación a su vencimiento, y d) Tratándose de Licencias para medios publicitarios de información cívica o cultural, éstas se otorgarán con temporalidad acotada variable.\nPor cada medio publicitario, la Secretaría deberá expedir una Licencia.\nArtículo 43. Una vez que se autorice la expedición de la Licencia, la persona titular de la misma tendrá un plazo de cinco días hábiles para entregar a la autoridad competente la póliza de seguro de responsabilidad civil para garantizar la reparación de daños a terceros o a sus bienes, la cual deberá mantenerse vigente durante el plazo de la Licencia. Dicha póliza deberá presentarse anualmente durante la vigencia de la\nLicencia.\nEn caso de no presentar la póliza de seguro de responsabilidad civil en el plazo establecido, la Licencia se revocará de pleno derecho.\nArtículo 44. Las Licencias deberán contener al menos los siguientes elementos:\nI. Nombre y domicilio de la persona titular;\nII. Objeto, fundamento y motivación de su otorgamiento;\n\nIII. Datos de ubicación, diseño, dimensiones, materiales y especificaciones técnicas;\nIV. Descripción general del medio publicitario;\nV. Vigencia de la Licencia;\nVI. La naturaleza y el monto de las garantías que, en su caso, deberá otorgar el licenciatario para el cumplimiento de las obligaciones contenidas en las disposiciones jurídicas aplicables;\nVII. Pago de derechos que se deriven de la Licencia, en términos del Código Fiscal de la Ciudad de México;\nVIII. Causales de revocación de la Licencia;\nIX. Los derechos y obligaciones del licenciatario, en la que se incluirá el cronograma de los trabajos de mantenimiento;\nX. La obligación de remitir informes avalados por un Director Responsable de Obra y un\nCorresponsable en Seguridad Estructural, en los términos que señale el Reglamento;\nXI. Fecha de otorgamiento;\nXII. Las razones que podrán dar lugar a la modificación del contenido de la Licencia, y\nXIII. Las que se señalen en el Reglamento y la Ley de Procedimiento Administrativo de la Ciudad de México.\nArtículo 45. Para la instalación de enseres utilizados para el servicio de acomodadores de vehículos con publicidad integrada se deberá presentar aviso a la Secretaría, y a la Alcaldía cuando los enseres se encuentren en vía secundaria, debiendo anexar al mismo el pago de derechos ante la Tesorería, conforme con lo establecido en el artículo 305 inciso b) del Código Fiscal de la Ciudad de México.\nEn ningún caso la instalación de dichos enseres podrá obstaculizar el libre tránsito de las personas en la vía pública, se deberá garantizar el uso adecuado de las áreas de tránsito peatonal y vehicular.\n\nArtículo 46. Las personas titulares de Licencias deberán ceder gratuitamente el cinco por ciento de sus espacios publicitarios a la Secretaría de manera permanente para difusión de publicidad institucional, salvo el tipo de casos que indique otro porcentaje en la presente Ley.\nArtículo 47. Queda prohibido ceder, gravar o enajenar a terceros la Licencia o alguno de los derechos otorgados a través de esta, por lo que, cualquier acto de cesión diferente al referido en el artículo inmediato anterior no tendrá ningún efecto jurídico.\nArtículo 48. La Licencia se extingue por las siguientes causas:\nI. Vencimiento del plazo por el que se haya otorgado;\nII. Renuncia;\nIII. Revocación o nulidad;\nIV. Quiebra o liquidación del licenciatario, y\nV. Las demás que señale el Reglamento.\nArtículo 49. Son causas de revocación de la Licencia:\nI. Ser sancionado dos veces por la comisión de una infracción prevista en esta Ley;\nII. Difundir mensajes que tengan el carácter de prohibidos por los ordenamientos aplicables;\nIII. Ceder, gravar o enajenar la Licencia o algunos de los derechos en ella establecidos;\nIV. No presentar la póliza de seguro de responsabilidad civil en el plazo establecido para tal efecto;\nV. Derribar o podar árboles en contravención a las disposiciones legales aplicables;\nVI. Instalar el medio publicitario en contravención a los requisitos establecidos en esta Ley;\n\nVII. Incumplir con el cronograma de mantenimiento al medio publicitario, de acuerdo con lo dispuesto en el Reglamento;\nVIII. Incumplir con las obligaciones que establezca la presente Ley, su Reglamento y demás ordenamientos aplicables, y\nIX. Las demás que establezca la presente Ley, su Reglamento y demás ordenamientos aplicables.\nArtículo 50. El titular de la Licencia deberá retirar los medios publicitarios dentro de los cinco días hábiles siguientes a la fecha en que haya concluido su vigencia.\nCAPÍTULO SEGUNDO\nDE LAS AUTORIZACIONES\nArtículo 51. Las Alcaldías podrán otorgar autorizaciones para la instalación de anuncios a través del cual se difunden mensajes de información de compra, venta, renta, traspaso de inmuebles, oferta de empleo o similares, así como los de tipo denominativo, tapiales y carteleras de muro ciegos en planta baja, ubicados en vialidades secundarias, siempre que no se encuentren en corredores publicitarios, en Áreas de\nConservación Patrimonial, en Áreas de Valor Ambiental, Áreas Naturales Protegidas o en Suelo de\nConservación.\nDichas autorizaciones tendrán la siguiente vigencia:\na) Tres meses prorrogables para anuncios de compra, venta, renta, traspaso de inmuebles, oferta de empleo o similares;\nb) Tres años prorrogables para los denominativos;\nc) Tratándose de tapiales, tendrá la misma vigencia que la manifestación de construcción respectiva, y d) En carteleras de muros ciegos en planta baja, su vigencia será de un año.\nLas Autorizaciones se otorgarán en los términos que señale el Reglamento.\n\nArtículo 52. Todo medio publicitario con una superficie inferior a la que se estipule en el Reglamento, no requerirá de Autorización.\nArtículo 53. Las Autorizaciones para la instalación de anuncios, deberán solicitarse por escrito a la persona titular de la Alcaldía respectiva, en el formato impreso o electrónico que a través del sistema de trámites en línea que se encuentre disponible en el Portal de Registro Electrónico de Trámites y Servicios de la Ciudad de México. Dichas autoridades resolverán en un plazo no mayor a 10 días hábiles. En caso de que la persona solicitante no reciba respuesta en el plazo señalado, aplicará la negativa ficta.\nEl formato de la solicitud de Autorización deberá contener los siguientes datos:\nI. Nombre, denominación o razón social del solicitante o, en su caso, de su representante legal;\nII. Tipo de inmueble;\nIII. Domicilio y dirección electrónica para oír y recibir notificaciones;\nIV. Plano en el que se indiquen ubicación, diseño, dimensiones, materiales, colores y demás especificaciones técnicas del anuncio, así como una fotografía del inmueble donde se pretendan instalar, con el montaje de estos;\nV. Fecha y firma del solicitante, y\nVI. Opinión técnica favorable en materia de protección civil emitida por la Unidad de Gestión de\nRiesgos y Protección Civil de la Alcaldía, únicamente cuando se trate de autorizaciones para anuncios, con excepción de los anuncios de compra, venta, renta, traspaso de inmuebles, oferta de empleo o similares.\nA la solicitud deberá agregarse el pago de derechos correspondiente en términos del Código Fiscal de la\nCiudad de México, además de los requisitos señalados en el Reglamento.\nArtículo 54. La Autorización se extingue por cualquiera de las siguientes causas:\nI. Vencimiento del plazo por el que se haya otorgado;\nII. Renuncia;\n\nIII. Expedición de la autorización de uso y ocupación del inmueble construido, en su caso;\nIV. Revocación o nulidad, y\nV. Las demás que señale el Reglamento.\nArtículo 55. El titular de la autorización deberá retirar los anuncios dentro de los 5 días hábiles siguientes a la fecha en que haya concluido la vigencia de la Autorización respectiva.\nCAPÍTULO TERCERO\nDE LOS PERMISOS\nArtículo 56. Para la instalación de medios publicitarios en vehículos de transporte, de pasajeros y de carga en todas sus modalidades se requerirá de Permiso otorgado por la SEMOVI.\nPor lo que hace a medios publicitarios en equipamiento auxiliar de transporte, será necesaria la obtención de la autorización respectiva por parte de la SEMOVI, además de la aprobación de la Comisión Mixta de\nMobiliario Urbano.\nLa instalación de los medios publicitarios referidos en el presente artículo se regirá por lo dispuesto en la\nLey de Movilidad de la Ciudad de México, la Ley del Régimen Patrimonial y del Servicio Público, la presente\nLey, sus respectivos reglamentos y demás ordenamientos que resulten aplicables, así como por lo dispuesto en los Lineamientos que para tal efecto emita la SEMOVI, dentro del ámbito de sus atribuciones.\nLos recursos generados por la contraprestación deberán ser ejercidos por los organismos de transporte correspondientes para garantizar el servicio, mantenimiento y funcionamiento de sus instalaciones y unidades.\nCAPÍTULO CUARTO\nPLATAFORMA DIGITAL DE PUBLICIDAD EXTERIOR\n\nArtículo 57. La Plataforma es la herramienta tecnológica que permitirá contar con una base de datos que proporcione la información relativa a las Licencias, Permisos y Autorizaciones que se emitan en materia de publicidad exterior, en términos de la presente Ley y su Reglamento.\nLa Plataforma contará con características tecnológicas que permitan la consulta de la información que contenga, así como mecanismos confiables de seguridad que garanticen la protección de la información recabada, de conformidad con lo que señale el Reglamento.\nArtículo 58. La Plataforma estará integrada por:\nI. Un catálogo oficial de las Licencias, Permisos y Autorizaciones otorgadas conforme a lo previsto en esta Ley;\nII. Los datos de ubicación de los medios publicitarios que cuenten con las Licencias,\nAutorizaciones o Permisos y, en su caso, de identificación del vehículo o bien en el que se instale;\nIII. Las opiniones técnicas favorables de los estudios de riesgos emitidos por la SGIRPC o por la\nUnidad de Gestión Integral de Riesgos y Protección Civil de la Alcaldía, cuando así proceda, y\nIV. El Registro de Publicistas inscritos ante la Secretaría.\nArtículo 59. La Agencia Digital de Innovación Pública de la Ciudad de México diseñará y dará mantenimiento técnico a la Plataforma., la cual será operada y actualizada por la Secretaría, las Alcaldías y la SEMOVI, respecto de la información correspondiente a las Licencias, Autorizaciones y Permisos que emitan en el ámbito de sus respectivas competencias y en términos de la presente Ley y su Reglamento.\nLa Secretaría será la encargada de administrar la Plataforma y asignará una cuenta de acceso a las autoridades competentes, que les permita utilizar la Plataforma para el ejercicio de sus atribuciones en términos de la presente Ley y demás normativa aplicable.\nArtículo 60. La Plataforma contará con mecanismos que aseguren el cumplimiento a las disposiciones previstas en materia de protección de datos personales, transparencia, acceso a la información pública y en materia de archivos.\nArtículo 61. El Catálogo Oficial contendrá, al menos, los siguientes elementos:\n\nI. Número de la Licencia, Permiso o Autorización, el nombre de su titular, vigencia y, de ser el caso, los datos de la prórroga o de la extinción;\nII. Resoluciones o sentencias firmes emitidas por autoridad judicial o administrativa que afecten las Licencias, Autorizaciones o Permisos;\nIII. Número de registro ante la SGIRPC del estudio de riesgo, así como la respectiva opinión técnica favorable, que en su caso corresponda;\nIV. Número de póliza de seguro de responsabilidad civil y, en su caso, fecha de renovación de la póliza correspondiente, y\nV. Los demás que se señalen en el Reglamento de la presente Ley.\nTÍTULO CUARTO\nÓRGANOS DE PARTICIPACIÓN\nCAPÍTULO ÚNICO\nCONSEJO CONSULTIVO PARA MEDIOS PUBLICITARIOS\nArtículo 62. El Consejo será el órgano de consulta, cuyo objeto es opinar y asesorar a la Secretaría sobre las acciones necesarias para dar cumplimiento a la presente Ley y su Reglamento.\nArtículo 63. El Consejo tendrá las siguientes funciones:\nI. Asesorar a la Secretaría en los asuntos de su competencia en materia de publicidad exterior conforme a la presente Ley;\nII. Recomendar a la Secretaría realizar estudios y, en su caso, proporcionar a la misma estudios con los que se cuente, así como adoptar políticas, acciones y metas tendientes a cumplir con las obligaciones establecidas en la presente Ley;\nIII. Promover la participación de la ciudadanía, de manera informada y responsable en materia de publicidad exterior;\n\nIV. Dar seguimiento a las políticas y acciones en la materia;\nV. Integrar grupos de trabajo especializados y comisiones que coadyuven, de manera honorífica, al cumplimiento de las funciones del Consejo;\nVI. Conocer de los informes de trabajo de la Secretaría y, en su caso, emitir las sugerencias que considere pertinentes para reforzar las políticas y acciones en materia de publicidad exterior;\nVII. Elaborar y aprobar sus lineamientos para su organización y funcionamiento;\nVIII. Celebrar y dar seguimiento a acuerdos interinstitucionales de manera coordinada con las áreas involucradas, según el asunto que, dentro del ámbito de sus atribuciones, cuenten con el objeto de cumplir con los fines de la presente ley, y\nIX. Las demás que se determinen en las disposiciones reglamentarias.\nArtículo 64. El Consejo estará integrado por una persona representante de las siguientes áreas de la\nAdministración Pública y del Congreso de la Ciudad de México, quienes contarán con derecho a voz:\nI. Persona titular de la Secretaría, quien lo presidirá;\nII. Secretarías de Gobierno;\nIII. Secretaría del Medio Ambiente;\nIV. Secretaría de Gestión Integral de Riesgos y Protección Civil;\nV. Secretaría de Administración y Finanzas;\nVI. Secretaría de Movilidad;\nVII. Instituto de Planeación Democrática y Prospectiva;\nVIII. Procuraduría Ambiental y del Ordenamiento Territorial, y\n\nIX. Las personas titulares de las Alcaldías, cuando se traten asuntos relacionados con su demarcación territorial.\nX. Tres Diputadas o Diputados de la Comisión de Desarrollo e Infraestructura Urbana del\nCongreso de la Ciudad de México, por acuerdo de la misma y ratificadas por el pleno.\nArtículo 65. A las sesiones del Consejo asistirán las siguientes personas, quienes contarán con derecho a voz:\nI. Cinco personas representantes de las asociaciones, cámaras, personas físicas o morales cuyas actividades tengan como fin u objeto la publicidad exterior, y\nII. Dos personas representantes de instituciones académicas.\nLa participación de las personas contempladas en el presente artículo, será honorífica; asimismo, la asesoría, recomendaciones, opiniones o sugerencias que emitan, tendrán el carácter consultivo, coincidente con la naturaleza del Consejo; por lo que no serán vinculantes.\nArtículo 66. El Consejo contará con una Secretaría Técnica designada por la Presidencia, quien elaborará los lineamientos de operación y funcionamiento del Consejo.\nLa Presidencia designará a las personas representantes de la industria de la publicidad exterior y de las instituciones académicas. Previo a la instalación de la primera sesión del Consejo, realizará las gestiones pertinentes para la designación de los referidos integrantes, posiciones que serán rotativas por periodos de 1 año, con posibilidad de ratificarse por un periodo igual.\nArtículo 67. Las personas representantes de las dependencias y entidades de la Administración Pública de la Ciudad de México, deberán tener, al menos el nivel de dirección general y podrán designar a un suplente con nivel mínimo de dirección de área o equivalente con atribuciones coincidentes en materia de la presente Ley.\nArtículo 68. Por la naturaleza de los temas a tratar en las sesiones de la Comisión, la Presidencia del Consejo podrá invitar a otras autoridades, así como a personas físicas y organizaciones relacionadas, con los temas relacionados de la presente Ley; y cuya participación será de carácter honorífico.\n\nArtículo 69. El Consejo aprobará, a propuesta de la Presida, los lineamientos de operación y funcionamiento de dicho órgano colegiado, los cuales deberán ser presentados en la sesión de instalación del Consejo establecer, cuando menos, los aspectos siguientes:\nI. Procedimiento para convocar a las sesiones, tanto ordinarias como extraordinarias y dejar constancia de los acuerdos tomados;\nII. Procedimiento para asegurar la participación de personas físicas o morales de los sectores vinculados a las materias objeto de la Ley, y\nIII. Mecanismos para la conformación de comisiones y grupos de trabajo sobre temas específicos, cuando así se considere necesario.\nArtículo 70. El Consejo sesionará en forma ordinaria cuatro veces al año y extraordinaria cuando la urgencia de los asuntos a tratar así lo amerite, previa convocatoria que realice la Secretaría Técnica por instrucciones de la Presidencia del Consejo. Las sesiones podrán ser presenciales, virtuales o mixtas; lo que se detallará en los lineamientos respectivos.\nEl Consejo sesionará válidamente con la asistencia de la mitad más uno de sus integrantes.\nTÍTULO QUINTO\nPROCEDIMIENTO DE VERIFICACIÓN ADMINISTRATIVA\nCAPÍTULO PRIMERO\nDISPOSICIONES GENERALES\nArtículo 71. La determinación y ejecución de visitas de verificación administrativa, de medidas cautelares y de seguridad, así como de las sanciones que correspondan, se sujetarán a las formalidades y al procedimiento que se prevé para tal efecto en la Ley de Procedimiento Administrativo de la Ciudad de\nMéxico, así como las demás disposiciones jurídicas y administrativas aplicables.\nArtículo 72. Las personas que se determinen como responsables solidarias de la instalación de un medio publicitario estarán obligadas a pagar los gastos que se generen a la Administración Pública de la Ciudad por el retiro de medios publicitarios que realicen las autoridades competentes.\n\nArtículo 73. Toda persona que advierta la instalación flagrante de un medio publicitario en contravención de lo dispuesto en esta Ley podrá solicitar a los elementos de la Secretaría de Seguridad Ciudadana de la\nCiudad de México que intervengan para su remisión correspondiente ante la autoridad competente, cuando no se acredite en forma suficiente la existencia de una Licencia, Autorización o Permiso de dicho medio publicitario.\nCualquier persona podrá presentar denuncia ciudadana por presuntos actos, hechos u omisiones que pudieran constituir incumplimiento a las disposiciones de esta Ley, su Reglamento y demás normativa aplicable en la materia, ante la Secretaría, la Procuraduría Ambiental y de Ordenamiento Territorial, el\nInstituto o la Alcaldía respectiva, en el ámbito de sus respectivas competencias, así como solicitar a estos dos últimos entes la práctica de las visitas de verificación administrativa.\nCAPÍTULO SEGUNDO\nMEDIDAS CAUTELARES Y DE SEGURIDAD\nArtículo 74. La autoridad competente podrá determinar una o más de las siguientes medidas cautelares y de seguridad:\nI. Aseguramiento de materiales, vehículos, utensilios, instrumentos, equipos, herramientas y cualquier bien directamente relacionado con el hecho que motiva la medida;\nII. Suspensión temporal total o parcial de los medios publicitarios;\nIII. Retiro total o parcial de medios publicitarios, estructuras e instalaciones;\nIV. Inhabilitación de medios publicitarios;\nV. Corte, pintado o cubrimiento de los medios publicitarios, así como cualquier otra acción que impida la visibilidad de las marcas, productos y servicios que se promocionen o de información que estos contengan, y\nVI. Las demás que establezcan los ordenamientos legales en la materia.\nLas autoridades competentes podrán solicitar el auxilio de la fuerza pública para ejecutar cualquiera de las medidas previstas en el presente artículo.\n\nLa Secretaría, la SEMOVI, la SGIRPC, las Alcaldías y el Instituto, ejecutarán, en el ámbito de sus respectivas competencias, las medidas y determinaciones que en materia de publicidad exterior dicten las autoridades jurisdiccionales.\nCAPÍTULO TERCERO\nINFRACCIONES Y SANCIONES\nArtículo 75. Las verificaciones e imposición de medidas cautelares y de seguridad, así como las sanciones por la comisión de infracciones a la presente Ley corresponderán al Instituto y a las Alcaldías en los términos siguientes:\nI. A las Alcaldías corresponderá, en el ámbito de su respectiva competencia, lo referente a los medios publicitarios considerados como anuncios conforme a lo definido en la presente Ley;\nII. Al Instituto, lo referente a todos los medios publicitarios, con excepción de los considerados anuncios conforme a lo definido en la presente Ley;\nIII. A los Juzgados Cívicos corresponde la imposición de arrestos administrativos, de conformidad con la Ley de Cultura Cívica de la Ciudad de México y demás ordenamientos que resulten aplicables, y\nIV. A la Secretaría de Seguridad Ciudadana de la Ciudad de México la remisión de los presuntos infractores y de vehículos al depósito, en los casos a los que se refiere esta Ley.\nArtículo 76. Las sanciones previstas en esta Ley se aplicarán sin perjuicio de las previstas en la legislación de desarrollo urbano y ordenamiento territorial, así como demás ordenamientos aplicables.\nArtículo 77. Independientemente de las sanciones de carácter civil, serán solidariamente responsables del pago de las multas y de los gastos causados por el retiro de medios publicitarios que ordene la autoridad, quienes hayan intervenido en la instalación de estos. Se presume, salvo prueba en contrario, que han intervenido en la instalación de los medios publicitarios:\nI. El publicista;\n\nII. El responsable del inmueble o mueble en el que se instaló, y\nIII. El anunciante, titular de la marca o producto o cualquier persona física o moral que intervenga en la comercialización de los espacios publicitarios, en los términos establecidos en esta Ley.\nLas lonas, mantas y materiales similares adosados a los inmuebles, así como los objetos publicitarios colocados provisionalmente sobre las banquetas o el arroyo vehicular, serán considerados bienes abandonados y la autoridad administrativa podrá retirarlos directamente.\nArtículo 78. En los procedimientos administrativos que se instruyan para la imposición de sanciones, harán prueba plena las fotografías y videograbaciones de los medios publicitarios instalados en contravención a la presente Ley, así como los pendones, gallardetes, carteles y, en general, los medios publicitarios o partes de ellos que logre asegurar o detectar el personal de verificación.\nArtículos 79. Los elementos de policía de la Secretaría de Seguridad Ciudadana de la Ciudad de México que adviertan la instalación ilegal flagrante de un elemento publicitario, deberán presentar a las personas responsables ante el Ministerio Público o el Juzgado Cívico, conforme al ámbito de su competencia.\nToda persona podrá presentar ante la Procuraduría Ambiental y del Ordenamiento Territorial de la Ciudad de México, denuncia ciudadana por presuntos actos, hechos u omisiones que constituyan o puedan constituir incumplimiento o falta de la aplicación de las disposiciones de esta Ley y las disposiciones que de ella deriven en los términos dispuestos en la Ley de dicha Entidad.\nArtículo 80. La Procuraduría Ambiental y del Ordenamiento Territorial de la Ciudad de México presentará a la autoridad administrativa competente o ante el Tribunal de Justicia Administrativa de la Ciudad de\nMéxico, la acción procedente para demandar la nulidad o revocación de actos administrativos dictados en contra de las disposiciones contenidas en esta Ley y demás disposiciones jurídicas de que ella emanen.\nArtículo 81. En los supuestos en que se determine el retiro de medios publicitarios como medida cautelar y de seguridad o en su caso como sanción, las personas responsables estarán obligadas a llevar a cabo dicho retiro total o parcial, en caso de no realizarlo, la autoridad competente lo podrá ejecutar a costa del responsable.\nEn caso de que la autoridad de la Administración Pública de la Ciudad de México lleve a cabo el retiro parcial o total de los medios publicitarios, por haber sido imposición como medida cautelar y de seguridad o sanción, los gastos que se generen serán determinados como créditos fiscales a cargo de las personas\n\ninfractoras y su cobro se realizará a través del procedimiento administrativo de ejecución, en términos del\nCódigo Fiscal de la Ciudad de México.\nLos restos del medio publicitario deberán ser reclamados por las personas interesadas dentro de los 30 días hábiles siguientes al retiro, los cuales serán entregados por la autoridad, previo pago del costo del retiro y del almacenaje, de conformidad con el Código Fiscal de la Ciudad de México. De no ser así, la autoridad ejecutora determinará su destino final, el cual podrá consistir en:\nI. Destrucción;\nII. Venta o remate;\nIII. Donación a instituciones públicas con fines de interés social, y\nIV. Cualquier otro que sea en beneficio del interés social.\nLo anterior, sin perjuicio de las determinaciones que se dicten con motivo de la calificación de las actas de visita de verificación administrativa o en las resoluciones administrativas correspondientes.\nLas especificaciones relacionadas con la determinación del destino final, se detallarán en el Reglamento.\nArtículo 82. La persona servidora pública que expida una Licencia, Permiso o Autorización en contravención de lo establecido en la presente Ley y demás disposiciones aplicables, será sancionada en términos de las disposiciones en materia de responsabilidades administrativas, civiles o penales aplicables.\nArtículo 83. Se sancionará con multa de 12,000 a 15,000 veces la Unidad de Medida y Actualización vigente, al titular de un Permiso Administrativo Temporal Revocable, Licencia o Autorización temporal cuando las características del medio publicitario instalado no correspondan a las previstas en los mismos.\nCuando el infractor cometa por segunda ocasión la misma infracción prevista en este artículo, será sancionado con el doble de la multa impuesta en la primera ocasión y el retiro del medio publicitario a su costa.\nEn caso de que el infractor cometa por tercera ocasión la misma infracción prevista en este artículo, será sancionado con el doble de la multa impuesta en la segunda ocasión y el retiro del medio publicitario a su costa.\n\nQuienes resulten afectados en su interés jurídico, en los términos de la Ley de Procedimiento\nAdministrativo de la Ciudad de México, pueden ejercer las acciones correspondientes ante las autoridades competentes, cuando se hayan otorgado Permisos, Licencias y Autorizaciones temporales en contravención a las disposiciones contenidas en la presente Ley.\nArtículo 84. Se sancionará con multa de 12,000 a 15,000 veces la Unidad de Medida y Actualización vigente y arresto administrativo inconmutable de 24 a 36 horas al publicista, anunciante, y cualquier persona física o moral que intervenga en la comercialización de los espacios publicitarios, así como el retiro del medio publicitario a costa del primero, que sin contar con el permiso administrativo temporal revocable, licencia o autorización temporal respectivo, ejecute o coadyuve en la instalación de un medio publicitario.\nArtículo 85. Se sancionará con multa de 12,000 a 15,000 veces la Unidad de Medida y Actualización vigente, arresto administrativo inconmutable de 24 a 36 horas y el retiro del medio publicitario a su costa, a la persona física o moral que sin contar con la Autorización o Licencia correspondiente, ejecute o coadyuve en la instalación de pendones o gallardetes en un inmueble público o privado, puente vehicular o peatonal, paso a desnivel, bajo-puente, muro de contención, talud, poste, semáforo, o en cualquier otro elemento de la infraestructura urbana.\nCuando el infractor cometa por segunda ocasión la misma infracción prevista en este artículo, será sancionado con el doble de la multa impuesta en la primera ocasión, arresto administrativo inconmutable de 24 a 36 horas y el retiro de los medios publicitarios a su costa.\nEn caso de que el infractor cometa por tercera ocasión la misma infracción prevista en este artículo, será sancionado con el doble de la multa impuesta en la segunda ocasión y el retiro a su costa del medio publicitario. El Instituto o en su caso la Alcaldía correspondiente, presentará, además, ante el Ministerio\nPúblico, la denuncia o querella por la comisión del delito que corresponda.\nCuando los pendones o gallardetes contengan publicidad relativa a la venta de inmuebles y no se haya expedido la autorización de uso y ocupación respectiva, la Alcaldía condicionará la expedición de dicha autorización al pago de la multa y al retiro de los pendones o gallardetes respectivos.\nArtículo 86. Se sancionará con multa de 12,000 a 15,000 veces la Unidad de Medida y Actualización vigente y arresto administrativo inconmutable de 24 a 36 horas y el retiro del medio publicitarios a su costa, a la persona física o moral que ejecute o coadyuve en la instalación de uno o más medios publicitarios\n\nadheridos a un inmueble público o privado, puente vehicular o peatonal, paso a desnivel, bajo-puente, muro de contención, talud, poste, semáforo, o a cualquier otro elemento de la infraestructura urbana.\nCuando el infractor cometa por segunda ocasión la misma infracción prevista en este artículo, será sancionado con el doble de la multa impuesta en la primera ocasión, arresto administrativo inconmutable de 24 a 36 horas y el retiro a su costa de los medios publicitarios.\nEn caso de que el infractor cometa por tercera ocasión la misma infracción prevista en este artículo, será sancionado con el doble de la multa impuesta en la segunda ocasión y el retiro a su costa de los medios publicitarios. El Instituto o en su caso la Alcaldía correspondiente presentarán, además, ante el Ministerio\nPúblico, la denuncia o querella por la comisión del delito que corresponda.\nEn cualquier caso, cuando el medio publicitario no autorizado contenga publicidad relativa a la celebración de un espectáculo público, las Alcaldías negarán el permiso para la celebración, o lo revocarán de oficio si ya lo hubieren expedido.\nArtículo 87. Se sancionará con multa de 6,000 a 12,000 veces la Unidad de Medida y Actualización vigente y retiro del medio publicitario a su costa, al titular de la Licencia o Autorización que incurra en cualquiera de las siguientes infracciones:\nI. Agregue elementos de propaganda al contenido de un medio publicitario denominativo;\nII. Adhiera medios publicitarios al vidrio de un ventanal o escaparate, y\nIII. Instale medios publicitarios no permitidos en el interior de un escaparate.\nCuando el infractor cometa por segunda ocasión la misma infracción prevista en este artículo, será sancionado con el doble de la multa impuesta en la primera ocasión y el retiro a su costa del medio publicitario.\nEn caso de que el infractor cometa por tercera ocasión la misma infracción prevista en este artículo, será sancionado con el doble de la multa impuesta en la segunda ocasión, el retiro a su costa del medio publicitario y arresto administrativo inconmutable de 24 a 36 horas. El Instituto o en su caso la Alcaldía correspondiente presentarán, además, ante el Ministerio Público, la denuncia o querella por la comisión del delito que corresponda.\n\nArtículo 88. Se sancionará con multa de 6,000 a 12,000 veces la Unidad de Medida y Actualización vigente y retiro a su costa del medio publicitario, al titular de la licencia o autorización que instale un medio publicitario denominativo en un inmueble distinto de aquel en donde se desarrolle la actividad de la denominación o razón social respectiva.\nCuando el infractor cometa por segunda ocasión la misma infracción prevista en este artículo, será sancionado con el doble de la multa impuesta en la primera ocasión y el retiro a su costa del medio publicitario.\nEn caso de que el infractor cometa por tercera ocasión la misma infracción prevista en este artículo, será sancionado con el doble de la multa impuesta en la segunda ocasión, el retiro a su costa del medio publicitario y arresto administrativo inconmutable de 24 a 36 horas. El Instituto o en su caso la Alcaldía correspondiente presentarán, además, ante el Ministerio Público, la denuncia o querella por la comisión del delito que corresponda.\nArtículo 89. Se sancionará con multa de 6,000 a 12,000 veces la Unidad de Medida y Actualización vigente y retiro a su costa del medio publicitario, al titular de la licencia o autorización que instale un medio publicitario denominativo de tal forma que sobresalga total o parcialmente del contorno de la fachada.\nCuando el infractor cometa por segunda ocasión la misma infracción prevista en este artículo, será sancionado con el doble de la multa impuesta en la primera ocasión y el retiro a su costa del medio publicitario.\nEn caso de que el infractor cometa por tercera ocasión la misma infracción prevista en este artículo, será sancionado con el doble de la multa impuesta en la segunda ocasión, el retiro a su costa del medio publicitario y arresto administrativo inconmutable de 24 a 36 horas. El Instituto o en su caso la Alcaldía correspondiente presentarán, además, ante el Ministerio Público, la denuncia o querella por la comisión del delito que corresponda.\nArtículo 90. Se sancionará con multa de 12,000 a 15,000 veces la Unidad de Medida y Actualización vigente, arresto administrativo inconmutable de 24 a 36 horas y el retiro del medio publicitario, a la persona física que ejecute o coadyuve en la instalación de un medio publicitario en un mueble urbano sin contar con la licencia de la Secretaría.\n\nSe entiende que coadyuva en la instalación quien coloque o introduzca el medio publicitario, equipo o materiales necesarios para su instalación en el mueble urbano donde vaya a ser o haya sido instalado el medio publicitario.\nCuando el infractor cometa por segunda ocasión la misma infracción prevista en este artículo, será sancionado con el doble de la multa impuesta en la primera ocasión, arresto administrativo inconmutable de 24 a 36 horas y el retiro a su costa del medio publicitario.\nEn caso de que el infractor cometa por tercera ocasión la misma infracción prevista en este artículo, será sancionado con el doble de la multa impuesta en la segunda ocasión y el retiro a su costa del medio publicitario. El Instituto o en su caso la Alcaldía correspondiente presentarán, además, ante el Ministerio\nPúblico, la denuncia o querella por la comisión del delito que corresponda.\nSi el mueble urbano consiste en una caseta telefónica o caja de registro de líneas telefónicas, el retiro del medio publicitario podrá consistir en la aplicación de pintura al mueble urbano.\nArtículo 91. Se sancionará con multa de 12,000 a 15,000 veces la Unidad de Medida y Actualización vigente y el retiro del medio publicitario a su costa, al titular de una licencia o autorización que no retire los gallardetes y demás medios publicitarios en el plazo de cinco días hábiles previstos en esta Ley.\nCuando el infractor cometa por segunda ocasión la misma infracción prevista en este artículo, será sancionado con el doble de la multa impuesta en la primera ocasión y el retiro de los medios publicitarios a su costa.\nEn caso de que el infractor cometa por tercera ocasión la misma infracción prevista en este artículo, será sancionado con el doble de la multa impuesta en la segunda ocasión y el retiro a su costa del medio publicitario.\nArtículo 92. Se sancionará con multa de 12,000 a 15,000 veces la Unidad de Medida y Actualización vigente al responsable del medio publicitario, así como la remisión del vehículo al depósito de la Secretaría de\nSeguridad Ciudadana de la Ciudad de México, y al conductor de un vehículo desde el cual se proyecten medios publicitarios sobre las edificaciones públicas o privadas, sea que el vehículo se encuentre en movimiento o estacionado.\nLa misma sanción se aplicará a las personas infractoras relacionadas y al conductor de un vehículo de propiedad pública o privada que se encuentre en movimiento o estacionado con cualquier tipo de estructura instalada, la cual difunda medios publicitarios de propaganda.\n\nEn todo caso, el propietario del vehículo será responsable solidario por las sanciones que se apliquen al conductor.\nCuando el infractor cometa por segunda ocasión la misma infracción prevista en este artículo, será sancionado con el doble de la multa impuesta en la primera ocasión y la remisión del vehículo al depósito.\nEn caso de que el infractor cometa por tercera ocasión la misma infracción prevista en este artículo, será sancionado con el doble de la multa impuesta en la segunda ocasión, arresto administrativo inconmutable de 24 a 36 horas y la remisión del vehículo al depósito.\nLos particulares o anunciantes que incumplan con las reglas de propaganda electoral que establezca la legislación electoral, estarán sujetos al régimen de sanciones que dispone este capítulo.\nArtículo 93. Se sancionará con multa de 12,000 a 15,000 veces la Unidad de Medida y Actualización vigente, y el retiro del medio publicitario a su costa, al titular de un Permiso Administrativo Temporal\nRevocable, Licencia o Autorización que incumpla con lo establecido en el artículo 17 de esta Ley.\nCuando el infractor cometa por segunda ocasión la misma infracción prevista en este artículo, será sancionado con el doble de la multa impuesta en la primera ocasión y el retiro de los medios publicitarios a su costa, si volviera a colocarlos.\nEn caso de que el infractor cometa por tercera ocasión la misma infracción prevista en este artículo, será sancionado con el doble de la multa impuesta en la segunda ocasión y el retiro a su costa del medio publicitario si lo coloca por tercera vez.\nEl Instituto deberá presentar, además, ante el ministerio público, la denuncia por la comisión del delito que corresponda.\nArtículo 94. Sin perjuicio de las sanciones referidas expresamente en los artículos anteriores de este capítulo, la autoridad competente podrá determinar cómo sanción el retiro parcial de medios publicitarios;\nla Revocación de Permisos, Licencias o Autorizaciones; la Exclusión temporal o permanente del Registro de publicistas, y las demás que señalen el reglamento y las disposiciones jurídicas aplicables.\nArtículo 95. Las multas impuestas en términos de las disposiciones anteriores, así como los gastos que se generen por el retiro parcial o total de los medios publicitarios por parte del Gobierno de la Ciudad de\n\nMéxico, cuando éste haya sido impuesto como medida cautelar y de seguridad, o sanción, serán considerados créditos fiscales a cargo de las personas infractoras y su cobro se realizará a través del procedimiento administrativo de ejecución, en términos del Código Fiscal de la Ciudad de México.\nSin perjuicio de las sanciones referidas expresamente en los artículos anteriores de este capítulo, la autoridad competente podrá determinar cómo sanción el retiro parcial de medios publicitarios; la\nRevocación de Permisos, Licencias o Autorizaciones; la Inhabilitación del medio publicitario; la exclusión temporal o permanente del Registro de publicistas, y las demás que señalen el Reglamento y las disposiciones jurídicas aplicables.\nCAPÍTULO CUARTO\nDE LOS DELITOS\nArtículo 96. Se le impondrá de tres a seis años de prisión, así como multa de 500 a 15,000 veces la Unidad de Medida y Actualización vigente, a quien atente contra la protección, conservación y regulación del paisaje urbano de la Ciudad de México al realizar o participar en la instalación de un medio publicitario:\na) En azoteas, instalados o pintados en cerros, rocas, árboles, bordes de ríos, lomas, laderas, bosques, lagos o en cualquier otra formación natural;\nb) Autosoportados prohibidos en los términos de esta Ley;\nc) Pintado o adherido en fachadas que no sean denominativos;\nd) Envolventes;\ne) Proyecciones sobre materiales plásticos, lonas, o elementos colocados o adheridos en fachadas;\nf) Que atenten contra la dignidad de las personas o vulneren los valores o derechos humanos, y g) En zonas de conservación ecológica, áreas de valor ambiental o áreas naturales protegidas;\n\nLas penas previstas en este artículo se duplicarán cuando una o más de las conductas descritas en el párrafo anterior se desarrollen en suelo de conservación ecológica, área natural protegida, área de valor ambiental, barrancas o áreas verdes en suelo urbano, de conformidad con las disposiciones jurídicas aplicables.\nEste delito se perseguirá de oficio, asimismo, la reparación del daño será a favor del Gobierno de la Ciudad de México, y consistirá en el retiro del medio publicitario instalado ilegalmente, o en el pago del costo del retiro del medio publicitario, cuando se haya llevado a cabo como medida precautoria, o sanción administrativa o penal, según lo resuelva el Juez competente.\nArtículo 97. Comete el delito en contra de la protección, conservación y regulación del paisaje urbano de la\nCiudad de México, quien permita la instalación de un medio publicitario en azoteas, así como de un medio publicitario adosado, tapial, valla o muro ciego sin contar con la licencia o autorización que exija esta ley, y se le impondrá de tres a seis años de prisión, así como de 6,000 a 15,000 veces la Unidad de Medida y\nActualización vigente.\nSe entiende que permite la instalación, el propietario, poseedor, responsable o administrador del inmueble, o quien celebre convenio con persona cuyo objeto consista en la colocación y venta de espacios publicitarios.\nArtículo 98. A quien tenga la propiedad, posesión, administración, disposición, uso o disfrute de una grúa o vehículo que se utilice, por sí o por interpósita persona, para la instalación de un medio publicitario en azotea, así como un medio publicitario autosoportado, adosado, tapial, valla, o en muro ciego sin contar con licencia o autorización que exija esta ley, se le impondrán las mismas penas establecidas en el artículo anterior, además de las multas administrativas de tránsito respectivas, al vehículo, si fuere el caso.\nArtículo 99. Comete delito contra el ambiente quien, para ejecutar, preparar, instalar o modificar un medio publicitario autosoportado, en azotea, adosado, tapial, valla muro ciego, pode, desmoche o tale uno o más árboles sin autorización o licencia que exija la legislación aplicable, y se le impondrá de un año a cuatro años de prisión, así como de 6,000 a 15,000 veces la Unidad de Medida y Actualización vigente.\nLas penas previstas en este artículo se duplicarán cuando una o más de las conductas descritas en el párrafo anterior se desarrolle en suelo de conservación ecológica, área natural protegida, área de valor ambiental, barrancas o áreas verdes en suelo urbano, de conformidad con las disposiciones jurídicas aplicables.\nArtículo 100. Los delitos de este Capítulo se perseguirán por denuncia, con excepción de los previstos en los dos primeros artículos de este, en los cuales se refiere que son de oficio, asimismo, la reparación del\n\ndaño será a favor del Gobierno de la Ciudad de México, y consistirá en el retiro del medio publicitario instalado ilegalmente, o en el pago del costo del retiro del medio publicitario, cuando se haya llevado a cabo como medida precautoria según lo resuelva el Juez competente.\nLas multas impuestas en términos de las disposiciones anteriores serán determinadas como créditos fiscales, a cargo de las personas infractoras y su cobro se realizará a través del procedimiento administrativo de ejecución, en términos del Código Fiscal de la Ciudad de México.\nCAPÍTULO QUINTO\nDE LOS MEDIOS DE IMPUGNACIÓN\nArtículo 101. Las personas que se consideren afectadas por los actos y resoluciones emitidas por las autoridades competentes conforme a lo dispuesto en esta Ley y su Reglamento, podrán interponer el recurso de inconformidad previsto en la Ley de Procedimiento Administrativo de la Ciudad de México, ajustándose a lo previsto por la misma o juicio de nulidad ante el Tribunal de Justicia Administrativa de la\nCiudad de México de conformidad con lo dispuesto por la Ley respectiva.\nTRANSITORIOS\nPRIMERO. Remítase a la persona titular de la Jefatura de Gobierno de la Ciudad de México para su promulgación y publicación en la Gaceta Oficial de la Ciudad de México.\nSEGUNDO. El presente Decreto entrará en vigor al día siguiente de su publicación en la Gaceta Oficial de la\nCiudad de México.\nTERCERO. Se abroga la Ley de Publicidad Exterior del Distrito Federal publicada el 20 de agosto de 2010 en la Gaceta Oficial del -entonces- Distrito Federal, no. 909, así como sus reformas y todos los ordenamientos que se opongan al presente Decreto.\nCUARTO. De conformidad con el principio de uniformidad, el “padrón de empresas comercializadoras de publicidad” contemplado en el artículo 159 de la Ley de Movilidad de la Ciudad de México, deberá migrar la información con la que cuenta, desde su creación hasta la entrada en vigor del presente Decreto, a la\nPlataforma Digital de Publicidad Exterior y al Registro de Publicistas, según corresponda. La Agencia Digital de Innovación Pública deberá diseñar, en coordinación con la Secretaría de Movilidad, las soluciones\n\ntecnológicas que permitan la migración de dicha información, en un término de 120 días naturales a partir de la entrada en vigor del presente Decreto.\nQUINTO. Los trámites y procedimientos iniciados con anterioridad a la entrada en vigor del presente\nDecreto se sustanciarán y concluirán de conformidad con las disposiciones jurídicas vigentes a la fecha en que se iniciaron.\nSEXTO. Todo medio publicitario prohibido deberá ser retirado por las personas que intervinieron en la instalación del mismo, la comercialización de los espacios publicitarios, así como la difusión del contenido publicitario en un periodo que no exceda de veinte días naturales contados a partir de la entrada en vigor del presente Decreto.\nEn el caso de los medios publicitarios prohibidos por la entrada en vigor del presente Decreto y que estén incluidos en el Padrón Oficial de Anuncios Sujetos al Reordenamiento de la Publicidad Exterior del Distrito\nFederal, publicado en la Gaceta Oficial del –entonces- Distrito Federal no. 242 tomo I, del 18 de diciembre de 2015, le será aplicable los dispuesto en el apartado 3 del siguiente artículo transitorio.\nSÉPTIMO:\n1. Las personas físicas y morales responsables de los medios publicitarios que se encuentren en cualquiera de las hipótesis previstas en el artículo 15 de la presente Ley y que corresponden a modalidades incluidas en el Padrón Oficial de Anuncios Sujetos al Reordenamiento de la\nPublicidad Exterior del Distrito Federal publicado en la Gaceta Oficial del Distrito Federal del 18 de diciembre de 2015, cuyo status se encuentre dentro de los “INSTALADOS”, y que acrediten tener un derecho adquirido podrán realizar las gestiones para obtener la Licencia, que permita la permanencia, cambio de modalidad y/o reubicación de dichos medios publicitarios, según proceda. El procedimiento a seguir será el establecido en el numeral 2 del presente Transitorio.\nLas personas físicas o morales que posean medios publicitarios autosoportados que hayan sido instalados conforme a la normatividad aplicable antes de la entrada en vigor de la presente Ley y cuyo status sea el de “INSTALADOS” deberán seguir los procedimientos descritos en los incisos a) y b) del numeral 2 de este Transitorio para obtener, en su caso, la Licencia de los mismos.\nAsimismo, las personas que posean medios publicitarios instalados conforme a la normativa aplicable en muros ciegos de colindancia en corredores publicitarios antes de la entrada en vigor de la presente Ley, y que se adapten al uso de un 40% del espacio factible de exhibición del muro\n\nsobre el que se colocan, podrán seguir los procedimientos aquí descritos para solicitar, en su caso, la obtención de Licencia de los mismos.\nDentro del análisis que al efecto realice la Secretaría de las solicitudes señaladas en los párrafos anteriores se considerará el cumplimiento de los solicitantes del retiro voluntario de medios publicitarios que no cumplan con lo establecido en la presente Ley.\n2. Las personas físicas o morales responsables de los medios publicitarios definidos en el anterior numeral de este transitorio, deberán, dentro de un plazo máximo de 70 días naturales contados a partir de la entrada en vigor de este Decreto:\na) Manifestar lo que a su derecho convenga y presentar ante la Secretaría de Desarrollo\nUrbano y Vivienda de la Ciudad de México o de la autoridad competente pruebas pertinentes, idóneas y suficientes para acreditar su legal y previa instalación y permanencia, como son: las licencias, permisos o autorizaciones respectivas, sentencias jurisdiccionales firmes, pago de derechos, entre otros.\nb) Acreditar que se encuentran enlistados con el status de “INSTALADOS” en el Padrón\nOficial de Anuncios Sujetos al Reordenamiento de la Publicidad Exterior del Distrito\nFederal publicado en la Gaceta Oficial del Distrito Federal del 18 de diciembre de 2015.\nc) Presentar a la Secretaría o autoridad competente la solicitud que incluya la propuesta de permanencia, cambio de modalidad y/o reubicación, según se trate, conforme a las disposiciones previstas en esta Ley en los supuestos procedentes, a efecto de analizar la viabilidad de ello y se determine lo procedente.\nd) En la propuesta se deberán además señalar las dimensiones y características de los medios publicitarios, considerando que los mismos deberán cumplir con una distancia mínima de doscientos cincuenta metros respecto a cualquier otro medio publicitario.\n3. En todos los casos de los medios publicitarios instalados en azoteas que estén incluidos en el\nPadrón Oficial de Anuncios Sujetos al Reordenamiento de la Publicidad Exterior del Distrito\nFederal publicado en la Gaceta Oficial del Distrito Federal del 18 de diciembre de 2015, independientemente del status, deberán ser retirados. Para ello las personas físicas o morales responsables deberán:\n\na) Anexar a la solicitud el cronograma del periodo en el que se realizará el retiro de los medios publicitarios prohibidos, el cual no deberá exceder de un año a partir de la entrada en vigor del presente ordenamiento. Dicho retiro deberá realizarse conforme a lo siguiente:\nb) Durante el primer semestre se deberán retirar por lo menos el 40 por ciento de la totalidad de los medios publicitarios que correspondan a las personas responsables de los mismos;\nc) Durante el tercer trimestre otro 40 por ciento; y d) En el último trimestre el resto de los medios publicitarios.\nA las personas responsables de los anuncios de azotea que no sean retirados en el periodo de un año contado a partir de la entrada en vigor de la presente Ley, se les impondrá multa, así como las demás sanciones adicionales que procedan.\nEl Gobierno de la Ciudad podrá retirar los medios publicitarios prohibidos notificando el crédito fiscal correspondiente a las personas físicas o morales propietarias de los mismos, responsables de su difusión y responsables de su instalación, en los términos de la presente Ley.\nUna vez recibida la solicitud de permanencia, cambio de modalidad y/o ubicación, la Secretaría o la autoridad competente contará con un plazo de ciento veinte días hábiles contados a partir de la recepción de la misma, para analizar y valorar la idoneidad y viabilidad de las pruebas y propuestas que reciba conforme a lo referido en el presente transitorio, así como para emitir su determinación y en su caso, para la emisión de la Licencia autorización o PATR correspondiente.\n4. Para la determinación de los cambios de modalidad y/o reubicación, o permanencia, según proceda, la Secretaría o la autoridad competente considerará lo siguiente:\na) En cuanto a la distribución de nuevas ubicaciones, así como, en los cambios de modalidad autorizados a favor de publicistas incluidos en el Padrón Oficial de Anuncios\nSujetos al Reordenamiento de la Publicidad Exterior del Distrito Federal, se contemplarán principios de proporcionalidad y equidad, siempre y cuando ello no se contraponga a los criterios respectivos definidos en esta Ley y las demás disposiciones aplicables.\n\nb) Respecto a los casos que sean parte del proceso de ordenamiento previsto en este transitorio, en que la Secretaría advierta la existencia de un acto de corrupción, documentos falsos o falsedad de declaraciones, se dará vista a la Fiscalía General de\nJusticia de la Ciudad de México a fin de que se inicien las carpetas de investigación correspondientes. En dicho supuesto, el trámite solicitado será negado.\nc) Una vez concluido el plazo de 70 días naturales contados a partir de la entrada en vigor de este Decreto, todos los medios publicitarios prohibidos conforme a la misma, respecto de los cuales no se haya solicitado su permanencia, cambio de modalidad y/o reubicación, conforme a lo previsto en este transitorio, se presumirán ilegales y, por lo tanto, se procederá a su retiro por parte del Instituto de Verificación Administrativa de la Ciudad de\nMéxico a costa de las personas responsables del anuncio o medio publicitario, sin perjuicio de las sanciones a que pudiera hacerse acreedora.\n5. Tratándose de los medios publicitarios colocados en muros ciegos y azoteas que en términos de lo previsto en este transitorio la Secretaría haya determinado que no es procedente su permanencia, cambio de modalidad y/o reubicación, se presumirán como ilegales y, por lo tanto, se procederá a su retiro por parte del Instituto de Verificación Administrativa de la Ciudad de\nMéxico a costa de las personas responsables del anuncio o medio publicitario, sin perjuicio de las sanciones a que pudiera hacerse acreedora.\n6. Para efectos de la reubicación de anuncios o cambios de modalidad, la Secretaría considerará domicilios alternativos para los publicistas que hayan hecho el retiro en los tiempos señalados.\n7. La Secretaría procurará que las ubicaciones de estas nuevas modalidades se encuentren en un radio de 250 metros respecto a los medios prohibidos retirados. De no ser factible ello por razones físicas espaciales o de protección civil, se buscarán otras ubicaciones viables de acuerdo a lo establecido por esta Ley. La publicidad que se coloca en el transporte público y otras modalidades establecidas en la presente Ley, podrán servir al fin que se describe en este apartado.\nEn todo caso, cualquier ubicación propuesta, y autorización que se derive de la misma, estará sujeta a las disposiciones y trámites administrativos que resulten aplicables en razón del tipo de bien de que se trate.\n\n8. Tendrán prioridad en la obtención de licencias o PATR de nuevas modalidades en nuevas ubicaciones aquellos publicistas que realicen el retiro en primera instancia.\n9. La Secretaría podrá otorgar Licencias para medios publicitarios en muros ciegos de colindancia en corredores publicitarios como modalidad sustituta de medios instalados en azotea que sean retirados en primera instancia. Estos deberán adaptarse al uso de un 40% del muro susceptible de publicitarse, sobre el que se colocan y no podrán tener una dimensión superior al anuncio retirado.\nLo anterior, previa solicitud del interesado y con la condición de que estos sirvan como modalidad sustituta de medios instalados en azotea que sean retirados en primera instancia.\n10. Los medios publicitarios respecto de los cuales se emitan licencias o permisos de conformidad con lo previsto en este transitorio, se podrán cambiar de ubicación siempre y cuando al momento de su solicitud se cumpla con las disposiciones vigentes.\nUna vez autorizado la permanencia, reubicación y/o cambio de modalidad, según proceda, las personas responsables de los medios publicitarios, podrán obtener la Licencia o permiso respectivo, para lo cual deberán además cumplir con los requisitos de esta Ley para la emisión de las mismas, así como las demás disposiciones aplicables.\nLa Secretaría emitirá los lineamientos para la aplicación de este Artículo Séptimo Transitorio en un plazo de 10 días hábiles a partir de la entrada en vigor de esta Ley.\nOCTAVO. El Reglamento de la presente Ley se expedirá en un plazo máximo de 120 días hábiles contados a partir de la entrada en vigor del presente Decreto. En tanto se emita el Reglamento de la Ley de Publicidad\nExterior en la Ciudad de México, continuará aplicándose el Reglamento de la Ley de Publicidad Exterior del\nDistrito Federal, en lo que no contravenga lo previsto en la presente Ley.\nNOVENO. Las referencias hechas a la Ley de Publicidad Exterior del Distrito Federal en otros ordenamientos, se entenderán hechas a la Ley de Publicidad Exterior en la Ciudad de México.\nDÉCIMO. El Consejo Consultivo para Medios Publicitarios deberá instalarse en un plazo máximo de 180 días hábiles contados a partir del día siguiente a la entrada en vigor del presente Decreto.\n\nDÉCIMO PRIMERO. El mobiliario urbano con publicidad integrada que cuente con un Permiso\nAdministrativo Temporal Revocable vigente continuará ubicado en el emplazamiento que tiene autorizado por la Secretaría.\nDÉCIMO SEGUNDO. Los Permisos Administrativos Temporales Revocables otorgados previo a la entrada en vigor de la presente Ley, podrán ser prorrogados en los términos indicados por los artículos 106 y 107 de la Ley del Régimen Patrimonial y del Servicio Público; en cuyo caso, para la tramitación de la prórroga deberán de aplicarse las disposiciones normativas vigentes en el momento del otorgamiento del Permiso.\nDÉCIMO TERCERO. Se reconocen los siguientes corredores publicitarios:\nI. El Anillo Periférico, en el tramo comprendido por los boulevares Manuel Ávila Camacho, Adolfo\nLópez Mateos, Adolfo Ruiz Cortines y la avenida Canal de Garay; Río San Joaquín; Eje 3 Oriente\nFrancisco del Paso y Troncoso, y Avenida Vasco de Quiroga;\nII. La calzada San Antonio Abad; la calzada de Tlalpan; la calzada Patriotismo; calzada Zaragoza, y Canal de Miramontes; y\nIII. Calzada Melchor Ocampo en su tramo de 3.5 km que comprende de la Avenida Marina\nNacional al Eje 4 Sur Benjamín Franklin;\nIV. Boulevard Puerto Aéreo en su tramo de 4.4 km que comprende de la Avenida Oceanía al\nViaducto Río Piedad;\nV. Avenida Río Churubusco en su tramo de 6 km que corresponde a la Avenida Insurgentes a la\nAvenida Cerro de las Torres;\nVI. Viaducto Miguel Alemán, Viaducto Rio Piedad;\nVII. Insurgentes Norte, Insurgentes Centro en su tramo que comprende de Avenida Puente de\nAlvarado a Avenida Buenavista;\nVIII. Avenida Constituyentes, a partir de su intersección con el periférico Manuel Ávila Camacho hacia el poniente de la Ciudad.;\n\nIX. Avenida Universidad, a partir de su intersección con avenida Cuauhtémoc, hasta el eje 10 sur y; y\nX. Avenida Cuauhtémoc a partir de su intersección con el viaducto Río Piedad hacia el sur.\nXI. Aquiles Serdán en su tramo de 6.3 km que comprende de Calzada de las Armas a Calzada\nMéxico Tacuba;\nXII. Eje 5 Sur en su tramo de 18.1 km que comprende del Anillo Periférico a la Avenida República\nFederal del Sur;\nXIII. Eje 6 Sur en su tramo de 19.3 km que comprende de la Avenida Revolución a Calzada Ermita\nIztapalapa;\nXIV. Eje 8 Sur Ermita Iztapalapa en su tramo de 20.8 km que comprende de la Avenida\nUniversidad a Calzada Ignacio Zaragoza;\nXV. Avenida Montevideo en su tramo de 2.5 km que comprende de Calzada Vallejo a la Avenida\nInsurgentes;\nXVI. Prolongación División del Norte en su tramo de 4.8 km que comprende de la Calzada Acoxpa a Francisco Goytia;\nXVII. Circuito Interior en los siguientes tramos:\na) Avenida Río Consulado en su tramo de 8.9 km que comprende del Eje 2 Norte a\nOceanía; Avenida Instituto Técnico Industrial en su tramo de 1.8 km que comprende del\nEje 2 Norte a Calzada México-Tacuba;\nb) Calzada Melchor Ocampo en su tramo de 0.9 km que comprende de la Calzada\nMéxico-Tacuba a la Avenida Marina Nacional;\nc) Avenida Revolución en su tramo de 3.9 km que comprende del Eje 4 Sur\nBenjamín Franklin a Molinos;\n\nd) Avenida Río Mixcoac en su tramo de 0.9 km que comprende de Molinos a la\nAvenida Insurgentes;\ne) Río Churubusco en su tramo de 7.6 km que comprende del Cerro de las Torres al\nViaducto Río de la Piedad.\nXVIII. Eje 10 Sur, en su tramo de 2.5 km que comprende de la Avenida Cerro del Agua a la\nAvenida Aztecas.\nDÉCIMO CUARTO. En un término de 30 días hábiles, la Agencia de Innovación Pública deberá diseñar, en coordinación con la Secretaría Desarrollo Urbano y Vivienda, el Registro de Publicistas y la Plataforma\nDigital de Publicidad Exterior, mediante las soluciones tecnológicas que permitan integrar la información con la que se cuente, así como implementar las nuevas determinaciones establecidas en la presente Ley.\nUna vez implementados dicha Plataforma y Registro, las autoridades responsables de subir información, contarán con 60 días hábiles para actualizarla.\nUna vez implementado el Registro de Publicistas, las personas físicas y morales dedicadas a la instalación, gestión, operación y comercialización de medios publicitarios, contarán con 60 días hábiles para registrarse y poder realizar sus actividades, en términos de la presente Ley.\nPalacio Legislativo del Congreso de la Ciudad de México, a los treinta y un días del mes de mayo del año dos mil veintidós. POR LA MESA DIRECTIVA, DIPUTADO HÉCTOR DIAZ POLANCO, PRESIDENTE. - DIPUTADA\nMARCELA FUENTE CASTILLO, SECRETARIA. - DIPUTADA FRIDA JIMENA GUILLÉN ORTIZ, SECRETARIA. -\n(Firmas)\nCon fundamento en lo dispuesto por los artículos 122, apartado A, fracción III de la Constitución Política de los Estados Unidos Mexicanos; 32, apartado C, numeral 1, inciso a) de la Constitución Política de la Ciudad de México; 2 párrafo segundo, 3 fracciones XVII y XVIII, 7 párrafo primero, 10 fracción II, 12 y 21 párrafo primero de la Ley Orgánica del Poder Ejecutivo y de la Administración Pública de la Ciudad de México; para su debida publicación y observancia, expido el presente Decreto Promulgatorio en la Residencia Oficial de la Jefatura de Gobierno de la Ciudad de México, a los tres días del mes de junio del año dos mil veintidós.-\nLA JEFA DE GOBIERNO DE LA CIUDAD DE MÉXICO, DRA. CLAUDIA SHEINBAUM PARDO.- FIRMA.- EL\nSECRETARIO DE GOBIERNO, MARTÍ BATRES GUADARRAMA.- FIRMA.- LA SECRETARIA DE ADMINISTRACIÓN\nY FINANZAS, LUZ ELENA GONZALES ESCOBAR.- FIRMA.- EL SECRETARIO DE DESARROLLO URBANO Y\nVIVIENDA, RAFAEL GREGORIO GÓMEZ CRUZ.- FIRMA.- LA SECRETARIA DE GESTIÓN INTEGRAL DE RIESGOS Y\n\nPROTECCIÓN CIVIL, MYRIAM VILMA URZÚA VENEGAS.- FIRMA.- EL SECRETARIO DE MOVILIDAD, ANDRÉS\nLAJOUS LOAEZA.- FIRMA.\nTRANSITORIOS DEL DECRETO POR EL QUE SE MODIFICA EL PRIMER PÁRRAFO Y SE ADICIONA UNO\nSEGUNDO, RECORRIENDO EN SU ORDEN EL SUBSECUENTE, A LA FRACCIÓN II DEL ARTÍCULO 14 DE LA LEY\nDE PUBLICIDAD EXTERIOR DE LA CIUDAD DE MÉXICO, PUBLICADO EN LA GACETA OFICIAL DE LA CIUDAD DE\nMÉXICO EL 28 DE MARZO DE 2023.\nPRIMERO. Remítase a la persona titular de la Jefatura de Gobierno para su promulgación y publicación en la Gaceta Oficial de la Ciudad de México.\nSEGUNDO. El presente decreto entrará en vigor al día siguiente de su publicación en la Gaceta Oficial de la Ciudad de México.\nPalacio Legislativo del Congreso de la Ciudad de México, a los veintisiete días del mes de marzo del año dos mil veintitrés. - POR LA MESA DIRECTIVA. - DIPUTADO GERARDO VILLANUEVA ALBARRÁN, PRESIDENTE.\n- DIPUTADA MARCELA FUENTE CASTILLO, SECRETARIA. - DIPUTADA MARIA GABRIELA SALIDO MAGOS,\nSECRETARIA. - (Firmas)\nCon fundamento en lo dispuesto por los artículos 122, apartado A, fracción III de la Constitución Política de los Estados Unidos Mexicanos; 32, apartado C, numeral 1, inciso a) de la Constitución Política de la Ciudad de México; 2 párrafo segundo, 3 fracciones XVII y XVIII, 7 párrafo primero, 10 fracción II, 12 y 21 párrafo primero de la Ley Orgánica del Poder Ejecutivo y de la Administración Pública de la Ciudad de México; para su debida publicación y observancia, expido el presente Decreto Promulgatorio en la Residencia Oficial de la Jefatura de Gobierno de la Ciudad de México, a los veintiocho días del mes de marzo del año dos mil veintitrés.- LA JEFA DE GOBIERNO DE LA CIUDAD DE MÉXICO, DRA. CLAUDIA SHEINBAUM PARDO.- FIRMA.-\nEL SECRETARIO DE GOBIERNO, MARTÍ BATRES GUADARRAMA.- FIRMA.- EL SECRETARIO DE DESARROLLO\nURBANO Y VIVIENDA, CARLOS ALBERTO ULLOA PÉREZ.- FIRMA.",
  "ordenamiento": "Marco Jurídico",
  "jurisdiccion": "CIUDAD DE MEXICO",
  "fuente_oficial": "Congreso de la Ciudad de México",
  "status": "Vigente",
  "Fecha de Publicación": "12-04-2023",
  "Fecha de Última Reforma": "28 de marzo de 2023",
  "numero_paginas": 64,
  "es_escaneado": false,
  "tiene_tablas": false,
  "url": "https://www.congresocdmx.gob.mx/archivo-6f0375b106c8fe6ebc5838d74fdf96d5f5dfb389.pdf",
  "materia": [
    "publicidad",
    "desarrollo urbano"
  ]
}