{
  "titulo": "Ley DE LOS DERECHOS CULTURALES DE LOS HABITANTES y VISITANTES DE LA CIUDAD DE MÉXICO",
  "Contenido": "PUBLICADA EN LA GACETA OFICIAL DE LA CIUDAD DE MÉXICO\nEL 22 DE ENERO DE 2018\nTEXTO VIGENTE\nÚLTIMA REFORMA PUBLICADA EN LA G.O. CDMX\nEL 27 DE MARZO DE 2024\nDECRETO POR EL QUE SE EXPIDE LA LEY DE LOS DERECHOS CULTURALES DE LOS HABITANTES Y VISITANTES\nDE LA CIUDAD DE MÉXICO\nMIGUEL ÁNGEL MANCERA ESPINOSA, Jefe de Gobierno de la Ciudad de México, a sus habitantes sabed:\nQue la H. Asamblea Legislativa del Distrito Federal, VII Legislatura se ha servido dirigirme el siguiente\nD E C R E T O\n(Al margen superior izquierdo el Escudo Nacional que dice: ESTADOS UNIDOS MEXICANOS.- ASAMBLEA\nLEGISLATIVA DEL DISTRITO FEDERAL.- VII LEGISLATURA)\nASAMBLEA LEGISLATIVA DEL DISTRITO FEDERAL\nVII LEGISLATURA\nD E C R E T A\nDECRETO POR EL QUE SE EXPIDE LA LEY DE LOS DERECHOS CULTURALES DE LOS HABITANTES Y VISITANTES\nDE LA CIUDAD DE MÉXICO.\nARTÍCULO ÚNICO.- Se expide la Ley de los Derechos Culturales de los Habitantes y Visitantes de la Ciudad de México, para quedar como sigue:\n\nLEY DE LOS DERECHOS CULTURALES DE LOS\nHABITANTES Y VISITANTES DE LA CIUDAD DE MÉXICO\nTÍTULO PRIMERO\nDISPOSICIONES GENERALES\nCAPÍTULO I\nDE LOS OBJETIVOS DE LA LEY\nARTÍCULO 1.-La presente Ley tiene como fundamento los artículos 1, 2, 4, de la Constitución Política de los\nEstados Unidos Mexicanos, así como el artículo 8, apartado D de la Constitución Política de la Ciudad de\nMéxico.\nARTÍCULO 2.- La presente ley es de orden público, interés social y de observancia obligatoria en la Ciudad de México;\nARTÍCULO 3.- Los objetivos de la presente Ley son los siguientes:\nI. Garantizar que toda persona, grupo o comunidad cultural que fije su residencia en la Ciudad de México o esté de tránsito en la misma tiene legitimidad para ejercer los derechos culturales previstos en esta ley, con base en los principios y disposiciones de la Constitución Política de los\nEstados Unidos Mexicanos, de la Constitución Política de la Ciudad de México, de los tratados internacionales de la materia de los que el Estado mexicano sea parte, de sus criterios interpretativos, directrices operativas, observaciones generales oficiales, y demás disposiciones aplicables.\nII. Establecer los lineamientos básicos, conforme a los cuales se articulen las políticas públicas en materia cultural, educativa y artística de la Ciudad de México de conformidad con los derechos culturales;\nIII. Fomentar el conocimiento, difusión, promoción y estímulo al desarrollo de la cultura y las artes, y de los derechos culturales conforme a la diversidad y pluralidad cultural y propiciar las múltiples formas de cohesión social de los grupos, comunidades y colectivos culturales de la\nCiudad de México;\n\nIV. Determinar las bases, instancias, procedimientos y recursos que provean los medios de defensa de los derechos culturales de todas las personas individuales y colectivas que habiten o transiten en la Ciudad de México;\nV. Garantizar el eficaz ejercicio de los derechos culturales, a cuyo efecto se observarán los mecanismos de su protección y defensa;\nVI. Reconocer la legitimidad procesal activa de las personas, grupos, comunidades y colectivos culturales de la Ciudad de México, en el ejercicio de los derechos culturales, así como proveer los mecanismos para su reconocimiento y defensa;\nVII. Establecer las bases en la política cultural que estimulen la generación y desarrollo de las industrias creativas y conferir de personalidad jurídica a los grupos, comunidades y colectivos culturales de la Ciudad de México en la forma en que deseen ser reconocidos en la sociedad;\nVIII. Facilitar a las personas con discapacidad las oportunidades necesarias para el uso y disfrute de las instalaciones destinadas a las expresiones culturales;\nIX. Salvaguardar la igualdad de género en la instrumentación y aplicación de políticas de apoyo y fomento a la cultura. Para ello, se deberán observar los principios de representatividad, paridad de género, igualdad sustantiva y protección a grupos de atención prioritaria.\nFracción modificada y publicada en la GOCDMX el 27 de marzo de 2024\nX. Garantizar el conocimiento y el acceso al patrimonio cultural tangible e intangible de la\nCiudad;\nXI. Garantizar la protección de los intereses morales y materiales que le correspondan por razón de sus producciones científicas, literarias o artísticas; y\nXII. Gozar de los beneficios del progreso científico y de sus aplicaciones.\nARTÍCULO 4.- Para efectos de aplicación de la presente ley, se entenderá por:\nI. Actividades Culturales: Conjunto de acciones que realizan los creadores culturales y las autoridades para la difusión y desarrollo de su obra artística;\n\nII. Comisión: Comisión de Derechos Humanos de la Ciudad de México;\nIII. Consejo: Consejo Consultivo Asesor del Instituto de los Derechos Culturales de la Ciudad de\nMéxico;\nIV. Constitución: Constitución Política de la Ciudad de México;\nV. Cultura: Conjunto de rasgos distintivos, espirituales, materiales, intelectuales y emocionales que caracterizan a los grupos humanos y que comprende, más allá de las artes y las letras, modos de vida, derechos humanos, sistemas de valores, tradiciones y creencias. En sus diversas manifestaciones, la cultura es fundamental en la búsqueda del concierto de nuestro país con las demás naciones, y representa una actividad que identifica a nuestro país por su riqueza, su diversidad y por su originalidad; por sí misma, la cultura constituye procesos generadores de identidad, simbólica individual y colectiva. Dichas manifestaciones constituyen parte integral de lo que denominamos cultura mexicana y es el cuarto pilar de una economía sostenible y sustentable;\nVI. Cultura Urbana: Toda expresión cultural registrada dentro del perímetro de la Ciudad de\nMéxico;\nVII. Establecimiento Cultural: Espacios colectivos, autogestivos, independientes de arte y cultura;\nVIII. Gobierno de la Ciudad: Gobierno de la Ciudad de México;\nIX. Instituto: Instituto de los Derechos Culturales de la Ciudad de México;\nX. Ley: Ley de los Derechos Culturales de los Habitantes y Visitantes de la Ciudad de México;\nXI. Pueblos Indígenas en el territorio de la Ciudad de México: Unidad social, económica y cultural de personas, que forman parte de pueblos indígenas de otras regiones del país, que se han asentado en la Ciudad de México y que en forma comunitaria reproducen total o parcialmente sus instituciones y tradiciones;\nXII. Pueblos y barrios Originarios: Son aquellos que descienden de poblaciones asentadas en el territorio actual de la Ciudad de México desde antes de la colonización y del establecimiento de\n\nlas fronteras actuales y que conservan sus propias instituciones sociales, económicas, culturales y políticas, sistemas normativos propios, tradición histórica, territorialidad y cosmovisión o parte de ellas;\nXIII. Recursos legales: Mecanismos conferidos a toda persona, grupo y comunidad cultural que aseguren el pleno ejercicio de sus derechos culturales, tanto en el ámbito administrativo como en el judicial;\nXIV. Reglamento: Reglamento de la Ley de los Derechos Culturales de los Habitantes y Visitantes de la Ciudad de México; y\nXV. Secretaría: Secretaría de Cultura del Gobierno de la Ciudad de México.\nXVI. Comunidad o colectivo cultural: Conjunto de ciudadanos que se identifican entre sí por compartir rasgos culturales comunes, tales como: la lengua, la memoria histórica, la adscripción a un pueblo indígena o barrio originario, por afinidades generacionales, de género o preferencias sexuales, formas de vida y convivencia y gustos artísticos y culturales, entre otros.\nCAPÍTULO II\nDE LA AUTORIDAD RESPONSABLE DE VIGILAR LA\nPUNTUALOBSERVANCIA DE ESTA LEY Y LA TRANSVERSALIDAD EN SU\nCUMPLIMIENTO\nARTÍCULO 5.-Las autoridades responsables de la puntual observancia de las disposiciones de la presente ley son:\nI. La persona titular de la Jefatura de Gobierno de la Ciudad de México; y\nII. La persona titular de la Secretaría de Cultura del Gobierno de la Ciudad de México; y\nIII. Las personas titulares de las Alcaldías de la Ciudad de México.\nARTÍCULO 6.- Todas las dependencias y entidades de la Administración Pública del Gobierno de la Ciudad y los órganos jurisdiccionales en el ámbito de su competencia están obligadas a procurar el pleno ejercicio\n\nde los derechos culturales, así como las personas u organismos que ejerzan funciones vinculadas a la autoridad.\nEl Poder Legislativo deberá considerar en todo momento la actualización de las normas relativas a los derechos culturales y su protección.\nDe igual manera dispondrá en la legislación específica de los recursos necesarios que hagan efectivo el ejercicio de estos derechos.\nEn cuanto al poder judicial, deberá observar en sus resoluciones siempre el principio pro-persona, se abstendrá de infringir en ella los derechos culturales y reconocerán la personalidad jurídica de los grupos, comunidades y colectivos culturales en la forma en la que deseen ser reconocidos en la sociedad.\nAmbos poderes deberán concertar convenios con instancias especializadas para la debida capacitación de su personal en esta materia.\nARTÍCULO 7.- Las dependencias y entidades de la Administración Pública de la Ciudad, en el ámbito de su competencia proveerán de los medios necesarios que hagan efectivo el ejercicio de los derechos culturales.\nLas acciones para el desarrollo de las culturas en la Ciudad de México que se emprendan y que se propongan por el gobierno de la Ciudad, las autoridades de las demarcaciones territoriales, individuos o comunidades, se instrumentarán con pleno respeto a su diversidad cultural y propiciarán el respeto al intercambio cultural y promoverán la revaloración y el fortalecimiento de las diversas identidades tendientes a consolidar la identidad de la Ciudad y la nacional.\nLos particulares deberán cumplir con las medidas cautelares que dicten las autoridades conforme a esta ley para asegurar el ejercicio de los derechos culturales.\nARTÍCULO 8.- Los gobiernos de las demarcaciones territoriales de la Ciudad de México coadyuvarán con la\nSecretaría de Cultura en la vigilancia y protección de los derechos culturales, de acuerdo a las disposiciones de esta Ley, del reglamento que para el efecto se promulgue, de los convenios o acuerdos que se consideren necesarios o de la ley que así corresponda.\nARTÍCULO 9.- La Comisión recibirá y dará curso a las quejas que en el ámbito de su competencia presenten en su caso las personas que consideren agraviados sus derechos culturales.\n\nLa Comisión y la Secretaría, a través del Instituto, establecerán los convenios necesarios con el objetivo de optimizar y actualizar los mecanismos e instrumentos de política pública destinados a la protección, respeto, promoción e investigación de los derechos culturales.\nTÍTULO SEGUNDO\nDE LOS DERECHOS CULTURALES\nCAPÍTULO I\nDE LOS DERECHOS CULTURALES EN LA CIUDAD DE MEXICO Y MEDIOS\nPARA SU EXIGIBILIDAD\nARTÍCULO 10.- El régimen jurídico de los derechos culturales pertenece al ámbito de los derechos humanos; su interpretación observará los principios de universalidad, indivisibilidad, interdependencia, progresividad, y pro-persona.\nCada persona, grupo, comunidad o colectivo cultural determinará libremente la forma y términos de su participación en la vida cultural de la Ciudad.\nARTÍCULO 11.- La presente Ley afianza la diversidad cultural de las personas, grupos, comunidades, barrios, colonias, pueblos y barrios originarios y de todos quienes habitan y transitan en la Ciudad de México; a estos efectos provee de un marco de libertad y equidad en sus expresiones y manifestaciones culturales en sus formas más diversas.\n1. Para los efectos toda persona, grupo, comunidad o colectivo cultural tendrá el acceso irrestricto a los bienes y servicios culturales que suministra el Gobierno de la Ciudad y les asiste la legitimidad en el ejercicio, entre otros, de manera enunciativa y no limitativa, de los siguientes derechos culturales.\na) A elegir y que se asegure, en la diversidad, su identidad cultural y formas de expresión y manifestación;\nb) A conocer y que se asegure la protección a su propia cultura;\nc) A la formación integral, individual o colectiva que contribuya al libre y pleno desarrollo de su identidad cultural;\n\nd) A acceder al patrimonio cultural constituido por los bienes, expresiones y manifestaciones de las diferentes culturas;\ne) A acceder y participar en la vida cultural de su comunidad, pueblo, colonia, barrio o cualquiera otra forma de expresión colectiva, que libremente elijan, así como de aquella que provenga de las políticas públicas del Gobierno de la Ciudad.\nA estos efectos tendrán acceso irrestricto a los espacios públicos para el ejercicio de sus expresiones culturales y artísticas sin más limitación que las que establezca la normatividad expresamente y el respeto a la dignidad de las personas;\nf) A ejercer las propias prácticas culturales y seguir un modo de vida asociado a sus formas tradicionales de conocimiento, organización y representación;\ng) A ejercer en plena libertad la innovación y emprendimiento de proyectos, iniciativas y propuestas culturales y artísticas;\nEl Gobierno de la Ciudad, proveerá para el desarrollo de dichos proyectos, de los soportes materiales en los términos de las convocatorias, programas, proyectos y, en general, de las políticas públicas que establezca en la materia;\nh) A constituir espacios colectivos, autogestivos, independientes y comunitarios de arte y cultura, los cuales contarán con una regulación específica para el fortalecimiento y desarrollo de sus actividades, siempre favoreciendo su fomento de acuerdo a los lineamientos que establezcan las entidades facultadas de la Administración Pública de la\nCiudad;\nLas entidades y dependencias de la Administración Pública de la Ciudad procurarán el suministro material para el fortalecimiento y desarrollo de las actividades culturales que se desarrollen en estos espacios colectivos y emitirán las acciones normativas necesarias en los términos que establece esta Ley;\ni) A ejercer la libertad cultural creativa, artística, de opinión e información; y j) A preservar su memoria colectiva sea escrita, oral o expresada en cualquier otro soporte;\n\nPara la mejor eficacia en el ejercicio de sus derechos culturales, el Gobierno de la Ciudad deberá desarrollar los mecanismos de participación democrática de los grupos y comunidades, en la elaboración, puesta en práctica y evaluación de las políticas culturales públicas del Gobierno de la Ciudad.\nToda persona individual o colectiva podrá, en el marco de la gobernanza democrática, tomar iniciativas que aseguren el pleno ejercicio de los derechos culturales y desarrollar modos de concertación y participación con personas y organizaciones sociales o con las entidades y dependencias del Gobierno de la Ciudad.\n2. Las autoridades del Gobierno de la Ciudad y sus demarcaciones territoriales, en el ámbito de sus respectivas competencias, protegerán los derechos culturales mediante el uso de toda clase de mecanismos de cualquier naturaleza de que dispongan. Asimismo, favorecerán a la promoción y el estímulo del desarrollo de las culturas y las artes.\nEs obligatorio que las dependencias de la Administración Pública de la Ciudad de México, los institutos y órganos desconcentrados, emitan un informe anual en los términos establecidos en la Ley de Transparencia y Acceso a la Información Pública y Rendición de Cuentas de la Ciudad de México, de las acciones implementadas y de los recursos erogados en el ejercicio del derecho al acceso a la cultura y de los derechos culturales enunciados en el numeral 1 del presente artículo.\n3. Esta ley reconoce el patrimonio cultural como un derecho humano: como una clave de nuestro desarrollo personal y colectivo.\nEl Gobierno de la Ciudad llevará un inventario de las expresiones y manifestaciones propias del patrimonio cultural inmaterial declarado y deberá asegurar su fomento, salvaguarda y difusión.\n4. El Gobierno de la Ciudad dispondrá de estímulos fiscales para el apoyo y fomento de la creación y difusión de la cultura y el arte y; para esos efectos las dependencias de cultura y hacendarias del Gobierno de la Ciudad, deberán elaborar un programa con objetivos y resultados esperados, así como los mecanismos necesarios de evaluación, transparencia y rendición de cuentas relacionados con los proyectos beneficiados.\n5. Los grupos y comunidades culturales gozarán del derecho de ser reconocidos en la sociedad y ante las autoridades, de acuerdo con el elemento de cohesión que manifiesten.\n\nARTÍCULO 12.- El arte y la ciencia son libres, en su creación, transmisión, manifestación y difusión en la\nCiudad de México. Queda prohibida toda clase de censura.\nLos pueblos y barrios originarios, así como los productores culturales populares, tienen derecho a la protección de sus saberes ancestrales, así como a la salvaguarda de sus costumbres, diseños, arte y artesanías en general, música, lenguas, rituales, festividades, modos de vida, arte culinario y de todo su patrimonio cultural material e inmaterial. El Gobierno, por medio de la Secretaría y el Instituto desarrollará los mecanismos, programas e instrumentos legislativos para proteger los derechos de los pueblos y barrios originarios y de su enorme patrimonio cultural.\nLa persona titular de la Jefatura de Gobierno de la Ciudad de México dotará de los recursos presupuestales necesarios para el desarrollo de esta ley en término de lo estipulado en el capítulo II, artículo 19, fracción\nIV de la Ley de Fomento Cultural del Distrito Federal.\nCAPÍTULO II\nDE LOS MEDIOS DE DEFENSA PARA LA EXIGIBILIDAD DE LOS\nDERECHOS CULTURALES\nARTÍCULO 13.- Toda persona, grupo o comunidad tiene el derecho de demandar el cese de cualquier trasgresión a sus derechos culturales, exigir su plena vigencia y el resarcimiento del daño causado a través de la interposición de la acción de protección efectiva de derechos ante las y los jueces de tutela de derechos humanos, de conformidad con el artículo 36, apartado B, numeral 3 de la Constitución local y las demás disposiciones legales aplicables, así como mediante la presentación de queja ante la Comisión, conforme a la legislación de la materia.\nEn caso de así requerirlo, se podrá solicitar al Instituto acompañamiento y orientación para la presentación de dichos medios de defensa.\nARTÍCULO 14.-Se Deroga.\nARTÍCULO 15.- Se Deroga.\nARTÍCULO 16.- Se Deroga.\n\nARTÍCULO 17.- Se Deroga.\nARTÍCULO 18.- Se Deroga.\nARTÍCULO 19.- Se Deroga.\nARTÍCULO 20.- Se Deroga.\nARTÍCULO 21.- Se Deroga.\nCAPÍTULO III\nDEL ÓRGANO ENCARGADO DE LA PROMOCIÓN, DIFUSIÓN E\nINVESTIGACIÓN DE LOS DERECHOS CULTURALES EN LA CIUDAD DE\nMÉXICO\nARTÍCULO 22.- Se crea el órgano desconcentrado denominado Instituto de los Derechos Culturales de la\nCiudad de México, dependiente de la Secretaria; dotado de autonomía gestión y de función.\nEl Instituto, teniendo su domicilio en la Ciudad de México, podrá establecer en coordinación con los gobiernos de las demarcaciones territoriales de la Ciudad, las instalaciones culturales y oficinas de atención que estime necesarias para el cumplimiento de su objeto.\nARTÍCULO 22 Bis.- El Instituto tendrá a su cargo la puntual observancia de los derechos culturales, y estará facultado para su promoción, difusión, respeto, protección y garantía.\nARTÍCULO 23.- El Instituto, tendrá entre otras, las siguientes atribuciones:\nI. Ser el órgano encargado del acompañamiento, cuando así se le solicite, durante el proceso del recurso de queja, que por motivo de transgresión de los derechos culturales presente cualquier persona, grupo o comunidad cultural;\nII. Llevar a cabo proyectos de investigación académica en materia de derechos culturales ya sea directamente o a través de convenios con universidades o centros de investigación;\n\nIII. Proponer a la Secretaría, normas reglamentarias y operativas para la mayor eficacia en la promoción, difusión e investigación de los derechos culturales en la Ciudad de México;\nIV. Elaborar y proponer a la Secretaría, para su aprobación, el Programa de Protección de los\nDerechos Culturales de la Ciudad de México, atendiendo a los lineamientos, criterios y disposiciones de consulta en materia de planeación establecidos en la Ley de Planeación, el cual deberá actualizarse anualmente; y\nV. Proponer todos los mecanismos e instrumentos tendientes a la protección de los derechos culturales que le competan a la Secretaría, a fin de orientar las políticas públicas en materia de cultura, atendiendo todas las disposiciones legales que así lo dispongan.\nEl Instituto elaborará un informe anual sobre los resultados de las acciones en materia de investigación y protección de los derechos culturales; dicho informe deberá entregarlo a la o el titular de la Secretaría y hacerlo público para su conocimiento.\nSe declara de interés público y social la investigación, protección y promoción de los derechos culturales;\nla organización y coordinación de las actividades encaminadas a este fin, garantizarán en todo momento la participación plural y democrática de las personas individuales y colectivas.\nARTÍCULO 24.- Se Deroga.\nARTÍCULO 25.- Se Deroga.\nARTÍCULO 26.- A falta de disposición expresa en la presente Ley, se aplicarán de manera supletoria en lo conducente:\nI. La Ley de Fomento Cultural de la Ciudad de México;\nII. La Ley de Archivos de la Ciudad de México;\nIII. La Ley de Fomento para la Lectura y el Libro de la Ciudad de México;\nIV. La Ley de Filmaciones de la Ciudad de México;\nV. La Ley de Salvaguarda del Patrimonio Urbanístico y Arquitectónico del D.F;\n\nVI. El Código Civil de la Ciudad de México;\nVII. El Código Procesal Civil de la Ciudad de México;\nVIII. El Código Penal de la Ciudad de México;\nIX. El Código de Procedimientos Penales de la Ciudad de México;\nX. La Ley Orgánica de la Administración Pública de la Ciudad de México; y\nXI. Las demás disposiciones legales aplicables relacionadas con las materias que regula esta ley y en última instancia se aplicarán los Principios Generales de Derecho.\nARTÍCULO 27.-El Instituto promoverá que en la actuación de las autoridades administrativas del Gobierno de la Ciudad de México se apliquen los criterios generales de interpretación y principios de los derechos culturales.\nARTÍCULO 28.-Para ser titular de este Instituto deberá contar conocimientos en el ámbito de los derechos culturales, ya sea mediante la producción de obra escrita en la materia, desempeño académico en materia cultural o con méritos y experiencia reconocidos en el ámbito de la cultura y en la defensa de los derechos culturales.\nSu nombramiento y remoción, serán atribuciones de la persona titular de la Secretaría.\nARTÍCULO 29.- Son facultades y obligaciones de la persona titular del Instituto:\nI. Representar legalmente al Instituto;\nII. Otorgar, revocar y sustituir poderes;\nIII. Acordar con la persona titular de la Secretaría los asuntos de su competencia;\nIV. Coordinar las acciones para ejecutar los acuerdos del Consejo;\nV. Aprobar, cumplir y hacer cumplir los programas de trabajo del Instituto;\n\nVI. Nombrar y remover al personal de confianza en los términos de la legislación aplicable;\nVII. Proponer, a la persona titular de la Secretaría, los proyectos de reglamentos y aprobar la normatividad necesaria para el funcionamiento y operación del Instituto;\nVIII. Celebrar contratos y realizar toda clase de actos de dominio;\nIX. Presentar oportunamente, a la persona titular de la Secretaría y gestionar ante las autoridades competentes, el proyecto de presupuesto anual del Instituto;\nX. Presentar a la persona titular de la Secretaría un informe anual de actividades del Instituto y el programa de trabajo anual a desarrollar;\nXI. Celebrar convenios con personas físicas o jurídicas y con organismos públicos o privados, nacionales, internacionales o extranjeros, en los términos de la legislación aplicable; y\nXII. Las demás que le confieran otras leyes, los reglamentos, el Jefe (a) de Gobierno de la Ciudad y el o la titular de la Secretaría, apegándose en todo momento a sus facultades, atribuciones y funciones establecidas.\nARTÍCULO 30.- El Instituto contará con un Consejo Consultivo que será presidido por la persona titular de la Secretaría. Su conformación y funcionamiento serán regulados por el reglamento de esta ley;\nARTÍCULO 31.- Son atribuciones del Consejo Consultivo:\nI. Conocer y opinar respecto al programa anual del Instituto, así como recomendar las mejoras que estime necesarias;\nII. Estudiar los planes y programas de trabajo necesarios para el cumplimiento de los objetivos del Instituto que les presente la persona titular de la Secretaría, con el objeto de opinar y hacer sugerencias sobre el mismo;\nIII. Brindar asesoría y apoyo a la persona titular del Instituto en la formulación y ejecución de proyectos y programas que eleven la calidad de los servicios culturales;\n\nIV. Se Deroga.\nV. Las demás que se le asignen.\nLos integrantes del Consejo Consultivo,serán personas que se distingan por su conocimiento, compromiso, experiencia o desarrollo de proyectos en el ámbito de la cultura y representativos de los distintos sectores o comunidades culturales.\nARTÍCULO 32.- Las relaciones laborales entre el Instituto y su personal se regirán por las Condiciones\nGenerales de Trabajo prevalecientes de la Secretaría.\nARTÍCULO 33.- El patrimonio del Instituto estará constituido:\nI. Los bienes muebles e inmuebles que le asigne la Secretaría;\nII. Los recursos presupuestales que anualmente le asigne el Gobierno de la Ciudad, a través de la Secretaría;\nIII. Se Deroga.\nIV. Se Deroga.\nV. Se Deroga.\nARTÍCULO 34.- Se Deroga.\nTÍTULO CUARTO\nDE LA POLITICA PUBLICA DEL GOBIERNO DE LA CIUDAD SOBRE LOS\nDERECHOS CULTURALES\nCAPÍTULO ÚNICO\nDE LA RECTORIA DELA POLITICA PUBLICA EN MATERIA DE DERECHOS\nCULTURALES Y LOS FINES DE LA MISMA\n\nARTÍCULO 35.-El Gobierno de la Ciudad a través de la Secretaría, tendrá a su cargo la rectoría de la política pública en el respeto, investigación, promoción y difusión de los derechos culturales.\nLas políticas culturales tendrán como finalidad:\nI. Afirmar y fortalecer el respeto a los derechos culturales de las personas individuales y colectivas, expresados a través de su propia identidad y la diversidad cultural de la Ciudad de México;\nII. Fomentar el respeto y conocimiento de los derechos culturales, a través del diálogo intercultural y del sistema educativo bajo responsabilidad del Gobierno de la Ciudad;\nIII. Incorporar al sistema educativo bajo responsabilidad del Gobierno de la Ciudad la enseñanza de los derechos culturales como un elemento fundamental para el desarrollo integral de la sociedad;\nIV. Fomentar el conocimiento y defensa de los derechos de los trabajadores de la cultura, de los investigadores, promotores, gestores, creadores, intérpretes, ejecutantes, actores, productores, artistas y todos aquellos que desempeñen labores en el campo de la cultura;\nV. Fomentar el conocimiento y defensa de los derechos culturales de todos los sectores de la\nCiudad; pueblos, barrios, colonias, unidades habitacionales, colectivos, agrupaciones culturales de vecinos, grupos artísticos y todas aquellas formas de organización colectiva de carácter cultural; y\nVI. Fomentar como un derecho cultural la pertenencia e identificación con la Ciudad de México, en un marco de tolerancia, apertura y respeto a la vida cultural de otros pueblos.\nARTÍCULO 36.-Las políticas culturales de la Ciudad de México en materia de derechos culturales favorecerán y promoverán la cooperación de todos aquellos que participen en la promoción, difusión y respeto a los derechos culturales y si fuere necesario, fortalecerán y complementarán la acción de éstos en los siguientes ámbitos:\nI. El conocimiento, desarrollo y difusión de los derechos culturales de todas las personas que conforman distintas culturas como parte de la Ciudad y de la nación mexicana;\nII. El conocimiento, desarrollo y difusión de los valores universales de los derechos culturales;\n\nIII. La investigación, defensa y protección de los derechos culturales;\nIV. La difusión y promoción de la creación y ejecución artísticas, en sus expresiones individuales y colectivas, incluido el ámbito de las nuevas tecnologías, como derechos culturales;\nV. El conocimiento, fortalecimiento, desarrollo y difusión de las culturas populares que incluyen a las culturas indígenas, de los pueblos y barrios originarios, a los grupos migrantes y a las culturas urbanas como derechos culturales;\nVI. El desarrollo y consolidación de los sistemas de educación formal y no formal, teatros, casas de cultura, archivos, bibliotecas, museos y demás espacios de expresión cultural como derechos culturales;\nVII. El fomento a la creatividad cultural como parte de los derechos culturales, con especial énfasis en la niñez, la juventud, así como en personas de la tercera edad y que estimule la integración de las personas con capacidades diferentes y demás grupos prioritarios;\nVIII. La incidencia en todos los sectores de la Administración Pública del Gobierno de la Ciudad, para que en sus políticas públicas se considere el criterio favorecedor de la protección y respeto de los derechos culturales;\nIX. La coordinación de las organizaciones culturales entre sí y en colaboración con acciones de gobierno relativas a campañas formativas en materia de derechos culturales;\nX. El diseño de estrategias para el financiamiento de proyectos y actividades relacionadas con los derechos culturales de acuerdo a los lineamientos que establezca la Secretaría;\nXI. En el apoyo a la creación, ampliación, remodelación y acondicionamiento de los inmuebles destinados a las actividades culturales y artísticas. Asimismo promoverá su uso adecuado a través de programas culturales específicos, acordes con la vocación del espacio; y\nXII. En la protección y defensa de los derechos culturales queda prohibida toda forma de discriminación por causa de género, ideologías, creencias, militancias políticas, preferencias sexuales, pertenencia a minorías étnicas, idioma o cualquiera otra forma de identidad.\n\nARTÍCULO 37.-La política pública del Gobierno de la Ciudad en materia de derechos culturales se aplicará en estricto apego a sus facultades establecidas en los artículos 73 fracción XXIXÑ, 122, 124 y 133, de la\nConstitución Política de los Estados Unidos Mexicanos, artículo 8º de la Constitución Política de la Ciudad de México, respetando en todo momento aquellas facultades consideradas como facultades exclusivas del\nGobierno Federal y, en estricto apego a su jurisdicción, acatando los principios y criterios de los instrumentos de derecho internacional signados por nuestro país.\nTÍTULO CUARTO\nDE LAS FALTAS, RESPONSABILIDADES Y DELITOS\nCAPÍTULO ÚNICO\nDE LAS FALTAS ADMINISTRATIVAS, DELITOS Y SANCIONES EN\nMATERIA DE DERECHOS CULTURALES\nARTÍCULO 38.-Las Faltas administrativas que se cometan por servidores públicos o particulares por razón de trasgresión de la presente Ley, serán calificadas como no graves o graves, conforme lo establece el Título\n4º de la Constitución Política de los Estados Unidos Mexicanos, La Ley General de Responsabilidades\nAdministrativas, el Capítulo II del Título Sexto de la Constitución Política de la Ciudad de México y la ley que regule esta materia en la Ciudad.\nARTÍCULO 39.- Para el caso de las demás responsabilidades, político, civil y penal se regirán por el mismo marco jurídico, más lo que disponga la legislación penal de la Ciudad de México.\nARTÍCULO 40.- En las situaciones en que se compruebe que los recursos públicos destinados a acciones culturales se utilicen para fines distintos, se sancionará, de acuerdo a lo previsto en la legislación aplicable sobre responsabilidades administrativas, civiles y penales que correspondan.\nARTÍCULO 41.- De manera especial, para efectos de la presente Ley, se consideran faltas administrativas en materia de derechos culturales:\nI. Cualquier conducta que por acción u omisión impida la expresión cultural de cualquier persona individual o colectiva;\nII. Ejecutar actos de discriminación contra personas individuales o colectivas por su condición cultural expresada en su lengua, creación artística, ideas, prácticas rituales, actos festivos,\n\nreligiosos, etc., siempre y cuando la expresión cultural no contravenga los principios de la\nConstitución Política de los Estados Unidos Mexicanos, los tratados internacionales en la materia suscritos por el Estado mexicano, la Constitución Política de la Ciudad de México, las disposiciones de la presente Ley y, no ofenda la dignidad y los derechos de persona alguna;\nIII. Perturbar las relaciones sociales comunitarias mediante la alteración o destrucción de su espacio común, sus referentes simbólicos y su entorno cultural; y\nIV. La trasgresión sistemática de los derechos culturales.\nARTÍCULO 42.- Se Deroga.\nARTÍCULOS TRANSITORIOS\nPRIMERO.- Publíquese el presente Decreto en la Gaceta Oficial de la Ciudad de México, y para su mayor difusión publíquese en el Diario Oficial de la Federación.\nSEGUNDO.-Se expide la Ley de los Derechos Culturales de los Habitantes y Visitantes de la Ciudad de\nMéxico.\nTERCERO.- El presente Decreto entrará en vigor a partir del día siguiente de su publicación en la Gaceta\nOficial del Gobierno de la Ciudad de México.\nCUARTO.-El Ejecutivo del Gobierno de la Ciudad expedirá el Reglamento de la presente Ley en un término máximo de 180 días naturales, a partir de la entrada en vigor del presente decreto, incluyendo el Titulo dispuesto en la fracción H, del inciso D, de artículo octavo de la Constitución de la Ciudad de México relativo a los establecimientos culturales.\nQUINTO.-En un plazo no mayor de 180 días naturales, el Gobierno de la ciudad deberá llevar a cabo las acciones administrativas correspondientes, a fin de que el Instituto quede establecido e inicie su funcionamiento.\nSEXTO.-El Gobierno de la Ciudad de México deberá hacer las previsiones presupuestales necesarias para la entrada en vigor de la presente Ley y La Asamblea Legislativa deberá proveer los recursos necesarios a fin\n\nde dar cumplimiento a las disposiciones de la presente Ley y, en lo sucesivo se garantizará para cada año fiscal correspondiente las partidas presupuestales destinadas al cumplimiento del presente Decreto.\nSÉPTIMO. Todo lo referente a los Pueblos y Barrios Originarios de la Ciudad de México, de conformidad a lo estipulado en el artículo VÍGESIMO OCTAVO TRANSITORIO de la Constitución Política de la Ciudad de\nMéxico, entrará en vigor hasta en tanto el Congreso de la Ciudad de México emita la Ley reglamentaria de los artículos 57, 58 y 59 y las demás leyes reglamentarias que correspondan.\nRecinto de la Asamblea Legislativa del Distrito Federal, a los veinte días del mes de diciembre del año dos mil diecisiete.- POR LA MESA DIRECTIVA.- DIP. ADRIÁN RUBALCAVA SUÁREZ, PRESIDENTE.- DIP. REBECA\nPERALTA LEÓN, SECRETARIA.- DIP. EVA ELOISA LESCAS HERNÁNDEZ, SECRETARIA. (Firmas)\nCon fundamento en lo dispuesto por los artículos 122, Apartado A, Base III, de la Constitución Política de los Estados Unidos Mexicanos; Transitorios Primero y Segundo del Decreto por el que se declaran reformadas y derogadas diversas disposiciones de la Constitución Política de los Estados Unidos Mexicanos, en materia de la Reforma Política de la Ciudad de México; 48, 49 y 67, fracción II, del Estatuto de Gobierno del Distrito Federal, para su debida publicación y observancia, expido el presente Decreto Promulgatorio en la Residencia Oficial del Jefe de Gobierno de la Ciudad de México, a los dieciocho días del mes de enero del año dos mil dieciocho.- EL JEFE DE GOBIERNO DE LA CIUDAD DE MÉXICO, MIGUEL ÁNGEL MANCERA\nESPINOSA.- FIRMA.- LA SECRETARIA DE GOBIERNO, DORA PATRICIA MERCADO CASTRO.- FIRMA.- EL\nSECRETARIO DE CULTURA, EDUARDO VÁZQUEZ MARTÍN.- FIRMA.- EL SECRETARIO DE FINANZAS, EDGAR\nABRAHAM AMADOR ZAMORA.- FIRMA.\nTRANSITORIOS DEL DECRETO POR EL QUE SE SE REFORMAN, DEROGAN Y ADICIONAN DIVERSAS\nDISPOSICIONES DE LA LEY DE LOS DERECHOS CULTURALES DE LOS HABITANTES Y VISITANTES DE LA\nCIUDAD DE MÉXICO, PUBLICADO EN LA GACETA OFICIAL DE LA CIUDAD DE MÉXICO EL 20 DE MAYO DE\n2019.\nPRIMERO.- Publíquese el presente Decreto en la Gaceta Oficial de la Ciudad de México, y para su mayor difusión, en el Diario Oficial de la Federación.\nSEGUNDO- El presente Decreto entrará en vigor a partir del día siguiente de su publicación en la Gaceta\nOficial de la Ciudad de México.\n\nTERCERO- El Gobierno de la Ciudad de México de conformidad con el principio de progresividad de los derechos, realizará las provisiones presupuestales necesarias para fortalecer las capacidades técnicas y financieras del Instituto a fin de favorecer el respeto, promoción, protección y garantía de los derechos culturales de las personas que habitan y visitan la Ciudad de México, así como la defensa de los mismos a través de los mecanismos de exigibilidad y justiciabilidad previstos por la normatividad aplicable. El\nCongreso de la Ciudad de México garantizará, para cada año fiscal correspondiente, proveer los recursos necesarios para el cumplimiento del presente Decreto.\nPalacio Legislativo del Congreso de la Ciudad de México, a los dos días del mes de abril del año dos mil diecinueve.- POR LA MESA DIRECTIVA.- DIPUTADO JOSÉ DE JESÚS MARTÍN DEL CAMPO CASTAÑEDA,\nPRESIDENTE.- DIPUTADA ISABELA ROSALES HERRERA, SECRETARIA.- DIPUTADA ANA PATRICIA BAEZ\nGUERRERO, SECRETARIA.- (Firmas)\nCon fundamento en lo dispuesto por los artículos 122, Apartado A, fracción III, de la Constitución Política de los Estados Unidos Mexicanos; 32 apartado C, numeral 1, inciso a) de la Constitución Política de la\nCiudad de México; 3 fracciones XVII y XVIII, 7, 10 fracción II y 21, párrafo primero, de la Ley Orgánica del\nPoder Ejecutivo y de la Administración Pública de la Ciudad de México; para su debida publicación y observancia, expido el presente Decreto Promulgatorio en la Residencia Oficial de la Jefatura de Gobierno de la Ciudad de México, a los quince días del mes de abril del año dos mil diecinueve.- LA JEFA DE\nGOBIERNO DE LA CIUDAD DE MÉXICO, DRA. CLAUDIA SHEINBAUM PARDO.- FIRMA.- LA SECRETARIA DE\nGOBIERNO, ROSA ÍCELA RODRÍGUEZ VELÁZQUEZ.- FIRMA.- LA SECRETARIA DE ADMINISTRACIÓN Y\nFINANZAS, LUZ ELENA GONZÁLEZ ESCOBAR.- FIRMA.- EL SECRETARIO DE CULTURA.- JOSÉ ALFONSO SUÁREZ\nDEL REAL Y AGUILERA.- FIRMA.\nTRANSITORIOS DEL DECRETO POR EL QUE SE REFORMA LA FRACCIÓN IX DEL ARTÍCULO 3 DE LA LEY DE\nDERECHOS CULTURALES DE LOS HABITANTES Y VISITANTES DE LA CIUDAD DE MÉXICO, PUBLICADO EN LA\nGACETA OFICIAL DE LA CIUDAD DE MÉXICO EL 27 DE MARZO DE 2024.\nPrimero. Remítase a la persona titular de la Jefatura de Gobierno de la Ciudad de México, para su promulgación y publicación en la Gaceta Oficial de la Ciudad de México.\nSegundo. El presente Decreto entrará en vigor al día siguiente de su publicación en la Gaceta Oficial de la\nCiudad de México.\n\nPalacio Legislativo del Congreso de la Ciudad de México, a los veintisiete días del mes de febrero del año dos mil veinticuatro.- POR LA MESA DIRECTIVA.- DIPUTADA MARÍA GABRIELA SALIDO MAGOS, PRESIDENTA.-\nDIPUTADA MARCELA FUENTE CASTILLO, SECRETARIA.- DIPUTADA ANA JOCELYN VILLAGRÁN VILLASANA,\nSECRETARIA.- (Firmas)\nCon fundamento en lo dispuesto por los artículos 122, apartado A, base III, de la Constitución Política de los Estados Unidos Mexicanos; 32, apartado C, numeral 1, inciso a), de la Constitución Política de la Ciudad de México; 2, párrafo segundo, 3, fracciones XVII y XVIII, 7, párrafo primero, 10, fracción II, 12 y 21, párrafo primero, de la Ley Orgánica del Poder Ejecutivo y de la Administración Pública de la Ciudad de México;\npara su debida publicación y observancia, expido el presente Decreto Promulgatorio en la Residencia\nOficial de la Jefatura de Gobierno de la Ciudad de México, a los veintiséis días del mes de marzo del año dos mil veinticuatro.- EL JEFE DE GOBIERNO DE LA CIUDAD DE MÉXICO, DR. MARTÍ BATRES GUADARRAMA.-\nFIRMA.- EL SECRETARIO DE GOBIERNO, RICARDO RUIZ SUÁREZ.- FIRMA.- LA SECRETARIA DE CULTURA,\nCLAUDIA STELLA CURIEL DE ICAZA.- FIRMA.- EL SECRETARIO DE INCLUSIÓN Y BIENESTAR SOCIAL, JUAN\nGERARDO LÓPEZ HERNÁNDEZ.- FIRMA.- LA SECRETARIA DE LAS MUJERES, INGRID AURORA GÓMEZ\nSARACÍBAR.- FIRMA.",
  "ordenamiento": "Marco Jurídico",
  "jurisdiccion": "CIUDAD DE MEXICO",
  "fuente_oficial": "Congreso de la Ciudad de México",
  "status": "Vigente",
  "Fecha de Publicación": "26-06-2024",
  "Fecha de Última Reforma": "27 de marzo de 2024",
  "numero_paginas": 22,
  "es_escaneado": false,
  "tiene_tablas": false,
  "url": "https://www.congresocdmx.gob.mx/archivo-291885b2ea202aa22a81aba92f2bfebf8a09f96e.pdf",
  "materia": [
    "cultura",
    "derechos humanos"
  ]
}