{
  "titulo": "Ley DE CULTURA CÍVICA DE LA CIUDAD DE MÉXICO",
  "Contenido": "PUBLICADA EN LA GACETA OFICIAL DE LA CIUDAD DE MÉXICO\nEL 07 DE JUNIO DE 2019\nTEXTO VIGENTE\nÚLTIMA REFORMA PUBLICADA EN LA GOCDMX\nEL 01 DE MARZO DE 2023\nDECRETO POR EL QUE SE SE ABROGA LA LEY DE CULTURA CÍVICA DE LA CIUDAD DE MÉXICO Y SE EXPIDE LA\nLEY DE CULTURA CÍVICA DE LA CIUDAD DE MÉXICO.\nDRA. CLAUDIA SHEINBAUM PARDO, Jefa de Gobierno de la Ciudad de México, a sus habitantes sabed.\nQue el H. Congreso de la Ciudad de México I Legislatura, se ha servido dirigirme el siguiente:\nCONGRESO DE LA CIUDAD DE MÉXICO\nI LEGISLATURA\nEL CONGRESO DE LA CIUDAD DE MÉXICO, DECRETA:\nSE ABROGA LA LEY DE CULTURA CÍVICA DE LA CIUDAD DE MÉXICO Y SE EXPIDE LA LEY DE CULTURA CÍVICA\nDE LA CIUDAD DE MÉXICO.\nÚNICO. Se Abroga la Ley de Cultura Cívica de la Ciudad de México y se expide la Ley de Cultura Cívica de la\nCiudad de México, para quedar como sigue:\n\nTÍTULO PRIMERO\nDISPOSICIONES PRELIMINARES\nCAPÍTULO I\nDISPOSICIONES GENERALES\nArtículo 1.- La presente Ley es de orden público e interés social, regirá en la Ciudad de México y tiene por objeto:\na) Establecer reglas mínimas de comportamiento cívico;\nb) Garantizar la sana convivencia, el respeto a las personas, los bienes públicos y privados y regular el funcionamiento de la Administración Pública de la Ciudad de México en su preservación;\nc) Determinar las acciones para su cumplimento;\nd) Fomentar la cultura de la legalidad que fortalezca la convivencia armónica, la difusión del orden normativo de la ciudad, además del conocimiento de los derechos y obligaciones de la ciudadanía y de las personas servidoras públicas;\ne) La promoción de una cultura de la paz;\nf) Sentar las bases de organización y funcionamiento de la cultura cívica; y g) Establecer las acciones que deberán llevar a cabo las autoridades para que las personas que habitan en la Ciudad de México puedan dirimir sus conflictos a través de mecanismos consensados de justicia alternativa.\nArtículo 2.- Son valores fundamentales para la Cultura Cívica en la Ciudad de México, que favorecen la convivencia armónica de sus habitantes, los siguientes:\nI. La corresponsabilidad entre las personas habitantes y las autoridades en la conservación del medio ambiente, el entorno urbano, las vías, espacios y servicios públicos y la seguridad\n\nciudadana;\nII. La autorregulación sustentada en la capacidad de los habitantes de la Ciudad de México para asumir una actitud de respeto a la normatividad y exigir a los demás y a las autoridades su observancia y cumplimiento;\nIII. La prevalencia del diálogo, la conciliación y la mediación como medios de solución de conflictos y la utilización de Auxiliares para la gestión y solución de conflictos;\nIV. La imparcialidad de las Autoridades para resolver un conflicto\nV. El respeto por la diferencia y la diversidad de la población de la Ciudad de México;\nVI. El sentido de pertenencia a la comunidad y a la Ciudad de México;\nVII. La colaboración como una vertiente del mejoramiento del entorno y de la calidad de vida;\nVIII. La legalidad como un sistema normativo y una cultura de acciones orientadas al ejercicio, respeto y cumplimiento de la ley porpartede las personas ciudadanas y las personas servidoras públicas; y\nIX. La capacitación de los elementos de policía en materia de cultura cívica\nArtículo 3.- Para los efectos de esta Ley, se entenderá por:\nI. Alcaldía: Al Órgano Político Administrativo en cada Demarcación Territorial;\nII. Amonestación: La reconvención que la Persona Juez haga a la Persona Infractora.\nIII. Animales de compañía: A los seres sintientes reconocidos por la Constitución de la Ciudad de\nMéxico a quienes debe brindarse un trato digno;\nIV. Arresto: La sanción consistente en la privación de la libertad hasta por 36 horas y que deberá cumplirse en lugar distinto a los señalados a la detención de indiciados, procesados o sentenciados, separando los lugares de arresto para varones y mujeres;\n\nV. Auxiliares de los Juzgados: A las personas peritas, mediadoras comunitarias y defensoras de oficio;\nVI. Consejería: La Consejería Jurídica y de Servicios Legales de la Ciudad de México;\nVII. Consejo: Al Consejo de Justicia Cívica de l a Ciudad de México;\nVIII. Dirección: A la Dirección Ejecutiva de Justicia Cívica;\nIX. Elemento de Policía: A la persona que ejerce el cargo de Policía de la Ciudad de México;\nX. Gaceta: La Gaceta Oficial de la Ciudad de México;\nXI. Infracción: Al acto u omisión que sanciona la presente Ley;\nXII. Jefatura de Gobierno: Órgano de Gobierno Ejecutivo de la Ciudad de México.\nXIII. Juzgado: Al Juzgado Cívico;\nXIV. Ley: A la presente Ley;\nXV. Mediación comunitaria: La negociación asistida por una persona tercera imparcial, denominada Mediadora Comunitaria, en la que participen dos o más personas involucradas en una controversia de carácter comunitario cuando así lo determine la Persona Juzgadora, o las partes se sometan a la mediación;\nXVI. Medidas para mejorar la convivencia ciudadana: A las actividades de apoyo a la comunidad que busca contribuir a la atención de las causas subyacentes que originan las conductas conflictivas de las personas infractoras y la implementación de mecanismos alternativos de solución de controversias;\nXVII. Multa: La sanción económica que la Persona Juez impone a la Persona Infractora;\nXVIII. Persona Adolescente: La persona cuya edad se encuentra comprendida entre los doce años cumplidos y menos de dieciocho años;\n\nXIX. Persona con discapacidad: A toda persona que presente temporal o permanentemente una limitación, pérdida o disminución de sus facultades físicas, intelectuales o sensoriales, para realizar sus actividades connaturales;\nXX. Persona Defensora: A la persona abogada o licenciada en derecho que ejerza esa profesión de manera privada;\nXXI. Persona Defensora de Oficio: A la persona abogada o licenciada en derecho que preste sus servicios en el Instituto de la Defensoría Pública;\nXXII. Persona en situación de calle: A la persona menor o adulta, que carece de un lugar permanente para residir y se ve obligada a vivir en el espacio público;\nXXIII. Persona en situación de descuido: A la persona desatendida por su padre, madre o tutor, tratándose de menores de edad o incapaces, o personas mayores desatendidas por el responsable de su cuidado;\nXXIV. Persona Juzgadora: La Persona titular del Juzgado Cívico;\nXXV. Persona Médica: Al médico o médica legista; La persona\nXXVI. Persona Mediadora comunitaria: A la persona especialista que habiendo satisfecho los requisitos aplicables, se encuentra capacitado, certificado y registrado por el Tribunal Superior de Justicia de la Ciudad de México, para conducir el procedimiento de mediación comunitaria.\nLas Alcaldías tendrán entre sus personas servidoras públicas a mediadores comunitarios;\nXXVII. Persona Perita: Persona que por sus conocimientos y experiencia profesional trabaja coordinado por la Persona Juzgadora para dar opiniones en determinada materia;\nXXVIII. Persona Probable Infractor: A la persona a quien se atribuye la comisión de una infracción;\nXXIX. Persona Secretaria: A la Persona Secretaria del Juzgado Cívico;\nXXX. Persona Trabajadora Comunitaria: A la persona que cumple su sanción mediante trabajo a favor de la comunidad;\n\nXXXI. Registro de Personas Infractoras: Al Registro de Personas que han sido sancionadas la\nPersona Juzgadora;\nXXXII. Re-mediación: Procedimiento posterior a la mediación, que se utiliza cuando el convenio alcanzado en ésta se ha incumplido parcial o totalmente, o cuando surgen nuevas circunstancias que hacen necesario someter el asunto nuevamente a mediación;\nXXXIII. Secretaría: A la Secretaría de Seguridad Ciudadana de la Ciudad de México;\nXXXIV. Secretaría de Salud: A la Secretaría de Salud de la Ciudad de México;\nXXXV. Sistema Tecnológico: Al conjunto organizado de dispositivos electrónicos, programas de cómputo y en general todo aquello basado en tecnologías de la información para apoyar las tareas de movilidad y seguridad vial de conformidad con el Reglamento de Transito de la Ciudad de México;\nXXXVI. Trabajo en favor de la Comunidad: El número de horas que deberá servir la Persona\nInfractora a la comunidad en los programas preestablecidos al respecto, o el número de horas que deberá asistir a los cursos, terapias o talleres diseñados para corregir su comportamiento;\nXXXVII. Unidad de Medida: A la Unidad de Medida y Actualización de la Ciudad de México vigente.\nXXXVIII. Espacio Público: El espacio público es el conjunto de bienes de uso común destinados a la generación y fomento de la interacción social, o bien, que permitan el desarrollo de las personas.\nArtículo 4.- Para los efectos de esta Ley, son considerados como responsables las Personas Adolescentes, las personas mayores de dieciocho años de edad, así como las personas físicas o morales que hubiesen ordenado la realización de las conductas que importen la comisión de una infracción.\nArtículo 5.- Se comete infracción cuando la conducta tenga lugar en:\nI. Lugares o espacios públicos de uso común o libre tránsito, como plazas, calles, avenidas, viaductos, calzadas, vías terrestres de comunicación, paseos, jardines, parques o áreas verdes y deportivas;\n\nII. Inmuebles públicos o privados de acceso público, como mercados, templos, cementerios, centros de recreo, de reunión, deportivos, de espectáculos o cualquier otro análogo;\nIII. Inmuebles públicos destinados a la prestación de servicios públicos;\nIV. Inmuebles, espacios y vehículos destinados al servicio público de transporte;\nV. Inmuebles y muebles de propiedad particular, siempre que tengan efectos en la vía, espacios y servicios públicos o se ocasionen molestias a las personas, y\nVI. Lugares de uso común tales como plazas, áreas verdes, jardines, senderos, calles, avenidas interiores y áreas deportivas, de recreo o esparcimiento, que formen parte de los inmuebles sujetos al régimen de propiedad en condominio, conforme a lo dispuesto por la ley de la materia.\nArtículo 6.- La responsabilidad determinada conforme a esta Ley es autónoma de las consecuencias jurídicas que las conductas pudieran generar en otro ámbito.\nLa Persona Juzgadora hará de conocimiento de manera inmediata y por escrito a la Persona Ministerio\nPúblico cuando, de los hechos de que tenga conocimiento con motivo de sus funciones, pueda constituirse un delito, dejando constancia en el expediente de la comunicación en donde se establezca:\na) La persona quien recibe la comunicación;\nb) El cargo de la persona que la recibe y adscripción;\nc) La fecha y hora; y d) La relatoría de los hechos posiblemente constitutivos de delito.\nArtículo 7.- La aplicación de esta Ley corresponde a:\nI. La Jefatura de Gobierno;\nII. La Consejería;\n\nIII. La Secretaría;\nIV. La Secretaría de Salud;\nV. Las Alcaldías;\nVI. La Dirección, y\nVII. Los Juzgados.\nCAPÍTULO II\nATRIBUCIONES DE LAS AUTORIDADES\nArtículo 8.- Corresponde a la Jefatura de Gobierno:\nI. Aprobar el número, distribución y competencia territorial de los Juzgados Cívicos, facultad que podrá ser delegada a la persona titular de la Consejería, mediante acuerdo que se publique en la Gaceta, y\nII. Nombrar y remover previo proceso de acreditación de la comisión de delito o falta administrativa a las Personas Juzgadoras y Secretarias de los Juzgados Cívicos. Esta facultad podrá ser delegada en la persona titular de la Dirección, mediante acuerdo que se publique en la Gaceta.\nArtículo 9.- Corresponde a la Consejería:\nI. Establecer el número, distribución y competencia territorial de los Juzgados que deban funcionar en cada Alcaldía, previo acuerdo que se publique en la Gaceta;\nII. Proponer a la Jefatura de Gobierno los nombramientos, adscripción y remoción de las\nPersonas Juzgadoras y Secretarias;\nIII. Diseñar los procedimientos para la supervisión, control y evaluación periódicos del personal de los Juzgados y de los peritos;\n\nIV. Emitir los lineamientos para la condonación de las sanciones impuestas por las personas\nJuzgadoras;\nV. Supervisar el funcionamiento de los Juzgados y del área de peritos, de manera periódica y constante, a fin de que realicen sus funciones conforme a esta Ley y a las disposiciones legales aplicables;\nVI. Establecer los criterios de selección para los cargos de Personas Juzgadora y Secretaria, pudiendo dispensar el examen de ingreso en casos excepcionales;\nVII.Diseñar y desarrollar los contenidos del curso propedéutico correspondiente al nombramiento de Personas Juzgadoras y Secretarias e instrumentar mecanismos de actualización mediante convenios con instituciones académicas;\nVIII. Dotar a los Juzgados de personal eficaz y suficiente para el desempeño de sus labores, de acuerdo a la carga de trabajo;\nIX. Promover la difusión de la Cultura Cívica a través de campañas de información sobre sus objetivos y procedimientos, profundizando en el conocimiento y observancia de los derechos y obligaciones de las personas Ciudadanas y personas Servidoras Públicas en la materia.\nX. Proponer a la Jefatura de Gobierno normas y criterios para mejorar los recursos y funcionamiento de la Justicia Cívica;\nXI. Proponer convenios que contribuyan al mejoramiento de los servicios de los Juzgados, tanto en materia de profesionalización, como de coordinación con otras instancias públicas o privadas, de orden federal o local, en beneficio de toda persona que sea presentada ante el Juzgado;\nXII. Establecer acuerdos de colaboración para el mejor ejercicio de las atribuciones establecidas en el presente artículo;\nXIII. Conocer del recurso de inconformidad a que se refiere el artículo 84 de esta Ley;\nXIV. Autorizar los registros e instrumentos necesarios que llevarán los Juzgados, facultad que podrá delegar a la Dirección;\n\nXV. Integrar el Registro de Personas Infractoras;\nXVI. Establecer las equivalencias entre los arrestos y el tiempo de realización de las actividades de apoyo a la comunidad;\nXVII. Establecer, con la Secretaría, los mecanismos necesarios para el intercambio de información respecto de las remisiones de infractores, procedimientos iniciados y concluidos, sanciones aplicadas e integración del Registro de Personas Infractoras;\nXVIII. Contar con las personas peritas necesarios, en materia de tránsito terrestre, de valuación de bienes y demás que se requieran, para atender el procedimiento establecido en el Capítulo\nV, del Título Cuarto de esta Ley, quienes tendrán como principios rectores: la especialización, el profesionalismo y la imparcialidad;\nXIX. Ejercitar la facultad que le delegue la persona titular de la Jefatura de Gobierno mediante acuerdo publicado en la Gaceta para crear Juzgados especializados, y\nXX. Establecer juzgados itinerantes para lograr una eficaz y pronta administración de justicia.\nXXI. Las demás facultades que le confiera la Ley.\nArtículo 10.- A la Secretaría le corresponde la prevención de la comisión de infracciones, preservación de la seguridad ciudadana, del orden público y de la tranquilidad de las personas, y supervisar que los elementos de policía vigilen, custodien y trasladen durante todas las etapas del procedimiento a las personas probables infractoras y contará con las siguientes atribuciones:\nI. Detener y presentar inmediatamente y bajo su más estricta responsabilidad ante la Persona\nJuzgadora a las personas probables infractoras, en los términos del artículo 65 de esta Ley;\nII. Ejecutar las órdenes de presentación que se dicten con motivo del procedimiento que establece esta Ley;\nIII. Trasladar y custodiar con estricto respeto a los derechos humanos a las personas probables infractoras a los lugares destinados al cumplimiento de arrestos;\nIV. Supervisar y evaluar el desempeño de sus elementos en la aplicación de la presente Ley,\n\nconsiderando el intercambio de información con las autoridades correspondientes;\nV. Incluir en los programas de formación policial, la materia de Cultura Cívica;\nVI. Proveer a sus elementos de los recursos materiales necesarios para la aplicación de la Ley;\nVII. Registrar las detenciones y remisiones de Personas Probables Infractoras realizadas por las personas policías;\nVIII. Auxiliar a las Personas Juzgadora en el ejercicio de sus funciones;\nIX. Auxiliar, con estricto apego a los protocolos sobre la materia a las áreas de Inclusión y\nBienestar Social en el traslado de las personas que pernocten en la vía y espacios públicos, a las instituciones públicas y privadas de asistencia social, y\nX. Comisionar en cada uno de los turnos de los Juzgados, por lo menos a una persona policía.\nXI. Llevar a cabo el registro de infracciones al reglamento de tránsito de la Ciudad de México, a través de sistemas tecnológicos.\nArtículo 11.- Corresponde a la Secretaría de Salud: planear, dirigir, controlar y evaluar los servicios de medicina legal, de salud, de prevención y atención de las adicciones en apoyo a los Juzgados, en los términos establecidos en la Ley de Salud de la Ciudad de México.\nArtículo 12.- Corresponde a las personas titulares de las Alcaldías:\nI. Dotar de espacios físicos, de recursos materiales y financieros para la eficaz operación de los\nJuzgados, a través de mecanismos de colaboración con la Consejería;\nII. Conservar los Juzgados en óptimas condiciones de uso;\nIII. Promover la difusión de la Ley y la participación de las personas ciudadanas en el conocimiento, ejercicio, respeto y cumplimiento de sus derechos y obligaciones;\nIV. Impulsar y fomentar políticas públicas tendientes a la difusión de los valores y principios en materia de cultura cívica y de la legalidad;\n\nV. Dotar de espacios físicos, de recursos materiales y financieros para la eficaz operación de los servicios de mediación comunitaria; y\nVI. Proponer a la Consejería a las personas servidoras públicas de la Alcaldía que reúnan los requisitos a que se refiere el artículo 78 de la Ley, para que éstos sean canalizados al Tribunal\nSuperior de Justicia de la Ciudad de México, para que se formen como Personas Mediadoras\nComunitarias;\nVII. Realizar acciones que motiven el respeto, mantenimiento, promoción y fomento de actividades en los espacios públicos en coordinación con la ciudadanía; y\nVIII. Llevar a cabo actividades deportivas, artísticas y culturales en espacios públicos en coordinación con la ciudadanía.\nArtículo 13.- A la Dirección le corresponde:\nI. La ejecución de las normas internas de funcionamiento;\nII. En ejercicio de la facultad que en su caso le delegue la persona titular de la Jefatura de\nGobierno, nombrar, remover y adscribir a las Personas Juzgadoras y Secretarias;\nIII. La supervisión, control y evaluación de los Juzgados;\nIV. Conocer de la queja a que se refiere el artículo 135 de esta Ley.\nV. Condonar las sanciones impuestas por la Persona Juzgadora;\nVI. Rotar periódicamente a las Personas Juzgadoras y Secretarias, peritas y auxiliares según las necesidades del servicio;\nVII. Recibir para su guarda y destino correspondiente, los documentos y objetos que le remitan los Juzgados, y\nVIII. Las demás funciones que le confiera la Ley y otras disposiciones legales.\n\nTÍTULO SEGUNDO\nDE LA CULTURA CÍVICA Y DE LA PARTICIPACIÓN VECINAL\nCAPÍTULO I\nDE LA CULTURA CÍVICA\nArtículo 14.- Para la preservación del orden público, la Administración Pública de la Ciudad de México promoverá el desarrollo de una Cultura Cívica, sustentada en los principios de corresponsabilidad, legalidad, solidaridad, honestidad, equidad, tolerancia e identidad, con objeto de:\nI. Fomentar la participación activa de las personas habitantes en la preservación del orden público, por medio del conocimiento, ejercicio, respeto y cumplimiento de sus derechos y obligaciones; y\nII. Promover el derecho que toda persona, habitante tiene participar en el mejoramiento de su entorno social, procurando:\na) El respeto y preservación de su integridad física y psicológica, cualquiera que sea su condición socioeconómica, edad, sexo, religión, orientación o preferencia sexual o grupo étnico;\nb) El respeto al ejercicio de los derechos y libertades de todas las personas;\nc) El buen funcionamiento de los servicios públicos y aquellos privados de acceso público;\nd) La conservación del medio ambiente y de la salubridad general;\ne) El respeto, en beneficio colectivo, del uso y destino de los bienes del dominio público, y f) La protección, respeto, mantenimiento, promoción y fomento de actividades deportivas, culturales y expresiones artísticas en los espacios públicos destinados para tales fines.\nArtículo 15.- La Cultura Cívica en la Ciudad de México, que garantiza la convivencia armónica de sus personas habitantes, se sustenta en los siguientes deberes ciudadanos:\nI. Cumplir la Constitución Política de los Estados Unidos Mexicanos, la Constitución Política de la\nCiudad de México, las leyes, reglamentos y demás disposiciones que rigen en la Ciudad de\nMéxico;\n\nII. Ejercer los derechos y libertades protegidos en esta Ley y respetar los de los demás;\nIII. Brindar trato digno a las personas, respetando la diversidad que caracteriza a la comunidad;\nIV. Prestar apoyo a las demás personas habitantes, especialmente a las personas victimizadas o en situación vulnerable;\nV. Prevenir riesgos contra la integridad física de las personas;\nVI. Permitir la libertad de acción de las personas en las vías y espacios públicos;\nVII. Llamar y/o solicitar los servicios de emergencia únicamente cuando haya una causa que lo justifique;\nVIII. Requerir la presencia policiaca en caso de percatarse de la realización de conductas o de hechos violentos que puedan causar daño a personas o bienes de terceros o que afecten la convivencia armónica;\nIX. Conservar limpias las vías y espacios públicos; y participar en jornadas de limpieza y mantenimiento de los mismos;\nX. Hacer uso adecuado de los bienes, espacios y servicios públicos conforme a su naturaleza y destino; y a su vez fomentar la promoción de las diversas actividades que ahí se ofrezcan;\nXI. Cuidar el equipamiento y mobiliario urbano, así como los bienes de interés cultural, urbanístico y arquitectónico de la ciudad;\nXII. Contribuir a un ambiente adecuado para su desarrollo, salud y bienestar;\nXIII. Proteger y preservar la flora y fauna en áreas verdes, áreas de valor ambiental, áreas naturales protegidas y suelo de conservación de la Ciudad de México;\nXIV. Utilizar adecuadamente la estructura vial así como respetar la señalización vial;\nXV. Mantener en buen estado las construcciones propias, así como reparar las averías o daños de la vivienda o lugar de trabajo que pongan en peligro, perjudiquen o molesten a las personas;\n\nXVI. Prevenir que los animales de compañía causen daño o molestia a las personas;\nXVII. Cumplir las normas de seguridad y prevención contra incendios y demás en materia de protección civil relativas a la seguridad en los espacios públicos, establecimientos comerciales y lugares de acceso público;\nXVIII. Contribuir a generar un ambiente libre de contaminación auditiva que altere la tranquilidad o represente un posible riesgo a la salud de terceros, trátese de vivienda de interés social, popular o residencial;\nXIX. Ejercer sus derechos sin perturbar el orden y la tranquilidad pública, ni afectar la continuidad del desarrollo normal de las actividades de los demás habitantes;\nXX. Denunciar o dar aviso a las autoridades de la comisión de cualquiera infracción a las leyes, así como de cualquier actividad o hecho que cause daño a terceros o afecte la convivencia;\nXXI. Colaborar con las autoridades cuando éstas lo soliciten y en situaciones de emergencia;\nXXII. Permitir a las autoridades el ejercicio de las funciones previstas en esta Ley y en su caso, colaborar con las mismas o requerir su actuación, y\nXXIII. Participar en los asuntos de interés de su colonia, barrio y Alcaldía principalmente en aquellos dirigidos a procurar la seguridad ciudadana; así como en la solución de los problemas comunitarios.\nArtículo 16.- En materia de Cultura Cívica, a la Administración Pública de la Ciudad de México le corresponde:\nI. Diseñar y promover los programas necesarios para la plena promoción, difusión, conocimiento y desarrollo de la Cultura Cívica democrática, así como para el fomento de la educación cívica en la comunidad;\nII. Promover programas permanentes para el fortalecimiento de la conciencia cívica a través de los medios de comunicación masiva así como la plena difusión de los principios y valores de la legalidad;\n\nIII. Promover la incorporación de contenidos cívicos y de la cultura de la legalidad en los diversos ciclos educativos, especialmente en el nivel básico, dando mayor atención a las conductas y a la prevención de las infracciones previstas en esta Ley, apoyándose con programas publicitarios dirigidos especialmente a la niñez;\nIV. Implementar e impulsar a través de todas las áreas de la Administración Pública local las políticas públicas, programas y líneas de acción sobre los valores y principios de la cultura cívica y el pleno conocimiento de los derechos y obligaciones de las personas ciudadanas y personas servidoras públicas;\nV. Promover los valores de la cultura cívica a través de campañas de información en los medios de comunicación masiva puntualizando sus objetivos y alcances;\nVI. Promover los métodos alternativos de solución de controversias con la intervención de mediadores comunitarios de las Alcaldías; y\nVII. Preservar y difundir el patrimonio cultural de la Ciudad de México.\nArtículo 17.- En el caso de las expresiones artísticas o culturales, éstas deberán estar debidamente registradas ante la autoridad competente y tener el permiso correspondiente para el uso del espacio público.\nCAPÍTULO II\nDE LA PARTICIPACIÓN VECINAL\nArtículo 18.- A la Administración Pública de la Ciudad de México le corresponde diseñar y promover programas vecinales que impliquen la participación de las personas habitantes en colaboración con las autoridades competentes para la preservación y conservación del orden público, los cuales tenderán a:\nI. Procurar el acercamiento entre las Personas Juzgadoras y la comunidad de la circunscripción territorial que les corresponda, a fin de propiciar una mayor comprensión y participación en las funciones que desarrollan;\nII. Establecer vínculos permanentes con los grupos organizados y las personas habitantes en\n\ngeneral, para la identificación de los problemas y fenómenos sociales que las aquejan, relacionados con esta Ley;\nIII. Organizar la participación vecinal para la prevención de infracciones;\nIV. Promover, en el ámbito de su competencia, la difusión de los valores y alcances de la cultura cívica y de la legalidad así como de campañas de información y cursos formativos entre los órganos de representación ciudadana, y\nV. Promover el uso de la mediación comunitaria en la gestión para la solución y prevención de conflictos comunitarios.\nArtículo 19.- Las Alcaldías deberán organizar conjuntamente con los órganos de representación ciudadana, organizaciones de la sociedad civil y/o instituciones educativas, por lo menos en forma trimestral:\nI. Jornadas de limpieza, mantenimiento y conservación de espacios públicos, en las que se incentive la participación ciudadana.\nII. Talleres, exposiciones, muestras culturales, artísticas y/o deportivas en espacios públicos.\nArtículo 20.- Las Personas Juzgadoras participarán activamente en los Comités por Alcaldía de Seguridad\nPública, así como en los programas de Seguridad Pública que promueva la Administración Pública de la\nCiudad de México, en los términos que determine la Consejería.\nArtículo 21.- Las Personas Juzgadoras celebrarán reuniones periódicas con los miembros de los órganos de representación ciudadana de la circunscripción territorial que les corresponda, con el propósito de informar lo relacionado con el desempeño de sus funciones, así como para conocer y atender la problemática que específicamente aqueja a las personas habitantes de esa comunidad, brindando alternativas de solución en los términos de esta Ley.\nLas reuniones se realizarán en lugares de acceso público y se podrá invitar a Personas Diputadas del\nCongreso de la Ciudad de México. De cada reunión, se elaborará una memoria que será remitida a la\nConsejería.\nArtículo 22.- La Dirección, integrará mediante convocatoria pública el cuerpo de Personas Colaboradoras\nComunitarias que voluntaria y gratuitamente brinden apoyo en las funciones de supervisión de los\n\njuzgados.\nLas Personas Colaboradoras Comunitarias serán acreditados por la Consejería ante las instancias correspondientes; siempre que hayan cubierto los requisitos que dicte la misma.\nArtículo 23.- Corresponde a las Personas Colaboradoras Comunitarias realizar visitas a las diversas áreas de los Juzgados, sin entorpecer o intervenir en las funciones del personal, con el objeto de detectar necesidades e irregularidades para hacerlo del conocimiento de la Consejería y de los órganos e instancias que ésta determine.\nArtículo 24.- Las Personas Juzgadoras y Secretarias, otorgarán las facilidades necesarias para que las\nPersonas Colaboradoras Comunitarias debidamente acreditados realicen sus visitas, proporcionándoles acceso a las diversas áreas así como la información que requieran, siempre que sea procedente de acuerdo a la normatividad vigente y a la Ley de Transparencia, Acceso a la Información Pública y Rendición de\nCuentas de la Ciudad de México.\nArtículo 25.- Las Personas Juzgadoras y Secretarias, conforme a los ordenamientos jurídicos aplicables, garantizarán el derecho de expresión de los grupos artísticos o culturales que estén debidamente acreditados ante la autoridad competente.\nTÍTULO TERCERO\nINFRACCIONES, SANCIONES Y DEL TRABAJO A FAVOR DE LA\nCOMUNIDAD\nCAPÍTULO I\nDE LAS INFRACCIONES\nArtículo 26.- Son infracciones contra la dignidad de las personas:\nI. Vejar, intimidar o maltratar física o verbalmente a cualquier persona o grupo de personas.\nEn este caso, sólo procederá la conciliación cuando las partes de común acuerdo fijen el monto del daño y el probable infractor repare el daño;\n\nII. Coaccionar de cualquier manera a otra persona para realizar alguna conducta que atente contra su voluntad, su libre autodeterminación o represente un trato degradante;\nIII. Coartar o atentar contra la privacidad de una persona. En este caso solo procederá la conciliación cuando el probable infractor repare el daño; las partes de común acuerdo fijarán el monto del daño.\nIV. Permitir a menores de edad el acceso a lugares a los que expresamente les esté prohibido, así como promover o permitir que estos realicen sobre vías de circulación vehicular, cualquier actividad por la que se pretenda obtener un ingreso económico;\nV. Propinar a una persona, en forma intencional y fuera de riña, golpes que no le causen lesión;\nVI.Lesionar a una persona siempre y cuando las lesiones que se causen de acuerdo con el dictamen médico tarden en sanar menos de quince días.\nEn este caso solo procederá la conciliación cuando el probable infractor repare el daño; las partes de común acuerdo fijarán el monto del daño.\nVII. Al propietario, poseedor o encargado de un animal que cause lesiones a una persona, que tarden en sanar menos de quince días.\nEn este caso solo procederá la conciliación cuando el probable infractor repare el daño; las partes de común acuerdo fijarán el monto del daño;\nVIII. Condicionar, insultar o intimidar a la mujer, que alimente a una niña o a un niño a través de la lactancia, en las vías y espacios públicos;\nIX. Proferir silbidos o expresiones verbales de connotación sexual a una persona con el propósito de afectar su dignidad; y\nX. Realizar la exhibición de órganos sexuales con la intención de molestar o agredir a otra persona. Sólo procederá la presentación de la persona probable infractora cuando exista queja de la persona agredida o molestada.\n\nXI. Vejar, intimidar, maltratar físicamente o incitar a la violencia contra un integrante de las instituciones de Seguridad Ciudadana.\nReforma publicada en la GOCDMX el 15 de junio de 2022\nArtículo 27.- Son infracciones contra la tranquilidad de las personas:\nI. Prestar algún servicio sin que le sea solicitado y coaccionar de cualquier manera a quien lo reciba para obtener un pago por el mismo. La presentación del infractor sólo procederá por queja previa;\nII. Poseer animales sin adoptar las medidas de higiene necesarias que impidan malos olores o la presencia de plagas que ocasionen cualquier molestia a los vecinos;\nIII. Producir o causar ruidos por cualquier medio que notoriamente atenten contra la tranquilidad o represente un posible riesgo a la salud;\nIV. Impedir el uso de los bienes del dominio público de uso común;\nV. Obstruir con cualquier objeto entradas o salidas de inmuebles sin autorización del propietario o poseedor del mismo;\nVI. Incitar o provocar reñir a una o más personas;\nVII. Ocupar los accesos de oficinas públicas o sus inmediaciones ofreciendo la realización de trámites que en la misma se proporcionen, sin tener autorización para ello.\nArtículo 28.- Son infracciones contra la seguridad ciudadana:\nI. Permitir a la persona propietaria o poseedora de un animal que este transite libremente o transitar con él sin adoptar las medidas de seguridad necesarias, de acuerdo con las características particulares del animal, para prevenir posibles ataques a otras personas o animales, así como azuzarlo o no contenerlo;\nII. Impedir o estorbar de cualquier forma el uso de la vía y el espacio público, la libertad de tránsito o de acción de las personas, siempre que no exista permiso ni causa justificada para ello, para estos efectos, se entenderá que existe causa justificada siempre que la obstrucción del uso\n\nde la vía pública, de la libertad de tránsito o de acción de las personas sea inevitable y necesaria y no constituya en sí misma un fin, sino un medio razonable de manifestación de las ideas, de expresión artística o cultural de asociación o de reunión pacífica;\nIII. Derogado;\nIV. Apagar, sin autorización el alumbrado público o afectar algún elemento del mismo que impida su normal funcionamiento;\nV. Ingerir bebidas alcohólicas en lugares públicos no autorizados o consumir, ingerir, inhalar o aspirar estupefacientes, psicotrópicos, enervantes o sustancias tóxicas en lugares públicos, independientemente de los delitos en que se incurra por la posesión de los estupefacientes, psicotrópicos, enervantes o sustancias toxicas;\nVI. Portar, transportar o usar, sin precaución objetos o sustancias que por su naturaleza sean peligrosas y sin observar, en su caso las disposiciones legales aplicables;\nVII. Detonar o encender cohetes, juegos pirotécnicos, fogatas o elevar aeróstatos sin permiso de la autoridad competente;\nVIII. Reñir con una o más personas;\nIX. Llamar o solicitar los servicios de emergencia con fines ociosos que distraigan la prestación de los mismos, que constituyan falsas alarmas de siniestros o que puedan producir o produzcan temor o pánico colectivos, la sanción correspondiente se aplicará al titular o poseedor de la línea telefónica desde la que se haya realizado la llamada; en caso de reincidencia se duplicará la sanción;\nX. Alterar el orden, arrojar líquidos u objetos, prender fuego o provocar altercados en los eventos o espectáculos públicos o en sus entradas o salidas;\nXI. Ofrecer o propiciar la venta de boletos de espectáculos públicos, con precios superiores a los autorizados;\nXII. Trepar bardas, enrejados o cualquier elemento constructivo semejante, para observar el interior de un inmueble ajeno;\n\nXIII. Abstenerse, la persona propietaria de bardar un inmueble sin construcción o no darle el cuidado necesario para mantenerlo libre de plagas o maleza, que puedan ser dañinas para los colindantes;\nXIV. Percutir armas de postas, diábolos, dardos o municiones contra personas o animales;\nXV. Participar de cualquier manera, organizar o inducir a otros a realizar competencias vehiculares de velocidad en vías públicas;\nXVI. Organizar o participar de cualquier manera en peleas de animales, de cualquier forma; y\nXVII. Causar daño a un bien mueble o inmueble ajeno, en forma culposa y con motivo del tránsito de vehículos.\nObra culposamente la persona que produce el daño, que no previó siendo previsible o previó confiado en que no se produciría, en virtud de la violación de un deber de cuidado que objetivamente era necesario observar.\nSi con los elementos de prueba ofrecidos por las partes a la Persona Juzgadora no es posible determinar quién es el responsable del daño causado, no se aplicará multa alguna y en el caso de vehículos estos se devolverán, quedando a salvo los derechos de las partes para hacerlos valer por la vía procedente.\nXVIII. Cometer las personas conductoras de vehículos motorizados, ya sea por acción u omisión, infracciones en materia de tránsito que atenten contra la seguridad vial de las personas, que sean captados por los sistemas tecnológicos de la Ciudad de México encargados de detectar dichas conductas; y\nXIX. Llevar los conductores del servicio de transporte público al interior del vehículo, a personas que los acompañen y que no sean usuarios, que los auxilien en el cobro del pasaje o a invitar a subirse a los usuarios o a distribuirse en la unidad, que obstaculicen el paso a los usuarios.\nArtículo. 29.- Son infracciones contra el entorno urbano de la Ciudad:\n\nI. Abstenerse de recoger del espacio público, las heces de un animal su propiedad o bajo su custodia, así como tirar o abandonar dichos desechos fuera de los contenedores;\nII. Orinar o defecar en los lugares a que se refiere el artículo 5 de esta Ley;\nIII. Arrojar, tirar o abandonar en el espacio público animales muertos, desechos, objetos o sustancias;\nIV. Tirar basura en lugares no autorizados;\nV. Dañar, pintar, maltratar, ensuciar o hacer uso indebido de las fachadas de inmuebles públicos o de particulares, sin autorización de éstos, estatuas, monumentos, postes, arbotantes, semáforos, parquímetros, buzones, tomas de agua, señalizaciones viales o de obras, puentes, pasos peatonales, plazas, parques, jardines, elementos de ornato u otros bienes semejantes; el daño a que se refiere esta fracción será competencia de la Persona Juzgadora hasta el valor de\n20 veces la Unidad de Medida.\nPara el caso de daños a bienes muebles o inmuebles, estatuas o monumentos con valor histórico catalogados por el INAH o el INBA, se aplicarán las sanciones estipuladas en la Ley Federal en la materia;\nVI. Cambiar de cualquier forma, el uso o destino del espacio público, sin la autorización correspondiente;\nVII. Abandonar muebles en áreas o vías públicas;\nVIII. Desperdiciar el agua o impedir su uso a quienes deban tener acceso a ella en tuberías, tanques o tinacos almacenadores, así como utilizar indebidamente los hidrantes públicos, obstruirlos o impedir su uso;\nIX. Colocar en el espacio público enseres o cualquier elemento propio de cualquier establecimiento mercantil, sin la autorización correspondiente;\nX. Arrojar en el espacio público desechos, sustancias peligrosas para la salud de las personas o que despidan olores desagradables;\n\nXI. Ingresar a zonas señaladas como de acceso restringido en los lugares o inmuebles destinados a servicios públicos, sin la autorización correspondiente o fuera de los horarios establecidos;\nXII. Cubrir, borrar, pintar, alterar o desprender los letreros, señales, números o letras que identifiquen vías, inmuebles y espacios públicos;\nXIII. Pintar, adherir, colgar o fijar anuncios o cualquier tipo de propaganda en elementos del equipamiento urbano, del mobiliario urbano, de ornato o árboles, sin autorización para ello;\nXIV. Colocar transitoriamente o fijar en el espacio público, sin autorización para ello, elementos destinados a la venta de productos o prestación de servicios;\nXV. Obstruir o permitir la obstrucción del espacio público con motivo de la instalación, modificación, cambio o mantenimiento de los elementos constitutivos de un anuncio y no exhibir la documentación correspondiente que autorice a realizar dichos trabajos; y\nXVI. Abandonar en la vía pública a un animal de compañía, esta conducta, además de sancionarse en los términos de la presente Ley, será notificada de oficio a la Procuraduría\nAmbiental y del Ordenamiento Territorial, antes de dictarse la sanción administrativa correspondiente.\nReforma publicada en la GOCDMX el 01 de marzo de 2023\nCAPÍTULO II\nDE LAS SANCIONES\nArticulo. 30.- Las sanciones aplicables a las infracciones cívicas son:\nI. Amonestación;\nII. Multa;\nIII. Arresto; y\nIV. Trabajo en favor de la comunidad.\n\nSi la persona infractora fuese jornalera, obrera o trabajadora, no podrá ser sancionada con multa mayor del importe de su jornal o salario de un día.\nTratándose de personas trabajadoras no asalariadas, la multa no excederá del equivalente a un día de su ingreso.\nArtículo 31.- Para efectos de esta Ley las infracciones se clasifican y sancionan de la siguiente manera:\nInfracciones tipo A, se sancionarán con una multa por el equivalente de 1 a 10 veces la Unidad de Medida o arresto de 6 a 12 horas o trabajo en favor de la comunidad de 3 a 6 horas;\nInfracciones tipo B, se sancionarán con multa equivalente de 11 a 40 Unidades de Medida, o arresto de 13 a 24 horas o trabajo en favor de la comunidad de 6 a 12 horas.\nInfracciones tipo C, se sancionarán con una multa equivalente de 21 a 30 Unidades de Medida, o arresto de 25 a 36 horas o trabajo comunitario de 12 a 18 horas;\nInfracciones tipo D, se sancionarán con arresto de 20 a 36 horas o de 10 a 18 horas de trabajo en favor de la comunidad;\nLa Persona Juzgadora, dependiendo de la gravedad de la infracción podrá imponer como sanción la amonestación, cuando en el registro del juzgado no existan antecedentes de la Persona Infractora.\nInfracciones tipo E, se sancionarán de 20 y hasta 36 horas, inconmutables de trabajo en favor de la comunidad;\nArtículo 32.- Para efectos del artículo anterior las infracciones se clasificarán de acuerdo al siguiente cuadro:\nArtículo Fracción Clase\nI. A\nII, V, IX y X B\n\nIII, IV, VI, VII y VIII D\nXI E\nI y II A\n\nIII, IV, V, y VI B\n\nVII D\nB\nI, II, III y IV\nC\n28 V, VI, VII, VIII, X, XII, XIII, XIV y XIX\nXI, XV, XVI, XVII y IX\nD\nI, II, III, IV, V, VI y VII B\n29 VIII y XV D\nIX, X, XI, XII, XIII y XIV C\nReforma publicada en la GOCDMX el 01 de marzo de 2023\nArtículo 33.- Sin perjuicio de la obligación de reparar el daño causado que determine la autoridad civil competente, la persona que sea declarada responsable de la conducta prevista en la fracción XVII, del artículo 28 y se negare a repáralo, será sancionado como infracción tipo D, o bien por multa cuya cuantificación deberá estar relacionada con el monto del daño, de la siguiente manera:\na) Multa por el equivalente de 50 a 110 veces la Unidad de Medida, cuando el monto del daño causado no exceda de 110 veces la Unidad de Medida;\nb) Multa por el equivalente de 111 a 235 veces la Unidad de Medida, cuando el monto del daño causado exceda 110, pero no de 235 veces la Unidad de Medida;\nc) Multa por el equivalente de 236 a 470 veces la Unidad de Medida, cuando el monto del daño causado exceda de 235, pero no de 470 veces la Unidad de Medida;\nd) Multa por el equivalente de 470 a 820 veces la Unidad de Medida, cuando el monto del daño causado exceda de 470, pero no de 820 veces la Unidad de Medida;\ne) Multa por el equivalente de 821 a 1410 veces la Unidad de Medida, cuando el monto de daño causado exceda 821, pero no de 1410 veces la Unidad de Medida;\nf) Multa por el equivalente de 1411 a 2115 veces la Unidad de medida, cuando el monto del daño causado exceda de 1411, pero no de 2115 veces la Unidad de Medida;\n\ng) Multa por el equivalente de 2116 veces la Unidad de Medida y hasta por el monto total del valor comercial del vehículo, cuando el monto del daño causado exceda de 2116 veces la Unidad de Medida.\nSólo se conmutará el arresto, si además de los requisitos que señala la Ley, cuando la persona conductora responsable acredite su domicilio, señale domicilio en la Ciudad de México para oír y recibir notificaciones y mencione en su caso, el domicilio del la persona propietaria del vehículo.\nArtículo. 34.- Las sanciones por infracciones en materia de tránsito establecidas en la fracción XVIII del artículo 28 de esta Ley, serán a través de multa, amonestaciones, cursos en línea, sensibilización presencial, cursos, talleres, trabajos a favor de la comunidad, remisión de vehículos a depósito y puntos de penalización a la licencia, en términos de lo dispuesto por el Reglamento de Tránsito de la Ciudad de\nMéxico.\nEn lo que respecta a los instrumentos tecnológicos de medición que sean utilizados para el levantamiento de infracciones, estos deberán de ser calibrados conforme a las especificaciones del fabricante, y debidamente certificados en los términos de la Ley Federal sobre Metrología y Normalización por un ente certificador acreditado ante la entidad Mexicana de Acreditación, o bien por el Centro Nacional de\nMetrología.\nLas personas serán responsables solidarias de las infracciones en materia de tránsito que sean cometidas en los vehículos de su propiedad, conforme a lo dispuesto en el artículo 1913 del Código Civil de la Ciudad de México.\nAl imponerse las sanciones por infracciones en materia de tránsito a personas adultas mayores, personas con discapacidad o mujeres con embarazo, deberán considerarse sus condiciones físicas y cognitivas.\nArtículo 35.- Las infracciones establecidas en las fracciones V, VI, XII y XIII del artículo 29 de la Ley, la Persona\nJuzgadora considerará al imponer la sanción la reparación de los daños causados por la persona infractora como mínimo, así como alguna otra actividad de apoyo a la comunidad de las previstas en esta Ley, conmutando de esa forma el arresto.\nArtículo 36.- Cuando una infracción se ejecute con la participación de dos o más personas, a cada una se le aplicará la sanción máxima que para esa infracción señala esta Ley.\n\nCuando la persona molestada u ofendida sea menor de edad, mujer lactante, persona adulta mayor, persona con discapacidad o personas pertenecientes a las poblaciones callejeras, se aumentará la sanción hasta en una mitad, sin exceder el máximo constitucional y legal establecido, para el caso de la multa.\nArtículo 37.- Cuando con una sola conducta se cometan varias infracciones, la Persona Juzgadora impondrá la sanción máxima aplicable, pudiendo aumentarse hasta en una mitad más sin que pueda exceder de 36 horas.\nCuando en diversas conductas se cometan varias infracciones, la Persona Juzgadora impondrá la sanción de la que merezca la mayor, pudiendo aumentarse con las sanciones que esta Ley señala para cada una de las infracciones restantes, siempre que tal acumulación no exceda el máximo establecido para el arresto.\nArtículo 38.- Cuando las conductas sancionadas por esta Ley sean cometidas en cumplimiento de órdenes emitidas por aquellos de quienes se tenga dependencia laboral o económica, la Persona Juzgadora impondrá la sanción correspondiente y girará el citatorio respectivo a quien hubiese emitido la orden.\nTratándose de personas morales, se requerirá la presencia del representante legal y en este caso sólo podrá imponerse como sanción la multa.\nArtículo 39.- En todos los casos y para efecto de la individualización de la sanción, la Persona Juzgadora considerará como agravante el estado de ebriedad del infractor o su intoxicación por el consumo de estupefacientes, psicotrópicos o sustancias toxicas al momento de la comisión de la infracción; pudiéndose aumentar la sanción hasta en una mitad, sin exceder el máximo establecido para el caso del arresto.\nArtículo 40.- Se entiende por reincidencia, la comisión de infracciones contenidas en la presente Ley y por dos o más veces, en un período que no exceda de seis meses, en este caso, la persona infractora no podrá gozar del beneficio de conmutar el arresto por multa. Para la determinación de la reincidencia, la Persona\nJuzgadora deberá consultar el registro de personas infractoras.\nCAPÍTULO III\nDEL TRABAJO EN FAVOR DE LA COMUNIDAD\nArtículo 41.- Cuando la Persona Infractora acredite de manera fehaciente su identidad y domicilio, podrá solicitar a la Persona Juzgadora le sea permitido realizar trabajo en favor de la comunidad a efecto de no cubrir el arresto que se le hubiese impuesto.\n\nEl trabajo en favor de la comunidad se desarrollará por un lapso equivalente a la mitad de las horas de arresto que correspondan a la infracción que se hubiere cometido. En ningún caso podrá realizarse dentro de la jornada laboral de la persona infractora.\nEn cuanto al cumplimiento de los trabajos a favor de la comunidad por las infracciones cometidas al\nReglamento de Tránsito de la Ciudad de México, se seguirán los lineamientos que para ello emita la\nConsejería.\nArtículo 42.- La Persona Juzgadora, valorando las circunstancias personales del infractor, podrá acordar la suspensión de la sanción impuesta y señalar los días, horas y lugares en que se llevarán a cabo el trabajo en favor a la comunidad y, sólo hasta la ejecución de las mismas cancelará la sanción de que se trate.\nLa Administración Pública de la Ciudad de México y las Alcaldías enviarán a la Consejería propuestas de trabajo en favor de la comunidad para que sean cumplidas por las personas infractoras, siguiendo los lineamientos y equivalencias de tiempo que ella misma determine.\nEn todos los casos, la Persona Juzgadora hará del conocimiento de la Persona Infractora la prerrogativa a que se refiere este artículo.\nArtículo 43.- Para los efectos de esta ley, se entiende por trabajo en favor de la comunidad la prestación de servicios voluntarios y honoríficos de orientación, limpieza, conservación, restauración u ornato, en lugares localizados en la circunscripción territorial en que se hubiere cometido la infracción.\nArtículo 44.- Se considera trabajo en favor de la comunidad:\nI. Limpieza, pintura o restauración de centros públicos educativos, de salud o de servicios;\nII. Limpieza, pintura o restauración de los bienes dañados por la persona infractora o semejantes a los mismos;\nIII. Realización de obras de ornato en lugares de uso común;\nIV. Realización de obras de balizamiento, limpia o reforestación en lugares de uso común;\nV. Impartición de pláticas a vecinos o educandos, relacionadas con la convivencia ciudadana o realización de actividades relacionadas con la profesión, oficio u ocupación de la Persona\n\nInfractora;\nVI. Participar en talleres, exposiciones, muestras culturales, artísticas y/o deportivas en espacios públicos que determine la Consejería.\nVII. Asistir a los cursos, terapias, talleres diseñados para corregir su comportamiento, en materias como autoestima, escuela para padres, relación de pareja, cultura de la paz, prevención de las adicciones, prevención de la violencia familiar, equidad de género, cultura vial, y los que determine la Consejería.\nDichas actividades podrán realizarse en las dependencias de la administración pública o en las instituciones educativas, sociales o privadas que determine la Consejería; y\nVIII. Las demás que determine la Consejería.\nArtículo 45.- El trabajo en favor de la comunidad se llevarán a cabo bajo la supervisión de personal de la\nDirección para el caso de las actividades que se desarrollen en las áreas centrales y de la Alcaldía en caso de que las actividades se realicen en la misma, atendiendo a los lineamientos que determine la Consejería.\nLos titulares de las áreas de la Administración Pública de la Ciudad de México y las Personas Titulares de las Alcaldías, proporcionarán los elementos necesarios para la ejecución de las actividades de apoyo a la comunidad y mensualmente harán del conocimiento de la Consejería los lugares, horarios y actividades que podrán realizarse en términos de este capítulo.\nArtículo 46.- En el supuesto de que la persona infractora no realice el trabajo en favor de la comunidad, la\nPersona Juzgadora emitirá la orden de presentación a efecto de que la sanción impuesta sea ejecutada de inmediato.\nTÍTULO CUARTO\nPROCEDIMIENTOS\nCAPÍTULO I\nDISPOSICIONES COMUNES\nArtículo.47.- Las personas probables infractores tienen derecho a:\n\nI. Que se le informe en todo momento, los hechos que se le atribuyen y los derechos que le asisten; le sean leídos los derechos contemplados por el artículo 20 de la Constitución Política de los Estados Unidos Mexicanos y la Constitución Política de la Ciudad de México;\nII. Que se reconozca su derecho a la presunción de inocencia;\nIII. Recibir trato digno;\nIV. Recibir alimentación, agua, asistencia médica y cualesquiera otras atenciones de urgencia durante el cumplimiento o ejecución de su arresto;\nV. Solicitar la conmutación de la pena por trabajo en favor de la comunidad en los casos que proceda;\nVI. Contar con un defensor de su confianza;\nVII. Ser oído en audiencia pública por la Persona Juzgadora;\nVIII. Hacer del conocimiento de un familiar o persona que desee, los motivos de su detención y el lugar en que se hallará bajo custodia en todo momento;\nIX. Recurrir las sanciones impuestas por la Persona Juzgadora, en los términos de esta Ley;\nX. Cumplir su arresto en espacios dignos;\nXI. No recibir sanciones que excedan lo dispuesto en la Constitución Política de los Estados\nUnidos Mexicanos;\nXII. Solicitar la conmutación del arresto por la multa correspondiente en términos de esta Ley; y\nXIII. Las demás que señalen las disposiciones aplicables.\nArtículo 48. El procedimiento será oral y público y se sustanciará en una sola audiencia.\nLos procedimientos que se realicen ante los juzgados, se iniciarán con la presentación de la persona\n\nprobable infractora, por la persona policía, con la queja de particulares por la probable comisión de infracciones, por la remisión o a solicitud de otras autoridades que pongan en conocimiento a la Persona\nJuzgadora hechos presuntamente considerados infracciones a esta Ley y demás ordenamientos aplicables, en caso de ser competente, así lo acordará y continuará con el procedimiento.\nAsimismo se conocerá de los procedimientos de hechos de tránsito causados por bache, para el reclamo del pago de daños ante la instancia correspondiente.\nLas resoluciones administrativas que impongan alguna sanción por violaciones a la presente Ley, podrán ser impugnadas mediante el recurso de revisión, que se tramitará ante la Consejería, juicio de nulidad administrativa o juicio de amparo.\nArtículo 49.- El procedimiento por daños causados por bache deberá contener:\na) Acuerdo de inicio;\nb) Fijación de competencia;\nc) Radicación;\nd) Declaración del afectado;\ne) Admisión y desahogo de pruebas;\nf) Intervención de peritos de la Consejería;\ng) Emisión del Dictamen;\nh) Acuerdo que pone fin al procedimiento.\nArtículo 50.- El Código Nacional de Procedimiento Penales será de aplicación supletoria a las disposiciones de este título.\nCuando en los procedimientos que establece esta Ley obren pruebas obtenidas por la Secretaría con equipos y sistemas tecnológicos, las mismas se apreciarán y valorarán en términos de la Ley que regula el uso de tecnología para la Seguridad Pública de la Ciudad de México.\n\nArtículo 51.- Las actuaciones deberán constar por escrito o por sistema informático y permanecerán en el local del Juzgado hasta que la Consejería determine su envío al archivo general para su resguardo.\nArtículo 52.- Cuando la persona probable infractora no hable español, o se trate de una persona con discapacidad para comunicarse y no cuente con persona traductora o intérprete, se le proporcionará una, sin cuya presencia el procedimiento administrativo no podrá dar inicio.\nArtículo 53.- En caso de que la persona probable infractora sea una Persona Adolescente, la persona juzgadora citará a quien detente la custodia o tutela, legal o de hecho, en cuya presencia se desarrollará la audiencia y se dictará la resolución.\nEn tanto acude quien custodia o tutela a la Persona Adolescente, ésta deberá permanecer en la oficina del\nJuzgado, en la sección de personas adolescentes. Si por cualquier causa no asistiera el responsable de la persona adolescente hasta por un plazo de dos horas, la Persona Juzgadora le nombrará a una persona representante del Sistema para el Desarrollo Integral de la Familia, a través de la Procuraduría de\nProtección de Niñas, Niños y Adolescentes de la Ciudad de México o a una persona Defensora de Oficio, la cual deberá ser profesional en derecho, para que lo asista y defienda y con ello determine la responsabilidad del infractor.\nReforma publicada en la GOCDMX el 12 de diciembre de 2022\nLa atención y asistencia del representante sustituto o coadyuvante, deberá ser inmediata a su designación, para lo cual la Persona Juzgadora deberá establecer las medidas necesarias de coordinación para este propósito.\nReforma publicada en la GOCDMX el 12 de diciembre de 2022\nCualquier persona que ostente la representación, no podrá deslindarse de las obligaciones que aquí se imponen, cualquier inasistencia, deberá ser justificada de forma pormenorizada y por escrito, señalando la imposibilidad para haber designado un representante sustituto o coadyuvante.\nReforma publicada en la GOCDMX el 12 de diciembre de 2022\nEstos representantes deberán continuar bajo la figura de representación en coadyuvancia hasta en tanto exista una revocación de este encargo de quien detente la custodia o tutela, ya sea legal o de hecho.\nReforma publicada en la GOCDMX el 12 de diciembre de 2022\nEn todos los casos, la Persona Juzgadora se asegurará y hará constar que, conforme a la edad, desarrollo\n\nevolutivo, cognoscitivo y grado de madurez de la Persona Adolescente, tenga conocimiento de su situación, la duración del procedimiento, a los derechos que tiene y las posibles sanciones a que puede ser acreedora.\nReforma publicada en la GOCDMX el 12 de diciembre de 2022\nEn caso de que la persona adolescente resulte responsable, la Persona Juzgadora lo amonestará y le hará saber las consecuencias jurídicas y sociales de su conducta.\nCuando se determine la responsabilidad de una Persona Adolescente en la comisión de alguna de las infracciones previstas en este ordenamiento, en ningún caso se le impondrá como sanción el arresto.\nSi a consideración de la Persona Juzgadora, la Persona Adolescente se encontrara en situación de riesgo, lo enviará alasautoridadescompetentesaefectodequerecibalaatencióncorrespondiente.\nArtículo 54.- Si después de iniciada la audiencia, la persona probable infractora acepta la responsabilidad en la comisión de la infracción imputada tal y como se le atribuye, la Persona Juzgadora dictará de inmediato su resolución e impondrá la menor de las sanciones para la infracción de que se trate, excepto en los casos previstos en los artículos 36, 37,39 y 40. Si la Persona Probable Infractora no acepta los cargos, se continuará el procedimiento.\nArtículo 55.- Cuando la persona infractora opte por cumplir la sanción mediante un arresto, la Persona\nJuzgadora dará intervención a la Persona Médica para que determine su estado físico y mental antes de que ingrese al área de seguridad.\nArtículo 56.- La Persona Juzgadora determinará la sanción aplicable en cada caso concreto, tomando en cuenta la naturaleza y las consecuencias individuales y sociales de la infracción, las condiciones en que ésta se hubiere cometido y las circunstancias personales de la persona infractora, pudiendo solicitar a la\nDirección la condonación de la sanción, en los casos en que las especiales circunstancias físicas, psicológicas, económicas y, en general, personales de la persona infractora lo ameriten, de acuerdo a su consideración y a petición expresa del mismo o de persona de su confianza, observando los lineamientos que para tales efectos dicte la Consejería.\nArtículo 57.- Si la Persona Infractora fuese jornalera, obrera, o trabajadora no podrá ser sancionado con multa mayor del importe de su jornal o salario de un día. Tratándose de personas trabajadoras no asalariadas, la multa no excederá del equivalente a un día de su ingreso. Tratándose de personas desempleadas o sin ingresos, la multa máxima será el equivalente a una vez la Unidad de Medida. Los medios para la acreditación de estas condiciones deberán ser indubitables.\n\nArtículo 58.- Al resolver la imposición de una sanción, la Persona Juzgadora apercibirá a la Persona\nInfractora para que no reincida, haciéndole saber las consecuencias sociales y jurídicas de su conducta.\nArtículo 59.- La Persona Juzgadora notificará de manera personal e inmediata, la resolución al presunto infractor y al quejoso, si estuviera presente.\nArtículo 60.- Si la Persona Probable Infractor resulta no ser responsable de la infracción imputada, la\nPersona Juzgadora resolverá en ese sentido y le autorizará que se retire.\nSi resulta responsable, al notificarle la resolución, la Persona Juzgadora le informará que podrá elegir entre cubrir la multa o cumplir el arresto que le corresponda; si sólo estuviere en posibilidad de pagar parte de la multa, se le recibirá el pago parcial y la Persona Juzgadora le permutará la diferencia por un arresto, en la proporción o porcentaje que corresponda a la parte no cubierta, subsistiendo esta posibilidad durante el tiempo de arresto del infractor.\nEn concordancia con lo señalado en el párrafo anterior, en caso de que el responsable de la infracción haya sido trasladado al Centro de Sanciones Administrativas y de Integración Social de la Ciudad de México y si la persona infractora solicita ahí cubrir parte de la multa impuesta, la persona titular de la Dirección del\nCentro podrá recibir el pago del porcentaje o proporción de la multa que en relación con las horas de sanción impuesta deba cubrir.\nArtículo 61.- En los casos en que el infractor opte por cumplir el arresto correspondiente, tendrá derecho a cumplirlo en las condiciones necesarias de subsistencia.\nDurante el tiempo de cumplimiento del arresto, la Persona Infractora podrá ser visitado por sus familiares o por persona de su confianza; así como de representantes de asociaciones u organismos públicos o privados, cuyos objetivos sean de trabajo social y cívico, acreditados ante la Consejería para estos efectos.\nArtículo 62.- Para conservar el orden en el Juzgado, la Persona Juzgadora podrá imponer las siguientes correcciones disciplinarias:\nI. Amonestación;\nII. Multa por el equivalente de 1 a 10 veces la Unidad de Medida de la Ciudad de México vigente;\ntratándose de personas jornaleras, obreras, trabajadoras no asalariadas, personas desempleadas\n\no sin ingresos, se estará a lo dispuesto por el artículo 57 de esta Ley; y\nIII. Arresto hasta por 12 horas.\nArtículo 63.- Las Personas Juzgadoras a fin de hacer cumplir sus órdenes y resoluciones, podrán hacer uso de los siguientes medios de apremio:\nI. Multa por el equivalente de 1 a 10 veces la Unidad de Medida de la Ciudad de México vigente;\ntratándose de personas jornaleras, obreras, trabajadoras no asalariadas, personas desempleadas o sin ingresos, se estará a lo dispuesto por el artículo 57 de esta Ley;\nII. Arresto hasta por 12 horas; y\nIII. Auxilio de la fuerza pública.\nCAPÍTULO II\nPROCEDIMIENTO POR PRESENTACION DE LA PERSONA PROBABLE\nINFRACTORA\nArtículo 64.- La acción para el inicio del procedimiento es pública y su ejercicio corresponde a la\nAdministración Pública de la Ciudad de México por conducto de las Personas Policías, las cuales serán parte en el mismo.\nArtículo 65.- La Persona Policía en servicio detendrá y presentará al probable infractor inmediatamente ante la Persona Juzgadora, en los siguientes casos:\nI. Cuando presencien la comisión de la infracción; y\nII. Cuando sean informados de la comisión de una infracción inmediatamente después de que hubiese sido realizada o se encuentre en su poder el objeto o instrumento, huellas o indicios que hagan presumir fundadamente su participación en la infracción.\nEn el caso de la fracción XVII del artículo 28 de la Ley, si las partes involucradas no se ponen de acuerdo en la forma de la reparación del daño, la Persona Policía remitirá el o los vehículos involucrados al depósito y notificará de los hechos a la Persona Juzgadora. Cuando las partes lleguen a un acuerdo sobre la reparación\n\nde los daños antes del inicio del procedimiento, la Persona Juez liberará los vehículos dejando constancia de la voluntad de las partes.\nLa Persona Policía que se abstenga de cumplir con lo dispuesto en este artículo, será sancionado por los órganos competentes de la Secretaría, en términos de las disposiciones aplicables.\nArtículo 66.- La detención y presentación de la Persona Probable Infractora ante la Persona Juzgadora, constará en una boleta de remisión, la cual contendrá por lo menos los siguientes datos:\nI. Nombre, edad y domicilio de la Persona Probable Infractora, así como los datos de los documentos con que los acredite;\nII. Una relación de los hechos que motivaron la detención, describiendo las circunstancias de tiempo, modo, lugar así como cualquier dato que pudiera contribuir para los fines del procedimiento;\nIII. Nombre, domicilio del ofendido o de la persona que hubiere informado de la comisión de la infracción si fuere el caso y datos del documento con que los acredite. Si la detención es por queja, deberán constar las circunstancias de comisión de la infracción y en tal caso no será necesario que la persona quejosa acuda al Juzgado;\nIV. En su caso, la lista de objetos recogidos que tuvieren relación con la probable infracción;\nV. Nombre, número de placa o jerarquía, unidad de adscripción y firma de la Persona Policía que hace la presentación, así como en su caso número de vehículo; y\nVI. Número del juzgado al que se hará la presentación de la Persona Probable Infractora, domicilio y número telefónico.\nLa Persona Policía proporcionará a la persona quejosa, cuando lo hubiere, una copia de la boleta de remisión e informará inmediatamente a su superior jerárquico de la detención de la Persona Probable\nInfractora.\nArtículo 67.- La Persona Juzgadora llevará a cabo las siguientes actuaciones:\nI. Dará lectura a la boleta de remisión o en su caso a la queja y si lo considera necesario, solicitará\n\nla declaración de la Persona Policía. Tratándose de la conducta prevista en la fracción XVII del artículo 28 de la Ley, la declaración de la persona policía será obligatoria. La Persona Juzgadora omitirá mencionar el domicilio del quejoso;\nII. Otorgará el uso de la palabra a la Persona Probable Infractora, para que formule las manifestaciones que estime convenientes y ofrezca en su descargo, las pruebas de que disponga. Se admitirán como pruebas señaladas en el Código Nacional de Procedimientos\nPenales;\nIII. Acordará la admisión de las pruebas y las desahogará de inmediato. En el caso de que la\nPersona Probable Infractora no presente las pruebas ofrecidas, las mismas serán desechadas en el mismo acto; y\nIV. Resolverá sobre la responsabilidad de la Persona Probable Infractora. En caso de que le encuentre responsable, se le informará el derecho que tiene a conmutar la sanción de arresto por pago de la multa proporcional o por actividades de apoyo a la comunidad.\nEn el caso de que la Persona Infractora opte por cumplir el arresto establecido, y a criterio de la Persona\nJuzgadora sea remitido al Centro de Sanciones Administrativas y de Integración Social la persona infractora también podrá realizar el pago proporcional de la multa establecida ante dicho Centro.\nLos procedimientos serán desahogados y resueltos de inmediato por la Persona Juzgadora que los hubiere iniciado.\nCuando se actualice la conducta prevista en la fracción XVII del artículo 28 de la Ley y después de concluido el procedimiento establecido en este cuerpo normativo, la Persona Juzgadora ordenará la devolución del vehículo conducido por quien resulte responsable de los daños causados, únicamente cuando se firme el convenio respectivo o quede suficientemente garantizada su reparación; y en caso contrario, pondrá a disposición de la Persona Juzgadora de Cuantía Menor el vehículo conjuntamente con la demanda que al efecto firme el agraviado.\nArtículo 68.- La Persona Juzgadora hará del conocimiento del Servicio Público de Localización Telefónica de la Ciudad de México lo siguiente:\nI. Datos de la persona presentada que consten en la boleta de remisión;\n\nII. Lugar en que hubiere sido detenida;\nIII. Nombre y número de placa dela persona policía que haya realizado la presentación;\nIV. Sanción que se hubiera impuesto, y\nV. En su caso, el lugar de ejecución del arresto inmediatamente después de su determinación.\nRespecto de aquellos para los que se hubiera determinado tiempo de recuperación para el inicio del procedimiento o que por otras circunstancias no se hubiera iniciado el mismo, se proporcionará la información a que se refieren las fracciones I a III de este artículo.\nArtículo 69.- En tanto se inicia la audiencia, la Persona Juzgadora ordenará que la persona probable infractora sea ubicada en la sección correspondiente, excepción hecha de las personas mayores de 65 años, las que deberán permanecer en la sala de audiencias.\nArtículo 70.- Cuando la Persona Probable Infractora se encuentre en estado de ebriedad o bajo el influjo de estupefacientes o sustancias psicotrópicas o tóxicas, la Persona Juzgadora ordenará a la Persona Médica que previó examen que practique, dictamine su estado y señale el plazo probable de recuperación, que será la base para fijar el inicio del procedimiento. En tanto se recupera será ubicado en la sección que corresponda.\nArtículo 71.- Tratándose de Personas Probables Infractoras que por su estado físico o mental denoten peligrosidad o intención de evadirse del Juzgado, se les retendrá en el área de seguridad hasta que se inicie la audiencia.\nArtículo 72.- Cuando la persona probable infractora sea una Persona con Discapacidad, a consideración de la Persona Médica, la Persona Juzgadora suspenderá el procedimiento y citará a las personas obligadas a la custodia de la persona enferma o persona con discapacidad y a falta de éstos, lo remitirá a las autoridades de salud o instituciones de asistencia social competentes de la Ciudad de México que deban intervenir, a fin de que se le proporcione la ayuda o asistencia que requiera.\nArtículo 73.- Cuando comparezca la Persona Probable Infractora ante la Persona Juzgadora, ésta le informará del derecho que tiene a comunicarse con la persona que determine para informar el lugar y la situación en la que se encuentra.\n\nArtículo 74.- Si la Persona Probable Infractora solicita comunicarse con persona que le asista y defienda, la\nPersona Juzgadora suspenderá el procedimiento, dándole dentro del juzgado las facilidades necesarias y le concederá un plazo que no excederá de dos horas para que se presente a la Persona Defensora o persona que le asista. Si ésta no se presenta la Persona Juzgadora le nombrará una Persona Defensora de Oficio o, a solicitud de la Persona Probable Infractora, ésta podrá defenderse por sí misma, salvo que se trate de\nPersonas Menores de Edad o Personas con Discapacidad.\nCAPÍTULO III\nMEDIACIÓN COMUNITARIA\nArtículo 75.- La mediación comunitaria es un mecanismo no jurisdiccional y voluntario, complementario a la cultura cívica, para gestionar la solución o prevención de conflictos o controversias entre personas, que surgen o pueden suscitarse en una comunidad que comparte valores, intereses o espacios que crean pertenencia, tales como colonias, barrios, unidades habitacionales, unidades o instalaciones deportivas, parques, jardines, mercados públicos y en general el espacio público, en el que un una persona tercera imparcial denominada persona mediadora comunitaria, les asistirá en el proceso de encontrar soluciones aceptables para todos, y beneficios para la comunidad. La Persona Juzgadora podrá dar intervención a la\nPersona Mediadora Comunitaria o por decisión voluntaria de las partes.\nArtículo 76.- La mediación comunitaria será aplicable en la gestión y prevención de las controversias que surjan o puedan surgir, en los siguientes supuestos:\nI. Cuando se actualice la conducta prevista en el artículo 27 fracción VII de ésta Ley, la Persona\nJuzgadora podrá dar intervención a una Persona Mediadora Comunitaria en el caso de que las personas involucradas decidan participar en el procedimiento de mediación;\nII. Para prevenir conflictos que puedan surgir en una comunidad por la definición de obras;\nIII. En apoyo a las instituciones escolares y para combatir el acoso escolar;\nIV. En apoyo a personas en situación de descuido;\nV. Entre las personas en situación de calle; y\nVI. Cuando se actualicen las conductas previstas en la fracción XVII del artículo 28 de esta Ley, la\n\nPersona Juzgadora podrá dar intervención a una Persona Mediadora Comunitaria en el caso de que las personas involucradas decidan participar en el procedimiento de mediación.\nArtículo 77.- Los acuerdos a los que lleguen las personas mediadas adoptarán la forma de convenio de mediación comunitaria por escrito y deberán contener las siguientes formalidades y requisitos:\nI. Lugar y fecha de la celebración;\nII. Nombre, edad, nacionalidad, estado civil, profesión u ocupación y domicilio de cada una de las personas mediadas;\nIII. En el caso de las personas morales, se acompañará como anexo, el documento con el que el la persona apoderada o representante legal de la persona mediada de que se trate, acreditó su personalidad;\nIV. Los antecedentes del conflicto entre las personas mediadas que los llevaron a utilizar la mediación;\nV. Un capítulo de declaraciones, si las personas mediadas lo estiman conveniente;\nVI. Una descripción de las obligaciones de dar, hacer o no hacer que hubieren acordado las personas mediadas; así como el lugar, la forma y el tiempo en que estas deben cumplirse;\nVII. Las firmas o huellas dactilares, en su caso de las personas mediadas;\nVIII. Nombre y firma de la persona actuante como Mediadora, para hacer constar que da fe de la celebración del convenio; así como el sello correspondiente; y\nIX. Número o clave del registro.\nArtículo 78.- El convenio se redactará al menos por triplicado, en todo caso se deberá procurar que, con independencia del número de ejemplares, uno sea conservado por el Juzgado y cada una de las partes reciba un ejemplar como constancia.\nEl convenio de mediación comunitaria se someterá a la consideración de la persona Juzgadora, quien en su caso lo elevará a resolución administrativa y tratándose de los supuestos previstos en la fracción XVII del\n\nartículo 28 de esta Ley, el convenio respectivo deberá suscribirse en términos del numeral 81 de este ordenamiento, para que surta los efectos señalados.\nLos convenios derivados del procedimiento de mediación comunitaria, que se realicen conforme a lo dispuesto en la Ley de Justicia Alternativa de la Ciudad de México, únicamente por lo que hace al de daño a particulares, serán ejecutados a través de la vía de apremio.\nLos convenios derivados de mediadores comunitario en ámbitos de competencia de la Secretaría de inclusión y Bienestar Social, la Procuraduría Social y de la Procuraduría Ambiental y del Ordenamiento\nTerritorial, se sujetarán a lo previsto por las disposiciones aplicables que correspondan.\nArtículo 79.- Para ser Persona Mediadora Comunitaria se deben reunir los siguientes requisitos:\nI. Ser persona ciudadana mexicana en pleno ejercicio de sus derechos civiles y políticos y tener cuando menos veinticinco años de edad al día de su designación;\nII. Contar con licenciatura en derecho o ser pasante en derecho;\nIII. No haber sido condenada en sentencia ejecutoriada por delito intencional ni suspendida o inhabilitada para el desempeño de un cargo público, y\nIV. Concursar y aprobar el proceso de selección correspondiente, sometiéndose a los exámenes y cursos de capacitación y entrenamiento específicos para la prestación de la mediación comunitaria.\nEl cargo de persona mediadora es de confianza y será designado y ratificado cada tres años por la Alcaldía, previa aprobación de un examen de competencias laborales. La Consejería expedirá los lineamientos para la designación y ratificación de las Personas Mediadoras Comunitarias.\nLa Persona Mediadora Comunitaria a que se refiere este apartado, se dedicará a esa función de forma exclusiva por lo que la Alcaldía evitará que atienda cualquier otra función, ajena al servicio de mediación comunitaria.\nArtículo 80.- En caso de que las partes no acepten someterse a la mediación comunitaria luego de realizada la sesión informativa previa, en la que las personas interesadas son orientadas sobre las ventajas, principios y características de la mediación, establecida en el artículo 21 de la Ley de Justicia Alternativa del Tribunal\n\nSuperior de Justicia para el Distrito Federal es obligación de la Persona Mediadora Comunitaria, sugerir las alternativas pertinentes.\nAsimismo, apoyará a las autoridades de la Alcaldía en las negociaciones que se realicen con los vecinos y a las autoridades escolares en la atención de controversias que se susciten en las comunidades escolares, planteando alternativas de solución.\nArtículo 81.- El procedimiento de mediación comunitaria se desahogará en un máximo de tres días. En el caso de no arribar a una solución y deseen las partes acudir con la Persona Juzgadora, la Persona\nMediadora las canalizará con la Persona Juzgadora a efecto de iniciar el procedimiento que corresponda.\nLa Persona Juzgadora determinará lo conducente.\nCAPÍTULO IV\nPROCEDIMIENTO POR QUEJA\nArtículo 82.- Las personas podrán presentar quejas orales o por escrito ante la Persona Juzgadora, por hechos constitutivos de probables infracciones; que considerará los elementos contenidos en la queja y si lo estima procedente, girará citatorio a la persona quejosa y a la Persona Presunta Infractora.\nLa queja deberá contener nombre y domicilio de las partes, relación de los hechos motivo de la queja y firma de la persona quejosa; asimismo cuando la persona quejosa lo considere relevante podrá presentar fotografías o videograbaciones relacionadas a la probable infracción, las cuales calificará la Persona\nJuzgadora y tendrán valor probatorio.\nArtículo 83.- El derecho a formular la queja prescribe en quince días naturales, contados a partir de la comisión de la probable infracción. La prescripción se interrumpirá por la formulación de la queja.\nArtículo 84.- En caso de que la Persona Juzgadora considere que la queja no contiene elementos suficientes que denoten la posible comisión de una infracción, acordará de inmediato, fundando y motivando la improcedencia; debiendo notificar a la persona quejosa en ese mismo acto. Si no fuere posible en ese momento, dejará constancia del motivo y tendrá un término de tres días para hacerlo.\nLa resolución a la que se refiere el párrafo anterior, podrá ser revisada a petición de la persona quejosa, para efectos de su confirmación o revocación por la Consejería, a través del recurso de inconformidad que se hará valer dentro de los diez días hábiles siguientes a su notificación. La Consejería resolverá de plano\n\nen un término igual notificando su resolución a la Persona Quejosa y a la Persona Juzgadora para su cumplimiento.\nArtículo 85.- El citatorio será notificado por quien determine ela Persona Juzgadora, acompañado por una\nPersona Policía y deberá contener, cuando menos, los siguientes elementos:\nI. Escudo de la Ciudad y folio;\nII. La Alcaldía y el número del Juzgado que corresponda, el domicilio y el teléfono del mismo;\nIII. Nombre, edad y domicilio de la persona probable infractora;\nIV. Una relación de los hechos de comisión de la probable infracción, que comprenda todas y cada una de las circunstancias de tiempo, modo, lugar, así como cualquier dato que pudiera contribuir para los fines del procedimiento;\nV. Nombre y domicilio de la persona quejosa;\nVI. Fecha y hora de la celebración de la audiencia;\nVII. Nombre, cargo y firma de quien notifique, y\nVIII. El contenido del artículo 86 y el último párrafo del artículo 94 de esta Ley.\nLa persona que lleve a cabo la notificación, recabará el nombre y firma de la persona que reciba el citatorio o la razón correspondiente.\nSi la Persona Probable Infractora fuese menor de edad, la citación se hará a él mismo, por medio de quien ejerza la patria potestad, la custodia o la tutela de derecho o de hecho.\nArtículo 86.- En caso de que la Persona Quejosa no se presentare, se desechará su queja, y si el que no se presentare fuera la persona probable infractora, la Persona Juzgadora librará orden de presentación en su contra, turnándola de inmediato a la persona titular de la unidad sectorial de la Secretaría que corresponda al domicilio del probable infractor, misma que será ejecutada bajo su más estricta responsabilidad, sin exceder de un plazo de 48 horas.\n\nArtículo 87.- Las personas policías que ejecuten las órdenes de presentación, deberán hacerlo sin demora alguna, haciendo comparecer ante la Persona Juzgadora a las personas probables infractoras a la brevedad posible, observando los principios de actuación a que están obligados.\nArtículo 88.- Al iniciar el procedimiento, la Persona Juzgadora verificará que las personas citadas se encuentren presentes; si lo considera necesario dará intervención a la Persona Médico, quien determinará el estado físico y en su caso, mental de aquéllas.\nAsimismo, la Persona Juzgadora verificará que las personas ausentes hayan sido citadas legalmente.\nEn caso de que haya más de una persona quejosa, deberán nombrar un representante común para efectos de la intervención en el procedimiento.\nArtículo 89.- La Persona Juzgadora celebrará en presencia de la persona quejosa y de la Persona Probable\nInfractora la audiencia de conciliación en la que procurará su avenimiento; de llegarse a éste, se hará constar por escrito el convenio entre las partes.\nEn todo momento, a solicitud de las partes o a consideración de la Persona Juzgadora, la audiencia se suspenderá por única ocasión; señalándose día y hora para su continuación, que no excederá de los quince días naturales siguientes, debiendo continuarla la Persona Juzgadora que determinó la suspensión.\nArtículo 90.- El convenio de conciliación puede tener por objeto:\nI. La reparación del daño, y\nII. No reincidir en conductas que den motivo a un nuevo procedimiento.\nEn el convenio se establecerá el término para el cumplimiento de lo señalado en la fracción I, así como para los demás acuerdos que asuman las partes.\nCuando el daño se cause con motivo de lo previsto en la fracción XVII del artículo 28 de la Ley, el convenio se elaborará con base en el valor del daño que se establezca en el dictamen en materia de tránsito terrestre emitido por las personas peritos adscritos a la Consejería, respetando el principio de autonomía de voluntad de las partes, pero sin que el monto a negociar pueda exceder o sea inferior a un veinte por ciento del valor del daño dictaminado.\n\nArtículo 91.- La Persona Juzgadora podrá remitir a las partes con una persona mediadora comunitaria para que intenten solucionar el conflicto que les afecte y en el supuesto de que se alcance un convenio de mediación, lo calificará y en su caso, lo elevará a resolución administrativa.\nArtículo 92.- Cuando se produzca incumplimiento de un convenio de mediación comunitaria por dificultades de interpretación del convenio o por causas supervenientes, la Persona Juzgadora remitirá a las personas involucradas con una Persona Mediadora Comunitaria para que se desahogue una remediación.\nArtículo 93.- A quien incumpla el convenio de conciliación o el de mediación o re-mediación cuando la\nPersona Juzgadora haya remitido a las partes a ese procedimiento, se le impondrá un arresto de 6 a 24 horas o una multa de 1 a 30 veces la Unidad de Medida.\nA partir del incumplimiento del convenio, la persona afectada tendrá 15 días para solicitar que se haga efectivo el apercibimiento.\nTranscurridos seis meses a partir de la firma del convenio, sólo se procederá por nueva queja que se presentare.\nArtículo 94.- En el caso de que las partes manifestaran su voluntad de no conciliar, se dará por concluida la audiencia de conciliación y se iniciará la audiencia sobre la responsabilidad de la persona probable infractora, en la cual la Persona Juzgadora, en presencia de la persona quejosa y de la persona probable infractora, llevará a cabo las siguientes actuaciones:\nI. Dará lectura a la queja, la cual podrá ser ampliada por la persona quejosa;\nII. Otorgará el uso de la palabra a la persona quejosa para que ofrezca las pruebas respectivas;\nIII. Otorgará el uso de la palabra a la persona probable infractora, para que formule las manifestaciones que estime convenientes y ofrezca pruebas en su descargo;\nIV. Acordará la admisión de las pruebas y las desahogará de inmediato, y\nV. Resolverá sobre la conducta imputada, considerando todos los elementos que consten en el expediente y resolverá sobre la responsabilidad de la persona probable infractora.\n\nSe admitirán como pruebas las testimoniales, las fotografías, las videograbaciones y las demás que a juicio de la Persona Juzgadora, sean idóneas en atención a las conductas imputadas por la Persona Quejosa.\nTratándose de daños causados con motivo del tránsito de vehículos, la Persona Juzgadora deberá ordenar en todos los casos la intervención de las Personas Peritas en materia de tránsito terrestre, autorizadas por la Consejería.\nPara el caso de las fotografías y videograbaciones, quienes las presenten deberán proporcionar a la Persona\nJuzgadora los medios para su reproducción al momento del desahogo de la prueba, en caso contrario estas serán desechadas.\nEn el caso de que la persona quejosa o la persona probable infractora no presentaren en la audiencia las pruebas ofrecidas, serán desechadas en el mismo acto. Cuando la presentación de las pruebas ofrecidas dependiera del acto de alguna autoridad, la Persona Juzgadora suspenderá la audiencia y señalará día y hora para la presentación y desahogo de las mismas.\nArtículo 95.- En el supuesto de que se libre orden de presentación a la persona presunta infractora y el día de la presentación no estuviere presente la persona quejosa, se llevará a cabo el procedimiento previsto en el artículo 66 de esta Ley y si se encuentra la persona quejosa, se llevará cabo el procedimiento por queja.\nArtículo 96.- En el caso de que derivado de un conflicto familiar o conyugal la persona ofendida haga de conocimiento a la Persona Juzgadora de hechos contemplados como alguna de las infracciones administrativas previstas en el Título Tercero de esta Ley, éste iniciará el procedimiento correspondiente en caso de ser competente, y dejará a salvo los derechos de cada una de las personas en caso de los hechos puedan constituir un delito.\nLa Persona Juzgadora canalizará mediante oficio, a las personas involucradas a las instituciones públicas especializadas.\nCAPÍTULO V\nPROCEDIMIENTO EN CASOS DE DAÑO CULPOSO CAUSADO CON\nMOTIVO DEL TRÁNSITO DE VEHÍCULOS\nArtículo 97.- Cuando se actualicen las conductas previstas en la fracción XVII del artículo 28 de esta Ley y las personas involucradas se encuentren ante la presencia de la Persona Juzgadora, éste hará de su conocimiento, dejando constancia escrita de ello, los beneficios de utilizar el procedimiento de mediación\n\npara conciliar sus intereses; la sanción que puede ser impuesta al responsable de los daños en caso de no llegar a un arreglo; la situación de los vehículos implicados; las actuaciones, alcances y efectos del procedimiento de conciliación; así como los derechos y acciones que en su caso, pueden ejercer ante la autoridad judicial.\nAsí mismo hará del conocimiento de las personas involucradas la posibilidad de otorgar fianza para garantizar el cumplimiento de las obligaciones que surjan por el daño culposo causado con motivo del tránsito de vehículos, para poder disponer de su vehículo.\nArtículo 98.- La Persona Juzgadora tomará la declaración de las personas conductoras involucrados y en su caso, de las personas testigos de los hechos, en los formatos que para el efecto se expidan, e inmediatamente después dará intervención, dejando constancia escrita de ello, a las Personas Peritas en tránsito terrestre, Perita en valuación mecánica, Perita en valuación de bienes muebles e inmuebles de la\nConsejería. Admitirá y desahogará como pruebas las demás que, a su juicio, sean idóneas en atención a las conductas imputadas por la persona quejosa.\nCuando alguna de las personas conductoras se niegue a rendir su declaración, se dará preponderancia, para la emisión del dictamen de tránsito terrestre, valoración de las probanzas y emisión de la resolución correspondiente, a las declaraciones rendidas por las demás personas conductoras y personas testigos de los hechos. Las Personas Peritas en tránsito terrestre, en todos los casos, deberán rendir el dictamen correspondiente.\nArtículo 99.- Las Personas Peritas rendirán su dictamen ante la Persona Juzgadora, en un plazo que no excederá de cuatro horas contadas a partir de que se solicite su intervención.\nCuando el número de vehículos implicados sea superior a cuatro, la Persona Juzgadora podrá ampliar el plazo para la entrega del dictamen hasta por dos horas.\nSi la Persona Perita rinde su dictamen fuera de los plazos previstos en este artículo, la Persona Juzgadora notificará de esta irregularidad a las autoridades competentes, para los efectos sancionatorios administrativos conducentes, sin afectar la validez del dictamen.\nArtículo 100.- La Persona Juzgadora, con la presencia de las personas involucradas y con base en el dictamen pericial y demás elementos de prueba que tenga a su alcance, celebrará audiencia en la que hará del conocimiento de las personas conductoras el resultado del dictamen, así como el monto de los daños causados, y procurará su avenimiento.\n\nDe considerarlo pertinente, la Persona Juzgadora ordenará a las personas involucradas que acudan al procedimiento de mediación a que se refiere la Ley de Justicia Alternativa del Tribunal Superior de Justicia para el Distrito Federal.\nArtículo 101.- Cuando las personas conductoras involucrados lleguen a un acuerdo, se hará constar por escrito el convenio respectivo y se eximirá de la imposición de las sanciones a que se refiere el artículo 33 de este ordenamiento a quien acepte la responsabilidad o resulte responsable de los daños causados.\nA la o las personas conductoras que no resulten responsables de los daños, les serán devueltos sus vehículos sin mayor trámite.\nArtículo 102.- El convenio que en su caso, suscriban las personas interesadas, ante la presencia de la\nPersona Juzgadora, será válido y traerá aparejada ejecución en vía de apremio ante los juzgados civiles de la Ciudad de México, quienes sólo podrán negarse a ordenar su ejecución cuando dicho instrumento tenga un objeto distinto a la reparación del daño.\nPara su validez, en todo convenio se hará constar la forma en que se garantice su cumplimiento, a través de alguna de las formas previstas en la ley correspondiente.\nArtículo 103.- Cuando alguno de los conductores manifieste su voluntad de no conciliar sus intereses, la\nPersona Juzgadora actuará de conformidad con lo siguiente:\nI. Impondrá a la persona o personas responsables de los daños, mediante resolución, la sanción que corresponda en términos de lo dispuesto en este ordenamiento, tomando en cuenta el dictamen pericial y los demás elementos probatorios que se hayan desahogado; dejando a salvo los derechos de las partes por cuanto hace a la reparación del daño;\nII. Proporcionará a la persona agraviada, en su caso, el formato de demanda respectivo para su llenado con auxilio de una Persona Defensora que le asigne la Defensoría Pública;\nIII. Cuando la persona conductora responsable garantice el pago de los daños le devolverá el vehículo que conducía; en caso contrario, si se presentó la demanda, lo pondrá a disposición de la Persona Juzgadora de Cuantía Menor en cumplimiento a la determinación del auto inicial;\nIV. Una vez firmada la demanda la enviará, inclusive por vía electrónica, dentro del plazo de doce\n\nhoras a la Persona Juzgadora de Cuantía Menor en turno;\nV. Inmediatamente que reciba el auto inicial la Persona Juzgadora de Cuantía Menor en turno, le dará el cumplimiento que corresponda en sus términos, con relación a los vehículos involucrados o lo que se determine; y\nVI. Remitirá a la autoridad judicial, dentro de las 24 horas siguientes a la determinación de responsabilidad administrativa y cuando la remisión de la demanda sea por vía electrónica, los originales del expediente formado.\nCuando se prevenga la demanda por causas provocadas por la persona agraviada y no se desahogue, se procederá en los términos del artículo siguiente.\nArtículo 104.- Si la persona agraviada manifestara su voluntad de no presentar su demanda en ese momento o solicitara como reparación del daño una cantidad que exceda del veinte por ciento del monto establecido en el dictamen emitido por las Personas Peritas adscritas a la Consejería, la Persona Juzgadora hará constar tal circunstancia dejando a salvo sus derechos para que los haga valer por la vía que estime procedente, en un plazo no mayor de dos años a partir de esa fecha, ordenando la liberación del vehículo conducido por el responsable.\nEn cualquier caso, la Persona Juzgadora, expedirá a la parte que lo solicite, copia certificada de las actuaciones realizadas ante ella.\nCAPÍTULO VI\nDEL PROCEDIMIENTO POR INFRACCIONES EN MATERIA DE TRÁNSITO\nArtículo 105.- El procedimiento para las infracciones en materia de tránsito podrá hacerse:\nI. Por vía electrónica, cuando la persona ciudadana otorgue la autorización para que le sean notificadas por esta vía las infracciones que hubiese cometido, así como el procedimiento administrativo correspondiente;\nII. Por procedimiento administrativo ordinario, conforme a lo dispuesto en la Ley del\nProcedimiento Administrativo de la Ciudad de México.\n\nArticulo 106.- El procedimiento administrativo vía electrónica, se llevará cabo de la siguiente manera:\nI. La Secretaria pondrá a disposición de la persona probable infractora un sistema de consulta de infracciones de tránsito; donde podrá ingresar el número de placa de su vehículo y acceder a las infracciones que están registradas; así como de las sanciones a que se haga acreedor.\nII. En este caso la persona probable infractora podrá otorgar su consentimiento para seguir el procedimiento administrativo vía electrónica.\nIII. En caso de que acepte las sanciones impuestas se seguirá el siguiente procedimiento.\na) Amonestación, quedara registrada en el sistema.\nb) Curso en línea; el sistema proporcionará a la persona infractora la información de las modalidades del curso; una vez acreditado otorgará una constancia electrónica, que permita comprobar que ha sido cubierta la sanción;\nc) Taller de sensibilización presencial; el sistema proporcionará un listado de los centros donde se impartirán, horarios y requisitos; la persona infractora podrá hacer su inscripción en vía electrónica o telefónica. Una vez que asista y acredite el curso, se le otorgará una constancia y una clave que le permita comprobar que ha cubierto la sanción.\nd) Trabajo en favor de la comunidad; el sistema proporcionará un listado de las jornadas de trabajo comunitario programadas en la Ciudad, a efecto de que la persona infractora se inscriba en la que prefiera; deberá presentarse en el día, hora y lugar indicado con el personal de la Consejería, de la administración Pública de la Ciudad o de la Alcaldía que corresponda, donde le indicarán las actividades que deberá realizar, al concluir la jornada de trabajo comunitario se le entregará una constancia que le permita comprobar que ha cubierto la sanción.\nIV. En caso de que la persona probable infractora no acepte la sanción impuesta podrá interponer el recurso de revisión vía electrónica a la Consejería, quien deberá resolver en los tiempos legales establecidos.\nAsimismo, podrá hacer la aclaración en caso de que ya no sea el propietario del vehículo en el cual se realizó la infracción en matería de tránsito, debiendo adjuntar copia simple del documento que lo acredite y en su caso señalar el nombre del propietario actual.\n\nV. En cualquier momento, la persona probable infractora podrá aceptar que las infracciones y los procedimientos administrativos le sean notificadas por medios electrónicos; en cuyo caso la\nPersona Juzgadora notificará las infracciones administrativas por tránsito que le hayan sido notificadas por la Secretaría.\nRecibida la notificación electrónica, la persona probable infractora ingresará al sistema electrónico de la Consejería donde iniciará el procedimiento administrativo, dándose por notificado; en caso de que la persona probable infractora no se dé por notificado dentro de los 3 días siguientes a la notificación, la Persona Juzgadora procederá a notificar por estrado electrónico en la página donde se lleve a cabo el procedimiento.\nSi la Persona Probable Infractora acepta las infracciones administrativas, se estará a lo dispuesto por la fracción III de este artículo.\nVI. Si la Persona Probable Infractora no está de acuerdo con las infracciones administrativas tendrá un plazo de 5 días hábiles para hacer valer lo que a su derecho convenga, así como presentar las pruebas que considere adecuadas, de manera electrónica; pasado ese plazo la\nPersona Juez emitirá su resolución, misma que hará saber de manera electrónica.\nArtículo 107.- El procedimiento administrativo ordinario se llevará de la siguiente manera:\nI. La Secretaría notificara a la Persona Juzgadora las Personas Probables Infractoras que tienen registros de infracciones administrativas de tránsito.\nII. La Persona Juzgadora enviará vía correo ordinario a las Personas Probables Infractoras la notificación de las infracciones administrativas de tránsito que se tienen registradas; quienes podrán optar por seguir el procedimiento administrativo vía electrónica, en cuyo caso deberán ingresar al sistema electrónico de la Consejería y seguir el procedimiento señalado en el artículo.\nIII. En caso de que el Persona Probable Infractora opte por el procedimiento Ordinario tendrá diez días hábiles para hacer por escrito sus manifestaciones y presentar las pruebas que considere adecuadas, vencido ese término la Persona Juzgadora emitirá su resolución, notificando por correo ordinario la misma.\nTÍTULO QUINTO\n\nDEL CONSEJO DE JUSTICIA CÍVICA\nCAPÍTULO ÚNICO\nArtículo 108.- El Consejo es el órgano consultivo del Gobierno de la Ciudad de México en materia de justicia cívica, el cual emitirá opiniones a las instancias competentes sobre el diseño de las normas internas de funcionamiento, la supervisión, el control y la evaluación de los Juzgados, así como las pertinentes al mejoramiento de la actuación policial en la materia de esta Ley.\nArtículo 109.- El Consejo está integrado por:\nI. La persona titular de la Consejería, quien lo presidirá;\nII. La persona titular de la Secretaría;\nIII. La persona titular de la Secretaría de Gobierno;\nIV La persona titular de la Dirección, quien fungirá como Secretaria Técnico;\nV. Una Persona Juzgadora de reconocida experiencia y probidad, designado por la persona titular de la Consejería;\nVI. Una persona representante del área de capital humano de la Secretaría de Administración y\nFinanzas del Gobierno de la Ciudad de México, designado por la persona titular de ésta;\nVII. Tres personas representantes de la sociedad civil, cuyas labores sean afines a los objetivos de la Justicia Cívica, quienes serán nombradas y removidas por la persona titular de la Jefatura de\nGobierno. Se designarán preferentemente a aquellas personas que se hayan distinguido en la realización de actividades de colaboradores comunitarios y desempeñarán su encargo de manera honoraria;\nVIII. Dos personas Diputados del Congreso de la Ciudad de México, designados por su pleno; y\nIX. Una persona representante de cada Alcaldía.\nLas personas integrantes del Consejo referidos en las fracciones I a IV y IX contarán con una persona\n\nsuplente designado por ellas mismas.\nLa organización y funcionamiento del Consejo se establecerán en el reglamento.\nArtículo 110.- Las personas Consejeras señalados en las fracciones V y VII del artículo anterior durarán tres años en su cargo, serán sustituidas de manera escalonada y no podrán ser nombradas para un nuevo periodo.\nEn el caso de la fracción IX del artículo anterior las personas serán nombradas y removidas por las personas titulares de la Alcaldía.\nTÍTULO SEXTO\nDE LA ORGANIZACIÓN ADMINISTRATIVA\nCAPITULO I\nJUZGADOS CÍVICOS\nArtículo 111.- En cada Juzgado actuarán Personas Juzgadoras en turnos sucesivos con diverso personal, que cubrirán las veinticuatro horas de todos los días del año.\nArtículo 112.- En cada Juzgado habrá por cada turno, cuando menos, el personal siguiente:\nI. Una Persona Juzgadora;\nII. Una Persona Secretaria;\nIII. Una Persona Médica;\nIV. Las Personas Policías comisionadas por la Secretaría; y\nV. El personal auxiliar que determine la Dirección.\nArtículo 113.- En los Juzgados se llevarán los registros que determine la Consejería.\nArtículo 114.- Los Juzgados contarán con los espacios físicos siguientes:\n\nI. Sala de audiencias;\nII. Sección de recuperación de personas en estado de ebriedad o intoxicación;\nIII. Sección de Personas Adolescentes;\nIV. Sección médica, y\nV. Área de seguridad.\nLas secciones a que se refieren las fracciones II, III, y V contarán con departamentos separados para hombres y mujeres.\nArtículo 115.- A las Personas Juzgadoras les corresponde:\nI. Conocer de las infracciones establecidas en esta Ley;\nII. Resolver sobre la responsabilidad de las personas probables infractores;\nIII. Ejercer las funciones conciliatorias a que se refiere esta Ley;\nIV. Aplicar las sanciones establecidas en esta Ley y otras ordenamientos que así lo determinen;\nV. Intervenir en los términos de la presente Ley, en conflictos vecinales, familiares o conyugales, con el fin de avenir a las partes o conocer de las infracciones cívicas que se deriven de tales conductas;\nVI. Llevar el control de los expedientes relativos a los asuntos que se ventilen en el Juzgado;\nVII. Expedir constancias relativas a hechos y documentos contenidos en los expedientes integrados con motivo de los procedimientos de que tenga conocimiento;\nVIII. Expedir constancias de hechos a solicitud de particulares, quienes harán las manifestaciones bajo protesta de decir verdad;\n\nIX. Solicitar por escrito a las autoridades competentes, el retiro de objetos que estorben la vía pública y la limpia de lugares que deterioren el ambiente y dañen la salud pública;\nX. El mando del personal que integra el Juzgado, para los efectos inherentes a su función, e informará a la Dirección, de manera inmediata, las ausencias del personal;\nXI. Reportar inmediatamente al Servicio Público de Localización Telefónica de la Administración\nPública de la Ciudad de México, la información sobre las personas presentadas, sancionadas, así como las que se encuentren en tiempo de recuperación;\nXII. Informar diariamente a la Consejería y a la Dirección sobre los asuntos tratados y las resoluciones que haya dictado;\nXIII. Ejecutar la condonación de la sanción que en su caso determine la Dirección;\nXIV. Habilitar al personal del Juzgado para suplir las ausencias temporales de la Persona\nSecretaria;\nXV. Asistir a las reuniones a que sea convocada, así como aquéllas que se tengan con instituciones con las cuales haya celebrado convenio la Consejería, y\nXVI. Retener y devolver los objetos y valores de las Personas Presuntas Infractoras, o que sean motivo de la controversia, previo recibo que expida. No podrá devolver los objetos que por su naturaleza sean peligrosos, o los que estén relacionados con las infracciones contenidas en el artículo 28, fracción VI de esta Ley, en cuyo caso deberá remitirlos al lugar que determine la\nDirección, pudiendo ser reclamados ante ésta cuando proceda;\nXVII. Comisionar al personal del Juzgado para realizar notificaciones y diligencias;\nXVIII. Autorizar y designar la realización de las actividades de apoyo a la comunidad a solicitud del responsable,\nXIX. Aplicar medidas para mejorar la convivencia cotidiana establecidos en esta Ley y otros ordenamientos aplicables a esta materia, y\nXX. Las demás atribuciones que le confieran esta Ley y otros ordenamientos.\n\nArtículo 116.- Para la aplicación de esta Ley es competente la Persona Juzgadora del lugar donde se haya cometido la infracción; si ésta se hubiese realizado en los límites de una circunscripción territorial y otra, será competente la Persona Juzgadora que prevenga, excepto en los casos que expresamente instruya la\nDirección.\nPor necesidades de servicio y para la eficaz y pronta administración de justicia, podrá ampliar el ámbito de actuación de los juzgados para conocer de presentaciones, procedimientos y diligencias que corresponda a los juzgados de otras circunscripciones territoriales e itinerantes.\nArtículo 117.- La Persona Juzgadora tomará las medidas necesarias para que los asuntos sometidos a su consideración durante su turno, se terminen dentro del mismo y solamente dejará pendientes de resolución aquéllos que por causas ajenas al Juzgado no pueda concluir, lo cual se hará constar en el registro respectivo que firmarán la Persona Juzgadora entrante y saliente.\nArtículo 118.- La Persona Juzgadora que termina el turno, bajo su estricta responsabilidad, hará entrega física de los asuntos en trámite y de las personas que se encuentren en las áreas del Juzgado, a la Persona\nJuzgadora entrante, lo que se hará constar en el registro respectivo.\nArtículo 119.- La Persona Juzgadora, al iniciar su turno, continuará la tramitación de los asuntos que hayan quedado sin terminar en el turno anterior. Los casos serán atendidos sucesivamente según el orden en que se hayan presentado en el Juzgado.\nArtículo 120.- Las Personas Juzgadoras estarán obligados a solicitar a las personas servidoras públicas los datos, informes o documentos sobre asuntos de su competencia, para mejor proveer y resolver lo conducente.\nArtículo 121.- En el caso de la infracción establecida en la fracción IX del artículo 28, realizar el requerimiento de información necesaria a las organizaciones públicas o privadas competentes, para identificar al titular de la línea telefónica o aplicaciones y su domicilio.\nArtículo 122.- La Persona Juzgadora, dentro del ámbito de su competencia y bajo su estricta responsabilidad, cuidará que se respeten la dignidad y los derechos humanos, por tanto, impedirá todo maltrato, abuso físico o verbal, cualquier tipo de incomunicación, exacción o coacción moral en agravio de las personas presentadas o que comparezcan al Juzgado.\n\nArtículo 123.- La remuneración de las Personas Juzgadora será equivalente al menos a la categoría básica que corresponda a Personas Agentes del Ministerio Público de la Fiscalía General de Justicia de la Ciudad de México adscritos a Juzgados del Fuero Común, atendiendo a los criterios del Servicio Público de Carrera, las cargas de trabajo y las responsabilidades asignadas, de conformidad con la disponibilidad presupuestal.\nArtículo 124.- A la Persona Secretaria le corresponde:\nI. Autorizar con su firma y el sello del Juzgado las actuaciones en que intervenga la Persona\nJuzgadora en ejercicio de sus funciones;\nII. Certificar y dar fe de las actuaciones que la Ley o la Persona Juzgadora ordenen;\nIII. Expedir copias certificadas relacionadas con las actuaciones del Juzgado;\nIV. Custodiar los objetos y valores de las Personas Probables Infractoras, previo recibo que expida;\nV. Llevar el control de la correspondencia e integrar y resguardar los expedientes relativos a los procedimientos del Juzgado;\nVI. Recibir el importe de las multas que se impongan, expedir el recibo correspondiente y enterar semanalmente a la Tesorería de la Ciudad de México las cantidades que reciba por este concepto, en los casos en que esta última no tenga establecida oficina recaudadora en la sede donde se ubique el Juzgado, y\nVII. Suplir las ausencias de la Persona Juzgadora.\nArtículo 125.- La remuneración de las Personas Secretarias será equivalente al menos a la categoría básica que corresponda a la Persona Oficial Secretaria del Ministerio Público de la Fiscalía General de Justicia de la Ciudad de México, adscritos a Juzgados del Fuero Común, atendiendo a los criterios del Servicio Público de Carrera, las cargas de trabajo y las responsabilidades asignadas, de conformidad con la disponibilidad presupuestal.\nArtículo 126.- La Persona Médica emitirá los dictámenes de su competencia, prestará la atención médica de emergencia, llevará un Registro de Certificaciones Médicas y en general, realizará las tareas que, acordes\n\ncon su profesión, requiera la Persona Juez en ejercicio de sus funciones.\nCAPÍTULO II\nPROFESIONALIZACIÓN DE LAS PERSONAS JUECES Y SECRETARIOS DE\nLOS JUZGADOS CÍVICOS\nArtículo 127.- Cuando una o más plazas de Persona Juzgadora o Secretaria estuvieran vacantes o se determine crear una o más, la Consejería publicará la convocatoria para que los aspirantes presenten los exámenes correspondientes, en los términos que disponga el Reglamento.\nDicha convocatoria señalará los requisitos a cubrir, según el caso, el día, hora y lugar de celebración del examen y será publicada por una sola vez en la Gaceta Oficial y un extracto de la misma por dos veces consecutivas, con intervalo de tres días, en dos de los periódicos de mayor circulación en la Ciudad de\nMéxico, así como en los Juzgados y en la página electrónica de la Consejería.\nArtículo 128.- La Consejería y la Dirección tienen, en materia de profesionalización de las Personas\nJuzgadoras y Secretarias, las siguientes atribuciones: persona\nI. Practicar los exámenes a los aspirantes a Personas Juzgadoras y Secretarias;\nII. Organizar y evaluar los cursos propedéuticos destinados a las personas aspirantes a ingresar a los Juzgados que hagan los exámenes correspondientes; así como los de actualización y profesionalización de Personas Juzgadoras, Secretarias, y personal de los Juzgados, los cuales deberán contemplar materias jurídicas, administrativas y de contenido cívico;\nIII. Evaluar el desempeño de las funciones de las Personas Juzgadoras, Secretarias y demás personal de los Juzgados, así como el aprovechamiento en los cursos de actualización y profesionalización que les sean impartidos;\nIV. Determinar el procedimiento para el ingreso de guardias y personal auxiliar, y\nV. Las demás que le señale la Ley.\nArtículo 129.- Para ser Persona Juzgadora, se deben reunir los siguientes requisitos:\n\nI. Ser persona mexicana, en pleno ejercicio de sus derechos y tener por lo menos 25 años de edad;\nII. Ser persona licenciada en derecho, con cédula profesional expedida por la autoridad competente y tener por lo menos un año de ejercicio profesional;\nIII. No haber sido condenado en sentencia ejecutoriada por delito intencional;\nIV. No haber sido suspendida o inhabilitada para el desempeño de un cargo público, y\nV. Acreditar los exámenes correspondientes y el curso.\nArtículo 130.- Para ser Persona Secretaria se deben reunir los siguientes requisitos:\nI. Ser persona mexicana en pleno ejercicio de sus derechos; tener por lo menos 20 años de edad;\nII. Ser persona licenciada en derecho, con cédula profesional expedida por la autoridad competente o pasante de esta carrera en los términos de la ley respectiva;\nIII. No haber sido condenado en sentencia ejecutoriada por delito intencional;\nIV. No haber sido suspendida o inhabilitada para el desempeño de un cargo público, y\nV. Acreditar los exámenes correspondientes y el curso.\nCAPÍTULO III\nDE LA SUPERVISIÓN A LOS JUZGADOS\nArtículo 131.- En la supervisión deberá verificarse, independientemente de lo que dicte la Consejería y lo establecido en el Reglamento, cuando menos lo siguiente:\nI. Que exista un estricto control de las boletas con que remitan las personas policías a las personas probables infractoras;\n\nII. Que exista total congruencia entre las boletas de remisión presentadas al juzgado y las reportadas por las personas policías, mediante los mecanismos que determine la Consejería en coordinación con la Secretaría;\nIII. Que los expedientes de cada uno de los procedimientos iniciados estén integrados con la debida motivación y fundamentación aplicable al caso concreto, y conforme a lo establecido por esta Ley y que la actuación del personal del juzgado cívico se lleve a cabo en cumplimiento de los principios de legalidad y debido proceso.\nIV. Que las constancias expedidas por la Persona Juez se refieran a hechos asentados en los registros a su cargo;\nV. Que el entero de las multas impuestas se realice en los términos de esta Ley y conforme al procedimiento respectivo;\nVI. Que se exhiba en lugar visible el contenido de los artículos 26, 27, 28 y 29 de esta Ley, así como los datos relativos a los lugares de recepción de quejas relacionadas con el despacho de los asuntos que son competencia de la Persona Juzgadora;\nVII. Que el Juzgado cuenta con los elementos humanos y materiales suficientes para prestar el servicio;\nVIII. Que los informes a que se refiere esta Ley sean presentados en los términos de la misma, y\nIX. Que en todos los procedimientos se respeten los derechos humanos y las garantías constitucionales de los involucrados.\nArtículo 132.- A la Dirección, en materia de supervisión y vigilancia, le corresponde:\nI. Dictar medidas emergentes para subsanar las irregularidades detectadas en las supervisiones;\nmediante lineamientos que emita la Dirección\nII. Tomar conocimiento de las quejas por parte del personal del Juzgado o del público y en general, de los hechos que redunden en demoras, excesos o deficiencias en el despacho de los asuntos que son competencia de los Juzgados;\n\nIII. Hacer del conocimiento de las autoridades competentes los hechos que puedan dar lugar a responsabilidad penal o administrativa del personal de los Juzgados,\nIV. Habilitar al personal que considere pertinente para realizar supervisiones extraordinarias a los juzgados; y\nV. Llevar a cabo la conciliación entre el entero de las multas impuestas derivadas de las infracciones de esta ley y las cantidades enteradas semanalmente a la Tesorería de la Ciudad de\nMéxico.\nLas quejas a que se refiere la fracción II serán del conocimiento de la Dirección, la que efectuará una investigación y procederá conforme a las disposiciones aplicables.\nPara cumplir con la función de supervisión, control y evaluación de los Juzgados, la Dirección contará con personal de apoyo.\nArtículo 133.- La Dirección determinará el alcance y contenido de las supervisiones extraordinarias.\nArtículo 134.- Las personas a quienes la Persona Juzgadora hubiere impuesto una corrección disciplinaria o medida de apremio que consideren infundada, se les haya retenido injustificadamente o no se les haya permitido la asistencia de persona de su confianza, defensora o traductora, podrán presentar su queja ante el área correspondiente de la Dirección, dentro de los quince días hábiles siguientes a que hayan sucedido estos.\nArtículo 135.- La queja podrá formularse en forma oral o mediante un escrito, no estará sujeta a forma especial alguna, y deberá precisarse el acto que se reclama y los motivos de la queja. Si la persona quejosa contare con pruebas documentales, deberá acompañarlas a su escrito, y podrá ofrecer las demás que estime pertinentes, con excepción de la confesional de la autoridad, observando las reglas establecidas en esta Ley y su Reglamento para las pruebas.\nArtículo 136.- La Dirección se allegará de las pruebas conducentes y ordenará la práctica de las diligencias tendientes al esclarecimiento de los hechos motivo de la queja, así como los derivados de las supervisiones.\nArtículo 137.- En caso de presumirse que el personal del Juzgado actuó con injusticia manifiesta o arbitraria, o violación a las disposiciones de esta Ley y demás disposiciones legales aplicables, la Dirección lo hará del conocimiento a la Secretaría de la Contraloría General de la Ciudad de México y dará vista en su\n\ncaso, al Ministerio Público.\nTÍTULO SÉPTIMO\nREGISTRO DE PERSONAS INFRACTORAS\nCAPÍTULO ÚNICO\nArtículo 138.- El Registro de Personas Infractoras contendrá la información de las personas que hubieran sido sancionadas por la comisión de las infracciones a que se refiere esta Ley y se integrará con los siguientes datos:\nI. Nombre, domicilio, sexo;\nII. Infracciones cometidas;\nIII. Lugares de comisión de la infracción;\nIV. Sanciones impuestas y, en su caso, lugares de cumplimiento del arresto;\nV. Realización de actividades de apoyo a la comunidad, y\nVI. Fotografía de la Persona Infractora.\nLos datos para la integración del registro serán incorporados al mismo por las Personas Juzgadoras; al efecto, en cada Juzgado se instalará el equipo informático necesario.\nArtículo 139.- El Registro de Personas Infractoras será de consulta obligatoria para las Personas Juzgadoras a efecto de obtener los elementos necesarios para motivar la aplicación de sanciones.\nArtículo 140.- El Registro de Personas Infractoras estará a cargo de la Consejería y sólo se proporcionará información de los registros que consten en el mismo, cuando exista mandamiento de autoridad competente que funde y motive su requerimiento.\nArtículo 141.- La información contenida en el Registro de Personas Infractoras tendrá por objeto contar con una base de datos que permita establecer los antecedentes de infracciones cometidas por una persona,\n\npara determinar su reincidencia, el cómputo de horas cumplidas como trabajo a favor de la comunidad, el diseño de las estrategias y acciones tendientes a la preservación del orden y la tranquilidad pública en la\nCiudad de México, así como la instrumentación de programas de desarrollo social y de prevención de adicciones.\nArtículo 142.- Con el fin de asegurar las condiciones de seguridad sobre manejo y acceso a la información del Registro de Personas Infractoras, los responsables de inscribir y los de proporcionar la información deberán tener claves confidenciales a fin de que quede debida constancia de cualquier movimiento de asientos, consultas y otorgamiento de información.\nTRANSITORIOS\nPRIMERO. Publíquese en la Gaceta Oficial de la Ciudad de México.\nSEGUNDO. La presente Ley entrará en vigor al día siguiente de su publicación.\nTERCERO. Se abroga la Ley de Cultura Cívica de la Ciudad de México publicada en la Gaceta Oficial de la\nCiudad de México del 29 de diciembre de 2017.\nCUARTO. Se derogan todas las disposiciones que se opongan a la presente Ley.\nQUINTO. Las autoridades administrativas tendrán un plazo de ciento veinte días para desarrollar el sistema para atender el procedimiento administrativo vía electrónica por infracciones en materia de tránsito; así como lo dispuesto en el segundo párrafo del artículo 34.\nSEXTO. La Jefatura de Gobierno de la Ciudad de México emitirá las disposiciones reglamentarias para el uso del procedimiento administrativo vía electrónica por infracciones en materia de tránsito.\nSÉPTIMO. La Consejería Jurídica emitirá en 90 días los lineamientos sobre las condiciones físicas que deben tener los juzgados cívicos.\nLas Alcaldías deberán llevar a cabo las modificaciones necesarias conforme a los lineamientos en un plazo de 6 meses, enviando un informe a la Consejería y al Congreso de la Ciudad de México.\nOCTAVO.- La Jefatura de Gobierno contará con 120 días para expedir el reglamento de esta Ley.\n\nTRANSITORIOS DEL DECRETO POR EL QUE SE MODIFICA LOS ARTÍCULOS 26, 27 Y 32 DEL DECRETO POR EL\nQUE SE EXPIDE LA LEY DE CULTURA CÍVICA DE LA CIUDAD DE MÉXICO Y SE ABROGA LA LEY DE CULTURA\nCÍVICA DE LA CIUDAD DE MÉXICO, DEL 29 DE DICIEMBRE DE 2017, PUBLICADO EN LA GACETA EL DÍA 07\nDE JUNIO DE 2019.\nÚNICO. Remítase a la Jefa de Gobierno, para su conocimiento y efectos legales.\nPalacio Legislativo del Congreso de la Ciudad de México, a los catorce días del mes de marzo del año dos mil diecinueve.- POR LA MESA DIRECTIVA.- DIPUTADO JOSÉ DE JESÚS MARTÍN DEL CAMPO CASTAÑEDA,\nPRESIDENTE.- DIPUTADA ISABELA ROSALES HERRERA, SECRETARIA.- DIPUTADA ANA PATRICIA BAEZ\nGUERRERO, SECRETARIA.- (Firmas)\nTRANSITORIOS DEL DECRETO POR EL SE REFORMAN Y ADICIONAN, DIVERSAS DISPOSICIONES DEL CÓDIGO\nPENAL DEL DISTRITO FEDERAL Y DE LA LEY DE CULTURA CÍVICA DE LA CIUDAD DE MÉXICO, PUBLICADO EN\nLA GACETA OFIFICAL DE LA CIUDAD DE MÉXICO EL 1° DE AGOSTO DE 2019.\nPRIMERO: El presente decreto entrará en vigor al día siguiente de su publicación en la Gaceta Oficial de la\nCiudad de México.\nSEGUNDO: Publíquese en la Gaceta Oficial de la Ciudad de México.\nPalacio Legislativo del Congreso de la Ciudad de México, a los treinta días del mes de julio del año dos mil diecinueve.- POR LA MESA DIRECTIVA.-DIPUTADO JOSÉ DE JESÚS MARTÍN DEL CAMPO\nCASTAÑEDA,PRESIDENTE.- DIPUTADA ISABELA ROSALES HERRERA, SECRETARIA.- DIPUTADA ANA PATRICIA\nBAEZ GUERRERO, SECRETARIA.- (Firmas)\nCon fundamento en lo dispuesto por los artículos 122, Apartado A, fracción III, de la Constitución Política de los Estados Unidos Mexicanos; 32 apartado C, numeral 1, inciso a) de la Constitución Política de la\nCiudad de México; 2, 3, fracciones XVII y XVIII, 7, 10 fracción II, 12 y 21 párrafo primero de la Ley Orgánica del Poder Ejecutivo y de la Administración Pública de la Ciudad de México; para su debida publicación y observancia, expido el presente Decreto Promulgatorio en la Residencia Oficial de la Jefatura de Gobierno de la Ciudad de México, el primer día del mes de agosto del año dos mil diecinueve.- LA JEFA DE GOBIERNO\nDE LA CIUDAD DE MÉXICO, DRA. CLAUDIA SHEINBAUM PARDO.- FIRMA.- LA SECRETARIA DE GOBIERNO,\n\nROSA ICELA RODRÍGUEZ VELÁZQUEZ.- FIRMA.- LA SECRETARIA DE LAS MUJERES, GABRIELA RODRÍGUEZ\nRAMÍREZ.- FIRMA.- EL SECRETARIO DE SEGURIDAD CIUDADANA, JESÚS ORTA MARTÍNEZ.- FIRMA.\nTRANSITORIOS DEL DECRETO POR EL QUE SE MODIFICA EL ARTÍCULO 206 DEL CÓDIGO PENAL PARA EL\nDISTRITO FEDERAL. SE REFORMA EL ARTICULO 12 DE LA LEY PARA PREVENIR Y ELIMINAR LA\nDISCRIMINACIÓN DE LA CIUDAD DE MÉXICO. SE MODIFICA LA FRACCIÓN I DEL ARTÍCULO 26 DE LA LEY DE\nCULTURA CÍVICA DE LA CIUDAD DE MÉXICO. SE MODIFICA EL PRIMER PÁRRAFO DEL ARTÍCULO 10, 65 Y 66\nPÁRRAFO PRIMERO Y SE ADICIONA LA FRACCIÓN VIII BIS, AL APARTADO A, DEL ARTÍCULO 10, TODOS DE LA\nLEY DE ESTABLECIMIENTOS MERCANTILES PARA LA CIUDAD DE MÉXICO. SE MODIFICA EL PÁRRAFO\nPRIMERO DEL ARTÍCULO 7 Y SE LE ADICIONA LA FRACCIÓN I BIS AL ARTÍCULO 49, TODOS DE LA LEY DE\nRESPONSABILIDADES ADMINISTRATIVAS DE LA CIUDAD DE MÉXICO. SE MODIFICA EL PRIMER PÁRRAFO Y\nSE ADICIONA LA FRACCIÓN III BIS, AMBAS AL ARTÍCULO 5 DE LA LEY DE PROTECCIÓN Y FOMENTO AL\nEMPLEO DEL DISTRITO FEDERAL. Y SE ADICIONA LA FRACCIÓN XXXVIII BIS AL ARTÍCULO 9, LA FRACCIÓN VII\nAL ARTÍCULO 77, LA FRACCIÓN XI AL ARTÍCULO 86, LA FRACCIÓN XIX AL ARTÍCULO 129, Y SE MODIFICAN\nLAS FRACCIONES V Y VI DEL ARTÍCULO 77, LAS FRACCIONES IX Y X DEL ARTÍCULO 86, EL ARTÍCULO 117, LAS\nFRACCIONES XVII Y XVIII DEL ARTÍCULO 129, TODOS DE LA LEY DE EDUCACIÓN DE LA CIUDAD DE MÉXICO;\nPUBLICADO EN LA GACETA OFICIAL DE LA CIUDAD DE MÉXICO, EL 15 DE JUNIO DE 2022.\nPrimero. - Remítase a la persona titular de la Jefatura de Gobierno, para su promulgación y publicación en la Gaceta Oficial de la Ciudad de México.\nSegundo. - El presente Decreto entrará en vigor al día siguiente al de su publicación en la Gaceta Oficial de la Ciudad de México.\nPalacio Legislativo del Congreso de la Ciudad de México, a los nueve días del mes de junio del año dos mil veintidós. POR LA MESA DIRECTIVA, DIPUTADO HÉCTOR DIAZ POLANCO, PRESIDENTE.- DIPUTADA MARCELA\nFUENTE CASTILLO, SECRETARIA.- DIPUTADA FRIDA JIMENA GUILLÉN ORTIZ, SECRETARIA.- (Firmas)\nCon fundamento en lo dispuesto por los artículos 122, apartado A, fracción III de la Constitución Política de los Estados Unidos Mexicanos; 32, apartado C, numeral 1, inciso a) de la Constitución Política de la Ciudad de México; 2 párrafo segundo, 3 fracciones XVII y XVIII, 7 párrafo primero, 10 fracción II, 12 y 21 párrafo primero de la Ley Orgánica del Poder Ejecutivo y de la Administración Pública de la Ciudad de México; para su debida publicación y observancia, expido el presente Decreto Promulgatorio en la Residencia Oficial de la Jefatura de Gobierno de la Ciudad de México, a los catorce días del mes de junio del año dos mil veintidós.- LA JEFA DE GOBIERNO DE LA CIUDAD DE MÉXICO, DRA. CLAUDIA SHEINBAUM PARDO.- FIRMA.-\nEL SECRETARIO DE GOBIERNO, MARTÍ BATRES GUADARRAMA.- FIRMA.- LA SECRETARIA DE\n\nADMINISTRACIÓN Y FINANZAS, LUZ ELENA GONZÁLEZ ESCOBAR.- FIRMA.- EL SECRETARIO DE LA\nCONTRALORÍA GENERAL, JUAN JOSÉ SERRANO MENDOZA.- FIRMA.- LA SECRETARIA DE CULTURA, CLAUDIA\nSTELLA CURIEL DE ICAZA.- FIRMA.- EL SECRETARIO DE DESARROLLO ECONÓMICO, FADLALA AKABANI\nHNEIDE.- FIRMA.- LA SECRETARIA DE EDUCACIÓN, CIENCIA, TECNOLOGÍA E INNOVACIÓN, ROSAURA RUIZ\nGUTIÉRREZ.- FIRMA.- LA SECRETARIA DE GESTIÓN INTEGRAL DE RIESGOS Y PROTECCIÓN CIVIL, MYRIAM\nVILMA URZÚA VENEGAS.- FIRMA.- EL SECRETARIO DE INCLUSIÓN Y BIENESTAR SOCIAL, CARLOS ALBERTO\nULLOA PÉREZ.- FIRMA.- LA SECRETARIA DEL MEDIO AMBIENTE, MARINA ROBLES GARCÍA.- FIRMA.- EL\nSECRETARIO DE MOVILIDAD, ANDRÉS LAJOUS LOAEZA.- FIRMA.- LA SECRETARIA DE LAS MUJERES, INGRID\nGÓMEZ SARACÍBAR.- FIRMA.- EL SECRETARIO DE OBRAS Y SERVICIOS, JESÚS ANTONIO ESTEVA MEDINA.-\nFIRMA.- LA SECRETARIA DE PUEBLOS Y BARRIOS ORIGINARIOS Y COMUNIDADES INDÍGENAS RESIDENTES,\nLAURA ITA ANDEHUI RUIZ MONDRAGÓN.- FIRMA.- LA SECRETARIA DE SALUD, OLIVA LÓPEZ ARELLANO.-\nFIRMA.- EL SECRETARIO DE SEGURIDAD CIUDADANA, OMAR HAMID GARCÍA HARFUCH.- FIRMA.- EL\nSECRETARIO DE TRABAJO Y FOMENTO AL EMPLEO, JOSÉ LUIS RODRÍGUEZ DÍAZ DE LEÓN.- FIRMA.- LA\nSECRETARIA DE TURISMO, REBECA OLIVIA SÁNCHEZ SANDÍN.- FIRMA.- EL CONSEJERO JURÍDICO, NÉSTOR\nVARGAS SOLANO.- FIRMA.-\nTRANSITORIOS DEL DECRETO POR EL QUE SE DEROGA LA FRACCIÓN III DEL ARTÍCULO 28; SE MODIFICA EL\nPÁRRAFO SEGUNDO Y SE ADICIONAN LOS PÁRRAFOS TERCERO, CUARTO, QUINTO Y SEXTO,\nRECORRIÉNDOSE LOS DEMÁS EN SU ORDEN, DEL ARTÍCULO 53 DE LA LEY DE CULTURA CÍVICA DE LA\nCIUDAD DE MÉXICO, PUBLICADO EN LA GACETA OFICIAL DE LA CIUDAD DE MÉXICO, EL 12 DE DICIEMBRE\nDE 2022.\nPrimero. - Remítase a la persona Titular de la Jefatura de Gobierno de la Ciudad de México, para su promulgación y publicación en la Gaceta Oficial de la Ciudad de México.\nSegundo. - El presente Decreto entrará en vigor al día siguiente de su publicación en la Gaceta Oficial de la\nCiudad de México.\nTercero. - Se derogan las disposiciones que se opongan al presente ordenamiento.\nPalacio Legislativo del Congreso de la Ciudad de México, a los quince días del mes de noviembre del año dos mil veintidós.- POR LA MESA DIRECTIVA.- DIPUTADO FAUSTO MANUEL ZAMORANO ESPARZA,\nPRESIDENTE.- DIPUTADA MARCELA FUENTE CASTILLO, SECRETARIA.- DIPUTADA MARIA GABRIELA SALIDO\nMAGOS, SECRETARIA.- (Firmas)\n\nCon fundamento en lo dispuesto por los artículos 122, apartado A, fracción III de la Constitución Política de los Estados Unidos Mexicanos; 32, apartado C, numeral 1, inciso a) de la Constitución Política de la Ciudad de México; 2 párrafo segundo, 3 fracciones XVII y XVIII, 7 párrafo primero, 10 fracción II, 12 y 21 párrafo primero de la Ley Orgánica del Poder Ejecutivo y de la Administración Pública de la Ciudad de México; para su debida publicación y observancia, expido el presente Decreto Promulgatorio en la Residencia Oficial de la Jefatura de Gobierno de la Ciudad de México, a los nueve días del mes de diciembre del año dos mil veintidós.- LA JEFA DE GOBIERNO DE LA CIUDAD DE MÉXICO, DRA. CLAUDIA SHEINBAUM PARDO.- FIRMA.-\nEL SECRETARIO DE INCLUSIÓN Y BIENESTAR SOCIAL, RIGOBERTO SALGADO VÁZQUEZ.- FIRMA.- EL\nSECRETARIO DE SEGURIDAD CIUDADANA, OMAR HAMID GARCÍA HARFUCH.- FIRMA.- EL CONSEJERO\nJURÍDICO Y DE SERVICIOS LEGALES, NÉSTOR VARGAS SOLANO.- FIRMA.\nTRANSITORIOS DEL DECRETO POR EL QUE SE SE ADICIONAN LOS ARTÍCULOS 226 BIS, 226 TER, 350 QUÁTER\nY 350 QUINQUIES, ASÍ COMO UN PÁRRAFO CUARTO Y QUINTO RECORRIÉNDOSE EL SUBSECUENTE DEL\nARTÍCULO 350 TER; ASIMISMO, SE REFORMAN LOS ARTÍCULOS 350 BIS Y 350 TER; TODOS DEL CÓDIGO\nPENAL PARA EL DISTRITO FEDERAL. SE REFORMAN LAS FRACCIONES III Y IX DEL ARTÍCULO 24, EL PÁRRAFO\nSEGUNDO DEL ARTÍCULO 24 BIS, LAS FRACCIONES XXIV Y XXV DEL ARTÍCULO 25, LA FRACCIÓN III DEL\nARTÍCULO 63, LA FRACCIÓN I Y LOS INCISOS B) Y C) DE LA FRACCIÓN III DEL ARTÍCULO 65; ASIMISMO; SE\nADICIONAN LAS FRACCIONES X Y XI RECORRIÉNDOSE LAS SUBSECUENTES, AL ARTÍCULO 24, UN PÁRRAFO\nTERCERO AL ARTÍCULO 24 BIS, LAS FRACCIONES XXVI, XXVII Y XXVIII AL ARTÍCULO 25; UNA FRACCIÓN III BIS\nAL ARTÍCULO 63; Y EL INCISO D) A LA FRACCIÓN III DEL ARTÍCULO 65, TODOS DE LA LEY DE PROTECCIÓN A\nLOS ANIMALES DE LA CIUDAD DE MÉXICO. SE REFORMAN LAS FRACCIONES XIV Y XV, SE ADICIONA LA\nFRACCIÓN XVI, TODOS DEL ARTÍCULO 29, SE REFORMA EL NUMERAL 29 DEL ARTÍCULO 32 DE LA LEY DE\nCULTURA CÍVICA DE LA CIUDAD DE MÉXICO, PUBLICADO EN LA GACETA OFICIAL DE LA CIUDAD DE MÉXICO,\nEL 1 DE MARZO DE 2023.\nPRIMERO. Remítase el presente Decreto a la persona titular de la Jefatura de Gobierno para su promulgación y publicación en la Gaceta Oficial de la Ciudad de México.\nSEGUNDO. El presente Decreto entrará en vigor al día siguiente de su publicación en la Gaceta Oficial de la\nCiudad de México.\nTERCERO. Dentro de un plazo de 180 días naturales, posteriores a la publicación del presente Decreto, la persona titular de la Jefatura de Gobierno deberá realizar las adecuaciones reglamentarias y normativas correspondientes con la finalidad de dar cumplimiento al mismo.\n\nPalacio Legislativo del Congreso de la Ciudad de México, a los dos días del mes de febrero del año dos mil veintitrés.- POR LA MESA DIRECTIVA.- DIPUTADO FAUSTO MANUEL ZAMORANO ESPARZA, PRESIDENTE.-\nDIPUTADA MARCELA FUENTE CASTILLO, SECRETARIA.- DIPUTADA MARIA GABRIELA SALIDO MAGOS,\nSECRETARIA.- (Firmas)\nCon fundamento en lo dispuesto por los artículos 122, apartado A, fracción III de la Constitución Política de los Estados Unidos Mexicanos; 32, apartado C, numeral 1, inciso a) de la Constitución Política de la Ciudad de México; 2 párrafo segundo, 3 fracciones XVII y XVIII, 7 párrafo primero, 10 fracción II, 12 y 21 párrafo primero de la Ley Orgánica del Poder Ejecutivo y de la Administración Pública de la Ciudad de México; para su debida publicación y observancia, expido el presente Decreto Promulgatorio en la Residencia Oficial de la Jefatura de Gobierno de la Ciudad de México, a los dieciocho días del mes de enero del año dos mil veintitrés.- LA JEFA DE GOBIERNO DE LA CIUDAD DE MÉXICO, DRA. CLAUDIA SHEINBAUM PARDO.- FIRMA.-\nEL SECRETARIO DE GOBIERNO, MARTÍ BATRES GUADARRAMA.- FIRMA.-LA SECRETARIA DEL MEDIO\nAMBIENTE, MARINA ROBLES GARCÍA.- FIRMA.- LA SECRETARIA DE SALUD, OLIVA LÓPEZ ARELLANO.- FIRMA.-\nEL SECRETARIO DE SEGURIDAD CIUDADANA, OMAR HAMID GARCÍA HARFUCH.- FIRMA.",
  "ordenamiento": "Marco Jurídico",
  "jurisdiccion": "CIUDAD DE MEXICO",
  "fuente_oficial": "Congreso de la Ciudad de México",
  "status": "Vigente",
  "Fecha de Publicación": "15-03-2023",
  "Fecha de Última Reforma": "01 de marzo de 2023",
  "numero_paginas": 69,
  "es_escaneado": false,
  "tiene_tablas": true,
  "url": "https://www.congresocdmx.gob.mx/archivo-2d138a1bf3bd98b883c46c3572754fad44a97a75.pdf",
  "materia": [
    "administrativo",
    "cultura cívica"
  ]
}