{
  "titulo": "Ley de Hidrocarburos",
  "Contenido": "TEXTO VIGENTE\nAl margen un sello con el Escudo Nacional, que dice: Estados Unidos Mexicanos.- Presidencia de la República.\nENRIQUE PEÑA NIETO, Presidente de los Estados Unidos Mexicanos, a sus habitantes sabed:\nQue el Honorable Congreso de la Unión, se ha servido dirigirme el siguiente\nDECRETO \"EL CONGRESO GENERAL DE LOS ESTADOS UNIDOS MEXICANOS, DECRETA:\nSE EXPIDE LA LEY DE HIDROCARBUROS Y SE REFORMAN DIVERSAS DISPOSICIONES DE LA LEY DE INVERSIÓN EXTRANJERA; LEY MINERA, Y LEY DE ASOCIACIONES PÚBLICO PRIVADAS ARTÍCULO PRIMERO. Se expide la Ley de Hidrocarburos.\nLEY DE HIDROCARBUROS\nTÍTULO PRIMERO\nDisposiciones Generales\nArtículo 1.- La presente Ley es reglamentaria de los artículos 25, párrafo cuarto; 27, párrafo séptimo y 28, párrafo cuarto de la Constitución Política de los Estados Unidos Mexicanos, en materia de Hidrocarburos.\nCorresponde a la Nación la propiedad directa, inalienable e imprescriptible de todos los Hidrocarburos que se encuentren en el subsuelo del territorio nacional, incluyendo la plataforma continental y la zona económica exclusiva situada fuera del mar territorial y adyacente a éste, en mantos o yacimientos, cualquiera que sea su estado físico.\nPara los efectos de esta Ley, se considerarán yacimientos transfronterizos aquéllos que se encuentren dentro de la jurisdicción nacional y tengan continuidad física fuera de ella.\nnacional, compartidos con otros países de acuerdo con los tratados en que México sea parte, o bajo lo dispuesto en la Convención de las Naciones Unidas sobre Derecho del Mar.\nArtículo 2.- Esta Ley tiene por objeto regular las siguientes actividades en territorio nacional:\nI. El Reconocimiento y Exploración Superficial, y la Exploración y Extracción de Hidrocarburos;\nII. El Tratamiento, refinación, enajenación, comercialización, Transporte y Almacenamiento del Petróleo;\nIII. El procesamiento, compresión, licuefacción, descompresión y regasificación, así como el Transporte, Almacenamiento, Distribución, comercialización y Expendio al Público de Gas\nNatural;\nIV. El Transporte, Almacenamiento, Distribución, comercialización y Expendio al Público de Petrolíferos, y\nV. El Transporte por ducto y el Almacenamiento que se encuentre vinculado a ductos, de Petroquímicos.\nArtículo 3.- De conformidad con lo dispuesto en los artículos 25, párrafo cuarto, 27, párrafo séptimo y 28, párrafo cuarto de la Constitución Política de los Estados Unidos Mexicanos, la Nación llevará a cabo la Exploración y Extracción de los Hidrocarburos, en los términos de esta Ley.\nLa Exploración y Extracción de Hidrocarburos en los yacimientos transfronterizos a que se refiere el artículo 1 de esta Ley podrá llevarse a cabo en los términos de los tratados y acuerdos en los que México sea parte, celebrados por el Presidente de la República y ratificados por la Cámara de Senadores.\nArtículo 4.- Para los efectos de esta Ley se entenderá, en singular o plural, por:\nI. Agencia: Agencia Nacional de Seguridad Industrial y de Protección al Medio Ambiente del Sector Hidrocarburos;\nII. Almacenamiento: Depósito y resguardo de Hidrocarburos, Petrolíferos y Petroquímicos en depósitos e instalaciones confinados que pueden ubicarse en la superficie, el mar o el subsuelo;\nIII. Área Contractual: La superficie y profundidad determinadas por la Secretaría de Energía, así como las formaciones geológicas contenidas en la proyección vertical en dicha superficie para dicha profundidad, en las que se realiza la Exploración y Extracción de Hidrocarburos a través de la celebración de Contratos para la Exploración y Extracción;\nIV. Área de Asignación: La superficie y profundidad determinadas por la Secretaría de Energía, así como las formaciones geológicas contenidas en la proyección vertical en dicha superficie para dicha profundidad, en las que se realiza la Exploración y Extracción de Hidrocarburos a través de una Asignación;\nV. Asignación: El acto jurídico administrativo mediante el cual el Ejecutivo Federal otorga exclusivamente a un Asignatario el derecho para realizar actividades de Exploración y Extracción de Hidrocarburos en el Área de Asignación, por una duración específica;\nVI. Asignatario: Petróleos Mexicanos o cualquier otra empresa productiva del Estado que sea titular de una Asignación y operador de un Área de Asignación;\nVII. Autorizado: El titular de una autorización en términos de esta Ley;\nVIII. Cadena Productiva: Conjunto de agentes económicos que participan directamente en la proveeduría, suministro, construcción y prestación de bienes y servicios para la industria de Hidrocarburos;\nIX. Contrato para la Exploración y Extracción: Acto jurídico que suscribe el Estado Mexicano, a través de la Comisión Nacional de Hidrocarburos, por el que se conviene la Exploración y Extracción de Hidrocarburos en un Área Contractual y por una duración específica;\nX. Contratista: Petróleos Mexicanos, cualquier otra empresa productiva del Estado o Persona\nMoral, que suscriba con la Comisión Nacional de Hidrocarburos un Contrato para la Exploración y Extracción, ya sea de manera individual o en consorcio o asociación en participación, en términos de la Ley de Ingresos sobre Hidrocarburos;\nXI. Distribución: Actividad logística relacionada con la repartición, incluyendo el traslado, de un determinado volumen de Gas Natural o Petrolíferos desde una ubicación determinada hacia uno o varios destinos previamente asignados, para su Expendio al Público o consumo final;\nXII. Ductos de Internación: Aquella infraestructura cuya capacidad esté destinada principalmente a conectar al país con infraestructura de Transporte o Almacenamiento de acceso abierto que se utilice para importar Gas Natural;\nXIII. Expendio al Público: La venta al menudeo directa al consumidor de Gas Natural o Petrolíferos, entre otros combustibles, en instalaciones con fin específico o multimodal, incluyendo estaciones de servicio, de compresión y de carburación, entre otras;\nXIV. Exploración: Actividad o conjunto de actividades que se valen de métodos directos, incluyendo la perforación de pozos, encaminadas a la identificación, descubrimiento y evaluación de Hidrocarburos en el Subsuelo, en un área definida;\nXV. Extracción: Actividad o conjunto de actividades destinadas a la producción de Hidrocarburos, incluyendo la perforación de pozos de producción, la inyección y la estimulación de yacimientos, la recuperación mejorada, la Recolección, el acondicionamiento y separación de Hidrocarburos, la eliminación de agua y sedimentos, dentro del Área Contractual o de Asignación, así como la construcción, localización, operación, uso, abandono y desmantelamiento de instalaciones para la producción;\nXVI. Gas Licuado de Petróleo: Aquél que es obtenido de los procesos de refinación del Petróleo y de las plantas procesadoras de Gas Natural, y está compuesto principalmente de gas butano y propano;\nXVII. Gas Natural: La mezcla de gases que se obtiene de la Extracción o del procesamiento industrial y que es constituida principalmente por metano. Usualmente esta mezcla contiene etano, propano, butanos y pentanos. Asimismo, puede contener dióxido de carbono, nitrógeno y ácido sulfhídrico, entre otros. Puede ser Gas Natural Asociado, Gas Natural No Asociado o gas asociado al carbón mineral;\nXVIII. Gas Natural Asociado: Gas Natural disuelto en el Petróleo de un yacimiento, bajo las condiciones de presión y de temperatura originales;\nXIX. Gas Natural No Asociado: Gas Natural que se encuentra en yacimientos que no contienen\nPetróleo a las condiciones de presión y temperatura originales;\nXX. Hidrocarburos: Petróleo, Gas Natural, condensados, líquidos del Gas Natural e hidratos de metano;\nXXI. Hidrocarburos en el Subsuelo: Los recursos totales o cantidades totales de Hidrocarburos con ocurrencia natural, antes de iniciar su producción, así como aquellas cantidades estimadas en acumulaciones aún por descubrir;\nXXII. Instituto: Instituto de Administración y Avalúos de Bienes Nacionales;\nXXIII. Particular: Persona física o Persona Moral;\nXXIV. Permisionario: Petróleos Mexicanos, cualquier otra empresa productiva del Estado o entidad paraestatal, o cualquier Particular que sea titular de un permiso para la realización de las actividades previstas en esta Ley;\nXXV. Persona Moral: Sociedad mercantil constituida de conformidad con la legislación mexicana;\nXXVI. Petróleo: Mezcla de carburos de hidrógeno que existe en fase líquida en los yacimientos y permanece así en condiciones originales de presión y temperatura. Puede incluir pequeñas cantidades de substancias que no son carburos de hidrógeno;\nXXVII. Petróleos Mexicanos: Petróleos Mexicanos y sus empresas productivas subsidiarias;\nXXVIII. Petrolíferos: Productos que se obtienen de la refinación del Petróleo o del procesamiento del Gas Natural y que derivan directamente de Hidrocarburos, tales como gasolinas, diésel, querosenos, combustóleo y Gas Licuado de Petróleo, entre otros, distintos de los Petroquímicos;\nXXIX. Petroquímicos: Aquellos líquidos o gases que se obtienen del procesamiento del Gas Natural o de la refinación del Petróleo y su transformación, que se utilizan habitualmente como materia prima para la industria;\nXXX. Procesamiento de Gas Natural: Separación del Gas Natural de otros gases o líquidos para su transformación o comercialización;\nXXXI. Recolección: Acopio de los Hidrocarburos de cada pozo del yacimiento una vez que han sido extraídos del subsuelo, mediante un sistema de líneas de descarga que van desde el cabezal de los pozos hasta las primeras baterías de separación o, en su caso, hasta los sistemas de transporte;\nXXXII. Reconocimiento y Exploración Superficial: Todos aquellos estudios de evaluación que se valen únicamente de actividades sobre la superficie del terreno o del mar para considerar la posible existencia de Hidrocarburos en un área determinada; dentro de éstos se incluyen los trabajos para la adquisición, el procesamiento, reprocesamiento o interpretación de información;\nXXXIII. Recursos Contingentes: El volumen estimado de Hidrocarburos en una fecha dada, que potencialmente es recuperable pero que, bajo condiciones económicas de evaluación correspondientes a la fecha de estimación, no se considera comercialmente recuperable debido a una o más contingencias;\nXXXIV. Recursos Prospectivos: El volumen de Hidrocarburos estimado a una fecha determinada, que todavía no se descubre pero que ha sido inferido y que se estima potencialmente recuperable, mediante la aplicación de proyectos de desarrollo futuros;\nXXXV. Reservas: El volumen de Hidrocarburos en el subsuelo, calculado a una fecha dada a condiciones atmosféricas, que se estima será producido técnica y económicamente, bajo el régimen fiscal aplicable, con cualquiera de los métodos y sistemas de Extracción aplicables a la fecha de evaluación;\nXXXVI. Sistema Integrado: Sistemas de Transporte por ducto y de Almacenamiento interconectados, de los servicios que permiten la coordinación operativa entre las diferentes instalaciones;\nXXXVII. Temporada Abierta: El procedimiento regulado por la Comisión Reguladora de Energía que, con el propósito de brindar equidad y transparencia en la asignación o adquisición de capacidad disponible a terceros de un sistema o de un nuevo proyecto o con motivo de una renuncia permanente de capacidad reservada, debe realizar un Permisionario de Transporte,\nAlmacenamiento o Distribución de Hidrocarburos, Petrolíferos y Petroquímicos para ponerla a disposición del público, a efecto de reasignar capacidad o determinar las necesidades de expansión o ampliación de capacidad;\nXXXVIII. Transporte: La actividad de recibir, entregar y, en su caso, conducir Hidrocarburos,\nPetrolíferos y Petroquímicos, de un lugar a otro por medio de ductos u otros medios, que no conlleva la enajenación o comercialización de dichos productos por parte de quien la realiza a través de ductos. Se excluye de esta definición la Recolección y el desplazamiento de Hidrocarburos dentro del perímetro de un Área Contractual o de un Área de Asignación, así como la Distribución;\nXXXIX. Tratamiento: Acondicionamiento del Petróleo que comprende todos los procesos industriales realizados fuera de un Área Contractual o de un Área de Asignación y anteriores a la refinación, y XL. Zona de Salvaguarda: Área de reserva en la que el Estado prohíbe las actividades de Exploración y Extracción de Hidrocarburos.\nArtículo 5.- Las actividades de Exploración y Extracción de Hidrocarburos, a que se refiere la fracción\nI del artículo 2 de esta Ley, se consideran estratégicas en los términos del párrafo cuarto del artículo 28 de la Constitución Política de los Estados Unidos Mexicanos. Sólo la Nación las llevará a cabo, por conducto de Asignatarios y Contratistas, en términos de la presente Ley.\nLas actividades de Reconocimiento y Exploración Superficial, así como las actividades referidas en las fracciones II a V del artículo 2 de esta Ley, podrán ser llevadas a cabo por Petróleos Mexicanos, cualquier otra empresa productiva del Estado o entidad paraestatal, así como por cualquier persona, previa autorización o permiso, según corresponda, en los términos de la presente Ley y de las disposiciones reglamentarias, técnicas y de cualquier otra regulación que se expida.\nTÍTULO SEGUNDO\nDe la Exploración y Extracción de Hidrocarburos y del Reconocimiento y Exploración\nSuperficial\nCapítulo I\nDe las Asignaciones\nArtículo 6.- El Ejecutivo Federal, por conducto de la Secretaría de Energía, podrá otorgar y modificar a Petróleos Mexicanos o a cualquier otra empresa productiva del Estado, de manera excepcional,\nAsignaciones para realizar la Exploración y Extracción de Hidrocarburos.\nPara el otorgamiento de una Asignación, la Secretaría de Energía deberá motivar que se trata del Hidrocarburos y que el posible Asignatario tiene la capacidad técnica, financiera y de ejecución para extraer los Hidrocarburos de forma eficiente y competitiva.\nPrevio al otorgamiento de las Asignaciones, la Secretaría de Energía deberá contar con opinión favorable de la Comisión Nacional de Hidrocarburos, la cual será emitida a través de un dictamen técnico.\nLos títulos de Asignación que otorgue la Secretaría de Energía incluirán, entre otros, los siguientes elementos:\nI. El Área de Asignación;\nII. Los términos y condiciones que deberán observarse en la Exploración y en la Extracción de Hidrocarburos;\nIII. Las condiciones y los mecanismos para la reducción o devolución del Área de Asignación;\nIV. La vigencia, así como las condiciones para su prórroga;\nV. La adquisición de garantías y seguros;\nVI. El porcentaje mínimo de contenido nacional, y\nVII. El plazo para que el Asignatario presente a la Comisión Nacional de Hidrocarburos, para su aprobación, el plan de Exploración o el plan de desarrollo para la Extracción, según corresponda.\nLos términos y condiciones podrán ser modificados por la Secretaría de Energía, previa opinión de la Comisión Nacional de Hidrocarburos.\nEn el supuesto de que la Secretaría de Energía modifique el título de una Asignación, y únicamente en caso de que dicha modificación impacte o modifique a su vez el plan de Exploración o el plan de desarrollo para la Extracción, se requerirá la presentación del plan modificado de que se trate, por parte del Asignatario, a la Comisión Nacional de Hidrocarburos para su aprobación.\nArtículo 7.- En materia de Asignaciones, corresponderá a la Comisión Nacional de Hidrocarburos:\nI. Apoyar técnicamente a la Secretaría de Energía en la selección del Área de Asignación;\nII. Administrar técnicamente y supervisar el cumplimiento de los términos y condiciones de las mismas, y\nIII. Aprobar los planes de Exploración y de desarrollo para la Extracción, así como sus modificaciones.\nArtículo 8.- Petróleos Mexicanos o las demás empresas productivas del Estado, únicamente podrán ceder una Asignación de la que sean titulares, cuando el cesionario sea otra empresa productiva del Estado, previa autorización de la Secretaría de Energía.\nHidrocarburos podrá renunciar a la Asignación correspondiente. Para lo anterior deberá contar con la aprobación de la Secretaría de Energía y dar aviso a la Comisión Nacional de Hidrocarburos.\nEn el supuesto previsto en el párrafo anterior, el Área de Asignación será devuelta al Estado, sin cargo, pago, ni indemnización alguna por parte de éste, y la Secretaría de Energía podrá determinar su operación en los términos que considere convenientes conforme a esta Ley.\nAsignatario.\nArtículo 9.- Para cumplir con el objeto de las Asignaciones que les otorgue el Ejecutivo Federal,\nPetróleos Mexicanos y las demás empresas productivas del Estado, sólo podrán celebrar con Particulares contratos de servicios para las actividades relacionadas con dichas Asignaciones, bajo esquemas que les permitan la mayor productividad y rentabilidad, siempre que la contraprestación se realice en efectivo.\nDichas contrataciones se llevarán a cabo conforme a lo dispuesto en la Ley de Petróleos Mexicanos o la que regule a la respectiva empresa productiva del Estado.\nArtículo 10.- El Ejecutivo Federal, por conducto de la Secretaría de Energía, podrá revocar una Asignación y recuperar el Área de Asignación cuando se presente alguna de las siguientes causas graves:\nI. Que, por más de ciento ochenta días naturales de forma continua, el Asignatario no inicie o suspenda las actividades previstas en el plan de Exploración o de desarrollo para la Extracción en el Área de Asignación, sin causa justificada ni autorización de la Comisión\nNacional de Hidrocarburos en los términos que establezca el título de Asignación;\nII. Que el Asignatario no cumpla con el compromiso mínimo de trabajo, sin causa justificada, conforme a los términos y condiciones de la Asignación otorgada;\nIII. Que se presente un accidente grave causado por dolo o culpa del Asignatario, que ocasione daño a instalaciones, fatalidad y pérdida de producción;\nIV. Que el Asignatario en más de una ocasión remita de forma dolosa o injustificada, información o reportes falsos o incompletos, o los oculte, a las Secretarías de Energía, de Hacienda y Crédito Público o de Economía, a la Comisión Nacional de Hidrocarburos o a la Agencia, respecto de la producción, costos o cualquier otro aspecto relevante de la Asignación, o\nV. Las demás causales que se establezcan en el título de Asignación.\nLa revocación requerirá notificación previa al Asignatario de la causal o causales que se invoquen y se regirá por la presente Ley y su Reglamento. Una vez notificada la causal, el Asignatario tendrá un máximo de treinta días naturales, contados a partir de la fecha de la notificación, para exponer lo que a su derecho convenga y aportar, en su caso, las pruebas que estime pertinentes.\nTranscurrido el plazo a que se refiere el párrafo anterior, la Secretaría de Energía contará con un plazo de noventa días naturales para resolver considerando los argumentos y pruebas que, en su caso, hubiere hecho valer el Asignatario. La determinación de revocar o no la Asignación deberá ser debidamente fundada, motivada y comunicada al Asignatario.\nEnergía emita la resolución respectiva, el procedimiento iniciado quedará sin efecto, previa aceptación y verificación de la Secretaría de Energía y aplicando, en su caso, las penas correspondientes conforme a lo dispuesto en la presente Ley.\nComo consecuencia de la revocación, el Asignatario transferirá al Estado sin cargo, pago, ni indemnización alguna y en buenas condiciones el Área de Asignación. Asimismo, se procederá a realizar establecidas en el título de la Asignación.\nEn cualquier caso, el Asignatario mantendrá la propiedad de los bienes e instalaciones que no sean conexos o accesorios exclusivos del área recuperada.\nLa revocación a que se refiere este artículo, no exime al Asignatario de la obligación de resarcir aquellos daños o perjuicios que correspondan en términos de las disposiciones jurídicas aplicables.\nCapítulo II\nDe los Contratos para la Exploración y Extracción\nArtículo 11.- El Ejecutivo Federal, por conducto de la Comisión Nacional de Hidrocarburos, observando los lineamientos que al efecto establezcan, en el ámbito de sus competencias, las Secretarías de Energía y de Hacienda y Crédito Público, podrá celebrar Contratos para la Exploración y Extracción. Los Contratos para la Exploración y Extracción establecerán invariablemente que los Hidrocarburos en el Subsuelo son propiedad de la Nación.\nArtículo 12.- Petróleos Mexicanos y las demás empresas productivas del Estado podrán solicitar a la Secretaría de Energía la migración de las Asignaciones de las que sean titulares a Contratos para la Exploración y Extracción. La Secretaría de Energía resolverá lo conducente con la asistencia técnica de la Comisión Nacional de Hidrocarburos.\nEn caso de que la migración sea procedente, la Secretaría de Hacienda y Crédito Público establecerá las condiciones económicas relativas a los términos fiscales que correspondan, según lo dispuesto en la Ley de Ingresos sobre Hidrocarburos.\nArtículo 13.- En los casos de Asignaciones que migren a Contratos para la Exploración y Extracción,\nPetróleos Mexicanos y las demás empresas productivas del Estado podrán celebrar alianzas o asociaciones con Personas Morales.\nPara las alianzas o asociaciones a que se refiere este artículo, la selección del socio de Petróleos\nMexicanos o de la empresa productiva del Estado de que se trate, se realizará mediante licitación que represente las mejores condiciones de selección y que más convenga a la Nación, observando las mejores prácticas en materia de transparencia. Dicha licitación se llevará a cabo por la Comisión\nNacional de Hidrocarburos, y conforme a los lineamientos técnicos y las condiciones económicas relativas a los términos fiscales que al efecto establezcan la Secretaría de Energía y la Secretaría de Hacienda y Crédito Público, respectivamente.\nEn la elaboración de los lineamientos técnicos del procedimiento de licitación a que se refiere este artículo, la Secretaría de Energía solicitará opinión favorable a Petróleos Mexicanos o a la empresa productiva del Estado de que se trate, respecto de los elementos técnicos, financieros, de ejecución y de experiencia que debieran reunir las Personas Morales que participen en la licitación.\nLos procedimientos de licitación establecidos en el presente artículo se sujetarán, en lo conducente, a lo dispuesto en esta Ley para la adjudicación de Contratos para la Exploración y Extracción, con excepción de lo dispuesto por la fracción III del artículo 24 de esta Ley.\nsocio de Petróleos Mexicanos o de la Empresa Productiva del Estado de que se trate, la Comisión del Estado de que se trate.\nUna vez seleccionado el socio en los términos de este artículo, la Comisión Nacional de Hidrocarburos celebre. A dichos contratos les será aplicable lo dispuesto en el artículo 15 de esta Ley.\nArtículo 14.- Petróleos Mexicanos y las demás empresas productivas del Estado podrán celebrar alianzas o asociaciones para participar en los procesos de licitación de Contratos para la Exploración y Extracción, conforme a las disposiciones previstas en la Ley de Petróleos Mexicanos o la que regule a la respectiva empresa productiva del Estado. Las alianzas o asociaciones a que se refiere el presente artículo se regirán por el derecho común.\nLas alianzas o asociaciones podrán realizarse bajo esquemas que permitan la mayor productividad y rentabilidad, incluyendo modalidades en las que podrán compartir costos, gastos, inversiones, riesgos, así como utilidades, producción y demás aspectos de la Exploración y la Extracción.\nPara realizar actividades de Exploración y Extracción de Hidrocarburos, Petróleos Mexicanos y las demás empresas productivas del Estado no podrán celebrar con Particulares contratos de asociación público privada en términos de la ley de la materia.\nArtículo 15.- Sólo el Estado Mexicano, por conducto de la Comisión Nacional de Hidrocarburos, podrá otorgar Contratos para la Exploración y Extracción. La selección del Contratista tendrá lugar a través de un proceso de licitación, en términos de lo dispuesto por el artículo 23 del presente ordenamiento.\nLa Comisión Nacional de Hidrocarburos deberá autorizar, de forma previa, la celebración de alianzas o asociaciones, en los que se ceda:\nI. El control corporativo y de gestión del Contratista, o\nII. El control de las operaciones en el Área Contractual, de forma parcial o total.\nPara autorizar la cesión del control de las operaciones a que se refiere la fracción II, la Comisión\nNacional de Hidrocarburos analizará, entre otros aspectos, que el operador del Contrato para la Exploración y Extracción cuente con la experiencia, las capacidades técnicas y financieras para dirigir y llevar a cabo las actividades en el Área Contractual y asumir las responsabilidades inherentes del Contrato para la Exploración y Extracción.\nLa Comisión Nacional de Hidrocarburos notificará a la Secretaría de Energía, la solicitud por parte del Contratista, dentro de los dos días siguientes a que se presente. La Secretaría de Energía podrá manifestar su inconformidad debidamente motivada, ante dicha Comisión, respecto de la cesión señalada en el segundo párrafo de este artículo, dentro de los 20 días posteriores a que sea notificada.\nLa Comisión Nacional de Hidrocarburos deberá resolver lo conducente dentro de los 10 días posteriores a que concluya el plazo otorgado a la Secretaría de Energía para pronunciarse. En caso de no emitirse una respuesta a la solicitud por parte de la Comisión Nacional de Hidrocarburos, dentro del plazo de 10 días antes mencionado, ésta se entenderá en sentido favorable.\nComo consecuencia de los contratos o convenios a que se refiere este artículo, la Comisión Nacional de Hidrocarburos realizará la adecuación correspondiente al Contrato para la Exploración y Extracción, la cual no implicará modificación alguna a los demás términos contractuales.\ncontractuales, será nula de pleno derecho.\ncambio en el control corporativo o de gestión del mismo, se deberá dar aviso a la Comisión Nacional de Hidrocarburos dentro de los siguientes treinta días naturales a la realización de la misma. Tratándose de empresas que se encuentren listadas en la Bolsa Mexicana de Valores, el aviso aquí referido se efectuará de conformidad con lo establecido en la Ley del Mercado de Valores.\nArtículo 16.- Dentro de los lineamientos para la licitación de Contratos para la Exploración y Extracción que determine la Secretaría de Energía, se podrá incluir una participación del Estado\nMexicano, a través de Petróleos Mexicanos, de cualquier otra empresa productiva del Estado o de un vehículo financiero especializado del Estado Mexicano, en los siguientes casos:\nI. Cuando el Área Contractual objeto de la licitación coexista, a distinta profundidad, con un Área de Asignación;\nII. Cuando existan oportunidades para impulsar la transferencia de conocimiento y tecnología para el desarrollo de las capacidades de Petróleos Mexicanos u otra empresa productiva del Estado, o\nIII. Cuando se trate de proyectos que se deseen impulsar a través de un vehículo financiero especializado del Estado Mexicano.\nEn los supuestos de las fracciones II y III anteriores, la participación de Petróleos Mexicanos, de cualquier otra empresa productiva del Estado o del vehículo financiero especializado que se establezca en el Contrato de Exploración y Extracción correspondiente, no podrá exceder del treinta por ciento de la inversión del proyecto.\nLa participación del Estado Mexicano, a través de Petróleos Mexicanos o de cualquier otra empresa productiva del Estado, deberá contar con la aprobación de su respectivo Consejo de Administración.\nLa determinación de la Secretaría de Energía deberá ser en todos los casos debidamente motivada, contar con la opinión técnica de la Comisión Nacional de Hidrocarburos y ser manifestada a los interesados en las bases del procedimiento de licitación y adjudicación del contrato respectivo, el cual deberá establecer la forma, términos y condiciones en las que podrá ejercerse la participación a que se refiere el presente artículo.\nArtículo 17.- La Secretaría de Energía, con la asistencia técnica de la Comisión Nacional de Hidrocarburos, establecerá una participación obligatoria de Petróleos Mexicanos u otra empresa productiva del Estado en los Contratos para la Exploración y Extracción en aquellas Áreas Contractuales en las que exista la posibilidad de encontrar yacimientos transfronterizos.\nEn el supuesto a que hace referencia este artículo, la participación obligatoria será de al menos veinte por ciento de la inversión del proyecto. La determinación de la Secretaría de Energía deberá ser manifestada a los interesados en las bases del procedimiento de licitación y adjudicación del contrato respectivo.\nEn caso de que se confirme la existencia de un yacimiento transfronterizo en el Área Contractual, se internacionales que México haya suscrito.\nArtículo 18.- La Secretaría de Energía establecerá el modelo de contratación correspondiente para cada Área Contractual que se licite o se adjudique en términos de la presente Ley, para lo cual podrá elegir, entre otros, los contratos de servicios, de utilidad o producción compartida, o de licencia.\nsujetarán a lo establecido en la Ley de Ingresos sobre Hidrocarburos.\nArtículo 19.- Los Contratos para la Exploración y Extracción deberán contar, al menos, con cláusulas sobre:\nI. La definición del Área Contractual;\nII. Los planes de Exploración y de desarrollo para la Extracción, incluyendo el plazo para su presentación;\nIII. El programa mínimo de trabajo y de inversión, en su caso;\nIV. Las obligaciones del Contratista, incluyendo los términos económicos y fiscales;\nV. La vigencia, así como las condiciones para su prórroga;\nVI. La adquisición de garantías y seguros;\nVII. La existencia de un sistema de auditorías externas para supervisar la efectiva recuperación, en su caso, de los costos incurridos y demás contabilidad involucrada en la operación del contrato;\nVIII. Las causales de terminación del contrato, incluyendo la terminación anticipada y la rescisión administrativa;\nIX. Las obligaciones de transparencia que posibiliten el acceso a la información derivada de los contratos, incluyendo la divulgación de las contraprestaciones, contribuciones y pagos que se prevean en el propio contrato;\nX. El porcentaje mínimo de contenido nacional;\nXI. Las condiciones y los mecanismos para la reducción o devolución del Área Contractual;\nXII. La solución de controversias, incluyendo los medios alternativos de solución de conflictos;\nXIII. Las penas aplicables en caso de incumplimiento de las obligaciones contractuales;\nXIV. La responsabilidad del Contratista y del operador conforme a las mejores prácticas internacionales. En caso de accidente, no se limitará la responsabilidad del Contratista u operador si se comprueba dolo o culpa por parte de éstos, y\nXV. La observancia de mejores prácticas internacionales para la operación en el Área Contractual.\nArtículo 20.- El Ejecutivo Federal, a través de la Comisión Nacional de Hidrocarburos, podrá rescindir únicamente cuando se presente alguna de las siguientes causas graves:\nI. Que, por más de ciento ochenta días naturales de forma continua, el Contratista no inicie o Extracción en el Área Contractual, sin causa justificada ni autorización de la Comisión\nNacional de Hidrocarburos;\nII. Que el Contratista no cumpla el compromiso mínimo de trabajo, sin causa justificada, conforme a los términos y condiciones del Contrato para la Exploración y Extracción;\nIII. Que el Contratista ceda parcial o totalmente la operación o los derechos conferidos en el Contrato de Exploración y Extracción, sin contar con la autorización previa en términos de lo dispuesto en el artículo 15 de esta Ley;\nIV. Que se presente un accidente grave causado por dolo o culpa del Contratista, que ocasione daño a instalaciones, fatalidad y pérdida de producción;\nV. Que el Contratista por más de una ocasión remita de forma dolosa o injustificada, información o reportes falsos o incompletos, o los oculte, a las Secretarías de Energía, de Hacienda y Crédito Público o de Economía, a la Comisión Nacional de Hidrocarburos o a la Agencia, respecto de la producción, costos o cualquier otro aspecto relevante del Contrato;\nVI. Que el Contratista incumpla una resolución definitiva de órganos jurisdiccionales federales, que constituya cosa juzgada, o\nVII. Que el Contratista omita, sin causa justificada, algún pago al Estado o entrega de Hidrocarburos a éste, conforme a los plazos y términos estipulados en el Contrato para la Exploración y Extracción.\nEl Contrato de Exploración y Extracción establecerá las causales de terminación y rescisión del mismo, sin menoscabo de las causales de rescisión administrativa contempladas en el presente artículo.\nLa declaración de rescisión administrativa requerirá notificación previa al Contratista de la causal o causales que se invoquen y se regirá por la presente Ley y su Reglamento. Una vez notificada la causal, el Contratista tendrá un máximo de treinta días naturales, contados a partir de la fecha de la notificación, para exponer lo que a su derecho convenga y aportar, en su caso, las pruebas que estime pertinentes.\nTranscurrido el plazo a que se refiere el párrafo anterior, la Comisión Nacional de Hidrocarburos contará con un plazo de noventa días naturales para resolver considerando los argumentos y pruebas que, en su caso, hubiere hecho valer el Contratista. La determinación de dar o no por rescindido administrativamente el contrato deberá ser debidamente fundada, motivada y comunicada al Contratista.\nSi el Contratista solventa la causal de rescisión en que haya incurrido antes de que la Comisión\nNacional de Hidrocarburos emita la resolución respectiva, el procedimiento iniciado quedará sin efecto, previa aceptación y verificación de la Comisión Nacional de Hidrocarburos y aplicando, en su caso, las penas correspondientes conforme a lo dispuesto en la presente Ley.\nComo consecuencia de la rescisión administrativa, el Contratista transferirá al Estado sin cargo, ni pago, ni indemnización alguna, el Área Contractual. Asimismo, se procederá a realizar el finiquito correspondiente en términos de las disposiciones jurídicas aplicables y de las previsiones contractuales.\nobligaciones a cargo del Contratista.\nEn cualquier caso, el Contratista mantendrá la propiedad de los bienes e instalaciones que no sean conexos o accesorios exclusivos del área recuperada.\nresarcir aquellos daños o perjuicios que correspondan, en términos de las disposiciones jurídicas aplicables.\nArtículo 21.- Tratándose de controversias referidas a los Contratos para la Exploración y Extracción, con excepción de lo mencionado en el artículo anterior, se podrán prever mecanismos alternativos para su solución, incluyendo acuerdos arbitrales en términos de lo dispuesto en el Título Cuarto del Libro controversias de los que México sea parte.\nLa Comisión Nacional de Hidrocarburos y los Contratistas no se someterán, en ningún caso, a leyes extranjeras. El procedimiento arbitral en todo caso, se ajustará a lo siguiente:\nI. Las leyes aplicables serán las leyes federales mexicanas;\nII. Se realizará en idioma español, y\nIII. El laudo será dictado en estricto derecho y será obligatorio y firme para ambas partes.\nArtículo 22.- Los Contratos para la Exploración y Extracción se regularán por lo dispuesto en la presente Ley y su Reglamento. Para los efectos de su ejecución será aplicable, supletoriamente y en lo que no se oponga a la presente Ley y su Reglamento, la legislación mercantil y el derecho común.\nArtículo 23.- La adjudicación de los Contratos para la Exploración y Extracción se llevará a cabo mediante licitación que realice la Comisión Nacional de Hidrocarburos. Las bases de licitación preverán que el Contrato para la Exploración y Extracción se podrá formalizar con Petróleos Mexicanos, otras empresas productivas del Estado y Personas Morales, ya sea de manera individual, en consorcio, o asociación en participación, en términos de la Ley de Ingresos sobre Hidrocarburos.\nEl proceso de licitación iniciará con la publicación de la convocatoria en el Diario Oficial de la Federación.\nEl proceso de licitación abarcará los actos y las etapas que se establezcan en los lineamientos y las disposiciones que para tal efecto emitan la Secretaría de Energía y la Comisión Nacional de Hidrocarburos, respectivamente. Los interesados en presentar propuestas deberán cumplir con los criterios de precalificación respecto de los elementos técnicos, financieros, de ejecución y de experiencia, en los términos señalados en los lineamientos que al efecto establezca la Secretaría de Energía.\nEntre la fecha de publicación de la convocatoria en el Diario Oficial de la Federación y aquélla en la que se presenten las propuestas deberán mediar al menos noventa días naturales. El mecanismo de adjudicación podrá ser, entre otros, una subasta ascendente, una subasta descendente o una subasta al primer precio en sobre cerrado, en cuyo caso los sobres deberán ser presentados y abiertos en una misma sesión pública. En los procesos de licitación se deberán contemplar criterios de desempate, los cuales se incluirán en las bases de licitación correspondientes.\nEn cualquier caso, los procesos de licitación se deberán llevar a cabo bajo los principios de transparencia, máxima publicidad, igualdad, competitividad y sencillez. Las propuestas podrán ser presentadas y analizadas a través de medios electrónicos, en los términos que establezca el Reglamento.\nLey y no serán aplicables la Ley de Obras Públicas y Servicios Relacionados con las Mismas, la Ley de Adquisiciones, Arrendamientos y Servicios del Sector Público, ni las disposiciones que deriven de dichas leyes.\nArtículo 24.- Las bases del procedimiento de licitación y adjudicación de los Contratos para la Exploración y Extracción, que se pongan a disposición de los interesados, deberán:\nI. Sujetarse a los lineamientos técnicos y a las condiciones económicas relativas a los términos y Crédito Público, respectivamente;\nII. Señalar, entre otros aspectos, el tipo de contrato, los criterios y plazos para el proceso de precalificación y de aclaración de las bases, las variables de adjudicación, el mecanismo para determinar al ganador y, en su caso, la modificación de sus términos y condiciones, y\nIII. Contar con opinión previa de la Comisión Federal de Competencia Económica, la cual versará exclusivamente sobre los criterios de precalificación y el mecanismo de adjudicación a que se refiere el artículo 23 del presente ordenamiento. La opinión de la Comisión Federal de Competencia Económica deberá ser proporcionada en un plazo no mayor a treinta días a partir de la solicitud correspondiente; en caso de no emitirse la opinión, dentro del plazo establecido, ésta se entenderá en sentido favorable.\nArtículo 25.- Contra las resoluciones mediante las cuales se asigne al ganador o se declare desierto el proceso de licitación de Contratos para la Exploración y Extracción, únicamente procederá el juicio de amparo indirecto.\nLos actos relacionados con el procedimiento de licitación y adjudicación de Contratos para la Exploración y Extracción se consideran de orden público e interés social.\nArtículo 26.- La Comisión Nacional de Hidrocarburos se abstendrá de considerar propuestas o celebrar Contratos para la Exploración y Extracción con quienes:\nI. Se encuentren inhabilitados o impedidos por autoridad competente para contratar con autoridades federales, en términos de las disposiciones aplicables;\nII. Tengan incumplimientos graves pendientes de solventar respecto de Contratos para la Exploración y Extracción adjudicados con anterioridad;\nIII. Utilicen a terceros para evadir lo dispuesto en este artículo;\nIV. Presenten información falsa o incompleta. En este último caso, la Comisión Nacional de Hidrocarburos prevendrá, por una sola vez, a los interesados para que subsanen la omisión dentro del término que para tal efecto se establezca, y\nV. Las demás que se establezcan en las bases de licitación.\nLa Comisión Nacional de Hidrocarburos podrá revocar el fallo para adjudicar un Contrato de Exploración y Extracción si se comprueba que la información presentada por el participante ganador durante la licitación es falsa. En dicho caso el contrato resultante se considerará nulo de pleno derecho.\nArtículo 27.- No se requerirá llevar a cabo un proceso de licitación y el Contrato para la Exploración y Extracción se podrá adjudicar directamente a los titulares de concesiones mineras, exclusivamente para producido por la misma. Para cada mina en que se realicen o se vayan a iniciar actividades de extracción de carbón, se podrá solicitar la adjudicación del contrato de exploración y extracción, en los términos del presente párrafo.\nLa Comisión Nacional de Hidrocarburos suscribirá el contrato correspondiente, siempre y cuando los concesionarios mineros acrediten, ante la Secretaría de Energía con opinión técnica favorable de la propia Comisión Nacional de Hidrocarburos, que cuentan con solvencia económica y capacidad técnica,\nGas Natural producido y contenido en la veta del carbón mineral.\nLa Exploración y Extracción de Hidrocarburos que existan en el área correspondiente a una concesión minera y que no se encuentren asociados al carbón mineral sólo se podrá realizar a través de un Contrato para la Exploración y Extracción que adjudique la Comisión Nacional de Hidrocarburos por medio de una licitación en los términos de este Capítulo o a través de una Asignación. Lo anterior en el entendido de que una concesión minera no otorga derechos para la Exploración y Extracción de Hidrocarburos, exceptuándose el Gas Natural producido y contenido en la veta de carbón mineral que se encuentre en extracción, al que se refiere el primer párrafo del presente artículo.\nLa Exploración y Extracción del Gas Natural asociado al carbón mineral que se realice sin explotar el carbón, sólo se podrá realizar a través de un Contrato para la Exploración y Extracción que adjudique la Comisión Nacional de Hidrocarburos por medio de una licitación en los términos de este Capítulo o a través de una Asignación.\nSi una vez concluida la licitación a cargo de la Comisión Nacional de Hidrocarburos para adjudicar un Contrato para la Exploración y Extracción de Hidrocarburos, u otorgada una Asignación, existiera una posible afectación a los derechos de una concesión minera respecto de la superficie objeto de la concesión en el que efectivamente se esté llevando a cabo la extracción de minerales, se abrirá un periodo de noventa días para que el Contratista o Asignatario y el concesionario minero lleven a cabo las negociaciones y alcancen el acuerdo que permita el desarrollo del proyecto a cargo del Contratista o Asignatario.\nLa negociación y acuerdo a que se refiere el párrafo anterior deberá realizarse de manera transparente y sujetarse a lo señalado en el Reglamento y a las siguientes bases:\nI. El Contratista o Asignatario deberá notificar a la Comisión Nacional de Hidrocarburos del inicio de las negociaciones con el concesionario minero.\nII. La contraprestación que se acuerde deberá ser proporcional a los requerimientos del Contratista o Asignatario conforme a las actividades que se realicen al amparo del Contrato o Asignación.\nIII. Los pagos de las contraprestaciones que se pacten podrán cubrirse en efectivo o, en su caso, mediante el compromiso para formar parte del proyecto extractivo de Hidrocarburos, o una combinación de las anteriores. En ningún caso se podrá pactar una contraprestación asociada a una parte de la producción de Hidrocarburos del proyecto a cargo del Contratista.\nIV. La contraprestación, así como los demás términos y condiciones que se pacten entre el Contratista o Asignatario y el concesionario minero, deberán constar invariablemente en un contrato por escrito, mismo que contendrá, al menos, los derechos y obligaciones de las partes, así como posibles mecanismos de solución de controversias.\nplazo de noventa días referido con antelación, la Comisión Nacional de Hidrocarburos, con la asistencia de las autoridades que resulten competentes, determinará si ambas actividades extractivas pueden objeto de la concesión en el que efectivamente se esté llevando a cabo la extracción de minerales.\nen el que efectivamente se esté llevando a cabo la extracción de minerales, dicha Comisión determinará\nAsignatario, a favor del concesionario minero, de conformidad con el avalúo respectivo, o en su caso, atendiendo a la gravedad de la afectación podrá fijar una contraprestación a favor del concesionario minero que podrá ser del punto cinco por ciento al dos por ciento de la utilidad del Contratista después del pago de contribuciones.\nLa Comisión Nacional de Hidrocarburos podrá autorizar a los titulares de concesiones mineras para realizar actividades específicas de exploración superficial de Hidrocarburos en las áreas en que coexistan sus derechos de conformidad con lo dispuesto en esta Ley y el Reglamento respectivo.\nEn el caso de que los concesionarios mineros estén llevando a cabo obras y trabajos de exploración al amparo de su concesión, aplicará lo dispuesto en este artículo en cuanto al acuerdo con el Contratista o Asignatario; en caso de que no exista acuerdo la Comisión Nacional de Hidrocarburos determinará el monto y los plazos de la indemnización de conformidad con el avalúo respectivo. Para que sea aplicable lo dispuesto en este párrafo en relación al acuerdo con el Contratista o Asignatario y, en su caso, la indemnización, las obras y trabajos de exploración de la concesión minera deberán constar en el informe de comprobación a que se refiere el artículo 28 de la Ley Minera, rendido el año anterior a que se hagan públicas por la Secretaría de Energía las áreas que podrán ser licitadas para la Exploración y Extracción de Hidrocarburos. El informe de comprobación referido deberá notificarse también a la Secretaría de Energía y a la Comisión Nacional de Hidrocarburos.\nEl concesionario minero que realice la Exploración o Extracción de Hidrocarburos a que se refiere este artículo, sin contar con el Contrato de Exploración y Extracción correspondiente, será sancionado conforme a lo establecido en esta Ley y la Secretaría de Economía, previo aviso de la Comisión Nacional de Hidrocarburos, sancionará a dicho concesionario con la cancelación de la concesión minera respectiva conforme a lo dispuesto en la Ley Minera.\nArtículo 28.- La Comisión Nacional de Hidrocarburos, a petición del Fondo Mexicano del Petróleo para la Estabilización y el Desarrollo, podrá contratar a Petróleos Mexicanos, a cualquier otra empresa productiva del Estado o a una Persona Moral, mediante licitación pública, para que a cambio de una contraprestación preste a la Nación los servicios de comercialización de los Hidrocarburos que el Estado obtenga como resultado de los Contratos para la Exploración y Extracción.\nCon independencia de lo dispuesto en el párrafo anterior, las facultades del Banco de México previstas en el artículo 34 de la Ley del Banco de México serán aplicables a cualquier persona que comercialice Hidrocarburos que se obtengan como resultado de Asignaciones o Contratos para la Exploración y Extracción e ingrese divisas al país, así como a Petróleos Mexicanos, sus empresas productivas subsidiarias y cualquier otro Asignatario.\nArtículo 29.- Respecto de los Contratos para la Exploración y Extracción, corresponde a la Secretaría de Energía:\nI. Seleccionar las Áreas Contractuales conforme a los criterios que la misma establezca, con la asistencia técnica de la Comisión Nacional de Hidrocarburos.\nPetróleos Mexicanos, cualquier otra empresa productiva del Estado o Persona Moral podrán poner a consideración de la Secretaría de Energía, áreas sobre las cuales exista interés para llevar a cabo la Exploración y Extracción de Hidrocarburos. Dicha propuesta no será vinculante, ni otorgará derechos preferenciales en relación con los Contratos para la Exploración y Extracción;\nII. Aprobar y emitir el plan quinquenal de licitaciones de Áreas Contractuales, el cual deberá ser público. El plan podrá ser adicionado o modificado con posterioridad a su publicación, en los términos del Reglamento respectivo;\nIII. Establecer el modelo de contratación para cada Área Contractual que mejor convenga para maximizar los ingresos de la Nación, con las opiniones de la Secretaría de Hacienda y Crédito\nPúblico y de la Comisión Nacional de Hidrocarburos;\nIV. Diseñar los términos y condiciones técnicos de los Contratos para la Exploración y Extracción;\nV. Establecer los lineamientos técnicos que deberán observarse en cada proceso de licitación de los Contratos para la Exploración y Extracción;\nVI. Realizar la planeación y el desarrollo de los eventos de promoción y difusión, a nivel nacional e internacional, de las rondas de licitación, y\nVII. Las demás que se prevean en los propios Contratos para la Exploración y Extracción y en las leyes aplicables.\nArtículo 30.- Respecto de los Contratos para la Exploración y Extracción, corresponde a la Secretaría de Hacienda y Crédito Público:\nI. Establecer las condiciones económicas relativas a los términos fiscales de las licitaciones y de los contratos que permitan a la Nación obtener, en el tiempo, ingresos que contribuyan a su desarrollo de largo plazo, en términos de lo dispuesto en la Ley de Ingresos sobre\nHidrocarburos;\nII. Determinar las variables de adjudicación de los procesos de licitación, en términos de la Ley de Ingresos sobre Hidrocarburos;\nIII. Participar en la administración y auditoría contables relativas a los términos fiscales de los Contratos para la Exploración y Extracción en términos de lo dispuesto en la Ley de Ingresos sobre Hidrocarburos. Lo anterior podrá realizarse con el apoyo de auditores o inspectores externos, mediante la contratación de los servicios correspondientes, y\nIV. Las demás que se prevean en los propios Contratos para la Exploración y Extracción y en las leyes aplicables.\nArtículo 31.- Respecto de los Contratos para la Exploración y Extracción, corresponde a la Comisión\nNacional de Hidrocarburos:\nI. Proveer asistencia técnica a la Secretaría de Energía en la selección de las Áreas\nContractuales;\nII. Proponer a la Secretaría de Energía el plan quinquenal de licitaciones de Áreas\nContractuales;\nIII. Emitir las bases que se observarán en el procedimiento de licitación y adjudicación de Contratos para la Exploración y Extracción. Lo anterior, siguiendo los lineamientos técnicos y económicos relativos a los términos fiscales que emitan las Secretarías de Energía, y de Hacienda y Crédito Público, respectivamente;\nIV. Realizar las licitaciones para la adjudicación de los Contratos para la Exploración y Extracción.\nPara la ejecución del proceso de contratación, la Comisión Nacional de Hidrocarburos será responsable de desarrollar, administrar y publicar la información técnica sobre las Áreas\nContractuales sujetas a licitación;\nV. Suscribir los Contratos para la Exploración y Extracción;\nVI. Administrar y supervisar, en materia técnica, los Contratos para la Exploración y Extracción.\nLa administración y supervisión técnica de los contratos podrán realizarse con el apoyo de auditores o inspectores externos, mediante la contratación de los servicios correspondientes;\nVII. Aprobar, en su caso, la modificación, cancelación o terminación de los Contratos para la Exploración y Extracción, conforme a las cláusulas que se prevean en el contrato respectivo y de acuerdo con los lineamientos técnicos y las condiciones económicas relativas a los términos fiscales que al efecto establezcan la Secretaría de Energía y la Secretaría de Hacienda y Crédito Público, respectivamente;\nVIII. Aprobar los planes de Exploración o de desarrollo para la Extracción, que maximicen la productividad del Área Contractual en el tiempo, así como sus modificaciones y supervisar el cumplimiento de los mismos, de acuerdo con la regulación que al respecto emita;\nIX. Apoyar técnicamente a la Secretaría de Hacienda y Crédito Público y al Fondo Mexicano del Petróleo para la Estabilización y el Desarrollo en el ejercicio de sus funciones, en términos de la Ley de Ingresos sobre Hidrocarburos;\nX. Aprobar, en su caso, los programas anuales de inversión y operación de los Contratos para la Exploración y Extracción;\nXI. Aprobar la cesión del control corporativo o de las operaciones, en términos de lo establecido en el artículo 15 de esta Ley y en los lineamientos que al efecto emita, y\nXII. Las demás que se prevean en los propios Contratos para la Exploración y Extracción y en las leyes aplicables.\nCapítulo III\nDe la información obtenida de las actividades de Reconocimiento y Exploración\nSuperficial, Exploración y Extracción de Hidrocarburos\nArtículo 32.- Pertenece a la Nación la información geológica, geofísica, petrofísica, petroquímica y, en general, la que se obtenga o se haya obtenido de las actividades de Reconocimiento y Exploración\nSuperficial, así como de Exploración y Extracción, llevadas a cabo por parte de Petróleos Mexicanos, cualquier otra empresa productiva del Estado o por cualquier persona.\nCorresponde a la Comisión Nacional de Hidrocarburos el acopio, resguardo, uso, administración y actualización, así como la publicación de la información referida en el presente artículo, por medio del Centro Nacional de Información de Hidrocarburos.\nSe prohíbe a Petróleos Mexicanos, a cualquier empresa productiva del Estado, así como a los Particulares, publicar, entregar o allegarse de información a la que se refiere el párrafo anterior, por\nComisión Nacional de Hidrocarburos. Lo anterior, sin perjuicio del aprovechamiento comercial de la información que sea obtenida por Asignatarios, Contratistas o Autorizados, conforme a lo dispuesto en el artículo 33 de la presente Ley.\nArtículo 33.- La información que se obtenga de las actividades de Reconocimiento y Exploración\nSuperficial deberá entregarse a la Comisión Nacional de Hidrocarburos. Esta información incluye:\nI. Adquisición, procesamiento, reprocesamiento, interpretación y control geológico de la sísmica 2D, 3D y multicomponente 3C;\nII. Pre-proceso, interpretación de datos sísmicos, modelo de velocidades y migración, en tiempo y en profundidad;\nIII. Adquisición magnética, gravimétrica, geoeléctrica y magnetotelúrica, y\nIV. Cualquier otra que se obtenga por medios diferentes a los previamente listados.\nLos Asignatarios, Contratistas y todos los Autorizados que realicen actividades de Reconocimiento y Exploración Superficial tendrán derecho al aprovechamiento comercial de la información que obtengan con motivo de sus actividades dentro del plazo que al efecto se establezca en la regulación que emita la Comisión Nacional de Hidrocarburos.\nLa Comisión Nacional de Hidrocarburos garantizará la confidencialidad de la información conforme a los plazos y criterios que establezca la regulación que al efecto emita. La interpretación de datos sísmicos será considerada información confidencial y se reservará por el periodo que corresponda conforme a lo establecido en la regulación respectiva.\nArtículo 34.- La Comisión Nacional de Hidrocarburos podrá realizar o contratar, conforme a las disposiciones aplicables en materia de contrataciones públicas, a Petróleos Mexicanos, a cualquier otra empresa productiva del Estado, a otras entidades públicas, a instituciones académicas y a cualquier otra persona para llevar a cabo actividades de Reconocimiento y Exploración Superficial, a cambio de una contraprestación, que en todos los casos deberá estar referida a condiciones de mercado.\nArtículo 35.- La Comisión Nacional de Hidrocarburos establecerá y administrará el Centro Nacional de Información de Hidrocarburos, integrado por un sistema para recabar, acopiar, resguardar, administrar, usar, analizar, mantener actualizada y publicar la información y estadística relativa a:\nI. La producción de Hidrocarburos;\nII. Las Reservas, incluyendo la información de reportes de estimación y estudios de evaluación o cuantificación y certificación;\nIII. La relación entre producción y Reservas;\nIV. Los Recursos Contingentes y Prospectivos;\nV. La información geológica, geofísica, petrofísica, petroquímica y demás, que se obtenga de las actividades de Reconocimiento y Exploración Superficial, así como de la Exploración y Extracción de Hidrocarburos, y\nVI. Cualquier otra información necesaria para realizar sus funciones, sean las establecidas en esta Ley o en las demás disposiciones jurídicas aplicables.\nEl Centro Nacional de Información de Hidrocarburos también resguardará, preservará y administrará los núcleos de roca, recortes de perforación y muestras de Hidrocarburos que se consideren necesarios para el acervo del conocimiento histórico y prospectivo de la producción de Hidrocarburos del país. Para lo anterior, la Comisión Nacional de Hidrocarburos deberá desarrollar y mantener una Litoteca Nacional de la Industria de Hidrocarburos.\nEn relación con lo establecido en este artículo, los Asignatarios, Contratistas y Autorizados deberán entregar la información y materiales de campo respectivos, así como la información procesada, interpretada e integrada, que se obtenga de las actividades de Reconocimiento y Exploración Superficial,\nExploración y Extracción de Hidrocarburos.\nLos Asignatarios, Contratistas y Autorizados serán responsables de la calidad, integridad y seguridad de la información que se entregue a la Comisión Nacional de Hidrocarburos.\nLa Comisión Nacional de Hidrocarburos definirá la confidencialidad y los criterios y plazos conforme a los cuales hará pública la información que reciba.\nLa normativa que emita la Comisión Nacional de Hidrocarburos establecerá los mecanismos que sean necesarios para validar la información que se le entregue.\nLas Secretarías de Energía y de Hacienda y Crédito Público tendrán acceso irrestricto a la información contenida en el Centro Nacional de Información de Hidrocarburos. Las universidades y centros de investigación tendrán acceso a la información en los términos de los convenios que al efecto celebren con la Comisión Nacional de Hidrocarburos.\nCapítulo IV\nDe las autorizaciones\nArtículo 36.- Los Asignatarios y Contratistas deberán contar con autorización de la Comisión Nacional de Hidrocarburos, conforme a la regulación y los lineamientos que para tal efecto emita la citada\nComisión, para llevar a cabo la perforación de pozos en los casos siguientes:\nI. Pozos exploratorios;\nII. Pozos en aguas profundas y ultra profundas, y\nIII. Pozos tipo que se utilicen como modelos de diseño.\nLa autorización a que se refiere este artículo se ajustará a los plazos establecidos conforme a la regulación que para tal efecto emita la Comisión Nacional de Hidrocarburos. En caso de no emitirse una respuesta a la solicitud por parte de la Comisión Nacional de Hidrocarburos, dentro del plazo establecido en dicha regulación, ésta se entenderá en sentido favorable.\nArtículo 37.- Las actividades de Reconocimiento y Exploración Superficial de las áreas para investigar la posible existencia de Hidrocarburos, requerirán autorización de la Comisión Nacional de Hidrocarburos.\nComisión Nacional de Hidrocarburos. En caso de no emitirse una respuesta a la solicitud por parte de la Comisión Nacional de Hidrocarburos, dentro del plazo establecido en dicha regulación, ésta se entenderá en sentido favorable.\nderechos de Exploración, ni derechos preferenciales en relación con las Asignaciones o con los Contratos para la Exploración y Extracción.\nSuperficial de las Áreas de Asignaciones y Áreas Contractuales de los que sean titulares; únicamente deberán dar aviso a la Comisión Nacional de Hidrocarburos y cumplir con los requerimientos de entrega de información y demás obligaciones que se establezcan en la regulación que emita la misma Comisión\nNacional de Hidrocarburos. Lo anterior, sin menoscabo del cumplimiento de los requisitos que otras autoridades competentes señalen al efecto.\nArtículo 38.- Las autorizaciones a que se refiere este Capítulo terminarán por cualquiera de las causas que se establecen para la terminación de los Permisos a que se refiere el artículo 54 de esta Ley, así como por la terminación del Contrato para la Exploración y Extracción o de la Asignación, según sea el caso.\nLa terminación de la autorización no exime a su titular de las responsabilidades contraídas durante su vigencia, con el Gobierno Federal y con terceros.\nArtículo 39.- Las autorizaciones caducarán si los sujetos de las mismas:\nI. No ejercen los derechos conferidos en la autorización en un plazo de ciento veinte días naturales, contados a partir de la fecha de su otorgamiento; salvo previa autorización de la Comisión Nacional de Hidrocarburos, por causa justificada, o\nII. Se ubican en los demás supuestos de caducidad previstos en la autorización respectiva.\nArtículo 40.- La Comisión Nacional de Hidrocarburos podrá revocar las autorizaciones por cualquiera de las causas siguientes:\nI. Que los Autorizados no otorguen o no mantengan en vigor las garantías, seguros o cualquier otro instrumento financiero requerido conforme a la regulación aplicable;\nII. Que los Autorizados no cumplan con la regulación que al efecto emita la Comisión Nacional de Hidrocarburos, así como con las condiciones establecidas en la autorización;\nIII. Que los Autorizados no realicen el pago de las contribuciones y aprovechamientos correspondientes por su otorgamiento o, en su caso, renovación, o\nIV. Las demás previstas en la autorización respectiva.\nCapítulo V\nDe la regulación y obligaciones\nArtículo 41.- El Ejecutivo Federal, a propuesta de la Secretaría de Energía, establecerá Zonas de Exploración y Extracción de Hidrocarburos. La incorporación de áreas específicas a las Zonas de Salvaguarda y su desincorporación de las mismas será hecha por decreto presidencial, fundado en los dictámenes técnicos respectivos.\nExtracción de Hidrocarburos.\nArtículo 42.- Corresponde a la Secretaría de Energía:\nI. Proponer al Ejecutivo Federal, con base en los dictámenes técnicos, el establecimiento de las Zonas de Salvaguarda;\nII. Instruir la unificación de campos o yacimientos de Extracción con base en el dictamen que al efecto emita la Comisión Nacional de Hidrocarburos. Lo anterior para los yacimientos nacionales y, en términos de los tratados internacionales, para los transfronterizos, y\nIII. Instruir, por sí misma o a propuesta de la Comisión Nacional de Hidrocarburos o de la Comisión Federal de Competencia Económica, en el ámbito de sus respectivas competencias, a las empresas productivas del Estado, sus subsidiarias y filiales que realicen las acciones necesarias para garantizar que sus actividades y operaciones no obstaculicen la competencia y el desarrollo eficiente de los mercados, así como la política pública en materia energética.\nLa Secretaría de Energía podrá realizar los estudios que considere pertinentes a fin de determinar la viabilidad de ejercer, por sí misma, la atribución a que se refiere la presente fracción.\nLas atribuciones a que se refieren las fracciones I y II anteriores, requerirán de la opinión de la Secretaría de Hacienda y Crédito Público.\nLas actividades de la Secretaría de Energía se orientarán de acuerdo con los intereses nacionales, incluyendo los de seguridad energética del país, sustentabilidad de la plataforma anual de Extracción de Hidrocarburos y la diversificación de mercados.\nArtículo 43.- Corresponde a la Comisión Nacional de Hidrocarburos:\nI. Emitir la regulación y supervisar su cumplimiento por parte de los Asignatarios, Contratistas y Autorizados en las materias de su competencia y, específicamente, en las siguientes actividades:\na) Reconocimiento y Exploración Superficial, incluyendo los criterios de confidencialidad y el derecho al aprovechamiento comercial de la información que se obtenga derivada de las mismas;\nb) El acopio, resguardo, uso, administración y actualización, así como, en su caso, la publicación de la información referida en el artículo 32 de esta Ley, por medio del Centro\nNacional de Información de Hidrocarburos;\nc) Exploración y Extracción de Hidrocarburos, incluyendo la elaboración de los respectivos planes para el dictamen a que se refiere el artículo 44 de esta Ley, así como el abandono y desmantelamiento;\nd) La Recolección de Hidrocarburos;\ne) La perforación de pozos;\nf) La cuantificación de Reservas y los Recursos Prospectivos y Contingentes;\ng) La certificación de Reservas de la Nación por parte de terceros independientes, así como el proceso de selección de los mismos;\nh) La medición de la producción de Hidrocarburos, considerando, al menos, la instalación y que los mismos sean auditables por terceros con reconocida experiencia internacional;\ni) El aprovechamiento del Gas Natural asociado;\nj) Los estándares técnicos y operativos para maximizar el factor de recuperación de Hidrocarburos, y k) Los requerimientos de información a los sujetos obligados, así como los lineamientos de transferencia, recepción, uso y publicación de la información recibida.\nLa regulación que emita la Comisión Nacional de Hidrocarburos será publicada en el Diario Oficial de la Federación.\nComo parte de la regulación que emita, la Comisión podrá instruir la adopción y observancia de estándares técnicos internacionales.\nEn los casos que así se requiera, expedirá normas oficiales mexicanas y supervisará, verificará y evaluará la conformidad de las mismas y aprobará a las personas acreditadas para su evaluación.\nII. Cuantificar el potencial de Hidrocarburos del país, para lo que deberá:\na) Realizar la estimación de los recursos prospectivos y contingentes de la Nación, y b) Consolidar anualmente la información nacional de Reservas que cuantifiquen los Asignatarios y Contratistas;\nIII. Generar indicadores de referencia para evaluar la eficiencia de los proyectos de Exploración y Extracción de Hidrocarburos, considerando la experiencia internacional y los planes de Exploración y de desarrollo para la Extracción de Hidrocarburos asociados a las Asignaciones y Contratos para la Exploración y Extracción, y\nIV. Proponer, en el ámbito de su competencia, a la Secretaría de Energía, que instruya a las empresas productivas del Estado, sus subsidiarias y filiales que realicen las acciones necesarias para garantizar que sus actividades y operaciones no obstaculicen la competencia y el desarrollo eficiente de los mercados, así como la política pública en materia energética.\nLa Comisión Nacional de Hidrocarburos ejercerá sus funciones, procurando elevar el factor de recuperación y la obtención del volumen máximo de Petróleo y de Gas Natural en el largo plazo y considerando la viabilidad económica de la Exploración y Extracción de Hidrocarburos en el Área de Asignación o del Área Contractual, así como su sustentabilidad.\nArtículo 44.- Los Asignatarios y Contratistas, previo a ejecutar el plan de Exploración o el plan de desarrollo para la Extracción, deberán contar con la aprobación de los mismos por parte de la Comisión\nNacional de Hidrocarburos.\nPara estos efectos, la Comisión Nacional de Hidrocarburos deberá emitir un dictamen técnico que comprenderá la evaluación de los siguientes aspectos:\nI. En relación con el plan de Exploración: la observancia de las mejores prácticas a nivel internacional para la evaluación del potencial de Hidrocarburos, la incorporación de Reservas y la delimitación del área sujeta a la Asignación o al Contrato para la Exploración y Extracción, y\nII. En relación con el plan de desarrollo para la Extracción: la tecnología y el plan de producción que permitan maximizar el factor de recuperación, en condiciones económicamente viables, el programa de aprovechamiento del Gas Natural y los mecanismos de medición de la producción de Hidrocarburos.\nLa Comisión Nacional de Hidrocarburos tendrá la obligación de emitir el dictamen técnico en un plazo que no excederá de ciento veinte días naturales a partir de que reciba la información necesaria. En caso de no emitirse una resolución por parte de la Comisión Nacional de Hidrocarburos dentro del plazo establecido, ésta se entenderá en sentido favorable.\nCorresponde a la Comisión Nacional de Hidrocarburos aprobar cualquier modificación al plan de Exploración o al plan de desarrollo para la Extracción.\nArtículo 45.- Los Asignatarios y Contratistas tendrán derecho a reportar, para efectos contables y financieros, la Asignación o el Contrato para la Exploración y Extracción, así como los beneficios esperados del mismo, siempre y cuando se afirme en dicha Asignación o Contrato, de manera expresa, que los Hidrocarburos en el Subsuelo son propiedad del Estado Mexicano.\nArtículo 46.- El conjunto de actividades de Exploración y Extracción de Hidrocarburos que se realicen en territorio nacional a través de Asignaciones y Contratos de Exploración y Extracción deberá alcanzar, en promedio, al menos treinta y cinco por ciento de contenido nacional.\nDicha meta excluirá la Exploración y Extracción de Hidrocarburos en aguas profundas y ultra profundas. La Secretaría de Economía, con la opinión de la Secretaría de Energía, deberá establecer una meta de contenido nacional acorde con las características de dichas actividades.\nLos Asignatarios y Contratistas deberán cumplir individualmente y de forma progresiva con un porcentaje mínimo de contenido nacional que la Secretaría de Energía, con la opinión de la Secretaría de Economía, establezca en las Asignaciones y Contratos para la Exploración y Extracción.\nLas Asignaciones y Contratos de Exploración y Extracción deberán incluir un programa de cumplimiento del porcentaje de contenido nacional a que se refiere el párrafo anterior, incluyendo los plazos y etapas aplicables. Para el caso de los Contratos para la Exploración y Extracción, la meta de contenido nacional deberá ser incluida en las bases del procedimiento de licitación y adjudicación de los mismos.\nLa Secretaría de Economía establecerá la metodología para medir el contenido nacional en Asignaciones y Contratos para la Exploración y Extracción y verificará el cumplimiento del porcentaje de contenido nacional de las Asignaciones y Contratos para la Exploración y Extracción, conforme al programa que se establezca, para lo cual podrá contar con el apoyo de un tercero independiente.\nPara el establecimiento de la metodología a la que se hace referencia en el párrafo anterior, la\nI. Bienes y servicios contratados, considerando su origen;\nII. La mano de obra nacional y de trabajo calificada;\nIII. La capacitación de la mano de obra nacional;\nIV. La inversión en infraestructura física local y regional, y\nV. La transferencia de la tecnología.\ncon el porcentaje de contenido nacional que le corresponda, informará a la Comisión Nacional de Hidrocarburos, quien impondrá las penalizaciones que correspondan conforme a lo dispuesto en la Asignación o Contrato para la Exploración y Extracción.\nLa aplicación de este artículo será sin perjuicio de lo dispuesto en los tratados internacionales y acuerdos comerciales suscritos por México.\nArtículo 47.- Los Asignatarios y Contratistas estarán obligados a:\nI. Contar, en su caso, con la autorización para llevar a cabo perforaciones previo al inicio de los trabajos correspondientes, en los términos de lo dispuesto por el artículo 36 de esta Ley y de la regulación que al efecto emita la Comisión Nacional de Hidrocarburos;\nII. Dar el aviso a que se refiere el artículo 37, párrafo tercero, de esta Ley antes de iniciar los trabajos de Reconocimiento y Exploración Superficial;\nIII. Cumplir los términos y condiciones que se establezcan en las Asignaciones, Contratos para la Exploración y Extracción y autorizaciones;\nIV. Abstenerse de ceder o traspasar, sin la autorización correspondiente, las Asignaciones o, en el caso de Contratos para la Exploración y Extracción, el control corporativo o de las operaciones;\nV. Contar con la aprobación de la Comisión Nacional de Hidrocarburos, previo a iniciar la ejecución del plan de Exploración y del plan de desarrollo para la Extracción;\nVI. Observar las disposiciones legales en materia laboral, fiscal y de transparencia que resulten aplicables;\nVII. Permitir el acceso a sus instalaciones y equipos, así como facilitar la labor de los inspectores y verificadores de las Secretarías de Energía, de Hacienda y Crédito Público y de Economía, de la Comisión Nacional de Hidrocarburos o de la Agencia;\nVIII. Cumplir con la regulación, lineamientos y disposiciones administrativas que emitan las Secretarías de Energía y de Hacienda y Crédito Público, la Comisión Nacional de Hidrocarburos y la Agencia en el ámbito de sus respectivas competencias;\nIX. Los Contratistas deberán observar los lineamientos que establezcan la Secretaría de Hacienda y Crédito Público y la Comisión Nacional de Hidrocarburos en relación con los Hidrocarburos;\nEn materia de seguridad industrial, operativa y protección al medio ambiente, los Asignatarios y Contratistas serán responsables de los desperdicios, derrames de Hidrocarburos o demás daños que resulten, en términos de las disposiciones jurídicas aplicables;\nX. Dar aviso a la Secretaría de Energía, a la Comisión Nacional de Hidrocarburos, a la Agencia y a las demás autoridades competentes sobre cualquier siniestro, hecho o contingencia que, como resultado de sus operaciones, ponga en peligro la vida, la salud y seguridad públicas, el medio ambiente, la seguridad de las instalaciones o la producción de Hidrocarburos; y aplicar los planes de contingencia, medidas de emergencia y acciones de contención que correspondan de acuerdo con su responsabilidad, en los términos de la regulación correspondiente. Sin perjuicio de lo anterior, deberán presentar ante dichas dependencias:\na) En un plazo que no excederá de diez días naturales, contados a partir del siniestro, hecho o contingencia de que se trate, un informe de hechos, así como las medidas tomadas para su control, en los términos de la regulación correspondiente, y b) En un plazo que no excederá de ciento ochenta días naturales, contados a partir del siniestro, hecho o contingencia de que se trate, un informe detallado sobre las causas que lo originaron y las medidas tomadas para su control y, en su caso, remediación, en los términos de la regulación correspondiente;\nXI. Proporcionar el auxilio que les sea requerido por las autoridades competentes en caso de emergencia o siniestro, conforme se establezca en la Asignación o el Contrato, y\nXII. Cumplir en tiempo y forma con las solicitudes de información y reportes que requieran las Secretarías de Energía, de Hacienda y Crédito Público y de Economía, la Comisión Nacional de Hidrocarburos, el Fondo Mexicano del Petróleo para la Estabilización y el Desarrollo y la Agencia, en el ámbito de sus respectivas competencias.\nLas infracciones a este Título y a sus disposiciones reglamentarias serán sancionadas conforme a lo previsto en el artículo 85 de esta Ley.\nTÍTULO TERCERO\nDe las demás Actividades de la Industria de Hidrocarburos\nCapítulo I\nDe los Permisos\nArtículo 48.- La realización de las actividades siguientes requerirá de permiso conforme a lo siguiente:\nI. Para el Tratamiento y refinación de Petróleo, el procesamiento de Gas Natural, y la exportación e importación de Hidrocarburos, y Petrolíferos, que serán expedidos por la Secretaría de Energía, y\nII. Para el Transporte, Almacenamiento, Distribución, compresión, licuefacción, descompresión, regasificación, comercialización y Expendio al Público de Hidrocarburos, Petrolíferos o Petroquímicos, según corresponda, así como la gestión de Sistemas Integrados, que serán expedidos por la Comisión Reguladora de Energía.\nArtículo 49.- Para realizar actividades de comercialización de Hidrocarburos, Petrolíferos y Petroquímicos en territorio nacional se requerirá de permiso. Los términos y condiciones de dicho permiso contendrán únicamente las siguientes obligaciones:\nI. Realizar la contratación, por sí mismos o a través de terceros, de los servicios de Transporte,\nAlmacenamiento, Distribución y Expendio al Público que, en su caso, requiera para la realización de sus actividades únicamente con Permisionarios;\nII. Cumplir con las disposiciones de seguridad de suministro que, en su caso, establezca la\nIII. Entregar la información que la Comisión Reguladora de Energía requiera para fines de supervisión y estadísticos del sector energético, y\nIV. Sujetarse a los lineamientos aplicables a los Permisionarios de las actividades reguladas, respecto de sus relaciones con personas que formen parte de su mismo grupo empresarial o consorcio.\nArtículo 50.- Los interesados en obtener los permisos a que se refiere este Título, deberán presentar solicitud a la Secretaría de Energía o a la Comisión Reguladora de Energía, según corresponda, que contendrá:\nI. El nombre y domicilio del solicitante;\nII. La actividad que desea realizar;\nIII. Las especificaciones técnicas del proyecto;\nIV. En su caso, el documento en que se exprese el compromiso de contar con las garantías o seguros que le sean requeridos por la autoridad competente, y\nV. La demás información que se establezca en la regulación correspondiente.\nArtículo 51.- Los permisos a que se refiere el presente Capítulo se otorgarán a Petróleos Mexicanos, a otras empresas productivas del Estado y a Particulares, con base en el Reglamento de esta Ley. El otorgamiento de los permisos estará sujeto a que el interesado demuestre que, en su caso, cuenta con:\nI. Un diseño de instalaciones o equipos acordes con la normativa aplicable y las mejores prácticas;\nII. Las condiciones apropiadas para garantizar la adecuada continuidad de la actividad objeto del permiso, y\nIII. La capacidad de almacenamiento que determine la Secretaría conforme a las disposiciones jurídicas aplicables.\nArtículo reformado DOF 04-05-2021\nArtículo 52.- En la evaluación y, en su caso, otorgamiento de un permiso de Transporte por ductos o de Almacenamiento de Hidrocarburos, Petrolíferos o Petroquímicos, la Comisión Reguladora de Energía podrá analizar su impacto sobre el desarrollo eficiente de dichas actividades y las necesidades de infraestructura común en la región que corresponda, pudiendo requerir que se modifique la naturaleza y el alcance de las instalaciones, a través de condiciones tales como el acceso abierto, la interconexión con otros sistemas permisionados y la regulación tarifaria.\nArtículo 53.- La cesión de los permisos o de la realización de las actividades reguladas al amparo del mismo, sólo podrá realizarse previa autorización de la Secretaría de Energía o de la Comisión\nReguladora de Energía, según corresponda, siempre que los permisos se encuentren vigentes, que el cedente haya cumplido con todas sus obligaciones, así como que el cesionario reúna los requisitos para permisos.\nLa Secretaría de Energía o la Comisión Reguladora de Energía, según el permiso de que se trate, deberá resolver la solicitud de cesión dentro de un plazo de noventa días naturales, contados a partir del día siguiente al de la recepción de la solicitud. En caso de no emitirse una resolución por parte de la establecido, ésta se entenderá en sentido negativo.\nPárrafo reformado DOF 04-05-2021\nCualquier cesión que se realice sin apegarse a lo establecido en este artículo será nula de pleno derecho.\nArtículo 54.- Los permisos podrán terminar por cualquiera de las causas siguientes:\nI. Vencimiento de la vigencia originalmente prevista en el permiso o de la prórroga otorgada;\nII. Renuncia del Permisionario, siempre que no se afecten derechos de terceros;\nIII. Caducidad;\nIV. Revocación;\nV. Desaparición del objeto o de la finalidad del permiso;\nVI. Disolución, liquidación o quiebra del Permisionario;\nVII. Resolución judicial o mandamiento firme de autoridad competente, o\nVIII. Las demás causas previstas en el permiso respectivo.\nLa terminación del permiso no exime a su titular de las responsabilidades contraídas durante su vigencia, con el Gobierno Federal y con terceros.\nDependiendo de la causal de terminación del permiso, se aplicará el importe de la garantía otorgada, en los términos que establezca el permiso de que se trate.\nArtículo 55.- Los permisos caducarán si los Permisionarios:\nI. No ejercen los derechos conferidos en el título del permiso de acuerdo con lo siguiente:\na) En el plazo que para tal efecto se establezca en el permiso, o b) A falta de plazo, por un periodo consecutivo de trescientos sesenta y cinco días naturales.\nII. Se ubican en los demás supuestos de caducidad previstos en el permiso respectivo.\nArtículo 56.- La Secretaría de Energía y la Comisión Reguladora de Energía podrán, en el ámbito de sus competencias, revocar los permisos expedidos en los términos establecidos en esta Ley.\nLos permisos podrán revocarse por cualquiera de las causas siguientes:\nI. Incumplir sin causa justificada y autorización de la Secretaría de Energía o de la Comisión\nReguladora de Energía, según corresponda, con el objeto, obligaciones o condiciones del permiso;\nII. Realizar prácticas indebidamente discriminatorias en perjuicio de los usuarios;\nIII. No respetar la regulación en materia de precios y tarifas, incluida la correspondiente en materia de contabilidad regulatoria, así como los términos y condiciones que, en su caso, llegare a fijar la autoridad competente o, en su caso las disposiciones que los regulan;\nIV. Ceder o gravar los permisos, los derechos en ellos conferidos, o los bienes utilizados para su ejecución, sin la autorización de la Secretaría de Energía o la Comisión Reguladora de Energía, según corresponda;\nV. No otorgar o no mantener en vigor las garantías o los seguros correspondientes incluyendo aquéllos necesarios para cubrir daños a terceros, conforme a la regulación que para el efecto se emita;\nVI. No cumplir con las normas oficiales mexicanas;\nVII. Incumplir de forma continua el pago de contribuciones y aprovechamientos por los servicios de supervisión de los permisos.\nPara efectos de esta fracción se considerará que el incumplimiento es continuo cuando el Permisionario omita el pago por más de un ejercicio fiscal;\nVIII. Interrumpir por un periodo de al menos treinta días naturales continuos las actividades objeto del permiso, sin causa justificada a juicio de la Secretaría de Energía o de la Comisión\nReguladora de Energía, según corresponda;\nIX. No acatar las resoluciones que, en el ámbito de su competencia, expida la Comisión Federal de Competencia Económica;\nX. No acatar las resoluciones que, en el ámbito de su competencia, expida la Agencia;\nXI. Realizar actividades de Transporte, Almacenamiento, Distribución o Expendio al Público de Hidrocarburos, Petrolíferos o Petroquímicos, que se compruebe hayan sido adquiridos de forma ilícita o por la comisión del delito de contrabando de Hidrocarburos, Petrolíferos y Petroquímicos, y que haya sido así determinado por resolución firme de autoridad competente;\nFracción reformada DOF 04-05-2021\nXII. Reincidir en las conductas señaladas en los incisos a) y h) de la fracción II del artículo 86 del presente ordenamiento, y\nFracción adicionada DOF 04-05-2021\nXIII. Las demás previstas en el permiso respectivo.\nArtículo 57.- En relación con los permisos a que se refiere esta Ley, la autoridad que lo haya expedido podrá llevar a cabo la ocupación temporal, la intervención o la suspensión, a fin de garantizar los intereses de la Nación, en el entendido de que quedarán salvaguardados los derechos de terceros.\nPara la continuidad en la operación de las actividades que ampare el permiso, la autoridad podrá contratar a empresas productivas del Estado para el manejo y control de las instalaciones ocupadas, intervenidas o suspendidas.\nArtículo 58.- Se consideran de utilidad pública, las actividades y servicios amparados por un permiso.\nProcederá la ocupación temporal de los bienes, derechos e instalaciones necesarias para la prestación del servicio o su adecuada operación, en los supuestos previstos en la Ley de Expropiación o cuando el Permisionario incumpla sus obligaciones por causas no imputables a éste, como pueden ser guerra, desastre natural, la grave alteración del orden público o cuando se prevea un peligro inminente para la seguridad nacional, la seguridad energética o para la economía nacional.\nLa autoridad que lo haya expedido integrará y tramitará el expediente de ocupación temporal de los bienes, derechos e instalaciones necesarias para la prestación del servicio u operación, a fin de garantizar los intereses de los usuarios finales y consumidores, quedando a salvo los derechos de los terceros.\nLa ocupación tendrá la duración que la autoridad determine sin que el plazo original o en su caso las prórrogas, en su conjunto, excedan de treinta y seis meses.\nEl Permisionario podrá solicitar a la autoridad que haya expedido el permiso la terminación de la ocupación, cuando demuestre que las causas que la ocasionaron ya fueron subsanadas o erradicadas, o han desaparecido.\nArtículo 59.- La autoridad que haya expedido el permiso podrá intervenir en la realización de la actividad o la prestación del servicio, cuando el Permisionario incumpla sus obligaciones, por causas imputables a éste, y ponga en peligro grave el suministro de los Hidrocarburos, Petrolíferos o Petroquímicos relacionados con el objeto del permiso.\nPara tales efectos, la autoridad deberá notificar al Permisionario la causa que motiva la intervención y señalar un plazo para subsanarla. Si dentro del plazo establecido el Permisionario no la corrige, la autoridad procederá a la intervención, sin perjuicio de las sanciones y responsabilidades en las que, en su caso, incurra el Permisionario.\nDurante la intervención, la autoridad que haya emitido el permiso se hará cargo de la administración y operación del Permisionario, para asegurar el adecuado suministro y desarrollo de las actividades objeto del mismo. Al efecto, podrá designar a uno o varios interventores, utilizar al personal que el Permisionario venía utilizando, contratar a un nuevo operador o una combinación de las anteriores.\nLos interventores podrán ser del sector público, privado o social, siempre y cuando cuenten con capacidad técnica y experiencia en el manejo y control de las instalaciones intervenidas. La autoridad y los interventores tendrán derecho a cobrar los gastos en que hayan incurrido, así como los honorarios correspondientes, con cargo a los ingresos del Permisionario durante el periodo de la intervención.\nLa intervención tendrá la duración que la autoridad determine sin que el plazo original y las prórrogas, en su conjunto, excedan de treinta y seis meses.\ndirectamente con la ejecución de las actividades sujetas a un permiso.\nEl Permisionario podrá solicitar la terminación de la intervención, cuando demuestre que las causas que la ocasionaron ya fueron subsanadas o erradicadas.\nSi transcurrido el plazo de la intervención, el Permisionario no está en condiciones de continuar con sus obligaciones, la autoridad procederá a la revocación del permiso.\nArtículo 59 Bis.- La Secretaría de Energía y la Comisión Reguladora de Energía podrán, en el ámbito de sus respectivas competencias, suspender los permisos expedidos en los términos establecidos en esta Ley, cuando se prevea un peligro inminente para la seguridad nacional, la seguridad energética o para la economía nacional.\nLa autoridad que lo haya expedido integrará y tramitará el expediente de suspensión del permiso, a fin de garantizar los intereses de los usuarios finales y consumidores, quedando a salvo los derechos de los terceros y el interés del Estado.\nLa suspensión requerirá la notificación previa al Permisionario indicando las causas que motivan la suspensión, las razones por las cuales se estima procedente y la afectación que podría darse en caso de que continúen los actos que ampare el permiso. Una vez realizada la notificación, el Permisionario contará con un plazo de quince días naturales, contados a partir de la fecha de la notificación, para exponer lo que a su derecho convenga y aportar, en su caso, las pruebas que estime pertinentes.\nTranscurrido el plazo de quince días a que se refiere el párrafo anterior, la autoridad que haya otorgado el permiso contará con un plazo de quince días naturales para resolver, considerando los argumentos y pruebas que, en su caso, hubiere hecho valer el Permisionario. La determinación de suspender o no el permiso deberá ser debidamente fundada, motivada y notificada al Permisionario, sin perjuicio de las infracciones y responsabilidades en las que, en su caso, este último incurra.\nLa autoridad que haya emitido el permiso se hará cargo de la administración y operación del Permisionario, para la continuidad en la operación de las actividades que ampare el permiso, a fin de garantizar los intereses de los usuarios finales y consumidores, quedando a salvo los derechos de los terceros. Al efecto, podrá utilizar al personal que el Permisionario venía utilizando, contratar a un nuevo operador o una combinación de las anteriores.\nLa suspensión tendrá la duración que la autoridad determine.\nEl Permisionario podrá solicitar a la autoridad que haya expedido el permiso la terminación de la suspensión, cuando demuestre que las causas que la ocasionaron ya fueron subsanadas o erradicadas, o han desaparecido, siempre y cuando la causa no tenga origen en un acto ilícito en la comercialización y/o Transporte o alteración de los componentes del combustible.\nSi transcurrido el plazo de la suspensión, el Permisionario no está en condiciones de continuar con sus obligaciones, la autoridad procederá a la revocación del permiso.\nArtículo adicionado DOF 04-05-2021\nCapítulo II\nDe los Sistemas Integrados\nArtículo 60.- Los sistemas de Transporte por ducto y de Almacenamiento de Gas Natural, Petrolíferos y Petroquímicos que se encuentren interconectados podrán conformar Sistemas Integrados, con objeto de ampliar la cobertura o aportar beneficios sistémicos en términos de mejoras en las condiciones de seguridad, continuidad, calidad y eficiencia en la prestación de los servicios.\nLa Secretaría de Energía, con base en la política pública en materia energética que al respecto emita, fin de alcanzar los objetivos planteados en el párrafo anterior. Asimismo, la Secretaría de Energía será la por ducto y Almacenamiento, tomando en consideración lo propuesto por los gestores de los sistemas integrados, previa asistencia técnica de la Comisión Reguladora de Energía.\nArtículo 61.- La Comisión Reguladora de Energía será la autoridad competente para aprobar la creación de Sistemas Integrados, así como para determinar la incorporación de nueva infraestructura a los mismos, de acuerdo con la política pública en materia energética que al efecto emita la Secretaría de Energía.\nLa prestación de los servicios en los Sistemas Integrados se sujetará a las disposiciones de carácter general que la Comisión Reguladora de Energía apruebe y expida.\nArtículo 62.- Cada Sistema Integrado será operado por un gestor que deberá tener el permiso correspondiente emitido por la Comisión Reguladora de Energía. Los gestores tendrán como objeto lo siguiente:\nI. Coordinar a los distintos Permisionarios de Transporte por ducto y Almacenamiento para lograr la continuidad, calidad, seguridad y eficiencia en la prestación de los servicios, garantizar el acceso abierto efectivo y no indebidamente discriminatorio;\nII. Responder respecto de las obligaciones de pago de las tarifas de los sistemas de Transporte o Almacenamiento que compongan el Sistema Integrado, en los términos que determine la Comisión Reguladora de Energía;\nIII. Propiciar el desarrollo de centros de mercado y mercados mayoristas;\nIV. Fomentar la liquidez de los mercados en que participe y asegurar el balance y operación del Sistema Integrado que corresponda, de conformidad con las disposiciones aplicables, y\nV. Administrar el mercado secundario de capacidad del Sistema Integrado que corresponda.\nLos gestores serán independientes de las personas que realicen actividades de producción, distribución y comercialización de Gas Natural, Petrolíferos o Petroquímicos.\nLos gestores operarán previo permiso otorgado por la Comisión Reguladora de Energía.\nArtículo 63.- Los gestores a que se refiere el artículo anterior podrán ser entidades públicas, privadas o público-privadas en las que podrán participar los Permisionarios que conformen el Sistema Integrado.\nEn sus actividades, dichos gestores podrán recuperar costos e inversiones, en los términos que establezca la Comisión Reguladora de Energía.\nEn todo caso, se deberá evitar el conflicto de interés entre el gestor y los Permisionarios de Transporte y Almacenamiento, así como de las personas que enajenen y comercialicen Gas Natural,\nPetrolíferos y Petroquímicos.\nArtículo 64.- La Comisión Reguladora de Energía establecerá, mediante disposiciones de carácter general, las reglas de operación y los códigos de ética que eviten conflictos de interés y establezcan la separación funcional correspondiente a dichos gestores.\nArtículo 65.- El Sistema de Transporte y Almacenamiento Nacional Integrado de Gas Natural se podrá conformar por la siguiente infraestructura:\nI. Ductos de Transporte e instalaciones de Almacenamiento de Gas Natural, y\nII. Equipos de compresión, licuefacción, descompresión, regasificación y demás instalaciones vinculadas a la infraestructura de Transporte y Almacenamiento de Gas Natural.\ninstalaciones de Recolección, Ductos de Internación al país o las instalaciones de procesamiento de Gas\nNatural y hasta los puntos de recepción y medición de los sistemas de Distribución, o de los usuarios finales conectados directamente, podrá integrarse al Sistema de Transporte y Almacenamiento Nacional\nIntegrado de Gas Natural.\nLa Comisión Reguladora de Energía será la autoridad competente para determinar la integración de la infraestructura pública referida en el párrafo anterior al Sistema de Transporte y Almacenamiento\nNacional Integrado de Gas Natural. La integración de los sistemas de almacenamiento y transporte privados es de carácter voluntario.\nCapítulo III\nDel Centro Nacional de Control del Gas Natural\nArtículo 66.- El Centro Nacional de Control del Gas Natural es el gestor y administrador independiente del Sistema de Transporte y Almacenamiento Nacional Integrado de Gas Natural y tiene por objeto garantizar la continuidad y seguridad en la prestación de los servicios en ese sistema para contribuir con la continuidad del suministro de dicho energético en territorio nacional, así como realizar las demás actividades señaladas en la presente Ley y en el respectivo Decreto del Ejecutivo Federal.\nLa gestión y administración a que se refiere la presente Ley deberá entenderse como la potestad del Centro Nacional de Control del Gas Natural para instruir las acciones necesarias a los Permisionarios de Transporte por ducto y Almacenamiento vinculado a ducto para que tanto la operación diaria como la de mediano y largo plazo del sistema permisionado, se realice en estricto apego a las obligaciones de acceso abierto, sin que se afecte en modo alguno la titularidad de los contratos de reserva de capacidad.\nEl Centro Nacional de Control del Gas Natural deberá ejercer sus funciones bajo los principios de eficiencia, transparencia y objetividad, así como de independencia respecto de los Permisionarios cuyos sistemas conformen el Sistema de Transporte y Almacenamiento Nacional Integrado de Gas Natural.\nEl Ejecutivo Federal deberá garantizar la independencia del Centro Nacional de Control del Gas\nNatural respecto de los demás Permisionarios y empresas del sector.\nLa conducción del Centro Nacional de Control del Gas Natural estará a cargo de un Consejo de Administración y de un Director General. La dirección y visión estratégica del Centro Nacional de Control del Gas Natural estará a cargo de su Consejo de Administración, mismo que contará al menos con una tercera parte de consejeros independientes.\nLos consejeros independientes del Centro Nacional de Control del Gas Natural no deberán tener conflicto de interés, por lo que no podrán tener relación laboral o profesional con los demás integrantes del mercado del Gas Natural.\nLa gestión, administración y ejecución de las funciones del Centro Nacional de Control del Gas\nNatural, en particular la asignación de la capacidad del Sistema Nacional de Transporte y Almacenamiento Integrado de Gas Natural, estarán a cargo exclusivamente de la Dirección General, para lo cual gozará de autonomía.\nEn los comités consultivos que, en su caso, cree el Consejo de Administración del Centro Nacional de Control del Gas Natural, participarán representantes del mercado de Gas Natural.\nArtículo 67.- El Centro Nacional de Control del Gas Natural no podrá privilegiar el uso de su infraestructura o la ampliación de la misma en calidad de Permisionario, en detrimento de la infraestructura integrada que pertenezca a otros Permisionarios.\nControl del Gas Natural para cumplir con lo previsto en el presente artículo.\nArtículo 68.- El Centro Nacional de Control del Gas Natural prestará los servicios de Transporte y Almacenamiento en la infraestructura de la que sea titular como Permisionario.\nCon independencia de su actividad como Permisionario de Transporte y de Almacenamiento, el Centro Nacional de Control del Gas Natural se sujetará a las reglas de operación que emita la Comisión\nReguladora de Energía para los gestores de los Sistemas Integrados.\nArtículo 69.- El Centro Nacional de Control del Gas Natural deberá proponer a la Secretaría de Energía, para su aprobación, previa opinión técnica de la Comisión Reguladora de Energía, el plan quinquenal de expansión del Sistema de Transporte y Almacenamiento Nacional Integrado de Gas\nNatural.\nEl plan quinquenal referido en el párrafo anterior contendrá, además de la planeación indicativa, los proyectos de cobertura social y aquellos que la Secretaría de Energía considere estratégicos para garantizar el desarrollo eficiente del Sistema de Transporte y Almacenamiento Nacional Integrado de Gas\nNatural.\nLos proyectos tendrán la naturaleza de estratégicos cuando cumplan con, al menos, alguna de las siguientes características:\nI. Tengan un diseño que considere como mínimo un diámetro de treinta pulgadas, una presión operativa igual o superior a 800 libras y una longitud de al menos 100 kilómetros;\nII. Aporten redundancia al sistema, incluyendo el almacenamiento;\nIII. Brinden una nueva ruta o fuente de suministro a un mercado relevante, o\nIV. Cuando por razones de seguridad de suministro, debidamente motivado, así lo determine la Secretaría de Energía.\nTratándose de los proyectos estratégicos, el Centro Nacional de Control del Gas Natural será el responsable de licitarlos. Las bases de licitación deberán ser aprobadas por la Comisión Reguladora de Energía y la infraestructura será desarrollada por terceros.\nEl Centro Nacional de Control del Gas Natural podrá convocar conjuntamente cualquier licitación, apoyado de las empresas productivas del Estado y los Particulares, cuando aporten una capacidad de demanda significativa.\nTratándose de proyectos no considerados como estratégicos, las empresas productivas del Estado y los Particulares podrán desarrollar, sujetos al cumplimiento de la normatividad aplicable, proyectos de infraestructura actuando bajo su propia cuenta y riesgo. En el caso de las empresas productivas del Estado, los proyectos deberán ejecutarse por terceros a través de procesos de licitación, en los cuales éstas reservarán la capacidad que requieran para sus operaciones. Las bases de licitación deberán ser aprobadas por la Comisión Reguladora de Energía.\nTemporadas Abiertas en los términos que establezca la Comisión Reguladora de Energía.\nLa Secretaría de Energía, con la asistencia técnica de la Comisión Reguladora de Energía, verificará lineamientos del plan quinquenal de expansión del Sistema de Transporte y Almacenamiento Nacional\nIntegrado de Gas Natural. En caso contrario, la Secretaría dictará las acciones correctivas que procedan.\nCada año, la Secretaría de Energía, con la asistencia técnica de la Comisión Reguladora de Energía, llevará a cabo una evaluación del plan quinquenal de expansión a fin de verificar su vigencia ante la evolución del mercado de Gas Natural y realizar los ajustes necesarios para garantizar el desarrollo eficiente del Sistema de Transporte y Almacenamiento Nacional Integrado de Gas Natural.\nCapítulo IV\nDel Acceso Abierto\nArtículo 70.- Los Permisionarios que presten a terceros los servicios de Transporte y Distribución por medio de ductos, así como de Almacenamiento de Hidrocarburos, Petrolíferos y Petroquímicos, tendrán la obligación de dar acceso abierto no indebidamente discriminatorio a sus instalaciones y servicios, sujeto a disponibilidad de capacidad en sus sistemas, en términos de la regulación emitida por la Comisión Reguladora de Energía.\nPara efectos de este artículo, los Permisionarios que cuenten con capacidad que no se encuentre contratada o que estando contratada no sea utilizada, la deberán hacer pública mediante boletines electrónicos permitiendo a terceros aprovechar dicha capacidad disponible, previo pago de la tarifa autorizada y conforme a las condiciones para la prestación del servicio establecidas por la Comisión\nReguladora de Energía.\nLa prestación de los servicios bajo el principio de acceso abierto se sujetará a las disposiciones de carácter general que expida la Comisión Reguladora de Energía.\nLa Comisión Reguladora de Energía expedirá la regulación a la que se sujetarán las instalaciones de Transporte y de Almacenamiento para que puedan ser consideradas como de usos propios.\nCorresponde a la Secretaría de Energía expedir la política pública en materia energética que se requiera para garantizar el suministro confiable y el acceso abierto a los Ductos de Internación de Gas\nNatural. Lo anterior, considerando el desarrollo eficiente de la industria, la seguridad, calidad y continuidad del suministro y los intereses de los usuarios.\nArtículo 71.- Los Permisionarios de Transporte por ductos y Almacenamiento que se encuentren sujetos a la obligación de acceso abierto no podrán enajenar o comercializar Hidrocarburos, Petrolíferos y Petroquímicos que hayan sido transportados o almacenados en sus sistemas permisionados, salvo cuando ello sea necesario para resolver una situación de emergencia operativa, caso fortuito o fuerza mayor. Asimismo, estos Permisionarios se sujetarán a lo siguiente:\nI. Sólo podrán prestar el servicio de transporte y almacenamiento a los usuarios que acrediten la propiedad del producto respectivo o a las personas que aquéllos designen expresamente;\nII. Sólo podrán transportar y almacenar productos de su propiedad siempre y cuando sea necesario para la operación de sus sistemas, y\nIII. En el caso de Petróleo, Petrolíferos y Petroquímicos, podrán destinar al Transporte y Almacenamiento de productos de su propiedad, el porcentaje de capacidad que para tal efecto determine la Comisión Reguladora de Energía en el permiso correspondiente.\nArtículo 72.- Cuando los Permisionarios presten a terceros los servicios señalados en el artículo 70 de esta Ley, la Comisión Reguladora de Energía podrá solicitar la certificación de la capacidad instalada, disponible y utilizada en las instalaciones de Transporte por ductos y de Almacenamiento de Hidrocarburos, Petrolíferos y Petroquímicos, a través de un tercero independiente debidamente calificado, en los términos de las disposiciones que emita la propia Comisión.\nArtículo 73.- Las personas que cuenten con contratos de reserva de capacidad y no la hagan efectiva, deberán comercializarla en mercados secundarios o ponerla a disposición del gestor independiente del Sistema Integrado o del transportista a cargo del ducto o almacenista cuando las instalaciones correspondientes no formen parte de un Sistema Integrado, quienes a su vez deberán hacerla pública en un boletín electrónico para que pueda ser contratada de manera firme en caso de certeza de no uso, de manera interrumpible o mediante una Temporada Abierta, si la liberación de capacidad fuera permanente.\nLa Comisión Reguladora de Energía establecerá los términos y condiciones a los que se sujetarán las personas previstas en el presente artículo.\nArtículo 74.- Los Permisionarios y usuarios podrán celebrar convenios de inversión para el desarrollo de ductos de Transporte y el Almacenamiento de Gas Natural, en los términos que apruebe la Comisión\nReguladora de Energía. El diseño de la infraestructura podrá considerar las necesidades de consumo propio para sus instalaciones o de comercialización según el usuario de que se trate, así como la demanda presente y futura de la zona de influencia del proyecto.\nA fin de cuantificar la demanda señalada en el párrafo anterior, el desarrollador del proyecto deberá realizar una Temporada Abierta, conforme a los términos de las disposiciones que emita la Comisión\nReguladora de Energía. En su defecto, previa justificación, la Secretaría de Energía podrá determinar el nivel de capacidad requerido en el proyecto de que se trate, y corresponderá a la Comisión Reguladora de Energía determinar la metodología tarifaria que permita la recuperación de las inversiones correspondientes.\nArtículo 75.- Para los efectos del artículo anterior, los Permisionarios y los usuarios podrán establecer las condiciones para el uso de capacidad adicional, sujeto a que no impidan a terceros el acceso abierto no indebidamente discriminatorio a la capacidad adicional generada, que no sea utilizada. Lo anterior, en los términos que apruebe la Comisión Reguladora de Energía.\nCuando la extensión o ampliación de la capacidad de infraestructura de Transporte y Almacenamiento de Gas Natural sea financiada por los Permisionarios, la capacidad adicional generada será hecha pública mediante un boletín electrónico. En caso de existir interés de terceros, dicha capacidad será asignada a los usuarios a través de una Temporada Abierta.\nCapítulo V\nDel Expendio al Público\nArtículo 76.- Los combustibles para aeronaves no podrán ser expendidos directamente al público.\nEnergía, estarán facultadas para realizar la actividad de Distribución de combustibles para aeronaves en aeródromos a los siguientes usuarios:\nI. Transportistas aéreos;\nII. Operadores aéreos, y\nIII. Terceros para actividades distintas de las aeronáuticas.\nEn el caso de la fracción III del presente artículo, dichos terceros deberán contar previamente con el pronunciamiento favorable de las Secretarías de Energía y de Comunicaciones y Transportes.\nPárrafo reformado DOF 20-05-2021\nLa Comisión Reguladora de Energía emitirá las disposiciones generales aplicables para el otorgamiento de los permisos previstos en el presente artículo.\nArtículo 77.- Los Hidrocarburos, los Petrolíferos y los Petroquímicos deberán transportarse, almacenarse, distribuirse, enajenarse, expenderse y suministrarse sin alteración, de conformidad con lo que establece esta Ley y demás disposiciones aplicables.\nPara efectos de la presente Ley, se considerará que los combustibles han sido alterados cuando se modifique su composición respecto de las especificaciones establecidas en las disposiciones aplicables.\nArtículo 78.- Las especificaciones de calidad de los Hidrocarburos, Petrolíferos y Petroquímicos serán establecidas en las normas oficiales mexicanas que al efecto expida la Comisión Reguladora de Energía.\nLas especificaciones de calidad corresponderán con los usos comerciales, nacionales e internacionales, en cada etapa de la cadena de producción y suministro.\nArtículo 79.- Los métodos de prueba, muestreo y verificación aplicables a las características cualitativas, así como al volumen en el Transporte, Almacenamiento, Distribución y, en su caso, el Expendio al Público de Hidrocarburos, Petrolíferos y Petroquímicos se establecerán en las normas oficiales mexicanas que para tal efecto expidan la Comisión Reguladora de Energía y la Secretaría de Economía, en el ámbito de su competencia.\nCapítulo VI\nDe la Regulación y Obligaciones de las demás Actividades de la Industria de Hidrocarburos\nArtículo 80.- Corresponde a la Secretaría de Energía:\nI. Regular y supervisar, sin perjuicio de las atribuciones que correspondan a la Agencia, así como otorgar, modificar y revocar los permisos para las siguientes actividades:\na) El Tratamiento y refinación de Petróleo;\nb) El procesamiento del Gas Natural, y c) La exportación e importación de Hidrocarburos y Petrolíferos en términos de la Ley de Comercio Exterior y con el apoyo de la Secretaría de Economía;\nII. Determinar la política pública en materia energética aplicable a los niveles de Almacenamiento y a la garantía de suministro de Hidrocarburos y Petrolíferos, a fin de salvaguardar los intereses y la seguridad nacionales.\nCon base en lo anterior, la Secretaría de Energía y la Comisión Reguladora de Energía establecerán, mediante disposiciones de carácter general o bien en los permisos correspondientes, las medidas que deberán cumplir los Permisionarios respecto de dicha política pública.\nLa gestión de los niveles mínimos de almacenamiento podrá ser llevada a cabo por la Secretaría de Energía o por la instancia que ésta designe;\nIII. Instruir, por sí misma o a propuesta de la Comisión Reguladora de Energía o de la Comisión\nFederal de Competencia Económica, en el ámbito de sus respectivas competencias, a las empresas productivas del Estado, sus subsidiarias y filiales que realicen las acciones necesarias para garantizar que sus actividades y operaciones no obstaculicen la competencia y el desarrollo eficiente de los mercados, así como la política pública en materia energética.\nLa Secretaría de Energía podrá realizar los estudios que considere pertinentes a fin de determinar la viabilidad de ejercer por sí misma la atribución a que se refiere la presente fracción;\nIV. Emitir el plan quinquenal de expansión y optimización de la infraestructura de Transporte por ducto y Almacenamiento a nivel nacional, con la asistencia técnica de la Comisión Reguladora de Energía, y considerando las propuestas que al efecto emitan, en su caso, los gestores de los Sistemas Integrados y los usuarios de dichos sistemas;\nV. Dictar los planes de emergencia para la continuidad de las actividades en los Sistemas\nIntegrados de Transporte por ducto y Almacenamiento, para lo cual considerará las opiniones que emitan la Comisión Reguladora de Energía y los gestores de dichos sistemas, y\nVI. Emitir los lineamientos de política pública en materia de Hidrocarburos, Petrolíferos y Petroquímicos a efecto de que la Comisión Reguladora de Energía los incorpore en la regulación de dichas actividades.\nComo parte de la regulación y las disposiciones de política que emita, la Secretaría de Energía podrá instruir la adopción y observancia de estándares técnicos internacionales.\nLas actividades de la Secretaría de Energía se orientarán con base en los objetivos de la política pública en materia energética, incluyendo los de seguridad energética del país, la sustentabilidad, continuidad del suministro de combustibles y la diversificación de mercados.\nArtículo 81.- Corresponde a la Comisión Reguladora de Energía:\nI. Regular y supervisar las siguientes actividades, sin perjuicio de las atribuciones que correspondan a la Agencia:\na) Transporte y Almacenamiento de Hidrocarburos y Petrolíferos;\nb) El Transporte por ducto y el Almacenamiento que se encuentre vinculado a ductos, de Petroquímicos;\nc) Distribución de Gas Natural y Petrolíferos;\nd) Regasificación, licuefacción, compresión y descompresión de Gas Natural;\ne) Comercialización y Expendio al Público de Gas Natural y Petrolíferos, y f) Gestión de los Sistemas Integrados, incluyendo el Sistema de Transporte y Almacenamiento Nacional Integrado de Gas Natural;\nII. Aprobar, con la opinión favorable de la Secretaría de Energía, la creación de Sistemas\nIntegrados, las condiciones de prestación del servicio en los mismos y expedir las metodologías tarifarias respectivas, así como expedir las reglas de operación de los gestores independientes de dichos Sistemas;\nIII. Aprobar las bases de las licitaciones que realice el Centro Nacional de Control del Gas\nNatural, así como los procesos de Temporadas Abiertas que realicen los Permisionarios para asignar la capacidad en los sistemas de Transporte y Almacenamiento de Gas Natural;\nIV. Opinar sobre la planificación de la expansión del Transporte y la Distribución de Gas Natural y de Gas Licuado de Petróleo, conforme a los lineamientos que para tal efecto establezca la Secretaría de Energía;\nV. Determinar, con la opinión de la Secretaría de Energía, las zonas geográficas para la Distribución por ducto de Gas Natural, de oficio o a solicitud de parte, considerando los elementos que permitan el desarrollo rentable y eficiente de los sistemas de distribución. Para efectos de lo anterior, la Comisión escuchará la opinión de las autoridades competentes, incluyendo las de desarrollo urbano, y partes interesadas;\nVI. Supervisar las actividades reguladas, con objeto de evaluar su funcionamiento conforme a los objetivos de la política pública en materia energética y, en su caso, tomar las medidas conducentes, tales como expedir o modificar la regulación, proveer información pública sobre los resultados de sus análisis y el desempeño de los participantes, e informar a la Secretaría de Energía o la Comisión Federal de Competencia Económica, en el ámbito de sus atribuciones;\nVII. Establecer lineamientos a los que se sujetarán los Permisionarios de las actividades reguladas, respecto de sus relaciones con personas que formen parte de su mismo grupo empresarial o consorcio que lleven a cabo actividades de comercialización de Hidrocarburos,\nPetrolíferos y Petroquímicos;\nVIII. Recopilar información sobre los precios, descuentos y volúmenes en materia de comercialización y Expendio al Público de Gas Natural y Petrolíferos, para fines estadísticos, regulatorios y de supervisión, y\nIX. Proponer, en el ámbito de su competencia, a la Secretaría de Energía que instruya a las empresas productivas del Estado, sus subsidiarias y filiales que realicen las acciones necesarias para garantizar que sus actividades y operaciones no obstaculicen la competencia y el desarrollo eficiente de los mercados, así como la política pública en materia energética.\nArtículo 82.- La Comisión Reguladora de Energía expedirá disposiciones de aplicación general para la regulación de las actividades a que se refiere esta Ley, en el ámbito de su competencia, incluyendo los términos y condiciones a los que deberán sujetarse la prestación de los servicios; al igual que la determinación de las contraprestaciones, precios y tarifas aplicables, entre otros.\nLa regulación de contraprestaciones, precios y tarifas que establezca la Comisión Reguladora de Energía, con excepción de las actividades de Expendio al Público de Gas Licuado de Petróleo, gasolinas y diésel, cuyos precios se determinarán conforme a las condiciones de mercado, se sujetará a lo siguiente:\nI. La regulación para cada actividad en particular será aplicable salvo que, a juicio de la Comisión Federal de Competencia Económica, existan condiciones de competencia efectiva en dicha actividad, en cuyo caso las contraprestaciones, precios o tarifas correspondientes se determinarán por las condiciones de mercado;\nII. La regulación, además de contemplar los impuestos que determinen las leyes aplicables, considerará que:\na) Las contraprestaciones, precios y tarifas, de los bienes y servicios susceptibles de comercializarse internacionalmente se fijarán considerando el costo de oportunidad y las condiciones de competitividad prevalecientes en el mercado internacional de estos productos, libres de impuestos, contribuciones o gravámenes, y b) Para aquellos bienes o servicios que no sean susceptibles de comercializarse en el mercado internacional, las contraprestaciones, precios y tarifas se fijarán de acuerdo a las metodologías de aplicación general para su cálculo que para tal efecto emita la Comisión Reguladora de Energía, considerando la estimación de costos eficientes para producir el bien o prestar el servicio, así como la obtención de una rentabilidad razonable que refleje el costo de oportunidad del capital invertido, el costo estimado de financiamiento y los riesgos inherentes del proyecto, entre otros.\nLa Secretaría de Energía, la Comisión Reguladora de Energía o los Permisionarios podrán solicitar a la Comisión Federal de Competencia Económica que evalúe la existencia de condiciones de competencia efectiva y, en su caso, que emita la declaratoria correspondiente.\nArtículo 83.- La Comisión Reguladora de Energía, con la opinión de la Comisión Federal de Competencia Económica, establecerá las disposiciones a las que deberán sujetarse los Permisionarios de Transporte, Almacenamiento, Distribución, Expendio al Público y comercialización de Hidrocarburos,\nPetrolíferos y Petroquímicos, así como los usuarios de dichos productos y servicios, con objeto de promover el desarrollo eficiente de mercados competitivos en estos sectores. Entre otros aspectos, dichas disposiciones podrán establecer la estricta separación legal entre las actividades permisionadas o la separación funcional, operativa y contable de las mismas; la emisión de códigos de conducta, límites a la participación en el capital social, así como la participación máxima que podrán tener los agentes económicos en el mercado de la comercialización y, en su caso, en la reserva de capacidad en los ductos de Transporte e instalaciones de Almacenamiento.\nLas disposiciones a que se refiere el párrafo anterior contemplarán que las personas que, directa o indirectamente, sean propietarias de capital social de usuarios finales, productores o comercializadores de Hidrocarburos, Petrolíferos y Petroquímicos que utilicen los servicios de Transporte por ducto o Almacenamiento sujetos a acceso abierto, solamente podrán participar, directa o indirectamente, en el capital social de los Permisionarios que presten estos servicios cuando dicha participación cruzada no afecte la competencia, la eficiencia en los mercados y el acceso abierto efectivo, para lo cual deberán:\nI. Realizar sus operaciones en sistemas independientes, o\nII. Establecer los mecanismos jurídicos y corporativos que impidan intervenir de cualquier manera en la operación y administración de los Permisionarios respectivos.\nEn todo caso, la participación cruzada a la que se refiere el segundo párrafo de este artículo y sus modificaciones deberán ser autorizadas por la Comisión Reguladora de Energía, quien deberá contar previamente con la opinión favorable de la Comisión Federal de Competencia Económica.\nArtículo 84.- Los Permisionarios de las actividades reguladas por la Secretaría de Energía o la Comisión Reguladora de Energía, deberán, según corresponda:\nI. Contar con el permiso vigente correspondiente;\nII. Cumplir los términos y condiciones establecidos en los permisos, así como abstenerse de ceder, traspasar, enajenar o gravar, total o parcialmente, los derechos u obligaciones derivados de los mismos en contravención de esta Ley;\nIII. Entregar la cantidad y calidad de Hidrocarburos, Petrolíferos y Petroquímicos, conforme se establezca en las disposiciones aplicables;\nIV. Cumplir con la cantidad, medición y calidad conforme se establezca en las disposiciones jurídicas aplicables;\nV. Realizar sus actividades, con Hidrocarburos, Petrolíferos y Petroquímicos de procedencia lícita;\nVI. Prestar los servicios de forma eficiente, uniforme, homogénea, regular, segura y continua, así como cumplir los términos y condiciones contenidos en los permisos;\nVII. Contar con un servicio permanente de recepción y atención de quejas y reportes de emergencia;\nVIII. Obtener autorización de la Secretaría de Energía, o de la Comisión Reguladora de Energía, para modificar las condiciones técnicas y de prestación del servicio de los sistemas, ductos, instalaciones o equipos, según corresponda;\nIX. Dar aviso a la Secretaría de Energía, o a la Comisión Reguladora de Energía, según corresponda, de cualquier circunstancia que implique la modificación de los términos y condiciones en la prestación del servicio;\nX. Abstenerse de otorgar subsidios cruzados en la prestación de los servicios permisionados, así como de realizar prácticas indebidamente discriminatorias;\nXI. Respetar los precios o tarifas máximas que se establezcan;\nXII. Obtener autorización de la Secretaría de Energía o de la Comisión Reguladora de Energía, según corresponda, para la suspensión de los servicios, salvo por causa de caso fortuito o fuerza mayor, en cuyo caso se deberá informar de inmediato a la autoridad correspondiente;\nXIII. Observar las disposiciones legales en materia laboral, fiscal y de transparencia que resulten aplicables;\nXIV. Permitir el acceso a sus instalaciones y equipos, así como facilitar la labor de los verificadores de las Secretarías de Energía, y de Hacienda y Crédito Público, así como de la Comisión\nReguladora de Energía y la Agencia, según corresponda;\nXV. Cumplir con la regulación, lineamientos y disposiciones administrativas que emitan las Secretarías de Energía, de Hacienda y Crédito Público, la Comisión Reguladora de Energía y la Agencia, en el ámbito de sus respectivas competencias.\nEn materia de seguridad industrial, operativa y protección al medio ambiente, los Permisionarios serán responsables de los desperdicios, derrames de Hidrocarburos,\nPetrolíferos y Petroquímicos o demás daños que resulten, en términos de las disposiciones jurídicas aplicables;\nXVI. Dar aviso a la Secretaría de Energía, a la Comisión Reguladora de Energía, a la Agencia y a las demás autoridades competentes sobre cualquier siniestro, hecho o contingencia que, como resultado de sus actividades, ponga en peligro la vida, la salud o la seguridad públicas, el medio ambiente; la seguridad de las instalaciones o la producción o suministro de Hidrocarburos, Petrolíferos y Petroquímicos; y aplicar los planes de contingencia, medidas de emergencia y acciones de contención que correspondan de acuerdo con su responsabilidad, en los términos de la regulación correspondiente. Sin perjuicio de lo anterior, deberán presentar ante dichas dependencias:\na) En un plazo que no excederá de diez días naturales, contados a partir del siniestro, hecho o contingencia de que se trate, un informe de hechos, así como las medidas tomadas para su control, en los términos de la regulación correspondiente, y b) En un plazo que no excederá de ciento ochenta días naturales, contados a partir del siniestro, hecho o contingencia de que se trate, un informe detallado sobre las causas que lo originaron y las medidas tomadas para su control y, en su caso, remediación, en los términos de la regulación correspondiente;\nXVII. Proporcionar el auxilio que les sea requerido por las autoridades competentes en caso de emergencia o siniestro;\nXVIII. Presentar anualmente, en los términos de las normas oficiales mexicanas aplicables, el programa de mantenimiento de sus sistemas e instalaciones y comprobar su cumplimiento con el dictamen de una unidad de verificación debidamente acreditada;\nXIX. Llevar un libro de bitácora para la operación, supervisión y mantenimiento de obras e instalaciones, así como capacitar a su personal en materias de prevención y atención de siniestros;\nXX. Cumplir en tiempo y forma con las solicitudes de información y reportes que soliciten las Secretarías de Energía y de Hacienda y Crédito Público, la Comisión Reguladora de Energía y la Agencia, y\nXXI. Presentar la información en los términos y formatos que les sea requerida por la Secretaría de Energía o la Comisión Reguladora de Energía, en el ámbito de sus competencias, en relación con las actividades reguladas.\nTÍTULO CUARTO\nCapítulo I\nDe las Sanciones\nArtículo 85.- Las infracciones al Título Segundo de esta Ley y a sus disposiciones reglamentarias serán sancionadas tomando en cuenta la gravedad de la falta, de acuerdo con lo siguiente:\nI. La Secretaría de Energía sancionará:\na) El incumplimiento de los términos y condiciones que se establezcan en las Asignaciones, con multa de entre quince mil y setenta y cinco mil veces el importe del salario mínimo;\nb) La cesión, enajenación, traspaso o gravamen total o parcial, de los derechos u Ley, con multa de entre trescientas setenta y cinco mil a setecientas cincuenta mil veces el importe del salario mínimo;\nc) La Exploración o Extracción de Hidrocarburos sin la Asignación o Contrato para la Exploración y Extracción vigente a que hace referencia esta Ley, con multa de entre cinco millones a siete millones quinientas mil veces el importe del salario mínimo; más un monto equivalente al valor de los Hidrocarburos que hayan sido extraídos conforme a la estimación que al efecto lleve a cabo la Comisión Nacional de Hidrocarburos, y d) Las demás violaciones al Título Segundo de esta Ley y a sus disposiciones reglamentarias, así como a la regulación, lineamientos y disposiciones administrativas competencia de la Secretaría de Energía, con multa de entre siete mil quinientas a doscientas veinticinco mil veces el importe del salario mínimo;\nII. La Comisión Nacional de Hidrocarburos sancionará:\na) No entregar en tiempo y forma la información que se obtenga como resultado de los trabajos de Reconocimiento y Exploración Superficial, así como de la Exploración y Extracción de Hidrocarburos, conforme a la regulación correspondiente, con multa de entre siete mil quinientas a doscientas veinticinco mil veces el importe del salario mínimo;\nb) El incumplimiento de los términos y condiciones que se establezcan en las autorizaciones para las actividades de Reconocimiento y Exploración Superficial que haya expedido, con multa de entre siete mil quinientas a setenta y cinco mil veces el importe del salario mínimo;\nc) El inicio de los trabajos de Reconocimiento y Exploración Superficial sin la autorización correspondiente, con multa de entre ciento cincuenta mil a cuatrocientas cincuenta mil veces el importe del salario mínimo;\nd) El inicio de los trabajos de Reconocimiento y Exploración Superficial por parte de Asignatarios y Contratistas, sin dar el aviso a que se refiere el párrafo tercero del artículo 37 de esta Ley, con multa de entre quince mil y setenta y cinco mil veces el importe del salario mínimo;\ne) La realización de perforaciones sin la autorización correspondiente en los términos de la regulación que al efecto emita la misma Comisión, con multa de entre ciento cincuenta mil a trescientas setenta y cinco mil veces el importe del salario mínimo;\nf) El inicio de la ejecución del plan de Exploración o del plan de desarrollo para la Extracción sin la aprobación correspondiente, con multa de entre setecientas cincuenta mil a tres millones de veces el importe del salario mínimo;\ng) Incumplir el plan de Exploración o el plan de desarrollo para la Extracción, con multa de entre ciento cincuenta mil a tres millones de veces el importe del salario mínimo;\nh) El incumplimiento a lo dispuesto en los artículos 101, fracciones I, II, VIII y IX; 112 y 113 de esta Ley, con multa de doscientas cincuenta a mil setecientas veces el importe del salario mínimo;\ni) El incumplimiento a lo dispuesto por los artículos 101 último párrafo, y 105, primer párrafo, de esta Ley, con multa de ochocientas cincuenta a quince mil veces el importe del salario mínimo;\nj) Realizar actividades de desarrollo y producción de Hidrocarburos sin el sistema de medición aprobado por la Comisión, con multa de entre tres millones a seis millones de veces el importe del salario mínimo;\nk) La cesión, enajenación, traspaso o gravamen total o parcial de los derechos u obligaciones derivados de un Contrato para la Exploración y Extracción, sin la aprobación correspondiente, con multa de entre setecientas cincuenta mil a seis millones de veces el importe del salario mínimo;\nl) Llevar a cabo cualquier acto que impida la Exploración, desarrollo y producción de Hidrocarburos, las actividades relacionadas con la ejecución de los trabajos geológicos, geofísicos u otros violando lo establecido en esta Ley y la regulación que emita la Comisión, con multa de entre setenta y cinco mil a doscientas veinticinco mil veces el importe del salario mínimo;\nm) Publicar, entregar o allegarse de información propiedad de la Nación a la que se refiere el artículo 32 de esta Ley, por medios distintos a los contemplados en la misma o sin contar con el consentimiento previo de la Comisión Nacional de Hidrocarburos con multa de entre setenta y cinco mil a doscientas veinticinco mil veces el importe del salario mínimo;\nn) Incumplir los requerimientos y los lineamientos que emita la Comisión Nacional de Hidrocarburos con la finalidad de integrar el Centro Nacional de Información de Hidrocarburos, con la información de la Nación existente a la fecha de entrada en vigor de esta Ley, con una multa de entre trescientos mil a un millón quinientas mil veces el importe del salario mínimo, y o) Las demás violaciones al Título Segundo de esta Ley y a sus disposiciones reglamentarias, así como a la regulación, lineamientos y disposiciones administrativas competencia de la Comisión Nacional de Hidrocarburos, serán sancionadas con multa de entre quince mil a cuatrocientas cincuenta mil veces el importe del salario mínimo;\nIII. Las Secretarías de Energía, de Hacienda y Crédito Público y de Economía, o la Comisión\nNacional de Hidrocarburos sancionarán, en el ámbito de sus competencias:\na) La restricción de acceso a instalaciones y equipos relacionados con actividades de la industria de Hidrocarburos, a los inspectores y verificadores, con multa de entre setenta y cinco mil a doscientas veinticinco mil veces el importe del salario mínimo;\nb) El incumplimiento o entorpecimiento de la obligación de informar o reportar, conforme a las disposiciones jurídicas aplicables, cualquier situación relacionada con esta Ley o sus disposiciones reglamentarias, con multa de entre siete mil quinientas a ciento cincuenta mil veces el importe del salario mínimo.\nreportar a las autoridades que correspondan, conforme a lo establecido en el Reglamento de esta Ley y demás disposiciones aplicables, y c) Proporcionar información falsa, alterada o simular registros de contabilidad, conforme a las disposiciones jurídicas aplicables, con multa de entre tres millones setecientas cincuenta mil a siete millones quinientas mil veces el importe del salario mínimo;\nIV. La Secretaría de Energía y la Comisión Nacional de Hidrocarburos sancionarán, en el ámbito de sus competencias, las violaciones graves o reiteradas a lo establecido en el Título\nSegundo de esta Ley, con amonestación, suspensión, remoción o inhabilitación del personal que preste sus servicios a un Asignatario, Contratista o Autorizado. Lo anterior, sin perjuicio de la sanción económica a la que se refieren las fracciones anteriores.\nArtículo 86.- Las infracciones al Título Tercero de esta Ley y a sus disposiciones reglamentarias serán sancionadas tomando en cuenta la gravedad de la falta, de acuerdo con lo siguiente:\nI. La Secretaría de Energía sancionará:\na) El incumplimiento de los términos y condiciones que se establezcan en los permisos que haya otorgado, con multa de entre setenta y cinco mil a trescientas mil veces el importe del salario mínimo;\nb) La suspensión de los servicios amparados por un permiso que haya otorgado sin la autorización correspondiente, salvo por causa de caso fortuito o fuerza mayor, con multa de entre quince mil a trescientas mil veces el importe del salario mínimo;\nc) La cesión, enajenación, traspaso o gravamen total o parcial, de los derechos u obligaciones derivados de un permiso que haya otorgado, sin la autorización correspondiente, con multa de entre ciento cincuenta mil a trescientas mil veces el importe del salario mínimo;\nd) La realización de actividades en el ámbito de su regulación sin permiso vigente, con multa de entre ciento cincuenta mil a trescientas mil veces el importe del salario mínimo, y e) Las demás violaciones al Título Tercero de esta Ley y a sus disposiciones reglamentarias, así como a la regulación, lineamientos y disposiciones administrativas competencia de la Secretaría de Energía, serán sancionadas con multa de entre siete mil quinientas a doscientas veinticinco mil veces el importe del salario mínimo;\nII. La Comisión Reguladora de Energía sancionará:\na) El incumplimiento de las disposiciones aplicables a la cantidad, calidad y medición de Hidrocarburos y Petrolíferos, con multa de entre quince mil a ciento cincuenta mil veces el importe del salario mínimo;\nb) La realización de actividades de Transporte, Almacenamiento, Distribución o Expendio al Público de Hidrocarburos, Petrolíferos o Petroquímicos, cuya adquisición lícita no se compruebe al momento de una verificación, con multas de entre siete mil quinientos a ciento cincuenta mil veces el importe del salario mínimo;\nc) El incumplimiento de los términos y condiciones que se establezcan en los permisos que haya otorgado, con multa de entre quince mil a ciento cincuenta mil veces el importe del salario mínimo;\nd) El incumplimiento de la obligación de acceso abierto, con multa de entre ciento cincuenta mil a cuatrocientas cincuenta mil veces el importe del salario mínimo;\ne) La suspensión sin la autorización correspondiente de los servicios amparados por un permiso que haya otorgado, salvo por causa de caso fortuito o fuerza mayor, con multa de entre quince mil a trescientas mil veces el importe del salario mínimo;\nf) El incumplimiento de la regulación que establezca sobre precios o tarifas máximas, con multa de entre quince mil a trescientas mil veces el importe del salario mínimo;\ng) La cesión, enajenación, traspaso o gravamen total o parcial, de los derechos u obligaciones derivados de un permiso que haya otorgado, sin la autorización correspondiente, con multa de entre ciento cincuenta mil a cuatrocientos cincuenta mil veces el importe del salario mínimo;\nh) La modificación de las condiciones técnicas de sistemas, ductos, instalaciones o equipos sin la autorización correspondiente, con multa de entre ciento cincuenta mil a trescientas mil veces el importe del salario mínimo;\ni) La realización de actividades en el ámbito de su regulación sin permiso vigente o autorización, con multa de entre ciento cincuenta mil a cuatrocientas cincuenta mil veces el importe del salario mínimo, y j) Las demás violaciones al Título Tercero de esta Ley y a sus disposiciones reglamentarias, así como a la regulación, lineamientos y disposiciones administrativas competencia de la Comisión Reguladora de Energía, serán sancionadas con multa de entre quince mil a cuatrocientas cincuenta mil veces el importe del salario mínimo;\nTratándose de las infracciones previstas en los incisos a) y h) de esta fracción, en caso de reincidencia, además de las sanciones señaladas en la presente Ley, se revocará el permiso respectivo;\nPárrafo adicionado DOF 04-05-2021\nIII. Las Secretarías de Energía y de Economía o la Comisión Reguladora de Energía sancionarán, en el ámbito de sus competencias:\na) La restricción de acceso a instalaciones y equipos relacionadas con actividades de la industria de Hidrocarburos, a los inspectores y verificadores, con multa de entre setenta y cinco mil a doscientas veinticinco mil veces el importe del salario mínimo;\nb) La falta de presentación de la información que se requiera a Permisionarios, con multa de mínimo, y c) El incumplimiento o entorpecimiento de la obligación de informar o reportar, conforme a las disposiciones jurídicas aplicables, cualquier situación relacionada con esta Ley o sus disposiciones reglamentarias, con multa de entre siete mil quinientas a ciento cincuenta mil veces el importe del salario mínimo;\nIV. La Secretaría de Energía y la Comisión Reguladora de Energía sancionarán, en el ámbito de sus competencias, las violaciones graves o reiteradas a lo establecido en el Título Tercero de esta Ley, con amonestación, suspensión, remoción o inhabilitación del personal que preste sus servicios a un Permisionario. Lo anterior, sin perjuicio de la sanción económica a la que se refieren las fracciones anteriores.\nArtículo 87.- Para la aplicación de las sanciones previstas en esta Ley, la autoridad administrativa deberá fundar y motivar su resolución considerando:\nI. Los daños que se hubieren producido o puedan producirse;\nII. El carácter intencional o no de la acción u omisión constitutiva de la infracción;\nIII. La gravedad de la infracción, y\nIV. La reincidencia del infractor.\nPara la aplicación de las sanciones se estará a lo dispuesto en la Ley Federal de Procedimiento\nAdministrativo. Para efectos del presente Capítulo, se entiende por salario mínimo, el salario mínimo general diario vigente en el Distrito Federal al momento de cometerse la infracción.\nLas sanciones señaladas en esta Ley se aplicarán sin perjuicio de la responsabilidad civil, penal o administrativa que resulte de la aplicación de sanciones por otros ordenamientos y, en su caso, de la revocación de la Asignación, permiso o autorización, o de la terminación del Contrato para la Exploración y Extracción.\nEn caso de reincidencia, se impondrá una multa por el doble de la anteriormente impuesta. Se considerará reincidente al que, habiendo incurrido en una infracción que haya sido sancionada, cometa otra del mismo tipo o naturaleza, dentro de un plazo de diez años, contados a partir de la imposición de la sanción.\nCapítulo II\nDe la Transparencia y el Combate a la Corrupción\nArtículo 88.- Corresponderá a la Secretaría de Energía poner a disposición del público, de forma mensual, al menos la siguiente información:\nI. El número de Asignaciones y permisos que se encuentran vigentes, así como sus términos y condiciones, y\nII. La información sobre las áreas a concursar en Contratos para la Exploración y Extracción, incluyendo su programa quinquenal.\nArtículo 89.- Corresponderá a la Comisión Nacional de Hidrocarburos poner a disposición del público, de forma mensual, al menos la siguiente información:\nI. Los resultados y estadísticas de los procesos de licitación de Contratos para la Exploración y Extracción;\nII. Las bases y reglas de los procesos de licitación que se hayan empleado para adjudicar los Contratos para la Exploración y Extracción;\nIII. El número de los Contratos para la Exploración y Extracción que se encuentran vigentes, así como sus términos y condiciones;\nIV. El número de autorizaciones que haya otorgado y se encuentran vigentes, así como sus términos y condiciones;\nV. La información relacionada con la administración técnica y supervisión de los Contratos para la Exploración y Extracción, y\nVI. El volumen de producción de Hidrocarburos por Contrato para la Exploración y Extracción.\nArtículo 90.- Corresponderá a la Comisión Reguladora de Energía poner a disposición del público, de forma mensual, al menos la siguiente información:\nI. El número de permisos que haya otorgado y se encuentren vigentes, así como sus términos y condiciones;\nII. El volumen de Gas Natural transportado y almacenado en los sistemas permisionados, incluido el Sistema de Transporte y Almacenamiento Nacional Integrado de Gas Natural;\nIII. La capacidad utilizada y disponible en las instalaciones y ductos de los Permisionarios;\nIV. Las estadísticas relacionadas con el Transporte, el Almacenamiento, la Distribución y el Expendio al Público de Gas Natural, Petrolíferos y Petroquímicos, a nivel nacional, y\nV. Los resultados y estadísticas de las actividades de los gestores de Sistemas Integrados.\nArtículo 91.- La información a que se refiere el presente Título deberá publicarse de tal forma que facilite su uso y comprensión, aprovechando los medios electrónicos y tecnologías de la información.\nLos Asignatarios, Contratistas, Permisionarios y Autorizados estarán obligados a entregar oportunamente la información que se requiera para la publicación a que se refiere este Capítulo, a través de los medios y en los términos que establezcan las autoridades correspondientes.\nArtículo 92.- Los servidores públicos de la Secretaría de Energía y la Agencia sujetarán sus actividades a un código de conducta que para tal efecto emitan, que será público y en el que se establecerá como mínimo:\nI. Las reglas para llevar a cabo audiencias con sujetos regulados;\nII. Las reglas para participar en eventos académicos o de difusión, así como en foros y eventos públicos, y\nIII. La prohibición de aceptar:\na) Obsequios, de conformidad con las disposiciones jurídicas aplicables, y b) El pago de viáticos y pasajes, servicios, financiamiento o aportaciones económicas o en especie, así como otras consideraciones de valor.\nArtículo 93.- Todos los procedimientos de contratación, sus actos previos y aquéllos que deriven de la celebración, ejecución y cumplimiento de las Asignaciones, los Contratos para la Exploración y Extracción, los Permisos y las autorizaciones, que se lleven a cabo al amparo de esta Ley, se sujetarán a las disposiciones aplicables en materia de combate a la corrupción.\nLa actuación de los servidores públicos en el ejercicio de sus atribuciones y facultades, derivada de los procedimientos de contratación, sus actos previos y aquéllos relacionados con la suscripción y administración de los Contratos para la Exploración y Extracción, así como de la administración y supervisión de las Asignaciones, Permisos, autorizaciones o cualquier otro acto o procedimiento relacionado con las actividades que se lleven a cabo al amparo de esta Ley, se sujetará a los principios constitucionales de legalidad, honradez, lealtad, imparcialidad y eficiencia.\nSin perjuicio de las disposiciones específicas en materia de combate a la corrupción, las personas físicas y morales, nacionales o extranjeras que participen en las contrataciones o permisos regulados por esta Ley serán sancionadas cuando realicen alguno o algunos de los hechos siguientes:\nI. Ofrezcan o entreguen dinero o cualquier otro beneficio a un servidor público o a un tercero que de cualquier forma intervenga en alguno o algunos de los actos dentro del procedimiento de contratación, a cambio de que dicho servidor público realice o se abstenga de realizar un acto relacionado con sus funciones o con las de otro servidor público, con el propósito de obtener o mantener una ventaja, con independencia de la recepción de dinero o un beneficio obtenido;\nII. Realice cualquier conducta u omisión que tengan por objeto o efecto evadir los requisitos o reglas establecidos para obtener cualquier tipo de contratación o simule el cumplimiento de éstos;\nIII. Intervenga en nombre propio pero en interés de otra u otras personas que se encuentren impedidas para participar en contrataciones públicas, con la finalidad de obtener, total o parcialmente, los beneficios derivados de la contratación, o\nIV. Ostente influencia o poder político sobre cualquier servidor público, con el propósito de obtener para sí o para un tercero un beneficio o ventaja, con independencia de la aceptación del servidor o de los servidores públicos o del resultado obtenido.\nArtículo 94.- Las sanciones relativas a las conductas previstas en el artículo anterior, serán determinadas por las autoridades competentes, de conformidad con la normatividad en materia de combate a la corrupción y podrán ser causales de terminación de las Asignaciones, contratos, permisos o autorizaciones respectivas.\nCapítulo III\nDe la Jurisdicción, Utilidad Pública y Procedimientos\nArtículo 95.- La industria de Hidrocarburos es de exclusiva jurisdicción federal. En consecuencia, únicamente el Gobierno Federal puede dictar las disposiciones técnicas, reglamentarias y de regulación en la materia, incluyendo aquéllas relacionadas con el desarrollo sustentable, el equilibrio ecológico y la protección al medio ambiente en el desarrollo de esta industria.\nesta Ley, en todo momento deberán seguirse criterios que fomenten la protección, la restauración y la conservación de los ecosistemas, además de cumplir estrictamente con las leyes, reglamentos y demás normativa aplicable en materia de medio ambiente, recursos naturales, aguas, bosques, flora y fauna silvestre, terrestre y acuática, así como de pesca.\nArtículo 96.- La industria de Hidrocarburos a que se refiere esta Ley es de utilidad pública. Procederá la constitución de servidumbres legales, o la ocupación o afectación superficial necesarias, para la realización de las actividades de la industria de Hidrocarburos, conforme a las disposiciones aplicables en los casos en los que la Nación lo requiera.\nLas actividades de Exploración y Extracción se consideran de interés social y orden público, por lo que tendrán preferencia sobre cualquier otra que implique el aprovechamiento de la superficie o del subsuelo de los terrenos afectos a aquéllas.\nLa Federación, los gobiernos de los Estados y el Distrito Federal, de los municipios y de las delegaciones, contribuirán al desarrollo de proyectos de Exploración y Extracción, así como de Transporte y Distribución por ductos y de Almacenamiento, mediante procedimientos y bases de coordinación que agilicen y garanticen el otorgamiento de los permisos y autorizaciones en el ámbito de su competencia.\nArtículo 97.- En lo no previsto por esta Ley, se consideran mercantiles los actos de la industria de Hidrocarburos, por lo que se regirán por el Código de Comercio y, de modo supletorio, por las disposiciones del Código Civil Federal.\nArtículo 98.- Los Autorizados, Asignatarios, Contratistas y Permisionarios, así como concesionarios mineros, no podrán oponerse al tendido de ductos, cables o a la instalación de cualquier otra infraestructura en el área comprendida en la Asignación, Contrato para la Exploración y Extracción o permiso correspondiente, siempre que sea técnicamente factible.\nEn el derecho de vía destinado a las actividades de Transporte por ducto, se permitirá el acceso y actividad de prestadores de servicios de cualquier industria a cambio de una contraprestación justa, siempre que no se ponga en riesgo la seguridad y continuidad de la prestación de los servicios. La Comisión Reguladora de Energía, con la opinión que corresponda a la Agencia, emitirá las disposiciones necesarias para que dicho acceso sea permitido y vigilará el cumplimiento de esta obligación, así como la forma en que se afectarán las tarifas de las actividades permisionadas por los ingresos que perciban los Permisionarios por el uso de terceros de sus derechos de vía.\nNo obstante, las obras e infraestructura a que se refiere este artículo deberán ser seguras, necesarias, adecuadas y proporcionales a los requerimientos de la Nación de acuerdo con lo que establezca la Secretaría de Energía, previa opinión de la Comisión Nacional de Hidrocarburos o de la Comisión Reguladora de Energía, según corresponda.\nArtículo 99.- Las Asignaciones, Contratos para la Exploración y Extracción, y permisos a que se refiere esta Ley, no limitan el derecho del Estado a otorgar concesiones, licencias o permisos para la exploración, extracción y aprovechamiento de otros recursos naturales, distintos de los Hidrocarburos, dentro de las áreas comprendidas en dichos títulos. En caso de ocurrir, no se deberá generar un inconveniente irrazonable al Asignatario, Contratista o Permisionario.\nCapítulo IV\nDel Uso y Ocupación Superficial\nArtículo 100.- La contraprestación, los términos y las condiciones para el uso, goce o afectación de los terrenos, bienes o derechos necesarios para realizar las actividades de Exploración y Extracción de Hidrocarburos serán negociados y acordados entre los propietarios o titulares de dichos terrenos, bienes o derechos, incluyendo derechos reales, ejidales o comunales, y los Asignatarios o Contratistas.\nTratándose de propiedad privada, además podrá convenirse la adquisición.\nLo dispuesto en el presente Capítulo será aplicable respecto de los derechos que la Constitución, las leyes y los tratados internacionales suscritos por el Estado Mexicano, reconocen a las comunidades indígenas.\nArtículo 101.- La negociación y acuerdo a que se refiere el artículo anterior deberá realizarse de manera transparente y sujetarse a las siguientes bases y a lo señalado en el Reglamento:\nI. El Asignatario o Contratista deberá expresar por escrito al propietario o titular del terreno, bien o derecho de que se trate, su interés de usar, gozar, afectar o, en su caso, adquirir tales terrenos, bienes o derechos;\nII. El Asignatario o Contratista deberá mostrar y describir el proyecto que planea desarrollar al amparo de la Asignación o Contrato para la Exploración y Extracción y atender las dudas y cuestionamientos del propietario o titular del terreno, bien o derecho de que se trate, de manera que entienda sus alcances, así como las posibles consecuencias y afectaciones que se podrían generar por su ejecución y, en su caso, los beneficios que le representaría en lo personal y/o en su comunidad o localidad;\nIII. La Secretaría de Energía podrá prever la participación de testigos sociales en los procesos de negociación, en los términos que señale el Reglamento;\nIV. Los Asignatarios y Contratistas deberán notificar a las Secretarías de Energía y de Desarrollo\nAgrario, Territorial y Urbano del inicio de las negociaciones a que se refiere este artículo;\nV. La forma o modalidad de uso, goce, afectación, en su caso, adquisición que se pacte deberá ser idónea para el desarrollo del proyecto en cuestión, según sus características. Al efecto, podrán emplearse las figuras de arrendamiento, servidumbre voluntaria, ocupación superficial, ocupación temporal, compraventa, permuta y cualquier otra que no contravenga la ley;\nVI. La contraprestación que se acuerde deberá ser proporcional a los requerimientos del Asignatario o Contratista, conforme a las actividades que se realicen al amparo de la Asignación o Contrato.\nDe acuerdo a las distintas formas o modalidades de uso, goce, afectación o, en su caso, adquisición que se pacte, los titulares de los terrenos, bienes o derechos tendrán derecho a que la contraprestación cubra, según sea el caso:\na) El pago de las afectaciones de bienes o derechos distintos de la tierra, así como la previsión de los daños y perjuicios, que se podrían sufrir con motivo del proyecto a desarrollar, calculado en función de la actividad habitual de dicha propiedad;\nb) La renta por concepto de ocupación, servidumbre o uso de la tierra;\nc) Tratándose de proyectos que alcancen la extracción comercial de Hidrocarburos, un en cuestión, después de haber descontado los pagos que deban realizarse al Fondo\nMexicano del Petróleo para la Estabilización y el Desarrollo, sujetándose a lo dispuesto en el último párrafo de este artículo.\nni mayor al tres por ciento en el caso del Gas Natural No Asociado, y en los demás casos no podrá ser menor al cero punto cinco por ciento ni mayor al dos por ciento, en ambos trate.\nLa Secretaría de Energía, con la asistencia técnica de la Comisión Nacional de Hidrocarburos, elaborará las metodologías, parámetros y lineamientos que podrán servir de referencia para determinar el porcentaje a que se refiere el primer párrafo de este inciso c). Dichas metodologías, parámetros y lineamientos deberán considerar las mejores prácticas internacionales en la materia, con especial énfasis en promover la competitividad del sector.\nEn lo dispuesto en los incisos a) y b) anteriores, se deberá considerar el valor comercial;\nVII. Los pagos de las contraprestaciones que se pacten podrán cubrirse en efectivo y, en su caso, mediante cualquiera de las siguientes modalidades:\na) Compromisos para ejecutar proyectos de desarrollo en beneficio de la comunidad o localidad afectada;\nb) Cualquier otra prestación que no sea contraria a la ley, o c) Una combinación de las anteriores.\nSin perjuicio de las modalidades de contraprestación a que se refiere esta fracción, los Asignatarios o Contratistas podrán proponer al propietario, titular del derecho o miembros de la comunidad o localidad a las que pertenezcan, la adquisición de bienes o insumos, o los servicios fabricados, suministrados o prestados por dichas personas, cuando esto sea compatible con el proyecto;\nVIII. La contraprestación, así como los demás términos y condiciones que se pacten para la adquisición, uso, goce o afectación de los terrenos, bienes o derechos deberán constar invariablemente en un contrato por escrito, y sujetarse a los lineamientos y a los modelos de contratos que emita la Secretaría de Energía con la opinión de la Secretaría de Desarrollo\nAgrario, Territorial y Urbano.\nEl contrato deberá contener, al menos, los derechos y obligaciones de las partes, así como posibles mecanismos de solución de controversias;\nIX. Los contratos en los que consten los acuerdos alcanzados no podrán prever cláusulas de confidencialidad sobre los términos, montos y condiciones de la contraprestación, que penalicen a las partes por su divulgación.\nLos Hidrocarburos en el Subsuelo son propiedad de la Nación, por lo que en ningún caso se podrá pactar una contraprestación asociada a una parte de la producción de Hidrocarburos del proyecto.\nArtículo 102.- Cuando estén involucrados terrenos, bienes o derechos sujetos a los regímenes previstos en la Ley Agraria, además de las disposiciones de dicha Ley y las demás contenidas en el presente Capítulo, se observará lo siguiente:\nI. El ejido, los ejidatarios, comunidades o comuneros podrán solicitar la asesoría y, en su caso,\nCapítulo;\nII. La autorización para el uso, goce o afectación y demás actos de disposición permitidos, deberá sujetarse invariablemente y sin perjuicio de las demás disposiciones aplicables, a las formalidades previstas en los artículos 24 a 28, 30 y 31 de la Ley Agraria para los actos señalados en las fracciones VII a XIV del artículo 23 de dicho ordenamiento;\nIII. Tratándose de ejidatarios o comuneros que, conforme a las disposiciones aplicables, tengan reconocidos derechos de manera individual, se les deberá entregar directamente la contraprestación respectiva por el uso, goce o afectación de tales derechos, salvo en el caso de la contraprestación señalada en el inciso c) de la fracción VI del artículo 101 anterior, en cuyo caso se estará a lo dispuesto en la fracción IV de este artículo. En caso contrario, se entregarán a través del Fideicomiso del Fondo Nacional de Fomento Ejidal, o cualquier otro fideicomiso si así lo acuerdan las partes, y\nIV. La contraprestación referida en el inciso c) de la fracción VI del artículo 101 anterior, será entregada al ejido o comunidad, a través de los órganos facultados para ello, para que sea distribuida entre todos sus integrantes en los términos que determine la asamblea o, en su caso, pueda destinarse a los proyectos a que se refiere el inciso a) de la fracción VII del artículo 101 de esta Ley.\nArtículo 103.- El Instituto elaborará y mantendrá actualizados tabuladores sobre los valores promedio de la tierra y, en su caso, de sus accesorios, para uso, ocupación o adquisición, según sus características, así como demás tabuladores y mecanismos de referencia que determine. Dichos tabuladores servirán de base para el inicio de las negociaciones que se realicen conforme a los artículos anteriores.\nEl Asignatario o Contratista deberá acompañar al escrito a que se refiere la fracción I del artículo 101, los tabuladores señalados en el párrafo anterior, según corresponda a su propuesta.\nArtículo 104.- Las partes podrán acordar la práctica de avalúos por el Instituto, instituciones de crédito del país que se encuentren autorizadas, corredores públicos o profesionistas con postgrado en valuación, siempre que formen parte del padrón que se establezca en los términos del Reglamento de esta Ley.\nLos avalúos citados considerarán, entre otros factores:\nI. La previsión de que el proyecto a desarrollar generará, dentro de su zona de influencia, una plusvalía de los terrenos, bienes o derechos de que se trate;\nII. La existencia de características en los inmuebles, bienes o derechos que, sin reflejarse en su valor comercial, los hace técnicamente idóneos para el desarrollo del proyecto de que se trate;\nIII. La afectación en la porción remanente de los inmuebles del cual forme parte la fracción por adquirir, usar o gozar;\nIV. Los gastos complementarios no previstos en el valor comercial, para que los afectados sustituyan los terrenos, bienes o derechos por adquirir, cuando sea necesaria la emigración de los afectados, y\nV. En los casos de otorgamiento del uso o goce de los terrenos, bienes o derechos, la previsión de los daños y perjuicios, las molestias o afectaciones que sus titulares podrían sufrir con motivo del proyecto a desarrollar, incluyendo aquéllos correspondientes a bienes o derechos distintos de la tierra, o el eventual perjuicio por el tiempo que la propiedad será afectada, calculado en función de la actividad habitual de dicha propiedad.\nPara el caso de adquisiciones, en ningún caso el valor será inferior al comercial.\nresulten convenientes.\nArtículo 105.- El acuerdo alcanzado en cualquier tiempo entre las partes deberá presentarse por el Asignatario o Contratista ante el Juez de Distrito en materia civil o Tribunal Unitario Agrario competente, con el fin de que sea validado, dándole el carácter de cosa juzgada.\nPara lo anterior, el Juez o Tribunal Unitario Agrario procederá a:\nI. Verificar si se cumplieron las formalidades exigidas tanto en la presente Ley como, en su caso, en la Ley Agraria y demás disposiciones aplicables, y\nII. Ordenar la publicación de un extracto del acuerdo alcanzado, a costa del Asignatario o Contratista, en un periódico de circulación local y, en su caso, en los lugares más visibles del ejido respectivo.\nEl Juez de Distrito o Tribunal Unitario Agrario emitirá su resolución, que tendrá el carácter de sentencia, dentro de los quince días siguientes a la primera publicación a que se refiere la fracción II anterior, siempre que no tenga conocimiento de la existencia de un juicio pendiente que involucre los terrenos, bienes o derechos en cuestión.\nEn contra de la resolución emitida sólo procederá el juicio de amparo.\nArtículo 106.- En caso de no existir un acuerdo entre las partes, transcurridos ciento ochenta días naturales contados a partir de la fecha de recepción del escrito referido en la fracción I del artículo 101 de esta Ley, el Asignatario o Contratista podrá:\nI. Promover ante el Juez de Distrito en materia civil o Tribunal Unitario Agrario competente la constitución de la servidumbre legal de hidrocarburos a que se refiere el artículo 109 de esta\nLey, o\nII. Solicitar a la Secretaría de Desarrollo Agrario, Territorial y Urbano una mediación que versará sobre las formas o modalidades de adquisición, uso, goce o afectación de los terrenos, bienes o derechos, así como la contraprestación que corresponda.\nArtículo 107.- La mediación a que se refiere el artículo anterior se desarrollará, al menos, conforme a las siguientes bases:\nI. La Secretaría de Desarrollo Agrario, Territorial y Urbano escuchará a las partes y sugerirá la forma o modalidad de adquisición, uso, goce o afectación que concilie sus intereses y pretensiones, según las características del proyecto y buscará que las partes alcancen una solución aceptable y voluntaria, procurando mejorar su comunicación y futura relación;\nII. A fin de sugerir el monto de la contraprestación, se estará a lo siguiente:\na) Si previo a la mediación, las partes hubieran practicado avalúos encargados por cada una de ellas, conforme al artículo 104 de esta Ley:\n1. Dichos avalúos deberán ser tomados en cuenta siempre que coincidan con la forma o modalidad de adquisición, uso, goce o afectación que sugiera la Secretaría de Desarrollo Agrario, Territorial y Urbano. De lo contrario, se procederá conforme al inciso b) siguiente;\n2. En caso de que la diferencia entre los avalúos de los dos peritos sea inferior a 15%, la Secretaría de Desarrollo Agrario, Territorial y Urbano tomará el promedio simple de los avalúos y el resultado servirá de base para formular la propuesta de contraprestación de la referida Secretaría, y\n3. En caso de que la diferencia entre los avalúos de los dos peritos sea superior a 15%, la Secretaría de Desarrollo Agrario, Territorial y Urbano solicitará al Instituto o a un perito que aleatoriamente seleccione del padrón a que se refiere el artículo 104 de esta Ley, la práctica de un avalúo, cuyo resultado servirá de base para formular la propuesta de contraprestación de la referida Secretaría, y b) En caso de que las partes no hayan practicado avalúos en términos del artículo 104 de esta Ley, la Secretaría de Desarrollo Agrario, Territorial y Urbano solicitará al Instituto o a un perito que aleatoriamente seleccione del padrón a que se refiere el artículo 104 de esta Ley, la práctica de un avalúo que servirá de base para la propuesta de contraprestación que formule la Secretaría de Desarrollo Agrario, Territorial y Urbano.\nEn el desarrollo de la mediación se atenderá a lo dispuesto en el artículo 101, fracciones V a VII, de la presente Ley.\nArtículo 108.- Si dentro de los treinta días naturales contados a partir de la sugerencia de contraprestación a que se refiere la fracción II del artículo anterior, las partes no alcanzaren un acuerdo, la Secretaría de Energía podrá solicitar a la Secretaría de Desarrollo Agrario, Territorial y Urbano que dé trámite ante el Ejecutivo Federal para la constitución de una servidumbre legal de hidrocarburos por vía administrativa.\nArtículo 109.- La servidumbre legal de hidrocarburos comprenderá el derecho de tránsito de personas; el de transporte, conducción y almacenamiento de materiales para la construcción, vehículos, maquinaria y bienes de todo tipo; el de construcción, instalación o mantenimiento de la infraestructura o realización de obras y trabajos necesarios para el adecuado desarrollo y vigilancia de las actividades amparadas por virtud de un Contrato o Asignación, así como todos aquéllos que sean necesarios para tal fin. En todo caso, la servidumbre legal de hidrocarburos no podrá exceder el plazo del Contrato o Asignación respectivo.\nLas servidumbres legales de hidrocarburos se decretarán a favor del Asignatario o Contratista y se regirán por las disposiciones del derecho común federal y las controversias relacionadas con las mismas, cualquiera que sea su naturaleza, serán competencia de los tribunales federales.\nLas servidumbres legales de hidrocarburos se podrán decretar por vía jurisdiccional o administrativa, en términos de esta Ley y las demás disposiciones aplicables.\n104 de la presente Ley y, en lo conducente, lo señalado en las fracciones V a VII del artículo 101 de esta\nLey.\nArtículo 110.- La contraprestación que corresponda por la servidumbre legal de hidrocarburos que se decrete por vía administrativa, se determinará con base en las propuestas que se hayan formulado conforme a la fracción II del artículo 107 de la presente Ley.\nTratándose de las demás modalidades de adquisición o afectación por figuras de derecho público, la indemnización respectiva se determinará considerando lo dispuesto en el artículo 104 y, en su caso, los valores de los avalúos que se obtengan conforme a la fracción II del artículo 107 de esta Ley.\nArtículo 111.- Lo dispuesto en los artículos anteriores no será impedimento para que las partes continúen sus negociaciones y alcancen un acuerdo en cualquier momento, debiendo cumplir con lo dispuesto en el artículo 105 de esta Ley.\nArtículo 112.- El Asignatario o Contratista deberá entregar a la Comisión Nacional de Hidrocarburos una copia de los documentos en los que consten los acuerdos alcanzados mediante negociación o las medidas decretadas por el Ejecutivo Federal o los tribunales competentes, conforme a este Capítulo.\nLas dependencias mencionadas en el presente Capítulo podrán celebrar los convenios de colaboración y coordinación que requieran para el cumplimiento de sus atribuciones.\nArtículo 113.- Los avalúos que se practiquen en términos de este Capítulo, así como los honorarios que, en su caso, se causen por la participación de testigos sociales, serán cubiertos por los Asignatarios y Contratistas, conforme a lo que señale el Reglamento.\nArtículo 114.- Los Asignatarios y Contratistas se abstendrán de realizar, directa o indirectamente, conductas o prácticas abusivas, discriminatorias o que busquen influir indebidamente en la decisión de los propietarios o titulares de los terrenos, bienes o derechos, durante las negociaciones y los procedimientos a que se refiere el presente Capítulo.\nEn los casos en que se acredite que el Asignatario o Contratista incurra en las conductas señaladas en este artículo en más de una ocasión, la Asignación y, en su caso, permisos o autorizaciones podrán ser revocados o el Contrato para la Exploración y Extracción rescindido.\nArtículo 115.- Sin perjuicio de las demás disposiciones y de las sanciones previstas en esta Ley y en otras aplicables, así como de las acciones legales que procedan:\nI. El acuerdo alcanzado entre las partes será nulo cuando:\na) Se acredite la contravención a lo dispuesto en el primer párrafo del artículo 114, o b) Se pacte una contraprestación en contravención a lo señalado en el último párrafo del artículo 101 de esta Ley, y\nII. Será causal de rescisión del contrato a que se refiere este Capítulo o, en su caso, procederá la declaración de insubsistencia de la servidumbre legal de hidrocarburos cuando:\na) Las obras o trabajos por desarrollar no se inicien dentro de los plazos establecidos en el Contrato para la Exploración y Extracción o Asignación o en las autorizaciones de las autoridades;\nb) El terreno objeto de las mismas sea destinado a un uso distinto de aquel que justificó la afectación;\nc) Se declare nula o cancele la Asignación o Contrato para la Exploración y Extracción con base en el cual se ejerció el derecho para obtenerle, y d) Se actualice algún supuesto que se establezca en las disposiciones aplicables o en las cláusulas del contrato.\nArtículo 116.- La regulación que emita la Agencia deberá prever, al menos, los mecanismos de sus instalaciones y abandono de los terrenos que hayan ocupado, usado, gozado o afectado por virtud de sus actividades, se realice atendiendo a los compromisos pactados con los propietarios de los terrenos, bienes o derechos y a las mejores prácticas, restableciéndolos en el pleno goce de sus derechos.\nLa regulación señalada en el párrafo anterior también deberá prever, al menos, mecanismos financieros para que Asignatarios y Contratistas cubran los daños y perjuicios no previstos en la contraprestación que se acuerde conforme a este Capítulo, que sus actividades y operaciones puedan ocasionar a los propietarios o titulares de terrenos, bienes y derechos.\nArtículo 117.- Lo dispuesto en el presente Capítulo será aplicable a la adquisición, uso, goce o afectación de los terrenos, bienes o derechos necesarios para realizar las actividades de Transporte por medio de ductos y Reconocimiento y Exploración Superficial.\nLa autoridad responsable de emitir el permiso o autorización deberá recibir por parte del Permisionario o Autorizado una copia de los documentos en los que consten los acuerdos alcanzados mediante negociación o las medidas decretadas por el Ejecutivo Federal o los tribunales competentes, conforme a este Capítulo y podrá imponer las sanciones que establece la fracción II, incisos h) e i), del artículo 85 de la presente Ley.\nCapítulo V\nDel Impacto Social\nArtículo 118.- Los proyectos de infraestructura de los sectores público y privado en la industria de Hidrocarburos atenderán los principios de sostenibilidad y respeto de los derechos humanos de las comunidades y pueblos de las regiones en los que se pretendan desarrollar.\nArtículo 119.- Previo al otorgamiento de una Asignación, o de la publicación de una convocatoria para la licitación de un Contrato para la Exploración y Extracción, la Secretaría de Energía, en coordinación con la Secretaría de Gobernación y demás dependencias y entidades competentes, realizará un estudio de impacto social respecto del área objeto de la Asignación o el Contrato.\nLos resultados del estudio se pondrán a disposición del Asignatario y de los participantes en los procesos de licitación de los Contratos para la Exploración y Extracción, sujeto a las disposiciones en materia de transparencia, acceso a la información pública y protección de datos personales.\nLa Secretaría de Energía deberá informar a los Asignatarios o Contratistas sobre la presencia de grupos sociales en situación de vulnerabilidad en las áreas en que se llevarán a cabo las actividades al amparo de Asignaciones y Contratos, con el fin de que se implementen las acciones necesarias para salvaguardar sus derechos.\nArtículo 120.- Con la finalidad de tomar en cuenta los intereses y derechos de las comunidades y pueblos indígenas en los que se desarrollen proyectos de la industria de Hidrocarburos, la Secretaría de Energía deberá llevar a cabo los procedimientos de consulta previa, libre e informada necesarios y cualquier otra actividad necesaria para su salvaguarda, en coordinación con la Secretaría de Gobernación y las dependencias que correspondan.\nAgencia, las empresas productivas del Estado y sus subsidiarios y empresas filiales, así como\nParticulares, conforme a la normatividad aplicable.\nLos procedimientos de consulta tendrán como objeto alcanzar acuerdos o, en su caso, el consentimiento conforme a la normatividad aplicable.\nLa Secretaría de Energía, previa opinión de la Secretaría de Hacienda y Crédito Público, podrá prever en las Asignaciones, así como dentro de los términos y condiciones que establezca para las licitaciones, los montos o las reglas para la determinación de los mismos, que el Contratista o Asignatario deberá destinar para el desarrollo humano y sustentable de las comunidades o localidades en las que realicen sus actividades, en materia de salud, educación, laboral, entre otras, sin menoscabo de las obligaciones del Estado.\nArtículo 121.- Los interesados en obtener un permiso o una autorización para desarrollar proyectos en materia de Hidrocarburos, así como los Asignatarios y Contratistas, deberán presentar a la Secretaría de Energía una evaluación de impacto social que deberá contener la identificación, caracterización, predicción y valoración de los impactos sociales que podrían derivarse de sus actividades, así como las medidas de mitigación y los planes de gestión social correspondientes, en los términos que señale el Reglamento de esta Ley.\nLa Secretaría de Energía emitirá la resolución y las recomendaciones que correspondan, en el plazo y los términos que señale el Reglamento de esta Ley.\nLa resolución señalada en el párrafo anterior deberá ser presentada por los Asignatarios, Contratistas,\nPermisionarios o Autorizados para efectos de la autorización de impacto ambiental.\nCapítulo VI\nDe la Cobertura Social y el Desarrollo de la Industria Nacional\nArtículo 122.- El Ejecutivo Federal, a través de la Secretaría de Energía, será responsable de fomentar y vigilar un adecuado suministro de energéticos en el territorio nacional, para lo cual podrá instruir, previa opinión favorable de la Secretaría de Hacienda y Crédito Público, a Petróleos Mexicanos, a las demás empresas productivas del Estado y al Centro Nacional de Control del Gas Natural llevar a cabo aquellos proyectos que considere necesarios para la generación de beneficios sociales y como mecanismos de promoción de desarrollo económico, en términos de esta Ley y de la política pública en materia energética del país. En el caso de proyectos que requieran permiso de la Comisión Reguladora de Energía, la Secretaría de Energía solicitará la opinión de dicha Comisión.\nLos proyectos podrán abarcar:\nI. El Tratamiento y refinación de Petróleo y el Procesamiento de Gas Natural;\nII. El Transporte y el Almacenamiento de Hidrocarburos o Petrolíferos;\nIII. El Transporte por ducto y el Almacenamiento, que se encuentre vinculados a ductos, de Petroquímicos;\nIV. La Distribución de Gas Natural o Petrolíferos, y\nV. El Expendio al Público de Gas Natural o Petrolíferos.\nmecanismos de inversión que correspondan y, en su caso, la contraprestación conducente relativa a los mecanismos de inversión a precios de mercado. Lo anterior, con independencia de la regulación tarifaria que, en su caso, establezca la Comisión Reguladora de Energía para la prestación de servicios permisionados.\nLos proyectos que instruya la Secretaría de Energía a Petróleos Mexicanos, a las demás empresas productivas del Estado o al Centro Nacional de Control del Gas Natural, conforme a lo establecido en el presente artículo, serán financiados con base en lo que para tal efecto determine la Cámara de Diputados dentro del Presupuesto de Egresos de la Federación.\nTratándose de proyectos de infraestructura de Transporte por ductos y de Almacenamiento de Gas\nNatural, a que se refiere el presente artículo la participación se realizará a través del Centro Nacional de Control del Gas Natural.\nLa Comisión Reguladora de Energía tomará en cuenta, en la regulación tarifaria respectiva, los recursos que se destinen a dicho financiamiento para el desarrollo de los proyectos permisionados cuando aquellos provengan de recursos públicos.\nSin perjuicio de lo anterior, la Secretaría de Energía podrá instruir la aplicación de mecanismos de asociación público privada para la realización de proyectos a los que se refiere este artículo.\nArtículo 123.- Cuando el Centro Nacional de Control del Gas Natural cuente con la indicación prevista en el artículo anterior, las empresas productivas del Estado podrán participar en los proyectos de infraestructura para el Transporte por ducto y el Almacenamiento de Gas Natural vinculado a ductos, que estén sujetos a reglas de acceso abierto, a través de contratos de reserva de capacidad vinculados a dicha infraestructura.\nPara el desarrollo de los proyectos a que se refiere este artículo, la Comisión Reguladora de Energía deberá emitir opinión favorable respecto de las bases de licitación o concurso, así como del impacto económico del proyecto, que realice el Centro Nacional de Control del Gas Natural, a fin de cuidar que no se establezcan condiciones que incrementen los costos de las tarifas en perjuicio de los usuarios.\nArtículo 124.- Las Secretarías de Hacienda y Crédito Público, de Energía y de Desarrollo Social evaluarán la conveniencia y, en su caso, instrumentarán programas de apoyos focalizados que tengan como objeto coadyuvar con el suministro adecuado y oportuno, a precios asequibles, de combustibles de consumo básico en zonas rurales y zonas urbanas marginadas.\nLa Comisión Reguladora de Energía y el Consejo Nacional de Evaluación de la Política de Desarrollo\nSocial deberán prestar el apoyo técnico que se requiera para los fines previstos en el presente artículo.\nArtículo 125.- La Secretaría de Economía, con la opinión de la Secretaría de Energía, definirá las estrategias para el fomento industrial de Cadenas Productivas locales y para el fomento de la inversión directa en la industria de Hidrocarburos, con especial atención a las pequeñas y medianas empresas, conforme a lo siguiente:\nI. La estrategia para el fomento industrial de Cadenas Productivas locales deberá:\na) Identificar los sectores industriales y las regiones en que se enfocará la estrategia, alineados a la demanda de la industria de Hidrocarburos, para ello podrá contratar la mercado, así como a los proveedores que los ofertan;\nb) Integrar, administrar y actualizar un registro de proveedores nacionales para la industria de Hidrocarburos, en el que se registren las empresas nacionales interesadas en participar en la industria y sus necesidades de desarrollo;\nc) Implementar programas para el desarrollo de proveedores y contratistas nacionales, a partir de la detección de oportunidades de negocio;\nd) Impulsar el cierre de brechas de capacidad técnica y de calidad de las empresas, a través de programas de apoyo para asistencia técnica y financiera, y e) Integrar un consejo consultivo, encabezado por la Secretaría de Economía, con representantes de la Secretaría de Energía, la Comisión Nacional de Hidrocarburos, la Comisión Reguladora de Energía, académicos y representantes del sector privado o de la industria, incluyendo al menos tres representantes de las cámaras u organizaciones empresariales que cuenten con presencia a nivel nacional.\nDicho consejo apoyará en la definición de políticas, criterios y metodologías para el diagnóstico de la oferta de productos, bienes y servicios; la promoción de la industria nacional; la formación de Cadenas Productivas regionales y nacionales, y el desarrollo del talento de los recursos humanos, la innovación y la tecnología;\nII. La estrategia para el fomento de la inversión directa deberá:\na) Fomentar la participación directa de empresas mexicanas para llevar a cabo, por sí mismas, las actividades en la industria de Hidrocarburos;\nb) Promover la asociación entre empresas mexicanas y extranjeras, para llevar a cabo las actividades en la industria de Hidrocarburos;\nc) Promover la inversión nacional y extranjera para que se realicen actividades de permanencia en México directamente en la industria de Hidrocarburos, o bien en la fabricación de bienes o prestación de servicios relacionados con esta industria, y d) Impulsar la transferencia de tecnología y conocimiento.\nCorresponde a la Secretaría de Economía dar seguimiento al avance de las estrategias a que se refiere este artículo, así como elaborar y publicar, de forma anual, un informe sobre los avances en la implementación de dichas estrategias, el cual deberá ser presentado al Congreso de la Unión a más tardar el 30 de junio de cada año.\nReforma DOF 06-11-2020: Derogó del artículo el entonces párrafo tercero\nArtículo 126.- La Secretaría de Economía establecerá la metodología para medir el contenido nacional en la industria de Hidrocarburos, así como su verificación, para lo cual podrá contar con el apoyo de un tercero independiente o de las autoridades del sector.\nLos Asignatarios y Contratistas, así como los Permisionarios a que se refiere esta Ley, deberán realicen, conforme a lo que establezcan las disposiciones que para tal efecto emita.\nArtículo 127.- Se deroga.\nArtículo 128.- La Secretaría de Energía, la Comisión Nacional de Hidrocarburos y la Comisión\nReguladora de Energía, con la opinión de la Secretaría de Economía, deberán establecer dentro de las condiciones que se incluyan en las Asignaciones y los Contratos para la Exploración y Extracción, así como en los permisos que contempla esta Ley que, bajo las mismas circunstancias, incluyendo igualdad de precios, calidad y entrega oportuna, se deberá dar preferencia a:\nI. La adquisición de bienes nacionales, y\nII. La contratación de servicios de origen nacional, incluyendo la capacitación y contratación, a nivel técnico y directivo, de personas de nacionalidad mexicana.\nCapítulo VII\nDe la Seguridad Industrial y la Protección al Medio Ambiente\nArtículo 129.- Corresponde a la Agencia emitir la regulación y la normatividad aplicable en materia de seguridad industrial y operativa, así como de protección al medio ambiente en la industria de Hidrocarburos, a fin de promover, aprovechar y desarrollar de manera sustentable las actividades de la industria de Hidrocarburos.\nLa Agencia deberá aportar los elementos técnicos para el diseño y la definición de la política pública en materia energética, de protección al medio ambiente y recursos naturales, así como para la formulación de los programas sectoriales en la materia, que se relacionen con su objeto.\nLa Agencia se regirá por lo dispuesto en su propia ley.\nArtículo 130.- Los Asignatarios, Contratistas, Autorizados y Permisionarios ejecutarán las acciones de prevención y de reparación de daños al medio ambiente o al equilibrio ecológico que ocasionen con sus actividades y estarán obligados a sufragar los costos inherentes a dicha reparación, cuando sean declarados responsables por resolución de la autoridad competente, en términos de las disposiciones aplicables.\nCapítulo VIII\nDe la Aplicación General de esta Ley\nArtículo 131.- La aplicación y la interpretación para efectos administrativos de esta Ley corresponde, en el ámbito de sus atribuciones, a las Secretarías de Energía, de Hacienda y Crédito Público y de Economía, a la Comisión Nacional de Hidrocarburos, a la Comisión Reguladora de Energía y a la Agencia Nacional de Seguridad Industrial y de Protección al Medio Ambiente del Sector Hidrocarburos.\nTRANSITORIOS\nPrimero.- La presente Ley entrará en vigor al día siguiente de su publicación en el Diario Oficial de la Federación.\nSegundo.- Se abroga la Ley Reglamentaria del Artículo 27 Constitucional en el Ramo del Petróleo, refieren los Transitorios Cuarto, Quinto y Décimo Noveno de la presente Ley.\nTercero.- Se derogan todas aquellas disposiciones que se opongan a lo dispuesto en la presente Ley.\nEn tanto se emite nueva regulación o se modifica la regulación correspondiente, la normatividad y Energía, las Comisiones Reguladora de Energía y Nacional de Hidrocarburos, continuarán en vigor, sin perjuicio de que puedan ser adecuadas, modificadas o sustituidas, en términos de las disposiciones de esta Ley y las demás disposiciones aplicables.\nCuarto.- El Ejecutivo Federal expedirá el Reglamento de esta Ley dentro de los ciento ochenta días naturales siguientes a la fecha de su entrada en vigor. El reglamento de la Ley Reglamentaria a que se refiere el Segundo transitorio de la presente Ley, así como los reglamentos de Gas Natural y de Gas\nLicuado de Petróleo, continuarán vigentes en lo que no se opongan a la misma y hasta que entren en vigor las nuevas disposiciones reglamentarias.\nQuinto.- En tanto se expiden los reglamentos correspondientes, las Secretarías de Energía, de Hacienda y Crédito Público y de Economía, la Comisión Nacional de Hidrocarburos y la Comisión\nReguladora de Energía están facultadas para ejercer las atribuciones que les otorga la presente Ley a partir de su entrada en vigor.\nLas solicitudes de autorización o permisos que se hayan recibido con anterioridad a la entrada en vigor de esta Ley, se tramitarán conforme a las disposiciones jurídicas que se encuentren vigentes al momento de expedición de la presente Ley y a las disposiciones que para el efecto haya emitido el órgano regulador competente con anterioridad a la presente Ley.\nSexto.- Durante el proceso previsto en el Sexto Transitorio del Decreto que reforma diversas disposiciones constitucionales en Materia de Energía publicado en el Diario Oficial de la Federación el 20 de diciembre de 2013, la Secretaría de Energía otorgará Asignaciones a Petróleos Mexicanos de conformidad con lo dispuesto en el referido transitorio. Las Asignaciones que se otorguen a Petróleos\nMexicanos durante dicho proceso se regularán conforme a las disposiciones establecidas en la presente\nLey.\nSéptimo.- Los titulares de concesiones mineras que a la entrada en vigor de la presente Ley cuenten con permiso para la recuperación y aprovechamiento de Gas Natural asociado a los yacimientos de carbón mineral, podrán continuar las actividades autorizadas en dicho permiso, sin que ello implique que les son conferidos derechos adicionales para la Exploración y Extracción de Hidrocarburos.\nSin perjuicio de lo anterior, los titulares de concesiones mineras tendrán un plazo de noventa días naturales, contados a partir de la entrada en vigor de la presente Ley, para solicitar a la Comisión\nNacional de Hidrocarburos la adjudicación directa del Contrato para la Exploración y Extracción que se encuentre en la veta de carbón mineral en el área amparada en el permiso. Lo anterior, siempre y cuando se encuentre en producción la concesión minera y acrediten que cuentan con la capacidad técnica, administrativa y financiera para llevar a cabo las actividades de Exploración y Extracción de Hidrocarburos.\nEl contrato deberá ser otorgado por la Comisión Nacional de Hidrocarburos en términos de esta Ley.\nTranscurrido un plazo de 180 días naturales, contados a partir de la entrada en vigor de la presente\nLey, cualquier permiso de recuperación y aprovechamiento de gas natural asociado a yacimientos de carbón mineral, quedará sin efectos.\nOctavo.- A partir de la entrada en vigor de la presente Ley, la Comisión Nacional de Hidrocarburos podrá adjudicar de manera directa a Petróleos Mexicanos, a alguna de sus empresas productivas subsidiarias o empresas filiales o a otra empresa productiva del Estado, un contrato para la y no podrá ser prorrogado o renovado.\nPara lo anterior, las Secretarías de Energía y de Hacienda y Crédito Público determinarán la contraprestación correspondiente por los servicios de comercialización, la cual deberá estar referida a condiciones de mercado.\nA partir del 1o. de enero de 2018 se estará a lo dispuesto en el artículo 28 de esta Ley y el Estado contratará los servicios de comercialización de los Hidrocarburos necesarios a través de una licitación pública que realice la Comisión Nacional de Hidrocarburos.\nNoveno.- Para integrar el Centro Nacional de Información de Hidrocarburos, Petróleos Mexicanos, sus organismos subsidiarios y empresas filiales, así como el Instituto Mexicano del Petróleo, transferirán a la Comisión Nacional de Hidrocarburos, a título gratuito, toda la información a que se refieren los artículos 32, 33 y 35 de esta Ley, que se haya obtenido a la fecha de entrada en vigor de esta Ley.\nDicha transferencia se realizará en un plazo que no excederá de dos años a partir de la entrada en vigor de esta Ley, conforme a los lineamientos que la Comisión Nacional de Hidrocarburos emita, dentro de los cuales se instruirá, entre otros, la elaboración de un inventario de la información y activos asociados, que incluirá los contratos que tengan suscritos Petróleos Mexicanos, sus organismos subsidiarios y empresas filiales, así como el Instituto Mexicano del Petróleo.\nLos contratos a los que se refiere el párrafo anterior incluyen los de servicios, de tecnologías de información y comunicaciones, de interpretación y cualquier otro relacionado con los sistemas, bases de datos e infraestructura que generan, manejan y procesan la información y que se usan en la administración de la misma.\nDe forma inmediata a la entrada en vigor del presente Decreto, Petróleos Mexicanos, sus organismos subsidiarios, sus empresas filiales y, en su caso, el Instituto Mexicano del Petróleo, llevarán a cabo las acciones y los convenios modificatorios que sean necesarios, a efecto de que se establezca que la Comisión Nacional de Hidrocarburos será beneficiaria de forma directa de los derechos contenidos en los contratos mencionados en el párrafo anterior, de manera que la Comisión Nacional de Hidrocarburos esté en posibilidad de requerir directamente a los proveedores o prestadores del servicio, la información y servicios que correspondan a cada uno de los contratos, para recopilar, descargar o transferir la información que requiera.\nAsimismo, de forma inmediata a la entrada en vigor del presente Decreto, la Comisión Nacional de Hidrocarburos tendrá acceso irrestricto, tanto de forma remota como dentro de las instalaciones, a la información y a los activos asociados de Petróleos Mexicanos y del Instituto Mexicano del Petróleo.\nEn caso de incumplimiento a lo dispuesto en este transitorio por parte de Petróleos Mexicanos o de las empresas contratistas, la Comisión Nacional de Hidrocarburos sancionará conforme a lo que se establece en el artículo 85, fracción II, inciso n) de esta Ley.\nDécimo.- Los permisos que se hubieran otorgado por la Secretaría de Energía o la Comisión\nReguladora de Energía para llevar a cabo las actividades de la industria de Hidrocarburos con anterioridad a la entrada en vigor de esta Ley, mantendrán su vigencia en los términos otorgados. Lo anterior, sin perjuicio de las obligaciones en materia de acceso abierto previstas en la presente Ley.\nDécimo Primero.- A partir del 1o. de enero de 2015, la Secretaría de Energía y la Comisión\nReguladora de Energía podrán otorgar, en el ámbito de sus respectivas competencias, los Permisos y presente Ley.\npermiso y no cuenten con el mismo, podrán continuar llevándolas a cabo conforme a lo siguiente:\nI. Tratándose del Tratamiento, refinación y Procesamiento, siempre que soliciten y obtengan el\nII. Tratándose de la compresión, licuefacción, descompresión y regasificación, Transporte,\nAlmacenamiento, Distribución, Expendio al Público o comercialización, siempre que soliciten y obtengan el permiso correspondiente de la Comisión Reguladora de Energía a más tardar el 31 de diciembre de 2015.\nDurante el plazo previsto en la presente fracción, se deberá continuar observando las disposiciones jurídicas y técnicas, así como las resoluciones y actos administrativos o autorizaciones aplicables a las instalaciones y equipos de transporte que se utilicen para las actividades de carga, traslado, depósito, recepción y manejo de productos, así como para el combate al mercado ilícito, vigentes a la fecha de entrada en vigor de la presente Ley.\nLa Secretaría de Energía y la Comisión Reguladora de Energía podrán solicitar a Petróleos Mexicanos y sus subsidiarias, la información y registros que tengan en sus bases de datos respecto de las personas que realicen las actividades señaladas en las fracciones I y II anteriores.\nLa Secretaría de Energía y la Comisión Reguladora de Energía establecerán los mecanismos que faciliten y agilicen la expedición de los permisos a que se refiere este artículo transitorio.\nSin perjuicio de lo establecido en el presente transitorio, el otorgamiento de permisos relacionados con la importación y Expendio al Público de gasolinas y diésel se realizará de conformidad con el transitorio\nDécimo cuarto, fracciones II y III, de esta Ley. De la misma forma, el otorgamiento de permisos relacionados con la importación de Gas Licuado de Petróleo se realizará de conformidad con lo establecido en el transitorio Vigésimo Noveno, fracción II, de esta Ley.\nDécimo Segundo.- A más tardar dentro de los doce meses siguientes a la entrada en vigor de la presente Ley, el Ejecutivo Federal emitirá el Decreto de creación del organismo público descentralizado denominado Centro Nacional de Control del Gas Natural, encargado de la gestión, administración y operación del Sistema de Transporte y Almacenamiento Nacional Integrado. En dicho Decreto se establecerá la organización, funcionamiento y facultades del citado organismo.\nAsimismo, el Decreto deberá proveer lo necesario para que Petróleos Mexicanos y sus organismos subsidiarios, transfieran los recursos necesarios para que el Centro Nacional de Control del Gas Natural adquiera y administre la infraestructura para el Transporte por ducto y el Almacenamiento de Gas Natural que tengan en propiedad para dar el servicio a los usuarios correspondientes.\nEl Decreto también preverá los términos y condiciones para que Petróleos Mexicanos, sus organismos subsidiarios, y las empresas en las que cuenten con participación directa o indirecta realicen los actos jurídicos necesarios a efecto de que el Centro Nacional de Control del Gas Natural, administre y gestione, conforme al párrafo segundo del artículo 66 de esta Ley, los siguientes contratos de reserva de capacidad de Transporte y de Almacenamiento de Gas Natural:\nI. Los que tengan suscritos con usuarios en calidad de Permisionario de Transporte de Gas\nNatural;\nII. Los que tengan suscritos con Permisionarios que a la fecha de entrada en vigor de esta Ley se encuentren operando;\nIII. Los que tengan suscritos con personas que no hayan iniciado operaciones, a la entrada en vigor de esta Ley;\nIV. Los que tengan suscritos o suscriban en ductos de Internación, y\nV. Los que suscriban en tanto entra en vigor el Decreto de creación del Centro Nacional de Control del Gas Natural.\nLo previsto en las fracciones II, III, IV y V también será aplicable a los contratos de reserva de capacidad de Transporte y de Almacenamiento de Gas Natural de la Comisión Federal de Electricidad conforme al párrafo segundo del artículo 66 de esta Ley.\nLos actos jurídicos que sean necesarios para que el Centro Nacional de Control del Gas Natural administre y gestione la capacidad de los contratos señalados en el presente transitorio, se realizarán sin perjuicio de que las empresas productivas del Estado, sus organismos subsidiarios y las empresas en las que los primeros cuenten con participación directa o indirecta reserven y/o mantengan los contratos de reserva de la capacidad que requieran para sus operaciones de generación eléctrica y transformación industrial de hidrocarburos, según sea el caso.\nPara efectos de la reserva y/o ejercicio de la capacidad en exceso a la requerida para sus operaciones, las empresas productivas del Estado, sus organismos subsidiarios y las empresas en las que los primeros cuenten con participación directa o indirecta participarán en igualdad de condiciones respecto de otros usuarios, en:\nI. La asignación de capacidad que realice el transportista, o en su caso, el Centro Nacional de Control del Gas Natural, a través de boletines electrónicos, en los términos que establezca la Comisión Reguladora de Energía, y/o\nII. Los procesos de Temporada Abierta que lleve a cabo el Transportista o en su caso, el Centro\nNacional de Control del Gas Natural para la expansión de sus sistemas en los términos que establezca la Comisión Reguladora de Energía.\nPara efecto de lo dispuesto en las fracciones anteriores, en cada caso, deberán preverse los mecanismos necesarios para el cobro y pago de la contraprestación de los servicios correspondientes a dichos contratos.\nEn los procesos previstos en el presente transitorio se establecerán los mecanismos necesarios para salvaguardar los derechos de terceros.\nLa Secretaría de Hacienda y Crédito Público emitirá los lineamientos financieros y de contraprestaciones a que, en su caso, se sujetarán las transferencias y actividades señaladas en los párrafos anteriores, contando con el apoyo que al efecto requiera de la Comisión Reguladora de Energía.\nEn tanto el Centro Nacional de Control del Gas Natural cuenta con los recursos presupuestarios y las capacidades técnicas para realizar las licitaciones de los proyectos de infraestructura del Sistema de Transporte y Almacenamiento Nacional Integrado de Gas Natural, lo que no podrá exceder de veinticuatro meses a partir de la emisión de su Decreto de creación, la Secretaría de Energía podrá determinar que las empresas productivas del Estado realicen dichas licitaciones, previa opinión técnica y autorización de las bases de licitación, por parte de la Comisión Reguladora de Energía, la cual deberá resolver en un plazo máximo de treinta días hábiles, o se entenderá autorizada.\nTransporte y Almacenamiento Nacional Integrado de Gas Natural.\ndel referido Centro.\nDécimo Tercero. Al haberse logrado una mayor participación de agentes económicos que propicien el desarrollo eficiente y competitivo de los mercados, se deja sin efectos la facultad otorgada a la Comisión Reguladora de Energía para sujetar a principios de regulación asimétrica las ventas de primera mano de Hidrocarburos, Petrolíferos o Petroquímicos, así como la comercialización que realicen personas controladas por Petróleos Mexicanos o sus organismos subsidiarios.\nLa enajenación que realicen Petróleos Mexicanos, sus empresas productivas subsidiarias, o una Persona Moral, por cuenta y orden del Estado, será considerada como comercialización en términos de lo establecido por la presente Ley y sus Reglamentos, por lo que se deberán observar los principios de generalidad y no indebida discriminación previstos en la misma.\nArtículo reformado DOF 19-05-2021\nDécimo Cuarto.- En relación con los mercados de gasolina y diésel se observará lo siguiente:\nI. Se deroga.\nFracción derogada DOF 15-11-2016\nII. A partir de la entrada en vigor de la presente Ley y, como máximo, hasta el 31 de diciembre de 2016, únicamente se podrán otorgar permisos para la importación de gasolinas y diésel a\nPetróleos Mexicanos o sus empresas productivas subsidiarias.\nA partir del 1o. de enero de 2017, o antes si las condiciones de mercado lo permiten, los permisos para la importación de gasolinas y diésel podrán otorgarse a cualquier interesado que cumpla con las disposiciones jurídicas aplicables.\nLos permisos para el Expendio al Público de gasolinas y diésel serán otorgados por la Comisión Reguladora de Energía a partir del 1° de enero de 2016.\nIII. La vigencia de los contratos de suministro que suscriban Petróleos Mexicanos, sus empresas productivas subsidiarias o sus empresas filiales no podrá exceder del 31 de diciembre de\n2016.\nLo anterior, sin perjuicio de que, a partir del 1o. de enero de 2017, Petróleos Mexicanos, sus empresas productivas subsidiarias o sus empresas filiales puedan celebrar contratos de suministro bajo las nuevas condiciones de mercado.\nLos contratos de suministro que suscriban Petróleos Mexicanos, sus empresas productivas subsidiarias o sus empresas filiales no podrán estar condicionados a la celebración de contratos de franquicia, ni limitar a las partes del contrato de suministro a darlo por terminado de manera unilateral, en competencia efectiva.\nDécimo Quinto.- La Comisión Reguladora de Energía deberá emitir dentro de los trescientos sesenta abierto a que se sujetará la infraestructura de Transporte, Almacenamiento y Distribución de Petrolíferos.\nadministrativas de carácter general para regular:\nI. El diseño, construcción, operación y mantenimiento de las instalaciones destinadas al Expendio al Público de Petrolíferos, y\nII. El diseño, construcción, operación y mantenimiento de equipos e infraestructura para realizar las actividades de Transporte, Almacenamiento y Distribución de Petrolíferos.\nComo parte de la regulación que emita, la Agencia podrá instruir la adopción y observancia de estándares técnicos internacionales.\nDécimo Séptimo.- La Secretaría de Energía, la Comisión Nacional de Hidrocarburos y la Comisión\nReguladora de Energía desarrollarán el sistema de información para dar cumplimiento a los artículos 88, 89 y 90 de esta Ley, respectivamente, a más tardar doce meses después de su entrada en vigor.\nDécimo Octavo.- Con el fin de cumplir con las atribuciones que le establece el presente ordenamiento, la Secretaría de Economía creará una unidad especializada que se encargará de:\nI. Dar seguimiento a las estrategias para el fomento industrial de Cadenas Productivas locales y para el fomento de la inversión directa en la industria de Hidrocarburos y elaborar y publicar el informe sobre los avances en la implementación de las mismas;\nII. Proponer la metodología para medir el contenido nacional en Asignaciones y Contratos de Exploración y Extracción, así como en las otras actividades a que se refiere el artículo 2 de esta Ley, y\nIII. Verificar el cumplimiento de las metas de contenido nacional establecidas en las Asignaciones y Contratos de Exploración y Extracción.\nDicha unidad contará con las áreas y estructura necesarias para ejercer las facultades señaladas en esta Ley. La Cámara de Diputados realizará las acciones necesarias para proveer de recursos presupuestarios a la unidad especializada a que se refiere el presente transitorio, con el fin de que pueda llevar a cabo sus funciones. El presupuesto aprobado deberá cubrir los capítulos de servicios personales, materiales y suministros, así como de servicios generales, necesarios para cumplir con sus funciones.\nSe realizarán las acciones necesarias para que la Secretaría de Economía emita la metodología para medir el contenido nacional a más tardar dentro de los noventa días naturales siguientes a la entrada en vigor de la presente Ley.\nCon base en dicha metodología, la Secretaría de Economía calculará el contenido nacional observado en las áreas en Exploración y en los campos en Extracción en el primer semestre de 2014, y lo publicará a más tardar dentro de los ciento ochenta días naturales siguientes a la entrada en vigor de la presente\nLey. Lo anterior con el fin de contar con la línea base para establecer los requerimientos de contenido que se llevará a cabo dichas actividades.\na que se refiere el párrafo anterior, las Asignaciones preverán que el porcentaje mínimo de contenido nacional al que se sujetarán, se definirá posteriormente mediante una modificación a los términos y condiciones de las mismas.\nDécimo Noveno.- Los contratos de obras, servicios, proveeduría u operación suscritos por Petróleos\nMexicanos, con fundamento en la Ley Reglamentaria del Artículo 27 Constitucional en el Ramo del Tercero Transitorio de la presente Ley, continuarán en vigor bajo los términos y condiciones en que hayan sido suscritos.\nVigésimo.- El Servicio Geológico Mexicano establecerá la coordinación necesaria con la Comisión\nNacional de Hidrocarburos, a efecto de que, en un plazo no mayor a ciento ochenta días, contados a partir de la entrada en vigor del presente Decreto, se le transfiera a esta última toda la información sobre el potencial gasífero asociado a yacimientos de carbón mineral con que cuente hasta la fecha o cualquier otra información que le pueda ser de utilidad, conforme a sus atribuciones de Exploración y Extracción de Hidrocarburos.\nVigésimo Primero.- En tanto entra en funciones la Agencia, de acuerdo con lo previsto en la Ley de la materia, la Secretaría de Energía, la Comisión Nacional de Hidrocarburos y la Comisión Reguladora de Energía continuarán regulando y supervisando, en el ámbito de sus atribuciones, la industria de los Hidrocarburos en materia de seguridad industrial y operativa.\nVigésimo Segundo.- Durante los dos años siguientes a la entrada en vigor de esta Ley, los plazos o términos previstos en ella, que correspondan a la Secretaría de Energía, a la Comisión Nacional de Hidrocarburos y a la Comisión Reguladora de Energía, se ampliarán hasta por un tercio del tiempo previsto en esta Ley.\nVigésimo Tercero.- En tanto se lleva a cabo su transición a empresas productivas del Estado, las disposiciones de esta Ley aplican a Petróleos Mexicanos y a sus organismos subsidiarios, así como a la Comisión Federal de Electricidad.\nVigésimo Cuarto.- El porcentaje mínimo promedio de contenido nacional en materia de Exploración y Extracción de Hidrocarburos, a que se refiere el primer párrafo del artículo 46 de esta Ley, aumentará de forma gradual a partir de 25% en 2015 hasta llegar al menos a 35% en 2025, debiendo revisarse con posterioridad cada cinco años.\nDicha meta excluirá actividades en aguas profundas y ultra profundas, para lo cual la Secretaría de Economía, con la opinión de la Secretaría de Energía, establecerá los valores para 2015 y 2025, con base en el estudio que realice del contenido nacional observado en dichas actividades al primer semestre de 2014.\nVigésimo Quinto.- Dentro de los ciento ochenta días siguientes a la entrada en vigor de la presente\nLey, se realizarán las acciones necesarias para que el Fideicomiso Público para Promover el Desarrollo de Proveedores y Contratistas Nacionales para la Industria Petrolera Estatal, constituido en términos del Artículo Décimo Cuarto Transitorio de la Ley de Petróleos Mexicanos, publicada en el Diario Oficial de la Federación el 28 de noviembre de 2008, se transforme en el Fideicomiso Público para Promover el Desarrollo de Proveedores y Contratistas Nacionales de la Industria Energética a que se refiere el artículo 127 de esta Ley.\nVigésimo Sexto.- Cuando los Permisionarios incrementen la capacidad de ductos de Transporte de financiados por usuarios, cuyo diseño haya sido considerado para satisfacer sus necesidades de consumo propio, así como alguna posible amplitud financiada por el mismo usuario, podrán recuperar un establezca la Comisión Reguladora de Energía.\nregulación y permisos para el Transporte, Almacenamiento y Distribución que no se encuentren vinculados a ductos, así como para el Expendio al Público de Gas Licuado de Petróleo serán expedidos por la Secretaría de Energía. Durante este plazo, las disposiciones y metodologías para determinar las tarifas máximas aplicables a dicho Transporte, Almacenamiento y Distribución serán emitidas por la Secretaría de Energía, con el apoyo técnico de la Comisión Reguladora de Energía.\nVigésimo Octavo.- Los contratos integrales de exploración y producción o contratos de obra pública financiada, que se encuentren vigentes, que hayan sido originalmente licitados y suscritos por Petróleos\nMexicanos o sus organismos subsidiarios previo a la entrada en vigor de esta Ley no sufrirán modificación alguna en sus términos y condiciones como resultado de la publicación de la misma.\nLas partes de dichos contratos podrán solicitar conjuntamente a la Secretaría de Energía, la migración de la Asignación a un Contrato para la Exploración y Extracción sin necesidad de agotar el procedimiento de licitación previsto en la presente Ley. Esta migración se realizará con base en los lineamientos técnicos que establezca la Secretaría de Energía y las condiciones económicas relativas a los términos fiscales, que conforme a la Ley de Ingresos sobre Hidrocarburos, disponga la Secretaría de Hacienda y Crédito Público, siempre y cuando no se afecte el balance de los ingresos esperados para el Estado. En la elaboración de los lineamientos técnicos a que se refiere este artículo, la Secretaría de Energía solicitará opinión a Petróleos Mexicanos.\nLas Secretarías de Energía y de Hacienda y Crédito Público informarán a las partes los términos contractuales y fiscales que al efecto establezcan. En caso de que los lineamientos técnicos y los términos contractuales y fiscales propuestos no resulten aceptables a las partes una vez realizada la petición de migración, éstas tendrán el derecho a mantener su relación contractual original bajo los contratos integrales de exploración y producción o contratos de obra pública financiada según corresponda.\nEn caso de que las partes manifiesten su conformidad a los términos contractuales y fiscales propuestos, la Secretaría de Energía aprobará la migración y procederá la formalización de un Contrato para la Exploración y Extracción que se firmará por parte de la Comisión Nacional de Hidrocarburos y la asociación o alianza que para este propósito específico constituyan la empresa productiva subsidiaria y la Persona Moral respectiva, de acuerdo con las políticas que dicte el Consejo de Administración de Petróleos Mexicanos.\nPrevio a la firma del Contrato para la Exploración y Extracción, deberá haberse dado por terminado de manera anticipada el contrato integral de exploración y producción o el contrato de obra pública financiada, según corresponda, sin que se ocasionen daños, perjuicios, sanciones o cualquier otra consecuencia punitiva a ninguna de las partes y debiendo salvaguardarse los derechos de terceros.\nLas inversiones realizadas con motivo de la ejecución del correspondiente contrato, podrán ser reconocidas por las partes como aportación de capital por parte de quien sea titular de las mismas a la asociación o alianza constituida entre estas para la ejecución y administración del Contrato.\nVigésimo Noveno.- En relación con el Expendio al Público de Gas Licuado de Petróleo, se observará lo siguiente:\nI. Hasta en tanto no se implemente un programa de apoyos focalizados a los consumidores de Gas Licuado del Petróleo, los precios máximos al público serán establecidos por el Ejecutivo\nFederal mediante acuerdo. Dicho acuerdo deberá considerar las diferencias relativas por público, en su caso. Asimismo, la política de precios máximos al público que se emita deberá prever, en caso de que los precios internacionales de estos combustibles experimenten alta volatilidad, mecanismos de ajuste que permitan revisar al alza los incrementos de los citados precios, de manera consistente con la evolución del mercado internacional.\ndeberá promover el aprovechamiento sustentable de la energía y la mayor generación posible de valor agregado y el uso eficiente de recursos.\nLos precios al público de Gas Licuado de Petróleo se determinarán bajo condiciones de mercado a partir del 1o. de enero de 2017 o antes, en la fecha en que se haya implementado el programa de apoyos focalizados a los consumidores a que se refiere el párrafo primero de esta fracción, y\nII. A partir de la entrada en vigor de la presente Ley y, como máximo hasta el 31 de diciembre de 2015, sólo se podrán otorgar permisos para la importación de Gas Licuado de Petróleo a\nPetróleos Mexicanos, sus subsidiarias y empresas filiales.\nA partir del 1o. de enero de 2016, o antes si las condiciones del mercado lo permiten, los permisos a que se refiere esta fracción se podrán otorgar a cualquier interesado que cumpla con las disposiciones jurídicas aplicables.\nTrigésimo.- A más tardar dentro de los doce meses posteriores a la entrada en vigor de la presente\nLey, el Ejecutivo Federal realizará las adecuaciones que correspondan a la organización y funcionamiento del Instituto Mexicano del Petróleo, con el fin de que pueda participar de manera competitiva y eficaz en la atención de las necesidades de investigación, desarrollo tecnológico y capacitación que tengan los distintos participantes del sector Hidrocarburos.\nTrigésimo Primero.- Durante los primeros dos años contados a partir de la entrada en vigor de la presente Ley, la Secretaría de Energía y la Comisión Nacional de Hidrocarburos podrán contratar las adquisiciones, arrendamientos y servicios que requieran para la construcción de cuartos de datos y del Centro Nacional de Información de Hidrocarburos, así como los servicios de asesoría legal, que sean necesarios para instrumentar los procesos de licitación de los Contratos para la Exploración y Extracción, sin sujetarse al procedimiento de licitación pública, a través de los procedimientos de invitación a cuando menos tres personas o de adjudicación directa, acreditando en todo momento los criterios de economía, eficacia, eficiencia, imparcialidad, honradez y transparencia que resulten procedentes para obtener las mejores condiciones para el Estado.\nTrigésimo Segundo.- Los contratos, convenios o instrumentos de naturaleza jurídica análoga a que se refiere esta Ley o que estén relacionados con ella por ministerio de ley, no podrán prever cláusula o acuerdo de voluntad alguno, que otorgue exclusividad o preferencia ilícitas en beneficio de organización empresarial, social o sindical alguna.\nARTÍCULOS SEGUNDO A QUINTO. ……….\nTRANSITORIOS\nPRIMERO. El presente Decreto entrará en vigor el día siguiente al de su publicación en el Diario\nOficial de la Federación.\nlas dependencias y entidades puedan cumplir las atribuciones conferidas en este Decreto.\nMéxico, D.F., a 5 de agosto de 2014.- Dip. José González Morfín, Presidente.- Sen. Raúl Cervantes\nAndrade, Presidente.- Dip. Javier Orozco Gómez, Secretario.- Sen. Lilia Guadalupe Merodio Reza,\nSecretaria.- Rúbricas.\"\nEn cumplimiento de lo dispuesto por la fracción I del Artículo 89 de la Constitución Política de los Estados Unidos Mexicanos, y para su debida publicación y observancia, expido el presente Decreto en la Residencia del Poder Ejecutivo Federal, en la Ciudad de México, Distrito Federal, a once de agosto de dos mil catorce.- Enrique Peña Nieto.- Rúbrica.- El Secretario de Gobernación, Miguel Ángel Osorio\nChong.- Rúbrica.\nFiscal de 2017.\nARTÍCULO PRIMERO. Se expide la Ley de Ingresos de la Federación para el Ejercicio Fiscal de\n2017.\n………\nTransitorios de la Ley de Ingresos de la Federación para el Ejercicio Fiscal de 2017\nPrimero. La presente Ley entrará en vigor el 1 de enero de 2017, salvo lo dispuesto en los transitorios\nDécimo Segundo y Décimo Cuarto, los cuales entrarán en vigor el día siguiente al de su publicación en el Diario Oficial de la Federación.\nSegundo. Se aprueban las modificaciones a la Tarifa de los Impuestos Generales de Importación y de Exportación efectuadas por el Ejecutivo Federal a las que se refiere el informe que, en cumplimiento de lo dispuesto en el segundo párrafo del artículo 131 de la Constitución Política de los Estados Unidos\nMexicanos, ha rendido el propio Ejecutivo Federal al Congreso de la Unión en el año 2016.\nTercero. Para los efectos de la Ley de Ingresos de la Federación para el Ejercicio Fiscal de 2017, cuando de conformidad con la Ley Orgánica de la Administración Pública Federal se modifique la denominación de alguna dependencia o entidad o las existentes desaparezcan, se entenderá que los ingresos estimados para éstas en la presente Ley corresponderán a las dependencias o entidades cuyas denominaciones hayan cambiado o que absorban las facultades de aquéllas que desaparezcan, según corresponda.\nCuarto. El gasto corriente estructural a que se refiere el artículo 2, fracción XXIV BIS de la Ley\nFederal de Presupuesto y Responsabilidad Hacendaria excluirá, adicionalmente a los conceptos de gasto previstos en dicha fracción, los gastos relativos a la implementación de las reformas a que se refiere el Decreto por el que se reforman y adicionan diversas disposiciones de la Constitución Política de los Estados Unidos Mexicanos en Materia de Energía, publicado en el Diario Oficial de la Federación el 20 de diciembre de 2013, así como de las leyes secundarias que derivan de dicho Decreto, publicadas en el mismo órgano de difusión oficial el 11 de agosto de 2014.\nQuinto. Durante el ejercicio fiscal de 2017 el Fondo de Compensación del Régimen de Pequeños\nContribuyentes y del Régimen de Intermedios creado mediante el Quinto transitorio de la Ley de Ingresos de la Federación para el Ejercicio Fiscal de 2014, publicada en el Diario Oficial de la Federación el 20 de noviembre de 2013 continuará destinándose en los términos del citado precepto.\nSexto. El Presupuesto de Egresos de la Federación para el Ejercicio Fiscal 2017 aprobado deberá impuesto especial sobre producción y servicios aplicable a las bebidas saborizadas, de acuerdo con lo previsto en el artículo 1o. de la Ley de Ingresos de la Federación para el Ejercicio Fiscal de 2017, una vez descontadas las participaciones que correspondan a las entidades federativas, para destinarse a programas de promoción, prevención, detección, tratamiento, control y combate a la desnutrición, sobrepeso, obesidad y enfermedades crónico degenerativas relativas, así como para apoyar el incremento en la cobertura de los servicios de agua potable en localidades rurales, y proveer bebederos con suministro continúo de agua potable en inmuebles escolares públicos con mayor rezago educativo, de conformidad con los artículos 7 y 11 de la Ley General de la Infraestructura Física Educativa.\nSéptimo. A partir del ejercicio fiscal 2017 las referencias que en materia de administración, determinación, liquidación, cobro, recaudación y fiscalización de las contribuciones se hacen a la Comisión Nacional del Agua en la Ley Federal de Derechos, así como en los artículos 51 de la Ley de Coordinación Fiscal y Décimo Tercero de las Disposiciones Transitorias del Decreto por el que se reforman y adicionan diversas disposiciones de la Ley de Coordinación Fiscal y de la Ley General de Contabilidad Gubernamental, publicado en el Diario Oficial de la Federación el 9 de diciembre de 2013 y las disposiciones que emanen de dichos ordenamientos se entenderán hechas también al Servicio de Administración Tributaria.\nOctavo. Para efectos de lo previsto en el artículo 107, fracción I de la Ley Federal de Presupuesto y Responsabilidad Hacendaria, la Secretaría de Hacienda y Crédito Público deberá incluir en los informes trimestrales información sobre los costos recaudatorios de las medidas que representan un gasto fiscal, así como de los beneficiarios de dichos mecanismos, contenidos en los decretos que emita el Ejecutivo\nFederal en el ejercicio de las facultades conferidas en las fracciones II y III del artículo 39 del Código\nFiscal de la Federación durante el trimestre que se reporta.\nNoveno. Para efectos de lo previsto en el artículo 107, fracción I de la Ley Federal de Presupuesto y Responsabilidad Hacendaria, la Secretaría de Hacienda y Crédito Público deberá reportar en los Informes Trimestrales la información sobre los ingresos excedentes que, en su caso, se hayan generado con respecto al calendario de ingresos derivado de la Ley de Ingresos de la Federación a que se refiere el artículo 23 de la Ley Federal de Presupuesto y Responsabilidad Hacendaria. En este reporte se presentará la comparación de los ingresos propios de las entidades paraestatales bajo control presupuestario directo, de las empresas productivas del Estado, así como del Gobierno Federal. En el caso de éstos últimos se presentará lo correspondiente a los ingresos provenientes de las transferencias del Fondo Mexicano del Petróleo para la Estabilización y el Desarrollo.\nDécimo. Las Entidades Federativas y Municipios que cuenten con disponibilidades de recursos federales, correspondientes a ejercicios fiscales anteriores al 2016, que no hayan sido devengados conforme a los calendarios respectivos, deberán enterarlos a la Tesorería de la Federación, incluyendo los rendimientos financieros que hubieran generado.\nPara efectos de lo anterior, los aprovechamientos provenientes de los enteros que realicen las Entidades Federativas y Municipios en términos del presente transitorio, no se considerarán extemporáneos, por lo que no causan daño a la hacienda pública ni se cubrirán cargas financieras, siempre y cuando dichas disponibilidades hayan estado depositadas en cuentas bancarias de la Entidad\nFederativa y/o Municipio.\nDécimo Primero. A partir del 1 de enero de 2017 se derogan las siguientes disposiciones:\nI. Las fracciones III y V del artículo Quinto del Decreto por el que se reforman, adicionan y derogan diversas disposiciones de la Ley del Impuesto sobre la Renta, de la Ley del Impuesto\nEspecial sobre Producción y Servicios, del Código Fiscal de la Federación y de la Ley Federal\nII. La fracción I y el último párrafo del artículo Décimo Cuarto Transitorio de la Ley de Décimo Segundo. Durante 2017 y 2018 los precios al público de las gasolinas y el diésel se determinarán de conformidad con lo siguiente:\nI. La Comisión Reguladora de Energía, tomando en cuenta la opinión que emita la Comisión\nFederal de Competencia Económica, emitirá los acuerdos o el cronograma de flexibilización para que durante los años de 2017 y 2018 los precios al público se determinen bajo condiciones de mercado. Los acuerdos o el cronograma se establecerán por regiones del país. La Comisión\nReguladora de Energía podrá modificar dichos acuerdos o cronograma, con base en la evolución de las condiciones de mercado y el desarrollo de la infraestructura de suministro en el país, entre otros factores. La Comisión Reguladora de Energía deberá publicar en el Diario\nOficial de la Federación los acuerdos o el cronograma actualizados. Las modificaciones únicamente podrán llevarse a cabo para adelantar el momento a partir del cual los precios al público se determinarán bajo condiciones de mercado.\nII. En las regiones del país, durante el tiempo en donde los precios al público de las gasolinas y el diésel no se determinen bajo condiciones de mercado conforme a lo establecido en la fracción anterior, la Secretaría de Hacienda y Crédito Público establecerá los precios máximos al público de las gasolinas y el diésel con base en lo siguiente:\na) Considerará el precio de la referencia internacional de los combustibles y, en su caso, las diferencias en la calidad de los mismos, las diferencias relativas por los costos de logística, incluyendo los costos de transporte entre regiones, los costos de distribución y comercialización en los centros de consumo y las diversas modalidades de distribución y expendio al público, procurando generar las condiciones para el abasto oportuno de dichos combustibles.\nLa Secretaría de Hacienda y Crédito Público publicará la metodología para determinar los precios máximos al público antes mencionados y el periodo de vigencia de los mismos a más tardar el 31 de diciembre de 2016.\nLa fijación de estos precios máximos tendrá como objetivo final la liberalización de los precios en la región que corresponda. Adicionalmente, en aquellas regiones con precio máximo, se deberá aplicar la regulación asimétrica para el acceso a la infraestructura, cuando así lo haya determinado la Comisión Reguladora de Energía y sin perjuicio de que dicha regulación pueda ser aplicada en el resto del territorio nacional.\nb) Emitirá un acuerdo en el que se especifique la región, los combustibles y el periodo de aplicación de los precios, mismo que se publicará en el Diario Oficial de la Federación con anticipación al periodo durante el cual se aplicarán.\nEn las regiones del país que al 1 de enero de 2017 no se apliquen los precios al público de las gasolinas y el diésel bajo condiciones de mercado, se deberán publicar los precios máximos al público de los combustibles mencionados, a más tardar el 31 de diciembre de\n2016.\nIII. Para los efectos de lo dispuesto en la fracción I de este artículo, cuando la Comisión\nReguladora de Energía, previa opinión de la Comisión Federal de Competencia Económica, comunique a la Secretaría de Hacienda y Crédito Público que, en las regiones en las que se de suministro, dicha Secretaría podrá establecer por regiones o subregiones, precios máximos al público de conformidad con lo dispuesto en la fracción II de este artículo.\nPara los efectos de lo dispuesto en el párrafo anterior, la Comisión Reguladora de Energía podrá ejercer la facultad establecida en la fracción IV del artículo 26 de esta Ley.\nDécimo Tercero. Para los efectos de lo dispuesto en el artículo 25, fracción I, inciso a), de la presente\nLey, los titulares de los permisos a que se refiere el artículo mencionado deberán reportar a la Comisión\nReguladora de Energía el precio de enajenación de las gasolinas, diésel, turbosina y gasavión, aplicado a partir del 1 de enero de 2017. Dicha información deberá ser proporcionada a más tardar el 15 de enero de 2017.\nDécimo Cuarto. Los titulares de permisos de comercialización, distribución y expendio al público de gas licuado de petróleo y propano deberán reportar a la Comisión Reguladora de Energía el precio de enajenación de los productos mencionados aplicado a partir del 1 de diciembre de 2016, información que deberá ser proporcionada a más tardar el 15 del mismo mes y año.\nDécimo Quinto. La aplicación de lo dispuesto en el artículo 26, fracción III de esta Ley entrará en vigor a partir del 1 de enero de 2019.\nDécimo Sexto. Para efectos de lo dispuesto en el último párrafo del artículo 5o. de la Ley del Impuesto Especial sobre Producción y Servicios, la Secretaría de Hacienda y Crédito Público en un plazo máximo de 90 días contados a partir de la entrada en vigor de la presente Ley, deberá emitir las reglas de carácter general aplicables al valor de los bonos de carbono y a su entrega como medio de pago del impuesto especial sobre producción y servicios aplicable a los combustibles fósiles. Dichas reglas deberán prever que también podrán ser aceptados como medio de pago los bonos de proyectos en México, avalados por la Organización de las Naciones Unidas dentro del Protocolo de Kioto o el instrumento que lo sustituya conforme al Acuerdo de Paris.\nDécimo Séptimo. Durante el ejercicio fiscal de 2017, para efectos del supuesto previsto en el artículo 21 Bis, fracción VIII, inciso b) de la Ley Federal de Presupuesto y Responsabilidad Hacendaria, referente al reintegro de recursos que las Entidades Federativas deben realizar al Fondo de Estabilización de los Ingresos de las Entidades Federativas, la Secretaría de Hacienda y Crédito Público compensará dicho reintegro en parcialidades contra las participaciones federales de la Entidad Federativa de que se trate, sin ninguna carga financiera adicional, dentro del término de seis meses contados a partir del día siguiente a aquél en el que se comunique a la Entidad Federativa el monto que deberá reintegrar.\nDécimo Octavo. La Secretaría de Hacienda y Crédito Público para el ejercicio fiscal de 2017, deberá reportar en los Informes Trimestrales que se presenten al Congreso de la Unión en términos del artículo 107, fracción I, de la Ley Federal de Presupuesto y Responsabilidad Hacendaria, la evolución del precio del petróleo observado respecto del cubierto mediante la Estrategia de Coberturas Petroleras para el ejercicio fiscal 2017, así como de la subcuenta que se haya constituido como complemento en el Fondo de Estabilización de los Ingresos Presupuestarios.\nDécimo Noveno. Con el propósito de coadyuvar a la transparencia y al análisis de la política fiscal, tributaria sobre dicha distribución, en el ejercicio fiscal 2017 la Secretaría de Hacienda y Crédito Público, a través del Servicio de Administración Tributaria, deberá hacer pública información estadística anónima morales. En ningún caso, la información pública podrá contener datos sobre el nombre, denominación o contribuyente.\nEl Servicio de Administración Tributaria determinará las características, fuentes, metodología y periodo de la información estadística a publicar, misma que dará a conocer en su página de Internet. La información estadística será actualizada cada dos años.\nVigésimo. En el ejercicio fiscal de 2017, la Secretaría de Hacienda y Crédito Público a través del Servicio de Administración Tributaria deberá publicar por lo menos dos estudios sobre la evasión fiscal en México. En la elaboración de dichos estudios deberán participar instituciones académicas de prestigio en el país, instituciones académicas extranjeras, centros de investigación, organismos o instituciones nacionales o internacionales que se dediquen a la investigación o que sean especialistas en la materia.\nPor lo menos uno de los estudios contendrá el análisis de la evasión fiscal por tipo de impuesto y utilizará información del ejercicio fiscal más reciente para el que ésta se encuentre disponible. Sus resultados deberán darse a conocer a las Comisiones de Hacienda y Crédito Público de ambas Cámaras del Congreso de la Unión, a más tardar 35 días después de terminado el ejercicio fiscal de 2017.\nVigésimo Primero. Con el fin de dar continuidad al cumplimiento de lo establecido por el Sexto\nTransitorio, párrafo quinto del “Decreto por el que se reforman y adicionan diversas disposiciones de la Constitución Política de los Estados Unidos Mexicanos, en Materia de Energía”, publicado el 20 de diciembre de 2013 en el Diario Oficial de la Federación, así como por el Décimo Segundo transitorio de la Ley de Ingresos de la Federación para el Ejercicio Fiscal de 2016, y de conformidad con lo establecido en el artículo 7o. de la Ley de Ingresos de la Federación para el Ejercicio Fiscal de 2017, la Secretaría de Energía deberá determinar durante el ejercicio fiscal 2017 el justo valor económico de las inversiones afectadas solicitado por Petróleos Mexicanos y la Secretaría de Hacienda y Crédito Público podrá autorizar a Petróleos Mexicanos a deducir de los pagos provisionales mensuales del derecho por la utilidad compartida del ejercicio fiscal de 2017, el justo valor económico de las inversiones afectadas que no hubiera sido compensado durante el 2016 conforme a lo dispuesto en el Décimo Segundo transitorio de la Ley de Ingresos de la Federación para el Ejercicio Fiscal de 2016.\nPara la determinación del justo valor económico al que hace referencia el párrafo anterior, la Secretaría de Energía deberá considerar todas las inversiones hechas en las áreas en exploración y campos en producción que Petróleos Mexicanos tuviera previo a la entrada en vigor del Decreto antes mencionado, que en el proceso de la Ronda Cero hubiera solicitado y que no le fueron otorgadas como asignaciones.\nEn adición al anterior, y de acuerdo al procedimiento establecido en el presente transitorio, la contraprestación que reciba Petróleos Mexicanos durante el ejercicio fiscal 2017 deberá incluir el justo valor económico correspondiente a sus inversiones que hayan resultado afectadas con motivo de las adjudicaciones de contratos para la exploración y extracción de hidrocarburos, efectuadas por la Comisión Nacional de Hidrocarburos derivados de la licitación CNH-R01-L04/2015, realizada durante el ejercicio fiscal 2016.\nVigésimo Segundo. Petróleos Mexicanos difundirá en su portal de Internet una versión pública de su\nPlan de Negocios, misma que no deberá contener información que pudiera comprometer o poner en riesgo sus estrategias comerciales.\n……..\nTransitorio\nÚnico. El presente Decreto entrará en vigor conforme a lo siguiente:\nI. El Artículo Primero, el 1 de enero de 2017, salvo lo dispuesto en los transitorios Décimo\nFederación del presente Decreto, y Sen. Pablo Escudero Morales, Presidente.- Dip. Ana Guadalupe Perea Santos, Secretaria.- Sen. Itzel\nS. Ríos de la Mora, Secretaria.- Rúbricas.\"\nEn cumplimiento de lo dispuesto por la fracción I del Artículo 89 de la Constitución Política de los Estados Unidos Mexicanos, y para su debida publicación y observancia, expido el presente Decreto en la Residencia del Poder Ejecutivo Federal, en la Ciudad de México, a catorce de noviembre de dos mil dieciséis.- Enrique Peña Nieto.- Rúbrica.- El Secretario de Gobernación, Miguel Ángel Osorio Chong.-\nRúbrica.\nProtección de Personas Defensoras de Derechos Humanos y Periodistas; de la Ley de Cooperación Internacional para el Desarrollo; de la Ley de Hidrocarburos; de la Ley de la Industria Eléctrica; de la Ley Federal de Presupuesto y Responsabilidad Hacendaria; de la Ley General de Protección Civil; de la Ley Orgánica de la Financiera Nacional de Desarrollo Agropecuario, Rural, Forestal y Pesquero; de la Ley de Ciencia y Tecnología;\nde la Ley Aduanera; de la Ley Reglamentaria del Servicio Ferroviario; de la Ley General de Cultura Física y Deporte; de la Ley Federal de Cinematografía; de la Ley Federal de Derechos; de la Ley del Fondo Mexicano del Petróleo para la Estabilización y el Desarrollo; de la Ley de Bioseguridad de Organismos Genéticamente Modificados; de la Ley General de Cambio Climático; de la Ley General de Víctimas y se abroga la Ley que crea el Fideicomiso que administrará el Fondo de Apoyo Social para Ex Trabajadores\nMigratorios Mexicanos.\nPublicado en el Diario Oficial de la Federación el 6 de noviembre de 2020 ARTÍCULO TERCERO. Se derogan los artículos 125, párrafo tercero y 127 de la Ley de Hidrocarburos, para quedar como sigue:\n………\nTransitorios\nPrimero. El presente Decreto entrará en vigor el día siguiente al de su publicación en el Diario Oficial de la Federación.\nSegundo. Se derogan todas las disposiciones que se opongan a lo dispuesto en el presente Decreto.\nTercero. Se abroga la Ley que crea el Fideicomiso que Administrará el Fondo para el Fortalecimiento de Sociedades y Cooperativas de Ahorro y Préstamo y de Apoyo a sus Ahorradores.\nCuarto. Las dependencias y entidades, por conducto de sus unidades responsables, deberán coordinar las acciones que correspondan para que a más tardar dentro de los 30 días naturales contados a partir de la entrada en vigor del presente Decreto concentren, en términos de la Ley de Ingresos de la Federación para el ejercicio fiscal que corresponda, en la Tesorería de la Federación la totalidad de los recursos públicos federales que formen parte de los fideicomisos, mandatos y análogos públicos previstos en las disposiciones que se abrogan, reforman o derogan por virtud de este Decreto, salvo que la Secretaría de Hacienda y Crédito Público determine una fecha distinta para la concentración de los recursos.\nA la extinción de los fideicomisos, y terminación de mandatos y análogos públicos las entidades concentrarán en sus respectivas tesorerías los recursos distintos a los fiscales, en el plazo señalado en el primer párrafo del presente Transitorio.\ncorrespondiente, con prioridad para el fortalecimiento de los programas y acciones en materia de salud, enfermedad Covid-19, que ocasiona el Coronavirus SARS-CoV2, incluyendo, en su caso, la obtención de la vacuna en el número de dosis necesarias, así como para procurar la estabilización del balance fiscal refiere el presente Decreto con anterioridad a la entrada en vigor del mismo.\nQuinto. Los ejecutores de gasto, por conducto de sus unidades responsables, deberán coordinarse extinguir los fideicomisos y dar por terminados los mandatos y análogos públicos a que se refieren las disposiciones que se reforman o derogan por virtud de este Decreto, con la finalidad de que durante el primer semestre del ejercicio 2021 se suscriban los convenios de extinción o terminación respectivamente, en términos de las disposiciones aplicables.\nLos derechos y obligaciones derivados de los instrumentos jurídicos que por virtud del presente\nDecreto se extinguen o terminan, serán asumidos por los ejecutores de gasto correspondientes con cargo a su presupuesto autorizado, de conformidad con las disposiciones aplicables.\nSexto. Las dependencias y entidades que coordinen la operación de los fideicomisos, mandatos o análogos públicos serán las responsables de realizar todos los actos necesarios que permitan llevar a cabo la extinción o terminación de éstos, entre otros, por lo que se refiere a los activos y pasivos con los que cuente, en términos de la Ley Federal de Presupuesto y Responsabilidad Hacendaria y su\nReglamento.\nSéptimo. El Consejo Nacional de Ciencia y Tecnología, así como los Centros Públicos de Investigación llevarán a cabo las acciones necesarias para que los fideicomisos constituidos al amparo de la Ley de Ciencia y Tecnología, se ajusten a lo dispuesto en la Ley Federal de Presupuesto y Responsabilidad Hacendaria y su Reglamento, y en consecuencia concentren en la Tesorería de la Federación, en términos de la Ley de Ingresos de la Federación para el ejercicio fiscal que corresponda, la totalidad de los recursos públicos federales que formen parte del patrimonio de dichos fideicomisos, en términos de las disposiciones aplicables, en la fecha que determine la Secretaría de Hacienda y Crédito\nPúblico en conjunto con el Consejo Nacional de Ciencia y Tecnología, sin que la misma rebase el 30 de junio de 2021. Por lo que a partir de la entrada en vigor del presente Decreto no podrán adquirir compromisos adicionales con cargo al patrimonio de dichos instrumentos.\nAsimismo, deberán concentrar en sus tesorerías los recursos distintos a los señalados en el primer párrafo del presente Transitorio en el plazo previsto en el mismo.\nEl Consejo Nacional de Ciencia y Tecnología y los Centros Públicos de Investigación deberán coordinarse con las instituciones que fungen como fiduciarias para llevar a cabo los actos y procesos necesarios para extinguir los fideicomisos públicos constituidos al amparo de la Ley de Ciencia y Tecnología, con la finalidad de que durante el ejercicio fiscal de 2021 se suscriban los convenios de extinción en términos de las disposiciones aplicables.\nLos fideicomisos públicos constituidos por Centros Públicos de Investigación para el cumplimiento exclusivo de obligaciones de carácter laboral o en materia de seguridad social continuarán operando con la finalidad de salvaguardar los derechos laborales de los trabajadores.\ndistinta naturaleza en un solo instrumento, deberán llevar a cabo la modificación a los mismos dentro de un plazo de 30 días naturales contados a partir de la entrada en vigor del presente Decreto, a efecto de materia de seguridad social, y concentren los recursos no relacionados con dichos fines en términos del primer párrafo del presente Transitorio.\ncorrespondiente, de conformidad con lo dispuesto por el último párrafo del transitorio Cuarto de este\nDecreto.\nA la entrada en vigor del presente Decreto, los fondos Sectorial CONACYT-Secretaría de Energía-\nHidrocarburos; Sectorial CONACYT-Secretaría de Energía-Sustentabilidad Energética, y de Investigación\nCientífica y Desarrollo Tecnológico del Instituto Mexicano del Petróleo, no podrán contraer obligaciones adicionales con cargo a sus respectivos patrimonios.\nLos recursos a que se refiere el artículo 88 de la Ley Federal de Presupuesto y Responsabilidad\nHacendaria, que se reforma por virtud del presente Decreto, se podrán destinar a cubrir los pagos derivados de los compromisos adquiridos por los fondos a que se refiere el párrafo anterior, previo a la entrada en vigor de este Decreto.\nOctavo. El Consejo Nacional de Ciencia y Tecnología, deberá llevar a cabo las acciones que correspondan para que a partir de la entrada en vigor del presente Decreto no se adquieran compromisos adicionales con cargo al patrimonio del fideicomiso público denominado Fondo para el Fomento y Apoyo a la Investigación Científica y Tecnológica en Bioseguridad y Biotecnología, y se concentren en la Tesorería de la Federación, en términos de la Ley de Ingresos de la Federación para el ejercicio fiscal que corresponda, la totalidad de los recursos públicos federales que formen parte del patrimonio del mismo en la fecha que determine la Secretaría de Hacienda y Crédito Público en conjunto con el Consejo\nNacional de Ciencia y Tecnología, sin que la misma rebase el 30 de junio de 2021. Cumplido lo anterior, el fideicomiso deberá extinguirse durante el ejercicio fiscal de 2021.\nLos ingresos excedentes que se concentren en la Tesorería de la Federación al amparo del presente\nTransitorio se destinarán en términos de la Ley de Ingresos de la Federación para el ejercicio fiscal correspondiente, de conformidad con lo dispuesto por el último párrafo del Artículo Cuarto Transitorio de este Decreto.\nNoveno. Se deroga el transitorio Tercero del Decreto por el que se reforman, adicionan y derogan diversas disposiciones de la Ley Aduanera, publicado en el Diario Oficial de la Federación el 1o. de enero de 2002.\nDécimo. La Comisión Nacional de Cultura Física y Deporte realizará las acciones conducentes para el otorgamiento de un reconocimiento económico vitalicio a los deportistas que en representación oficial obtengan o hayan obtenido una o más medallas en Juegos Olímpicos o Paralímpicos, con cargo a su presupuesto autorizado, para lo cual el Reglamento de la Ley General de Cultura Física y Deporte establecerá los criterios y bases para el otorgamiento de dicho reconocimiento.\nDécimo Primero. Dentro de un plazo de ciento ochenta días naturales, el Ejecutivo Federal deberá reformar los Reglamentos de las leyes que se reforman por virtud de la entrada en vigor del presente\nDecreto, en lo que resulte conducente.\nDécimo Segundo. La Secretaría de Gobernación, con cargo a su presupuesto autorizado, asumirá\nTrabajadores Migratorios Mexicanos, hasta su total cumplimiento.\nDécimo Tercero. Los recursos que integran el patrimonio de los fideicomisos públicos denominados lo dispuesto en el transitorio Cuarto del presente Decreto. Los recursos aportados deberán ser destinados, en primer término, al Programa de Mejoramiento Urbano a cargo de la Secretaría de Desarrollo Agrario, Territorial y Urbano.\nDécimo Cuarto. Los recursos que integran el patrimonio del fideicomiso público denominado Fondo recursos obtenidos previo al ejercicio fiscal 2019. Por lo que se refiere a los recursos obtenidos durante el ejercicio fiscal 2019 se estará a lo dispuesto por la autoridad jurisdiccional competente y, en caso de resultar procedente se sujetarán a dicho Transitorio.\nUna vez realizado lo anterior, la Secretaría de Economía por conducto de la unidad responsable de dicho fideicomiso público en conjunto con la institución fiduciaria procederán en términos de lo señalado en el transitorio Quinto.\nDécimo Quinto. A la entrada en vigor del presente Decreto, el Fideicomiso para promover el acceso al financiamiento de MIPYMES y Emprendedores no podrá contraer obligaciones adicionales con cargo a su patrimonio, sin embargo, continuará cumpliendo con los compromisos derivados de los instrumentos de garantía contratados, conforme a las disposiciones aplicables, para el cumplimiento de sus fines.\nUna vez cumplidas la totalidad de las obligaciones y se ejerzan los derechos derivados de los instrumentos a que se refiere el párrafo anterior, el Fideicomiso para promover el acceso al financiamiento de MIPYMES y Emprendedores se extinguirá en términos de las disposiciones aplicables.\nA la extinción de dicho vehículo, la Secretaría de Economía por conducto de la unidad responsable, realizará las acciones necesarias para concentrar los recursos federales remanentes en la Tesorería de la Federación.\nLos ingresos excedentes que se concentren en la Tesorería de la Federación al amparo del presente\nTransitorio se destinarán en términos de la Ley de Ingresos de la Federación para el ejercicio fiscal correspondiente.\nDécimo Sexto. La Secretaría de Hacienda y Crédito Público, en su carácter de mandante en el contrato de Mandato para la Administración de los Recursos del Programa de Cooperación Energética para Países de Centroamérica y el Caribe, deberá coordinarse con la institución que funja con el carácter de mandataria para llevar a cabo las acciones necesarias para formalizar la terminación de dicho instrumento en términos del transitorio Quinto del presente Decreto. De igual forma, por conducto de la unidad responsable del mandato, deberá coordinar las acciones que correspondan para que concentre los recursos públicos federales en la Tesorería de la Federación, de conformidad con lo dispuesto en el transitorio Cuarto del presente Decreto.\nAsimismo, la unidad responsable del Mandato deberá llevar a cabo las acciones conducentes para efectuar la recuperación de los créditos que, en su caso, se hubiesen otorgado con cargo a los recursos del Mandato a que se refiere el presente transitorio, a efecto de que dichos recursos sean concentrados en Tesorería de la Federación, en los términos previstos en el transitorio Cuarto del presente Decreto.\nDécimo Séptimo. A partir de la entrada en vigor del presente Decreto, los ejecutores de gasto no podrán comprometer recursos públicos con cargo a los fideicomisos sin estructura orgánica, mandatos o análogos públicos, a que se refieren las disposiciones que se reforman o derogan por virtud de este\nDecreto y de sus disposiciones transitorias.\nDécimo Octavo. Los recursos que integran el patrimonio del Fondo a que se refiere el segundo párrafo del artículo 22 de la Ley Orgánica de la Financiera Nacional de Desarrollo Agropecuario, Rural, su patrimonio, salvo el monto que, en su caso, la Secretaría de Hacienda y Crédito Público determine se reintegre a la Tesorería de la Federación. Asimismo, la Financiera, en conjunto con la institución crediticia del citado Fondo, procederá en términos de lo señalado en los transitorios Cuarto y Quinto del presente\nDecreto.\nDécimo Noveno. Se deroga el transitorio Noveno del Decreto por el que se expide la Ley General de A partir del 1o. de enero de 2021, el Fideicomiso Fondo de Desastres Naturales no asumirá compromisos adicionales a los adquiridos previamente, salvo los relativos a los gastos de operación, y únicamente podrán llevarse a cabo los actos tendientes a su extinción. Con los recursos a que se refiere el artículo 37 de la Ley Federal de Presupuesto y Responsabilidad Hacendaria se podrán cubrir las obligaciones que se tengan pendientes y que no se paguen con cargo al patrimonio del Fideicomiso.\nLos remanentes de recursos de este Fideicomiso se deberán concentrar a más tardar el 30 de junio de 2021, por concepto de aprovechamientos, a la Tesorería de la Federación y se destinarán por la Secretaría de Hacienda y Crédito Público para la atención de desastres naturales, así como para cubrir las obligaciones pendientes y que no se paguen con cargo al patrimonio del Fideicomiso.\nVigésimo. Se faculta a la SHCP, para que en coordinación con la Fiduciaria establecida por la Ley del FIPAGO, en su caso, realice los convenios, acuerdos, y todos los actos jurídicos que sean necesarios, para dar cumplimiento a las obligaciones contraídas y convenios en proceso de formalización al 20 de septiembre de 2020. Asimismo, se faculta a la SHCP para realizar los convenios, acuerdos, y todos los actos jurídicos que se requieran, en coordinación con las Entidades Federativas en las que se localizan las citadas cajas de ahorro, para dar cumplimiento a las obligaciones contraídas y convenios en proceso de formalización que hayan sido reportados por la SHCP.\nCiudad de México, a 20 de octubre de 2020.- Dip. Dulce María Sauri Riancho, Presidenta.- Sen.\nOscar Eduardo Ramírez Aguilar, Presidente.- Dip. María Guadalupe Díaz Avilez, Secretaria.- Sen.\nLilia Margarita Valdez Martínez, Secretaria.- Rúbricas.\"\nEn cumplimiento de lo dispuesto por la fracción I del Artículo 89 de la Constitución Política de los Estados Unidos Mexicanos, y para su debida publicación y observancia, expido el presente Decreto en la Residencia del Poder Ejecutivo Federal, en la Ciudad de México, a 4 de noviembre de 2020.- Andrés\nManuel López Obrador.- Rúbrica.- La Secretaria de Gobernación, Dra. Olga María del Carmen\nSánchez Cordero Dávila.- Rúbrica.\nHidrocarburos.\nArtículo Único. Se reforman los artículos 51; 53, párrafo segundo; 56, fracción XI, y 57, y se adicionan una fracción III al artículo 51, una fracción XII, pasando la actual fracción XII a ser fracción XIII, al artículo 56; el artículo 59 Bis, y un párrafo segundo a la fracción II del artículo 86, de la Ley de Hidrocarburos, para quedar como sigue:\n……….\nTransitorios\nPrimero. El presente Decreto entrará en vigor el día siguiente al de su publicación en el Diario Oficial de la Federación.\nSegundo. Se derogan todas aquellas disposiciones que se opongan a lo dispuesto en el presente\nDecreto.\nTercero. Todos aquellos permisionarios que pudieran ser perjudicados en su esfera jurídica y sus derechos, podrán solicitar en el marco de la normatividad de la materia correspondiente, el pago de las afectaciones correspondientes.\nCuarto. La autoridad competente procederá a la revocación de aquellos permisos que, a la fecha de entrada en vigor del presente Decreto, incumplan con el requisito de almacenamiento determinado por la Secretaría de Energía conforme a las disposiciones jurídicas aplicables.\nQuinto. La autoridad competente privará de efectos jurídicos a los permisos que hayan caducado en términos de lo dispuesto en el artículo 55, fracción I, incisos a) y b) de la Ley de Hidrocarburos.\nSexto. A la entrada en vigor del presente Decreto se revocarán los permisos respecto de los cuales se compruebe que sus titulares no cumplen con los requisitos correspondientes o que infrinjan las disposiciones de la Ley de Hidrocarburos.\nSéptimo. A la entrada en vigor del presente Decreto, la Comisión Reguladora de Energía y el Servicio de Administración Tributaria, en el ámbito de sus respectivas competencias, llevarán a cabo los actos conducentes para verificar el cumplimiento de las disposiciones aplicables en materia de medición de hidrocarburos, petrolíferos y petroquímicos, de conformidad con lo previsto en las disposiciones jurídicas correspondientes.\nCiudad de México, a 22 de abril de 2021.- Dip. Dulce María Sauri Riancho, Presidenta.- Sen. Oscar\nEduardo Ramírez Aguilar, Presidente.- Dip. Mónica Bautista Rodríguez, Secretaria.- Sen. Lilia\nMargarita Valdez Martínez, Secretaria.- Rúbricas.\"\nEn cumplimiento de lo dispuesto por la fracción I del Artículo 89 de la Constitución Política de los Estados Unidos Mexicanos, y para su debida publicación y observancia, expido el presente Decreto en la López Obrador.- Rúbrica.- La Secretaria de Gobernación, Dra. Olga María del Carmen Sánchez\nCordero Dávila.- Rúbrica.\nArtículo Único.- Se reforma el Artículo Décimo Tercero Transitorio de la Ley de Hidrocarburos, publicada en el Diario Oficial de la Federación el 11 de agosto de 2014, para quedar como sigue:\n……..\nTransitorios\nPrimero. El presente Decreto entrará en vigor el día siguiente al de su publicación en el Diario Oficial de la Federación.\nSegundo. Se derogan todas las disposiciones que se opongan a lo dispuesto en este Decreto.\nTercero. En un plazo de 30 días naturales a partir de la entrada en vigor del presente Decreto, la Comisión Reguladora de Energía deberá dejar sin efectos los acuerdos, disposiciones administrativas de carácter general, resoluciones y lineamientos relacionados con la imposición de principios de regulación asimétrica a Petróleos Mexicanos y sus organismos subsidiarios, bajo la atribución concedida por la disposición transitoria que se reforma en el presente Decreto.\nCiudad de México, a 29 de abril de 2021.- Dip. Dulce María Sauri Riancho, Presidenta.- Sen. Oscar\nEduardo Ramírez Aguilar, Presidente.- Dip. Edgar Guzmán Valdez, Secretario.- Sen. Nancy de la Sierra Arámburo, Secretaria.- Rúbricas.\"\nEn cumplimiento de lo dispuesto por la fracción I del Artículo 89 de la Constitución Política de los Estados Unidos Mexicanos, y para su debida publicación y observancia, expido el presente Decreto en la Manuel López Obrador.- Rúbrica.- La Secretaria de Gobernación, Dra. Olga María del Carmen\nSánchez Cordero Dávila.- Rúbrica.\nDECRETO por el que se expide la Ley de la Fiscalía General de la República, se abroga la Ley Orgánica de la Fiscalía General de la República y se reforman, adicionan y derogan diversas disposiciones de distintos ordenamientos legales.\nArtículo Décimo Primero.- Se reforma el párrafo tercero del artículo 76 de la Ley de Hidrocarburos, para quedar como sigue:\n………\nTransitorios\nPrimero. El presente Decreto entrará en vigor al día siguiente de su publicación en el Diario Oficial de la Federación y se expide en cumplimento al artículo Décimo Tercero transitorio del Decreto por el que se expidió la Ley Orgánica de la Fiscalía General de la República.\nSegundo. Se abroga la Ley Orgánica de la Fiscalía General de la República.\nTodas las referencias normativas a la Procuraduría General de la República o del Procurador General de la República, se entenderán referidas a la Fiscalía General de la República o a su persona titular, respectivamente, en los términos de sus funciones constitucionales vigentes.\nTercero. Las designaciones, nombramientos y procesos en curso para designación, realizados de conformidad con las disposiciones constitucionales y legales, relativos a la persona titular de la Fiscalía\nGeneral de la República, las Fiscalías Especializadas, el Órgano Interno de Control y las demás personas titulares de las unidades administrativas, órganos desconcentrados y órganos que se encuentren en el ámbito de la Fiscalía General de la República, así como de las personas integrantes del Consejo\nCiudadano de la Fiscalía General de la República, continuarán vigentes por el periodo para el cual fueron designados o hasta la conclusión en el ejercicio de la función o, en su caso, hasta la terminación del proceso pendiente.\nCuarto. La persona titular de la Fiscalía General de la República contará con un término de noventa días naturales siguientes a la entrada en vigor del presente Decreto, para expedir el Estatuto orgánico de la Fiscalía General de la República y de ciento ochenta días naturales, contados a partir de la expedición de éste, para expedir el Estatuto del Servicio Profesional de Carrera.\nEn tanto se expiden los Estatutos y normatividad, continuarán aplicándose las normas y actos jurídicos que se han venido aplicando, en lo que no se opongan al presente Decreto.\nLos instrumentos jurídicos, convenios, acuerdos interinstitucionales, contratos o actos equivalentes, celebrados o emitidos por la Procuraduría General de la República o la Fiscalía General de la República se entenderán como vigentes y obligarán en sus términos a la Institución, en lo que no se opongan al presente Decreto, sin perjuicio del derecho de las partes a ratificarlos, modificarlos o rescindirlos posteriormente o, en su caso, de ser derogados o abrogados.\nQuinto. A partir de la entrada en vigor de este Decreto quedará desincorporado de la Administración pasará a ser un órgano con personalidad jurídica y patrimonio propio, que gozará de autonomía técnica y de gestión, dentro del ámbito de la Fiscalía General de la República.\ntransitar al servicio profesional de carrera.\nPara acceder al servicio profesional de carrera, el personal que deseé continuar prestando sus servicios al Instituto Nacional de Ciencias Penales deberá sujetarse al proceso de evaluación según disponga el Estatuto del Servicio Profesional de Carrera, dándose por terminada aquella relación con aquellos servidores públicos que no se sometan o no acrediten el proceso de evaluación.\nEl Instituto Nacional de Ciencias Penales deberá terminar sus relaciones laborales con sus personas trabajadoras una vez que se instale el servicio profesional de carrera, conforme al programa de liquidación del personal que autorice la Junta de Gobierno, hasta que esto no suceda, las relaciones laborales subsistirán.\nA la entrada en vigor de este Decreto, las personas integrantes de la Junta de Gobierno del Instituto\nNacional de Ciencias Penales pertenecientes a la Administración Pública Federal dejarán el cargo, y sus lugares serán ocupados por las personas que determine la persona titular de la Fiscalía General de la República.\nDentro de los sesenta días naturales siguientes a la entrada en vigor de este Decreto, la Junta de Gobierno emitirá un nuevo Estatuto orgánico y establecerá un servicio profesional de carrera, así como un programa de liquidación del personal que, por cualquier causa, no transite al servicio profesional de carrera que se instale.\nLos recursos materiales, financieros y presupuestales, incluyendo los bienes muebles, con los que cuente el Instituto a la entrada en vigor del presente Decreto, pasarán al Instituto Nacional de Ciencias\nPenales de la Fiscalía General de la República conforme al Décimo Primero Transitorio del presente\nDecreto.\nSexto. El conocimiento y resolución de los asuntos que se encuentren en trámite a la entrada en vigor del presente Decreto o que se inicien con posterioridad a éste, corresponderá a las unidades competentes, en términos de la normatividad aplicable o a aquellas que de conformidad con las atribuciones que les otorga el presente Decreto, asuman su conocimiento, hasta en tanto se expiden los Estatutos y demás normatividad derivada del presente Decreto.\nSéptimo. El personal que a la fecha de entrada en vigor del presente Decreto tenga nombramiento o Formato Único de Personal expedido por la entonces Procuraduría General de la República, conservará los derechos que haya adquirido en virtud de su calidad de persona servidora pública, con independencia de la denominación que corresponda a sus actividades o naturaleza de la plaza que ocupe. Para acceder al servicio profesional de carrera el personal que deseé continuar prestando sus servicios con la Fiscalía\nGeneral de la República deberá sujetarse al proceso de evaluación según disponga el Estatuto del servicio profesional de carrera. Se dará por terminada aquella relación con aquellas personas servidoras públicas que no se sometan o no acrediten el proceso de evaluación.\nnombramiento, de conformidad con los Lineamientos L/001/19 y L/003/19, por los que se regula la contratación del personal de transición, así como al personal adscrito a la entonces Procuraduría General de la República que continúa en la Fiscalía General de la República, así como para el personal de transición.\nOctavo. Las personas servidoras públicas que cuenten con nombramiento o Formato Único de de este Decreto y que, por cualquier causa, no transiten al servicio profesional de carrera deberán adherirse a los programas de liquidación que para tales efectos se expidan.\nNoveno. La persona titular de la Oficialía Mayor contará con el plazo de noventa días naturales para constituir el Fideicomiso denominado “Fondo para el Mejoramiento de la Procuración de Justicia” o modificar el objeto de cualquier instrumento jurídico ya existente de naturaleza igual, similar o análoga.\nDécimo. La persona titular de la Oficialía Mayor emitirá los lineamientos para la transferencia de recursos humanos, materiales, financieros o presupuestales, incluyendo los muebles, con los que cuente la Fiscalía General de la República en el momento de la entrada en vigor de este Decreto, así como para la liquidación de pasivos y demás obligaciones que se encuentren pendientes respecto de la extinción de la Procuraduría General de la República.\nQueda sin efectos el Plan Estratégico de Transición establecido en el artículo Noveno transitorio de la Ley Orgánica de la Fiscalía General de la República que se abroga a través del presente Decreto.\nDécimo Primero. Los bienes inmuebles que sean propiedad de la Fiscalía General de la República, o de los órganos que se encuentren dentro su ámbito o de la Federación que, a la fecha de entrada en vigor del presente Decreto se encuentren dados en asignación o destino a la Fiscalía General de la República, pasarán a formar parte de su patrimonio.\nLos bienes muebles y demás recursos materiales, financieros o presupuestales, que hayan sido asignados o destinados, a la Fiscalía General de la República pasarán a formar parte de su patrimonio a la entrada en vigor del presente Decreto.\nDécimo Segundo. La persona titular de la Fiscalía General de la República contará con un plazo de un año a partir de la publicación del presente Decreto para emitir el Plan Estratégico de Procuración de Justicia de la Fiscalía General de la República, con el que se conducirá la labor sustantiva de la Institución conforme a la obligación a que refiere el artículo 88 del presente Decreto. Mismo que deberá ser presentado por la persona titular de la Fiscalía General de la República en términos del párrafo tercero del artículo 88 del presente Decreto.\nEl Plan Estratégico de Procuración de Justicia se presentará ante el Senado de la República, durante el segundo periodo ordinario de sesiones, en su caso, seis meses después de la entrada en vigor del presente Decreto.\nPara la emisión del Plan Estratégico de Procuración de Justicia, la Fiscalía General de la República contará con la opinión del Consejo Ciudadano. La falta de instalación de dicho Consejo Ciudadano no impedirá la presentación del Plan Estratégico de Procuración de Justicia.\nDécimo Tercero. Las unidades administrativas de la Fiscalía General de la República que a la fecha de entrada en vigor del presente Decreto se encargan de los procedimientos relativos a las responsabilidades administrativas de las personas servidoras públicas de la Fiscalía General de la República, tendrán el plazo de noventa días naturales para remitirlos al Órgano Interno de Control, para que se encargue de su conocimiento y resolución, atendiendo a la competencia que se prevé en el presente Decreto.\nDécimo Cuarto. Por lo que hace a la fiscalización del Instituto Nacional de Ciencias Penales, corresponderá al Órgano Interno de Control de la Fiscalía General de la República, a la entrada en vigor del presente Decreto, sin perjuicio de las atribuciones que correspondan a la Auditoría Superior de la Federación.\nLos expedientes iniciados y pendientes de trámite a la entrada en vigor del presente Decreto, serán resueltos por la Secretaría de la Función Pública.\nPor cuanto hace a la estructura orgánica, así como a los recursos materiales, financieros o presupuestales del Órgano Interno de Control en el Instituto Nacional de Ciencias Penales, pasarán al Órgano Interno de Control de la Fiscalía General de la República.\nDécimo Quinto. Los bienes que hayan sido asegurados por la Procuraduría General de la República o Fiscalía General de la República, con anterioridad a la entrada en vigor de este Decreto, que sean susceptibles de administración o se determine su destino legal, se pondrán a disposición del Instituto para Devolver al Pueblo lo Robado, conforme a la legislación aplicable.\nDécimo Sexto. Quedan derogadas todas las disposiciones que se opongan a este Decreto.\nCiudad de México, a 29 de abril de 2021.- Dip. Dulce María Sauri Riancho, Presidenta.- Sen. Oscar\nEduardo Ramírez Aguilar, Presidente.- Dip. Lizbeth Mata Lozano, Secretaria.- Sen. María Merced\nGonzález González, Secretaria.- Rúbricas.\"\nEn cumplimiento de lo dispuesto por la fracción I del Artículo 89 de la Constitución Política de los Estados Unidos Mexicanos, y para su debida publicación y observancia, expido el presente Decreto en la Manuel López Obrador.- Rúbrica.- La Secretaria de Gobernación, Dra. Olga María del Carmen\nSánchez Cordero Dávila.- Rúbrica.",
  "ordenamiento": "LEYES FEDERALES",
  "jurisdiccion": "ESTADO DE MÉXICO",
  "fuente_oficial": "DIARIO OFICIAL DE LA FEDERACION",
  "status": "Vigente",
  "Fecha de Publicación": "11 de agosto de 2014",
  "Última Reforma Publicada": "20-05-2021",
  "es_escaneado": false,
  "tiene_tablas": false,
  "url": "https://www.gob.mx/cms/uploads/attachment/file/724497/Ley_de_Hidrocarburos_20-05-2021.pdf",
  "materia": [
    "energético",
    "recursos naturales"
  ]
}