{
  "titulo": "Acuerdo 087se18 12 2009, Mediante el Que Se Aprueban los Lineamientos A los Que Se Debe Ajustar el P",
  "Contenido": "PARA LLEVAR A CABO LA EVALUACIÓN DEL\nDESEMPEÑO DE LOS PRESIDENTES Y\nCONSEJEROS ELECTORALES DE LOS CONSEJOS\nDISTRITALES, ASÍ COMO EL FORMATO\nRELATIVO A DICHA EVALUACIÓN\nTEXTO ORIGINAL\nLineamientos publicado en el Periódico Oficial del Gobierno del Estado No. 6, el\nMartes 19 de Enero de 2010.\nACUERDO 087/SE/18-12-2009, MEDIANTE EL QUE SE APRUEBAN LOS\nLINEAMIENTOS A LOS QUE SE DEBE AJUSTAR EL PROCEDIMIENTO PARA\nLLEVAR A CABO LA EVALUACIÓN DEL DESEMPEÑO DE LOS PRESIDENTES Y\nCONSEJEROS ELECTORALES DE LOS CONSEJOS DISTRITALES, ASÍ COMO EL\nFORMATO RELATIVO A DICHA EVALUACIÓN.\nAL MARGEN UN SELLO CON EL ESTADO DE GUERRERO Y UNA LEYENDA\nQUE DICE: \"INSTITUTO ELECTORAL\":\nI. De conformidad con lo que establece el artículo 25 párrafos segundo y quinto las elecciones es una función estatal, que se realiza a través de un organismo público autónomo, de carácter permanente, denominado Instituto Electoral del Estado de\nGuerrero, dotado de personalidad jurídica y patrimonio propios, en cuya integración concurren los partidos políticos, coaliciones y los ciudadanos, en los términos que ordene la Ley. En el ejercicio de esta función estatal, la certeza, legalidad, independencia, imparcialidad y objetividad serán principios rectores. El Instituto Electoral será autoridad en la materia, autónomo en su funcionamiento e independiente en sus decisiones, contará en su estructura con consejos distritales; de igual manera, contará con órganos de vigilancia.\nII. En congruencia con el artículo 25 de la Constitución Local, el diverso 86 de la\nLey de Instituciones y Procedimientos Electorales del Estado de Guerrero, refiere que el\nInstituto Electoral, es un Organismo Público Autónomo, de carácter permanente, independiente en sus decisiones y funcionamiento, con personalidad jurídica y patrimonio\nPARA LLEVAR A CABO LA EVALUACIÓN DEL\nDESEMPEÑO DE LOS PRESIDENTES Y\nCONSEJEROS ELECTORALES DE LOS CONSEJOS\nDISTRITALES, ASÍ COMO EL FORMATO\nRELATIVO A DICHA EVALUACIÓN propios, responsable de vigilar el cumplimiento de las disposiciones constitucionales y reglamentarias en materia electoral; así como de velar porque los principios de certeza, legalidad, independencia, imparcialidad y objetividad, guíen las actividades de los organismos electorales; encargado de coordinar, preparar, desarrollar y vigilar los procesos electorales estatales y municipales, ordinarios y extraordinarios, en los términos de la legislación aplicable.\nIII. Que en términos de lo que establece el artículo 85 de la Ley Electoral vigente, los fines del Instituto Electoral son, entre otros, asegurar a los ciudadanos el ejercicio de los derechos políticos-electorales y vigilar el cumplimiento de sus obligaciones; garantizar la celebración periódica y pacífica de las elecciones, para renovar a los integrantes de los\nPoderes Legislativo y Ejecutivo del Estado y de los Ayuntamientos; así como de velar por la autenticidad y efectividad del sufragio.\nIV. Que para llevar a cabo las anteriores atribuciones, el artículo 88 dispone en sus fracciones I, II, III, y IV, que el Instituto Electoral contará en su estructura con: un\nConsejo General; una Junta Estatal; Un Consejo Distrital Electoral en cada distrito electoral uninominal, que funcionará durante el proceso electoral y Mesas Directivas de\nCasilla.\nV. Que con el objeto de atender el propósito de la reforma electoral que derivó en la creación de la Ley Electoral vigente, la integración de los órganos electorales deriva de un procedimiento de selección eminentemente ciudadano, imparcial y dotado de credibilidad a través de una convocatoria que emite el Consejo General, quien realiza una evaluación de los aspirantes para integrar los Consejos Electorales Distritales, el\nPresidente de estos órganos se selecciona de entre de los Consejeros Electorales.\nVI. Que como lo refiere el artículo 126 de la Ley Electoral, en cada una de las cabeceras de los Distritos Electorales del Estado, funcionará un Consejo Distrital\nElectoral, el cual se integrará de la manera siguiente: Un Presidente, cuatro Consejeros\nElectorales, con voz y voto, designados por las dos terceras partes de votos del Consejo\nPARA LLEVAR A CABO LA EVALUACIÓN DEL\nDESEMPEÑO DE LOS PRESIDENTES Y\nCONSEJEROS ELECTORALES DE LOS CONSEJOS\nDISTRITALES, ASÍ COMO EL FORMATO\nRELATIVO A DICHA EVALUACIÓN\nGeneral del Instituto; un representante de cada partido político, coalición y una Secretaría\nTécnica, todos ellos con voz pero sin voto.\nVII. Que para integrar los Consejos Distritales en los términos que lo refieren los considerandos V y VI que anteceden, el Consejo General emitió el acuerdo 22/SE/15-042008 con el que aprobó la convocatoria conteniendo las bases bajo las cuales fueron electos los Consejeros Electorales Distritales que fueron nombrados en los términos que se dispuso en el acuerdo 039/SE/29-05-2008 de este Consejo General.\nVIII. Que como lo refiere el citado artículo 126 en su fracción VII párrafo tercero, los Consejeros Electorales y el Presidente durarán en su encargo dos procesos electorales ordinarios, pudiendo ser ratificados para un proceso electoral más. El\nPresidente y los consejeros electorales distritales a la conclusión del proceso electoral serán evaluados por la Junta Estatal y la Comisión de Organización Electoral y el resultado de la evaluación será enviado al Consejo General del Instituto para su resolución.\nIX. Que para cumplir con la disposición antes referida, la Comisión de\nOrganización Electoral, en reunión celebrada el día 15 de diciembre del año en curso, aprobó los Lineamientos a los que se debe ajustar el procedimiento para llevar a cabo la evaluación del desempeño de los Presidentes y Consejeros Electorales. Asimismo, en la dicha comisión y la Junta Estatal, conforme las facultades que en el ámbito de su competencia dispone la Ley de la materia.\nX. Que para el efecto de proceder en los términos que establecen las fracciones\nIII, XXIX, LXXV, del artículo 99 de la Ley Electoral, las cuales disponen que son atribuciones del Consejo General, entre otras: expedir los reglamentos interiores necesarios para el buen funcionamiento del Instituto Electoral; conocer los informes, proyectos y dictámenes de las Comisiones y resolver al respecto; dictar los acuerdos\nPARA LLEVAR A CABO LA EVALUACIÓN DEL\nDESEMPEÑO DE LOS PRESIDENTES Y\nCONSEJEROS ELECTORALES DE LOS CONSEJOS\nDISTRITALES, ASÍ COMO EL FORMATO\nRELATIVO A DICHA EVALUACIÓN\nLey; lo procedente es aprobar los lineamientos a los que se debe ajustar el procedimiento para llevar a cabo la evaluación del desempeño de los Presidentes y\nConsejeros Electorales Distritales.\nPor lo antes señalado, con fundamento en lo que establecen los artículos 25 de la\nIII, XXIX y LXXV de la Ley de Instituciones y Procedimientos Electorales del Estado, el\nConsejo General del Instituto Electoral tiene a bien expedir el siguiente:\nPRIMERO. Se aprueban los Lineamientos a los que se debe ajustar el procedimiento para llevar a cabo la evaluación del desempeño de los Presidentes y\nConsejeros Electorales de los Consejos Distritales, así como el formato que será utilizado para llevar a cabo la evaluación, mismos que se anexan al presente acuerdo y forman parte del mismo.\nSEGUNDO. Se faculta a la Comisión de Organización Electoral y a la Junta aprobados, emitiendo los dictámenes que correspondan a efecto de que en los términos electoral.\nTERCERO. Publíquese el presente acuerdo y sus anexos en el Periódico Oficial acreditados ante este Instituto Electoral en términos de lo dispuesto por el artículo 34 de la Ley del Sistema de Medios de Impugnación en Materia Electoral del Estado.\nPARA LLEVAR A CABO LA EVALUACIÓN DEL\nDESEMPEÑO DE LOS PRESIDENTES Y\nCONSEJEROS ELECTORALES DE LOS CONSEJOS\nDISTRITALES, ASÍ COMO EL FORMATO\nRELATIVO A DICHA EVALUACIÓN\nEl presente Acuerdo fue aprobado por unanimidad de votos en la Décima Sesión\nGuerrero, el día dieciocho de diciembre del año dos mil nueve.\nELECTORAL DEL ESTADO.\nLIC. CÉSAR GUSTAVO RAMOS CASTRO.\nRúbrica.\nEL SECRETARIO GENERAL.\nLIC. CARLOS ALBERTO VILLALPANDO MILIÁN.\nRúbrica.\nPARA LLEVAR A CABO LA EVALUACIÓN DEL\nDESEMPEÑO DE LOS PRESIDENTES Y\nCONSEJEROS ELECTORALES DE LOS CONSEJOS\nDISTRITALES, ASÍ COMO EL FORMATO\nRELATIVO A DICHA EVALUACIÓN\nLINEAMIENTOS A LOS QUE SE DEBE AJUSTAR EL PROCEDIMIENTO PARA\nLLEVAR A CABO LA EVALUACIÓN DEL DESEMPEÑO DE LOS PRESIDENTES Y\nCONSEJEROS ELECTORALES.\n1. Objetivo\nEstablecer los criterios y pasos para llevar a cabo la evaluación del desempeño de los integrantes de los Presidentes y Consejeros Electorales de los Consejos\nDistritales para determinar o no su ratificación.\n2. Alcance\n• Consejo General\n• Comisión de Organización Electoral\n• Comisión del Servicio Profesional Electoral\n• Junta Estatal\n• Secretaría General\n3. Generalidades\n3.1. De conformidad con lo que establece la Ley de Instituciones y\nProcedimientos Electorales en el artículo 115 fracción VI, es atribución de la Comisión de los integrantes de los Consejos Distritales, en el proceso electoral, cuya evaluación de la misma será enviado al Consejo General para su resolución, en términos de lo ordenado por el artículo 126 fracción VII, párrafo tercero de la citada Ley.\nPARA LLEVAR A CABO LA EVALUACIÓN DEL\nDESEMPEÑO DE LOS PRESIDENTES Y\nCONSEJEROS ELECTORALES DE LOS CONSEJOS\nDISTRITALES, ASÍ COMO EL FORMATO\nRELATIVO A DICHA EVALUACIÓN\n3.2. En la evaluación al desempeño y atribuciones de los Presidentes y\nConsejeros Electorales de los órganos administrativos electorales que se instalen en el proceso electoral, se tomará en consideración factores de: estándares profesionales basados en principios y perfiles de actuación, eficacia, eficiencia y trabajo en equipo, que darán los resultados globales; esta evaluación, deberá comprender los logros obtenidos durante el ejercicio de su desempeño en el órgano electoral como servidores públicos electorales distritales.\n3.3. La evaluación del desempeño se acreditará con una calificación mínima de 7 en una escala de 0 a 10. El desempeño del personal de los Consejos Distritales durante el proceso electoral que corresponda, será considerado integralmente, con base en las ponderaciones de cada uno de los factores a evaluar en la forma siguiente:\n3.3.1 Estándares profesionales basados en principios y perfiles de actuación\nPERFIL DE ÉXITO ORGANIZACIONAL\nEl servidor público se esfuerza por conocer las necesidades o\n1 Actitud de servicio requerimientos de los usuarios de un bien o servicio público y/o resolver su problemática, así como de incorporar este conocimiento en la forma de planificar sus acciones y actividades, atendiendo adecuadamente las instrucciones de sus superiores.\nPARA LLEVAR A CABO LA EVALUACIÓN DEL\nDESEMPEÑO DE LOS PRESIDENTES Y\nCONSEJEROS ELECTORALES DE LOS CONSEJOS\nDISTRITALES, ASÍ COMO EL FORMATO\nRELATIVO A DICHA EVALUACIÓN\nPERFIL DE CAPACIDAD DE GESTIÓN\nCapacidad de determinar eficazmente los objetivos, metas y prioridades de su\n2 Capacidad actividad/área/proyecto, estableciendo la\nOrganizativa acción, plazos y recursos requeridos, así como los mecanismos de control para asegurar que se cumplan.\nPERFIL DE ÉTICA PÚBLICA\nEl servidor público orienta su\nOrientación al bien comportamiento al bien de los común ciudadanos, de su comunidad y de su\n3 institución, entiende sus necesidades y trata de atenderlas de la mejor manera posible. Tiene compromiso social.\nPERFIL DE RENDICIÓN DE CUENTAS\nEl servidor público informa y presenta\nRinde cuentas cuentas claras de su trabajo, así como\n4 de la aplicación adecuada y oportuna de los recursos financieros a su cargo.\n3.3.2. Principios: se considerará legalidad, certeza, objetividad, imparcialidad e independencia, conforme a la interpretación siguiente:\nPARA LLEVAR A CABO LA EVALUACIÓN DEL\nDESEMPEÑO DE LOS PRESIDENTES Y\nCONSEJEROS ELECTORALES DE LOS CONSEJOS\nDISTRITALES, ASÍ COMO EL FORMATO\nRELATIVO A DICHA EVALUACIÓN\n{\"tabla_1\":{\"columnas\":[\"No.\",\"PRINCIPIOS\",\"DESCRIPTOR\"],\"filas\":[{\"columna_1\":\"5\",\"columna_2\":\"Certeza\",\"columna_3\":\"Conocimiento pleno de la función electoral,\\nveracidad y confiabilidad en los actos,\\nresultados y decisiones, por lo que son\\ncompletamente verificables.\"},{\"columna_1\":\"6\",\"columna_2\":\"Legalidad\",\"columna_3\":\"Apego estricto a las disposiciones jurídicas\\nelectorales y técnico administrativas, así\\ncomo a los principios institucionales\\nestablecidos en la constitución, la ley y demás\\nnormas aplicables en materia electoral.\"},{\"columna_1\":\"7\",\"columna_2\":\"Independencia\",\"columna_3\":\"Desempeño en actos y resoluciones sin\\npresión alguna que implicara dependencia de\\ncriterios y opiniones ajenos a los principios y\\nnormas establecidos en la constitución y la\\nley.\"},{\"columna_1\":\"8\",\"columna_2\":\"Imparcialidad\",\"columna_3\":\"Comportamiento y toma de decisiones sin\\nfavoritismos o inclinaciones de ninguna\\nespecie.\"}]}}\nPARA LLEVAR A CABO LA EVALUACIÓN DEL\nDESEMPEÑO DE LOS PRESIDENTES Y\nCONSEJEROS ELECTORALES DE LOS CONSEJOS\nDISTRITALES, ASÍ COMO EL FORMATO\nRELATIVO A DICHA EVALUACIÓN\n9 Objetividad Conocimiento pleno y aplicación de metodologías preestablecidas en los análisis y procedimientos con el fin de evitar sesgos derivados de intereses o preferencias personales y no basados en juicios o principios subjetivos.\nEstos principios que deberán ser considerados en todo momento en armonía con las ponderaciones que deban ser consideradas serán establecidos en los formatos de evaluación que serán aprobados por la Comisión de Organización Electoral.\n3.3.3. Este factor será considerado conforme a las interpretaciones siguientes:\nPERFIL DE EFICACIA\nSe evalúa a partir de los resultados concretos obtenidos en el desempeño de los Presidentes y\nConsejeros Electorales Distritales de los\n10 Eficacia programas institucionales; acuerdos del Consejo\nGeneral; instrucciones especificas, circulares y, todas aquellas disposiciones emanadas de las áreas normativas en función de la calidad y aplicación de éstos. elaboración\n3.3.4. Eficiencia: este factor será considerado conforme a la interpretación siguiente:\nPARA LLEVAR A CABO LA EVALUACIÓN DEL\nDESEMPEÑO DE LOS PRESIDENTES Y\nCONSEJEROS ELECTORALES DE LOS CONSEJOS\nDISTRITALES, ASÍ COMO EL FORMATO\nRELATIVO A DICHA EVALUACIÓN\nPERFIL DE EFICIENCIA\nEs la correspondencia entre las instrucciones giradas o el cumplimiento de los programas con\n11 Eficiencia relación al desempeño cotidiano de los\nPresidentes y Consejeros Electorales Distritales frente a las evidencias demostradas con los logros obtenidos, en función a su encargo.\n{\"tabla_2\":{\"columnas\":[\"Tiempo\",\"Entrega oportuna de los productos requeridos\"],\"filas\":[{\"columna_1\":\"Productividad\",\"columna_2\":\"Cantidad de los productos en razón de tiempo y circunstancia\\nde su elaboración\"}]}}\n3.3.5. Trabajo en equipo: Para determinar la adecuada relación laboral hacia el órgano colegiado distrital, será considerado este factor conforme a la interpretación siguiente:\nCapacidad de cooperar y colaborar con los\n12 Trabajo en equipo demás, de formar parte de un grupo y trabajar juntos para lograr objetivos comunes.\nCohesión Logra establecer una armonía al interior del\n13 órgano colegiado a partir de la identidad con los que desarrolla.\n14 fortalecer los mecanismos para la realización de las tareas.\n15 desempeño de las funciones desarrolladas en el órgano.\nPARA LLEVAR A CABO LA EVALUACIÓN DEL\nDESEMPEÑO DE LOS PRESIDENTES Y\nCONSEJEROS ELECTORALES DE LOS CONSEJOS\nDISTRITALES, ASÍ COMO EL FORMATO\nRELATIVO A DICHA EVALUACIÓN\nLos factores que deberán ser considerados serán establecidos en el formato de evaluación en que se contengan.\n3.4. Los resultados de la evaluación del desempeño deberán quedar debidamente asentados en minutas y considerandos en los dictámenes individuales que emitan la\nJunta Estatal y la Comisión de Organización Electoral; mismos que serán considerados en el dictamen final que se someta a consideración del Consejo General para su resolución, en términos de lo que establece el tercer párrafo de la fracción VII del artículo\n126 de la Ley de Instituciones y Procedimientos Electorales y con posterioridad serán dados a conocer a los interesados de manera personal y confidencial por medio de la\nSecretaría General.\n4. Lineamientos y Criterios Generales\n4.1. La Junta Estatal y la Comisión de Organización Electoral realizarán bajo un mismo formato, la evaluación del desempeño de los Presidentes y Consejeros\nElectorales correspondiente al proceso electoral en el que se haya desempeñado.\n4.2. Para efectos de la evaluación del desempeño se ponderarán por separado y basados en los principios de la materia los siguientes elementos: estándares profesionales, eficacia, eficiencia y trabajo en equipo. Estos elementos serán sumados desempeño.\n4.2.1. Para la evaluación de los elementos antes descritos se contará con el apoyo de las áreas centrales, quienes oportunamente aportarán a las Instancias evaluadoras la información de su competencia.\n4.2.2. 25% lo comprende el resultado de los estándares profesionales encaminados al cumplimiento de los principios rectores de la materia electoral.\nPARA LLEVAR A CABO LA EVALUACIÓN DEL\nDESEMPEÑO DE LOS PRESIDENTES Y\nCONSEJEROS ELECTORALES DE LOS CONSEJOS\nDISTRITALES, ASÍ COMO EL FORMATO\nRELATIVO A DICHA EVALUACIÓN\n4.2.3. 25% comprenderá el factor de eficacia para ejercer y desempeñar el cargo, susceptible de ser calificados en forma individual.\n4.2.4. 25% lo comprenderá el factor de eficiencia susceptible de ser evaluado en forma individual\n4.2.5. 25% lo comprenderá el factor trabajo en equipo, también susceptible de ser evaluado en forma individual.\n4.2.6. La participación en actividades complementarias de formación y capacitación de carácter interna será considerada de manera adicional en la evaluación del desempeño en las actividades relacionadas con el proceso electoral.\n4.3. La Junta Estatal y la Comisión de Organización Electoral ponderarán los resultados a que se refieren los puntos 4.2.2, 4.2.3, 4.2.4 y 4.2.5 de los presentes lineamientos y en base a éstos, emitirán una calificación final de la evaluación del desempeño. La calificación estará expresada en una escala de 0 a 10 incluyendo decimales. En ningún caso dicha calificación podrá ser mayor de 10, los decimales que sean.5 o mayor se convertirán en entero inmediato superior en la calificación general y definitiva.\n4.4. Los órganos evaluadores en su dictamen deberán fundar y motivar los méritos o deméritos que cada sujeto evaluado pudiera tener; lo anterior, se hará en forma individual y repercutirá en la calificación final, aumentando o disminuyendo hasta por dos puntos la calificación del sujeto evaluado, sin exceder la escala de 10.\n4.5. La Junta Estatal y la Comisión de Organización Electoral iniciarán con el proceso electoral que corresponda.\nPARA LLEVAR A CABO LA EVALUACIÓN DEL\nDESEMPEÑO DE LOS PRESIDENTES Y\nCONSEJEROS ELECTORALES DE LOS CONSEJOS\nDISTRITALES, ASÍ COMO EL FORMATO\nRELATIVO A DICHA EVALUACIÓN\n4.6. Los órganos evaluadores primeramente elaborarán un dictamen individual y con base a estos resultados elaboraran el dictamen final que será dado a conocer al\nConsejo General en la forma señalada en el punto 3.4.\n4.7. Los resultados de la evaluación del desempeño deberán notificarse a los interesados en forma personal y confidencial, dentro de los 15 días posteriores a la emisión de la resolución por el Consejo General, dicha notificación deberá contener como mínimo los datos: nombre, cargo, adscripción y el resultado de la evaluación del desempeño.\n5. Documentos aplicables y/o anexos\nNotificación de resultados de la evaluación del desempeño.\n6. Definiciones.\n6.1. Promedio General de la evaluación del rendimiento. Es el resultado de la suma de las calificaciones ponderadas asignadas por las instancias evaluadoras. (Junta\nEstatal y Comisión de Organización Electoral) en los factores de desempeño, actuación y principios con base en los indicadores definidos para cada uno de ellos.\n6.2. Actividades complementarias de formación y capacitación: corresponde a la dentro del órgano distrital electoral, situación que se corroborará con la información que proporcionen las áreas centrales del Instituto.\n7. Descripción del procedimiento.\nPARA LLEVAR A CABO LA EVALUACIÓN DEL\nDESEMPEÑO DE LOS PRESIDENTES Y\nCONSEJEROS ELECTORALES DE LOS CONSEJOS\nDISTRITALES, ASÍ COMO EL FORMATO\nRELATIVO A DICHA EVALUACIÓN\n{\"tabla_3\":{\"columnas\":[\"(sin encabezado)\",\"No\",\"(sin encabezado)\",\"ACTIVIDAD\",\"RESPONSABLE\",\"(sin encabezado)\",\"DOCUMENTACIÓN\",\"(sin encabezado)\",\"PRODUCTOS\"],\"filas\":[{\"columna_1\":\"(sin dato)\",\"columna_2\":\".\",\"columna_3\":\"(sin dato)\",\"columna_4\":\"(sin dato)\",\"columna_5\":\"(sin dato)\",\"columna_6\":\"(sin dato)\",\"columna_7\":\"EMPLEADA\",\"columna_8\":\"(sin dato)\",\"columna_9\":\"(sin dato)\"},{\"columna_1\":\"1.\",\"columna_2\":\"(sin dato)\",\"columna_3\":\"(sin dato)\",\"columna_4\":\"Analizar y evaluar el\\ndesempeño de los\\nPresidentes y\\nConsejeros\\nElectorales de los 28\\nDistritos del Estado\\nde Guerrero.\",\"columna_5\":\"Junta Estatal\\nComisión de\\nOrganización\\nElectoral\",\"columna_6\":\"Factores y formatos\\npara la evaluación a\\nPresidentes y\\nSecretarios Técnicos\\nde los Consejos\\nDistritales\",\"columna_7\":\"(sin dato)\",\"columna_8\":\"(sin dato)\",\"columna_9\":\"Llenado de los\\nformatos de la\\nevaluación\"},{\"columna_1\":\"2.\",\"columna_2\":\"(sin dato)\",\"columna_3\":\"(sin dato)\",\"columna_4\":\"La emisión de un\\ndictamen que\\ncontiene las\\ncalificaciones\\nobtenidas en forma\\nindividual.\",\"columna_5\":\"Junta Estatal\\nComisión de\\nOrganización\\nElectoral\",\"columna_6\":\"Dictámenes de las\\nInstancias\\nEvaluadores\",\"columna_7\":\"(sin dato)\",\"columna_8\":\"(sin dato)\",\"columna_9\":\"Dictamen de la\\nJunta Estatal\\nComisión de\\nOrganización\\nElectoral.\"},{\"columna_1\":\"3.\",\"columna_2\":\"(sin dato)\",\"columna_3\":\"(sin dato)\",\"columna_4\":\"Elaboración del\\ndictamen final que\\ncontiene la\\nevaluación de los\\nPresidentes y\\nConsejeros\\nElectorales de los 28\\nDistritos Electorales\\npara su envío al\\nConsejo General.\",\"columna_5\":\"Junta Estatal\\nComisión de\\nOrganización\\nElectoral\",\"columna_6\":\"Formatos de\\nevaluación\",\"columna_7\":\"(sin dato)\",\"columna_8\":\"(sin dato)\",\"columna_9\":\"Dictamen de\\nevaluación de\\nlos órganos\\nevaluadores.\"}]}}\nPARA LLEVAR A CABO LA EVALUACIÓN DEL\nDESEMPEÑO DE LOS PRESIDENTES Y\nCONSEJEROS ELECTORALES DE LOS CONSEJOS\nDISTRITALES, ASÍ COMO EL FORMATO\nRELATIVO A DICHA EVALUACIÓN\n4. El Consejo General Consejo General Dictamen de la Junta Informe al Pleno conoce, resuelve e Estatal y de la del Consejo informa al Pleno de Comisión de General los resultados de la Organización evaluación del Electoral. desempeño del personal de los\nPresidentes y\nConsejeros\nElectorales de los 28\nConsejos Distritales en el Estado de\nGuerrero a través del dictamen definitivo.\n5. El Secretario Secretario Notificaciones Acuse de recibo\nGeneral por acuerdo General del Consejo General realiza las notificaciones personalizadas de los resultados obtenidos en la evaluación del desempeño en forma personal y confidencial.\nPARA LLEVAR A CABO LA EVALUACIÓN DEL\nDESEMPEÑO DE LOS PRESIDENTES Y\nCONSEJEROS ELECTORALES DE LOS CONSEJOS\nDISTRITALES, ASÍ COMO EL FORMATO\nRELATIVO A DICHA EVALUACIÓN\n{\"tabla_4\":{\"columnas\":[\"6.\",\"La Dirección\\nEjecutiva de\\nAdministración y del\\nServicio Profesional\\nElectoral, recibe los\\nacuses de las\\nnotificaciones y los\\nintegra a los\\nexpedientes del\\npersonal que\\nintegraron los 28\\nConsejos Distritales\\nElectorales en la\\npróxima pasada\\nelección.\",\"La Dirección\\nEjecutiva de\\nAdministración y\\ndel Servicio\\nProfesional\\nElectoral\",\"Acuses de recibo\",\"Archivos\"],\"filas\":[{\"columna_1\":\"7.\",\"columna_2\":\"Fin del\\nprocedimiento.\",\"columna_3\":\"(sin dato)\",\"columna_4\":\"(sin dato)\",\"columna_5\":\"(sin dato)\"}]}}\nPARA LLEVAR A CABO LA EVALUACIÓN DEL\nDESEMPEÑO DE LOS PRESIDENTES Y\nCONSEJEROS ELECTORALES DE LOS CONSEJOS\nDISTRITALES, ASÍ COMO EL FORMATO\nRELATIVO A DICHA EVALUACIÓN\nINSTITUTO ELECTORAL DEL ESTADO DE GUERRERO\nPARA LLEVAR A CABO LA EVALUACIÓN DEL\nDESEMPEÑO DE LOS PRESIDENTES Y\nCONSEJEROS ELECTORALES DE LOS CONSEJOS\nDISTRITALES, ASÍ COMO EL FORMATO\nRELATIVO A DICHA EVALUACIÓN\nINSTITUTO ELECTORAL DEL ESTADO DE GUERRERO\nComisión de Organización Electoral\nEJERCICIO 2010 ò 2011\nDESGLOSE DE CALIFICACIONES\nNOMBRE:\nPUESTO:\nADSCRIPCIÓN:",
  "ordenamiento": "LINEAMIENTO",
  "jurisdiccion": "GUERRERO",
  "fuente_oficial": "DIARIO OFICIAL DE LA FEDERACION",
  "Fecha de Publicación": "19 de Enero de 2010",
  "ULTIMA REFORMA PUBLICADA": null,
  "status": "VIGENTE",
  "es_escaneado": false,
  "tiene_tablas": true,
  "materia": [
    "general"
  ]
}