{
  "titulo": "Acuerdo 031SE10 10 2014, Mediante el Cual Se Aprueban los Lineamientos de Candidaturas Independiente",
  "Contenido": "OBSERVAR LOS CIUDADANOS INTERESADOS EN\nPARTICIPAR COMO CANDIDATOS INDEPENDIENTES\nEN EL PROCESO ELECTORAL ORDINARIO DE\nGOBERNADOR, DIPUTADOS Y AYUNTAMIENTOS\n2014-2015\nTEXTO ORIGINAL.\nAcuerdo Publicado en el Periódico Oficial del Gobierno del Estado No. 95, el Viernes 28 de\nNoviembre de 2014.\nINSTITUTO ELECTORAL Y DE PARTICIPACION CIUDADANA DEL ESTADO DE GUERRERO\nAL MARGEN UN SELLO CON EL ESTADO DE GUERRERO Y UNA LEYENDA QUE DICE:\n\"INSTITUTO ELECTORAL\":\nINSTITUTO ELECTORAL Y DE PARTICIPACIÓN CIUDADANA DEL ESTADO\nACUERDO 031/SE/10-10-2014\nMEDIANTE EL CUAL SE APRUEBAN LOS LINEAMIENTOS DE CANDIDATURAS INDEPENDIENTES,\nQUE DEBERÁN OBSERVAR LOS CIUDADANOS INTERESADOS EN PARTICIPAR COMO\nCANDIDATOS INDEPENDIENTES EN EL PROCESO ELECTORAL ORDINARIO DE GOBERNADOR,\nDIPUTADOS Y AYUNTAMIENTOS 2014-2015.\n1. Con fecha 09 de agosto del 2012, se publicó en el Diario Oficial de la Federación, la reforma al artículo 35 fracción II de la Constitución Política de los Estados Unidos Mexicanos, para introducir el derecho de los ciudadanos a registrar candidaturas de forma independiente.\n2. Con fecha 10 de febrero del 2014, se publicó en el Diario Oficial de la Federación, el Decreto mediante el cual se reforman, adicionan y derogan diversas disposiciones de la Constitución Política de los Estados Unidos Mexicanos, en materia político - electoral. de fecha 15 de mayo del 2014, la cual abroga el Código Federal de Instituciones y Procedimientos\nLey número 483 de Instituciones y Procedimientos Electorales del Estado de Guerrero, abrogando la que\nOBSERVAR LOS CIUDADANOS INTERESADOS EN\nPARTICIPAR COMO CANDIDATOS INDEPENDIENTES\nEN EL PROCESO ELECTORAL ORDINARIO DE\nGOBERNADOR, DIPUTADOS Y AYUNTAMIENTOS\n2014-2015 se encontraba en vigor expedida mediante Decreto 571, publicada el 01 de enero del 2008 en el\nPeriódico Oficial del Gobierno del Estado, y\nQue de conformidad con el artículo 98, párrafos 1 y 2 de la Ley General de Instituciones y\nProcedimientos Electorales, los Organismos Públicos Locales, como lo es este Instituto Electoral y de\nParticipación Ciudadana del Estado de Guerrero, están dotados de personalidad jurídica y patrimonio propio; gozarán de autonomía en su funcionamiento e independencia en sus decisiones, en los términos previstos en la Constitución, la Ley en cita, las constituciones y leyes locales; serán profesionales en su desempeño; se regirán por los principios de certeza, imparcialidad, independencia, legalidad, máxima publicidad y objetividad; y son autoridad en la materia electoral, en los términos que establece la correspondientes.\nQue de acuerdo a lo establecido por los artículos 124 de la Constitución Política Local y 86 de la\nLey de Instituciones y Procedimientos Electorales del Estado, el Instituto Electoral y de Participación\nCiudadana del Estado de Guerrero, es un organismo público autónomo, de carácter permanente, independiente en sus decisiones y funcionamiento, con personalidad jurídica y patrimonio propio, responsable de vigilar el cumplimiento de las disposiciones constitucionales y reglamentarias en materia electoral; así como de velar porque los principios de certeza, legalidad, independencia, imparcialidad y objetividad, guíen las actividades de los organismos electorales; encargado de coordinar, preparar, desarrollar y vigilar los procesos electorales estatales y municipales, ordinarios y extraordinarios, en los términos de la legislación aplicable.\nQue en atención a lo establecido por los artículos 35 fracción II de la Constitución Política de los\nEstados Unidos Mexicanos y 19 fracción II de la Constitución Política Local, es derecho de los mexicanos poder ser votados para todos los cargos de elección popular, teniendo las calidades que establezca la\nLey; y el derecho de los ciudadanos guerrerenses de ser votados para los cargos de representación popular, a través de candidaturas de partido o independientes, en los términos dispuestos en la Ley.\nQue ante la proximidad del inicio del proceso electoral 2014-2015 para elegir gobernador, diputados y ayuntamientos, es necesario que este órgano electoral emita los lineamientos que contengan las disposiciones relativas al registro de los candidatos independientes.\nQue corresponde al Instituto Electoral del Estado, de acuerdo a lo establecido en el artículo 177 de la Ley de Instituciones y Procedimientos Electorales del Estado, aplicar las disposiciones generales, reglas, lineamientos, criterios y formatos, que en ejercicio de sus facultades le confiere la Constitución\nOBSERVAR LOS CIUDADANOS INTERESADOS EN\nPARTICIPAR COMO CANDIDATOS INDEPENDIENTES\nEN EL PROCESO ELECTORAL ORDINARIO DE\nGOBERNADOR, DIPUTADOS Y AYUNTAMIENTOS\n2014-2015\nFederal y Local, las leyes generales Electoral y de Partidos Políticos, la Ley electoral local y el Instituto\nNacional;\nQue por lo anterior, entendiendo a la emisión de lineamientos como un acto administrativo que deriva de una ley u ordenamiento que determina las bases de una actividad o proceso, el Consejo\nGeneral ha determinado emitir los\nLINEAMIENTOS PARA EL REGISTRO DE ASPIRANTES Y CANDIDATOS INDEPENDIENTES A LOS\nCARGOS DE GOBERNADOR, DIPUTADOS DE MAYORÍA RELATIVA Y AYUNTAMIENTOS DEL\nESTADO DE GUERRERO PARA EL PROCESO ELECTORAL 2014 - 2015\nTÍTULO PRIMERO\nDE LAS CANDIDATURAS INDEPENDIENTES\nCAPÍTULO ÚNICO\nDISPOSICIONES GENERALES\n1. Los presentes lineamientos tienen por objeto establecer las reglas del procedimiento de registro que deben seguir los ciudadanos que deseen participar como candidatos independientes a los cargos de elección para Gobernador, fórmulas de diputados por el principio de mayoría relativa y miembros de ayuntamientos, de conformidad a lo establecido en el artículo 23 de la Ley de Instituciones y\nProcedimientos Electorales del Estado de Guerrero, así como reglamentar los actos que para cumplir con los requisitos de Ley deban realizar dichos ciudadanos.\n2. Para los efectos de estos Lineamientos, se entiende por:\nII. Ley Electoral: La Ley de Instituciones y Procedimientos Electorales del Estado de Guerrero.\nIII. Lineamientos: Los Lineamientos para el registro de aspirantes y candidatos independientes a los cargos de Gobernador, Diputados de Mayoría Relativa y Ayuntamientos del Estado de Guerrero.\nIV. Instituto: El Instituto Electoral y de Participación Ciudadana del Estado de Guerrero.\nV. Consejo General: El Consejo General del Instituto Electoral y de Participación Ciudadana del\nEstado de Guerrero.\nOBSERVAR LOS CIUDADANOS INTERESADOS EN\nPARTICIPAR COMO CANDIDATOS INDEPENDIENTES\nEN EL PROCESO ELECTORAL ORDINARIO DE\nGOBERNADOR, DIPUTADOS Y AYUNTAMIENTOS\n2014-2015\nVI. Secretario: El Secretario Ejecutivo del Instituto Electoral y de Participación Ciudadana del\nEstado de Guerrero.\nVII. Comisión de Fiscalización: La Comisión de Fiscalización del Instituto Electoral y de\nParticipación Ciudadana del Estado de Guerrero.\nVIII. Dirección Ejecutiva: La Dirección Ejecutiva de Prerrogativas y Partidos Políticos del\nInstituto Electoral y de Participación Ciudadana del Estado de Guerrero.\nIX. Aspirantes a Candidatos Independientes: Los ciudadanos que inicien los trámites correspondientes para obtener su registro como candidatos independientes a los cargos de elección popular para Gobernador, fórmulas de diputados por el principio de mayoría relativa y miembros de ayuntamientos.\nX. Candidatos Independientes: Los ciudadanos que cuenten con registro otorgado por los consejos correspondientes del Instituto Electoral y de Participación Ciudadana del Estado de Guerrero para participar como candidatos independientes a los cargos de elección popular de Gobernador, fórmulas de diputados por el principio de mayoría relativa y miembros de ayuntamientos.\nXI. Actos Tendentes a Recabar el Apoyo Ciudadano: Conjunto de reuniones públicas, asambleas, marchas y todas aquellas actividades dirigidas a la ciudadanía en general, que realizan los aspirantes con el objeto de obtener el apoyo ciudadano para satisfacer el requisito en términos de la Ley\nElectoral.\nXII. Campaña Electoral: Conjunto de actividades llevadas a cabo por los candidatos independientes registrados, para la obtención del voto.\nXIII. Actos de Campaña: Las reuniones públicas, asambleas, marchas y todos aquellos actos en que los candidatos independientes se dirijan al electorado para promover sus candidaturas.\n3. La interpretación de los presentes lineamientos, se hará conforme a los criterios gramatical, sistemático y funcional, de acuerdo con lo dispuesto en el párrafo segundo del artículo 4 de la Ley\nElectoral.\n4. En lo no previsto en los presentes Lineamientos, se estará a lo dispuesto en la Ley Electoral, el Reglamento Interno del Instituto Electoral y demás Reglamentos en la materia.\nOBSERVAR LOS CIUDADANOS INTERESADOS EN\nPARTICIPAR COMO CANDIDATOS INDEPENDIENTES\nEN EL PROCESO ELECTORAL ORDINARIO DE\nGOBERNADOR, DIPUTADOS Y AYUNTAMIENTOS\n2014-2015\nTÍTULO SEGUNDO\nDEL PROCESO DE SELECCIÓN DE\nCANDIDATOS INDEPENDIENTES\nCAPÍTULO I\nDE LA CONVOCATORIA\n5. A más tardar en el mes de noviembre del dos mil catorce, el Consejo General aprobará la convocatoria para todos aquellos ciudadanos que estén interesados en participar en el proceso de selección de aspirantes a candidatos independientes, de conformidad con lo dispuesto en el artículo 35 de la Ley de Instituciones y Procedimientos Electorales el Estado de Guerrero.\nEl Instituto Electoral publicará, al día siguiente de su aprobación, la convocatoria para el registro de candidaturas independientes en al menos dos medios de comunicación impresos de mayor circulación en la entidad y en la página web www. iepcgro. mx del Instituto Electoral y de Participación Ciudadana del\nEstado de Guerrero.\n6. La convocatoria para las candidaturas independientes deberá contener, al menos, lo siguiente:\nI. Fecha de expedición;\nII. Órgano que la expide;\nIII. Los cargos de elección popular para los que se convoca;\nIV. Los requisitos de elegibilidad de los aspirantes establecidos en la Constitución Política Local y en la Ley Electoral;\nV. El calendario que establezca las fechas, horarios y el domicilio donde deberán presentarse las solicitudes de registro de los aspirantes;\nVI. El formato de solicitud de registro como aspirante a candidato independiente, así como la documentación que deberá anexarse a la misma;\nVII. Los requisitos y plazos para que recabar el apoyo ciudadano;\nOBSERVAR LOS CIUDADANOS INTERESADOS EN\nPARTICIPAR COMO CANDIDATOS INDEPENDIENTES\nEN EL PROCESO ELECTORAL ORDINARIO DE\nGOBERNADOR, DIPUTADOS Y AYUNTAMIENTOS\n2014-2015\nCAPÍTULO II\nDE LOS ACTOS PREVIOS AL REGISTRO\n7. Los interesados en obtener su registro como aspirantes a candidatos deberán hacerlo del conocimiento del Instituto Electoral por escrito mediante el formato previsto en estos Lineamientos, a partir del día siguiente al en que se emita la convocatoria y hasta que dé inicio el periodo para recabar el apoyo ciudadano correspondiente, conforme a las siguientes reglas:\na) Los aspirantes al cargo de Gobernador del estado, ante el Presidente o Secretario Ejecutivo de Instituto Electoral.\nb) Los aspirantes al cargo de diputado por el principio de mayoría relativa, ante el Presidente o\nSecretario del consejo distrital correspondiente.\nc) Los aspirantes a miembros de Ayuntamientos, ante el Presidente o Secretario del consejo distrital correspondiente.\n8. La solicitud de registro como aspirante a candidato independiente deberá contener como mínimo la siguiente información:\nI. Apellido paterno, materno y nombre (s);\nII. Lugar y fecha de nacimiento;\nIII. Domicilio particular;\nDe la misma manera deberá acreditar su alta ante el Sistema de Administración Tributaria y financiamiento público y privado correspondiente.\n11. La persona moral a la que se refiere el párrafo anterior deberá estar constituida con por lo menos el aspirante a candidato independiente, su representante legal y el encargado de la administración de los recurso de la candidatura independiente.\nCAPÍTULO III\nDE LA OBTENCIÓN DEL APOYO CIUDADANO\n12. A partir del día siguiente de la fecha en que obtengan la calidad de aspirantes, mediante constancia que emita y le notifique la autoridad electoral correspondiente, previo cumplimiento de los\nOBSERVAR LOS CIUDADANOS INTERESADOS EN\nPARTICIPAR COMO CANDIDATOS INDEPENDIENTES\nEN EL PROCESO ELECTORAL ORDINARIO DE\nGOBERNADOR, DIPUTADOS Y AYUNTAMIENTOS\n2014-2015 requisitos, éstos podrán realizar actos tendentes a recabar el porcentaje de apoyo ciudadano requerido por medios diversos a la radio y la televisión, siempre que los mismos no constituyan actos anticipados de campaña.\n13. Los actos tendentes a recabar el apoyo ciudadano en los procesos electorales que correspondan, se sujetarán a los plazos que establezca la convocatoria.\na) Los aspirantes a candidato independiente para el cargo de Gobernador del Estado, contarán con sesenta días.\nb) Los aspirantes a candidatos independientes para el cargo de diputado de mayoría relativa o miembro de Ayuntamiento, contarán con treinta días.\n14. La obtención de apoyo ciudadano se sujetará a lo siguiente:\nI. Para Gobernador del Estado, la cédula de respaldo deber contener cuando menos la firma de una cantidad de ciudadanos equivalente al 3% de la lista nominal de electores con corte al 31 de agosto del año previo al de la elección y estar integrada por electores de por lo menos 41 municipios, que sumen cuando menos el 3% de ciudadanos que figuren en la lista nominal de electores en cada una de ellas.\nII. Para fórmulas de diputados de mayoría relativa, la cédula de respaldo deberá contener cuando menos la firma de una cantidad de ciudadanos equivalente al 3% de la lista nominal de electores correspondiente al distrito electoral en cuestión, con corte al 31 de agosto del año previo al de la elección y estar integrada por ciudadanos de por lo menos la mitad de las secciones electorales que sumen cuando menos el 3% de ciudadanos que figuren en la lista nominal de electores en cada una de ellas.\nIII. Para miembros de Ayuntamientos, la cédula de respaldo deberá contener cuando menos la firma de una cantidad de ciudadanos equivalente al 3% de la lista nominal de electores correspondiente al municipio en cuestión, con corte al 31 de agosto del año previo al de la elección y estar integrada por ciudadanos de por lo menos la mitad de las secciones electorales que sumen cuando menos el 3% de ciudadanos que figuren en la lista nominal de electores en cada una de ellas.\n15. Los aspirantes no podrán realizar actos anticipados de campaña por ningún medio. La violación a esta disposición se sancionará con la negativa de registro como candidato independiente.\n16. Queda prohibido a los aspirantes, en todo tiempo, la contratación de propaganda o cualquier otra forma de promoción personal en radio y televisión. La violación a esta norma se sancionará con la negativa de registro como candidato independiente o, en su caso, con la cancelación de dicho registro.\nOBSERVAR LOS CIUDADANOS INTERESADOS EN\nPARTICIPAR COMO CANDIDATOS INDEPENDIENTES\nEN EL PROCESO ELECTORAL ORDINARIO DE\nGOBERNADOR, DIPUTADOS Y AYUNTAMIENTOS\n2014-2015\n17. La cuenta a la que se refiere el numeral 10 de los presentes Lineamientos, servirá para el manejo de los recursos para obtener el apoyo ciudadano y para, en su caso, la campaña electoral.\nLa utilización de la cuenta será a partir del inicio de los actos tendentes a obtener el apoyo ciudadano y hasta la conclusión de las campañas electorales y con posterioridad, exclusivamente para cubrir los pasivos contraídos y demás erogaciones. Su cancelación deberá realizarse una vez que se concluyan los procedimientos que correspondan a la unidad de fiscalización respectiva.\nSECCIÓN PRIMERA\nDEL FINANCIAMIENTO PRIVADO PARA LA ETAPA\nDE LA OBTENCIÓN DEL APOYO CIUDADANO\n18. Los actos tendentes a recabar el apoyo ciudadano se financiarán con recursos privados de origen lícito, en los términos de la legislación aplicable, y estarán sujetos al tope de gastos que determine el Consejo General por el tipo de elección para la que pretenda ser postulado.\n19. El Consejo General determinará el tope de gastos equivalente al diez por ciento del establecido para las campañas inmediatas anteriores, según la elección de que se trate.\n20. Los aspirantes que rebasen el tope de gastos señalado en el párrafo anterior, perderán el derecho a ser registrados como candidato independiente o, en su caso, si ya está hecho el registro, se cancelará el mismo.\n21. Todo egreso deberá cubrirse con cheque nominativo o transferencia electrónica y los comprobantes que los amparen, deberán ser expedidos a nombre del aspirante y la persona encargada del manejo de recursos financieros en cuentas mancomunadas, debiendo constar en original como soporte a los informes financieros de los actos tendentes a obtener el apoyo ciudadano.\n22. Los aspirantes deberán nombrar una persona encargada del manejo de los recursos financieros y administración de los recursos relacionados con el apoyo ciudadano, así como de la presentación de los informes en los términos de Ley.\nSECCIÓN SEGUNDA\n23. El Consejo General, a propuesta de la unidad de fiscalización correspondiente, determinará tendentes a recabar el apoyo ciudadano.\nOBSERVAR LOS CIUDADANOS INTERESADOS EN\nPARTICIPAR COMO CANDIDATOS INDEPENDIENTES\nEN EL PROCESO ELECTORAL ORDINARIO DE\nGOBERNADOR, DIPUTADOS Y AYUNTAMIENTOS\n2014-2015\n24. El aspirante que no entregue el informe de ingresos y egresos, dentro de los treinta días siguientes a la conclusión del periodo para recabar el apoyo ciudadano, le será negado el registro como candidato independiente.\nLos aspirantes que sin haber obtenido el registro a la candidatura independiente no entreguen los informes antes señalados, serán sancionados en los términos de Ley.\nCAPÍTULO IV\nDE LOS DERECHOS Y OBLIGACIONES DE LOS ASPIRANTES\n25. Son derechos de los aspirantes:\na) Solicitar a los órganos electorales, dependiendo del tipo de elección, su registro como aspirante;\nb) Realizar actos para promover sus ideas y propuestas con el fin de obtener el apoyo ciudadano para el cargo al que desea aspirar;\nc) Utilizar financiamiento privado para el desarrollo de sus actividades, en términos de Ley;\nd) Nombrar a un representante para asistir a las sesiones de los consejos general y distritales, sin derecho a voz ni voto;\ne) Insertar en su propaganda la leyenda Aspirante a candidato independiente, y\nf) Los demás establecidos por la Ley Electoral.\n26. Son obligaciones de los aspirantes:\na) Conducirse con respeto irrestricto a lo dispuesto en la Constitución y en la Ley Electoral;\nb) No aceptar ni utilizar recursos de procedencia ilícita para realizar actos tendentes a obtener el apoyo ciudadano;\nc) Sujetarse a los lineamientos y disposiciones relacionadas con el financiamiento privado de los partidos políticos candidatos que prevé la Ley Electoral:\nOBSERVAR LOS CIUDADANOS INTERESADOS EN\nPARTICIPAR COMO CANDIDATOS INDEPENDIENTES\nEN EL PROCESO ELECTORAL ORDINARIO DE\nGOBERNADOR, DIPUTADOS Y AYUNTAMIENTOS\n2014-2015\nd) Rechazar toda clase de apoyo económico, político o propagandístico proveniente de extranjeros o de ministros de culto de cualquier religión, así como de las asociaciones y organizaciones religiosas e iglesias. Tampoco podrán aceptar aportaciones o donativos, en dinero o en especie, por sí o por interpósita persona y bajo ninguna circunstancia de:\nI) Los poderes Ejecutivo, Legislativo y Judicial de la Federación, del Estado, o de los\nAyuntamientos, salvo en el caso del financiamiento público establecido en la Constitución y en la Ley\nElectoral;\nII) Las dependencias, entidades u organismos de la Administración Pública Federal, estatal o municipal, centralizada o paraestatal, y los órganos de gobierno del Distrito Federal;\nIII) Los organismos autónomos federales, estatales y del Distrito Federal;\nIV) Los partidos políticos, personas físicas o morales extranjeras;\nV) Los organismos internacionales de cualquier naturaleza;\nVI) Las personas morales, y\nVII) Las personas que vivan o trabajen en el extranjero.\ne) Abstenerse de realizar por sí o por interpósita persona, actos de presión o coacción para obtener el apoyo ciudadano;\nf) Abstenerse de proferir ofensas, difamación, calumnia o cualquier expresión que denigre a otros aspirantes o precandidatos, partidos políticos, personas, instituciones públicas o privadas;\ng) Rendir el informe de ingresos y egresos;\nh) Respetar los topes de gastos fijados para obtener el apoyo ciudadano, en los términos que establece la Ley Electoral, y\ni) Las demás establecidas por la Ley.\nOBSERVAR LOS CIUDADANOS INTERESADOS EN\nPARTICIPAR COMO CANDIDATOS INDEPENDIENTES\nEN EL PROCESO ELECTORAL ORDINARIO DE\nGOBERNADOR, DIPUTADOS Y AYUNTAMIENTOS\n2014-2015\nTÍTULO TERCERO\nDEL REGISTRO DE CANDIDATOS INDEPENDIENTES\nCAPÍTULO I\nDE LOS REQUISITOS DE ELEGIBILIDAD\n27. Los ciudadanos que aspiren a participar como candidatos independientes en las elecciones de Diputado Local, Gobernador del Estado o miembro de Ayuntamiento, deberán satisfacer además de los requisitos señalados en los artículos 116 de la Constitución Federal, 46, 75, 76 y 173 de la\nConstitución Local, los siguientes:\nI. Estar inscrito en el Padrón del Registro Federal de Electores y contar con la credencial para votar;\nII. No ser Consejero ni Secretario Ejecutivo de los organismos electorales locales o nacionales, salvo que se separe del cargo dos años antes de la fecha de inicio del proceso electoral;\nIII. No ser Magistrado o Secretario del Tribunal Electoral del Poder Judicial de la Federación, salvo que se separe del cargo dos años antes de la fecha de inicio del proceso electoral;\nIV. No ser Magistrado, Juez o Secretario del Tribunal Electoral del Estado, salvo que se separe del cargo dos años antes de la fecha de inicio del proceso electoral;\nV. No ser miembro del Servicio Profesional Electoral Nacional, salvo que se separe del cargo dos años antes de la fecha de inicio del proceso electoral;\nVI. No ser representante popular federal, estatal o municipal; servidor público de los tres niveles de gobierno o de los organismos públicos descentralizados, salvo que se separe del cargo noventa días antes de la jornada electoral.\nVII. En el caso de que se haya tenido la responsabilidad de administrar recursos públicos en los cinco años anteriores a la elección, manifestar bajo protesta de decir verdad, haber cumplido en tiempo y\nEstado de Guerrero, en cuanto a la entrega de informes semestrales y cuentas públicas anuales, según corresponda.\nVIII. No estar inhabilitado para ocupar un cargo público por resolución ejecutoriada emitida por autoridad competente.\nOBSERVAR LOS CIUDADANOS INTERESADOS EN\nPARTICIPAR COMO CANDIDATOS INDEPENDIENTES\nEN EL PROCESO ELECTORAL ORDINARIO DE\nGOBERNADOR, DIPUTADOS Y AYUNTAMIENTOS\n2014-2015\nCAPÍTULO II\nDE LOS PLAZOS PARA EL REGISTRO DE CANDIDATURA\n28. El registro de la candidatura independiente deberá realizarse de conformidad con los plazos y ante los órganos electorales siguientes:\nI. Para Gobernador del Estado, del dieciocho de febrero al primero de marzo del año de la elección ante el Consejo General del Instituto Electoral;\nII. Para diputados por el principio de mayoría relativa, del veintiséis de marzo al primero de abril, del año de la elección ante los consejos distritales electorales correspondientes; y\nIII. Para Ayuntamiento del quince al veintiuno de abril del año de la elección ante los consejos distritales electorales correspondientes.\nEl Instituto Electoral dará amplia difusión a la apertura de registro de las candidaturas independientes y a los plazos a que se refiere el presente numeral.\nCAPÍTULO III\nDE LA SOLICITUD DE REGISTRO\n29. La solicitud de registro de candidaturas independientes deberá contener los siguientes datos:\nI. Apellido paterno, apellido materno, nombre completo y firma o, en su caso, huella dactilar del solicitante;\nII. Lugar y fecha de nacimiento del solicitante;\nIII. Domicilio del solicitante y tiempo de residencia en el mismo;\nIV. Ocupación del solicitante;\nV. Clave de la credencial para votar del solicitante;\nVI. Cargo para el que se pretenda postular el solicitante;\nVII. Designación del representante legal y domicilio para oír y recibir notificaciones, y\nOBSERVAR LOS CIUDADANOS INTERESADOS EN\nPARTICIPAR COMO CANDIDATOS INDEPENDIENTES\nEN EL PROCESO ELECTORAL ORDINARIO DE\nGOBERNADOR, DIPUTADOS Y AYUNTAMIENTOS\n2014-2015\nVIII. Designación de la persona encargada del manejo de los recursos financieros y de la rendición de informes correspondientes.\nA la solicitud de registro de candidaturas independientes deberá acompañarse de la siguiente documentación:\nI. Formato en el que manifieste su voluntad de ser candidato independiente, a que se refiere esta\nLey;\nII. Copia del acta de nacimiento y del anverso y reverso de la credencial para votar vigente;\nIII. La plataforma electoral que contenga las principales propuestas que el candidato independiente sostendrá en la campaña electoral;\nIV. Los datos de identificación de la cuenta bancaria aperturada para el manejo de los recursos de la candidatura independiente, en los términos de la Ley Electoral;\nV. Los informes de gastos y egresos de los actos tendentes a obtener el apoyo ciudadano;\nVI. La cédula de respaldo que contenga el nombre, firma, clave de elector, y el número identificador al reverso de la credencial de elector derivado del reconocimiento óptico de caracteres\n(OCR) de la credencial para votar con fotografía vigente de cada uno de los ciudadanos que manifiestan el apoyo en el porcentaje requerido en los términos de esta Ley, así como en medio óptico la base de datos de la información de cada ciudadano conforme a los requerimientos que determine la Dirección\nEjecutiva del Registro Federal de Electores del Instituto Nacional;\nVII. Manifestación por escrito, bajo protesta de decir verdad, de:\n1) No aceptar recursos de procedencia ilícita para campañas y actos para obtener el apoyo ciudadano;\n2) No ser presidente del comité ejecutivo nacional, estatal, municipal, dirigente, militante, afiliado o su equivalente, de un partido político, conforme a lo establecido en la Ley, a menos que se haya separado del partido político con anticipación de al menos dos años, y\n3) No tener ningún otro impedimento de tipo legal para contender como candidato.\nVIII. Escrito en el que manifieste su conformidad para que todos los ingresos y egresos de la cuenta bancaria aperturada sean fiscalizados, en cualquier momento, por la autoridad competente.\nOBSERVAR LOS CIUDADANOS INTERESADOS EN\nPARTICIPAR COMO CANDIDATOS INDEPENDIENTES\nEN EL PROCESO ELECTORAL ORDINARIO DE\nGOBERNADOR, DIPUTADOS Y AYUNTAMIENTOS\n2014-2015\n30. Recibida una solicitud de registro de candidatura independiente por el presidente o secretario del consejo que corresponda, se verificará dentro de los tres días siguientes que se cumplió con todos los requisitos señalados en el párrafo anterior, con excepción de lo relativo al apoyo ciudadano.\n31. Si de la verificación realizada se advierte que se omitió el cumplimiento de uno o varios requisitos, se notificará de inmediato al solicitante o a su representante, para que dentro de las cuarenta y ocho horas siguientes subsane el o los requisitos omitidos, siempre y cuando esto pueda realizarse dentro de los plazos que señala la Ley Electoral.\nSi no se subsanan los requisitos omitidos o se advierte que la solicitud se realizó en forma extemporánea, se tendrá por no presentada.\n32. Una vez que se cumplan los demás requisitos establecidos en esta Ley, la autoridad procederá a verificar que se haya reunido el porcentaje de apoyo ciudadano que corresponda según la elección de que se trate, constatando que los ciudadanos aparecen en la lista nominal de electores.\nPara realizar lo anterior, la Dirección Ejecutiva de Prerrogativas y Partidos Políticos del Instituto\nElectoral, verificará la cantidad de manifestaciones de apoyo válidas obtenidas por cada uno de los aspirantes a candidatos independientes a los distintos cargos de elección popular.\nLa declaración de nulidad de las manifestaciones de apoyo ciudadano será realizada por el\nConsejo General del Instituto Electoral a propuesta de la Dirección Ejecutiva de Prerrogativas y Partidos\nPolíticos del Instituto Electoral.\nPara realizar la revisión en la lista nominal de electores, el Instituto Electoral solicitará el apoyo del Instituto Nacional, proveyendo el primero la información requerida por el segundo.\n33. Las firmas no se computarán para los efectos del porcentaje requerido cuando se presente alguna de las siguientes circunstancias:\na) Nombres con datos falsos o erróneos;\nb) No se acompañen las copias de la credencial para votar vigente;\nc) En el caso de candidato a Gobernador del Estado, los ciudadanos no tengan su domicilio en el estado;\nOBSERVAR LOS CIUDADANOS INTERESADOS EN\nPARTICIPAR COMO CANDIDATOS INDEPENDIENTES\nEN EL PROCESO ELECTORAL ORDINARIO DE\nGOBERNADOR, DIPUTADOS Y AYUNTAMIENTOS\n2014-2015\nd) En el caso de candidatos a diputados de mayoría relativa y miembros de ayuntamiento, los ciudadanos no tengan su domicilio en el distrito o municipio, según corresponda, para el que se está postulando;\ne) Los ciudadanos hayan sido dados de baja de la lista nominal;\nf) En el caso que se haya presentado por una misma persona más de una manifestación a favor de un mismo aspirante, sólo se computará una, y\ng) En el caso que una misma persona haya presentado manifestación en favor de más de un aspirante, sólo se computará la primera manifestación presentada.\nPara tal efecto, la Dirección de Prerrogativas y Partidos Políticos realizará la compulsa correspondiente o solicitará el apoyo al Instituto Nacional Electoral.\n34. De todos los aspirantes a un mismo cargo de elección popular, solamente tendrá derecho a ser candidato independiente aquel que de manera individual, por fórmula o planilla, según sea el caso, obtenga el mayor número de manifestaciones de apoyo válidas y supere el porcentaje mínimo antes mencionado.\nSe declarará desierto el proceso de selección de candidatos independientes en la demarcación de que se trate, cuando ninguno de los aspirantes obtenga por lo menos el porcentaje requerido como mínimo de respaldo ciudadano.\nEn ningún caso, se publicará la información relativa al respaldo ciudadano que reciban los aspirantes.\nSi la solicitud no reúne el porcentaje requerido se tendrá por no presentada.\n35. Ninguna persona podrá registrarse como candidato a distintos cargos de elección popular en el mismo proceso electoral; tampoco podrá ser candidato para un cargo local de elección popular y simultáneamente para otro de la federación. En este supuesto, si el registro para el cargo de la elección local ya estuviere hecho, se procederá a la cancelación automática del registro. candidato por un partido político o coalición en el mismo proceso electoral local.\nOBSERVAR LOS CIUDADANOS INTERESADOS EN\nPARTICIPAR COMO CANDIDATOS INDEPENDIENTES\nEN EL PROCESO ELECTORAL ORDINARIO DE\nGOBERNADOR, DIPUTADOS Y AYUNTAMIENTOS\n2014-2015\nCAPÍTULO IV\nDEL REGISTRO DE CANDIDATURAS\n36. La aprobación del registro de candidaturas se llevará a cabo:\nI. Para Gobernador: del dos al cinco de marzo del dos mil quince;\nII. Para Diputados de Mayoría Relativa: del dos al cuatro de abril del dos mil quince; y\nIII. Para Ayuntamientos: del veintidós al veinticuatro de abril del dos mil quince.\n37. El Secretario del Consejo General y los presidentes de los consejos distritales, según corresponda, tomarán las medidas necesarias para hacer pública la conclusión del registro de candidaturas independientes, dando a conocer los nombres de los candidatos o fórmulas registradas y de aquéllos que no cumplieron con los requisitos.\nCAPÍTULO V\nDE LA SUSTITUCIÓN Y CANCELACIÓN DEL REGISTRO\n38. Los candidatos independientes que obtengan su registro no podrán ser sustituidos en ninguna de las etapas del proceso electoral, de conformidad con lo dispuesto por el artículo 57 de la Ley de Instituciones y Procedimientos Electorales del Estado de Guerrero.\n39. Tratándose de la fórmula de diputados, será cancelado el registro de la fórmula completa cuando falte el propietario. La ausencia del suplente no invalidará la fórmula.\n40. En el caso de las planillas de candidatos independientes a miembros de ayuntamiento, si por cualquier causa falta uno de los integrantes propietarios de una de las fórmulas de la planilla, se cancelará el registro de la Planilla y de la lista de regidores. En el caso de la lista de regidores si por cualquier causa falta uno de los integrantes propietarios se cancelará la fórmula y se recorrerá la lista.\nLa ausencia del suplente no invalidará las fórmulas.\nOBSERVAR LOS CIUDADANOS INTERESADOS EN\nPARTICIPAR COMO CANDIDATOS INDEPENDIENTES\nEN EL PROCESO ELECTORAL ORDINARIO DE\nGOBERNADOR, DIPUTADOS Y AYUNTAMIENTOS\n2014-2015\nTÍTULO CUARTO\nDE LAS PRERROGATIVAS, DERECHOS Y OBLIGACIONES\nCAPÍTULO I\nDE LOS DERECHOS Y OBLIGACIONES\n41. Son prerrogativas y derechos de los candidatos independientes registrados:\na) Participar en la campaña electoral correspondiente y en la elección al cargo para el que hayan sido registrados;\nb) Tener acceso a los tiempos de radio y televisión, como si se tratara de un partido político de nuevo registro, pero en forma proporcional al tipo de elección de que se trate, únicamente en la etapa de las campañas electorales;\nc) Obtener financiamiento público y privado, en los términos de la Ley Electoral;\nd) Realizar actos de campaña y difundir propaganda electoral en los términos de la Ley\nElectoral;\ne) Replicar y aclarar la información que generen los medios de comunicación, cuando consideren que se deforma su imagen o que se difundan hechos falsos o sin sustento alguno;\nf) Designar representantes ante los órganos del Instituto, en los términos dispuestos por la Ley\nElectoral;\ng) Solicitar a los órganos electorales copia de la documentación electoral, a través de sus representantes acreditados, y\nh) Las demás que les otorgue la Ley Electoral, y los demás ordenamientos aplicables.\n42. Son obligaciones de los candidatos independientes registrados:\na) Conducirse con respeto irrestricto a lo dispuesto en la Constitución y en la Ley Electoral;\nb) Respetar y acatar los acuerdos que emita el órgano electoral competente;\nc) Respetar y acatar los topes de gastos de campaña en los términos de la Ley Electoral;\nOBSERVAR LOS CIUDADANOS INTERESADOS EN\nPARTICIPAR COMO CANDIDATOS INDEPENDIENTES\nEN EL PROCESO ELECTORAL ORDINARIO DE\nGOBERNADOR, DIPUTADOS Y AYUNTAMIENTOS\n2014-2015\nd) Proporcionar al Instituto Electoral la información y documentación que éste solicite, en los términos de la Ley Electoral;\ne) Ejercer las prerrogativas y aplicar el financiamiento exclusivamente para los gastos de campaña;\nf) Rechazar toda clase de apoyo económico, político o propagandístico proveniente de extranjeros o de ministros de culto de cualquier religión, así como de las asociaciones y organizaciones religiosas e iglesias. Tampoco podrán aceptar aportaciones o donativos, en dinero o en especie, por sí o por interpósita persona y bajo ninguna circunstancia de:\nI) Los poderes Ejecutivo, Legislativo y Judicial de la Federación y de las entidades federativas, del estado, y los Ayuntamientos, salvo en el caso del financiamiento público establecido en la\nConstitución y la Ley Electoral;\nII) Las dependencias, entidades u organismos de la Administración Pública Federal, estatal o municipal, centralizada o paraestatal, y los órganos de gobierno del Distrito Federal;\nIII) Los organismos autónomos federales, estatales y del Distrito Federal;\nIV) Los partidos políticos, personas físicas o morales extranjeras;\nV) Los organismos internacionales de cualquier naturaleza;\nVI) Las personas morales, y\nVII) Las personas que vivan o trabajen en el extranjero.\ng) Depositar únicamente en la cuenta bancaria aperturada sus aportaciones y realizar todos los egresos de los actos de campaña con dicha cuenta;\nh) Abstenerse de utilizar símbolos religiosos, así como expresiones, alusiones o fundamentaciones de carácter religioso en su propaganda;\ni) Abstenerse de proferir ofensas, difamación, calumnia o cualquier expresión que denigre a otros candidatos, partidos políticos, personas, instituciones públicas o privadas;\nj) Insertar en su propaganda de manera visible la leyenda: \"candidato independiente\";\nOBSERVAR LOS CIUDADANOS INTERESADOS EN\nPARTICIPAR COMO CANDIDATOS INDEPENDIENTES\nEN EL PROCESO ELECTORAL ORDINARIO DE\nGOBERNADOR, DIPUTADOS Y AYUNTAMIENTOS\n2014-2015\nk) Abstenerse de utilizar en su propaganda política o electoral, emblemas y colores utilizados por partidos políticos nacionales o locales;\nl) Abstenerse de realizar actos que generen presión o coacción a los electores;\nm) Abstenerse de recibir metales y piedras preciosas por cualquier persona física o moral y depositar a la cuenta las aportaciones y donaciones en efectivo que reciba;\nn) Presentar, en los mismos términos en que lo hagan los partidos políticos, los informes de campaña sobre el origen y monto de todos sus ingresos, así como su aplicación y empleo; ñ) Ser responsable solidario, junto con el encargado de la administración de sus recursos financieros, dentro de los procedimientos de fiscalización de los recursos correspondientes, y\no) Las demás que establezcan la Ley Electoral, y los demás ordenamientos.\nCAPÍTULO II\nDE LOS REPRESENTANTES ANTE LOS ÓRGANOS\nDEL INSTITUTO ELECTORAL\n43. Los candidatos independientes podrán designar representantes ante los órganos del Instituto\nElectoral, en los términos siguientes:\na) Los candidatos independientes a Gobernador del Estado, ante el Consejo General y la totalidad de los consejos distritales;\nb) Los candidatos independientes a diputados, ante el consejo distrital por la cual se quiera postular;\nc) Los candidatos independientes a miembros de Ayuntamientos, ante el consejo distrital al que pertenezca el municipio por el cual se quiera postular; quince días posteriores al de la aprobación de su registro como aspirante a candidato independiente.\nSi la designación no se realiza en el plazo previsto en el párrafo anterior perderá este derecho.\nOBSERVAR LOS CIUDADANOS INTERESADOS EN\nPARTICIPAR COMO CANDIDATOS INDEPENDIENTES\nEN EL PROCESO ELECTORAL ORDINARIO DE\nGOBERNADOR, DIPUTADOS Y AYUNTAMIENTOS\n2014-2015\nCAPÍTULO III\nDE LOS REPRESENTANTES ANTE MESA\nDIRECTIVA DE CASILLA\n44. El registro de los nombramientos de los representantes ante mesas directivas de casilla y generales, se realizará en los términos previstos en el artículo 299 de la Ley de Instituciones y\nProcedimientos Electorales del Estado de Guerrero.\nCAPÍTULO IV\nDE LAS PRERROGATIVAS\nSECCIÓN PRIMERA\nDEL FINANCIAMIENTO\n45. El régimen de financiamiento de los candidatos independientes tendrá las siguientes modalidades:\na) Financiamiento privado, y\nb) Financiamiento público.\n46. El financiamiento privado se constituye por las aportaciones que realicen el candidato independiente y sus simpatizantes, el cual no podrá rebasar en ningún caso, el 10% del tope de gasto para la elección de que se trate.\n47. Los candidatos independientes al recibir aportaciones y donaciones en efectivo por cualquier persona física o moral deberán depositarlo a la cuenta que refiere el numeral 10 de los presentes\nLineamientos.\nLos candidatos independientes tienen prohibido recibir metales y piedras preciosas, por cualquier persona física o moral.\n48. No podrán realizar aportaciones o donativos en efectivo, metales y piedras preciosas o en especie por sí o por interpósita persona, a los aspirantes o candidatos independientes a cargos de elección popular, bajo ninguna circunstancia:\na) Los Poderes Ejecutivo, Legislativo y Judicial de la Federación y del estado, así como los\nAyuntamientos;\nOBSERVAR LOS CIUDADANOS INTERESADOS EN\nPARTICIPAR COMO CANDIDATOS INDEPENDIENTES\nEN EL PROCESO ELECTORAL ORDINARIO DE\nGOBERNADOR, DIPUTADOS Y AYUNTAMIENTOS\n2014-2015\nb) Las dependencias, entidades u organismos de la Administración Pública Federal, estatal o municipal, así como los del Distrito Federal;\nc) Los organismos autónomos federales, estatales y del Distrito Federal;\nd) Los partidos políticos, personas físicas o morales extranjeras;\ne) Las organizaciones gremiales, sindicatos y corporativos;\nf) Los organismos internacionales de cualquier naturaleza;\ng) Los ministros de culto, asociaciones, iglesias o agrupaciones de cualquier religión;\nh) Las personas que vivan o trabajen en el extranjero, y\ni) Las empresas mexicanas de carácter mercantil.\n49. Los candidatos independientes no podrán solicitar créditos provenientes de la banca de desarrollo para el financia-miento de sus actividades. Tampoco podrán recibir aportaciones de personas no identificadas.\n50. Para el manejo de los recursos de campaña electoral, se deberá utilizar la cuenta bancaria aperturada a que se refiere la Ley Electoral y los presentes Lineamientos; todas las aportaciones deberán realizarse exclusivamente en dicha cuenta, mediante cheque o transferencia bancaria.\n51. Todo egreso deberá cubrirse con cheque nominativo o transferencia electrónica. En el caso de los pagos por la prestación de bienes o servicios, adicionalmente el cheque deberá contener la leyenda \"para abono en cuenta del beneficiario\". Las pólizas de los cheques deberán conservarse anexas a la documentación comprobatoria junto con la copia del cheque a que se hace referencia.\nLos comprobantes que amparen los egresos que realicen los candidatos independientes, campañas electorales, los cuales estarán a disposición de la unidad de fiscalización correspondiente para su revisión de conformidad con lo dispuesto en la Ley Electoral. Dicha documentación deberá cumplir con los requisitos que exigen las disposiciones fiscales aplicables, así como las establecidas por el\nReglamento de Fiscalización que corresponda.\n52. Las aportaciones de bienes muebles, servicios o de cualquier otra en especie, deberán destinarse exclusivamente a las actividades de la candidatura independiente.\nOBSERVAR LOS CIUDADANOS INTERESADOS EN\nPARTICIPAR COMO CANDIDATOS INDEPENDIENTES\nEN EL PROCESO ELECTORAL ORDINARIO DE\nGOBERNADOR, DIPUTADOS Y AYUNTAMIENTOS\n2014-2015\n53. En ningún caso, los candidatos independientes podrán recibir en propiedad bienes inmuebles para las actividades de su candidatura, así como adquirir bienes inmuebles con el financia-miento público o privado que reciban.\n54. Los candidatos independientes tendrán derecho a recibir financiamiento público para sus gastos de campaña. Para los efectos de la distribución del financiamiento público y prerrogativas a que tienen derecho los candidatos independientes, en su conjunto, serán considerados como un partido político de nuevo registro.\n55. El monto que le correspondería a un partido de nuevo registro, se distribuirá entre todos los candidatos independientes de la siguiente manera:\na) Un 33.3% que se otorgara al candidato independiente al cargo de Gobernador del Estado;\nb) Un 33.3% que se distribuirá de manera igualitaria entre todas las fórmulas de candidatos independientes al cargo de diputado, y\nc) Un 33.3% que se distribuirá de manera proporcional conforme a la lista nominal que represente en cada uno de los municipios, entre todas las planillas de candidatos independientes al cargo de Ayuntamientos.\nEn el supuesto del incisos b), en el que un sólo candidato obtenga su registro, no podrá recibir financiamiento que exceda del 50% del monto referido. Tampoco podrá exceder el 90% del total de tope de campaña de la elección.\n56. Los candidatos deberán nombrar una persona encargada del manejo de los recursos financieros y administración de los recursos generales y de campaña, así como de la presentación de los informes a que se refiere la Ley Electoral.\n57. Los candidatos independientes deberán reembolsar al Instituto el monto del financia-miento público no erogado.\nSECCIÓN SEGUNDA\nDEL ACCESO A RADIO Y TELEVISIÓN\n58. El Instituto Nacional, como autoridad única para la administración del tiempo que corresponda al Estado en radio y televisión, garantizará a los candidatos independientes el uso de sus prerrogativas en radio y televisión; establecerá las pautas para la asignación de los mensajes y programas que tengan derecho a difundir durante las campañas electorales; atenderá las quejas y denuncias por la violación a las normas aplicables y determinará, en su caso, las sanciones.\nOBSERVAR LOS CIUDADANOS INTERESADOS EN\nPARTICIPAR COMO CANDIDATOS INDEPENDIENTES\nEN EL PROCESO ELECTORAL ORDINARIO DE\nGOBERNADOR, DIPUTADOS Y AYUNTAMIENTOS\n2014-2015\nEl Instituto Electoral, participara en los términos que indique la Legislación, los reglamentos, lineamientos, criterios y demás disposiciones establecidas por la autoridad competente.\nCAPÍTULO V\nDE LA PROPAGANDA ELECTORAL DE LOS\nCANDIDATOS INDEPENDIENTES\n59. Son aplicables a los candidatos independientes, las normas sobre propaganda electoral contenidas en la Ley Electoral.\n60. La propaganda electoral de los candidatos independientes deberá tener el emblema y color o colores que los caractericen y diferencien de otros partidos políticos y de otros candidatos independientes, así como tener visible la leyenda: \"Candidato Independiente\".\nCAPÍTULO VI\nDE LA FISCALIZACIÓN\n61. La fiscalización corresponde al Instituto Nacional Electoral, el cual podrá delegar esta facultad al Instituto Electoral quien atenderá a los lineamientos generales que emita el Consejo General del Instituto Nacional Electoral.\nTÍTULO QUINTO\nDE LOS ACTOS DE LA JORNADA ELECTORAL\nCAPÍTULO I\nDE LA DOCUMENTACIÓN Y EL MATERIAL ELECTORAL\n62. Los candidatos independientes figurarán en la misma boleta que el Consejo General apruebe para los candidatos de los partidos políticos, coaliciones o candidaturas comunes, según la elección en la que participen, de conformidad con el artículo 308 de la Ley de Instituciones y Procedimientos Electorales del Estado de Guerrero. independientes, con el mismo tamaño y en un espacio de las mismas dimensiones que aquéllos que se destinen en la boleta a los partidos, coaliciones o candidaturas comunes que participan. Estos recuadros serán colocados después de los destinados a los partidos políticos.\nOBSERVAR LOS CIUDADANOS INTERESADOS EN\nPARTICIPAR COMO CANDIDATOS INDEPENDIENTES\nEN EL PROCESO ELECTORAL ORDINARIO DE\nGOBERNADOR, DIPUTADOS Y AYUNTAMIENTOS\n2014-2015\n63. En la boleta, de acuerdo a la elección de que se trate, aparecerá el nombre completo del candidato independiente o de los integrantes de la fórmula o planilla de Ayuntamientos de candidatos independientes.\nEn la boleta no se incluirá, ni la fotografía, ni la silueta del candidato.\n64. Los documentos y el materiales electorales serán elaborados en los términos que establezca la Ley Electoral y demás ordenamientos aplicables.\nCAPÍTULO II\nDEL CÓMPUTO DE LOS VOTOS\n65. Se contará como voto válido la marca que haga el elector en un solo recuadro en el que se contenga el emblema o el nombre de un candidato independiente, en términos de lo dispuesto por la Ley.\nCAPÍTULO III\nDE LAS INFRACCIONES\n66. En términos del artículo 415 de la Ley de Instituciones y Procedimientos Electorales del\nEstado de Guerrero, los aspirantes o candidatos independientes podrán ser sancionados por el Instituto\nElectoral por la comisión de las infracciones siguientes.\na) El incumplimiento de las obligaciones establecidas en la Ley Electoral;\nb) La realización de actos anticipados de campaña;\nc) Solicitar o recibir recursos en efectivo o en especie, de personas no autorizadas por la Ley\nElectoral;\nd) Liquidar o pagar, así como aceptar la liquidación o el pago de actos u operaciones mediante el uso de efectivo o metales y piedras preciosas;\ne) Utilizar recursos de procedencia ilícita para el financiamiento de cualquiera de sus actividades;\nf) Recibir, tratándose de aspirantes aportaciones y donaciones en efectivo, y en el caso de candidatos recibirlas y no depositarlas a la cuenta;\ng) Recibir metales y/o piedras preciosas de cualquier persona física o moral;\nOBSERVAR LOS CIUDADANOS INTERESADOS EN\nPARTICIPAR COMO CANDIDATOS INDEPENDIENTES\nEN EL PROCESO ELECTORAL ORDINARIO DE\nGOBERNADOR, DIPUTADOS Y AYUNTAMIENTOS\n2014-2015\nh) No presentar los informes que correspondan para obtener el apoyo ciudadano y de campaña establecidos en la Ley Electoral y en los presentes Lineamientos;\ni) Exceder el tope de gastos para obtener el apoyo ciudadano y de campaña establecido por el\nConsejo General;\nj) No reembolsar los recursos provenientes del financiamiento público no ejercidos durante las actividades de campaña;\nk) El incumplimiento de las resoluciones y acuerdos del Instituto;\nl) La contratación, en forma directa o por terceras personas, de tiempo en cualquier modalidad en radio o televisión;\nm) La obtención de bienes inmuebles con recursos provenientes del financiamiento público o privado;\nn) La difusión de propaganda política o electoral que contenga expresiones que calumnien a las personas, instituciones o los partidos políticos;\no) La omisión o el incumplimiento de la obligación de proporcionar en tiempo y forma, la información que les sea solicitada por los órganos del Instituto, y\np) El incumplimiento de cual quiera de las disposiciones contenidas en la Ley Electoral y demás disposiciones aplicables.\nCAPÍTULO IV\nDE LAS DISPOSICIONES COMPLEMENTARIAS\n67. Corresponde al Instituto Nacional, la organización, desarrollo, otorgamiento y vigilancia de las prerrogativas que en materia de radio y televisión tienen derecho los candidatos independientes, conforme a lo establecido en la Ley Electoral.\nSoberano de Guerrero; 173, 174, 177 y 188 y demás relativos y aplicables de la Ley número 483 de\nInstituciones y Procedimientos Electorales del Estado de Guerrero, se emite el siguiente\nOBSERVAR LOS CIUDADANOS INTERESADOS EN\nPARTICIPAR COMO CANDIDATOS INDEPENDIENTES\nEN EL PROCESO ELECTORAL ORDINARIO DE\nGOBERNADOR, DIPUTADOS Y AYUNTAMIENTOS\n2014-2015\nACUERDO\nPRIMERO.- Se aprueban los Lineamientos para el Registro de Aspirantes y Candidatos\nIndependientes a los Cargos de Gobernador, Diputados de Mayoría Relativa y Ayuntamientos del Estado de Guerrero para El Proceso Electoral 2014-2015, en términos de los títulos que lo conforman.\nSEGUNDO.- Publíquense los presentes lineamientos en el Periódico Oficial del Gobierno del\nEstado de Guerrero y en la página web de este Instituto para conocimiento general.\nSe notifica a los representantes de los Partidos Políticos acreditados ante este órgano electoral, en términos de lo dispuesto por el artículo 34 de la Ley del Sistema de Medios de Impugnación en\nMateria Electoral del Estado de Guerrero.\nEl presente acuerdo fue aprobado por unanimidad de votos de la Séptima Sesión Extraordinaria celebrada el día diez de octubre del año dos mil catorce, por el Pleno del Consejo General del Instituto\nElectoral y de Participación Ciudadana del Estado de Guerrero.\nLA CONSEJERA PRESIDENTA DEL CONSEJO GENERAL\nDEL INSTITUTO ELECTORAL Y DE PARTICIPACIÓN\nCIUDADANA DEL ESTADO DE GUERRERO.\nC. MARISELA REYES REYES.\nRúbrica.\nSECRETARIO EJECUTIVO.\nC. CARLOS ALBERTO VILLALPANDO MILIÁN.\nRúbrica.",
  "ordenamiento": "LINEAMIENTO",
  "jurisdiccion": "GUERRERO",
  "fuente_oficial": "DIARIO OFICIAL DE LA FEDERACION",
  "Fecha de Publicación": "28 de \nNoviembre de 2014",
  "ULTIMA REFORMA PUBLICADA": null,
  "status": "VIGENTE",
  "es_escaneado": false,
  "tiene_tablas": false,
  "materia": [
    "electoral"
  ]
}